{
  "type": "Feature",
  "properties": {
    "addr:full":"10 W Beech St Islip NY 11751",
    "addr:housenumber":"10",
    "addr:postcode":"11751",
    "addr:street":"W Beech St",
    "iso:country":"US",
    "sg:address":"10 W Beech St",
    "sg:city":"Islip",
    "sg:classifiers":[
        {
            "category":"Retail",
            "subcategory":"Auto Repair",
            "type":"Services"
        }
    ],
    "sg:phone":"+1 631 581 7020",
    "sg:postcode":"11751",
    "sg:province":"NY",
    "sg:tags":[
        "repairing",
        "automobile"
    ],
    "wof:name":"Hulk Jr Towing & Recovery Inc",
    "wof:placetype":"venue"
},
  "geometry": {"coordinates":[-73.209925,40.750239],"type":"Point"}
}