{
  "type": "Feature",
  "properties": {
    "addr:full":"128 Jefferson Ct Yorktown Heights NY 10598",
    "addr:housenumber":"128",
    "addr:postcode":"10598",
    "addr:street":"Jefferson Ct",
    "iso:country":"US",
    "sg:address":"128 Jefferson Ct",
    "sg:city":"Yorktown Heights",
    "sg:classifiers":[
        {
            "category":"Home & Garden",
            "subcategory":"Building Materials",
            "type":"Retail Goods"
        }
    ],
    "sg:phone":"+1 914 779 1300",
    "sg:postcode":"10598",
    "sg:province":"NY",
    "sg:tags":[
        "door",
        "gate",
        "operating",
        "devices"
    ],
    "wof:name":"Atlantic Special Svc",
    "wof:placetype":"venue"
},
  "geometry": {"coordinates":[-73.783045,41.330511],"type":"Point"}
}