{
  "type": "Feature",
  "properties": {
    "iso:country":"US",
    "sg:address":"2001 Ridge Rd",
    "sg:city":"Ontario",
    "sg:phone":"+1 315 524 4345",
    "sg:postcode":"14519",
    "sg:province":"NY",
    "wof:name":"H T Jewelers",
    "wof:placetype":"venue"
},
  "geometry": {"coordinates":[-77.283787,43.221018],"type":"Point"}
}