{
  "type": "Feature",
  "properties": {
    "addr:full":"73 Ireland Pl Amityville NY 11701",
    "addr:housenumber":"73",
    "addr:postcode":"11701",
    "addr:street":"Ireland Pl",
    "iso:country":"US",
    "sg:address":"73 Ireland Pl",
    "sg:city":"Amityville",
    "sg:classifiers":[
        {
            "category":"Building & Trades",
            "subcategory":"Construction",
            "type":"Services"
        }
    ],
    "sg:phone":"+1 631 842 6300",
    "sg:postcode":"11701",
    "sg:province":"NY",
    "sg:tags":[
        "contractor"
    ],
    "wof:name":"A-1 Solar Guardian",
    "wof:placetype":"venue"
},
  "geometry": {"coordinates":[-73.418336,40.6773],"type":"Point"}
}