{
  "type": "Feature",
  "properties": {
    "addr:full":"512 86th St Brooklyn NY 11209",
    "addr:housenumber":"512",
    "addr:postcode":"11209",
    "addr:street":"86Th St",
    "iso:country":"US",
    "sg:address":"512 86th St",
    "sg:city":"Brooklyn",
    "sg:classifiers":[
        {
            "category":"Banks & Credit Unions",
            "subcategory":"Bank",
            "type":"Services"
        }
    ],
    "sg:phone":"+1 718 921 2900",
    "sg:postcode":"11209",
    "sg:province":"NY",
    "sg:website":"www.citibank.com",
    "wof:name":"Citibank Na",
    "wof:placetype":"venue"
},
  "geometry": {"coordinates":[-74.025841,40.621242],"type":"Point"}
}