{
  "type": "Feature",
  "properties": {
    "addr:full":"7700 Maple Rd Baldwinsville NY 13027",
    "addr:housenumber":"7700",
    "addr:postcode":"13027",
    "addr:street":"Maple Rd",
    "iso:country":"US",
    "sg:address":"7700 Maple Rd",
    "sg:city":"Baldwinsville",
    "sg:classifiers":[
        {
            "category":"Retail",
            "subcategory":"Auto Repair",
            "type":"Services"
        }
    ],
    "sg:phone":"+1   ",
    "sg:postcode":"13027",
    "sg:province":"NY",
    "sg:tags":[
        "general"
    ],
    "wof:name":"J & L Automotive",
    "wof:placetype":"venue"
},
  "geometry": {"coordinates":[-76.318725,43.142393],"type":"Point"}
}