{
  "type": "Feature",
  "properties": {
    "iso:country":"US",
    "sg:address":"359 Lafayette St",
    "sg:city":"New York",
    "sg:classifiers":[
        {
            "category":"Shopping",
            "subcategory":"Used Merchandise",
            "type":"Retail Goods"
        }
    ],
    "sg:phone":"+1   ",
    "sg:postcode":"10012",
    "sg:province":"NY",
    "wof:name":"Gueridon LLC",
    "wof:placetype":"venue"
},
  "geometry": {"coordinates":[-73.99364,40.727289],"type":"Point"}
}