{
  "type": "Feature",
  "properties": {
    "addr:full":"4260 Broadway New York NY 10033",
    "addr:housenumber":"4260",
    "addr:postcode":"10033",
    "addr:street":"Broadway",
    "iso:country":"US",
    "sg:address":"4260 Broadway",
    "sg:city":"New York",
    "sg:classifiers":[
        {
            "category":"Health Services",
            "subcategory":"Clinic",
            "type":"Services"
        }
    ],
    "sg:phone":"+1 212 923 2547",
    "sg:postcode":"10033",
    "sg:province":"NY",
    "wof:name":"Careplus Health Plan",
    "wof:placetype":"venue"
},
  "geometry": {"coordinates":[-73.93538100000001,40.850685],"type":"Point"}
}