{
  "type": "Feature",
  "properties": {
    "iso:country":"US",
    "sg:address":"1378 Teller Ave",
    "sg:city":"Bronx",
    "sg:classifiers":[
        {
            "category":"Banks & Credit Unions",
            "subcategory":"Bank",
            "type":"Services"
        }
    ],
    "sg:phone":"+1 718 588 2628",
    "sg:postcode":"10456",
    "sg:province":"NY",
    "sg:tags":[
        "depository",
        "banking"
    ],
    "wof:name":"National Foreign Exchange Inc",
    "wof:placetype":"venue"
},
  "geometry": {"coordinates":[-73.909859,40.834924],"type":"Point"}
}