{
  "type": "Feature",
  "properties": {
    "addr:full":"24 N Henry St Brooklyn NY 11222",
    "addr:housenumber":"24",
    "addr:postcode":"11222",
    "addr:street":"N Henry St",
    "iso:country":"US",
    "sg:address":"24 N Henry St",
    "sg:city":"Brooklyn",
    "sg:classifiers":[
        {
            "category":"Real Estate",
            "subcategory":"Real Estate Operator",
            "type":"Services"
        },
        {
            "category":"Recreation",
            "type":"Entertainment"
        }
    ],
    "sg:phone":"+1 718 383 9796",
    "sg:postcode":"11222",
    "sg:province":"NY",
    "sg:tags":[
        "building",
        "nonresidential",
        "hall",
        "auditorium"
    ],
    "wof:name":"St Cecilia's Auditorium",
    "wof:placetype":"venue"
},
  "geometry": {"coordinates":[-73.942503,40.719473],"type":"Point"}
}