{
  "type": "Feature",
  "properties": {
    "iso:country":"US",
    "sg:address":"6165 Strickland Ave Mill Basin",
    "sg:city":"Brooklyn",
    "sg:classifiers":[
        {
            "category":"Restaurant",
            "type":"Food & Drink"
        }
    ],
    "sg:phone":"+1 347 492 7644",
    "sg:postcode":"11234",
    "sg:province":"NY",
    "sg:tags":[
        "kosher",
        "seafood",
        "brunch",
        "breakfast"
    ],
    "wof:name":"Cafe K Mill Basin",
    "wof:placetype":"venue"
},
  "geometry": {"coordinates":[-73.912425,40.613419],"type":"Point"}
}