{
  "type": "Feature",
  "properties": {
    "iso:country":"US",
    "sg:address":"3701 Bedford Ave",
    "sg:city":"Brooklyn",
    "sg:classifiers":[
        {
            "category":"Social Services",
            "type":"Services"
        }
    ],
    "sg:phone":"+1 718 692 3252",
    "sg:postcode":"11229",
    "sg:province":"NY",
    "sg:tags":[
        "psychologist"
    ],
    "wof:name":"Ny Institute",
    "wof:placetype":"venue"
},
  "geometry": {"coordinates":[-73.948909,40.61262],"type":"Point"}
}