{
  "type": "Feature",
  "properties": {
    "iso:country":"US",
    "sg:address":"1601 Valley Dr",
    "sg:city":"Syracuse",
    "sg:classifiers":[
        {
            "category":"Deli",
            "type":"Food & Drink"
        },
        {
            "category":"Restaurant",
            "type":"Food & Drink"
        },
        {
            "category":"Food & Beverages",
            "subcategory":"Groceries & Convenience Stores",
            "type":"Retail Goods"
        }
    ],
    "sg:phone":"+1 315 492 4101",
    "sg:postcode":"13207",
    "sg:province":"NY",
    "sg:tags":[
        "shop",
        "delicatessen",
        "sandwich"
    ],
    "wof:name":"Jreck Subs",
    "wof:placetype":"venue"
},
  "geometry": {"coordinates":[-76.15319100000001,43.002071],"type":"Point"}
}