{
  "type": "Feature",
  "properties": {
    "addr:full":"1003 Hudson River Rd Mechanicville NY 12118",
    "addr:housenumber":"1003",
    "addr:postcode":"12118",
    "addr:street":"Hudson River Rd",
    "iso:country":"US",
    "sg:address":"1003 Hudson River Rd",
    "sg:city":"Mechanicville",
    "sg:classifiers":[
        {
            "category":"Autos & Motor Vehicles",
            "subcategory":"Automobile Sales",
            "type":"Retail Goods"
        },
        {
            "category":"Retail",
            "subcategory":"Auto Repair",
            "type":"Services"
        }
    ],
    "sg:phone":"+1 518 664 9841",
    "sg:postcode":"12118",
    "sg:province":"NY",
    "sg:tags":[
        "truck",
        "leasing",
        "car",
        "new"
    ],
    "sg:website":"http://www.jackbyrne.com",
    "wof:name":"Jack Byrne Ford Mercury",
    "wof:placetype":"venue"
},
  "geometry": {"coordinates":[-73.679394,42.875287],"type":"Point"}
}