{
  "type": "Feature",
  "properties": {
    "addr:full":"22 Lincoln Ave Huntington Station NY 11746",
    "addr:housenumber":"22",
    "addr:postcode":"11746",
    "addr:street":"Lincoln Ave Huntington",
    "iso:country":"US",
    "sg:address":"22 Lincoln Ave",
    "sg:city":"Huntington Station",
    "sg:classifiers":[
        {
            "category":"Professional",
            "type":"Services"
        }
    ],
    "sg:phone":"+1   ",
    "sg:postcode":"11746",
    "sg:province":"NY",
    "wof:name":"Buttons Bows Designs",
    "wof:placetype":"venue"
},
  "geometry": {"coordinates":[-73.311904,40.799177],"type":"Point"}
}