{
  "type": "Feature",
  "properties": {
    "addr:full":"1011 1st Avenue New York NY 10022",
    "addr:housenumber":"1011",
    "addr:postcode":"10022",
    "addr:street":"1St Avenue",
    "iso:country":"US",
    "sg:address":"1011 1st Avenue",
    "sg:city":"New York",
    "sg:classifiers":[
        {
            "category":"Organizations",
            "subcategory":"Non-profit Organization",
            "type":"Services"
        }
    ],
    "sg:phone":"+1 212 753 8583",
    "sg:postcode":"10022",
    "sg:province":"NY",
    "sg:tags":[
        "service/non-profit",
        "community"
    ],
    "wof:name":"Inner-City Scholarship Fund",
    "wof:placetype":"venue"
},
  "geometry": {"coordinates":[-73.963712,40.757247],"type":"Point"}
}