{
  "type": "Feature",
  "properties": {
    "iso:country":"US",
    "sg:address":"593 Lakeside Rd",
    "sg:city":"Newburgh",
    "sg:classifiers":[
        {
            "category":"Real Estate",
            "subcategory":"Real Estate Agent",
            "type":"Services"
        }
    ],
    "sg:phone":"+1 845 566 4505",
    "sg:postcode":"12550",
    "sg:province":"NY",
    "wof:name":"Rhoda Ciancio Co",
    "wof:placetype":"venue"
},
  "geometry": {"coordinates":[-74.09385,41.568995],"type":"Point"}
}