{
  "type": "Feature",
  "properties": {
    "iso:country":"US",
    "sg:address":"60 E 12 St",
    "sg:city":"New York",
    "sg:classifiers":[
        {
            "category":"Building & Trades",
            "subcategory":"Construction",
            "type":"Services"
        }
    ],
    "sg:phone":"+1 212 501 1901",
    "sg:postcode":"10003",
    "sg:province":"NY",
    "sg:tags":[
        "roofing",
        "contractor"
    ],
    "wof:name":"M & P Roofing",
    "wof:placetype":"venue"
},
  "geometry": {"coordinates":[-73.990027,40.732755],"type":"Point"}
}