{
  "type": "Feature",
  "properties": {
    "iso:country":"US",
    "sg:address":"7 Dana Hill Rd",
    "sg:city":"Russell",
    "sg:classifiers":[
        {
            "category":"Retail",
            "subcategory":"Auto Repair",
            "type":"Services"
        }
    ],
    "sg:phone":"+1 315 562 2559",
    "sg:postcode":"13684",
    "sg:province":"NY",
    "sg:tags":[
        "repairing",
        "automobile"
    ],
    "wof:name":"Gerald's Auto Repair",
    "wof:placetype":"venue"
},
  "geometry": {"coordinates":[-75.191868,44.37347],"type":"Point"}
}