{
  "type": "Feature",
  "properties": {
    "addr:full":"136 Whitman Ave Staten Island NY 10308",
    "addr:housenumber":"136",
    "addr:postcode":"10308",
    "addr:street":"Whitman Ave",
    "iso:country":"US",
    "sg:address":"136 Whitman Ave",
    "sg:city":"Staten Island",
    "sg:classifiers":[
        {
            "category":"Building & Trades",
            "subcategory":"Construction",
            "type":"Services"
        }
    ],
    "sg:phone":"+1 718 984 5565",
    "sg:postcode":"10308",
    "sg:province":"NY",
    "sg:tags":[
        "home",
        "remodeling",
        "contractor"
    ],
    "wof:name":"Thompson-Norris Home Imprvs",
    "wof:placetype":"venue"
},
  "geometry": {"coordinates":[-74.142753,40.54412],"type":"Point"}
}