{
  "type": "Feature",
  "properties": {
    "addr:full":"435 W 19th St New York NY 10011",
    "addr:housenumber":"435",
    "addr:postcode":"10011",
    "addr:street":"W 19Th St",
    "iso:country":"US",
    "sg:address":"435 W 19th St",
    "sg:city":"New York",
    "sg:classifiers":[
        {
            "category":"Shopping",
            "subcategory":"Adult",
            "type":"Retail Goods"
        }
    ],
    "sg:phone":"+1 212 414 4801",
    "sg:postcode":"10011",
    "sg:province":"NY",
    "sg:tags":[
        "entertainment"
    ],
    "wof:name":"Maximum Films & Mgmt",
    "wof:placetype":"venue"
},
  "geometry": {"coordinates":[-74.380886,40.744732],"type":"Point"}
}