{
  "type": "Feature",
  "properties": {
    "addr:full":"7121 18th Ave Brooklyn NY 11204",
    "addr:housenumber":"7121",
    "addr:postcode":"11204",
    "addr:street":"18Th Ave",
    "iso:country":"US",
    "sg:address":"7121 18th Ave",
    "sg:city":"Brooklyn",
    "sg:classifiers":[
        {
            "category":"Fast Food",
            "type":"Food & Drink"
        }
    ],
    "sg:phone":"+1 718 232 1522",
    "sg:postcode":"11204",
    "sg:province":"NY",
    "wof:name":"Dunkin' Donuts/Baskin Robbins",
    "wof:placetype":"venue"
},
  "geometry": {"coordinates":[-73.993763,40.615554],"type":"Point"}
}