{
  "type": "Feature",
  "properties": {
    "iso:country":"US",
    "sg:address":"10 Black Stallion Ct",
    "sg:city":"Middletown",
    "sg:classifiers":[
        {
            "category":"Building & Trades",
            "subcategory":"Electrical",
            "type":"Services"
        }
    ],
    "sg:phone":"+1 845 343 0843",
    "sg:postcode":"10940",
    "sg:province":"NY",
    "sg:tags":[
        "electrician",
        "contractor"
    ],
    "wof:name":"Fgs Electric",
    "wof:placetype":"venue"
},
  "geometry": {"coordinates":[-74.385755,41.439559],"type":"Point"}
}