{
  "type": "Feature",
  "properties": {
    "iso:country":"US",
    "sg:address":"612 Argyle Rd Apt 5L",
    "sg:city":"Brooklyn",
    "sg:classifiers":[
        {
            "category":"Arts & Performance",
            "subcategory":"Arts Center",
            "type":"Entertainment"
        }
    ],
    "sg:phone":"+1 718 434 5655",
    "sg:postcode":"11230",
    "sg:province":"NY",
    "sg:tags":[
        "information"
    ],
    "sg:website":"http://www.ricia.com",
    "wof:name":"Mainhardt, Ricia",
    "wof:placetype":"venue"
},
  "geometry": {"coordinates":[-73.964983,40.634278],"type":"Point"}
}