{
  "type": "Feature",
  "properties": {
    "addr:full":"1087 Jericho Tpke Commack NY 11725",
    "addr:housenumber":"1087",
    "addr:postcode":"11725",
    "addr:street":"Jericho Tpke",
    "iso:country":"US",
    "sg:address":"1087 Jericho Tpke",
    "sg:city":"Commack",
    "sg:phone":"+1 631 543 6790",
    "sg:postcode":"11725",
    "sg:province":"NY",
    "wof:name":"Sil La Joung",
    "wof:placetype":"venue"
},
  "geometry": {"coordinates":[-73.25833900000001,40.84679],"type":"Point"}
}