{
  "type": "Feature",
  "properties": {
    "iso:country":"US",
    "sg:address":"2758 W Henrietta Rd",
    "sg:city":"Rochester",
    "sg:classifiers":[
        {
            "category":"Restaurant",
            "type":"Food & Drink"
        }
    ],
    "sg:phone":"+1 585 424 6440",
    "sg:postcode":"14623",
    "sg:province":"NY",
    "wof:name":"Woody's Ii",
    "wof:placetype":"venue"
},
  "geometry": {"coordinates":[-77.631739,43.09664],"type":"Point"}
}