{
  "type": "Feature",
  "properties": {
    "iso:country":"US",
    "sg:address":"841 James Pl",
    "sg:city":"Uniondale",
    "sg:classifiers":[
        {
            "category":"Social Services",
            "subcategory":"Child Care",
            "type":"Services"
        }
    ],
    "sg:phone":"+1 516 505 1656",
    "sg:postcode":"11553",
    "sg:province":"NY",
    "sg:tags":[
        "day"
    ],
    "wof:name":"Early Light Childcare",
    "wof:placetype":"venue"
},
  "geometry": {"coordinates":[-73.58760100000001,40.696201],"type":"Point"}
}