{
  "type": "Feature",
  "properties": {
    "iso:country":"US",
    "sg:address":"1448 Middle Country Rd",
    "sg:city":"Centereach",
    "sg:classifiers":[
        {
            "category":"Shopping",
            "subcategory":"Clothing, Apparel, & Fashions",
            "type":"Retail Goods"
        }
    ],
    "sg:phone":"+1 631 736 6753",
    "sg:postcode":"11720",
    "sg:province":"NY",
    "sg:tags":[
        "item",
        "boutique"
    ],
    "wof:name":"Skull City Fashions",
    "wof:placetype":"venue"
},
  "geometry": {"coordinates":[-73.06574500000001,40.860835],"type":"Point"}
}