{
  "type": "Feature",
  "properties": {
    "addr:full":"500 Rockaway Ave Valley Stream NY 11581",
    "addr:housenumber":"500",
    "addr:postcode":"11581",
    "addr:street":"Rockaway Ave",
    "iso:country":"US",
    "sg:address":"500 Rockaway Ave",
    "sg:city":"Valley Stream",
    "sg:classifiers":[
        {
            "category":"Real Estate",
            "subcategory":"Real Estate Agent",
            "type":"Services"
        }
    ],
    "sg:phone":"+1 516 561 0301",
    "sg:postcode":"11581",
    "sg:province":"NY",
    "wof:name":"Al Mac Realty Inc",
    "wof:placetype":"venue"
},
  "geometry": {"coordinates":[-73.701139,40.657348],"type":"Point"}
}