{
  "type": "Feature",
  "properties": {
    "addr:full":"15 Rumsey Rd Yonkers NY 10705",
    "addr:housenumber":"15",
    "addr:postcode":"10705",
    "addr:street":"Rumsey Rd",
    "iso:country":"US",
    "sg:address":"15 Rumsey Rd",
    "sg:city":"Yonkers",
    "sg:classifiers":[
        {
            "category":"Manufacturing",
            "subcategory":"Electronics",
            "type":"Manufacturing & Wholesale Goods"
        }
    ],
    "sg:phone":"+1   ",
    "sg:postcode":"10705",
    "sg:province":"NY",
    "wof:name":"Rumsey Corp",
    "wof:placetype":"venue"
},
  "geometry": {"coordinates":[-73.887281,40.920109],"type":"Point"}
}