{
  "type": "Feature",
  "properties": {
    "iso:country":"US",
    "sg:address":"4029 Broadway",
    "sg:city":"New York",
    "sg:classifiers":[
        {
            "category":"Shopping",
            "subcategory":"Clothing, Apparel, & Fashions",
            "type":"Retail Goods"
        }
    ],
    "sg:phone":"+1 212 795 4274",
    "sg:postcode":"10032",
    "sg:province":"NY",
    "sg:tags":[
        "dress",
        "sportswear"
    ],
    "wof:name":"Broadway Fashions",
    "wof:placetype":"venue"
},
  "geometry": {"coordinates":[-73.939356,40.842106],"type":"Point"}
}