{
  "type": "Feature",
  "properties": {
    "iso:country":"US",
    "sg:address":"1076 Co Rd 27",
    "sg:city":"Clifton Springs",
    "sg:classifiers":[
        {
            "category":"Building & Trades",
            "subcategory":"Cleaning & Sanitation",
            "type":"Services"
        }
    ],
    "sg:phone":"+1 315 462 6081",
    "sg:postcode":"14432",
    "sg:province":"NY",
    "sg:tags":[
        "maintenance",
        "contractor"
    ],
    "wof:name":"Sure Sweep Chimney Service",
    "wof:placetype":"venue"
},
  "geometry": {"coordinates":[-77.13439700000001,42.984143],"type":"Point"}
}