{
  "type": "Feature",
  "properties": {
    "addr:full":"255 Red Apple Ct Central Valley NY 10917",
    "addr:housenumber":"255",
    "addr:postcode":"10917",
    "addr:street":"Red Apple Ct",
    "iso:country":"US",
    "sg:address":"255 Red Apple Ct",
    "sg:city":"Central Valley",
    "sg:classifiers":[
        {
            "category":"Shopping",
            "subcategory":"Discount & Variety Stores",
            "type":"Retail Goods"
        }
    ],
    "sg:phone":"+1 845 928 9003",
    "sg:postcode":"10917",
    "sg:province":"NY",
    "sg:tags":[
        "outlet"
    ],
    "wof:name":"Dansk Factory Outlet Woodbury Cmn Premium Outlet",
    "wof:placetype":"venue"
},
  "geometry": {"coordinates":[-74.12690000000001,41.314999],"type":"Point"}
}