{
  "type": "Feature",
  "properties": {
    "addr:full":"3484 Union St North Chili NY 14514",
    "addr:housenumber":"3484",
    "addr:postcode":"14514",
    "addr:street":"Union St",
    "iso:country":"US",
    "sg:address":"3484 Union St",
    "sg:city":"North Chili",
    "sg:classifiers":[
        {
            "category":"Wholesale",
            "subcategory":"Scrap",
            "type":"Manufacturing & Wholesale Goods"
        }
    ],
    "sg:phone":"+1 585 594 1600",
    "sg:postcode":"14514",
    "sg:province":"NY",
    "sg:tags":[
        "recycling",
        "center"
    ],
    "wof:name":"Union Processing Corp",
    "wof:placetype":"venue"
},
  "geometry": {"coordinates":[-77.801045,43.104155],"type":"Point"}
}