{
  "type": "Feature",
  "properties": {
    "iso:country":"US",
    "sg:address":"57 E Kingsbridge Rd",
    "sg:city":"Bronx",
    "sg:classifiers":[
        {
            "category":"Shopping",
            "subcategory":"Pharmacy",
            "type":"Retail Goods"
        }
    ],
    "sg:phone":"+1 718 295 4444",
    "sg:postcode":"10468",
    "sg:province":"NY",
    "wof:name":"Star Drug Store",
    "wof:placetype":"venue"
},
  "geometry": {"coordinates":[-73.89554800000001,40.866761],"type":"Point"}
}