{
  "type": "Feature",
  "properties": {
    "addr:full":"57 E Kingsbridge Rd Bronx NY 10468",
    "addr:housenumber":"57",
    "addr:postcode":"10468",
    "addr:street":"E Kingsbridge Rd",
    "iso:country":"US",
    "sg:address":"57 E Kingsbridge Rd",
    "sg:city":"Bronx",
    "sg:classifiers":[
        {
            "category":"Shopping",
            "subcategory":"Pharmacy",
            "type":"Retail Goods"
        }
    ],
    "sg:phone":"+1 718 295 4444",
    "sg:postcode":"10468",
    "sg:province":"NY",
    "wof:name":"Star Drug Store",
    "wof:placetype":"venue"
},
  "geometry": {"coordinates":[-73.8959402965,40.867032969],"type":"Point"}
}