{
  "type": "Feature",
  "properties": {
    "iso:country":"US",
    "sg:address":"1136 Vine St",
    "sg:city":"Liverpool",
    "sg:classifiers":[
        {
            "category":"Real Estate",
            "subcategory":"Real Estate Operator",
            "type":"Services"
        }
    ],
    "sg:phone":"+1 315 422 8780",
    "sg:postcode":"13088",
    "sg:province":"NY",
    "sg:tags":[
        "building",
        "apartment"
    ],
    "wof:name":"Pine Tree Apartments",
    "wof:placetype":"venue"
},
  "geometry": {"coordinates":[-76.19156,43.115769],"type":"Point"}
}