{
  "type": "Feature",
  "properties": {
    "iso:country":"US",
    "sg:address":"555 Spencer St",
    "sg:city":"Syracuse",
    "sg:classifiers":[
        {
            "category":"Retail",
            "subcategory":"Auto Repair",
            "type":"Services"
        }
    ],
    "sg:phone":"+1 315 422 0281",
    "sg:postcode":"13204",
    "sg:province":"NY",
    "sg:tags":[
        "body",
        "automobile",
        "painting"
    ],
    "wof:name":"Free Spirit Design",
    "wof:placetype":"venue"
},
  "geometry": {"coordinates":[-76.168824,43.056936],"type":"Point"}
}