{
  "type": "Feature",
  "properties": {
    "addr:full":"447 Forest Ave Locust Valley NY 11560",
    "addr:housenumber":"447",
    "addr:postcode":"11560",
    "addr:street":"Forest Ave",
    "iso:country":"US",
    "sg:address":"447 Forest Ave",
    "sg:city":"Locust Valley",
    "sg:classifiers":[
        {
            "category":"Home & Garden",
            "subcategory":"Building Materials",
            "type":"Retail Goods"
        },
        {
            "category":"Building & Trades",
            "subcategory":"Plumbing",
            "type":"Services"
        }
    ],
    "sg:phone":"+1 516 671 7254",
    "sg:postcode":"11560",
    "sg:province":"NY",
    "sg:tags":[
        "plumbing",
        "contractor",
        "fixture",
        "supply"
    ],
    "wof:name":"Graziose Larry Plumbing & Htg",
    "wof:placetype":"venue"
},
  "geometry": {"coordinates":[-73.612984,40.874218],"type":"Point"}
}