{
  "type": "Feature",
  "properties": {
    "iso:country":"US",
    "sg:address":"7203 20th Ave",
    "sg:city":"Brooklyn",
    "sg:classifiers":[
        {
            "category":"Restaurant",
            "type":"Food & Drink"
        }
    ],
    "sg:phone":"+1 347 492 5623",
    "sg:postcode":"11204",
    "sg:province":"NY",
    "sg:tags":[
        "pizza"
    ],
    "wof:name":"Tasty Pizza On Third",
    "wof:placetype":"venue"
},
  "geometry": {"coordinates":[-73.989857,40.612439],"type":"Point"}
}