{
  "type": "Feature",
  "properties": {
    "iso:country":"US",
    "sg:address":"9 Center St",
    "sg:city":"Saugerties",
    "sg:classifiers":[
        {
            "category":"Building & Trades",
            "subcategory":"Landscaping Services",
            "type":"Services"
        }
    ],
    "sg:phone":"+1 845 246 1765",
    "sg:postcode":"12477",
    "sg:province":"NY",
    "sg:tags":[
        "landscape",
        "contractor"
    ],
    "wof:name":"J & J Lawn Svc",
    "wof:placetype":"venue"
},
  "geometry": {"coordinates":[-73.947999,42.077469],"type":"Point"}
}