{
  "type": "Feature",
  "properties": {
    "iso:country":"US",
    "sg:address":"312 Main St",
    "sg:city":"Highland Falls",
    "sg:classifiers":[
        {
            "category":"Shopping",
            "subcategory":"Used Merchandise",
            "type":"Retail Goods"
        }
    ],
    "sg:phone":"+1 845 446 5500",
    "sg:postcode":"10928",
    "sg:province":"NY",
    "sg:tags":[
        "antique"
    ],
    "wof:name":"Old Stock Exchange",
    "wof:placetype":"venue"
},
  "geometry": {"coordinates":[-73.964896,41.370732],"type":"Point"}
}