{
  "type": "Feature",
  "properties": {
    "iso:country":"US",
    "sg:address":"10 Washington Ave",
    "sg:city":"Plainview",
    "sg:classifiers":[
        {
            "category":"Shopping",
            "subcategory":"Optical Goods",
            "type":"Retail Goods"
        }
    ],
    "sg:phone":"+1   ",
    "sg:postcode":"11803",
    "sg:province":"NY",
    "sg:tags":[
        "medical",
        "doctor"
    ],
    "sg:website":"www.eyeglasshouse.com",
    "wof:name":"Eyeglass House",
    "wof:placetype":"venue"
},
  "geometry": {"coordinates":[-73.466078,40.778988],"type":"Point"}
}