{
  "type": "Feature",
  "properties": {
    "iso:country":"US",
    "sg:address":"37 W 26th St",
    "sg:city":"New York",
    "sg:classifiers":[
        {
            "category":"Personal",
            "type":"Services"
        }
    ],
    "sg:phone":"+1 212 683 9242",
    "sg:postcode":"10010",
    "sg:province":"NY",
    "sg:tags":[
        "sewing",
        "alteration"
    ],
    "wof:name":"Odette Barsa",
    "wof:placetype":"venue"
},
  "geometry": {"coordinates":[-73.990409,40.744626],"type":"Point"}
}