{
  "type": "Feature",
  "properties": {
    "addr:full":"New Yorker Hotel 481 Eighth Ave New York NY 10001",
    "addr:housenumber":"481",
    "addr:postcode":"10001",
    "addr:street":"Eighth Ave",
    "iso:country":"US",
    "sg:address":"New Yorker Hotel 481 Eighth Ave",
    "sg:city":"New York",
    "sg:classifiers":[
        {
            "category":"Restaurant",
            "type":"Food & Drink"
        }
    ],
    "sg:phone":"+1 212 268 8460",
    "sg:postcode":"10001",
    "sg:province":"NY",
    "sg:tags":[
        "traditional",
        "american"
    ],
    "sg:website":"cooperstavern.com/",
    "wof:name":"Cooper's Tavern",
    "wof:placetype":"venue"
},
  "geometry": {"coordinates":[-73.99344000000001,40.752226],"type":"Point"}
}