{
  "type": "Feature",
  "properties": {
    "iso:country":"US",
    "sg:address":"78 Lake St",
    "sg:city":"Le Roy",
    "sg:classifiers":[
        {
            "category":"Restaurant",
            "type":"Food & Drink"
        }
    ],
    "sg:phone":"+1 585 768 2770",
    "sg:postcode":"14482",
    "sg:province":"NY",
    "sg:tags":[
        "out"
    ],
    "wof:name":"Spirits",
    "wof:placetype":"venue"
},
  "geometry": {"coordinates":[-77.992267,42.981776],"type":"Point"}
}