{
  "type": "Feature",
  "properties": {
    "addr:full":"219 Lookout Cir Syracuse NY 13209",
    "addr:housenumber":"219",
    "addr:postcode":"13209",
    "addr:street":"Lookout Cir",
    "iso:country":"US",
    "sg:address":"219 Lookout Cir",
    "sg:city":"Syracuse",
    "sg:classifiers":[
        {
            "category":"Real Estate",
            "subcategory":"Real Estate Agent",
            "type":"Services"
        }
    ],
    "sg:phone":"+1 315 487 6992",
    "sg:postcode":"13209",
    "sg:province":"NY",
    "wof:name":"Anne M Murphy Realtor",
    "wof:placetype":"venue"
},
  "geometry": {"coordinates":[-76.23962400000001,43.059403],"type":"Point"}
}