{
  "type": "Feature",
  "properties": {
    "addr:full":"3688 State Rte 14A Penn Yan NY 14527",
    "addr:housenumber":"3688",
    "addr:postcode":"14527",
    "addr:street":"State Rte 14A",
    "iso:country":"US",
    "sg:address":"3688 State Rte 14A",
    "sg:city":"Penn Yan",
    "sg:classifiers":[
        {
            "category":"Real Estate",
            "subcategory":"Real Estate Agent",
            "type":"Services"
        }
    ],
    "sg:phone":"+1 315 531 3131",
    "sg:postcode":"14527",
    "sg:province":"NY",
    "wof:name":"Lake Living Realty",
    "wof:placetype":"venue"
},
  "geometry": {"coordinates":[-77.037057,42.588719],"type":"Point"}
}