{
  "type": "Feature",
  "properties": {
    "addr:full":"1119 Bedford Ave Brooklyn NY 11216",
    "addr:housenumber":"1119",
    "addr:postcode":"11216",
    "addr:street":"Bedford Ave",
    "iso:country":"US",
    "sg:address":"1119 Bedford Ave",
    "sg:city":"Brooklyn",
    "sg:classifiers":[
        {
            "category":"Education",
            "subcategory":"School",
            "type":"Public Place"
        }
    ],
    "sg:phone":"+1 718 783 2200",
    "sg:postcode":"11216",
    "sg:province":"NY",
    "sg:tags":[
        "high",
        "middle",
        "elementary"
    ],
    "wof:name":"Y M C A Technical Schools",
    "wof:placetype":"venue"
},
  "geometry": {"coordinates":[-73.954201,40.6856],"type":"Point"}
}