{
  "type": "Feature",
  "properties": {
    "addr:full":"106 Mappa Ave Barneveld NY 13304",
    "addr:housenumber":"106",
    "addr:postcode":"13304",
    "addr:street":"Mappa Ave",
    "iso:country":"US",
    "sg:address":"106 Mappa Ave",
    "sg:city":"Barneveld",
    "sg:classifiers":[
        {
            "category":"Personal",
            "subcategory":"Beauty Salon",
            "type":"Services"
        }
    ],
    "sg:phone":"+1 315 896 6112",
    "sg:postcode":"13304",
    "sg:province":"NY",
    "wof:name":"New Attitude",
    "wof:placetype":"venue"
},
  "geometry": {"coordinates":[-75.191322,43.275194],"type":"Point"}
}