{
  "type": "Feature",
  "properties": {
    "addr:full":"156 William Street Rm 1100 New York NY 10038",
    "addr:housenumber":"156",
    "addr:postcode":"1100;10038",
    "addr:street":"William Street",
    "iso:country":"US",
    "sg:address":"156 William Street Rm 1100",
    "sg:city":"New York",
    "sg:classifiers":[
        {
            "category":"Professional",
            "subcategory":"Lawyer & Legal Services",
            "type":"Services"
        }
    ],
    "sg:phone":"+1 212 571 0169",
    "sg:postcode":"10038",
    "sg:province":"NY",
    "wof:name":"Howard Borkan PC",
    "wof:placetype":"venue"
},
  "geometry": {"coordinates":[-74.00617200000001,40.709823],"type":"Point"}
}