{
  "type": "Feature",
  "properties": {
    "addr:full":"300 Broadway Dobbs Ferry NY 10522",
    "addr:housenumber":"300",
    "addr:postcode":"10522",
    "addr:street":"Broadway",
    "iso:country":"US",
    "sg:address":"300 Broadway",
    "sg:city":"Dobbs Ferry",
    "sg:classifiers":[
        {
            "category":"Building & Trades",
            "subcategory":"Plumbing",
            "type":"Services"
        }
    ],
    "sg:phone":"+1 914 674 0844",
    "sg:postcode":"10522",
    "sg:province":"NY",
    "sg:tags":[
        "contractor"
    ],
    "wof:name":"Morrow Plumbing & Heating RPS",
    "wof:placetype":"venue"
},
  "geometry": {"coordinates":[-73.875062,41.0128],"type":"Point"}
}