{
  "type": "Feature",
  "properties": {
    "iso:country":"US",
    "sg:address":"152 N Titmus Dr",
    "sg:city":"Mastic",
    "sg:classifiers":[
        {
            "category":"Wholesale",
            "subcategory":"Toys & Hobbies",
            "type":"Manufacturing & Wholesale Goods"
        }
    ],
    "sg:phone":"+1 631 395 5257",
    "sg:postcode":"11950",
    "sg:province":"NY",
    "sg:tags":[
        "toys-wholesale",
        "manufacturer"
    ],
    "sg:website":"http://www.giftbonanza.com",
    "wof:name":"Cathy's Gallery",
    "wof:placetype":"venue"
},
  "geometry": {"coordinates":[-72.854868,40.816226],"type":"Point"}
}