{
  "type": "Feature",
  "properties": {
    "iso:country":"US",
    "sg:address":"113 N 5th St",
    "sg:city":"Brooklyn",
    "sg:classifiers":[
        {
            "category":"Home & Garden",
            "subcategory":"Home Furnishings",
            "type":"Retail Goods"
        }
    ],
    "sg:phone":"+1 718 486 0863",
    "sg:postcode":"11211",
    "sg:province":"NY",
    "sg:tags":[
        "lighting"
    ],
    "wof:name":"Pure Lion Lighting Inc",
    "wof:placetype":"venue"
},
  "geometry": {"coordinates":[-73.959172,40.717038],"type":"Point"}
}