{
  "type": "Feature",
  "properties": {
    "addr:full":"57 Christian Ave Setauket NY 11733",
    "addr:housenumber":"57",
    "addr:postcode":"11733",
    "addr:street":"Christian Ave",
    "iso:country":"US",
    "sg:address":"57 Christian Ave",
    "sg:city":"Setauket",
    "sg:classifiers":[
        {
            "category":"Professional",
            "subcategory":"Lawyer & Legal Services",
            "type":"Services"
        }
    ],
    "sg:phone":"+1 631 941 1016",
    "sg:postcode":"11733",
    "sg:province":"NY",
    "sg:tags":[
        "clinic"
    ],
    "wof:name":"Glenda L Gregory Csw",
    "wof:placetype":"venue"
},
  "geometry": {"coordinates":[-73.12621300000001,40.940331],"type":"Point"}
}