{
  "type": "Feature",
  "properties": {
    "addr:full":"453 Dixon Rd Queensbury NY 12804",
    "addr:housenumber":"453",
    "addr:postcode":"12804",
    "addr:street":"Dixon Rd",
    "iso:country":"US",
    "sg:address":"453 Dixon Rd",
    "sg:city":"Queensbury",
    "sg:classifiers":[
        {
            "category":"Health Services",
            "subcategory":"Doctor",
            "type":"Services"
        }
    ],
    "sg:phone":"+1 518 792 1108",
    "sg:postcode":"12804",
    "sg:province":"NY",
    "sg:tags":[
        "dentist"
    ],
    "wof:name":"Patrick J Esmond DDS",
    "wof:placetype":"venue"
},
  "geometry": {"coordinates":[-73.696275,43.32826],"type":"Point"}
}