{
  "type": "Feature",
  "properties": {
    "addr:full":"353 E 14th St New York NY 10003",
    "addr:housenumber":"353",
    "addr:postcode":"10003",
    "addr:street":"E 14Th St",
    "iso:country":"US",
    "sg:address":"353 E 14th St",
    "sg:city":"New York",
    "sg:classifiers":[
        {
            "category":"Food & Beverages",
            "subcategory":"Groceries & Convenience Stores",
            "type":"Retail Goods"
        }
    ],
    "sg:phone":"+1 212 420 8182",
    "sg:postcode":"10003",
    "sg:province":"NY",
    "wof:name":"New Manila Food Mart",
    "wof:placetype":"venue"
},
  "geometry": {"coordinates":[-73.9832,40.731701],"type":"Point"}
}