{
  "type": "Feature",
  "properties": {
    "iso:country":"US",
    "sg:address":"11 5th St",
    "sg:city":"Canisteo",
    "sg:classifiers":[
        {
            "category":"Real Estate",
            "subcategory":"Real Estate Operator",
            "type":"Services"
        }
    ],
    "sg:phone":"+1 607 698 2963",
    "sg:postcode":"14823",
    "sg:province":"NY",
    "sg:tags":[
        "building",
        "apartment"
    ],
    "wof:name":"Canisteo Manor",
    "wof:placetype":"venue"
},
  "geometry": {"coordinates":[-77.605239,42.268426],"type":"Point"}
}