{
  "type": "Feature",
  "properties": {
    "addr:full":"1 Jennifer Ln Hartsdale NY 10530",
    "addr:housenumber":"1",
    "addr:postcode":"10530",
    "addr:street":"Jennifer Ln",
    "iso:country":"US",
    "sg:address":"1 Jennifer Ln",
    "sg:city":"Hartsdale",
    "sg:classifiers":[
        {
            "category":"Building & Trades",
            "subcategory":"Construction",
            "type":"Services"
        }
    ],
    "sg:phone":"+1 914 693 6183",
    "sg:postcode":"10530",
    "sg:province":"NY",
    "sg:tags":[
        "general",
        "contractor"
    ],
    "wof:name":"Neil Paladino Contractor Inc",
    "wof:placetype":"venue"
},
  "geometry": {"coordinates":[-73.82436199999999,41.029614],"type":"Point"}
}