{
  "type": "Feature",
  "properties": {
    "addr:full":"57 Columbine Ln Kings Park NY 11754",
    "addr:housenumber":"57",
    "addr:postcode":"11754",
    "addr:street":"Columbine Ln",
    "iso:country":"US",
    "sg:address":"57 Columbine Ln",
    "sg:city":"Kings Park",
    "sg:classifiers":[
        {
            "category":"Professional",
            "subcategory":"Advertising",
            "type":"Services"
        }
    ],
    "sg:phone":"+1 631 724 6493",
    "sg:postcode":"11754",
    "sg:province":"NY",
    "sg:website":"www.dot.com",
    "wof:name":"Dot.Com Consulting",
    "wof:placetype":"venue"
},
  "geometry": {"coordinates":[-73.238635,40.882595],"type":"Point"}
}