{
  "type": "Feature",
  "properties": {
    "addr:full":"158 Spencer Rd Candor NY 13743",
    "addr:housenumber":"158",
    "addr:postcode":"13743",
    "addr:street":"Spencer Rd",
    "iso:country":"US",
    "sg:address":"158 Spencer Rd",
    "sg:city":"Candor",
    "sg:classifiers":[
        {
            "category":"Retail",
            "subcategory":"Repair Shop",
            "type":"Services"
        }
    ],
    "sg:phone":"+1 607 659 4041",
    "sg:postcode":"13743",
    "sg:province":"NY",
    "sg:tags":[
        "tractor"
    ],
    "wof:name":"M T Auto & Tractor Repair",
    "wof:placetype":"venue"
},
  "geometry": {"coordinates":[-76.359796,42.23244],"type":"Point"}
}