{
  "type": "Feature",
  "properties": {
    "addr:full":"8416 Fathom Dr Baldwinsville NY 13027",
    "addr:housenumber":"8416",
    "addr:postcode":"13027",
    "addr:street":"Fathom Dr",
    "iso:country":"US",
    "sg:address":"8416 Fathom Dr",
    "sg:city":"Baldwinsville",
    "sg:classifiers":[
        {
            "category":"Professional",
            "subcategory":"Management & Consulting",
            "type":"Services"
        }
    ],
    "sg:phone":"+1 315 559 9579",
    "sg:postcode":"13027",
    "sg:province":"NY",
    "sg:tags":[
        "consultant"
    ],
    "wof:name":"Integrated Consulting Solution",
    "wof:placetype":"venue"
},
  "geometry": {"coordinates":[-76.262141,43.176713],"type":"Point"}
}