{
  "type": "Feature",
  "properties": {
    "iso:country":"US",
    "sg:address":"578 Golf Course Rd",
    "sg:city":"Warrensburg",
    "sg:classifiers":[
        {
            "category":"Personal",
            "subcategory":"Massage",
            "type":"Services"
        }
    ],
    "sg:phone":"+1 518 623 9898",
    "sg:postcode":"12885",
    "sg:province":"NY",
    "wof:name":"Jane Feldbum Therapeutic Massage",
    "wof:placetype":"venue"
},
  "geometry": {"coordinates":[-73.81204200000001,43.517502],"type":"Point"}
}