{
  "type": "Feature",
  "properties": {
    "addr:full":"88 W Broadway New York NY 10007",
    "addr:housenumber":"88",
    "addr:postcode":"10007",
    "addr:street":"W Broadway",
    "iso:country":"US",
    "sg:address":"88 W Broadway",
    "sg:city":"New York",
    "sg:classifiers":[
        {
            "category":"Real Estate",
            "subcategory":"Architect",
            "type":"Services"
        }
    ],
    "sg:phone":"+1 212 267 2378",
    "sg:postcode":"10007",
    "sg:province":"NY",
    "sg:tags":[
        "architectural"
    ],
    "wof:name":"Audrey Matlock Architect",
    "wof:placetype":"venue"
},
  "geometry": {"coordinates":[-74.009471,40.715271],"type":"Point"}
}