{
  "type": "Feature",
  "properties": {
    "iso:country":"US",
    "sg:address":"15 W 47 St",
    "sg:city":"New York",
    "sg:classifiers":[
        {
            "category":"Wholesale",
            "subcategory":"Jewelry",
            "type":"Manufacturing & Wholesale Goods"
        }
    ],
    "sg:phone":"+1 212 719 3430",
    "sg:postcode":"10036",
    "sg:province":"NY",
    "sg:tags":[
        "buyer",
        "diamond"
    ],
    "wof:name":"Leon Rafalowicz Diamond Co",
    "wof:placetype":"venue"
},
  "geometry": {"coordinates":[-73.981408,40.757891],"type":"Point"}
}