{
  "type": "Feature",
  "properties": {
    "iso:country":"US",
    "sg:address":"204 W Water St",
    "sg:city":"Elmira",
    "sg:classifiers":[
        {
            "category":"Shopping",
            "subcategory":"Music",
            "type":"Retail Goods"
        }
    ],
    "sg:phone":"+1 607 733 0556",
    "sg:postcode":"14901",
    "sg:province":"NY",
    "sg:tags":[
        "compact",
        "record",
        "disc",
        "tape"
    ],
    "wof:name":"Sounds Fine",
    "wof:placetype":"venue"
},
  "geometry": {"coordinates":[-76.808763,42.087453],"type":"Point"}
}