{
  "type": "Feature",
  "properties": {
    "iso:country":"US",
    "sg:address":"1995 Randallsville Rd",
    "sg:city":"Hamilton",
    "sg:classifiers":[
        {
            "category":"Shopping",
            "subcategory":"Optical Goods",
            "type":"Retail Goods"
        }
    ],
    "sg:phone":"+1   ",
    "sg:postcode":"13346",
    "sg:province":"NY",
    "wof:name":"Visions Edge",
    "wof:placetype":"venue"
},
  "geometry": {"coordinates":[-75.55726,42.810453],"type":"Point"}
}