{
  "type": "Feature",
  "properties": {
    "addr:full":"1370 Richmond Rd Staten Island NY 10304",
    "addr:housenumber":"1370",
    "addr:postcode":"10304",
    "addr:street":"Richmond Rd",
    "iso:country":"US",
    "sg:address":"1370 Richmond Rd",
    "sg:city":"Staten Island",
    "sg:classifiers":[
        {
            "category":"Health Services",
            "subcategory":"Health Practitioner",
            "type":"Services"
        }
    ],
    "sg:phone":"+1 718 667 3336",
    "sg:postcode":"10304",
    "sg:province":"NY",
    "sg:tags":[
        "therapist",
        "physical"
    ],
    "wof:name":"Champion Medical Svc",
    "wof:placetype":"venue"
},
  "geometry": {"coordinates":[-74.097987,40.59493],"type":"Point"}
}