{
  "type": "Feature",
  "properties": {
    "addr:full":"242 Greenpoint Ave Brooklyn NY 11222",
    "addr:housenumber":"242",
    "addr:postcode":"11222",
    "addr:street":"Greenpoint Ave",
    "iso:country":"US",
    "sg:address":"242 Greenpoint Ave",
    "sg:city":"Brooklyn",
    "sg:classifiers":[
        {
            "category":"Building & Trades",
            "subcategory":"Cleaning & Sanitation",
            "type":"Services"
        }
    ],
    "sg:phone":"+1 718 349 0491",
    "sg:postcode":"11222",
    "sg:province":"NY",
    "sg:tags":[
        "maintenance"
    ],
    "wof:name":"Greenpoint Industrial Ctr",
    "wof:placetype":"venue"
},
  "geometry": {"coordinates":[-73.94937299999999,40.730583],"type":"Point"}
}