{
  "type": "Feature",
  "properties": {
    "iso:country":"US",
    "sg:address":"1228 Penora St",
    "sg:city":"Depew",
    "sg:classifiers":[
        {
            "category":"Retail",
            "subcategory":"Auto Repair",
            "type":"Services"
        }
    ],
    "sg:phone":"+1   ",
    "sg:postcode":"14043",
    "sg:province":"NY",
    "sg:tags":[
        "general"
    ],
    "wof:name":"High Street Automotive",
    "wof:placetype":"venue"
},
  "geometry": {"coordinates":[-78.687758,42.890264],"type":"Point"}
}