{
  "type": "Feature",
  "properties": {
    "addr:full":"276 5th Ave New York NY 10001",
    "addr:housenumber":"276",
    "addr:postcode":"10001",
    "addr:street":"5Th Ave",
    "iso:country":"US",
    "sg:address":"276 5th Ave",
    "sg:city":"New York",
    "sg:classifiers":[
        {
            "category":"Arts & Performance",
            "subcategory":"Music",
            "type":"Entertainment"
        }
    ],
    "sg:phone":"+1 347 723 4886",
    "sg:postcode":"10001",
    "sg:province":"NY",
    "sg:tags":[
        "dj"
    ],
    "sg:website":"www.weddingDJinNY.com",
    "wof:name":"Wedding DJ in NY",
    "wof:placetype":"venue"
},
  "geometry": {"coordinates":[-73.98693799999999,40.745846],"type":"Point"}
}