{
  "type": "Feature",
  "properties": {
    "addr:full":"10123 124th Street South Richmond Hill NY 11419",
    "addr:housenumber":"10123",
    "addr:postcode":"11419",
    "addr:street":"124Th Street South",
    "iso:country":"US",
    "sg:address":"10123 124th Street",
    "sg:city":"South Richmond Hill",
    "sg:classifiers":[
        {
            "category":"Education",
            "subcategory":"School",
            "type":"Public Place"
        }
    ],
    "sg:phone":"+1 718 441 5493",
    "sg:postcode":"11419",
    "sg:province":"NY",
    "sg:tags":[
        "high",
        "middle",
        "elementary"
    ],
    "wof:name":"N Y City of",
    "wof:placetype":"venue"
},
  "geometry": {"coordinates":[-73.82162,40.691],"type":"Point"}
}