{
  "type": "Feature",
  "properties": {
    "iso:country":"US",
    "sg:address":"75 Wilson Ave",
    "sg:city":"Brooklyn",
    "sg:classifiers":[
        {
            "category":"Manufacturing",
            "subcategory":"Tools & Machinery",
            "type":"Manufacturing & Wholesale Goods"
        },
        {
            "category":"Shopping",
            "subcategory":"Crafts & Fabrics",
            "type":"Retail Goods"
        }
    ],
    "sg:phone":"+1 718 388 9048",
    "sg:postcode":"11237",
    "sg:province":"NY",
    "sg:tags":[
        "sewing",
        "machines-household",
        "machines-industrial"
    ],
    "wof:name":"Schlesinger Adolf",
    "wof:placetype":"venue"
},
  "geometry": {"coordinates":[-73.92810299999999,40.702044],"type":"Point"}
}