{
  "type": "Feature",
  "properties": {
    "iso:country":"US",
    "sg:address":"1314 Cortelyou Rd",
    "sg:city":"Brooklyn",
    "sg:classifiers":[
        {
            "category":"Restaurant",
            "type":"Food & Drink"
        }
    ],
    "sg:phone":"+1 718 940 8188",
    "sg:postcode":"11226",
    "sg:province":"NY",
    "sg:tags":[
        "fusion",
        "asian",
        "filipino"
    ],
    "sg:website":"www.purpleyamnyc.com",
    "wof:name":"Purple Yam",
    "wof:placetype":"venue"
},
  "geometry": {"coordinates":[-73.966048,40.640482],"type":"Point"}
}