{
  "type": "Feature",
  "properties": {
    "iso:country":"US",
    "sg:address":"3172 Middle Country Rd",
    "sg:city":"Lake Grove",
    "sg:classifiers":[
        {
            "category":"Shopping",
            "subcategory":"Clothing, Apparel, & Fashions",
            "type":"Retail Goods"
        }
    ],
    "sg:phone":"+1 631 676 7142",
    "sg:postcode":"11755",
    "sg:province":"NY",
    "sg:tags":[
        "costume"
    ],
    "wof:name":"Halloween USA",
    "wof:placetype":"venue"
},
  "geometry": {"coordinates":[-73.124359,40.861607],"type":"Point"}
}