{
  "type": "Feature",
  "properties": {
    "iso:country":"US",
    "sg:address":"658 Clarence Ave",
    "sg:city":"Bronx",
    "sg:classifiers":[
        {
            "category":"Organizations",
            "subcategory":"Community Association",
            "type":"Services"
        }
    ],
    "sg:phone":"+1 718 822 8965",
    "sg:postcode":"10465",
    "sg:province":"NY",
    "sg:tags":[
        "club"
    ],
    "wof:name":"Manhem Club Inc",
    "wof:placetype":"venue"
},
  "geometry": {"coordinates":[-73.814223,40.828468],"type":"Point"}
}