{
  "type": "Feature",
  "properties": {
    "iso:country":"US",
    "sg:address":"3388 Southwestern Blvd",
    "sg:city":"Orchard Park",
    "sg:classifiers":[
        {
            "category":"Autos & Motor Vehicles",
            "subcategory":"Fuel & Gas Station",
            "type":"Retail Goods"
        }
    ],
    "sg:phone":"+1 716 675 7681",
    "sg:postcode":"14127",
    "sg:province":"NY",
    "sg:tags":[
        "oil"
    ],
    "wof:name":"White Arrow Svc Stations Inc",
    "wof:placetype":"venue"
},
  "geometry": {"coordinates":[-78.754375,42.794854],"type":"Point"}
}