{
  "type": "Feature",
  "properties": {
    "iso:country":"US",
    "sg:address":"599 Spencer Rd",
    "sg:city":"Ithaca",
    "sg:classifiers":[
        {
            "category":"Home & Garden",
            "subcategory":"Furniture",
            "type":"Retail Goods"
        }
    ],
    "sg:phone":"+1   ",
    "sg:postcode":"14850",
    "sg:province":"NY",
    "wof:name":"Fuchs Productions",
    "wof:placetype":"venue"
},
  "geometry": {"coordinates":[-76.513367,42.423077],"type":"Point"}
}