{
  "type": "Feature",
  "properties": {
    "iso:country":"US",
    "sg:address":"77 Singworth St",
    "sg:city":"Oyster Bay",
    "sg:classifiers":[
        {
            "category":"Real Estate",
            "subcategory":"Real Estate Agent",
            "type":"Services"
        }
    ],
    "sg:phone":"+1 516 922 5977",
    "sg:postcode":"11771",
    "sg:province":"NY",
    "wof:name":"Green Mountain Basics",
    "wof:placetype":"venue"
},
  "geometry": {"coordinates":[-73.528093,40.862055],"type":"Point"}
}