{
  "type": "Feature",
  "properties": {
    "addr:full":"2376 Parkview Pl Baldwin NY 11510",
    "addr:housenumber":"2376",
    "addr:postcode":"11510",
    "addr:street":"Parkview Pl",
    "iso:country":"US",
    "sg:address":"2376 Parkview Pl",
    "sg:city":"Baldwin",
    "sg:classifiers":[
        {
            "category":"Shopping",
            "subcategory":"Clothing, Apparel, & Fashions",
            "type":"Retail Goods"
        }
    ],
    "sg:phone":"+1   ",
    "sg:postcode":"11510",
    "sg:province":"NY",
    "wof:name":"One Stop Leather Shop",
    "wof:placetype":"venue"
},
  "geometry": {"coordinates":[-73.619218,40.649703],"type":"Point"}
}