{
  "type": "Feature",
  "properties": {
    "addr:full":"166 E 34th St New York NY 10016",
    "addr:housenumber":"166",
    "addr:postcode":"10016",
    "addr:street":"E 34Th St",
    "iso:country":"US",
    "sg:address":"166 E 34th St",
    "sg:city":"New York",
    "sg:classifiers":[
        {
            "category":"Building & Trades",
            "subcategory":"Locksmith",
            "type":"Services"
        }
    ],
    "sg:phone":"+1 646 365 0306",
    "sg:postcode":"10016",
    "sg:province":"NY",
    "sg:tags":[
        "key"
    ],
    "wof:name":"Apropo Locksmith",
    "wof:placetype":"venue"
},
  "geometry": {"coordinates":[-73.97910299999999,40.746101],"type":"Point"}
}