{
  "type": "Feature",
  "properties": {
    "iso:country":"US",
    "sg:address":"7 S River Rd",
    "sg:city":"Calverton",
    "sg:classifiers":[
        {
            "category":"Shopping",
            "subcategory":"Clothing, Apparel, & Fashions",
            "type":"Retail Goods"
        }
    ],
    "sg:phone":"+1   ",
    "sg:postcode":"11933",
    "sg:province":"NY",
    "wof:name":"Carolina Sewing",
    "wof:placetype":"venue"
},
  "geometry": {"coordinates":[-72.716656,40.912447],"type":"Point"}
}