{
  "type": "Feature",
  "properties": {
    "addr:full":"270 Buell Rd Rochester NY 14624",
    "addr:housenumber":"270",
    "addr:postcode":"14624",
    "addr:street":"Buell Rd",
    "iso:country":"US",
    "sg:address":"270 Buell Rd",
    "sg:city":"Rochester",
    "sg:classifiers":[
        {
            "category":"Airline",
            "type":"Transportation"
        }
    ],
    "sg:phone":"+1   ",
    "sg:postcode":"14624",
    "sg:province":"NY",
    "sg:tags":[
        "courier",
        "air"
    ],
    "wof:name":"Geologistics Americas Inc",
    "wof:placetype":"venue"
},
  "geometry": {"coordinates":[-77.665854,43.13638],"type":"Point"}
}