{
  "type": "Feature",
  "properties": {
    "iso:country":"US",
    "sg:address":"651 E 183rd St",
    "sg:city":"Bronx",
    "sg:classifiers":[
        {
            "category":"Retail",
            "subcategory":"Repair Shop",
            "type":"Services"
        }
    ],
    "sg:phone":"+1 718 887 2370",
    "sg:postcode":"10458",
    "sg:province":"NY",
    "sg:tags":[
        "lock",
        "locksmith"
    ],
    "wof:name":"USA Locksmith",
    "wof:placetype":"venue"
},
  "geometry": {"coordinates":[-73.887608,40.852715],"type":"Point"}
}