{
  "type": "Feature",
  "properties": {
    "addr:full":"40 W 36 St New York NY 10018",
    "addr:housenumber":"40",
    "addr:postcode":"10018",
    "addr:street":"W 36 St",
    "iso:country":"US",
    "sg:address":"40 W 36 St",
    "sg:city":"New York",
    "sg:classifiers":[
        {
            "category":"Wholesale",
            "subcategory":"Apparel",
            "type":"Manufacturing & Wholesale Goods"
        }
    ],
    "sg:phone":"+1 212 213 4680",
    "sg:postcode":"10018",
    "sg:province":"NY",
    "wof:name":"Creative Clothing Inc",
    "wof:placetype":"venue"
},
  "geometry": {"coordinates":[-73.985917,40.750479],"type":"Point"}
}