{
  "type": "Feature",
  "properties": {
    "iso:country":"US",
    "sg:address":"88 Montauk Hwy",
    "sg:city":"Copiague",
    "sg:classifiers":[
        {
            "category":"Restaurant",
            "type":"Food & Drink"
        }
    ],
    "sg:menulink":"http://www.allmenus.com/ny/babylon/56209-joes-pizzeria/menu/",
    "sg:phone":"+1 631 789 8020",
    "sg:postcode":"11726",
    "sg:province":"NY",
    "sg:tags":[
        "italian"
    ],
    "wof:name":"Joe's Pizzeria",
    "wof:placetype":"venue"
},
  "geometry": {"coordinates":[-73.39936899999999,40.667762],"type":"Point"}
}