{
  "type": "Feature",
  "properties": {
    "iso:country":"US",
    "sg:address":"13 Deerfield Pl",
    "sg:city":"Ballston Spa",
    "sg:classifiers":[
        {
            "category":"Professional",
            "subcategory":"Employment Agencies",
            "type":"Services"
        }
    ],
    "sg:phone":"+1 518 885 2631",
    "sg:postcode":"12020",
    "sg:province":"NY",
    "wof:name":"Booth Yllin Physcn Recruitment",
    "wof:placetype":"venue"
},
  "geometry": {"coordinates":[-73.847416,43.035195],"type":"Point"}
}