{
  "type": "Feature",
  "properties": {
    "addr:full":"28 Debevoise St Brooklyn NY 11206",
    "addr:housenumber":"28",
    "addr:postcode":"11206",
    "addr:street":"Debevoise St",
    "iso:country":"US",
    "sg:address":"28 Debevoise St",
    "sg:city":"Brooklyn",
    "sg:classifiers":[
        {
            "category":"Shopping",
            "subcategory":"Clothing, Apparel, & Fashions",
            "type":"Retail Goods"
        }
    ],
    "sg:phone":"+1 718 218 6403",
    "sg:postcode":"11206",
    "sg:province":"NY",
    "sg:tags":[
        "accessory",
        "clothing",
        "women's"
    ],
    "wof:name":"Cliquer's Clothing",
    "wof:placetype":"venue"
},
  "geometry": {"coordinates":[-73.942018,40.701514],"type":"Point"}
}