{
  "type": "Feature",
  "properties": {
    "addr:full":"1142 Merrick Ave Merrick NY 11566",
    "addr:housenumber":"1142",
    "addr:postcode":"11566",
    "addr:street":"Merrick Ave",
    "iso:country":"US",
    "sg:address":"1142 Merrick Ave",
    "sg:city":"Merrick",
    "sg:classifiers":[
        {
            "category":"Food & Beverages",
            "subcategory":"Meat & Fish",
            "type":"Retail Goods"
        }
    ],
    "sg:phone":"+1   ",
    "sg:postcode":"11566",
    "sg:province":"NY",
    "wof:name":"Beef Barn",
    "wof:placetype":"venue"
},
  "geometry": {"coordinates":[-73.564447,40.693538],"type":"Point"}
}