{
  "type": "Feature",
  "properties": {
    "iso:country":"US",
    "sg:address":"66 Bogart Ave",
    "sg:city":"Port Washington",
    "sg:classifiers":[
        {
            "category":"Professional",
            "subcategory":"Management & Consulting",
            "type":"Services"
        }
    ],
    "sg:phone":"+1   ",
    "sg:postcode":"11050",
    "sg:province":"NY",
    "sg:tags":[
        "retail",
        "direct",
        "sales"
    ],
    "wof:name":"Cod Fuel Oil Corp",
    "wof:placetype":"venue"
},
  "geometry": {"coordinates":[-73.67675699999999,40.831422],"type":"Point"}
}