{
  "type": "Feature",
  "properties": {
    "addr:full":"210 Central Ave Lancaster NY 14086",
    "addr:housenumber":"210",
    "addr:postcode":"14086",
    "addr:street":"Central Ave",
    "iso:country":"US",
    "sg:address":"210 Central Ave",
    "sg:city":"Lancaster",
    "sg:classifiers":[
        {
            "category":"Personal",
            "subcategory":"Beauty Salon",
            "type":"Services"
        }
    ],
    "sg:phone":"+1 716 683 7005",
    "sg:postcode":"14086",
    "sg:province":"NY",
    "wof:name":"Hair Central",
    "wof:placetype":"venue"
},
  "geometry": {"coordinates":[-78.67144999999999,42.908857],"type":"Point"}
}