{
  "type": "Feature",
  "properties": {
    "addr:full":"299 Central Park Ave Yonkers NY 10704",
    "addr:housenumber":"299",
    "addr:postcode":"10704",
    "addr:street":"Central Park Ave",
    "iso:country":"US",
    "sg:address":"299 Central Park Ave",
    "sg:city":"Yonkers",
    "sg:classifiers":[
        {
            "category":"Retail",
            "subcategory":"Veterinary Services",
            "type":"Services"
        }
    ],
    "sg:phone":"+1 914 963 2600",
    "sg:postcode":"10704",
    "sg:province":"NY",
    "sg:tags":[
        "veterinarian",
        "specialty"
    ],
    "wof:name":"Home Vet Care Mobile Veterinary House",
    "wof:placetype":"venue"
},
  "geometry": {"coordinates":[-73.872964,40.915768],"type":"Point"}
}