{
  "type": "Feature",
  "properties": {
    "addr:full":"232 W Old Country Rd Hicksville NY 11801",
    "addr:housenumber":"232",
    "addr:postcode":"11801",
    "addr:street":"W Old Country Rd",
    "iso:country":"US",
    "sg:address":"232 W Old Country Rd",
    "sg:city":"Hicksville",
    "sg:classifiers":[
        {
            "category":"Shopping",
            "subcategory":"Photographic Equipment",
            "type":"Retail Goods"
        }
    ],
    "sg:phone":"+1 516 937 0707",
    "sg:postcode":"11801",
    "sg:province":"NY",
    "sg:tags":[
        "camera",
        "photography",
        "computer",
        "store",
        "supply"
    ],
    "sg:website":"www.westburycameras.com",
    "wof:name":"Westbury Camera & Computers",
    "wof:placetype":"venue"
},
  "geometry": {"coordinates":[-73.529701,40.761398],"type":"Point"}
}