{
  "type": "Feature",
  "properties": {
    "addr:full":"9 James St Middletown NY 10940",
    "addr:housenumber":"9",
    "addr:postcode":"10940",
    "addr:street":"James St",
    "iso:country":"US",
    "sg:address":"9 James St",
    "sg:city":"Middletown",
    "sg:classifiers":[
        {
            "category":"Cinema",
            "subcategory":"Drive-in Theater",
            "type":"Entertainment"
        }
    ],
    "sg:phone":"+1   ",
    "sg:postcode":"10940",
    "sg:province":"NY",
    "sg:tags":[
        "movie",
        "drive"
    ],
    "wof:name":"Fair Oaks Drive In Theater",
    "wof:placetype":"venue"
},
  "geometry": {"coordinates":[-74.421396,41.445706],"type":"Point"}
}