{
  "type": "Feature",
  "properties": {
    "iso:country":"US",
    "sg:address":"711 Clinton St",
    "sg:city":"Buffalo",
    "sg:classifiers":[
        {
            "category":"Manufacturing",
            "subcategory":"Building Materials",
            "type":"Manufacturing & Wholesale Goods"
        }
    ],
    "sg:phone":"+1 716 854 0360",
    "sg:postcode":"14210",
    "sg:province":"NY",
    "sg:tags":[
        "cabinet"
    ],
    "wof:name":"Frans Cabinet & Display Co",
    "wof:placetype":"venue"
},
  "geometry": {"coordinates":[-78.848133,42.880815],"type":"Point"}
}