{
  "type": "Feature",
  "properties": {
    "iso:country":"US",
    "sg:address":"204 Kramer Dr",
    "sg:city":"Syracuse",
    "sg:classifiers":[
        {
            "category":"Shopping",
            "type":"Retail Goods"
        }
    ],
    "sg:phone":"+1 315 378 0046",
    "sg:postcode":"13207",
    "sg:province":"NY",
    "sg:tags":[
        "cosmetic",
        "perfume"
    ],
    "wof:name":"Pierot Beauty Supply",
    "wof:placetype":"venue"
},
  "geometry": {"coordinates":[-76.15529600000001,43.001055],"type":"Point"}
}