{
  "type": "Feature",
  "properties": {
    "iso:country":"US",
    "sg:address":"6 Trinity Way",
    "sg:city":"Lagrangeville",
    "sg:classifiers":[
        {
            "category":"Professional",
            "subcategory":"Lawyer & Legal Services",
            "type":"Services"
        }
    ],
    "sg:phone":"+1 845 226 2991",
    "sg:postcode":"12540",
    "sg:province":"NY",
    "sg:tags":[
        "attorney"
    ],
    "wof:name":"Thomas Cunningham",
    "wof:placetype":"venue"
},
  "geometry": {"coordinates":[-73.745746,41.67392],"type":"Point"}
}