{
  "type": "Feature",
  "properties": {
    "iso:country":"US",
    "sg:address":"364 Ann St",
    "sg:city":"Newburgh",
    "sg:classifiers":[
        {
            "category":"Retail",
            "subcategory":"Car Wash",
            "type":"Services"
        }
    ],
    "sg:phone":"+1 845 569 4075",
    "sg:postcode":"12550",
    "sg:province":"NY",
    "sg:tags":[
        "automobile",
        "detail",
        "clean"
    ],
    "wof:name":"J & F Auto Detailing",
    "wof:placetype":"venue"
},
  "geometry": {"coordinates":[-74.023824,41.500165],"type":"Point"}
}