{
  "type": "Feature",
  "properties": {
    "iso:country":"US",
    "sg:address":"1903 State Hwy 203",
    "sg:city":"Chatham",
    "sg:classifiers":[
        {
            "category":"Building & Trades",
            "subcategory":"Construction",
            "type":"Services"
        }
    ],
    "sg:phone":"+1 518 392 5676",
    "sg:postcode":"12037",
    "sg:province":"NY",
    "sg:tags":[
        "utility",
        "contractor"
    ],
    "wof:name":"Davis Valve Installation Inc",
    "wof:placetype":"venue"
},
  "geometry": {"coordinates":[-73.611694,42.359836],"type":"Point"}
}