{
  "type": "Feature",
  "properties": {
    "iso:country":"US",
    "sg:address":"457 W 22nd St Apt B",
    "sg:city":"New York",
    "sg:classifiers":[
        {
            "category":"Arts & Performance",
            "subcategory":"Music",
            "type":"Entertainment"
        },
        {
            "category":"Shopping",
            "subcategory":"Computers & Home Electronics",
            "type":"Retail Goods"
        }
    ],
    "sg:phone":"+1 212 924 5727",
    "sg:postcode":"10011",
    "sg:province":"NY",
    "sg:tags":[
        "dj"
    ],
    "wof:name":"Sine Audio",
    "wof:placetype":"venue"
},
  "geometry": {"coordinates":[-74.003502,40.746601],"type":"Point"}
}