{
  "type": "Feature",
  "properties": {
    "addr:full":"754 5th Ave New York NY 10019",
    "addr:housenumber":"754",
    "addr:postcode":"10019",
    "addr:street":"5Th Ave",
    "iso:country":"US",
    "sg:address":"754 5th Ave",
    "sg:city":"New York",
    "sg:classifiers":[
        {
            "category":"Home & Garden",
            "subcategory":"Home Furnishings",
            "type":"Retail Goods"
        }
    ],
    "sg:phone":"+1 212 753 7352",
    "sg:postcode":"10019",
    "sg:province":"NY",
    "sg:tags":[
        "linen"
    ],
    "wof:name":"Leslie Anderson LTD",
    "wof:placetype":"venue"
},
  "geometry": {"coordinates":[-73.973759,40.763279],"type":"Point"}
}