{
  "type": "Feature",
  "properties": {
    "addr:full":"128 Mott St New York NY 10013",
    "addr:housenumber":"128",
    "addr:postcode":"10013",
    "addr:street":"Mott St",
    "iso:country":"US",
    "sg:address":"128 Mott St",
    "sg:city":"New York",
    "sg:classifiers":[
        {
            "category":"Health Services",
            "subcategory":"Doctor",
            "type":"Services"
        }
    ],
    "sg:phone":"+1 212 587 8838",
    "sg:postcode":"10013",
    "sg:province":"NY",
    "wof:name":"Chan Edward V, MD",
    "wof:placetype":"venue"
},
  "geometry": {"coordinates":[-73.99647899999999,40.718464],"type":"Point"}
}