{
  "type": "Feature",
  "properties": {
    "addr:full":"3041 Hempstead Tpke Levittown NY 11756",
    "addr:housenumber":"3041",
    "addr:postcode":"11756",
    "addr:street":"Hempstead Tpke",
    "iso:country":"US",
    "sg:address":"3041 Hempstead Tpke",
    "sg:city":"Levittown",
    "sg:classifiers":[
        {
            "category":"Shopping",
            "subcategory":"Jewelry",
            "type":"Retail Goods"
        }
    ],
    "sg:phone":"+1 516 579 7154",
    "sg:postcode":"11756",
    "sg:province":"NY",
    "sg:website":"www.turkanjewelry.com",
    "wof:name":"Turkan Jewelry",
    "wof:placetype":"venue"
},
  "geometry": {"coordinates":[-73.52330000000001,40.725101],"type":"Point"}
}