{
  "type": "Feature",
  "properties": {
    "iso:country":"US",
    "sg:address":"525 Pavement Rd",
    "sg:city":"Lancaster",
    "sg:classifiers":[
        {
            "category":"Government",
            "subcategory":"Office",
            "type":"Public Place"
        }
    ],
    "sg:phone":"+1 716 684 3320",
    "sg:postcode":"14086",
    "sg:province":"NY",
    "sg:tags":[
        "department",
        "recreation"
    ],
    "wof:name":"Recreation Office",
    "wof:placetype":"venue"
},
  "geometry": {"coordinates":[-78.62271200000001,42.929973],"type":"Point"}
}