{
  "type": "Feature",
  "properties": {
    "addr:full":"750 Baychester Ave Bronx NY 10475",
    "addr:housenumber":"750",
    "addr:postcode":"10475",
    "addr:street":"Baychester Ave",
    "iso:country":"US",
    "sg:address":"750 Baychester Ave",
    "sg:city":"Bronx",
    "sg:classifiers":[
        {
            "category":"Building & Trades",
            "subcategory":"Construction",
            "type":"Services"
        }
    ],
    "sg:phone":"+1 718 862 1060",
    "sg:postcode":"10475",
    "sg:province":"NY",
    "sg:tags":[
        "company"
    ],
    "wof:name":"Iannelli Construction",
    "wof:placetype":"venue"
},
  "geometry": {"coordinates":[-73.833392,40.873775],"type":"Point"}
}