{
  "type": "Feature",
  "properties": {
    "addr:full":"207 Ave U Brooklyn NY 11223",
    "addr:housenumber":"207",
    "addr:postcode":"11223",
    "addr:street":"Ave U",
    "iso:country":"US",
    "sg:address":"207 Ave U",
    "sg:city":"Brooklyn",
    "sg:classifiers":[
        {
            "category":"Retail",
            "subcategory":"Repair Shop",
            "type":"Services"
        }
    ],
    "sg:phone":"+1 718 301 7214",
    "sg:postcode":"11223",
    "sg:province":"NY",
    "sg:tags":[
        "lock",
        "locksmith"
    ],
    "wof:name":"24 All Day Emergency Locksmith",
    "wof:placetype":"venue"
},
  "geometry": {"coordinates":[-73.975663,40.596784],"type":"Point"}
}