{
  "type": "Feature",
  "properties": {
    "addr:full":"1626 E 16th St Brooklyn NY 11229",
    "addr:housenumber":"1626",
    "addr:postcode":"11229",
    "addr:street":"E 16Th St",
    "iso:country":"US",
    "sg:address":"1626 E 16th St",
    "sg:city":"Brooklyn",
    "sg:classifiers":[
        {
            "category":"Food & Beverages",
            "subcategory":"Meat & Fish",
            "type":"Retail Goods"
        }
    ],
    "sg:phone":"+1   ",
    "sg:postcode":"11229",
    "sg:province":"NY",
    "wof:name":"Polyas Fish Market",
    "wof:placetype":"venue"
},
  "geometry": {"coordinates":[-73.95755200000001,40.609619],"type":"Point"}
}