{
  "type": "Feature",
  "properties": {
    "addr:full":"1742 Chrisler Ave Schenectady NY 12303",
    "addr:housenumber":"1742",
    "addr:postcode":"12303",
    "addr:street":"Chrisler Ave",
    "iso:country":"US",
    "sg:address":"1742 Chrisler Ave",
    "sg:city":"Schenectady",
    "sg:classifiers":[
        {
            "category":"Personal",
            "subcategory":"Beauty Salon",
            "type":"Services"
        }
    ],
    "sg:phone":"+1 518 372 6012",
    "sg:postcode":"12303",
    "sg:province":"NY",
    "sg:tags":[
        "shop"
    ],
    "wof:name":"Mane Attraction",
    "wof:placetype":"venue"
},
  "geometry": {"coordinates":[-73.93058000000001,42.784218],"type":"Point"}
}