{
  "type": "Feature",
  "properties": {
    "iso:country":"US",
    "sg:address":"50 Gibbs Rd",
    "sg:city":"Coram",
    "sg:classifiers":[
        {
            "category":"Real Estate",
            "subcategory":"Real Estate Operator",
            "type":"Services"
        }
    ],
    "sg:phone":"+1 631 928 0488",
    "sg:postcode":"11727",
    "sg:province":"NY",
    "sg:tags":[
        "condominium"
    ],
    "wof:name":"Coram Isle LLC",
    "wof:placetype":"venue"
},
  "geometry": {"coordinates":[-73.00619399999999,40.894089],"type":"Point"}
}