{
  "type": "Feature",
  "properties": {
    "addr:full":"1057 Southern Blvd Bronx NY 10459",
    "addr:housenumber":"1057",
    "addr:postcode":"10459",
    "addr:street":"Southern Blvd",
    "iso:country":"US",
    "sg:address":"1057 Southern Blvd",
    "sg:city":"Bronx",
    "sg:classifiers":[
        {
            "category":"Restaurant",
            "type":"Food & Drink"
        }
    ],
    "sg:phone":"+1   ",
    "sg:postcode":"10459",
    "sg:province":"NY",
    "sg:tags":[
        "eating"
    ],
    "wof:name":"Shinglung Restaurant",
    "wof:placetype":"venue"
},
  "geometry": {"coordinates":[-73.891913,40.826794],"type":"Point"}
}