{
  "type": "Feature",
  "properties": {
    "addr:full":"9520 Jamaica Ave Woodhaven NY 11421",
    "addr:housenumber":"9520",
    "addr:postcode":"11421",
    "addr:street":"Jamaica Ave",
    "iso:country":"US",
    "sg:address":"9520 Jamaica Ave",
    "sg:city":"Woodhaven",
    "sg:classifiers":[
        {
            "category":"Real Estate",
            "subcategory":"Real Estate Services",
            "type":"Services"
        },
        {
            "category":"Real Estate",
            "subcategory":"Real Estate Agent",
            "type":"Services"
        }
    ],
    "sg:phone":"+1 917 941 1854",
    "sg:postcode":"11421",
    "sg:province":"NY",
    "sg:tags":[
        "buyer",
        "broker"
    ],
    "wof:name":"9520 Jamaica Realty Corp.",
    "wof:placetype":"venue"
},
  "geometry": {"coordinates":[-73.85201600000001,40.693716],"type":"Point"}
}