{
  "type": "Feature",
  "properties": {
    "addr:full":"500 E Fordham Rd Bronx NY 10458",
    "addr:housenumber":"500",
    "addr:postcode":"10458",
    "addr:street":"E Fordham Rd",
    "iso:country":"US",
    "sg:address":"500 E Fordham Rd",
    "sg:city":"Bronx",
    "sg:classifiers":[
        {
            "category":"Professional",
            "type":"Services"
        }
    ],
    "sg:phone":"+1 718 561 6181",
    "sg:postcode":"10458",
    "sg:province":"NY",
    "wof:name":"Integratrak Service Bureau",
    "wof:placetype":"venue"
},
  "geometry": {"coordinates":[-73.887745,40.859736],"type":"Point"}
}