{
  "type": "Feature",
  "properties": {
    "addr:full":"5801 Woodside Ave Woodside NY 11377",
    "addr:housenumber":"5801",
    "addr:postcode":"11377",
    "addr:street":"Woodside Ave",
    "iso:country":"US",
    "sg:address":"5801 Woodside Ave",
    "sg:city":"Woodside",
    "sg:classifiers":[
        {
            "category":"Food & Beverages",
            "subcategory":"Ethnic Foods",
            "type":"Retail Goods"
        }
    ],
    "sg:phone":"+1 718 446 8514",
    "sg:postcode":"11377",
    "sg:province":"NY",
    "wof:name":"Big Boy Farm Inc",
    "wof:placetype":"venue"
},
  "geometry": {"coordinates":[-73.90630299999999,40.745701],"type":"Point"}
}