{
  "type": "Feature",
  "properties": {
    "addr:full":"1270 52nd St Brooklyn NY 11219",
    "addr:housenumber":"1270",
    "addr:postcode":"11219",
    "addr:street":"52Nd St",
    "iso:country":"US",
    "sg:address":"1270 52nd St",
    "sg:city":"Brooklyn",
    "sg:classifiers":[
        {
            "category":"Education",
            "subcategory":"School",
            "type":"Public Place"
        }
    ],
    "sg:phone":"+1 718 851 4700",
    "sg:postcode":"11219",
    "sg:province":"NY",
    "sg:tags":[
        "high",
        "middle",
        "elementary"
    ],
    "wof:name":"Ohr Moshe",
    "wof:placetype":"venue"
},
  "geometry": {"coordinates":[-73.994576,40.633609],"type":"Point"}
}