{
  "type": "Feature",
  "properties": {
    "iso:country":"US",
    "sg:address":"12 Liberty St",
    "sg:city":"Arcade",
    "sg:classifiers":[
        {
            "category":"Wholesale",
            "subcategory":"Groceries",
            "type":"Manufacturing & Wholesale Goods"
        }
    ],
    "sg:phone":"+1 585 492 2101",
    "sg:postcode":"14009",
    "sg:province":"NY",
    "sg:tags":[
        "food",
        "item"
    ],
    "wof:name":"Liberty Food Group Inc",
    "wof:placetype":"venue"
},
  "geometry": {"coordinates":[-78.422738,42.533893],"type":"Point"}
}