{
  "type": "Feature",
  "properties": {
    "addr:full":"166 Madison Avenue New York NY 10016",
    "addr:housenumber":"166",
    "addr:postcode":"10016",
    "addr:street":"Madison Avenue",
    "iso:country":"US",
    "sg:address":"166 Madison Avenue",
    "sg:city":"New York",
    "sg:classifiers":[
        {
            "category":"Banks & Credit Unions",
            "subcategory":"Investment Brokerage",
            "type":"Services"
        }
    ],
    "sg:phone":"+1 212 213 4823",
    "sg:postcode":"10016",
    "sg:province":"NY",
    "sg:tags":[
        "investing"
    ],
    "wof:name":"Miracle Corners of the World",
    "wof:placetype":"venue"
},
  "geometry": {"coordinates":[-73.98346600000001,40.747047],"type":"Point"}
}