{
  "type": "Feature",
  "properties": {
    "addr:full":"10 Leonard St Beacon NY 12508",
    "addr:housenumber":"10",
    "addr:postcode":"12508",
    "addr:street":"Leonard St",
    "iso:country":"US",
    "sg:address":"10 Leonard St",
    "sg:city":"Beacon",
    "sg:classifiers":[
        {
            "category":"Building & Trades",
            "subcategory":"Construction",
            "type":"Services"
        }
    ],
    "sg:phone":"+1 845 831 2900",
    "sg:postcode":"12508",
    "sg:province":"NY",
    "sg:tags":[
        "general",
        "contractor"
    ],
    "wof:name":"Ron Sauers Assoc",
    "wof:placetype":"venue"
},
  "geometry": {"coordinates":[-73.96077699999999,41.502472],"type":"Point"}
}