{
  "type": "Feature",
  "properties": {
    "iso:country":"US",
    "sg:address":"7 Park Ave",
    "sg:city":"Stillwater",
    "sg:classifiers":[
        {
            "category":"Manufacturing",
            "subcategory":"Printing",
            "type":"Manufacturing & Wholesale Goods"
        },
        {
            "category":"Manufacturing",
            "subcategory":"Motor Vehicles & Parts",
            "type":"Manufacturing & Wholesale Goods"
        }
    ],
    "sg:phone":"+1 518 664 2570",
    "sg:postcode":"12170",
    "sg:province":"NY",
    "sg:tags":[
        "screen",
        "mfg",
        "trimming"
    ],
    "wof:name":"America's Team",
    "wof:placetype":"venue"
},
  "geometry": {"coordinates":[-73.658849,42.937878],"type":"Point"}
}