{
  "type": "Feature",
  "properties": {
    "iso:country":"US",
    "sg:address":"2701 US Hwy 20",
    "sg:city":"Richfield Spgs",
    "sg:classifiers":[
        {
            "category":"Shopping",
            "subcategory":"Used Merchandise",
            "type":"Retail Goods"
        }
    ],
    "sg:phone":"+1 315 858 9354",
    "sg:postcode":"13439",
    "sg:province":"NY",
    "sg:tags":[
        "antique"
    ],
    "wof:name":"Rick Worden's Antiques",
    "wof:placetype":"venue"
},
  "geometry": {"coordinates":[-75.029438,42.868077],"type":"Point"}
}