{
  "type": "Feature",
  "properties": {
    "addr:full":"5 Broad Ave Ossining NY 10562",
    "addr:housenumber":"5",
    "addr:postcode":"10562",
    "addr:street":"Broad Ave",
    "iso:country":"US",
    "sg:address":"5 Broad Ave",
    "sg:city":"Ossining",
    "sg:classifiers":[
        {
            "category":"Manufacturing",
            "subcategory":"Retail Goods",
            "type":"Manufacturing & Wholesale Goods"
        }
    ],
    "sg:phone":"+1 914 762 8700",
    "sg:postcode":"10562",
    "sg:province":"NY",
    "sg:tags":[
        "brush"
    ],
    "wof:name":"Greco Brush Co",
    "wof:placetype":"venue"
},
  "geometry": {"coordinates":[-73.864149,41.157346],"type":"Point"}
}