{
  "type": "Feature",
  "properties": {
    "addr:full":"2935 Broadway New York NY 10025",
    "addr:housenumber":"2935",
    "addr:postcode":"10025",
    "addr:street":"Broadway",
    "iso:country":"US",
    "sg:address":"2935 Broadway",
    "sg:city":"New York",
    "sg:classifiers":[
        {
            "category":"Restaurant",
            "type":"Food & Drink"
        },
        {
            "category":"Food & Beverages",
            "subcategory":"Groceries & Convenience Stores",
            "type":"Retail Goods"
        }
    ],
    "sg:phone":"+1 212 280 4600",
    "sg:postcode":"10025",
    "sg:province":"NY",
    "sg:tags":[
        "japanese"
    ],
    "wof:name":"M2M Mart Corporation",
    "wof:placetype":"venue"
},
  "geometry": {"coordinates":[-73.964564,40.807274],"type":"Point"}
}