{
  "type": "Feature",
  "properties": {
    "iso:country":"US",
    "sg:address":"21 Main St",
    "sg:city":"West Sayville",
    "sg:classifiers":[
        {
            "category":"Restaurant",
            "type":"Food & Drink"
        }
    ],
    "sg:menulink":"http://www.allmenus.com/ny/islip/184985-21-main--prime-steak-house-/menu/",
    "sg:phone":"+1 631 567 0900",
    "sg:postcode":"11796",
    "sg:province":"NY",
    "sg:tags":[
        "american",
        "steakhouse"
    ],
    "wof:name":"21 Main ( Prime Steak House )",
    "wof:placetype":"venue"
},
  "geometry": {"coordinates":[-73.09232799999999,40.73052],"type":"Point"}
}