{
  "type": "Feature",
  "properties": {
    "addr:full":"101 E Hook Cross Rd Hopewell Junction NY 12533",
    "addr:housenumber":"101",
    "addr:postcode":"12533",
    "addr:street":"E Hook Cross Rd",
    "iso:country":"US",
    "sg:address":"101 E Hook Cross Rd",
    "sg:city":"Hopewell Junction",
    "sg:classifiers":[
        {
            "category":"Wholesale",
            "subcategory":"Non-durable Goods",
            "type":"Manufacturing & Wholesale Goods"
        }
    ],
    "sg:phone":"+1 845 897 8624",
    "sg:postcode":"12533",
    "sg:province":"NY",
    "wof:name":"J J Enterprises",
    "wof:placetype":"venue"
},
  "geometry": {"coordinates":[-73.81229999999999,41.516966],"type":"Point"}
}