{
  "type": "Feature",
  "properties": {
    "iso:country":"US",
    "sg:address":"257 S 2nd St",
    "sg:city":"Fulton",
    "sg:classifiers":[
        {
            "category":"Retail",
            "subcategory":"Auto Repair",
            "type":"Services"
        }
    ],
    "sg:phone":"+1 315 598 1269",
    "sg:postcode":"13069",
    "sg:province":"NY",
    "sg:tags":[
        "repairing",
        "automobile",
        "brake"
    ],
    "sg:website":"http://www.monro.com",
    "wof:name":"Monro Muffler Brake & Service",
    "wof:placetype":"venue"
},
  "geometry": {"coordinates":[-76.413157,43.319171],"type":"Point"}
}