{
  "type": "Feature",
  "properties": {
    "iso:country":"US",
    "sg:address":"3241 Rte 112",
    "sg:city":"Medford",
    "sg:classifiers":[
        {
            "category":"Insurance",
            "subcategory":"Insurance Agent",
            "type":"Services"
        }
    ],
    "sg:phone":"+1 631 732 8100",
    "sg:postcode":"11763",
    "sg:province":"NY",
    "wof:name":"Suffolk County Municipal Emplo",
    "wof:placetype":"venue"
},
  "geometry": {"coordinates":[-72.99631100000001,40.838982],"type":"Point"}
}