{
  "type": "Feature",
  "properties": {
    "addr:full":"1032 Avenue of the Americ New York NY 10018",
    "addr:housenumber":"1032",
    "addr:postcode":"10018",
    "addr:street":"Avenue Of The",
    "iso:country":"US",
    "sg:address":"1032 Avenue of the Americ",
    "sg:city":"New York",
    "sg:classifiers":[
        {
            "category":"Retail",
            "subcategory":"Portrait Studio",
            "type":"Services"
        },
        {
            "category":"Professional",
            "subcategory":"Art Services",
            "type":"Services"
        }
    ],
    "sg:phone":"+1 212 997 5155",
    "sg:postcode":"10018",
    "sg:province":"NY",
    "sg:tags":[
        "photographer",
        "photography",
        "store"
    ],
    "wof:name":"Ragland Worthington Photography",
    "wof:placetype":"venue"
},
  "geometry": {"coordinates":[-73.985609,40.752706],"type":"Point"}
}