{
  "type": "Feature",
  "properties": {
    "addr:full":"300 Lafayette St New York NY 10012",
    "addr:housenumber":"300",
    "addr:postcode":"10012",
    "addr:street":"Lafayette St",
    "iso:country":"US",
    "sg:address":"300 Lafayette St",
    "sg:city":"New York",
    "sg:classifiers":[
        {
            "category":"Autos & Motor Vehicles",
            "subcategory":"Fuel & Gas Station",
            "type":"Retail Goods"
        }
    ],
    "sg:phone":"+1 212 220 4216",
    "sg:postcode":"10012",
    "sg:province":"NY",
    "sg:website":"www.bp.com/heliospower/modularho...",
    "wof:name":"Harris M Kalish",
    "wof:placetype":"venue"
},
  "geometry": {"coordinates":[-73.995392,40.725234],"type":"Point"}
}