{
  "type": "Feature",
  "properties": {
    "addr:full":"572 Route 6 Mahopac NY 10541",
    "addr:housenumber":"572",
    "addr:postcode":"10541",
    "addr:street":"Route 6",
    "iso:country":"US",
    "sg:address":"572 Route 6",
    "sg:city":"Mahopac",
    "sg:classifiers":[
        {
            "category":"Health Services",
            "subcategory":"Doctor",
            "type":"Services"
        }
    ],
    "sg:phone":"+1 845 621 9196",
    "sg:postcode":"10541",
    "sg:province":"NY",
    "sg:tags":[
        "obstetrician",
        "gynecologist"
    ],
    "wof:name":"Tai Nhan MD",
    "wof:placetype":"venue"
},
  "geometry": {"coordinates":[-73.73809799999999,41.370201],"type":"Point"}
}