{
  "type": "Feature",
  "properties": {
    "iso:country":"US",
    "sg:address":"7 Atlantic Ave",
    "sg:city":"Wynantskill",
    "sg:classifiers":[
        {
            "category":"Building & Trades",
            "subcategory":"Construction",
            "type":"Services"
        }
    ],
    "sg:phone":"+1 518 283 4986",
    "sg:postcode":"12198",
    "sg:province":"NY",
    "sg:tags":[
        "roofing",
        "contractor"
    ],
    "wof:name":"DMR Roofing",
    "wof:placetype":"venue"
},
  "geometry": {"coordinates":[-73.641429,42.697244],"type":"Point"}
}