{
  "type": "Feature",
  "properties": {
    "iso:country":"US",
    "sg:address":"3826 Nostrand Ave",
    "sg:city":"Brooklyn",
    "sg:classifiers":[
        {
            "category":"Shopping",
            "subcategory":"Optical Goods",
            "type":"Retail Goods"
        }
    ],
    "sg:phone":"+1   ",
    "sg:postcode":"11235",
    "sg:province":"NY",
    "wof:name":"Joel F Sklar Dr",
    "wof:placetype":"venue"
},
  "geometry": {"coordinates":[-73.940043,40.590743],"type":"Point"}
}