{
  "type": "Feature",
  "properties": {
    "iso:country":"US",
    "sg:address":"51 E 42nd St",
    "sg:city":"New York",
    "sg:classifiers":[
        {
            "category":"Banks & Credit Unions",
            "subcategory":"Investment Brokerage",
            "type":"Services"
        }
    ],
    "sg:phone":"+1 212 973 9800",
    "sg:postcode":"10017",
    "sg:province":"NY",
    "sg:tags":[
        "advisory"
    ],
    "wof:name":"River Capital Management",
    "wof:placetype":"venue"
},
  "geometry": {"coordinates":[-73.978855,40.75277],"type":"Point"}
}