{
  "type": "Feature",
  "properties": {
    "iso:country":"US",
    "sg:address":"101 Wyckoff Ave",
    "sg:city":"Brooklyn",
    "sg:classifiers":[
        {
            "category":"Manufacturing",
            "subcategory":"Textiles",
            "type":"Manufacturing & Wholesale Goods"
        }
    ],
    "sg:phone":"+1   ",
    "sg:postcode":"11237",
    "sg:province":"NY",
    "sg:tags":[
        "mill",
        "knit",
        "outerwear",
        "mfg"
    ],
    "wof:name":"Tiffany Sweater Manufacturing",
    "wof:placetype":"venue"
},
  "geometry": {"coordinates":[-73.91923,40.704312],"type":"Point"}
}