{
  "type": "Feature",
  "properties": {
    "addr:full":"17 James St Auburn NY 13021",
    "addr:housenumber":"17",
    "addr:postcode":"13021",
    "addr:street":"James St",
    "iso:country":"US",
    "sg:address":"17 James St",
    "sg:city":"Auburn",
    "sg:classifiers":[
        {
            "category":"Shopping",
            "subcategory":"Gifts & Souvenirs",
            "type":"Retail Goods"
        }
    ],
    "sg:phone":"+1   ",
    "sg:postcode":"13021",
    "sg:province":"NY",
    "wof:name":"Upstate Party Rental",
    "wof:placetype":"venue"
},
  "geometry": {"coordinates":[-76.572424,42.93047],"type":"Point"}
}