{
  "type": "Feature",
  "properties": {
    "addr:full":"56 W Old Country Rd Hicksville NY 11801",
    "addr:housenumber":"56",
    "addr:postcode":"11801",
    "addr:street":"W Old Country Rd",
    "iso:country":"US",
    "sg:address":"56 W Old Country Rd",
    "sg:city":"Hicksville",
    "sg:classifiers":[
        {
            "category":"Autos & Motor Vehicles",
            "subcategory":"Auto Supplies",
            "type":"Retail Goods"
        }
    ],
    "sg:phone":"+1 516 931 8225",
    "sg:postcode":"11801",
    "sg:province":"NY",
    "sg:tags":[
        "glass"
    ],
    "sg:website":"www.glassdoctor.com",
    "wof:name":"Glass Doctor",
    "wof:placetype":"venue"
},
  "geometry": {"coordinates":[-73.522195,40.763542],"type":"Point"}
}