{
  "type": "Feature",
  "properties": {
    "addr:full":"100 S Elmwood Ave Buffalo NY 14202",
    "addr:housenumber":"100",
    "addr:postcode":"14202",
    "addr:street":"S Elmwood Ave",
    "iso:country":"US",
    "sg:address":"100 S Elmwood Ave",
    "sg:city":"Buffalo",
    "sg:classifiers":[
        {
            "category":"Shopping",
            "type":"Retail Goods"
        }
    ],
    "sg:phone":"+1   ",
    "sg:postcode":"14202",
    "sg:province":"NY",
    "sg:tags":[
        "machine",
        "retailer",
        "photocopy",
        "facsimile"
    ],
    "wof:name":"Copier Fax Business Tech",
    "wof:placetype":"venue"
},
  "geometry": {"coordinates":[-78.879533,42.887225],"type":"Point"}
}