{
  "type": "Feature",
  "properties": {
    "addr:full":"435 Clinton St Hempstead NY 11550",
    "addr:housenumber":"435",
    "addr:postcode":"11550",
    "addr:street":"Clinton St",
    "iso:country":"US",
    "sg:address":"435 Clinton St",
    "sg:city":"Hempstead",
    "sg:classifiers":[
        {
            "category":"Food & Beverages",
            "subcategory":"Groceries & Convenience Stores",
            "type":"Retail Goods"
        }
    ],
    "sg:phone":"+1 516 538 0686",
    "sg:postcode":"11550",
    "sg:province":"NY",
    "sg:tags":[
        "grocer"
    ],
    "wof:name":"Clinton Food Mart",
    "wof:placetype":"venue"
},
  "geometry": {"coordinates":[-73.620903,40.719299],"type":"Point"}
}