{
  "type": "Feature",
  "properties": {
    "iso:country":"US",
    "sg:address":"15 Spencer Pl",
    "sg:city":"Scarsdale",
    "sg:classifiers":[
        {
            "category":"Retail",
            "subcategory":"Photofinishing",
            "type":"Services"
        }
    ],
    "sg:phone":"+1 914 725 8515",
    "sg:postcode":"10583",
    "sg:province":"NY",
    "sg:tags":[
        "photo",
        "finishing",
        "developing"
    ],
    "sg:website":"www.scarsdalephotos.com",
    "wof:name":"Photo Center Inc",
    "wof:placetype":"venue"
},
  "geometry": {"coordinates":[-73.80785299999999,40.989852],"type":"Point"}
}