{
  "type": "Feature",
  "properties": {
    "addr:full":"1125 Victory Blvd Staten Island NY 10301",
    "addr:housenumber":"1125",
    "addr:postcode":"10301",
    "addr:street":"Victory Blvd",
    "iso:country":"US",
    "sg:address":"1125 Victory Blvd",
    "sg:city":"Staten Island",
    "sg:classifiers":[
        {
            "category":"Professional",
            "subcategory":"Lawyer & Legal Services",
            "type":"Services"
        }
    ],
    "sg:phone":"+1 212 587 1110",
    "sg:postcode":"10301",
    "sg:province":"NY",
    "sg:tags":[
        "attorney"
    ],
    "wof:name":"Deguerre Law Firm",
    "wof:placetype":"venue"
},
  "geometry": {"coordinates":[-74.10169500000001,40.617858],"type":"Point"}
}