{
  "type": "Feature",
  "properties": {
    "addr:full":"2763 US Hwy 6 Slate Hill NY 10973",
    "addr:housenumber":"2763",
    "addr:postcode":"10973",
    "addr:street":"Us Hwy 6 Slate",
    "iso:country":"US",
    "sg:address":"2763 US Hwy 6",
    "sg:city":"Slate Hill",
    "sg:classifiers":[
        {
            "category":"Manufacturing",
            "subcategory":"Tools & Machinery",
            "type":"Manufacturing & Wholesale Goods"
        }
    ],
    "sg:phone":"+1   ",
    "sg:postcode":"10973",
    "sg:province":"NY",
    "sg:tags":[
        "industrial",
        "mfg"
    ],
    "wof:name":"Slate Hill Metal Works",
    "wof:placetype":"venue"
},
  "geometry": {"coordinates":[-74.475928,41.390909],"type":"Point"}
}