{
  "type": "Feature",
  "properties": {
    "iso:country":"US",
    "sg:address":"1531 Niagara Falls Blvd",
    "sg:city":"Amherst",
    "sg:classifiers":[
        {
            "category":"Banks & Credit Unions",
            "subcategory":"Bank",
            "type":"Services"
        }
    ],
    "sg:phone":"+1 716 625 7600",
    "sg:postcode":"14228",
    "sg:province":"NY",
    "wof:name":"First Niagara Bank",
    "wof:placetype":"venue"
},
  "geometry": {"coordinates":[-78.822406,42.995684],"type":"Point"}
}