{
  "type": "Feature",
  "properties": {
    "iso:country":"US",
    "sg:address":"319 Tremont Ave",
    "sg:city":"Buffalo",
    "sg:classifiers":[
        {
            "category":"Building & Trades",
            "subcategory":"Construction",
            "type":"Services"
        }
    ],
    "sg:phone":"+1 716 876 8585",
    "sg:postcode":"14217",
    "sg:province":"NY",
    "sg:tags":[
        "home",
        "specialty",
        "improvement"
    ],
    "wof:name":"Jaco Construction & Service",
    "wof:placetype":"venue"
},
  "geometry": {"coordinates":[-78.88502200000001,42.965799],"type":"Point"}
}