{
  "type": "Feature",
  "properties": {
    "iso:country":"US",
    "sg:address":"1705 Broadway",
    "sg:city":"Hewlett",
    "sg:classifiers":[
        {
            "category":"Health Services",
            "subcategory":"Doctor",
            "type":"Services"
        }
    ],
    "sg:phone":"+1 516 599 4446",
    "sg:postcode":"11557",
    "sg:province":"NY",
    "sg:tags":[
        "surgeon",
        "oral"
    ],
    "wof:name":"Kreisman Burt R DDS",
    "wof:placetype":"venue"
},
  "geometry": {"coordinates":[-73.690102,40.646999],"type":"Point"}
}