{
  "type": "Feature",
  "properties": {
    "addr:full":"145 W 45th St New York NY 10036",
    "addr:housenumber":"145",
    "addr:postcode":"10036",
    "addr:street":"W 45Th St",
    "iso:country":"US",
    "sg:address":"145 W 45th St",
    "sg:city":"New York",
    "sg:classifiers":[
        {
            "category":"Restaurant",
            "type":"Food & Drink"
        }
    ],
    "sg:phone":"+1 212 302 3663",
    "sg:postcode":"10036",
    "sg:province":"NY",
    "wof:name":"Blimpie",
    "wof:placetype":"venue"
},
  "geometry": {"coordinates":[-73.984802,40.757702],"type":"Point"}
}