{
  "type": "Feature",
  "properties": {
    "addr:full":"72 N Park Ave Buffalo NY 14216",
    "addr:housenumber":"72",
    "addr:postcode":"14216",
    "addr:street":"N Park Ave",
    "iso:country":"US",
    "sg:address":"72 N Park Ave",
    "sg:city":"Buffalo",
    "sg:classifiers":[
        {
            "category":"Building & Trades",
            "subcategory":"Cleaning & Sanitation",
            "type":"Services"
        }
    ],
    "sg:phone":"+1 716 871 0095",
    "sg:postcode":"14216",
    "sg:province":"NY",
    "sg:tags":[
        "janitor"
    ],
    "wof:name":"D & C Cleaning Svc",
    "wof:placetype":"venue"
},
  "geometry": {"coordinates":[-78.855959,42.947157],"type":"Point"}
}