{
  "type": "Feature",
  "properties": {
    "addr:full":"5 California Rd Warwick NY 10990",
    "addr:housenumber":"5",
    "addr:postcode":"10990",
    "addr:street":"California Rd",
    "iso:country":"US",
    "sg:address":"5 California Rd",
    "sg:city":"Warwick",
    "sg:classifiers":[
        {
            "category":"Personal",
            "subcategory":"Beauty Salon",
            "type":"Services"
        }
    ],
    "sg:phone":"+1 845 986 4671",
    "sg:postcode":"10990",
    "sg:province":"NY",
    "sg:tags":[
        "hair",
        "stylist"
    ],
    "wof:name":"Cher Dore Inc",
    "wof:placetype":"venue"
},
  "geometry": {"coordinates":[-74.330652,41.215658],"type":"Point"}
}