{
  "type": "Feature",
  "properties": {
    "iso:country":"US",
    "sg:address":"510 Hempstead Ave",
    "sg:city":"West Hempstead",
    "sg:classifiers":[
        {
            "category":"Personal",
            "subcategory":"Barber",
            "type":"Services"
        }
    ],
    "sg:phone":"+1 516 486 1780",
    "sg:postcode":"11552",
    "sg:province":"NY",
    "wof:name":"Euro Style",
    "wof:placetype":"venue"
},
  "geometry": {"coordinates":[-73.655479,40.69485],"type":"Point"}
}