{
  "type": "Feature",
  "properties": {
    "iso:country":"US",
    "sg:address":"11655 Moore Rd",
    "sg:city":"Springville",
    "sg:classifiers":[
        {
            "category":"Building & Trades",
            "subcategory":"Construction",
            "type":"Services"
        }
    ],
    "sg:phone":"+1 716 592 5516",
    "sg:postcode":"14141",
    "sg:province":"NY",
    "sg:tags":[
        "carpentry",
        "contractor"
    ],
    "wof:name":"3 In 1 Const",
    "wof:placetype":"venue"
},
  "geometry": {"coordinates":[-78.724368,42.570638],"type":"Point"}
}