{
  "type": "Feature",
  "properties": {
    "iso:country":"US",
    "sg:address":"104 S Broadway",
    "sg:city":"Yonkers",
    "sg:classifiers":[
        {
            "category":"Government",
            "subcategory":"Department Of Motor Vehicles",
            "type":"Public Place"
        }
    ],
    "sg:phone":"+1 914 476 5262",
    "sg:postcode":"10701",
    "sg:province":"NY",
    "sg:tags":[
        "license",
        "registration"
    ],
    "wof:name":"Pre Trial Svces of Westchester",
    "wof:placetype":"venue"
},
  "geometry": {"coordinates":[-73.897789,40.930309],"type":"Point"}
}