{
  "type": "Feature",
  "properties": {
    "iso:country":"US",
    "sg:address":"755 State Hwy 131",
    "sg:city":"Massena",
    "sg:classifiers":[
        {
            "category":"Food & Beverages",
            "subcategory":"Specialty",
            "type":"Retail Goods"
        }
    ],
    "sg:phone":"+1 315 769 2431",
    "sg:postcode":"13662",
    "sg:province":"NY",
    "sg:tags":[
        "water",
        "bulk",
        "company"
    ],
    "wof:name":"Louisville Town-Water",
    "wof:placetype":"venue"
},
  "geometry": {"coordinates":[-74.978872,44.951029],"type":"Point"}
}