{
  "type": "Feature",
  "properties": {
    "iso:country":"US",
    "sg:address":"581 Ave of the Americas",
    "sg:city":"New York",
    "sg:classifiers":[
        {
            "category":"Professional",
            "subcategory":"Management & Consulting",
            "type":"Services"
        }
    ],
    "sg:phone":"+1 212 349 7412",
    "sg:postcode":"10011",
    "sg:province":"NY",
    "sg:tags":[
        "consultant",
        "business"
    ],
    "wof:name":"Kasina LLC",
    "wof:placetype":"venue"
},
  "geometry": {"coordinates":[-73.995633,40.739089],"type":"Point"}
}