{
  "type": "Feature",
  "properties": {
    "iso:country":"US",
    "sg:address":"1992 State Hwy 19",
    "sg:city":"Wyoming",
    "sg:classifiers":[
        {
            "category":"Home & Garden",
            "subcategory":"Building Materials",
            "type":"Retail Goods"
        }
    ],
    "sg:phone":"+1 585 786 0050",
    "sg:postcode":"14591",
    "sg:province":"NY",
    "sg:tags":[
        "modular"
    ],
    "wof:name":"K & L Home Sales",
    "wof:placetype":"venue"
},
  "geometry": {"coordinates":[-78.11996000000001,42.786284],"type":"Point"}
}