{
  "type": "Feature",
  "properties": {
    "addr:full":"167 Dupont Ave Newburgh NY 12550",
    "addr:housenumber":"167",
    "addr:postcode":"12550",
    "addr:street":"Dupont Ave",
    "iso:country":"US",
    "sg:address":"167 Dupont Ave",
    "sg:city":"Newburgh",
    "sg:classifiers":[
        {
            "category":"Home & Garden",
            "subcategory":"Garden Supply",
            "type":"Retail Goods"
        }
    ],
    "sg:phone":"+1   ",
    "sg:postcode":"12550",
    "sg:province":"NY",
    "wof:name":"California Water Gardens",
    "wof:placetype":"venue"
},
  "geometry": {"coordinates":[-74.041044,41.506956],"type":"Point"}
}