{
  "type": "Feature",
  "properties": {
    "addr:full":"64 Prince Rd Mahopac NY 10541",
    "addr:housenumber":"64",
    "addr:postcode":"10541",
    "addr:street":"Prince Rd",
    "iso:country":"US",
    "sg:address":"64 Prince Rd",
    "sg:city":"Mahopac",
    "sg:classifiers":[
        {
            "category":"Professional",
            "subcategory":"Business Services",
            "type":"Services"
        }
    ],
    "sg:phone":"+1 845 628 0812",
    "sg:postcode":"10541",
    "sg:province":"NY",
    "wof:name":"L M Branca Development Corp",
    "wof:placetype":"venue"
},
  "geometry": {"coordinates":[-73.719503,41.364248],"type":"Point"}
}