{
  "type": "Feature",
  "properties": {
    "iso:country":"US",
    "sg:address":"12 E 49th Street",
    "sg:city":"New York",
    "sg:classifiers":[
        {
            "category":"Professional",
            "subcategory":"Lawyer & Legal Services",
            "type":"Services"
        }
    ],
    "sg:phone":"+1 212 299 8600",
    "sg:postcode":"10017",
    "sg:province":"NY",
    "wof:name":"Roberts Sheridan & Kotel",
    "wof:placetype":"venue"
},
  "geometry": {"coordinates":[-73.977379,40.757638],"type":"Point"}
}