{
  "type": "Feature",
  "properties": {
    "iso:country":"US",
    "sg:address":"700 Main St Ste 2",
    "sg:city":"Islip",
    "sg:classifiers":[
        {
            "category":"Retail",
            "subcategory":"Veterinary Services",
            "type":"Services"
        }
    ],
    "sg:phone":"+1 631 277 2266",
    "sg:postcode":"11751",
    "sg:province":"NY",
    "sg:tags":[
        "veterinarian"
    ],
    "wof:name":"Animal Hospital Of East Islip",
    "wof:placetype":"venue"
},
  "geometry": {"coordinates":[-73.20957300000001,40.729721],"type":"Point"}
}