{
  "type": "Feature",
  "properties": {
    "iso:country":"US",
    "sg:address":"145 Shore Rd",
    "sg:city":"Mount Sinai",
    "sg:classifiers":[
        {
            "category":"Building & Trades",
            "subcategory":"Construction",
            "type":"Services"
        }
    ],
    "sg:phone":"+1 631 331 4803",
    "sg:postcode":"11766",
    "sg:province":"NY",
    "sg:tags":[
        "house"
    ],
    "wof:name":"Glen Edlund Construction Inc",
    "wof:placetype":"venue"
},
  "geometry": {"coordinates":[-73.030349,40.948525],"type":"Point"}
}