{
  "type": "Feature",
  "properties": {
    "addr:full":"1395 Jerusalem Ave Merrick NY 11566",
    "addr:housenumber":"1395",
    "addr:postcode":"11566",
    "addr:street":"Jerusalem Ave",
    "iso:country":"US",
    "sg:address":"1395 Jerusalem Ave",
    "sg:city":"Merrick",
    "sg:classifiers":[
        {
            "category":"Insurance",
            "subcategory":"Insurance Agent",
            "type":"Services"
        }
    ],
    "sg:phone":"+1 516 505 9769",
    "sg:postcode":"11566",
    "sg:province":"NY",
    "sg:tags":[
        "consulting",
        "management"
    ],
    "wof:name":"Primerica",
    "wof:placetype":"venue"
},
  "geometry": {"coordinates":[-73.568978,40.69388],"type":"Point"}
}