{
  "type": "Feature",
  "properties": {
    "addr:full":"110 E 59 St New York NY 10022",
    "addr:housenumber":"110;59",
    "addr:postcode":"10022",
    "addr:street":"E;St",
    "iso:country":"US",
    "sg:address":"110 E 59 St",
    "sg:city":"New York",
    "sg:classifiers":[
        {
            "category":"Banks & Credit Unions",
            "subcategory":"Financial Services",
            "type":"Services"
        }
    ],
    "sg:phone":"+1 212 355 5200",
    "sg:postcode":"10022",
    "sg:province":"NY",
    "sg:tags":[
        "firm",
        "investment"
    ],
    "wof:name":"Stonehill Investment Corp",
    "wof:placetype":"venue"
},
  "geometry": {"coordinates":[-73.968583,40.762363],"type":"Point"}
}