{
  "type": "Feature",
  "properties": {
    "addr:full":"1013 Barker Rd Dolgeville NY 13329",
    "addr:housenumber":"1013",
    "addr:postcode":"13329",
    "addr:street":"Barker Rd",
    "iso:country":"US",
    "sg:address":"1013 Barker Rd",
    "sg:city":"Dolgeville",
    "sg:classifiers":[
        {
            "category":"Manufacturing",
            "subcategory":"Rubber & Plastics",
            "type":"Manufacturing & Wholesale Goods"
        }
    ],
    "sg:phone":"+1 315 429 3101",
    "sg:postcode":"13329",
    "sg:province":"NY",
    "wof:name":"Tumble Forms Inc",
    "wof:placetype":"venue"
},
  "geometry": {"coordinates":[-74.68518,43.083801],"type":"Point"}
}