{
  "type": "Feature",
  "properties": {
    "iso:country":"US",
    "sg:address":"234 W 13th St Apt 58",
    "sg:city":"New York",
    "sg:classifiers":[
        {
            "category":"Building & Trades",
            "subcategory":"Construction",
            "type":"Services"
        }
    ],
    "sg:phone":"+1 212 206 7741",
    "sg:postcode":"10011",
    "sg:province":"NY",
    "sg:tags":[
        "contractor"
    ],
    "wof:name":"Setter Construction Llc",
    "wof:placetype":"venue"
},
  "geometry": {"coordinates":[-74.011878,40.73805],"type":"Point"}
}