{
  "type": "Feature",
  "properties": {
    "iso:country":"US",
    "sg:address":"132 W 65th St",
    "sg:city":"New York",
    "sg:classifiers":[
        {
            "category":"Arena",
            "subcategory":"Stadium",
            "type":"Entertainment"
        }
    ],
    "sg:phone":"+1 212 595 0631",
    "sg:postcode":"10023",
    "sg:province":"NY",
    "wof:name":"Avery Fisher Hall",
    "wof:placetype":"venue"
},
  "geometry": {"coordinates":[-73.98324100000001,40.773309],"type":"Point"}
}