{
  "type": "Feature",
  "properties": {
    "addr:full":"238 W 108th St New York NY 10025",
    "addr:housenumber":"238",
    "addr:postcode":"10025",
    "addr:street":"W 108Th St",
    "iso:country":"US",
    "sg:address":"238 W 108th St",
    "sg:city":"New York",
    "sg:classifiers":[
        {
            "category":"Home & Garden",
            "subcategory":"Building Materials",
            "type":"Retail Goods"
        }
    ],
    "sg:phone":"+1   ",
    "sg:postcode":"10025",
    "sg:province":"NY",
    "sg:tags":[
        "mfg"
    ],
    "wof:name":"Wood-O-Rama Inc",
    "wof:placetype":"venue"
},
  "geometry": {"coordinates":[-73.966792,40.802405],"type":"Point"}
}