{
  "type": "Feature",
  "properties": {
    "addr:full":"110 William St Newburgh NY 12550",
    "addr:housenumber":"110",
    "addr:postcode":"12550",
    "addr:street":"William St",
    "iso:country":"US",
    "sg:address":"110 William St",
    "sg:city":"Newburgh",
    "sg:classifiers":[
        {
            "category":"Retail",
            "subcategory":"Repair Shop",
            "type":"Services"
        }
    ],
    "sg:phone":"+1 845 565 5524",
    "sg:postcode":"12550",
    "sg:province":"NY",
    "sg:tags":[
        "vinyl"
    ],
    "wof:name":"Flores Upholstery Repairs",
    "wof:placetype":"venue"
},
  "geometry": {"coordinates":[-74.01638,41.495659],"type":"Point"}
}