{
  "type": "Feature",
  "properties": {
    "addr:full":"4791 Makyes Rd Syracuse NY 13215",
    "addr:housenumber":"4791",
    "addr:postcode":"13215",
    "addr:street":"Makyes Rd",
    "iso:country":"US",
    "sg:address":"4791 Makyes Rd",
    "sg:city":"Syracuse",
    "sg:classifiers":[
        {
            "category":"Organizations",
            "subcategory":"Religious Organization",
            "type":"Services"
        }
    ],
    "sg:phone":"+1 315 469 1940",
    "sg:postcode":"13215",
    "sg:province":"NY",
    "sg:tags":[
        "clergy"
    ],
    "wof:name":"Robert B Langston",
    "wof:placetype":"venue"
},
  "geometry": {"coordinates":[-76.183561,43.004192],"type":"Point"}
}