{
  "type": "Feature",
  "properties": {
    "addr:full":"71 Ave C New York NY 10009",
    "addr:postcode":"10009",
    "addr:street":"71 Ave C",
    "iso:country":"US",
    "sg:address":"71 Ave C",
    "sg:city":"New York",
    "sg:classifiers":[
        {
            "category":"Personal",
            "subcategory":"Beauty Salon",
            "type":"Services"
        }
    ],
    "sg:phone":"+1 212 780 6012",
    "sg:postcode":"10009",
    "sg:province":"NY",
    "wof:name":"Jonannys Unisex",
    "wof:placetype":"venue"
},
  "geometry": {"coordinates":[-73.979281,40.723504],"type":"Point"}
}