{
  "type": "Feature",
  "properties": {
    "addr:full":"501 5th Avenue Rm 2010 New York NY 10017",
    "addr:housenumber":"501;2010",
    "addr:postcode":"10017",
    "addr:street":"5Th Avenue Rm",
    "iso:country":"US",
    "sg:address":"501 5th Avenue Rm 2010",
    "sg:city":"New York",
    "sg:classifiers":[
        {
            "category":"Professional",
            "subcategory":"Accounting & Tax Preparation",
            "type":"Services"
        }
    ],
    "sg:phone":"+1 212 687 7886",
    "sg:postcode":"10017",
    "sg:province":"NY",
    "sg:tags":[
        "accountant"
    ],
    "wof:name":"The Office of George Y Hara",
    "wof:placetype":"venue"
},
  "geometry": {"coordinates":[-73.971509,40.752843],"type":"Point"}
}