{
  "type": "Feature",
  "properties": {
    "addr:full":"14450 Northern Blvd Flushing NY 11354",
    "addr:housenumber":"14450",
    "addr:postcode":"11354",
    "addr:street":"Northern Blvd",
    "iso:country":"US",
    "sg:address":"14450 Northern Blvd",
    "sg:city":"Flushing",
    "sg:classifiers":[
        {
            "category":"Food & Beverages",
            "subcategory":"Groceries & Convenience Stores",
            "type":"Retail Goods"
        }
    ],
    "sg:postcode":"11354",
    "sg:province":"NY",
    "sg:website":"www.gw-supermarket.com/",
    "wof:name":"Great Wall Supermarket",
    "wof:placetype":"venue"
},
  "geometry": {"coordinates":[-73.82163199999999,40.764854],"type":"Point"}
}