{
  "type": "Feature",
  "properties": {
    "addr:full":"6620 Fresh Pond Rd Ridgewood NY 11385",
    "addr:postcode":"6620;11385",
    "addr:street":"Fresh Pond Rd",
    "iso:country":"US",
    "sg:address":"6620 Fresh Pond Rd",
    "sg:city":"Ridgewood",
    "sg:classifiers":[
        {
            "category":"Home & Garden",
            "subcategory":"Home Furnishings",
            "type":"Retail Goods"
        }
    ],
    "sg:phone":"+1 718 417 1096",
    "sg:postcode":"11385",
    "sg:province":"NY",
    "sg:tags":[
        "furniture-children's"
    ],
    "wof:name":"Kiddie City",
    "wof:placetype":"venue"
},
  "geometry": {"coordinates":[-73.896317,40.705219],"type":"Point"}
}