{
  "type": "Feature",
  "properties": {
    "iso:country":"US",
    "sg:address":"3117 Lords Hill Rd",
    "sg:city":"Nedrow",
    "sg:classifiers":[
        {
            "category":"Manufacturing",
            "subcategory":"Printing",
            "type":"Manufacturing & Wholesale Goods"
        }
    ],
    "sg:phone":"+1   ",
    "sg:postcode":"13120",
    "sg:province":"NY",
    "sg:tags":[
        "publishing"
    ],
    "wof:name":"Edward Michael Publishing",
    "wof:placetype":"venue"
},
  "geometry": {"coordinates":[-76.219121,42.91344],"type":"Point"}
}