{
  "type": "Feature",
  "properties": {
    "addr:full":"90 Lake St Youngstown NY 14174",
    "addr:housenumber":"90",
    "addr:postcode":"14174",
    "addr:street":"Lake St",
    "iso:country":"US",
    "sg:address":"90 Lake St",
    "sg:city":"Youngstown",
    "sg:classifiers":[
        {
            "category":"Real Estate",
            "subcategory":"Real Estate Operator",
            "type":"Services"
        }
    ],
    "sg:phone":"+1 716 633 3177",
    "sg:postcode":"14174",
    "sg:province":"NY",
    "sg:tags":[
        "apartment"
    ],
    "wof:name":"Youngstown Associates",
    "wof:placetype":"venue"
},
  "geometry": {"coordinates":[-79.046898,43.255859],"type":"Point"}
}