{
  "type": "Feature",
  "properties": {
    "addr:full":"219 E 188th St Bronx NY 10458",
    "addr:housenumber":"219",
    "addr:postcode":"10458",
    "addr:street":"E 188Th St",
    "iso:country":"US",
    "sg:address":"219 E 188th St",
    "sg:city":"Bronx",
    "sg:classifiers":[
        {
            "category":"Real Estate",
            "subcategory":"Real Estate Agent",
            "type":"Services"
        }
    ],
    "sg:phone":"+1 718 561 1863",
    "sg:postcode":"10458",
    "sg:province":"NY",
    "wof:name":"Tevins Realty",
    "wof:placetype":"venue"
},
  "geometry": {"coordinates":[-73.89677,40.8612],"type":"Point"}
}