{
  "type": "Feature",
  "properties": {
    "iso:country":"US",
    "sg:address":"249 Nelson Ave",
    "sg:city":"Staten Island",
    "sg:classifiers":[
        {
            "category":"Arts & Performance",
            "subcategory":"Arts Center",
            "type":"Entertainment"
        }
    ],
    "sg:phone":"+1 718 967 1797",
    "sg:postcode":"10308",
    "sg:province":"NY",
    "sg:tags":[
        "performing"
    ],
    "wof:name":"Dance Sensations",
    "wof:placetype":"venue"
},
  "geometry": {"coordinates":[-74.14717899999999,40.543468],"type":"Point"}
}