{
  "type": "Feature",
  "properties": {
    "addr:full":"237 Park Ave Fl 20 New York NY 10017",
    "addr:housenumber":"237;20",
    "addr:postcode":"10017",
    "addr:street":"Park Ave Fl",
    "iso:country":"US",
    "sg:address":"237 Park Ave Fl 20",
    "sg:city":"New York",
    "sg:classifiers":[
        {
            "category":"Professional",
            "subcategory":"Lawyer & Legal Services",
            "type":"Services"
        }
    ],
    "sg:phone":"+1 212 880 6000",
    "sg:postcode":"10017",
    "sg:province":"NY",
    "wof:name":"Feldman Sandy K",
    "wof:placetype":"venue"
},
  "geometry": {"coordinates":[-73.974917,40.753979],"type":"Point"}
}