{
  "type": "Feature",
  "properties": {
    "addr:full":"8414 Northern Blvd Jackson Heights NY 11372",
    "addr:housenumber":"8414",
    "addr:postcode":"11372",
    "addr:street":"Northern Blvd",
    "iso:country":"US",
    "sg:address":"8414 Northern Blvd",
    "sg:city":"Jackson Heights",
    "sg:classifiers":[
        {
            "category":"Arts & Performance",
            "subcategory":"Arts Center",
            "type":"Entertainment"
        }
    ],
    "sg:phone":"+1 718 476 8071",
    "sg:postcode":"11372",
    "sg:province":"NY",
    "sg:tags":[
        "performing"
    ],
    "wof:name":"Dance Dynamics Inc",
    "wof:placetype":"venue"
},
  "geometry": {"coordinates":[-73.883003,40.755699],"type":"Point"}
}