{
  "type": "Feature",
  "properties": {
    "iso:country":"US",
    "sg:address":"319 Willoughby Ave",
    "sg:city":"Brooklyn",
    "sg:classifiers":[
        {
            "category":"Manufacturing",
            "subcategory":"Apparel",
            "type":"Manufacturing & Wholesale Goods"
        }
    ],
    "sg:phone":"+1   ",
    "sg:postcode":"11205",
    "sg:province":"NY",
    "sg:tags":[
        "household",
        "furnishing",
        "mfg"
    ],
    "wof:name":"Vyphius Co",
    "wof:placetype":"venue"
},
  "geometry": {"coordinates":[-73.95828899999999,40.692763],"type":"Point"}
}