{
  "type": "Feature",
  "properties": {
    "addr:full":"82 School St Glen Cove NY 11542",
    "addr:housenumber":"82",
    "addr:postcode":"11542",
    "addr:street":"School St",
    "iso:country":"US",
    "sg:address":"82 School St",
    "sg:city":"Glen Cove",
    "sg:classifiers":[
        {
            "category":"Shopping",
            "subcategory":"Discount & Variety Stores",
            "type":"Retail Goods"
        }
    ],
    "sg:phone":"+1 516 759 5900",
    "sg:postcode":"11542",
    "sg:province":"NY",
    "sg:tags":[
        "merchandise",
        "general"
    ],
    "wof:name":"My Phone Store Inc",
    "wof:placetype":"venue"
},
  "geometry": {"coordinates":[-73.630764,40.867643],"type":"Point"}
}