{
  "type": "Feature",
  "properties": {
    "addr:full":"3871 Sedgwick Ave Apt 1B Bronx NY 10463",
    "addr:housenumber":"3871",
    "addr:postcode":"10463",
    "addr:street":"Sedgwick Ave Apt",
    "iso:country":"US",
    "sg:address":"3871 Sedgwick Ave Apt 1B",
    "sg:city":"Bronx",
    "sg:classifiers":[
        {
            "category":"Health Services",
            "subcategory":"Chiropractor",
            "type":"Services"
        }
    ],
    "sg:phone":"+1 718 548 1212",
    "sg:postcode":"10463",
    "sg:province":"NY",
    "sg:tags":[
        "chiropractic"
    ],
    "wof:name":"Vov Chiropractic, P.C.",
    "wof:placetype":"venue"
},
  "geometry": {"coordinates":[-73.894263,40.883001],"type":"Point"}
}