{
  "type": "Feature",
  "properties": {
    "addr:full":"2497 State Hwy 9n Scn Au Sable Forks NY 12912",
    "addr:housenumber":"2497",
    "addr:postcode":"12912",
    "addr:street":"State Hwy;Au Sable",
    "iso:country":"US",
    "sg:address":"2497 State Hwy 9n Scn",
    "sg:city":"Au Sable Forks",
    "sg:classifiers":[
        {
            "category":"Personal",
            "subcategory":"Beauty Salon",
            "type":"Services"
        }
    ],
    "sg:phone":"+1 518 647 8673",
    "sg:postcode":"12912",
    "sg:province":"NY",
    "wof:name":"Dee's Haircrafting",
    "wof:placetype":"venue"
},
  "geometry": {"coordinates":[-73.676621,44.440261],"type":"Point"}
}