{
  "type": "Feature",
  "properties": {
    "addr:full":"2486 Montauk Hwy Brookhaven NY 11719",
    "addr:housenumber":"2486",
    "addr:postcode":"11719",
    "addr:street":"Montauk Hwy",
    "iso:country":"US",
    "sg:address":"2486 Montauk Hwy",
    "sg:city":"Brookhaven",
    "sg:classifiers":[
        {
            "category":"Government",
            "subcategory":"Fire Station",
            "type":"Public Place"
        }
    ],
    "sg:phone":"+1 631 286 0282",
    "sg:postcode":"11719",
    "sg:province":"NY",
    "sg:tags":[
        "protection"
    ],
    "wof:name":"Brookhaven Fire District",
    "wof:placetype":"venue"
},
  "geometry": {"coordinates":[-72.916855,40.785476],"type":"Point"}
}