{
  "type": "Feature",
  "properties": {
    "iso:country":"US",
    "sg:address":"658 W Onondaga St",
    "sg:city":"Syracuse",
    "sg:classifiers":[
        {
            "category":"Organizations",
            "subcategory":"Community Association",
            "type":"Services"
        }
    ],
    "sg:phone":"+1 315 475 1170",
    "sg:postcode":"13204",
    "sg:province":"NY",
    "sg:tags":[
        "environmental",
        "ecological",
        "protection",
        "product"
    ],
    "sg:website":"http://www.aslf.org",
    "wof:name":"Atlantic States Legal Fndtn",
    "wof:placetype":"venue"
},
  "geometry": {"coordinates":[-76.16077300000001,43.038147],"type":"Point"}
}