{
  "type": "Feature",
  "properties": {
    "iso:country":"US",
    "sg:address":"11 Holland Ave",
    "sg:city":"White Plains",
    "sg:classifiers":[
        {
            "category":"Social Services",
            "type":"Services"
        }
    ],
    "sg:phone":"+1 914 997 2642",
    "sg:postcode":"10603",
    "sg:province":"NY",
    "wof:name":"Exchange Club The",
    "wof:placetype":"venue"
},
  "geometry": {"coordinates":[-73.770692,41.049731],"type":"Point"}
}