{
  "type": "Feature",
  "properties": {
    "iso:country":"US",
    "sg:address":"1587 Main St",
    "sg:city":"Buffalo",
    "sg:classifiers":[
        {
            "category":"Wholesale",
            "subcategory":"Hardware",
            "type":"Manufacturing & Wholesale Goods"
        }
    ],
    "sg:phone":"+1 716 882 2100",
    "sg:postcode":"14209",
    "sg:province":"NY",
    "sg:tags":[
        "plumbing",
        "fixture",
        "supply"
    ],
    "wof:name":"IRR Supply Ctr",
    "wof:placetype":"venue"
},
  "geometry": {"coordinates":[-78.863147,42.916362],"type":"Point"}
}