{
  "type": "Feature",
  "properties": {
    "addr:full":"383 Smithtown Blvd Ronkonkoma NY 11779",
    "addr:housenumber":"383",
    "addr:postcode":"11779",
    "addr:street":"Smithtown Blvd",
    "iso:country":"US",
    "sg:address":"383 Smithtown Blvd",
    "sg:city":"Ronkonkoma",
    "sg:classifiers":[
        {
            "category":"Food & Beverages",
            "subcategory":"Groceries & Convenience Stores",
            "type":"Retail Goods"
        }
    ],
    "sg:phone":"+1   ",
    "sg:postcode":"11779",
    "sg:province":"NY",
    "sg:website":"www.7-eleven.com",
    "wof:name":"7-Eleven",
    "wof:placetype":"venue"
},
  "geometry": {"coordinates":[-73.13084600000001,40.831976],"type":"Point"}
}