{
  "type": "Feature",
  "properties": {
    "addr:full":"337 River Rd Saint James NY 11780",
    "addr:housenumber":"337",
    "addr:postcode":"11780",
    "addr:street":"River Rd",
    "iso:country":"US",
    "sg:address":"337 River Rd",
    "sg:city":"Saint James",
    "sg:classifiers":[
        {
            "category":"Professional",
            "subcategory":"Art Services",
            "type":"Services"
        }
    ],
    "sg:phone":"+1   ",
    "sg:postcode":"11780",
    "sg:province":"NY",
    "sg:tags":[
        "commercial",
        "design"
    ],
    "wof:name":"Altair Graphic Design Inc",
    "wof:placetype":"venue"
},
  "geometry": {"coordinates":[-73.18910099999999,40.875792],"type":"Point"}
}