{
  "type": "Feature",
  "properties": {
    "addr:full":"1463 E 70th St Brooklyn NY 11234",
    "addr:housenumber":"1463",
    "addr:postcode":"11234",
    "addr:street":"E 70Th St",
    "iso:country":"US",
    "sg:address":"1463 E 70th St",
    "sg:city":"Brooklyn",
    "sg:classifiers":[
        {
            "category":"Shopping",
            "subcategory":"Optical Goods",
            "type":"Retail Goods"
        }
    ],
    "sg:phone":"+1   ",
    "sg:postcode":"11234",
    "sg:province":"NY",
    "wof:name":"Da Visions Optical Inc",
    "wof:placetype":"venue"
},
  "geometry": {"coordinates":[-73.909904,40.62108],"type":"Point"}
}