{
  "type": "Feature",
  "properties": {
    "addr:full":"201 W 16 St New York NY 10011",
    "addr:housenumber":"201",
    "addr:postcode":"10011",
    "addr:street":"W 16 St",
    "iso:country":"US",
    "sg:address":"201 W 16 St",
    "sg:city":"New York",
    "sg:classifiers":[
        {
            "category":"Professional",
            "subcategory":"Art Services",
            "type":"Services"
        }
    ],
    "sg:phone":"+1 212 243 9337",
    "sg:postcode":"10011",
    "sg:province":"NY",
    "sg:tags":[
        "graphic",
        "designer"
    ],
    "wof:name":"Binocular Design LTD",
    "wof:placetype":"venue"
},
  "geometry": {"coordinates":[-74.001555,40.74108],"type":"Point"}
}