{
  "type": "Feature",
  "properties": {
    "iso:country":"US",
    "sg:address":"2235 5 Ave",
    "sg:city":"New York",
    "sg:classifiers":[
        {
            "category":"Travel",
            "subcategory":"Travel Agent",
            "type":"Entertainment"
        }
    ],
    "sg:phone":"+1   ",
    "sg:postcode":"10037",
    "sg:province":"NY",
    "sg:tags":[
        "agency"
    ],
    "wof:name":"Shop Untill You Drop Inc",
    "wof:placetype":"venue"
},
  "geometry": {"coordinates":[-73.939494,40.810209],"type":"Point"}
}