{
  "type": "Feature",
  "properties": {
    "iso:country":"US",
    "sg:address":"536 Laguardia Pl",
    "sg:city":"New York",
    "sg:classifiers":[
        {
            "category":"Education",
            "subcategory":"Special Training",
            "type":"Public Place"
        }
    ],
    "sg:phone":"+1 212 358 6133",
    "sg:postcode":"10012",
    "sg:province":"NY",
    "sg:tags":[
        "center"
    ],
    "wof:name":"Learning By Design",
    "wof:placetype":"venue"
},
  "geometry": {"coordinates":[-73.99825,40.728905],"type":"Point"}
}