{
  "type": "Feature",
  "properties": {
    "iso:country":"US",
    "sg:address":"1704 Saint Johns Pl",
    "sg:city":"Brooklyn",
    "sg:classifiers":[
        {
            "category":"Real Estate",
            "subcategory":"Real Estate Operator",
            "type":"Services"
        }
    ],
    "sg:phone":"+1 718 756 4996",
    "sg:postcode":"11233",
    "sg:province":"NY",
    "sg:tags":[
        "apartment"
    ],
    "wof:name":"John Walter Edwards Apartments",
    "wof:placetype":"venue"
},
  "geometry": {"coordinates":[-73.920998,40.669998],"type":"Point"}
}