{
  "type": "Feature",
  "properties": {
    "iso:country":"US",
    "sg:address":"250 Babylon Tpke",
    "sg:city":"Roosevelt",
    "sg:classifiers":[
        {
            "category":"Building & Trades",
            "subcategory":"Construction",
            "type":"Services"
        }
    ],
    "sg:phone":"+1 516 868 3403",
    "sg:postcode":"11575",
    "sg:province":"NY",
    "sg:tags":[
        "handyman"
    ],
    "wof:name":"Leroys Automobile Repair",
    "wof:placetype":"venue"
},
  "geometry": {"coordinates":[-73.582368,40.674026],"type":"Point"}
}