{
  "type": "Feature",
  "properties": {
    "addr:full":"525 Broome St New York NY 10013",
    "addr:housenumber":"525",
    "addr:postcode":"10013",
    "addr:street":"Broome St",
    "iso:country":"US",
    "sg:address":"525 Broome St",
    "sg:city":"New York",
    "sg:classifiers":[
        {
            "category":"Bars & Pubs",
            "subcategory":"Lounge",
            "type":"Food & Drink"
        },
        {
            "category":"Restaurant",
            "type":"Food & Drink"
        }
    ],
    "sg:phone":"+1 646 596 8778",
    "sg:postcode":"10013",
    "sg:province":"NY",
    "sg:tags":[
        "hawaiian"
    ],
    "sg:website":"www.lanikainy.com",
    "wof:name":"Lani Kai",
    "wof:placetype":"venue"
},
  "geometry": {"coordinates":[-74.003986,40.72386],"type":"Point"}
}