{
  "type": "Feature",
  "properties": {
    "addr:full":"115 S Country Rd Bellport NY 11713",
    "addr:housenumber":"115",
    "addr:postcode":"11713",
    "addr:street":"S Country Rd",
    "iso:country":"US",
    "sg:address":"115 S Country Rd",
    "sg:city":"Bellport",
    "sg:classifiers":[
        {
            "category":"Wholesale",
            "subcategory":"Scrap",
            "type":"Manufacturing & Wholesale Goods"
        }
    ],
    "sg:phone":"+1 631 286 8190",
    "sg:postcode":"11713",
    "sg:province":"NY",
    "sg:tags":[
        "recycling",
        "center"
    ],
    "wof:name":"Tomra Metro",
    "wof:placetype":"venue"
},
  "geometry": {"coordinates":[-72.940828,40.756336],"type":"Point"}
}