{
  "type": "Feature",
  "properties": {
    "addr:full":"186 Tait Ave Rochester NY 14616",
    "addr:housenumber":"186",
    "addr:postcode":"14616",
    "addr:street":"Tait Ave",
    "iso:country":"US",
    "sg:address":"186 Tait Ave",
    "sg:city":"Rochester",
    "sg:classifiers":[
        {
            "category":"Building & Trades",
            "subcategory":"Construction",
            "type":"Services"
        }
    ],
    "sg:phone":"+1 585 621 2827",
    "sg:postcode":"14616",
    "sg:province":"NY",
    "sg:tags":[
        "house"
    ],
    "wof:name":"Complete Home Remodeling",
    "wof:placetype":"venue"
},
  "geometry": {"coordinates":[-77.651017,43.22741],"type":"Point"}
}