{
  "type": "Feature",
  "properties": {
    "iso:country":"US",
    "sg:address":"1619 Grand Central Ave",
    "sg:city":"Elmira",
    "sg:classifiers":[
        {
            "category":"Local Transit",
            "type":"Transportation"
        }
    ],
    "sg:phone":"+1 607 732 3430",
    "sg:postcode":"14903",
    "sg:province":"NY",
    "sg:tags":[
        "limousine"
    ],
    "wof:name":"Silk Limousine",
    "wof:placetype":"venue"
},
  "geometry": {"coordinates":[-76.815984,42.120594],"type":"Point"}
}