{
  "type": "Feature",
  "properties": {
    "iso:country":"US",
    "sg:address":"146 Beekman St",
    "sg:city":"New York",
    "sg:classifiers":[
        {
            "category":"Bars & Pubs",
            "type":"Food & Drink"
        }
    ],
    "sg:phone":"+1 212 962 0053",
    "sg:postcode":"10079",
    "sg:province":"NY",
    "sg:tags":[
        "new",
        "american"
    ],
    "sg:website":"www.freshsalt.com",
    "wof:name":"Fresh Salt",
    "wof:placetype":"venue"
},
  "geometry": {"coordinates":[-74.002698,40.707174],"type":"Point"}
}