{
  "type": "Feature",
  "properties": {
    "addr:full":"90 John St New York NY 10038",
    "addr:housenumber":"90",
    "addr:postcode":"10038",
    "addr:street":"John St",
    "iso:country":"US",
    "sg:address":"90 John St",
    "sg:city":"New York",
    "sg:classifiers":[
        {
            "category":"Banks & Credit Unions",
            "subcategory":"Investment Brokerage",
            "type":"Services"
        }
    ],
    "sg:phone":"+1 212 748 3500",
    "sg:postcode":"10038",
    "sg:province":"NY",
    "sg:tags":[
        "advisory",
        "financial"
    ],
    "wof:name":"MVP Financial Inc",
    "wof:placetype":"venue"
},
  "geometry": {"coordinates":[-74.006987,40.708506],"type":"Point"}
}