{
  "type": "Feature",
  "properties": {
    "addr:full":"1550 Grand Ave Baldwin NY 11510",
    "addr:housenumber":"1550",
    "addr:postcode":"11510",
    "addr:street":"Grand Ave",
    "iso:country":"US",
    "sg:address":"1550 Grand Ave",
    "sg:city":"Baldwin",
    "sg:classifiers":[
        {
            "category":"Professional",
            "subcategory":"Business Services",
            "type":"Services"
        }
    ],
    "sg:phone":"+1   ",
    "sg:postcode":"11510",
    "sg:province":"NY",
    "sg:tags":[
        "post",
        "contract"
    ],
    "wof:name":"Postal Connection",
    "wof:placetype":"venue"
},
  "geometry": {"coordinates":[-73.61090299999999,40.672058],"type":"Point"}
}