{
  "type": "Feature",
  "properties": {
    "addr:full":"7102 18th Avenue Brooklyn NY 11204",
    "addr:housenumber":"7102",
    "addr:postcode":"11204",
    "addr:street":"18Th Avenue",
    "iso:country":"US",
    "sg:address":"7102 18th Avenue",
    "sg:city":"Brooklyn",
    "sg:classifiers":[
        {
            "category":"Ice Cream",
            "type":"Food & Drink"
        }
    ],
    "sg:phone":"+1 718 837 2820",
    "sg:postcode":"11204",
    "sg:province":"NY",
    "sg:tags":[
        "frozen",
        "yogurt"
    ],
    "wof:name":"Ox Lucky Corner",
    "wof:placetype":"venue"
},
  "geometry": {"coordinates":[-73.99365899999999,40.615657],"type":"Point"}
}