{
  "type": "Feature",
  "properties": {
    "addr:full":"210 S Fehr Way Bay Shore NY 11706",
    "addr:housenumber":"210",
    "addr:postcode":"11706",
    "addr:street":"S Fehr Way",
    "iso:country":"US",
    "sg:address":"210 S Fehr Way",
    "sg:city":"Bay Shore",
    "sg:classifiers":[
        {
            "category":"Professional",
            "subcategory":"Management & Consulting",
            "type":"Services"
        }
    ],
    "sg:phone":"+1 631 462 1325",
    "sg:postcode":"11706",
    "sg:province":"NY",
    "sg:tags":[
        "party",
        "planning"
    ],
    "sg:website":"www.partyantics.com",
    "wof:name":"Party Antics",
    "wof:placetype":"venue"
},
  "geometry": {"coordinates":[-73.28456,40.764849],"type":"Point"}
}