{
  "type": "Feature",
  "properties": {
    "iso:country":"US",
    "sg:address":"355 Orchard Park Rd",
    "sg:city":"Buffalo",
    "sg:classifiers":[
        {
            "category":"Banks & Credit Unions",
            "subcategory":"Bank",
            "type":"Services"
        }
    ],
    "sg:phone":"+1 716 823 5317",
    "sg:postcode":"14224",
    "sg:province":"NY",
    "sg:website":"www.citizensbank.com",
    "wof:name":"Citizens Bank",
    "wof:placetype":"venue"
},
  "geometry": {"coordinates":[-78.785259,42.834272],"type":"Point"}
}