{
  "type": "Feature",
  "properties": {
    "addr:full":"748 Union St Brooklyn NY 11215",
    "addr:housenumber":"748",
    "addr:postcode":"11215",
    "addr:street":"Union St",
    "iso:country":"US",
    "sg:address":"748 Union St",
    "sg:city":"Brooklyn",
    "sg:classifiers":[
        {
            "category":"Arts & Performance",
            "subcategory":"Arts Center",
            "type":"Entertainment"
        }
    ],
    "sg:phone":"+1 718 857 5158",
    "sg:postcode":"11215",
    "sg:province":"NY",
    "sg:tags":[
        "performing"
    ],
    "wof:name":"Spoke The Hub Dancing Co",
    "wof:placetype":"venue"
},
  "geometry": {"coordinates":[-73.978194,40.675372],"type":"Point"}
}