{
  "type": "Feature",
  "properties": {
    "addr:full":"1230 Park Ave New York NY 10128",
    "addr:housenumber":"1230",
    "addr:postcode":"10128",
    "addr:street":"Park Ave",
    "iso:country":"US",
    "sg:address":"1230 Park Ave",
    "sg:city":"New York",
    "sg:classifiers":[
        {
            "category":"Health Services",
            "subcategory":"Doctor",
            "type":"Services"
        }
    ],
    "sg:phone":"+1 212 348 8311",
    "sg:postcode":"10128",
    "sg:province":"NY",
    "sg:tags":[
        "medical"
    ],
    "wof:name":"Heath Desmond MD PC",
    "wof:placetype":"venue"
},
  "geometry": {"coordinates":[-73.95282400000001,40.78621],"type":"Point"}
}