{
  "type": "Feature",
  "properties": {
    "addr:full":"922 Hazelwood Ave Syracuse NY 13224",
    "addr:housenumber":"922",
    "addr:postcode":"13224",
    "addr:street":"Hazelwood Ave",
    "iso:country":"US",
    "sg:address":"922 Hazelwood Ave",
    "sg:city":"Syracuse",
    "sg:classifiers":[
        {
            "category":"Sports & Exercise",
            "subcategory":"Bowling",
            "type":"Entertainment"
        }
    ],
    "sg:phone":"+1 315 449 9514",
    "sg:postcode":"13224",
    "sg:province":"NY",
    "sg:website":"http://www.hcds.com",
    "wof:name":"Bowl Mor",
    "wof:placetype":"venue"
},
  "geometry": {"coordinates":[-76.0919,43.052002],"type":"Point"}
}