{
  "type": "Feature",
  "properties": {
    "iso:country":"US",
    "sg:address":"542 Jerusalem Ave",
    "sg:city":"North Bellmore",
    "sg:classifiers":[
        {
            "category":"Bagels",
            "subcategory":"None",
            "type":"Food & Drink"
        }
    ],
    "sg:phone":"+1 516 781 6575",
    "sg:postcode":"11710",
    "sg:province":"NY",
    "wof:name":"Bellmore Bagel & Deli",
    "wof:placetype":"venue"
},
  "geometry": {"coordinates":[-73.548599,40.690701],"type":"Point"}
}