{
  "type": "Feature",
  "properties": {
    "addr:full":"280 Glen St Glen Cove NY 11542",
    "addr:housenumber":"280",
    "addr:postcode":"11542",
    "addr:street":"Glen St",
    "iso:country":"US",
    "sg:address":"280 Glen St",
    "sg:city":"Glen Cove",
    "sg:classifiers":[
        {
            "category":"Real Estate",
            "subcategory":"Real Estate Agent",
            "type":"Services"
        }
    ],
    "sg:phone":"+1 516 671 3976",
    "sg:postcode":"11542",
    "sg:province":"NY",
    "wof:name":"Coristan Realty",
    "wof:placetype":"venue"
},
  "geometry": {"coordinates":[-73.620587,40.859115],"type":"Point"}
}