{
  "type": "Feature",
  "properties": {
    "addr:full":"340 Main St Binghamton NY 13905",
    "addr:housenumber":"340",
    "addr:postcode":"13905",
    "addr:street":"Main St",
    "iso:country":"US",
    "sg:address":"340 Main St",
    "sg:city":"Binghamton",
    "sg:classifiers":[
        {
            "category":"Personal",
            "subcategory":"Beauty Salon",
            "type":"Services"
        }
    ],
    "sg:phone":"+1   ",
    "sg:postcode":"13905",
    "sg:province":"NY",
    "sg:tags":[
        "shop"
    ],
    "wof:name":"Apropos",
    "wof:placetype":"venue"
},
  "geometry": {"coordinates":[-75.944866,42.111174],"type":"Point"}
}