{
  "type": "Feature",
  "properties": {
    "iso:country":"US",
    "sg:address":"4702 Avenue N",
    "sg:city":"Brooklyn",
    "sg:classifiers":[
        {
            "category":"Ice Cream",
            "type":"Food & Drink"
        }
    ],
    "sg:phone":"+1 718 338 9355",
    "sg:postcode":"11234",
    "sg:province":"NY",
    "sg:tags":[
        "frozen",
        "yogurt"
    ],
    "wof:name":"Carvel",
    "wof:placetype":"venue"
},
  "geometry": {"coordinates":[-73.92965700000001,40.618661],"type":"Point"}
}