{
  "type": "Feature",
  "properties": {
    "addr:full":"1745 Ole Jule Ln Mattituck NY 11952",
    "addr:housenumber":"1745",
    "addr:postcode":"11952",
    "addr:street":"Ole Jule Ln",
    "iso:country":"US",
    "sg:address":"1745 Ole Jule Ln",
    "sg:city":"Mattituck",
    "sg:classifiers":[
        {
            "category":"Retail",
            "subcategory":"Animal Services",
            "type":"Services"
        }
    ],
    "sg:phone":"+1 631 298 4572",
    "sg:postcode":"11952",
    "sg:province":"NY",
    "wof:name":"Papish Horse Farm",
    "wof:placetype":"venue"
},
  "geometry": {"coordinates":[-72.528721,40.989696],"type":"Point"}
}