{
  "type": "Feature",
  "properties": {
    "addr:full":"603 State St Schenectady NY 12305",
    "addr:housenumber":"603",
    "addr:postcode":"12305",
    "addr:street":"State St",
    "iso:country":"US",
    "sg:address":"603 State St",
    "sg:city":"Schenectady",
    "sg:classifiers":[
        {
            "category":"Organizations",
            "subcategory":"Religious Organization",
            "type":"Services"
        }
    ],
    "sg:phone":"+1 518 374 4403",
    "sg:postcode":"12305",
    "sg:province":"NY",
    "sg:website":"www.gbgm-umc.org",
    "wof:name":"First United Methodist Church",
    "wof:placetype":"venue"
},
  "geometry": {"coordinates":[-73.93837499999999,42.810641],"type":"Point"}
}