{
  "type": "Feature",
  "properties": {
    "iso:country":"US",
    "sg:address":"1241 Deer Park Ave",
    "sg:city":"North Babylon",
    "sg:classifiers":[
        {
            "category":"Shopping",
            "subcategory":"Discount & Variety Stores",
            "type":"Retail Goods"
        }
    ],
    "sg:phone":"+1 631 667 4558",
    "sg:postcode":"11703",
    "sg:province":"NY",
    "wof:name":"Family City Inc",
    "wof:placetype":"venue"
},
  "geometry": {"coordinates":[-73.320864,40.739024],"type":"Point"}
}