{
  "type": "Feature",
  "properties": {
    "addr:full":"33 Chestnut St Rochester NY 14604",
    "addr:housenumber":"33",
    "addr:postcode":"14604",
    "addr:street":"Chestnut St",
    "iso:country":"US",
    "sg:address":"33 Chestnut St",
    "sg:city":"Rochester",
    "sg:classifiers":[
        {
            "category":"Health Services",
            "subcategory":"Clinic",
            "type":"Services"
        }
    ],
    "sg:phone":"+1 585 262 4330",
    "sg:postcode":"14604",
    "sg:province":"NY",
    "sg:tags":[
        "substance",
        "abuse"
    ],
    "wof:name":"ABC",
    "wof:placetype":"venue"
},
  "geometry": {"coordinates":[-77.602784,43.1564],"type":"Point"}
}