{
  "type": "Feature",
  "properties": {
    "addr:full":"1629 2nd Ave Between 84th and 85th St New York NY 10028",
    "addr:housenumber":"1629",
    "addr:postcode":"10028",
    "addr:street":"2Nd Ave Between;85Th St",
    "iso:country":"US",
    "sg:address":"1629 2nd Ave Between 84th and 85th St",
    "sg:city":"New York",
    "sg:classifiers":[
        {
            "category":"Fast Food",
            "type":"Food & Drink"
        },
        {
            "category":"Bars & Pubs",
            "subcategory":"Dive Bar",
            "type":"Food & Drink"
        }
    ],
    "sg:phone":"+1 212 628 2364",
    "sg:postcode":"10028",
    "sg:province":"NY",
    "sg:tags":[
        "burger"
    ],
    "wof:name":"Swig",
    "wof:placetype":"venue"
},
  "geometry": {"coordinates":[-73.952462,40.776866],"type":"Point"}
}