{
  "type": "Feature",
  "properties": {
    "iso:country":"US",
    "sg:address":"146 Bangor St",
    "sg:city":"Lindenhurst",
    "sg:classifiers":[
        {
            "category":"Wholesale",
            "subcategory":"Durable Goods & Equipment",
            "type":"Manufacturing & Wholesale Goods"
        }
    ],
    "sg:phone":"+1 631 957 7980",
    "sg:postcode":"11757",
    "sg:province":"NY",
    "sg:tags":[
        "light",
        "safety",
        "highway",
        "barrier",
        "sign"
    ],
    "wof:name":"Selecto-Flash Safety Inc",
    "wof:placetype":"venue"
},
  "geometry": {"coordinates":[-73.38559100000001,40.685163],"type":"Point"}
}