{
  "type": "Feature",
  "properties": {
    "iso:country":"US",
    "sg:address":"577 Route 303",
    "sg:city":"Blauvelt",
    "sg:classifiers":[
        {
            "category":"Professional",
            "type":"Services"
        },
        {
            "category":"Restaurant",
            "type":"Food & Drink"
        }
    ],
    "sg:phone":"+1 845 359 4823",
    "sg:postcode":"10913",
    "sg:province":"NY",
    "sg:tags":[
        "mexican",
        "caterer"
    ],
    "sg:website":"http://www.manorhouse.net",
    "wof:name":"Casa Mia Manor House",
    "wof:placetype":"venue"
},
  "geometry": {"coordinates":[-73.949113,41.063512],"type":"Point"}
}