{
  "type": "Feature",
  "properties": {
    "addr:full":"1937 Fairport Nine Mile Point Rd Penfield NY 14526",
    "addr:housenumber":"1937",
    "addr:postcode":"14526",
    "addr:street":"Fairport Nine Mile Point Rd",
    "iso:country":"US",
    "sg:address":"1937 Fairport Nine Mile Point Rd",
    "sg:city":"Penfield",
    "sg:classifiers":[
        {
            "category":"Professional",
            "subcategory":"Business Services",
            "type":"Services"
        }
    ],
    "sg:phone":"+1 585 388 0049",
    "sg:postcode":"14526",
    "sg:province":"NY",
    "sg:tags":[
        "fund",
        "promotion",
        "raising"
    ],
    "wof:name":"Upstate Watercraft Promotions",
    "wof:placetype":"venue"
},
  "geometry": {"coordinates":[-77.436094,43.149055],"type":"Point"}
}