{
  "type": "Feature",
  "properties": {
    "iso:country":"US",
    "sg:address":"204 Main St",
    "sg:city":"Goshen",
    "sg:classifiers":[
        {
            "category":"Professional",
            "subcategory":"Lawyer & Legal Services",
            "type":"Services"
        }
    ],
    "sg:phone":"+1 845 294 2771",
    "sg:postcode":"10924",
    "sg:province":"NY",
    "sg:tags":[
        "personal",
        "injury"
    ],
    "wof:name":"Law Office of D R Dollinger",
    "wof:placetype":"venue"
},
  "geometry": {"coordinates":[-74.319901,41.403702],"type":"Point"}
}