{
  "type": "Feature",
  "properties": {
    "addr:full":"130 W 30 St New York NY 10001",
    "addr:housenumber":"130",
    "addr:postcode":"10001",
    "addr:street":"W 30 St",
    "iso:country":"US",
    "sg:address":"130 W 30 St",
    "sg:city":"New York",
    "sg:classifiers":[
        {
            "category":"Building & Trades",
            "subcategory":"Plumbing",
            "type":"Services"
        }
    ],
    "sg:phone":"+1 212 239 7280",
    "sg:postcode":"10001",
    "sg:province":"NY",
    "sg:tags":[
        "plumbing",
        "air",
        "heating",
        "conditioning",
        "contractor"
    ],
    "wof:name":"Gkcl Service Corp",
    "wof:placetype":"venue"
},
  "geometry": {"coordinates":[-73.991839,40.748038],"type":"Point"}
}