{
  "type": "Feature",
  "properties": {
    "addr:full":"209 Pinehurst Ave New York NY 10033",
    "addr:housenumber":"209",
    "addr:postcode":"10033",
    "addr:street":"Pinehurst Ave",
    "iso:country":"US",
    "sg:address":"209 Pinehurst Ave",
    "sg:city":"New York",
    "sg:classifiers":[
        {
            "category":"Food & Beverages",
            "subcategory":"Liquor & Beverages",
            "type":"Retail Goods"
        }
    ],
    "sg:phone":"+1 212 923 0584",
    "sg:postcode":"10033",
    "sg:province":"NY",
    "sg:tags":[
        "beer",
        "spirit",
        "wine"
    ],
    "sg:website":"www.vinesonpine.com/",
    "wof:name":"Vines On Pine",
    "wof:placetype":"venue"
},
  "geometry": {"coordinates":[-73.937974,40.854225],"type":"Point"}
}