{
  "type": "Feature",
  "properties": {
    "addr:full":"635 E 211th St Bronx NY 10467",
    "addr:housenumber":"635",
    "addr:postcode":"10467",
    "addr:street":"E 211Th St",
    "iso:country":"US",
    "sg:address":"635 E 211th St",
    "sg:city":"Bronx",
    "sg:classifiers":[
        {
            "category":"Personal",
            "subcategory":"Adult",
            "type":"Services"
        }
    ],
    "sg:phone":"+1 718 515 0633",
    "sg:postcode":"10467",
    "sg:province":"NY",
    "sg:tags":[
        "escort"
    ],
    "wof:name":"Fantasy Escort Svc",
    "wof:placetype":"venue"
},
  "geometry": {"coordinates":[-73.868441,40.878587],"type":"Point"}
}