{
  "type": "Feature",
  "properties": {
    "iso:country":"US",
    "sg:address":"9 E 96 St",
    "sg:city":"New York",
    "sg:classifiers":[
        {
            "category":"Health Services",
            "subcategory":"Doctor",
            "type":"Services"
        }
    ],
    "sg:phone":"+1 212 289 5024",
    "sg:postcode":"10128",
    "sg:province":"NY",
    "sg:tags":[
        "medical"
    ],
    "wof:name":"Francis Baudry MD",
    "wof:placetype":"venue"
},
  "geometry": {"coordinates":[-73.954339,40.787412],"type":"Point"}
}