{
  "type": "Feature",
  "properties": {
    "iso:country":"US",
    "sg:address":"160 Boney Ln",
    "sg:city":"St James",
    "sg:classifiers":[
        {
            "category":"Building & Trades",
            "subcategory":"Construction",
            "type":"Services"
        }
    ],
    "sg:phone":"+1 631 862 8435",
    "sg:postcode":"11780",
    "sg:province":"NY",
    "sg:tags":[
        "general",
        "contractor"
    ],
    "wof:name":"Lakeview Contrctng",
    "wof:placetype":"venue"
},
  "geometry": {"coordinates":[-73.206182,40.905088],"type":"Point"}
}