{
  "type": "Feature",
  "properties": {
    "addr:full":"422 Conklin St Farmingdale NY 11735",
    "addr:housenumber":"422",
    "addr:postcode":"11735",
    "addr:street":"Conklin St",
    "iso:country":"US",
    "sg:address":"422 Conklin St",
    "sg:city":"Farmingdale",
    "sg:classifiers":[
        {
            "category":"Professional",
            "subcategory":"Printing & Photocopies",
            "type":"Services"
        }
    ],
    "sg:phone":"+1 516 454 9076",
    "sg:postcode":"11735",
    "sg:province":"NY",
    "sg:tags":[
        "duplicating",
        "copying"
    ],
    "sg:website":"www.scan-a-chrome.com",
    "wof:name":"Scan-A-Chrome Color Inc",
    "wof:placetype":"venue"
},
  "geometry": {"coordinates":[-73.444368,40.733014],"type":"Point"}
}