{
  "type": "Feature",
  "properties": {
    "iso:country":"US",
    "sg:address":"2788 Old Yorktown Rd",
    "sg:city":"Yorktown Heights",
    "sg:classifiers":[
        {
            "category":"Professional",
            "subcategory":"Accounting & Tax Preparation",
            "type":"Services"
        }
    ],
    "sg:phone":"+1   ",
    "sg:postcode":"10598",
    "sg:province":"NY",
    "wof:name":"James C C P A P C Cardillo",
    "wof:placetype":"venue"
},
  "geometry": {"coordinates":[-73.808733,41.298952],"type":"Point"}
}