{
  "type": "Feature",
  "properties": {
    "addr:full":"580 Nostrand Ave Brooklyn NY 11216",
    "addr:housenumber":"580",
    "addr:postcode":"11216",
    "addr:street":"Nostrand Ave",
    "iso:country":"US",
    "sg:address":"580 Nostrand Ave",
    "sg:city":"Brooklyn",
    "sg:classifiers":[
        {
            "category":"Shopping",
            "subcategory":"Pharmacy",
            "type":"Retail Goods"
        }
    ],
    "sg:phone":"+1 718 783 1143",
    "sg:postcode":"11216",
    "sg:province":"NY",
    "wof:name":"County Pharmacy Inc",
    "wof:placetype":"venue"
},
  "geometry": {"coordinates":[-73.949679,40.678543],"type":"Point"}
}