{
  "type": "Feature",
  "properties": {
    "addr:full":"1886 Broadway Frnt 2 New York NY 10023",
    "addr:housenumber":"1886;2",
    "addr:postcode":"10023",
    "addr:street":"Broadway Frnt",
    "iso:country":"US",
    "sg:address":"1886 Broadway Frnt 2",
    "sg:city":"New York",
    "sg:classifiers":[
        {
            "category":"Health Services",
            "subcategory":"Doctor",
            "type":"Services"
        }
    ],
    "sg:phone":"+1 212 765 0765",
    "sg:postcode":"10023",
    "sg:province":"NY",
    "sg:tags":[
        "cardiologist"
    ],
    "wof:name":"West Side Cardiology",
    "wof:placetype":"venue"
},
  "geometry": {"coordinates":[-73.98201,40.770621],"type":"Point"}
}