{
  "type": "Feature",
  "properties": {
    "addr:full":"486 Metropolitan Ave Brooklyn NY 11211",
    "addr:housenumber":"486",
    "addr:postcode":"11211",
    "addr:street":"Metropolitan Ave",
    "iso:country":"US",
    "sg:address":"486 Metropolitan Ave",
    "sg:city":"Brooklyn",
    "sg:classifiers":[
        {
            "category":"Bars & Pubs",
            "type":"Food & Drink"
        },
        {
            "category":"Restaurant",
            "type":"Food & Drink"
        }
    ],
    "sg:phone":"+1 718 218 7600",
    "sg:postcode":"11211",
    "sg:province":"NY",
    "sg:tags":[
        "new",
        "american"
    ],
    "sg:website":"www.odyssealounge.com",
    "wof:name":"Odyssea",
    "wof:placetype":"venue"
},
  "geometry": {"coordinates":[-73.95270600000001,40.714056],"type":"Point"}
}