{
  "type": "Feature",
  "properties": {
    "addr:full":"407 Plattekill Rd Freehold NY 12083",
    "addr:housenumber":"407",
    "addr:postcode":"12083",
    "addr:street":"Plattekill Rd",
    "iso:country":"US",
    "sg:address":"407 Plattekill Rd",
    "sg:city":"Freehold",
    "sg:classifiers":[
        {
            "category":"Restaurant",
            "type":"Food & Drink"
        }
    ],
    "sg:phone":"+1   ",
    "sg:postcode":"12083",
    "sg:province":"NY",
    "sg:tags":[
        "eating"
    ],
    "wof:name":"Hot Stuff Catering",
    "wof:placetype":"venue"
},
  "geometry": {"coordinates":[-74.00832200000001,42.375584],"type":"Point"}
}