{
  "type": "Feature",
  "properties": {
    "addr:full":"756 Quaker Rd Queensbury NY 12804",
    "addr:housenumber":"756",
    "addr:postcode":"12804",
    "addr:street":"Quaker Rd",
    "iso:country":"US",
    "sg:address":"756 Quaker Rd",
    "sg:city":"Queensbury",
    "sg:classifiers":[
        {
            "category":"Food & Beverages",
            "subcategory":"Groceries & Convenience Stores",
            "type":"Retail Goods"
        }
    ],
    "sg:phone":"+1 518 761 9506",
    "sg:postcode":"12804",
    "sg:province":"NY",
    "wof:name":"Hess Station 32391",
    "wof:placetype":"venue"
},
  "geometry": {"coordinates":[-73.613798,43.317043],"type":"Point"}
}