{
  "type": "Feature",
  "properties": {
    "iso:country":"US",
    "sg:address":"695 Knickerbocker Ave",
    "sg:city":"Brooklyn",
    "sg:classifiers":[
        {
            "category":"Education",
            "subcategory":"Special Training",
            "type":"Public Place"
        }
    ],
    "sg:phone":"+1 718 456 1185",
    "sg:postcode":"11221",
    "sg:province":"NY",
    "sg:tags":[
        "school",
        "instruction",
        "driving"
    ],
    "wof:name":"G & C Auto Driving School",
    "wof:placetype":"venue"
},
  "geometry": {"coordinates":[-73.910698,40.6945],"type":"Point"}
}