{
  "type": "Feature",
  "properties": {
    "iso:country":"US",
    "sg:address":"806 North St",
    "sg:city":"Endicott",
    "sg:classifiers":[
        {
            "category":"Professional",
            "subcategory":"Management & Consulting",
            "type":"Services"
        }
    ],
    "sg:phone":"+1 607 754 6666",
    "sg:postcode":"13760",
    "sg:province":"NY",
    "sg:tags":[
        "pr",
        "health",
        "specialty",
        "outpatient"
    ],
    "wof:name":"Acupuncture Clinic",
    "wof:placetype":"venue"
},
  "geometry": {"coordinates":[-76.05330600000001,42.103486],"type":"Point"}
}