{
  "type": "Feature",
  "properties": {
    "addr:full":"4 Temme Ct Plainview NY 11803",
    "addr:housenumber":"4",
    "addr:postcode":"11803",
    "addr:street":"Temme Ct",
    "iso:country":"US",
    "sg:address":"4 Temme Ct",
    "sg:city":"Plainview",
    "sg:classifiers":[
        {
            "category":"Professional",
            "subcategory":"Art Services",
            "type":"Services"
        }
    ],
    "sg:phone":"+1 516 938 6949",
    "sg:postcode":"11803",
    "sg:province":"NY",
    "sg:tags":[
        "designer",
        "display",
        "producer"
    ],
    "wof:name":"Relentless Designs Co",
    "wof:placetype":"venue"
},
  "geometry": {"coordinates":[-73.471603,40.761644],"type":"Point"}
}