{
  "type": "Feature",
  "properties": {
    "addr:full":"97 Fall St Seneca Falls NY 13148",
    "addr:housenumber":"97",
    "addr:postcode":"13148",
    "addr:street":"Fall St",
    "iso:country":"US",
    "sg:address":"97 Fall St",
    "sg:city":"Seneca Falls",
    "sg:classifiers":[
        {
            "category":"Real Estate",
            "subcategory":"Developer",
            "type":"Services"
        }
    ],
    "sg:phone":"+1 315 568 1063",
    "sg:postcode":"13148",
    "sg:province":"NY",
    "wof:name":"Seneca Knit Development Corp",
    "wof:placetype":"venue"
},
  "geometry": {"coordinates":[-76.79759300000001,42.910364],"type":"Point"}
}