{
  "type": "Feature",
  "properties": {
    "iso:country":"US",
    "sg:address":"55 W 39th St",
    "sg:city":"New York",
    "sg:classifiers":[
        {
            "category":"Shopping",
            "subcategory":"Crafts & Fabrics",
            "type":"Retail Goods"
        }
    ],
    "sg:phone":"+1 212 869 2460",
    "sg:postcode":"10018",
    "sg:province":"NY",
    "sg:tags":[
        "store"
    ],
    "wof:name":"Rainbow Mills",
    "wof:placetype":"venue"
},
  "geometry": {"coordinates":[-73.9841,40.752399],"type":"Point"}
}