{
  "type": "Feature",
  "properties": {
    "addr:full":"47 Marian Ave Poughkeepsie NY 12601",
    "addr:housenumber":"47",
    "addr:postcode":"12601",
    "addr:street":"Marian Ave",
    "iso:country":"US",
    "sg:address":"47 Marian Ave",
    "sg:city":"Poughkeepsie",
    "sg:classifiers":[
        {
            "category":"Freight",
            "type":"Transportation"
        }
    ],
    "sg:phone":"+1   ",
    "sg:postcode":"12601",
    "sg:province":"NY",
    "sg:tags":[
        "operator",
        "trucking"
    ],
    "wof:name":"Mc Niff Trucking",
    "wof:placetype":"venue"
},
  "geometry": {"coordinates":[-73.919578,41.688645],"type":"Point"}
}