{
  "type": "Feature",
  "properties": {
    "addr:full":"1300 Madison Avenue New York NY 10128",
    "addr:housenumber":"1300",
    "addr:postcode":"10128",
    "addr:street":"Madison Avenue",
    "iso:country":"US",
    "sg:address":"1300 Madison Avenue",
    "sg:city":"New York",
    "sg:classifiers":[
        {
            "category":"Shopping",
            "subcategory":"Optician",
            "type":"Retail Goods"
        }
    ],
    "sg:phone":"+1 212 722 1600",
    "sg:postcode":"10128",
    "sg:province":"NY",
    "sg:tags":[
        "eyewear"
    ],
    "sg:website":"www.robertmarc.com",
    "wof:name":"Robert Marc",
    "wof:placetype":"venue"
},
  "geometry": {"coordinates":[-73.95613400000001,40.78496],"type":"Point"}
}