{
  "type": "Feature",
  "properties": {
    "iso:country":"US",
    "sg:address":"710 Quaker Rd",
    "sg:city":"East Aurora",
    "sg:classifiers":[
        {
            "category":"Real Estate",
            "subcategory":"Real Estate Operator",
            "type":"Services"
        }
    ],
    "sg:phone":"+1 716 652 9706",
    "sg:postcode":"14052",
    "sg:province":"NY",
    "sg:tags":[
        "apartment"
    ],
    "wof:name":"Trinity Park Apartments",
    "wof:placetype":"venue"
},
  "geometry": {"coordinates":[-78.664539,42.76492],"type":"Point"}
}