{
  "type": "Feature",
  "properties": {
    "iso:country":"US",
    "sg:address":"20 Dew Line Rd",
    "sg:city":"Liverpool",
    "sg:classifiers":[
        {
            "category":"Shopping",
            "subcategory":"Catalog Store",
            "type":"Retail Goods"
        }
    ],
    "sg:phone":"+1   ",
    "sg:postcode":"13090",
    "sg:province":"NY",
    "sg:tags":[
        "mail",
        "house"
    ],
    "wof:name":"Jnj Goods",
    "wof:placetype":"venue"
},
  "geometry": {"coordinates":[-76.21282100000001,43.133847],"type":"Point"}
}