{
  "type": "Feature",
  "properties": {
    "iso:country":"US",
    "sg:address":"2577 State Hwy 11A",
    "sg:city":"La Fayette",
    "sg:classifiers":[
        {
            "category":"Government",
            "subcategory":"Fire Station",
            "type":"Public Place"
        }
    ],
    "sg:phone":"+1 315 677 3680",
    "sg:postcode":"13084",
    "sg:province":"NY",
    "sg:tags":[
        "marshal"
    ],
    "wof:name":"La Fayette Fire Marshall",
    "wof:placetype":"venue"
},
  "geometry": {"coordinates":[-76.106525,42.896763],"type":"Point"}
}