{
  "type": "Feature",
  "properties": {
    "addr:full":"600 W 115th Street New York NY 10025",
    "addr:housenumber":"600",
    "addr:postcode":"10025",
    "addr:street":"W 115Th Street",
    "iso:country":"US",
    "sg:address":"600 W 115th Street",
    "sg:city":"New York",
    "sg:classifiers":[
        {
            "category":"Restaurant",
            "type":"Food & Drink"
        }
    ],
    "sg:phone":"+1 212 662 1000",
    "sg:postcode":"10025",
    "sg:province":"NY",
    "sg:tags":[
        "pizza"
    ],
    "sg:website":"www.pizzapronto.com",
    "wof:name":"Pronto Pizza",
    "wof:placetype":"venue"
},
  "geometry": {"coordinates":[-73.964489,40.807359],"type":"Point"}
}