{
  "type": "Feature",
  "properties": {
    "addr:full":"5521 11th Ave Brooklyn NY 11219",
    "addr:housenumber":"5521",
    "addr:postcode":"11219",
    "addr:street":"11Th Ave",
    "iso:country":"US",
    "sg:address":"5521 11th Ave",
    "sg:city":"Brooklyn",
    "sg:classifiers":[
        {
            "category":"Building & Trades",
            "subcategory":"Construction",
            "type":"Services"
        }
    ],
    "sg:phone":"+1 718 853 7807",
    "sg:postcode":"11219",
    "sg:province":"NY",
    "sg:tags":[
        "a",
        "specializing",
        "residential",
        "contractor",
        "re",
        "as",
        "operates"
    ],
    "wof:name":"Shtern Construction & Rmdlg",
    "wof:placetype":"venue"
},
  "geometry": {"coordinates":[-74.00045,40.633833],"type":"Point"}
}