{
  "type": "Feature",
  "properties": {
    "iso:country":"US",
    "sg:address":"1522 Neptune Ave",
    "sg:city":"Brooklyn",
    "sg:classifiers":[
        {
            "category":"Professional",
            "subcategory":"Business Services",
            "type":"Services"
        }
    ],
    "sg:phone":"+1 718 946 5299",
    "sg:postcode":"11224",
    "sg:province":"NY",
    "sg:tags":[
        "packaging"
    ],
    "wof:name":"Neptune Shipping Inc",
    "wof:placetype":"venue"
},
  "geometry": {"coordinates":[-73.983958,40.579002],"type":"Point"}
}