{
  "type": "Feature",
  "properties": {
    "addr:full":"6 Overlook Ln Plainview NY 11803",
    "addr:housenumber":"6",
    "addr:postcode":"11803",
    "addr:street":"Overlook Ln",
    "iso:country":"US",
    "sg:address":"6 Overlook Ln",
    "sg:city":"Plainview",
    "sg:classifiers":[
        {
            "category":"Retail",
            "subcategory":"Portrait Studio",
            "type":"Services"
        }
    ],
    "sg:phone":"+1 516 937 0100",
    "sg:postcode":"11803",
    "sg:province":"NY",
    "sg:tags":[
        "photographer",
        "photography",
        "videography"
    ],
    "sg:website":"http://www.jardinstudio.com",
    "wof:name":"Jardin International Video & P",
    "wof:placetype":"venue"
},
  "geometry": {"coordinates":[-73.470253,40.781311],"type":"Point"}
}