{
  "type": "Feature",
  "properties": {
    "addr:full":"40 Scout Rd Gansevoort NY 12831",
    "addr:housenumber":"40",
    "addr:postcode":"12831",
    "addr:street":"Scout Rd",
    "iso:country":"US",
    "sg:address":"40 Scout Rd",
    "sg:city":"Gansevoort",
    "sg:classifiers":[
        {
            "category":"Wholesale",
            "subcategory":"Hardware",
            "type":"Manufacturing & Wholesale Goods"
        }
    ],
    "sg:phone":"+1 518 587 9885",
    "sg:postcode":"12831",
    "sg:province":"NY",
    "wof:name":"Ruud Central AC & Htg",
    "wof:placetype":"venue"
},
  "geometry": {"coordinates":[-73.69080200000001,43.152366],"type":"Point"}
}