{
  "type": "Feature",
  "properties": {
    "addr:full":"2983 Long Beach Rd Oceanside NY 11572",
    "addr:housenumber":"2983",
    "addr:postcode":"11572",
    "addr:street":"Long Beach Rd",
    "iso:country":"US",
    "sg:address":"2983 Long Beach Rd",
    "sg:city":"Oceanside",
    "sg:classifiers":[
        {
            "category":"Health Services",
            "subcategory":"Health Practitioner",
            "type":"Services"
        }
    ],
    "sg:phone":"+1 516 536 0620",
    "sg:postcode":"11572",
    "sg:province":"NY",
    "sg:tags":[
        "psychologist"
    ],
    "wof:name":"American Sleep Apnea Corp",
    "wof:placetype":"venue"
},
  "geometry": {"coordinates":[-73.639966,40.638114],"type":"Point"}
}