{
  "type": "Feature",
  "properties": {
    "iso:country":"US",
    "sg:address":"2335 Bath Ave",
    "sg:city":"Brooklyn",
    "sg:classifiers":[
        {
            "category":"Autos & Motor Vehicles",
            "subcategory":"Automobile Sales",
            "type":"Retail Goods"
        }
    ],
    "sg:phone":"+1 718 946 1400",
    "sg:postcode":"11214",
    "sg:province":"NY",
    "sg:tags":[
        "car",
        "repair"
    ],
    "wof:name":"Flash Services",
    "wof:placetype":"venue"
},
  "geometry": {"coordinates":[-73.994202,40.5965],"type":"Point"}
}