{
  "type": "Feature",
  "properties": {
    "addr:full":"23 Crown St Kingston NY 12401",
    "addr:housenumber":"23",
    "addr:postcode":"12401",
    "addr:street":"Crown St",
    "iso:country":"US",
    "sg:address":"23 Crown St",
    "sg:city":"Kingston",
    "sg:classifiers":[
        {
            "category":"Professional",
            "subcategory":"Lawyer & Legal Services",
            "type":"Services"
        }
    ],
    "sg:phone":"+1 845 339 5550",
    "sg:postcode":"12401",
    "sg:province":"NY",
    "sg:tags":[
        "plan"
    ],
    "wof:name":"Murray Francis T",
    "wof:placetype":"venue"
},
  "geometry": {"coordinates":[-74.02089599999999,41.933166],"type":"Point"}
}