{
  "type": "Feature",
  "properties": {
    "iso:country":"US",
    "sg:address":"60 W 55 St",
    "sg:city":"New York",
    "sg:classifiers":[
        {
            "category":"Real Estate",
            "subcategory":"Real Estate Agent",
            "type":"Services"
        }
    ],
    "sg:phone":"+1 212 582 9273",
    "sg:postcode":"10019",
    "sg:province":"NY",
    "wof:name":"60 West 55 Street Corp",
    "wof:placetype":"venue"
},
  "geometry": {"coordinates":[-73.97669999999999,40.762138],"type":"Point"}
}