{
  "type": "Feature",
  "properties": {
    "addr:full":"218 E 14th St Manhattan NY 10003",
    "addr:housenumber":"218",
    "addr:postcode":"10003",
    "addr:street":"E 14Th St",
    "iso:country":"US",
    "sg:address":"218 E 14th St",
    "sg:city":"Manhattan",
    "sg:classifiers":[
        {
            "category":"Coffee & Tea",
            "type":"Food & Drink"
        },
        {
            "category":"Donuts",
            "subcategory":"None",
            "type":"Food & Drink"
        }
    ],
    "sg:phone":"+1 212 388 9992",
    "sg:postcode":"10003",
    "sg:province":"NY",
    "sg:website":"www.dunkindonuts.com/",
    "wof:name":"Dunkin Donuts",
    "wof:placetype":"venue"
},
  "geometry": {"coordinates":[-73.98641000000001,40.732814],"type":"Point"}
}