{
  "type": "Feature",
  "properties": {
    "iso:country":"US",
    "sg:address":"4085 State Hwy 31",
    "sg:city":"Canastota",
    "sg:classifiers":[
        {
            "category":"Building & Trades",
            "subcategory":"Landscaping Services",
            "type":"Services"
        }
    ],
    "sg:phone":"+1 315 363 9529",
    "sg:postcode":"13032",
    "sg:province":"NY",
    "wof:name":"Leggett Tree Servicee",
    "wof:placetype":"venue"
},
  "geometry": {"coordinates":[-75.726669,43.154504],"type":"Point"}
}