{
  "type": "Feature",
  "properties": {
    "addr:full":"10817 Liberty Ave South Richmond Hill NY 11419",
    "addr:housenumber":"10817",
    "addr:postcode":"11419",
    "addr:street":"Liberty Ave South",
    "iso:country":"US",
    "sg:address":"10817 Liberty Ave",
    "sg:city":"South Richmond Hill",
    "sg:classifiers":[
        {
            "category":"Deli",
            "type":"Food & Drink"
        }
    ],
    "sg:menulink":"http://www.allmenus.com/ny/queens/51409-hot-on-the-spot-roti-shop-and-restaurant/menu/",
    "sg:phone":"+1 718 322 3903",
    "sg:postcode":"11419",
    "sg:province":"NY",
    "sg:tags":[
        "american"
    ],
    "wof:name":"Hot On The Spot Roti Shop And Restaurant",
    "wof:placetype":"venue"
},
  "geometry": {"coordinates":[-73.83295099999999,40.684028],"type":"Point"}
}