{
  "type": "Feature",
  "properties": {
    "iso:country":"US",
    "sg:address":"257 Riverside Dr",
    "sg:city":"Johnson City",
    "sg:classifiers":[
        {
            "category":"Shopping",
            "subcategory":"Gifts & Souvenirs",
            "type":"Retail Goods"
        }
    ],
    "sg:phone":"+1 607 770 9030",
    "sg:postcode":"13790",
    "sg:province":"NY",
    "sg:tags":[
        "cards",
        "greeting"
    ],
    "wof:name":"Tracy's LTD",
    "wof:placetype":"venue"
},
  "geometry": {"coordinates":[-75.957902,42.099916],"type":"Point"}
}