{
  "type": "Feature",
  "properties": {
    "addr:full":"534 Abbott Rd Buffalo NY 14220",
    "addr:housenumber":"534",
    "addr:postcode":"14220",
    "addr:street":"Abbott Rd",
    "iso:country":"US",
    "sg:address":"534 Abbott Rd",
    "sg:city":"Buffalo",
    "sg:classifiers":[
        {
            "category":"Health Services",
            "subcategory":"Doctor",
            "type":"Services"
        }
    ],
    "sg:phone":"+1 716 822 8078",
    "sg:postcode":"14220",
    "sg:province":"NY",
    "wof:name":"Bhattacharyya Dr JK",
    "wof:placetype":"venue"
},
  "geometry": {"coordinates":[-78.813318,42.84915],"type":"Point"}
}