{
  "type": "Feature",
  "properties": {
    "addr:full":"6 W 32 St New York NY 10001",
    "addr:housenumber":"6",
    "addr:postcode":"10001",
    "addr:street":"W 32 St",
    "iso:country":"US",
    "sg:address":"6 W 32 St",
    "sg:city":"New York",
    "sg:classifiers":[
        {
            "category":"Real Estate",
            "subcategory":"Real Estate Agent",
            "type":"Services"
        }
    ],
    "sg:phone":"+1 212 947 6363",
    "sg:postcode":"10001",
    "sg:province":"NY",
    "wof:name":"Helaina Properties LLC",
    "wof:placetype":"venue"
},
  "geometry": {"coordinates":[-73.988051,40.748133],"type":"Point"}
}