{
  "type": "Feature",
  "properties": {
    "iso:country":"US",
    "sg:address":"33 E 33 St",
    "sg:city":"New York",
    "sg:classifiers":[
        {
            "category":"Home & Garden",
            "subcategory":"Carpets & Floor Coverings",
            "type":"Retail Goods"
        }
    ],
    "sg:phone":"+1 212 779 4310",
    "sg:postcode":"10016",
    "sg:province":"NY",
    "sg:tags":[
        "dealer",
        "rug"
    ],
    "wof:name":"Nima Rugs & Antiques Inc",
    "wof:placetype":"venue"
},
  "geometry": {"coordinates":[-73.981898,40.746539],"type":"Point"}
}