{
  "type": "Feature",
  "properties": {
    "iso:country":"US",
    "sg:address":"255 East Dr",
    "sg:city":"Copiague",
    "sg:classifiers":[
        {
            "category":"Building & Trades",
            "subcategory":"Landscaping Services",
            "type":"Services"
        }
    ],
    "sg:phone":"+1 631 842 6746",
    "sg:postcode":"11726",
    "sg:province":"NY",
    "wof:name":"Hollywood Star Landscaping",
    "wof:placetype":"venue"
},
  "geometry": {"coordinates":[-73.390434,40.665456],"type":"Point"}
}