{
  "type": "Feature",
  "properties": {
    "iso:country":"US",
    "sg:address":"218 Cleveland Dr",
    "sg:city":"Croton On Hudson",
    "sg:classifiers":[
        {
            "category":"Health Services",
            "subcategory":"Health Practitioner",
            "type":"Services"
        }
    ],
    "sg:phone":"+1 914 271 1276",
    "sg:postcode":"10520",
    "sg:province":"NY",
    "sg:tags":[
        "psychologist"
    ],
    "wof:name":"Womens Counseling Assoc",
    "wof:placetype":"venue"
},
  "geometry": {"coordinates":[-73.87263299999999,41.213235],"type":"Point"}
}