{
  "type": "Feature",
  "properties": {
    "addr:full":"71 Cleveland Ave Massapequa NY 11758",
    "addr:housenumber":"71",
    "addr:postcode":"11758",
    "addr:street":"Cleveland Ave",
    "iso:country":"US",
    "sg:address":"71 Cleveland Ave",
    "sg:city":"Massapequa",
    "sg:classifiers":[
        {
            "category":"Arts & Performance",
            "subcategory":"Theater",
            "type":"Entertainment"
        }
    ],
    "sg:phone":"+1 516 541 5859",
    "sg:postcode":"11758",
    "sg:province":"NY",
    "sg:tags":[
        "band",
        "orchestra"
    ],
    "wof:name":"Niteflight",
    "wof:placetype":"venue"
},
  "geometry": {"coordinates":[-73.47255800000001,40.685093],"type":"Point"}
}