{
  "type": "Feature",
  "properties": {
    "addr:full":"540 Gidney Ave Newburgh NY 12550",
    "addr:housenumber":"540",
    "addr:postcode":"12550",
    "addr:street":"Gidney Ave",
    "iso:country":"US",
    "sg:address":"540 Gidney Ave",
    "sg:city":"Newburgh",
    "sg:classifiers":[
        {
            "category":"Professional",
            "subcategory":"Accounting & Tax Preparation",
            "type":"Services"
        }
    ],
    "sg:phone":"+1 845 566 0806",
    "sg:postcode":"12550",
    "sg:province":"NY",
    "sg:tags":[
        "bookkeeping",
        "return",
        "accountants-certified",
        "preparation-business",
        "public"
    ],
    "wof:name":"Gilman & Ciocia",
    "wof:placetype":"venue"
},
  "geometry": {"coordinates":[-74.030807,41.518681],"type":"Point"}
}