{
  "type": "Feature",
  "properties": {
    "iso:country":"US",
    "sg:address":"779 Brooklyn Ave",
    "sg:city":"Baldwin",
    "sg:classifiers":[
        {
            "category":"Restaurant",
            "type":"Food & Drink"
        }
    ],
    "sg:phone":"+1   ",
    "sg:postcode":"11510",
    "sg:province":"NY",
    "sg:tags":[
        "drinking",
        "eating"
    ],
    "wof:name":"Cafe Oasis",
    "wof:placetype":"venue"
},
  "geometry": {"coordinates":[-73.607668,40.656981],"type":"Point"}
}