{
  "type": "Feature",
  "properties": {
    "addr:full":"2415 Avenue U Brooklyn NY 11229",
    "addr:housenumber":"2415",
    "addr:postcode":"11229",
    "addr:street":"Avenue U",
    "iso:country":"US",
    "sg:address":"2415 Avenue U",
    "sg:city":"Brooklyn",
    "sg:classifiers":[
        {
            "category":"Health Services",
            "subcategory":"Dentist",
            "type":"Services"
        }
    ],
    "sg:phone":"+1 718 646 7030",
    "sg:postcode":"11229",
    "sg:province":"NY",
    "wof:name":"Sheinkman G V DDS",
    "wof:placetype":"venue"
},
  "geometry": {"coordinates":[-73.947463,40.599951],"type":"Point"}
}