{
  "type": "Feature",
  "properties": {
    "addr:full":"117 Wilson Ave Brooklyn NY 11237",
    "addr:housenumber":"117",
    "addr:postcode":"11237",
    "addr:street":"Wilson Ave",
    "iso:country":"US",
    "sg:address":"117 Wilson Ave",
    "sg:city":"Brooklyn",
    "sg:classifiers":[
        {
            "category":"Home & Garden",
            "subcategory":"Furniture",
            "type":"Retail Goods"
        }
    ],
    "sg:phone":"+1 718 821 5509",
    "sg:postcode":"11237",
    "sg:province":"NY",
    "sg:tags":[
        "store"
    ],
    "wof:name":"Kenya Furniture Corp",
    "wof:placetype":"venue"
},
  "geometry": {"coordinates":[-73.926226,40.70129],"type":"Point"}
}