{
  "type": "Feature",
  "properties": {
    "iso:country":"US",
    "sg:address":"8160 Wolcott Rd",
    "sg:city":"East Amherst",
    "sg:classifiers":[
        {
            "category":"Wholesale",
            "subcategory":"Construction Materials",
            "type":"Manufacturing & Wholesale Goods"
        }
    ],
    "sg:phone":"+1 716 741 4072",
    "sg:postcode":"14051",
    "sg:province":"NY",
    "sg:tags":[
        "shop",
        "mill"
    ],
    "wof:name":"Lawrence Corp",
    "wof:placetype":"venue"
},
  "geometry": {"coordinates":[-78.692059,43.058382],"type":"Point"}
}