{
  "type": "Feature",
  "properties": {
    "iso:country":"US",
    "sg:address":"24 Floral Ave",
    "sg:city":"Huntington",
    "sg:classifiers":[
        {
            "category":"Building & Trades",
            "subcategory":"Construction",
            "type":"Services"
        }
    ],
    "sg:phone":"+1 631 673 8301",
    "sg:postcode":"11743",
    "sg:province":"NY",
    "sg:tags":[
        "contractor"
    ],
    "wof:name":"T P Farrell Home Builders",
    "wof:placetype":"venue"
},
  "geometry": {"coordinates":[-73.364531,40.828959],"type":"Point"}
}