{
  "type": "Feature",
  "properties": {
    "addr:full":"250 3rd St Troy NY 12180",
    "addr:housenumber":"250",
    "addr:postcode":"12180",
    "addr:street":"3Rd St",
    "iso:country":"US",
    "sg:address":"250 3rd St",
    "sg:city":"Troy",
    "sg:classifiers":[
        {
            "category":"Shopping",
            "subcategory":"Gifts & Souvenirs",
            "type":"Retail Goods"
        }
    ],
    "sg:phone":"+1 518 272 0042",
    "sg:postcode":"12180",
    "sg:province":"NY",
    "sg:tags":[
        "shop"
    ],
    "wof:name":"Gifts Gadgets & More",
    "wof:placetype":"venue"
},
  "geometry": {"coordinates":[-73.692159,42.722662],"type":"Point"}
}