{
  "type": "Feature",
  "properties": {
    "iso:country":"US",
    "sg:address":"5381 Kings Hwy",
    "sg:city":"Brooklyn",
    "sg:classifiers":[
        {
            "category":"Banks & Credit Unions",
            "subcategory":"Financial Services",
            "type":"Services"
        }
    ],
    "sg:phone":"+1 718 451 1046",
    "sg:postcode":"11203",
    "sg:province":"NY",
    "sg:tags":[
        "company",
        "holding"
    ],
    "wof:name":"Clareden Holding Co Inc",
    "wof:placetype":"venue"
},
  "geometry": {"coordinates":[-73.925871,40.63865],"type":"Point"}
}