{
  "type": "Feature",
  "properties": {
    "addr:full":"1030 Sheridan Ave Bronx NY 10456",
    "addr:housenumber":"1030",
    "addr:postcode":"10456",
    "addr:street":"Sheridan Ave",
    "iso:country":"US",
    "sg:address":"1030 Sheridan Ave",
    "sg:city":"Bronx",
    "sg:classifiers":[
        {
            "category":"Professional",
            "subcategory":"Management & Consulting",
            "type":"Services"
        }
    ],
    "sg:phone":"+1 718 410 9009",
    "sg:postcode":"10456",
    "sg:province":"NY",
    "wof:name":"Acm Management Corp",
    "wof:placetype":"venue"
},
  "geometry": {"coordinates":[-73.919096,40.829805],"type":"Point"}
}