{
  "type": "Feature",
  "properties": {
    "iso:country":"US",
    "sg:address":"9 South St",
    "sg:city":"Marathon",
    "sg:classifiers":[
        {
            "category":"Manufacturing",
            "subcategory":"Tools & Machinery",
            "type":"Manufacturing & Wholesale Goods"
        },
        {
            "category":"Industrial Area",
            "type":"Public Place"
        }
    ],
    "sg:phone":"+1 607 849 4385",
    "sg:postcode":"13803",
    "sg:province":"NY",
    "sg:tags":[
        "repair",
        "equipment-repairing",
        "machinery-rebuild"
    ],
    "wof:name":"Mobile Mechanics",
    "wof:placetype":"venue"
},
  "geometry": {"coordinates":[-76.03438800000001,42.435772],"type":"Point"}
}