{
  "type": "Feature",
  "properties": {
    "iso:country":"US",
    "sg:address":"340 State Hwy 37",
    "sg:city":"Hogansburg",
    "sg:classifiers":[
        {
            "category":"Autos & Motor Vehicles",
            "subcategory":"Fuel & Gas Station",
            "type":"Retail Goods"
        }
    ],
    "sg:phone":"+1 518 358 3165",
    "sg:postcode":"13655",
    "sg:province":"NY",
    "sg:tags":[
        "oil"
    ],
    "wof:name":"Jock's Gas Station",
    "wof:placetype":"venue"
},
  "geometry": {"coordinates":[-74.69861299999999,44.978048],"type":"Point"}
}