{
  "type": "Feature",
  "properties": {
    "iso:country":"US",
    "sg:address":"40 E 52 St",
    "sg:city":"New York",
    "sg:classifiers":[
        {
            "category":"Organizations",
            "subcategory":"Community Association",
            "type":"Services"
        }
    ],
    "sg:phone":"+1 212 421 1367",
    "sg:postcode":"10022",
    "sg:province":"NY",
    "sg:tags":[
        "club"
    ],
    "wof:name":"Bridgehampton Polo Club Inc",
    "wof:placetype":"venue"
},
  "geometry": {"coordinates":[-73.973314,40.758483],"type":"Point"}
}