{
  "type": "Feature",
  "properties": {
    "iso:country":"US",
    "sg:address":"139 E 35 St",
    "sg:city":"New York",
    "sg:classifiers":[
        {
            "category":"Professional",
            "subcategory":"Management & Consulting",
            "type":"Services"
        }
    ],
    "sg:phone":"+1 212 972 1750",
    "sg:postcode":"10016",
    "sg:province":"NY",
    "sg:tags":[
        "counselor",
        "public",
        "relations"
    ],
    "wof:name":"Elaine Siegel Assoc",
    "wof:placetype":"venue"
},
  "geometry": {"coordinates":[-73.97823,40.746643],"type":"Point"}
}