{
  "type": "Feature",
  "properties": {
    "addr:full":"70 Western Hwy S Tappan NY 10983",
    "addr:housenumber":"70",
    "addr:postcode":"10983",
    "addr:street":"Western Hwy S",
    "iso:country":"US",
    "sg:address":"70 Western Hwy S",
    "sg:city":"Tappan",
    "sg:classifiers":[
        {
            "category":"Food & Beverages",
            "subcategory":"Groceries & Convenience Stores",
            "type":"Retail Goods"
        }
    ],
    "sg:phone":"+1   ",
    "sg:postcode":"10983",
    "sg:province":"NY",
    "wof:name":"Fusion Food Corp",
    "wof:placetype":"venue"
},
  "geometry": {"coordinates":[-73.95231699999999,41.024458],"type":"Point"}
}