{
  "type": "Feature",
  "properties": {
    "addr:full":"165 N Village Ave Ste 204 Rockville Centre NY 11570",
    "addr:housenumber":"165",
    "addr:postcode":"11570",
    "addr:street":"N Village Ave Ste 204",
    "iso:country":"US",
    "sg:address":"165 N Village Ave Ste 204",
    "sg:city":"Rockville Centre",
    "sg:classifiers":[
        {
            "category":"Health Services",
            "subcategory":"Doctor",
            "type":"Services"
        },
        {
            "category":"Personal",
            "subcategory":"Adult",
            "type":"Services"
        }
    ],
    "sg:phone":"+1 516 764 5380",
    "sg:postcode":"11570",
    "sg:province":"NY",
    "sg:tags":[
        "midwife"
    ],
    "wof:name":"Blinderman Arnelle Heim MD",
    "wof:placetype":"venue"
},
  "geometry": {"coordinates":[-73.648399,40.6623],"type":"Point"}
}