{
  "type": "Feature",
  "properties": {
    "addr:full":"15 Broad Street Suite 912 New York NY 10005",
    "addr:housenumber":"15;912",
    "addr:postcode":"10005",
    "addr:street":"Broad Street Suite",
    "iso:country":"US",
    "sg:address":"15 Broad Street Suite 912",
    "sg:city":"New York",
    "sg:classifiers":[
        {
            "category":"Professional",
            "subcategory":"Computer Services",
            "type":"Services"
        }
    ],
    "sg:phone":"+1 646 485 5267",
    "sg:postcode":"10005",
    "sg:province":"NY",
    "sg:website":"http://www.plastyc.com/",
    "wof:name":"Plastyc",
    "wof:placetype":"venue"
},
  "geometry": {"coordinates":[-74.010819,40.706897],"type":"Point"}
}