{
  "type": "Feature",
  "properties": {
    "iso:country":"US",
    "sg:address":"240 Madison Ave",
    "sg:city":"New York",
    "sg:classifiers":[
        {
            "category":"Professional",
            "subcategory":"Lawyer & Legal Services",
            "type":"Services"
        }
    ],
    "sg:phone":"+1 212 557 7747",
    "sg:postcode":"10016",
    "sg:province":"NY",
    "sg:tags":[
        "attorney"
    ],
    "wof:name":"Depetris & Bachrach LLP",
    "wof:placetype":"venue"
},
  "geometry": {"coordinates":[-73.98138299999999,40.749968],"type":"Point"}
}