{
  "type": "Feature",
  "properties": {
    "iso:country":"US",
    "sg:address":"1470 Bedford Ave",
    "sg:city":"Brooklyn",
    "sg:classifiers":[
        {
            "category":"Organizations",
            "subcategory":"Religious Organization",
            "type":"Services"
        }
    ],
    "sg:phone":"+1 718 636 8074",
    "sg:postcode":"11216",
    "sg:province":"NY",
    "sg:tags":[
        "clergy"
    ],
    "wof:name":"Ezell Brown",
    "wof:placetype":"venue"
},
  "geometry": {"coordinates":[-73.95420300000001,40.673449],"type":"Point"}
}