{
  "type": "Feature",
  "properties": {
    "iso:country":"US",
    "sg:address":"60 Halstead Ave",
    "sg:city":"Harrison",
    "sg:classifiers":[
        {
            "category":"Restaurant",
            "type":"Food & Drink"
        }
    ],
    "sg:menulink":"http://www.allmenus.com/ny/harrison/146611-al-dente-trattoria/menu/",
    "sg:phone":"+1 914 835 2535",
    "sg:postcode":"10528",
    "sg:province":"NY",
    "sg:tags":[
        "italian"
    ],
    "wof:name":"Al Dente Trattoria",
    "wof:placetype":"venue"
},
  "geometry": {"coordinates":[-73.72151599999999,40.963195],"type":"Point"}
}