{
  "type": "Feature",
  "properties": {
    "iso:country":"US",
    "sg:address":"432 Park Ave S",
    "sg:city":"New York",
    "sg:classifiers":[
        {
            "category":"Wholesale",
            "subcategory":"Stationery",
            "type":"Manufacturing & Wholesale Goods"
        }
    ],
    "sg:phone":"+1 212 683 8967",
    "sg:postcode":"10016",
    "sg:province":"NY",
    "sg:tags":[
        "business",
        "form",
        "system"
    ],
    "wof:name":"City Data Products Inc",
    "wof:placetype":"venue"
},
  "geometry": {"coordinates":[-73.983413,40.744289],"type":"Point"}
}