{
  "type": "Feature",
  "properties": {
    "iso:country":"US",
    "sg:address":"191 W Islip Rd",
    "sg:city":"West Islip",
    "sg:classifiers":[
        {
            "category":"Bars & Pubs",
            "type":"Food & Drink"
        }
    ],
    "sg:phone":"+1   ",
    "sg:postcode":"11795",
    "sg:province":"NY",
    "sg:tags":[
        "drinking"
    ],
    "wof:name":"Prospect Place",
    "wof:placetype":"venue"
},
  "geometry": {"coordinates":[-73.316807,40.694025],"type":"Point"}
}