{
  "type": "Feature",
  "properties": {
    "addr:full":"2266 Cropsey Ave Brooklyn NY 11214",
    "addr:housenumber":"2266",
    "addr:postcode":"11214",
    "addr:street":"Cropsey Ave",
    "iso:country":"US",
    "sg:address":"2266 Cropsey Ave",
    "sg:city":"Brooklyn",
    "sg:classifiers":[
        {
            "category":"Health Services",
            "subcategory":"Nursing And Care Facility",
            "type":"Services"
        }
    ],
    "sg:phone":"+1 718 266 6100",
    "sg:postcode":"11214",
    "sg:province":"NY",
    "sg:tags":[
        "home",
        "skilled",
        "convalescent"
    ],
    "wof:name":"Sephardic Home For Aged Inc",
    "wof:placetype":"venue"
},
  "geometry": {"coordinates":[-73.99691799999999,40.595721],"type":"Point"}
}