{
  "type": "Feature",
  "properties": {
    "addr:full":"1879 Putnam Ave Ridgewood NY 11385",
    "addr:housenumber":"1879",
    "addr:postcode":"11385",
    "addr:street":"Putnam Ave",
    "iso:country":"US",
    "sg:address":"1879 Putnam Ave",
    "sg:city":"Ridgewood",
    "sg:classifiers":[
        {
            "category":"Shopping",
            "subcategory":"Discount & Variety Stores",
            "type":"Retail Goods"
        }
    ],
    "sg:phone":"+1   ",
    "sg:postcode":"11385",
    "sg:province":"NY",
    "sg:tags":[
        "merchandise",
        "general"
    ],
    "wof:name":"Kesshin Inc",
    "wof:placetype":"venue"
},
  "geometry": {"coordinates":[-73.904087,40.703109],"type":"Point"}
}