{
  "type": "Feature",
  "properties": {
    "iso:country":"US",
    "sg:address":"1995 University Ave",
    "sg:city":"Bronx",
    "sg:classifiers":[
        {
            "category":"Shopping",
            "subcategory":"Clothing, Apparel, & Fashions",
            "type":"Retail Goods"
        }
    ],
    "sg:phone":"+1 718 583 3309",
    "sg:postcode":"10453",
    "sg:province":"NY",
    "wof:name":"Pedro Donde Fashion",
    "wof:placetype":"venue"
},
  "geometry": {"coordinates":[-73.914254,40.851155],"type":"Point"}
}