{
  "type": "Feature",
  "properties": {
    "addr:full":"7 W 51st St New York NY 10019",
    "addr:housenumber":"7",
    "addr:postcode":"10019",
    "addr:street":"W 51St St",
    "iso:country":"US",
    "sg:address":"7 W 51st St",
    "sg:city":"New York",
    "sg:classifiers":[
        {
            "category":"Health Services",
            "subcategory":"Doctor",
            "type":"Services"
        }
    ],
    "sg:phone":"+1 212 245 7900",
    "sg:postcode":"10019",
    "sg:province":"NY",
    "wof:name":"Allen Douglas Doctor D O Pc",
    "wof:placetype":"venue"
},
  "geometry": {"coordinates":[-73.977278,40.759556],"type":"Point"}
}