{
  "type": "Feature",
  "properties": {
    "addr:full":"708 Long Pond Rd Mahopac NY 10541",
    "addr:housenumber":"708",
    "addr:postcode":"10541",
    "addr:street":"Long Pond Rd",
    "iso:country":"US",
    "sg:address":"708 Long Pond Rd",
    "sg:city":"Mahopac",
    "sg:classifiers":[
        {
            "category":"Professional",
            "type":"Services"
        }
    ],
    "sg:phone":"+1 845 621 1585",
    "sg:postcode":"10541",
    "sg:province":"NY",
    "sg:tags":[
        "establishment"
    ],
    "wof:name":"Moonstone",
    "wof:placetype":"venue"
},
  "geometry": {"coordinates":[-73.73123099999999,41.413775],"type":"Point"}
}