{
  "type": "Feature",
  "properties": {
    "addr:full":"79 Broadway Newburgh NY 12550",
    "addr:housenumber":"79",
    "addr:postcode":"12550",
    "addr:street":"Broadway",
    "iso:country":"US",
    "sg:address":"79 Broadway",
    "sg:city":"Newburgh",
    "sg:classifiers":[
        {
            "category":"Real Estate",
            "subcategory":"Developer",
            "type":"Services"
        }
    ],
    "sg:phone":"+1 845 565 6999",
    "sg:postcode":"12550",
    "sg:province":"NY",
    "wof:name":"Mesh Realty Group",
    "wof:placetype":"venue"
},
  "geometry": {"coordinates":[-74.00854099999999,41.499839],"type":"Point"}
}