{
  "type": "Feature",
  "properties": {
    "addr:full":"338 White Pond Rd Stormville NY 12582",
    "addr:housenumber":"338",
    "addr:postcode":"12582",
    "addr:street":"White Pond Rd",
    "iso:country":"US",
    "sg:address":"338 White Pond Rd",
    "sg:city":"Stormville",
    "sg:classifiers":[
        {
            "category":"Building & Trades",
            "subcategory":"Electrical",
            "type":"Services"
        }
    ],
    "sg:phone":"+1 845 878 3342",
    "sg:postcode":"12582",
    "sg:province":"NY",
    "sg:tags":[
        "electrical",
        "contractor"
    ],
    "wof:name":"Solutions",
    "wof:placetype":"venue"
},
  "geometry": {"coordinates":[-73.72032400000001,41.508439],"type":"Point"}
}