{
  "type": "Feature",
  "properties": {
    "addr:full":"105 W Main St Macedon NY 14502",
    "addr:housenumber":"105",
    "addr:postcode":"14502",
    "addr:street":"W Main St",
    "iso:country":"US",
    "sg:address":"105 W Main St",
    "sg:city":"Macedon",
    "sg:classifiers":[
        {
            "category":"Retail",
            "subcategory":"Auto Repair",
            "type":"Services"
        }
    ],
    "sg:phone":"+1 315 986 4451",
    "sg:postcode":"14502",
    "sg:province":"NY",
    "sg:tags":[
        "automobile",
        "electric"
    ],
    "sg:website":"www.northstarautoelectric.com",
    "wof:name":"North Star Auto Electric Inc",
    "wof:placetype":"venue"
},
  "geometry": {"coordinates":[-77.300518,43.068577],"type":"Point"}
}