{
  "type": "Feature",
  "properties": {
    "iso:country":"US",
    "sg:address":"62 William St",
    "sg:city":"New York",
    "sg:classifiers":[
        {
            "category":"Wholesale",
            "subcategory":"Electrical",
            "type":"Manufacturing & Wholesale Goods"
        }
    ],
    "sg:phone":"+1 212 248 1845",
    "sg:postcode":"10005",
    "sg:province":"NY",
    "sg:tags":[
        "control",
        "security",
        "system"
    ],
    "wof:name":"Burns International Security",
    "wof:placetype":"venue"
},
  "geometry": {"coordinates":[-74.008743,40.707065],"type":"Point"}
}