{
  "type": "Feature",
  "properties": {
    "addr:full":"340 Pelham Rd New Rochelle NY 10805",
    "addr:housenumber":"340",
    "addr:postcode":"10805",
    "addr:street":"Pelham Rd",
    "iso:country":"US",
    "sg:address":"340 Pelham Rd",
    "sg:city":"New Rochelle",
    "sg:classifiers":[
        {
            "category":"Restaurant",
            "type":"Food & Drink"
        }
    ],
    "sg:phone":"+1 914 632 5888",
    "sg:postcode":"10805",
    "sg:province":"NY",
    "wof:name":"Tasty Kitchen",
    "wof:placetype":"venue"
},
  "geometry": {"coordinates":[-73.778009,40.898633],"type":"Point"}
}