{
  "type": "Feature",
  "properties": {
    "iso:country":"US",
    "sg:address":"2 Brewster Rd",
    "sg:city":"Scarsdale",
    "sg:classifiers":[
        {
            "category":"Government",
            "subcategory":"Office",
            "type":"Public Place"
        }
    ],
    "sg:phone":"+1 914 721 2438",
    "sg:postcode":"10583",
    "sg:province":"NY",
    "sg:tags":[
        "educational",
        "program",
        "administrative"
    ],
    "wof:name":"Scarsdales Public Schools",
    "wof:placetype":"venue"
},
  "geometry": {"coordinates":[-73.794084,40.995674],"type":"Point"}
}