{
  "type": "Feature",
  "properties": {
    "iso:country":"US",
    "sg:address":"65 Main St",
    "sg:city":"Brewster",
    "sg:classifiers":[
        {
            "category":"Shopping",
            "subcategory":"Used Merchandise",
            "type":"Retail Goods"
        }
    ],
    "sg:phone":"+1   ",
    "sg:postcode":"10509",
    "sg:province":"NY",
    "wof:name":"Eagle Eye Thrift Shop",
    "wof:placetype":"venue"
},
  "geometry": {"coordinates":[-73.618362,41.394321],"type":"Point"}
}