{
  "type": "Feature",
  "properties": {
    "iso:country":"US",
    "sg:address":"637 State St",
    "sg:city":"Ogdensburg",
    "sg:classifiers":[
        {
            "category":"Food & Beverages",
            "subcategory":"Groceries & Convenience Stores",
            "type":"Retail Goods"
        }
    ],
    "sg:phone":"+1   ",
    "sg:postcode":"13669",
    "sg:province":"NY",
    "wof:name":"Stewarts Shops Corp",
    "wof:placetype":"venue"
},
  "geometry": {"coordinates":[-75.489867,44.693929],"type":"Point"}
}