{
  "type": "Feature",
  "properties": {
    "addr:full":"1717 US Hwy 6 Carmel NY 10512",
    "addr:housenumber":"1717",
    "addr:postcode":"10512",
    "addr:street":"Us Hwy 6",
    "iso:country":"US",
    "sg:address":"1717 US Hwy 6",
    "sg:city":"Carmel",
    "sg:classifiers":[
        {
            "category":"Communications",
            "subcategory":"Film & Video Production",
            "type":"Services"
        }
    ],
    "sg:phone":"+1 845 225 5666",
    "sg:postcode":"10512",
    "sg:province":"NY",
    "sg:tags":[
        "animated"
    ],
    "wof:name":"Peach Nova Productions LLC",
    "wof:placetype":"venue"
},
  "geometry": {"coordinates":[-73.672387,41.416776],"type":"Point"}
}