{
  "type": "Feature",
  "properties": {
    "addr:full":"263 Howe Rd Lake Luzerne NY 12846",
    "addr:housenumber":"263",
    "addr:postcode":"12846",
    "addr:street":"Howe Rd",
    "iso:country":"US",
    "sg:address":"263 Howe Rd",
    "sg:city":"Lake Luzerne",
    "sg:classifiers":[
        {
            "category":"Shopping",
            "subcategory":"Gifts & Souvenirs",
            "type":"Retail Goods"
        }
    ],
    "sg:phone":"+1 518 696 4778",
    "sg:postcode":"12846",
    "sg:province":"NY",
    "sg:tags":[
        "shop"
    ],
    "wof:name":"Carroll's Gift Corner",
    "wof:placetype":"venue"
},
  "geometry": {"coordinates":[-73.821293,43.342166],"type":"Point"}
}