{
  "type": "Feature",
  "properties": {
    "addr:full":"77 S Ireland Pl Amityville NY 11701",
    "addr:housenumber":"77",
    "addr:postcode":"11701",
    "addr:street":"S Ireland Pl",
    "iso:country":"US",
    "sg:address":"77 S Ireland Pl",
    "sg:city":"Amityville",
    "sg:classifiers":[
        {
            "category":"Wholesale",
            "subcategory":"Tobacco Products",
            "type":"Manufacturing & Wholesale Goods"
        }
    ],
    "sg:phone":"+1 631 598 4786",
    "sg:postcode":"11701",
    "sg:province":"NY",
    "wof:name":"Tobacco Tycoons Inc",
    "wof:placetype":"venue"
},
  "geometry": {"coordinates":[-73.418234,40.666892],"type":"Point"}
}