{
  "type": "Feature",
  "properties": {
    "addr:full":"1127 Eastern Pkwy Brooklyn NY 11213",
    "addr:housenumber":"1127",
    "addr:postcode":"11213",
    "addr:street":"Eastern Pkwy",
    "iso:country":"US",
    "sg:address":"1127 Eastern Pkwy",
    "sg:city":"Brooklyn",
    "sg:classifiers":[
        {
            "category":"Professional",
            "subcategory":"Accounting & Tax Preparation",
            "type":"Services"
        }
    ],
    "sg:phone":"+1 718 774 0985",
    "sg:postcode":"11213",
    "sg:province":"NY",
    "sg:tags":[
        "return",
        "filing"
    ],
    "wof:name":"Zirin Tax Co",
    "wof:placetype":"venue"
},
  "geometry": {"coordinates":[-73.92839600000001,40.668725],"type":"Point"}
}