{
  "type": "Feature",
  "properties": {
    "addr:full":"720 5th Ave Lbby New York NY 10019",
    "addr:housenumber":"720",
    "addr:postcode":"10019",
    "addr:street":"5Th Ave",
    "iso:country":"US",
    "sg:address":"720 5th Ave Lbby",
    "sg:city":"New York",
    "sg:classifiers":[
        {
            "category":"Building & Trades",
            "subcategory":"Locksmith",
            "type":"Services"
        }
    ],
    "sg:phone":"+1 917 237 7975",
    "sg:postcode":"10019",
    "sg:province":"NY",
    "sg:tags":[
        "key"
    ],
    "wof:name":"A Locksmith A Emergency 24 Hour",
    "wof:placetype":"venue"
},
  "geometry": {"coordinates":[-73.985901,40.765499],"type":"Point"}
}