{
  "type": "Feature",
  "properties": {
    "addr:full":"23 Harding Pl Huntington Sta NY 11746",
    "addr:housenumber":"23",
    "addr:postcode":"11746",
    "addr:street":"Harding Pl",
    "iso:country":"US",
    "sg:address":"23 Harding Pl",
    "sg:city":"Huntington Sta",
    "sg:classifiers":[
        {
            "category":"Education",
            "subcategory":"School",
            "type":"Public Place"
        }
    ],
    "sg:phone":"+1 631 425 5511",
    "sg:postcode":"11746",
    "sg:province":"NY",
    "wof:name":"Silas Wood Sixth Grade Ctr",
    "wof:placetype":"venue"
},
  "geometry": {"coordinates":[-73.402421,40.833049],"type":"Point"}
}