{
  "type": "Feature",
  "properties": {
    "iso:country":"US",
    "sg:address":"53 Main St",
    "sg:city":"Tarrytown",
    "sg:classifiers":[
        {
            "category":"Banks & Credit Unions",
            "subcategory":"Investment Brokerage",
            "type":"Services"
        },
        {
            "category":"Shopping",
            "subcategory":"Computers & Home Electronics",
            "type":"Retail Goods"
        }
    ],
    "sg:phone":"+1 914 631 6787",
    "sg:postcode":"10591",
    "sg:province":"NY",
    "sg:tags":[
        "dvd",
        "video",
        "tape",
        "sale",
        "dvds-rental"
    ],
    "wof:name":"Home Video",
    "wof:placetype":"venue"
},
  "geometry": {"coordinates":[-73.860546,41.076762],"type":"Point"}
}