{
  "type": "Feature",
  "properties": {
    "addr:full":"14 Main St Cattaraugus NY 14719",
    "addr:housenumber":"14",
    "addr:postcode":"14719",
    "addr:street":"Main St",
    "iso:country":"US",
    "sg:address":"14 Main St",
    "sg:city":"Cattaraugus",
    "sg:classifiers":[
        {
            "category":"Government",
            "subcategory":"Police Station",
            "type":"Public Place"
        }
    ],
    "sg:phone":"+1 716 257 9119",
    "sg:postcode":"14719",
    "sg:province":"NY",
    "sg:tags":[
        "department"
    ],
    "wof:name":"Cattaraugus Police Dept",
    "wof:placetype":"venue"
},
  "geometry": {"coordinates":[-78.868809,42.330048],"type":"Point"}
}