{
  "type": "Feature",
  "properties": {
    "addr:full":"35 Lewis Rd Akron NY 14001",
    "addr:housenumber":"35",
    "addr:postcode":"14001",
    "addr:street":"Lewis Rd",
    "iso:country":"US",
    "sg:address":"35 Lewis Rd",
    "sg:city":"Akron",
    "sg:classifiers":[
        {
            "category":"Government",
            "subcategory":"Post Office",
            "type":"Public Place"
        }
    ],
    "sg:phone":"+1 585 542 9952",
    "sg:postcode":"14001",
    "sg:province":"NY",
    "wof:name":"Newstead Memorial Post",
    "wof:placetype":"venue"
},
  "geometry": {"coordinates":[-78.506528,43.028081],"type":"Point"}
}