{
  "type": "Feature",
  "properties": {
    "iso:country":"US",
    "sg:address":"1113 State Route 17M",
    "sg:city":"Monroe",
    "sg:classifiers":[
        {
            "category":"Building & Trades",
            "subcategory":"Construction",
            "type":"Services"
        }
    ],
    "sg:phone":"+1 845 782 0308",
    "sg:postcode":"10950",
    "sg:province":"NY",
    "sg:tags":[
        "contractor"
    ],
    "wof:name":"AZ CONTRACTING",
    "wof:placetype":"venue"
},
  "geometry": {"coordinates":[-74.214494,41.344228],"type":"Point"}
}