{
  "type": "Feature",
  "properties": {
    "addr:full":"1193 E 19th St Brooklyn NY 11230",
    "addr:housenumber":"1193",
    "addr:postcode":"11230",
    "addr:street":"E 19Th St",
    "iso:country":"US",
    "sg:address":"1193 E 19th St",
    "sg:city":"Brooklyn",
    "sg:classifiers":[
        {
            "category":"Real Estate",
            "subcategory":"Developer",
            "type":"Services"
        }
    ],
    "sg:phone":"+1 718 377 6653",
    "sg:postcode":"11230",
    "sg:province":"NY",
    "wof:name":"K&K Development",
    "wof:placetype":"venue"
},
  "geometry": {"coordinates":[-73.956873,40.622621],"type":"Point"}
}