{
  "type": "Feature",
  "properties": {
    "addr:full":"581 Broadway New York NY 10012",
    "addr:housenumber":"581",
    "addr:postcode":"10012",
    "addr:street":"Broadway",
    "iso:country":"US",
    "sg:address":"581 Broadway",
    "sg:city":"New York",
    "sg:classifiers":[
        {
            "category":"Wholesale",
            "subcategory":"Apparel",
            "type":"Manufacturing & Wholesale Goods"
        }
    ],
    "sg:phone":"+1 212 226 7841",
    "sg:postcode":"10012",
    "sg:province":"NY",
    "sg:tags":[
        "hat"
    ],
    "wof:name":"Lord Shivas Properties LLC",
    "wof:placetype":"venue"
},
  "geometry": {"coordinates":[-73.997078,40.725094],"type":"Point"}
}