{
  "type": "Feature",
  "properties": {
    "addr:full":"94 3rd Ave New York NY 10003",
    "addr:housenumber":"94",
    "addr:postcode":"10003",
    "addr:street":"3Rd Ave",
    "iso:country":"US",
    "sg:address":"94 3rd Ave",
    "sg:city":"New York",
    "sg:classifiers":[
        {
            "category":"Food & Beverages",
            "subcategory":"Bakery",
            "type":"Retail Goods"
        }
    ],
    "sg:phone":"+1 212 253 2700",
    "sg:postcode":"10003",
    "sg:province":"NY",
    "sg:tags":[
        "sandwich"
    ],
    "sg:website":"99milestophillyeastvillage.com/",
    "wof:name":"99 Miles to Philly",
    "wof:placetype":"venue"
},
  "geometry": {"coordinates":[-73.987984,40.732197],"type":"Point"}
}