{
  "type": "Feature",
  "properties": {
    "addr:full":"17 Beechview Ave Jamestown NY 14701",
    "addr:housenumber":"17",
    "addr:postcode":"14701",
    "addr:street":"Beechview Ave",
    "iso:country":"US",
    "sg:address":"17 Beechview Ave",
    "sg:city":"Jamestown",
    "sg:classifiers":[
        {
            "category":"Communications",
            "subcategory":"Film & Video Production",
            "type":"Services"
        }
    ],
    "sg:phone":"+1   ",
    "sg:postcode":"14701",
    "sg:province":"NY",
    "sg:tags":[
        "motion"
    ],
    "wof:name":"Fifth Dimension Productions",
    "wof:placetype":"venue"
},
  "geometry": {"coordinates":[-79.233637,42.112385],"type":"Point"}
}