{
  "type": "Feature",
  "properties": {
    "addr:full":"584 3rd St Albany NY 12206",
    "addr:housenumber":"584",
    "addr:postcode":"12206",
    "addr:street":"3Rd St",
    "iso:country":"US",
    "sg:address":"584 3rd St",
    "sg:city":"Albany",
    "sg:classifiers":[
        {
            "category":"Government",
            "subcategory":"Office",
            "type":"Public Place"
        }
    ],
    "sg:phone":"+1 518 458 2533",
    "sg:postcode":"12206",
    "sg:province":"NY",
    "sg:tags":[
        "development",
        "housing",
        "education"
    ],
    "wof:name":"Soul Saving Ministries",
    "wof:placetype":"venue"
},
  "geometry": {"coordinates":[-73.77499,42.671509],"type":"Point"}
}