{
  "type": "Feature",
  "properties": {
    "addr:full":"429 W Delavan Ave Buffalo NY 14213",
    "addr:housenumber":"429",
    "addr:postcode":"14213",
    "addr:street":"W Delavan Ave",
    "iso:country":"US",
    "sg:address":"429 W Delavan Ave",
    "sg:city":"Buffalo",
    "sg:classifiers":[
        {
            "category":"Organizations",
            "subcategory":"Community Association",
            "type":"Services"
        }
    ],
    "sg:phone":"+1   ",
    "sg:postcode":"14213",
    "sg:province":"NY",
    "wof:name":"Western New York Hispanic",
    "wof:placetype":"venue"
},
  "geometry": {"coordinates":[-78.882515,42.922063],"type":"Point"}
}