{
  "type": "Feature",
  "properties": {
    "iso:country":"US",
    "sg:address":"1170 Ulster Ave",
    "sg:city":"Kingston",
    "sg:classifiers":[
        {
            "category":"Shopping",
            "subcategory":"Florist",
            "type":"Retail Goods"
        }
    ],
    "sg:phone":"+1   ",
    "sg:postcode":"12401",
    "sg:province":"NY",
    "sg:tags":[
        "shop",
        "gift"
    ],
    "wof:name":"Blooming Boutique Florist",
    "wof:placetype":"venue"
},
  "geometry": {"coordinates":[-73.989842,41.964372],"type":"Point"}
}