{
  "type": "Feature",
  "properties": {
    "addr:full":"2005 Merrick Rd Merrick NY 11566",
    "addr:housenumber":"2005",
    "addr:postcode":"11566",
    "addr:street":"Merrick Rd",
    "iso:country":"US",
    "sg:address":"2005 Merrick Rd",
    "sg:city":"Merrick",
    "sg:classifiers":[
        {
            "category":"Professional",
            "subcategory":"Advertising",
            "type":"Services"
        }
    ],
    "sg:phone":"+1 516 771 5556",
    "sg:postcode":"11566",
    "sg:province":"NY",
    "sg:tags":[
        "mailing",
        "shipping"
    ],
    "wof:name":"UPS Store",
    "wof:placetype":"venue"
},
  "geometry": {"coordinates":[-73.549573,40.656323],"type":"Point"}
}