{
  "type": "Feature",
  "properties": {
    "addr:full":"626 Wythe Pl Brooklyn NY 11211",
    "addr:housenumber":"626",
    "addr:postcode":"11211",
    "addr:street":"Wythe Pl",
    "iso:country":"US",
    "sg:address":"626 Wythe Pl",
    "sg:city":"Brooklyn",
    "sg:classifiers":[
        {
            "category":"Organizations",
            "subcategory":"Religious Organization",
            "type":"Services"
        }
    ],
    "sg:phone":"+1 718 387 8456",
    "sg:postcode":"11211",
    "sg:province":"NY",
    "sg:tags":[
        "clergy"
    ],
    "wof:name":"Naftuly Grunhut",
    "wof:placetype":"venue"
},
  "geometry": {"coordinates":[-73.96476,40.704655],"type":"Point"}
}