{
  "type": "Feature",
  "properties": {
    "iso:country":"US",
    "sg:address":"29 Rombout Rd",
    "sg:city":"Poughkeepsie",
    "sg:classifiers":[
        {
            "category":"Real Estate",
            "subcategory":"Real Estate Agent",
            "type":"Services"
        }
    ],
    "sg:phone":"+1 845 483 1001",
    "sg:postcode":"12603",
    "sg:province":"NY",
    "wof:name":"Freedom Properties LLC",
    "wof:placetype":"venue"
},
  "geometry": {"coordinates":[-73.835539,41.712391],"type":"Point"}
}