{
  "type": "Feature",
  "properties": {
    "addr:full":"297 Meeker Ave Brooklyn NY 11211",
    "addr:housenumber":"297",
    "addr:postcode":"11211",
    "addr:street":"Meeker Ave",
    "iso:country":"US",
    "sg:address":"297 Meeker Ave",
    "sg:city":"Brooklyn",
    "sg:classifiers":[
        {
            "category":"Building & Trades",
            "subcategory":"Construction",
            "type":"Services"
        }
    ],
    "sg:phone":"+1 718 388 1542",
    "sg:postcode":"11211",
    "sg:province":"NY",
    "sg:tags":[
        "general",
        "contractor"
    ],
    "wof:name":"Arcon Construction Co Ny Inc",
    "wof:placetype":"venue"
},
  "geometry": {"coordinates":[-73.9495,40.717155],"type":"Point"}
}