{
  "type": "Feature",
  "properties": {
    "addr:full":"201 E 42nd St New York NY 10017",
    "addr:housenumber":"201",
    "addr:postcode":"10017",
    "addr:street":"E 42Nd St",
    "iso:country":"US",
    "sg:address":"201 E 42nd St",
    "sg:city":"New York",
    "sg:classifiers":[
        {
            "category":"Communications",
            "subcategory":"News Services",
            "type":"Services"
        }
    ],
    "sg:phone":"+1   ",
    "sg:postcode":"10017",
    "sg:province":"NY",
    "sg:tags":[
        "syndicate"
    ],
    "wof:name":"Irna News Agency",
    "wof:placetype":"venue"
},
  "geometry": {"coordinates":[-73.97220299999999,40.749823],"type":"Point"}
}