{
  "type": "Feature",
  "properties": {
    "addr:full":"326 Amherst St Buffalo NY 14207",
    "addr:housenumber":"326",
    "addr:postcode":"14207",
    "addr:street":"Amherst St",
    "iso:country":"US",
    "sg:address":"326 Amherst St",
    "sg:city":"Buffalo",
    "sg:classifiers":[
        {
            "category":"Bars & Pubs",
            "type":"Food & Drink"
        }
    ],
    "sg:phone":"+1 716 874 7734",
    "sg:postcode":"14207",
    "sg:province":"NY",
    "sg:tags":[
        "drinking"
    ],
    "wof:name":"Sportsman's Tavern",
    "wof:placetype":"venue"
},
  "geometry": {"coordinates":[-78.891514,42.93762],"type":"Point"}
}