{
  "type": "Feature",
  "properties": {
    "addr:full":"108 Delaware Ave Buffalo NY 14202",
    "addr:housenumber":"108",
    "addr:postcode":"14202",
    "addr:street":"Delaware Ave",
    "iso:country":"US",
    "sg:address":"108 Delaware Ave",
    "sg:city":"Buffalo",
    "sg:classifiers":[
        {
            "category":"Professional",
            "subcategory":"Lawyer & Legal Services",
            "type":"Services"
        }
    ],
    "sg:phone":"+1 716 854 5200",
    "sg:postcode":"14202",
    "sg:province":"NY",
    "wof:name":"Borins Stel Snitzer Brownstein",
    "wof:placetype":"venue"
},
  "geometry": {"coordinates":[-78.87776700000001,42.887817],"type":"Point"}
}