{
  "type": "Feature",
  "properties": {
    "addr:full":"1034 Rogers Avenue Brooklyn NY 11226",
    "addr:housenumber":"1034",
    "addr:postcode":"11226",
    "addr:street":"Rogers Avenue",
    "iso:country":"US",
    "sg:address":"1034 Rogers Avenue",
    "sg:city":"Brooklyn",
    "sg:classifiers":[
        {
            "category":"Building & Trades",
            "subcategory":"Plumbing",
            "type":"Services"
        }
    ],
    "sg:phone":"+1 718 756 5200",
    "sg:postcode":"11226",
    "sg:province":"NY",
    "wof:name":"Dumont Plumbing & Heating Corporation",
    "wof:placetype":"venue"
},
  "geometry": {"coordinates":[-73.952003,40.644855],"type":"Point"}
}