{
  "type": "Feature",
  "properties": {
    "addr:full":"203 Lake St Elmira NY 14901",
    "addr:housenumber":"203",
    "addr:postcode":"14901",
    "addr:street":"Lake St",
    "iso:country":"US",
    "sg:address":"203 Lake St",
    "sg:city":"Elmira",
    "sg:classifiers":[
        {
            "category":"Government",
            "subcategory":"Court House",
            "type":"Public Place"
        }
    ],
    "sg:phone":"+1 607 737 2982",
    "sg:postcode":"14901",
    "sg:province":"NY",
    "sg:tags":[
        "county",
        "counsel"
    ],
    "wof:name":"Chemung County Attorney",
    "wof:placetype":"venue"
},
  "geometry": {"coordinates":[-76.80217,42.090566],"type":"Point"}
}