{
  "type": "Feature",
  "properties": {
    "addr:full":"127 Genesee St Oneida NY 13421",
    "addr:housenumber":"127",
    "addr:postcode":"13421",
    "addr:street":"Genesee St",
    "iso:country":"US",
    "sg:address":"127 Genesee St",
    "sg:city":"Oneida",
    "sg:classifiers":[
        {
            "category":"Restaurant",
            "type":"Food & Drink"
        }
    ],
    "sg:menulink":"http://www.allmenus.com/ny/oneida/151704-aw-restaurant/menu/",
    "sg:phone":"+1 315 366 0340",
    "sg:postcode":"13421",
    "sg:province":"NY",
    "sg:tags":[
        "burger",
        "american",
        "dog",
        "pub",
        "hot"
    ],
    "wof:name":"A&W Restaurant",
    "wof:placetype":"venue"
},
  "geometry": {"coordinates":[-75.643052,43.078904],"type":"Point"}
}