{
  "type": "Feature",
  "properties": {
    "addr:full":"16 Elan Ln Ronkonkoma NY 11779",
    "addr:housenumber":"16",
    "addr:postcode":"11779",
    "addr:street":"Elan Ln",
    "iso:country":"US",
    "sg:address":"16 Elan Ln",
    "sg:city":"Ronkonkoma",
    "sg:classifiers":[
        {
            "category":"Wholesale",
            "subcategory":"Electrical",
            "type":"Manufacturing & Wholesale Goods"
        }
    ],
    "sg:phone":"+1 631 736 9711",
    "sg:postcode":"11779",
    "sg:province":"NY",
    "sg:tags":[
        "equipment"
    ],
    "wof:name":"GE",
    "wof:placetype":"venue"
},
  "geometry": {"coordinates":[-73.069507,40.82309],"type":"Point"}
}