{
  "type": "Feature",
  "properties": {
    "addr:full":"307 Nanuet Mall S Nanuet NY 10954",
    "addr:housenumber":"307",
    "addr:postcode":"10954",
    "addr:street":"Nanuet Mall S",
    "iso:country":"US",
    "sg:address":"307 Nanuet Mall S",
    "sg:city":"Nanuet",
    "sg:classifiers":[
        {
            "category":"Restaurant",
            "type":"Food & Drink"
        }
    ],
    "sg:phone":"+1 845 623 6860",
    "sg:postcode":"10954",
    "sg:province":"NY",
    "sg:tags":[
        "japanese"
    ],
    "wof:name":"Azuma Sushi Restaurant",
    "wof:placetype":"venue"
},
  "geometry": {"coordinates":[-74.013161,41.093315],"type":"Point"}
}