{
  "type": "Feature",
  "properties": {
    "addr:full":"7010 Irish Rd Marcy NY 13403",
    "addr:housenumber":"7010",
    "addr:postcode":"13403",
    "addr:street":"Irish Rd",
    "iso:country":"US",
    "sg:address":"7010 Irish Rd",
    "sg:city":"Marcy",
    "sg:classifiers":[
        {
            "category":"Retail",
            "subcategory":"Repair Shop",
            "type":"Services"
        }
    ],
    "sg:phone":"+1 315 865 5746",
    "sg:postcode":"13403",
    "sg:province":"NY",
    "sg:tags":[
        "machine",
        "sewing"
    ],
    "wof:name":"Sewing Machine Repair",
    "wof:placetype":"venue"
},
  "geometry": {"coordinates":[-75.29192399999999,43.19242],"type":"Point"}
}