{
  "type": "Feature",
  "properties": {
    "addr:full":"5 Harbor Park Dr Port Washington NY 11050",
    "addr:housenumber":"5",
    "addr:postcode":"11050",
    "addr:street":"Harbor Park Dr",
    "iso:country":"US",
    "sg:address":"5 Harbor Park Dr",
    "sg:city":"Port Washington",
    "sg:classifiers":[
        {
            "category":"Health Services",
            "subcategory":"Medical Lab",
            "type":"Services"
        }
    ],
    "sg:phone":"+1 516 829 4933",
    "sg:postcode":"11050",
    "sg:province":"NY",
    "sg:tags":[
        "laboratory"
    ],
    "sg:website":"www.jasonjkim.com",
    "wof:name":"Jason J Kim Dental Labs Inc",
    "wof:placetype":"venue"
},
  "geometry": {"coordinates":[-73.65855999999999,40.812621],"type":"Point"}
}