{
  "type": "Feature",
  "properties": {
    "iso:country":"US",
    "sg:address":"251 State Hwy 32",
    "sg:city":"New Paltz",
    "sg:classifiers":[
        {
            "category":"Retail",
            "subcategory":"Auto Repair",
            "type":"Services"
        }
    ],
    "sg:phone":"+1 845 255 8130",
    "sg:postcode":"12561",
    "sg:province":"NY",
    "sg:tags":[
        "repairing",
        "automobile"
    ],
    "wof:name":"John Domitrovits Inc",
    "wof:placetype":"venue"
},
  "geometry": {"coordinates":[-74.084858,41.715604],"type":"Point"}
}