{
  "type": "Feature",
  "properties": {
    "addr:full":"162 Prince St New York NY 10012",
    "addr:housenumber":"162",
    "addr:postcode":"10012",
    "addr:street":"Prince St",
    "iso:country":"US",
    "sg:address":"162 Prince St",
    "sg:city":"New York",
    "sg:classifiers":[
        {
            "category":"Restaurant",
            "type":"Food & Drink"
        }
    ],
    "sg:phone":"+1 212 226 9340",
    "sg:postcode":"10012",
    "sg:province":"NY",
    "wof:name":"Miladys Restaurant",
    "wof:placetype":"venue"
},
  "geometry": {"coordinates":[-74.00122500000001,40.725787],"type":"Point"}
}