{
  "type": "Feature",
  "properties": {
    "iso:country":"US",
    "sg:address":"3710 Milestrip Rd",
    "sg:city":"Blasdell",
    "sg:classifiers":[
        {
            "category":"Retail",
            "subcategory":"Auto Rental",
            "type":"Services"
        }
    ],
    "sg:phone":"+1 716 824 2244",
    "sg:postcode":"14219",
    "sg:province":"NY",
    "sg:tags":[
        "renting",
        "truck",
        "leasing"
    ],
    "sg:website":"www.penske.com",
    "wof:name":"Penske Truck Leasing",
    "wof:placetype":"venue"
},
  "geometry": {"coordinates":[-78.841976,42.793818],"type":"Point"}
}