{
  "type": "Feature",
  "properties": {
    "iso:country":"US",
    "sg:address":"2413 9th Ave",
    "sg:city":"Sylvan Beach",
    "sg:classifiers":[
        {
            "category":"Home & Garden",
            "subcategory":"Household Appliances",
            "type":"Retail Goods"
        }
    ],
    "sg:phone":"+1   ",
    "sg:postcode":"13157",
    "sg:province":"NY",
    "wof:name":"A & M Aplncs",
    "wof:placetype":"venue"
},
  "geometry": {"coordinates":[-75.72800100000001,43.199321],"type":"Point"}
}