{
  "type": "Feature",
  "properties": {
    "iso:country":"US",
    "sg:address":"1310 48th St",
    "sg:city":"Brooklyn",
    "sg:classifiers":[
        {
            "category":"Shopping",
            "subcategory":"Jewelry",
            "type":"Retail Goods"
        }
    ],
    "sg:phone":"+1 718 871 7540",
    "sg:postcode":"11219",
    "sg:province":"NY",
    "wof:name":"Uniquely Yours",
    "wof:placetype":"venue"
},
  "geometry": {"coordinates":[-73.991302,40.635399],"type":"Point"}
}