{
  "type": "Feature",
  "properties": {
    "iso:country":"US",
    "sg:address":"78 Bay View Ave",
    "sg:city":"Bayport",
    "sg:classifiers":[
        {
            "category":"Professional",
            "type":"Services"
        }
    ],
    "sg:phone":"+1 631 472 2773",
    "sg:postcode":"11705",
    "sg:province":"NY",
    "sg:tags":[
        "establishment"
    ],
    "wof:name":"Luchese",
    "wof:placetype":"venue"
},
  "geometry": {"coordinates":[-73.060031,40.73177],"type":"Point"}
}