{
  "type": "Feature",
  "properties": {
    "iso:country":"US",
    "sg:address":"165 Trenton Ave",
    "sg:city":"White Plains",
    "sg:classifiers":[
        {
            "category":"Building & Trades",
            "subcategory":"Construction",
            "type":"Services"
        }
    ],
    "sg:phone":"+1 914 946 2379",
    "sg:postcode":"10606",
    "sg:province":"NY",
    "sg:tags":[
        "general",
        "contractor"
    ],
    "wof:name":"Plexus Construction Inc",
    "wof:placetype":"venue"
},
  "geometry": {"coordinates":[-73.788122,41.028603],"type":"Point"}
}