{
  "type": "Feature",
  "properties": {
    "iso:country":"US",
    "sg:address":"200 1st St",
    "sg:city":"Troy",
    "sg:classifiers":[
        {
            "category":"Arts & Performance",
            "subcategory":"Art Gallery",
            "type":"Entertainment"
        }
    ],
    "sg:phone":"+1 518 326 3946",
    "sg:postcode":"12180",
    "sg:province":"NY",
    "sg:tags":[
        "consultant",
        "galleries"
    ],
    "wof:name":"Art Gallery",
    "wof:placetype":"venue"
},
  "geometry": {"coordinates":[-73.69462,42.723205],"type":"Point"}
}