{
  "type": "Feature",
  "properties": {
    "addr:full":"1321 Ave U Brooklyn NY 11229",
    "addr:postcode":"11229",
    "addr:street":"1321 Ave U",
    "iso:country":"US",
    "sg:address":"1321 Ave U",
    "sg:city":"Brooklyn",
    "sg:classifiers":[
        {
            "category":"Food & Beverages",
            "subcategory":"Meat & Fish",
            "type":"Retail Goods"
        }
    ],
    "sg:phone":"+1 718 645 2784",
    "sg:postcode":"11229",
    "sg:province":"NY",
    "sg:tags":[
        "seafood"
    ],
    "wof:name":"Xin Kwong Seafood Restaurant",
    "wof:placetype":"venue"
},
  "geometry": {"coordinates":[-73.957486,40.598784],"type":"Point"}
}