{
  "type": "Feature",
  "properties": {
    "iso:country":"US",
    "sg:address":"398 Main St",
    "sg:city":"Islip",
    "sg:classifiers":[
        {
            "category":"Manufacturing",
            "subcategory":"Printing",
            "type":"Manufacturing & Wholesale Goods"
        }
    ],
    "sg:phone":"+1   ",
    "sg:postcode":"11751",
    "sg:province":"NY",
    "sg:tags":[
        "art",
        "graphic",
        "design"
    ],
    "wof:name":"Graphic Impressions",
    "wof:placetype":"venue"
},
  "geometry": {"coordinates":[-73.21623,40.728485],"type":"Point"}
}