{
  "type": "Feature",
  "properties": {
    "iso:country":"US",
    "sg:address":"609 Ridge Rd",
    "sg:city":"Lackawanna",
    "sg:classifiers":[
        {
            "category":"Manufacturing",
            "subcategory":"Printing",
            "type":"Manufacturing & Wholesale Goods"
        }
    ],
    "sg:phone":"+1 716 826 5547",
    "sg:postcode":"14218",
    "sg:province":"NY",
    "sg:tags":[
        "printer"
    ],
    "wof:name":"Al-Fuad & Al-Kubad",
    "wof:placetype":"venue"
},
  "geometry": {"coordinates":[-78.82851700000001,42.82571],"type":"Point"}
}