{
  "type": "Feature",
  "properties": {
    "iso:country":"US",
    "sg:address":"1409 Locust Avenue",
    "sg:city":"Brooklyn",
    "sg:classifiers":[
        {
            "category":"Professional",
            "subcategory":"Computer Services",
            "type":"Services"
        }
    ],
    "sg:phone":"+1 718 252 1984",
    "sg:postcode":"11230",
    "sg:province":"NY",
    "sg:tags":[
        "stereo",
        "installation"
    ],
    "wof:name":"Securely Yours",
    "wof:placetype":"venue"
},
  "geometry": {"coordinates":[-73.960982,40.619087],"type":"Point"}
}