{
  "type": "Feature",
  "properties": {
    "iso:country":"US",
    "sg:address":"1900 Military Rd",
    "sg:city":"Niagara Falls",
    "sg:classifiers":[
        {
            "category":"Real Estate",
            "subcategory":"Real Estate Operator",
            "type":"Services"
        }
    ],
    "sg:phone":"+1 716 297 2022",
    "sg:postcode":"14304",
    "sg:province":"NY",
    "sg:tags":[
        "building",
        "nonresidential"
    ],
    "wof:name":"Prime Otlets At Nagara FLS USA",
    "wof:placetype":"venue"
},
  "geometry": {"coordinates":[-78.97384,43.095805],"type":"Point"}
}