{
  "type": "Feature",
  "properties": {
    "iso:country":"US",
    "sg:address":"13 Rose Ln",
    "sg:city":"Walden",
    "sg:classifiers":[
        {
            "category":"Social Services",
            "subcategory":"Child Care",
            "type":"Services"
        }
    ],
    "sg:phone":"+1 845 566 3798",
    "sg:postcode":"12586",
    "sg:province":"NY",
    "wof:name":"Dr Darrigo's Super Kids Club",
    "wof:placetype":"venue"
},
  "geometry": {"coordinates":[-74.1131,41.552223],"type":"Point"}
}