{
  "type": "Feature",
  "properties": {
    "addr:full":"487 Atlantic Ave Brooklyn NY 11217",
    "addr:housenumber":"487",
    "addr:postcode":"11217",
    "addr:street":"Atlantic Ave",
    "iso:country":"US",
    "sg:address":"487 Atlantic Ave",
    "sg:city":"Brooklyn",
    "sg:classifiers":[
        {
            "category":"Home & Garden",
            "subcategory":"Furniture",
            "type":"Retail Goods"
        }
    ],
    "sg:phone":"+1 718 855 6442",
    "sg:postcode":"11217",
    "sg:province":"NY",
    "sg:tags":[
        "store"
    ],
    "sg:website":"www.homeandabroad.biz",
    "wof:name":"Home & Abroad",
    "wof:placetype":"venue"
},
  "geometry": {"coordinates":[-73.981635,40.685837],"type":"Point"}
}