{
  "type": "Feature",
  "properties": {
    "addr:full":"111 Roger Ave Inwood NY 11096",
    "addr:housenumber":"111",
    "addr:postcode":"11096",
    "addr:street":"Roger Ave",
    "iso:country":"US",
    "sg:address":"111 Roger Ave",
    "sg:city":"Inwood",
    "sg:classifiers":[
        {
            "category":"Home & Garden",
            "subcategory":"Garden Supply",
            "type":"Retail Goods"
        }
    ],
    "sg:phone":"+1 516 239 7659",
    "sg:postcode":"11096",
    "sg:province":"NY",
    "sg:tags":[
        "c"
    ],
    "wof:name":"Custom Irrigation Corp",
    "wof:placetype":"venue"
},
  "geometry": {"coordinates":[-73.75503500000001,40.615324],"type":"Point"}
}