{
  "type": "Feature",
  "properties": {
    "iso:country":"US",
    "sg:address":"9 Trent Ln",
    "sg:city":"Smithtown",
    "sg:classifiers":[
        {
            "category":"Building & Trades",
            "subcategory":"Landscaping Services",
            "type":"Services"
        }
    ],
    "sg:phone":"+1 631 265 6683",
    "sg:postcode":"11787",
    "sg:province":"NY",
    "sg:tags":[
        "landscape"
    ],
    "wof:name":"Steven Schappert Landscape",
    "wof:placetype":"venue"
},
  "geometry": {"coordinates":[-73.21626500000001,40.878449],"type":"Point"}
}