{
  "type": "Feature",
  "properties": {
    "addr:full":"172 Amsterdam Ave New York NY 10023",
    "addr:housenumber":"172",
    "addr:postcode":"10023",
    "addr:street":"Amsterdam Ave",
    "iso:country":"US",
    "sg:address":"172 Amsterdam Ave",
    "sg:city":"New York",
    "sg:classifiers":[
        {
            "category":"Shopping",
            "subcategory":"Pharmacy",
            "type":"Retail Goods"
        }
    ],
    "sg:phone":"+1   ",
    "sg:postcode":"10023",
    "sg:province":"NY",
    "wof:name":"Hip Pharmacy Services 511",
    "wof:placetype":"venue"
},
  "geometry": {"coordinates":[-73.983806,40.775676],"type":"Point"}
}