{
  "type": "Feature",
  "properties": {
    "iso:country":"US",
    "sg:address":"976 Roanoke Ave",
    "sg:city":"Riverhead",
    "sg:classifiers":[
        {
            "category":"Insurance",
            "subcategory":"Insurance Agent",
            "type":"Services"
        }
    ],
    "sg:phone":"+1 631 369 3373",
    "sg:postcode":"11901",
    "sg:province":"NY",
    "sg:tags":[
        "abstract",
        "title"
    ],
    "wof:name":"Republic Abstract Corp",
    "wof:placetype":"venue"
},
  "geometry": {"coordinates":[-72.67068999999999,40.929027],"type":"Point"}
}