{
  "type": "Feature",
  "properties": {
    "addr:full":"534 Hooper Rd Endicott NY 13760",
    "addr:housenumber":"534",
    "addr:postcode":"13760",
    "addr:street":"Hooper Rd",
    "iso:country":"US",
    "sg:address":"534 Hooper Rd",
    "sg:city":"Endicott",
    "sg:classifiers":[
        {
            "category":"Personal",
            "subcategory":"Beauty Salon",
            "type":"Services"
        }
    ],
    "sg:phone":"+1 607 785 1525",
    "sg:postcode":"13760",
    "sg:province":"NY",
    "sg:tags":[
        "shop"
    ],
    "wof:name":"Head To Toe",
    "wof:placetype":"venue"
},
  "geometry": {"coordinates":[-76.020949,42.122834],"type":"Point"}
}