{
  "type": "Feature",
  "properties": {
    "addr:full":"353 Fort Washington Ave New York NY 10033",
    "addr:housenumber":"353",
    "addr:postcode":"10033",
    "addr:street":"Fort Washington Ave",
    "iso:country":"US",
    "sg:address":"353 Fort Washington Ave",
    "sg:city":"New York",
    "sg:classifiers":[
        {
            "category":"Manufacturing",
            "subcategory":"Tools & Machinery",
            "type":"Manufacturing & Wholesale Goods"
        }
    ],
    "sg:phone":"+1   ",
    "sg:postcode":"10033",
    "sg:province":"NY",
    "sg:tags":[
        "surgical",
        "mfg"
    ],
    "wof:name":"Orthotic & Prosthetic Care",
    "wof:placetype":"venue"
},
  "geometry": {"coordinates":[-73.939779,40.84721],"type":"Point"}
}