{
  "type": "Feature",
  "properties": {
    "iso:country":"US",
    "sg:address":"20 N Central Ave",
    "sg:city":"Valley Stream",
    "sg:classifiers":[
        {
            "category":"Real Estate",
            "subcategory":"Real Estate Operator",
            "type":"Services"
        }
    ],
    "sg:phone":"+1 516 872 5700",
    "sg:postcode":"11580",
    "sg:province":"NY",
    "sg:tags":[
        "building",
        "residential"
    ],
    "wof:name":"Gottlieb Properties Co",
    "wof:placetype":"venue"
},
  "geometry": {"coordinates":[-73.708084,40.667946],"type":"Point"}
}