{
  "type": "Feature",
  "properties": {
    "addr:full":"119 Avalon Pines Dr Coram NY 11727",
    "addr:housenumber":"119",
    "addr:postcode":"11727",
    "addr:street":"Avalon Pines Dr",
    "iso:country":"US",
    "sg:address":"119 Avalon Pines Dr",
    "sg:city":"Coram",
    "sg:classifiers":[
        {
            "category":"Building & Trades",
            "subcategory":"Construction",
            "type":"Services"
        }
    ],
    "sg:phone":"+1 631 928 0391",
    "sg:postcode":"11727",
    "sg:province":"NY",
    "sg:tags":[
        "interior",
        "design"
    ],
    "wof:name":"Nilssen Design Associates Inc",
    "wof:placetype":"venue"
},
  "geometry": {"coordinates":[-73.158574,40.88894],"type":"Point"}
}