{
  "type": "Feature",
  "properties": {
    "iso:country":"US",
    "sg:address":"46 Pines Bridge Rd",
    "sg:city":"Ossining",
    "sg:classifiers":[
        {
            "category":"Building & Trades",
            "subcategory":"Landscaping Services",
            "type":"Services"
        }
    ],
    "sg:phone":"+1 914 923 2285",
    "sg:postcode":"10562",
    "sg:province":"NY",
    "sg:tags":[
        "landscape",
        "contractor"
    ],
    "wof:name":"Green Forest Landscape Svc",
    "wof:placetype":"venue"
},
  "geometry": {"coordinates":[-73.82675999999999,41.18497],"type":"Point"}
}