{
  "type": "Feature",
  "properties": {
    "addr:full":"339 Morris Ave Bronx NY 10451",
    "addr:housenumber":"339",
    "addr:postcode":"10451",
    "addr:street":"Morris Ave",
    "iso:country":"US",
    "sg:address":"339 Morris Ave",
    "sg:city":"Bronx",
    "sg:classifiers":[
        {
            "category":"Education",
            "subcategory":"School",
            "type":"Public Place"
        }
    ],
    "sg:phone":"+1 718 401 4891",
    "sg:postcode":"10451",
    "sg:province":"NY",
    "wof:name":"Bronx Academy Of Letters",
    "wof:placetype":"venue"
},
  "geometry": {"coordinates":[-73.925657,40.813432],"type":"Point"}
}