{
  "type": "Feature",
  "properties": {
    "addr:full":"75 9th Ave, 8th Fl New York NY 10011",
    "addr:housenumber":"75",
    "addr:postcode":"10011",
    "addr:street":"9Th Ave",
    "iso:country":"US",
    "sg:address":"75 9th Ave, 8th Fl",
    "sg:city":"New York",
    "sg:classifiers":[
        {
            "category":"Professional",
            "subcategory":"Advertising",
            "type":"Services"
        }
    ],
    "sg:phone":"+1 800 321 9398",
    "sg:postcode":"10011",
    "sg:province":"NY",
    "sg:tags":[
        "advertising",
        "mobile",
        "local",
        "performance-advertising",
        "pay-per-call",
        "pay-per-action-phone-calls"
    ],
    "sg:website":"http://www.yext.com",
    "wof:name":"Yext",
    "wof:placetype":"venue"
},
  "geometry": {"coordinates":[-74.00285700000001,40.739166],"type":"Point"}
}