{
  "type": "Feature",
  "properties": {
    "addr:full":"169 Hilltop Dr Brentwood NY 11717",
    "addr:housenumber":"169",
    "addr:postcode":"11717",
    "addr:street":"Hilltop Dr",
    "iso:country":"US",
    "sg:address":"169 Hilltop Dr",
    "sg:city":"Brentwood",
    "sg:classifiers":[
        {
            "category":"Shopping",
            "subcategory":"Gifts & Souvenirs",
            "type":"Retail Goods"
        }
    ],
    "sg:phone":"+1   ",
    "sg:postcode":"11717",
    "sg:province":"NY",
    "wof:name":"Gift of Life Inc of Rotar",
    "wof:placetype":"venue"
},
  "geometry": {"coordinates":[-73.23279599999999,40.772145],"type":"Point"}
}