{
  "type": "Feature",
  "properties": {
    "addr:full":"59 Grand St New York NY 10013",
    "addr:housenumber":"59",
    "addr:postcode":"10013",
    "addr:street":"Grand St",
    "iso:country":"US",
    "sg:address":"59 Grand St",
    "sg:city":"New York",
    "sg:classifiers":[
        {
            "category":"Banks & Credit Unions",
            "subcategory":"Investment Brokerage",
            "type":"Services"
        }
    ],
    "sg:phone":"+1 212 343 0660",
    "sg:postcode":"10013",
    "sg:province":"NY",
    "sg:tags":[
        "research"
    ],
    "wof:name":"Open Systems of Switzerland",
    "wof:placetype":"venue"
},
  "geometry": {"coordinates":[-74.003238,40.722078],"type":"Point"}
}