{
  "type": "Feature",
  "properties": {
    "addr:full":"2789 State Hwy 26 Cincinnatus NY 13040",
    "addr:housenumber":"2789",
    "addr:postcode":"13040",
    "addr:street":"State Hwy 26 Cincinnatus",
    "iso:country":"US",
    "sg:address":"2789 State Hwy 26",
    "sg:city":"Cincinnatus",
    "sg:classifiers":[
        {
            "category":"Travel",
            "subcategory":"Hotels & Motels",
            "type":"Entertainment"
        }
    ],
    "sg:phone":"+1 607 863 3934",
    "sg:postcode":"13040",
    "sg:province":"NY",
    "sg:tags":[
        "breakfast",
        "operation",
        "bed",
        "accommodation"
    ],
    "wof:name":"Alice's Dowry Bed & Breakfast",
    "wof:placetype":"venue"
},
  "geometry": {"coordinates":[-75.903215,42.546675],"type":"Point"}
}