{
  "type": "Feature",
  "properties": {
    "iso:country":"US",
    "sg:address":"4236 Albany Post Rd",
    "sg:city":"Hyde Park",
    "sg:classifiers":[
        {
            "category":"Health Services",
            "subcategory":"Doctor",
            "type":"Services"
        }
    ],
    "sg:phone":"+1 845 229 2196",
    "sg:postcode":"12538",
    "sg:province":"NY",
    "sg:tags":[
        "physician",
        "surgeon"
    ],
    "wof:name":"Gwendoline Lanza MD",
    "wof:placetype":"venue"
},
  "geometry": {"coordinates":[-73.93472300000001,41.788324],"type":"Point"}
}