{
  "type": "Feature",
  "properties": {
    "addr:full":"160 Davison Ave Oceanside NY 11572",
    "addr:housenumber":"160",
    "addr:postcode":"11572",
    "addr:street":"Davison Ave",
    "iso:country":"US",
    "sg:address":"160 Davison Ave",
    "sg:city":"Oceanside",
    "sg:classifiers":[
        {
            "category":"Autos & Motor Vehicles",
            "subcategory":"Fuel & Gas Station",
            "type":"Retail Goods"
        }
    ],
    "sg:phone":"+1 516 678 5803",
    "sg:postcode":"11572",
    "sg:province":"NY",
    "sg:website":"www.bp.com/heliospower/modularho...",
    "wof:name":"Oceanside Petro Corp",
    "wof:placetype":"venue"
},
  "geometry": {"coordinates":[-73.634073,40.641892],"type":"Point"}
}