{
  "type": "Feature",
  "properties": {
    "iso:country":"US",
    "sg:address":"16 W Prospect Ave",
    "sg:city":"Mt Vernon",
    "sg:classifiers":[
        {
            "category":"Restaurant",
            "type":"Food & Drink"
        }
    ],
    "sg:phone":"+1 914 667 2141",
    "sg:postcode":"10550",
    "sg:province":"NY",
    "wof:name":"Blimpie Subs & Salads",
    "wof:placetype":"venue"
},
  "geometry": {"coordinates":[-73.83778599999999,40.912639],"type":"Point"}
}