{
  "type": "Feature",
  "properties": {
    "addr:full":"280 Katonah Ave Katonah NY 10536",
    "addr:housenumber":"280",
    "addr:postcode":"10536",
    "addr:street":"Katonah Ave",
    "iso:country":"US",
    "sg:address":"280 Katonah Ave",
    "sg:city":"Katonah",
    "sg:classifiers":[
        {
            "category":"Restaurant",
            "type":"Food & Drink"
        }
    ],
    "sg:phone":"+1 914 232 8027",
    "sg:postcode":"10536",
    "sg:province":"NY",
    "wof:name":"Broadway III Pizzeria",
    "wof:placetype":"venue"
},
  "geometry": {"coordinates":[-73.683835,41.255095],"type":"Point"}
}