{
  "type": "Feature",
  "properties": {
    "addr:full":"3 Lafayette Ave Brooklyn NY 11217",
    "addr:housenumber":"3",
    "addr:postcode":"11217",
    "addr:street":"Lafayette Ave",
    "iso:country":"US",
    "sg:address":"3 Lafayette Ave",
    "sg:city":"Brooklyn",
    "sg:classifiers":[
        {
            "category":"Education",
            "subcategory":"Dance Studio",
            "type":"Public Place"
        }
    ],
    "sg:phone":"+1 718 624 8400",
    "sg:postcode":"11217",
    "sg:province":"NY",
    "sg:website":"mmdg.org",
    "wof:name":"Mark Morris Dance Group",
    "wof:placetype":"venue"
},
  "geometry": {"coordinates":[-73.9785,40.686901],"type":"Point"}
}