{
  "type": "Feature",
  "properties": {
    "iso:country":"US",
    "sg:address":"394 Broadway Fl 5",
    "sg:city":"New York",
    "sg:classifiers":[
        {
            "category":"Professional",
            "subcategory":"Advertising",
            "type":"Services"
        }
    ],
    "sg:phone":"+1 347 675 1974",
    "sg:postcode":"10013",
    "sg:province":"NY",
    "sg:tags":[
        "marketing"
    ],
    "sg:website":"www.idea-evolver.com/",
    "wof:name":"Idea-Evolver, LLC",
    "wof:placetype":"venue"
},
  "geometry": {"coordinates":[-74.002619,40.718282],"type":"Point"}
}