{
  "type": "Feature",
  "properties": {
    "addr:full":"464 William Floyd Pkwy Shirley NY 11967",
    "addr:housenumber":"464",
    "addr:postcode":"11967",
    "addr:street":"William Floyd Pkwy",
    "iso:country":"US",
    "sg:address":"464 William Floyd Pkwy",
    "sg:city":"Shirley",
    "sg:classifiers":[
        {
            "category":"Personal",
            "subcategory":"Beauty Salon",
            "type":"Services"
        }
    ],
    "sg:phone":"+1 631 399 3399",
    "sg:postcode":"11967",
    "sg:province":"NY",
    "sg:tags":[
        "shop"
    ],
    "wof:name":"Lemon Tree Unisex Haircutters",
    "wof:placetype":"venue"
},
  "geometry": {"coordinates":[-72.863782,40.787487],"type":"Point"}
}