{
  "type": "Feature",
  "properties": {
    "iso:country":"US",
    "sg:address":"1387 County Route 5",
    "sg:city":"Canaan",
    "sg:classifiers":[
        {
            "category":"Social Services",
            "type":"Services"
        },
        {
            "category":"Government",
            "subcategory":"Fire Station",
            "type":"Public Place"
        }
    ],
    "sg:phone":"+1 800 304 1136",
    "sg:postcode":"12029",
    "sg:province":"NY",
    "sg:tags":[
        "recovery",
        "services-information",
        "program",
        "relief",
        "referral",
        "disaster"
    ],
    "wof:name":"Rapid Restoration-24/7 Fire & Flood Damage Cleanup",
    "wof:placetype":"venue"
},
  "geometry": {"coordinates":[-73.456633,42.395031],"type":"Point"}
}