{
  "type": "Feature",
  "properties": {
    "addr:full":"24 Major Appleby Rd Ardsley NY 10502",
    "addr:housenumber":"24",
    "addr:postcode":"10502",
    "addr:street":"Major Appleby Rd",
    "iso:country":"US",
    "sg:address":"24 Major Appleby Rd",
    "sg:city":"Ardsley",
    "sg:classifiers":[
        {
            "category":"Real Estate",
            "subcategory":"Real Estate Agent",
            "type":"Services"
        }
    ],
    "sg:phone":"+1 914 478 8200",
    "sg:postcode":"10502",
    "sg:province":"NY",
    "wof:name":"John P Fitzmaurice",
    "wof:placetype":"venue"
},
  "geometry": {"coordinates":[-73.83942500000001,41.015386],"type":"Point"}
}