{
  "type": "Feature",
  "properties": {
    "addr:full":"400 Post Ave Ste 201 Westbury NY 11590",
    "addr:housenumber":"400",
    "addr:postcode":"11590",
    "addr:street":"Post Ave Ste 201",
    "iso:country":"US",
    "sg:address":"400 Post Ave Ste 201",
    "sg:city":"Westbury",
    "sg:classifiers":[
        {
            "category":"Professional",
            "subcategory":"Lawyer & Legal Services",
            "type":"Services"
        }
    ],
    "sg:phone":"+1 212 757 0069",
    "sg:postcode":"11590",
    "sg:province":"NY",
    "wof:name":"Blankstein Jeffrey",
    "wof:placetype":"venue"
},
  "geometry": {"coordinates":[-73.586868,40.762296],"type":"Point"}
}