{
  "type": "Feature",
  "properties": {
    "iso:country":"US",
    "sg:address":"5 Dakota Dr",
    "sg:city":"New Hyde Park",
    "sg:classifiers":[
        {
            "category":"Professional",
            "type":"Services"
        }
    ],
    "sg:phone":"+1 516 358 2235",
    "sg:postcode":"11042",
    "sg:province":"NY",
    "sg:tags":[
        "establishment"
    ],
    "wof:name":"We'Re Associates Inc",
    "wof:placetype":"venue"
},
  "geometry": {"coordinates":[-73.69485899999999,40.759728],"type":"Point"}
}