{
  "type": "Feature",
  "properties": {
    "addr:full":"2 Manor Ln Lawrence NY 11559",
    "addr:housenumber":"2",
    "addr:postcode":"11559",
    "addr:street":"Manor Ln",
    "iso:country":"US",
    "sg:address":"2 Manor Ln",
    "sg:city":"Lawrence",
    "sg:classifiers":[
        {
            "category":"Manufacturing",
            "subcategory":"Textiles",
            "type":"Manufacturing & Wholesale Goods"
        }
    ],
    "sg:phone":"+1   ",
    "sg:postcode":"11559",
    "sg:province":"NY",
    "sg:tags":[
        "sweater",
        "knit"
    ],
    "wof:name":"Vinrose Industries Inc",
    "wof:placetype":"venue"
},
  "geometry": {"coordinates":[-73.731684,40.610786],"type":"Point"}
}