{
  "type": "Feature",
  "properties": {
    "addr:full":"4144 W Lake Rd Canandaigua NY 14424",
    "addr:housenumber":"4144",
    "addr:postcode":"14424",
    "addr:street":"W Lake Rd",
    "iso:country":"US",
    "sg:address":"4144 W Lake Rd",
    "sg:city":"Canandaigua",
    "sg:classifiers":[
        {
            "category":"Professional",
            "subcategory":"Computer Services",
            "type":"Services"
        }
    ],
    "sg:phone":"+1   ",
    "sg:postcode":"14424",
    "sg:province":"NY",
    "sg:tags":[
        "related"
    ],
    "wof:name":"McComb Enterprises Inc",
    "wof:placetype":"venue"
},
  "geometry": {"coordinates":[-77.28686999999999,42.819168],"type":"Point"}
}