{
  "type": "Feature",
  "properties": {
    "addr:full":"2000 Washington Ave Bronx NY 10457",
    "addr:housenumber":"2000",
    "addr:postcode":"10457",
    "addr:street":"Washington Ave",
    "iso:country":"US",
    "sg:address":"2000 Washington Ave",
    "sg:city":"Bronx",
    "sg:classifiers":[
        {
            "category":"Real Estate",
            "subcategory":"Real Estate Services",
            "type":"Services"
        }
    ],
    "sg:phone":"+1 718 294 3591",
    "sg:postcode":"10457",
    "sg:province":"NY",
    "sg:tags":[
        "management",
        "property"
    ],
    "wof:name":"Parkview Apts",
    "wof:placetype":"venue"
},
  "geometry": {"coordinates":[-73.89679700000001,40.8493],"type":"Point"}
}