{
  "type": "Feature",
  "properties": {
    "addr:full":"78 Clinton Street New York NY 10002",
    "addr:housenumber":"78",
    "addr:postcode":"10002",
    "addr:street":"Clinton Street",
    "iso:country":"US",
    "sg:address":"78 Clinton Street",
    "sg:city":"New York",
    "sg:classifiers":[
        {
            "category":"Shopping",
            "subcategory":"Pharmacy",
            "type":"Retail Goods"
        }
    ],
    "sg:phone":"+1 212 388 9886",
    "sg:postcode":"10002",
    "sg:province":"NY",
    "sg:tags":[
        "drugstore"
    ],
    "wof:name":"Medi Express Pharmacy",
    "wof:placetype":"venue"
},
  "geometry": {"coordinates":[-73.985122,40.718972],"type":"Point"}
}