{
  "type": "Feature",
  "properties": {
    "iso:country":"US",
    "sg:address":"164 N Wellwood Ave",
    "sg:city":"Lindenhurst",
    "sg:classifiers":[
        {
            "category":"Health Services",
            "subcategory":"Optometrist",
            "type":"Services"
        }
    ],
    "sg:phone":"+1 631 226 2313",
    "sg:postcode":"11757",
    "sg:province":"NY",
    "sg:tags":[
        "optical",
        "merchandise",
        "g"
    ],
    "wof:name":"Harvey I Estren OD",
    "wof:placetype":"venue"
},
  "geometry": {"coordinates":[-73.374425,40.687747],"type":"Point"}
}