{
  "type": "Feature",
  "properties": {
    "iso:country":"US",
    "sg:address":"402 Wingate Pl",
    "sg:city":"Youngstown",
    "sg:classifiers":[
        {
            "category":"Shopping",
            "subcategory":"Discount & Variety Stores",
            "type":"Retail Goods"
        }
    ],
    "sg:phone":"+1 716 745 9560",
    "sg:postcode":"14174",
    "sg:province":"NY",
    "sg:tags":[
        "merchandising",
        "merchandise"
    ],
    "wof:name":"F Two Enterprises",
    "wof:placetype":"venue"
},
  "geometry": {"coordinates":[-79.042469,43.254487],"type":"Point"}
}