{
  "type": "Feature",
  "properties": {
    "addr:full":"3512 Veterans Memorial Hwy Bohemia NY 11716",
    "addr:housenumber":"3512",
    "addr:postcode":"11716",
    "addr:street":"Veterans Memorial Hwy",
    "iso:country":"US",
    "sg:address":"3512 Veterans Memorial Hwy",
    "sg:city":"Bohemia",
    "sg:classifiers":[
        {
            "category":"Health Services",
            "subcategory":"Medical Lab",
            "type":"Services"
        }
    ],
    "sg:phone":"+1 631 285 7732",
    "sg:postcode":"11716",
    "sg:province":"NY",
    "sg:tags":[
        "laboratory"
    ],
    "wof:name":"MDK Dental",
    "wof:placetype":"venue"
},
  "geometry": {"coordinates":[-73.121269,40.786882],"type":"Point"}
}