{
  "type": "Feature",
  "properties": {
    "addr:full":"22 Warburton Ave Yonkers NY 10701",
    "addr:housenumber":"22",
    "addr:postcode":"10701",
    "addr:street":"Warburton Ave",
    "iso:country":"US",
    "sg:address":"22 Warburton Ave",
    "sg:city":"Yonkers",
    "sg:classifiers":[
        {
            "category":"Restaurant",
            "type":"Food & Drink"
        }
    ],
    "sg:menulink":"http://www.allmenus.com/ny/yonkers/158262-lejends-restaurant/menu/",
    "sg:phone":"+1 914 709 9840",
    "sg:postcode":"10701",
    "sg:province":"NY",
    "sg:tags":[
        "jamaican"
    ],
    "wof:name":"Lejends Restaurant",
    "wof:placetype":"venue"
},
  "geometry": {"coordinates":[-73.899143,40.934885],"type":"Point"}
}