{
  "type": "Feature",
  "properties": {
    "addr:full":"4921 State Hwy 17M New Hampton NY 10958",
    "addr:housenumber":"4921",
    "addr:postcode":"10958",
    "addr:street":"State Hwy",
    "iso:country":"US",
    "sg:address":"4921 State Hwy 17M",
    "sg:city":"New Hampton",
    "sg:classifiers":[
        {
            "category":"Restaurant",
            "type":"Food & Drink"
        }
    ],
    "sg:phone":"+1   ",
    "sg:postcode":"10958",
    "sg:province":"NY",
    "sg:tags":[
        "eating"
    ],
    "wof:name":"Tooties",
    "wof:placetype":"venue"
},
  "geometry": {"coordinates":[-74.41046,41.407846],"type":"Point"}
}