{
  "type": "Feature",
  "properties": {
    "addr:full":"501 Genesee St Chittenango NY 13037",
    "addr:housenumber":"501",
    "addr:postcode":"13037",
    "addr:street":"Genesee St",
    "iso:country":"US",
    "sg:address":"501 Genesee St",
    "sg:city":"Chittenango",
    "sg:classifiers":[
        {
            "category":"Health Services",
            "subcategory":"Doctor",
            "type":"Services"
        }
    ],
    "sg:phone":"+1 315 687 9177",
    "sg:postcode":"13037",
    "sg:province":"NY",
    "sg:tags":[
        "physician",
        "surgeon"
    ],
    "wof:name":"Roy A Smith MD",
    "wof:placetype":"venue"
},
  "geometry": {"coordinates":[-75.86606,43.052272],"type":"Point"}
}