{
  "type": "Feature",
  "properties": {
    "addr:full":"230 N Main St New City NY 10956",
    "addr:housenumber":"230",
    "addr:postcode":"10956",
    "addr:street":"N Main St",
    "iso:country":"US",
    "sg:address":"230 N Main St",
    "sg:city":"New City",
    "sg:classifiers":[
        {
            "category":"Insurance",
            "subcategory":"Insurance Agent",
            "type":"Services"
        }
    ],
    "sg:phone":"+1 845 638 2300",
    "sg:postcode":"10956",
    "sg:province":"NY",
    "wof:name":"Westrock Insurance Group",
    "wof:placetype":"venue"
},
  "geometry": {"coordinates":[-73.988471,41.158235],"type":"Point"}
}