{
  "type": "Feature",
  "properties": {
    "addr:full":"376 W Main St West Winfield NY 13491",
    "addr:housenumber":"376",
    "addr:postcode":"13491",
    "addr:street":"W Main St",
    "iso:country":"US",
    "sg:address":"376 W Main St",
    "sg:city":"West Winfield",
    "sg:classifiers":[
        {
            "category":"Government",
            "subcategory":"Post Office",
            "type":"Public Place"
        }
    ],
    "sg:phone":"+1 315 822 5350",
    "sg:postcode":"13491",
    "sg:province":"NY",
    "wof:name":"US Post Office",
    "wof:placetype":"venue"
},
  "geometry": {"coordinates":[-75.19440400000001,42.885009],"type":"Point"}
}