{
  "type": "Feature",
  "properties": {
    "addr:full":"33 E Main St Elmsford NY 10523",
    "addr:housenumber":"33",
    "addr:postcode":"10523",
    "addr:street":"E Main St",
    "iso:country":"US",
    "sg:address":"33 E Main St",
    "sg:city":"Elmsford",
    "sg:classifiers":[
        {
            "category":"Personal",
            "subcategory":"Barber",
            "type":"Services"
        }
    ],
    "sg:phone":"+1   ",
    "sg:postcode":"10523",
    "sg:province":"NY",
    "sg:tags":[
        "shop"
    ],
    "wof:name":"Elmsford Barber & Styling",
    "wof:placetype":"venue"
},
  "geometry": {"coordinates":[-73.817374,41.054086],"type":"Point"}
}