{
  "type": "Feature",
  "properties": {
    "iso:country":"US",
    "sg:address":"123 Riverside Dr",
    "sg:city":"Fultonville",
    "sg:classifiers":[
        {
            "category":"Travel",
            "subcategory":"Hotels & Motels",
            "type":"Entertainment"
        }
    ],
    "sg:phone":"+1 518 853 4511",
    "sg:postcode":"12072",
    "sg:province":"NY",
    "wof:name":"Travelodge",
    "wof:placetype":"venue"
},
  "geometry": {"coordinates":[-74.347961,42.944889],"type":"Point"}
}