{
  "type": "Feature",
  "properties": {
    "addr:full":"3018 Wickham Ave Bronx NY 10469",
    "addr:housenumber":"3018",
    "addr:postcode":"10469",
    "addr:street":"Wickham Ave",
    "iso:country":"US",
    "sg:address":"3018 Wickham Ave",
    "sg:city":"Bronx",
    "sg:classifiers":[
        {
            "category":"Professional",
            "subcategory":"Management & Consulting",
            "type":"Services"
        }
    ],
    "sg:phone":"+1   ",
    "sg:postcode":"10469",
    "sg:province":"NY",
    "wof:name":"Synergy Marketing Ltd",
    "wof:placetype":"venue"
},
  "geometry": {"coordinates":[-73.838928,40.872369],"type":"Point"}
}