{
  "type": "Feature",
  "properties": {
    "iso:country":"US",
    "sg:address":"110 E 84th St",
    "sg:city":"New York",
    "sg:classifiers":[
        {
            "category":"Professional",
            "subcategory":"Computer Services",
            "type":"Services"
        }
    ],
    "sg:phone":"+1   ",
    "sg:postcode":"10028",
    "sg:province":"NY",
    "sg:tags":[
        "prepackaged",
        "software"
    ],
    "wof:name":"UNI Software Ltd",
    "wof:placetype":"venue"
},
  "geometry": {"coordinates":[-73.956874,40.778277],"type":"Point"}
}