{
  "type": "Feature",
  "properties": {
    "addr:full":"271 Read Ave Tuckahoe NY 10707",
    "addr:housenumber":"271",
    "addr:postcode":"10707",
    "addr:street":"Read Ave",
    "iso:country":"US",
    "sg:address":"271 Read Ave",
    "sg:city":"Tuckahoe",
    "sg:classifiers":[
        {
            "category":"Local Transit",
            "type":"Transportation"
        }
    ],
    "sg:phone":"+1 914 337 3550",
    "sg:postcode":"10707",
    "sg:province":"NY",
    "sg:tags":[
        "limousine",
        "driver"
    ],
    "wof:name":"We'Ll Drive Limousine",
    "wof:placetype":"venue"
},
  "geometry": {"coordinates":[-73.821485,40.963108],"type":"Point"}
}