{
  "type": "Feature",
  "properties": {
    "addr:full":"207 W 78 St New York NY 10024",
    "addr:housenumber":"207",
    "addr:postcode":"10024",
    "addr:street":"W 78 St",
    "iso:country":"US",
    "sg:address":"207 W 78 St",
    "sg:city":"New York",
    "sg:classifiers":[
        {
            "category":"Social Services",
            "subcategory":"Child Care",
            "type":"Services"
        }
    ],
    "sg:phone":"+1   ",
    "sg:postcode":"10024",
    "sg:province":"NY",
    "sg:tags":[
        "day"
    ],
    "wof:name":"Productivity Learning Systems",
    "wof:placetype":"venue"
},
  "geometry": {"coordinates":[-73.98027999999999,40.783139],"type":"Point"}
}