{
  "type": "Feature",
  "properties": {
    "iso:country":"US",
    "sg:address":"462 N Perry St",
    "sg:city":"Johnstown",
    "sg:classifiers":[
        {
            "category":"Social Services",
            "subcategory":"Adult Care",
            "type":"Services"
        },
        {
            "category":"Social Services",
            "type":"Services"
        }
    ],
    "sg:phone":"+1 518 762 2294",
    "sg:postcode":"12095",
    "sg:province":"NY",
    "sg:tags":[
        "organization",
        "residential",
        "welfare"
    ],
    "wof:name":"Fulton Friendship House Inc",
    "wof:placetype":"venue"
},
  "geometry": {"coordinates":[-74.367,43.026387],"type":"Point"}
}