{
  "type": "Feature",
  "properties": {
    "addr:full":"160 Broadway Rm 600 New York NY 10038",
    "addr:housenumber":"160;600",
    "addr:postcode":"10038",
    "addr:street":"Broadway Rm",
    "iso:country":"US",
    "sg:address":"160 Broadway Rm 600",
    "sg:city":"New York",
    "sg:classifiers":[
        {
            "category":"Professional",
            "subcategory":"Lawyer & Legal Services",
            "type":"Services"
        }
    ],
    "sg:phone":"+1 212 684 5454",
    "sg:postcode":"10038",
    "sg:province":"NY",
    "wof:name":"Kimmel Jeffrey",
    "wof:placetype":"venue"
},
  "geometry": {"coordinates":[-74.01002200000001,40.709406],"type":"Point"}
}