{
  "type": "Feature",
  "properties": {
    "iso:country":"US",
    "sg:address":"12111 Vaughn St",
    "sg:city":"East Concord",
    "sg:classifiers":[
        {
            "category":"Banks & Credit Unions",
            "subcategory":"Investment Brokerage",
            "type":"Services"
        }
    ],
    "sg:phone":"+1 716 592 9225",
    "sg:postcode":"14055",
    "sg:province":"NY",
    "sg:tags":[
        "consultant",
        "planning",
        "financial"
    ],
    "wof:name":"Kevin L Mahoney Investments",
    "wof:placetype":"venue"
},
  "geometry": {"coordinates":[-78.640463,42.54925],"type":"Point"}
}