{
  "type": "Feature",
  "properties": {
    "iso:country":"US",
    "sg:address":"6097 Spencer Ave",
    "sg:city":"Bronx",
    "sg:classifiers":[
        {
            "category":"Building & Trades",
            "subcategory":"Construction",
            "type":"Services"
        }
    ],
    "sg:phone":"+1 718 601 3473",
    "sg:postcode":"10471",
    "sg:province":"NY",
    "sg:tags":[
        "contractor"
    ],
    "wof:name":"Zap Contracting",
    "wof:placetype":"venue"
},
  "geometry": {"coordinates":[-73.899141,40.907766],"type":"Point"}
}