{
  "type": "Feature",
  "properties": {
    "iso:country":"US",
    "sg:address":"32 Valley Dr E",
    "sg:city":"Yorktown Heights",
    "sg:classifiers":[
        {
            "category":"Building & Trades",
            "subcategory":"Construction",
            "type":"Services"
        }
    ],
    "sg:phone":"+1 914 243 9593",
    "sg:postcode":"10598",
    "sg:province":"NY",
    "sg:tags":[
        "restoration",
        "cleaning",
        "patio",
        "deck"
    ],
    "wof:name":"Sawhorse",
    "wof:placetype":"venue"
},
  "geometry": {"coordinates":[-73.74509999999999,41.332595],"type":"Point"}
}