{
  "type": "Feature",
  "properties": {
    "addr:full":"430 Main St Center Moriches NY 11934",
    "addr:housenumber":"430",
    "addr:postcode":"11934",
    "addr:street":"Main St",
    "iso:country":"US",
    "sg:address":"430 Main St",
    "sg:city":"Center Moriches",
    "sg:classifiers":[
        {
            "category":"Communications",
            "subcategory":"Radio Station",
            "type":"Services"
        }
    ],
    "sg:phone":"+1 631 874 4417",
    "sg:postcode":"11934",
    "sg:province":"NY",
    "sg:tags":[
        "company",
        "broadcasting"
    ],
    "wof:name":"WBAB",
    "wof:placetype":"venue"
},
  "geometry": {"coordinates":[-72.795935,40.800422],"type":"Point"}
}