{
  "type": "Feature",
  "properties": {
    "iso:country":"US",
    "sg:address":"456 West Ave",
    "sg:city":"Albion",
    "sg:classifiers":[
        {
            "category":"Education",
            "subcategory":"Junior College",
            "type":"Public Place"
        }
    ],
    "sg:phone":"+1 585 589 4936",
    "sg:postcode":"14411",
    "sg:province":"NY",
    "sg:tags":[
        "technical",
        "institute",
        "university"
    ],
    "sg:website":"http://www.genesee.edu",
    "wof:name":"Genesee Community College",
    "wof:placetype":"venue"
},
  "geometry": {"coordinates":[-78.206988,43.24076],"type":"Point"}
}