{
  "type": "Feature",
  "properties": {
    "addr:full":"2622 Merrick Rd Bellmore NY 11710",
    "addr:housenumber":"2622",
    "addr:postcode":"11710",
    "addr:street":"Merrick Rd",
    "iso:country":"US",
    "sg:address":"2622 Merrick Rd",
    "sg:city":"Bellmore",
    "sg:classifiers":[
        {
            "category":"Personal",
            "type":"Services"
        }
    ],
    "sg:phone":"+1 516 679 5094",
    "sg:postcode":"11710",
    "sg:province":"NY",
    "sg:tags":[
        "hair",
        "replacement"
    ],
    "wof:name":"Bellmore Hair Replacement",
    "wof:placetype":"venue"
},
  "geometry": {"coordinates":[-73.528442,40.662885],"type":"Point"}
}