{
  "type": "Feature",
  "properties": {
    "addr:full":"91 Baldwin St Binghamton NY 13903",
    "addr:housenumber":"91",
    "addr:postcode":"13903",
    "addr:street":"Baldwin St",
    "iso:country":"US",
    "sg:address":"91 Baldwin St",
    "sg:city":"Binghamton",
    "sg:classifiers":[
        {
            "category":"Organizations",
            "subcategory":"Religious Organization",
            "type":"Services"
        }
    ],
    "sg:phone":"+1 607 724 1252",
    "sg:postcode":"13903",
    "sg:province":"NY",
    "wof:name":"Conklin Ave Frst Baptst Church",
    "wof:placetype":"venue"
},
  "geometry": {"coordinates":[-75.891949,42.09671],"type":"Point"}
}