{
  "type": "Feature",
  "properties": {
    "addr:full":"1615 Palmetto St Flushing NY 11385",
    "addr:housenumber":"1615",
    "addr:postcode":"11385",
    "addr:street":"Palmetto St",
    "iso:country":"US",
    "sg:address":"1615 Palmetto St",
    "sg:city":"Flushing",
    "sg:classifiers":[
        {
            "category":"Food & Beverages",
            "subcategory":"Bakery",
            "type":"Retail Goods"
        }
    ],
    "sg:phone":"+1 718 821 0501",
    "sg:postcode":"11385",
    "sg:province":"NY",
    "sg:tags":[
        "baker"
    ],
    "wof:name":"Danny's Bakery",
    "wof:placetype":"venue"
},
  "geometry": {"coordinates":[-73.910229,40.70034],"type":"Point"}
}