{
  "type": "Feature",
  "properties": {
    "iso:country":"US",
    "sg:address":"872 Merrick Rd",
    "sg:city":"Baldwin",
    "sg:classifiers":[
        {
            "category":"Retail",
            "subcategory":"Laundry & Dry Cleaning",
            "type":"Services"
        }
    ],
    "sg:phone":"+1 516 623 7780",
    "sg:postcode":"11510",
    "sg:province":"NY",
    "sg:tags":[
        "cleaners"
    ],
    "wof:name":"Stylon Cleaners",
    "wof:placetype":"venue"
},
  "geometry": {"coordinates":[-73.609436,40.650885],"type":"Point"}
}