{
  "type": "Feature",
  "properties": {
    "addr:full":"1157 42nd St Brooklyn NY 11219",
    "addr:housenumber":"1157",
    "addr:postcode":"11219",
    "addr:street":"42Nd St",
    "iso:country":"US",
    "sg:address":"1157 42nd St",
    "sg:city":"Brooklyn",
    "sg:classifiers":[
        {
            "category":"Organizations",
            "subcategory":"Religious Organization",
            "type":"Services"
        }
    ],
    "sg:phone":"+1 718 436 8072",
    "sg:postcode":"11219",
    "sg:province":"NY",
    "sg:tags":[
        "clergy"
    ],
    "wof:name":"Yitzchok Stein",
    "wof:placetype":"venue"
},
  "geometry": {"coordinates":[-73.991237,40.641163],"type":"Point"}
}