{
  "type": "Feature",
  "properties": {
    "iso:country":"US",
    "sg:address":"14 Edgewater Dr",
    "sg:city":"Middletown",
    "sg:classifiers":[
        {
            "category":"Insurance",
            "subcategory":"Insurance Agent",
            "type":"Services"
        }
    ],
    "sg:phone":"+1 845 344 1111",
    "sg:postcode":"10940",
    "sg:province":"NY",
    "wof:name":"Tataryn Associates",
    "wof:placetype":"venue"
},
  "geometry": {"coordinates":[-74.387366,41.455819],"type":"Point"}
}