{
  "type": "Feature",
  "properties": {
    "addr:full":"9773 Ridge Rd Middleport NY 14105",
    "addr:housenumber":"9773",
    "addr:postcode":"14105",
    "addr:street":"Ridge Rd",
    "iso:country":"US",
    "sg:address":"9773 Ridge Rd",
    "sg:city":"Middleport",
    "sg:classifiers":[
        {
            "category":"Retail",
            "subcategory":"Repair Shop",
            "type":"Services"
        }
    ],
    "sg:phone":"+1   ",
    "sg:postcode":"14105",
    "sg:province":"NY",
    "wof:name":"Lords Home Maintenance Co",
    "wof:placetype":"venue"
},
  "geometry": {"coordinates":[-78.478723,43.25006],"type":"Point"}
}