{
  "type": "Feature",
  "properties": {
    "addr:full":"55 Fairview Hill Rd Addison NY 14801",
    "addr:housenumber":"55",
    "addr:postcode":"14801",
    "addr:street":"Fairview Hill Rd",
    "iso:country":"US",
    "sg:address":"55 Fairview Hill Rd",
    "sg:city":"Addison",
    "sg:classifiers":[
        {
            "category":"Retail",
            "subcategory":"Portrait Studio",
            "type":"Services"
        }
    ],
    "sg:phone":"+1 607 359 3704",
    "sg:postcode":"14801",
    "sg:province":"NY",
    "sg:tags":[
        "photographer"
    ],
    "wof:name":"Lasting Impressions Photogrphy",
    "wof:placetype":"venue"
},
  "geometry": {"coordinates":[-77.243405,42.101518],"type":"Point"}
}