{
  "type": "Feature",
  "properties": {
    "addr:full":"361 State Hwy 59 Spring Valley NY 10977",
    "addr:housenumber":"361",
    "addr:postcode":"10977",
    "addr:street":"State Hwy 59",
    "iso:country":"US",
    "sg:address":"361 State Hwy 59",
    "sg:city":"Spring Valley",
    "sg:classifiers":[
        {
            "category":"Education",
            "subcategory":"School",
            "type":"Public Place"
        }
    ],
    "sg:phone":"+1 845 577 6533",
    "sg:postcode":"10977",
    "sg:province":"NY",
    "wof:name":"Spring Valley Sr High School",
    "wof:placetype":"venue"
},
  "geometry": {"coordinates":[-74.05797800000001,41.108601],"type":"Point"}
}