{
  "type": "Feature",
  "properties": {
    "addr:full":"279 E 44th St New York NY 10017",
    "addr:housenumber":"279",
    "addr:postcode":"10017",
    "addr:street":"E 44Th St",
    "iso:country":"US",
    "sg:address":"279 E 44th St",
    "sg:city":"New York",
    "sg:classifiers":[
        {
            "category":"Real Estate",
            "subcategory":"Real Estate Operator",
            "type":"Services"
        }
    ],
    "sg:phone":"+1 212 697 2636",
    "sg:postcode":"10017",
    "sg:province":"NY",
    "sg:tags":[
        "apartment"
    ],
    "wof:name":"Olympia House",
    "wof:placetype":"venue"
},
  "geometry": {"coordinates":[-73.971583,40.751313],"type":"Point"}
}