{
  "type": "Feature",
  "properties": {
    "iso:country":"US",
    "sg:address":"222 Drewville Rd",
    "sg:city":"Carmel",
    "sg:classifiers":[
        {
            "category":"Wholesale",
            "subcategory":"Machinery & Supplies",
            "type":"Manufacturing & Wholesale Goods"
        }
    ],
    "sg:phone":"+1 845 621 2396",
    "sg:postcode":"10512",
    "sg:province":"NY",
    "sg:tags":[
        "equipment",
        "industrial"
    ],
    "wof:name":"Lawrence Frederick",
    "wof:placetype":"venue"
},
  "geometry": {"coordinates":[-73.694975,41.389276],"type":"Point"}
}