{
  "type": "Feature",
  "properties": {
    "addr:full":"524 Food Ct Central Valley NY 10917",
    "addr:housenumber":"524",
    "addr:postcode":"10917",
    "addr:street":"Food Ct",
    "iso:country":"US",
    "sg:address":"524 Food Ct",
    "sg:city":"Central Valley",
    "sg:classifiers":[
        {
            "category":"Shopping",
            "subcategory":"Discount & Variety Stores",
            "type":"Retail Goods"
        }
    ],
    "sg:phone":"+1 845 928 5148",
    "sg:postcode":"10917",
    "sg:province":"NY",
    "sg:tags":[
        "outlet"
    ],
    "wof:name":"Harry & David Woodbury Common Premium Outlet",
    "wof:placetype":"venue"
},
  "geometry": {"coordinates":[-74.125801,41.316002],"type":"Point"}
}