{
  "type": "Feature",
  "properties": {
    "iso:country":"US",
    "sg:address":"45 Overlook Ter",
    "sg:city":"New York",
    "sg:classifiers":[
        {
            "category":"Utilities",
            "subcategory":"Telephone",
            "type":"Services"
        }
    ],
    "sg:phone":"+1   ",
    "sg:postcode":"10033",
    "sg:province":"NY",
    "sg:tags":[
        "communications"
    ],
    "wof:name":"Rcn Long Distance Company",
    "wof:placetype":"venue"
},
  "geometry": {"coordinates":[-73.936525,40.852746],"type":"Point"}
}