{
  "type": "Feature",
  "properties": {
    "addr:full":"275 Warner Ave Roslyn Heights NY 11577",
    "addr:housenumber":"275",
    "addr:postcode":"11577",
    "addr:street":"Warner Ave",
    "iso:country":"US",
    "sg:address":"275 Warner Ave",
    "sg:city":"Roslyn Heights",
    "sg:classifiers":[
        {
            "category":"Social Services",
            "type":"Services"
        }
    ],
    "sg:phone":"+1 516 626 9076",
    "sg:postcode":"11577",
    "sg:province":"NY",
    "sg:tags":[
        "counselor",
        "marriage",
        "family"
    ],
    "wof:name":"Elizabeth P Marshall",
    "wof:placetype":"venue"
},
  "geometry": {"coordinates":[-73.64590800000001,40.791747],"type":"Point"}
}