{
  "type": "Feature",
  "properties": {
    "iso:country":"US",
    "sg:address":"98 Lake St",
    "sg:city":"West Harrison",
    "sg:classifiers":[
        {
            "category":"Building & Trades",
            "subcategory":"Construction",
            "type":"Services"
        }
    ],
    "sg:phone":"+1 914 946 9141",
    "sg:postcode":"10604",
    "sg:province":"NY",
    "sg:tags":[
        "general",
        "contractor"
    ],
    "wof:name":"Casa Bella Contracting",
    "wof:placetype":"venue"
},
  "geometry": {"coordinates":[-73.756173,41.039709],"type":"Point"}
}