{
  "type": "Feature",
  "properties": {
    "addr:full":"1414 2 Ave New York NY 10021",
    "addr:housenumber":"1414",
    "addr:postcode":"10021",
    "addr:street":"2 Ave",
    "iso:country":"US",
    "sg:address":"1414 2 Ave",
    "sg:city":"New York",
    "sg:classifiers":[
        {
            "category":"Shopping",
            "subcategory":"Jewelry",
            "type":"Retail Goods"
        }
    ],
    "sg:phone":"+1 212 535 3102",
    "sg:postcode":"10021",
    "sg:province":"NY",
    "sg:tags":[
        "jeweler"
    ],
    "wof:name":"Iwen's Jewelry & Gifts",
    "wof:placetype":"venue"
},
  "geometry": {"coordinates":[-73.959318,40.767493],"type":"Point"}
}