{
  "type": "Feature",
  "properties": {
    "addr:full":"29 Broadway St Haverstraw NY 10927",
    "addr:housenumber":"29",
    "addr:postcode":"10927",
    "addr:street":"Broadway St",
    "iso:country":"US",
    "sg:address":"29 Broadway St",
    "sg:city":"Haverstraw",
    "sg:classifiers":[
        {
            "category":"Health Services",
            "subcategory":"Doctor",
            "type":"Services"
        }
    ],
    "sg:phone":"+1 845 429 9501",
    "sg:postcode":"10927",
    "sg:province":"NY",
    "sg:tags":[
        "physician",
        "surgeon"
    ],
    "wof:name":"Helen D De Asis MD",
    "wof:placetype":"venue"
},
  "geometry": {"coordinates":[-73.964698,41.197916],"type":"Point"}
}