{
  "type": "Feature",
  "properties": {
    "addr:full":"430 Factory St Watertown NY 13601",
    "addr:housenumber":"430",
    "addr:postcode":"13601",
    "addr:street":"Factory St",
    "iso:country":"US",
    "sg:address":"430 Factory St",
    "sg:city":"Watertown",
    "sg:classifiers":[
        {
            "category":"Food & Beverages",
            "subcategory":"Groceries & Convenience Stores",
            "type":"Retail Goods"
        }
    ],
    "sg:phone":"+1 315 786 8084",
    "sg:postcode":"13601",
    "sg:province":"NY",
    "sg:website":"http://www.valentinestores.com",
    "wof:name":"Nice N Easy Grocery Shoppe",
    "wof:placetype":"venue"
},
  "geometry": {"coordinates":[-75.903623,43.976255],"type":"Point"}
}