{
  "type": "Feature",
  "properties": {
    "iso:country":"US",
    "sg:address":"196 Merrick Rd",
    "sg:city":"Lynbrook",
    "sg:classifiers":[
        {
            "category":"Autos & Motor Vehicles",
            "subcategory":"Automobile Sales",
            "type":"Retail Goods"
        }
    ],
    "sg:phone":"+1 516 599 8770",
    "sg:postcode":"11563",
    "sg:province":"NY",
    "sg:tags":[
        "truck"
    ],
    "wof:name":"T F Motors New York Inc",
    "wof:placetype":"venue"
},
  "geometry": {"coordinates":[-73.66584400000001,40.658091],"type":"Point"}
}