{
  "type": "Feature",
  "properties": {
    "iso:country":"US",
    "sg:address":"72 Elm St",
    "sg:city":"East Aurora",
    "sg:classifiers":[
        {
            "category":"Professional",
            "type":"Services"
        }
    ],
    "sg:phone":"+1 716 652 5517",
    "sg:postcode":"14052",
    "sg:province":"NY",
    "sg:tags":[
        "establishment"
    ],
    "wof:name":"Double S Equipment LLC",
    "wof:placetype":"venue"
},
  "geometry": {"coordinates":[-78.611268,42.766729],"type":"Point"}
}