{
  "type": "Feature",
  "properties": {
    "iso:country":"US",
    "sg:address":"1010 Front St",
    "sg:city":"Uniondale",
    "sg:classifiers":[
        {
            "category":"Shopping",
            "type":"Retail Goods"
        }
    ],
    "sg:phone":"+1 516 565 9211",
    "sg:postcode":"11553",
    "sg:province":"NY",
    "sg:tags":[
        "telephone",
        "cellular"
    ],
    "wof:name":"Best Buy Communications & Mktg",
    "wof:placetype":"venue"
},
  "geometry": {"coordinates":[-73.59295400000001,40.709417],"type":"Point"}
}