{
  "type": "Feature",
  "properties": {
    "addr:full":"718 2nd Ave New York NY 10016",
    "addr:housenumber":"718",
    "addr:postcode":"10016",
    "addr:street":"2Nd Ave",
    "iso:country":"US",
    "sg:address":"718 2nd Ave",
    "sg:city":"New York",
    "sg:classifiers":[
        {
            "category":"Restaurant",
            "type":"Food & Drink"
        }
    ],
    "sg:menulink":"http://www.allmenus.com/ny/new-york/2669-el-pote-espanol/menu/",
    "sg:phone":"+1 212 889 6680",
    "sg:postcode":"10016",
    "sg:province":"NY",
    "sg:tags":[
        "mexican"
    ],
    "wof:name":"El Pote Espanol",
    "wof:placetype":"venue"
},
  "geometry": {"coordinates":[-73.97376300000001,40.747676],"type":"Point"}
}