{
  "type": "Feature",
  "properties": {
    "iso:country":"US",
    "sg:address":"1859 Commerce St",
    "sg:city":"Yorktown Heights",
    "sg:classifiers":[
        {
            "category":"Retail",
            "subcategory":"Repair Shop",
            "type":"Services"
        }
    ],
    "sg:phone":"+1 914 962 9380",
    "sg:postcode":"10598",
    "sg:province":"NY",
    "sg:tags":[
        "television",
        "radio"
    ],
    "wof:name":"Commerce Street Properties Inc",
    "wof:placetype":"venue"
},
  "geometry": {"coordinates":[-73.78057200000001,41.271605],"type":"Point"}
}