{
  "type": "Feature",
  "properties": {
    "addr:full":"134 Mineola Blvd Mineola NY 11501",
    "addr:housenumber":"134",
    "addr:postcode":"11501",
    "addr:street":"Mineola Blvd",
    "iso:country":"US",
    "sg:address":"134 Mineola Blvd",
    "sg:city":"Mineola",
    "sg:classifiers":[
        {
            "category":"Health Services",
            "subcategory":"Doctor",
            "type":"Services"
        }
    ],
    "sg:phone":"+1   ",
    "sg:postcode":"11501",
    "sg:province":"NY",
    "sg:tags":[
        "osteopathic"
    ],
    "wof:name":"Emil Ganjian",
    "wof:placetype":"venue"
},
  "geometry": {"coordinates":[-73.640776,40.742956],"type":"Point"}
}