{
  "type": "Feature",
  "properties": {
    "addr:full":"237 State Hwy 59 Suffern NY 10901",
    "addr:housenumber":"237",
    "addr:postcode":"10901",
    "addr:street":"State Hwy 59",
    "iso:country":"US",
    "sg:address":"237 State Hwy 59",
    "sg:city":"Suffern",
    "sg:classifiers":[
        {
            "category":"Government",
            "subcategory":"Office",
            "type":"Public Place"
        }
    ],
    "sg:phone":"+1 845 357 5100",
    "sg:postcode":"10901",
    "sg:province":"NY",
    "sg:tags":[
        "town",
        "manager"
    ],
    "wof:name":"Town of Ramapo",
    "wof:placetype":"venue"
},
  "geometry": {"coordinates":[-74.137822,41.11265],"type":"Point"}
}