{
  "type": "Feature",
  "properties": {
    "addr:full":"185 Halstead Ave Harrison NY 10528",
    "addr:housenumber":"185",
    "addr:postcode":"10528",
    "addr:street":"Halstead Ave",
    "iso:country":"US",
    "sg:address":"185 Halstead Ave",
    "sg:city":"Harrison",
    "sg:classifiers":[
        {
            "category":"Professional",
            "subcategory":"Accounting & Tax Preparation",
            "type":"Services"
        }
    ],
    "sg:phone":"+1 914 835 4542",
    "sg:postcode":"10528",
    "sg:province":"NY",
    "sg:tags":[
        "accountant",
        "auditing",
        "bookkeeping"
    ],
    "wof:name":"Bilotta & Santoli PC",
    "wof:placetype":"venue"
},
  "geometry": {"coordinates":[-73.715825,40.966914],"type":"Point"}
}