{
  "type": "Feature",
  "properties": {
    "addr:full":"881 Manhattan Ave Brooklyn NY 11222",
    "addr:housenumber":"881",
    "addr:postcode":"11222",
    "addr:street":"Manhattan Ave",
    "iso:country":"US",
    "sg:address":"881 Manhattan Ave",
    "sg:city":"Brooklyn",
    "sg:classifiers":[
        {
            "category":"Banks & Credit Unions",
            "subcategory":"Bank",
            "type":"Services"
        }
    ],
    "sg:phone":"+1 718 349 1320",
    "sg:postcode":"11222",
    "sg:province":"NY",
    "sg:tags":[
        "money",
        "order"
    ],
    "wof:name":"Pekao Trading Corp",
    "wof:placetype":"venue"
},
  "geometry": {"coordinates":[-73.954233,40.729908],"type":"Point"}
}