{
  "type": "Feature",
  "properties": {
    "iso:country":"US",
    "sg:address":"88 Coursen Pl",
    "sg:city":"Staten Island",
    "sg:classifiers":[
        {
            "category":"Autos & Motor Vehicles",
            "subcategory":"Boat Sales",
            "type":"Retail Goods"
        }
    ],
    "sg:phone":"+1 718 816 6365",
    "sg:postcode":"10304",
    "sg:province":"NY",
    "sg:tags":[
        "equipment",
        "marine",
        "supply"
    ],
    "wof:name":"Alpha Marine Repair Inc",
    "wof:placetype":"venue"
},
  "geometry": {"coordinates":[-74.080151,40.619296],"type":"Point"}
}