{
  "type": "Feature",
  "properties": {
    "iso:country":"US",
    "sg:address":"604 Tompkins Ave",
    "sg:city":"Mamaroneck",
    "sg:classifiers":[
        {
            "category":"Building & Trades",
            "subcategory":"Landscaping Services",
            "type":"Services"
        }
    ],
    "sg:phone":"+1 914 381 1680",
    "sg:postcode":"10543",
    "sg:province":"NY",
    "sg:tags":[
        "landscape"
    ],
    "wof:name":"Adj Landscaping",
    "wof:placetype":"venue"
},
  "geometry": {"coordinates":[-73.72698800000001,40.952461],"type":"Point"}
}