{
  "type": "Feature",
  "properties": {
    "addr:full":"5 Cooper Morris Dr Pomona NY 10970",
    "addr:housenumber":"5",
    "addr:postcode":"10970",
    "addr:street":"Cooper Morris Dr",
    "iso:country":"US",
    "sg:address":"5 Cooper Morris Dr",
    "sg:city":"Pomona",
    "sg:classifiers":[
        {
            "category":"Professional",
            "subcategory":"Business Services",
            "type":"Services"
        },
        {
            "category":"Professional",
            "subcategory":"Research",
            "type":"Services"
        }
    ],
    "sg:phone":"+1 845 362 8610",
    "sg:postcode":"10970",
    "sg:province":"NY",
    "sg:tags":[
        "conference",
        "organization",
        "center",
        "noncommercial"
    ],
    "wof:name":"Cejjes Institute Inc",
    "wof:placetype":"venue"
},
  "geometry": {"coordinates":[-74.034127,41.176617],"type":"Point"}
}