{
  "type": "Feature",
  "properties": {
    "iso:country":"US",
    "sg:address":"105 Marys Ave",
    "sg:city":"Kingston",
    "sg:classifiers":[
        {
            "category":"Health Services",
            "subcategory":"Doctor",
            "type":"Services"
        }
    ],
    "sg:phone":"+1   ",
    "sg:postcode":"12401",
    "sg:province":"NY",
    "wof:name":"Mid Hudson Oral Maxifacial",
    "wof:placetype":"venue"
},
  "geometry": {"coordinates":[-73.999281,41.922234],"type":"Point"}
}