{
  "type": "Feature",
  "properties": {
    "iso:country":"US",
    "sg:address":"209 W 96 St",
    "sg:city":"New York",
    "sg:classifiers":[
        {
            "category":"Real Estate",
            "subcategory":"Real Estate Agent",
            "type":"Services"
        }
    ],
    "sg:phone":"+1 212 662 4062",
    "sg:postcode":"10025",
    "sg:province":"NY",
    "wof:name":"Mway Management LLC",
    "wof:placetype":"venue"
},
  "geometry": {"coordinates":[-73.97157199999999,40.794615],"type":"Point"}
}