{
  "type": "Feature",
  "properties": {
    "iso:country":"US",
    "sg:address":"656 Morris Park Ave",
    "sg:city":"Bronx",
    "sg:classifiers":[
        {
            "category":"Utilities",
            "subcategory":"Refuse",
            "type":"Services"
        }
    ],
    "sg:phone":"+1 718 829 7763",
    "sg:postcode":"10462",
    "sg:province":"NY",
    "sg:tags":[
        "carting",
        "private",
        "garbage",
        "collection"
    ],
    "wof:name":"Heritage Carting Corp",
    "wof:placetype":"venue"
},
  "geometry": {"coordinates":[-73.866996,40.844955],"type":"Point"}
}