{
  "type": "Feature",
  "properties": {
    "iso:country":"US",
    "sg:address":"506 N James St",
    "sg:city":"Rome",
    "sg:classifiers":[
        {
            "category":"Food & Beverages",
            "subcategory":"Groceries & Convenience Stores",
            "type":"Retail Goods"
        }
    ],
    "sg:phone":"+1   ",
    "sg:postcode":"13440",
    "sg:province":"NY",
    "wof:name":"Dibella Fancy Fruit Baskets",
    "wof:placetype":"venue"
},
  "geometry": {"coordinates":[-75.452731,43.215669],"type":"Point"}
}