{
  "type": "Feature",
  "properties": {
    "iso:country":"US",
    "sg:address":"27 Union Sq W Suite 300",
    "sg:city":"New York",
    "sg:classifiers":[
        {
            "category":"Banks & Credit Unions",
            "subcategory":"Financial Services",
            "type":"Services"
        }
    ],
    "sg:phone":"+1 212 929 3500",
    "sg:postcode":"10003",
    "sg:province":"NY",
    "sg:tags":[
        "broker",
        "mortgage"
    ],
    "wof:name":"Split Rock Group",
    "wof:placetype":"venue"
},
  "geometry": {"coordinates":[-73.990989,40.736485],"type":"Point"}
}