{
  "type": "Feature",
  "properties": {
    "iso:country":"US",
    "sg:address":"14 Great Neck Rd",
    "sg:city":"Great Neck",
    "sg:classifiers":[
        {
            "category":"Banks & Credit Unions",
            "subcategory":"Financial Services",
            "type":"Services"
        }
    ],
    "sg:phone":"+1 516 829 7480",
    "sg:postcode":"11021",
    "sg:province":"NY",
    "wof:name":"Hillerys Yogurt Kit Franchise",
    "wof:placetype":"venue"
},
  "geometry": {"coordinates":[-73.727951,40.785906],"type":"Point"}
}