{
  "type": "Feature",
  "properties": {
    "iso:country":"US",
    "sg:address":"9 Lisa Ln",
    "sg:city":"Port Jefferson Station",
    "sg:classifiers":[
        {
            "category":"Shopping",
            "subcategory":"Gifts & Souvenirs",
            "type":"Retail Goods"
        }
    ],
    "sg:phone":"+1   ",
    "sg:postcode":"11776",
    "sg:province":"NY",
    "wof:name":"Party Rentals By Doug",
    "wof:placetype":"venue"
},
  "geometry": {"coordinates":[-73.048648,40.906431],"type":"Point"}
}