{
  "type": "Feature",
  "properties": {
    "addr:full":"847 Union St Brooklyn NY 11215",
    "addr:housenumber":"847",
    "addr:postcode":"11215",
    "addr:street":"Union St",
    "iso:country":"US",
    "sg:address":"847 Union St",
    "sg:city":"Brooklyn",
    "sg:classifiers":[
        {
            "category":"Shopping",
            "type":"Retail Goods"
        }
    ],
    "sg:phone":"+1   ",
    "sg:postcode":"11215",
    "sg:province":"NY",
    "sg:tags":[
        "merchandise"
    ],
    "wof:name":"Art Vanguard Gallery",
    "wof:placetype":"venue"
},
  "geometry": {"coordinates":[-73.977071,40.675375],"type":"Point"}
}