{
  "type": "Feature",
  "properties": {
    "iso:country":"US",
    "sg:address":"263 North Ave",
    "sg:city":"Webster",
    "sg:classifiers":[
        {
            "category":"Wholesale",
            "subcategory":"Durable Goods & Equipment",
            "type":"Manufacturing & Wholesale Goods"
        }
    ],
    "sg:phone":"+1 585 872 1461",
    "sg:postcode":"14580",
    "sg:province":"NY",
    "sg:tags":[
        "laser"
    ],
    "wof:name":"Crysta-Line Inc",
    "wof:placetype":"venue"
},
  "geometry": {"coordinates":[-77.430012,43.218669],"type":"Point"}
}