{
  "type": "Feature",
  "properties": {
    "addr:full":"1895 Weast Rd Pattersonville NY 12306",
    "addr:housenumber":"1895",
    "addr:postcode":"12306",
    "addr:street":"Weast Rd",
    "iso:country":"US",
    "sg:address":"1895 Weast Rd",
    "sg:city":"Pattersonville",
    "sg:classifiers":[
        {
            "category":"Building & Trades",
            "subcategory":"Construction",
            "type":"Services"
        }
    ],
    "sg:phone":"+1 518 864 5649",
    "sg:postcode":"12306",
    "sg:province":"NY",
    "sg:tags":[
        "house"
    ],
    "wof:name":"Unser Builders & Remodelers",
    "wof:placetype":"venue"
},
  "geometry": {"coordinates":[-74.11152800000001,42.83209],"type":"Point"}
}