{
  "type": "Feature",
  "properties": {
    "iso:country":"US",
    "sg:address":"70 Maple Ave",
    "sg:city":"Rockville Centre",
    "sg:classifiers":[
        {
            "category":"Sports & Exercise",
            "subcategory":"Gym",
            "type":"Entertainment"
        }
    ],
    "sg:phone":"+1 516 536 7388",
    "sg:postcode":"11570",
    "sg:province":"NY",
    "wof:name":"Universal Racquet Club",
    "wof:placetype":"venue"
},
  "geometry": {"coordinates":[-73.64191,40.658662],"type":"Point"}
}