{
  "type": "Feature",
  "properties": {
    "addr:full":"6412 Baird Ave Syracuse NY 13206",
    "addr:housenumber":"6412",
    "addr:postcode":"13206",
    "addr:street":"Baird Ave",
    "iso:country":"US",
    "sg:address":"6412 Baird Ave",
    "sg:city":"Syracuse",
    "sg:classifiers":[
        {
            "category":"Building & Trades",
            "subcategory":"Plumbing",
            "type":"Services"
        }
    ],
    "sg:phone":"+1 315 431 0900",
    "sg:postcode":"13206",
    "sg:province":"NY",
    "sg:tags":[
        "air",
        "heating",
        "conditioning",
        "contractor"
    ],
    "wof:name":"John W Danforth Company",
    "wof:placetype":"venue"
},
  "geometry": {"coordinates":[-76.115161,43.080905],"type":"Point"}
}