{
  "type": "Feature",
  "properties": {
    "addr:full":"912 Beverly Dr Syracuse NY 13219",
    "addr:housenumber":"912",
    "addr:postcode":"13219",
    "addr:street":"Beverly Dr",
    "iso:country":"US",
    "sg:address":"912 Beverly Dr",
    "sg:city":"Syracuse",
    "sg:classifiers":[
        {
            "category":"Building & Trades",
            "subcategory":"Construction",
            "type":"Services"
        }
    ],
    "sg:phone":"+1 315 450 3384",
    "sg:postcode":"13219",
    "sg:province":"NY",
    "sg:tags":[
        "residential",
        "contractor"
    ],
    "wof:name":"T J C Contracting",
    "wof:placetype":"venue"
},
  "geometry": {"coordinates":[-76.234261,43.040275],"type":"Point"}
}