{
  "type": "Feature",
  "properties": {
    "addr:full":"198 Elizabeth St New York NY 10012",
    "addr:housenumber":"198",
    "addr:postcode":"10012",
    "addr:street":"Elizabeth St",
    "iso:country":"US",
    "sg:address":"198 Elizabeth St",
    "sg:city":"New York",
    "sg:classifiers":[
        {
            "category":"Professional",
            "subcategory":"Lawyer & Legal Services",
            "type":"Services"
        }
    ],
    "sg:phone":"+1   ",
    "sg:postcode":"10012",
    "sg:province":"NY",
    "sg:tags":[
        "law"
    ],
    "wof:name":"Karam Francis P Law Office",
    "wof:placetype":"venue"
},
  "geometry": {"coordinates":[-73.99424399999999,40.722151],"type":"Point"}
}