{
  "type": "Feature",
  "properties": {
    "iso:country":"US",
    "sg:address":"2385 Grand Concourse",
    "sg:city":"Bronx",
    "sg:classifiers":[
        {
            "category":"Arts & Performance",
            "subcategory":"Theater",
            "type":"Entertainment"
        }
    ],
    "sg:phone":"+1 718 733 9334",
    "sg:postcode":"10468",
    "sg:province":"NY",
    "sg:tags":[
        "company",
        "production",
        "musical"
    ],
    "wof:name":"Paper Chase Productions",
    "wof:placetype":"venue"
},
  "geometry": {"coordinates":[-73.898426,40.860165],"type":"Point"}
}