{
  "type": "Feature",
  "properties": {
    "addr:full":"3589 Hylan Boulevard Staten Island NY 10308",
    "addr:housenumber":"3589",
    "addr:postcode":"10308",
    "addr:street":"Hylan Boulevard",
    "iso:country":"US",
    "sg:address":"3589 Hylan Boulevard",
    "sg:city":"Staten Island",
    "sg:classifiers":[
        {
            "category":"Health Services",
            "subcategory":"Optometrist",
            "type":"Services"
        }
    ],
    "sg:phone":"+1 718 966 3700",
    "sg:postcode":"10308",
    "sg:province":"NY",
    "wof:name":"Marchisella Joseph OD",
    "wof:placetype":"venue"
},
  "geometry": {"coordinates":[-74.13674399999999,40.549926],"type":"Point"}
}