{
  "type": "Feature",
  "properties": {
    "addr:full":"262 Angola Rd Cornwall NY 12518",
    "addr:housenumber":"262",
    "addr:postcode":"12518",
    "addr:street":"Angola Rd",
    "iso:country":"US",
    "sg:address":"262 Angola Rd",
    "sg:city":"Cornwall",
    "sg:classifiers":[
        {
            "category":"Building & Trades",
            "subcategory":"Construction",
            "type":"Services"
        }
    ],
    "sg:phone":"+1 845 534 9674",
    "sg:postcode":"12518",
    "sg:province":"NY",
    "sg:tags":[
        "excavating",
        "contractor"
    ],
    "wof:name":"Nannini & Callahan Excavating",
    "wof:placetype":"venue"
},
  "geometry": {"coordinates":[-74.047982,41.419016],"type":"Point"}
}