{
  "type": "Feature",
  "properties": {
    "addr:full":"128 Wooster St New York NY 10012",
    "addr:housenumber":"128",
    "addr:postcode":"10012",
    "addr:street":"Wooster St",
    "iso:country":"US",
    "sg:address":"128 Wooster St",
    "sg:city":"New York",
    "sg:classifiers":[
        {
            "category":"Manufacturing",
            "subcategory":"Apparel",
            "type":"Manufacturing & Wholesale Goods"
        }
    ],
    "sg:phone":"+1 212 226 2079",
    "sg:postcode":"10012",
    "sg:province":"NY",
    "sg:tags":[
        "clothing"
    ],
    "wof:name":"Mahmoud Muhawish",
    "wof:placetype":"venue"
},
  "geometry": {"coordinates":[-74.001127,40.724166],"type":"Point"}
}