{
  "type": "Feature",
  "properties": {
    "iso:country":"US",
    "sg:address":"2635 Pettit Ave",
    "sg:city":"Bellmore",
    "sg:classifiers":[
        {
            "category":"Professional",
            "subcategory":"Research",
            "type":"Services"
        }
    ],
    "sg:phone":"+1 516 409 5800",
    "sg:postcode":"11710",
    "sg:province":"NY",
    "sg:tags":[
        "environmental",
        "ecological",
        "consultant"
    ],
    "wof:name":"G A Environmental Services Inc",
    "wof:placetype":"venue"
},
  "geometry": {"coordinates":[-73.53071199999999,40.668725],"type":"Point"}
}