{
  "type": "Feature",
  "properties": {
    "addr:full":"44 Robin Rd Staten Island NY 10305",
    "addr:housenumber":"44",
    "addr:postcode":"10305",
    "addr:street":"Robin Rd",
    "iso:country":"US",
    "sg:address":"44 Robin Rd",
    "sg:city":"Staten Island",
    "sg:classifiers":[
        {
            "category":"Food & Beverages",
            "subcategory":"Candy",
            "type":"Retail Goods"
        }
    ],
    "sg:phone":"+1 718 981 6400",
    "sg:postcode":"10305",
    "sg:province":"NY",
    "sg:tags":[
        "store"
    ],
    "wof:name":"South Beach Novelties & Confectionery Co Inc",
    "wof:placetype":"venue"
},
  "geometry": {"coordinates":[-74.06379699999999,40.595501],"type":"Point"}
}