{
  "type": "Feature",
  "properties": {
    "iso:country":"US",
    "sg:address":"60 Lincoln Center Plz",
    "sg:city":"New York",
    "sg:classifiers":[
        {
            "category":"Education",
            "subcategory":"Special Training",
            "type":"Public Place"
        }
    ],
    "sg:phone":"+1 212 431 9330",
    "sg:postcode":"10023",
    "sg:province":"NY",
    "sg:tags":[
        "language"
    ],
    "wof:name":"Els Language Center",
    "wof:placetype":"venue"
},
  "geometry": {"coordinates":[-73.982873,40.771587],"type":"Point"}
}