{
  "type": "Feature",
  "properties": {
    "iso:country":"US",
    "sg:address":"846 Co Rte 55",
    "sg:city":"Fulton",
    "sg:classifiers":[
        {
            "category":"Building & Trades",
            "subcategory":"Construction",
            "type":"Services"
        }
    ],
    "sg:phone":"+1 315 592 5367",
    "sg:postcode":"13069",
    "sg:province":"NY",
    "sg:tags":[
        "house"
    ],
    "wof:name":"Dave Becks Remodeling",
    "wof:placetype":"venue"
},
  "geometry": {"coordinates":[-76.43094499999999,43.278387],"type":"Point"}
}