{
  "type": "Feature",
  "properties": {
    "addr:full":"115 S Wellwood Ave Lindenhurst NY 11757",
    "addr:housenumber":"115",
    "addr:postcode":"11757",
    "addr:street":"S Wellwood Ave",
    "iso:country":"US",
    "sg:address":"115 S Wellwood Ave",
    "sg:city":"Lindenhurst",
    "sg:classifiers":[
        {
            "category":"Wholesale",
            "subcategory":"Machinery & Supplies",
            "type":"Manufacturing & Wholesale Goods"
        },
        {
            "category":"Shopping",
            "subcategory":"Beauty & Cosmetics",
            "type":"Retail Goods"
        }
    ],
    "sg:phone":"+1 631 957 4949",
    "sg:postcode":"11757",
    "sg:province":"NY",
    "sg:tags":[
        "salon",
        "establishment",
        "merchandise"
    ],
    "wof:name":"TCS Beauty Supplies",
    "wof:placetype":"venue"
},
  "geometry": {"coordinates":[-73.370756,40.684436],"type":"Point"}
}