{
  "type": "Feature",
  "properties": {
    "addr:full":"163 Beach 121st St Rockaway Park NY 11694",
    "addr:housenumber":"163",
    "addr:postcode":"11694",
    "addr:street":"Beach 121St St",
    "iso:country":"US",
    "sg:address":"163 Beach 121st St",
    "sg:city":"Rockaway Park",
    "sg:classifiers":[
        {
            "category":"Building & Trades",
            "subcategory":"Construction",
            "type":"Services"
        }
    ],
    "sg:phone":"+1 718 945 4926",
    "sg:postcode":"11694",
    "sg:province":"NY",
    "sg:tags":[
        "housing"
    ],
    "wof:name":"Tubridy Contg & Consulting",
    "wof:placetype":"venue"
},
  "geometry": {"coordinates":[-73.840872,40.57704],"type":"Point"}
}