{
  "type": "Feature",
  "properties": {
    "iso:country":"US",
    "sg:address":"517 Beech St",
    "sg:city":"Fulton",
    "sg:classifiers":[
        {
            "category":"Freight",
            "type":"Transportation"
        }
    ],
    "sg:phone":"+1 315 592 5015",
    "sg:postcode":"13069",
    "sg:province":"NY",
    "sg:tags":[
        "commercial",
        "storage"
    ],
    "wof:name":"Malone's Parkside Mini-Storage",
    "wof:placetype":"venue"
},
  "geometry": {"coordinates":[-76.42357800000001,43.313362],"type":"Point"}
}