{
  "type": "Feature",
  "properties": {
    "addr:full":"8952 Strong Hill Rd Naples NY 14512",
    "addr:housenumber":"8952",
    "addr:postcode":"14512",
    "addr:street":"Strong Hill Rd",
    "iso:country":"US",
    "sg:address":"8952 Strong Hill Rd",
    "sg:city":"Naples",
    "sg:classifiers":[
        {
            "category":"Real Estate",
            "subcategory":"Real Estate Operator",
            "type":"Services"
        }
    ],
    "sg:phone":"+1 585 374 2700",
    "sg:postcode":"14512",
    "sg:province":"NY",
    "wof:name":"Fran Realty",
    "wof:placetype":"venue"
},
  "geometry": {"coordinates":[-77.420355,42.589073],"type":"Point"}
}