{
  "type": "Feature",
  "properties": {
    "addr:full":"70 Old Cross Rd Warwick NY 10990",
    "addr:housenumber":"70",
    "addr:postcode":"10990",
    "addr:street":"Old Cross Rd",
    "iso:country":"US",
    "sg:address":"70 Old Cross Rd",
    "sg:city":"Warwick",
    "sg:classifiers":[
        {
            "category":"Retail",
            "subcategory":"Veterinary Services",
            "type":"Services"
        }
    ],
    "sg:phone":"+1 845 986 2669",
    "sg:postcode":"10990",
    "sg:province":"NY",
    "wof:name":"Mac Namara Brian",
    "wof:placetype":"venue"
},
  "geometry": {"coordinates":[-74.41582099999999,41.244381],"type":"Point"}
}