{
  "type": "Feature",
  "properties": {
    "addr:full":"31 Frost Ln Lawrence NY 11559",
    "addr:housenumber":"31",
    "addr:postcode":"11559",
    "addr:street":"Frost Ln",
    "iso:country":"US",
    "sg:address":"31 Frost Ln",
    "sg:city":"Lawrence",
    "sg:classifiers":[
        {
            "category":"Health Services",
            "subcategory":"Doctor",
            "type":"Services"
        },
        {
            "category":"Health Services",
            "subcategory":"Dentist",
            "type":"Services"
        }
    ],
    "sg:phone":"+1 516 295 1155",
    "sg:postcode":"11559",
    "sg:province":"NY",
    "sg:tags":[
        "surgeon",
        "oral",
        "pediatric"
    ],
    "wof:name":"Krauss Steven DDS",
    "wof:placetype":"venue"
},
  "geometry": {"coordinates":[-73.727997,40.617802],"type":"Point"}
}