{
  "type": "Feature",
  "properties": {
    "addr:full":"214 Ellicott Sq Bldg Buffalo NY 14203",
    "addr:housenumber":"214",
    "addr:postcode":"14203",
    "addr:street":"Ellicott Sq Bldg",
    "iso:country":"US",
    "sg:address":"214 Ellicott Sq Bldg",
    "sg:city":"Buffalo",
    "sg:classifiers":[
        {
            "category":"Shopping",
            "subcategory":"Jewelry",
            "type":"Retail Goods"
        }
    ],
    "sg:phone":"+1 716 856 6434",
    "sg:postcode":"14203",
    "sg:province":"NY",
    "wof:name":"Diamond Cutters Of Western Newyork",
    "wof:placetype":"venue"
},
  "geometry": {"coordinates":[-78.87259400000001,42.884458],"type":"Point"}
}