{
  "type": "Feature",
  "properties": {
    "iso:country":"US",
    "sg:address":"361 Ocean Ave",
    "sg:city":"Massapequa",
    "sg:classifiers":[
        {
            "category":"Social Services",
            "type":"Services"
        }
    ],
    "sg:phone":"+1 516 795 8557",
    "sg:postcode":"11758",
    "sg:province":"NY",
    "sg:tags":[
        "counselor",
        "marriage",
        "family"
    ],
    "wof:name":"Therese Dunne PHD",
    "wof:placetype":"venue"
},
  "geometry": {"coordinates":[-73.470485,40.67212],"type":"Point"}
}