{
  "type": "Feature",
  "properties": {
    "iso:country":"US",
    "sg:address":"110 E 149th St",
    "sg:city":"Bronx",
    "sg:classifiers":[
        {
            "category":"Food & Beverages",
            "subcategory":"Meat & Fish",
            "type":"Retail Goods"
        }
    ],
    "sg:phone":"+1 718 665 2756",
    "sg:postcode":"10451",
    "sg:province":"NY",
    "sg:tags":[
        "shop"
    ],
    "wof:name":"Strauss Siegmund Mkt & Pltry",
    "wof:placetype":"venue"
},
  "geometry": {"coordinates":[-73.92983,40.818545],"type":"Point"}
}