{
  "type": "Feature",
  "properties": {
    "iso:country":"US",
    "sg:address":"33 S Service Rd",
    "sg:city":"Jericho",
    "sg:classifiers":[
        {
            "category":"Real Estate",
            "subcategory":"Real Estate Services",
            "type":"Services"
        }
    ],
    "sg:phone":"+1 516 333 2000",
    "sg:postcode":"11753",
    "sg:province":"NY",
    "sg:tags":[
        "management",
        "property"
    ],
    "wof:name":"Rosen Assocs Managmnt Corp",
    "wof:placetype":"venue"
},
  "geometry": {"coordinates":[-73.51840199999999,40.791],"type":"Point"}
}