{
  "type": "Feature",
  "properties": {
    "iso:country":"US",
    "sg:address":"66 Greenwich Ave",
    "sg:city":"New York",
    "sg:classifiers":[
        {
            "category":"Shopping",
            "subcategory":"Used Merchandise",
            "type":"Retail Goods"
        },
        {
            "category":"Manufacturing",
            "subcategory":"Textiles",
            "type":"Manufacturing & Wholesale Goods"
        }
    ],
    "sg:phone":"+1 212 924 8444",
    "sg:postcode":"10011",
    "sg:province":"NY",
    "sg:tags":[
        "fabric"
    ],
    "wof:name":"Be Seated Inc",
    "wof:placetype":"venue"
},
  "geometry": {"coordinates":[-74.000884,40.736275],"type":"Point"}
}