{
  "type": "Feature",
  "properties": {
    "addr:full":"952 Atlantic Ave Brooklyn NY 11238",
    "addr:housenumber":"952",
    "addr:postcode":"11238",
    "addr:street":"Atlantic Ave",
    "iso:country":"US",
    "sg:address":"952 Atlantic Ave",
    "sg:city":"Brooklyn",
    "sg:phone":"+1 718 230 4079",
    "sg:postcode":"11238",
    "sg:province":"NY",
    "sg:tags":[
        "equipment",
        "supply"
    ],
    "wof:name":"Atlantic Restaurant Supply Inc",
    "wof:placetype":"venue"
},
  "geometry": {"coordinates":[-73.961741,40.6805],"type":"Point"}
}