{
  "type": "Feature",
  "properties": {
    "iso:country":"US",
    "sg:address":"48 5th Ave",
    "sg:city":"Brooklyn",
    "sg:classifiers":[
        {
            "category":"Shopping",
            "subcategory":"Hobbies, Toys, & Games",
            "type":"Retail Goods"
        },
        {
            "category":"Personal",
            "subcategory":"Beauty Salon",
            "type":"Services"
        }
    ],
    "sg:phone":"+1 718 832 3732",
    "sg:postcode":"11217",
    "sg:province":"NY",
    "sg:tags":[
        "hair",
        "toy",
        "store"
    ],
    "sg:website":"www.luluscuts.com",
    "wof:name":"Lulu's Cuts and Toys",
    "wof:placetype":"venue"
},
  "geometry": {"coordinates":[-73.977165,40.681695],"type":"Point"}
}