{
  "type": "Feature",
  "properties": {
    "addr:full":"24 Farragut Ave Hastings On Hudson NY 10706",
    "addr:housenumber":"24",
    "addr:postcode":"10706",
    "addr:street":"Farragut Ave",
    "iso:country":"US",
    "sg:address":"24 Farragut Ave",
    "sg:city":"Hastings On Hudson",
    "sg:classifiers":[
        {
            "category":"Organizations",
            "subcategory":"Religious Organization",
            "type":"Services"
        }
    ],
    "sg:phone":"+1   ",
    "sg:postcode":"10706",
    "sg:province":"NY",
    "wof:name":"First Reformed Church",
    "wof:placetype":"venue"
},
  "geometry": {"coordinates":[-73.87764300000001,40.994325],"type":"Point"}
}