{
  "type": "Feature",
  "properties": {
    "addr:full":"55 E 72 St New York NY 10021",
    "addr:housenumber":"55;72",
    "addr:postcode":"10021",
    "addr:street":"E;St",
    "iso:country":"US",
    "sg:address":"55 E 72 St",
    "sg:city":"New York",
    "sg:classifiers":[
        {
            "category":"Professional",
            "type":"Services"
        }
    ],
    "sg:phone":"+1 212 752 9377",
    "sg:postcode":"10021",
    "sg:province":"NY",
    "sg:tags":[
        "establishment"
    ],
    "wof:name":"Kehoe White Savage & Co",
    "wof:placetype":"venue"
},
  "geometry": {"coordinates":[-73.964218,40.771409],"type":"Point"}
}