{
  "type": "Feature",
  "properties": {
    "iso:country":"US",
    "sg:address":"164 Madison Ave",
    "sg:city":"New York",
    "sg:classifiers":[
        {
            "category":"Professional",
            "subcategory":"Research",
            "type":"Services"
        }
    ],
    "sg:phone":"+1 212 447 5382",
    "sg:postcode":"10016",
    "sg:province":"NY",
    "sg:tags":[
        "nonphysical",
        "consulting",
        "management",
        "commercial",
        "s"
    ],
    "wof:name":"Romero Earl J",
    "wof:placetype":"venue"
},
  "geometry": {"coordinates":[-73.983738,40.74672],"type":"Point"}
}