{
  "type": "Feature",
  "properties": {
    "iso:country":"US",
    "sg:address":"4348 County Line Rd",
    "sg:city":"Auburn",
    "sg:classifiers":[
        {
            "category":"Building & Trades",
            "subcategory":"Construction",
            "type":"Services"
        }
    ],
    "sg:phone":"+1 315 685 1405",
    "sg:postcode":"13021",
    "sg:province":"NY",
    "sg:tags":[
        "home",
        "general",
        "contractor"
    ],
    "wof:name":"Kasper Construction Company",
    "wof:placetype":"venue"
},
  "geometry": {"coordinates":[-76.456294,42.915036],"type":"Point"}
}