{
  "type": "Feature",
  "properties": {
    "addr:full":"1881 Park Ave New York NY 10035",
    "addr:housenumber":"1881",
    "addr:postcode":"10035",
    "addr:street":"Park Ave",
    "iso:country":"US",
    "sg:address":"1881 Park Ave",
    "sg:city":"New York",
    "sg:classifiers":[
        {
            "category":"Social Services",
            "subcategory":"Job Training",
            "type":"Services"
        }
    ],
    "sg:phone":"+1 212 427 1342",
    "sg:postcode":"10035",
    "sg:province":"NY",
    "sg:tags":[
        "rehabilitation"
    ],
    "wof:name":"Addicts Rehabilitation",
    "wof:placetype":"venue"
},
  "geometry": {"coordinates":[-73.937153,40.807492],"type":"Point"}
}