{
  "type": "Feature",
  "properties": {
    "iso:country":"US",
    "sg:address":"1 Langdon St",
    "sg:city":"Islip",
    "sg:classifiers":[
        {
            "category":"Retail",
            "subcategory":"Laundry & Dry Cleaning",
            "type":"Services"
        }
    ],
    "sg:phone":"+1 631 581 2615",
    "sg:postcode":"11751",
    "sg:province":"NY",
    "sg:tags":[
        "cleaners",
        "rug",
        "carpet"
    ],
    "wof:name":"ATL Maintenance",
    "wof:placetype":"venue"
},
  "geometry": {"coordinates":[-73.22523,40.749846],"type":"Point"}
}