{
  "type": "Feature",
  "properties": {
    "addr:full":"8206 3rd Avenue Brooklyn NY 11209",
    "addr:housenumber":"8206",
    "addr:postcode":"11209",
    "addr:street":"3Rd Avenue",
    "iso:country":"US",
    "sg:address":"8206 3rd Avenue",
    "sg:city":"Brooklyn",
    "sg:classifiers":[
        {
            "category":"Sports & Exercise",
            "subcategory":"Gym",
            "type":"Entertainment"
        }
    ],
    "sg:phone":"+1 718 765 0099",
    "sg:postcode":"11209",
    "sg:province":"NY",
    "sg:tags":[
        "yoga"
    ],
    "sg:website":"www.dahnyoga.com/Bay-Ridge/",
    "wof:name":"Dahn Yoga Bay Ridge",
    "wof:placetype":"venue"
},
  "geometry": {"coordinates":[-74.030074,40.626222],"type":"Point"}
}