{
  "type": "Feature",
  "properties": {
    "iso:country":"US",
    "sg:address":"425 Kenwood Ave",
    "sg:city":"Delmar",
    "sg:classifiers":[
        {
            "category":"Professional",
            "subcategory":"Lawyer & Legal Services",
            "type":"Services"
        }
    ],
    "sg:phone":"+1 518 449 9680",
    "sg:postcode":"12054",
    "sg:province":"NY",
    "sg:tags":[
        "attorney",
        "practice"
    ],
    "wof:name":"S Spring",
    "wof:placetype":"venue"
},
  "geometry": {"coordinates":[-73.83574900000001,42.622964],"type":"Point"}
}