{
  "type": "Feature",
  "properties": {
    "iso:country":"US",
    "sg:address":"1843 Deer Park Ave",
    "sg:city":"Deer Park",
    "sg:classifiers":[
        {
            "category":"Social Services",
            "subcategory":"Child Care",
            "type":"Services"
        }
    ],
    "sg:phone":"+1 631 586 0562",
    "sg:postcode":"11729",
    "sg:province":"NY",
    "sg:tags":[
        "kindergarten",
        "academic",
        "school"
    ],
    "wof:name":"Deer Park Pre-School Inc",
    "wof:placetype":"venue"
},
  "geometry": {"coordinates":[-73.328881,40.760838],"type":"Point"}
}