{
  "type": "Feature",
  "properties": {
    "iso:country":"US",
    "sg:address":"521 W 57 St",
    "sg:city":"New York",
    "sg:classifiers":[
        {
            "category":"Manufacturing",
            "subcategory":"Chemicals & Compounds",
            "type":"Manufacturing & Wholesale Goods"
        }
    ],
    "sg:phone":"+1 212 765 5500",
    "sg:postcode":"10019",
    "sg:province":"NY",
    "sg:tags":[
        "extract",
        "flavoring"
    ],
    "sg:website":"www.iff.com",
    "wof:name":"International Flavors & Frgncs",
    "wof:placetype":"venue"
},
  "geometry": {"coordinates":[-73.991242,40.77031],"type":"Point"}
}