{
  "type": "Feature",
  "properties": {
    "iso:country":"US",
    "sg:address":"137 Willis Ave Ste 300",
    "sg:city":"Mineola",
    "sg:classifiers":[
        {
            "category":"Insurance",
            "subcategory":"Insurance Agent",
            "type":"Services"
        },
        {
            "category":"Insurance",
            "subcategory":"Hazard Insurance",
            "type":"Services"
        }
    ],
    "sg:phone":"+1 516 742 8815",
    "sg:postcode":"11501",
    "sg:province":"NY",
    "sg:tags":[
        "surety",
        "fidelity",
        "commercial",
        "business",
        "bond"
    ],
    "sg:website":"http://www.jaspersurety.com",
    "wof:name":"Jasper Surety Agency",
    "wof:placetype":"venue"
},
  "geometry": {"coordinates":[-73.637935,40.74362],"type":"Point"}
}