{
  "type": "Feature",
  "properties": {
    "addr:full":"6161 W Quaker St Orchard Park NY 14127",
    "addr:housenumber":"6161",
    "addr:postcode":"14127",
    "addr:street":"W Quaker St",
    "iso:country":"US",
    "sg:address":"6161 W Quaker St",
    "sg:city":"Orchard Park",
    "sg:classifiers":[
        {
            "category":"Food & Beverages",
            "subcategory":"Liquor & Beverages",
            "type":"Retail Goods"
        }
    ],
    "sg:phone":"+1   ",
    "sg:postcode":"14127",
    "sg:province":"NY",
    "sg:tags":[
        "alcoholic"
    ],
    "wof:name":"Consumers Beverages Inc",
    "wof:placetype":"venue"
},
  "geometry": {"coordinates":[-78.755323,42.763729],"type":"Point"}
}