{
  "type": "Feature",
  "properties": {
    "iso:country":"US",
    "sg:address":"141 W 4 St",
    "sg:city":"New York",
    "sg:classifiers":[
        {
            "category":"Social Services",
            "subcategory":"Adult Care",
            "type":"Services"
        }
    ],
    "sg:phone":"+1 212 674 1397",
    "sg:postcode":"10012",
    "sg:province":"NY",
    "sg:tags":[
        "residential"
    ],
    "wof:name":"Malozzemoss House",
    "wof:placetype":"venue"
},
  "geometry": {"coordinates":[-74.000401,40.731437],"type":"Point"}
}