{
  "type": "Feature",
  "properties": {
    "addr:full":"6616 Fresh Pond Rd Ridgewood NY 11385",
    "addr:housenumber":"6616",
    "addr:postcode":"11385",
    "addr:street":"Fresh Pond Rd",
    "iso:country":"US",
    "sg:address":"6616 Fresh Pond Rd",
    "sg:city":"Ridgewood",
    "sg:classifiers":[
        {
            "category":"Shopping",
            "subcategory":"Pets & Pet Supplies",
            "type":"Retail Goods"
        }
    ],
    "sg:phone":"+1 718 366 6921",
    "sg:postcode":"11385",
    "sg:province":"NY",
    "sg:tags":[
        "store"
    ],
    "wof:name":"Paradise Aquarium",
    "wof:placetype":"venue"
},
  "geometry": {"coordinates":[-73.898201,40.7085],"type":"Point"}
}