{
  "type": "Feature",
  "properties": {
    "iso:country":"US",
    "sg:address":"8503 4th Ave",
    "sg:city":"Brooklyn",
    "sg:classifiers":[
        {
            "category":"Retail",
            "subcategory":"Laundry & Dry Cleaning",
            "type":"Services"
        }
    ],
    "sg:phone":"+1 718 833 6517",
    "sg:postcode":"11209",
    "sg:province":"NY",
    "wof:name":"Best Svce Tailors & Cleaners",
    "wof:placetype":"venue"
},
  "geometry": {"coordinates":[-74.02800000000001,40.623299],"type":"Point"}
}