{
  "type": "Feature",
  "properties": {
    "addr:full":"27 Heller Pl Hauppauge NY 11788",
    "addr:housenumber":"27",
    "addr:postcode":"11788",
    "addr:street":"Heller Pl",
    "iso:country":"US",
    "sg:address":"27 Heller Pl",
    "sg:city":"Hauppauge",
    "sg:classifiers":[
        {
            "category":"Shopping",
            "subcategory":"Bicycles & Sporting Goods",
            "type":"Retail Goods"
        }
    ],
    "sg:phone":"+1   ",
    "sg:postcode":"11788",
    "sg:province":"NY",
    "sg:tags":[
        "printing",
        "commercial"
    ],
    "wof:name":"Double Touch",
    "wof:placetype":"venue"
},
  "geometry": {"coordinates":[-73.208809,40.811507],"type":"Point"}
}