{
  "type": "Feature",
  "properties": {
    "iso:country":"US",
    "sg:address":"561 Riga Mumford Rd",
    "sg:city":"Churchville",
    "sg:classifiers":[
        {
            "category":"Personal",
            "subcategory":"Beauty Salon",
            "type":"Services"
        }
    ],
    "sg:phone":"+1 585 293 3677",
    "sg:postcode":"14428",
    "sg:province":"NY",
    "wof:name":"Jk Hair Designs",
    "wof:placetype":"venue"
},
  "geometry": {"coordinates":[-77.878998,43.046034],"type":"Point"}
}