{
  "type": "Feature",
  "properties": {
    "iso:country":"US",
    "sg:address":"358 Foster Ave",
    "sg:city":"Sayville",
    "sg:classifiers":[
        {
            "category":"Shopping",
            "subcategory":"Antiques",
            "type":"Retail Goods"
        }
    ],
    "sg:phone":"+1 631 589 2010",
    "sg:postcode":"11782",
    "sg:province":"NY",
    "wof:name":"Gwj Harrington Antiques",
    "wof:placetype":"venue"
},
  "geometry": {"coordinates":[-73.075631,40.725835],"type":"Point"}
}