{
  "type": "Feature",
  "properties": {
    "iso:country":"US",
    "sg:address":"8063 Canning Factory Rd",
    "sg:city":"Waterville",
    "sg:classifiers":[
        {
            "category":"Farming",
            "subcategory":"Dairy Farm",
            "type":"Manufacturing & Wholesale Goods"
        }
    ],
    "sg:phone":"+1 315 841 8075",
    "sg:postcode":"13480",
    "sg:province":"NY",
    "wof:name":"Buschor Farms",
    "wof:placetype":"venue"
},
  "geometry": {"coordinates":[-75.358306,42.936898],"type":"Point"}
}