{
  "type": "Feature",
  "properties": {
    "addr:full":"985 E 174th Street Bronx NY 10460",
    "addr:housenumber":"985",
    "addr:postcode":"10460",
    "addr:street":"E 174Th Street",
    "iso:country":"US",
    "sg:address":"985 E 174th Street",
    "sg:city":"Bronx",
    "sg:classifiers":[
        {
            "category":"Retail",
            "subcategory":"Laundry & Dry Cleaning",
            "type":"Services"
        }
    ],
    "sg:phone":"+1 718 542 7643",
    "sg:postcode":"10460",
    "sg:province":"NY",
    "wof:name":"Hill Cleaners",
    "wof:placetype":"venue"
},
  "geometry": {"coordinates":[-73.885017,40.836456],"type":"Point"}
}