{
  "type": "Feature",
  "properties": {
    "iso:country":"US",
    "sg:address":"99 Reservoir Rd",
    "sg:city":"Fort Edward",
    "sg:classifiers":[
        {
            "category":"Government",
            "subcategory":"Office",
            "type":"Public Place"
        }
    ],
    "sg:phone":"+1 518 792 7150",
    "sg:postcode":"12828",
    "sg:province":"NY",
    "sg:tags":[
        "village"
    ],
    "wof:name":"Fort Edward Village Office",
    "wof:placetype":"venue"
},
  "geometry": {"coordinates":[-73.63095199999999,43.263939],"type":"Point"}
}