{
  "type": "Feature",
  "properties": {
    "iso:country":"US",
    "sg:address":"1536 Scribner Rd",
    "sg:city":"Penfield",
    "sg:classifiers":[
        {
            "category":"Professional",
            "type":"Services"
        }
    ],
    "sg:phone":"+1 585 671 6612",
    "sg:postcode":"14526",
    "sg:province":"NY",
    "sg:tags":[
        "establishment"
    ],
    "wof:name":"Sonabilis",
    "wof:placetype":"venue"
},
  "geometry": {"coordinates":[-77.484622,43.1714],"type":"Point"}
}