{
  "type": "Feature",
  "properties": {
    "addr:full":"3 Fawn Ln Queensbury NY 12804",
    "addr:housenumber":"3",
    "addr:postcode":"12804",
    "addr:street":"Fawn Ln",
    "iso:country":"US",
    "sg:address":"3 Fawn Ln",
    "sg:city":"Queensbury",
    "sg:classifiers":[
        {
            "category":"Shopping",
            "subcategory":"Crafts & Fabrics",
            "type":"Retail Goods"
        }
    ],
    "sg:phone":"+1   ",
    "sg:postcode":"12804",
    "sg:province":"NY",
    "sg:tags":[
        "sewing"
    ],
    "wof:name":"Sew What",
    "wof:placetype":"venue"
},
  "geometry": {"coordinates":[-73.718513,43.311677],"type":"Point"}
}