{
  "type": "Feature",
  "properties": {
    "iso:country":"US",
    "sg:address":"1524 86th St",
    "sg:city":"Brooklyn",
    "sg:classifiers":[
        {
            "category":"Retail",
            "subcategory":"Repair Shop",
            "type":"Services"
        }
    ],
    "sg:phone":"+1 718 232 4127",
    "sg:postcode":"11228",
    "sg:province":"NY",
    "sg:tags":[
        "lock",
        "locksmith"
    ],
    "wof:name":"American Access Inc",
    "wof:placetype":"venue"
},
  "geometry": {"coordinates":[-74.009297,40.611282],"type":"Point"}
}