{
  "type": "Feature",
  "properties": {
    "addr:full":"394 Broadway Ave. 5th Floor Manhattan NY 10013",
    "addr:housenumber":"394;5th",
    "addr:postcode":"10013",
    "addr:street":"Broadway Ave.;Floor",
    "iso:country":"US",
    "sg:address":"394 Broadway Ave. 5th Floor",
    "sg:city":"Manhattan",
    "sg:classifiers":[
        {
            "category":"Personal",
            "type":"Services"
        }
    ],
    "sg:phone":"+1 646 783 8616",
    "sg:postcode":"10013",
    "sg:province":"NY",
    "sg:tags":[
        "party",
        "planning",
        "event"
    ],
    "sg:website":"www.greenspacesny.com/",
    "wof:name":"Green Spaces",
    "wof:placetype":"venue"
},
  "geometry": {"coordinates":[-74.002619,40.718282],"type":"Point"}
}