{
  "type": "Feature",
  "properties": {
    "addr:full":"300 E 40th Street New York NY 10016",
    "addr:housenumber":"300",
    "addr:postcode":"10016",
    "addr:street":"E 40Th Street",
    "iso:country":"US",
    "sg:address":"300 E 40th Street",
    "sg:city":"New York",
    "sg:classifiers":[
        {
            "category":"Retail",
            "subcategory":"Laundry & Dry Cleaning",
            "type":"Services"
        }
    ],
    "sg:phone":"+1 212 867 5005",
    "sg:postcode":"10016",
    "sg:province":"NY",
    "wof:name":"Valet Belevedre",
    "wof:placetype":"venue"
},
  "geometry": {"coordinates":[-73.97315999999999,40.74851],"type":"Point"}
}