{
  "type": "Feature",
  "properties": {
    "iso:country":"US",
    "sg:address":"48 Main St",
    "sg:city":"Westhampton Bch",
    "sg:classifiers":[
        {
            "category":"Banks & Credit Unions",
            "subcategory":"Bank",
            "type":"Services"
        }
    ],
    "sg:phone":"+1 631 288 4500",
    "sg:postcode":"11978",
    "sg:province":"NY",
    "sg:tags":[
        "mortgage",
        "loan",
        "broker",
        "real estate"
    ],
    "wof:name":"South Fork Mortgage Corp",
    "wof:placetype":"venue"
},
  "geometry": {"coordinates":[-72.64587,40.808877],"type":"Point"}
}