{
  "type": "Feature",
  "properties": {
    "addr:full":"101 Ave U Brooklyn NY 11223",
    "addr:housenumber":"101",
    "addr:postcode":"11223",
    "addr:street":"Ave U",
    "iso:country":"US",
    "sg:address":"101 Ave U",
    "sg:city":"Brooklyn",
    "sg:classifiers":[
        {
            "category":"Home & Garden",
            "subcategory":"Furniture",
            "type":"Retail Goods"
        }
    ],
    "sg:phone":"+1   ",
    "sg:postcode":"11223",
    "sg:province":"NY",
    "wof:name":"Global Design Furniture Inc",
    "wof:placetype":"venue"
},
  "geometry": {"coordinates":[-73.980879,40.59619],"type":"Point"}
}