{
  "type": "Feature",
  "properties": {
    "addr:full":"267 Broadway New York NY 10007",
    "addr:housenumber":"267",
    "addr:postcode":"10007",
    "addr:street":"Broadway",
    "iso:country":"US",
    "sg:address":"267 Broadway",
    "sg:city":"New York",
    "sg:classifiers":[
        {
            "category":"Professional",
            "subcategory":"Lawyer & Legal Services",
            "type":"Services"
        }
    ],
    "sg:phone":"+1 212 267 9090",
    "sg:postcode":"10007",
    "sg:province":"NY",
    "wof:name":"Salles Stuart Law Office",
    "wof:placetype":"venue"
},
  "geometry": {"coordinates":[-74.006542,40.713931],"type":"Point"}
}