{
  "type": "Feature",
  "properties": {
    "addr:full":"781 4th Ave Brooklyn NY 11232",
    "addr:housenumber":"781",
    "addr:postcode":"11232",
    "addr:street":"4Th Ave",
    "iso:country":"US",
    "sg:address":"781 4th Ave",
    "sg:city":"Brooklyn",
    "sg:classifiers":[
        {
            "category":"Travel",
            "subcategory":"Travel Agent",
            "type":"Entertainment"
        }
    ],
    "sg:phone":"+1   ",
    "sg:postcode":"11232",
    "sg:province":"NY",
    "sg:tags":[
        "agency"
    ],
    "wof:name":"Pacific Travel",
    "wof:placetype":"venue"
},
  "geometry": {"coordinates":[-73.998598,40.659912],"type":"Point"}
}