{
  "type": "Feature",
  "properties": {
    "iso:country":"US",
    "sg:address":"13 Oakwood Rd",
    "sg:city":"Delmar",
    "sg:classifiers":[
        {
            "category":"Building & Trades",
            "subcategory":"Construction",
            "type":"Services"
        }
    ],
    "sg:phone":"+1 518 439 6300",
    "sg:postcode":"12054",
    "sg:province":"NY",
    "sg:tags":[
        "general",
        "contractor"
    ],
    "wof:name":"Whitney & Ryan General Contr",
    "wof:placetype":"venue"
},
  "geometry": {"coordinates":[-73.805547,42.619819],"type":"Point"}
}