{
  "type": "Feature",
  "properties": {
    "addr:full":"59 W 12th Street New York NY 10011",
    "addr:housenumber":"59",
    "addr:postcode":"10011",
    "addr:street":"W 12Th Street",
    "iso:country":"US",
    "sg:address":"59 W 12th Street",
    "sg:city":"New York",
    "sg:classifiers":[
        {
            "category":"Health Services",
            "subcategory":"Doctor",
            "type":"Services"
        }
    ],
    "sg:phone":"+1 646 638 1528",
    "sg:postcode":"10011",
    "sg:province":"NY",
    "wof:name":"Gualtieri Nicholas MD",
    "wof:placetype":"venue"
},
  "geometry": {"coordinates":[-73.996667,40.735559],"type":"Point"}
}