{
  "type": "Feature",
  "properties": {
    "addr:full":"989 Joan St Massapequa NY 11758",
    "addr:housenumber":"989",
    "addr:postcode":"11758",
    "addr:street":"Joan St",
    "iso:country":"US",
    "sg:address":"989 Joan St",
    "sg:city":"Massapequa",
    "sg:classifiers":[
        {
            "category":"Building & Trades",
            "subcategory":"Construction",
            "type":"Services"
        }
    ],
    "sg:phone":"+1 516 579 5096",
    "sg:postcode":"11758",
    "sg:province":"NY",
    "wof:name":"Gal-Gil Restaurant Contracting",
    "wof:placetype":"venue"
},
  "geometry": {"coordinates":[-73.480774,40.704612],"type":"Point"}
}