{
  "type": "Feature",
  "properties": {
    "iso:country":"US",
    "sg:address":"1136 State Hwy 9d",
    "sg:city":"Wappingers Falls",
    "sg:classifiers":[
        {
            "category":"Professional",
            "subcategory":"Management & Consulting",
            "type":"Services"
        }
    ],
    "sg:phone":"+1 845 297 4848",
    "sg:postcode":"12590",
    "sg:province":"NY",
    "sg:tags":[
        "consultant",
        "business"
    ],
    "wof:name":"Glocal Vantage Hudson Valley",
    "wof:placetype":"venue"
},
  "geometry": {"coordinates":[-73.964733,41.527071],"type":"Point"}
}