{
  "type": "Feature",
  "properties": {
    "addr:full":"4985 Long Acre Dr Syracuse NY 13215",
    "addr:housenumber":"4985",
    "addr:postcode":"13215",
    "addr:street":"Long Acre Dr",
    "iso:country":"US",
    "sg:address":"4985 Long Acre Dr",
    "sg:city":"Syracuse",
    "sg:classifiers":[
        {
            "category":"Manufacturing",
            "subcategory":"Printing",
            "type":"Manufacturing & Wholesale Goods"
        }
    ],
    "sg:phone":"+1   ",
    "sg:postcode":"13215",
    "sg:province":"NY",
    "sg:tags":[
        "publishing"
    ],
    "wof:name":"Niedt Write Ink Inc",
    "wof:placetype":"venue"
},
  "geometry": {"coordinates":[-76.17106200000001,43.003752],"type":"Point"}
}