{
  "type": "Feature",
  "properties": {
    "addr:full":"98102 Queens Boulevard Rego Park NY 11374",
    "addr:housenumber":"98102",
    "addr:postcode":"11374",
    "addr:street":"Queens Boulevard",
    "iso:country":"US",
    "sg:address":"98102 Queens Boulevard",
    "sg:city":"Rego Park",
    "sg:classifiers":[
        {
            "category":"Restaurant",
            "type":"Food & Drink"
        }
    ],
    "sg:phone":"+1 718 897 4829",
    "sg:postcode":"11374",
    "sg:province":"NY",
    "sg:tags":[
        "kosher",
        "middle",
        "eastern"
    ],
    "sg:website":"www.on-the-grill.com",
    "wof:name":"On the Grill B & D",
    "wof:placetype":"venue"
},
  "geometry": {"coordinates":[-73.855125,40.727395],"type":"Point"}
}