{
  "type": "Feature",
  "properties": {
    "addr:full":"2084 Grand Ave Bronx NY 10453",
    "addr:housenumber":"2084",
    "addr:postcode":"10453",
    "addr:street":"Grand Ave",
    "iso:country":"US",
    "sg:address":"2084 Grand Ave",
    "sg:city":"Bronx",
    "sg:classifiers":[
        {
            "category":"Retail",
            "subcategory":"Repair Shop",
            "type":"Services"
        }
    ],
    "sg:phone":"+1 718 685 5787",
    "sg:postcode":"10453",
    "sg:province":"NY",
    "sg:tags":[
        "lock",
        "locksmith"
    ],
    "wof:name":"Emergency Locksmith",
    "wof:placetype":"venue"
},
  "geometry": {"coordinates":[-73.90729899999999,40.856404],"type":"Point"}
}