{
  "type": "Feature",
  "properties": {
    "addr:full":"100 Motor Pkwy Hauppauge NY 11788",
    "addr:housenumber":"100",
    "addr:postcode":"11788",
    "addr:street":"Motor Pkwy",
    "iso:country":"US",
    "sg:address":"100 Motor Pkwy",
    "sg:city":"Hauppauge",
    "sg:classifiers":[
        {
            "category":"Wholesale",
            "subcategory":"Electrical",
            "type":"Manufacturing & Wholesale Goods"
        }
    ],
    "sg:phone":"+1 631 300 3505",
    "sg:postcode":"11788",
    "sg:province":"NY",
    "sg:tags":[
        "electric",
        "motor"
    ],
    "wof:name":"100 Motor Parkway Assoc",
    "wof:placetype":"venue"
},
  "geometry": {"coordinates":[-73.246793,40.807289],"type":"Point"}
}