{
  "type": "Feature",
  "properties": {
    "addr:full":"75 Whittier Rd Rochester NY 14624",
    "addr:housenumber":"75",
    "addr:postcode":"14624",
    "addr:street":"Whittier Rd",
    "iso:country":"US",
    "sg:address":"75 Whittier Rd",
    "sg:city":"Rochester",
    "sg:classifiers":[
        {
            "category":"Education",
            "subcategory":"Preschool",
            "type":"Public Place"
        }
    ],
    "sg:phone":"+1 585 594 9481",
    "sg:postcode":"14624",
    "sg:province":"NY",
    "sg:tags":[
        "school",
        "nursery"
    ],
    "sg:website":"http://www.learninggroup.com",
    "wof:name":"Childtime Childcare, Inc",
    "wof:placetype":"venue"
},
  "geometry": {"coordinates":[-77.76532,43.136089],"type":"Point"}
}