{
  "type": "Feature",
  "properties": {
    "iso:country":"US",
    "sg:address":"664 Stoneleigh Ave",
    "sg:city":"Carmel",
    "sg:classifiers":[
        {
            "category":"Health Services",
            "subcategory":"Doctor",
            "type":"Services"
        }
    ],
    "sg:phone":"+1 845 279 3300",
    "sg:postcode":"10512",
    "sg:province":"NY",
    "sg:tags":[
        "obstetrician",
        "gynecologist"
    ],
    "wof:name":"Vosko Susan MD",
    "wof:placetype":"venue"
},
  "geometry": {"coordinates":[-73.66419999999999,41.385899],"type":"Point"}
}