{
  "type": "Feature",
  "properties": {
    "iso:country":"US",
    "sg:address":"2500 Pond Vw",
    "sg:city":"Castleton On Hudson",
    "sg:classifiers":[
        {
            "category":"Social Services",
            "subcategory":"Child Care",
            "type":"Services"
        }
    ],
    "sg:phone":"+1 518 477 7103",
    "sg:postcode":"12033",
    "sg:province":"NY",
    "sg:tags":[
        "kindergarten",
        "academic",
        "school",
        "day"
    ],
    "sg:website":"www.storyplacepreschool.com",
    "wof:name":"Story Place Preschool",
    "wof:placetype":"venue"
},
  "geometry": {"coordinates":[-73.670998,42.583599],"type":"Point"}
}