{
  "type": "Feature",
  "properties": {
    "addr:full":"903 Lexington Ave New York NY 10021",
    "addr:housenumber":"903",
    "addr:postcode":"10021",
    "addr:street":"Lexington Ave",
    "iso:country":"US",
    "sg:address":"903 Lexington Ave",
    "sg:city":"New York",
    "sg:classifiers":[
        {
            "category":"Health Services",
            "subcategory":"Doctor",
            "type":"Services"
        }
    ],
    "sg:phone":"+1 212 639 9161",
    "sg:postcode":"10021",
    "sg:province":"NY",
    "wof:name":"Levy Stephen M MD",
    "wof:placetype":"venue"
},
  "geometry": {"coordinates":[-73.9645,40.767502],"type":"Point"}
}