{
  "type": "Feature",
  "properties": {
    "iso:country":"US",
    "sg:address":"220 New Main St",
    "sg:city":"Yonkers",
    "sg:classifiers":[
        {
            "category":"Professional",
            "subcategory":"Management & Consulting",
            "type":"Services"
        }
    ],
    "sg:phone":"+1 914 375 8044",
    "sg:postcode":"10701",
    "sg:province":"NY",
    "wof:name":"Daisys Management",
    "wof:placetype":"venue"
},
  "geometry": {"coordinates":[-73.89560400000001,40.930767],"type":"Point"}
}