{
  "type": "Feature",
  "properties": {
    "iso:country":"US",
    "sg:address":"46 Riverside Dr",
    "sg:city":"Binghamton",
    "sg:classifiers":[
        {
            "category":"Health Services",
            "subcategory":"Health Practitioner",
            "type":"Services"
        }
    ],
    "sg:phone":"+1 607 772 1766",
    "sg:postcode":"13905",
    "sg:province":"NY",
    "sg:tags":[
        "psychologist"
    ],
    "wof:name":"Riverside Group",
    "wof:placetype":"venue"
},
  "geometry": {"coordinates":[-75.923523,42.092492],"type":"Point"}
}