{
  "type": "Feature",
  "properties": {
    "iso:country":"US",
    "sg:address":"38 Daffodil Dr",
    "sg:city":"Farmingdale",
    "sg:classifiers":[
        {
            "category":"Real Estate",
            "subcategory":"Developer",
            "type":"Services"
        }
    ],
    "sg:phone":"+1 516 445 1666",
    "sg:postcode":"11735",
    "sg:province":"NY",
    "wof:name":"Aban Development",
    "wof:placetype":"venue"
},
  "geometry": {"coordinates":[-73.435367,40.746847],"type":"Point"}
}