{
  "type": "Feature",
  "properties": {
    "addr:full":"127 W 56 St New York NY 10019",
    "addr:housenumber":"127",
    "addr:postcode":"10019",
    "addr:street":"W 56 St",
    "iso:country":"US",
    "sg:address":"127 W 56 St",
    "sg:city":"New York",
    "sg:classifiers":[
        {
            "category":"Communications",
            "subcategory":"Film & Video Production",
            "type":"Services"
        }
    ],
    "sg:phone":"+1 212 582 2803",
    "sg:postcode":"10019",
    "sg:province":"NY",
    "sg:tags":[
        "audio"
    ],
    "wof:name":"Arena Pictures Inc",
    "wof:placetype":"venue"
},
  "geometry": {"coordinates":[-73.979919,40.764591],"type":"Point"}
}