{
  "type": "Feature",
  "properties": {
    "iso:country":"US",
    "sg:address":"430 Plainview Rd",
    "sg:city":"Hicksville",
    "sg:classifiers":[
        {
            "category":"Autos & Motor Vehicles",
            "subcategory":"Automobile Sales",
            "type":"Retail Goods"
        }
    ],
    "sg:phone":"+1 516 938 0160",
    "sg:postcode":"11801",
    "sg:province":"NY",
    "sg:tags":[
        "new",
        "car"
    ],
    "wof:name":"Audi Walters Auto Group",
    "wof:placetype":"venue"
},
  "geometry": {"coordinates":[-73.503658,40.769491],"type":"Point"}
}