{
  "type": "Feature",
  "properties": {
    "addr:full":"23 Woodlawn Ave Yonkers NY 10704",
    "addr:housenumber":"23",
    "addr:postcode":"10704",
    "addr:street":"Woodlawn Ave",
    "iso:country":"US",
    "sg:address":"23 Woodlawn Ave",
    "sg:city":"Yonkers",
    "sg:classifiers":[
        {
            "category":"Real Estate",
            "subcategory":"Architect",
            "type":"Services"
        }
    ],
    "sg:phone":"+1 914 237 5070",
    "sg:postcode":"10704",
    "sg:province":"NY",
    "wof:name":"Stefani Group",
    "wof:placetype":"venue"
},
  "geometry": {"coordinates":[-73.86392499999999,40.904019],"type":"Point"}
}