{
  "type": "Feature",
  "properties": {
    "addr:full":"19215 Linden Blvd Saint Albans NY 11412",
    "addr:housenumber":"19215",
    "addr:postcode":"11412",
    "addr:street":"Linden Blvd",
    "iso:country":"US",
    "sg:address":"19215 Linden Blvd",
    "sg:city":"Saint Albans",
    "sg:classifiers":[
        {
            "category":"Restaurant",
            "type":"Food & Drink"
        }
    ],
    "sg:menulink":"http://www.allmenus.com/ny/queens/236597-taste-of-china/menu/",
    "sg:phone":"+1 718 528 4717",
    "sg:postcode":"11412",
    "sg:province":"NY",
    "sg:tags":[
        "asian",
        "chinese"
    ],
    "wof:name":"Taste Of China",
    "wof:placetype":"venue"
},
  "geometry": {"coordinates":[-73.759288,40.692507],"type":"Point"}
}