{
  "type": "Feature",
  "properties": {
    "iso:country":"US",
    "sg:address":"1 Powelton Rd",
    "sg:city":"Newburgh",
    "sg:classifiers":[
        {
            "category":"Professional",
            "subcategory":"Lawyer & Legal Services",
            "type":"Services"
        }
    ],
    "sg:phone":"+1 845 569 1400",
    "sg:postcode":"12550",
    "sg:province":"NY",
    "wof:name":"Dennis Kenny Atty",
    "wof:placetype":"venue"
},
  "geometry": {"coordinates":[-74.024902,41.521198],"type":"Point"}
}