{
  "type": "Feature",
  "properties": {
    "iso:country":"US",
    "sg:address":"1672 86th Street",
    "sg:city":"Brooklyn",
    "sg:classifiers":[
        {
            "category":"Retail",
            "subcategory":"Auto Rental",
            "type":"Services"
        }
    ],
    "sg:phone":"+1 718 331 9007",
    "sg:postcode":"11214",
    "sg:province":"NY",
    "sg:tags":[
        "car"
    ],
    "wof:name":"Hellex Car Rental Systems",
    "wof:placetype":"venue"
},
  "geometry": {"coordinates":[-74.005606,40.608908],"type":"Point"}
}