{
  "type": "Feature",
  "properties": {
    "iso:country":"US",
    "sg:address":"3401 Jerome Ave",
    "sg:city":"Bronx",
    "sg:classifiers":[
        {
            "category":"Food & Beverages",
            "subcategory":"Candy",
            "type":"Retail Goods"
        }
    ],
    "sg:phone":"+1 718 881 0947",
    "sg:postcode":"10467",
    "sg:province":"NY",
    "sg:tags":[
        "confectionery"
    ],
    "wof:name":"J S Newstand",
    "wof:placetype":"venue"
},
  "geometry": {"coordinates":[-73.88352399999999,40.880828],"type":"Point"}
}