{
  "type": "Feature",
  "properties": {
    "addr:full":"95 Madison Ave New York NY 10016",
    "addr:housenumber":"95",
    "addr:postcode":"10016",
    "addr:street":"Madison Ave",
    "iso:country":"US",
    "sg:address":"95 Madison Ave",
    "sg:city":"New York",
    "sg:classifiers":[
        {
            "category":"Professional",
            "subcategory":"Art Services",
            "type":"Services"
        }
    ],
    "sg:phone":"+1 212 213 2224",
    "sg:postcode":"10016",
    "sg:province":"NY",
    "sg:tags":[
        "graphic",
        "designer"
    ],
    "sg:website":"www.deplano.com",
    "wof:name":"De Plano Design",
    "wof:placetype":"venue"
},
  "geometry": {"coordinates":[-73.98569500000001,40.744008],"type":"Point"}
}