{
  "type": "Feature",
  "properties": {
    "addr:full":"165 E 56 St New York NY 10022",
    "addr:housenumber":"165;56",
    "addr:postcode":"10022",
    "addr:street":"E;St",
    "iso:country":"US",
    "sg:address":"165 E 56 St",
    "sg:city":"New York",
    "sg:classifiers":[
        {
            "category":"Organizations",
            "subcategory":"Non-profit Organization",
            "type":"Services"
        }
    ],
    "sg:phone":"+1 212 870 2226",
    "sg:postcode":"10022",
    "sg:province":"NY",
    "wof:name":"Interns For Peace",
    "wof:placetype":"venue"
},
  "geometry": {"coordinates":[-73.968513,40.759935],"type":"Point"}
}