{
  "type": "Feature",
  "properties": {
    "iso:country":"US",
    "sg:address":"225 Lenox Ave",
    "sg:city":"New York",
    "sg:classifiers":[
        {
            "category":"Organizations",
            "subcategory":"Religious Organization",
            "type":"Services"
        }
    ],
    "sg:phone":"+1 212 222 0470",
    "sg:postcode":"10027",
    "sg:province":"NY",
    "sg:tags":[
        "church"
    ],
    "wof:name":"Ebenezer Gospel Tabernacle",
    "wof:placetype":"venue"
},
  "geometry": {"coordinates":[-73.947042,40.805736],"type":"Point"}
}