{
  "type": "Feature",
  "properties": {
    "iso:country":"US",
    "sg:address":"1140 Bronx River Ave",
    "sg:city":"Bronx",
    "sg:classifiers":[
        {
            "category":"Real Estate",
            "subcategory":"Real Estate Agent",
            "type":"Services"
        }
    ],
    "sg:phone":"+1 718 585 7743",
    "sg:postcode":"10472",
    "sg:province":"NY",
    "wof:name":"J & L Holding Corp",
    "wof:placetype":"venue"
},
  "geometry": {"coordinates":[-73.883195,40.827108],"type":"Point"}
}