{
  "type": "Feature",
  "properties": {
    "addr:full":"599 Holland Rd Arcade NY 14009",
    "addr:housenumber":"599",
    "addr:postcode":"14009",
    "addr:street":"Holland Rd",
    "iso:country":"US",
    "sg:address":"599 Holland Rd",
    "sg:city":"Arcade",
    "sg:classifiers":[
        {
            "category":"Building & Trades",
            "subcategory":"Electrical",
            "type":"Services"
        }
    ],
    "sg:phone":"+1 585 457 3217",
    "sg:postcode":"14009",
    "sg:province":"NY",
    "sg:tags":[
        "electrical",
        "contractor"
    ],
    "wof:name":"Francis A Simons & Associates",
    "wof:placetype":"venue"
},
  "geometry": {"coordinates":[-78.438213,42.673108],"type":"Point"}
}