{
  "type": "Feature",
  "properties": {
    "iso:country":"US",
    "sg:address":"380 Hempstead Ave Ste 2",
    "sg:city":"West Hempstead",
    "sg:classifiers":[
        {
            "category":"Health Services",
            "subcategory":"Dentist",
            "type":"Services"
        }
    ],
    "sg:phone":"+1 516 538 7433",
    "sg:postcode":"11552",
    "sg:province":"NY",
    "sg:tags":[
        "pediatric"
    ],
    "wof:name":"Miller & Rosenfeld DMD DDS",
    "wof:placetype":"venue"
},
  "geometry": {"coordinates":[-73.651659,40.698627],"type":"Point"}
}