{
  "type": "Feature",
  "properties": {
    "iso:country":"US",
    "sg:address":"5900 Decatur St",
    "sg:city":"Flushing",
    "sg:classifiers":[
        {
            "category":"Wholesale",
            "subcategory":"Durable Goods & Equipment",
            "type":"Manufacturing & Wholesale Goods"
        }
    ],
    "sg:phone":"+1 718 366 6888",
    "sg:postcode":"11385",
    "sg:province":"NY",
    "sg:tags":[
        "importer"
    ],
    "wof:name":"At Home USA",
    "wof:placetype":"venue"
},
  "geometry": {"coordinates":[-73.896096,40.700666],"type":"Point"}
}