{
  "type": "Feature",
  "properties": {
    "addr:full":"720 E 89th St Brooklyn NY 11236",
    "addr:housenumber":"720",
    "addr:postcode":"11236",
    "addr:street":"E 89Th St",
    "iso:country":"US",
    "sg:address":"720 E 89th St",
    "sg:city":"Brooklyn",
    "sg:classifiers":[
        {
            "category":"Real Estate",
            "subcategory":"Real Estate Agent",
            "type":"Services"
        }
    ],
    "sg:phone":"+1 718 953 6031",
    "sg:postcode":"11236",
    "sg:province":"NY",
    "wof:name":"Orinduik Development Corp",
    "wof:placetype":"venue"
},
  "geometry": {"coordinates":[-73.906927,40.639839],"type":"Point"}
}