{
  "type": "Feature",
  "properties": {
    "addr:full":"6 Technology Dr Ste 200 East Setauket NY 11733",
    "addr:housenumber":"6",
    "addr:postcode":"11733",
    "addr:street":"Technology Dr Ste 200 East",
    "iso:country":"US",
    "sg:address":"6 Technology Dr Ste 200",
    "sg:city":"East Setauket",
    "sg:classifiers":[
        {
            "category":"Health Services",
            "subcategory":"Doctor",
            "type":"Services"
        }
    ],
    "sg:phone":"+1 631 444 4686",
    "sg:postcode":"11733",
    "sg:province":"NY",
    "wof:name":"Budnick Lauri MD",
    "wof:placetype":"venue"
},
  "geometry": {"coordinates":[-73.086281,40.896721],"type":"Point"}
}