{
  "type": "Feature",
  "properties": {
    "iso:country":"US",
    "sg:address":"184 Brookside Ave",
    "sg:city":"Amsterdam",
    "sg:classifiers":[
        {
            "category":"Professional",
            "subcategory":"Computer Services",
            "type":"Services"
        }
    ],
    "sg:phone":"+1   ",
    "sg:postcode":"12010",
    "sg:province":"NY",
    "sg:tags":[
        "related"
    ],
    "wof:name":"Jma Ventures",
    "wof:placetype":"venue"
},
  "geometry": {"coordinates":[-74.182125,42.948131],"type":"Point"}
}