{
  "type": "Feature",
  "properties": {
    "addr:full":"4322 Buffalo Rd North Chili NY 14514",
    "addr:housenumber":"4322",
    "addr:postcode":"14514",
    "addr:street":"Buffalo Rd",
    "iso:country":"US",
    "sg:address":"4322 Buffalo Rd",
    "sg:city":"North Chili",
    "sg:classifiers":[
        {
            "category":"Social Services",
            "type":"Services"
        }
    ],
    "sg:phone":"+1 585 594 4800",
    "sg:postcode":"14514",
    "sg:province":"NY",
    "sg:tags":[
        "counselor",
        "marriage",
        "family"
    ],
    "wof:name":"Agape Counseling Associates",
    "wof:placetype":"venue"
},
  "geometry": {"coordinates":[-77.79947799999999,43.122744],"type":"Point"}
}