{
  "type": "Feature",
  "properties": {
    "addr:full":"108 S Washington St Herkimer NY 13350",
    "addr:housenumber":"108",
    "addr:postcode":"13350",
    "addr:street":"S Washington St",
    "iso:country":"US",
    "sg:address":"108 S Washington St",
    "sg:city":"Herkimer",
    "sg:classifiers":[
        {
            "category":"Personal",
            "subcategory":"Beauty Salon",
            "type":"Services"
        }
    ],
    "sg:phone":"+1 315 866 6865",
    "sg:postcode":"13350",
    "sg:province":"NY",
    "wof:name":"Endless Summer Tanning & Bty",
    "wof:placetype":"venue"
},
  "geometry": {"coordinates":[-74.98441200000001,43.025863],"type":"Point"}
}