{
  "type": "Feature",
  "properties": {
    "addr:full":"901 Woodland Ave Schenectady NY 12309",
    "addr:housenumber":"901",
    "addr:postcode":"12309",
    "addr:street":"Woodland Ave",
    "iso:country":"US",
    "sg:address":"901 Woodland Ave",
    "sg:city":"Schenectady",
    "sg:classifiers":[
        {
            "category":"Food & Beverages",
            "subcategory":"Specialty",
            "type":"Retail Goods"
        }
    ],
    "sg:phone":"+1   ",
    "sg:postcode":"12309",
    "sg:province":"NY",
    "wof:name":"Brixton Hill Ltd",
    "wof:placetype":"venue"
},
  "geometry": {"coordinates":[-73.90506499999999,42.804936],"type":"Point"}
}