{
  "type": "Feature",
  "properties": {
    "addr:full":"566 Grand Street New York NY 10002",
    "addr:housenumber":"566",
    "addr:postcode":"10002",
    "addr:street":"Grand Street",
    "iso:country":"US",
    "sg:address":"566 Grand Street",
    "sg:city":"New York",
    "sg:classifiers":[
        {
            "category":"Personal",
            "subcategory":"Shoe Repair & Shine",
            "type":"Services"
        }
    ],
    "sg:phone":"+1 718 782 0074",
    "sg:postcode":"10002",
    "sg:province":"NY",
    "wof:name":"Kims Shoe Repr",
    "wof:placetype":"venue"
},
  "geometry": {"coordinates":[-73.98018500000001,40.713921],"type":"Point"}
}