{
  "type": "Feature",
  "properties": {
    "addr:full":"148 N Maple St Massapequa NY 11758",
    "addr:housenumber":"148",
    "addr:postcode":"11758",
    "addr:street":"N Maple St",
    "iso:country":"US",
    "sg:address":"148 N Maple St",
    "sg:city":"Massapequa",
    "sg:classifiers":[
        {
            "category":"Shopping",
            "subcategory":"Crafts & Fabrics",
            "type":"Retail Goods"
        }
    ],
    "sg:phone":"+1 516 541 5757",
    "sg:postcode":"11758",
    "sg:province":"NY",
    "sg:tags":[
        "material",
        "needlework"
    ],
    "wof:name":"Bunka Embroidery Studio",
    "wof:placetype":"venue"
},
  "geometry": {"coordinates":[-73.458006,40.701009],"type":"Point"}
}