{
  "type": "Feature",
  "properties": {
    "addr:full":"3226 Richmond Road Staten Island NY 10306",
    "addr:housenumber":"3226",
    "addr:postcode":"10306",
    "addr:street":"Richmond Road",
    "iso:country":"US",
    "sg:address":"3226 Richmond Road",
    "sg:city":"Staten Island",
    "sg:classifiers":[
        {
            "category":"Health Services",
            "subcategory":"Dentist",
            "type":"Services"
        }
    ],
    "sg:phone":"+1 718 668 3636",
    "sg:postcode":"10306",
    "sg:province":"NY",
    "wof:name":"Vaynshteyn Dental",
    "wof:placetype":"venue"
},
  "geometry": {"coordinates":[-74.128156,40.575177],"type":"Point"}
}