{
  "type": "Feature",
  "properties": {
    "addr:full":"239 Bryant St Buffalo NY 14222",
    "addr:housenumber":"239",
    "addr:postcode":"14222",
    "addr:street":"Bryant St",
    "iso:country":"US",
    "sg:address":"239 Bryant St",
    "sg:city":"Buffalo",
    "sg:classifiers":[
        {
            "category":"Professional",
            "subcategory":"Research",
            "type":"Services"
        }
    ],
    "sg:phone":"+1 716 881 6407",
    "sg:postcode":"14222",
    "sg:province":"NY",
    "sg:tags":[
        "laboratory"
    ],
    "wof:name":"Meth-Path Laboratories",
    "wof:placetype":"venue"
},
  "geometry": {"coordinates":[-78.87606,42.908984],"type":"Point"}
}