{
  "type": "Feature",
  "properties": {
    "addr:full":"614 Columbia Tpke East Greenbush NY 12061",
    "addr:housenumber":"614",
    "addr:postcode":"12061",
    "addr:street":"Columbia Tpke",
    "iso:country":"US",
    "sg:address":"614 Columbia Tpke",
    "sg:city":"East Greenbush",
    "sg:classifiers":[
        {
            "category":"Shopping",
            "subcategory":"Pharmacy",
            "type":"Retail Goods"
        }
    ],
    "sg:phone":"+1 518 479 4230",
    "sg:postcode":"12061",
    "sg:province":"NY",
    "sg:tags":[
        "drugstore"
    ],
    "wof:name":"Rite Aid",
    "wof:placetype":"venue"
},
  "geometry": {"coordinates":[-73.708603,42.597301],"type":"Point"}
}