{
  "type": "Feature",
  "properties": {
    "addr:full":"1686 Randall Ave Apt 6G Bronx NY 10473",
    "addr:housenumber":"1686",
    "addr:postcode":"10473",
    "addr:street":"Randall Ave Apt 6G",
    "iso:country":"US",
    "sg:address":"1686 Randall Ave Apt 6G",
    "sg:city":"Bronx",
    "sg:classifiers":[
        {
            "category":"Professional",
            "subcategory":"Engineering",
            "type":"Services"
        },
        {
            "category":"Manufacturing",
            "subcategory":"Electronics",
            "type":"Manufacturing & Wholesale Goods"
        }
    ],
    "sg:phone":"+1 646 239 1560",
    "sg:postcode":"10473",
    "sg:province":"NY",
    "sg:tags":[
        "control",
        "system",
        "automation",
        "electronic",
        "controls-manufacturers",
        "engineer"
    ],
    "wof:name":"J.V. Electronics, Inc.",
    "wof:placetype":"venue"
},
  "geometry": {"coordinates":[-73.86715100000001,40.816404],"type":"Point"}
}