{
  "type": "Feature",
  "properties": {
    "addr:full":"400 Garden City Plz Ste 100 Garden City NY 11530",
    "addr:housenumber":"400",
    "addr:postcode":"11530",
    "addr:street":"Garden;Ste 100",
    "iso:country":"US",
    "sg:address":"400 Garden City Plz Ste 100",
    "sg:city":"Garden City",
    "sg:classifiers":[
        {
            "category":"Professional",
            "subcategory":"Accounting & Tax Preparation",
            "type":"Services"
        }
    ],
    "sg:phone":"+1 516 256 7100",
    "sg:postcode":"11530",
    "sg:province":"NY",
    "sg:tags":[
        "accountant"
    ],
    "sg:website":"www.cpabtc.com",
    "wof:name":"Biscotti Toback & Co PC CPAs",
    "wof:placetype":"venue"
},
  "geometry": {"coordinates":[-73.61196,40.735714],"type":"Point"}
}