{
  "type": "Feature",
  "properties": {
    "iso:country":"US",
    "sg:address":"201 E 67 St",
    "sg:city":"New York",
    "sg:classifiers":[
        {
            "category":"Professional",
            "type":"Services"
        }
    ],
    "sg:phone":"+1 212 879 5044",
    "sg:postcode":"10065",
    "sg:province":"NY",
    "sg:tags":[
        "establishment"
    ],
    "wof:name":"Bellrock Development Ctr",
    "wof:placetype":"venue"
},
  "geometry": {"coordinates":[-73.96108,40.765778],"type":"Point"}
}