{
  "type": "Feature",
  "properties": {
    "iso:country":"US",
    "sg:address":"575 Lexington Ave",
    "sg:city":"New York",
    "sg:classifiers":[
        {
            "category":"Manufacturing",
            "subcategory":"Printing",
            "type":"Manufacturing & Wholesale Goods"
        }
    ],
    "sg:phone":"+1 212 230 0200",
    "sg:postcode":"10022",
    "sg:province":"NY",
    "sg:tags":[
        "publisher"
    ],
    "wof:name":"Curtco Publishing",
    "wof:placetype":"venue"
},
  "geometry": {"coordinates":[-73.971451,40.757749],"type":"Point"}
}