{
  "type": "Feature",
  "properties": {
    "iso:country":"US",
    "sg:address":"5573 Water St",
    "sg:city":"Lowville",
    "sg:classifiers":[
        {
            "category":"Organizations",
            "subcategory":"Religious Organization",
            "type":"Services"
        }
    ],
    "sg:phone":"+1 315 346 1683",
    "sg:postcode":"13367",
    "sg:province":"NY",
    "sg:tags":[
        "church"
    ],
    "sg:website":"www.word-of-grace.com",
    "wof:name":"Rhema Fellowship",
    "wof:placetype":"venue"
},
  "geometry": {"coordinates":[-75.483064,43.784377],"type":"Point"}
}