{
  "type": "Feature",
  "properties": {
    "addr:full":"1068 Hicksville Rd Massapequa NY 11758",
    "addr:housenumber":"1068",
    "addr:postcode":"11758",
    "addr:street":"Hicksville Rd",
    "iso:country":"US",
    "sg:address":"1068 Hicksville Rd",
    "sg:city":"Massapequa",
    "sg:classifiers":[
        {
            "category":"Health Services",
            "subcategory":"Doctor",
            "type":"Services"
        }
    ],
    "sg:phone":"+1 516 798 3808",
    "sg:postcode":"11758",
    "sg:province":"NY",
    "sg:tags":[
        "dentist"
    ],
    "wof:name":"Stutman Khalida",
    "wof:placetype":"venue"
},
  "geometry": {"coordinates":[-73.481807,40.700023],"type":"Point"}
}