{
  "type": "Feature",
  "properties": {
    "iso:country":"US",
    "sg:address":"17 Squadron Blvd",
    "sg:city":"New City",
    "sg:classifiers":[
        {
            "category":"Banks & Credit Unions",
            "subcategory":"Investment Brokerage",
            "type":"Services"
        }
    ],
    "sg:phone":"+1 845 634 6050",
    "sg:postcode":"10956",
    "sg:province":"NY",
    "sg:tags":[
        "consultant",
        "planning",
        "financial"
    ],
    "wof:name":"Creative Financial Planning",
    "wof:placetype":"venue"
},
  "geometry": {"coordinates":[-73.98285300000001,41.157315],"type":"Point"}
}