{
  "type": "Feature",
  "properties": {
    "addr:full":"1471 Westchester Ave Bronx NY 10472",
    "addr:housenumber":"1471",
    "addr:postcode":"10472",
    "addr:street":"Westchester Ave",
    "iso:country":"US",
    "sg:address":"1471 Westchester Ave",
    "sg:city":"Bronx",
    "sg:classifiers":[
        {
            "category":"Retail",
            "subcategory":"Repair Shop",
            "type":"Services"
        }
    ],
    "sg:phone":"+1 718 887 2273",
    "sg:postcode":"10472",
    "sg:province":"NY",
    "sg:tags":[
        "lock",
        "locksmith"
    ],
    "wof:name":"7 Day Emergency 24 Hr Lcksmth",
    "wof:placetype":"venue"
},
  "geometry": {"coordinates":[-73.88144699999999,40.828464],"type":"Point"}
}