{
  "type": "Feature",
  "properties": {
    "addr:full":"326 Foster Avenue Brooklyn NY 11230",
    "addr:housenumber":"326",
    "addr:postcode":"11230",
    "addr:street":"Foster Avenue",
    "iso:country":"US",
    "sg:address":"326 Foster Avenue",
    "sg:city":"Brooklyn",
    "sg:classifiers":[
        {
            "category":"Building & Trades",
            "subcategory":"Construction",
            "type":"Services"
        }
    ],
    "sg:phone":"+1 718 854 1988",
    "sg:postcode":"11230",
    "sg:province":"NY",
    "sg:tags":[
        "contractor"
    ],
    "wof:name":"A Sukkur Construction Corporation",
    "wof:placetype":"venue"
},
  "geometry": {"coordinates":[-73.97409,40.628636],"type":"Point"}
}