{
  "type": "Feature",
  "properties": {
    "iso:country":"US",
    "sg:address":"755 Co Op City Blvd",
    "sg:city":"Bronx",
    "sg:classifiers":[
        {
            "category":"Education",
            "subcategory":"School",
            "type":"Public Place"
        }
    ],
    "sg:phone":"+1 718 320 0300",
    "sg:postcode":"10475",
    "sg:province":"NY",
    "sg:website":"www.cnr.edu",
    "wof:name":"College Of New Rochelle",
    "wof:placetype":"venue"
},
  "geometry": {"coordinates":[-73.825772,40.879319],"type":"Point"}
}