{
  "type": "Feature",
  "properties": {
    "iso:country":"US",
    "sg:address":"686 Leray St",
    "sg:city":"Watertown",
    "sg:classifiers":[
        {
            "category":"Retail",
            "subcategory":"Auto Repair",
            "type":"Services"
        }
    ],
    "sg:phone":"+1 315 782 6120",
    "sg:postcode":"13601",
    "sg:province":"NY",
    "sg:tags":[
        "repairing",
        "automobile"
    ],
    "wof:name":"Schorrs' Service Ctr",
    "wof:placetype":"venue"
},
  "geometry": {"coordinates":[-75.91116100000001,43.984984],"type":"Point"}
}