{
  "type": "Feature",
  "properties": {
    "addr:full":"4328 Albany Post Rd Hyde Park NY 12538",
    "addr:housenumber":"4328",
    "addr:postcode":"12538",
    "addr:street":"Albany Post Rd",
    "iso:country":"US",
    "sg:address":"4328 Albany Post Rd",
    "sg:city":"Hyde Park",
    "sg:classifiers":[
        {
            "category":"Real Estate",
            "subcategory":"Real Estate Agent",
            "type":"Services"
        }
    ],
    "sg:phone":"+1 845 229 7653",
    "sg:postcode":"12538",
    "sg:province":"NY",
    "sg:website":"www.christinejonesrealty.com",
    "wof:name":"Christine Jones Realty",
    "wof:placetype":"venue"
},
  "geometry": {"coordinates":[-73.934741,41.788376],"type":"Point"}
}