{
  "type": "Feature",
  "properties": {
    "addr:full":"21510 Northern Blvd Bayside NY 11361",
    "addr:housenumber":"21510",
    "addr:postcode":"11361",
    "addr:street":"Northern Blvd",
    "iso:country":"US",
    "sg:address":"21510 Northern Blvd",
    "sg:city":"Bayside",
    "sg:classifiers":[
        {
            "category":"Restaurant",
            "type":"Food & Drink"
        }
    ],
    "sg:menulink":"http://www.allmenus.com/ny/queens/115926-quiznos-sub/menu/",
    "sg:phone":"+1 718 631 5000",
    "sg:postcode":"11361",
    "sg:province":"NY",
    "sg:tags":[
        "wrap",
        "american",
        "sandwich"
    ],
    "wof:name":"Quiznos Sub",
    "wof:placetype":"venue"
},
  "geometry": {"coordinates":[-73.767126,40.760521],"type":"Point"}
}