{
  "type": "Feature",
  "properties": {
    "addr:full":"2808 Dewey Ave Rochester NY 14616",
    "addr:housenumber":"2808",
    "addr:postcode":"14616",
    "addr:street":"Dewey Ave",
    "iso:country":"US",
    "sg:address":"2808 Dewey Ave",
    "sg:city":"Rochester",
    "sg:classifiers":[
        {
            "category":"Professional",
            "subcategory":"Advertising",
            "type":"Services"
        }
    ],
    "sg:phone":"+1 585 663 0068",
    "sg:postcode":"14616",
    "sg:province":"NY",
    "sg:website":"www.adnetdirect.net",
    "wof:name":"Adnet Direct",
    "wof:placetype":"venue"
},
  "geometry": {"coordinates":[-77.641205,43.220392],"type":"Point"}
}