{
  "type": "Feature",
  "properties": {
    "iso:country":"US",
    "sg:address":"5892 Scenic Ave",
    "sg:city":"Mexico",
    "sg:classifiers":[
        {
            "category":"Retail",
            "subcategory":"Auto Rental",
            "type":"Services"
        }
    ],
    "sg:phone":"+1 315 963 8351",
    "sg:postcode":"13114",
    "sg:province":"NY",
    "sg:tags":[
        "car",
        "puller"
    ],
    "wof:name":"Mexico Car Wash",
    "wof:placetype":"venue"
},
  "geometry": {"coordinates":[-76.23313400000001,43.474879],"type":"Point"}
}