{
  "type": "Feature",
  "properties": {
    "iso:country":"US",
    "sg:address":"60 E 116th St",
    "sg:city":"New York",
    "sg:classifiers":[
        {
            "category":"Shopping",
            "type":"Retail Goods"
        }
    ],
    "sg:phone":"+1   ",
    "sg:postcode":"10029",
    "sg:province":"NY",
    "sg:tags":[
        "merchandise"
    ],
    "wof:name":"House Of Candles",
    "wof:placetype":"venue"
},
  "geometry": {"coordinates":[-73.94348599999999,40.799361],"type":"Point"}
}