{
  "type": "Feature",
  "properties": {
    "addr:full":"58 W 8th St New York NY 10011",
    "addr:housenumber":"58",
    "addr:postcode":"10011",
    "addr:street":"W 8Th St",
    "iso:country":"US",
    "sg:address":"58 W 8th St",
    "sg:city":"New York",
    "sg:classifiers":[
        {
            "category":"Coffee & Tea",
            "type":"Food & Drink"
        }
    ],
    "sg:phone":"+1 212 473 4015",
    "sg:postcode":"10011",
    "sg:province":"NY",
    "wof:name":"Choux Factory",
    "wof:placetype":"venue"
},
  "geometry": {"coordinates":[-73.99920299999999,40.733208],"type":"Point"}
}