{
  "type": "Feature",
  "properties": {
    "iso:country":"US",
    "sg:address":"95 Montauk Hwy",
    "sg:city":"Montauk",
    "sg:classifiers":[
        {
            "category":"Shopping",
            "subcategory":"Department Store",
            "type":"Retail Goods"
        }
    ],
    "sg:phone":"+1 631 668 2994",
    "sg:postcode":"11954",
    "sg:province":"NY",
    "wof:name":"White's Drug & Dept Store",
    "wof:placetype":"venue"
},
  "geometry": {"coordinates":[-71.897926,41.0546],"type":"Point"}
}