{
  "type": "Feature",
  "properties": {
    "iso:country":"US",
    "sg:address":"342 E 46th Street",
    "sg:city":"New York",
    "sg:classifiers":[
        {
            "category":"Restaurant",
            "type":"Food & Drink"
        }
    ],
    "sg:phone":"+1 212 370 1866",
    "sg:postcode":"10017",
    "sg:province":"NY",
    "sg:website":"www.alcalarestaurant.com",
    "wof:name":"Alcala Restaurant",
    "wof:placetype":"venue"
},
  "geometry": {"coordinates":[-73.969347,40.751904],"type":"Point"}
}