{
  "type": "Feature",
  "properties": {
    "addr:full":"239 8th Ave New York NY 10011",
    "addr:housenumber":"239",
    "addr:postcode":"10011",
    "addr:street":"8Th Ave",
    "iso:country":"US",
    "sg:address":"239 8th Ave",
    "sg:city":"New York",
    "sg:classifiers":[
        {
            "category":"Deli",
            "type":"Food & Drink"
        },
        {
            "category":"Food & Beverages",
            "subcategory":"Bakery",
            "type":"Retail Goods"
        }
    ],
    "sg:phone":"+1 212 242 3133",
    "sg:postcode":"10011",
    "sg:province":"NY",
    "sg:tags":[
        "sandwich"
    ],
    "wof:name":"Express Deli",
    "wof:placetype":"venue"
},
  "geometry": {"coordinates":[-73.999053,40.744783],"type":"Point"}
}