{
  "type": "Feature",
  "properties": {
    "iso:country":"US",
    "sg:address":"4 Skyline Dr",
    "sg:city":"Hawthorne",
    "sg:classifiers":[
        {
            "category":"Professional",
            "type":"Services"
        }
    ],
    "sg:phone":"+1 914 592 1539",
    "sg:postcode":"10532",
    "sg:province":"NY",
    "sg:tags":[
        "establishment"
    ],
    "sg:website":"www.evonyx.com",
    "wof:name":"Evonyx Inc",
    "wof:placetype":"venue"
},
  "geometry": {"coordinates":[-73.812962,41.094364],"type":"Point"}
}