{
  "type": "Feature",
  "properties": {
    "iso:country":"US",
    "sg:address":"170 S Main St",
    "sg:city":"New City",
    "sg:classifiers":[
        {
            "category":"Retail",
            "subcategory":"Laundry & Dry Cleaning",
            "type":"Services"
        }
    ],
    "sg:phone":"+1 845 638 8014",
    "sg:postcode":"10956",
    "sg:province":"NY",
    "sg:tags":[
        "cleaners"
    ],
    "wof:name":"Van Tassel Green Earth Dry",
    "wof:placetype":"venue"
},
  "geometry": {"coordinates":[-73.990145,41.143083],"type":"Point"}
}