{
  "type": "Feature",
  "properties": {
    "addr:full":"43 Onslow Pl Freeport NY 11520",
    "addr:housenumber":"43",
    "addr:postcode":"11520",
    "addr:street":"Onslow Pl",
    "iso:country":"US",
    "sg:address":"43 Onslow Pl",
    "sg:city":"Freeport",
    "sg:classifiers":[
        {
            "category":"Organizations",
            "subcategory":"Religious Organization",
            "type":"Services"
        }
    ],
    "sg:phone":"+1 516 867 8033",
    "sg:postcode":"11520",
    "sg:province":"NY",
    "sg:tags":[
        "clergy"
    ],
    "wof:name":"Randy Larson",
    "wof:placetype":"venue"
},
  "geometry": {"coordinates":[-73.593908,40.646915],"type":"Point"}
}