{
  "type": "Feature",
  "properties": {
    "iso:country":"US",
    "sg:address":"68 S Harvest St",
    "sg:city":"Buffalo",
    "sg:classifiers":[
        {
            "category":"Wholesale",
            "subcategory":"Hardware",
            "type":"Manufacturing & Wholesale Goods"
        }
    ],
    "sg:phone":"+1 716 634 1342",
    "sg:postcode":"14221",
    "sg:province":"NY",
    "wof:name":"Mjk Services",
    "wof:placetype":"venue"
},
  "geometry": {"coordinates":[-78.751132,42.949926],"type":"Point"}
}