{
  "type": "Feature",
  "properties": {
    "addr:full":"1791 Madison Ave New York NY 10035",
    "addr:housenumber":"1791",
    "addr:postcode":"10035",
    "addr:street":"Madison Ave",
    "iso:country":"US",
    "sg:address":"1791 Madison Ave",
    "sg:city":"New York",
    "sg:classifiers":[
        {
            "category":"Autos & Motor Vehicles",
            "subcategory":"Auto Supplies",
            "type":"Retail Goods"
        }
    ],
    "sg:phone":"+1 800 400 9074",
    "sg:postcode":"10035",
    "sg:province":"NY",
    "sg:tags":[
        "tire"
    ],
    "wof:name":"Ike Gamble Tire Shop",
    "wof:placetype":"venue"
},
  "geometry": {"coordinates":[-73.943962,40.800895],"type":"Point"}
}