{
  "type": "Feature",
  "properties": {
    "addr:full":"140 Brewster Rd Scarsdale NY 10583",
    "addr:housenumber":"140",
    "addr:postcode":"10583",
    "addr:street":"Brewster Rd",
    "iso:country":"US",
    "sg:address":"140 Brewster Rd",
    "sg:city":"Scarsdale",
    "sg:classifiers":[
        {
            "category":"Manufacturing",
            "subcategory":"Textiles",
            "type":"Manufacturing & Wholesale Goods"
        }
    ],
    "sg:phone":"+1   ",
    "sg:postcode":"10583",
    "sg:province":"NY",
    "sg:tags":[
        "mill",
        "fabric"
    ],
    "wof:name":"Village Squares Quilters",
    "wof:placetype":"venue"
},
  "geometry": {"coordinates":[-73.786862,41.00982],"type":"Point"}
}