{
  "type": "Feature",
  "properties": {
    "addr:full":"9473 Hawkinsville Rd Boonville NY 13309",
    "addr:housenumber":"9473",
    "addr:postcode":"13309",
    "addr:street":"Hawkinsville Rd",
    "iso:country":"US",
    "sg:address":"9473 Hawkinsville Rd",
    "sg:city":"Boonville",
    "sg:classifiers":[
        {
            "category":"Autos & Motor Vehicles",
            "subcategory":"Boat Sales",
            "type":"Retail Goods"
        },
        {
            "category":"Shopping",
            "subcategory":"Bicycles & Sporting Goods",
            "type":"Retail Goods"
        }
    ],
    "sg:phone":"+1 315 942 2431",
    "sg:postcode":"13309",
    "sg:province":"NY",
    "sg:tags":[
        "sales",
        "dealer"
    ],
    "sg:website":"www.adirondacksportcenter.com",
    "wof:name":"Adirondack Sports Center",
    "wof:placetype":"venue"
},
  "geometry": {"coordinates":[-75.249526,43.50043],"type":"Point"}
}