{
  "type": "Feature",
  "properties": {
    "iso:country":"US",
    "sg:address":"221 Middle Neck Rd",
    "sg:city":"Great Neck",
    "sg:classifiers":[
        {
            "category":"Real Estate",
            "subcategory":"Real Estate Agent",
            "type":"Services"
        }
    ],
    "sg:phone":"+1 516 498 9531",
    "sg:postcode":"11021",
    "sg:province":"NY",
    "wof:name":"Commercial Realty Svc LLC",
    "wof:placetype":"venue"
},
  "geometry": {"coordinates":[-73.73430999999999,40.796493],"type":"Point"}
}