{
  "type": "Feature",
  "properties": {
    "addr:full":"3929 Amboy Rd Staten Island NY 10308",
    "addr:housenumber":"3929",
    "addr:postcode":"10308",
    "addr:street":"Amboy Rd",
    "iso:country":"US",
    "sg:address":"3929 Amboy Rd",
    "sg:city":"Staten Island",
    "sg:classifiers":[
        {
            "category":"Professional",
            "subcategory":"Management & Consulting",
            "type":"Services"
        }
    ],
    "sg:phone":"+1 718 227 0808",
    "sg:postcode":"10308",
    "sg:province":"NY",
    "wof:name":"Limeri Agency",
    "wof:placetype":"venue"
},
  "geometry": {"coordinates":[-74.14779299999999,40.55169],"type":"Point"}
}