{
  "type": "Feature",
  "properties": {
    "addr:full":"1411 41st St Brooklyn NY 11218",
    "addr:housenumber":"1411",
    "addr:postcode":"11218",
    "addr:street":"41St St",
    "iso:country":"US",
    "sg:address":"1411 41st St",
    "sg:city":"Brooklyn",
    "sg:classifiers":[
        {
            "category":"Organizations",
            "subcategory":"Religious Organization",
            "type":"Services"
        }
    ],
    "sg:phone":"+1 718 436 2816",
    "sg:postcode":"11218",
    "sg:province":"NY",
    "sg:tags":[
        "clergy"
    ],
    "wof:name":"Elimelach Paneth",
    "wof:placetype":"venue"
},
  "geometry": {"coordinates":[-73.983176,40.63704],"type":"Point"}
}