{
  "type": "Feature",
  "properties": {
    "iso:country":"US",
    "sg:address":"2930 E Genesee St",
    "sg:city":"Syracuse",
    "sg:classifiers":[
        {
            "category":"Building & Trades",
            "subcategory":"Construction",
            "type":"Services"
        }
    ],
    "sg:phone":"+1 315 445 1350",
    "sg:postcode":"13224",
    "sg:province":"NY",
    "sg:tags":[
        "home",
        "improvement"
    ],
    "wof:name":"Organized Contracting Svc Co",
    "wof:placetype":"venue"
},
  "geometry": {"coordinates":[-76.102147,43.042295],"type":"Point"}
}