{
  "type": "Feature",
  "properties": {
    "iso:country":"US",
    "sg:address":"73 Spring St",
    "sg:city":"New York",
    "sg:classifiers":[
        {
            "category":"Building & Trades",
            "subcategory":"Construction",
            "type":"Services"
        }
    ],
    "sg:phone":"+1 212 343 0336",
    "sg:postcode":"10012",
    "sg:province":"NY",
    "sg:tags":[
        "contractor"
    ],
    "sg:website":"www.airmaxairconditioning.com/",
    "wof:name":"Airmax Air Conditioning",
    "wof:placetype":"venue"
},
  "geometry": {"coordinates":[-73.997651,40.722668],"type":"Point"}
}