{
  "type": "Feature",
  "properties": {
    "addr:full":"749 Hillside Ave New Hyde Park NY 11040",
    "addr:housenumber":"749",
    "addr:postcode":"11040",
    "addr:street":"Hillside Ave",
    "iso:country":"US",
    "sg:address":"749 Hillside Ave",
    "sg:city":"New Hyde Park",
    "sg:classifiers":[
        {
            "category":"Shopping",
            "subcategory":"Pharmacy",
            "type":"Retail Goods"
        }
    ],
    "sg:phone":"+1   ",
    "sg:postcode":"11040",
    "sg:province":"NY",
    "wof:name":"Lakeville Pharmacy",
    "wof:placetype":"venue"
},
  "geometry": {"coordinates":[-73.666189,40.752404],"type":"Point"}
}