{
  "type": "Feature",
  "properties": {
    "iso:country":"US",
    "sg:address":"2 Middleneck Rd ",
    "sg:city":"Roslyn",
    "sg:classifiers":[
        {
            "category":"Restaurant",
            "type":"Food & Drink"
        }
    ],
    "sg:menulink":"http://www.allmenus.com/ny/manhasset/33194-bryant--cooper-steakhouse/menu/",
    "sg:phone":"+1 516 627 7270",
    "sg:postcode":"11576",
    "sg:province":"NY",
    "sg:tags":[
        "american",
        "steakhouse"
    ],
    "wof:name":"Bryant & Cooper Steakhouse",
    "wof:placetype":"venue"
},
  "geometry": {"coordinates":[-73.663318,40.798545],"type":"Point"}
}