{
  "type": "Feature",
  "properties": {
    "addr:full":"366 Railroad Ave Center Moriches NY 11934",
    "addr:housenumber":"366",
    "addr:postcode":"11934",
    "addr:street":"Railroad Ave Center",
    "iso:country":"US",
    "sg:address":"366 Railroad Ave",
    "sg:city":"Center Moriches",
    "sg:classifiers":[
        {
            "category":"Building & Trades",
            "subcategory":"Landscaping Services",
            "type":"Services"
        }
    ],
    "sg:phone":"+1 631 878 7050",
    "sg:postcode":"11934",
    "sg:province":"NY",
    "sg:tags":[
        "landscape",
        "contractor"
    ],
    "wof:name":"Lomonaco Landscaping Inc",
    "wof:placetype":"venue"
},
  "geometry": {"coordinates":[-72.792018,40.820194],"type":"Point"}
}