{
  "type": "Feature",
  "properties": {
    "iso:country":"US",
    "sg:address":"810 Shannon Corners Rd",
    "sg:city":"Dundee",
    "sg:classifiers":[
        {
            "category":"Farming",
            "subcategory":"Vineyard",
            "type":"Manufacturing & Wholesale Goods"
        }
    ],
    "sg:phone":"+1 607 243 7098",
    "sg:postcode":"14837",
    "sg:province":"NY",
    "sg:tags":[
        "grape"
    ],
    "wof:name":"Green Lawn Farms",
    "wof:placetype":"venue"
},
  "geometry": {"coordinates":[-76.961195,42.544961],"type":"Point"}
}