{
  "type": "Feature",
  "properties": {
    "addr:full":"119 Magnolia Dr Selden NY 11784",
    "addr:housenumber":"119",
    "addr:postcode":"11784",
    "addr:street":"Magnolia Dr",
    "iso:country":"US",
    "sg:address":"119 Magnolia Dr",
    "sg:city":"Selden",
    "sg:classifiers":[
        {
            "category":"Building & Trades",
            "subcategory":"Pest Control",
            "type":"Services"
        }
    ],
    "sg:phone":"+1   ",
    "sg:postcode":"11784",
    "sg:province":"NY",
    "wof:name":"Vanish Termite & Pest Ctrl Co",
    "wof:placetype":"venue"
},
  "geometry": {"coordinates":[-73.043262,40.871978],"type":"Point"}
}