{
  "type": "Feature",
  "properties": {
    "addr:full":"1545 Bushwick Ave Brooklyn NY 11207",
    "addr:housenumber":"1545",
    "addr:postcode":"11207",
    "addr:street":"Bushwick Ave",
    "iso:country":"US",
    "sg:address":"1545 Bushwick Ave",
    "sg:city":"Brooklyn",
    "sg:classifiers":[
        {
            "category":"Autos & Motor Vehicles",
            "subcategory":"Automobile Sales",
            "type":"Retail Goods"
        }
    ],
    "sg:phone":"+1   ",
    "sg:postcode":"11207",
    "sg:province":"NY",
    "sg:tags":[
        "car",
        "used",
        "truck"
    ],
    "wof:name":"Garet Motors Used Cars",
    "wof:placetype":"venue"
},
  "geometry": {"coordinates":[-73.905147,40.682245],"type":"Point"}
}