{
  "type": "Feature",
  "properties": {
    "addr:full":"816 Franklin Ave Brooklyn NY 11225",
    "addr:housenumber":"816",
    "addr:postcode":"11225",
    "addr:street":"Franklin Ave",
    "iso:country":"US",
    "sg:address":"816 Franklin Ave",
    "sg:city":"Brooklyn",
    "sg:classifiers":[
        {
            "category":"Wholesale",
            "subcategory":"Machinery & Supplies",
            "type":"Manufacturing & Wholesale Goods"
        }
    ],
    "sg:phone":"+1 718 735 2692",
    "sg:postcode":"11225",
    "sg:province":"NY",
    "sg:tags":[
        "equipment",
        "salon",
        "salons-equipment",
        "beauty"
    ],
    "wof:name":"Franklin Beauty Supply, Inc",
    "wof:placetype":"venue"
},
  "geometry": {"coordinates":[-73.95823300000001,40.669948],"type":"Point"}
}