{
  "type": "Feature",
  "properties": {
    "iso:country":"US",
    "sg:address":"2078 Cleveland Rd",
    "sg:city":"Corfu",
    "sg:classifiers":[
        {
            "category":"Manufacturing",
            "subcategory":"Tools & Machinery",
            "type":"Manufacturing & Wholesale Goods"
        }
    ],
    "sg:phone":"+1   ",
    "sg:postcode":"14036",
    "sg:province":"NY",
    "sg:tags":[
        "machine",
        "shop"
    ],
    "wof:name":"Thayer Sales & Service",
    "wof:placetype":"venue"
},
  "geometry": {"coordinates":[-78.349887,43.009392],"type":"Point"}
}