{
  "type": "Feature",
  "properties": {
    "iso:country":"US",
    "sg:address":"600 Trimmer Rd",
    "sg:city":"Spencerport",
    "sg:classifiers":[
        {
            "category":"Recreation",
            "type":"Entertainment"
        }
    ],
    "sg:phone":"+1   ",
    "sg:postcode":"14559",
    "sg:province":"NY",
    "sg:tags":[
        "club",
        "course",
        "membership",
        "golf",
        "public"
    ],
    "wof:name":"Buttonwood Golf Course PAR 3",
    "wof:placetype":"venue"
},
  "geometry": {"coordinates":[-77.822783,43.197535],"type":"Point"}
}