{
  "type": "Feature",
  "properties": {
    "addr:full":"149 W 105th St New York NY 10025",
    "addr:housenumber":"149",
    "addr:postcode":"10025",
    "addr:street":"W 105Th St",
    "iso:country":"US",
    "sg:address":"149 W 105th St",
    "sg:city":"New York",
    "sg:classifiers":[
        {
            "category":"Health Services",
            "subcategory":"Hospital",
            "type":"Services"
        }
    ],
    "sg:phone":"+1 212 222 5740",
    "sg:postcode":"10025",
    "sg:province":"NY",
    "wof:name":"Jewish Home & Hospital",
    "wof:placetype":"venue"
},
  "geometry": {"coordinates":[-73.965114,40.79924],"type":"Point"}
}