{
  "type": "Feature",
  "properties": {
    "addr:full":"544 Vanderbilt Ave Brooklyn NY 11238",
    "addr:housenumber":"544",
    "addr:postcode":"11238",
    "addr:street":"Vanderbilt Ave",
    "iso:country":"US",
    "sg:address":"544 Vanderbilt Ave",
    "sg:city":"Brooklyn",
    "sg:classifiers":[
        {
            "category":"Retail",
            "subcategory":"Funeral Services",
            "type":"Services"
        }
    ],
    "sg:phone":"+1   ",
    "sg:postcode":"11238",
    "sg:province":"NY",
    "wof:name":"Browns Funeral Home",
    "wof:placetype":"venue"
},
  "geometry": {"coordinates":[-73.967879,40.680745],"type":"Point"}
}