{
  "type": "Feature",
  "properties": {
    "iso:country":"US",
    "sg:address":"226 Clinton St",
    "sg:city":"Hempstead",
    "sg:classifiers":[
        {
            "category":"Health Services",
            "subcategory":"Doctor",
            "type":"Services"
        }
    ],
    "sg:phone":"+1 516 560 1853",
    "sg:postcode":"11550",
    "sg:province":"NY",
    "sg:tags":[
        "physician",
        "surgeon"
    ],
    "wof:name":"Pamela T Htay-Sha MD",
    "wof:placetype":"venue"
},
  "geometry": {"coordinates":[-73.620707,40.712321],"type":"Point"}
}