{
  "type": "Feature",
  "properties": {
    "addr:full":"5023 14th Ave Brooklyn NY 11219",
    "addr:housenumber":"5023",
    "addr:postcode":"11219",
    "addr:street":"14Th Ave",
    "iso:country":"US",
    "sg:address":"5023 14th Ave",
    "sg:city":"Brooklyn",
    "sg:classifiers":[
        {
            "category":"Real Estate",
            "subcategory":"Real Estate Agent",
            "type":"Services"
        }
    ],
    "sg:phone":"+1 718 853 8451",
    "sg:postcode":"11219",
    "sg:province":"NY",
    "wof:name":"Ablan Properties & Management",
    "wof:placetype":"venue"
},
  "geometry": {"coordinates":[-73.990922,40.632654],"type":"Point"}
}