{
  "type": "Feature",
  "properties": {
    "iso:country":"US",
    "sg:address":"122 Belzano Rd",
    "sg:city":"Johnstown",
    "sg:classifiers":[
        {
            "category":"Wholesale",
            "subcategory":"Furniture",
            "type":"Manufacturing & Wholesale Goods"
        }
    ],
    "sg:phone":"+1 518 773 0423",
    "sg:postcode":"12095",
    "sg:province":"NY",
    "wof:name":"Versatile Wood Fabrication",
    "wof:placetype":"venue"
},
  "geometry": {"coordinates":[-74.34253,43.019378],"type":"Point"}
}