{
  "type": "Feature",
  "properties": {
    "addr:full":"129 Rutledge St Brooklyn NY 11211",
    "addr:housenumber":"129",
    "addr:postcode":"11211",
    "addr:street":"Rutledge St",
    "iso:country":"US",
    "sg:address":"129 Rutledge St",
    "sg:city":"Brooklyn",
    "sg:classifiers":[
        {
            "category":"Manufacturing",
            "subcategory":"Textiles",
            "type":"Manufacturing & Wholesale Goods"
        }
    ],
    "sg:phone":"+1   ",
    "sg:postcode":"11211",
    "sg:province":"NY",
    "sg:tags":[
        "fabric",
        "mfg"
    ],
    "wof:name":"Hatzlucha Textile & Nonwoven",
    "wof:placetype":"venue"
},
  "geometry": {"coordinates":[-73.956619,40.702382],"type":"Point"}
}