{
  "type": "Feature",
  "properties": {
    "addr:full":"212 E 19 St New York NY 10003",
    "addr:housenumber":"212;19",
    "addr:postcode":"10003",
    "addr:street":"E;St",
    "iso:country":"US",
    "sg:address":"212 E 19 St",
    "sg:city":"New York",
    "sg:classifiers":[
        {
            "category":"Retail",
            "subcategory":"Auto Repair",
            "type":"Services"
        }
    ],
    "sg:phone":"+1 212 937 1299",
    "sg:postcode":"10003",
    "sg:province":"NY",
    "sg:tags":[
        "wrecker"
    ],
    "wof:name":"Admond 24 Hour Towing",
    "wof:placetype":"venue"
},
  "geometry": {"coordinates":[-73.98477099999999,40.736275],"type":"Point"}
}