{
  "type": "Feature",
  "properties": {
    "addr:full":"7 Railroad Ave Valhalla NY 10595",
    "addr:housenumber":"7",
    "addr:postcode":"10595",
    "addr:street":"Railroad Ave",
    "iso:country":"US",
    "sg:address":"7 Railroad Ave",
    "sg:city":"Valhalla",
    "sg:classifiers":[
        {
            "category":"Retail",
            "subcategory":"Repair Shop",
            "type":"Services"
        }
    ],
    "sg:phone":"+1 914 946 6872",
    "sg:postcode":"10595",
    "sg:province":"NY",
    "sg:tags":[
        "welding"
    ],
    "wof:name":"New York Welding & Heavy Equip",
    "wof:placetype":"venue"
},
  "geometry": {"coordinates":[-73.783919,41.083205],"type":"Point"}
}