{
  "type": "Feature",
  "properties": {
    "addr:full":"524 Broadway New York NY 10012",
    "addr:housenumber":"524",
    "addr:postcode":"10012",
    "addr:street":"Broadway",
    "iso:country":"US",
    "sg:address":"524 Broadway",
    "sg:city":"New York",
    "sg:classifiers":[
        {
            "category":"Communications",
            "type":"Services"
        }
    ],
    "sg:phone":"+1 212 343 2878",
    "sg:postcode":"10012",
    "sg:province":"NY",
    "sg:tags":[
        "web",
        "design"
    ],
    "wof:name":"Mauro & Mauro Design",
    "wof:placetype":"venue"
},
  "geometry": {"coordinates":[-73.99885,40.722942],"type":"Point"}
}