{
  "type": "Feature",
  "properties": {
    "addr:full":"2635 Jerusalem Ave Apt T North Bellmore NY 11710",
    "addr:housenumber":"2635",
    "addr:postcode":"11710",
    "addr:street":"Jerusalem Ave Apt T North",
    "iso:country":"US",
    "sg:address":"2635 Jerusalem Ave Apt T",
    "sg:city":"North Bellmore",
    "sg:classifiers":[
        {
            "category":"Shopping",
            "subcategory":"Pharmacy",
            "type":"Retail Goods"
        }
    ],
    "sg:phone":"+1 516 409 6871",
    "sg:postcode":"11710",
    "sg:province":"NY",
    "sg:tags":[
        "drugstore"
    ],
    "sg:website":"www.cvs.com",
    "wof:name":"CVS pharmacy",
    "wof:placetype":"venue"
},
  "geometry": {"coordinates":[-73.534907,40.69156],"type":"Point"}
}