{
  "type": "Feature",
  "properties": {
    "addr:full":"5858 E Molloy Rd Syracuse NY 13211",
    "addr:housenumber":"5858",
    "addr:postcode":"13211",
    "addr:street":"E Molloy Rd",
    "iso:country":"US",
    "sg:address":"5858 E Molloy Rd",
    "sg:city":"Syracuse",
    "sg:classifiers":[
        {
            "category":"Retail",
            "subcategory":"Laundry & Dry Cleaning",
            "type":"Services"
        }
    ],
    "sg:phone":"+1 315 455 1775",
    "sg:postcode":"13211",
    "sg:province":"NY",
    "sg:tags":[
        "cleaners",
        "rug",
        "carpet"
    ],
    "wof:name":"Kauffmann's Carpet Upholstery",
    "wof:placetype":"venue"
},
  "geometry": {"coordinates":[-76.114011,43.098417],"type":"Point"}
}