{
  "type": "Feature",
  "properties": {
    "addr:full":"45 Talisman Dr Dix Hills NY 11746",
    "addr:housenumber":"45",
    "addr:postcode":"11746",
    "addr:street":"Talisman Dr",
    "iso:country":"US",
    "sg:address":"45 Talisman Dr",
    "sg:city":"Dix Hills",
    "sg:classifiers":[
        {
            "category":"Organizations",
            "subcategory":"Religious Organization",
            "type":"Services"
        }
    ],
    "sg:phone":"+1 631 499 3140",
    "sg:postcode":"11746",
    "sg:province":"NY",
    "sg:tags":[
        "church"
    ],
    "sg:website":"www.graceofgod.info",
    "wof:name":"Grace Of God Evangelical Luth",
    "wof:placetype":"venue"
},
  "geometry": {"coordinates":[-73.34013,40.800286],"type":"Point"}
}