{
  "type": "Feature",
  "properties": {
    "addr:full":"110 Leroy St New York NY 10014",
    "addr:housenumber":"110",
    "addr:postcode":"10014",
    "addr:street":"Leroy St",
    "iso:country":"US",
    "sg:address":"110 Leroy St",
    "sg:city":"New York",
    "sg:classifiers":[
        {
            "category":"Real Estate",
            "subcategory":"Real Estate Agent",
            "type":"Services"
        }
    ],
    "sg:phone":"+1 212 352 0222",
    "sg:postcode":"10014",
    "sg:province":"NY",
    "wof:name":"Royalton Realty",
    "wof:placetype":"venue"
},
  "geometry": {"coordinates":[-74.007846,40.730232],"type":"Point"}
}