{
  "type": "Feature",
  "properties": {
    "iso:country":"US",
    "sg:address":"11 Seeger Dr",
    "sg:city":"Nanuet",
    "sg:classifiers":[
        {
            "category":"Real Estate",
            "subcategory":"Real Estate Operator",
            "type":"Services"
        }
    ],
    "sg:phone":"+1 845 623 1267",
    "sg:postcode":"10954",
    "sg:province":"NY",
    "sg:tags":[
        "property",
        "commercial"
    ],
    "wof:name":"Olori Brothers",
    "wof:placetype":"venue"
},
  "geometry": {"coordinates":[-74.002314,41.099207],"type":"Point"}
}