{
  "type": "Feature",
  "properties": {
    "addr:full":"35 Manor Rd Smithtown NY 11787",
    "addr:housenumber":"35",
    "addr:postcode":"11787",
    "addr:street":"Manor Rd",
    "iso:country":"US",
    "sg:address":"35 Manor Rd",
    "sg:city":"Smithtown",
    "sg:classifiers":[
        {
            "category":"Organizations",
            "subcategory":"Political Organization",
            "type":"Services"
        }
    ],
    "sg:phone":"+1 631 265 3007",
    "sg:postcode":"11787",
    "sg:province":"NY",
    "wof:name":"Smithtown Republican Hdqrtrs",
    "wof:placetype":"venue"
},
  "geometry": {"coordinates":[-73.194897,40.856331],"type":"Point"}
}