{
  "type": "Feature",
  "properties": {
    "iso:country":"US",
    "sg:address":"15 S Bayles Ave",
    "sg:city":"Port Washington",
    "sg:classifiers":[
        {
            "category":"Professional",
            "subcategory":"Lawyer & Legal Services",
            "type":"Services"
        }
    ],
    "sg:phone":"+1   ",
    "sg:postcode":"11050",
    "sg:province":"NY",
    "wof:name":"Joseph Sciacca Atty",
    "wof:placetype":"venue"
},
  "geometry": {"coordinates":[-73.686369,40.829445],"type":"Point"}
}