{
  "type": "Feature",
  "properties": {
    "addr:full":"7219 Roosevelt Ave Jackson Heights NY 11372",
    "addr:housenumber":"7219",
    "addr:postcode":"11372",
    "addr:street":"Roosevelt Ave",
    "iso:country":"US",
    "sg:address":"7219 Roosevelt Ave",
    "sg:city":"Jackson Heights",
    "sg:classifiers":[
        {
            "category":"Shopping",
            "subcategory":"Mobile Phones",
            "type":"Retail Goods"
        }
    ],
    "sg:phone":"+1 718 426 0800",
    "sg:postcode":"11372",
    "sg:province":"NY",
    "wof:name":"Games & Wireless International Corp",
    "wof:placetype":"venue"
},
  "geometry": {"coordinates":[-73.893359,40.74678],"type":"Point"}
}