{
  "type": "Feature",
  "properties": {
    "iso:country":"US",
    "sg:address":"82 Arlington Ave",
    "sg:city":"St James",
    "sg:phone":"+1 631 724 2333",
    "sg:postcode":"11780",
    "sg:province":"NY",
    "sg:tags":[
        "fuel",
        "diesel"
    ],
    "sg:website":"www.benit.com",
    "wof:name":"Benit Fuels Sales & Svc",
    "wof:placetype":"venue"
},
  "geometry": {"coordinates":[-73.161828,40.863228],"type":"Point"}
}