{
  "type": "Feature",
  "properties": {
    "addr:full":"17 Clare Dr East Northport NY 11731",
    "addr:housenumber":"17",
    "addr:postcode":"11731",
    "addr:street":"Clare Dr",
    "iso:country":"US",
    "sg:address":"17 Clare Dr",
    "sg:city":"East Northport",
    "sg:classifiers":[
        {
            "category":"Home & Garden",
            "subcategory":"Household Appliances",
            "type":"Retail Goods"
        }
    ],
    "sg:phone":"+1 631 262 9773",
    "sg:postcode":"11731",
    "sg:province":"NY",
    "sg:tags":[
        "equipment",
        "dehumidifying"
    ],
    "wof:name":"Munters Drycool",
    "wof:placetype":"venue"
},
  "geometry": {"coordinates":[-73.332353,40.885249],"type":"Point"}
}