{
  "type": "Feature",
  "properties": {
    "addr:full":"216 N Main St Ste E Freeport NY 11520",
    "addr:housenumber":"216",
    "addr:postcode":"11520",
    "addr:street":"N Main St Ste E",
    "iso:country":"US",
    "sg:address":"216 N Main St Ste E",
    "sg:city":"Freeport",
    "sg:classifiers":[
        {
            "category":"Real Estate",
            "subcategory":"Real Estate Services",
            "type":"Services"
        },
        {
            "category":"Real Estate",
            "subcategory":"Real Estate Agent",
            "type":"Services"
        }
    ],
    "sg:phone":"+1 516 867 2261",
    "sg:postcode":"11520",
    "sg:province":"NY",
    "sg:tags":[
        "buyer",
        "broker"
    ],
    "wof:name":"K B Realty",
    "wof:placetype":"venue"
},
  "geometry": {"coordinates":[-73.586349,40.663908],"type":"Point"}
}