{
  "type": "Feature",
  "properties": {
    "iso:country":"US",
    "sg:address":"69 Stuyvesant Rd",
    "sg:city":"Pittsford",
    "sg:classifiers":[
        {
            "category":"Travel",
            "subcategory":"Campground",
            "type":"Entertainment"
        }
    ],
    "sg:phone":"+1   ",
    "sg:postcode":"14534",
    "sg:province":"NY",
    "sg:tags":[
        "camp"
    ],
    "wof:name":"David Staehl",
    "wof:placetype":"venue"
},
  "geometry": {"coordinates":[-77.509035,43.065256],"type":"Point"}
}