{
  "type": "Feature",
  "properties": {
    "addr:full":"2799 Route 112 Ste 5 Medford NY 11763",
    "addr:housenumber":"2799",
    "addr:postcode":"11763",
    "addr:street":"Route 112 Ste 5",
    "iso:country":"US",
    "sg:address":"2799 Route 112 Ste 5",
    "sg:city":"Medford",
    "sg:classifiers":[
        {
            "category":"Social Services",
            "subcategory":"Child Care",
            "type":"Services"
        },
        {
            "category":"Personal",
            "subcategory":"Massage",
            "type":"Services"
        },
        {
            "category":"Health Services",
            "subcategory":"Nursing And Care Facility",
            "type":"Services"
        },
        {
            "category":"Health Services",
            "subcategory":"Health Practitioner",
            "type":"Services"
        },
        {
            "category":"Health Services",
            "subcategory":"Chiropractor",
            "type":"Services"
        }
    ],
    "sg:phone":"+1 631 576 4718",
    "sg:postcode":"11763",
    "sg:province":"NY",
    "sg:tags":[
        "product",
        "management",
        "pain",
        "chiropractic",
        "back",
        "therapist",
        "treatment",
        "medicine",
        "injury",
        "sport",
        "physical"
    ],
    "sg:website":"http://www.totalchiro.com",
    "wof:name":"Total Chiropractic Care and Wellness",
    "wof:placetype":"venue"
},
  "geometry": {"coordinates":[-72.995041,40.826984],"type":"Point"}
}