{
  "type": "Feature",
  "properties": {
    "addr:full":"198 Lamberts Ln Staten Island NY 10314",
    "addr:housenumber":"198",
    "addr:postcode":"10314",
    "addr:street":"Lamberts Ln",
    "iso:country":"US",
    "sg:address":"198 Lamberts Ln",
    "sg:city":"Staten Island",
    "sg:classifiers":[
        {
            "category":"Freight",
            "type":"Transportation"
        }
    ],
    "sg:phone":"+1 718 761 1111",
    "sg:postcode":"10314",
    "sg:province":"NY",
    "wof:name":"V & S Enterprises",
    "wof:placetype":"venue"
},
  "geometry": {"coordinates":[-74.16360299999999,40.615992],"type":"Point"}
}