{
  "type": "Feature",
  "properties": {
    "iso:country":"US",
    "sg:address":"223 Front St",
    "sg:city":"Owego",
    "sg:classifiers":[
        {
            "category":"Organizations",
            "subcategory":"Community Association",
            "type":"Services"
        }
    ],
    "sg:phone":"+1 607 687 1039",
    "sg:postcode":"13827",
    "sg:province":"NY",
    "sg:tags":[
        "fraternal"
    ],
    "wof:name":"Elks Lodge",
    "wof:placetype":"venue"
},
  "geometry": {"coordinates":[-76.257614,42.104078],"type":"Point"}
}