{
  "type": "Feature",
  "properties": {
    "iso:country":"US",
    "sg:address":"736 Caroline Ave",
    "sg:city":"Elmont",
    "sg:classifiers":[
        {
            "category":"Health Services",
            "subcategory":"Clinic",
            "type":"Services"
        }
    ],
    "sg:phone":"+1   ",
    "sg:postcode":"11003",
    "sg:province":"NY",
    "wof:name":"Raphael Paul S Medical PC",
    "wof:placetype":"venue"
},
  "geometry": {"coordinates":[-73.70537299999999,40.686698],"type":"Point"}
}