{
  "type": "Feature",
  "properties": {
    "iso:country":"US",
    "sg:address":"1283 Prospect Ave 3rd Fl",
    "sg:city":"Brooklyn",
    "sg:classifiers":[
        {
            "category":"Communications",
            "subcategory":"Film & Video Production",
            "type":"Services"
        },
        {
            "category":"Professional",
            "subcategory":"Art Services",
            "type":"Services"
        }
    ],
    "sg:phone":"+1 347 669 3686",
    "sg:postcode":"11218",
    "sg:province":"NY",
    "sg:tags":[
        "photographer",
        "video/film"
    ],
    "sg:website":"www.chamberimages.com",
    "wof:name":"Chamber Images Photography Studio",
    "wof:placetype":"venue"
},
  "geometry": {"coordinates":[-73.97562499999999,40.651881],"type":"Point"}
}