{
  "type": "Feature",
  "properties": {
    "addr:full":"116 W 23rd St New York NY 10011",
    "addr:housenumber":"116",
    "addr:postcode":"10011",
    "addr:street":"W 23Rd St",
    "iso:country":"US",
    "sg:address":"116 W 23rd St",
    "sg:city":"New York",
    "sg:classifiers":[
        {
            "category":"Real Estate",
            "subcategory":"Real Estate Operator",
            "type":"Services"
        }
    ],
    "sg:phone":"+1 212 851 8400",
    "sg:postcode":"10011",
    "sg:province":"NY",
    "sg:tags":[
        "building",
        "commercial"
    ],
    "wof:name":"Avitex Co Inc",
    "wof:placetype":"venue"
},
  "geometry": {"coordinates":[-73.99533,40.743838],"type":"Point"}
}