{
  "type": "Feature",
  "properties": {
    "addr:full":"4097 Lake Shore Rd Hamburg NY 14075",
    "addr:housenumber":"4097",
    "addr:postcode":"14075",
    "addr:street":"Lake Shore Rd",
    "iso:country":"US",
    "sg:address":"4097 Lake Shore Rd",
    "sg:city":"Hamburg",
    "sg:classifiers":[
        {
            "category":"Food & Beverages",
            "subcategory":"Fruits & Vegetables",
            "type":"Retail Goods"
        }
    ],
    "sg:phone":"+1 716 627 5855",
    "sg:postcode":"14075",
    "sg:province":"NY",
    "wof:name":"Fruity Stand",
    "wof:placetype":"venue"
},
  "geometry": {"coordinates":[-78.863506,42.773381],"type":"Point"}
}