{
  "type": "Feature",
  "properties": {
    "addr:full":"39 Fox Ln Shoreham NY 11786",
    "addr:housenumber":"39",
    "addr:postcode":"11786",
    "addr:street":"Fox Ln",
    "iso:country":"US",
    "sg:address":"39 Fox Ln",
    "sg:city":"Shoreham",
    "sg:classifiers":[
        {
            "category":"Professional",
            "type":"Services"
        }
    ],
    "sg:phone":"+1 631 821 3444",
    "sg:postcode":"11786",
    "sg:province":"NY",
    "wof:name":"Crest Services",
    "wof:placetype":"venue"
},
  "geometry": {"coordinates":[-72.88287699999999,40.944057],"type":"Point"}
}