{
  "type": "Feature",
  "properties": {
    "addr:full":"76 Avenue U Ste A Brooklyn NY 11223",
    "addr:housenumber":"76",
    "addr:postcode":"11223",
    "addr:street":"Avenue U Ste A",
    "iso:country":"US",
    "sg:address":"76 Avenue U Ste A",
    "sg:city":"Brooklyn",
    "sg:classifiers":[
        {
            "category":"Health Services",
            "subcategory":"Doctor",
            "type":"Services"
        }
    ],
    "sg:phone":"+1 718 449 0700",
    "sg:postcode":"11223",
    "sg:province":"NY",
    "wof:name":"Marlboro Medical Group",
    "wof:placetype":"venue"
},
  "geometry": {"coordinates":[-73.981796,40.596001],"type":"Point"}
}