{
  "type": "Feature",
  "properties": {
    "addr:full":"5802 5th Ave Brooklyn NY 11220",
    "addr:housenumber":"5802",
    "addr:postcode":"11220",
    "addr:street":"5Th Ave",
    "iso:country":"US",
    "sg:address":"5802 5th Ave",
    "sg:city":"Brooklyn",
    "sg:classifiers":[
        {
            "category":"Restaurant",
            "type":"Food & Drink"
        },
        {
            "category":"Food & Beverages",
            "subcategory":"Groceries & Convenience Stores",
            "type":"Retail Goods"
        }
    ],
    "sg:phone":"+1 718 439 4494",
    "sg:postcode":"11220",
    "sg:province":"NY",
    "sg:tags":[
        "deli",
        "delicatessen"
    ],
    "wof:name":"Sunset Ridge Deli",
    "wof:placetype":"venue"
},
  "geometry": {"coordinates":[-74.015198,40.640598],"type":"Point"}
}