{
  "type": "Feature",
  "properties": {
    "addr:full":"112 Ave U Brooklyn NY 11223",
    "addr:postcode":"11223",
    "addr:street":"112 Ave U",
    "iso:country":"US",
    "sg:address":"112 Ave U",
    "sg:city":"Brooklyn",
    "sg:classifiers":[
        {
            "category":"Shopping",
            "subcategory":"Used Merchandise",
            "type":"Retail Goods"
        }
    ],
    "sg:phone":"+1   ",
    "sg:postcode":"11223",
    "sg:province":"NY",
    "wof:name":"Rouge Moulin",
    "wof:placetype":"venue"
},
  "geometry": {"coordinates":[-73.979485,40.596209],"type":"Point"}
}