{
  "type": "Feature",
  "properties": {
    "addr:full":"45 Webster Ave Goshen NY 10924",
    "addr:housenumber":"45",
    "addr:postcode":"10924",
    "addr:street":"Webster Ave",
    "iso:country":"US",
    "sg:address":"45 Webster Ave",
    "sg:city":"Goshen",
    "sg:classifiers":[
        {
            "category":"Health Services",
            "subcategory":"Health Practitioner",
            "type":"Services"
        },
        {
            "category":"Social Services",
            "type":"Services"
        }
    ],
    "sg:phone":"+1 845 294 7856",
    "sg:postcode":"10924",
    "sg:province":"NY",
    "sg:tags":[
        "counselor",
        "marriage",
        "family"
    ],
    "wof:name":"Robin Sherwin Csw",
    "wof:placetype":"venue"
},
  "geometry": {"coordinates":[-74.32338900000001,41.402665],"type":"Point"}
}