{
  "type": "Feature",
  "properties": {
    "iso:country":"US",
    "sg:address":"1491 2nd Ave",
    "sg:city":"Manhattan",
    "sg:classifiers":[
        {
            "category":"Restaurant",
            "type":"Food & Drink"
        }
    ],
    "sg:phone":"+1 212 249 6080",
    "sg:postcode":"10075",
    "sg:province":"NY",
    "sg:tags":[
        "mexican"
    ],
    "wof:name":"MXco",
    "wof:placetype":"venue"
},
  "geometry": {"coordinates":[-73.955832,40.772566],"type":"Point"}
}