{
  "type": "Feature",
  "properties": {
    "addr:full":"250 W 135th Street New York NY 10030",
    "addr:housenumber":"250",
    "addr:postcode":"10030",
    "addr:street":"W 135Th Street",
    "iso:country":"US",
    "sg:address":"250 W 135th Street",
    "sg:city":"New York",
    "sg:classifiers":[
        {
            "category":"Restaurant",
            "type":"Food & Drink"
        }
    ],
    "sg:phone":"+1 212 694 2829",
    "sg:postcode":"10030",
    "sg:province":"NY",
    "wof:name":"Sammy's Fried Chicken",
    "wof:placetype":"venue"
},
  "geometry": {"coordinates":[-73.94508999999999,40.816022],"type":"Point"}
}