{
  "type": "Feature",
  "properties": {
    "iso:country":"US",
    "sg:address":"250 W 135th Street",
    "sg:city":"New York",
    "sg:classifiers":[
        {
            "category":"Restaurant",
            "type":"Food & Drink"
        }
    ],
    "sg:phone":"+1 212 694 2829",
    "sg:postcode":"10030",
    "sg:province":"NY",
    "wof:name":"Sammy's Fried Chicken",
    "wof:placetype":"venue"
},
  "geometry": {"coordinates":[-73.94508999999999,40.816022],"type":"Point"}
}