{
  "type": "Feature",
  "properties": {
    "iso:country":"US",
    "sg:address":"206 N Walnut St",
    "sg:city":"Massapequa",
    "sg:classifiers":[
        {
            "category":"Retail",
            "subcategory":"Repair Shop",
            "type":"Services"
        }
    ],
    "sg:phone":"+1   ",
    "sg:postcode":"11758",
    "sg:province":"NY",
    "sg:tags":[
        "satellite",
        "installation",
        "television",
        "sales"
    ],
    "wof:name":"D K Connections Inc",
    "wof:placetype":"venue"
},
  "geometry": {"coordinates":[-73.463689,40.699875],"type":"Point"}
}