{
  "type": "Feature",
  "properties": {
    "addr:full":"557 Leonard St Brooklyn NY 11222",
    "addr:housenumber":"557",
    "addr:postcode":"11222",
    "addr:street":"Leonard St",
    "iso:country":"US",
    "sg:address":"557 Leonard St",
    "sg:city":"Brooklyn",
    "sg:classifiers":[
        {
            "category":"Retail",
            "subcategory":"Repair Shop",
            "type":"Services"
        }
    ],
    "sg:phone":"+1 718 887 2389",
    "sg:postcode":"11222",
    "sg:province":"NY",
    "sg:tags":[
        "lock",
        "locksmith"
    ],
    "wof:name":"Emergency Locksmith",
    "wof:placetype":"venue"
},
  "geometry": {"coordinates":[-73.949403,40.722631],"type":"Point"}
}