{
  "type": "Feature",
  "properties": {
    "iso:country":"US",
    "sg:address":"243 E Amherst St",
    "sg:city":"Buffalo",
    "sg:classifiers":[
        {
            "category":"Social Services",
            "subcategory":"Child Care",
            "type":"Services"
        }
    ],
    "sg:phone":"+1 716 835 2912",
    "sg:postcode":"14214",
    "sg:province":"NY",
    "wof:name":"Little Angels Daycare",
    "wof:placetype":"venue"
},
  "geometry": {"coordinates":[-78.82986,42.94008],"type":"Point"}
}