{
  "type": "Feature",
  "properties": {
    "addr:full":"305 Lafayette Ave Buffalo NY 14213",
    "addr:housenumber":"305",
    "addr:postcode":"14213",
    "addr:street":"Lafayette Ave",
    "iso:country":"US",
    "sg:address":"305 Lafayette Ave",
    "sg:city":"Buffalo",
    "sg:classifiers":[
        {
            "category":"Organizations",
            "subcategory":"Religious Organization",
            "type":"Services"
        }
    ],
    "sg:phone":"+1 716 886 2957",
    "sg:postcode":"14213",
    "sg:province":"NY",
    "sg:tags":[
        "clergy"
    ],
    "wof:name":"R Patrick Lavery",
    "wof:placetype":"venue"
},
  "geometry": {"coordinates":[-78.88722300000001,42.920122],"type":"Point"}
}