{
  "type": "Feature",
  "properties": {
    "addr:full":"21 Bloomingdale Rd White Plains NY 10605",
    "addr:housenumber":"21",
    "addr:postcode":"10605",
    "addr:street":"Bloomingdale Rd",
    "iso:country":"US",
    "sg:address":"21 Bloomingdale Rd",
    "sg:city":"White Plains",
    "sg:classifiers":[
        {
            "category":"Social Services",
            "type":"Services"
        }
    ],
    "sg:phone":"+1 914 997 5774",
    "sg:postcode":"10605",
    "sg:province":"NY",
    "sg:tags":[
        "worker"
    ],
    "wof:name":"Synthia Pommiss",
    "wof:placetype":"venue"
},
  "geometry": {"coordinates":[-73.758314,41.032548],"type":"Point"}
}