{
  "type": "Feature",
  "properties": {
    "iso:country":"US",
    "sg:address":"114 Hart St",
    "sg:city":"Fulton",
    "sg:classifiers":[
        {
            "category":"Wholesale",
            "subcategory":"Dairy",
            "type":"Manufacturing & Wholesale Goods"
        }
    ],
    "sg:phone":"+1 315 593 6455",
    "sg:postcode":"13069",
    "sg:province":"NY",
    "sg:tags":[
        "product"
    ],
    "sg:website":"www.hudsondairy.com",
    "wof:name":"Hudson's Dairy",
    "wof:placetype":"venue"
},
  "geometry": {"coordinates":[-76.42206899999999,43.322024],"type":"Point"}
}