{
  "type": "Feature",
  "properties": {
    "iso:country":"US",
    "sg:address":"1872 Webster Ave",
    "sg:city":"Bronx",
    "sg:classifiers":[
        {
            "category":"Bars & Pubs",
            "type":"Food & Drink"
        }
    ],
    "sg:phone":"+1 718 294 3112",
    "sg:postcode":"10457",
    "sg:province":"NY",
    "wof:name":"Entertainers Sports Bar & Cafe",
    "wof:placetype":"venue"
},
  "geometry": {"coordinates":[-73.901,40.847405],"type":"Point"}
}