{
  "type": "Feature",
  "properties": {
    "addr:full":"1872 Webster Ave Bronx NY 10457",
    "addr:housenumber":"1872",
    "addr:postcode":"10457",
    "addr:street":"Webster Ave",
    "iso:country":"US",
    "sg:address":"1872 Webster Ave",
    "sg:city":"Bronx",
    "sg:classifiers":[
        {
            "category":"Bars & Pubs",
            "type":"Food & Drink"
        }
    ],
    "sg:phone":"+1 718 294 3112",
    "sg:postcode":"10457",
    "sg:province":"NY",
    "wof:name":"Entertainers Sports Bar & Cafe",
    "wof:placetype":"venue"
},
  "geometry": {"coordinates":[-73.901,40.847405],"type":"Point"}
}