{
  "type": "Feature",
  "properties": {
    "addr:full":"567 Cedar St West Hempstead NY 11552",
    "addr:housenumber":"567",
    "addr:postcode":"11552",
    "addr:street":"Cedar St",
    "iso:country":"US",
    "sg:address":"567 Cedar St",
    "sg:city":"West Hempstead",
    "sg:classifiers":[
        {
            "category":"Wholesale",
            "subcategory":"Non-durable Goods",
            "type":"Manufacturing & Wholesale Goods"
        }
    ],
    "sg:phone":"+1 516 486 6256",
    "sg:postcode":"11552",
    "sg:province":"NY",
    "sg:tags":[
        "novelty",
        "gift"
    ],
    "wof:name":"Ping-An International Inc",
    "wof:placetype":"venue"
},
  "geometry": {"coordinates":[-73.64161,40.699277],"type":"Point"}
}