{
  "type": "Feature",
  "properties": {
    "iso:country":"US",
    "sg:address":"36 James St",
    "sg:city":"Alexandria Bay",
    "sg:classifiers":[
        {
            "category":"Bars & Pubs",
            "type":"Food & Drink"
        }
    ],
    "sg:phone":"+1 315 482 3303",
    "sg:postcode":"13607",
    "sg:province":"NY",
    "sg:tags":[
        "club",
        "night"
    ],
    "wof:name":"Bootlegger's Cafe & Night Club",
    "wof:placetype":"venue"
},
  "geometry": {"coordinates":[-75.917734,44.338042],"type":"Point"}
}