{
  "type": "Feature",
  "properties": {
    "iso:country":"US",
    "sg:address":"6388 Heise Rd",
    "sg:city":"Clarence Center",
    "sg:classifiers":[
        {
            "category":"Real Estate",
            "subcategory":"Real Estate Operator",
            "type":"Services"
        }
    ],
    "sg:phone":"+1 716 741 8592",
    "sg:postcode":"14032",
    "sg:province":"NY",
    "sg:tags":[
        "building",
        "apartment"
    ],
    "wof:name":"Imperium Enterprises Inc",
    "wof:placetype":"venue"
},
  "geometry": {"coordinates":[-78.65253,43.02102],"type":"Point"}
}