{
  "type": "Feature",
  "properties": {
    "addr:full":"210 Post Ave Westbury NY 11590",
    "addr:housenumber":"210",
    "addr:postcode":"11590",
    "addr:street":"Post Ave",
    "iso:country":"US",
    "sg:address":"210 Post Ave",
    "sg:city":"Westbury",
    "sg:classifiers":[
        {
            "category":"Retail",
            "subcategory":"Portrait Studio",
            "type":"Services"
        },
        {
            "category":"Shopping",
            "subcategory":"Pharmacy",
            "type":"Retail Goods"
        }
    ],
    "sg:phone":"+1 516 876 0592",
    "sg:postcode":"11590",
    "sg:province":"NY",
    "sg:tags":[
        "photography",
        "drugstore",
        "store"
    ],
    "wof:name":"Rite Aid Pharmacies",
    "wof:placetype":"venue"
},
  "geometry": {"coordinates":[-73.5877,40.7547],"type":"Point"}
}