{
  "type": "Feature",
  "properties": {
    "addr:full":"27 Lark Dr Woodbury NY 11797",
    "addr:housenumber":"27",
    "addr:postcode":"11797",
    "addr:street":"Lark Dr",
    "iso:country":"US",
    "sg:address":"27 Lark Dr",
    "sg:city":"Woodbury",
    "sg:classifiers":[
        {
            "category":"Arts & Performance",
            "subcategory":"Theater",
            "type":"Entertainment"
        }
    ],
    "sg:phone":"+1 516 579 3535",
    "sg:postcode":"11797",
    "sg:province":"NY",
    "sg:tags":[
        "live",
        "music"
    ],
    "wof:name":"Up-Beat Entertainment",
    "wof:placetype":"venue"
},
  "geometry": {"coordinates":[-73.485798,40.796685],"type":"Point"}
}