{
  "type": "Feature",
  "properties": {
    "iso:country":"US",
    "sg:address":"20928 State Hwy 28",
    "sg:city":"Delhi",
    "sg:classifiers":[
        {
            "category":"Building & Trades",
            "subcategory":"Construction",
            "type":"Services"
        }
    ],
    "sg:phone":"+1 607 746 6400",
    "sg:postcode":"13753",
    "sg:province":"NY",
    "sg:tags":[
        "boring",
        "drilling",
        "contractor"
    ],
    "wof:name":"Tel Power",
    "wof:placetype":"venue"
},
  "geometry": {"coordinates":[-74.892109,42.256104],"type":"Point"}
}