{
  "type": "Feature",
  "properties": {
    "addr:full":"12 Peconic Ave Medford NY 11763",
    "addr:housenumber":"12",
    "addr:postcode":"11763",
    "addr:street":"Peconic Ave",
    "iso:country":"US",
    "sg:address":"12 Peconic Ave",
    "sg:city":"Medford",
    "sg:classifiers":[
        {
            "category":"Freight",
            "type":"Transportation"
        }
    ],
    "sg:phone":"+1   ",
    "sg:postcode":"11763",
    "sg:province":"NY",
    "sg:tags":[
        "operator",
        "refuse",
        "local",
        "system",
        "trucking"
    ],
    "wof:name":"Armar Carting Corp",
    "wof:placetype":"venue"
},
  "geometry": {"coordinates":[-72.96716499999999,40.817828],"type":"Point"}
}