{
  "type": "Feature",
  "properties": {
    "addr:full":"455 Neighborhood Rd Mastic Beach NY 11951",
    "addr:housenumber":"455",
    "addr:postcode":"11951",
    "addr:street":"Neighborhood Rd",
    "iso:country":"US",
    "sg:address":"455 Neighborhood Rd",
    "sg:city":"Mastic Beach",
    "sg:classifiers":[
        {
            "category":"Health Services",
            "subcategory":"Dentist",
            "type":"Services"
        }
    ],
    "sg:phone":"+1 631 281 5717",
    "sg:postcode":"11951",
    "sg:province":"NY",
    "wof:name":"Mond Gregg DMD",
    "wof:placetype":"venue"
},
  "geometry": {"coordinates":[-72.861504,40.761501],"type":"Point"}
}