{
  "type": "Feature",
  "properties": {
    "addr:full":"14 Executive Dr New Hyde Park NY 11040",
    "addr:housenumber":"14",
    "addr:postcode":"11040",
    "addr:street":"Executive Dr New",
    "iso:country":"US",
    "sg:address":"14 Executive Dr",
    "sg:city":"New Hyde Park",
    "sg:classifiers":[
        {
            "category":"Health Services",
            "subcategory":"Clinic",
            "type":"Services"
        }
    ],
    "sg:phone":"+1 516 365 7878",
    "sg:postcode":"11040",
    "sg:province":"NY",
    "sg:tags":[
        "counseling",
        "mental"
    ],
    "wof:name":"Behavior Motivation",
    "wof:placetype":"venue"
},
  "geometry": {"coordinates":[-73.68789700000001,40.758099],"type":"Point"}
}