{
  "type": "Feature",
  "properties": {
    "addr:full":"7201 15th Ave Brooklyn NY 11228",
    "addr:housenumber":"7201",
    "addr:postcode":"11228",
    "addr:street":"15Th Ave",
    "iso:country":"US",
    "sg:address":"7201 15th Ave",
    "sg:city":"Brooklyn",
    "sg:classifiers":[
        {
            "category":"Organizations",
            "subcategory":"Professional Association",
            "type":"Services"
        }
    ],
    "sg:phone":"+1 718 232 6268",
    "sg:postcode":"11228",
    "sg:province":"NY",
    "wof:name":"Associations - Informed Voic",
    "wof:placetype":"venue"
},
  "geometry": {"coordinates":[-74.001818,40.618806],"type":"Point"}
}