{
  "type": "Feature",
  "properties": {
    "addr:full":"100 Martine Ave White Plains NY 10601",
    "addr:housenumber":"100",
    "addr:postcode":"10601",
    "addr:street":"Martine Ave",
    "iso:country":"US",
    "sg:address":"100 Martine Ave",
    "sg:city":"White Plains",
    "sg:classifiers":[
        {
            "category":"Education",
            "subcategory":"Library",
            "type":"Public Place"
        }
    ],
    "sg:phone":"+1 914 422 1406",
    "sg:postcode":"10601",
    "sg:province":"NY",
    "sg:tags":[
        "executive"
    ],
    "wof:name":"White Plains Public Library",
    "wof:placetype":"venue"
},
  "geometry": {"coordinates":[-73.76795799999999,41.030961],"type":"Point"}
}