{
  "type": "Feature",
  "properties": {
    "iso:country":"US",
    "sg:address":"36 Mountain Ash Trl",
    "sg:city":"Webster",
    "sg:classifiers":[
        {
            "category":"Real Estate",
            "subcategory":"Real Estate Operator",
            "type":"Services"
        }
    ],
    "sg:phone":"+1 585 671 7930",
    "sg:postcode":"14580",
    "sg:province":"NY",
    "sg:tags":[
        "condominium"
    ],
    "wof:name":"Willow Point On The Bay",
    "wof:placetype":"venue"
},
  "geometry": {"coordinates":[-77.51237500000001,43.198265],"type":"Point"}
}