{
  "type": "Feature",
  "properties": {
    "addr:full":"160 E 26th Street New York NY 10010",
    "addr:housenumber":"160",
    "addr:postcode":"10010",
    "addr:street":"E 26Th Street",
    "iso:country":"US",
    "sg:address":"160 E 26th Street",
    "sg:city":"New York",
    "sg:classifiers":[
        {
            "category":"Restaurant",
            "type":"Food & Drink"
        }
    ],
    "sg:phone":"+1 212 532 3323",
    "sg:postcode":"10010",
    "sg:province":"NY",
    "wof:name":"Famous Pubs",
    "wof:placetype":"venue"
},
  "geometry": {"coordinates":[-73.98237,40.740924],"type":"Point"}
}