{
  "type": "Feature",
  "properties": {
    "addr:full":"7610 18th Ave Brooklyn NY 11214",
    "addr:housenumber":"7610",
    "addr:postcode":"11214",
    "addr:street":"18Th Ave",
    "iso:country":"US",
    "sg:address":"7610 18th Ave",
    "sg:city":"Brooklyn",
    "sg:classifiers":[
        {
            "category":"Communications",
            "type":"Services"
        }
    ],
    "sg:phone":"+1 718 331 2886",
    "sg:postcode":"11214",
    "sg:province":"NY",
    "wof:name":"Beyond Communications",
    "wof:placetype":"venue"
},
  "geometry": {"coordinates":[-73.997186,40.612319],"type":"Point"}
}