{
  "type": "Feature",
  "properties": {
    "iso:country":"US",
    "sg:address":"356 Lake Ave",
    "sg:city":"Saint James",
    "sg:classifiers":[
        {
            "category":"Food & Beverages",
            "subcategory":"Groceries & Convenience Stores",
            "type":"Retail Goods"
        }
    ],
    "sg:phone":"+1 631 862 8210",
    "sg:postcode":"11780",
    "sg:province":"NY",
    "wof:name":"7-Eleven",
    "wof:placetype":"venue"
},
  "geometry": {"coordinates":[-73.157061,40.879206],"type":"Point"}
}