{
  "type": "Feature",
  "properties": {
    "iso:country":"US",
    "sg:address":"15 W 53rd Street",
    "sg:city":"New York",
    "sg:classifiers":[
        {
            "category":"Arts & Performance",
            "subcategory":"Art Gallery",
            "type":"Entertainment"
        }
    ],
    "sg:phone":"+1 212 977 7966",
    "sg:postcode":"10019",
    "sg:province":"NY",
    "wof:name":"Yasuda Fine Arts",
    "wof:placetype":"venue"
},
  "geometry": {"coordinates":[-73.978004,40.761214],"type":"Point"}
}