{
  "type": "Feature",
  "properties": {
    "iso:country":"US",
    "sg:address":"230 Red Apple Ct",
    "sg:city":"Central Valley",
    "sg:classifiers":[
        {
            "category":"Shopping",
            "subcategory":"Discount & Variety Stores",
            "type":"Retail Goods"
        }
    ],
    "sg:phone":"+1 845 928 5280",
    "sg:postcode":"10917",
    "sg:province":"NY",
    "sg:tags":[
        "outlet"
    ],
    "wof:name":"Movado Company Store Woodbury Cmn Premium Outlet",
    "wof:placetype":"venue"
},
  "geometry": {"coordinates":[-74.126999,41.314602],"type":"Point"}
}