{
  "type": "Feature",
  "properties": {
    "addr:full":"68 40th St Islip NY 11751",
    "addr:housenumber":"68",
    "addr:postcode":"11751",
    "addr:street":"40Th St",
    "iso:country":"US",
    "sg:address":"68 40th St",
    "sg:city":"Islip",
    "sg:classifiers":[
        {
            "category":"Manufacturing",
            "subcategory":"Food",
            "type":"Manufacturing & Wholesale Goods"
        },
        {
            "category":"Wholesale",
            "subcategory":"Groceries",
            "type":"Manufacturing & Wholesale Goods"
        }
    ],
    "sg:phone":"+1 631 224 1234",
    "sg:postcode":"11751",
    "sg:province":"NY",
    "sg:tags":[
        "baker",
        "product",
        "mfg"
    ],
    "wof:name":"Dessert Dessert Inc",
    "wof:placetype":"venue"
},
  "geometry": {"coordinates":[-73.216055,40.752458],"type":"Point"}
}