{
  "type": "Feature",
  "properties": {
    "addr:full":"5788 Bridge St East Syracuse NY 13057",
    "addr:housenumber":"5788",
    "addr:postcode":"13057",
    "addr:street":"Bridge St",
    "iso:country":"US",
    "sg:address":"5788 Bridge St",
    "sg:city":"East Syracuse",
    "sg:classifiers":[
        {
            "category":"Shopping",
            "subcategory":"Department Store",
            "type":"Retail Goods"
        }
    ],
    "sg:phone":"+1 315 446 5316",
    "sg:postcode":"13057",
    "sg:province":"NY",
    "sg:tags":[
        "shop"
    ],
    "sg:website":"www.pier1.com",
    "wof:name":"Pier 1 Imports",
    "wof:placetype":"venue"
},
  "geometry": {"coordinates":[-76.071314,43.049727],"type":"Point"}
}