{
  "type": "Feature",
  "properties": {
    "addr:full":"2160 Madison Ave New York NY 10037",
    "addr:housenumber":"2160",
    "addr:postcode":"10037",
    "addr:street":"Madison Ave",
    "iso:country":"US",
    "sg:address":"2160 Madison Ave",
    "sg:city":"New York",
    "sg:classifiers":[
        {
            "category":"Social Services",
            "subcategory":"Child Care",
            "type":"Services"
        }
    ],
    "sg:phone":"+1 917 507 3730",
    "sg:postcode":"10037",
    "sg:province":"NY",
    "sg:tags":[
        "day"
    ],
    "wof:name":"Warner's Learning Center",
    "wof:placetype":"venue"
},
  "geometry": {"coordinates":[-73.93759900000001,40.812698],"type":"Point"}
}