{
  "type": "Feature",
  "properties": {
    "addr:full":"88 Roosevelt Ave Jackson Heights NY 11372",
    "addr:housenumber":"88",
    "addr:postcode":"11372",
    "addr:street":"Roosevelt Ave",
    "iso:country":"US",
    "sg:address":"88 Roosevelt Ave",
    "sg:city":"Jackson Heights",
    "sg:classifiers":[
        {
            "category":"Shopping",
            "subcategory":"Shoes",
            "type":"Retail Goods"
        }
    ],
    "sg:phone":"+1   ",
    "sg:postcode":"11372",
    "sg:province":"NY",
    "sg:tags":[
        "jacket"
    ],
    "wof:name":"Zapateria Mexico Inc",
    "wof:placetype":"venue"
},
  "geometry": {"coordinates":[-73.893173,40.746559],"type":"Point"}
}