{
  "type": "Feature",
  "properties": {
    "iso:country":"US",
    "sg:address":"2225 Clinton Ave S",
    "sg:city":"Rochester",
    "sg:classifiers":[
        {
            "category":"Health Services",
            "subcategory":"Podiatrist",
            "type":"Services"
        }
    ],
    "sg:phone":"+1 585 473 5051",
    "sg:postcode":"14618",
    "sg:province":"NY",
    "wof:name":"Louis J Tallo DPM",
    "wof:placetype":"venue"
},
  "geometry": {"coordinates":[-77.596974,43.115743],"type":"Point"}
}