{
  "type": "Feature",
  "properties": {
    "addr:full":"165 Park Row New York NY 10038",
    "addr:housenumber":"165",
    "addr:postcode":"10038",
    "addr:street":"Park Row",
    "iso:country":"US",
    "sg:address":"165 Park Row",
    "sg:city":"New York",
    "sg:classifiers":[
        {
            "category":"Building & Trades",
            "subcategory":"Locksmith",
            "type":"Services"
        }
    ],
    "sg:phone":"+1 212 897 7639",
    "sg:postcode":"10038",
    "sg:province":"NY",
    "sg:tags":[
        "key"
    ],
    "wof:name":"AA Emergency Locksmith Co",
    "wof:placetype":"venue"
},
  "geometry": {"coordinates":[-74.001503,40.712799],"type":"Point"}
}