{
  "type": "Feature",
  "properties": {
    "iso:country":"US",
    "sg:address":"10432 Crump Rd",
    "sg:city":"Glenwood",
    "sg:classifiers":[
        {
            "category":"Real Estate",
            "subcategory":"Surveying",
            "type":"Services"
        }
    ],
    "sg:phone":"+1 716 592 7740",
    "sg:postcode":"14069",
    "sg:province":"NY",
    "sg:tags":[
        "surveyor"
    ],
    "sg:website":"www.freemansurveyors.com",
    "wof:name":"Freeman & Freeman",
    "wof:placetype":"venue"
},
  "geometry": {"coordinates":[-78.610463,42.606344],"type":"Point"}
}