{
  "type": "Feature",
  "properties": {
    "addr:full":"371 Amsterdam Ave New York NY 10024",
    "addr:housenumber":"371",
    "addr:postcode":"10024",
    "addr:street":"Amsterdam Ave",
    "iso:country":"US",
    "sg:address":"371 Amsterdam Ave",
    "sg:city":"New York",
    "sg:classifiers":[
        {
            "category":"Sports & Exercise",
            "subcategory":"Gym",
            "type":"Entertainment"
        }
    ],
    "sg:phone":"+1 212 721 4000",
    "sg:postcode":"10024",
    "sg:province":"NY",
    "sg:tags":[
        "yoga"
    ],
    "wof:name":"Integral Interfaith Weddings",
    "wof:placetype":"venue"
},
  "geometry": {"coordinates":[-73.978667,40.782102],"type":"Point"}
}