{
  "type": "Feature",
  "properties": {
    "addr:full":"501 Milton Rd Rye NY 10580",
    "addr:housenumber":"501",
    "addr:postcode":"10580",
    "addr:street":"Milton Rd",
    "iso:country":"US",
    "sg:address":"501 Milton Rd",
    "sg:city":"Rye",
    "sg:classifiers":[
        {
            "category":"Professional",
            "subcategory":"Business Services",
            "type":"Services"
        }
    ],
    "sg:phone":"+1 914 921 6188",
    "sg:postcode":"10580",
    "sg:province":"NY",
    "sg:tags":[
        "interior",
        "consultant",
        "design",
        "decorator"
    ],
    "wof:name":"Karen Mulhern Design",
    "wof:placetype":"venue"
},
  "geometry": {"coordinates":[-73.68752499999999,40.963915],"type":"Point"}
}