{
  "type": "Feature",
  "properties": {
    "iso:country":"US",
    "sg:address":"6989 Transit Rd",
    "sg:city":"East Amherst",
    "sg:classifiers":[
        {
            "category":"Education",
            "subcategory":"Dance Studio",
            "type":"Public Place"
        }
    ],
    "sg:phone":"+1 716 636 1060",
    "sg:postcode":"14051",
    "sg:province":"NY",
    "sg:tags":[
        "instruction",
        "dancing"
    ],
    "wof:name":"Celebrity Dance Emporium",
    "wof:placetype":"venue"
},
  "geometry": {"coordinates":[-78.696848,43.042352],"type":"Point"}
}