{
  "type": "Feature",
  "properties": {
    "iso:country":"US",
    "sg:address":"123 Lafayette Street",
    "sg:city":"New York",
    "sg:classifiers":[
        {
            "category":"Health Services",
            "subcategory":"Doctor",
            "type":"Services"
        }
    ],
    "sg:phone":"+1 212 680 0538",
    "sg:postcode":"10013",
    "sg:province":"NY",
    "wof:name":"Chinatown Community Medical PC",
    "wof:placetype":"venue"
},
  "geometry": {"coordinates":[-74.000342,40.718776],"type":"Point"}
}