{
  "type": "Feature",
  "properties": {
    "addr:full":"1620 59th St Brooklyn NY 11204",
    "addr:housenumber":"1620",
    "addr:postcode":"11204",
    "addr:street":"59Th St",
    "iso:country":"US",
    "sg:address":"1620 59th St",
    "sg:city":"Brooklyn",
    "sg:classifiers":[
        {
            "category":"Restaurant",
            "type":"Food & Drink"
        }
    ],
    "sg:phone":"+1   ",
    "sg:postcode":"11204",
    "sg:province":"NY",
    "sg:tags":[
        "eating"
    ],
    "wof:name":"S Tyberg Catering Inc",
    "wof:placetype":"venue"
},
  "geometry": {"coordinates":[-73.99132899999999,40.625349],"type":"Point"}
}