{
  "type": "Feature",
  "properties": {
    "addr:full":"29 Commerce St Schenectady NY 12302",
    "addr:housenumber":"29",
    "addr:postcode":"12302",
    "addr:street":"Commerce St",
    "iso:country":"US",
    "sg:address":"29 Commerce St",
    "sg:city":"Schenectady",
    "sg:classifiers":[
        {
            "category":"Building & Trades",
            "subcategory":"Electrical",
            "type":"Services"
        }
    ],
    "sg:phone":"+1 518 370 4828",
    "sg:postcode":"12302",
    "sg:province":"NY",
    "sg:tags":[
        "electrical",
        "contractor"
    ],
    "wof:name":"Joe Casella & Sons Electric",
    "wof:placetype":"venue"
},
  "geometry": {"coordinates":[-73.961521,42.838249],"type":"Point"}
}