{
  "type": "Feature",
  "properties": {
    "iso:country":"US",
    "sg:address":"66 Hortontown Hill Rd",
    "sg:city":"Hopewell Junction",
    "sg:classifiers":[
        {
            "category":"Retail",
            "subcategory":"Veterinary Services",
            "type":"Services"
        }
    ],
    "sg:phone":"+1 845 226 3290",
    "sg:postcode":"12533",
    "sg:province":"NY",
    "wof:name":"Community Pet Center",
    "wof:placetype":"venue"
},
  "geometry": {"coordinates":[-73.80391299999999,41.499627],"type":"Point"}
}