{
  "type": "Feature",
  "properties": {
    "iso:country":"US",
    "sg:address":"170 Old Country Rd Ste 610",
    "sg:city":"Mineola",
    "sg:classifiers":[
        {
            "category":"Professional",
            "subcategory":"Lawyer & Legal Services",
            "type":"Services"
        }
    ],
    "sg:phone":"+1 516 858 0075",
    "sg:postcode":"11501",
    "sg:province":"NY",
    "sg:website":"www.austinlawassociates.com/",
    "wof:name":"Austin Law Associates, PC",
    "wof:placetype":"venue"
},
  "geometry": {"coordinates":[-73.637259,40.739388],"type":"Point"}
}