{
  "type": "Feature",
  "properties": {
    "iso:country":"US",
    "sg:address":"612 North Ave",
    "sg:city":"New Rochelle",
    "sg:classifiers":[
        {
            "category":"Retail",
            "subcategory":"Auto Repair",
            "type":"Services"
        }
    ],
    "sg:phone":"+1 914 633 4166",
    "sg:postcode":"10801",
    "sg:province":"NY",
    "sg:tags":[
        "general"
    ],
    "wof:name":"Performance Auto Clinic",
    "wof:placetype":"venue"
},
  "geometry": {"coordinates":[-73.78816399999999,40.921887],"type":"Point"}
}