{
  "type": "Feature",
  "properties": {
    "iso:country":"US",
    "sg:address":"3 Mulberry St",
    "sg:city":"Rhinebeck",
    "sg:classifiers":[
        {
            "category":"Organizations",
            "subcategory":"Religious Organization",
            "type":"Services"
        }
    ],
    "sg:phone":"+1 845 876 1767",
    "sg:postcode":"12572",
    "sg:province":"NY",
    "sg:tags":[
        "clergy"
    ],
    "wof:name":"Lawrence Xavier",
    "wof:placetype":"venue"
},
  "geometry": {"coordinates":[-73.90728799999999,41.926204],"type":"Point"}
}