{
  "type": "Feature",
  "properties": {
    "iso:country":"US",
    "sg:address":"318 Scudder Ave",
    "sg:city":"Northport",
    "sg:classifiers":[
        {
            "category":"Professional",
            "subcategory":"Computer Services",
            "type":"Services"
        }
    ],
    "sg:phone":"+1   ",
    "sg:postcode":"11768",
    "sg:province":"NY",
    "sg:tags":[
        "damaged",
        "hard",
        "drive",
        "recovery"
    ],
    "wof:name":"Digital Data Recovery Inc",
    "wof:placetype":"venue"
},
  "geometry": {"coordinates":[-73.343039,40.894754],"type":"Point"}
}