{
  "type": "Feature",
  "properties": {
    "addr:full":"209 W Islip Rd West Islip NY 11795",
    "addr:housenumber":"209",
    "addr:postcode":"11795",
    "addr:street":"W Islip Rd",
    "iso:country":"US",
    "sg:address":"209 W Islip Rd",
    "sg:city":"West Islip",
    "sg:classifiers":[
        {
            "category":"Professional",
            "type":"Services"
        }
    ],
    "sg:phone":"+1   ",
    "sg:postcode":"11795",
    "sg:province":"NY",
    "wof:name":"Viking Resources Inc",
    "wof:placetype":"venue"
},
  "geometry": {"coordinates":[-73.316822,40.694682],"type":"Point"}
}