{
  "type": "Feature",
  "properties": {
    "addr:full":"38 Pebble Ln Staten Island NY 10305",
    "addr:housenumber":"38",
    "addr:postcode":"10305",
    "addr:street":"Pebble Ln",
    "iso:country":"US",
    "sg:address":"38 Pebble Ln",
    "sg:city":"Staten Island",
    "sg:classifiers":[
        {
            "category":"Recreation",
            "type":"Entertainment"
        }
    ],
    "sg:phone":"+1 718 815 8858",
    "sg:postcode":"10305",
    "sg:province":"NY",
    "wof:name":"Denchakroun Yssine Inc",
    "wof:placetype":"venue"
},
  "geometry": {"coordinates":[-74.06626199999999,40.59907],"type":"Point"}
}