{
  "type": "Feature",
  "properties": {
    "iso:country":"US",
    "sg:address":"244 Paul Rd",
    "sg:city":"Rochester",
    "sg:classifiers":[
        {
            "category":"Professional",
            "subcategory":"Lawyer & Legal Services",
            "type":"Services"
        }
    ],
    "sg:phone":"+1 585 328 3180",
    "sg:postcode":"14624",
    "sg:province":"NY",
    "sg:tags":[
        "attorney"
    ],
    "wof:name":"Kernzer & Galliher",
    "wof:placetype":"venue"
},
  "geometry": {"coordinates":[-77.69231499999999,43.107015],"type":"Point"}
}