{
  "type": "Feature",
  "properties": {
    "addr:full":"1366 E 32nd St Brooklyn NY 11210",
    "addr:housenumber":"1366",
    "addr:postcode":"11210",
    "addr:street":"E 32Nd St",
    "iso:country":"US",
    "sg:address":"1366 E 32nd St",
    "sg:city":"Brooklyn",
    "sg:classifiers":[
        {
            "category":"Health Services",
            "subcategory":"Doctor",
            "type":"Services"
        }
    ],
    "sg:phone":"+1 718 891 5595",
    "sg:postcode":"11210",
    "sg:province":"NY",
    "sg:tags":[
        "physician",
        "surgeon"
    ],
    "wof:name":"Eduardo Plantilla MD",
    "wof:placetype":"venue"
},
  "geometry": {"coordinates":[-73.943386,40.618507],"type":"Point"}
}