{
  "type": "Feature",
  "properties": {
    "iso:country":"US",
    "sg:address":"6316 Bay Parkway",
    "sg:city":"Brooklyn",
    "sg:classifiers":[
        {
            "category":"Restaurant",
            "type":"Food & Drink"
        }
    ],
    "sg:phone":"+1 718 837 0366",
    "sg:postcode":"11204",
    "sg:province":"NY",
    "wof:name":"Golden Dynasty Restaurant",
    "wof:placetype":"venue"
},
  "geometry": {"coordinates":[-73.98073599999999,40.614689],"type":"Point"}
}