{
  "type": "Feature",
  "properties": {
    "addr:full":"2335 1 Ave New York NY 10035",
    "addr:housenumber":"2335",
    "addr:postcode":"10035",
    "addr:street":"1 Ave",
    "iso:country":"US",
    "sg:address":"2335 1 Ave",
    "sg:city":"New York",
    "sg:classifiers":[
        {
            "category":"Wholesale",
            "subcategory":"Groceries",
            "type":"Manufacturing & Wholesale Goods"
        }
    ],
    "sg:phone":"+1 212 996 3238",
    "sg:postcode":"10035",
    "sg:province":"NY",
    "sg:tags":[
        "grocer"
    ],
    "wof:name":"A C Grocery & Deli",
    "wof:placetype":"venue"
},
  "geometry": {"coordinates":[-73.93491299999999,40.796679],"type":"Point"}
}