{
  "type": "Feature",
  "properties": {
    "addr:full":"857 Ulster Ave Kingston NY 12401",
    "addr:housenumber":"857",
    "addr:postcode":"12401",
    "addr:street":"Ulster Ave",
    "iso:country":"US",
    "sg:address":"857 Ulster Ave",
    "sg:city":"Kingston",
    "sg:classifiers":[
        {
            "category":"Restaurant",
            "type":"Food & Drink"
        }
    ],
    "sg:phone":"+1 845 331 7200",
    "sg:postcode":"12401",
    "sg:province":"NY",
    "sg:tags":[
        "drinking",
        "eating"
    ],
    "sg:website":"www.thebowerydugout.com",
    "wof:name":"Bowery Dugout The",
    "wof:placetype":"venue"
},
  "geometry": {"coordinates":[-73.994523,41.954475],"type":"Point"}
}