{
  "type": "Feature",
  "properties": {
    "addr:full":"202 Gardner Ave Jericho NY 11753",
    "addr:housenumber":"202",
    "addr:postcode":"11753",
    "addr:street":"Gardner Ave",
    "iso:country":"US",
    "sg:address":"202 Gardner Ave",
    "sg:city":"Jericho",
    "sg:classifiers":[
        {
            "category":"Shopping",
            "subcategory":"Gifts & Souvenirs",
            "type":"Retail Goods"
        }
    ],
    "sg:phone":"+1   ",
    "sg:postcode":"11753",
    "sg:province":"NY",
    "sg:tags":[
        "basket",
        "silk",
        "flower"
    ],
    "wof:name":"Simple Treasures",
    "wof:placetype":"venue"
},
  "geometry": {"coordinates":[-73.536176,40.779658],"type":"Point"}
}