{
  "type": "Feature",
  "properties": {
    "iso:country":"US",
    "sg:address":"50 Cherry St",
    "sg:city":"Katonah",
    "sg:classifiers":[
        {
            "category":"Building & Trades",
            "subcategory":"Construction",
            "type":"Services"
        }
    ],
    "sg:phone":"+1 914 232 7433",
    "sg:postcode":"10536",
    "sg:province":"NY",
    "sg:tags":[
        "home"
    ],
    "wof:name":"J & H Contracting Inc",
    "wof:placetype":"venue"
},
  "geometry": {"coordinates":[-73.699972,41.266437],"type":"Point"}
}