{
  "type": "Feature",
  "properties": {
    "iso:country":"US",
    "sg:address":"825 8 Ave",
    "sg:city":"New York",
    "sg:classifiers":[
        {
            "category":"Professional",
            "subcategory":"Business Services",
            "type":"Services"
        }
    ],
    "sg:phone":"+1 212 408 6100",
    "sg:postcode":"10019",
    "sg:province":"NY",
    "wof:name":"London Records",
    "wof:placetype":"venue"
},
  "geometry": {"coordinates":[-73.98656099999999,40.76166],"type":"Point"}
}