{
  "type": "Feature",
  "properties": {
    "addr:full":"4024 5th Ave Brooklyn NY 11232",
    "addr:housenumber":"4024",
    "addr:postcode":"11232",
    "addr:street":"5Th Ave",
    "iso:country":"US",
    "sg:address":"4024 5th Ave",
    "sg:city":"Brooklyn",
    "sg:classifiers":[
        {
            "category":"Shopping",
            "subcategory":"Discount & Variety Stores",
            "type":"Retail Goods"
        }
    ],
    "sg:phone":"+1 718 686 0758",
    "sg:postcode":"11232",
    "sg:province":"NY",
    "wof:name":"Ninety Nine Cents Vrty Store",
    "wof:placetype":"venue"
},
  "geometry": {"coordinates":[-74.00502400000001,40.650331],"type":"Point"}
}