{
  "type": "Feature",
  "properties": {
    "addr:full":"8 Roaring Brook Dr Putnam Valley NY 10579",
    "addr:housenumber":"8",
    "addr:postcode":"10579",
    "addr:street":"Roaring Brook Dr Putnam",
    "iso:country":"US",
    "sg:address":"8 Roaring Brook Dr",
    "sg:city":"Putnam Valley",
    "sg:classifiers":[
        {
            "category":"Professional",
            "type":"Services"
        }
    ],
    "sg:phone":"+1   ",
    "sg:postcode":"10579",
    "sg:province":"NY",
    "wof:name":"Anthony P Dinota",
    "wof:placetype":"venue"
},
  "geometry": {"coordinates":[-73.797307,41.441047],"type":"Point"}
}