{
  "type": "Feature",
  "properties": {
    "addr:full":"413 E 70th St New York NY 10021",
    "addr:housenumber":"413",
    "addr:postcode":"10021",
    "addr:street":"E 70Th St",
    "iso:country":"US",
    "sg:address":"413 E 70th St",
    "sg:city":"New York",
    "sg:classifiers":[
        {
            "category":"Bars & Pubs",
            "type":"Food & Drink"
        }
    ],
    "sg:phone":"+1 212 861 7700",
    "sg:postcode":"10021",
    "sg:province":"NY",
    "wof:name":"For Pete's Sake",
    "wof:placetype":"venue"
},
  "geometry": {"coordinates":[-73.955725,40.766276],"type":"Point"}
}