{
  "type": "Feature",
  "properties": {
    "iso:country":"US",
    "sg:address":"6 Forest Dr",
    "sg:city":"Jericho",
    "sg:classifiers":[
        {
            "category":"Manufacturing",
            "subcategory":"Apparel",
            "type":"Manufacturing & Wholesale Goods"
        }
    ],
    "sg:phone":"+1   ",
    "sg:postcode":"11753",
    "sg:province":"NY",
    "wof:name":"Sooner Screenprinters",
    "wof:placetype":"venue"
},
  "geometry": {"coordinates":[-73.518593,40.798437],"type":"Point"}
}