{
  "type": "Feature",
  "properties": {
    "addr:full":"25 White St Cohoes NY 12047",
    "addr:housenumber":"25",
    "addr:postcode":"12047",
    "addr:street":"White St",
    "iso:country":"US",
    "sg:address":"25 White St",
    "sg:city":"Cohoes",
    "sg:classifiers":[
        {
            "category":"Restaurant",
            "type":"Food & Drink"
        }
    ],
    "sg:phone":"+1 518 235 3199",
    "sg:postcode":"12047",
    "sg:province":"NY",
    "wof:name":"Black Cat Ale House",
    "wof:placetype":"venue"
},
  "geometry": {"coordinates":[-73.701318,42.772694],"type":"Point"}
}