{
  "type": "Feature",
  "properties": {
    "addr:full":"560 Tuckahoe Rd Yonkers NY 10710",
    "addr:housenumber":"560",
    "addr:postcode":"10710",
    "addr:street":"Tuckahoe Rd",
    "iso:country":"US",
    "sg:address":"560 Tuckahoe Rd",
    "sg:city":"Yonkers",
    "sg:classifiers":[
        {
            "category":"Professional",
            "subcategory":"Accounting & Tax Preparation",
            "type":"Services"
        }
    ],
    "sg:phone":"+1   ",
    "sg:postcode":"10710",
    "sg:province":"NY",
    "sg:tags":[
        "billing"
    ],
    "wof:name":"Express Billing Service",
    "wof:placetype":"venue"
},
  "geometry": {"coordinates":[-73.850137,40.952697],"type":"Point"}
}