{
  "type": "Feature",
  "properties": {
    "addr:full":"2484 7th Ave New York NY 10030",
    "addr:housenumber":"2484",
    "addr:postcode":"10030",
    "addr:street":"7Th Ave",
    "iso:country":"US",
    "sg:address":"2484 7th Ave",
    "sg:city":"New York",
    "sg:classifiers":[
        {
            "category":"Personal",
            "subcategory":"Beauty Salon",
            "type":"Services"
        }
    ],
    "sg:phone":"+1 212 491 6707",
    "sg:postcode":"10030",
    "sg:province":"NY",
    "wof:name":"Ada's Beauty Salon",
    "wof:placetype":"venue"
},
  "geometry": {"coordinates":[-73.93922499999999,40.821523],"type":"Point"}
}