{
  "type": "Feature",
  "properties": {
    "iso:country":"US",
    "sg:address":"140 S Ocean Ave",
    "sg:city":"Freeport",
    "sg:classifiers":[
        {
            "category":"Insurance",
            "subcategory":"Insurance Agent",
            "type":"Services"
        },
        {
            "category":"Insurance",
            "subcategory":"Hazard Insurance",
            "type":"Services"
        }
    ],
    "sg:phone":"+1 516 377 0300",
    "sg:postcode":"11520",
    "sg:province":"NY",
    "sg:tags":[
        "adjuster"
    ],
    "sg:website":"http://www.maguireandmaguire.com",
    "wof:name":"Maguire & Maguire Inc",
    "wof:placetype":"venue"
},
  "geometry": {"coordinates":[-73.585971,40.652043],"type":"Point"}
}