{
  "type": "Feature",
  "properties": {
    "addr:full":"1037 Kensington Ave Buffalo NY 14215",
    "addr:housenumber":"1037",
    "addr:postcode":"14215",
    "addr:street":"Kensington Ave",
    "iso:country":"US",
    "sg:address":"1037 Kensington Ave",
    "sg:city":"Buffalo",
    "sg:classifiers":[
        {
            "category":"Organizations",
            "subcategory":"Religious Organization",
            "type":"Services"
        }
    ],
    "sg:phone":"+1 716 836 5702",
    "sg:postcode":"14215",
    "sg:province":"NY",
    "sg:tags":[
        "church"
    ],
    "wof:name":"Mission Of God",
    "wof:placetype":"venue"
},
  "geometry": {"coordinates":[-78.815387,42.937153],"type":"Point"}
}