{
  "type": "Feature",
  "properties": {
    "addr:full":"1301 Ave of the Americas New York NY 10019",
    "addr:housenumber":"1301",
    "addr:postcode":"10019",
    "addr:street":"Ave Of The Americas",
    "iso:country":"US",
    "sg:address":"1301 Ave of the Americas",
    "sg:city":"New York",
    "sg:classifiers":[
        {
            "category":"Professional",
            "type":"Services"
        }
    ],
    "sg:phone":"+1 212 245 7550",
    "sg:postcode":"10019",
    "sg:province":"NY",
    "sg:tags":[
        "establishment"
    ],
    "wof:name":"Kasowitz",
    "wof:placetype":"venue"
},
  "geometry": {"coordinates":[-73.979057,40.76177],"type":"Point"}
}