{
  "type": "Feature",
  "properties": {
    "iso:country":"US",
    "sg:address":"325 Gifford St",
    "sg:city":"Syracuse",
    "sg:classifiers":[
        {
            "category":"Food & Beverages",
            "subcategory":"Groceries & Convenience Stores",
            "type":"Retail Goods"
        }
    ],
    "sg:phone":"+1 315 476 1757",
    "sg:postcode":"13204",
    "sg:province":"NY",
    "sg:tags":[
        "grocer"
    ],
    "wof:name":"Di Maria's Groceries",
    "wof:placetype":"venue"
},
  "geometry": {"coordinates":[-76.16024899999999,43.043278],"type":"Point"}
}