{
  "type": "Feature",
  "properties": {
    "addr:full":"30 Church St Rochester NY 14614",
    "addr:housenumber":"30",
    "addr:postcode":"14614",
    "addr:street":"Church St",
    "iso:country":"US",
    "sg:address":"30 Church St",
    "sg:city":"Rochester",
    "sg:classifiers":[
        {
            "category":"Manufacturing",
            "subcategory":"Tools & Machinery",
            "type":"Manufacturing & Wholesale Goods"
        }
    ],
    "sg:phone":"+1   ",
    "sg:postcode":"14614",
    "sg:province":"NY",
    "sg:tags":[
        "measuring",
        "instrument",
        "electrical",
        "mfg"
    ],
    "wof:name":"City of Rochester The",
    "wof:placetype":"venue"
},
  "geometry": {"coordinates":[-77.614859,43.15681],"type":"Point"}
}