{
  "type": "Feature",
  "properties": {
    "iso:country":"US",
    "sg:address":"228 7th Avenue",
    "sg:city":"Brooklyn",
    "sg:classifiers":[
        {
            "category":"Shopping",
            "subcategory":"Mobile Phones",
            "type":"Retail Goods"
        }
    ],
    "sg:phone":"+1 718 369 6969",
    "sg:postcode":"11215",
    "sg:province":"NY",
    "wof:name":"Cel Tel",
    "wof:placetype":"venue"
},
  "geometry": {"coordinates":[-73.97891,40.670163],"type":"Point"}
}