{
  "type": "Feature",
  "properties": {
    "iso:country":"US",
    "sg:address":"70 Fernbrook St",
    "sg:city":"Yonkers",
    "sg:classifiers":[
        {
            "category":"Bus Charters",
            "type":"Transportation"
        }
    ],
    "sg:phone":"+1   ",
    "sg:postcode":"10705",
    "sg:province":"NY",
    "sg:tags":[
        "passenger",
        "school",
        "chart",
        "operator",
        "local",
        "transport"
    ],
    "wof:name":"Autobus Inc",
    "wof:placetype":"venue"
},
  "geometry": {"coordinates":[-73.906223,40.924647],"type":"Point"}
}