{
  "type": "Feature",
  "properties": {
    "iso:country":"US",
    "sg:address":"106 Ridge St",
    "sg:city":"New York",
    "sg:classifiers":[
        {
            "category":"Shopping",
            "subcategory":"Bicycles & Sporting Goods",
            "type":"Retail Goods"
        }
    ],
    "sg:phone":"+1 212 388 1077",
    "sg:postcode":"10002",
    "sg:province":"NY",
    "sg:tags":[
        "bike"
    ],
    "sg:website":"www.bikecult.com/works",
    "wof:name":"Bike Works",
    "wof:placetype":"venue"
},
  "geometry": {"coordinates":[-73.98312199999999,40.718696],"type":"Point"}
}