{
  "type": "Feature",
  "properties": {
    "iso:country":"US",
    "sg:address":"1615 1st Ave",
    "sg:city":"New York",
    "sg:classifiers":[
        {
            "category":"Retail",
            "subcategory":"Laundry & Dry Cleaning",
            "type":"Services"
        }
    ],
    "sg:phone":"+1 212 249 9493",
    "sg:postcode":"10028",
    "sg:province":"NY",
    "wof:name":"Swans III Cleaners",
    "wof:placetype":"venue"
},
  "geometry": {"coordinates":[-73.95059999999999,40.775398],"type":"Point"}
}