{
  "type": "Feature",
  "properties": {
    "iso:country":"US",
    "sg:address":"95 Beekman Ave",
    "sg:city":"Sleepy Hollow",
    "sg:classifiers":[
        {
            "category":"Real Estate",
            "subcategory":"Architect",
            "type":"Services"
        }
    ],
    "sg:phone":"+1 914 631 9107",
    "sg:postcode":"10591",
    "sg:province":"NY",
    "sg:tags":[
        "architectural"
    ],
    "wof:name":"Turnquist Architects",
    "wof:placetype":"venue"
},
  "geometry": {"coordinates":[-73.862601,41.084185],"type":"Point"}
}