{
  "type": "Feature",
  "properties": {
    "addr:full":"1300 Hertel Ave Buffalo NY 14216",
    "addr:housenumber":"1300",
    "addr:postcode":"14216",
    "addr:street":"Hertel Ave",
    "iso:country":"US",
    "sg:address":"1300 Hertel Ave",
    "sg:city":"Buffalo",
    "sg:classifiers":[
        {
            "category":"Shopping",
            "subcategory":"Clothing, Apparel, & Fashions",
            "type":"Retail Goods"
        }
    ],
    "sg:phone":"+1 716 876 2045",
    "sg:postcode":"14216",
    "sg:province":"NY",
    "sg:tags":[
        "lingerie"
    ],
    "wof:name":"Cupid's Lingerie Boutique",
    "wof:placetype":"venue"
},
  "geometry": {"coordinates":[-78.859433,42.947807],"type":"Point"}
}