{
  "type": "Feature",
  "properties": {
    "addr:full":"212 Mineola Ave Roslyn Heights NY 11577",
    "addr:housenumber":"212",
    "addr:postcode":"11577",
    "addr:street":"Mineola Ave",
    "iso:country":"US",
    "sg:address":"212 Mineola Ave",
    "sg:city":"Roslyn Heights",
    "sg:classifiers":[
        {
            "category":"Retail",
            "subcategory":"Veterinary Services",
            "type":"Services"
        }
    ],
    "sg:phone":"+1 516 484 6622",
    "sg:postcode":"11577",
    "sg:province":"NY",
    "sg:tags":[
        "veterinarian"
    ],
    "wof:name":"Animal Hospital of Roslyn",
    "wof:placetype":"venue"
},
  "geometry": {"coordinates":[-73.649399,40.786201],"type":"Point"}
}