{
  "type": "Feature",
  "properties": {
    "addr:full":"555 Bedford Rd Bedford Hills NY 10507",
    "addr:housenumber":"555",
    "addr:postcode":"10507",
    "addr:street":"Bedford Rd",
    "iso:country":"US",
    "sg:address":"555 Bedford Rd",
    "sg:city":"Bedford Hills",
    "sg:classifiers":[
        {
            "category":"Wholesale",
            "subcategory":"Plants",
            "type":"Manufacturing & Wholesale Goods"
        },
        {
            "category":"Building & Trades",
            "subcategory":"Landscaping Services",
            "type":"Services"
        }
    ],
    "sg:phone":"+1 914 242 5472",
    "sg:postcode":"10507",
    "sg:province":"NY",
    "sg:tags":[
        "nursery",
        "landscape",
        "contractor"
    ],
    "wof:name":"Saw Mill River Nurseries LLC",
    "wof:placetype":"venue"
},
  "geometry": {"coordinates":[-73.710593,41.228658],"type":"Point"}
}