{
  "type": "Feature",
  "properties": {
    "iso:country":"US",
    "sg:address":"137 Glenmore Rd",
    "sg:city":"Troy",
    "sg:classifiers":[
        {
            "category":"Professional",
            "type":"Services"
        }
    ],
    "sg:phone":"+1 518 283 4700",
    "sg:postcode":"12180",
    "sg:province":"NY",
    "sg:tags":[
        "establishment"
    ],
    "wof:name":"Nys Army National Guard",
    "wof:placetype":"venue"
},
  "geometry": {"coordinates":[-73.689105,42.691967],"type":"Point"}
}