{
  "type": "Feature",
  "properties": {
    "iso:country":"US",
    "sg:address":"602 Vine St",
    "sg:city":"Liverpool",
    "sg:classifiers":[
        {
            "category":"Professional",
            "subcategory":"Lawyer & Legal Services",
            "type":"Services"
        }
    ],
    "sg:phone":"+1 315 451 1010",
    "sg:postcode":"13088",
    "sg:province":"NY",
    "sg:tags":[
        "attorney"
    ],
    "wof:name":"Thomas Mc Carthy",
    "wof:placetype":"venue"
},
  "geometry": {"coordinates":[-76.204157,43.105124],"type":"Point"}
}