{
  "type": "Feature",
  "properties": {
    "iso:country":"US",
    "sg:address":"1575 Washington St",
    "sg:city":"Watertown",
    "sg:classifiers":[
        {
            "category":"Health Services",
            "subcategory":"Doctor",
            "type":"Services"
        }
    ],
    "sg:phone":"+1 315 786 7300",
    "sg:postcode":"13601",
    "sg:province":"NY",
    "sg:tags":[
        "physician",
        "surgeon"
    ],
    "wof:name":"Wetterhahn Joseph MD",
    "wof:placetype":"venue"
},
  "geometry": {"coordinates":[-75.91492,43.950082],"type":"Point"}
}