{
  "type": "Feature",
  "properties": {
    "iso:country":"US",
    "sg:address":"245 E Main St",
    "sg:city":"Smithtown",
    "sg:classifiers":[
        {
            "category":"Farming",
            "subcategory":"Farm",
            "type":"Manufacturing & Wholesale Goods"
        }
    ],
    "sg:phone":"+1 631 361 5045",
    "sg:postcode":"11787",
    "sg:province":"NY",
    "wof:name":"Franklin Arthur Farm",
    "wof:placetype":"venue"
},
  "geometry": {"coordinates":[-73.203805,40.856628],"type":"Point"}
}