{
  "type": "Feature",
  "properties": {
    "iso:country":"US",
    "sg:address":"92 Salem Rd",
    "sg:city":"Pound Ridge",
    "sg:classifiers":[
        {
            "category":"Building & Trades",
            "subcategory":"Plumbing",
            "type":"Services"
        }
    ],
    "sg:phone":"+1 914 764 0415",
    "sg:postcode":"10576",
    "sg:province":"NY",
    "sg:tags":[
        "contractor"
    ],
    "wof:name":"Philip Abbondola Jr",
    "wof:placetype":"venue"
},
  "geometry": {"coordinates":[-73.565748,41.222773],"type":"Point"}
}