{
  "type": "Feature",
  "properties": {
    "iso:country":"US",
    "sg:address":"159 Route 164",
    "sg:city":"Patterson",
    "sg:classifiers":[
        {
            "category":"Building & Trades",
            "subcategory":"Electrical",
            "type":"Services"
        }
    ],
    "sg:phone":"+1 845 878 7996",
    "sg:postcode":"12563",
    "sg:province":"NY",
    "sg:tags":[
        "electrician"
    ],
    "wof:name":"Industrial Power & Electric Motor Co",
    "wof:placetype":"venue"
},
  "geometry": {"coordinates":[-73.613129,41.480389],"type":"Point"}
}