{
  "type": "Feature",
  "properties": {
    "addr:full":"39 Mill St Hannibal NY 13074",
    "addr:housenumber":"39",
    "addr:postcode":"13074",
    "addr:street":"Mill St",
    "iso:country":"US",
    "sg:address":"39 Mill St",
    "sg:city":"Hannibal",
    "sg:classifiers":[
        {
            "category":"Wholesale",
            "subcategory":"Durable Goods & Equipment",
            "type":"Manufacturing & Wholesale Goods"
        }
    ],
    "sg:phone":"+1 315 564 5840",
    "sg:postcode":"13074",
    "sg:province":"NY",
    "wof:name":"L&M Supplies",
    "wof:placetype":"venue"
},
  "geometry": {"coordinates":[-76.579654,43.326893],"type":"Point"}
}