{
  "type": "Feature",
  "properties": {
    "addr:full":"1500 Blondell Avenue Bronx NY 10461",
    "addr:housenumber":"1500",
    "addr:postcode":"10461",
    "addr:street":"Blondell Avenue",
    "iso:country":"US",
    "sg:address":"1500 Blondell Avenue",
    "sg:city":"Bronx",
    "sg:classifiers":[
        {
            "category":"Health Services",
            "subcategory":"Doctor",
            "type":"Services"
        }
    ],
    "sg:phone":"+1 718 920 8437",
    "sg:postcode":"10461",
    "sg:province":"NY",
    "wof:name":"Olsewski John M MD",
    "wof:placetype":"venue"
},
  "geometry": {"coordinates":[-73.84504,40.845365],"type":"Point"}
}