{
  "type": "Feature",
  "properties": {
    "addr:full":"1825 Grand Central Ave Elmira NY 14903",
    "addr:housenumber":"1825",
    "addr:postcode":"14903",
    "addr:street":"Grand Central Ave",
    "iso:country":"US",
    "sg:address":"1825 Grand Central Ave",
    "sg:city":"Elmira",
    "sg:classifiers":[
        {
            "category":"Home & Garden",
            "subcategory":"Garden Supply",
            "type":"Retail Goods"
        }
    ],
    "sg:phone":"+1   ",
    "sg:postcode":"14903",
    "sg:province":"NY",
    "wof:name":"Parker Rs Landscape",
    "wof:placetype":"venue"
},
  "geometry": {"coordinates":[-76.82008999999999,42.135956],"type":"Point"}
}