{
  "type": "Feature",
  "properties": {
    "iso:country":"US",
    "sg:address":"260 W Main St",
    "sg:city":"Victor",
    "sg:classifiers":[
        {
            "category":"Restaurant",
            "type":"Food & Drink"
        }
    ],
    "sg:phone":"+1   ",
    "sg:postcode":"14564",
    "sg:province":"NY",
    "sg:tags":[
        "shop",
        "donut",
        "coffee"
    ],
    "sg:website":"www.timhorton.com",
    "wof:name":"Tim Hortons",
    "wof:placetype":"venue"
},
  "geometry": {"coordinates":[-77.418195,42.986713],"type":"Point"}
}