{
  "type": "Feature",
  "properties": {
    "addr:full":"17 Chelsea Dr Smithtown NY 11787",
    "addr:housenumber":"17",
    "addr:postcode":"11787",
    "addr:street":"Chelsea Dr",
    "iso:country":"US",
    "sg:address":"17 Chelsea Dr",
    "sg:city":"Smithtown",
    "sg:classifiers":[
        {
            "category":"Professional",
            "subcategory":"Computer Services",
            "type":"Services"
        }
    ],
    "sg:phone":"+1 631 265 2213",
    "sg:postcode":"11787",
    "sg:province":"NY",
    "sg:tags":[
        "software"
    ],
    "wof:name":"Symantec Corp",
    "wof:placetype":"venue"
},
  "geometry": {"coordinates":[-73.165351,40.851506],"type":"Point"}
}