{
  "type": "Feature",
  "properties": {
    "iso:country":"US",
    "sg:address":"331 Canterbury Rd",
    "sg:city":"Rochester",
    "sg:classifiers":[
        {
            "category":"Wholesale",
            "subcategory":"Electrical",
            "type":"Manufacturing & Wholesale Goods"
        }
    ],
    "sg:phone":"+1 716 693 7201",
    "sg:postcode":"14607",
    "sg:province":"NY",
    "sg:tags":[
        "control"
    ],
    "wof:name":"San Wal",
    "wof:placetype":"venue"
},
  "geometry": {"coordinates":[-77.577639,43.143626],"type":"Point"}
}