{
  "type": "Feature",
  "properties": {
    "addr:full":"303 W 42nd St New York NY 10036",
    "addr:housenumber":"303",
    "addr:postcode":"10036",
    "addr:street":"W 42Nd St",
    "iso:country":"US",
    "sg:address":"303 W 42nd St",
    "sg:city":"New York",
    "sg:classifiers":[
        {
            "category":"Manufacturing",
            "subcategory":"Signs",
            "type":"Manufacturing & Wholesale Goods"
        }
    ],
    "sg:phone":"+1   ",
    "sg:postcode":"10036",
    "sg:province":"NY",
    "sg:tags":[
        "specialty",
        "mfg"
    ],
    "wof:name":"Able Sign Co",
    "wof:placetype":"venue"
},
  "geometry": {"coordinates":[-73.992553,40.758471],"type":"Point"}
}