{
  "type": "Feature",
  "properties": {
    "addr:full":"342 Kingsborough 3rd Wlk Brooklyn NY 11233",
    "addr:housenumber":"342",
    "addr:postcode":"11233",
    "addr:street":"Kingsborough 3Rd Wlk",
    "iso:country":"US",
    "sg:address":"342 Kingsborough 3rd Wlk",
    "sg:city":"Brooklyn",
    "sg:classifiers":[
        {
            "category":"Health Services",
            "subcategory":"Hospital",
            "type":"Services"
        }
    ],
    "sg:phone":"+1 718 221 3000",
    "sg:postcode":"11233",
    "sg:province":"NY",
    "wof:name":"Saint Vincent Catholic Medical Centers",
    "wof:placetype":"venue"
},
  "geometry": {"coordinates":[-73.925301,40.675499],"type":"Point"}
}