{
  "type": "Feature",
  "properties": {
    "addr:full":"1519 Kings Hwy Brooklyn NY 11229",
    "addr:housenumber":"1519",
    "addr:postcode":"11229",
    "addr:street":"Kings Hwy",
    "iso:country":"US",
    "sg:address":"1519 Kings Hwy",
    "sg:city":"Brooklyn",
    "sg:classifiers":[
        {
            "category":"Restaurant",
            "type":"Food & Drink"
        }
    ],
    "sg:menulink":"http://www.allmenus.com/ny/brooklyn/63092-hayashi-ya/menu/",
    "sg:phone":"+1 718 998 8882",
    "sg:postcode":"11229",
    "sg:province":"NY",
    "sg:tags":[
        "sushi",
        "japanese",
        "asian"
    ],
    "wof:name":"Hayashi Ya",
    "wof:placetype":"venue"
},
  "geometry": {"coordinates":[-73.95819400000001,40.608745],"type":"Point"}
}