{
  "type": "Feature",
  "properties": {
    "iso:country":"US",
    "sg:address":"100 N Hamilton St",
    "sg:city":"Poughkeepsie",
    "sg:classifiers":[
        {
            "category":"Retail",
            "subcategory":"Auto Repair",
            "type":"Services"
        }
    ],
    "sg:phone":"+1 845 485 1900",
    "sg:postcode":"12601",
    "sg:province":"NY",
    "sg:tags":[
        "glass",
        "coating",
        "tinting"
    ],
    "wof:name":"Greater Metro Sun & Energy",
    "wof:placetype":"venue"
},
  "geometry": {"coordinates":[-73.921239,41.707532],"type":"Point"}
}