{
  "type": "Feature",
  "properties": {
    "addr:full":"2478 Arthur Ave Bronx NY 10458",
    "addr:housenumber":"2478",
    "addr:postcode":"10458",
    "addr:street":"Arthur Ave",
    "iso:country":"US",
    "sg:address":"2478 Arthur Ave",
    "sg:city":"Bronx",
    "sg:classifiers":[
        {
            "category":"Insurance",
            "subcategory":"Hazard Insurance",
            "type":"Services"
        }
    ],
    "sg:phone":"+1 718 561 0830",
    "sg:postcode":"10458",
    "sg:province":"NY",
    "sg:website":"www.bronxone.com/",
    "wof:name":"Bronx One Brokerage - Insurance",
    "wof:placetype":"venue"
},
  "geometry": {"coordinates":[-73.885684,40.85735],"type":"Point"}
}