{
  "type": "Feature",
  "properties": {
    "iso:country":"US",
    "sg:address":"1004 Route 45",
    "sg:city":"Pomona",
    "sg:classifiers":[
        {
            "category":"Building & Trades",
            "subcategory":"Landscaping Services",
            "type":"Services"
        }
    ],
    "sg:phone":"+1 845 639 6161",
    "sg:postcode":"10970",
    "sg:province":"NY",
    "sg:tags":[
        "landscape",
        "contractor"
    ],
    "sg:website":"http://www.cmeredithlandscape.com",
    "wof:name":"Christopher Meredith Landscaping",
    "wof:placetype":"venue"
},
  "geometry": {"coordinates":[-74.03256,41.176996],"type":"Point"}
}