{
  "type": "Feature",
  "properties": {
    "addr:full":"11211 159th St Jamaica NY 11433",
    "addr:housenumber":"11211",
    "addr:postcode":"11433",
    "addr:street":"159Th St",
    "iso:country":"US",
    "sg:address":"11211 159th St",
    "sg:city":"Jamaica",
    "sg:classifiers":[
        {
            "category":"Building & Trades",
            "subcategory":"Construction",
            "type":"Services"
        }
    ],
    "sg:phone":"+1 718 323 5137",
    "sg:postcode":"11433",
    "sg:province":"NY",
    "sg:tags":[
        "contractor"
    ],
    "wof:name":"De Ram Builders Incorporated",
    "wof:placetype":"venue"
},
  "geometry": {"coordinates":[-73.78949900000001,40.689438],"type":"Point"}
}