{
  "type": "Feature",
  "properties": {
    "addr:full":"60 Main St Mineola NY 11501",
    "addr:housenumber":"60",
    "addr:postcode":"11501",
    "addr:street":"Main St",
    "iso:country":"US",
    "sg:address":"60 Main St",
    "sg:city":"Mineola",
    "sg:classifiers":[
        {
            "category":"Professional",
            "subcategory":"Computer Services",
            "type":"Services"
        },
        {
            "category":"Communications",
            "type":"Services"
        },
        {
            "category":"Communications",
            "subcategory":"Television Station",
            "type":"Services"
        }
    ],
    "sg:phone":"+1 866 310 4761",
    "sg:postcode":"11501",
    "sg:province":"NY",
    "sg:tags":[
        "satellite",
        "cable",
        "tv",
        "isp",
        "system",
        "equipment",
        "internet",
        "provider"
    ],
    "sg:website":"http://www.directsattv.com/directv/?tfid=ypm",
    "wof:name":"Direct Sat TV - An Authorized DIRECTV Dealer",
    "wof:placetype":"venue"
},
  "geometry": {"coordinates":[-73.63811200000001,40.740313],"type":"Point"}
}