{
  "type": "Feature",
  "properties": {
    "addr:full":"87 Grove Ave Staten Island NY 10302",
    "addr:housenumber":"87",
    "addr:postcode":"10302",
    "addr:street":"Grove Ave",
    "iso:country":"US",
    "sg:address":"87 Grove Ave",
    "sg:city":"Staten Island",
    "sg:classifiers":[
        {
            "category":"Food & Beverages",
            "subcategory":"Meat & Fish",
            "type":"Retail Goods"
        }
    ],
    "sg:phone":"+1 718 720 8008",
    "sg:postcode":"10302",
    "sg:province":"NY",
    "sg:tags":[
        "seafood",
        "market"
    ],
    "wof:name":"Coast To Coast Seafood Brokers",
    "wof:placetype":"venue"
},
  "geometry": {"coordinates":[-74.135902,40.638302],"type":"Point"}
}