{
  "type": "Feature",
  "properties": {
    "addr:full":"4405 13th Ave Brooklyn NY 11219",
    "addr:housenumber":"4405",
    "addr:postcode":"11219",
    "addr:street":"13Th Ave",
    "iso:country":"US",
    "sg:address":"4405 13th Ave",
    "sg:city":"Brooklyn",
    "sg:classifiers":[
        {
            "category":"Professional",
            "subcategory":"Employment Agencies",
            "type":"Services"
        }
    ],
    "sg:phone":"+1 718 854 5841",
    "sg:postcode":"11219",
    "sg:province":"NY",
    "sg:tags":[
        "employee",
        "leasing"
    ],
    "wof:name":"Goethals Bridge",
    "wof:placetype":"venue"
},
  "geometry": {"coordinates":[-73.989712,40.637239],"type":"Point"}
}