{
  "type": "Feature",
  "properties": {
    "addr:full":"1809 Lakeville Rd New Hyde Park NY 11040",
    "addr:housenumber":"1809",
    "addr:postcode":"11040",
    "addr:street":"Lakeville Rd",
    "iso:country":"US",
    "sg:address":"1809 Lakeville Rd",
    "sg:city":"New Hyde Park",
    "sg:classifiers":[
        {
            "category":"Restaurant",
            "type":"Food & Drink"
        }
    ],
    "sg:phone":"+1 516 354 4666",
    "sg:postcode":"11040",
    "sg:province":"NY",
    "sg:tags":[
        "diner"
    ],
    "sg:website":"omegainn.kpsearch.com/df/default...",
    "wof:name":"Omega Diner",
    "wof:placetype":"venue"
},
  "geometry": {"coordinates":[-73.694588,40.744199],"type":"Point"}
}