{
  "type": "Feature",
  "properties": {
    "addr:full":"2431 Long Beach Rd Oceanside NY 11572",
    "addr:housenumber":"2431",
    "addr:postcode":"11572",
    "addr:street":"Long Beach Rd",
    "iso:country":"US",
    "sg:address":"2431 Long Beach Rd",
    "sg:city":"Oceanside",
    "sg:classifiers":[
        {
            "category":"Retail",
            "subcategory":"Auto Repair",
            "type":"Services"
        }
    ],
    "sg:phone":"+1 516 536 3696",
    "sg:postcode":"11572",
    "sg:province":"NY",
    "sg:tags":[
        "transmission"
    ],
    "wof:name":"Ralph's Transmissions",
    "wof:placetype":"venue"
},
  "geometry": {"coordinates":[-73.63827499999999,40.646489],"type":"Point"}
}