{
  "type": "Feature",
  "properties": {
    "addr:full":"2330 Eastchester Rd Bronx NY 10469",
    "addr:housenumber":"2330",
    "addr:postcode":"10469",
    "addr:street":"Eastchester Rd",
    "iso:country":"US",
    "sg:address":"2330 Eastchester Rd",
    "sg:city":"Bronx",
    "sg:classifiers":[
        {
            "category":"Health Services",
            "subcategory":"Doctor",
            "type":"Services"
        }
    ],
    "sg:phone":"+1 718 732 4000",
    "sg:postcode":"10469",
    "sg:province":"NY",
    "sg:website":"www.eastchestercenter.com",
    "wof:name":"Volterra Fabio MD",
    "wof:placetype":"venue"
},
  "geometry": {"coordinates":[-73.842871,40.859955],"type":"Point"}
}