{
  "type": "Feature",
  "properties": {
    "addr:full":"141 Co Rte 7 Nassau NY 12123",
    "addr:housenumber":"141",
    "addr:postcode":"12123",
    "addr:street":"Co Rte 7",
    "iso:country":"US",
    "sg:address":"141 Co Rte 7",
    "sg:city":"Nassau",
    "sg:classifiers":[
        {
            "category":"Building & Trades",
            "subcategory":"Construction",
            "type":"Services"
        }
    ],
    "sg:phone":"+1 518 495 7072",
    "sg:postcode":"12123",
    "sg:province":"NY",
    "sg:tags":[
        "roofing",
        "contractor"
    ],
    "wof:name":"Brothers Roofing & Siding",
    "wof:placetype":"venue"
},
  "geometry": {"coordinates":[-73.607654,42.53189],"type":"Point"}
}