{
  "type": "Feature",
  "properties": {
    "addr:full":"346 Devoe Ave New York NY 10001",
    "addr:housenumber":"346",
    "addr:postcode":"10001",
    "addr:street":"Devoe Ave",
    "iso:country":"US",
    "sg:address":"346 Devoe Ave",
    "sg:city":"New York",
    "sg:classifiers":[
        {
            "category":"Fast Food",
            "type":"Food & Drink"
        },
        {
            "category":"Food & Beverages",
            "subcategory":"Meat & Fish",
            "type":"Retail Goods"
        }
    ],
    "sg:phone":"+1 347 810 6979",
    "sg:postcode":"10001",
    "sg:province":"NY",
    "sg:tags":[
        "burger",
        "hot",
        "dog"
    ],
    "wof:name":"Jimbos Hamburger Palace",
    "wof:placetype":"venue"
},
  "geometry": {"coordinates":[-73.877976,40.839078],"type":"Point"}
}