{
  "type": "Feature",
  "properties": {
    "addr:full":"1545 2nd Avenue New York NY 10028",
    "addr:housenumber":"1545",
    "addr:postcode":"10028",
    "addr:street":"2Nd Avenue",
    "iso:country":"US",
    "sg:address":"1545 2nd Avenue",
    "sg:city":"New York",
    "sg:classifiers":[
        {
            "category":"Food & Beverages",
            "subcategory":"Liquor & Beverages",
            "type":"Retail Goods"
        }
    ],
    "sg:phone":"+1 212 517 9463",
    "sg:postcode":"10028",
    "sg:province":"NY",
    "sg:tags":[
        "beer",
        "spirit",
        "wine"
    ],
    "sg:website":"www.wine-emporium.com",
    "wof:name":"Wine Emporium",
    "wof:placetype":"venue"
},
  "geometry": {"coordinates":[-73.95452400000001,40.774264],"type":"Point"}
}