{
  "type": "Feature",
  "properties": {
    "addr:full":"963 Route 146 Clifton Park NY 12065",
    "addr:housenumber":"963",
    "addr:postcode":"12065",
    "addr:street":"Route 146;Park",
    "iso:country":"US",
    "sg:address":"963 Route 146",
    "sg:city":"Clifton Park",
    "sg:classifiers":[
        {
            "category":"Health Services",
            "subcategory":"Doctor",
            "type":"Services"
        }
    ],
    "sg:phone":"+1 518 383 0001",
    "sg:postcode":"12065",
    "sg:province":"NY",
    "wof:name":"Katlan Michael G MD",
    "wof:placetype":"venue"
},
  "geometry": {"coordinates":[-73.80740400000001,42.868599],"type":"Point"}
}