{
  "type": "Feature",
  "properties": {
    "addr:full":"1403 44th St Brooklyn NY 11219",
    "addr:housenumber":"1403",
    "addr:postcode":"11219",
    "addr:street":"44Th St",
    "iso:country":"US",
    "sg:address":"1403 44th St",
    "sg:city":"Brooklyn",
    "sg:classifiers":[
        {
            "category":"Insurance",
            "subcategory":"Insurance Agent",
            "type":"Services"
        }
    ],
    "sg:phone":"+1 718 236 7044",
    "sg:postcode":"11219",
    "sg:province":"NY",
    "wof:name":"Select Land Service LLC",
    "wof:placetype":"venue"
},
  "geometry": {"coordinates":[-73.984784,40.635251],"type":"Point"}
}