{
  "type": "Feature",
  "properties": {
    "addr:full":"5701 Flatlands Ave Brooklyn NY 11234",
    "addr:housenumber":"5701",
    "addr:postcode":"11234",
    "addr:street":"Flatlands Ave",
    "iso:country":"US",
    "sg:address":"5701 Flatlands Ave",
    "sg:city":"Brooklyn",
    "sg:classifiers":[
        {
            "category":"Shopping",
            "subcategory":"Computers & Home Electronics",
            "type":"Retail Goods"
        }
    ],
    "sg:phone":"+1   ",
    "sg:postcode":"11234",
    "sg:province":"NY",
    "wof:name":"Mark Auto Sounds Inc",
    "wof:placetype":"venue"
},
  "geometry": {"coordinates":[-73.920418,40.630904],"type":"Point"}
}