{
  "type": "Feature",
  "properties": {
    "addr:full":"211 Ross St Brooklyn NY 11211",
    "addr:housenumber":"211",
    "addr:postcode":"11211",
    "addr:street":"Ross St",
    "iso:country":"US",
    "sg:address":"211 Ross St",
    "sg:city":"Brooklyn",
    "sg:classifiers":[
        {
            "category":"Professional",
            "subcategory":"Art Services",
            "type":"Services"
        },
        {
            "category":"Manufacturing",
            "subcategory":"Printing",
            "type":"Manufacturing & Wholesale Goods"
        }
    ],
    "sg:phone":"+1 718 218 6700",
    "sg:postcode":"11211",
    "sg:province":"NY",
    "sg:tags":[
        "graphic",
        "printer",
        "designer"
    ],
    "wof:name":"Royal Images Inc",
    "wof:placetype":"venue"
},
  "geometry": {"coordinates":[-73.95930300000001,40.706362],"type":"Point"}
}