{
  "type": "Feature",
  "properties": {
    "addr:full":"1504 Old Country Rd Westbury NY 11590",
    "addr:housenumber":"1504",
    "addr:postcode":"11590",
    "addr:street":"Old Country Rd",
    "iso:country":"US",
    "sg:address":"1504 Old Country Rd",
    "sg:city":"Westbury",
    "sg:classifiers":[
        {
            "category":"Sports & Exercise",
            "subcategory":"Bicycle Rental",
            "type":"Entertainment"
        }
    ],
    "sg:phone":"+1 516 794 2883",
    "sg:postcode":"11590",
    "sg:province":"NY",
    "sg:tags":[
        "wear"
    ],
    "wof:name":"Pacific Sunware of California Inc",
    "wof:placetype":"venue"
},
  "geometry": {"coordinates":[-73.55740400000001,40.7551],"type":"Point"}
}