{
  "type": "Feature",
  "properties": {
    "addr:full":"2318 Grand Concourse Bronx NY 10458",
    "addr:housenumber":"2318",
    "addr:postcode":"10458",
    "addr:street":"Grand Concourse",
    "iso:country":"US",
    "sg:address":"2318 Grand Concourse",
    "sg:city":"Bronx",
    "sg:classifiers":[
        {
            "category":"Retail",
            "subcategory":"Portrait Studio",
            "type":"Services"
        },
        {
            "category":"Professional",
            "subcategory":"Art Services",
            "type":"Services"
        }
    ],
    "sg:phone":"+1 718 364 4123",
    "sg:postcode":"10458",
    "sg:province":"NY",
    "sg:tags":[
        "photographer",
        "photography",
        "store"
    ],
    "wof:name":"Margie's Bridal Dot Com",
    "wof:placetype":"venue"
},
  "geometry": {"coordinates":[-73.89941899999999,40.857703],"type":"Point"}
}