{
  "type": "Feature",
  "properties": {
    "addr:full":"575 Broadway New York NY 10012",
    "addr:housenumber":"575",
    "addr:postcode":"10012",
    "addr:street":"Broadway",
    "iso:country":"US",
    "sg:address":"575 Broadway",
    "sg:city":"New York",
    "sg:classifiers":[
        {
            "category":"Communications",
            "subcategory":"Newspaper",
            "type":"Services"
        }
    ],
    "sg:phone":"+1 212 941 2900",
    "sg:postcode":"10012",
    "sg:province":"NY",
    "sg:tags":[
        "print",
        "medium"
    ],
    "sg:website":"www.interviewmagazine.com",
    "wof:name":"Interview Magazine",
    "wof:placetype":"venue"
},
  "geometry": {"coordinates":[-73.997704,40.7244],"type":"Point"}
}