{
  "type": "Feature",
  "properties": {
    "iso:country":"US",
    "sg:address":"1228 Brooklyn Ave",
    "sg:city":"Brooklyn",
    "sg:classifiers":[
        {
            "category":"Travel",
            "subcategory":"Travel Agent",
            "type":"Entertainment"
        }
    ],
    "sg:phone":"+1 718 282 6202",
    "sg:postcode":"11203",
    "sg:province":"NY",
    "sg:tags":[
        "agency",
        "bureau"
    ],
    "wof:name":"Around The World Travel Corp",
    "wof:placetype":"venue"
},
  "geometry": {"coordinates":[-73.942857,40.64168],"type":"Point"}
}