{
  "type": "Feature",
  "properties": {
    "iso:country":"US",
    "sg:address":"250 E Houston St",
    "sg:city":"New York",
    "sg:classifiers":[
        {
            "category":"Real Estate",
            "subcategory":"Real Estate Agent",
            "type":"Services"
        }
    ],
    "sg:phone":"+1 212 529 9595",
    "sg:postcode":"10002",
    "sg:province":"NY",
    "sg:tags":[
        "apartment"
    ],
    "wof:name":"Red Sq",
    "wof:placetype":"venue"
},
  "geometry": {"coordinates":[-73.985435,40.72219],"type":"Point"}
}