{
  "type": "Feature",
  "properties": {
    "iso:country":"US",
    "sg:address":"1711 Wayneport Rd",
    "sg:city":"Macedon",
    "sg:classifiers":[
        {
            "category":"Building & Trades",
            "subcategory":"Construction",
            "type":"Services"
        }
    ],
    "sg:phone":"+1 585 223 6421",
    "sg:postcode":"14502",
    "sg:province":"NY",
    "sg:tags":[
        "excavating",
        "contractor"
    ],
    "wof:name":"Macedon Exc & Paving Inc",
    "wof:placetype":"venue"
},
  "geometry": {"coordinates":[-77.361203,43.069747],"type":"Point"}
}