{
  "type": "Feature",
  "properties": {
    "iso:country":"US",
    "sg:address":"160 Marine St",
    "sg:city":"Farmingdale",
    "sg:classifiers":[
        {
            "category":"Wholesale",
            "subcategory":"Non-durable Goods",
            "type":"Manufacturing & Wholesale Goods"
        }
    ],
    "sg:phone":"+1 631 249 3474",
    "sg:postcode":"11735",
    "sg:province":"NY",
    "sg:tags":[
        "tropical",
        "fish"
    ],
    "wof:name":"Long Island Aquatics Inc",
    "wof:placetype":"venue"
},
  "geometry": {"coordinates":[-73.41538300000001,40.714897],"type":"Point"}
}