{
  "type": "Feature",
  "properties": {
    "addr:full":"940 4th Ave Brooklyn NY 11232",
    "addr:housenumber":"940",
    "addr:postcode":"11232",
    "addr:street":"4Th Ave",
    "iso:country":"US",
    "sg:address":"940 4th Ave",
    "sg:city":"Brooklyn",
    "sg:classifiers":[
        {
            "category":"Food & Beverages",
            "subcategory":"Candy",
            "type":"Retail Goods"
        }
    ],
    "sg:phone":"+1 718 768 6845",
    "sg:postcode":"11232",
    "sg:province":"NY",
    "sg:tags":[
        "confectionery",
        "store"
    ],
    "wof:name":"J E M Smoke Shoppe",
    "wof:placetype":"venue"
},
  "geometry": {"coordinates":[-74.004204,40.6548],"type":"Point"}
}