{
  "type": "Feature",
  "properties": {
    "iso:country":"US",
    "sg:address":"214 Bouchard Dr",
    "sg:city":"Plattsburgh",
    "sg:classifiers":[
        {
            "category":"Restaurant",
            "type":"Food & Drink"
        }
    ],
    "sg:phone":"+1 518 563 1321",
    "sg:postcode":"12901",
    "sg:province":"NY",
    "wof:name":"Marina Champlain",
    "wof:placetype":"venue"
},
  "geometry": {"coordinates":[-73.419785,44.75072],"type":"Point"}
}