{
  "type": "Feature",
  "properties": {
    "iso:country":"US",
    "sg:address":"44 Ave B",
    "sg:city":"New York",
    "sg:classifiers":[
        {
            "category":"Retail",
            "subcategory":"Laundry & Dry Cleaning",
            "type":"Services"
        }
    ],
    "sg:phone":"+1 212 477 6223",
    "sg:postcode":"10009",
    "sg:province":"NY",
    "wof:name":"Reliable Laundry & Cleaners",
    "wof:placetype":"venue"
},
  "geometry": {"coordinates":[-73.982889,40.722985],"type":"Point"}
}