{
  "type": "Feature",
  "properties": {
    "addr:full":"200 Reid St Lindenhurst NY 11757",
    "addr:housenumber":"200",
    "addr:postcode":"11757",
    "addr:street":"Reid St",
    "iso:country":"US",
    "sg:address":"200 Reid St",
    "sg:city":"Lindenhurst",
    "sg:classifiers":[
        {
            "category":"Wholesale",
            "subcategory":"Auto Parts",
            "type":"Manufacturing & Wholesale Goods"
        }
    ],
    "sg:phone":"+1 631 589 2384",
    "sg:postcode":"11757",
    "sg:province":"NY",
    "sg:tags":[
        "equipment",
        "truck"
    ],
    "wof:name":"Suffolk Auto Recycling Inc",
    "wof:placetype":"venue"
},
  "geometry": {"coordinates":[-73.35500500000001,40.695752],"type":"Point"}
}