{
  "type": "Feature",
  "properties": {
    "iso:country":"US",
    "sg:address":"287 Lattingtown Rd",
    "sg:city":"Locust Valley",
    "sg:classifiers":[
        {
            "category":"Shopping",
            "subcategory":"Discount & Variety Stores",
            "type":"Retail Goods"
        }
    ],
    "sg:phone":"+1   ",
    "sg:postcode":"11560",
    "sg:province":"NY",
    "wof:name":"Chiqui-Nena Woolworth",
    "wof:placetype":"venue"
},
  "geometry": {"coordinates":[-73.60548900000001,40.888535],"type":"Point"}
}