{
  "type": "Feature",
  "properties": {
    "addr:full":"276 Miles Ave Staten Island NY 10308",
    "addr:housenumber":"276",
    "addr:postcode":"10308",
    "addr:street":"Miles Ave",
    "iso:country":"US",
    "sg:address":"276 Miles Ave",
    "sg:city":"Staten Island",
    "sg:classifiers":[
        {
            "category":"Building & Trades",
            "subcategory":"Construction",
            "type":"Services"
        }
    ],
    "sg:phone":"+1 718 356 7397",
    "sg:postcode":"10308",
    "sg:province":"NY",
    "sg:tags":[
        "house"
    ],
    "wof:name":"J & J Tile Renovations Inc",
    "wof:placetype":"venue"
},
  "geometry": {"coordinates":[-74.15125500000001,40.558902],"type":"Point"}
}