{
  "type": "Feature",
  "properties": {
    "addr:full":"223 Gordon St Staten Island NY 10304",
    "addr:housenumber":"223",
    "addr:postcode":"10304",
    "addr:street":"Gordon St",
    "iso:country":"US",
    "sg:address":"223 Gordon St",
    "sg:city":"Staten Island",
    "sg:classifiers":[
        {
            "category":"Professional",
            "type":"Services"
        }
    ],
    "sg:phone":"+1 718 420 1012",
    "sg:postcode":"10304",
    "sg:province":"NY",
    "sg:tags":[
        "establishment"
    ],
    "wof:name":"DES & Daddy O",
    "wof:placetype":"venue"
},
  "geometry": {"coordinates":[-74.083387,40.620363],"type":"Point"}
}