{
  "type": "Feature",
  "properties": {
    "addr:full":"41-40 Main St Flushing NY 11355",
    "addr:housenumber":"41-40",
    "addr:postcode":"11355",
    "addr:street":"Main St",
    "iso:country":"US",
    "sg:address":"41-40 Main St",
    "sg:city":"Flushing",
    "sg:classifiers":[
        {
            "category":"Restaurant",
            "type":"Food & Drink"
        }
    ],
    "sg:postcode":"11355",
    "sg:province":"NY",
    "sg:tags":[
        "chinese"
    ],
    "wof:name":"Oriental Express Food Lucky L & LWC",
    "wof:placetype":"venue"
},
  "geometry": {"coordinates":[-73.82895499999999,40.757072],"type":"Point"}
}