{
  "type": "Feature",
  "properties": {
    "addr:full":"425 E 58th St New York NY 10022",
    "addr:housenumber":"425",
    "addr:postcode":"10022",
    "addr:street":"E 58Th St",
    "iso:country":"US",
    "sg:address":"425 E 58th St",
    "sg:city":"New York",
    "sg:classifiers":[
        {
            "category":"Autos & Motor Vehicles",
            "subcategory":"Fuel & Gas Station",
            "type":"Retail Goods"
        }
    ],
    "sg:phone":"+1 212 754 8080",
    "sg:postcode":"10022",
    "sg:province":"NY",
    "wof:name":"ampm",
    "wof:placetype":"venue"
},
  "geometry": {"coordinates":[-73.96180699999999,40.758881],"type":"Point"}
}