{
  "type": "Feature",
  "properties": {
    "addr:full":"662 Lake St Wilson NY 14172",
    "addr:housenumber":"662",
    "addr:postcode":"14172",
    "addr:street":"Lake St",
    "iso:country":"US",
    "sg:address":"662 Lake St",
    "sg:city":"Wilson",
    "sg:classifiers":[
        {
            "category":"Shopping",
            "subcategory":"Computers & Home Electronics",
            "type":"Retail Goods"
        }
    ],
    "sg:phone":"+1   ",
    "sg:postcode":"14172",
    "sg:province":"NY",
    "wof:name":"Garden Computer Services",
    "wof:placetype":"venue"
},
  "geometry": {"coordinates":[-78.82592200000001,43.298661],"type":"Point"}
}