{
  "type": "Feature",
  "properties": {
    "addr:full":"14 Ramona Park Rochester NY 14615",
    "addr:housenumber":"14",
    "addr:postcode":"14615",
    "addr:street":"Ramona Park",
    "iso:country":"US",
    "sg:address":"14 Ramona Park",
    "sg:city":"Rochester",
    "sg:classifiers":[
        {
            "category":"Real Estate",
            "subcategory":"Real Estate Operator",
            "type":"Services"
        }
    ],
    "sg:phone":"+1 585 254 0463",
    "sg:postcode":"14615",
    "sg:province":"NY",
    "sg:tags":[
        "apartment"
    ],
    "wof:name":"Rochester Management",
    "wof:placetype":"venue"
},
  "geometry": {"coordinates":[-77.65020800000001,43.197441],"type":"Point"}
}