{
  "type": "Feature",
  "properties": {
    "addr:full":"70 Broadway Hicksville NY 11801",
    "addr:housenumber":"70",
    "addr:postcode":"11801",
    "addr:street":"Broadway",
    "iso:country":"US",
    "sg:address":"70 Broadway",
    "sg:city":"Hicksville",
    "sg:classifiers":[
        {
            "category":"Museum",
            "type":"Entertainment"
        }
    ],
    "sg:phone":"+1 516 931 1500",
    "sg:postcode":"11801",
    "sg:province":"NY",
    "sg:tags":[
        "theatrical",
        "gallery"
    ],
    "wof:name":"Long Island Reptile Museum",
    "wof:placetype":"venue"
},
  "geometry": {"coordinates":[-73.524101,40.767399],"type":"Point"}
}