{
  "type": "Feature",
  "properties": {
    "addr:full":"25 Roslyn Rd Mineola NY 11501",
    "addr:housenumber":"25",
    "addr:postcode":"11501",
    "addr:street":"Roslyn Rd",
    "iso:country":"US",
    "sg:address":"25 Roslyn Rd",
    "sg:city":"Mineola",
    "sg:classifiers":[
        {
            "category":"Organizations",
            "subcategory":"Labor Organization",
            "type":"Services"
        }
    ],
    "sg:phone":"+1 516 742 3500",
    "sg:postcode":"11501",
    "sg:province":"NY",
    "sg:tags":[
        "service/non-profit",
        "community"
    ],
    "wof:name":"Joint Board 18",
    "wof:placetype":"venue"
},
  "geometry": {"coordinates":[-73.634102,40.740898],"type":"Point"}
}