{
  "type": "Feature",
  "properties": {
    "addr:full":"877 Fairmount Pl Bronx NY 10460",
    "addr:housenumber":"877",
    "addr:postcode":"10460",
    "addr:street":"Fairmount Pl",
    "iso:country":"US",
    "sg:address":"877 Fairmount Pl",
    "sg:city":"Bronx",
    "sg:classifiers":[
        {
            "category":"Professional",
            "type":"Services"
        }
    ],
    "sg:phone":"+1 718 893 2291",
    "sg:postcode":"10460",
    "sg:province":"NY",
    "sg:tags":[
        "establishment"
    ],
    "wof:name":"New York Restoration",
    "wof:placetype":"venue"
},
  "geometry": {"coordinates":[-73.88669899999999,40.841755],"type":"Point"}
}