{
  "type": "Feature",
  "properties": {
    "addr:full":"5 Coventry Pl Garden City NY 11530",
    "addr:housenumber":"5",
    "addr:postcode":"11530",
    "addr:street":"Coventry Pl",
    "iso:country":"US",
    "sg:address":"5 Coventry Pl",
    "sg:city":"Garden City",
    "sg:classifiers":[
        {
            "category":"Health Services",
            "subcategory":"Doctor",
            "type":"Services"
        }
    ],
    "sg:phone":"+1 516 747 0079",
    "sg:postcode":"11530",
    "sg:province":"NY",
    "sg:tags":[
        "medical"
    ],
    "wof:name":"Pugliese Susan",
    "wof:placetype":"venue"
},
  "geometry": {"coordinates":[-73.62449100000001,40.727328],"type":"Point"}
}