{
  "type": "Feature",
  "properties": {
    "addr:full":"11210 Clinton St Elma NY 14059",
    "addr:housenumber":"11210",
    "addr:postcode":"14059",
    "addr:street":"Clinton St",
    "iso:country":"US",
    "sg:address":"11210 Clinton St",
    "sg:city":"Elma",
    "sg:classifiers":[
        {
            "category":"Farming",
            "subcategory":"Farm",
            "type":"Manufacturing & Wholesale Goods"
        }
    ],
    "sg:phone":"+1 716 681 3707",
    "sg:postcode":"14059",
    "sg:province":"NY",
    "sg:tags":[
        "crop",
        "general"
    ],
    "wof:name":"Berner Farms",
    "wof:placetype":"venue"
},
  "geometry": {"coordinates":[-78.565524,42.856512],"type":"Point"}
}