{
  "type": "Feature",
  "properties": {
    "iso:country":"US",
    "sg:address":"735 11th Ave",
    "sg:city":"New York",
    "sg:classifiers":[
        {
            "category":"Food & Beverages",
            "subcategory":"Bakery",
            "type":"Retail Goods"
        }
    ],
    "sg:phone":"+1 212 582 5800",
    "sg:postcode":"10019",
    "sg:province":"NY",
    "sg:tags":[
        "sandwich"
    ],
    "wof:name":"Subway",
    "wof:placetype":"venue"
},
  "geometry": {"coordinates":[-73.994108,40.767164],"type":"Point"}
}