{
  "type": "Feature",
  "properties": {
    "addr:full":"139 Casimer Rd Middletown NY 10941",
    "addr:housenumber":"139",
    "addr:postcode":"10941",
    "addr:street":"Casimer Rd",
    "iso:country":"US",
    "sg:address":"139 Casimer Rd",
    "sg:city":"Middletown",
    "sg:classifiers":[
        {
            "category":"Professional",
            "subcategory":"Employment Agencies",
            "type":"Services"
        }
    ],
    "sg:phone":"+1 845 695 2220",
    "sg:postcode":"10941",
    "sg:province":"NY",
    "sg:tags":[
        "opportunity"
    ],
    "wof:name":"Dental Medical Power Per Agcy",
    "wof:placetype":"venue"
},
  "geometry": {"coordinates":[-74.30558000000001,41.469456],"type":"Point"}
}