{
  "type": "Feature",
  "properties": {
    "addr:full":"118 Haven Ave Mount Vernon NY 10553",
    "addr:housenumber":"118",
    "addr:postcode":"10553",
    "addr:street":"Haven Ave",
    "iso:country":"US",
    "sg:address":"118 Haven Ave",
    "sg:city":"Mount Vernon",
    "sg:classifiers":[
        {
            "category":"Restaurant",
            "type":"Food & Drink"
        }
    ],
    "sg:phone":"+1   ",
    "sg:postcode":"10553",
    "sg:province":"NY",
    "sg:tags":[
        "mobile"
    ],
    "wof:name":"Lurs Caribbean Style Bbq LLC",
    "wof:placetype":"venue"
},
  "geometry": {"coordinates":[-73.82227399999999,40.910505],"type":"Point"}
}