{
  "type": "Feature",
  "properties": {
    "addr:full":"96 E Bridge St Oswego NY 13126",
    "addr:housenumber":"96",
    "addr:postcode":"13126",
    "addr:street":"E Bridge St",
    "iso:country":"US",
    "sg:address":"96 E Bridge St",
    "sg:city":"Oswego",
    "sg:classifiers":[
        {
            "category":"Social Services",
            "type":"Services"
        }
    ],
    "sg:phone":"+1 315 343 8246",
    "sg:postcode":"13126",
    "sg:province":"NY",
    "sg:tags":[
        "worker"
    ],
    "wof:name":"Patricia A Muroski-Samul",
    "wof:placetype":"venue"
},
  "geometry": {"coordinates":[-76.504558,43.458521],"type":"Point"}
}