{
  "type": "Feature",
  "properties": {
    "addr:full":"76 Virginia Ave Long Beach NY 11561",
    "addr:housenumber":"76",
    "addr:postcode":"11561",
    "addr:street":"Virginia Ave",
    "iso:country":"US",
    "sg:address":"76 Virginia Ave",
    "sg:city":"Long Beach",
    "sg:classifiers":[
        {
            "category":"Shopping",
            "subcategory":"Computers & Home Electronics",
            "type":"Retail Goods"
        }
    ],
    "sg:phone":"+1 516 897 9427",
    "sg:postcode":"11561",
    "sg:province":"NY",
    "sg:tags":[
        "system"
    ],
    "wof:name":"Audio Video Concepts Inc",
    "wof:placetype":"venue"
},
  "geometry": {"coordinates":[-73.69247900000001,40.587471],"type":"Point"}
}