{
  "type": "Feature",
  "properties": {
    "iso:country":"US",
    "sg:address":"720 Willow Ave",
    "sg:city":"Ithaca",
    "sg:classifiers":[
        {
            "category":"Home & Garden",
            "subcategory":"Building Materials",
            "type":"Retail Goods"
        }
    ],
    "sg:phone":"+1 607 273 0333",
    "sg:postcode":"14850",
    "sg:province":"NY",
    "wof:name":"Kelmar Construction Sales",
    "wof:placetype":"venue"
},
  "geometry": {"coordinates":[-76.50635200000001,42.453442],"type":"Point"}
}