{
  "type": "Feature",
  "properties": {
    "iso:country":"US",
    "sg:address":"25 Smith Haven Mall",
    "sg:city":"Lake Grove",
    "sg:classifiers":[
        {
            "category":"Retail",
            "subcategory":"Portrait Studio",
            "type":"Services"
        }
    ],
    "sg:phone":"+1 631 361 6650",
    "sg:postcode":"11755",
    "sg:province":"NY",
    "sg:tags":[
        "photographer"
    ],
    "sg:website":"www.picturepeople.com",
    "wof:name":"Picture People",
    "wof:placetype":"venue"
},
  "geometry": {"coordinates":[-73.12806399999999,40.863358],"type":"Point"}
}