{
  "type": "Feature",
  "properties": {
    "addr:full":"3096 Carman Rd Schenectady NY 12303",
    "addr:housenumber":"3096",
    "addr:postcode":"12303",
    "addr:street":"Carman Rd",
    "iso:country":"US",
    "sg:address":"3096 Carman Rd",
    "sg:city":"Schenectady",
    "sg:classifiers":[
        {
            "category":"Retail",
            "subcategory":"Repair Shop",
            "type":"Services"
        }
    ],
    "sg:phone":"+1   ",
    "sg:postcode":"12303",
    "sg:province":"NY",
    "sg:tags":[
        "equipment",
        "lawn",
        "gasoline",
        "garden",
        "motor"
    ],
    "wof:name":"Thruway Engine Clinic",
    "wof:placetype":"venue"
},
  "geometry": {"coordinates":[-73.94032900000001,42.763273],"type":"Point"}
}