{
  "type": "Feature",
  "properties": {
    "iso:country":"US",
    "sg:address":"74 Main St",
    "sg:city":"Brockport",
    "sg:classifiers":[
        {
            "category":"Restaurant",
            "type":"Food & Drink"
        }
    ],
    "sg:phone":"+1 585 637 3981",
    "sg:postcode":"14420",
    "sg:province":"NY",
    "wof:name":"Munchy's",
    "wof:placetype":"venue"
},
  "geometry": {"coordinates":[-77.938852,43.214691],"type":"Point"}
}