{
  "type": "Feature",
  "properties": {
    "addr:full":"120 E 37th Street Ofc New York NY 10016",
    "addr:housenumber":"120",
    "addr:postcode":"10016",
    "addr:street":"E 37Th Street",
    "iso:country":"US",
    "sg:address":"120 E 37th Street Ofc",
    "sg:city":"New York",
    "sg:classifiers":[
        {
            "category":"Professional",
            "subcategory":"Lawyer & Legal Services",
            "type":"Services"
        }
    ],
    "sg:phone":"+1 212 685 3650",
    "sg:postcode":"10016",
    "sg:province":"NY",
    "sg:website":"www.serafinnlaw.com",
    "wof:name":"Serafinn Patricia A M Atty",
    "wof:placetype":"venue"
},
  "geometry": {"coordinates":[-73.978953,40.748545],"type":"Point"}
}