{
  "type": "Feature",
  "properties": {
    "addr:full":"2968 Bruckner Blvd Bronx NY 10465",
    "addr:housenumber":"2968",
    "addr:postcode":"10465",
    "addr:street":"Bruckner Blvd",
    "iso:country":"US",
    "sg:address":"2968 Bruckner Blvd",
    "sg:city":"Bronx",
    "sg:classifiers":[
        {
            "category":"Social Services",
            "subcategory":"Adult Care",
            "type":"Services"
        },
        {
            "category":"Social Services",
            "type":"Services"
        }
    ],
    "sg:phone":"+1 718 892 6090",
    "sg:postcode":"10465",
    "sg:province":"NY",
    "sg:tags":[
        "organization",
        "senior",
        "citizen"
    ],
    "wof:name":"Northeast Bronx Senior Citizen",
    "wof:placetype":"venue"
},
  "geometry": {"coordinates":[-73.826385,40.83369],"type":"Point"}
}