{
  "type": "Feature",
  "properties": {
    "addr:full":"532 W 30 St New York NY 10001",
    "addr:housenumber":"532",
    "addr:postcode":"10001",
    "addr:street":"W 30 St",
    "iso:country":"US",
    "sg:address":"532 W 30 St",
    "sg:city":"New York",
    "sg:classifiers":[
        {
            "category":"Shopping",
            "subcategory":"Gifts & Souvenirs",
            "type":"Retail Goods"
        }
    ],
    "sg:phone":"+1 212 594 0529",
    "sg:postcode":"10001",
    "sg:province":"NY",
    "sg:tags":[
        "shop"
    ],
    "wof:name":"Gado Baskets",
    "wof:placetype":"venue"
},
  "geometry": {"coordinates":[-74.003145,40.752817],"type":"Point"}
}