{
  "type": "Feature",
  "properties": {
    "iso:country":"US",
    "sg:address":"109 Dwight Ave",
    "sg:city":"Corning",
    "sg:classifiers":[
        {
            "category":"Building & Trades",
            "subcategory":"Electrical",
            "type":"Services"
        }
    ],
    "sg:phone":"+1 607 936 3501",
    "sg:postcode":"14830",
    "sg:province":"NY",
    "sg:tags":[
        "electric",
        "contractor"
    ],
    "wof:name":"Gary A Mc Carty Electric",
    "wof:placetype":"venue"
},
  "geometry": {"coordinates":[-77.072597,42.152711],"type":"Point"}
}