{
  "type": "Feature",
  "properties": {
    "addr:full":"1698 Pitkin Ave Brooklyn NY 11212",
    "addr:housenumber":"1698",
    "addr:postcode":"11212",
    "addr:street":"Pitkin Ave",
    "iso:country":"US",
    "sg:address":"1698 Pitkin Ave",
    "sg:city":"Brooklyn",
    "sg:classifiers":[
        {
            "category":"Utilities",
            "subcategory":"Mobile Phone",
            "type":"Services"
        },
        {
            "category":"Shopping",
            "subcategory":"Mobile Phones",
            "type":"Retail Goods"
        },
        {
            "category":"Utilities",
            "subcategory":"Telephone",
            "type":"Services"
        },
        {
            "category":"Professional",
            "subcategory":"Computer Services",
            "type":"Services"
        }
    ],
    "sg:phone":"+1 718 485 9531",
    "sg:postcode":"11212",
    "sg:province":"NY",
    "sg:tags":[
        "telecommunication",
        "supply",
        "communication",
        "system",
        "wireless",
        "equipment",
        "cellular"
    ],
    "sg:website":"http://clickserve.dartsearch.net/link/click?lid=43000000308049899",
    "wof:name":"T-Mobile",
    "wof:placetype":"venue"
},
  "geometry": {"coordinates":[-73.910563,40.669717],"type":"Point"}
}