{
  "type": "Feature",
  "properties": {
    "addr:full":"254 Norwood Cir Webster NY 14580",
    "addr:housenumber":"254",
    "addr:postcode":"14580",
    "addr:street":"Norwood Cir",
    "iso:country":"US",
    "sg:address":"254 Norwood Cir",
    "sg:city":"Webster",
    "sg:classifiers":[
        {
            "category":"Recreation",
            "type":"Entertainment"
        }
    ],
    "sg:phone":"+1 585 671 2362",
    "sg:postcode":"14580",
    "sg:province":"NY",
    "sg:tags":[
        "party",
        "fishing"
    ],
    "wof:name":"Enticer Charters",
    "wof:placetype":"venue"
},
  "geometry": {"coordinates":[-77.519887,43.218435],"type":"Point"}
}