{
  "type": "Feature",
  "properties": {
    "iso:country":"US",
    "sg:address":"49 Henry St",
    "sg:city":"New York",
    "sg:classifiers":[
        {
            "category":"Parking",
            "type":"Transportation"
        }
    ],
    "sg:phone":"+1 212 285 1583",
    "sg:postcode":"10002",
    "sg:province":"NY",
    "sg:tags":[
        "garage"
    ],
    "wof:name":"Henry Operating Corp",
    "wof:placetype":"venue"
},
  "geometry": {"coordinates":[-73.99597799999999,40.712929],"type":"Point"}
}