{
  "type": "Feature",
  "properties": {
    "iso:country":"US",
    "sg:address":"251 Bainbridge St Apt 2",
    "sg:city":"Wilson",
    "sg:classifiers":[
        {
            "category":"Real Estate",
            "subcategory":"Real Estate Operator",
            "type":"Services"
        }
    ],
    "sg:phone":"+1 716 751 6597",
    "sg:postcode":"14172",
    "sg:province":"NY",
    "sg:tags":[
        "apartment"
    ],
    "wof:name":"Kevin M King",
    "wof:placetype":"venue"
},
  "geometry": {"coordinates":[-78.83041900000001,43.310005],"type":"Point"}
}