{
  "type": "Feature",
  "properties": {
    "addr:full":"1858 State St Schenectady NY 12304",
    "addr:housenumber":"1858",
    "addr:postcode":"12304",
    "addr:street":"State St",
    "iso:country":"US",
    "sg:address":"1858 State St",
    "sg:city":"Schenectady",
    "sg:classifiers":[
        {
            "category":"Social Services",
            "subcategory":"Child Care",
            "type":"Services"
        }
    ],
    "sg:phone":"+1   ",
    "sg:postcode":"12304",
    "sg:province":"NY",
    "sg:tags":[
        "organization",
        "religious",
        "day"
    ],
    "wof:name":"Woodlawn Reform Church Nursery",
    "wof:placetype":"venue"
},
  "geometry": {"coordinates":[-73.90234100000001,42.778867],"type":"Point"}
}