{
  "type": "Feature",
  "properties": {
    "addr:full":"200 E 94th St Apt 1417 New York NY 10128",
    "addr:housenumber":"200",
    "addr:postcode":"1417;10128",
    "addr:street":"E 94Th St Apt",
    "iso:country":"US",
    "sg:address":"200 E 94th St Apt 1417",
    "sg:city":"New York",
    "sg:classifiers":[
        {
            "category":"Health Services",
            "subcategory":"Doctor",
            "type":"Services"
        }
    ],
    "sg:phone":"+1 212 570 1933",
    "sg:postcode":"10128",
    "sg:province":"NY",
    "wof:name":"Attwell Chap MD",
    "wof:placetype":"venue"
},
  "geometry": {"coordinates":[-73.950305,40.783685],"type":"Point"}
}