{
  "type": "Feature",
  "properties": {
    "iso:country":"US",
    "sg:address":"364 Ryerson Ave",
    "sg:city":"Manorville",
    "sg:classifiers":[
        {
            "category":"Personal",
            "type":"Services"
        },
        {
            "category":"Retail",
            "subcategory":"Auto Repair",
            "type":"Services"
        }
    ],
    "sg:phone":"+1 631 878 6886",
    "sg:postcode":"11949",
    "sg:province":"NY",
    "sg:tags":[
        "body",
        "shop",
        "towing"
    ],
    "wof:name":"Crossroads Body & Fender Works",
    "wof:placetype":"venue"
},
  "geometry": {"coordinates":[-72.80999799999999,40.861198],"type":"Point"}
}