{
  "type": "Feature",
  "properties": {
    "addr:full":"19 White Oak Dr Smithtown NY 11787",
    "addr:housenumber":"19",
    "addr:postcode":"11787",
    "addr:street":"White Oak Dr",
    "iso:country":"US",
    "sg:address":"19 White Oak Dr",
    "sg:city":"Smithtown",
    "sg:classifiers":[
        {
            "category":"Building & Trades",
            "subcategory":"Landscaping Services",
            "type":"Services"
        }
    ],
    "sg:phone":"+1 631 864 5638",
    "sg:postcode":"11787",
    "sg:province":"NY",
    "wof:name":"Richard Prianti",
    "wof:placetype":"venue"
},
  "geometry": {"coordinates":[-73.250877,40.831783],"type":"Point"}
}