{
  "type": "Feature",
  "properties": {
    "addr:full":"54 Lexington Ave Patchogue NY 11772",
    "addr:housenumber":"54",
    "addr:postcode":"11772",
    "addr:street":"Lexington Ave",
    "iso:country":"US",
    "sg:address":"54 Lexington Ave",
    "sg:city":"Patchogue",
    "sg:classifiers":[
        {
            "category":"Food & Beverages",
            "subcategory":"Specialty",
            "type":"Retail Goods"
        }
    ],
    "sg:phone":"+1   ",
    "sg:postcode":"11772",
    "sg:province":"NY",
    "wof:name":"L A DOT Com",
    "wof:placetype":"venue"
},
  "geometry": {"coordinates":[-73.029741,40.790164],"type":"Point"}
}