{
  "type": "Feature",
  "properties": {
    "addr:full":"43 Dahl Dr Sand Lake NY 12153",
    "addr:housenumber":"43",
    "addr:postcode":"12153",
    "addr:street":"Dahl Dr",
    "iso:country":"US",
    "sg:address":"43 Dahl Dr",
    "sg:city":"Sand Lake",
    "sg:classifiers":[
        {
            "category":"Building & Trades",
            "subcategory":"Construction",
            "type":"Services"
        }
    ],
    "sg:phone":"+1 518 674 3179",
    "sg:postcode":"12153",
    "sg:province":"NY",
    "sg:tags":[
        "excavation",
        "work",
        "logging"
    ],
    "wof:name":"George Dahl",
    "wof:placetype":"venue"
},
  "geometry": {"coordinates":[-73.502729,42.64245],"type":"Point"}
}