{
  "type": "Feature",
  "properties": {
    "iso:country":"US",
    "sg:address":"751 Coach Rd",
    "sg:city":"Argyle",
    "sg:classifiers":[
        {
            "category":"Building & Trades",
            "subcategory":"Construction",
            "type":"Services"
        }
    ],
    "sg:phone":"+1 518 638 8444",
    "sg:postcode":"12809",
    "sg:province":"NY",
    "sg:tags":[
        "roofing",
        "industrial",
        "contractors-commercial",
        "contractor"
    ],
    "wof:name":"Marino Phil Roofing Specialist",
    "wof:placetype":"venue"
},
  "geometry": {"coordinates":[-73.470467,43.232255],"type":"Point"}
}