{
  "type": "Feature",
  "properties": {
    "iso:country":"US",
    "sg:address":"535 Atlantic Ave",
    "sg:city":"Brooklyn",
    "sg:classifiers":[
        {
            "category":"Insurance",
            "subcategory":"Insurance Agent",
            "type":"Services"
        }
    ],
    "sg:phone":"+1 718 522 3444",
    "sg:postcode":"11217",
    "sg:province":"NY",
    "wof:name":"Dart Auto Insurance",
    "wof:placetype":"venue"
},
  "geometry": {"coordinates":[-73.9789,40.684771],"type":"Point"}
}