{
  "type": "Feature",
  "properties": {
    "iso:country":"US",
    "sg:address":"3281 Veterans Memorial Hwy",
    "sg:city":"Ronkonkoma",
    "sg:classifiers":[
        {
            "category":"Professional",
            "subcategory":"Employment Agencies",
            "type":"Services"
        }
    ],
    "sg:phone":"+1 631 585 2800",
    "sg:postcode":"11779",
    "sg:province":"NY",
    "sg:tags":[
        "help",
        "supply"
    ],
    "wof:name":"V S Managmnt",
    "wof:placetype":"venue"
},
  "geometry": {"coordinates":[-73.132278,40.787707],"type":"Point"}
}