{
  "type": "Feature",
  "properties": {
    "addr:full":"938 Wyoming Rd Wyoming NY 14591",
    "addr:housenumber":"938",
    "addr:postcode":"14591",
    "addr:street":"Wyoming Rd",
    "iso:country":"US",
    "sg:address":"938 Wyoming Rd",
    "sg:city":"Wyoming",
    "sg:classifiers":[
        {
            "category":"Real Estate",
            "subcategory":"Real Estate Operator",
            "type":"Services"
        }
    ],
    "sg:phone":"+1 585 495 6596",
    "sg:postcode":"14591",
    "sg:province":"NY",
    "sg:tags":[
        "property",
        "lessor"
    ],
    "wof:name":"Lawrence Wright",
    "wof:placetype":"venue"
},
  "geometry": {"coordinates":[-78.057605,42.835626],"type":"Point"}
}