{
  "type": "Feature",
  "properties": {
    "addr:full":"7227 US Hwy 20 Madison NY 13402",
    "addr:housenumber":"7227",
    "addr:postcode":"13402",
    "addr:street":"Us Hwy 20",
    "iso:country":"US",
    "sg:address":"7227 US Hwy 20",
    "sg:city":"Madison",
    "sg:classifiers":[
        {
            "category":"Food & Beverages",
            "subcategory":"Groceries & Convenience Stores",
            "type":"Retail Goods"
        }
    ],
    "sg:phone":"+1 315 893 1882",
    "sg:postcode":"13402",
    "sg:province":"NY",
    "wof:name":"A & We-Z Mart",
    "wof:placetype":"venue"
},
  "geometry": {"coordinates":[-75.523309,42.896073],"type":"Point"}
}