{
  "type": "Feature",
  "properties": {
    "iso:country":"US",
    "sg:address":"102 Park St",
    "sg:city":"Glens Falls",
    "sg:classifiers":[
        {
            "category":"Health Services",
            "subcategory":"Health Practitioner",
            "type":"Services"
        }
    ],
    "sg:phone":"+1 518 798 1159",
    "sg:postcode":"12801",
    "sg:province":"NY",
    "sg:tags":[
        "psychologist"
    ],
    "wof:name":"Marice Pappo PHD",
    "wof:placetype":"venue"
},
  "geometry": {"coordinates":[-73.646241,43.307188],"type":"Point"}
}