{
  "type": "Feature",
  "properties": {
    "iso:country":"US",
    "sg:address":"274 Madison Ave Rm 1801",
    "sg:city":"New York",
    "sg:classifiers":[
        {
            "category":"Professional",
            "subcategory":"Employment Agencies",
            "type":"Services"
        }
    ],
    "sg:phone":"+1 212 685 9677",
    "sg:postcode":"10016",
    "sg:province":"NY",
    "sg:website":"www.stanhamlet.com",
    "wof:name":"Stan Hamlet Assocs Inc",
    "wof:placetype":"venue"
},
  "geometry": {"coordinates":[-73.98054,40.751339],"type":"Point"}
}