{
  "type": "Feature",
  "properties": {
    "addr:full":"832 Mc Clellan St Schenectady NY 12304",
    "addr:housenumber":"832",
    "addr:postcode":"12304",
    "addr:street":"Mc Clellan St",
    "iso:country":"US",
    "sg:address":"832 Mc Clellan St",
    "sg:city":"Schenectady",
    "sg:classifiers":[
        {
            "category":"Shopping",
            "subcategory":"Florist",
            "type":"Retail Goods"
        }
    ],
    "sg:phone":"+1 518 372 1696",
    "sg:postcode":"12304",
    "sg:province":"NY",
    "wof:name":"Central Market Florist",
    "wof:placetype":"venue"
},
  "geometry": {"coordinates":[-73.916893,42.804937],"type":"Point"}
}