{
  "type": "Feature",
  "properties": {
    "iso:country":"US",
    "sg:address":"252 Saint Anns Avenue",
    "sg:city":"Bronx",
    "sg:classifiers":[
        {
            "category":"Restaurant",
            "type":"Food & Drink"
        }
    ],
    "sg:phone":"+1 718 585 8665",
    "sg:postcode":"10454",
    "sg:province":"NY",
    "sg:tags":[
        "chinese"
    ],
    "wof:name":"China Cafe",
    "wof:placetype":"venue"
},
  "geometry": {"coordinates":[-73.91703800000001,40.807228],"type":"Point"}
}