{
  "type": "Feature",
  "properties": {
    "iso:country":"US",
    "sg:address":"207 W 96 St",
    "sg:city":"New York",
    "sg:classifiers":[
        {
            "category":"Social Services",
            "type":"Services"
        }
    ],
    "sg:phone":"+1 212 932 8040",
    "sg:postcode":"10025",
    "sg:province":"NY",
    "wof:name":"Franciscan Community Ctr",
    "wof:placetype":"venue"
},
  "geometry": {"coordinates":[-73.97161699999999,40.79464],"type":"Point"}
}