{
  "type": "Feature",
  "properties": {
    "iso:country":"US",
    "sg:address":"1591 Route 22",
    "sg:city":"Brewster",
    "sg:classifiers":[
        {
            "category":"Health Services",
            "subcategory":"Doctor",
            "type":"Services"
        }
    ],
    "sg:phone":"+1 845 278 8797",
    "sg:postcode":"10509",
    "sg:province":"NY",
    "wof:name":"Route Twenty Two Medical",
    "wof:placetype":"venue"
},
  "geometry": {"coordinates":[-73.57798200000001,41.426569],"type":"Point"}
}