{
  "type": "Feature",
  "properties": {
    "addr:full":"2802 23rd Ave Astoria NY 11105",
    "addr:housenumber":"2802",
    "addr:postcode":"11105",
    "addr:street":"23Rd Ave",
    "iso:country":"US",
    "sg:address":"2802 23rd Ave",
    "sg:city":"Astoria",
    "sg:phone":"+1 718 728 9066",
    "sg:postcode":"11105",
    "sg:province":"NY",
    "wof:name":"Andrew Franks Delicatessen",
    "wof:placetype":"venue"
},
  "geometry": {"coordinates":[-73.906738,40.77001],"type":"Point"}
}