{
  "type": "Feature",
  "properties": {
    "iso:country":"US",
    "sg:address":"1354 Amherst St",
    "sg:city":"Buffalo",
    "sg:classifiers":[
        {
            "category":"Health Services",
            "subcategory":"Dentist",
            "type":"Services"
        }
    ],
    "sg:phone":"+1 716 836 2555",
    "sg:postcode":"14216",
    "sg:province":"NY",
    "wof:name":"Western New York Dental Group Pc Dds",
    "wof:placetype":"venue"
},
  "geometry": {"coordinates":[-78.85311900000001,42.941334],"type":"Point"}
}