{
  "type": "Feature",
  "properties": {
    "addr:full":"34 Wayaawi Ave Bayville NY 11709",
    "addr:housenumber":"34",
    "addr:postcode":"11709",
    "addr:street":"Wayaawi Ave",
    "iso:country":"US",
    "sg:address":"34 Wayaawi Ave",
    "sg:city":"Bayville",
    "sg:classifiers":[
        {
            "category":"Building & Trades",
            "subcategory":"Construction",
            "type":"Services"
        }
    ],
    "sg:phone":"+1 516 628 1664",
    "sg:postcode":"11709",
    "sg:province":"NY",
    "sg:tags":[
        "contractor"
    ],
    "wof:name":"Renato Grella Contracting Inc",
    "wof:placetype":"venue"
},
  "geometry": {"coordinates":[-73.569772,40.913559],"type":"Point"}
}