{
  "type": "Feature",
  "properties": {
    "addr:full":"961 Port Washington Blvd # 3 Port Washington NY 11050",
    "addr:housenumber":"961",
    "addr:postcode":"11050",
    "addr:street":"Port Washington Blvd # 3",
    "iso:country":"US",
    "sg:address":"961 Port Washington Blvd # 3",
    "sg:city":"Port Washington",
    "sg:classifiers":[
        {
            "category":"Retail",
            "subcategory":"Portrait Studio",
            "type":"Services"
        },
        {
            "category":"Shopping",
            "subcategory":"Pharmacy",
            "type":"Retail Goods"
        }
    ],
    "sg:phone":"+1 516 944 6148",
    "sg:postcode":"11050",
    "sg:province":"NY",
    "sg:tags":[
        "photography",
        "drugstore",
        "store"
    ],
    "wof:name":"Eckerd Pharmacy",
    "wof:placetype":"venue"
},
  "geometry": {"coordinates":[-73.683774,40.829834],"type":"Point"}
}