{
  "type": "Feature",
  "properties": {
    "addr:full":"714 W 181st St Frnt 1 New York NY 10033",
    "addr:housenumber":"714;1",
    "addr:postcode":"10033",
    "addr:street":"W 181St St Frnt",
    "iso:country":"US",
    "sg:address":"714 W 181st St Frnt 1",
    "sg:city":"New York",
    "sg:classifiers":[
        {
            "category":"Personal",
            "subcategory":"Nail Salon",
            "type":"Services"
        }
    ],
    "sg:phone":"+1 212 927 2385",
    "sg:postcode":"10033",
    "sg:province":"NY",
    "wof:name":"Transformation Hair",
    "wof:placetype":"venue"
},
  "geometry": {"coordinates":[-73.93701299999999,40.85041],"type":"Point"}
}