{
  "type": "Feature",
  "properties": {
    "addr:full":"254 E 203rd St Bronx NY 10458",
    "addr:housenumber":"254",
    "addr:postcode":"10458",
    "addr:street":"E 203Rd St",
    "iso:country":"US",
    "sg:address":"254 E 203rd St",
    "sg:city":"Bronx",
    "sg:classifiers":[
        {
            "category":"Real Estate",
            "subcategory":"Real Estate Agent",
            "type":"Services"
        }
    ],
    "sg:phone":"+1 718 562 7448",
    "sg:postcode":"10458",
    "sg:province":"NY",
    "wof:name":"Chatham Realty",
    "wof:placetype":"venue"
},
  "geometry": {"coordinates":[-73.883363,40.873112],"type":"Point"}
}