{
  "type": "Feature",
  "properties": {
    "iso:country":"US",
    "sg:address":"26 Racquet Rd",
    "sg:city":"Newburgh",
    "sg:classifiers":[
        {
            "category":"Building & Trades",
            "subcategory":"Construction",
            "type":"Services"
        }
    ],
    "sg:phone":"+1 845 562 1350",
    "sg:postcode":"12550",
    "sg:province":"NY",
    "sg:tags":[
        "general",
        "contractor"
    ],
    "wof:name":"Hudson River Contracting Co",
    "wof:placetype":"venue"
},
  "geometry": {"coordinates":[-74.114012,41.528937],"type":"Point"}
}