{
  "type": "Feature",
  "properties": {
    "addr:full":"159 W 62 St New York NY 10023",
    "addr:housenumber":"159",
    "addr:postcode":"10023",
    "addr:street":"W 62 St",
    "iso:country":"US",
    "sg:address":"159 W 62 St",
    "sg:city":"New York",
    "sg:classifiers":[
        {
            "category":"Retail",
            "subcategory":"Auto Repair",
            "type":"Services"
        }
    ],
    "sg:phone":"+1 212 838 2075",
    "sg:postcode":"10023",
    "sg:province":"NY",
    "sg:tags":[
        "repairing",
        "automobile"
    ],
    "wof:name":"Garage Mgmt Co LLC",
    "wof:placetype":"venue"
},
  "geometry": {"coordinates":[-73.98496,40.771676],"type":"Point"}
}