{
  "type": "Feature",
  "properties": {
    "iso:country":"US",
    "sg:address":"64th & Broadway",
    "sg:city":"Manhattan",
    "sg:classifiers":[
        {
            "category":"Communications",
            "type":"Services"
        }
    ],
    "sg:phone":"+1 646 320 5019",
    "sg:postcode":"10023",
    "sg:province":"NY",
    "sg:tags":[
        "medium",
        "mass"
    ],
    "sg:website":"www.norcrossmedia.com",
    "wof:name":"Norcross Media, LLC",
    "wof:placetype":"venue"
},
  "geometry": {"coordinates":[-73.982063,40.772189],"type":"Point"}
}