{
  "type": "Feature",
  "properties": {
    "iso:country":"US",
    "sg:address":"8 Grove St",
    "sg:city":"Cooperstown",
    "sg:classifiers":[
        {
            "category":"Shopping",
            "subcategory":"Used Merchandise",
            "type":"Retail Goods"
        }
    ],
    "sg:phone":"+1   ",
    "sg:postcode":"13326",
    "sg:province":"NY",
    "wof:name":"Zone Sports Cards",
    "wof:placetype":"venue"
},
  "geometry": {"coordinates":[-74.932909,42.700846],"type":"Point"}
}