{
  "type": "Feature",
  "properties": {
    "iso:country":"US",
    "sg:address":"1001 Richmond Hill Road",
    "sg:city":"Staten Island",
    "sg:classifiers":[
        {
            "category":"Sports & Exercise",
            "subcategory":"Golf",
            "type":"Entertainment"
        }
    ],
    "sg:phone":"+1 718 351 1889",
    "sg:postcode":"10306",
    "sg:province":"NY",
    "wof:name":"Latourette Golf Course",
    "wof:placetype":"venue"
},
  "geometry": {"coordinates":[-74.146697,40.574042],"type":"Point"}
}