{
  "type": "Feature",
  "properties": {
    "addr:full":"203 Rochester Ave Brooklyn NY 11213",
    "addr:housenumber":"203",
    "addr:postcode":"11213",
    "addr:street":"Rochester Ave",
    "iso:country":"US",
    "sg:address":"203 Rochester Ave",
    "sg:city":"Brooklyn",
    "sg:classifiers":[
        {
            "category":"Organizations",
            "subcategory":"Religious Organization",
            "type":"Services"
        }
    ],
    "sg:phone":"+1 718 756 3350",
    "sg:postcode":"11213",
    "sg:province":"NY",
    "wof:name":"New Gethsemane Bible Institute",
    "wof:placetype":"venue"
},
  "geometry": {"coordinates":[-73.928003,40.671589],"type":"Point"}
}