{
  "type": "Feature",
  "properties": {
    "addr:full":"30 Princeton Ln Fairport NY 14450",
    "addr:housenumber":"30",
    "addr:postcode":"14450",
    "addr:street":"Princeton Ln",
    "iso:country":"US",
    "sg:address":"30 Princeton Ln",
    "sg:city":"Fairport",
    "sg:classifiers":[
        {
            "category":"Banks & Credit Unions",
            "subcategory":"Investment Brokerage",
            "type":"Services"
        }
    ],
    "sg:phone":"+1 585 489 6444",
    "sg:postcode":"14450",
    "sg:province":"NY",
    "wof:name":"Lifetime Financial Consultants",
    "wof:placetype":"venue"
},
  "geometry": {"coordinates":[-77.400558,43.1018],"type":"Point"}
}