{
  "type": "Feature",
  "properties": {
    "iso:country":"US",
    "sg:address":"2 Kennedy Dr",
    "sg:city":"Liberty",
    "sg:classifiers":[
        {
            "category":"Real Estate",
            "subcategory":"Surveying",
            "type":"Services"
        }
    ],
    "sg:phone":"+1   ",
    "sg:postcode":"12754",
    "sg:province":"NY",
    "sg:tags":[
        "engineering"
    ],
    "wof:name":"Woods Surveyor & Civil Engrg",
    "wof:placetype":"venue"
},
  "geometry": {"coordinates":[-74.74130599999999,41.810964],"type":"Point"}
}