{
  "type": "Feature",
  "properties": {
    "iso:country":"US",
    "sg:address":"202 Old Cahoonzie Rd",
    "sg:city":"Sparrow Bush",
    "sg:classifiers":[
        {
            "category":"Farming",
            "subcategory":"Nursery",
            "type":"Manufacturing & Wholesale Goods"
        }
    ],
    "sg:phone":"+1 845 856 5804",
    "sg:postcode":"12780",
    "sg:province":"NY",
    "sg:tags":[
        "florist",
        "ornamental",
        "sup"
    ],
    "wof:name":"Twin Oaks Greenhouses",
    "wof:placetype":"venue"
},
  "geometry": {"coordinates":[-74.71894399999999,41.421257],"type":"Point"}
}