{
  "type": "Feature",
  "properties": {
    "addr:full":"60 Lakeview Dr Mastic Beach NY 11951",
    "addr:housenumber":"60",
    "addr:postcode":"11951",
    "addr:street":"Lakeview Dr",
    "iso:country":"US",
    "sg:address":"60 Lakeview Dr",
    "sg:city":"Mastic Beach",
    "sg:classifiers":[
        {
            "category":"Building & Trades",
            "subcategory":"Cleaning & Sanitation",
            "type":"Services"
        }
    ],
    "sg:phone":"+1 631 772 4417",
    "sg:postcode":"11951",
    "sg:province":"NY",
    "sg:tags":[
        "carpet"
    ],
    "wof:name":"Pro Care Carpet Cleaning",
    "wof:placetype":"venue"
},
  "geometry": {"coordinates":[-72.836536,40.765965],"type":"Point"}
}