{
  "type": "Feature",
  "properties": {
    "addr:full":"327 State Hwy 59 West Nyack NY 10994",
    "addr:housenumber":"327",
    "addr:postcode":"10994",
    "addr:street":"State Hwy 59",
    "iso:country":"US",
    "sg:address":"327 State Hwy 59",
    "sg:city":"West Nyack",
    "sg:classifiers":[
        {
            "category":"Personal",
            "subcategory":"Beauty Salon",
            "type":"Services"
        }
    ],
    "sg:phone":"+1   ",
    "sg:postcode":"10994",
    "sg:province":"NY",
    "sg:tags":[
        "shop"
    ],
    "wof:name":"Bogart Hair Design",
    "wof:placetype":"venue"
},
  "geometry": {"coordinates":[-73.96209399999999,41.094259],"type":"Point"}
}