{
  "type": "Feature",
  "properties": {
    "addr:full":"12637 37th Ave Corona NY 11368",
    "addr:housenumber":"12637",
    "addr:postcode":"11368",
    "addr:street":"37Th Ave",
    "iso:country":"US",
    "sg:address":"12637 37th Ave",
    "sg:city":"Corona",
    "sg:classifiers":[
        {
            "category":"Organizations",
            "subcategory":"Religious Organization",
            "type":"Services"
        }
    ],
    "sg:phone":"+1 718 672 9187",
    "sg:postcode":"11368",
    "sg:province":"NY",
    "wof:name":"Brother Jesus",
    "wof:placetype":"venue"
},
  "geometry": {"coordinates":[-73.84304899999999,40.758175],"type":"Point"}
}