{
  "type": "Feature",
  "properties": {
    "addr:full":"203 State Hwy 59 Airmont NY 10952",
    "addr:housenumber":"203",
    "addr:postcode":"10952",
    "addr:street":"State Hwy 59",
    "iso:country":"US",
    "sg:address":"203 State Hwy 59",
    "sg:city":"Airmont",
    "sg:classifiers":[
        {
            "category":"Restaurant",
            "type":"Food & Drink"
        }
    ],
    "sg:phone":"+1 845 352 2806",
    "sg:postcode":"10952",
    "sg:province":"NY",
    "wof:name":"Three Boys From Italy",
    "wof:placetype":"venue"
},
  "geometry": {"coordinates":[-74.084745,41.108834],"type":"Point"}
}