{
  "type": "Feature",
  "properties": {
    "addr:full":"36 Overlook Rd Great Neck NY 11020",
    "addr:housenumber":"36",
    "addr:postcode":"11020",
    "addr:street":"Overlook Rd",
    "iso:country":"US",
    "sg:address":"36 Overlook Rd",
    "sg:city":"Great Neck",
    "sg:classifiers":[
        {
            "category":"Professional",
            "subcategory":"Accounting & Tax Preparation",
            "type":"Services"
        }
    ],
    "sg:phone":"+1   ",
    "sg:postcode":"11020",
    "sg:province":"NY",
    "wof:name":"P Darvin & Co",
    "wof:placetype":"venue"
},
  "geometry": {"coordinates":[-73.724503,40.767596],"type":"Point"}
}