{
  "type": "Feature",
  "properties": {
    "addr:full":"10642 157th St Jamaica NY 11433",
    "addr:housenumber":"10642",
    "addr:postcode":"11433",
    "addr:street":"157Th St",
    "iso:country":"US",
    "sg:address":"10642 157th St",
    "sg:city":"Jamaica",
    "sg:classifiers":[
        {
            "category":"Retail",
            "subcategory":"Auto Repair",
            "type":"Services"
        }
    ],
    "sg:phone":"+1 718 657 7779",
    "sg:postcode":"11433",
    "sg:province":"NY",
    "sg:tags":[
        "body",
        "shop"
    ],
    "wof:name":"Well Done Auto Body",
    "wof:placetype":"venue"
},
  "geometry": {"coordinates":[-73.796997,40.696602],"type":"Point"}
}