{
  "type": "Feature",
  "properties": {
    "addr:full":"301 25th St Watervliet NY 12189",
    "addr:housenumber":"301",
    "addr:postcode":"12189",
    "addr:street":"25Th St",
    "iso:country":"US",
    "sg:address":"301 25th St",
    "sg:city":"Watervliet",
    "sg:classifiers":[
        {
            "category":"Restaurant",
            "type":"Food & Drink"
        }
    ],
    "sg:phone":"+1 518 271 2525",
    "sg:postcode":"12189",
    "sg:province":"NY",
    "wof:name":"25th St Pizza",
    "wof:placetype":"venue"
},
  "geometry": {"coordinates":[-73.70254799999999,42.735517],"type":"Point"}
}