{
  "type": "Feature",
  "properties": {
    "addr:full":"464 W 51st St New York NY 10019",
    "addr:housenumber":"464",
    "addr:postcode":"10019",
    "addr:street":"W 51St St",
    "iso:country":"US",
    "sg:address":"464 W 51st St",
    "sg:city":"New York",
    "sg:classifiers":[
        {
            "category":"Retail",
            "subcategory":"Repair Shop",
            "type":"Services"
        }
    ],
    "sg:phone":"+1 212 581 5596",
    "sg:postcode":"10019",
    "sg:province":"NY",
    "sg:tags":[
        "refrigeration"
    ],
    "wof:name":"Trouble Shooters Appliance",
    "wof:placetype":"venue"
},
  "geometry": {"coordinates":[-73.989964,40.76446],"type":"Point"}
}