{
  "type": "Feature",
  "properties": {
    "iso:country":"US",
    "sg:address":"867 Flatbush Ave",
    "sg:city":"Brooklyn",
    "sg:classifiers":[
        {
            "category":"Restaurant",
            "type":"Food & Drink"
        }
    ],
    "sg:phone":"+1   ",
    "sg:postcode":"11226",
    "sg:province":"NY",
    "sg:tags":[
        "eating"
    ],
    "wof:name":"Kwong Fat Restaurant",
    "wof:placetype":"venue"
},
  "geometry": {"coordinates":[-73.95866599999999,40.650566],"type":"Point"}
}