{
  "type": "Feature",
  "properties": {
    "addr:full":"609 E 40 New York NY 10001",
    "addr:housenumber":"609;40",
    "addr:postcode":"10001",
    "addr:street":"E",
    "iso:country":"US",
    "sg:address":"609 E 40",
    "sg:city":"New York",
    "sg:classifiers":[
        {
            "category":"Organizations",
            "subcategory":"Non-profit Organization",
            "type":"Services"
        }
    ],
    "sg:phone":"+1 718 872 6951",
    "sg:postcode":"10001",
    "sg:province":"NY",
    "sg:tags":[
        "service/non-profit",
        "community"
    ],
    "wof:name":"Little Angel Hands Inc",
    "wof:placetype":"venue"
},
  "geometry": {"coordinates":[-73.999392,40.759763],"type":"Point"}
}