{
  "type": "Feature",
  "properties": {
    "iso:country":"US",
    "sg:address":"35 Main St",
    "sg:city":"Adams",
    "sg:classifiers":[
        {
            "category":"Social Services",
            "type":"Services"
        }
    ],
    "sg:phone":"+1 315 232 4673",
    "sg:postcode":"13605",
    "sg:province":"NY",
    "sg:tags":[
        "youth",
        "organization",
        "center"
    ],
    "wof:name":"Edge Teen Ctr",
    "wof:placetype":"venue"
},
  "geometry": {"coordinates":[-76.02434100000001,43.80841],"type":"Point"}
}