{
  "type": "Feature",
  "properties": {
    "addr:full":"43 Bogart St Brooklyn NY 11206",
    "addr:housenumber":"43",
    "addr:postcode":"11206",
    "addr:street":"Bogart St",
    "iso:country":"US",
    "sg:address":"43 Bogart St",
    "sg:city":"Brooklyn",
    "sg:classifiers":[
        {
            "category":"Arts & Performance",
            "subcategory":"Art Gallery",
            "type":"Entertainment"
        }
    ],
    "sg:postcode":"11206",
    "sg:province":"NY",
    "sg:website":"www.eastern-district.com/",
    "wof:name":"Eastern District",
    "wof:placetype":"venue"
},
  "geometry": {"coordinates":[-73.93351199999999,40.705091],"type":"Point"}
}