{
  "type": "Feature",
  "properties": {
    "iso:country":"US",
    "sg:address":"123 Wade Rd",
    "sg:city":"Latham",
    "sg:classifiers":[
        {
            "category":"Real Estate",
            "subcategory":"Real Estate Services",
            "type":"Services"
        },
        {
            "category":"Building & Trades",
            "subcategory":"Cleaning & Sanitation",
            "type":"Services"
        }
    ],
    "sg:phone":"+1 518 785 9170",
    "sg:postcode":"12110",
    "sg:province":"NY",
    "sg:tags":[
        "maintenance",
        "cleaners-interior"
    ],
    "wof:name":"Pfg Welding And Maint",
    "wof:placetype":"venue"
},
  "geometry": {"coordinates":[-73.78671900000001,42.746648],"type":"Point"}
}