{
  "type": "Feature",
  "properties": {
    "addr:full":"1974 Commerce St Yorktown Heights NY 10598",
    "addr:housenumber":"1974",
    "addr:postcode":"10598",
    "addr:street":"Commerce St",
    "iso:country":"US",
    "sg:address":"1974 Commerce St",
    "sg:city":"Yorktown Heights",
    "sg:classifiers":[
        {
            "category":"Government",
            "subcategory":"Office",
            "type":"Public Place"
        }
    ],
    "sg:phone":"+1 914 245 2088",
    "sg:postcode":"10598",
    "sg:province":"NY",
    "wof:name":"Westchester County Sr Programs",
    "wof:placetype":"venue"
},
  "geometry": {"coordinates":[-73.78225500000001,41.276234],"type":"Point"}
}