{
  "type": "Feature",
  "properties": {
    "addr:full":"428 Beach 139th St Rockaway Park NY 11694",
    "addr:housenumber":"428",
    "addr:postcode":"11694",
    "addr:street":"Beach 139Th St",
    "iso:country":"US",
    "sg:address":"428 Beach 139th St",
    "sg:city":"Rockaway Park",
    "sg:classifiers":[
        {
            "category":"Manufacturing",
            "subcategory":"Food",
            "type":"Manufacturing & Wholesale Goods"
        }
    ],
    "sg:phone":"+1   ",
    "sg:postcode":"11694",
    "sg:province":"NY",
    "sg:tags":[
        "mfg"
    ],
    "wof:name":"Not Just Sweet Inc",
    "wof:placetype":"venue"
},
  "geometry": {"coordinates":[-73.858103,40.576424],"type":"Point"}
}