{
  "type": "Feature",
  "properties": {
    "iso:country":"US",
    "sg:address":"149 Covert Ave",
    "sg:city":"New Hyde Park",
    "sg:classifiers":[
        {
            "category":"Professional",
            "subcategory":"Management & Consulting",
            "type":"Services"
        }
    ],
    "sg:phone":"+1 516 328 1597",
    "sg:postcode":"11040",
    "sg:province":"NY",
    "wof:name":"Global Sourcing Network",
    "wof:placetype":"venue"
},
  "geometry": {"coordinates":[-73.687775,40.730672],"type":"Point"}
}