{
  "type": "Feature",
  "properties": {
    "addr:full":"71-19 Eliot Avenue New York NY 11379",
    "addr:housenumber":"71-19",
    "addr:postcode":"11379",
    "addr:street":"Eliot Avenue",
    "iso:country":"US",
    "sg:address":"71-19 Eliot Avenue",
    "sg:city":"New York",
    "sg:classifiers":[
        {
            "category":"Bakery",
            "type":"Food & Drink"
        }
    ],
    "sg:phone":"+1 718 639 9170",
    "sg:postcode":"11379",
    "sg:province":"NY",
    "wof:name":"Panardo Pasticceria & Salumeria",
    "wof:placetype":"venue"
},
  "geometry": {"coordinates":[-73.887109,40.721339],"type":"Point"}
}