{
  "type": "Feature",
  "properties": {
    "iso:country":"US",
    "sg:address":"1314 60th St",
    "sg:city":"Brooklyn",
    "sg:classifiers":[
        {
            "category":"Manufacturing",
            "subcategory":"Tools & Machinery",
            "type":"Manufacturing & Wholesale Goods"
        }
    ],
    "sg:phone":"+1   ",
    "sg:postcode":"11219",
    "sg:province":"NY",
    "sg:tags":[
        "packaging",
        "mfg"
    ],
    "wof:name":"Volckening Inc",
    "wof:placetype":"venue"
},
  "geometry": {"coordinates":[-73.996819,40.627754],"type":"Point"}
}