{
  "type": "Feature",
  "properties": {
    "iso:country":"US",
    "sg:address":"678 1st Ave",
    "sg:city":"Troy",
    "sg:classifiers":[
        {
            "category":"Building & Trades",
            "subcategory":"Construction",
            "type":"Services"
        }
    ],
    "sg:phone":"+1 518 253 5767",
    "sg:postcode":"12182",
    "sg:province":"NY",
    "sg:tags":[
        "home",
        "improvement"
    ],
    "wof:name":"M & L Contracting",
    "wof:placetype":"venue"
},
  "geometry": {"coordinates":[-73.67645400000001,42.778965],"type":"Point"}
}