{
  "type": "Feature",
  "properties": {
    "addr:full":"908 State Hwy 394 Kennedy NY 14747",
    "addr:housenumber":"908",
    "addr:postcode":"14747",
    "addr:street":"State Hwy 394 Kennedy",
    "iso:country":"US",
    "sg:address":"908 State Hwy 394",
    "sg:city":"Kennedy",
    "sg:classifiers":[
        {
            "category":"Utilities",
            "subcategory":"Fuel Oil & Lpg",
            "type":"Services"
        }
    ],
    "sg:phone":"+1   ",
    "sg:postcode":"14747",
    "sg:province":"NY",
    "sg:tags":[
        "liquefied",
        "gas",
        "petroleum"
    ],
    "wof:name":"Ferrellgas",
    "wof:placetype":"venue"
},
  "geometry": {"coordinates":[-79.11064,42.143624],"type":"Point"}
}