{
  "type": "Feature",
  "properties": {
    "addr:full":"3 Cricket Hollow Rd East Setauket NY 11733",
    "addr:housenumber":"3",
    "addr:postcode":"11733",
    "addr:street":"Cricket Hollow Rd",
    "iso:country":"US",
    "sg:address":"3 Cricket Hollow Rd",
    "sg:city":"East Setauket",
    "sg:classifiers":[
        {
            "category":"Manufacturing",
            "subcategory":"Printing",
            "type":"Manufacturing & Wholesale Goods"
        }
    ],
    "sg:phone":"+1   ",
    "sg:postcode":"11733",
    "sg:province":"NY",
    "sg:tags":[
        "commercial",
        "graphic",
        "design",
        "computer"
    ],
    "wof:name":"Hunt Graphics Inc",
    "wof:placetype":"venue"
},
  "geometry": {"coordinates":[-73.124184,40.944389],"type":"Point"}
}