{
  "type": "Feature",
  "properties": {
    "iso:country":"US",
    "sg:address":"30 Colpitts Dr",
    "sg:city":"Windsor",
    "sg:classifiers":[
        {
            "category":"Manufacturing",
            "subcategory":"Buildings",
            "type":"Manufacturing & Wholesale Goods"
        },
        {
            "category":"Building & Trades",
            "subcategory":"Construction",
            "type":"Services"
        }
    ],
    "sg:phone":"+1 607 775 1104",
    "sg:postcode":"13865",
    "sg:province":"NY",
    "sg:tags":[
        "home",
        "builder",
        "contractor"
    ],
    "wof:name":"Macnamee Construction",
    "wof:placetype":"venue"
},
  "geometry": {"coordinates":[-75.763775,42.099042],"type":"Point"}
}