{
  "type": "Feature",
  "properties": {
    "iso:country":"US",
    "sg:address":"6810 20th Ave",
    "sg:city":"Brooklyn",
    "sg:classifiers":[
        {
            "category":"Social Services",
            "subcategory":"Child Care",
            "type":"Services"
        }
    ],
    "sg:phone":"+1 718 837 1212",
    "sg:postcode":"11204",
    "sg:province":"NY",
    "sg:tags":[
        "day"
    ],
    "wof:name":"Creative Learning Center",
    "wof:placetype":"venue"
},
  "geometry": {"coordinates":[-73.988247,40.614345],"type":"Point"}
}