{
  "type": "Feature",
  "properties": {
    "addr:full":"640 Parkside Ave Brooklyn NY 11226",
    "addr:housenumber":"640",
    "addr:postcode":"11226",
    "addr:street":"Parkside Ave",
    "iso:country":"US",
    "sg:address":"640 Parkside Ave",
    "sg:city":"Brooklyn",
    "sg:classifiers":[
        {
            "category":"Retail",
            "subcategory":"Storage",
            "type":"Services"
        }
    ],
    "sg:phone":"+1 718 462 8110",
    "sg:postcode":"11226",
    "sg:province":"NY",
    "sg:tags":[
        "warehouse",
        "household",
        "commercial",
        "cold"
    ],
    "sg:website":"http://www.nypasta.com",
    "wof:name":"Crown Cold Storage Inc",
    "wof:placetype":"venue"
},
  "geometry": {"coordinates":[-73.952107,40.656129],"type":"Point"}
}