{
  "type": "Feature",
  "properties": {
    "iso:country":"US",
    "sg:address":"36 Owego St",
    "sg:city":"Cortland",
    "sg:classifiers":[
        {
            "category":"Social Services",
            "type":"Services"
        }
    ],
    "sg:phone":"+1 607 756 5637",
    "sg:postcode":"13045",
    "sg:province":"NY",
    "wof:name":"Central NY Dvlpmental Svcs Off",
    "wof:placetype":"venue"
},
  "geometry": {"coordinates":[-76.184977,42.592808],"type":"Point"}
}