{
  "type": "Feature",
  "properties": {
    "iso:country":"US",
    "sg:address":"117 E 70 St",
    "sg:city":"New York",
    "sg:classifiers":[
        {
            "category":"Education",
            "subcategory":"Special Training",
            "type":"Public Place"
        }
    ],
    "sg:phone":"+1 212 861 5762",
    "sg:postcode":"10021",
    "sg:province":"NY",
    "sg:tags":[
        "center"
    ],
    "wof:name":"Alderton House",
    "wof:placetype":"venue"
},
  "geometry": {"coordinates":[-73.963517,40.769397],"type":"Point"}
}