{
  "type": "Feature",
  "properties": {
    "addr:full":"1717 Milton Ave Syracuse NY 13209",
    "addr:housenumber":"1717",
    "addr:postcode":"13209",
    "addr:street":"Milton Ave",
    "iso:country":"US",
    "sg:address":"1717 Milton Ave",
    "sg:city":"Syracuse",
    "sg:classifiers":[
        {
            "category":"Real Estate",
            "subcategory":"Real Estate Services",
            "type":"Services"
        }
    ],
    "sg:phone":"+1 315 730 9688",
    "sg:postcode":"13209",
    "sg:province":"NY",
    "sg:tags":[
        "management"
    ],
    "wof:name":"M&M Endeavors",
    "wof:placetype":"venue"
},
  "geometry": {"coordinates":[-76.20419200000001,43.060847],"type":"Point"}
}