{
  "type": "Feature",
  "properties": {
    "iso:country":"US",
    "sg:address":"1 Wall St",
    "sg:city":"New York",
    "sg:classifiers":[
        {
            "category":"Organizations",
            "subcategory":"Membership Organization",
            "type":"Services"
        }
    ],
    "sg:phone":"+1 212 219 9401",
    "sg:postcode":"10005",
    "sg:province":"NY",
    "sg:tags":[
        "visual",
        "performing",
        "arts",
        "provides"
    ],
    "wof:name":"LMCC",
    "wof:placetype":"venue"
},
  "geometry": {"coordinates":[-74.01125399999999,40.707507],"type":"Point"}
}