{
  "type": "Feature",
  "properties": {
    "addr:full":"21 Laurel St Centereach NY 11720",
    "addr:housenumber":"21",
    "addr:postcode":"11720",
    "addr:street":"Laurel St",
    "iso:country":"US",
    "sg:address":"21 Laurel St",
    "sg:city":"Centereach",
    "sg:classifiers":[
        {
            "category":"Building & Trades",
            "subcategory":"Construction",
            "type":"Services"
        }
    ],
    "sg:phone":"+1 631 588 2434",
    "sg:postcode":"11720",
    "sg:province":"NY",
    "sg:tags":[
        "resurfacing",
        "refinishing",
        "floor"
    ],
    "wof:name":"IAIA & Son's",
    "wof:placetype":"venue"
},
  "geometry": {"coordinates":[-73.101727,40.86389],"type":"Point"}
}