{
  "type": "Feature",
  "properties": {
    "addr:full":"28 East St Honeoye Falls NY 14472",
    "addr:housenumber":"28",
    "addr:postcode":"14472",
    "addr:street":"East St",
    "iso:country":"US",
    "sg:address":"28 East St",
    "sg:city":"Honeoye Falls",
    "sg:classifiers":[
        {
            "category":"Health Services",
            "subcategory":"Clinic",
            "type":"Services"
        }
    ],
    "sg:phone":"+1 585 624 3090",
    "sg:postcode":"14472",
    "sg:province":"NY",
    "sg:tags":[
        "specialty",
        "outpatient"
    ],
    "wof:name":"Crestwood Childrens Center",
    "wof:placetype":"venue"
},
  "geometry": {"coordinates":[-77.588775,42.952529],"type":"Point"}
}