{
  "type": "Feature",
  "properties": {
    "addr:full":"1660 Sweet Rd East Aurora NY 14052",
    "addr:housenumber":"1660",
    "addr:postcode":"14052",
    "addr:street":"Sweet Rd",
    "iso:country":"US",
    "sg:address":"1660 Sweet Rd",
    "sg:city":"East Aurora",
    "sg:classifiers":[
        {
            "category":"Professional",
            "subcategory":"Art Services",
            "type":"Services"
        }
    ],
    "sg:phone":"+1 716 652 3988",
    "sg:postcode":"14052",
    "sg:province":"NY",
    "sg:tags":[
        "graphic",
        "designer"
    ],
    "wof:name":"Square One Graphics",
    "wof:placetype":"venue"
},
  "geometry": {"coordinates":[-78.621808,42.737535],"type":"Point"}
}