{
  "type": "Feature",
  "properties": {
    "iso:country":"US",
    "sg:address":"174 Glen St",
    "sg:city":"Glens Falls",
    "sg:classifiers":[
        {
            "category":"Shopping",
            "subcategory":"Stationery & Office Supplies",
            "type":"Retail Goods"
        }
    ],
    "sg:phone":"+1 518 792 4422",
    "sg:postcode":"12801",
    "sg:province":"NY",
    "wof:name":"Russell & Wait Inc",
    "wof:placetype":"venue"
},
  "geometry": {"coordinates":[-73.645529,43.3104],"type":"Point"}
}