{
  "type": "Feature",
  "properties": {
    "iso:country":"US",
    "sg:address":"222 N Division St",
    "sg:city":"Auburn",
    "sg:classifiers":[
        {
            "category":"Retail",
            "subcategory":"Auto Repair",
            "type":"Services"
        }
    ],
    "sg:phone":"+1 315 253 2891",
    "sg:postcode":"13021",
    "sg:province":"NY",
    "sg:tags":[
        "repairing",
        "automobile"
    ],
    "wof:name":"Bob Scott Motors",
    "wof:placetype":"venue"
},
  "geometry": {"coordinates":[-76.586494,42.948181],"type":"Point"}
}