{
  "type": "Feature",
  "properties": {
    "iso:country":"US",
    "sg:address":"14387 State Hwy 37",
    "sg:city":"Massena",
    "sg:classifiers":[
        {
            "category":"Shopping",
            "subcategory":"Bicycles & Sporting Goods",
            "type":"Retail Goods"
        }
    ],
    "sg:phone":"+1   ",
    "sg:postcode":"13662",
    "sg:province":"NY",
    "wof:name":"Custom Reloading Service",
    "wof:placetype":"venue"
},
  "geometry": {"coordinates":[-75.022993,44.910045],"type":"Point"}
}