{
  "type": "Feature",
  "properties": {
    "addr:full":"591 Co Rd 7 Clifton Springs NY 14432",
    "addr:housenumber":"591",
    "addr:postcode":"14432",
    "addr:street":"Co Rd 7",
    "iso:country":"US",
    "sg:address":"591 Co Rd 7",
    "sg:city":"Clifton Springs",
    "sg:classifiers":[
        {
            "category":"Manufacturing",
            "subcategory":"Tools & Machinery",
            "type":"Manufacturing & Wholesale Goods"
        }
    ],
    "sg:phone":"+1 315 462 3533",
    "sg:postcode":"14432",
    "sg:province":"NY",
    "sg:tags":[
        "die",
        "maker"
    ],
    "wof:name":"J T Tool & Die",
    "wof:placetype":"venue"
},
  "geometry": {"coordinates":[-77.176134,43.007562],"type":"Point"}
}