{
  "type": "Feature",
  "properties": {
    "iso:country":"US",
    "sg:address":"4221 Sprague Ave",
    "sg:city":"Hamburg",
    "sg:classifiers":[
        {
            "category":"Shopping",
            "subcategory":"Florist",
            "type":"Retail Goods"
        }
    ],
    "sg:phone":"+1   ",
    "sg:postcode":"14075",
    "sg:province":"NY",
    "wof:name":"David J Flowers Construction",
    "wof:placetype":"venue"
},
  "geometry": {"coordinates":[-78.822716,42.749177],"type":"Point"}
}