{
  "type": "Feature",
  "properties": {
    "addr:full":"289 Lewis Ave Brooklyn NY 11221",
    "addr:housenumber":"289",
    "addr:postcode":"11221",
    "addr:street":"Lewis Ave",
    "iso:country":"US",
    "sg:address":"289 Lewis Ave",
    "sg:city":"Brooklyn",
    "sg:classifiers":[
        {
            "category":"Social Services",
            "subcategory":"Child Care",
            "type":"Services"
        },
        {
            "category":"Organizations",
            "subcategory":"Religious Organization",
            "type":"Services"
        }
    ],
    "sg:phone":"+1 718 452 5970",
    "sg:postcode":"11221",
    "sg:province":"NY",
    "sg:tags":[
        "day",
        "church"
    ],
    "wof:name":"Cornerstone Day Care Center",
    "wof:placetype":"venue"
},
  "geometry": {"coordinates":[-73.93560100000001,40.686276],"type":"Point"}
}