{
  "type": "Feature",
  "properties": {
    "iso:country":"US",
    "sg:address":"284 Troy Schenectady Rd",
    "sg:city":"Latham",
    "sg:classifiers":[
        {
            "category":"Shopping",
            "subcategory":"Clothing, Apparel, & Fashions",
            "type":"Retail Goods"
        }
    ],
    "sg:phone":"+1 518 220 9244",
    "sg:postcode":"12110",
    "sg:province":"NY",
    "sg:tags":[
        "uniform"
    ],
    "wof:name":"Smith Industries School Unifrm",
    "wof:placetype":"venue"
},
  "geometry": {"coordinates":[-73.74109300000001,42.742107],"type":"Point"}
}