{
  "type": "Feature",
  "properties": {
    "iso:country":"US",
    "sg:address":"4816 8th Avenue",
    "sg:city":"Brooklyn",
    "sg:classifiers":[
        {
            "category":"Shopping",
            "subcategory":"Mobile Phones",
            "type":"Retail Goods"
        }
    ],
    "sg:phone":"+1 718 438 2300",
    "sg:postcode":"11220",
    "sg:province":"NY",
    "wof:name":"Pcc Wireless",
    "wof:placetype":"venue"
},
  "geometry": {"coordinates":[-74.002987,40.641987],"type":"Point"}
}