{
  "type": "Feature",
  "properties": {
    "iso:country":"US",
    "sg:address":"2100 Highland Ave",
    "sg:city":"Rochester",
    "sg:classifiers":[
        {
            "category":"Manufacturing",
            "subcategory":"Printing",
            "type":"Manufacturing & Wholesale Goods"
        }
    ],
    "sg:phone":"+1   ",
    "sg:postcode":"14610",
    "sg:province":"NY",
    "sg:tags":[
        "work"
    ],
    "wof:name":"Arrow Services",
    "wof:placetype":"venue"
},
  "geometry": {"coordinates":[-77.559192,43.136897],"type":"Point"}
}