{
  "type": "Feature",
  "properties": {
    "addr:full":"300 W 74 St New York NY 10023",
    "addr:housenumber":"300",
    "addr:postcode":"10023",
    "addr:street":"W 74 St",
    "iso:country":"US",
    "sg:address":"300 W 74 St",
    "sg:city":"New York",
    "sg:classifiers":[
        {
            "category":"Retail",
            "subcategory":"Auto Repair",
            "type":"Services"
        }
    ],
    "sg:phone":"+1 212 547 6467",
    "sg:postcode":"10023",
    "sg:province":"NY",
    "sg:tags":[
        "wrecker"
    ],
    "wof:name":"AAA Emergency Towing",
    "wof:placetype":"venue"
},
  "geometry": {"coordinates":[-73.985174,40.781817],"type":"Point"}
}