{
  "type": "Feature",
  "properties": {
    "addr:full":"635 South St Garden City NY 11530",
    "addr:housenumber":"635",
    "addr:postcode":"11530",
    "addr:street":"South St",
    "iso:country":"US",
    "sg:address":"635 South St",
    "sg:city":"Garden City",
    "sg:classifiers":[
        {
            "category":"Recreation",
            "type":"Entertainment"
        }
    ],
    "sg:phone":"+1   ",
    "sg:postcode":"11530",
    "sg:province":"NY",
    "wof:name":"Bulldog Boxing",
    "wof:placetype":"venue"
},
  "geometry": {"coordinates":[-73.606482,40.734886],"type":"Point"}
}