{
  "type": "Feature",
  "properties": {
    "iso:country":"US",
    "sg:address":"11145 Main St",
    "sg:city":"Clarence",
    "sg:classifiers":[
        {
            "category":"Home & Garden",
            "subcategory":"Carpets & Floor Coverings",
            "type":"Retail Goods"
        }
    ],
    "sg:phone":"+1 716 759 2260",
    "sg:postcode":"14031",
    "sg:province":"NY",
    "sg:tags":[
        "rug"
    ],
    "sg:website":"http://www.kellyschultz.com",
    "wof:name":"Schultz Klly Antq Orental Rugs",
    "wof:placetype":"venue"
},
  "geometry": {"coordinates":[-78.571681,42.984071],"type":"Point"}
}