{
  "type": "Feature",
  "properties": {
    "addr:full":"76 Beadel St Brooklyn NY 11222",
    "addr:housenumber":"76",
    "addr:postcode":"11222",
    "addr:street":"Beadel St",
    "iso:country":"US",
    "sg:address":"76 Beadel St",
    "sg:city":"Brooklyn",
    "sg:classifiers":[
        {
            "category":"Building & Trades",
            "subcategory":"Construction",
            "type":"Services"
        }
    ],
    "sg:phone":"+1 718 599 2244",
    "sg:postcode":"11222",
    "sg:province":"NY",
    "sg:tags":[
        "contractor"
    ],
    "wof:name":"Agc Contractors",
    "wof:placetype":"venue"
},
  "geometry": {"coordinates":[-73.937629,40.721467],"type":"Point"}
}