{
  "type": "Feature",
  "properties": {
    "addr:full":"2014 Hering Ave Bronx NY 10461",
    "addr:housenumber":"2014",
    "addr:postcode":"10461",
    "addr:street":"Hering Ave",
    "iso:country":"US",
    "sg:address":"2014 Hering Ave",
    "sg:city":"Bronx",
    "sg:classifiers":[
        {
            "category":"Wholesale",
            "subcategory":"Scrap",
            "type":"Manufacturing & Wholesale Goods"
        }
    ],
    "sg:phone":"+1 718 518 9800",
    "sg:postcode":"10461",
    "sg:province":"NY",
    "sg:tags":[
        "recycling",
        "center"
    ],
    "wof:name":"PMC Recycling Corp",
    "wof:placetype":"venue"
},
  "geometry": {"coordinates":[-73.853298,40.855701],"type":"Point"}
}