{
  "type": "Feature",
  "properties": {
    "addr:full":"126 N Main St Liberty NY 12754",
    "addr:housenumber":"126",
    "addr:postcode":"12754",
    "addr:street":"N Main St",
    "iso:country":"US",
    "sg:address":"126 N Main St",
    "sg:city":"Liberty",
    "sg:classifiers":[
        {
            "category":"Professional",
            "subcategory":"Lawyer & Legal Services",
            "type":"Services"
        }
    ],
    "sg:phone":"+1 845 292 0000",
    "sg:postcode":"12754",
    "sg:province":"NY",
    "sg:tags":[
        "attorney",
        "practice",
        "plan"
    ],
    "wof:name":"Law Office Of Sergio A Saravia Immigration",
    "wof:placetype":"venue"
},
  "geometry": {"coordinates":[-74.746933,41.801472],"type":"Point"}
}