{
  "type": "Feature",
  "properties": {
    "iso:country":"US",
    "sg:address":"110 Saw Mill River Rd",
    "sg:city":"Yonkers",
    "sg:classifiers":[
        {
            "category":"Retail",
            "subcategory":"Auto Rental",
            "type":"Services"
        },
        {
            "category":"Building & Trades",
            "subcategory":"Equipment Rental",
            "type":"Services"
        },
        {
            "category":"Retail",
            "subcategory":"Storage",
            "type":"Services"
        }
    ],
    "sg:phone":"+1 914 476 8358",
    "sg:postcode":"10701",
    "sg:province":"NY",
    "sg:tags":[
        "truck",
        "moving-self",
        "leasing",
        "yard",
        "store"
    ],
    "wof:name":"Hertz Truck Rental System",
    "wof:placetype":"venue"
},
  "geometry": {"coordinates":[-73.88171,40.9422],"type":"Point"}
}