{
  "type": "Feature",
  "properties": {
    "addr:full":"350 Fordham Pl Bronx NY 10464",
    "addr:housenumber":"350",
    "addr:postcode":"10464",
    "addr:street":"Fordham Pl",
    "iso:country":"US",
    "sg:address":"350 Fordham Pl",
    "sg:city":"Bronx",
    "sg:classifiers":[
        {
            "category":"Autos & Motor Vehicles",
            "subcategory":"Boat Sales",
            "type":"Retail Goods"
        },
        {
            "category":"Recreation",
            "subcategory":"Marina",
            "type":"Entertainment"
        }
    ],
    "sg:phone":"+1 718 885 9802",
    "sg:postcode":"10464",
    "sg:province":"NY",
    "sg:tags":[
        "operation",
        "dealer",
        "sales"
    ],
    "wof:name":"Barron's Boat Yard",
    "wof:placetype":"venue"
},
  "geometry": {"coordinates":[-73.783326,40.848115],"type":"Point"}
}