{
  "type": "Feature",
  "properties": {
    "addr:full":"6715 Bay Pkwy Brooklyn NY 11204",
    "addr:housenumber":"6715",
    "addr:postcode":"11204",
    "addr:street":"Bay Pkwy",
    "iso:country":"US",
    "sg:address":"6715 Bay Pkwy",
    "sg:city":"Brooklyn",
    "sg:classifiers":[
        {
            "category":"Manufacturing",
            "subcategory":"Printing",
            "type":"Manufacturing & Wholesale Goods"
        }
    ],
    "sg:phone":"+1 718 259 4820",
    "sg:postcode":"11204",
    "sg:province":"NY",
    "sg:tags":[
        "newspaper"
    ],
    "wof:name":"EMD",
    "wof:placetype":"venue"
},
  "geometry": {"coordinates":[-73.982913,40.61241],"type":"Point"}
}