{
  "type": "Feature",
  "properties": {
    "addr:full":"59 Colony Dr Holbrook NY 11741",
    "addr:housenumber":"59",
    "addr:postcode":"11741",
    "addr:street":"Colony Dr",
    "iso:country":"US",
    "sg:address":"59 Colony Dr",
    "sg:city":"Holbrook",
    "sg:classifiers":[
        {
            "category":"Insurance",
            "subcategory":"Insurance Agent",
            "type":"Services"
        }
    ],
    "sg:phone":"+1 631 499 3399",
    "sg:postcode":"11741",
    "sg:province":"NY",
    "wof:name":"American Fire Adjustment Co",
    "wof:placetype":"venue"
},
  "geometry": {"coordinates":[-73.060079,40.806677],"type":"Point"}
}