{
  "type": "Feature",
  "properties": {
    "iso:country":"US",
    "sg:address":"439 5th Ave",
    "sg:city":"Pelham",
    "sg:classifiers":[
        {
            "category":"Autos & Motor Vehicles",
            "subcategory":"Fuel & Gas Station",
            "type":"Retail Goods"
        }
    ],
    "sg:phone":"+1 914 738 1572",
    "sg:postcode":"10803",
    "sg:province":"NY",
    "sg:tags":[
        "station",
        "oil"
    ],
    "wof:name":"M & M Automotive Svce",
    "wof:placetype":"venue"
},
  "geometry": {"coordinates":[-73.805824,40.918618],"type":"Point"}
}