{
  "type": "Feature",
  "properties": {
    "iso:country":"US",
    "sg:address":"512 Fashion Ave",
    "sg:city":"New York",
    "sg:classifiers":[
        {
            "category":"Professional",
            "subcategory":"Accounting & Tax Preparation",
            "type":"Services"
        }
    ],
    "sg:phone":"+1 212 354 0920",
    "sg:postcode":"10018",
    "sg:province":"NY",
    "sg:tags":[
        "accountant"
    ],
    "wof:name":"Bronsteen Edw & Co CPA",
    "wof:placetype":"venue"
},
  "geometry": {"coordinates":[-73.98908299999999,40.753138],"type":"Point"}
}