{
  "type": "Feature",
  "properties": {
    "addr:full":"1901 State St Schenectady NY 12304",
    "addr:housenumber":"1901",
    "addr:postcode":"12304",
    "addr:street":"State St",
    "iso:country":"US",
    "sg:address":"1901 State St",
    "sg:city":"Schenectady",
    "sg:classifiers":[
        {
            "category":"Wholesale",
            "subcategory":"Furniture",
            "type":"Manufacturing & Wholesale Goods"
        }
    ],
    "sg:phone":"+1 518 346 7110",
    "sg:postcode":"12304",
    "sg:province":"NY",
    "wof:name":"T M C Contract Furnshng",
    "wof:placetype":"venue"
},
  "geometry": {"coordinates":[-73.900278,42.777184],"type":"Point"}
}