{
  "type": "Feature",
  "properties": {
    "iso:country":"US",
    "sg:address":"900 8th Avenue",
    "sg:city":"New York",
    "sg:classifiers":[
        {
            "category":"Real Estate",
            "subcategory":"Real Estate Operator",
            "type":"Services"
        }
    ],
    "sg:phone":"+1 212 765 6272",
    "sg:postcode":"10019",
    "sg:province":"NY",
    "sg:tags":[
        "apartment"
    ],
    "wof:name":"Marc 900 8th Avenue",
    "wof:placetype":"venue"
},
  "geometry": {"coordinates":[-73.984263,40.764792],"type":"Point"}
}