{
  "type": "Feature",
  "properties": {
    "addr:full":"615 E 6th St Manhattan NY 10009",
    "addr:housenumber":"615",
    "addr:postcode":"10009",
    "addr:street":"E 6Th St",
    "iso:country":"US",
    "sg:address":"615 E 6th St",
    "sg:city":"Manhattan",
    "sg:classifiers":[
        {
            "category":"Arts & Performance",
            "subcategory":"Arts Center",
            "type":"Entertainment"
        }
    ],
    "sg:phone":"+1 646 233 3546",
    "sg:postcode":"10009",
    "sg:province":"NY",
    "wof:name":"GigMaven",
    "wof:placetype":"venue"
},
  "geometry": {"coordinates":[-73.980605,40.724284],"type":"Point"}
}