{
  "type": "Feature",
  "properties": {
    "addr:full":"43 New Scotland Ave Albany NY 12208",
    "addr:housenumber":"43",
    "addr:postcode":"12208",
    "addr:street":"New Scotland Ave",
    "iso:country":"US",
    "sg:address":"43 New Scotland Ave",
    "sg:city":"Albany",
    "sg:classifiers":[
        {
            "category":"Health Services",
            "subcategory":"Doctor",
            "type":"Services"
        }
    ],
    "sg:phone":"+1 518 262 5640",
    "sg:postcode":"12208",
    "sg:province":"NY",
    "sg:tags":[
        "physician",
        "surgeon"
    ],
    "wof:name":"Albany Vascular Surgeons",
    "wof:placetype":"venue"
},
  "geometry": {"coordinates":[-73.774507,42.652912],"type":"Point"}
}