{
  "type": "Feature",
  "properties": {
    "addr:full":"94 E 1 St New York NY 10009",
    "addr:housenumber":"94;1",
    "addr:postcode":"10009",
    "addr:street":"E;St",
    "iso:country":"US",
    "sg:address":"94 E 1 St",
    "sg:city":"New York",
    "sg:classifiers":[
        {
            "category":"Social Services",
            "type":"Services"
        }
    ],
    "sg:phone":"+1 212 982 5130",
    "sg:postcode":"10009",
    "sg:province":"NY",
    "sg:tags":[
        "senior",
        "citizen"
    ],
    "wof:name":"Meltzer Senior Ctr",
    "wof:placetype":"venue"
},
  "geometry": {"coordinates":[-73.98738,40.72296],"type":"Point"}
}