{
  "type": "Feature",
  "properties": {
    "addr:full":"5502 Church Ave Brooklyn NY 11203",
    "addr:housenumber":"5502",
    "addr:postcode":"11203",
    "addr:street":"Church Ave",
    "iso:country":"US",
    "sg:address":"5502 Church Ave",
    "sg:city":"Brooklyn",
    "sg:classifiers":[
        {
            "category":"Shopping",
            "subcategory":"Beauty & Cosmetics",
            "type":"Retail Goods"
        }
    ],
    "sg:phone":"+1   ",
    "sg:postcode":"11203",
    "sg:province":"NY",
    "sg:tags":[
        "supply"
    ],
    "wof:name":"SDA Health and Beauty Supply",
    "wof:placetype":"venue"
},
  "geometry": {"coordinates":[-73.92465,40.652424],"type":"Point"}
}