{
  "type": "Feature",
  "properties": {
    "addr:full":"2297 Bailey Ave Buffalo NY 14211",
    "addr:housenumber":"2297",
    "addr:postcode":"14211",
    "addr:street":"Bailey Ave",
    "iso:country":"US",
    "sg:address":"2297 Bailey Ave",
    "sg:city":"Buffalo",
    "sg:classifiers":[
        {
            "category":"Autos & Motor Vehicles",
            "subcategory":"Automobile Sales",
            "type":"Retail Goods"
        }
    ],
    "sg:phone":"+1 716 897 5095",
    "sg:postcode":"14211",
    "sg:province":"NY",
    "sg:tags":[
        "car",
        "dealer"
    ],
    "wof:name":"Carmaxx II",
    "wof:placetype":"venue"
},
  "geometry": {"coordinates":[-78.813619,42.91738],"type":"Point"}
}