{
  "type": "Feature",
  "properties": {
    "iso:country":"US",
    "sg:address":"22 Clifton Country Rd",
    "sg:city":"Clifton Park",
    "sg:classifiers":[
        {
            "category":"Food & Beverages",
            "subcategory":"Specialty",
            "type":"Retail Goods"
        }
    ],
    "sg:phone":"+1 518 371 8799",
    "sg:postcode":"12065",
    "sg:province":"NY",
    "sg:tags":[
        "health",
        "diet"
    ],
    "wof:name":"GNC",
    "wof:placetype":"venue"
},
  "geometry": {"coordinates":[-73.78090400000001,42.860468],"type":"Point"}
}