{
  "type": "Feature",
  "properties": {
    "iso:country":"US",
    "sg:address":"852 E New York Ave",
    "sg:city":"Brooklyn",
    "sg:classifiers":[
        {
            "category":"Retail",
            "subcategory":"Laundry & Dry Cleaning",
            "type":"Services"
        }
    ],
    "sg:phone":"+1 718 778 0228",
    "sg:postcode":"11203",
    "sg:province":"NY",
    "sg:tags":[
        "cleaner"
    ],
    "wof:name":"Han's Dry Cleaners Inc",
    "wof:placetype":"venue"
},
  "geometry": {"coordinates":[-73.93710299999999,40.6623],"type":"Point"}
}