{
  "type": "Feature",
  "properties": {
    "iso:country":"US",
    "sg:address":"162 Aldrich St",
    "sg:city":"Gowanda",
    "sg:classifiers":[
        {
            "category":"Building & Trades",
            "subcategory":"Construction",
            "type":"Services"
        }
    ],
    "sg:phone":"+1 716 532 2317",
    "sg:postcode":"14070",
    "sg:province":"NY",
    "sg:tags":[
        "contractor"
    ],
    "wof:name":"B & C Pressure Washing",
    "wof:placetype":"venue"
},
  "geometry": {"coordinates":[-78.94159399999999,42.465497],"type":"Point"}
}