{
  "type": "Feature",
  "properties": {
    "addr:full":"806 54th St Brooklyn NY 11220",
    "addr:housenumber":"806",
    "addr:postcode":"11220",
    "addr:street":"54Th St",
    "iso:country":"US",
    "sg:address":"806 54th St",
    "sg:city":"Brooklyn",
    "sg:classifiers":[
        {
            "category":"Food & Beverages",
            "subcategory":"Specialty",
            "type":"Retail Goods"
        }
    ],
    "sg:phone":"+1   ",
    "sg:postcode":"11220",
    "sg:province":"NY",
    "sg:tags":[
        "health"
    ],
    "wof:name":"Zhag Zongai",
    "wof:placetype":"venue"
},
  "geometry": {"coordinates":[-74.003987,40.637569],"type":"Point"}
}