{
  "type": "Feature",
  "properties": {
    "iso:country":"US",
    "sg:address":"1460 Sheridan Expy",
    "sg:city":"Bronx",
    "sg:classifiers":[
        {
            "category":"Wholesale",
            "subcategory":"Auto Parts",
            "type":"Manufacturing & Wholesale Goods"
        }
    ],
    "sg:phone":"+1 718 589 6014",
    "sg:postcode":"10459",
    "sg:province":"NY",
    "sg:tags":[
        "automobile",
        "wrecking"
    ],
    "wof:name":"Hunts Points Auto Wreckers Inc",
    "wof:placetype":"venue"
},
  "geometry": {"coordinates":[-73.885515,40.828399],"type":"Point"}
}