{
  "type": "Feature",
  "properties": {
    "iso:country":"US",
    "sg:address":"180 Varick St., Suite 1514",
    "sg:city":"New York",
    "sg:classifiers":[
        {
            "category":"Professional",
            "subcategory":"Computer Services",
            "type":"Services"
        }
    ],
    "sg:phone":"+1 415 263 7700",
    "sg:postcode":"10014",
    "sg:province":"NY",
    "sg:website":"http://www.fluid.com",
    "wof:name":"Fluid",
    "wof:placetype":"venue"
},
  "geometry": {"coordinates":[-74.005391,40.72756],"type":"Point"}
}