{
  "type": "Feature",
  "properties": {
    "addr:full":"26 Wellesley Ln Hicksville NY 11801",
    "addr:housenumber":"26",
    "addr:postcode":"11801",
    "addr:street":"Wellesley Ln",
    "iso:country":"US",
    "sg:address":"26 Wellesley Ln",
    "sg:city":"Hicksville",
    "sg:classifiers":[
        {
            "category":"Utilities",
            "subcategory":"Mobile Phone",
            "type":"Services"
        }
    ],
    "sg:phone":"+1   ",
    "sg:postcode":"11801",
    "sg:province":"NY",
    "sg:tags":[
        "communication",
        "computer",
        "radiotelephone",
        "programing",
        "custom"
    ],
    "wof:name":"ABG Communications Inc",
    "wof:placetype":"venue"
},
  "geometry": {"coordinates":[-73.503108,40.779008],"type":"Point"}
}