{
  "type": "Feature",
  "properties": {
    "addr:full":"58 2nd Ave Brooklyn NY 11215",
    "addr:housenumber":"58",
    "addr:postcode":"11215",
    "addr:street":"2Nd Ave",
    "iso:country":"US",
    "sg:address":"58 2nd Ave",
    "sg:city":"Brooklyn",
    "sg:classifiers":[
        {
            "category":"Wholesale",
            "subcategory":"Durable Goods & Equipment",
            "type":"Manufacturing & Wholesale Goods"
        }
    ],
    "sg:phone":"+1 718 369 4160",
    "sg:postcode":"11215",
    "sg:province":"NY",
    "sg:tags":[
        "marketing",
        "sport",
        "design",
        "bag",
        "luggage"
    ],
    "wof:name":"DYNAMIC CLASSICS",
    "wof:placetype":"venue"
},
  "geometry": {"coordinates":[-73.992861,40.673373],"type":"Point"}
}