{
  "type": "Feature",
  "properties": {
    "addr:full":"1239 Broadway Hewlett NY 11557",
    "addr:housenumber":"1239",
    "addr:postcode":"11557",
    "addr:street":"Broadway",
    "iso:country":"US",
    "sg:address":"1239 Broadway",
    "sg:city":"Hewlett",
    "sg:classifiers":[
        {
            "category":"Food & Beverages",
            "subcategory":"Bakery",
            "type":"Retail Goods"
        }
    ],
    "sg:phone":"+1 516 612 3102",
    "sg:postcode":"11557",
    "sg:province":"NY",
    "sg:tags":[
        "sandwich"
    ],
    "sg:website":"www.subway.com",
    "wof:name":"Subway Sandwiches",
    "wof:placetype":"venue"
},
  "geometry": {"coordinates":[-73.70182699999999,40.637504],"type":"Point"}
}