{
  "type": "Feature",
  "properties": {
    "iso:country":"US",
    "sg:address":"1 Pinetop Dr",
    "sg:city":"Central Islip",
    "sg:classifiers":[
        {
            "category":"Building & Trades",
            "subcategory":"Construction",
            "type":"Services"
        }
    ],
    "sg:phone":"+1 631 234 9279",
    "sg:postcode":"11722",
    "sg:province":"NY",
    "sg:tags":[
        "house"
    ],
    "wof:name":"P Artusa Construction",
    "wof:placetype":"venue"
},
  "geometry": {"coordinates":[-73.21326999999999,40.793689],"type":"Point"}
}