{
  "type": "Feature",
  "properties": {
    "addr:full":"9 Broadway Amityville NY 11701",
    "addr:housenumber":"9",
    "addr:postcode":"11701",
    "addr:street":"Broadway",
    "iso:country":"US",
    "sg:address":"9 Broadway",
    "sg:city":"Amityville",
    "sg:classifiers":[
        {
            "category":"Professional",
            "type":"Services"
        }
    ],
    "sg:phone":"+1 631 691 6372",
    "sg:postcode":"11701",
    "sg:province":"NY",
    "sg:tags":[
        "establishment"
    ],
    "wof:name":"Ten Mountain Adventures",
    "wof:placetype":"venue"
},
  "geometry": {"coordinates":[-73.41612600000001,40.672569],"type":"Point"}
}