{
  "type": "Feature",
  "properties": {
    "iso:country":"US",
    "sg:address":"292 Madison Ave",
    "sg:city":"New York",
    "sg:classifiers":[
        {
            "category":"Professional",
            "subcategory":"Lawyer & Legal Services",
            "type":"Services"
        },
        {
            "category":"Government",
            "subcategory":"Court House",
            "type":"Public Place"
        }
    ],
    "sg:phone":"+1 212 532 0050",
    "sg:postcode":"10017",
    "sg:province":"NY",
    "sg:tags":[
        "counsel",
        "attorney"
    ],
    "wof:name":"Stanley Cembalest",
    "wof:placetype":"venue"
},
  "geometry": {"coordinates":[-73.980048,40.75179],"type":"Point"}
}