{
  "type": "Feature",
  "properties": {
    "iso:country":"US",
    "sg:address":"97 Guerin Dr",
    "sg:city":"Montgomery",
    "sg:classifiers":[
        {
            "category":"Social Services",
            "subcategory":"Child Care",
            "type":"Services"
        }
    ],
    "sg:phone":"+1 845 457 1041",
    "sg:postcode":"12549",
    "sg:province":"NY",
    "sg:tags":[
        "day"
    ],
    "wof:name":"Little Guardian Family Child Care",
    "wof:placetype":"venue"
},
  "geometry": {"coordinates":[-74.227097,41.515202],"type":"Point"}
}