{
  "type": "Feature",
  "properties": {
    "iso:country":"US",
    "sg:address":"669 Lakeside Dr",
    "sg:city":"Baldwin",
    "sg:classifiers":[
        {
            "category":"Government",
            "subcategory":"Fire Station",
            "type":"Public Place"
        }
    ],
    "sg:phone":"+1 516 623 3822",
    "sg:postcode":"11510",
    "sg:province":"NY",
    "sg:tags":[
        "protection"
    ],
    "wof:name":"Baldwin Ffire Dept Hose Co",
    "wof:placetype":"venue"
},
  "geometry": {"coordinates":[-73.616287,40.648983],"type":"Point"}
}