{
  "type": "Feature",
  "properties": {
    "addr:full":"322 Bear St Syracuse NY 13208",
    "addr:housenumber":"322",
    "addr:postcode":"13208",
    "addr:street":"Bear St",
    "iso:country":"US",
    "sg:address":"322 Bear St",
    "sg:city":"Syracuse",
    "sg:classifiers":[
        {
            "category":"Education",
            "subcategory":"College",
            "type":"Public Place"
        }
    ],
    "sg:phone":"+1 315 470 6692",
    "sg:postcode":"13208",
    "sg:province":"NY",
    "wof:name":"College Envrmental Science For",
    "wof:placetype":"venue"
},
  "geometry": {"coordinates":[-76.161316,43.069449],"type":"Point"}
}