{
  "type": "Feature",
  "properties": {
    "addr:full":"99 Church Ave Brooklyn NY 11218",
    "addr:housenumber":"99",
    "addr:postcode":"11218",
    "addr:street":"Church Ave",
    "iso:country":"US",
    "sg:address":"99 Church Ave",
    "sg:city":"Brooklyn",
    "sg:classifiers":[
        {
            "category":"Shopping",
            "subcategory":"Discount & Variety Stores",
            "type":"Retail Goods"
        }
    ],
    "sg:phone":"+1 718 686 6380",
    "sg:postcode":"11218",
    "sg:province":"NY",
    "wof:name":"Church Discount",
    "wof:placetype":"venue"
},
  "geometry": {"coordinates":[-73.98042,40.642385],"type":"Point"}
}