{
  "type": "Feature",
  "properties": {
    "iso:country":"US",
    "sg:address":"8606 Vieley Rd",
    "sg:city":"Campbell",
    "sg:classifiers":[
        {
            "category":"Home & Garden",
            "subcategory":"Home Furnishings",
            "type":"Retail Goods"
        }
    ],
    "sg:phone":"+1 607 527 8767",
    "sg:postcode":"14821",
    "sg:province":"NY",
    "sg:tags":[
        "draperies",
        "curtain",
        "window",
        "treatment"
    ],
    "wof:name":"Nell's Custom Draperies",
    "wof:placetype":"venue"
},
  "geometry": {"coordinates":[-77.191033,42.204404],"type":"Point"}
}