{
  "type": "Feature",
  "properties": {
    "addr:full":"1481 Weaver St Scarsdale NY 10583",
    "addr:housenumber":"1481",
    "addr:postcode":"10583",
    "addr:street":"Weaver St",
    "iso:country":"US",
    "sg:address":"1481 Weaver St",
    "sg:city":"Scarsdale",
    "sg:classifiers":[
        {
            "category":"Ice Cream",
            "type":"Food & Drink"
        }
    ],
    "sg:menulink":"http://www.allmenus.com/ny/scarsdale/184220-cold-stone-creamery/menu/",
    "sg:phone":"+1 914 725 7007",
    "sg:postcode":"10583",
    "sg:province":"NY",
    "sg:tags":[
        "smoothy",
        "juice",
        "american"
    ],
    "wof:name":"Cold Stone Creamery",
    "wof:placetype":"venue"
},
  "geometry": {"coordinates":[-73.776224,40.98125],"type":"Point"}
}