{
  "type": "Feature",
  "properties": {
    "iso:country":"US",
    "sg:address":"687 Albany Ave",
    "sg:city":"Amityville",
    "sg:classifiers":[
        {
            "category":"Manufacturing",
            "subcategory":"Apparel",
            "type":"Manufacturing & Wholesale Goods"
        }
    ],
    "sg:phone":"+1   ",
    "sg:postcode":"11701",
    "sg:province":"NY",
    "sg:tags":[
        "mfg",
        "auto",
        "accessory",
        "racing",
        "suit"
    ],
    "wof:name":"Pit Stop Store",
    "wof:placetype":"venue"
},
  "geometry": {"coordinates":[-73.40218299999999,40.714213],"type":"Point"}
}