{
  "type": "Feature",
  "properties": {
    "addr:full":"169 Jerusalem Ave Hicksville NY 11801",
    "addr:housenumber":"169",
    "addr:postcode":"11801",
    "addr:street":"Jerusalem Ave",
    "iso:country":"US",
    "sg:address":"169 Jerusalem Ave",
    "sg:city":"Hicksville",
    "sg:classifiers":[
        {
            "category":"Education",
            "subcategory":"Library",
            "type":"Public Place"
        }
    ],
    "sg:phone":"+1 516 931 1417",
    "sg:postcode":"11801",
    "sg:province":"NY",
    "sg:tags":[
        "executive"
    ],
    "wof:name":"Hicksville Free Public Library",
    "wof:placetype":"venue"
},
  "geometry": {"coordinates":[-73.523202,40.761734],"type":"Point"}
}