{
  "type": "Feature",
  "properties": {
    "addr:full":"893 Birdsey Rd Waterloo NY 13165",
    "addr:housenumber":"893",
    "addr:postcode":"13165",
    "addr:street":"Birdsey Rd",
    "iso:country":"US",
    "sg:address":"893 Birdsey Rd",
    "sg:city":"Waterloo",
    "sg:classifiers":[
        {
            "category":"Building & Trades",
            "subcategory":"Construction",
            "type":"Services"
        }
    ],
    "sg:phone":"+1 315 539 0609",
    "sg:postcode":"13165",
    "sg:province":"NY",
    "sg:tags":[
        "home",
        "improvement"
    ],
    "wof:name":"Christina Construction Co",
    "wof:placetype":"venue"
},
  "geometry": {"coordinates":[-76.868208,42.981297],"type":"Point"}
}