{
  "type": "Feature",
  "properties": {
    "iso:country":"US",
    "sg:address":"5556 Main St",
    "sg:city":"Sodus",
    "sg:classifiers":[
        {
            "category":"Building & Trades",
            "subcategory":"Construction",
            "type":"Services"
        }
    ],
    "sg:phone":"+1 315 483 0234",
    "sg:postcode":"14551",
    "sg:province":"NY",
    "sg:tags":[
        "painter"
    ],
    "wof:name":"Todd Montondo Painting",
    "wof:placetype":"venue"
},
  "geometry": {"coordinates":[-77.024773,43.204092],"type":"Point"}
}