{
  "type": "Feature",
  "properties": {
    "iso:country":"US",
    "sg:address":"583 E 138th St",
    "sg:city":"Bronx",
    "sg:classifiers":[
        {
            "category":"Banks & Credit Unions",
            "subcategory":"Bank",
            "type":"Services"
        }
    ],
    "sg:phone":"+1 718 585 4739",
    "sg:postcode":"10454",
    "sg:province":"NY",
    "sg:tags":[
        "cashing",
        "check"
    ],
    "wof:name":"Rite Check Cashing Inc",
    "wof:placetype":"venue"
},
  "geometry": {"coordinates":[-73.91473499999999,40.805781],"type":"Point"}
}