{
  "type": "Feature",
  "properties": {
    "iso:country":"US",
    "sg:address":"2345 Broadway Suite #5",
    "sg:city":"New York",
    "sg:classifiers":[
        {
            "category":"Autos & Motor Vehicles",
            "subcategory":"Automobile Sales",
            "type":"Retail Goods"
        }
    ],
    "sg:phone":"+1 917 843 7014",
    "sg:postcode":"10024",
    "sg:province":"NY",
    "sg:tags":[
        "limo"
    ],
    "sg:website":"www.jfkairporttransportation.org",
    "wof:name":"JFK airport transportation",
    "wof:placetype":"venue"
},
  "geometry": {"coordinates":[-73.976585,40.788371],"type":"Point"}
}