{
  "type": "Feature",
  "properties": {
    "addr:full":"59 Midwood St Brooklyn NY 11225",
    "addr:housenumber":"59",
    "addr:postcode":"11225",
    "addr:street":"Midwood St",
    "iso:country":"US",
    "sg:address":"59 Midwood St",
    "sg:city":"Brooklyn",
    "sg:classifiers":[
        {
            "category":"Restaurant",
            "type":"Food & Drink"
        }
    ],
    "sg:phone":"+1   ",
    "sg:postcode":"11225",
    "sg:province":"NY",
    "sg:tags":[
        "caterer"
    ],
    "wof:name":"Felicias HRT Lght Live Soul",
    "wof:placetype":"venue"
},
  "geometry": {"coordinates":[-73.958258,40.659685],"type":"Point"}
}