{
  "type": "Feature",
  "properties": {
    "addr:full":"75 W 47th St Unit 1 New York NY 10036",
    "addr:housenumber":"75;1",
    "addr:postcode":"10036",
    "addr:street":"W 47Th St Unit",
    "iso:country":"US",
    "sg:address":"75 W 47th St Unit 1",
    "sg:city":"New York",
    "sg:classifiers":[
        {
            "category":"Shopping",
            "subcategory":"Jewelry",
            "type":"Retail Goods"
        }
    ],
    "sg:phone":"+1 212 575 8875",
    "sg:postcode":"10036",
    "sg:province":"NY",
    "wof:name":"Leon Zoland & Son Inc",
    "wof:placetype":"venue"
},
  "geometry": {"coordinates":[-73.981296,40.757926],"type":"Point"}
}