{
  "type": "Feature",
  "properties": {
    "iso:country":"US",
    "sg:address":"167 Phyllis Ave",
    "sg:city":"Buffalo",
    "sg:classifiers":[
        {
            "category":"Wholesale",
            "subcategory":"Apparel",
            "type":"Manufacturing & Wholesale Goods"
        }
    ],
    "sg:phone":"+1 716 835 6391",
    "sg:postcode":"14215",
    "sg:province":"NY",
    "sg:tags":[
        "clothing"
    ],
    "wof:name":"Jabez Fashions",
    "wof:placetype":"venue"
},
  "geometry": {"coordinates":[-78.809504,42.935746],"type":"Point"}
}