{
  "type": "Feature",
  "properties": {
    "iso:country":"US",
    "sg:address":"216 Bradhurst Ave",
    "sg:city":"New York",
    "sg:classifiers":[
        {
            "category":"Social Services",
            "subcategory":"Child Care",
            "type":"Services"
        }
    ],
    "sg:phone":"+1 212 862 3668",
    "sg:postcode":"10039",
    "sg:province":"NY",
    "sg:tags":[
        "day"
    ],
    "wof:name":"Pinckney Marvi",
    "wof:placetype":"venue"
},
  "geometry": {"coordinates":[-73.93936600000001,40.827791],"type":"Point"}
}