{
  "type": "Feature",
  "properties": {
    "addr:full":"1042 Union Rd Buffalo NY 14224",
    "addr:housenumber":"1042",
    "addr:postcode":"14224",
    "addr:street":"Union Rd",
    "iso:country":"US",
    "sg:address":"1042 Union Rd",
    "sg:city":"Buffalo",
    "sg:classifiers":[
        {
            "category":"Restaurant",
            "type":"Food & Drink"
        }
    ],
    "sg:phone":"+1 716 674 2222",
    "sg:postcode":"14224",
    "sg:province":"NY",
    "sg:tags":[
        "pizzeria",
        "pizza"
    ],
    "wof:name":"Brando's Pizza",
    "wof:placetype":"venue"
},
  "geometry": {"coordinates":[-78.753557,42.828137],"type":"Point"}
}