{
  "type": "Feature",
  "properties": {
    "iso:country":"US",
    "sg:address":"192 Monhagen Ave",
    "sg:city":"Middletown",
    "sg:classifiers":[
        {
            "category":"Retail",
            "subcategory":"Laundry & Dry Cleaning",
            "type":"Services"
        }
    ],
    "sg:phone":"+1 845 343 4126",
    "sg:postcode":"10940",
    "sg:province":"NY",
    "sg:website":"www.unitextile.com",
    "wof:name":"Unitex/Shared Textile Svc Inc",
    "wof:placetype":"venue"
},
  "geometry": {"coordinates":[-74.435571,41.454543],"type":"Point"}
}