{
  "type": "Feature",
  "properties": {
    "iso:country":"US",
    "sg:address":"14 Van Buren St",
    "sg:city":"Staten Island",
    "sg:classifiers":[
        {
            "category":"Building & Trades",
            "subcategory":"Construction",
            "type":"Services"
        }
    ],
    "sg:phone":"+1 718 447 4819",
    "sg:postcode":"10301",
    "sg:province":"NY",
    "wof:name":"Bruce Molinari",
    "wof:placetype":"venue"
},
  "geometry": {"coordinates":[-74.091562,40.645022],"type":"Point"}
}