{
  "type": "Feature",
  "properties": {
    "iso:country":"US",
    "sg:address":"4235 Bolivar Rd",
    "sg:city":"Wellsville",
    "sg:classifiers":[
        {
            "category":"Autos & Motor Vehicles",
            "subcategory":"Auto Supplies",
            "type":"Retail Goods"
        }
    ],
    "sg:phone":"+1 585 593 3720",
    "sg:postcode":"14895",
    "sg:province":"NY",
    "sg:tags":[
        "automobile",
        "parts"
    ],
    "wof:name":"Western Auto Store",
    "wof:placetype":"venue"
},
  "geometry": {"coordinates":[-77.970438,42.125664],"type":"Point"}
}