{
  "type": "Feature",
  "properties": {
    "addr:full":"4101 Kissena Blvd Flushing NY 11355",
    "addr:housenumber":"4101",
    "addr:postcode":"11355",
    "addr:street":"Kissena Blvd",
    "iso:country":"US",
    "sg:address":"4101 Kissena Blvd",
    "sg:city":"Flushing",
    "sg:classifiers":[
        {
            "category":"Restaurant",
            "type":"Food & Drink"
        }
    ],
    "sg:menulink":"http://www.allmenus.com/ny/queens/51963-pho-hoang/menu/",
    "sg:phone":"+1 718 762 6151",
    "sg:postcode":"11355",
    "sg:province":"NY",
    "sg:tags":[
        "asian",
        "vietnamese"
    ],
    "wof:name":"Pho Hoang",
    "wof:placetype":"venue"
},
  "geometry": {"coordinates":[-73.828536,40.757946],"type":"Point"}
}