{
  "type": "Feature",
  "properties": {
    "addr:full":"614 W 181st St New York NY 10033",
    "addr:housenumber":"614",
    "addr:postcode":"10033",
    "addr:street":"W 181St St",
    "iso:country":"US",
    "sg:address":"614 W 181st St",
    "sg:city":"New York",
    "sg:classifiers":[
        {
            "category":"Shopping",
            "subcategory":"Discount & Variety Stores",
            "type":"Retail Goods"
        }
    ],
    "sg:phone":"+1   ",
    "sg:postcode":"10033",
    "sg:province":"NY",
    "wof:name":"Gem Stores of W 181st Street",
    "wof:placetype":"venue"
},
  "geometry": {"coordinates":[-73.934639,40.849572],"type":"Point"}
}