{
  "type": "Feature",
  "properties": {
    "addr:full":"50 Weller Dr Rochester NY 14617",
    "addr:housenumber":"50",
    "addr:postcode":"14617",
    "addr:street":"Weller Dr",
    "iso:country":"US",
    "sg:address":"50 Weller Dr",
    "sg:city":"Rochester",
    "sg:classifiers":[
        {
            "category":"Personal",
            "subcategory":"Beauty Salon",
            "type":"Services"
        }
    ],
    "sg:phone":"+1   ",
    "sg:postcode":"14617",
    "sg:province":"NY",
    "sg:tags":[
        "shop",
        "merchandise"
    ],
    "wof:name":"Alla Skin Care Salon",
    "wof:placetype":"venue"
},
  "geometry": {"coordinates":[-77.602464,43.250121],"type":"Point"}
}