{
  "type": "Feature",
  "properties": {
    "addr:full":"5508 37th Ave Woodside NY 11377",
    "addr:housenumber":"5508",
    "addr:postcode":"11377",
    "addr:street":"37Th Ave",
    "iso:country":"US",
    "sg:address":"5508 37th Ave",
    "sg:city":"Woodside",
    "sg:classifiers":[
        {
            "category":"Retail",
            "subcategory":"Repair Shop",
            "type":"Services"
        }
    ],
    "sg:phone":"+1 718 482 7880",
    "sg:postcode":"11377",
    "sg:province":"NY",
    "sg:tags":[
        "reupholstery",
        "furniture"
    ],
    "wof:name":"Aramos Upholstery",
    "wof:placetype":"venue"
},
  "geometry": {"coordinates":[-73.906797,40.750535],"type":"Point"}
}