{
  "type": "Feature",
  "properties": {
    "iso:country":"US",
    "sg:address":"201 Audubon Ave",
    "sg:city":"New York",
    "sg:classifiers":[
        {
            "category":"Personal",
            "subcategory":"Barber",
            "type":"Services"
        }
    ],
    "sg:phone":"+1 212 740 1302",
    "sg:postcode":"10033",
    "sg:province":"NY",
    "wof:name":"Keyla Cris Unisex",
    "wof:placetype":"venue"
},
  "geometry": {"coordinates":[-73.935097,40.8451],"type":"Point"}
}