{
  "type": "Feature",
  "properties": {
    "iso:country":"US",
    "sg:address":"2308 N Ocean Ave",
    "sg:city":"Farmingville",
    "sg:classifiers":[
        {
            "category":"Shopping",
            "subcategory":"Pharmacy",
            "type":"Retail Goods"
        }
    ],
    "sg:phone":"+1 631 732 0633",
    "sg:postcode":"11738",
    "sg:province":"NY",
    "sg:tags":[
        "drugstore"
    ],
    "sg:website":"www.stopandshop.com",
    "wof:name":"Farmingville Prescription Centre",
    "wof:placetype":"venue"
},
  "geometry": {"coordinates":[-73.021202,40.831501],"type":"Point"}
}