{
  "type": "Feature",
  "properties": {
    "addr:full":"21 Garden St New York Mills NY 13417",
    "addr:housenumber":"21",
    "addr:postcode":"13417",
    "addr:street":"Garden St",
    "iso:country":"US",
    "sg:address":"21 Garden St",
    "sg:city":"New York Mills",
    "sg:classifiers":[
        {
            "category":"Organizations",
            "subcategory":"Community Association",
            "type":"Services"
        }
    ],
    "sg:phone":"+1 315 736 3416",
    "sg:postcode":"13417",
    "sg:province":"NY",
    "wof:name":"V F W Post 7393",
    "wof:placetype":"venue"
},
  "geometry": {"coordinates":[-75.296218,43.104301],"type":"Point"}
}