{
  "type": "Feature",
  "properties": {
    "addr:full":"2113 Frederick Douglass Blvd Harlem NY 10026",
    "addr:housenumber":"2113",
    "addr:postcode":"10026",
    "addr:street":"Frederick Douglass Blvd",
    "iso:country":"US",
    "sg:address":"2113 Frederick Douglass Blvd",
    "sg:city":"Harlem",
    "sg:classifiers":[
        {
            "category":"Restaurant",
            "type":"Food & Drink"
        }
    ],
    "sg:phone":"+1 212 300 4399",
    "sg:postcode":"10026",
    "sg:province":"NY",
    "sg:tags":[
        "seafood"
    ],
    "sg:website":"questansharlem.com/",
    "wof:name":"Questan's",
    "wof:placetype":"venue"
},
  "geometry": {"coordinates":[-73.956222,40.803283],"type":"Point"}
}