{
  "type": "Feature",
  "properties": {
    "iso:country":"US",
    "sg:address":"225 W 39 St",
    "sg:city":"New York",
    "sg:classifiers":[
        {
            "category":"Wholesale",
            "subcategory":"Apparel",
            "type":"Manufacturing & Wholesale Goods"
        }
    ],
    "sg:phone":"+1 212 925 4100",
    "sg:postcode":"10018",
    "sg:province":"NY",
    "sg:tags":[
        "textile",
        "woven"
    ],
    "wof:name":"Jomark Textiles",
    "wof:placetype":"venue"
},
  "geometry": {"coordinates":[-73.990613,40.755102],"type":"Point"}
}