{
  "type": "Feature",
  "properties": {
    "addr:full":"1 Roosevelt St Garden City NY 11530",
    "addr:housenumber":"1",
    "addr:postcode":"11530",
    "addr:street":"Roosevelt St",
    "iso:country":"US",
    "sg:address":"1 Roosevelt St",
    "sg:city":"Garden City",
    "sg:classifiers":[
        {
            "category":"Shopping",
            "subcategory":"Gifts & Souvenirs",
            "type":"Retail Goods"
        }
    ],
    "sg:phone":"+1 516 739 0089",
    "sg:postcode":"11530",
    "sg:province":"NY",
    "sg:tags":[
        "party",
        "supply"
    ],
    "wof:name":"Erawan Handicraft Co",
    "wof:placetype":"venue"
},
  "geometry": {"coordinates":[-73.681511,40.716905],"type":"Point"}
}