{
  "type": "Feature",
  "properties": {
    "iso:country":"US",
    "sg:address":"37 Harth Dr",
    "sg:city":"New Windsor",
    "sg:classifiers":[
        {
            "category":"Real Estate",
            "subcategory":"Real Estate Agent",
            "type":"Services"
        }
    ],
    "sg:phone":"+1 845 565 4363",
    "sg:postcode":"12553",
    "sg:province":"NY",
    "wof:name":"Skyer Real Estate",
    "wof:placetype":"venue"
},
  "geometry": {"coordinates":[-74.043421,41.470223],"type":"Point"}
}