{
  "type": "Feature",
  "properties": {
    "addr:full":"2252 E 27th St Brooklyn NY 11229",
    "addr:housenumber":"2252",
    "addr:postcode":"11229",
    "addr:street":"E 27Th St",
    "iso:country":"US",
    "sg:address":"2252 E 27th St",
    "sg:city":"Brooklyn",
    "sg:classifiers":[
        {
            "category":"Professional",
            "subcategory":"Computer Services",
            "type":"Services"
        }
    ],
    "sg:phone":"+1   ",
    "sg:postcode":"11229",
    "sg:province":"NY",
    "sg:tags":[
        "programing",
        "custom"
    ],
    "wof:name":"Quest Software Solutions",
    "wof:placetype":"venue"
},
  "geometry": {"coordinates":[-73.944142,40.596862],"type":"Point"}
}