{
  "type": "Feature",
  "properties": {
    "iso:country":"US",
    "sg:address":"190 Miner Street Rd",
    "sg:city":"Canton",
    "sg:classifiers":[
        {
            "category":"Organizations",
            "subcategory":"Professional Association",
            "type":"Services"
        },
        {
            "category":"Building & Trades",
            "subcategory":"Landscaping Services",
            "type":"Services"
        }
    ],
    "sg:phone":"+1 315 386 3574",
    "sg:postcode":"13617",
    "sg:province":"NY",
    "wof:name":"Fairview Cemetery Association",
    "wof:placetype":"venue"
},
  "geometry": {"coordinates":[-75.167565,44.581917],"type":"Point"}
}