{
  "type": "Feature",
  "properties": {
    "iso:country":"US",
    "sg:address":"99 3rd Ave",
    "sg:city":"Brentwood",
    "sg:classifiers":[
        {
            "category":"Sports & Exercise",
            "subcategory":"Gym",
            "type":"Entertainment"
        },
        {
            "category":"Sports & Exercise",
            "subcategory":"Sports Center",
            "type":"Entertainment"
        }
    ],
    "sg:phone":"+1 631 273 9543",
    "sg:postcode":"11717",
    "sg:province":"NY",
    "sg:tags":[
        "athletic"
    ],
    "wof:name":"Police Athletic League",
    "wof:placetype":"venue"
},
  "geometry": {"coordinates":[-73.25140399999999,40.7771],"type":"Point"}
}