{
  "type": "Feature",
  "properties": {
    "addr:full":"193 Genesee St Rochester NY 14611",
    "addr:housenumber":"193",
    "addr:postcode":"14611",
    "addr:street":"Genesee St",
    "iso:country":"US",
    "sg:address":"193 Genesee St",
    "sg:city":"Rochester",
    "sg:classifiers":[
        {
            "category":"Food & Beverages",
            "subcategory":"Groceries & Convenience Stores",
            "type":"Retail Goods"
        }
    ],
    "sg:phone":"+1 585 436 9960",
    "sg:postcode":"14611",
    "sg:province":"NY",
    "sg:tags":[
        "market"
    ],
    "wof:name":"Anjam Market",
    "wof:placetype":"venue"
},
  "geometry": {"coordinates":[-77.636127,43.14632],"type":"Point"}
}