{
  "type": "Feature",
  "properties": {
    "addr:full":"56 Lafayette Ave White Plains NY 10603",
    "addr:housenumber":"56",
    "addr:postcode":"10603",
    "addr:street":"Lafayette Ave",
    "iso:country":"US",
    "sg:address":"56 Lafayette Ave",
    "sg:city":"White Plains",
    "sg:classifiers":[
        {
            "category":"Communications",
            "subcategory":"Radio Station",
            "type":"Services"
        }
    ],
    "sg:phone":"+1 914 397 0127",
    "sg:postcode":"10603",
    "sg:province":"NY",
    "sg:tags":[
        "company",
        "broadcasting"
    ],
    "wof:name":"WXPK",
    "wof:placetype":"venue"
},
  "geometry": {"coordinates":[-73.771737,41.06473],"type":"Point"}
}