{
  "type": "Feature",
  "properties": {
    "addr:full":"50 Griffith St Buffalo NY 14212",
    "addr:housenumber":"50",
    "addr:postcode":"14212",
    "addr:street":"Griffith St",
    "iso:country":"US",
    "sg:address":"50 Griffith St",
    "sg:city":"Buffalo",
    "sg:classifiers":[
        {
            "category":"Recreation",
            "type":"Entertainment"
        }
    ],
    "sg:phone":"+1 716 896 2996",
    "sg:postcode":"14212",
    "sg:province":"NY",
    "sg:tags":[
        "parks"
    ],
    "wof:name":"Sloan Village Park",
    "wof:placetype":"venue"
},
  "geometry": {"coordinates":[-78.79202100000001,42.891838],"type":"Point"}
}