{
  "type": "Feature",
  "properties": {
    "addr:full":"1 E Market St Hyde Park NY 12538",
    "addr:housenumber":"1",
    "addr:postcode":"12538",
    "addr:street":"E Market St",
    "iso:country":"US",
    "sg:address":"1 E Market St",
    "sg:city":"Hyde Park",
    "sg:classifiers":[
        {
            "category":"Professional",
            "subcategory":"Business Services",
            "type":"Services"
        }
    ],
    "sg:phone":"+1   ",
    "sg:postcode":"12538",
    "sg:province":"NY",
    "wof:name":"Hyde Park Post Office",
    "wof:placetype":"venue"
},
  "geometry": {"coordinates":[-73.93198599999999,41.790892],"type":"Point"}
}