{
  "type": "Feature",
  "properties": {
    "addr:full":"435 New Karner Rd Albany NY 12205",
    "addr:housenumber":"435",
    "addr:postcode":"12205",
    "addr:street":"New Karner Rd",
    "iso:country":"US",
    "sg:address":"435 New Karner Rd",
    "sg:city":"Albany",
    "sg:classifiers":[
        {
            "category":"Social Services",
            "subcategory":"Job Training",
            "type":"Services"
        }
    ],
    "sg:phone":"+1 518 464 6250",
    "sg:postcode":"12205",
    "sg:province":"NY",
    "sg:tags":[
        "development",
        "placement"
    ],
    "sg:website":"www.career-connect.com",
    "wof:name":"Career Connections",
    "wof:placetype":"venue"
},
  "geometry": {"coordinates":[-73.846408,42.735392],"type":"Point"}
}