{
  "type": "Feature",
  "properties": {
    "iso:country":"US",
    "sg:address":"1281 Franklin Ave",
    "sg:city":"Bronx",
    "sg:classifiers":[
        {
            "category":"Organizations",
            "subcategory":"Religious Organization",
            "type":"Services"
        }
    ],
    "sg:phone":"+1 718 992 5668",
    "sg:postcode":"10456",
    "sg:province":"NY",
    "sg:tags":[
        "church"
    ],
    "wof:name":"Franklin Ave Baptist Church",
    "wof:placetype":"venue"
},
  "geometry": {"coordinates":[-73.90209900000001,40.831571],"type":"Point"}
}