{
  "type": "Feature",
  "properties": {
    "addr:full":"5959 Broadway Bronx NY 10463",
    "addr:housenumber":"5959",
    "addr:postcode":"10463",
    "addr:street":"Broadway",
    "iso:country":"US",
    "sg:address":"5959 Broadway",
    "sg:city":"Bronx",
    "sg:classifiers":[
        {
            "category":"Retail",
            "subcategory":"Repair Shop",
            "type":"Services"
        }
    ],
    "sg:phone":"+1 347 332 0745",
    "sg:postcode":"10463",
    "sg:province":"NY",
    "sg:tags":[
        "lock",
        "locksmith"
    ],
    "wof:name":"USA Locksmiths",
    "wof:placetype":"venue"
},
  "geometry": {"coordinates":[-73.89984,40.886537],"type":"Point"}
}