{
  "type": "Feature",
  "properties": {
    "iso:country":"US",
    "sg:address":"80 S Broadway Ave",
    "sg:city":"Nyack",
    "sg:classifiers":[
        {
            "category":"Food & Beverages",
            "subcategory":"Groceries & Convenience Stores",
            "type":"Retail Goods"
        },
        {
            "category":"Autos & Motor Vehicles",
            "subcategory":"Fuel & Gas Station",
            "type":"Retail Goods"
        }
    ],
    "sg:phone":"+1 845 358 1688",
    "sg:postcode":"10960",
    "sg:province":"NY",
    "sg:tags":[
        "station",
        "gasoline"
    ],
    "wof:name":"Faith Mini Mart Inc",
    "wof:placetype":"venue"
},
  "geometry": {"coordinates":[-73.919213,41.088058],"type":"Point"}
}