{
  "type": "Feature",
  "properties": {
    "addr:full":"9401 Ave L Brooklyn NY 11236",
    "addr:housenumber":"9401",
    "addr:postcode":"11236",
    "addr:street":"Ave L",
    "iso:country":"US",
    "sg:address":"9401 Ave L",
    "sg:city":"Brooklyn",
    "sg:classifiers":[
        {
            "category":"Food & Beverages",
            "subcategory":"Groceries & Convenience Stores",
            "type":"Retail Goods"
        }
    ],
    "sg:phone":"+1 718 272 1570",
    "sg:postcode":"11236",
    "sg:province":"NY",
    "sg:tags":[
        "grocer"
    ],
    "wof:name":"Deli Grocery",
    "wof:placetype":"venue"
},
  "geometry": {"coordinates":[-73.896868,40.637657],"type":"Point"}
}