{
  "type": "Feature",
  "properties": {
    "addr:full":"440 Gould Ave Depew NY 14043",
    "addr:housenumber":"440",
    "addr:postcode":"14043",
    "addr:street":"Gould Ave",
    "iso:country":"US",
    "sg:address":"440 Gould Ave",
    "sg:city":"Depew",
    "sg:classifiers":[
        {
            "category":"Autos & Motor Vehicles",
            "subcategory":"Auto Supplies",
            "type":"Retail Goods"
        }
    ],
    "sg:phone":"+1 716 685 4048",
    "sg:postcode":"14043",
    "sg:province":"NY",
    "sg:tags":[
        "tire"
    ],
    "wof:name":"Ziegler Tire",
    "wof:placetype":"venue"
},
  "geometry": {"coordinates":[-78.692572,42.905468],"type":"Point"}
}