{
  "type": "Feature",
  "properties": {
    "iso:country":"US",
    "sg:address":"112 Columbus Ave",
    "sg:city":"Rome",
    "sg:classifiers":[
        {
            "category":"Social Services",
            "type":"Services"
        }
    ],
    "sg:phone":"+1 315 339 9970",
    "sg:postcode":"13440",
    "sg:province":"NY",
    "wof:name":"Boys Grls CLB of Utica NY Inc",
    "wof:placetype":"venue"
},
  "geometry": {"coordinates":[-75.44220900000001,43.20597],"type":"Point"}
}