{
  "type": "Feature",
  "properties": {
    "iso:country":"US",
    "sg:address":"802 Grand St",
    "sg:city":"Brooklyn",
    "sg:classifiers":[
        {
            "category":"Retail",
            "subcategory":"Laundry & Dry Cleaning",
            "type":"Services"
        }
    ],
    "sg:phone":"+1 718 387 6033",
    "sg:postcode":"11211",
    "sg:province":"NY",
    "sg:tags":[
        "cleaners"
    ],
    "wof:name":"Y & Y Cleaners",
    "wof:placetype":"venue"
},
  "geometry": {"coordinates":[-73.94142100000001,40.711785],"type":"Point"}
}