{
  "type": "Feature",
  "properties": {
    "iso:country":"US",
    "sg:address":"897 Troy Schenectady Rd",
    "sg:city":"Latham",
    "sg:phone":"+1 518 785 5262",
    "sg:postcode":"12110",
    "sg:province":"NY",
    "wof:name":"Juliet House Of Brides",
    "wof:placetype":"venue"
},
  "geometry": {"coordinates":[-73.792997,42.761712],"type":"Point"}
}