{
  "type": "Feature",
  "properties": {
    "iso:country":"US",
    "sg:address":"12279 Oswego St",
    "sg:city":"Wolcott",
    "sg:classifiers":[
        {
            "category":"Restaurant",
            "type":"Food & Drink"
        }
    ],
    "sg:phone":"+1   ",
    "sg:postcode":"14590",
    "sg:province":"NY",
    "sg:tags":[
        "eating"
    ],
    "wof:name":"Ruthies Restaraunt",
    "wof:placetype":"venue"
},
  "geometry": {"coordinates":[-76.80644700000001,43.222423],"type":"Point"}
}