{
  "type": "Feature",
  "properties": {
    "addr:full":"1198 Wantagh Ave Wantagh NY 11793",
    "addr:housenumber":"1198",
    "addr:postcode":"11793",
    "addr:street":"Wantagh Ave",
    "iso:country":"US",
    "sg:address":"1198 Wantagh Ave",
    "sg:city":"Wantagh",
    "sg:classifiers":[
        {
            "category":"Retail",
            "subcategory":"Auto Repair",
            "type":"Services"
        }
    ],
    "sg:phone":"+1   ",
    "sg:postcode":"11793",
    "sg:province":"NY",
    "sg:tags":[
        "general"
    ],
    "wof:name":"Cherrywood Amoco",
    "wof:placetype":"venue"
},
  "geometry": {"coordinates":[-73.50719599999999,40.696262],"type":"Point"}
}