{
  "type": "Feature",
  "properties": {
    "iso:country":"US",
    "sg:address":"350 7th Avenue",
    "sg:city":"New York",
    "sg:classifiers":[
        {
            "category":"Building & Trades",
            "subcategory":"Construction",
            "type":"Services"
        }
    ],
    "sg:phone":"+1 212 239 0442",
    "sg:postcode":"10001",
    "sg:province":"NY",
    "sg:tags":[
        "interior",
        "design"
    ],
    "wof:name":"Alspector Architecture",
    "wof:placetype":"venue"
},
  "geometry": {"coordinates":[-73.99275400000001,40.74809],"type":"Point"}
}