{
  "type": "Feature",
  "properties": {
    "addr:full":"923 Port Washington Blvd Port Washington NY 11050",
    "addr:housenumber":"923",
    "addr:postcode":"11050",
    "addr:street":"Port Washington Blvd",
    "iso:country":"US",
    "sg:address":"923 Port Washington Blvd",
    "sg:city":"Port Washington",
    "sg:classifiers":[
        {
            "category":"Restaurant",
            "type":"Food & Drink"
        },
        {
            "category":"Ice Cream",
            "type":"Food & Drink"
        }
    ],
    "sg:menulink":"http://www.allmenus.com/ny/port-washington/243564-baskin-robbins/menu/",
    "sg:phone":"+1 516 883 1870",
    "sg:postcode":"11050",
    "sg:province":"NY",
    "sg:tags":[
        "american",
        "ice",
        "cream"
    ],
    "wof:name":"Baskin-Robbins",
    "wof:placetype":"venue"
},
  "geometry": {"coordinates":[-73.683729,40.828986],"type":"Point"}
}