{
  "type": "Feature",
  "properties": {
    "addr:full":"10353 Old Creek Rd Alexander NY 14005",
    "addr:housenumber":"10353",
    "addr:postcode":"14005",
    "addr:street":"Old Creek Rd",
    "iso:country":"US",
    "sg:address":"10353 Old Creek Rd",
    "sg:city":"Alexander",
    "sg:classifiers":[
        {
            "category":"Real Estate",
            "subcategory":"Surveying",
            "type":"Services"
        }
    ],
    "sg:phone":"+1   ",
    "sg:postcode":"14005",
    "sg:province":"NY",
    "wof:name":"Donald D Grower",
    "wof:placetype":"venue"
},
  "geometry": {"coordinates":[-78.227988,42.913386],"type":"Point"}
}