{
  "type": "Feature",
  "properties": {
    "iso:country":"US",
    "sg:address":"219 N Prospect St",
    "sg:city":"Herkimer",
    "sg:classifiers":[
        {
            "category":"Professional",
            "subcategory":"Employment Agencies",
            "type":"Services"
        }
    ],
    "sg:phone":"+1 315 866 8000",
    "sg:postcode":"13350",
    "sg:province":"NY",
    "sg:tags":[
        "opportunity"
    ],
    "wof:name":"Staffworks",
    "wof:placetype":"venue"
},
  "geometry": {"coordinates":[-74.98956800000001,43.026801],"type":"Point"}
}