{
  "type": "Feature",
  "properties": {
    "addr:full":"344 State Hwy 59 Nanuet NY 10954",
    "addr:housenumber":"344",
    "addr:postcode":"10954",
    "addr:street":"State Hwy 59",
    "iso:country":"US",
    "sg:address":"344 State Hwy 59",
    "sg:city":"Nanuet",
    "sg:classifiers":[
        {
            "category":"Shopping",
            "subcategory":"Bicycles & Sporting Goods",
            "type":"Retail Goods"
        }
    ],
    "sg:phone":"+1   ",
    "sg:postcode":"10954",
    "sg:province":"NY",
    "sg:tags":[
        "sc",
        "repair",
        "teach",
        "rent",
        "scuba"
    ],
    "wof:name":"Scuba Quest Diving Center",
    "wof:placetype":"venue"
},
  "geometry": {"coordinates":[-74.02781400000001,41.102498],"type":"Point"}
}