{
  "type": "Feature",
  "properties": {
    "iso:country":"US",
    "sg:address":"73 Garden St",
    "sg:city":"Seneca Falls",
    "sg:classifiers":[
        {
            "category":"Professional",
            "subcategory":"Computer Services",
            "type":"Services"
        }
    ],
    "sg:phone":"+1   ",
    "sg:postcode":"13148",
    "sg:province":"NY",
    "sg:tags":[
        "related"
    ],
    "wof:name":"J & S Sales",
    "wof:placetype":"venue"
},
  "geometry": {"coordinates":[-76.788275,42.905459],"type":"Point"}
}