{
  "type": "Feature",
  "properties": {
    "iso:country":"US",
    "sg:address":"133 Saratoga Rd",
    "sg:city":"Scotia",
    "sg:classifiers":[
        {
            "category":"Shopping",
            "subcategory":"Gifts & Souvenirs",
            "type":"Retail Goods"
        }
    ],
    "sg:phone":"+1 518 399 4112",
    "sg:postcode":"12302",
    "sg:province":"NY",
    "sg:tags":[
        "announcement",
        "printing",
        "commercial",
        "invitation"
    ],
    "wof:name":"Innovative Invitations",
    "wof:placetype":"venue"
},
  "geometry": {"coordinates":[-73.933271,42.861615],"type":"Point"}
}