{
  "type": "Feature",
  "properties": {
    "addr:full":"12160 McNeeley Rd Akron NY 14001",
    "addr:housenumber":"12160",
    "addr:postcode":"14001",
    "addr:street":"Mcneeley Rd",
    "iso:country":"US",
    "sg:address":"12160 McNeeley Rd",
    "sg:city":"Akron",
    "sg:classifiers":[
        {
            "category":"Organizations",
            "subcategory":"Labor Organization",
            "type":"Services"
        }
    ],
    "sg:phone":"+1   ",
    "sg:postcode":"14001",
    "sg:province":"NY",
    "wof:name":"Pace International Union",
    "wof:placetype":"venue"
},
  "geometry": {"coordinates":[-78.53277799999999,43.022887],"type":"Point"}
}