{
  "type": "Feature",
  "properties": {
    "addr:full":"7830 Metropolitan Ave Middle Village NY 11379",
    "addr:housenumber":"7830",
    "addr:postcode":"11379",
    "addr:street":"Metropolitan Ave",
    "iso:country":"US",
    "sg:address":"7830 Metropolitan Ave",
    "sg:city":"Middle Village",
    "sg:classifiers":[
        {
            "category":"Professional",
            "subcategory":"Lawyer & Legal Services",
            "type":"Services"
        }
    ],
    "sg:phone":"+1 718 894 4401",
    "sg:postcode":"11379",
    "sg:province":"NY",
    "wof:name":"Affatato Domenick Atty",
    "wof:placetype":"venue"
},
  "geometry": {"coordinates":[-73.874298,40.7131],"type":"Point"}
}