{
  "type": "Feature",
  "properties": {
    "addr:full":"867 47th St Brooklyn NY 11220",
    "addr:housenumber":"867",
    "addr:postcode":"11220",
    "addr:street":"47Th St",
    "iso:country":"US",
    "sg:address":"867 47th St",
    "sg:city":"Brooklyn",
    "sg:classifiers":[
        {
            "category":"Organizations",
            "subcategory":"Religious Organization",
            "type":"Services"
        }
    ],
    "sg:phone":"+1 718 851 8540",
    "sg:postcode":"11220",
    "sg:province":"NY",
    "sg:tags":[
        "clergy"
    ],
    "wof:name":"Yoshua Y Lustig",
    "wof:placetype":"venue"
},
  "geometry": {"coordinates":[-74.00083600000001,40.642423],"type":"Point"}
}