{
  "type": "Feature",
  "properties": {
    "addr:full":"5434 David Gray Hill Rd Geneseo NY 14454",
    "addr:housenumber":"5434",
    "addr:postcode":"14454",
    "addr:street":"David Gray Hill Rd",
    "iso:country":"US",
    "sg:address":"5434 David Gray Hill Rd",
    "sg:city":"Geneseo",
    "sg:classifiers":[
        {
            "category":"Organizations",
            "subcategory":"Membership Organization",
            "type":"Services"
        }
    ],
    "sg:phone":"+1 585 243 0533",
    "sg:postcode":"14454",
    "sg:province":"NY",
    "sg:tags":[
        "personal",
        "interest"
    ],
    "wof:name":"Genesee Vly Handspinning Guild",
    "wof:placetype":"venue"
},
  "geometry": {"coordinates":[-77.717185,42.722055],"type":"Point"}
}