{
  "type": "Feature",
  "properties": {
    "addr:full":"804 Sweet Home Rd Buffalo NY 14226",
    "addr:housenumber":"804",
    "addr:postcode":"14226",
    "addr:street":"Sweet Home Rd",
    "iso:country":"US",
    "sg:address":"804 Sweet Home Rd",
    "sg:city":"Buffalo",
    "sg:classifiers":[
        {
            "category":"Cinema",
            "subcategory":"Drive-in Theater",
            "type":"Entertainment"
        }
    ],
    "sg:phone":"+1 716 625 8535",
    "sg:postcode":"14226",
    "sg:province":"NY",
    "sg:tags":[
        "drive"
    ],
    "wof:name":"Transit Drive-In Theatre Inc",
    "wof:placetype":"venue"
},
  "geometry": {"coordinates":[-78.807749,42.984507],"type":"Point"}
}