{
  "type": "Feature",
  "properties": {
    "iso:country":"US",
    "sg:address":"155 Main St",
    "sg:city":"Farmingdale",
    "sg:classifiers":[
        {
            "category":"Organizations",
            "subcategory":"Religious Organization",
            "type":"Services"
        }
    ],
    "sg:phone":"+1 516 756 0497",
    "sg:postcode":"11735",
    "sg:province":"NY",
    "sg:tags":[
        "church"
    ],
    "wof:name":"Seventh Street Toys",
    "wof:placetype":"venue"
},
  "geometry": {"coordinates":[-73.445871,40.733398],"type":"Point"}
}