{
  "type": "Feature",
  "properties": {
    "addr:full":"296 W Main St Sayville NY 11782",
    "addr:housenumber":"296",
    "addr:postcode":"11782",
    "addr:street":"W Main St",
    "iso:country":"US",
    "sg:address":"296 W Main St",
    "sg:city":"Sayville",
    "sg:classifiers":[
        {
            "category":"Autos & Motor Vehicles",
            "subcategory":"Auto Supplies",
            "type":"Retail Goods"
        }
    ],
    "sg:phone":"+1 631 244 3535",
    "sg:postcode":"11782",
    "sg:province":"NY",
    "sg:tags":[
        "tire"
    ],
    "wof:name":"Traction Plus Discount Tires",
    "wof:placetype":"venue"
},
  "geometry": {"coordinates":[-73.089527,40.732227],"type":"Point"}
}