{
  "type": "Feature",
  "properties": {
    "iso:country":"US",
    "sg:address":"726 Densefield Rd",
    "sg:city":"West Babylon",
    "sg:classifiers":[
        {
            "category":"Building & Trades",
            "subcategory":"Construction",
            "type":"Services"
        }
    ],
    "sg:phone":"+1 631 422 2558",
    "sg:postcode":"11704",
    "sg:province":"NY",
    "sg:tags":[
        "hanging",
        "contractor"
    ],
    "wof:name":"Capelli Bill Painting Contr",
    "wof:placetype":"venue"
},
  "geometry": {"coordinates":[-73.354805,40.703178],"type":"Point"}
}