{
  "type": "Feature",
  "properties": {
    "iso:country":"US",
    "sg:address":"63 Liberty St",
    "sg:city":"Walton",
    "sg:classifiers":[
        {
            "category":"Personal",
            "subcategory":"Beauty Salon",
            "type":"Services"
        },
        {
            "category":"Personal",
            "subcategory":"Barber",
            "type":"Services"
        }
    ],
    "sg:phone":"+1 607 865 7321",
    "sg:postcode":"13856",
    "sg:province":"NY",
    "wof:name":"Carolyn's Salon",
    "wof:placetype":"venue"
},
  "geometry": {"coordinates":[-75.129929,42.172536],"type":"Point"}
}