{
  "type": "Feature",
  "properties": {
    "iso:country":"US",
    "sg:address":"14500 State Hwy 37",
    "sg:city":"Massena",
    "sg:classifiers":[
        {
            "category":"Shopping",
            "subcategory":"Discount & Variety Stores",
            "type":"Retail Goods"
        }
    ],
    "sg:phone":"+1   ",
    "sg:postcode":"13662",
    "sg:province":"NY",
    "sg:tags":[
        "merchandise",
        "general"
    ],
    "wof:name":"G & G Country Store",
    "wof:placetype":"venue"
},
  "geometry": {"coordinates":[-74.993827,44.916249],"type":"Point"}
}