{
  "type": "Feature",
  "properties": {
    "addr:full":"1010 W Belden Ave Syracuse NY 13204",
    "addr:housenumber":"1010",
    "addr:postcode":"13204",
    "addr:street":"W Belden Ave",
    "iso:country":"US",
    "sg:address":"1010 W Belden Ave",
    "sg:city":"Syracuse",
    "sg:classifiers":[
        {
            "category":"Retail",
            "subcategory":"Auto Repair",
            "type":"Services"
        }
    ],
    "sg:phone":"+1 315 471 0669",
    "sg:postcode":"13204",
    "sg:province":"NY",
    "sg:tags":[
        "body",
        "automobile",
        "painting",
        "repairing"
    ],
    "wof:name":"Blaires Collision",
    "wof:placetype":"venue"
},
  "geometry": {"coordinates":[-76.167951,43.05493],"type":"Point"}
}