{
  "type": "Feature",
  "properties": {
    "addr:full":"45 Evergreen Ln Wilmington NY 12997",
    "addr:housenumber":"45",
    "addr:postcode":"12997",
    "addr:street":"Evergreen Ln",
    "iso:country":"US",
    "sg:address":"45 Evergreen Ln",
    "sg:city":"Wilmington",
    "sg:classifiers":[
        {
            "category":"Government",
            "subcategory":"Office",
            "type":"Public Place"
        }
    ],
    "sg:phone":"+1 518 946 7196",
    "sg:postcode":"12997",
    "sg:province":"NY",
    "sg:tags":[
        "village"
    ],
    "wof:name":"Wilmington Town Garage",
    "wof:placetype":"venue"
},
  "geometry": {"coordinates":[-73.786535,44.435353],"type":"Point"}
}