{
  "type": "Feature",
  "properties": {
    "addr:full":"130 Albany St Cazenovia NY 13035",
    "addr:housenumber":"130",
    "addr:postcode":"13035",
    "addr:street":"Albany St",
    "iso:country":"US",
    "sg:address":"130 Albany St",
    "sg:city":"Cazenovia",
    "sg:classifiers":[
        {
            "category":"Professional",
            "subcategory":"Accounting & Tax Preparation",
            "type":"Services"
        }
    ],
    "sg:phone":"+1 315 655 9361",
    "sg:postcode":"13035",
    "sg:province":"NY",
    "sg:tags":[
        "accountant"
    ],
    "wof:name":"Outaouais Group",
    "wof:placetype":"venue"
},
  "geometry": {"coordinates":[-75.850874,42.929808],"type":"Point"}
}