{
  "type": "Feature",
  "properties": {
    "addr:full":"18 Windgate Dr Orchard Park NY 14127",
    "addr:housenumber":"18",
    "addr:postcode":"14127",
    "addr:street":"Windgate Dr",
    "iso:country":"US",
    "sg:address":"18 Windgate Dr",
    "sg:city":"Orchard Park",
    "sg:classifiers":[
        {
            "category":"Organizations",
            "subcategory":"Religious Organization",
            "type":"Services"
        }
    ],
    "sg:phone":"+1 716 649 4205",
    "sg:postcode":"14127",
    "sg:province":"NY",
    "sg:tags":[
        "clergy"
    ],
    "wof:name":"Thomas N Dobmeier",
    "wof:placetype":"venue"
},
  "geometry": {"coordinates":[-78.792192,42.738336],"type":"Point"}
}