{
  "type": "Feature",
  "properties": {
    "addr:full":"4555 Merrick Rd Massapequa NY 11758",
    "addr:housenumber":"4555",
    "addr:postcode":"11758",
    "addr:street":"Merrick Rd",
    "iso:country":"US",
    "sg:address":"4555 Merrick Rd",
    "sg:city":"Massapequa",
    "sg:classifiers":[
        {
            "category":"Professional",
            "subcategory":"Accounting & Tax Preparation",
            "type":"Services"
        }
    ],
    "sg:phone":"+1 516 797 3400",
    "sg:postcode":"11758",
    "sg:province":"NY",
    "wof:name":"Griesmeyer Roger J",
    "wof:placetype":"venue"
},
  "geometry": {"coordinates":[-73.468481,40.666712],"type":"Point"}
}