{
  "type": "Feature",
  "properties": {
    "addr:full":"435 W 23rd St New York NY 10011",
    "addr:housenumber":"435",
    "addr:postcode":"10011",
    "addr:street":"W 23Rd St",
    "iso:country":"US",
    "sg:address":"435 W 23rd St",
    "sg:city":"New York",
    "sg:classifiers":[
        {
            "category":"Wholesale",
            "subcategory":"Medical Equipment & Supplies",
            "type":"Manufacturing & Wholesale Goods"
        }
    ],
    "sg:phone":"+1 212 929 8024",
    "sg:postcode":"10011",
    "sg:province":"NY",
    "sg:tags":[
        "physician",
        "surgeon"
    ],
    "wof:name":"Dentation",
    "wof:placetype":"venue"
},
  "geometry": {"coordinates":[-74.003384,40.74734],"type":"Point"}
}