{
  "type": "Feature",
  "properties": {
    "addr:full":"2702 Knapp St Brooklyn NY 11235",
    "addr:housenumber":"2702",
    "addr:postcode":"11235",
    "addr:street":"Knapp St",
    "iso:country":"US",
    "sg:address":"2702 Knapp St",
    "sg:city":"Brooklyn",
    "sg:classifiers":[
        {
            "category":"Food & Beverages",
            "subcategory":"Groceries & Convenience Stores",
            "type":"Retail Goods"
        }
    ],
    "sg:phone":"+1 718 648 8035",
    "sg:postcode":"11235",
    "sg:province":"NY",
    "sg:website":"www.7-eleven.com",
    "wof:name":"7-Eleven",
    "wof:placetype":"venue"
},
  "geometry": {"coordinates":[-73.9319,40.5882],"type":"Point"}
}