{
  "type": "Feature",
  "properties": {
    "addr:full":"226 E 86th St New York NY 10028",
    "addr:housenumber":"226",
    "addr:postcode":"10028",
    "addr:street":"E 86Th St",
    "iso:country":"US",
    "sg:address":"226 E 86th St",
    "sg:city":"New York",
    "sg:classifiers":[
        {
            "category":"Fast Food",
            "type":"Food & Drink"
        },
        {
            "category":"Restaurant",
            "type":"Food & Drink"
        }
    ],
    "sg:phone":"+1 212 452 4675",
    "sg:postcode":"10028",
    "sg:province":"NY",
    "sg:website":"www.burgerking.com",
    "wof:name":"Burger King",
    "wof:placetype":"venue"
},
  "geometry": {"coordinates":[-73.952946,40.778235],"type":"Point"}
}