{
  "type": "Feature",
  "properties": {
    "addr:full":"190 Elizabeth St New York NY 10012",
    "addr:housenumber":"190",
    "addr:postcode":"10012",
    "addr:street":"Elizabeth St",
    "iso:country":"US",
    "sg:address":"190 Elizabeth St",
    "sg:city":"New York",
    "sg:classifiers":[
        {
            "category":"Professional",
            "subcategory":"Management & Consulting",
            "type":"Services"
        }
    ],
    "sg:phone":"+1 212 274 8002",
    "sg:postcode":"10012",
    "sg:province":"NY",
    "sg:tags":[
        "construction"
    ],
    "wof:name":"Jump Tech Construction",
    "wof:placetype":"venue"
},
  "geometry": {"coordinates":[-73.994151,40.722465],"type":"Point"}
}