{
  "type": "Feature",
  "properties": {
    "addr:full":"123 Montgomery St Goshen NY 10924",
    "addr:housenumber":"123",
    "addr:postcode":"10924",
    "addr:street":"Montgomery St",
    "iso:country":"US",
    "sg:address":"123 Montgomery St",
    "sg:city":"Goshen",
    "sg:classifiers":[
        {
            "category":"Shopping",
            "subcategory":"Florist",
            "type":"Retail Goods"
        }
    ],
    "sg:phone":"+1 845 294 5233",
    "sg:postcode":"10924",
    "sg:province":"NY",
    "wof:name":"Esposito Thomas",
    "wof:placetype":"venue"
},
  "geometry": {"coordinates":[-74.32199900000001,41.4072],"type":"Point"}
}