{
  "type": "Feature",
  "properties": {
    "iso:country":"US",
    "sg:address":"699 E High St",
    "sg:city":"Lockport",
    "sg:classifiers":[
        {
            "category":"Social Services",
            "subcategory":"Adult Care",
            "type":"Services"
        }
    ],
    "sg:phone":"+1 716 439 8699",
    "sg:postcode":"14094",
    "sg:province":"NY",
    "sg:tags":[
        "residential"
    ],
    "wof:name":"Western New York Dbso",
    "wof:placetype":"venue"
},
  "geometry": {"coordinates":[-78.67477599999999,43.164077],"type":"Point"}
}