{
  "type": "Feature",
  "properties": {
    "addr:full":"3520 31st St Astoria NY 11106",
    "addr:housenumber":"3520",
    "addr:postcode":"11106",
    "addr:street":"31St St",
    "iso:country":"US",
    "sg:address":"3520 31st St",
    "sg:city":"Astoria",
    "sg:classifiers":[
        {
            "category":"Professional",
            "subcategory":"Accounting & Tax Preparation",
            "type":"Services"
        }
    ],
    "sg:phone":"+1 718 392 6572",
    "sg:postcode":"11106",
    "sg:province":"NY",
    "sg:tags":[
        "accountant"
    ],
    "wof:name":"Marios Laoutas",
    "wof:placetype":"venue"
},
  "geometry": {"coordinates":[-73.929001,40.757702],"type":"Point"}
}