{
  "type": "Feature",
  "properties": {
    "iso:country":"US",
    "sg:address":"9472 Smith Rd",
    "sg:city":"Boonville",
    "sg:classifiers":[
        {
            "category":"Manufacturing",
            "subcategory":"Printing",
            "type":"Manufacturing & Wholesale Goods"
        }
    ],
    "sg:phone":"+1 315 942 2276",
    "sg:postcode":"13309",
    "sg:province":"NY",
    "sg:tags":[
        "printer"
    ],
    "wof:name":"O' Connor Printing",
    "wof:placetype":"venue"
},
  "geometry": {"coordinates":[-75.25846,43.507391],"type":"Point"}
}