{
  "type": "Feature",
  "properties": {
    "iso:country":"US",
    "sg:address":"1045 Shoemaker Rd",
    "sg:city":"Webster",
    "sg:classifiers":[
        {
            "category":"Manufacturing",
            "subcategory":"Motor Vehicles & Parts",
            "type":"Manufacturing & Wholesale Goods"
        }
    ],
    "sg:phone":"+1   ",
    "sg:postcode":"14580",
    "sg:province":"NY",
    "sg:tags":[
        "horse",
        "snowmobile",
        "trailer",
        "mfg"
    ],
    "wof:name":"Web Trailers Inc",
    "wof:placetype":"venue"
},
  "geometry": {"coordinates":[-77.44963,43.238773],"type":"Point"}
}