{
  "type": "Feature",
  "properties": {
    "addr:full":"396 Stottle Rd Scottsville NY 14546",
    "addr:housenumber":"396",
    "addr:postcode":"14546",
    "addr:street":"Stottle Rd",
    "iso:country":"US",
    "sg:address":"396 Stottle Rd",
    "sg:city":"Scottsville",
    "sg:classifiers":[
        {
            "category":"Retail",
            "subcategory":"Auto Repair",
            "type":"Services"
        }
    ],
    "sg:phone":"+1   ",
    "sg:postcode":"14546",
    "sg:province":"NY",
    "sg:tags":[
        "general"
    ],
    "wof:name":"Ghysel Auto",
    "wof:placetype":"venue"
},
  "geometry": {"coordinates":[-77.783492,43.055317],"type":"Point"}
}