{
  "type": "Feature",
  "properties": {
    "iso:country":"US",
    "sg:address":"333 E Broadway",
    "sg:city":"Long Beach",
    "sg:classifiers":[
        {
            "category":"Professional",
            "subcategory":"Lawyer & Legal Services",
            "type":"Services"
        }
    ],
    "sg:phone":"+1 516 432 1573",
    "sg:postcode":"11561",
    "sg:province":"NY",
    "sg:tags":[
        "attorney"
    ],
    "wof:name":"David A Bythewood",
    "wof:placetype":"venue"
},
  "geometry": {"coordinates":[-73.65314100000001,40.584862],"type":"Point"}
}