{
  "type": "Feature",
  "properties": {
    "iso:country":"US",
    "sg:address":"3731 10th St",
    "sg:city":"Long Island City",
    "sg:classifiers":[
        {
            "category":"Shopping",
            "subcategory":"Crafts & Fabrics",
            "type":"Retail Goods"
        }
    ],
    "sg:phone":"+1 718 433 4444",
    "sg:postcode":"11101",
    "sg:province":"NY",
    "sg:tags":[
        "store"
    ],
    "wof:name":"Vertex",
    "wof:placetype":"venue"
},
  "geometry": {"coordinates":[-73.941721,40.759566],"type":"Point"}
}