{
  "type": "Feature",
  "properties": {
    "iso:country":"US",
    "sg:address":"28 W Buffalo St",
    "sg:city":"Churchville",
    "sg:classifiers":[
        {
            "category":"Building & Trades",
            "subcategory":"Construction",
            "type":"Services"
        }
    ],
    "sg:phone":"+1 585 293 2673",
    "sg:postcode":"14428",
    "sg:province":"NY",
    "sg:tags":[
        "house"
    ],
    "wof:name":"Henry Issacs Home Remodel",
    "wof:placetype":"venue"
},
  "geometry": {"coordinates":[-77.88467199999999,43.104386],"type":"Point"}
}