{
  "type": "Feature",
  "properties": {
    "iso:country":"US",
    "sg:address":"355 Genesee St",
    "sg:city":"Auburn",
    "sg:classifiers":[
        {
            "category":"Professional",
            "type":"Services"
        }
    ],
    "sg:phone":"+1 315 255 3329",
    "sg:postcode":"13021",
    "sg:province":"NY",
    "sg:tags":[
        "establishment"
    ],
    "wof:name":"Cayuga Bank",
    "wof:placetype":"venue"
},
  "geometry": {"coordinates":[-76.588464,42.92078],"type":"Point"}
}