{
  "type": "Feature",
  "properties": {
    "addr:full":"733 Hattie Clark Rd Greene NY 13778",
    "addr:housenumber":"733",
    "addr:postcode":"13778",
    "addr:street":"Hattie Clark Rd",
    "iso:country":"US",
    "sg:address":"733 Hattie Clark Rd",
    "sg:city":"Greene",
    "sg:classifiers":[
        {
            "category":"Education",
            "subcategory":"Special Training",
            "type":"Public Place"
        },
        {
            "category":"Shopping",
            "subcategory":"Crafts & Fabrics",
            "type":"Retail Goods"
        }
    ],
    "sg:phone":"+1 607 843 6745",
    "sg:postcode":"13778",
    "sg:province":"NY",
    "sg:tags":[
        "school",
        "instruction",
        "art"
    ],
    "wof:name":"Florence A Milk",
    "wof:placetype":"venue"
},
  "geometry": {"coordinates":[-75.690456,42.390858],"type":"Point"}
}