{
  "type": "Feature",
  "properties": {
    "iso:country":"US",
    "sg:address":"129 Altamont Dr",
    "sg:city":"Hurley",
    "sg:classifiers":[
        {
            "category":"Building & Trades",
            "subcategory":"Construction",
            "type":"Services"
        }
    ],
    "sg:phone":"+1 845 339 4265",
    "sg:postcode":"12443",
    "sg:province":"NY",
    "sg:tags":[
        "contractor"
    ],
    "wof:name":"Colusa Contracting Inc",
    "wof:placetype":"venue"
},
  "geometry": {"coordinates":[-74.07898900000001,41.910389],"type":"Point"}
}