{
  "type": "Feature",
  "properties": {
    "iso:country":"US",
    "sg:address":"15 Mariner Dr",
    "sg:city":"Southampton",
    "sg:classifiers":[
        {
            "category":"Home & Garden",
            "subcategory":"Furniture",
            "type":"Retail Goods"
        }
    ],
    "sg:phone":"+1 631 283 7209",
    "sg:postcode":"11968",
    "sg:province":"NY",
    "sg:tags":[
        "store"
    ],
    "wof:name":"John Rogers Collection",
    "wof:placetype":"venue"
},
  "geometry": {"coordinates":[-72.383184,40.898708],"type":"Point"}
}