{
  "type": "Feature",
  "properties": {
    "addr:full":"4240 Bell Blvd Ste 601 Bayside NY 11361",
    "addr:housenumber":"4240",
    "addr:postcode":"11361",
    "addr:street":"Bell Blvd Ste 601",
    "iso:country":"US",
    "sg:address":"4240 Bell Blvd Ste 601",
    "sg:city":"Bayside",
    "sg:classifiers":[
        {
            "category":"Real Estate",
            "subcategory":"Real Estate Services",
            "type":"Services"
        },
        {
            "category":"Real Estate",
            "subcategory":"Real Estate Agent",
            "type":"Services"
        }
    ],
    "sg:phone":"+1 718 279 3131",
    "sg:postcode":"11361",
    "sg:province":"NY",
    "sg:tags":[
        "buyer",
        "management",
        "broker"
    ],
    "wof:name":"Bayside Terrace Realty",
    "wof:placetype":"venue"
},
  "geometry": {"coordinates":[-73.770523,40.762705],"type":"Point"}
}