{
  "type": "Feature",
  "properties": {
    "addr:full":"350 W 50th Street New York NY 10019",
    "addr:housenumber":"350",
    "addr:postcode":"10019",
    "addr:street":"W 50Th Street",
    "iso:country":"US",
    "sg:address":"350 W 50th Street",
    "sg:city":"New York",
    "sg:classifiers":[
        {
            "category":"Arts & Performance",
            "subcategory":"Art Gallery",
            "type":"Entertainment"
        }
    ],
    "sg:phone":"+1 212 586 8979",
    "sg:postcode":"10019",
    "sg:province":"NY",
    "wof:name":"Wada Takashi Gallery",
    "wof:placetype":"venue"
},
  "geometry": {"coordinates":[-73.987539,40.76289],"type":"Point"}
}