{
  "type": "Feature",
  "properties": {
    "iso:country":"US",
    "sg:address":"5 Parkhurst Rd",
    "sg:city":"Gansevoort",
    "sg:classifiers":[
        {
            "category":"Museum",
            "type":"Entertainment"
        }
    ],
    "sg:phone":"+1 518 583 3645",
    "sg:postcode":"12831",
    "sg:province":"NY",
    "wof:name":"Wilton Heritage Society",
    "wof:placetype":"venue"
},
  "geometry": {"coordinates":[-73.74882599999999,43.179632],"type":"Point"}
}