{
  "type": "Feature",
  "properties": {
    "addr:full":"1300 Scottsville Mumford Rd Scottsville NY 14546",
    "addr:housenumber":"1300",
    "addr:postcode":"14546",
    "addr:street":"Scottsville Mumford Rd",
    "iso:country":"US",
    "sg:address":"1300 Scottsville Mumford Rd",
    "sg:city":"Scottsville",
    "sg:classifiers":[
        {
            "category":"Autos & Motor Vehicles",
            "subcategory":"Auto Supplies",
            "type":"Retail Goods"
        }
    ],
    "sg:phone":"+1 585 889 2250",
    "sg:postcode":"14546",
    "sg:province":"NY",
    "sg:tags":[
        "equipment",
        "racing",
        "car",
        "automobile"
    ],
    "wof:name":"Red's Speed Shop",
    "wof:placetype":"venue"
},
  "geometry": {"coordinates":[-77.797197,43.012842],"type":"Point"}
}