{
  "type": "Feature",
  "properties": {
    "iso:country":"US",
    "sg:address":"306 E State St",
    "sg:city":"Ithaca",
    "sg:classifiers":[
        {
            "category":"Professional",
            "subcategory":"Lawyer & Legal Services",
            "type":"Services"
        }
    ],
    "sg:phone":"+1 607 277 8121",
    "sg:postcode":"14850",
    "sg:province":"NY",
    "sg:tags":[
        "attorney"
    ],
    "wof:name":"Hertzberg Law Office",
    "wof:placetype":"venue"
},
  "geometry": {"coordinates":[-76.495419,42.439693],"type":"Point"}
}