{
  "type": "Feature",
  "properties": {
    "iso:country":"US",
    "sg:address":"35 Pinelawn Rd",
    "sg:city":"Melville",
    "sg:classifiers":[
        {
            "category":"Professional",
            "subcategory":"Lawyer & Legal Services",
            "type":"Services"
        }
    ],
    "sg:phone":"+1 631 454 8282",
    "sg:postcode":"11747",
    "sg:province":"NY",
    "sg:tags":[
        "attorney"
    ],
    "wof:name":"Anthony Broscritto Esq",
    "wof:placetype":"venue"
},
  "geometry": {"coordinates":[-73.410313,40.783455],"type":"Point"}
}