{
  "type": "Feature",
  "properties": {
    "iso:country":"US",
    "sg:address":"1120 E Genesee St",
    "sg:city":"Syracuse",
    "sg:classifiers":[
        {
            "category":"Health Services",
            "subcategory":"Clinic",
            "type":"Services"
        }
    ],
    "sg:phone":"+1 315 475 5525",
    "sg:postcode":"13210",
    "sg:province":"NY",
    "wof:name":"Planned Parenthd The Rochester",
    "wof:placetype":"venue"
},
  "geometry": {"coordinates":[-76.13243199999999,43.046837],"type":"Point"}
}