{
  "type": "Feature",
  "properties": {
    "addr:full":"2301 Dewey Ave Rochester NY 14615",
    "addr:housenumber":"2301",
    "addr:postcode":"14615",
    "addr:street":"Dewey Ave",
    "iso:country":"US",
    "sg:address":"2301 Dewey Ave",
    "sg:city":"Rochester",
    "sg:classifiers":[
        {
            "category":"Shopping",
            "type":"Retail Goods"
        }
    ],
    "sg:phone":"+1 585 865 6746",
    "sg:postcode":"14615",
    "sg:province":"NY",
    "sg:tags":[
        "monument"
    ],
    "sg:website":"http://www.hartandbrigdenmemorials.com",
    "wof:name":"Hart Monument Company",
    "wof:placetype":"venue"
},
  "geometry": {"coordinates":[-77.63857400000001,43.210774],"type":"Point"}
}