{
  "type": "Feature",
  "properties": {
    "iso:country":"US",
    "sg:address":"3907 Prince St",
    "sg:city":"Flushing",
    "sg:classifiers":[
        {
            "category":"Health Services",
            "subcategory":"Dentist",
            "type":"Services"
        }
    ],
    "sg:phone":"+1 718 961 1628",
    "sg:postcode":"11354",
    "sg:province":"NY",
    "wof:name":"Bright Dental PC",
    "wof:placetype":"venue"
},
  "geometry": {"coordinates":[-73.83229799999999,40.759602],"type":"Point"}
}