{
  "type": "Feature",
  "properties": {
    "iso:country":"US",
    "sg:address":"156 W 56 St",
    "sg:city":"New York",
    "sg:classifiers":[
        {
            "category":"Professional",
            "subcategory":"Advertising",
            "type":"Services"
        }
    ],
    "sg:phone":"+1 212 779 3506",
    "sg:postcode":"10019",
    "sg:province":"NY",
    "sg:tags":[
        "agency"
    ],
    "wof:name":"Schoenfeld & Partners LLC",
    "wof:placetype":"venue"
},
  "geometry": {"coordinates":[-73.979333,40.764093],"type":"Point"}
}