{
  "type": "Feature",
  "properties": {
    "iso:country":"US",
    "sg:address":"2166 Brighton Henrietta Town Line Rd",
    "sg:city":"Rochester",
    "sg:classifiers":[
        {
            "category":"Professional",
            "type":"Services"
        }
    ],
    "sg:phone":"+1 585 427 8595",
    "sg:postcode":"14623",
    "sg:province":"NY",
    "sg:tags":[
        "establishment"
    ],
    "wof:name":"Forte Technologies Inc",
    "wof:placetype":"venue"
},
  "geometry": {"coordinates":[-77.616255,43.0947],"type":"Point"}
}