{
  "type": "Feature",
  "properties": {
    "addr:full":"37 W 37th St Fl 2 New York NY 10018",
    "addr:housenumber":"37;2",
    "addr:postcode":"10018",
    "addr:street":"W 37Th St",
    "iso:country":"US",
    "sg:address":"37 W 37th St Fl 2",
    "sg:city":"New York",
    "sg:classifiers":[
        {
            "category":"Retail",
            "subcategory":"Event Space",
            "type":"Services"
        }
    ],
    "sg:phone":"+1 646 278 0924",
    "sg:postcode":"10018",
    "sg:province":"NY",
    "sg:tags":[
        "venue"
    ],
    "wof:name":"Ballroom on Fifth",
    "wof:placetype":"venue"
},
  "geometry": {"coordinates":[-73.984594,40.751096],"type":"Point"}
}