{
  "type": "Feature",
  "properties": {
    "addr:full":"13625 37th Ave Ste 301A Flushing NY 11354",
    "addr:housenumber":"13625",
    "addr:postcode":"11354",
    "addr:street":"37Th Ave Ste 301A",
    "iso:country":"US",
    "sg:address":"13625 37th Ave Ste 301A",
    "sg:city":"Flushing",
    "sg:classifiers":[
        {
            "category":"Professional",
            "subcategory":"Lawyer & Legal Services",
            "type":"Services"
        }
    ],
    "sg:phone":"+1 718 886 2211",
    "sg:postcode":"11354",
    "sg:province":"NY",
    "wof:name":"Leong & Rayfield",
    "wof:placetype":"venue"
},
  "geometry": {"coordinates":[-73.830399,40.7617],"type":"Point"}
}