{
  "type": "Feature",
  "properties": {
    "iso:country":"US",
    "sg:address":"2588 Pitkin Ave",
    "sg:city":"Brooklyn",
    "sg:classifiers":[
        {
            "category":"Deli",
            "type":"Food & Drink"
        },
        {
            "category":"Food & Beverages",
            "subcategory":"Bakery",
            "type":"Retail Goods"
        }
    ],
    "sg:phone":"+1 347 221 0368",
    "sg:postcode":"11208",
    "sg:province":"NY",
    "sg:tags":[
        "sandwich"
    ],
    "wof:name":"Tony Deli",
    "wof:placetype":"venue"
},
  "geometry": {"coordinates":[-73.87664599999999,40.674583],"type":"Point"}
}