{
  "type": "Feature",
  "properties": {
    "iso:country":"US",
    "sg:address":"915 Park Ave",
    "sg:city":"Syracuse",
    "sg:classifiers":[
        {
            "category":"Organizations",
            "subcategory":"Community Association",
            "type":"Services"
        }
    ],
    "sg:phone":"+1 315 471 9708",
    "sg:postcode":"13204",
    "sg:province":"NY",
    "sg:tags":[
        "club"
    ],
    "wof:name":"Polish Community Home",
    "wof:placetype":"venue"
},
  "geometry": {"coordinates":[-76.179233,43.052271],"type":"Point"}
}