{
  "type": "Feature",
  "properties": {
    "addr:full":"140 Broadway Amityville NY 11701",
    "addr:housenumber":"140",
    "addr:postcode":"11701",
    "addr:street":"Broadway",
    "iso:country":"US",
    "sg:address":"140 Broadway",
    "sg:city":"Amityville",
    "sg:classifiers":[
        {
            "category":"Personal",
            "subcategory":"Beauty Salon",
            "type":"Services"
        }
    ],
    "sg:phone":"+1 631 598 7383",
    "sg:postcode":"11701",
    "sg:province":"NY",
    "wof:name":"Yole's Beauty Salon",
    "wof:placetype":"venue"
},
  "geometry": {"coordinates":[-73.416456,40.674768],"type":"Point"}
}