{
  "type": "Feature",
  "properties": {
    "addr:full":"4 S Clinton St Syracuse NY 13202",
    "addr:housenumber":"4",
    "addr:postcode":"13202",
    "addr:street":"S Clinton St",
    "iso:country":"US",
    "sg:address":"4 S Clinton St",
    "sg:city":"Syracuse",
    "sg:classifiers":[
        {
            "category":"Real Estate",
            "subcategory":"Architect",
            "type":"Services"
        }
    ],
    "sg:phone":"+1 315 422 0201",
    "sg:postcode":"13202",
    "sg:province":"NY",
    "sg:tags":[
        "architectural"
    ],
    "wof:name":"Pos Dal Architect PC",
    "wof:placetype":"venue"
},
  "geometry": {"coordinates":[-76.153614,43.050551],"type":"Point"}
}