{
  "type": "Feature",
  "properties": {
    "iso:country":"US",
    "sg:address":"360 W 22 St",
    "sg:city":"New York",
    "sg:classifiers":[
        {
            "category":"Professional",
            "subcategory":"Lawyer & Legal Services",
            "type":"Services"
        }
    ],
    "sg:phone":"+1 917 846 7840",
    "sg:postcode":"10011",
    "sg:province":"NY",
    "sg:tags":[
        "attorney"
    ],
    "wof:name":"Judith Levin",
    "wof:placetype":"venue"
},
  "geometry": {"coordinates":[-74.000531,40.745028],"type":"Point"}
}