{
  "type": "Feature",
  "properties": {
    "addr:full":"5216 Barnett Avenue Sunnyside NY 11104",
    "addr:housenumber":"5216",
    "addr:postcode":"11104",
    "addr:street":"Barnett Avenue",
    "iso:country":"US",
    "sg:address":"5216 Barnett Avenue",
    "sg:city":"Sunnyside",
    "sg:classifiers":[
        {
            "category":"Shopping",
            "subcategory":"Shoes",
            "type":"Retail Goods"
        }
    ],
    "sg:phone":"+1 718 446 1800",
    "sg:postcode":"11104",
    "sg:province":"NY",
    "sg:tags":[
        "store"
    ],
    "sg:website":"www.stevemadden.com",
    "wof:name":"Steve Madden Ltd",
    "wof:placetype":"venue"
},
  "geometry": {"coordinates":[-73.91070999999999,40.749755],"type":"Point"}
}