{
  "type": "Feature",
  "properties": {
    "addr:full":"2929 Broadway Fl 3 New York NY 10025",
    "addr:housenumber":"2929;3",
    "addr:postcode":"10025",
    "addr:street":"Broadway",
    "iso:country":"US",
    "sg:address":"2929 Broadway Fl 3",
    "sg:city":"New York",
    "sg:classifiers":[
        {
            "category":"Education",
            "subcategory":"University",
            "type":"Public Place"
        }
    ],
    "sg:phone":"+1 212 854 2793",
    "sg:postcode":"10025",
    "sg:province":"NY",
    "sg:tags":[
        "college"
    ],
    "sg:website":"www.columbia.edu",
    "wof:name":"Columbia University",
    "wof:placetype":"venue"
},
  "geometry": {"coordinates":[-73.964699,40.807098],"type":"Point"}
}