{
  "type": "Feature",
  "properties": {
    "iso:country":"US",
    "sg:address":"2 Half Acre Ct",
    "sg:city":"Smithtown",
    "sg:classifiers":[
        {
            "category":"Freight",
            "type":"Transportation"
        }
    ],
    "sg:phone":"+1   ",
    "sg:postcode":"11787",
    "sg:province":"NY",
    "sg:tags":[
        "operator",
        "local",
        "trucking"
    ],
    "wof:name":"Slate Rock Transport",
    "wof:placetype":"venue"
},
  "geometry": {"coordinates":[-73.19805100000001,40.860965],"type":"Point"}
}