{
  "type": "Feature",
  "properties": {
    "addr:full":"227 Thorn Ave Orchard Park NY 14127",
    "addr:housenumber":"227",
    "addr:postcode":"14127",
    "addr:street":"Thorn Ave",
    "iso:country":"US",
    "sg:address":"227 Thorn Ave",
    "sg:city":"Orchard Park",
    "sg:classifiers":[
        {
            "category":"Wholesale",
            "subcategory":"Machinery & Supplies",
            "type":"Manufacturing & Wholesale Goods"
        }
    ],
    "sg:phone":"+1 716 662 7030",
    "sg:postcode":"14127",
    "sg:province":"NY",
    "sg:tags":[
        "heat",
        "exchanger"
    ],
    "sg:website":"www.bos-hatten.com",
    "wof:name":"Adsco Heaters",
    "wof:placetype":"venue"
},
  "geometry": {"coordinates":[-78.75416199999999,42.762149],"type":"Point"}
}