{
  "type": "Feature",
  "properties": {
    "addr:full":"158 Fulton Ave Hempstead NY 11550",
    "addr:housenumber":"158",
    "addr:postcode":"11550",
    "addr:street":"Fulton Ave",
    "iso:country":"US",
    "sg:address":"158 Fulton Ave",
    "sg:city":"Hempstead",
    "sg:classifiers":[
        {
            "category":"Food & Beverages",
            "subcategory":"Specialty",
            "type":"Retail Goods"
        }
    ],
    "sg:phone":"+1 516 481 0400",
    "sg:postcode":"11550",
    "sg:province":"NY",
    "sg:tags":[
        "vitamin"
    ],
    "wof:name":"GNC",
    "wof:placetype":"venue"
},
  "geometry": {"coordinates":[-73.629093,40.707462],"type":"Point"}
}