{
  "type": "Feature",
  "properties": {
    "addr:full":"244 E 58th St New York NY 10022",
    "addr:housenumber":"244",
    "addr:postcode":"10022",
    "addr:street":"E 58Th St",
    "iso:country":"US",
    "sg:address":"244 E 58th St",
    "sg:city":"New York",
    "sg:classifiers":[
        {
            "category":"Professional",
            "subcategory":"Research",
            "type":"Services"
        }
    ],
    "sg:phone":"+1 212 371 3220",
    "sg:postcode":"10022",
    "sg:province":"NY",
    "sg:tags":[
        "foundation",
        "philanthropic"
    ],
    "wof:name":"Caron Foundation NY",
    "wof:placetype":"venue"
},
  "geometry": {"coordinates":[-73.965599,40.76034],"type":"Point"}
}