{
  "type": "Feature",
  "properties": {
    "addr:full":"320 Columbus Ave New York NY 10023",
    "addr:housenumber":"320",
    "addr:postcode":"10023",
    "addr:street":"Columbus Ave",
    "iso:country":"US",
    "sg:address":"320 Columbus Ave",
    "sg:city":"New York",
    "sg:classifiers":[
        {
            "category":"Restaurant",
            "type":"Food & Drink"
        }
    ],
    "sg:menulink":"http://www.allmenus.com/ny/new-york/7898-mughlai/menu/",
    "sg:phone":"+1 212 724 6363",
    "sg:postcode":"10023",
    "sg:province":"NY",
    "sg:tags":[
        "indian",
        "asian"
    ],
    "wof:name":"Mughlai",
    "wof:placetype":"venue"
},
  "geometry": {"coordinates":[-73.977681,40.779608],"type":"Point"}
}