{
  "type": "Feature",
  "properties": {
    "iso:country":"US",
    "sg:address":"5370 Waits Rd",
    "sg:city":"Owego",
    "sg:classifiers":[
        {
            "category":"Professional",
            "subcategory":"Business Services",
            "type":"Services"
        }
    ],
    "sg:phone":"+1   ",
    "sg:postcode":"13827",
    "sg:province":"NY",
    "sg:tags":[
        "print",
        "broker"
    ],
    "wof:name":"Lake View Graphics Inc",
    "wof:placetype":"venue"
},
  "geometry": {"coordinates":[-76.265478,42.00735],"type":"Point"}
}