{
  "type": "Feature",
  "properties": {
    "iso:country":"US",
    "sg:address":"4377 Bronx Blvd",
    "sg:city":"Bronx",
    "sg:classifiers":[
        {
            "category":"Organizations",
            "subcategory":"Non-profit Organization",
            "type":"Services"
        }
    ],
    "sg:phone":"+1 718 994 3500",
    "sg:postcode":"10466",
    "sg:province":"NY",
    "sg:tags":[
        "alternative",
        "abortion"
    ],
    "wof:name":"Free Abortion Alternatives",
    "wof:placetype":"venue"
},
  "geometry": {"coordinates":[-73.85817400000001,40.899254],"type":"Point"}
}