{
  "type": "Feature",
  "properties": {
    "iso:country":"US",
    "sg:address":"125 Rockne St",
    "sg:city":"Staten Island",
    "sg:classifiers":[
        {
            "category":"Freight",
            "type":"Transportation"
        }
    ],
    "sg:phone":"+1   ",
    "sg:postcode":"10314",
    "sg:province":"NY",
    "sg:tags":[
        "arrangement"
    ],
    "wof:name":"328 Resourcing Inc",
    "wof:placetype":"venue"
},
  "geometry": {"coordinates":[-74.160157,40.585531],"type":"Point"}
}