{
  "type": "Feature",
  "properties": {
    "addr:full":"86 Alexander St Yonkers NY 10701",
    "addr:housenumber":"86",
    "addr:postcode":"10701",
    "addr:street":"Alexander St",
    "iso:country":"US",
    "sg:address":"86 Alexander St",
    "sg:city":"Yonkers",
    "sg:classifiers":[
        {
            "category":"Shopping",
            "subcategory":"Clothing, Apparel, & Fashions",
            "type":"Retail Goods"
        }
    ],
    "sg:phone":"+1 914 969 0378",
    "sg:postcode":"10701",
    "sg:province":"NY",
    "sg:tags":[
        "apparel",
        "racing",
        "sportswear",
        "merchandise"
    ],
    "wof:name":"Smooth Sportswear",
    "wof:placetype":"venue"
},
  "geometry": {"coordinates":[-73.90143399999999,40.938136],"type":"Point"}
}