{
  "type": "Feature",
  "properties": {
    "addr:full":"24 Delmar Ave Buffalo NY 14225",
    "addr:housenumber":"24",
    "addr:postcode":"14225",
    "addr:street":"Delmar Ave",
    "iso:country":"US",
    "sg:address":"24 Delmar Ave",
    "sg:city":"Buffalo",
    "sg:classifiers":[
        {
            "category":"Building & Trades",
            "subcategory":"Construction",
            "type":"Services"
        }
    ],
    "sg:phone":"+1 716 631 4825",
    "sg:postcode":"14225",
    "sg:province":"NY",
    "sg:tags":[
        "dry wall",
        "contractor"
    ],
    "wof:name":"Elite Plastering & Drywall",
    "wof:placetype":"venue"
},
  "geometry": {"coordinates":[-78.76308299999999,42.946866],"type":"Point"}
}