{
  "type": "Feature",
  "properties": {
    "addr:full":"492 Western Ave Albany NY 12203",
    "addr:housenumber":"492",
    "addr:postcode":"12203",
    "addr:street":"Western Ave",
    "iso:country":"US",
    "sg:address":"492 Western Ave",
    "sg:city":"Albany",
    "sg:classifiers":[
        {
            "category":"Wholesale",
            "subcategory":"Durable Goods & Equipment",
            "type":"Manufacturing & Wholesale Goods"
        }
    ],
    "sg:phone":"+1 518 482 0971",
    "sg:postcode":"12203",
    "sg:province":"NY",
    "sg:tags":[
        "importer"
    ],
    "wof:name":"Triskel Imports",
    "wof:placetype":"venue"
},
  "geometry": {"coordinates":[-73.78921699999999,42.66548],"type":"Point"}
}