{
  "type": "Feature",
  "properties": {
    "iso:country":"US",
    "sg:address":"85 Sutter Ave",
    "sg:city":"Ozone Park",
    "sg:classifiers":[
        {
            "category":"Shopping",
            "subcategory":"Gifts & Souvenirs",
            "type":"Retail Goods"
        }
    ],
    "sg:phone":"+1   ",
    "sg:postcode":"11417",
    "sg:province":"NY",
    "sg:tags":[
        "decoration",
        "party",
        "balloon"
    ],
    "wof:name":"Mollys Balloons",
    "wof:placetype":"venue"
},
  "geometry": {"coordinates":[-73.83593999999999,40.676897],"type":"Point"}
}