{
  "type": "Feature",
  "properties": {
    "addr:full":"252 E Fordham Rd Bronx NY 10458",
    "addr:housenumber":"252",
    "addr:postcode":"10458",
    "addr:street":"E Fordham Rd",
    "iso:country":"US",
    "sg:address":"252 E Fordham Rd",
    "sg:city":"Bronx",
    "sg:classifiers":[
        {
            "category":"Shopping",
            "subcategory":"Clothing, Apparel, & Fashions",
            "type":"Retail Goods"
        }
    ],
    "sg:phone":"+1   ",
    "sg:postcode":"10458",
    "sg:province":"NY",
    "wof:name":"Hyperactive",
    "wof:placetype":"venue"
},
  "geometry": {"coordinates":[-73.894876,40.862],"type":"Point"}
}