{
  "type": "Feature",
  "properties": {
    "addr:full":"1439 1st Avenue New York NY 10021",
    "addr:housenumber":"1439",
    "addr:postcode":"10021",
    "addr:street":"1St Avenue",
    "iso:country":"US",
    "sg:address":"1439 1st Avenue",
    "sg:city":"New York",
    "sg:classifiers":[
        {
            "category":"Personal",
            "type":"Services"
        }
    ],
    "sg:phone":"+1 212 734 5666",
    "sg:postcode":"10021",
    "sg:province":"NY",
    "sg:tags":[
        "mover"
    ],
    "wof:name":"Sea & Air International",
    "wof:placetype":"venue"
},
  "geometry": {"coordinates":[-73.954745,40.769727],"type":"Point"}
}