{
  "type": "Feature",
  "properties": {
    "addr:full":"385 Roaring Brook Rd Chappaqua NY 10514",
    "addr:housenumber":"385",
    "addr:postcode":"10514",
    "addr:street":"Roaring Brook Rd",
    "iso:country":"US",
    "sg:address":"385 Roaring Brook Rd",
    "sg:city":"Chappaqua",
    "sg:classifiers":[
        {
            "category":"Shopping",
            "subcategory":"Computers & Home Electronics",
            "type":"Retail Goods"
        }
    ],
    "sg:phone":"+1 914 238 5805",
    "sg:postcode":"10514",
    "sg:province":"NY",
    "sg:tags":[
        "equipment",
        "dealer"
    ],
    "sg:website":"www.jimshankman.com",
    "wof:name":"Riverrun Consulting Inc",
    "wof:placetype":"venue"
},
  "geometry": {"coordinates":[-73.771081,41.181621],"type":"Point"}
}