{
  "type": "Feature",
  "properties": {
    "iso:country":"US",
    "sg:address":"789 S 6th St",
    "sg:city":"Lindenhurst",
    "sg:classifiers":[
        {
            "category":"Building & Trades",
            "subcategory":"Construction",
            "type":"Services"
        }
    ],
    "sg:phone":"+1 631 225 1525",
    "sg:postcode":"11757",
    "sg:province":"NY",
    "sg:tags":[
        "house"
    ],
    "wof:name":"Hc Hergenhan Const",
    "wof:placetype":"venue"
},
  "geometry": {"coordinates":[-73.372027,40.671938],"type":"Point"}
}