{
  "type": "Feature",
  "properties": {
    "addr:full":"1434 US Hwy 9 Wappingers Falls NY 12590",
    "addr:housenumber":"1434",
    "addr:postcode":"12590",
    "addr:street":"Us Hwy 9",
    "iso:country":"US",
    "sg:address":"1434 US Hwy 9",
    "sg:city":"Wappingers Falls",
    "sg:classifiers":[
        {
            "category":"Personal",
            "subcategory":"Beauty Salon",
            "type":"Services"
        }
    ],
    "sg:phone":"+1   ",
    "sg:postcode":"12590",
    "sg:province":"NY",
    "sg:tags":[
        "shop"
    ],
    "wof:name":"Illusions Salon Inc",
    "wof:placetype":"venue"
},
  "geometry": {"coordinates":[-73.90930299999999,41.574279],"type":"Point"}
}