{
  "type": "Feature",
  "properties": {
    "addr:full":"485 7 Ave New York NY 10018",
    "addr:housenumber":"485",
    "addr:postcode":"10018",
    "addr:street":"7 Ave",
    "iso:country":"US",
    "sg:address":"485 7 Ave",
    "sg:city":"New York",
    "sg:classifiers":[
        {
            "category":"Shopping",
            "subcategory":"Clothing, Apparel, & Fashions",
            "type":"Retail Goods"
        }
    ],
    "sg:phone":"+1 212 967 9192",
    "sg:postcode":"10018",
    "sg:province":"NY",
    "wof:name":"Children Clothing House",
    "wof:placetype":"venue"
},
  "geometry": {"coordinates":[-73.989694,40.75228],"type":"Point"}
}