{
  "type": "Feature",
  "properties": {
    "addr:full":"1545 William St Buffalo NY 14206",
    "addr:housenumber":"1545",
    "addr:postcode":"14206",
    "addr:street":"William St",
    "iso:country":"US",
    "sg:address":"1545 William St",
    "sg:city":"Buffalo",
    "sg:classifiers":[
        {
            "category":"Freight",
            "type":"Transportation"
        }
    ],
    "sg:phone":"+1 716 895 7250",
    "sg:postcode":"14206",
    "sg:province":"NY",
    "sg:tags":[
        "commercial",
        "storage"
    ],
    "wof:name":"Spare Room Self Storage",
    "wof:placetype":"venue"
},
  "geometry": {"coordinates":[-78.809927,42.884668],"type":"Point"}
}