{
  "type": "Feature",
  "properties": {
    "addr:full":"114 Pine St Corning NY 14830",
    "addr:housenumber":"114",
    "addr:postcode":"14830",
    "addr:street":"Pine St",
    "iso:country":"US",
    "sg:address":"114 Pine St",
    "sg:city":"Corning",
    "sg:classifiers":[
        {
            "category":"Parking",
            "type":"Transportation"
        }
    ],
    "sg:phone":"+1 607 962 4018",
    "sg:postcode":"14830",
    "sg:province":"NY",
    "sg:tags":[
        "garage"
    ],
    "wof:name":"Centerway Parking Garage",
    "wof:placetype":"venue"
},
  "geometry": {"coordinates":[-77.05435799999999,42.143674],"type":"Point"}
}