{
  "type": "Feature",
  "properties": {
    "iso:country":"US",
    "sg:address":"19 Donald St",
    "sg:city":"Roslyn Heights",
    "sg:classifiers":[
        {
            "category":"Building & Trades",
            "subcategory":"Construction",
            "type":"Services"
        }
    ],
    "sg:phone":"+1 516 621 5803",
    "sg:postcode":"11577",
    "sg:province":"NY",
    "sg:tags":[
        "contractor"
    ],
    "wof:name":"Design Consortium General",
    "wof:placetype":"venue"
},
  "geometry": {"coordinates":[-73.640052,40.788044],"type":"Point"}
}