{
  "type": "Feature",
  "properties": {
    "iso:country":"US",
    "sg:address":"775 N Greece Rd",
    "sg:city":"Rochester",
    "sg:classifiers":[
        {
            "category":"Building & Trades",
            "subcategory":"Construction",
            "type":"Services"
        }
    ],
    "sg:phone":"+1 585 227 0874",
    "sg:postcode":"14626",
    "sg:province":"NY",
    "sg:tags":[
        "house"
    ],
    "wof:name":"Ard Home Improvements",
    "wof:placetype":"venue"
},
  "geometry": {"coordinates":[-77.733341,43.242297],"type":"Point"}
}