{
  "type": "Feature",
  "properties": {
    "addr:full":"2357 E 26th St Brooklyn NY 11229",
    "addr:housenumber":"2357",
    "addr:postcode":"11229",
    "addr:street":"E 26Th St",
    "iso:country":"US",
    "sg:address":"2357 E 26th St",
    "sg:city":"Brooklyn",
    "sg:classifiers":[
        {
            "category":"Real Estate",
            "subcategory":"Real Estate Agent",
            "type":"Services"
        }
    ],
    "sg:phone":"+1 718 332 1945",
    "sg:postcode":"11229",
    "sg:province":"NY",
    "wof:name":"Hsk Appraisals Inc",
    "wof:placetype":"venue"
},
  "geometry": {"coordinates":[-73.94450999999999,40.594606],"type":"Point"}
}