{
  "type": "Feature",
  "properties": {
    "addr:full":"1624 Castle Gardens Rd Vestal NY 13850",
    "addr:housenumber":"1624",
    "addr:postcode":"13850",
    "addr:street":"Castle Gardens Rd",
    "iso:country":"US",
    "sg:address":"1624 Castle Gardens Rd",
    "sg:city":"Vestal",
    "sg:classifiers":[
        {
            "category":"Food & Beverages",
            "subcategory":"Groceries & Convenience Stores",
            "type":"Retail Goods"
        },
        {
            "category":"Food & Beverages",
            "subcategory":"Bakery",
            "type":"Retail Goods"
        }
    ],
    "sg:phone":"+1 607 786 0956",
    "sg:postcode":"13850",
    "sg:province":"NY",
    "sg:tags":[
        "product",
        "whole"
    ],
    "wof:name":"Best Foods Baking Group",
    "wof:placetype":"venue"
},
  "geometry": {"coordinates":[-76.07874700000001,42.079734],"type":"Point"}
}