{
  "type": "Feature",
  "properties": {
    "addr:full":"15 E 30th St New York NY 10016",
    "addr:housenumber":"15",
    "addr:postcode":"10016",
    "addr:street":"E 30Th St",
    "iso:country":"US",
    "sg:address":"15 E 30th St",
    "sg:city":"New York",
    "sg:classifiers":[
        {
            "category":"Home & Garden",
            "subcategory":"Carpets & Floor Coverings",
            "type":"Retail Goods"
        }
    ],
    "sg:phone":"+1 212 532 0340",
    "sg:postcode":"10016",
    "sg:province":"NY",
    "sg:tags":[
        "carpeting"
    ],
    "wof:name":"Bashian & Yonaty Oriental Rugs Corp",
    "wof:placetype":"venue"
},
  "geometry": {"coordinates":[-73.985298,40.745399],"type":"Point"}
}