{
  "type": "Feature",
  "properties": {
    "iso:country":"US",
    "sg:address":"409 Highland Ave Exd",
    "sg:city":"Middletown",
    "sg:classifiers":[
        {
            "category":"Manufacturing",
            "subcategory":"Building Materials",
            "type":"Manufacturing & Wholesale Goods"
        },
        {
            "category":"Manufacturing",
            "subcategory":"Lumber",
            "type":"Manufacturing & Wholesale Goods"
        }
    ],
    "sg:phone":"+1 845 342 1511",
    "sg:postcode":"10940",
    "sg:province":"NY",
    "sg:tags":[
        "hardwood",
        "mill",
        "mater"
    ],
    "wof:name":"Federal Cabinet Co Inc",
    "wof:placetype":"venue"
},
  "geometry": {"coordinates":[-74.403327,41.472272],"type":"Point"}
}