{
  "type": "Feature",
  "properties": {
    "addr:full":"4295 Zenner Rd Eden NY 14057",
    "addr:postcode":"4295;14057",
    "addr:street":"Zenner Rd",
    "iso:country":"US",
    "sg:address":"4295 Zenner Rd",
    "sg:city":"Eden",
    "sg:classifiers":[
        {
            "category":"Building & Trades",
            "subcategory":"Landscaping Services",
            "type":"Services"
        }
    ],
    "sg:phone":"+1 716 992 2760",
    "sg:postcode":"14057",
    "sg:province":"NY",
    "sg:tags":[
        "landscape",
        "contractor"
    ],
    "wof:name":"Highland Acres Landscaping Inc",
    "wof:placetype":"venue"
},
  "geometry": {"coordinates":[-78.818707,42.635992],"type":"Point"}
}