{
  "type": "Feature",
  "properties": {
    "addr:full":"18 Santa Cir Pittsford NY 14534",
    "addr:housenumber":"18",
    "addr:postcode":"14534",
    "addr:street":"Santa Cir",
    "iso:country":"US",
    "sg:address":"18 Santa Cir",
    "sg:city":"Pittsford",
    "sg:classifiers":[
        {
            "category":"Real Estate",
            "subcategory":"Real Estate Agent",
            "type":"Services"
        }
    ],
    "sg:phone":"+1 585 264 0380",
    "sg:postcode":"14534",
    "sg:province":"NY",
    "sg:website":"www.rochesterhomes4u.com",
    "wof:name":"David Rose Realtors",
    "wof:placetype":"venue"
},
  "geometry": {"coordinates":[-77.483007,43.085286],"type":"Point"}
}