{
  "type": "Feature",
  "properties": {
    "iso:country":"US",
    "sg:address":"1752 Shearing Dr",
    "sg:city":"Marilla",
    "sg:classifiers":[
        {
            "category":"Home & Garden",
            "subcategory":"Building Materials",
            "type":"Retail Goods"
        }
    ],
    "sg:phone":"+1   ",
    "sg:postcode":"14102",
    "sg:province":"NY",
    "wof:name":"Glass Palace",
    "wof:placetype":"venue"
},
  "geometry": {"coordinates":[-78.562624,42.839407],"type":"Point"}
}