{
  "type": "Feature",
  "properties": {
    "addr:full":"3732 Route 112 Coram NY 11727",
    "addr:housenumber":"3732",
    "addr:postcode":"11727",
    "addr:street":"Route 112",
    "iso:country":"US",
    "sg:address":"3732 Route 112",
    "sg:city":"Coram",
    "sg:classifiers":[
        {
            "category":"Banks & Credit Unions",
            "subcategory":"Financial Services",
            "type":"Services"
        }
    ],
    "sg:phone":"+1 631 736 6633",
    "sg:postcode":"11727",
    "sg:province":"NY",
    "sg:tags":[
        "broker",
        "mortgage"
    ],
    "wof:name":"Century 21-Rustic Realty",
    "wof:placetype":"venue"
},
  "geometry": {"coordinates":[-72.997597,40.8494],"type":"Point"}
}