{
  "type": "Feature",
  "properties": {
    "iso:country":"US",
    "sg:address":"86 Marc Dr",
    "sg:city":"Ridge",
    "sg:classifiers":[
        {
            "category":"Building & Trades",
            "subcategory":"Construction",
            "type":"Services"
        }
    ],
    "sg:phone":"+1 631 345 2475",
    "sg:postcode":"11961",
    "sg:province":"NY",
    "sg:tags":[
        "house"
    ],
    "wof:name":"Culcase Homes Inc",
    "wof:placetype":"venue"
},
  "geometry": {"coordinates":[-72.890935,40.904293],"type":"Point"}
}