{
  "type": "Feature",
  "properties": {
    "addr:full":"236 Washington St Binghamton NY 13901",
    "addr:housenumber":"236",
    "addr:postcode":"13901",
    "addr:street":"Washington St",
    "iso:country":"US",
    "sg:address":"236 Washington St",
    "sg:city":"Binghamton",
    "sg:classifiers":[
        {
            "category":"Government",
            "subcategory":"Office",
            "type":"Public Place"
        }
    ],
    "sg:phone":"+1 607 778 2480",
    "sg:postcode":"13901",
    "sg:province":"NY",
    "sg:website":"www.gobroomecounty.com",
    "wof:name":"Broome County Forum Theatre",
    "wof:placetype":"venue"
},
  "geometry": {"coordinates":[-75.912538,42.100951],"type":"Point"}
}