{
  "type": "Feature",
  "properties": {
    "addr:full":"351 Broadway Fl 3 New York NY 10013",
    "addr:housenumber":"351;3",
    "addr:postcode":"10013",
    "addr:street":"Broadway",
    "iso:country":"US",
    "sg:address":"351 Broadway Fl 3",
    "sg:city":"New York",
    "sg:classifiers":[
        {
            "category":"Professional",
            "subcategory":"Lawyer & Legal Services",
            "type":"Services"
        }
    ],
    "sg:phone":"+1 212 545 8611",
    "sg:postcode":"10013",
    "sg:province":"NY",
    "wof:name":"Soloman & Bernstein",
    "wof:placetype":"venue"
},
  "geometry": {"coordinates":[-74.00429200000001,40.717216],"type":"Point"}
}