{
  "type": "Feature",
  "properties": {
    "iso:country":"US",
    "sg:address":"1879 Bronxdale Ave",
    "sg:city":"Bronx",
    "sg:classifiers":[
        {
            "category":"Food & Beverages",
            "subcategory":"Groceries & Convenience Stores",
            "type":"Retail Goods"
        }
    ],
    "sg:phone":"+1   ",
    "sg:postcode":"10462",
    "sg:province":"NY",
    "sg:tags":[
        "delicatessen"
    ],
    "wof:name":"Ninos Delicatessen",
    "wof:placetype":"venue"
},
  "geometry": {"coordinates":[-73.85943899999999,40.846658],"type":"Point"}
}