{
  "type": "Feature",
  "properties": {
    "iso:country":"US",
    "sg:address":"219 Burnet Ave",
    "sg:city":"Syracuse",
    "sg:classifiers":[
        {
            "category":"Building & Trades",
            "subcategory":"Construction",
            "type":"Services"
        }
    ],
    "sg:phone":"+1 315 475 8404",
    "sg:postcode":"13203",
    "sg:province":"NY",
    "sg:tags":[
        "general",
        "contractor"
    ],
    "sg:website":"www.zausmerfrisch.com",
    "wof:name":"Zausmer-Frisch",
    "wof:placetype":"venue"
},
  "geometry": {"coordinates":[-76.14395399999999,43.052334],"type":"Point"}
}