{
  "type": "Feature",
  "properties": {
    "addr:full":"1563 Ralph Ave Brooklyn NY 11236",
    "addr:housenumber":"1563",
    "addr:postcode":"11236",
    "addr:street":"Ralph Ave",
    "iso:country":"US",
    "sg:address":"1563 Ralph Ave",
    "sg:city":"Brooklyn",
    "sg:classifiers":[
        {
            "category":"Shopping",
            "subcategory":"Pharmacy",
            "type":"Retail Goods"
        }
    ],
    "sg:phone":"+1 718 676 0697",
    "sg:postcode":"11236",
    "sg:province":"NY",
    "sg:tags":[
        "drugstore"
    ],
    "wof:name":"Teps Pharmacy",
    "wof:placetype":"venue"
},
  "geometry": {"coordinates":[-73.919138,40.638896],"type":"Point"}
}