{
  "type": "Feature",
  "properties": {
    "addr:full":"625 Main St Farmingdale NY 11735",
    "addr:housenumber":"625",
    "addr:postcode":"11735",
    "addr:street":"Main St",
    "iso:country":"US",
    "sg:address":"625 Main St",
    "sg:city":"Farmingdale",
    "sg:classifiers":[
        {
            "category":"Retail",
            "subcategory":"Laundry & Dry Cleaning",
            "type":"Services"
        }
    ],
    "sg:phone":"+1   ",
    "sg:postcode":"11735",
    "sg:province":"NY",
    "sg:tags":[
        "power"
    ],
    "wof:name":"Triangle Plaza Laundramat",
    "wof:placetype":"venue"
},
  "geometry": {"coordinates":[-73.443355,40.726049],"type":"Point"}
}