{
  "type": "Feature",
  "properties": {
    "iso:country":"US",
    "sg:address":"1205 Franklin Ave Ste 100",
    "sg:city":"Garden City",
    "sg:classifiers":[
        {
            "category":"Professional",
            "subcategory":"Lawyer & Legal Services",
            "type":"Services"
        }
    ],
    "sg:phone":"+1 516 746 3483",
    "sg:postcode":"11530",
    "sg:province":"NY",
    "wof:name":"Putney Twombly Hall & Hirson",
    "wof:placetype":"venue"
},
  "geometry": {"coordinates":[-73.636775,40.733061],"type":"Point"}
}