{
  "type": "Feature",
  "properties": {
    "iso:country":"US",
    "sg:address":"31 South St",
    "sg:city":"Oyster Bay",
    "sg:classifiers":[
        {
            "category":"Wholesale",
            "subcategory":"Durable Goods & Equipment",
            "type":"Manufacturing & Wholesale Goods"
        },
        {
            "category":"Shopping",
            "subcategory":"Bicycles & Sporting Goods",
            "type":"Retail Goods"
        }
    ],
    "sg:phone":"+1 516 922 1376",
    "sg:postcode":"11771",
    "sg:province":"NY",
    "sg:tags":[
        "gun",
        "gunsmith"
    ],
    "wof:name":"Oyster Bay Industries Inc",
    "wof:placetype":"venue"
},
  "geometry": {"coordinates":[-73.52922700000001,40.873579],"type":"Point"}
}