{
  "type": "Feature",
  "properties": {
    "iso:country":"US",
    "sg:address":"948 4th Ave",
    "sg:city":"Brooklyn",
    "sg:classifiers":[
        {
            "category":"Food & Beverages",
            "subcategory":"Bakery",
            "type":"Retail Goods"
        }
    ],
    "sg:phone":"+1 718 788 0594",
    "sg:postcode":"11220",
    "sg:province":"NY",
    "sg:tags":[
        "baker",
        "mexican"
    ],
    "wof:name":"Ines Bakery",
    "wof:placetype":"venue"
},
  "geometry": {"coordinates":[-74.00435899999999,40.654451],"type":"Point"}
}