{
  "type": "Feature",
  "properties": {
    "iso:country":"US",
    "sg:address":"479 Truax Rd",
    "sg:city":"Amsterdam",
    "sg:classifiers":[
        {
            "category":"Freight",
            "type":"Transportation"
        }
    ],
    "sg:phone":"+1 518 843 9478",
    "sg:postcode":"12010",
    "sg:province":"NY",
    "sg:tags":[
        "hauling",
        "trucking"
    ],
    "wof:name":"Nantista's Market LTD",
    "wof:placetype":"venue"
},
  "geometry": {"coordinates":[-74.14810900000001,42.934894],"type":"Point"}
}