{
  "type": "Feature",
  "properties": {
    "iso:country":"US",
    "sg:address":"316 Towne Dr",
    "sg:city":"Fayetteville",
    "sg:classifiers":[
        {
            "category":"Restaurant",
            "type":"Food & Drink"
        }
    ],
    "sg:menulink":"http://www.allmenus.com/ny/manlius/253622-great-northern-pizza-kitchen/menu/",
    "sg:phone":"+1 315 637 3287",
    "sg:postcode":"13066",
    "sg:province":"NY",
    "sg:tags":[
        "american",
        "pizza"
    ],
    "wof:name":"Great Northern Pizza Kitchen",
    "wof:placetype":"venue"
},
  "geometry": {"coordinates":[-76.017898,43.033605],"type":"Point"}
}