{
  "type": "Feature",
  "properties": {
    "addr:full":"1957 Westchester Ave Bronx NY 10462",
    "addr:housenumber":"1957",
    "addr:postcode":"10462",
    "addr:street":"Westchester Ave",
    "iso:country":"US",
    "sg:address":"1957 Westchester Ave",
    "sg:city":"Bronx",
    "sg:classifiers":[
        {
            "category":"Real Estate",
            "subcategory":"Real Estate Services",
            "type":"Services"
        }
    ],
    "sg:phone":"+1 718 822 6620",
    "sg:postcode":"10462",
    "sg:province":"NY",
    "sg:tags":[
        "management",
        "property"
    ],
    "wof:name":"Remax Executive Realty",
    "wof:placetype":"venue"
},
  "geometry": {"coordinates":[-73.859076,40.833566],"type":"Point"}
}