{
  "type": "Feature",
  "properties": {
    "iso:country":"US",
    "sg:address":"427 73rd St",
    "sg:city":"Niagara Falls",
    "sg:classifiers":[
        {
            "category":"Professional",
            "subcategory":"Business Services",
            "type":"Services"
        }
    ],
    "sg:phone":"+1 716 934 4352",
    "sg:postcode":"14304",
    "sg:province":"NY",
    "sg:tags":[
        "auctioneer"
    ],
    "wof:name":"Metrose Auctions & Realty",
    "wof:placetype":"venue"
},
  "geometry": {"coordinates":[-78.980621,43.082512],"type":"Point"}
}