{
  "type": "Feature",
  "properties": {
    "iso:country":"US",
    "sg:address":"8 E Genesee St",
    "sg:city":"Auburn",
    "sg:classifiers":[
        {
            "category":"Personal",
            "subcategory":"Beauty Salon",
            "type":"Services"
        }
    ],
    "sg:phone":"+1 315 252 2874",
    "sg:postcode":"13021",
    "sg:province":"NY",
    "sg:tags":[
        "manicuring"
    ],
    "wof:name":"Volpe Nails & Tanning",
    "wof:placetype":"venue"
},
  "geometry": {"coordinates":[-76.563074,42.93303],"type":"Point"}
}