{
  "type": "Feature",
  "properties": {
    "addr:full":"16819 Union Tpke Flushing NY 11366",
    "addr:housenumber":"16819",
    "addr:postcode":"11366",
    "addr:street":"Union Tpke",
    "iso:country":"US",
    "sg:address":"16819 Union Tpke",
    "sg:city":"Flushing",
    "sg:classifiers":[
        {
            "category":"Restaurant",
            "type":"Food & Drink"
        }
    ],
    "sg:menulink":"http://www.allmenus.com/ny/queens/23672-vincenzos/menu/",
    "sg:phone":"+1 718 969 7434",
    "sg:postcode":"11366",
    "sg:province":"NY",
    "sg:tags":[
        "american",
        "pizza"
    ],
    "wof:name":"Vincenzo's",
    "wof:placetype":"venue"
},
  "geometry": {"coordinates":[-73.80004599999999,40.72305],"type":"Point"}
}