{
  "type": "Feature",
  "properties": {
    "iso:country":"US",
    "sg:address":"45 Rockefeller Plz",
    "sg:city":"New York",
    "sg:classifiers":[
        {
            "category":"Professional",
            "subcategory":"Business Services",
            "type":"Services"
        }
    ],
    "sg:phone":"+1 212 757 5640",
    "sg:postcode":"10020",
    "sg:province":"NY",
    "sg:tags":[
        "convention",
        "meeting",
        "facility"
    ],
    "wof:name":"Japan Convention Bur",
    "wof:placetype":"venue"
},
  "geometry": {"coordinates":[-73.97800100000001,40.759514],"type":"Point"}
}