{
  "type": "Feature",
  "properties": {
    "addr:full":"330 E 46th St New York NY 10017",
    "addr:housenumber":"330",
    "addr:postcode":"10017",
    "addr:street":"E 46Th St",
    "iso:country":"US",
    "sg:address":"330 E 46th St",
    "sg:city":"New York",
    "sg:classifiers":[
        {
            "category":"Professional",
            "subcategory":"Management & Consulting",
            "type":"Services"
        }
    ],
    "sg:phone":"+1 917 587 7311",
    "sg:postcode":"10017",
    "sg:province":"NY",
    "sg:tags":[
        "consultant",
        "business"
    ],
    "wof:name":"Iintegrate LLC",
    "wof:placetype":"venue"
},
  "geometry": {"coordinates":[-73.968496,40.751589],"type":"Point"}
}