{
  "type": "Feature",
  "properties": {
    "addr:full":"8444 Eliot Ave Middle Village NY 11379",
    "addr:housenumber":"8444",
    "addr:postcode":"11379",
    "addr:street":"Eliot Ave",
    "iso:country":"US",
    "sg:address":"8444 Eliot Ave",
    "sg:city":"Middle Village",
    "sg:classifiers":[
        {
            "category":"Retail",
            "subcategory":"Laundry & Dry Cleaning",
            "type":"Services"
        }
    ],
    "sg:phone":"+1 718 424 3343",
    "sg:postcode":"11379",
    "sg:province":"NY",
    "wof:name":"Fantastic Dry Cleaning Incorporated",
    "wof:placetype":"venue"
},
  "geometry": {"coordinates":[-73.873925,40.727284],"type":"Point"}
}