{
  "type": "Feature",
  "properties": {
    "iso:country":"US",
    "sg:address":"263 Cumberland St",
    "sg:city":"Brooklyn",
    "sg:classifiers":[
        {
            "category":"Shopping",
            "subcategory":"Books",
            "type":"Retail Goods"
        }
    ],
    "sg:phone":"+1   ",
    "sg:postcode":"11205",
    "sg:province":"NY",
    "wof:name":"Blauner Books",
    "wof:placetype":"venue"
},
  "geometry": {"coordinates":[-73.972892,40.689275],"type":"Point"}
}