{
  "type": "Feature",
  "properties": {
    "addr:full":"19 Acorn Ter New Rochelle NY 10801",
    "addr:housenumber":"19",
    "addr:postcode":"10801",
    "addr:street":"Acorn Ter",
    "iso:country":"US",
    "sg:address":"19 Acorn Ter",
    "sg:city":"New Rochelle",
    "sg:classifiers":[
        {
            "category":"Building & Trades",
            "subcategory":"Construction",
            "type":"Services"
        }
    ],
    "sg:phone":"+1 914 934 0524",
    "sg:postcode":"10801",
    "sg:province":"NY",
    "sg:tags":[
        "hanging",
        "business",
        "contractor"
    ],
    "wof:name":"Fcr",
    "wof:placetype":"venue"
},
  "geometry": {"coordinates":[-73.775199,40.91941],"type":"Point"}
}