{
  "type": "Feature",
  "properties": {
    "iso:country":"US",
    "sg:address":"128 Islip Blvd",
    "sg:city":"Islip Terrace",
    "sg:classifiers":[
        {
            "category":"Building & Trades",
            "subcategory":"Plumbing",
            "type":"Services"
        }
    ],
    "sg:phone":"+1 631 581 1717",
    "sg:postcode":"11752",
    "sg:province":"NY",
    "sg:tags":[
        "contractor"
    ],
    "wof:name":"Hancock Cooling Corp",
    "wof:placetype":"venue"
},
  "geometry": {"coordinates":[-73.196934,40.743716],"type":"Point"}
}