{
  "type": "Feature",
  "properties": {
    "iso:country":"US",
    "sg:address":"142 Sullivan St",
    "sg:city":"New York",
    "sg:classifiers":[
        {
            "category":"Shopping",
            "subcategory":"Clothing, Apparel, & Fashions",
            "type":"Retail Goods"
        }
    ],
    "sg:phone":"+1   ",
    "sg:postcode":"10012",
    "sg:province":"NY",
    "sg:tags":[
        "store"
    ],
    "wof:name":"Stork Club Inc",
    "wof:placetype":"venue"
},
  "geometry": {"coordinates":[-74.00175299999999,40.72722],"type":"Point"}
}