{
  "type": "Feature",
  "properties": {
    "addr:full":"2201 Hempstead Tpke East Meadow NY 11554",
    "addr:housenumber":"2201",
    "addr:postcode":"11554",
    "addr:street":"Hempstead Tpke",
    "iso:country":"US",
    "sg:address":"2201 Hempstead Tpke",
    "sg:city":"East Meadow",
    "sg:classifiers":[
        {
            "category":"Health Services",
            "subcategory":"Hospital",
            "type":"Services"
        }
    ],
    "sg:phone":"+1 516 572 0723",
    "sg:postcode":"11554",
    "sg:province":"NY",
    "sg:website":"www.northshorelij.com",
    "wof:name":"NORTH SHORE LIJ PHYSICIAN REFERRAL",
    "wof:placetype":"venue"
},
  "geometry": {"coordinates":[-73.554401,40.725437],"type":"Point"}
}