{
  "type": "Feature",
  "properties": {
    "addr:full":"453 Robinson Ave Newburgh NY 12550",
    "addr:housenumber":"453",
    "addr:postcode":"12550",
    "addr:street":"Robinson Ave",
    "iso:country":"US",
    "sg:address":"453 Robinson Ave",
    "sg:city":"Newburgh",
    "sg:classifiers":[
        {
            "category":"Autos & Motor Vehicles",
            "subcategory":"Automobile Sales",
            "type":"Retail Goods"
        }
    ],
    "sg:phone":"+1 845 561 2620",
    "sg:postcode":"12550",
    "sg:province":"NY",
    "sg:tags":[
        "new",
        "car"
    ],
    "wof:name":"Second Generation Wholesalers",
    "wof:placetype":"venue"
},
  "geometry": {"coordinates":[-74.01989,41.517209],"type":"Point"}
}