{
  "type": "Feature",
  "properties": {
    "addr:full":"6231 Happy Valley Rd Verona NY 13478",
    "addr:housenumber":"6231",
    "addr:postcode":"13478",
    "addr:street":"Happy Valley Rd",
    "iso:country":"US",
    "sg:address":"6231 Happy Valley Rd",
    "sg:city":"Verona",
    "sg:classifiers":[
        {
            "category":"Shopping",
            "subcategory":"Jewelry",
            "type":"Retail Goods"
        }
    ],
    "sg:phone":"+1   ",
    "sg:postcode":"13478",
    "sg:province":"NY",
    "wof:name":"Western Vision",
    "wof:placetype":"venue"
},
  "geometry": {"coordinates":[-75.62880800000001,43.181023],"type":"Point"}
}