{
  "type": "Feature",
  "properties": {
    "addr:full":"451 Fishkill Ave Beacon NY 12508",
    "addr:housenumber":"451",
    "addr:postcode":"12508",
    "addr:street":"Fishkill Ave",
    "iso:country":"US",
    "sg:address":"451 Fishkill Ave",
    "sg:city":"Beacon",
    "sg:classifiers":[
        {
            "category":"Shopping",
            "subcategory":"Department Store",
            "type":"Retail Goods"
        }
    ],
    "sg:phone":"+1 845 838 0058",
    "sg:postcode":"12508",
    "sg:province":"NY",
    "sg:website":"www.familydollar.com",
    "wof:name":"Family Dollar",
    "wof:placetype":"venue"
},
  "geometry": {"coordinates":[-73.950423,41.513337],"type":"Point"}
}