{
  "type": "Feature",
  "properties": {
    "addr:full":"353 Windsor Hwy New Windsor NY 12553",
    "addr:housenumber":"353",
    "addr:postcode":"12553",
    "addr:street":"Windsor Hwy",
    "iso:country":"US",
    "sg:address":"353 Windsor Hwy",
    "sg:city":"New Windsor",
    "sg:classifiers":[
        {
            "category":"Banks & Credit Unions",
            "subcategory":"Bank",
            "type":"Services"
        }
    ],
    "sg:phone":"+1 845 565 5380",
    "sg:postcode":"12553",
    "sg:province":"NY",
    "sg:tags":[
        "state",
        "commercial"
    ],
    "wof:name":"Bank Of New York",
    "wof:placetype":"venue"
},
  "geometry": {"coordinates":[-74.051665,41.463802],"type":"Point"}
}