{
  "type": "Feature",
  "properties": {
    "addr:full":"87 N Main St Mechanicville NY 12118",
    "addr:housenumber":"87",
    "addr:postcode":"12118",
    "addr:street":"N Main St",
    "iso:country":"US",
    "sg:address":"87 N Main St",
    "sg:city":"Mechanicville",
    "sg:classifiers":[
        {
            "category":"Restaurant",
            "type":"Food & Drink"
        }
    ],
    "sg:phone":"+1 518 664 5323",
    "sg:postcode":"12118",
    "sg:province":"NY",
    "sg:website":"www.cloverleaftavern.com",
    "wof:name":"Clover Leaf Tavern",
    "wof:placetype":"venue"
},
  "geometry": {"coordinates":[-73.684793,42.904917],"type":"Point"}
}