{
  "type": "Feature",
  "properties": {
    "iso:country":"US",
    "sg:address":"221 S Warren St",
    "sg:city":"Syracuse",
    "sg:classifiers":[
        {
            "category":"Professional",
            "subcategory":"Lawyer & Legal Services",
            "type":"Services"
        }
    ],
    "sg:phone":"+1 315 637 0108",
    "sg:postcode":"13202",
    "sg:province":"NY",
    "sg:tags":[
        "attorney"
    ],
    "wof:name":"Charles S Edwards",
    "wof:placetype":"venue"
},
  "geometry": {"coordinates":[-76.150682,43.048848],"type":"Point"}
}