{
  "type": "Feature",
  "properties": {
    "addr:full":"111 Sapbush Rd Chenango Forks NY 13746",
    "addr:housenumber":"111",
    "addr:postcode":"13746",
    "addr:street":"Sapbush Rd",
    "iso:country":"US",
    "sg:address":"111 Sapbush Rd",
    "sg:city":"Chenango Forks",
    "sg:classifiers":[
        {
            "category":"Wholesale",
            "subcategory":"Stationery",
            "type":"Manufacturing & Wholesale Goods"
        }
    ],
    "sg:phone":"+1 607 656 7679",
    "sg:postcode":"13746",
    "sg:province":"NY",
    "sg:tags":[
        "packaging",
        "material"
    ],
    "wof:name":"Markham Packaging Co",
    "wof:placetype":"venue"
},
  "geometry": {"coordinates":[-75.85494,42.298309],"type":"Point"}
}