{
  "type": "Feature",
  "properties": {
    "iso:country":"US",
    "sg:address":"50 Legion Dr",
    "sg:city":"Valhalla",
    "sg:classifiers":[
        {
            "category":"Health Services",
            "subcategory":"Doctor",
            "type":"Services"
        }
    ],
    "sg:phone":"+1 914 949 2713",
    "sg:postcode":"10595",
    "sg:province":"NY",
    "wof:name":"Jessica Hilburg DDS",
    "wof:placetype":"venue"
},
  "geometry": {"coordinates":[-73.779169,41.0706],"type":"Point"}
}