{
  "type": "Feature",
  "properties": {
    "iso:country":"US",
    "sg:address":"13221 41st Avenue",
    "sg:city":"Flushing",
    "sg:classifiers":[
        {
            "category":"Shopping",
            "subcategory":"Pharmacy",
            "type":"Retail Goods"
        }
    ],
    "sg:phone":"+1 718 353 5948",
    "sg:postcode":"11355",
    "sg:province":"NY",
    "sg:tags":[
        "drugstore"
    ],
    "wof:name":"Elizabeth Pharmacy",
    "wof:placetype":"venue"
},
  "geometry": {"coordinates":[-73.833513,40.756544],"type":"Point"}
}