{
  "type": "Feature",
  "properties": {
    "addr:full":"243 India St Brooklyn NY 11222",
    "addr:housenumber":"243",
    "addr:postcode":"11222",
    "addr:street":"India St",
    "iso:country":"US",
    "sg:address":"243 India St",
    "sg:city":"Brooklyn",
    "sg:classifiers":[
        {
            "category":"Real Estate",
            "subcategory":"Real Estate Services",
            "type":"Services"
        }
    ],
    "sg:phone":"+1 800 750 5834",
    "sg:postcode":"11222",
    "sg:province":"NY",
    "wof:name":"Strauss Ted Rl Est",
    "wof:placetype":"venue"
},
  "geometry": {"coordinates":[-73.950104,40.732899],"type":"Point"}
}