{
  "type": "Feature",
  "properties": {
    "addr:full":"1135 Brookdale Ave Bay Shore NY 11706",
    "addr:housenumber":"1135",
    "addr:postcode":"11706",
    "addr:street":"Brookdale Ave",
    "iso:country":"US",
    "sg:address":"1135 Brookdale Ave",
    "sg:city":"Bay Shore",
    "sg:classifiers":[
        {
            "category":"Building & Trades",
            "subcategory":"Construction",
            "type":"Services"
        }
    ],
    "sg:phone":"+1 631 236 2055",
    "sg:postcode":"11706",
    "sg:province":"NY",
    "sg:tags":[
        "house"
    ],
    "wof:name":"J Foy Construction",
    "wof:placetype":"venue"
},
  "geometry": {"coordinates":[-73.302668,40.746772],"type":"Point"}
}