{
  "type": "Feature",
  "properties": {
    "iso:country":"US",
    "sg:address":"808 Garnsey Rd",
    "sg:city":"Palmyra",
    "sg:classifiers":[
        {
            "category":"Building & Trades",
            "subcategory":"Plumbing",
            "type":"Services"
        }
    ],
    "sg:phone":"+1 315 597 1154",
    "sg:postcode":"14522",
    "sg:province":"NY",
    "sg:tags":[
        "heating",
        "contractor"
    ],
    "wof:name":"M P Hedges Plumbing Heating",
    "wof:placetype":"venue"
},
  "geometry": {"coordinates":[-77.181479,43.048873],"type":"Point"}
}