{
  "type": "Feature",
  "properties": {
    "iso:country":"US",
    "sg:address":"85 Pickwick Dr",
    "sg:city":"Rochester",
    "sg:classifiers":[
        {
            "category":"Organizations",
            "subcategory":"Religious Organization",
            "type":"Services"
        }
    ],
    "sg:phone":"+1 585 244 6993",
    "sg:postcode":"14618",
    "sg:province":"NY",
    "sg:tags":[
        "clergy"
    ],
    "wof:name":"Wesley Perkins",
    "wof:placetype":"venue"
},
  "geometry": {"coordinates":[-77.54336600000001,43.110992],"type":"Point"}
}