{
  "type": "Feature",
  "properties": {
    "addr:full":"1950 New Michigan Rd Canandaigua NY 14424",
    "addr:housenumber":"1950",
    "addr:postcode":"14424",
    "addr:street":"New Michigan Rd",
    "iso:country":"US",
    "sg:address":"1950 New Michigan Rd",
    "sg:city":"Canandaigua",
    "sg:phone":"+1 585 394 3131",
    "sg:postcode":"14424",
    "sg:province":"NY",
    "sg:tags":[
        "farm",
        "corn"
    ],
    "wof:name":"Dave Emery",
    "wof:placetype":"venue"
},
  "geometry": {"coordinates":[-77.36059400000001,42.938553],"type":"Point"}
}