{
  "type": "Feature",
  "properties": {
    "iso:country":"US",
    "sg:address":"2 Pike Creek Dr",
    "sg:city":"Cohoes",
    "sg:classifiers":[
        {
            "category":"Professional",
            "type":"Services"
        }
    ],
    "sg:phone":"+1 518 687 0723",
    "sg:postcode":"12047",
    "sg:province":"NY",
    "sg:tags":[
        "establishment"
    ],
    "wof:name":"Interclaim Worldwide Claims",
    "wof:placetype":"venue"
},
  "geometry": {"coordinates":[-73.723585,42.790244],"type":"Point"}
}