{
  "type": "Feature",
  "properties": {
    "addr:full":"2904 US Hwy 13 Pulaski NY 13142",
    "addr:housenumber":"2904",
    "addr:postcode":"13142",
    "addr:street":"Us Hwy 13",
    "iso:country":"US",
    "sg:address":"2904 US Hwy 13",
    "sg:city":"Pulaski",
    "sg:classifiers":[
        {
            "category":"Travel",
            "subcategory":"Campground",
            "type":"Entertainment"
        }
    ],
    "sg:phone":"+1 315 298 2325",
    "sg:postcode":"13142",
    "sg:province":"NY",
    "sg:website":"www.salmonriver.net",
    "wof:name":"Stoney's Pineville Campground",
    "wof:placetype":"venue"
},
  "geometry": {"coordinates":[-76.045699,43.532004],"type":"Point"}
}