{
  "type": "Feature",
  "properties": {
    "addr:full":"168 E Seneca St Sherrill NY 13461",
    "addr:housenumber":"168",
    "addr:postcode":"13461",
    "addr:street":"E Seneca St",
    "iso:country":"US",
    "sg:address":"168 E Seneca St",
    "sg:city":"Sherrill",
    "sg:classifiers":[
        {
            "category":"Organizations",
            "subcategory":"Community Association",
            "type":"Services"
        }
    ],
    "sg:phone":"+1 315 363 3920",
    "sg:postcode":"13461",
    "sg:province":"NY",
    "sg:tags":[
        "military"
    ],
    "wof:name":"American Legion",
    "wof:placetype":"venue"
},
  "geometry": {"coordinates":[-75.597746,43.0769],"type":"Point"}
}