{
  "type": "Feature",
  "properties": {
    "addr:full":"25301 Rockaway Boulevard Suite 13 Rosedale NY 11422",
    "addr:housenumber":"25301;13",
    "addr:postcode":"11422",
    "addr:street":"Rockaway Boulevard Suite",
    "iso:country":"US",
    "sg:address":"25301 Rockaway Boulevard Suite 13",
    "sg:city":"Rosedale",
    "sg:classifiers":[
        {
            "category":"Shopping",
            "subcategory":"Shoes",
            "type":"Retail Goods"
        }
    ],
    "sg:phone":"+1 516 295 0351",
    "sg:postcode":"11422",
    "sg:province":"NY",
    "sg:tags":[
        "store"
    ],
    "wof:name":"Payless Shoesource",
    "wof:placetype":"venue"
},
  "geometry": {"coordinates":[-73.74019199999999,40.63613],"type":"Point"}
}