{
  "type": "Feature",
  "properties": {
    "addr:full":"3344 Baker St Exd Jamestown NY 14701",
    "addr:housenumber":"3344",
    "addr:postcode":"14701",
    "addr:street":"Baker St Exd",
    "iso:country":"US",
    "sg:address":"3344 Baker St Exd",
    "sg:city":"Jamestown",
    "sg:classifiers":[
        {
            "category":"Building & Trades",
            "subcategory":"Electrical",
            "type":"Services"
        }
    ],
    "sg:phone":"+1 716 664 5336",
    "sg:postcode":"14701",
    "sg:province":"NY",
    "sg:tags":[
        "electrical",
        "contractor"
    ],
    "wof:name":"Fsc Systems LLC",
    "wof:placetype":"venue"
},
  "geometry": {"coordinates":[-79.277216,42.074127],"type":"Point"}
}