{
  "type": "Feature",
  "properties": {
    "addr:full":"10 Esquire Rd New City NY 10956",
    "addr:housenumber":"10",
    "addr:postcode":"10956",
    "addr:street":"Esquire Rd",
    "iso:country":"US",
    "sg:address":"10 Esquire Rd",
    "sg:city":"New City",
    "sg:classifiers":[
        {
            "category":"Home & Garden",
            "subcategory":"Home Furnishings",
            "type":"Retail Goods"
        }
    ],
    "sg:phone":"+1 845 634 1907",
    "sg:postcode":"10956",
    "sg:province":"NY",
    "sg:tags":[
        "lighting"
    ],
    "sg:website":"www.gfclighting.com",
    "wof:name":"GFC Lighting Wholesalers Inc",
    "wof:placetype":"venue"
},
  "geometry": {"coordinates":[-73.99336099999999,41.138003],"type":"Point"}
}