{
  "type": "Feature",
  "properties": {
    "iso:country":"US",
    "sg:address":"34 Union St",
    "sg:city":"Cortland",
    "sg:classifiers":[
        {
            "category":"Shopping",
            "subcategory":"Florist",
            "type":"Retail Goods"
        }
    ],
    "sg:phone":"+1 607 756 7290",
    "sg:postcode":"13045",
    "sg:province":"NY",
    "wof:name":"Cortland Florist",
    "wof:placetype":"venue"
},
  "geometry": {"coordinates":[-76.18246499999999,42.592969],"type":"Point"}
}