{
  "type": "Feature",
  "properties": {
    "addr:full":"47 Linda Ln E Riverhead NY 11901",
    "addr:housenumber":"47",
    "addr:postcode":"11901",
    "addr:street":"Linda Ln E",
    "iso:country":"US",
    "sg:address":"47 Linda Ln E",
    "sg:city":"Riverhead",
    "sg:classifiers":[
        {
            "category":"Building & Trades",
            "subcategory":"Landscaping Services",
            "type":"Services"
        }
    ],
    "sg:phone":"+1 631 369 2594",
    "sg:postcode":"11901",
    "sg:province":"NY",
    "sg:tags":[
        "lawn"
    ],
    "wof:name":"C K Martin Inc",
    "wof:placetype":"venue"
},
  "geometry": {"coordinates":[-72.70559900000001,40.974994],"type":"Point"}
}