{
  "type": "Feature",
  "properties": {
    "addr:full":"2401 Monroe Ave Rochester NY 14618",
    "addr:housenumber":"2401",
    "addr:postcode":"14618",
    "addr:street":"Monroe Ave",
    "iso:country":"US",
    "sg:address":"2401 Monroe Ave",
    "sg:city":"Rochester",
    "sg:classifiers":[
        {
            "category":"Social Services",
            "type":"Services"
        }
    ],
    "sg:phone":"+1 585 271 4980",
    "sg:postcode":"14618",
    "sg:province":"NY",
    "sg:tags":[
        "organization",
        "welfare"
    ],
    "sg:website":"www.lutheran-jamestown.org",
    "wof:name":"Grace Lutheran Residential Svc",
    "wof:placetype":"venue"
},
  "geometry": {"coordinates":[-77.554779,43.117471],"type":"Point"}
}