{
  "type": "Feature",
  "properties": {
    "iso:country":"US",
    "sg:address":"42 Greene Ave",
    "sg:city":"Amityville",
    "sg:classifiers":[
        {
            "category":"Health Services",
            "subcategory":"Doctor",
            "type":"Services"
        }
    ],
    "sg:phone":"+1 631 264 1010",
    "sg:postcode":"11701",
    "sg:province":"NY",
    "sg:tags":[
        "dentist"
    ],
    "wof:name":"B Kalman Friedman DDS",
    "wof:placetype":"venue"
},
  "geometry": {"coordinates":[-73.41821899999999,40.678297],"type":"Point"}
}