{
  "type": "Feature",
  "properties": {
    "addr:full":"185 Varick St New York NY 10014",
    "addr:housenumber":"185",
    "addr:postcode":"10014",
    "addr:street":"Varick St",
    "iso:country":"US",
    "sg:address":"185 Varick St",
    "sg:city":"New York",
    "sg:classifiers":[
        {
            "category":"Wholesale",
            "subcategory":"Plants",
            "type":"Manufacturing & Wholesale Goods"
        }
    ],
    "sg:phone":"+1 212 366 6175",
    "sg:postcode":"10014",
    "sg:province":"NY",
    "sg:tags":[
        "import",
        "flower",
        "dried"
    ],
    "wof:name":"Swan Floral International",
    "wof:placetype":"venue"
},
  "geometry": {"coordinates":[-74.00557999999999,40.727256],"type":"Point"}
}