{
  "type": "Feature",
  "properties": {
    "addr:full":"7523 Fort Hamilton Pkwy Brooklyn NY 11228",
    "addr:housenumber":"7523",
    "addr:postcode":"11228",
    "addr:street":"Fort Hamilton Pkwy",
    "iso:country":"US",
    "sg:address":"7523 Fort Hamilton Pkwy",
    "sg:city":"Brooklyn",
    "sg:classifiers":[
        {
            "category":"Health Services",
            "subcategory":"Doctor",
            "type":"Services"
        }
    ],
    "sg:phone":"+1 718 236 1975",
    "sg:postcode":"11228",
    "sg:province":"NY",
    "wof:name":"Robert Graffeo PC",
    "wof:placetype":"venue"
},
  "geometry": {"coordinates":[-74.017081,40.625325],"type":"Point"}
}