{
  "type": "Feature",
  "properties": {
    "addr:full":"6450 Dewey Rd Rome NY 13440",
    "addr:housenumber":"6450",
    "addr:postcode":"13440",
    "addr:street":"Dewey Rd",
    "iso:country":"US",
    "sg:address":"6450 Dewey Rd",
    "sg:city":"Rome",
    "sg:classifiers":[
        {
            "category":"Education",
            "subcategory":"Special Training",
            "type":"Public Place"
        }
    ],
    "sg:phone":"+1 315 336 0154",
    "sg:postcode":"13440",
    "sg:province":"NY",
    "sg:tags":[
        "educational"
    ],
    "sg:website":"http://www.nmdaasset.com",
    "wof:name":"The National Miniature Donkey Association",
    "wof:placetype":"venue"
},
  "geometry": {"coordinates":[-75.467438,43.174519],"type":"Point"}
}