{
  "type": "Feature",
  "properties": {
    "addr:full":"315 Westchester Ave Port Chester NY 10573",
    "addr:housenumber":"315",
    "addr:postcode":"10573",
    "addr:street":"Westchester Ave",
    "iso:country":"US",
    "sg:address":"315 Westchester Ave",
    "sg:city":"Port Chester",
    "sg:classifiers":[
        {
            "category":"Professional",
            "type":"Services"
        }
    ],
    "sg:phone":"+1 914 937 0100",
    "sg:postcode":"10573",
    "sg:province":"NY",
    "sg:tags":[
        "establishment"
    ],
    "wof:name":"Lenat Co",
    "wof:placetype":"venue"
},
  "geometry": {"coordinates":[-73.669781,41.003702],"type":"Point"}
}