{
  "type": "Feature",
  "properties": {
    "addr:full":"855 Central Ave Albany NY 12206",
    "addr:housenumber":"855",
    "addr:postcode":"12206",
    "addr:street":"Central Ave",
    "iso:country":"US",
    "sg:address":"855 Central Ave",
    "sg:city":"Albany",
    "sg:classifiers":[
        {
            "category":"Government",
            "subcategory":"Office",
            "type":"Public Place"
        }
    ],
    "sg:phone":"+1 518 457 1198",
    "sg:postcode":"12206",
    "sg:province":"NY",
    "wof:name":"Labor Management",
    "wof:placetype":"venue"
},
  "geometry": {"coordinates":[-73.787892,42.678194],"type":"Point"}
}