{
  "type": "Feature",
  "properties": {
    "addr:full":"309 E 83rd St New York NY 10028",
    "addr:housenumber":"309",
    "addr:postcode":"10028",
    "addr:street":"E 83Rd St",
    "iso:country":"US",
    "sg:address":"309 E 83rd St",
    "sg:city":"New York",
    "sg:classifiers":[
        {
            "category":"Shopping",
            "subcategory":"Clothing, Apparel, & Fashions",
            "type":"Retail Goods"
        }
    ],
    "sg:phone":"+1   ",
    "sg:postcode":"10028",
    "sg:province":"NY",
    "wof:name":"Golden Star",
    "wof:placetype":"venue"
},
  "geometry": {"coordinates":[-73.950907,40.775074],"type":"Point"}
}