{
  "type": "Feature",
  "properties": {
    "iso:country":"US",
    "sg:address":"10 Prague Ct",
    "sg:city":"Staten Island",
    "sg:classifiers":[
        {
            "category":"Building & Trades",
            "subcategory":"Construction",
            "type":"Services"
        }
    ],
    "sg:phone":"+1 718 966 5431",
    "sg:postcode":"10309",
    "sg:province":"NY",
    "sg:tags":[
        "contractor"
    ],
    "wof:name":"Nagori Contracting Corp",
    "wof:placetype":"venue"
},
  "geometry": {"coordinates":[-74.198634,40.518573],"type":"Point"}
}