{
  "type": "Feature",
  "properties": {
    "addr:full":"2741 Frederick Douglass Blvd New York NY 10039",
    "addr:housenumber":"2741",
    "addr:postcode":"10039",
    "addr:street":"Frederick Douglass Blvd",
    "iso:country":"US",
    "sg:address":"2741 Frederick Douglass Blvd",
    "sg:city":"New York",
    "sg:classifiers":[
        {
            "category":"Food & Beverages",
            "subcategory":"Groceries & Convenience Stores",
            "type":"Retail Goods"
        }
    ],
    "sg:phone":"+1 212 281 6100",
    "sg:postcode":"10039",
    "sg:province":"NY",
    "wof:name":"True Blue Deli Grocery",
    "wof:placetype":"venue"
},
  "geometry": {"coordinates":[-73.94143200000001,40.823547],"type":"Point"}
}