{
  "type": "Feature",
  "properties": {
    "addr:full":"20 Abbott Rd Buffalo NY 14220",
    "addr:housenumber":"20",
    "addr:postcode":"14220",
    "addr:street":"Abbott Rd",
    "iso:country":"US",
    "sg:address":"20 Abbott Rd",
    "sg:city":"Buffalo",
    "sg:classifiers":[
        {
            "category":"Retail",
            "subcategory":"Auto Repair",
            "type":"Services"
        }
    ],
    "sg:phone":"+1 716 825 8678",
    "sg:postcode":"14220",
    "sg:province":"NY",
    "sg:tags":[
        "body",
        "shop",
        "painting",
        "automobile"
    ],
    "wof:name":"Koepnick's Collision",
    "wof:placetype":"venue"
},
  "geometry": {"coordinates":[-78.828598,42.856899],"type":"Point"}
}