{
  "type": "Feature",
  "properties": {
    "addr:full":"1425 Townsend Ave Bronx NY 10452",
    "addr:housenumber":"1425",
    "addr:postcode":"10452",
    "addr:street":"Townsend Ave",
    "iso:country":"US",
    "sg:address":"1425 Townsend Ave",
    "sg:city":"Bronx",
    "sg:classifiers":[
        {
            "category":"Personal",
            "subcategory":"Barber",
            "type":"Services"
        }
    ],
    "sg:phone":"+1 718 537 0294",
    "sg:postcode":"10452",
    "sg:province":"NY",
    "wof:name":"Mi Tierra Barbershop",
    "wof:placetype":"venue"
},
  "geometry": {"coordinates":[-73.91636800000001,40.840464],"type":"Point"}
}