{
  "type": "Feature",
  "properties": {
    "addr:full":"2305 Grand Central Ave A Horseheads NY 14845",
    "addr:housenumber":"2305",
    "addr:postcode":"14845",
    "addr:street":"Grand Central Ave A",
    "iso:country":"US",
    "sg:address":"2305 Grand Central Ave A",
    "sg:city":"Horseheads",
    "sg:classifiers":[
        {
            "category":"Arts & Performance",
            "subcategory":"Dance",
            "type":"Entertainment"
        }
    ],
    "sg:phone":"+1 607 796 2689",
    "sg:postcode":"14845",
    "sg:province":"NY",
    "sg:tags":[
        "instruction",
        "dancing"
    ],
    "wof:name":"Let's Dance",
    "wof:placetype":"venue"
},
  "geometry": {"coordinates":[-76.821831,42.166271],"type":"Point"}
}