{
  "type": "Feature",
  "properties": {
    "iso:country":"US",
    "sg:address":"14101 State Rte 31",
    "sg:city":"Savannah",
    "sg:phone":"+1 315 365 3494",
    "sg:postcode":"13146",
    "sg:province":"NY",
    "sg:tags":[
        "farm",
        "potato"
    ],
    "wof:name":"Jackson Farms Inc",
    "wof:placetype":"venue"
},
  "geometry": {"coordinates":[-76.74815599999999,43.032907],"type":"Point"}
}