{
  "type": "Feature",
  "properties": {
    "iso:country":"US",
    "sg:address":"50 Commonwealth Dr",
    "sg:city":"Wyandanch",
    "sg:classifiers":[
        {
            "category":"Social Services",
            "type":"Services"
        }
    ],
    "sg:phone":"+1 631 789 1777",
    "sg:postcode":"11798",
    "sg:province":"NY",
    "sg:tags":[
        "organization",
        "welfare"
    ],
    "sg:website":"www.redcross.org",
    "wof:name":"American Red Cross",
    "wof:placetype":"venue"
},
  "geometry": {"coordinates":[-73.36121799999999,40.752719],"type":"Point"}
}