{
  "type": "Feature",
  "properties": {
    "iso:country":"US",
    "sg:address":"1060 Broadway Rd",
    "sg:city":"Darien Center",
    "sg:classifiers":[
        {
            "category":"Retail",
            "subcategory":"Repair Shop",
            "type":"Services"
        }
    ],
    "sg:phone":"+1 585 547 9549",
    "sg:postcode":"14040",
    "sg:province":"NY",
    "sg:tags":[
        "welding"
    ],
    "wof:name":"Sanitec Welding Svc",
    "wof:placetype":"venue"
},
  "geometry": {"coordinates":[-78.41175,42.900649],"type":"Point"}
}