{
  "type": "Feature",
  "properties": {
    "addr:full":"8 Bergen St Brooklyn NY 11201",
    "addr:housenumber":"8",
    "addr:postcode":"11201",
    "addr:street":"Bergen St",
    "iso:country":"US",
    "sg:address":"8 Bergen St",
    "sg:city":"Brooklyn",
    "sg:classifiers":[
        {
            "category":"Restaurant",
            "type":"Food & Drink"
        }
    ],
    "sg:phone":"+1   ",
    "sg:postcode":"11201",
    "sg:province":"NY",
    "sg:tags":[
        "mexican"
    ],
    "wof:name":"California Taqueria",
    "wof:placetype":"venue"
},
  "geometry": {"coordinates":[-73.992152,40.687337],"type":"Point"}
}