{
  "type": "Feature",
  "properties": {
    "iso:country":"US",
    "sg:address":"291 Windermere Blvd",
    "sg:city":"Amherst",
    "sg:classifiers":[
        {
            "category":"Education",
            "subcategory":"School",
            "type":"Public Place"
        }
    ],
    "sg:phone":"+1 716 362 4100",
    "sg:postcode":"14226",
    "sg:province":"NY",
    "sg:website":"www.amherstschools.org",
    "wof:name":"Windermere Boulevard Elem Schl",
    "wof:placetype":"venue"
},
  "geometry": {"coordinates":[-78.819463,42.965378],"type":"Point"}
}