{
  "type": "Feature",
  "properties": {
    "iso:country":"US",
    "sg:address":"4701 15th Ave",
    "sg:city":"Brooklyn",
    "sg:classifiers":[
        {
            "category":"Home & Garden",
            "subcategory":"Household Appliances",
            "type":"Retail Goods"
        }
    ],
    "sg:phone":"+1 718 435 4800",
    "sg:postcode":"11219",
    "sg:province":"NY",
    "sg:tags":[
        "equipment",
        "system",
        "cleaners-household-dealers",
        "vacuum"
    ],
    "wof:name":"Elite Central Vacuums Inc",
    "wof:placetype":"venue"
},
  "geometry": {"coordinates":[-73.986549,40.63348],"type":"Point"}
}