{
  "type": "Feature",
  "properties": {
    "iso:country":"US",
    "sg:address":"1944 Rippleton Cross Rd",
    "sg:city":"Cazenovia",
    "sg:classifiers":[
        {
            "category":"Building & Trades",
            "subcategory":"Landscaping Services",
            "type":"Services"
        }
    ],
    "sg:phone":"+1 315 655 9321",
    "sg:postcode":"13035",
    "sg:province":"NY",
    "wof:name":"K C Gardners",
    "wof:placetype":"venue"
},
  "geometry": {"coordinates":[-75.86718399999999,42.911221],"type":"Point"}
}