{
  "type": "Feature",
  "properties": {
    "iso:country":"US",
    "sg:address":"228 N Union St",
    "sg:city":"Olean",
    "sg:classifiers":[
        {
            "category":"Shopping",
            "subcategory":"Musical Instruments",
            "type":"Retail Goods"
        }
    ],
    "sg:phone":"+1 716 372 3704",
    "sg:postcode":"14760",
    "sg:province":"NY",
    "wof:name":"Don's Music Shop",
    "wof:placetype":"venue"
},
  "geometry": {"coordinates":[-78.42982499999999,42.081075],"type":"Point"}
}