{
  "type": "Feature",
  "properties": {
    "addr:full":"544 W Broadway Port Jefferson NY 11777",
    "addr:housenumber":"544",
    "addr:postcode":"11777",
    "addr:street":"W Broadway",
    "iso:country":"US",
    "sg:address":"544 W Broadway",
    "sg:city":"Port Jefferson",
    "sg:classifiers":[
        {
            "category":"Retail",
            "subcategory":"Veterinary Services",
            "type":"Services"
        }
    ],
    "sg:phone":"+1 631 473 0942",
    "sg:postcode":"11777",
    "sg:province":"NY",
    "wof:name":"Countryside Animal Hospital",
    "wof:placetype":"venue"
},
  "geometry": {"coordinates":[-73.08323799999999,40.9453],"type":"Point"}
}