{
  "type": "Feature",
  "properties": {
    "addr:full":"14625 Horace Harding Expy Flushing NY 11367",
    "addr:housenumber":"14625",
    "addr:postcode":"11367",
    "addr:street":"Horace Harding Expy",
    "iso:country":"US",
    "sg:address":"14625 Horace Harding Expy",
    "sg:city":"Flushing",
    "sg:classifiers":[
        {
            "category":"Professional",
            "subcategory":"Computer Services",
            "type":"Services"
        }
    ],
    "sg:phone":"+1 718 359 8889",
    "sg:postcode":"11367",
    "sg:province":"NY",
    "sg:tags":[
        "repair"
    ],
    "wof:name":"Amtech International Trading Inc",
    "wof:placetype":"venue"
},
  "geometry": {"coordinates":[-73.82260100000001,40.741699],"type":"Point"}
}