{
  "type": "Feature",
  "properties": {
    "addr:full":"2167 Newbridge Rd Bellmore NY 11710",
    "addr:housenumber":"2167",
    "addr:postcode":"11710",
    "addr:street":"Newbridge Rd",
    "iso:country":"US",
    "sg:address":"2167 Newbridge Rd",
    "sg:city":"Bellmore",
    "sg:classifiers":[
        {
            "category":"Retail",
            "subcategory":"Repair Shop",
            "type":"Services"
        }
    ],
    "sg:phone":"+1 516 783 3138",
    "sg:postcode":"11710",
    "sg:province":"NY",
    "sg:tags":[
        "welding"
    ],
    "wof:name":"Ken Maksyms Portable Weld Svc",
    "wof:placetype":"venue"
},
  "geometry": {"coordinates":[-73.537719,40.667989],"type":"Point"}
}