{
  "type": "Feature",
  "properties": {
    "addr:full":"61 Gates Ave Lackawanna NY 14218",
    "addr:housenumber":"61",
    "addr:postcode":"14218",
    "addr:street":"Gates Ave",
    "iso:country":"US",
    "sg:address":"61 Gates Ave",
    "sg:city":"Lackawanna",
    "sg:classifiers":[
        {
            "category":"Professional",
            "subcategory":"Business Services",
            "type":"Services"
        }
    ],
    "sg:phone":"+1 716 876 7622",
    "sg:postcode":"14218",
    "sg:province":"NY",
    "sg:tags":[
        "inspection",
        "automotive",
        "parts",
        "assembly"
    ],
    "wof:name":"Accu Sort America Inc",
    "wof:placetype":"venue"
},
  "geometry": {"coordinates":[-78.849129,42.823601],"type":"Point"}
}