{
  "type": "Feature",
  "properties": {
    "addr:full":"400 Post Ave Ste 205 Westbury NY 11590",
    "addr:housenumber":"400",
    "addr:postcode":"11590",
    "addr:street":"Post Ave Ste 205",
    "iso:country":"US",
    "sg:address":"400 Post Ave Ste 205",
    "sg:city":"Westbury",
    "sg:classifiers":[
        {
            "category":"Professional",
            "subcategory":"Lawyer & Legal Services",
            "type":"Services"
        }
    ],
    "sg:phone":"+1 516 334 2120",
    "sg:postcode":"11590",
    "sg:province":"NY",
    "wof:name":"Golombek Lori",
    "wof:placetype":"venue"
},
  "geometry": {"coordinates":[-73.586922,40.762675],"type":"Point"}
}