{
  "type": "Feature",
  "properties": {
    "addr:full":"47 Ontario St Canandaigua NY 14424",
    "addr:housenumber":"47",
    "addr:postcode":"14424",
    "addr:street":"Ontario St",
    "iso:country":"US",
    "sg:address":"47 Ontario St",
    "sg:city":"Canandaigua",
    "sg:classifiers":[
        {
            "category":"Professional",
            "subcategory":"Lawyer & Legal Services",
            "type":"Services"
        }
    ],
    "sg:phone":"+1 585 394 8340",
    "sg:postcode":"14424",
    "sg:province":"NY",
    "sg:tags":[
        "attorney"
    ],
    "wof:name":"Kathleen Curran",
    "wof:placetype":"venue"
},
  "geometry": {"coordinates":[-77.27999,42.888339],"type":"Point"}
}