{
  "type": "Feature",
  "properties": {
    "addr:full":"95 Pulaski St Buffalo NY 14206",
    "addr:housenumber":"95",
    "addr:postcode":"14206",
    "addr:street":"Pulaski St",
    "iso:country":"US",
    "sg:address":"95 Pulaski St",
    "sg:city":"Buffalo",
    "sg:classifiers":[
        {
            "category":"Restaurant",
            "type":"Food & Drink"
        }
    ],
    "sg:phone":"+1   ",
    "sg:postcode":"14206",
    "sg:province":"NY",
    "sg:tags":[
        "pizzeria"
    ],
    "wof:name":"Hollywood Pzza Sndwich Sub LLC",
    "wof:placetype":"venue"
},
  "geometry": {"coordinates":[-78.804847,42.87339],"type":"Point"}
}