{
  "type": "Feature",
  "properties": {
    "addr:full":"35 Walden Pl Rochester NY 14610",
    "addr:housenumber":"35",
    "addr:postcode":"14610",
    "addr:street":"Walden Pl",
    "iso:country":"US",
    "sg:address":"35 Walden Pl",
    "sg:city":"Rochester",
    "sg:classifiers":[
        {
            "category":"Education",
            "subcategory":"Dance Studio",
            "type":"Public Place"
        }
    ],
    "sg:phone":"+1 585 381 5406",
    "sg:postcode":"14610",
    "sg:province":"NY",
    "sg:tags":[
        "instruction",
        "dancing"
    ],
    "wof:name":"Pamela Wilkens White School",
    "wof:placetype":"venue"
},
  "geometry": {"coordinates":[-77.537007,43.139353],"type":"Point"}
}