{
  "type": "Feature",
  "properties": {
    "addr:full":"1405 Ridge Rd E Rochester NY 14621",
    "addr:housenumber":"1405",
    "addr:postcode":"14621",
    "addr:street":"Ridge Rd E",
    "iso:country":"US",
    "sg:address":"1405 Ridge Rd E",
    "sg:city":"Rochester",
    "sg:classifiers":[
        {
            "category":"Building & Trades",
            "subcategory":"Equipment Rental",
            "type":"Services"
        }
    ],
    "sg:phone":"+1 585 339 9100",
    "sg:postcode":"14621",
    "sg:province":"NY",
    "sg:tags":[
        "leasing",
        "furniture"
    ],
    "sg:website":"www.rentway.com",
    "wof:name":"Rent Way",
    "wof:placetype":"venue"
},
  "geometry": {"coordinates":[-77.580792,43.198238],"type":"Point"}
}