{
  "type": "Feature",
  "properties": {
    "iso:country":"US",
    "sg:address":"408 Hunt Ln",
    "sg:city":"Manhasset",
    "sg:classifiers":[
        {
            "category":"Professional",
            "subcategory":"Management & Consulting",
            "type":"Services"
        }
    ],
    "sg:phone":"+1 516 417 6622",
    "sg:postcode":"11030",
    "sg:province":"NY",
    "sg:tags":[
        "consultant",
        "restaurant"
    ],
    "wof:name":"William Lopez Food and drink services",
    "wof:placetype":"venue"
},
  "geometry": {"coordinates":[-73.68604000000001,40.795369],"type":"Point"}
}