{
  "type": "Feature",
  "properties": {
    "addr:full":"935 Sheridan Dr Tonawanda NY 14150",
    "addr:housenumber":"935",
    "addr:postcode":"14150",
    "addr:street":"Sheridan Dr",
    "iso:country":"US",
    "sg:address":"935 Sheridan Dr",
    "sg:city":"Tonawanda",
    "sg:classifiers":[
        {
            "category":"Shopping",
            "subcategory":"Bicycles & Sporting Goods",
            "type":"Retail Goods"
        }
    ],
    "sg:phone":"+1   ",
    "sg:postcode":"14150",
    "sg:province":"NY",
    "sg:tags":[
        "club",
        "repair",
        "golf"
    ],
    "wof:name":"Bill Lindners Golf Service",
    "wof:placetype":"venue"
},
  "geometry": {"coordinates":[-78.899489,42.98059],"type":"Point"}
}