{
  "type": "Feature",
  "properties": {
    "addr:full":"161 Exchange St Albany NY 12205",
    "addr:housenumber":"161",
    "addr:postcode":"12205",
    "addr:street":"Exchange St",
    "iso:country":"US",
    "sg:address":"161 Exchange St",
    "sg:city":"Albany",
    "sg:classifiers":[
        {
            "category":"Building & Trades",
            "subcategory":"Landscaping Services",
            "type":"Services"
        }
    ],
    "sg:phone":"+1 518 458 8030",
    "sg:postcode":"12205",
    "sg:province":"NY",
    "sg:tags":[
        "lawn"
    ],
    "wof:name":"Empire State Companies",
    "wof:placetype":"venue"
},
  "geometry": {"coordinates":[-73.789428,42.689169],"type":"Point"}
}