{
  "type": "Feature",
  "properties": {
    "iso:country":"US",
    "sg:address":"126 University Pl",
    "sg:city":"New York",
    "sg:classifiers":[
        {
            "category":"Shopping",
            "subcategory":"Optical Goods",
            "type":"Retail Goods"
        }
    ],
    "sg:phone":"+1 212 260 2700",
    "sg:postcode":"10003",
    "sg:province":"NY",
    "sg:tags":[
        "optician"
    ],
    "wof:name":"Eye To Eye Vision Ctr",
    "wof:placetype":"venue"
},
  "geometry": {"coordinates":[-73.991913,40.735],"type":"Point"}
}