{
  "type": "Feature",
  "properties": {
    "addr:full":"8 Dearfield Dr Greenwich NY 06831",
    "addr:housenumber":"8",
    "addr:postcode":"06831",
    "addr:street":"Dearfield Dr",
    "iso:country":"US",
    "sg:address":"8 Dearfield Dr",
    "sg:city":"Greenwich",
    "sg:classifiers":[
        {
            "category":"Health Services",
            "subcategory":"Podiatrist",
            "type":"Services"
        },
        {
            "category":"Health Services",
            "subcategory":"Doctor",
            "type":"Services"
        }
    ],
    "sg:phone":"+1 203 661 9311",
    "sg:postcode":"06831",
    "sg:province":"NY",
    "sg:tags":[
        "medical"
    ],
    "wof:name":"P E Kopenhaver DPM",
    "wof:placetype":"venue"
},
  "geometry": {"coordinates":[-73.630628,41.029235],"type":"Point"}
}