{
  "type": "Feature",
  "properties": {
    "addr:full":"88 Woodland Rd Highland Mills NY 10930",
    "addr:housenumber":"88",
    "addr:postcode":"10930",
    "addr:street":"Woodland Rd",
    "iso:country":"US",
    "sg:address":"88 Woodland Rd",
    "sg:city":"Highland Mills",
    "sg:classifiers":[
        {
            "category":"Farming",
            "subcategory":"Dairy Farm",
            "type":"Manufacturing & Wholesale Goods"
        },
        {
            "category":"Wholesale",
            "subcategory":"Dairy",
            "type":"Manufacturing & Wholesale Goods"
        }
    ],
    "sg:phone":"+1 845 928 4817",
    "sg:postcode":"10930",
    "sg:province":"NY",
    "sg:tags":[
        "product"
    ],
    "wof:name":"C & J Dairy Distributors Inc",
    "wof:placetype":"venue"
},
  "geometry": {"coordinates":[-74.109606,41.352218],"type":"Point"}
}