{
  "type": "Feature",
  "properties": {
    "iso:country":"US",
    "sg:address":"19 Alderfield Ln",
    "sg:city":"Melville",
    "sg:classifiers":[
        {
            "category":"Real Estate",
            "subcategory":"Real Estate Agent",
            "type":"Services"
        }
    ],
    "sg:phone":"+1 631 673 1305",
    "sg:postcode":"11747",
    "sg:province":"NY",
    "wof:name":"New Generation Realty Inc",
    "wof:placetype":"venue"
},
  "geometry": {"coordinates":[-73.40196299999999,40.802617],"type":"Point"}
}