{
  "type": "Feature",
  "properties": {
    "iso:country":"US",
    "sg:address":"131 Jericho Tpke",
    "sg:city":"Jericho",
    "sg:classifiers":[
        {
            "category":"Banks & Credit Unions",
            "subcategory":"Financial Services",
            "type":"Services"
        }
    ],
    "sg:phone":"+1 516 333 8500",
    "sg:postcode":"11753",
    "sg:province":"NY",
    "sg:tags":[
        "firm",
        "investment"
    ],
    "wof:name":"Donald E Axinn Companies",
    "wof:placetype":"venue"
},
  "geometry": {"coordinates":[-73.550369,40.785512],"type":"Point"}
}