{
  "type": "Feature",
  "properties": {
    "addr:full":"11 E Park Pl Norwich NY 13815",
    "addr:housenumber":"11",
    "addr:postcode":"13815",
    "addr:street":"E Park Pl",
    "iso:country":"US",
    "sg:address":"11 E Park Pl",
    "sg:city":"Norwich",
    "sg:classifiers":[
        {
            "category":"Professional",
            "subcategory":"Business Services",
            "type":"Services"
        }
    ],
    "sg:phone":"+1 607 336 4031",
    "sg:postcode":"13815",
    "sg:province":"NY",
    "wof:name":"Citizens Telecomm LLC",
    "wof:placetype":"venue"
},
  "geometry": {"coordinates":[-75.523684,42.531891],"type":"Point"}
}