{
  "type": "Feature",
  "properties": {
    "addr:full":"440 Exterior St Bronx NY 10451",
    "addr:housenumber":"440",
    "addr:postcode":"10451",
    "addr:street":"Exterior St",
    "iso:country":"US",
    "sg:address":"440 Exterior St",
    "sg:city":"Bronx",
    "sg:classifiers":[
        {
            "category":"Professional",
            "subcategory":"Advertising",
            "type":"Services"
        }
    ],
    "sg:phone":"+1 718 993 1480",
    "sg:postcode":"10451",
    "sg:province":"NY",
    "wof:name":"Universal Outdoor Inc",
    "wof:placetype":"venue"
},
  "geometry": {"coordinates":[-73.93067499999999,40.817367],"type":"Point"}
}