{
  "type": "Feature",
  "properties": {
    "addr:full":"620 Manida St Bronx NY 10474",
    "addr:housenumber":"620",
    "addr:postcode":"10474",
    "addr:street":"Manida St",
    "iso:country":"US",
    "sg:address":"620 Manida St",
    "sg:city":"Bronx",
    "sg:classifiers":[
        {
            "category":"Autos & Motor Vehicles",
            "subcategory":"Auto Supplies",
            "type":"Retail Goods"
        }
    ],
    "sg:phone":"+1   ",
    "sg:postcode":"10474",
    "sg:province":"NY",
    "wof:name":"L&M 2",
    "wof:placetype":"venue"
},
  "geometry": {"coordinates":[-73.888159,40.813773],"type":"Point"}
}