{
  "type": "Feature",
  "properties": {
    "addr:full":"52 E Halley Ln Central Islip NY 11722",
    "addr:housenumber":"52",
    "addr:postcode":"11722",
    "addr:street":"E Halley Ln",
    "iso:country":"US",
    "sg:address":"52 E Halley Ln",
    "sg:city":"Central Islip",
    "sg:classifiers":[
        {
            "category":"Arts & Performance",
            "subcategory":"Theater",
            "type":"Entertainment"
        }
    ],
    "sg:phone":"+1   ",
    "sg:postcode":"11722",
    "sg:province":"NY",
    "wof:name":"P H Ent",
    "wof:placetype":"venue"
},
  "geometry": {"coordinates":[-73.200776,40.79788],"type":"Point"}
}