{
  "type": "Feature",
  "properties": {
    "addr:full":"77 Rockville Ave Rockville Centre NY 11570",
    "addr:housenumber":"77",
    "addr:postcode":"11570",
    "addr:street":"Rockville Ave",
    "iso:country":"US",
    "sg:address":"77 Rockville Ave",
    "sg:city":"Rockville Centre",
    "sg:classifiers":[
        {
            "category":"Health Services",
            "subcategory":"Doctor",
            "type":"Services"
        }
    ],
    "sg:phone":"+1 516 536 8151",
    "sg:postcode":"11570",
    "sg:province":"NY",
    "sg:tags":[
        "physician",
        "surgeon"
    ],
    "sg:website":"www.tcvsurg.org",
    "wof:name":"Winthrop-University Hospital",
    "wof:placetype":"venue"
},
  "geometry": {"coordinates":[-73.640063,40.650837],"type":"Point"}
}