{
  "type": "Feature",
  "properties": {
    "iso:country":"US",
    "sg:address":"69 Spring St",
    "sg:city":"New York",
    "sg:classifiers":[
        {
            "category":"Deli",
            "type":"Food & Drink"
        }
    ],
    "sg:postcode":"10304",
    "sg:province":"NY",
    "wof:name":"D&D Delicatessen",
    "wof:placetype":"venue"
},
  "geometry": {"coordinates":[-74.094655,40.603539],"type":"Point"}
}