{
  "type": "Feature",
  "properties": {
    "addr:full":"514 77th St Brooklyn NY 11209",
    "addr:housenumber":"514",
    "addr:postcode":"11209",
    "addr:street":"77Th St",
    "iso:country":"US",
    "sg:address":"514 77th St",
    "sg:city":"Brooklyn",
    "sg:classifiers":[
        {
            "category":"Professional",
            "type":"Services"
        }
    ],
    "sg:phone":"+1   ",
    "sg:postcode":"11209",
    "sg:province":"NY",
    "wof:name":"Be Nice Inc",
    "wof:placetype":"venue"
},
  "geometry": {"coordinates":[-74.021197,40.626688],"type":"Point"}
}