{
  "type": "Feature",
  "properties": {
    "iso:country":"US",
    "sg:address":"215 Main St E",
    "sg:city":"Rochester",
    "sg:classifiers":[
        {
            "category":"Personal",
            "subcategory":"Beauty Salon",
            "type":"Services"
        }
    ],
    "sg:phone":"+1 585 335 9780",
    "sg:postcode":"14604",
    "sg:province":"NY",
    "wof:name":"Trend Waves",
    "wof:placetype":"venue"
},
  "geometry": {"coordinates":[-77.607056,43.156875],"type":"Point"}
}