{
  "type": "Feature",
  "properties": {
    "addr:full":"385 Tompkins Ave Brooklyn NY 11216",
    "addr:housenumber":"385",
    "addr:postcode":"11216",
    "addr:street":"Tompkins Ave",
    "iso:country":"US",
    "sg:address":"385 Tompkins Ave",
    "sg:city":"Brooklyn",
    "sg:classifiers":[
        {
            "category":"Food & Beverages",
            "subcategory":"Groceries & Convenience Stores",
            "type":"Retail Goods"
        }
    ],
    "sg:phone":"+1   ",
    "sg:postcode":"11216",
    "sg:province":"NY",
    "wof:name":"Sajoma Grocery",
    "wof:placetype":"venue"
},
  "geometry": {"coordinates":[-73.944012,40.68431],"type":"Point"}
}