{
  "type": "Feature",
  "properties": {
    "addr:full":"14 Pine Tree Rd Southampton NY 11968",
    "addr:housenumber":"14",
    "addr:postcode":"11968",
    "addr:street":"Pine Tree Rd",
    "iso:country":"US",
    "sg:address":"14 Pine Tree Rd",
    "sg:city":"Southampton",
    "sg:classifiers":[
        {
            "category":"Building & Trades",
            "subcategory":"Construction",
            "type":"Services"
        }
    ],
    "sg:phone":"+1 631 287 5167",
    "sg:postcode":"11968",
    "sg:province":"NY",
    "sg:tags":[
        "contractor"
    ],
    "wof:name":"D Oliver Contracting",
    "wof:placetype":"venue"
},
  "geometry": {"coordinates":[-72.38835899999999,40.964022],"type":"Point"}
}