{
  "type": "Feature",
  "properties": {
    "addr:full":"57 Old Rte 9w New Windsor NY 12553",
    "addr:housenumber":"57",
    "addr:postcode":"12553",
    "addr:street":"Old Rte 9W",
    "iso:country":"US",
    "sg:address":"57 Old Rte 9w",
    "sg:city":"New Windsor",
    "sg:classifiers":[
        {
            "category":"Autos & Motor Vehicles",
            "subcategory":"Automobile Sales",
            "type":"Retail Goods"
        }
    ],
    "sg:phone":"+1 845 471 2919",
    "sg:postcode":"12553",
    "sg:province":"NY",
    "sg:tags":[
        "car",
        "dealer"
    ],
    "wof:name":"Pachyderms Plus Inc",
    "wof:placetype":"venue"
},
  "geometry": {"coordinates":[-74.01627999999999,41.471983],"type":"Point"}
}