{
  "type": "Feature",
  "properties": {
    "addr:full":"862 Union St Brooklyn NY 11215",
    "addr:housenumber":"862",
    "addr:postcode":"11215",
    "addr:street":"Union St",
    "iso:country":"US",
    "sg:address":"862 Union St",
    "sg:city":"Brooklyn",
    "sg:classifiers":[
        {
            "category":"Wholesale",
            "subcategory":"Apparel",
            "type":"Manufacturing & Wholesale Goods"
        }
    ],
    "sg:phone":"+1 718 636 5093",
    "sg:postcode":"11215",
    "sg:province":"NY",
    "sg:tags":[
        "clothing"
    ],
    "wof:name":"Monsters With Sideburns",
    "wof:placetype":"venue"
},
  "geometry": {"coordinates":[-73.974632,40.674265],"type":"Point"}
}