{
  "type": "Feature",
  "properties": {
    "addr:full":"15718 88th Street Howard Beach NY 11414",
    "addr:housenumber":"15718",
    "addr:postcode":"11414",
    "addr:street":"88Th Street",
    "iso:country":"US",
    "sg:address":"15718 88th Street",
    "sg:city":"Howard Beach",
    "sg:classifiers":[
        {
            "category":"Building & Trades",
            "subcategory":"Construction",
            "type":"Services"
        }
    ],
    "sg:phone":"+1 718 845 7913",
    "sg:postcode":"11414",
    "sg:province":"NY",
    "sg:tags":[
        "contractor"
    ],
    "wof:name":"Arc-Matic Corporation",
    "wof:placetype":"venue"
},
  "geometry": {"coordinates":[-73.84545199999999,40.661557],"type":"Point"}
}