{
  "type": "Feature",
  "properties": {
    "iso:country":"US",
    "sg:address":"198 Main St",
    "sg:city":"Goshen",
    "sg:classifiers":[
        {
            "category":"Professional",
            "subcategory":"Lawyer & Legal Services",
            "type":"Services"
        }
    ],
    "sg:phone":"+1 845 294 5421",
    "sg:postcode":"10924",
    "sg:province":"NY",
    "sg:tags":[
        "attorney"
    ],
    "wof:name":"John G Meehan",
    "wof:placetype":"venue"
},
  "geometry": {"coordinates":[-74.32100199999999,41.402833],"type":"Point"}
}