{
  "type": "Feature",
  "properties": {
    "addr:full":"273 E 149th St Bronx NY 10451",
    "addr:housenumber":"273",
    "addr:postcode":"10451",
    "addr:street":"E 149Th St",
    "iso:country":"US",
    "sg:address":"273 E 149th St",
    "sg:city":"Bronx",
    "sg:classifiers":[
        {
            "category":"Personal",
            "subcategory":"Barber",
            "type":"Services"
        }
    ],
    "sg:phone":"+1 718 585 5611",
    "sg:postcode":"10451",
    "sg:province":"NY",
    "wof:name":"Whos First Barbershop II",
    "wof:placetype":"venue"
},
  "geometry": {"coordinates":[-73.91957499999999,40.816644],"type":"Point"}
}