{
  "type": "Feature",
  "properties": {
    "addr:full":"8037 State Hwy 32 Cairo NY 12414",
    "addr:housenumber":"8037",
    "addr:postcode":"12414",
    "addr:street":"State Hwy 32",
    "iso:country":"US",
    "sg:address":"8037 State Hwy 32",
    "sg:city":"Cairo",
    "sg:classifiers":[
        {
            "category":"Retail",
            "subcategory":"Auto Repair",
            "type":"Services"
        }
    ],
    "sg:phone":"+1 518 622 9934",
    "sg:postcode":"12414",
    "sg:province":"NY",
    "sg:tags":[
        "transmission",
        "automotive"
    ],
    "wof:name":"J R Transmissions",
    "wof:placetype":"venue"
},
  "geometry": {"coordinates":[-74.012444,42.315895],"type":"Point"}
}