{
  "type": "Feature",
  "properties": {
    "iso:country":"US",
    "sg:address":"108 W 44th St",
    "sg:city":"New York",
    "sg:classifiers":[
        {
            "category":"Restaurant",
            "type":"Food & Drink"
        }
    ],
    "sg:phone":"+1 212 302 0707",
    "sg:postcode":"10036",
    "sg:province":"NY",
    "sg:tags":[
        "sushi",
        "bar",
        "japanese"
    ],
    "sg:website":"www.sushizen-ny.com",
    "wof:name":"Sushi Zen",
    "wof:placetype":"venue"
},
  "geometry": {"coordinates":[-73.983617,40.75632],"type":"Point"}
}