{
  "type": "Feature",
  "properties": {
    "addr:full":"224 Tompkins Ave Brooklyn NY 11216",
    "addr:housenumber":"224",
    "addr:postcode":"11216",
    "addr:street":"Tompkins Ave",
    "iso:country":"US",
    "sg:address":"224 Tompkins Ave",
    "sg:city":"Brooklyn",
    "sg:classifiers":[
        {
            "category":"Food & Beverages",
            "subcategory":"Groceries & Convenience Stores",
            "type":"Retail Goods"
        }
    ],
    "sg:phone":"+1 718 599 2515",
    "sg:postcode":"11216",
    "sg:province":"NY",
    "wof:name":"M & M Supermarket",
    "wof:placetype":"venue"
},
  "geometry": {"coordinates":[-73.94560199999999,40.691101],"type":"Point"}
}