{
  "type": "Feature",
  "properties": {
    "iso:country":"US",
    "sg:address":"1727 Veterans Hwy",
    "sg:city":"Islandia",
    "sg:classifiers":[
        {
            "category":"Health Services",
            "subcategory":"Dentist",
            "type":"Services"
        }
    ],
    "sg:phone":"+1 631 232 1400",
    "sg:postcode":"11749",
    "sg:province":"NY",
    "wof:name":"Suffolk County Dental Soc",
    "wof:placetype":"venue"
},
  "geometry": {"coordinates":[-73.176804,40.802799],"type":"Point"}
}