{
  "type": "Feature",
  "properties": {
    "iso:country":"US",
    "sg:address":"4345 Clear View Dr",
    "sg:city":"Geneseo",
    "sg:classifiers":[
        {
            "category":"Building & Trades",
            "subcategory":"Construction",
            "type":"Services"
        }
    ],
    "sg:phone":"+1 585 243 6838",
    "sg:postcode":"14454",
    "sg:province":"NY",
    "sg:tags":[
        "carpenter"
    ],
    "wof:name":"Carpenter Nancy & Ro",
    "wof:placetype":"venue"
},
  "geometry": {"coordinates":[-77.779579,42.797649],"type":"Point"}
}