{
  "type": "Feature",
  "properties": {
    "iso:country":"US",
    "sg:address":"1926 Bath Ave",
    "sg:city":"Brooklyn",
    "sg:classifiers":[
        {
            "category":"Food & Beverages",
            "subcategory":"Candy",
            "type":"Retail Goods"
        },
        {
            "category":"Coffee & Tea",
            "type":"Food & Drink"
        },
        {
            "category":"Professional",
            "subcategory":"Business Services",
            "type":"Services"
        }
    ],
    "sg:phone":"+1 718 513 6355",
    "sg:postcode":"11214",
    "sg:province":"NY",
    "sg:tags":[
        "delivery",
        "dessert"
    ],
    "sg:website":"www.yatyatsweet.com",
    "wof:name":"Yat Yat Sweet",
    "wof:placetype":"venue"
},
  "geometry": {"coordinates":[-74.003123,40.601978],"type":"Point"}
}