{
  "type": "Feature",
  "properties": {
    "addr:full":"4 Court Sq Long Island City NY 11120",
    "addr:housenumber":"4",
    "addr:postcode":"11120",
    "addr:street":"Court Sq",
    "iso:country":"US",
    "sg:address":"4 Court Sq",
    "sg:city":"Long Island City",
    "sg:classifiers":[
        {
            "category":"Wholesale",
            "subcategory":"Durable Goods & Equipment",
            "type":"Manufacturing & Wholesale Goods"
        }
    ],
    "sg:phone":"+1 718 786 7812",
    "sg:postcode":"11120",
    "sg:province":"NY",
    "sg:tags":[
        "importer"
    ],
    "wof:name":"Architectural Stone Source Inc",
    "wof:placetype":"venue"
},
  "geometry": {"coordinates":[-73.943618,40.745931],"type":"Point"}
}