{
  "type": "Feature",
  "properties": {
    "addr:full":"3640 Union Street Flushing NY 11354",
    "addr:housenumber":"3640",
    "addr:postcode":"11354",
    "addr:street":"Union Street",
    "iso:country":"US",
    "sg:address":"3640 Union Street",
    "sg:city":"Flushing",
    "sg:classifiers":[
        {
            "category":"Education",
            "subcategory":"Kindergarten",
            "type":"Public Place"
        }
    ],
    "sg:phone":"+1 718 460 0096",
    "sg:postcode":"11354",
    "sg:province":"NY",
    "sg:tags":[
        "school",
        "driving"
    ],
    "wof:name":"Mon Ami Driving School",
    "wof:placetype":"venue"
},
  "geometry": {"coordinates":[-73.82491400000001,40.766769],"type":"Point"}
}