{
  "type": "Feature",
  "properties": {
    "iso:country":"US",
    "sg:address":"2 Kahan Dr",
    "sg:city":"Monroe",
    "sg:classifiers":[
        {
            "category":"Professional",
            "subcategory":"Business Services",
            "type":"Services"
        }
    ],
    "sg:phone":"+1 845 783 4198",
    "sg:postcode":"10950",
    "sg:province":"NY",
    "sg:tags":[
        "interior",
        "decorating"
    ],
    "wof:name":"Azar Decorating Inc",
    "wof:placetype":"venue"
},
  "geometry": {"coordinates":[-74.16122,41.33828],"type":"Point"}
}