{
  "type": "Feature",
  "properties": {
    "iso:country":"US",
    "sg:address":"351 Plandome Rd Ste 2",
    "sg:city":"Manhasset",
    "sg:classifiers":[
        {
            "category":"Real Estate",
            "subcategory":"Real Estate Services",
            "type":"Services"
        },
        {
            "category":"Real Estate",
            "subcategory":"Real Estate Agent",
            "type":"Services"
        }
    ],
    "sg:phone":"+1 516 627 9191",
    "sg:postcode":"11030",
    "sg:province":"NY",
    "sg:tags":[
        "buyer",
        "management",
        "broker"
    ],
    "wof:name":"Manhasset Realty",
    "wof:placetype":"venue"
},
  "geometry": {"coordinates":[-73.69967699999999,40.797473],"type":"Point"}
}