{
  "type": "Feature",
  "properties": {
    "addr:full":"1 Hanson Pl Ste 1205 Brooklyn NY 11243",
    "addr:housenumber":"1",
    "addr:postcode":"11243",
    "addr:street":"Hanson Pl Ste 1205",
    "iso:country":"US",
    "sg:address":"1 Hanson Pl Ste 1205",
    "sg:city":"Brooklyn",
    "sg:classifiers":[
        {
            "category":"Health Services",
            "subcategory":"Doctor",
            "type":"Services"
        }
    ],
    "sg:phone":"+1 718 230 5423",
    "sg:postcode":"11243",
    "sg:province":"NY",
    "wof:name":"Polavarapu Tulasi MD",
    "wof:placetype":"venue"
},
  "geometry": {"coordinates":[-73.977997,40.685001],"type":"Point"}
}