{
  "type": "Feature",
  "properties": {
    "iso:country":"US",
    "sg:address":"1530 Bowen Rd",
    "sg:city":"Elma",
    "sg:classifiers":[
        {
            "category":"Communications",
            "type":"Services"
        }
    ],
    "sg:phone":"+1 716 674 6018",
    "sg:postcode":"14059",
    "sg:province":"NY",
    "wof:name":"Matteo Communications",
    "wof:placetype":"venue"
},
  "geometry": {"coordinates":[-78.636673,42.81584],"type":"Point"}
}