{
  "type": "Feature",
  "properties": {
    "iso:country":"US",
    "sg:address":"325 Park Avenue",
    "sg:city":"New York",
    "sg:classifiers":[
        {
            "category":"Place Of Worship",
            "subcategory":"Church",
            "type":"Public Place"
        }
    ],
    "sg:phone":"+1 212 378 0222",
    "sg:postcode":"10022",
    "sg:province":"NY",
    "sg:website":"www.stbarts.org",
    "wof:name":"St Bartholomew's Church",
    "wof:placetype":"venue"
},
  "geometry": {"coordinates":[-73.97358699999999,40.757506],"type":"Point"}
}