{
  "type": "Feature",
  "properties": {
    "addr:full":"116 Fremont St Gloversville NY 12078",
    "addr:housenumber":"116",
    "addr:postcode":"12078",
    "addr:street":"Fremont St",
    "iso:country":"US",
    "sg:address":"116 Fremont St",
    "sg:city":"Gloversville",
    "sg:classifiers":[
        {
            "category":"Retail",
            "subcategory":"Auto Repair",
            "type":"Services"
        }
    ],
    "sg:phone":"+1   ",
    "sg:postcode":"12078",
    "sg:province":"NY",
    "sg:tags":[
        "general"
    ],
    "wof:name":"Lennys Auto Service",
    "wof:placetype":"venue"
},
  "geometry": {"coordinates":[-74.34296500000001,43.04691],"type":"Point"}
}