{
  "type": "Feature",
  "properties": {
    "iso:country":"US",
    "sg:address":"581 Livingston Ave",
    "sg:city":"Albany",
    "sg:classifiers":[
        {
            "category":"Manufacturing",
            "subcategory":"Food",
            "type":"Manufacturing & Wholesale Goods"
        }
    ],
    "sg:phone":"+1 518 449 8830",
    "sg:postcode":"12206",
    "sg:province":"NY",
    "sg:tags":[
        "seafood",
        "product",
        "fish",
        "prepared"
    ],
    "sg:website":"www.cousinsfish.com",
    "wof:name":"Cousins Fish Markets Inc",
    "wof:placetype":"venue"
},
  "geometry": {"coordinates":[-73.76821099999999,42.669219],"type":"Point"}
}