{
  "type": "Feature",
  "properties": {
    "addr:full":"47 University Pl New York NY 10003",
    "addr:housenumber":"47",
    "addr:postcode":"10003",
    "addr:street":"University Pl",
    "iso:country":"US",
    "sg:address":"47 University Pl",
    "sg:city":"New York",
    "sg:classifiers":[
        {
            "category":"Food & Beverages",
            "subcategory":"Liquor & Beverages",
            "type":"Retail Goods"
        }
    ],
    "sg:phone":"+1 212 473 2525",
    "sg:postcode":"10003",
    "sg:province":"NY",
    "sg:tags":[
        "beer",
        "spirit",
        "wine"
    ],
    "wof:name":"B&S Zeeman Wines and Liquors",
    "wof:placetype":"venue"
},
  "geometry": {"coordinates":[-73.994102,40.732601],"type":"Point"}
}