{
  "type": "Feature",
  "properties": {
    "addr:full":"8000 Plainville Rd Plainville NY 13137",
    "addr:postcode":"8000;13137",
    "addr:street":"Plainville Rd",
    "iso:country":"US",
    "sg:address":"8000 Plainville Rd",
    "sg:city":"Plainville",
    "sg:classifiers":[
        {
            "category":"Government",
            "subcategory":"Post Office",
            "type":"Public Place"
        }
    ],
    "sg:phone":"+1 315 638 8123",
    "sg:postcode":"13137",
    "sg:province":"NY",
    "wof:name":"US Post Office",
    "wof:placetype":"venue"
},
  "geometry": {"coordinates":[-76.445611,43.150255],"type":"Point"}
}