{
  "type": "Feature",
  "properties": {
    "addr:full":"205 Hardscrabble Rd Cadyville NY 12918",
    "addr:housenumber":"205",
    "addr:postcode":"12918",
    "addr:street":"Hardscrabble Rd",
    "iso:country":"US",
    "sg:address":"205 Hardscrabble Rd",
    "sg:city":"Cadyville",
    "sg:classifiers":[
        {
            "category":"Farming",
            "subcategory":"Dairy Farm",
            "type":"Manufacturing & Wholesale Goods"
        }
    ],
    "sg:phone":"+1 518 293 8834",
    "sg:postcode":"12918",
    "sg:province":"NY",
    "wof:name":"Duquette Farms",
    "wof:placetype":"venue"
},
  "geometry": {"coordinates":[-73.635251,44.676759],"type":"Point"}
}