{
  "type": "Feature",
  "properties": {
    "addr:full":"78 Richmond Ter Staten Island NY 10301",
    "addr:housenumber":"78",
    "addr:postcode":"10301",
    "addr:street":"Richmond Ter",
    "iso:country":"US",
    "sg:address":"78 Richmond Ter",
    "sg:city":"Staten Island",
    "sg:classifiers":[
        {
            "category":"Government",
            "subcategory":"Police Station",
            "type":"Public Place"
        }
    ],
    "sg:phone":"+1 718 876 8500",
    "sg:postcode":"10301",
    "sg:province":"NY",
    "sg:tags":[
        "protection"
    ],
    "wof:name":"N Y C Police Dept",
    "wof:placetype":"venue"
},
  "geometry": {"coordinates":[-74.07763300000001,40.645343],"type":"Point"}
}