{
  "type": "Feature",
  "properties": {
    "addr:full":"8046 Kew Gardens Road Kew Gardens NY 11415",
    "addr:housenumber":"8046",
    "addr:postcode":"11415",
    "addr:street":"Kew Gardens Road",
    "iso:country":"US",
    "sg:address":"8046 Kew Gardens Road",
    "sg:city":"Kew Gardens",
    "sg:classifiers":[
        {
            "category":"Health Services",
            "subcategory":"Chiropractor",
            "type":"Services"
        }
    ],
    "sg:phone":"+1 718 261 3600",
    "sg:postcode":"11415",
    "sg:province":"NY",
    "wof:name":"New York Medical & Diagnostic Center",
    "wof:placetype":"venue"
},
  "geometry": {"coordinates":[-73.830125,40.71336],"type":"Point"}
}