{
  "type": "Feature",
  "properties": {
    "addr:full":"100 Princetown Rd Schenectady NY 12306",
    "addr:housenumber":"100",
    "addr:postcode":"12306",
    "addr:street":"Princetown Rd",
    "iso:country":"US",
    "sg:address":"100 Princetown Rd",
    "sg:city":"Schenectady",
    "sg:classifiers":[
        {
            "category":"Social Services",
            "type":"Services"
        }
    ],
    "sg:phone":"+1 518 355 5387",
    "sg:postcode":"12306",
    "sg:province":"NY",
    "sg:tags":[
        "youth",
        "organization",
        "center"
    ],
    "wof:name":"Rotterdam Youth Soccer Field",
    "wof:placetype":"venue"
},
  "geometry": {"coordinates":[-73.988365,42.794544],"type":"Point"}
}