{
  "type": "Feature",
  "properties": {
    "iso:country":"US",
    "sg:address":"1265 Niagara Falls Blvd",
    "sg:city":"Amherst",
    "sg:classifiers":[
        {
            "category":"Utilities",
            "subcategory":"Mobile Phone",
            "type":"Services"
        }
    ],
    "sg:phone":"+1 716 836 7923",
    "sg:postcode":"14226",
    "sg:province":"NY",
    "sg:tags":[
        "telephone",
        "cellular"
    ],
    "wof:name":"Monster Wireless",
    "wof:placetype":"venue"
},
  "geometry": {"coordinates":[-78.82254,42.988735],"type":"Point"}
}