{
  "type": "Feature",
  "properties": {
    "addr:full":"310 5th Ave New York NY 10001",
    "addr:housenumber":"310",
    "addr:postcode":"10001",
    "addr:street":"5Th Ave",
    "iso:country":"US",
    "sg:address":"310 5th Ave",
    "sg:city":"New York",
    "sg:classifiers":[
        {
            "category":"Professional",
            "type":"Services"
        }
    ],
    "sg:phone":"+1 212 904 1148",
    "sg:postcode":"10001",
    "sg:province":"NY",
    "sg:tags":[
        "establishment"
    ],
    "wof:name":"Congkeren Broch",
    "wof:placetype":"venue"
},
  "geometry": {"coordinates":[-73.98571699999999,40.746908],"type":"Point"}
}