{
  "type": "Feature",
  "properties": {
    "iso:country":"US",
    "sg:address":"161 Neptune Ave",
    "sg:city":"Brooklyn",
    "sg:classifiers":[
        {
            "category":"Home & Garden",
            "subcategory":"Hardware",
            "type":"Retail Goods"
        }
    ],
    "sg:phone":"+1   ",
    "sg:postcode":"11235",
    "sg:province":"NY",
    "wof:name":"Kahn Hardware",
    "wof:placetype":"venue"
},
  "geometry": {"coordinates":[-73.959726,40.582097],"type":"Point"}
}