{
  "type": "Feature",
  "properties": {
    "iso:country":"US",
    "sg:address":"26 Topland Rd",
    "sg:city":"Hartsdale",
    "sg:classifiers":[
        {
            "category":"Building & Trades",
            "subcategory":"Construction",
            "type":"Services"
        }
    ],
    "sg:phone":"+1 914 946 8001",
    "sg:postcode":"10530",
    "sg:province":"NY",
    "sg:tags":[
        "general",
        "contractor"
    ],
    "wof:name":"Belmont & Son Inc",
    "wof:placetype":"venue"
},
  "geometry": {"coordinates":[-73.821822,41.01492],"type":"Point"}
}