{
  "type": "Feature",
  "properties": {
    "iso:country":"US",
    "sg:address":"1379 Bay Ridge Ave",
    "sg:city":"Brooklyn",
    "sg:classifiers":[
        {
            "category":"Building & Trades",
            "subcategory":"Construction",
            "type":"Services"
        },
        {
            "category":"Home & Garden",
            "subcategory":"Home Furnishings",
            "type":"Retail Goods"
        }
    ],
    "sg:phone":"+1 718 232 4750",
    "sg:postcode":"11219",
    "sg:province":"NY",
    "sg:tags":[
        "fireplace",
        "contractor"
    ],
    "wof:name":"Fireplaces & Chimneys New York",
    "wof:placetype":"venue"
},
  "geometry": {"coordinates":[-74.00297500000001,40.623488],"type":"Point"}
}