{
  "type": "Feature",
  "properties": {
    "addr:full":"111 Yuma Ln East Islip NY 11730",
    "addr:housenumber":"111",
    "addr:postcode":"11730",
    "addr:street":"Yuma Ln",
    "iso:country":"US",
    "sg:address":"111 Yuma Ln",
    "sg:city":"East Islip",
    "sg:classifiers":[
        {
            "category":"Insurance",
            "subcategory":"Insurance Agent",
            "type":"Services"
        }
    ],
    "sg:phone":"+1 631 224 1222",
    "sg:postcode":"11730",
    "sg:province":"NY",
    "wof:name":"Brokerage Inc Island Wide Ins",
    "wof:placetype":"venue"
},
  "geometry": {"coordinates":[-73.179317,40.725282],"type":"Point"}
}