{
  "type": "Feature",
  "properties": {
    "addr:full":"31 Woodland Rd Bedford NY 10506",
    "addr:housenumber":"31",
    "addr:postcode":"10506",
    "addr:street":"Woodland Rd",
    "iso:country":"US",
    "sg:address":"31 Woodland Rd",
    "sg:city":"Bedford",
    "sg:classifiers":[
        {
            "category":"Professional",
            "subcategory":"Detective & Security Services",
            "type":"Services"
        }
    ],
    "sg:phone":"+1   ",
    "sg:postcode":"10506",
    "sg:province":"NY",
    "sg:tags":[
        "system"
    ],
    "wof:name":"STI Inc",
    "wof:placetype":"venue"
},
  "geometry": {"coordinates":[-73.648573,41.171493],"type":"Point"}
}