{
  "type": "Feature",
  "properties": {
    "addr:full":"21 Holly Ln Liverpool NY 13090",
    "addr:housenumber":"21",
    "addr:postcode":"13090",
    "addr:street":"Holly Ln",
    "iso:country":"US",
    "sg:address":"21 Holly Ln",
    "sg:city":"Liverpool",
    "sg:classifiers":[
        {
            "category":"Insurance",
            "subcategory":"Hazard Insurance",
            "type":"Services"
        }
    ],
    "sg:phone":"+1 315 652 8494",
    "sg:postcode":"13090",
    "sg:province":"NY",
    "sg:tags":[
        "commercial",
        "business"
    ],
    "wof:name":"General Casualty Insurance",
    "wof:placetype":"venue"
},
  "geometry": {"coordinates":[-76.21402,43.135738],"type":"Point"}
}