{
  "type": "Feature",
  "properties": {
    "iso:country":"US",
    "sg:address":"483 1st St",
    "sg:city":"Brooklyn",
    "sg:classifiers":[
        {
            "category":"Retail",
            "subcategory":"Self-service Laundry",
            "type":"Services"
        }
    ],
    "sg:phone":"+1   ",
    "sg:postcode":"11215",
    "sg:province":"NY",
    "sg:tags":[
        "coin"
    ],
    "wof:name":"Pinzon Alba",
    "wof:placetype":"venue"
},
  "geometry": {"coordinates":[-73.97597,40.671157],"type":"Point"}
}