{
  "type": "Feature",
  "properties": {
    "addr:full":"280 Bayview Ave Manhasset NY 11030",
    "addr:housenumber":"280",
    "addr:postcode":"11030",
    "addr:street":"Bayview Ave",
    "iso:country":"US",
    "sg:address":"280 Bayview Ave",
    "sg:city":"Manhasset",
    "sg:classifiers":[
        {
            "category":"Wholesale",
            "subcategory":"Construction Materials",
            "type":"Manufacturing & Wholesale Goods"
        }
    ],
    "sg:phone":"+1 516 627 7095",
    "sg:postcode":"11030",
    "sg:province":"NY",
    "sg:tags":[
        "building",
        "equipment"
    ],
    "wof:name":"Anka Systems Inc",
    "wof:placetype":"venue"
},
  "geometry": {"coordinates":[-73.708732,40.797089],"type":"Point"}
}