{
  "type": "Feature",
  "properties": {
    "addr:full":"1630 Casey Rd Wellsville NY 14895",
    "addr:housenumber":"1630",
    "addr:postcode":"14895",
    "addr:street":"Casey Rd",
    "iso:country":"US",
    "sg:address":"1630 Casey Rd",
    "sg:city":"Wellsville",
    "sg:classifiers":[
        {
            "category":"Autos & Motor Vehicles",
            "subcategory":"Automobile Sales",
            "type":"Retail Goods"
        }
    ],
    "sg:phone":"+1   ",
    "sg:postcode":"14895",
    "sg:province":"NY",
    "sg:tags":[
        "car",
        "used"
    ],
    "wof:name":"Gibney Auto",
    "wof:placetype":"venue"
},
  "geometry": {"coordinates":[-77.817007,42.070213],"type":"Point"}
}