{
  "type": "Feature",
  "properties": {
    "addr:full":"15 Point St Wappingers Falls NY 12590",
    "addr:housenumber":"15",
    "addr:postcode":"12590",
    "addr:street":"Point St",
    "iso:country":"US",
    "sg:address":"15 Point St",
    "sg:city":"Wappingers Falls",
    "sg:classifiers":[
        {
            "category":"Recreation",
            "subcategory":"Marina",
            "type":"Entertainment"
        },
        {
            "category":"Autos & Motor Vehicles",
            "subcategory":"Boat Sales",
            "type":"Retail Goods"
        }
    ],
    "sg:phone":"+1 845 297 8520",
    "sg:postcode":"12590",
    "sg:province":"NY",
    "sg:tags":[
        "boating",
        "operates",
        "marine",
        "supply"
    ],
    "wof:name":"White Hudson River Marina",
    "wof:placetype":"venue"
},
  "geometry": {"coordinates":[-73.950232,41.586428],"type":"Point"}
}