{
  "type": "Feature",
  "properties": {
    "addr:full":"99 Commerce St Brooklyn NY 11231",
    "addr:housenumber":"99",
    "addr:postcode":"11231",
    "addr:street":"Commerce St",
    "iso:country":"US",
    "sg:address":"99 Commerce St",
    "sg:city":"Brooklyn",
    "sg:classifiers":[
        {
            "category":"Wholesale",
            "subcategory":"Groceries",
            "type":"Manufacturing & Wholesale Goods"
        }
    ],
    "sg:phone":"+1 718 643 8100",
    "sg:postcode":"11231",
    "sg:province":"NY",
    "sg:tags":[
        "beverage"
    ],
    "wof:name":"Concrete Island Beverage Inc",
    "wof:placetype":"venue"
},
  "geometry": {"coordinates":[-74.00903099999999,40.681245],"type":"Point"}
}