{
  "type": "Feature",
  "properties": {
    "addr:full":"331 W 89 St New York NY 10024",
    "addr:housenumber":"331",
    "addr:postcode":"10024",
    "addr:street":"W 89 St",
    "iso:country":"US",
    "sg:address":"331 W 89 St",
    "sg:city":"New York",
    "sg:classifiers":[
        {
            "category":"Retail",
            "subcategory":"Repair Shop",
            "type":"Services"
        }
    ],
    "sg:phone":"+1 646 224 0841",
    "sg:postcode":"10024",
    "sg:province":"NY",
    "sg:tags":[
        "lock",
        "locksmith"
    ],
    "wof:name":"Locksmith Emergency",
    "wof:placetype":"venue"
},
  "geometry": {"coordinates":[-73.97811900000001,40.79153],"type":"Point"}
}