{
  "type": "Feature",
  "properties": {
    "addr:full":"677 Morris Park Ave Bronx NY 10462",
    "addr:housenumber":"677",
    "addr:postcode":"10462",
    "addr:street":"Morris Park Ave",
    "iso:country":"US",
    "sg:address":"677 Morris Park Ave",
    "sg:city":"Bronx",
    "sg:classifiers":[
        {
            "category":"Shopping",
            "subcategory":"Clothing, Apparel, & Fashions",
            "type":"Retail Goods"
        }
    ],
    "sg:phone":"+1 718 892 6083",
    "sg:postcode":"10462",
    "sg:province":"NY",
    "wof:name":"Barry Fashion",
    "wof:placetype":"venue"
},
  "geometry": {"coordinates":[-73.866187,40.845282],"type":"Point"}
}