{
  "type": "Feature",
  "properties": {
    "addr:full":"129 Broadway Hicksville NY 11801",
    "addr:housenumber":"129",
    "addr:postcode":"11801",
    "addr:street":"Broadway",
    "iso:country":"US",
    "sg:address":"129 Broadway",
    "sg:city":"Hicksville",
    "sg:classifiers":[
        {
            "category":"Organizations",
            "subcategory":"Religious Organization",
            "type":"Services"
        }
    ],
    "sg:phone":"+1 516 935 6873",
    "sg:postcode":"11801",
    "sg:province":"NY",
    "wof:name":"St Ignatius Loyola R C Church",
    "wof:placetype":"venue"
},
  "geometry": {"coordinates":[-73.521896,40.766201],"type":"Point"}
}