{
  "type": "Feature",
  "properties": {
    "addr:full":"20 E Moriches Blvd East Moriches NY 11940",
    "addr:housenumber":"20",
    "addr:postcode":"11940",
    "addr:street":"E Moriches Blvd East",
    "iso:country":"US",
    "sg:address":"20 E Moriches Blvd",
    "sg:city":"East Moriches",
    "sg:classifiers":[
        {
            "category":"Building & Trades",
            "subcategory":"Construction",
            "type":"Services"
        }
    ],
    "sg:phone":"+1 631 878 5159",
    "sg:postcode":"11940",
    "sg:province":"NY",
    "sg:tags":[
        "water",
        "well",
        "drilling"
    ],
    "wof:name":"Clearwater Drilling Inc",
    "wof:placetype":"venue"
},
  "geometry": {"coordinates":[-72.746078,40.814797],"type":"Point"}
}