{
  "type": "Feature",
  "properties": {
    "addr:full":"243 Berry St Brooklyn NY 11211",
    "addr:housenumber":"243",
    "addr:postcode":"11211",
    "addr:street":"Berry St",
    "iso:country":"US",
    "sg:address":"243 Berry St",
    "sg:city":"Brooklyn",
    "sg:classifiers":[
        {
            "category":"Retail",
            "subcategory":"Pet Boarding",
            "type":"Services"
        }
    ],
    "sg:phone":"+1 718 599 1656",
    "sg:postcode":"11211",
    "sg:province":"NY",
    "sg:tags":[
        "boarding/pet",
        "sitting"
    ],
    "sg:website":"www.dogaddiction.com",
    "wof:name":"Dog Addiction",
    "wof:placetype":"venue"
},
  "geometry": {"coordinates":[-73.962563,40.715308],"type":"Point"}
}