{
  "type": "Feature",
  "properties": {
    "addr:full":"278 Grand St New York NY 10002",
    "addr:housenumber":"278",
    "addr:postcode":"10002",
    "addr:street":"Grand St",
    "iso:country":"US",
    "sg:address":"278 Grand St",
    "sg:city":"New York",
    "sg:classifiers":[
        {
            "category":"Cinema",
            "subcategory":"Movie Rental",
            "type":"Entertainment"
        }
    ],
    "sg:phone":"+1 212 219 2066",
    "sg:postcode":"10002",
    "sg:province":"NY",
    "sg:tags":[
        "leasing",
        "video",
        "disc",
        "tape"
    ],
    "wof:name":"Grand Video Ctr Inc",
    "wof:placetype":"venue"
},
  "geometry": {"coordinates":[-73.992487,40.717845],"type":"Point"}
}