{
  "type": "Feature",
  "properties": {
    "addr:full":"2630 Millersport Hwy Getzville NY 14068",
    "addr:postcode":"2630;14068",
    "addr:street":"Millersport Hwy",
    "iso:country":"US",
    "sg:address":"2630 Millersport Hwy",
    "sg:city":"Getzville",
    "sg:classifiers":[
        {
            "category":"Social Services",
            "type":"Services"
        }
    ],
    "sg:phone":"+1 716 689 6229",
    "sg:postcode":"14068",
    "sg:province":"NY",
    "sg:tags":[
        "counseling",
        "center"
    ],
    "wof:name":"University Center Services",
    "wof:placetype":"venue"
},
  "geometry": {"coordinates":[-78.766744,43.017339],"type":"Point"}
}