{
  "type": "Feature",
  "properties": {
    "addr:full":"222 W Main St Smithtown NY 11787",
    "addr:housenumber":"222",
    "addr:postcode":"11787",
    "addr:street":"W Main St",
    "iso:country":"US",
    "sg:address":"222 W Main St",
    "sg:city":"Smithtown",
    "sg:classifiers":[
        {
            "category":"Professional",
            "subcategory":"Lawyer & Legal Services",
            "type":"Services"
        }
    ],
    "sg:phone":"+1 631 265 0102",
    "sg:postcode":"11787",
    "sg:province":"NY",
    "wof:name":"Ronald S Cook",
    "wof:placetype":"venue"
},
  "geometry": {"coordinates":[-73.202997,40.85628],"type":"Point"}
}