{
  "type": "Feature",
  "properties": {
    "addr:full":"63 Sly Pond Rd Fort Ann NY 12827",
    "addr:housenumber":"63",
    "addr:postcode":"12827",
    "addr:street":"Sly Pond Rd",
    "iso:country":"US",
    "sg:address":"63 Sly Pond Rd",
    "sg:city":"Fort Ann",
    "sg:classifiers":[
        {
            "category":"Professional",
            "subcategory":"Management & Consulting",
            "type":"Services"
        }
    ],
    "sg:phone":"+1 518 798 2000",
    "sg:postcode":"12827",
    "sg:province":"NY",
    "sg:tags":[
        "specializing",
        "meeting",
        "business"
    ],
    "wof:name":"Mission Control Productions",
    "wof:placetype":"venue"
},
  "geometry": {"coordinates":[-73.58134099999999,43.465922],"type":"Point"}
}