{
  "type": "Feature",
  "properties": {
    "addr:full":"440 E 116th St New York NY 10029",
    "addr:housenumber":"440",
    "addr:postcode":"10029",
    "addr:street":"E 116Th St",
    "iso:country":"US",
    "sg:address":"440 E 116th St",
    "sg:city":"New York",
    "sg:classifiers":[
        {
            "category":"Social Services",
            "type":"Services"
        }
    ],
    "sg:phone":"+1 212 427 9010",
    "sg:postcode":"10029",
    "sg:province":"NY",
    "wof:name":"Headstart",
    "wof:placetype":"venue"
},
  "geometry": {"coordinates":[-73.93388899999999,40.795377],"type":"Point"}
}