{
  "type": "Feature",
  "properties": {
    "addr:full":"2634 West St Brooklyn NY 11223",
    "addr:housenumber":"2634",
    "addr:postcode":"11223",
    "addr:street":"West St",
    "iso:country":"US",
    "sg:address":"2634 West St",
    "sg:city":"Brooklyn",
    "sg:classifiers":[
        {
            "category":"Professional",
            "subcategory":"Management & Consulting",
            "type":"Services"
        }
    ],
    "sg:phone":"+1 718 368 9641",
    "sg:postcode":"11223",
    "sg:province":"NY",
    "sg:tags":[
        "consultant",
        "business"
    ],
    "wof:name":"Beach Haven Management Corp",
    "wof:placetype":"venue"
},
  "geometry": {"coordinates":[-73.96942199999999,40.586307],"type":"Point"}
}