{
  "type": "Feature",
  "properties": {
    "addr:full":"35 Covert Ave Floral Park NY 11001",
    "addr:housenumber":"35",
    "addr:postcode":"11001",
    "addr:street":"Covert Ave",
    "iso:country":"US",
    "sg:address":"35 Covert Ave",
    "sg:city":"Floral Park",
    "sg:classifiers":[
        {
            "category":"Food & Beverages",
            "subcategory":"Meat & Fish",
            "type":"Retail Goods"
        }
    ],
    "sg:phone":"+1 516 488 8841",
    "sg:postcode":"11001",
    "sg:province":"NY",
    "sg:tags":[
        "seafood",
        "market"
    ],
    "wof:name":"Righthouse Seafood",
    "wof:placetype":"venue"
},
  "geometry": {"coordinates":[-73.68759900000001,40.723801],"type":"Point"}
}