{
  "type": "Feature",
  "properties": {
    "iso:country":"US",
    "sg:address":"69 E 89 St",
    "sg:city":"New York",
    "sg:classifiers":[
        {
            "category":"Professional",
            "type":"Services"
        }
    ],
    "sg:phone":"+1 212 289 7800",
    "sg:postcode":"10128",
    "sg:province":"NY",
    "sg:tags":[
        "establishment"
    ],
    "wof:name":"Borer Brondi",
    "wof:placetype":"venue"
},
  "geometry": {"coordinates":[-73.956367,40.782515],"type":"Point"}
}