{
  "type": "Feature",
  "properties": {
    "addr:full":"70 McCormack Dr Lake George NY 12845",
    "addr:housenumber":"70",
    "addr:postcode":"12845",
    "addr:street":"Mccormack Dr",
    "iso:country":"US",
    "sg:address":"70 McCormack Dr",
    "sg:city":"Lake George",
    "sg:classifiers":[
        {
            "category":"Building & Trades",
            "subcategory":"Construction",
            "type":"Services"
        }
    ],
    "sg:phone":"+1 518 792 9278",
    "sg:postcode":"12845",
    "sg:province":"NY",
    "sg:tags":[
        "contractor"
    ],
    "wof:name":"Raven Industries Inc",
    "wof:placetype":"venue"
},
  "geometry": {"coordinates":[-73.691051,43.363204],"type":"Point"}
}