{
  "type": "Feature",
  "properties": {
    "iso:country":"US",
    "sg:address":"239 Genesee St Ste 127",
    "sg:city":"Utica",
    "sg:classifiers":[
        {
            "category":"Insurance",
            "subcategory":"Insurance Agent",
            "type":"Services"
        },
        {
            "category":"Insurance",
            "subcategory":"Hazard Insurance",
            "type":"Services"
        },
        {
            "category":"Insurance",
            "subcategory":"Title Insurance",
            "type":"Services"
        }
    ],
    "sg:phone":"+1 315 735 4414",
    "sg:postcode":"13501",
    "sg:province":"NY",
    "sg:tags":[
        "business",
        "auto",
        "commercial",
        "homeowner",
        "property",
        "casualty"
    ],
    "sg:website":"http://www.mercuryinsurance.com",
    "wof:name":"Mercury Insurance - Loughlin Agency, Inc. The",
    "wof:placetype":"venue"
},
  "geometry": {"coordinates":[-75.233707,43.100161],"type":"Point"}
}