{
  "type": "Feature",
  "properties": {
    "iso:country":"US",
    "sg:address":"1687 English Rd",
    "sg:city":"Rochester",
    "sg:classifiers":[
        {
            "category":"Professional",
            "type":"Services"
        }
    ],
    "sg:phone":"+1 585 225 1000",
    "sg:postcode":"14616",
    "sg:province":"NY",
    "sg:tags":[
        "establishment"
    ],
    "wof:name":"Imageview",
    "wof:placetype":"venue"
},
  "geometry": {"coordinates":[-77.69332,43.238369],"type":"Point"}
}