{
  "type": "Feature",
  "properties": {
    "iso:country":"US",
    "sg:address":"2 Hobart Ct",
    "sg:city":"Fairport",
    "sg:classifiers":[
        {
            "category":"Wholesale",
            "subcategory":"Stationery",
            "type":"Manufacturing & Wholesale Goods"
        }
    ],
    "sg:phone":"+1 585 223 0520",
    "sg:postcode":"14450",
    "sg:province":"NY",
    "sg:tags":[
        "business",
        "form",
        "system"
    ],
    "wof:name":"Bajan Group",
    "wof:placetype":"venue"
},
  "geometry": {"coordinates":[-77.39903,43.095884],"type":"Point"}
}