{
  "type": "Feature",
  "properties": {
    "addr:full":"1306 Hicksville Rd Massapequa NY 11758",
    "addr:housenumber":"1306",
    "addr:postcode":"11758",
    "addr:street":"Hicksville Rd",
    "iso:country":"US",
    "sg:address":"1306 Hicksville Rd",
    "sg:city":"Massapequa",
    "sg:classifiers":[
        {
            "category":"Insurance",
            "subcategory":"Insurance Agent",
            "type":"Services"
        }
    ],
    "sg:phone":"+1 516 797 0124",
    "sg:postcode":"11758",
    "sg:province":"NY",
    "wof:name":"Hair Craze",
    "wof:placetype":"venue"
},
  "geometry": {"coordinates":[-73.482899,40.708592],"type":"Point"}
}