{
  "type": "Feature",
  "properties": {
    "addr:full":"172 Main St Islip NY 11751",
    "addr:housenumber":"172",
    "addr:postcode":"11751",
    "addr:street":"Main St",
    "iso:country":"US",
    "sg:address":"172 Main St",
    "sg:city":"Islip",
    "sg:classifiers":[
        {
            "category":"Retail",
            "subcategory":"Funeral Services",
            "type":"Services"
        }
    ],
    "sg:phone":"+1 631 581 5085",
    "sg:postcode":"11751",
    "sg:province":"NY",
    "sg:tags":[
        "director"
    ],
    "sg:website":"www.overtonfuneralhome.com",
    "wof:name":"Overton Funeral Home Inc",
    "wof:placetype":"venue"
},
  "geometry": {"coordinates":[-73.224683,40.727942],"type":"Point"}
}