{
  "type": "Feature",
  "properties": {
    "addr:full":"165 E 72 St New York NY 10021",
    "addr:housenumber":"165;72",
    "addr:postcode":"10021",
    "addr:street":"E;St",
    "iso:country":"US",
    "sg:address":"165 E 72 St",
    "sg:city":"New York",
    "sg:classifiers":[
        {
            "category":"Professional",
            "subcategory":"Management & Consulting",
            "type":"Services"
        }
    ],
    "sg:phone":"+1 212 861 5246",
    "sg:postcode":"10021",
    "sg:province":"NY",
    "sg:tags":[
        "consultant",
        "business"
    ],
    "sg:website":"www.lettersbyhand.com",
    "wof:name":"Letters By Hand",
    "wof:placetype":"venue"
},
  "geometry": {"coordinates":[-73.96107000000001,40.770094],"type":"Point"}
}