{
  "type": "Feature",
  "properties": {
    "iso:country":"US",
    "sg:address":"2 Gannett Dr",
    "sg:city":"White Plains",
    "sg:classifiers":[
        {
            "category":"Wholesale",
            "subcategory":"Durable Goods & Equipment",
            "type":"Manufacturing & Wholesale Goods"
        },
        {
            "category":"Wholesale",
            "subcategory":"Jewelry",
            "type":"Manufacturing & Wholesale Goods"
        }
    ],
    "sg:phone":"+1 914 640 2800",
    "sg:postcode":"10604",
    "sg:province":"NY",
    "sg:tags":[
        "pearl",
        "importer",
        "cultured"
    ],
    "wof:name":"Shogun Trading Co Inc",
    "wof:placetype":"venue"
},
  "geometry": {"coordinates":[-73.725934,41.021195],"type":"Point"}
}