{
  "type": "Feature",
  "properties": {
    "iso:country":"US",
    "sg:address":"31 Old Jerome Ave",
    "sg:city":"Yonkers",
    "sg:classifiers":[
        {
            "category":"Building & Trades",
            "subcategory":"Construction",
            "type":"Services"
        }
    ],
    "sg:phone":"+1 718 994 1917",
    "sg:postcode":"10704",
    "sg:province":"NY",
    "sg:tags":[
        "contractor",
        "laying",
        "flooring",
        "floor"
    ],
    "wof:name":"Paul's Flooring",
    "wof:placetype":"venue"
},
  "geometry": {"coordinates":[-73.87445099999999,40.906319],"type":"Point"}
}