{
  "type": "Feature",
  "properties": {
    "iso:country":"US",
    "sg:address":"116 Walsh Rd",
    "sg:city":"Lagrangeville",
    "sg:classifiers":[
        {
            "category":"Building & Trades",
            "subcategory":"Landscaping Services",
            "type":"Services"
        }
    ],
    "sg:phone":"+1 845 227 8475",
    "sg:postcode":"12540",
    "sg:province":"NY",
    "sg:tags":[
        "landscape"
    ],
    "wof:name":"Pelican Home Services",
    "wof:placetype":"venue"
},
  "geometry": {"coordinates":[-73.714539,41.679388],"type":"Point"}
}