{
  "type": "Feature",
  "properties": {
    "addr:full":"132 Plymouth Dr Syracuse NY 13206",
    "addr:housenumber":"132",
    "addr:postcode":"13206",
    "addr:street":"Plymouth Dr",
    "iso:country":"US",
    "sg:address":"132 Plymouth Dr",
    "sg:city":"Syracuse",
    "sg:classifiers":[
        {
            "category":"Travel",
            "subcategory":"Travel Agent",
            "type":"Entertainment"
        }
    ],
    "sg:phone":"+1   ",
    "sg:postcode":"13206",
    "sg:province":"NY",
    "sg:tags":[
        "operator",
        "tour"
    ],
    "wof:name":"Belle Tours",
    "wof:placetype":"venue"
},
  "geometry": {"coordinates":[-76.100044,43.067923],"type":"Point"}
}