{
  "type": "Feature",
  "properties": {
    "iso:country":"US",
    "sg:address":"6 Fiesta Ct",
    "sg:city":"Patchogue",
    "sg:classifiers":[
        {
            "category":"Wholesale",
            "subcategory":"Auto Parts",
            "type":"Manufacturing & Wholesale Goods"
        }
    ],
    "sg:phone":"+1 631 289 3997",
    "sg:postcode":"11772",
    "sg:province":"NY",
    "wof:name":"Brook Stony Sales Associates",
    "wof:placetype":"venue"
},
  "geometry": {"coordinates":[-73.01316799999999,40.7926],"type":"Point"}
}