{
  "type": "Feature",
  "properties": {
    "iso:country":"US",
    "sg:address":"656 Rosevale Ave",
    "sg:city":"Ronkonkoma",
    "sg:classifiers":[
        {
            "category":"Manufacturing",
            "subcategory":"Printing",
            "type":"Manufacturing & Wholesale Goods"
        }
    ],
    "sg:phone":"+1   ",
    "sg:postcode":"11779",
    "sg:province":"NY",
    "sg:tags":[
        "commercial",
        "lithographic"
    ],
    "wof:name":"St James Printing Inc",
    "wof:placetype":"venue"
},
  "geometry": {"coordinates":[-73.134373,40.829482],"type":"Point"}
}