{
  "type": "Feature",
  "properties": {
    "addr:full":"368 President St Brooklyn NY 11231",
    "addr:housenumber":"368",
    "addr:postcode":"11231",
    "addr:street":"President St",
    "iso:country":"US",
    "sg:address":"368 President St",
    "sg:city":"Brooklyn",
    "sg:classifiers":[
        {
            "category":"Professional",
            "subcategory":"Lawyer & Legal Services",
            "type":"Services"
        }
    ],
    "sg:phone":"+1 212 406 0700",
    "sg:postcode":"11231",
    "sg:province":"NY",
    "wof:name":"Siegel Franklin Atty",
    "wof:placetype":"venue"
},
  "geometry": {"coordinates":[-73.991096,40.6796],"type":"Point"}
}