{
  "type": "Feature",
  "properties": {
    "addr:full":"200 W 37th St New York NY 10018",
    "addr:housenumber":"200",
    "addr:postcode":"10018",
    "addr:street":"W 37Th St",
    "iso:country":"US",
    "sg:address":"200 W 37th St",
    "sg:city":"New York",
    "sg:classifiers":[
        {
            "category":"Building & Trades",
            "subcategory":"Locksmith",
            "type":"Services"
        }
    ],
    "sg:phone":"+1 212 209 0398",
    "sg:postcode":"10018",
    "sg:province":"NY",
    "sg:tags":[
        "key"
    ],
    "wof:name":"A 24 Hour A Locksmith",
    "wof:placetype":"venue"
},
  "geometry": {"coordinates":[-73.989098,40.752998],"type":"Point"}
}