{
  "type": "Feature",
  "properties": {
    "iso:country":"US",
    "sg:address":"1101 State St",
    "sg:city":"Clayton",
    "sg:classifiers":[
        {
            "category":"Recreation",
            "type":"Entertainment"
        }
    ],
    "sg:phone":"+1 315 686 2500",
    "sg:postcode":"13624",
    "sg:province":"NY",
    "sg:tags":[
        "charter",
        "boat"
    ],
    "sg:website":"www.tiadventures.com",
    "wof:name":"T I Adventures",
    "wof:placetype":"venue"
},
  "geometry": {"coordinates":[-76.091694,44.231465],"type":"Point"}
}