{
  "type": "Feature",
  "properties": {
    "addr:full":"3801 Hudson Manor Ter Bronx NY 10463",
    "addr:housenumber":"3801",
    "addr:postcode":"10463",
    "addr:street":"Hudson Manor Ter",
    "iso:country":"US",
    "sg:address":"3801 Hudson Manor Ter",
    "sg:city":"Bronx",
    "sg:classifiers":[
        {
            "category":"Food & Beverages",
            "subcategory":"Bakery",
            "type":"Retail Goods"
        }
    ],
    "sg:phone":"+1   ",
    "sg:postcode":"10463",
    "sg:province":"NY",
    "wof:name":"Morey Doreys Cheesecake",
    "wof:placetype":"venue"
},
  "geometry": {"coordinates":[-73.91551699999999,40.889447],"type":"Point"}
}