{
  "type": "Feature",
  "properties": {
    "iso:country":"US",
    "sg:address":"97 E Fulton St",
    "sg:city":"Gloversville",
    "sg:classifiers":[
        {
            "category":"Personal",
            "subcategory":"Beauty Salon",
            "type":"Services"
        }
    ],
    "sg:phone":"+1   ",
    "sg:postcode":"12078",
    "sg:province":"NY",
    "sg:tags":[
        "shop"
    ],
    "wof:name":"Doll House",
    "wof:placetype":"venue"
},
  "geometry": {"coordinates":[-74.340592,43.050936],"type":"Point"}
}