{
  "type": "Feature",
  "properties": {
    "addr:full":"4 Crestview Ave Cortlandt Manor NY 10567",
    "addr:housenumber":"4",
    "addr:postcode":"10567",
    "addr:street":"Crestview Ave Cortlandt",
    "iso:country":"US",
    "sg:address":"4 Crestview Ave",
    "sg:city":"Cortlandt Manor",
    "sg:classifiers":[
        {
            "category":"Banks & Credit Unions",
            "subcategory":"Bank",
            "type":"Services"
        }
    ],
    "sg:phone":"+1 914 734 4795",
    "sg:postcode":"10567",
    "sg:province":"NY",
    "sg:tags":[
        "loan",
        "mortgage",
        "real estate"
    ],
    "sg:website":"www.wemakeithappen.com",
    "wof:name":"Finder Mortgage Inc",
    "wof:placetype":"venue"
},
  "geometry": {"coordinates":[-73.879216,41.291883],"type":"Point"}
}