{
  "type": "Feature",
  "properties": {
    "addr:full":"1388 Flatbush Avenue Brooklyn NY 11210",
    "addr:housenumber":"1388",
    "addr:postcode":"11210",
    "addr:street":"Flatbush Avenue",
    "iso:country":"US",
    "sg:address":"1388 Flatbush Avenue",
    "sg:city":"Brooklyn",
    "sg:classifiers":[
        {
            "category":"Shopping",
            "subcategory":"Pharmacy",
            "type":"Retail Goods"
        }
    ],
    "sg:phone":"+1 718 859 0007",
    "sg:postcode":"11210",
    "sg:province":"NY",
    "sg:tags":[
        "drugstore"
    ],
    "wof:name":"B & M Family Pharmacy Corporation",
    "wof:placetype":"venue"
},
  "geometry": {"coordinates":[-73.951859,40.636689],"type":"Point"}
}