{
  "type": "Feature",
  "properties": {
    "iso:country":"US",
    "sg:address":"76 Bluebird Rd",
    "sg:city":"S Glens Falls",
    "sg:classifiers":[
        {
            "category":"Education",
            "subcategory":"School",
            "type":"Public Place"
        }
    ],
    "sg:phone":"+1 518 793 9644",
    "sg:postcode":"12803",
    "sg:province":"NY",
    "sg:website":"www.sgfallssd.org",
    "wof:name":"Moreau Elementary School",
    "wof:placetype":"venue"
},
  "geometry": {"coordinates":[-73.638998,43.273996],"type":"Point"}
}