{
  "type": "Feature",
  "properties": {
    "iso:country":"US",
    "sg:address":"36 Fulton Ave",
    "sg:city":"New Hyde Park",
    "sg:classifiers":[
        {
            "category":"Professional",
            "subcategory":"Advertising",
            "type":"Services"
        }
    ],
    "sg:phone":"+1 516 741 6708",
    "sg:postcode":"11040",
    "sg:province":"NY",
    "sg:tags":[
        "representative"
    ],
    "wof:name":"American Pheasant Wtr Foul Soc",
    "wof:placetype":"venue"
},
  "geometry": {"coordinates":[-73.664181,40.735822],"type":"Point"}
}