{
  "type": "Feature",
  "properties": {
    "iso:country":"US",
    "sg:address":"5507 Kings Hwy",
    "sg:city":"Brooklyn",
    "sg:classifiers":[
        {
            "category":"Professional",
            "subcategory":"Computer Services",
            "type":"Services"
        }
    ],
    "sg:phone":"+1 347 613 6709",
    "sg:postcode":"11203",
    "sg:province":"NY",
    "sg:tags":[
        "technical",
        "assistance",
        "support"
    ],
    "wof:name":"Academic Quest International",
    "wof:placetype":"venue"
},
  "geometry": {"coordinates":[-73.924725,40.645081],"type":"Point"}
}