{
  "type": "Feature",
  "properties": {
    "addr:full":"7 Park Ln Massapequa NY 11758",
    "addr:housenumber":"7",
    "addr:postcode":"11758",
    "addr:street":"Park Ln",
    "iso:country":"US",
    "sg:address":"7 Park Ln",
    "sg:city":"Massapequa",
    "sg:classifiers":[
        {
            "category":"Building & Trades",
            "subcategory":"Plumbing",
            "type":"Services"
        }
    ],
    "sg:phone":"+1 516 795 8063",
    "sg:postcode":"11758",
    "sg:province":"NY",
    "sg:tags":[
        "plumber",
        "industrial",
        "contractors-commercial"
    ],
    "wof:name":"Park Lane Plumbing",
    "wof:placetype":"venue"
},
  "geometry": {"coordinates":[-73.439719,40.679377],"type":"Point"}
}