{
  "type": "Feature",
  "properties": {
    "iso:country":"US",
    "sg:address":"325 N Tyner Rd",
    "sg:city":"Oxford",
    "sg:classifiers":[
        {
            "category":"Farming",
            "subcategory":"Dairy Farm",
            "type":"Manufacturing & Wholesale Goods"
        }
    ],
    "sg:phone":"+1 607 843 6291",
    "sg:postcode":"13830",
    "sg:province":"NY",
    "wof:name":"Anthony Zdobylak Farm",
    "wof:placetype":"venue"
},
  "geometry": {"coordinates":[-75.664732,42.443867],"type":"Point"}
}