{
  "type": "Feature",
  "properties": {
    "addr:full":"57 Village Grn Bardonia NY 10954",
    "addr:housenumber":"57",
    "addr:postcode":"10954",
    "addr:street":"Village Grn",
    "iso:country":"US",
    "sg:address":"57 Village Grn",
    "sg:city":"Bardonia",
    "sg:classifiers":[
        {
            "category":"Professional",
            "subcategory":"Business Services",
            "type":"Services"
        }
    ],
    "sg:phone":"+1 914 523 0601",
    "sg:postcode":"10954",
    "sg:province":"NY",
    "sg:tags":[
        "consultant",
        "coach"
    ],
    "wof:name":"Hochron Consulting",
    "wof:placetype":"venue"
},
  "geometry": {"coordinates":[-73.99896200000001,41.10611],"type":"Point"}
}