{
  "type": "Feature",
  "properties": {
    "iso:country":"US",
    "sg:address":"156 Beaver Dr",
    "sg:city":"Kings Park",
    "sg:classifiers":[
        {
            "category":"Building & Trades",
            "subcategory":"Construction",
            "type":"Services"
        }
    ],
    "sg:phone":"+1 631 361 9651",
    "sg:postcode":"11754",
    "sg:province":"NY",
    "sg:tags":[
        "painting",
        "contractor"
    ],
    "wof:name":"Vita Painting & Decorating",
    "wof:placetype":"venue"
},
  "geometry": {"coordinates":[-73.221898,40.8969],"type":"Point"}
}