{
  "type": "Feature",
  "properties": {
    "iso:country":"US",
    "sg:address":"3 Gem Ct",
    "sg:city":"Bay Shore",
    "sg:classifiers":[
        {
            "category":"Manufacturing",
            "subcategory":"Building Materials",
            "type":"Manufacturing & Wholesale Goods"
        }
    ],
    "sg:phone":"+1 631 647 5903",
    "sg:postcode":"11717",
    "sg:province":"NY",
    "wof:name":"Long Island Millwk & Strbldr",
    "wof:placetype":"venue"
},
  "geometry": {"coordinates":[-73.2176,40.772868],"type":"Point"}
}