{
  "type": "Feature",
  "properties": {
    "iso:country":"US",
    "sg:address":"949 Central Ave",
    "sg:city":"Woodmere",
    "sg:classifiers":[
        {
            "category":"Health Services",
            "subcategory":"Doctor",
            "type":"Services"
        }
    ],
    "sg:phone":"+1 516 374 7246",
    "sg:postcode":"11598",
    "sg:province":"NY",
    "sg:tags":[
        "medical"
    ],
    "wof:name":"Braunstein Ellen Joy",
    "wof:placetype":"venue"
},
  "geometry": {"coordinates":[-73.710048,40.631087],"type":"Point"}
}