{
  "type": "Feature",
  "properties": {
    "addr:full":"39 Waller St Piercefield NY 12973",
    "addr:housenumber":"39",
    "addr:postcode":"12973",
    "addr:street":"Waller St",
    "iso:country":"US",
    "sg:address":"39 Waller St",
    "sg:city":"Piercefield",
    "sg:classifiers":[
        {
            "category":"Government",
            "subcategory":"Post Office",
            "type":"Public Place"
        }
    ],
    "sg:phone":"+1 518 359 3410",
    "sg:postcode":"12973",
    "sg:province":"NY",
    "wof:name":"US Post Office",
    "wof:placetype":"venue"
},
  "geometry": {"coordinates":[-74.565236,44.231496],"type":"Point"}
}