{
  "type": "Feature",
  "properties": {
    "iso:country":"US",
    "sg:address":"9839 67th Avenue",
    "sg:city":"Rego Park",
    "sg:classifiers":[
        {
            "category":"Health Services",
            "subcategory":"Doctor",
            "type":"Services"
        }
    ],
    "sg:phone":"+1 718 830 3509",
    "sg:postcode":"11374",
    "sg:province":"NY",
    "wof:name":"Paras Jewish Organization MD",
    "wof:placetype":"venue"
},
  "geometry": {"coordinates":[-73.854902,40.725512],"type":"Point"}
}