{
  "type": "Feature",
  "properties": {
    "addr:full":"16 Manlon Ter Buffalo NY 14225",
    "addr:housenumber":"16",
    "addr:postcode":"14225",
    "addr:street":"Manlon Ter",
    "iso:country":"US",
    "sg:address":"16 Manlon Ter",
    "sg:city":"Buffalo",
    "sg:classifiers":[
        {
            "category":"Building & Trades",
            "subcategory":"Electrical",
            "type":"Services"
        }
    ],
    "sg:phone":"+1 716 837 3918",
    "sg:postcode":"14225",
    "sg:province":"NY",
    "sg:tags":[
        "electric",
        "industrial",
        "contractors-commercial",
        "contractor"
    ],
    "wof:name":"K Belcher Electric",
    "wof:placetype":"venue"
},
  "geometry": {"coordinates":[-78.772356,42.945955],"type":"Point"}
}