{
  "type": "Feature",
  "properties": {
    "iso:country":"US",
    "sg:address":"104 John St",
    "sg:city":"New York",
    "sg:classifiers":[
        {
            "category":"Restaurant",
            "type":"Food & Drink"
        }
    ],
    "sg:phone":"+1 212 227 8333",
    "sg:postcode":"10038",
    "sg:province":"NY",
    "sg:tags":[
        "japanese"
    ],
    "wof:name":"Sumou Japanese Restaurant Inc",
    "wof:placetype":"venue"
},
  "geometry": {"coordinates":[-74.00599699999999,40.707699],"type":"Point"}
}