{
  "type": "Feature",
  "properties": {
    "addr:full":"285 Central Park W New York NY 10024",
    "addr:housenumber":"285",
    "addr:postcode":"10024",
    "addr:street":"Central Park W",
    "iso:country":"US",
    "sg:address":"285 Central Park W",
    "sg:city":"New York",
    "sg:classifiers":[
        {
            "category":"Health Services",
            "subcategory":"Doctor",
            "type":"Services"
        }
    ],
    "sg:phone":"+1 212 873 1542",
    "sg:postcode":"10024",
    "sg:province":"NY",
    "wof:name":"Halpern Jeffrey",
    "wof:placetype":"venue"
},
  "geometry": {"coordinates":[-73.968221,40.787102],"type":"Point"}
}