{
  "type": "Feature",
  "properties": {
    "iso:country":"US",
    "sg:address":"3167 Countyline Rd",
    "sg:city":"Middleport",
    "sg:classifiers":[
        {
            "category":"Building & Trades",
            "subcategory":"Construction",
            "type":"Services"
        }
    ],
    "sg:phone":"+1 585 735 3644",
    "sg:postcode":"14105",
    "sg:province":"NY",
    "sg:tags":[
        "roofing",
        "industrial",
        "contractors-commercial",
        "contractor"
    ],
    "wof:name":"Miller, Wayne Siding & Roofing",
    "wof:placetype":"venue"
},
  "geometry": {"coordinates":[-78.46216099999999,43.246242],"type":"Point"}
}