{
  "type": "Feature",
  "properties": {
    "iso:country":"US",
    "sg:address":"1619 Clark Street Rd",
    "sg:city":"Auburn",
    "sg:classifiers":[
        {
            "category":"Home & Garden",
            "subcategory":"Garden Supply",
            "type":"Retail Goods"
        }
    ],
    "sg:phone":"+1   ",
    "sg:postcode":"13021",
    "sg:province":"NY",
    "wof:name":"Sears Roebuck and Co Inc",
    "wof:placetype":"venue"
},
  "geometry": {"coordinates":[-76.633353,42.925873],"type":"Point"}
}