{
  "type": "Feature",
  "properties": {
    "iso:country":"US",
    "sg:address":"427 Truthville Rd",
    "sg:city":"Granville",
    "sg:classifiers":[
        {
            "category":"Wholesale",
            "subcategory":"Auto Parts",
            "type":"Manufacturing & Wholesale Goods"
        }
    ],
    "sg:phone":"+1 518 642 9401",
    "sg:postcode":"12832",
    "sg:province":"NY",
    "sg:tags":[
        "used"
    ],
    "wof:name":"Monroes Auto Salvage",
    "wof:placetype":"venue"
},
  "geometry": {"coordinates":[-73.324342,43.471188],"type":"Point"}
}