{
  "type": "Feature",
  "properties": {
    "iso:country":"US",
    "sg:address":"407 W 13 St",
    "sg:city":"New York",
    "sg:classifiers":[
        {
            "category":"Wholesale",
            "subcategory":"Poultry",
            "type":"Manufacturing & Wholesale Goods"
        }
    ],
    "sg:phone":"+1 212 255 6350",
    "sg:postcode":"10014",
    "sg:province":"NY",
    "wof:name":"Jarmco Holding Corp",
    "wof:placetype":"venue"
},
  "geometry": {"coordinates":[-74.007217,40.74088],"type":"Point"}
}