{
  "type": "Feature",
  "properties": {
    "iso:country":"US",
    "sg:address":"3169 Fulton St",
    "sg:city":"Brooklyn",
    "sg:classifiers":[
        {
            "category":"Shopping",
            "subcategory":"Musical Instruments",
            "type":"Retail Goods"
        }
    ],
    "sg:phone":"+1 718 647 7714",
    "sg:postcode":"11208",
    "sg:province":"NY",
    "sg:tags":[
        "music",
        "dealer"
    ],
    "wof:name":"Music Place & More",
    "wof:placetype":"venue"
},
  "geometry": {"coordinates":[-73.879126,40.681675],"type":"Point"}
}