{
  "type": "Feature",
  "properties": {
    "addr:full":"19 Gramatan Ave Mt Vernon NY 10550",
    "addr:housenumber":"19",
    "addr:postcode":"10550",
    "addr:street":"Gramatan Ave",
    "iso:country":"US",
    "sg:address":"19 Gramatan Ave",
    "sg:city":"Mt Vernon",
    "sg:classifiers":[
        {
            "category":"Professional",
            "subcategory":"Accounting & Tax Preparation",
            "type":"Services"
        }
    ],
    "sg:phone":"+1 914 667 6217",
    "sg:postcode":"10550",
    "sg:province":"NY",
    "sg:tags":[
        "return",
        "filing"
    ],
    "wof:name":"H & R Block Tax Svc",
    "wof:placetype":"venue"
},
  "geometry": {"coordinates":[-73.83730799999999,40.914351],"type":"Point"}
}