{
  "type": "Feature",
  "properties": {
    "addr:full":"509 Cortelyou Rd Brooklyn NY 11218",
    "addr:housenumber":"509",
    "addr:postcode":"11218",
    "addr:street":"Cortelyou Rd",
    "iso:country":"US",
    "sg:address":"509 Cortelyou Rd",
    "sg:city":"Brooklyn",
    "sg:classifiers":[
        {
            "category":"Deli",
            "type":"Food & Drink"
        },
        {
            "category":"Food & Beverages",
            "subcategory":"Bakery",
            "type":"Retail Goods"
        }
    ],
    "sg:phone":"+1 718 941 6586",
    "sg:postcode":"11218",
    "sg:province":"NY",
    "sg:tags":[
        "sandwich"
    ],
    "wof:name":"Kosher Meat Market Inc",
    "wof:placetype":"venue"
},
  "geometry": {"coordinates":[-73.974479,40.638516],"type":"Point"}
}