{
  "type": "Feature",
  "properties": {
    "iso:country":"US",
    "sg:address":"242 Merrick Rd Ste 402",
    "sg:city":"Rockville Centre",
    "sg:classifiers":[
        {
            "category":"Health Services",
            "subcategory":"Doctor",
            "type":"Services"
        }
    ],
    "sg:phone":"+1 516 763 2800",
    "sg:postcode":"11570",
    "sg:province":"NY",
    "sg:tags":[
        "cardiologist"
    ],
    "wof:name":"South Shore Heart Associates PC",
    "wof:placetype":"venue"
},
  "geometry": {"coordinates":[-73.644203,40.655998],"type":"Point"}
}