{
  "type": "Feature",
  "properties": {
    "iso:country":"US",
    "sg:address":"5101 13th Ave",
    "sg:city":"Brooklyn",
    "sg:classifiers":[
        {
            "category":"Retail",
            "subcategory":"Repair Shop",
            "type":"Services"
        }
    ],
    "sg:phone":"+1 718 854 5308",
    "sg:postcode":"11219",
    "sg:province":"NY",
    "sg:tags":[
        "upholsterer"
    ],
    "wof:name":"Deco Dine Inc",
    "wof:placetype":"venue"
},
  "geometry": {"coordinates":[-73.993866,40.633347],"type":"Point"}
}