{
  "type": "Feature",
  "properties": {
    "addr:full":"3 Horizon Farms Dr Warwick NY 10990",
    "addr:housenumber":"3",
    "addr:postcode":"10990",
    "addr:street":"Horizon Farms Dr",
    "iso:country":"US",
    "sg:address":"3 Horizon Farms Dr",
    "sg:city":"Warwick",
    "sg:classifiers":[
        {
            "category":"Organizations",
            "subcategory":"Professional Association",
            "type":"Services"
        }
    ],
    "sg:phone":"+1 845 258 1818",
    "sg:postcode":"10990",
    "sg:province":"NY",
    "wof:name":"Horizon Homeowner's Assoc",
    "wof:placetype":"venue"
},
  "geometry": {"coordinates":[-74.462329,41.280683],"type":"Point"}
}