{
  "type": "Feature",
  "properties": {
    "addr:full":"1384 E 70th St Brooklyn NY 11234",
    "addr:housenumber":"1384",
    "addr:postcode":"11234",
    "addr:street":"E 70Th St",
    "iso:country":"US",
    "sg:address":"1384 E 70th St",
    "sg:city":"Brooklyn",
    "sg:classifiers":[
        {
            "category":"Building & Trades",
            "subcategory":"Cleaning & Sanitation",
            "type":"Services"
        }
    ],
    "sg:phone":"+1 347 587 6260",
    "sg:postcode":"11234",
    "sg:province":"NY",
    "sg:tags":[
        "carpet"
    ],
    "wof:name":"Mr Clean Carpet Upholstery",
    "wof:placetype":"venue"
},
  "geometry": {"coordinates":[-73.910984,40.621708],"type":"Point"}
}