{
  "type": "Feature",
  "properties": {
    "addr:full":"1086 Rutland Rd Brooklyn NY 11212",
    "addr:housenumber":"1086",
    "addr:postcode":"11212",
    "addr:street":"Rutland Rd",
    "iso:country":"US",
    "sg:address":"1086 Rutland Rd",
    "sg:city":"Brooklyn",
    "sg:classifiers":[
        {
            "category":"Shopping",
            "subcategory":"Computers & Home Electronics",
            "type":"Retail Goods"
        }
    ],
    "sg:phone":"+1   ",
    "sg:postcode":"11212",
    "sg:province":"NY",
    "wof:name":"Den-Tron Inc",
    "wof:placetype":"venue"
},
  "geometry": {"coordinates":[-73.92419700000001,40.663898],"type":"Point"}
}