{
  "type": "Feature",
  "properties": {
    "addr:full":"1307 Olean-Portville Rd Olean NY 14760",
    "addr:housenumber":"1307",
    "addr:postcode":"14760",
    "addr:street":"Olean-Portville Rd",
    "iso:country":"US",
    "sg:address":"1307 Olean-Portville Rd",
    "sg:city":"Olean",
    "sg:classifiers":[
        {
            "category":"Wholesale",
            "subcategory":"Durable Goods & Equipment",
            "type":"Manufacturing & Wholesale Goods"
        }
    ],
    "sg:phone":"+1 716 372 2383",
    "sg:postcode":"14760",
    "sg:province":"NY",
    "sg:tags":[
        "fire",
        "extinguisher",
        "protection",
        "automatic"
    ],
    "wof:name":"Ganoung's Fire Protection Inc",
    "wof:placetype":"venue"
},
  "geometry": {"coordinates":[-78.374756,42.060545],"type":"Point"}
}