{
  "type": "Feature",
  "properties": {
    "iso:country":"US",
    "sg:address":"1942 Colvin Blvd",
    "sg:city":"Tonawanda",
    "sg:classifiers":[
        {
            "category":"Wholesale",
            "subcategory":"Jewelry",
            "type":"Manufacturing & Wholesale Goods"
        }
    ],
    "sg:phone":"+1 716 831 8044",
    "sg:postcode":"14150",
    "sg:province":"NY",
    "sg:tags":[
        "industrial",
        "clocks",
        "time"
    ],
    "sg:website":"www.buffalotime.com",
    "wof:name":"Buffalo Time Clock Inc",
    "wof:placetype":"venue"
},
  "geometry": {"coordinates":[-78.85283699999999,42.990469],"type":"Point"}
}