{
  "type": "Feature",
  "properties": {
    "addr:full":"2500 Whitney Rd E Fairport NY 14450",
    "addr:housenumber":"2500",
    "addr:postcode":"14450",
    "addr:street":"Whitney Rd E",
    "iso:country":"US",
    "sg:address":"2500 Whitney Rd E",
    "sg:city":"Fairport",
    "sg:classifiers":[
        {
            "category":"Recreation",
            "type":"Entertainment"
        }
    ],
    "sg:phone":"+1 585 377 5220",
    "sg:postcode":"14450",
    "sg:province":"NY",
    "sg:tags":[
        "stable"
    ],
    "wof:name":"Whitney Hill Stables Inc",
    "wof:placetype":"venue"
},
  "geometry": {"coordinates":[-77.377833,43.108964],"type":"Point"}
}