{
  "type": "Feature",
  "properties": {
    "iso:country":"US",
    "sg:address":"460 Hawthorne Ave",
    "sg:city":"Uniondale",
    "sg:classifiers":[
        {
            "category":"Professional",
            "subcategory":"Business Services",
            "type":"Services"
        }
    ],
    "sg:phone":"+1 516 538 6201",
    "sg:postcode":"11553",
    "sg:province":"NY",
    "wof:name":"Daryl Hughes Assoc",
    "wof:placetype":"venue"
},
  "geometry": {"coordinates":[-73.600222,40.702071],"type":"Point"}
}