{
  "type": "Feature",
  "properties": {
    "addr:full":"3136 S Winton Rd Rochester NY 14623",
    "addr:housenumber":"3136",
    "addr:postcode":"14623",
    "addr:street":"S Winton Rd",
    "iso:country":"US",
    "sg:address":"3136 S Winton Rd",
    "sg:city":"Rochester",
    "sg:classifiers":[
        {
            "category":"Professional",
            "subcategory":"Research",
            "type":"Services"
        }
    ],
    "sg:phone":"+1 585 424 6560",
    "sg:postcode":"14623",
    "sg:province":"NY",
    "wof:name":"Muscular Dystrophy Assn Inc",
    "wof:placetype":"venue"
},
  "geometry": {"coordinates":[-77.581885,43.089766],"type":"Point"}
}