{
  "type": "Feature",
  "properties": {
    "iso:country":"US",
    "sg:address":"628 10th Ave",
    "sg:city":"New York",
    "sg:classifiers":[
        {
            "category":"Food & Beverages",
            "subcategory":"Liquor & Beverages",
            "type":"Retail Goods"
        }
    ],
    "sg:phone":"+1 212 245 4660",
    "sg:postcode":"10036",
    "sg:province":"NY",
    "sg:tags":[
        "beer",
        "spirit",
        "wine"
    ],
    "sg:website":"www.paleewong.com",
    "wof:name":"Paleewong Siam Enterprise Co",
    "wof:placetype":"venue"
},
  "geometry": {"coordinates":[-73.994202,40.761299],"type":"Point"}
}