{
  "type": "Feature",
  "properties": {
    "iso:country":"US",
    "sg:address":"3054 Bley Rd",
    "sg:city":"Eden",
    "sg:classifiers":[
        {
            "category":"Professional",
            "type":"Services"
        }
    ],
    "sg:phone":"+1 716 992 9441",
    "sg:postcode":"14057",
    "sg:province":"NY",
    "sg:tags":[
        "establishment"
    ],
    "wof:name":"Watertight Coatings Co Inc",
    "wof:placetype":"venue"
},
  "geometry": {"coordinates":[-78.881371,42.681531],"type":"Point"}
}