{
  "type": "Feature",
  "properties": {
    "iso:country":"US",
    "sg:address":"19 Virginia Rd",
    "sg:city":"Syosset",
    "sg:classifiers":[
        {
            "category":"Retail",
            "subcategory":"Auto Repair",
            "type":"Services"
        }
    ],
    "sg:phone":"+1 631 549 0118",
    "sg:postcode":"11791",
    "sg:province":"NY",
    "sg:tags":[
        "automobile",
        "customizing"
    ],
    "wof:name":"Creative Rod & Kustom LLC",
    "wof:placetype":"venue"
},
  "geometry": {"coordinates":[-73.505056,40.803814],"type":"Point"}
}