{
  "type": "Feature",
  "properties": {
    "iso:country":"US",
    "sg:address":"7 Clubway",
    "sg:city":"Mount Kisco",
    "sg:classifiers":[
        {
            "category":"Health Services",
            "subcategory":"Health Practitioner",
            "type":"Services"
        }
    ],
    "sg:phone":"+1   ",
    "sg:postcode":"10549",
    "sg:province":"NY",
    "wof:name":"Wendy Joondeph",
    "wof:placetype":"venue"
},
  "geometry": {"coordinates":[-73.73215399999999,41.17993],"type":"Point"}
}