{
  "type": "Feature",
  "properties": {
    "addr:full":"280 Plaza Rd Kingston NY 12401",
    "addr:housenumber":"280",
    "addr:postcode":"12401",
    "addr:street":"Plaza Rd",
    "iso:country":"US",
    "sg:address":"280 Plaza Rd",
    "sg:city":"Kingston",
    "sg:classifiers":[
        {
            "category":"Shopping",
            "subcategory":"Clothing, Apparel, & Fashions",
            "type":"Retail Goods"
        }
    ],
    "sg:phone":"+1 845 338 0233",
    "sg:postcode":"12401",
    "sg:province":"NY",
    "sg:tags":[
        "accessory",
        "clothing",
        "women's"
    ],
    "sg:website":"fashionbug.charmingshoppes.com",
    "wof:name":"Fashion Bug",
    "wof:placetype":"venue"
},
  "geometry": {"coordinates":[-73.942171,40.669908],"type":"Point"}
}