{
  "type": "Feature",
  "properties": {
    "iso:country":"US",
    "sg:address":"19 Chenango St",
    "sg:city":"Binghamton",
    "sg:classifiers":[
        {
            "category":"Professional",
            "subcategory":"Lawyer & Legal Services",
            "type":"Services"
        }
    ],
    "sg:phone":"+1 607 724 3300",
    "sg:postcode":"13901",
    "sg:province":"NY",
    "sg:tags":[
        "attorney"
    ],
    "wof:name":"Wayne M Chariff Law Office",
    "wof:placetype":"venue"
},
  "geometry": {"coordinates":[-75.91081200000001,42.099285],"type":"Point"}
}