{
  "type": "Feature",
  "properties": {
    "addr:full":"1517 Co Rd 32 Greene NY 13778",
    "addr:housenumber":"1517;32",
    "addr:postcode":"13778",
    "addr:street":"Co Rd",
    "iso:country":"US",
    "sg:address":"1517 Co Rd 32",
    "sg:city":"Greene",
    "sg:classifiers":[
        {
            "category":"Local Transit",
            "type":"Transportation"
        }
    ],
    "sg:phone":"+1 607 656 8931",
    "sg:postcode":"13778",
    "sg:province":"NY",
    "sg:tags":[
        "bus",
        "line"
    ],
    "wof:name":"Greene Central School Bus Grge",
    "wof:placetype":"venue"
},
  "geometry": {"coordinates":[-75.744956,42.333328],"type":"Point"}
}