{
  "type": "Feature",
  "properties": {
    "iso:country":"US",
    "sg:address":"613 Sutter Ave",
    "sg:city":"Brooklyn",
    "sg:classifiers":[
        {
            "category":"Food & Beverages",
            "subcategory":"Liquor & Beverages",
            "type":"Retail Goods"
        }
    ],
    "sg:phone":"+1 718 342 2445",
    "sg:postcode":"11207",
    "sg:province":"NY",
    "sg:tags":[
        "beer",
        "wine",
        "spirit",
        "alcoholic"
    ],
    "wof:name":"Hu-Dell Wine & Liquors Co Inc",
    "wof:placetype":"venue"
},
  "geometry": {"coordinates":[-73.8964,40.6693],"type":"Point"}
}