{
  "type": "Feature",
  "properties": {
    "addr:full":"45 Broadway Ste 2200 New York NY 10006",
    "addr:housenumber":"45",
    "addr:postcode":"10006",
    "addr:street":"Broadway Ste 2200",
    "iso:country":"US",
    "sg:address":"45 Broadway Ste 2200",
    "sg:city":"New York",
    "sg:classifiers":[
        {
            "category":"Professional",
            "subcategory":"Lawyer & Legal Services",
            "type":"Services"
        }
    ],
    "sg:phone":"+1 212 363 3780",
    "sg:postcode":"10006",
    "sg:province":"NY",
    "wof:name":"Bolatti & Griffith",
    "wof:placetype":"venue"
},
  "geometry": {"coordinates":[-74.01288,40.706376],"type":"Point"}
}