{
  "type": "Feature",
  "properties": {
    "iso:country":"US",
    "sg:address":"54 Leroy Ave",
    "sg:city":"Yonkers",
    "sg:classifiers":[
        {
            "category":"Freight",
            "type":"Transportation"
        }
    ],
    "sg:phone":"+1 914 375 6020",
    "sg:postcode":"10705",
    "sg:province":"NY",
    "wof:name":"R & T Transportation Inc",
    "wof:placetype":"venue"
},
  "geometry": {"coordinates":[-73.88680600000001,40.910961],"type":"Point"}
}