{
  "type": "Feature",
  "properties": {
    "iso:country":"US",
    "sg:address":"2124 Deer Park Ave",
    "sg:city":"Deer Park",
    "sg:classifiers":[
        {
            "category":"Retail",
            "subcategory":"Laundry & Dry Cleaning",
            "type":"Services"
        }
    ],
    "sg:phone":"+1   ",
    "sg:postcode":"11729",
    "sg:province":"NY",
    "sg:tags":[
        "cleaners"
    ],
    "wof:name":"Betty Brite Cleaners",
    "wof:placetype":"venue"
},
  "geometry": {"coordinates":[-73.33411700000001,40.773001],"type":"Point"}
}