{
  "type": "Feature",
  "properties": {
    "addr:full":"969 3rd Ave New York NY 10022",
    "addr:housenumber":"969",
    "addr:postcode":"10022",
    "addr:street":"3Rd Ave",
    "iso:country":"US",
    "sg:address":"969 3rd Ave",
    "sg:city":"New York",
    "sg:classifiers":[
        {
            "category":"Personal",
            "subcategory":"Barber",
            "type":"Services"
        }
    ],
    "sg:phone":"+1 212 888 0144",
    "sg:postcode":"10022",
    "sg:province":"NY",
    "sg:website":"premiumbarbershop.com/",
    "wof:name":"Premium Barber Shop",
    "wof:placetype":"venue"
},
  "geometry": {"coordinates":[-73.96705799999999,40.760892],"type":"Point"}
}