{
  "type": "Feature",
  "properties": {
    "iso:country":"US",
    "sg:address":"310 E 46th St",
    "sg:city":"New York",
    "sg:classifiers":[
        {
            "category":"Health Services",
            "subcategory":"Clinic",
            "type":"Services"
        }
    ],
    "sg:phone":"+1 212 599 7576",
    "sg:postcode":"10017",
    "sg:province":"NY",
    "sg:tags":[
        "parapsychologist"
    ],
    "wof:name":"Fortune Tellers Galore",
    "wof:placetype":"venue"
},
  "geometry": {"coordinates":[-73.96811700000001,40.751376],"type":"Point"}
}