{
  "type": "Feature",
  "properties": {
    "addr:full":"619 E 108th St Brooklyn NY 11236",
    "addr:housenumber":"619",
    "addr:postcode":"11236",
    "addr:street":"E 108Th St",
    "iso:country":"US",
    "sg:address":"619 E 108th St",
    "sg:city":"Brooklyn",
    "sg:classifiers":[
        {
            "category":"Freight",
            "type":"Transportation"
        }
    ],
    "sg:phone":"+1   ",
    "sg:postcode":"11236",
    "sg:province":"NY",
    "sg:tags":[
        "operator",
        "local",
        "trucking"
    ],
    "wof:name":"Critical Medicine",
    "wof:placetype":"venue"
},
  "geometry": {"coordinates":[-73.89761,40.653454],"type":"Point"}
}