{
  "type": "Feature",
  "properties": {
    "iso:country":"US",
    "sg:address":"291 Montauk Hwy",
    "sg:city":"Sayville",
    "sg:classifiers":[
        {
            "category":"Shopping",
            "subcategory":"Jewelry",
            "type":"Retail Goods"
        }
    ],
    "sg:phone":"+1   ",
    "sg:postcode":"11782",
    "sg:province":"NY",
    "wof:name":"Idone Jewelry Inc",
    "wof:placetype":"venue"
},
  "geometry": {"coordinates":[-73.078755,40.741049],"type":"Point"}
}