{
  "type": "Feature",
  "properties": {
    "addr:full":"1308 Nostrand Ave Brooklyn NY 11226",
    "addr:housenumber":"1308",
    "addr:postcode":"11226",
    "addr:street":"Nostrand Ave",
    "iso:country":"US",
    "sg:address":"1308 Nostrand Ave",
    "sg:city":"Brooklyn",
    "sg:classifiers":[
        {
            "category":"Personal",
            "subcategory":"Beauty Salon",
            "type":"Services"
        }
    ],
    "sg:phone":"+1 718 941 0074",
    "sg:postcode":"11226",
    "sg:province":"NY",
    "sg:tags":[
        "nail",
        "manicuring"
    ],
    "wof:name":"Jenny Nails",
    "wof:placetype":"venue"
},
  "geometry": {"coordinates":[-73.949997,40.653999],"type":"Point"}
}