{
  "type": "Feature",
  "properties": {
    "addr:full":"1152 Coney Island Ave Brooklyn NY 11230",
    "addr:housenumber":"1152",
    "addr:postcode":"11230",
    "addr:street":"Coney Island Ave",
    "iso:country":"US",
    "sg:address":"1152 Coney Island Ave",
    "sg:city":"Brooklyn",
    "sg:classifiers":[
        {
            "category":"Food & Beverages",
            "subcategory":"Groceries & Convenience Stores",
            "type":"Retail Goods"
        }
    ],
    "sg:phone":"+1   ",
    "sg:postcode":"11230",
    "sg:province":"NY",
    "wof:name":"Oakdale Dairy",
    "wof:placetype":"venue"
},
  "geometry": {"coordinates":[-73.966675,40.631921],"type":"Point"}
}