{
  "type": "Feature",
  "properties": {
    "addr:full":"571 E 141st St Bronx NY 10454",
    "addr:housenumber":"571",
    "addr:postcode":"10454",
    "addr:street":"E 141St St",
    "iso:country":"US",
    "sg:address":"571 E 141st St",
    "sg:city":"Bronx",
    "sg:classifiers":[
        {
            "category":"Restaurant",
            "type":"Food & Drink"
        }
    ],
    "sg:phone":"+1 718 401 0976",
    "sg:postcode":"10454",
    "sg:province":"NY",
    "wof:name":"China Garden",
    "wof:placetype":"venue"
},
  "geometry": {"coordinates":[-73.91553999999999,40.808622],"type":"Point"}
}