{
  "type": "Feature",
  "properties": {
    "iso:country":"US",
    "sg:address":"134 Orchard Rd",
    "sg:city":"Briarcliff Manor",
    "sg:classifiers":[
        {
            "category":"Health Services",
            "subcategory":"Doctor",
            "type":"Services"
        }
    ],
    "sg:phone":"+1 914 941 8585",
    "sg:postcode":"10510",
    "sg:province":"NY",
    "sg:tags":[
        "dentist"
    ],
    "wof:name":"William M Fortinash DDS",
    "wof:placetype":"venue"
},
  "geometry": {"coordinates":[-73.84557599999999,41.162668],"type":"Point"}
}