{
  "type": "Feature",
  "properties": {
    "addr:full":"1002 Jamaica Ave Ste 1 Brooklyn NY 11208",
    "addr:housenumber":"1002",
    "addr:postcode":"11208",
    "addr:street":"Jamaica Ave Ste 1",
    "iso:country":"US",
    "sg:address":"1002 Jamaica Ave Ste 1",
    "sg:city":"Brooklyn",
    "sg:classifiers":[
        {
            "category":"Restaurant",
            "type":"Food & Drink"
        },
        {
            "category":"Bars & Pubs",
            "subcategory":"Nightclub",
            "type":"Food & Drink"
        }
    ],
    "sg:phone":"+1 718 277 3593",
    "sg:postcode":"11208",
    "sg:province":"NY",
    "sg:tags":[
        "mexican",
        "nightlife"
    ],
    "sg:website":"www.zonarosalounge.com",
    "wof:name":"Zona Rosa Lounge & Restaurant",
    "wof:placetype":"venue"
},
  "geometry": {"coordinates":[-73.86878,40.690896],"type":"Point"}
}