{
  "type": "Feature",
  "properties": {
    "iso:country":"US",
    "sg:address":"12 Jennifer Ct",
    "sg:city":"Saratoga Springs",
    "sg:classifiers":[
        {
            "category":"Social Services",
            "subcategory":"Job Training",
            "type":"Services"
        }
    ],
    "sg:phone":"+1 518 373 1883",
    "sg:postcode":"12866",
    "sg:province":"NY",
    "sg:tags":[
        "consulting",
        "management"
    ],
    "wof:name":"Training Group",
    "wof:placetype":"venue"
},
  "geometry": {"coordinates":[-73.758651,43.127237],"type":"Point"}
}