{
  "type": "Feature",
  "properties": {
    "addr:full":"5 Pinelawn Ave Farmingville NY 11738",
    "addr:housenumber":"5",
    "addr:postcode":"11738",
    "addr:street":"Pinelawn Ave",
    "iso:country":"US",
    "sg:address":"5 Pinelawn Ave",
    "sg:city":"Farmingville",
    "sg:classifiers":[
        {
            "category":"Building & Trades",
            "subcategory":"Cleaning & Sanitation",
            "type":"Services"
        }
    ],
    "sg:phone":"+1 631 696 1176",
    "sg:postcode":"11738",
    "sg:province":"NY",
    "sg:tags":[
        "house"
    ],
    "wof:name":"Refined House Cleaning",
    "wof:placetype":"venue"
},
  "geometry": {"coordinates":[-73.02352999999999,40.834945],"type":"Point"}
}