{
  "type": "Feature",
  "properties": {
    "addr:full":"760 Manhattan Ave Brooklyn NY 11222",
    "addr:housenumber":"760",
    "addr:postcode":"11222",
    "addr:street":"Manhattan Ave",
    "iso:country":"US",
    "sg:address":"760 Manhattan Ave",
    "sg:city":"Brooklyn",
    "sg:classifiers":[
        {
            "category":"Banks & Credit Unions",
            "subcategory":"Bank",
            "type":"Services"
        }
    ],
    "sg:phone":"+1 718 349 3531",
    "sg:postcode":"11222",
    "sg:province":"NY",
    "sg:tags":[
        "loan",
        "real estate"
    ],
    "wof:name":"Union Federal Mortgage",
    "wof:placetype":"venue"
},
  "geometry": {"coordinates":[-73.952,40.725702],"type":"Point"}
}