{
  "type": "Feature",
  "properties": {
    "iso:country":"US",
    "sg:address":"5 Sunnyside Rd",
    "sg:city":"Schenectady",
    "sg:classifiers":[
        {
            "category":"Building & Trades",
            "subcategory":"Construction",
            "type":"Services"
        }
    ],
    "sg:phone":"+1 518 393 8164",
    "sg:postcode":"12302",
    "sg:province":"NY",
    "sg:tags":[
        "work",
        "carpentry"
    ],
    "wof:name":"Kenneth L Le Gere",
    "wof:placetype":"venue"
},
  "geometry": {"coordinates":[-73.954702,42.829832],"type":"Point"}
}