{
  "type": "Feature",
  "properties": {
    "addr:full":"107 E 42nd Street New York NY 10017",
    "addr:housenumber":"107",
    "addr:postcode":"10017",
    "addr:street":"E 42Nd Street",
    "iso:country":"US",
    "sg:address":"107 E 42nd Street",
    "sg:city":"New York",
    "sg:classifiers":[
        {
            "category":"Food & Beverages",
            "subcategory":"Liquor & Beverages",
            "type":"Retail Goods"
        }
    ],
    "sg:phone":"+1 212 682 5855",
    "sg:postcode":"10017",
    "sg:province":"NY",
    "sg:tags":[
        "beer",
        "spirit",
        "wine"
    ],
    "wof:name":"Grand Harvest Wines",
    "wof:placetype":"venue"
},
  "geometry": {"coordinates":[-73.976623,40.751795],"type":"Point"}
}