{
  "type": "Feature",
  "properties": {
    "addr:full":"617 W 181st St New York NY 10033",
    "addr:housenumber":"617",
    "addr:postcode":"10033",
    "addr:street":"W 181St St",
    "iso:country":"US",
    "sg:address":"617 W 181st St",
    "sg:city":"New York",
    "sg:classifiers":[
        {
            "category":"Shopping",
            "subcategory":"Shoes",
            "type":"Retail Goods"
        }
    ],
    "sg:phone":"+1 212 665 9083",
    "sg:postcode":"10033",
    "sg:province":"NY",
    "sg:tags":[
        "store"
    ],
    "wof:name":"Option Shops",
    "wof:placetype":"venue"
},
  "geometry": {"coordinates":[-73.934478,40.849922],"type":"Point"}
}