{
  "type": "Feature",
  "properties": {
    "addr:full":"247 Centre St New York NY 10013",
    "addr:housenumber":"247",
    "addr:postcode":"10013",
    "addr:street":"Centre St",
    "iso:country":"US",
    "sg:address":"247 Centre St",
    "sg:city":"New York",
    "sg:classifiers":[
        {
            "category":"Professional",
            "subcategory":"Business Services",
            "type":"Services"
        }
    ],
    "sg:phone":"+1 212 645 9111",
    "sg:postcode":"10013",
    "sg:province":"NY",
    "sg:tags":[
        "interior",
        "consultant",
        "design",
        "decorator"
    ],
    "wof:name":"Doug Stiles Interior Design",
    "wof:placetype":"venue"
},
  "geometry": {"coordinates":[-73.99808400000001,40.720293],"type":"Point"}
}