{
  "type": "Feature",
  "properties": {
    "addr:full":"7128 5th Ave Brooklyn NY 11209",
    "addr:housenumber":"7128",
    "addr:postcode":"11209",
    "addr:street":"5Th Ave",
    "iso:country":"US",
    "sg:address":"7128 5th Ave",
    "sg:city":"Brooklyn",
    "sg:classifiers":[
        {
            "category":"Banks & Credit Unions",
            "subcategory":"Bank",
            "type":"Services"
        }
    ],
    "sg:phone":"+1 917 662 5903",
    "sg:postcode":"11209",
    "sg:province":"NY",
    "sg:tags":[
        "banking",
        "system"
    ],
    "sg:website":"www.atmexpress.com",
    "wof:name":"New York City Atm",
    "wof:placetype":"venue"
},
  "geometry": {"coordinates":[-74.02173000000001,40.631965],"type":"Point"}
}