{
  "type": "Feature",
  "properties": {
    "addr:full":"8703 5th Ave Brooklyn NY 11209",
    "addr:housenumber":"8703",
    "addr:postcode":"11209",
    "addr:street":"5Th Ave",
    "iso:country":"US",
    "sg:address":"8703 5th Ave",
    "sg:city":"Brooklyn",
    "sg:classifiers":[
        {
            "category":"Bars & Pubs",
            "type":"Food & Drink"
        }
    ],
    "sg:phone":"+1   ",
    "sg:postcode":"11209",
    "sg:province":"NY",
    "wof:name":"Kilcar House Restaurant",
    "wof:placetype":"venue"
},
  "geometry": {"coordinates":[-74.02715000000001,40.620293],"type":"Point"}
}