{
  "type": "Feature",
  "properties": {
    "addr:full":"258 Ave A Ronkonkoma NY 11779",
    "addr:housenumber":"258",
    "addr:postcode":"11779",
    "addr:street":"Ave A",
    "iso:country":"US",
    "sg:address":"258 Ave A",
    "sg:city":"Ronkonkoma",
    "sg:classifiers":[
        {
            "category":"Building & Trades",
            "subcategory":"Construction",
            "type":"Services"
        }
    ],
    "sg:phone":"+1 631 467 2909",
    "sg:postcode":"11779",
    "sg:province":"NY",
    "sg:tags":[
        "designer"
    ],
    "wof:name":"Kelly Land Designs Inc",
    "wof:placetype":"venue"
},
  "geometry": {"coordinates":[-73.078408,40.833953],"type":"Point"}
}