{
  "type": "Feature",
  "properties": {
    "iso:country":"US",
    "sg:address":"26162 Pink School House Rd",
    "sg:city":"Theresa",
    "sg:classifiers":[
        {
            "category":"Retail",
            "subcategory":"Auto Repair",
            "type":"Services"
        }
    ],
    "sg:phone":"+1 315 629 5104",
    "sg:postcode":"13691",
    "sg:province":"NY",
    "sg:tags":[
        "shop",
        "automotive",
        "wrecker",
        "towing",
        "general"
    ],
    "wof:name":"French's Auto Repair Shop",
    "wof:placetype":"venue"
},
  "geometry": {"coordinates":[-75.83027800000001,44.15454],"type":"Point"}
}