{
  "type": "Feature",
  "properties": {
    "iso:country":"US",
    "sg:address":"10 W 46 St",
    "sg:city":"New York",
    "sg:classifiers":[
        {
            "category":"Wholesale",
            "subcategory":"Jewelry",
            "type":"Manufacturing & Wholesale Goods"
        }
    ],
    "sg:phone":"+1 212 391 1155",
    "sg:postcode":"10036",
    "sg:province":"NY",
    "sg:tags":[
        "precious",
        "stone"
    ],
    "wof:name":"Andre Assaf",
    "wof:placetype":"venue"
},
  "geometry": {"coordinates":[-73.98208700000001,40.757208],"type":"Point"}
}