{
  "type": "Feature",
  "properties": {
    "addr:full":"65 Abrahamson Rd Middletown NY 10940",
    "addr:housenumber":"65",
    "addr:postcode":"10940",
    "addr:street":"Abrahamson Rd",
    "iso:country":"US",
    "sg:address":"65 Abrahamson Rd",
    "sg:city":"Middletown",
    "sg:classifiers":[
        {
            "category":"Building & Trades",
            "subcategory":"Construction",
            "type":"Services"
        }
    ],
    "sg:phone":"+1 845 386 5500",
    "sg:postcode":"10940",
    "sg:province":"NY",
    "sg:tags":[
        "carpentry",
        "contractor",
        "w",
        "mfg"
    ],
    "wof:name":"Avalon Hill Woodworks",
    "wof:placetype":"venue"
},
  "geometry": {"coordinates":[-74.47252,41.468706],"type":"Point"}
}