{
  "type": "Feature",
  "properties": {
    "iso:country":"US",
    "sg:address":"103 N 13th St",
    "sg:city":"Brooklyn",
    "sg:classifiers":[
        {
            "category":"Wholesale",
            "subcategory":"Fruits & Vegetables",
            "type":"Manufacturing & Wholesale Goods"
        }
    ],
    "sg:phone":"+1 718 388 9886",
    "sg:postcode":"11211",
    "sg:province":"NY",
    "sg:tags":[
        "veggie"
    ],
    "wof:name":"Amerihua Produce Inc",
    "wof:placetype":"venue"
},
  "geometry": {"coordinates":[-73.956639,40.72287],"type":"Point"}
}