{
  "type": "Feature",
  "properties": {
    "iso:country":"US",
    "sg:address":"1 Judson Ave",
    "sg:city":"Binghamton",
    "sg:classifiers":[
        {
            "category":"Organizations",
            "subcategory":"Religious Organization",
            "type":"Services"
        }
    ],
    "sg:phone":"+1 607 797 8388",
    "sg:postcode":"13905",
    "sg:province":"NY",
    "sg:tags":[
        "monastery",
        "convent"
    ],
    "wof:name":"Methodius Sisters Of SS Cyril",
    "wof:placetype":"venue"
},
  "geometry": {"coordinates":[-75.93865099999999,42.114993],"type":"Point"}
}