{
  "type": "Feature",
  "properties": {
    "iso:country":"US",
    "sg:address":"2101 Teall Ave",
    "sg:city":"Syracuse",
    "sg:classifiers":[
        {
            "category":"Manufacturing",
            "subcategory":"Tools & Machinery",
            "type":"Manufacturing & Wholesale Goods"
        }
    ],
    "sg:phone":"+1   ",
    "sg:postcode":"13206",
    "sg:province":"NY",
    "sg:tags":[
        "industrial",
        "mfg"
    ],
    "wof:name":"Roboshop Inc",
    "wof:placetype":"venue"
},
  "geometry": {"coordinates":[-76.12348299999999,43.080254],"type":"Point"}
}