{
  "type": "Feature",
  "properties": {
    "iso:country":"US",
    "sg:address":"7 Cedar Ln",
    "sg:city":"Setauket",
    "sg:classifiers":[
        {
            "category":"Banks & Credit Unions",
            "subcategory":"Investment Brokerage",
            "type":"Services"
        }
    ],
    "sg:phone":"+1 631 689 7000",
    "sg:postcode":"11733",
    "sg:province":"NY",
    "sg:tags":[
        "advisory",
        "financial"
    ],
    "wof:name":"Ny Financial Technologies",
    "wof:placetype":"venue"
},
  "geometry": {"coordinates":[-73.11540100000001,40.963509],"type":"Point"}
}