{
  "type": "Feature",
  "properties": {
    "addr:full":"7718 Flatlands Ave Brooklyn NY 11236",
    "addr:housenumber":"7718",
    "addr:postcode":"11236",
    "addr:street":"Flatlands Ave",
    "iso:country":"US",
    "sg:address":"7718 Flatlands Ave",
    "sg:city":"Brooklyn",
    "sg:classifiers":[
        {
            "category":"Professional",
            "subcategory":"Lawyer & Legal Services",
            "type":"Services"
        }
    ],
    "sg:phone":"+1 718 756 0983",
    "sg:postcode":"11236",
    "sg:province":"NY",
    "wof:name":"David Lafleur & Ingrid Wyllie Esq",
    "wof:placetype":"venue"
},
  "geometry": {"coordinates":[-73.915192,40.634029],"type":"Point"}
}