{
  "type": "Feature",
  "properties": {
    "addr:full":"916 3rd Avenue Frnt 2 New York NY 10022",
    "addr:housenumber":"916;2",
    "addr:postcode":"10022",
    "addr:street":"3Rd Avenue Frnt",
    "iso:country":"US",
    "sg:address":"916 3rd Avenue Frnt 2",
    "sg:city":"New York",
    "sg:classifiers":[
        {
            "category":"Personal",
            "subcategory":"Nail Salon",
            "type":"Services"
        }
    ],
    "sg:phone":"+1 212 751 6245",
    "sg:postcode":"10022",
    "sg:province":"NY",
    "wof:name":"Nail Studio",
    "wof:placetype":"venue"
},
  "geometry": {"coordinates":[-73.96831899999999,40.758974],"type":"Point"}
}