{
  "type": "Feature",
  "properties": {
    "addr:full":"193 Aspinwall St Westbury NY 11590",
    "addr:housenumber":"193",
    "addr:postcode":"11590",
    "addr:street":"Aspinwall St",
    "iso:country":"US",
    "sg:address":"193 Aspinwall St",
    "sg:city":"Westbury",
    "sg:classifiers":[
        {
            "category":"Building & Trades",
            "subcategory":"Construction",
            "type":"Services"
        }
    ],
    "sg:phone":"+1 516 333 4308",
    "sg:postcode":"11590",
    "sg:province":"NY",
    "sg:tags":[
        "contractor"
    ],
    "wof:name":"L D Contrctng",
    "wof:placetype":"venue"
},
  "geometry": {"coordinates":[-73.60380499999999,40.754325],"type":"Point"}
}