{
  "type": "Feature",
  "properties": {
    "addr:full":"15 Reed Dr Roslyn NY 11576",
    "addr:housenumber":"15",
    "addr:postcode":"11576",
    "addr:street":"Reed Dr",
    "iso:country":"US",
    "sg:address":"15 Reed Dr",
    "sg:city":"Roslyn",
    "sg:classifiers":[
        {
            "category":"Professional",
            "subcategory":"Lawyer & Legal Services",
            "type":"Services"
        }
    ],
    "sg:phone":"+1 516 535 3900",
    "sg:postcode":"11576",
    "sg:province":"NY",
    "wof:name":"Sosnick Matthew Law Office Attorney",
    "wof:placetype":"venue"
},
  "geometry": {"coordinates":[-73.659599,40.762901],"type":"Point"}
}