{
  "type": "Feature",
  "properties": {
    "iso:country":"US",
    "sg:address":"66 W Barclay St",
    "sg:city":"Hicksville",
    "sg:classifiers":[
        {
            "category":"Shopping",
            "subcategory":"Gifts & Souvenirs",
            "type":"Retail Goods"
        }
    ],
    "sg:phone":"+1   ",
    "sg:postcode":"11801",
    "sg:province":"NY",
    "wof:name":"Card Treasures & Memorabilia",
    "wof:placetype":"venue"
},
  "geometry": {"coordinates":[-73.528831,40.768025],"type":"Point"}
}