{
  "type": "Feature",
  "properties": {
    "addr:full":"345 Parsells Ave Rochester NY 14609",
    "addr:housenumber":"345",
    "addr:postcode":"14609",
    "addr:street":"Parsells Ave",
    "iso:country":"US",
    "sg:address":"345 Parsells Ave",
    "sg:city":"Rochester",
    "sg:classifiers":[
        {
            "category":"Organizations",
            "subcategory":"Religious Organization",
            "type":"Services"
        }
    ],
    "sg:phone":"+1 585 482 4413",
    "sg:postcode":"14609",
    "sg:province":"NY",
    "sg:tags":[
        "church"
    ],
    "wof:name":"Parsells Ave Community Church",
    "wof:placetype":"venue"
},
  "geometry": {"coordinates":[-77.56952699999999,43.165704],"type":"Point"}
}