{
  "type": "Feature",
  "properties": {
    "addr:full":"114 Blacksmith Rd E Levittown NY 11756",
    "addr:housenumber":"114",
    "addr:postcode":"11756",
    "addr:street":"Blacksmith Rd E",
    "iso:country":"US",
    "sg:address":"114 Blacksmith Rd E",
    "sg:city":"Levittown",
    "sg:classifiers":[
        {
            "category":"Social Services",
            "subcategory":"Child Care",
            "type":"Services"
        }
    ],
    "sg:phone":"+1 516 735 7659",
    "sg:postcode":"11756",
    "sg:province":"NY",
    "sg:tags":[
        "day"
    ],
    "wof:name":"Jackson Heights Childrens Ctr",
    "wof:placetype":"venue"
},
  "geometry": {"coordinates":[-73.51496400000001,40.737947],"type":"Point"}
}