{
  "type": "Feature",
  "properties": {
    "addr:full":"627 Maple Ave Saratoga Springs NY 12866",
    "addr:housenumber":"627",
    "addr:postcode":"12866",
    "addr:street":"Maple Ave",
    "iso:country":"US",
    "sg:address":"627 Maple Ave",
    "sg:city":"Saratoga Springs",
    "sg:classifiers":[
        {
            "category":"Real Estate",
            "subcategory":"Architect",
            "type":"Services"
        }
    ],
    "sg:phone":"+1 518 580 1905",
    "sg:postcode":"12866",
    "sg:province":"NY",
    "wof:name":"Rucinski Hall Architecture",
    "wof:placetype":"venue"
},
  "geometry": {"coordinates":[-73.768353,43.122918],"type":"Point"}
}