{
  "type": "Feature",
  "properties": {
    "addr:full":"390 Knickerbocker Ave # 15 Bohemia NY 11716",
    "addr:housenumber":"390;15",
    "addr:postcode":"11716",
    "addr:street":"Knickerbocker Ave #",
    "iso:country":"US",
    "sg:address":"390 Knickerbocker Ave # 15",
    "sg:city":"Bohemia",
    "sg:classifiers":[
        {
            "category":"Food & Beverages",
            "subcategory":"Bakery",
            "type":"Retail Goods"
        },
        {
            "category":"Bakery",
            "type":"Food & Drink"
        }
    ],
    "sg:phone":"+1 631 563 0092",
    "sg:postcode":"11716",
    "sg:province":"NY",
    "sg:tags":[
        "bakers-wholesale"
    ],
    "wof:name":"Kara's Organic Bakery",
    "wof:placetype":"venue"
},
  "geometry": {"coordinates":[-73.08775799999999,40.780582],"type":"Point"}
}