{
  "type": "Feature",
  "properties": {
    "addr:full":"69 Grand Island Blvd Tonawanda NY 14150",
    "addr:housenumber":"69",
    "addr:postcode":"14150",
    "addr:street":"Grand Island Blvd",
    "iso:country":"US",
    "sg:address":"69 Grand Island Blvd",
    "sg:city":"Tonawanda",
    "sg:classifiers":[
        {
            "category":"Deli",
            "type":"Food & Drink"
        }
    ],
    "sg:menulink":"http://www.allmenus.com/ny/tonawanda/245675-louies-original-foot-long-hot-dogs/menu/",
    "sg:phone":"+1 716 877 9701",
    "sg:postcode":"14150",
    "sg:province":"NY",
    "sg:tags":[
        "american"
    ],
    "wof:name":"Louie's Original Foot Long Hot Dogs",
    "wof:placetype":"venue"
},
  "geometry": {"coordinates":[-78.90520600000001,42.980581],"type":"Point"}
}