{
  "type": "Feature",
  "properties": {
    "iso:country":"US",
    "sg:address":"2002 Utica Ave",
    "sg:city":"Brooklyn",
    "sg:classifiers":[
        {
            "category":"Autos & Motor Vehicles",
            "subcategory":"Automobile Sales",
            "type":"Retail Goods"
        }
    ],
    "sg:phone":"+1   ",
    "sg:postcode":"11234",
    "sg:province":"NY",
    "sg:tags":[
        "used"
    ],
    "wof:name":"Sheepshead Motors",
    "wof:placetype":"venue"
},
  "geometry": {"coordinates":[-73.927251,40.621865],"type":"Point"}
}