{
  "type": "Feature",
  "properties": {
    "addr:full":"2297 E 21st St Brooklyn NY 11229",
    "addr:housenumber":"2297",
    "addr:postcode":"11229",
    "addr:street":"E 21St St",
    "iso:country":"US",
    "sg:address":"2297 E 21st St",
    "sg:city":"Brooklyn",
    "sg:classifiers":[
        {
            "category":"Professional",
            "subcategory":"Lawyer & Legal Services",
            "type":"Services"
        }
    ],
    "sg:phone":"+1 718 434 0507",
    "sg:postcode":"11229",
    "sg:province":"NY",
    "sg:tags":[
        "naturalization",
        "immigration"
    ],
    "wof:name":"Immigration Farm Filling Svc",
    "wof:placetype":"venue"
},
  "geometry": {"coordinates":[-73.949546,40.5957],"type":"Point"}
}