{
  "type": "Feature",
  "properties": {
    "iso:country":"US",
    "sg:address":"86 Rapp Rd",
    "sg:city":"Monticello",
    "sg:classifiers":[
        {
            "category":"Shopping",
            "subcategory":"Used Merchandise",
            "type":"Retail Goods"
        }
    ],
    "sg:phone":"+1   ",
    "sg:postcode":"12701",
    "sg:province":"NY",
    "wof:name":"Kids Exchange",
    "wof:placetype":"venue"
},
  "geometry": {"coordinates":[-74.733603,41.696106],"type":"Point"}
}