{
  "type": "Feature",
  "properties": {
    "addr:full":"1492 Richmond Rd Staten Island NY 10304",
    "addr:housenumber":"1492",
    "addr:postcode":"10304",
    "addr:street":"Richmond Rd",
    "iso:country":"US",
    "sg:address":"1492 Richmond Rd",
    "sg:city":"Staten Island",
    "sg:classifiers":[
        {
            "category":"Manufacturing",
            "subcategory":"Printing",
            "type":"Manufacturing & Wholesale Goods"
        }
    ],
    "sg:phone":"+1   ",
    "sg:postcode":"10304",
    "sg:province":"NY",
    "sg:tags":[
        "publisher",
        "magazine"
    ],
    "wof:name":"Newborn News",
    "wof:placetype":"venue"
},
  "geometry": {"coordinates":[-74.10065299999999,40.592861],"type":"Point"}
}