{
  "type": "Feature",
  "properties": {
    "addr:full":"240 Grand St New York NY 10002",
    "addr:housenumber":"240",
    "addr:postcode":"10002",
    "addr:street":"Grand St",
    "iso:country":"US",
    "sg:address":"240 Grand St",
    "sg:city":"New York",
    "sg:classifiers":[
        {
            "category":"Shopping",
            "type":"Retail Goods"
        }
    ],
    "sg:phone":"+1 212 966 2777",
    "sg:postcode":"10002",
    "sg:province":"NY",
    "sg:tags":[
        "art",
        "gallery",
        "dealer"
    ],
    "wof:name":"Art Design Studio",
    "wof:placetype":"venue"
},
  "geometry": {"coordinates":[-73.99396400000001,40.718283],"type":"Point"}
}