{
  "type": "Feature",
  "properties": {
    "addr:full":"140 Swansea Dr Syracuse NY 13206",
    "addr:housenumber":"140",
    "addr:postcode":"13206",
    "addr:street":"Swansea Dr",
    "iso:country":"US",
    "sg:address":"140 Swansea Dr",
    "sg:city":"Syracuse",
    "sg:classifiers":[
        {
            "category":"Organizations",
            "subcategory":"Religious Organization",
            "type":"Services"
        }
    ],
    "sg:phone":"+1 315 437 8203",
    "sg:postcode":"13206",
    "sg:province":"NY",
    "sg:tags":[
        "church"
    ],
    "wof:name":"Trinity Lutheran Church",
    "wof:placetype":"venue"
},
  "geometry": {"coordinates":[-76.12036000000001,43.071373],"type":"Point"}
}