{
  "type": "Feature",
  "properties": {
    "addr:full":"7720 Soundview Ave Southold NY 11971",
    "addr:housenumber":"7720",
    "addr:postcode":"11971",
    "addr:street":"Soundview Ave",
    "iso:country":"US",
    "sg:address":"7720 Soundview Ave",
    "sg:city":"Southold",
    "sg:classifiers":[
        {
            "category":"Building & Trades",
            "subcategory":"Landscaping Services",
            "type":"Services"
        }
    ],
    "sg:phone":"+1 631 765 2528",
    "sg:postcode":"11971",
    "sg:province":"NY",
    "sg:tags":[
        "landscape"
    ],
    "wof:name":"Blue Water Irrigation LLC",
    "wof:placetype":"venue"
},
  "geometry": {"coordinates":[-72.452287,41.065637],"type":"Point"}
}