{
  "type": "Feature",
  "properties": {
    "addr:full":"1156 Merrick Rd North Merrick NY 11566",
    "addr:housenumber":"1156",
    "addr:postcode":"11566",
    "addr:street":"Merrick Rd",
    "iso:country":"US",
    "sg:address":"1156 Merrick Rd",
    "sg:city":"North Merrick",
    "sg:classifiers":[
        {
            "category":"Personal",
            "subcategory":"Barber",
            "type":"Services"
        }
    ],
    "sg:phone":"+1 516 481 7180",
    "sg:postcode":"11566",
    "sg:province":"NY",
    "wof:name":"Bob's Shear Bobs Barber Stylst",
    "wof:placetype":"venue"
},
  "geometry": {"coordinates":[-73.56531099999999,40.653748],"type":"Point"}
}