{
  "type": "Feature",
  "properties": {
    "iso:country":"US",
    "sg:address":"74 W Main St",
    "sg:city":"Springville",
    "sg:classifiers":[
        {
            "category":"Shopping",
            "subcategory":"Optical Goods",
            "type":"Retail Goods"
        }
    ],
    "sg:phone":"+1 716 592 5505",
    "sg:postcode":"14141",
    "sg:province":"NY",
    "wof:name":"Springville Optical",
    "wof:placetype":"venue"
},
  "geometry": {"coordinates":[-78.672489,42.50872],"type":"Point"}
}