{
  "type": "Feature",
  "properties": {
    "addr:full":"2061 Western Ave Guilderland NY 12084",
    "addr:housenumber":"2061",
    "addr:postcode":"12084",
    "addr:street":"Western Ave",
    "iso:country":"US",
    "sg:address":"2061 Western Ave",
    "sg:city":"Guilderland",
    "sg:classifiers":[
        {
            "category":"Building & Trades",
            "subcategory":"Construction",
            "type":"Services"
        }
    ],
    "sg:phone":"+1 518 218 0420",
    "sg:postcode":"12084",
    "sg:province":"NY",
    "sg:tags":[
        "general",
        "contractor"
    ],
    "wof:name":"Triangle Construction",
    "wof:placetype":"venue"
},
  "geometry": {"coordinates":[-73.888346,42.697679],"type":"Point"}
}