{
  "type": "Feature",
  "properties": {
    "iso:country":"US",
    "sg:address":"1768 Jerome Ave",
    "sg:city":"Bronx",
    "sg:classifiers":[
        {
            "category":"Building & Trades",
            "subcategory":"Construction",
            "type":"Services"
        }
    ],
    "sg:phone":"+1 718 299 8484",
    "sg:postcode":"10453",
    "sg:province":"NY",
    "sg:tags":[
        "front",
        "metal",
        "installation",
        "store"
    ],
    "wof:name":"A SILMAC GLASS",
    "wof:placetype":"venue"
},
  "geometry": {"coordinates":[-73.911973,40.848073],"type":"Point"}
}