{
  "type": "Feature",
  "properties": {
    "addr:full":"11 Adams Ave Centereach NY 11720",
    "addr:housenumber":"11",
    "addr:postcode":"11720",
    "addr:street":"Adams Ave",
    "iso:country":"US",
    "sg:address":"11 Adams Ave",
    "sg:city":"Centereach",
    "sg:classifiers":[
        {
            "category":"Professional",
            "subcategory":"Business Services",
            "type":"Services"
        }
    ],
    "sg:phone":"+1 631 736 2973",
    "sg:postcode":"11720",
    "sg:province":"NY",
    "wof:name":"Monkey Business",
    "wof:placetype":"venue"
},
  "geometry": {"coordinates":[-73.063478,40.876178],"type":"Point"}
}