{
  "type": "Feature",
  "properties": {
    "addr:full":"225 E 26th St New York NY 10010",
    "addr:housenumber":"225",
    "addr:postcode":"10010",
    "addr:street":"E 26Th St",
    "iso:country":"US",
    "sg:address":"225 E 26th St",
    "sg:city":"New York",
    "sg:classifiers":[
        {
            "category":"Shopping",
            "subcategory":"Optical Goods",
            "type":"Retail Goods"
        }
    ],
    "sg:phone":"+1   ",
    "sg:postcode":"10010",
    "sg:province":"NY",
    "wof:name":"Brite Eyes LLC",
    "wof:placetype":"venue"
},
  "geometry": {"coordinates":[-73.98063,40.74038],"type":"Point"}
}