{
  "type": "Feature",
  "properties": {
    "iso:country":"US",
    "sg:address":"678 Troy Schenectady Rd",
    "sg:city":"Latham",
    "sg:classifiers":[
        {
            "category":"Professional",
            "subcategory":"Management & Consulting",
            "type":"Services"
        }
    ],
    "sg:phone":"+1   ",
    "sg:postcode":"12110",
    "sg:province":"NY",
    "sg:tags":[
        "retail",
        "direct",
        "sales"
    ],
    "wof:name":"Encyclopaedia Britannica Inc",
    "wof:placetype":"venue"
},
  "geometry": {"coordinates":[-73.77512900000001,42.755642],"type":"Point"}
}