{
  "type": "Feature",
  "properties": {
    "addr:full":"6907 50th Avenue Woodside NY 11377",
    "addr:housenumber":"6907",
    "addr:postcode":"11377",
    "addr:street":"50Th Avenue",
    "iso:country":"US",
    "sg:address":"6907 50th Avenue",
    "sg:city":"Woodside",
    "sg:classifiers":[
        {
            "category":"Retail",
            "subcategory":"Auto Rental",
            "type":"Services"
        }
    ],
    "sg:phone":"+1 718 424 8679",
    "sg:postcode":"11377",
    "sg:province":"NY",
    "sg:tags":[
        "car"
    ],
    "wof:name":"Sunset & Sunrise Corporation",
    "wof:placetype":"venue"
},
  "geometry": {"coordinates":[-73.895735,40.736919],"type":"Point"}
}