{
  "type": "Feature",
  "properties": {
    "addr:full":"54 Lander St Newburgh NY 12550",
    "addr:housenumber":"54",
    "addr:postcode":"12550",
    "addr:street":"Lander St",
    "iso:country":"US",
    "sg:address":"54 Lander St",
    "sg:city":"Newburgh",
    "sg:classifiers":[
        {
            "category":"Arts & Performance",
            "subcategory":"Theater",
            "type":"Entertainment"
        }
    ],
    "sg:phone":"+1 845 565 2450",
    "sg:postcode":"12550",
    "sg:province":"NY",
    "sg:tags":[
        "bureau"
    ],
    "wof:name":"Card Head Entertainment",
    "wof:placetype":"venue"
},
  "geometry": {"coordinates":[-74.012631,41.500198],"type":"Point"}
}