{
  "type": "Feature",
  "properties": {
    "addr:full":"5312 Briercliff Dr Hamburg NY 14075",
    "addr:housenumber":"5312",
    "addr:postcode":"14075",
    "addr:street":"Briercliff Dr",
    "iso:country":"US",
    "sg:address":"5312 Briercliff Dr",
    "sg:city":"Hamburg",
    "sg:classifiers":[
        {
            "category":"Shopping",
            "subcategory":"Bicycles & Sporting Goods",
            "type":"Retail Goods"
        }
    ],
    "sg:phone":"+1   ",
    "sg:postcode":"14075",
    "sg:province":"NY",
    "wof:name":"Game Balz Inc",
    "wof:placetype":"venue"
},
  "geometry": {"coordinates":[-78.894625,42.74165],"type":"Point"}
}