{
  "type": "Feature",
  "properties": {
    "iso:country":"US",
    "sg:address":"345 E Union St",
    "sg:city":"Newark",
    "sg:classifiers":[
        {
            "category":"Shopping",
            "subcategory":"Books",
            "type":"Retail Goods"
        }
    ],
    "sg:phone":"+1   ",
    "sg:postcode":"14513",
    "sg:province":"NY",
    "wof:name":"E Books Make Money",
    "wof:placetype":"venue"
},
  "geometry": {"coordinates":[-77.086776,43.046338],"type":"Point"}
}