{
  "type": "Feature",
  "properties": {
    "addr:full":"450 Ave of the Americas New York NY 10011",
    "addr:housenumber":"450",
    "addr:postcode":"10011",
    "addr:street":"Ave Of The Americas",
    "iso:country":"US",
    "sg:address":"450 Ave of the Americas",
    "sg:city":"New York",
    "sg:classifiers":[
        {
            "category":"Building & Trades",
            "subcategory":"Construction",
            "type":"Services"
        }
    ],
    "sg:phone":"+1 212 533 6984",
    "sg:postcode":"10011",
    "sg:province":"NY",
    "sg:tags":[
        "designer"
    ],
    "wof:name":"France Eve Designs",
    "wof:placetype":"venue"
},
  "geometry": {"coordinates":[-73.998239,40.735299],"type":"Point"}
}