{
  "type": "Feature",
  "properties": {
    "addr:full":"3374 Boston Rd Bronx NY 10469",
    "addr:housenumber":"3374",
    "addr:postcode":"10469",
    "addr:street":"Boston Rd",
    "iso:country":"US",
    "sg:address":"3374 Boston Rd",
    "sg:city":"Bronx",
    "sg:classifiers":[
        {
            "category":"Recreation",
            "type":"Entertainment"
        }
    ],
    "sg:phone":"+1 718 519 7458",
    "sg:postcode":"10469",
    "sg:province":"NY",
    "sg:tags":[
        "martial",
        "arts",
        "instruction"
    ],
    "wof:name":"Boston Road Tae KWON Do Inc",
    "wof:placetype":"venue"
},
  "geometry": {"coordinates":[-73.850695,40.875382],"type":"Point"}
}