{
  "type": "Feature",
  "properties": {
    "addr:full":"2104 Crotona Pkwy Bronx NY 10460",
    "addr:housenumber":"2104",
    "addr:postcode":"10460",
    "addr:street":"Crotona Pkwy",
    "iso:country":"US",
    "sg:address":"2104 Crotona Pkwy",
    "sg:city":"Bronx",
    "sg:classifiers":[
        {
            "category":"Food & Beverages",
            "subcategory":"Meat & Fish",
            "type":"Retail Goods"
        }
    ],
    "sg:phone":"+1 800 632 8658",
    "sg:postcode":"10460",
    "sg:province":"NY",
    "sg:tags":[
        "shop"
    ],
    "wof:name":"Crotona Meats",
    "wof:placetype":"venue"
},
  "geometry": {"coordinates":[-73.88389599999999,40.845842],"type":"Point"}
}