{
  "type": "Feature",
  "properties": {
    "addr:full":"307 Pinewoods Ave Troy NY 12180",
    "addr:housenumber":"307",
    "addr:postcode":"12180",
    "addr:street":"Pinewoods Ave",
    "iso:country":"US",
    "sg:address":"307 Pinewoods Ave",
    "sg:city":"Troy",
    "sg:classifiers":[
        {
            "category":"Real Estate",
            "subcategory":"Real Estate Agent",
            "type":"Services"
        }
    ],
    "sg:phone":"+1 518 584 1473",
    "sg:postcode":"12180",
    "sg:province":"NY",
    "sg:website":"www.scottfilm.com",
    "wof:name":"Scott Film Realty",
    "wof:placetype":"venue"
},
  "geometry": {"coordinates":[-73.63829,42.716999],"type":"Point"}
}