{
  "type": "Feature",
  "properties": {
    "addr:full":"1249 Atlantic Ave Brooklyn NY 11216",
    "addr:housenumber":"1249",
    "addr:postcode":"11216",
    "addr:street":"Atlantic Ave",
    "iso:country":"US",
    "sg:address":"1249 Atlantic Ave",
    "sg:city":"Brooklyn",
    "sg:classifiers":[
        {
            "category":"Restaurant",
            "type":"Food & Drink"
        }
    ],
    "sg:phone":"+1   ",
    "sg:postcode":"11216",
    "sg:province":"NY",
    "sg:tags":[
        "eating"
    ],
    "wof:name":"Perfect Touch Cuisine",
    "wof:placetype":"venue"
},
  "geometry": {"coordinates":[-73.94713900000001,40.678483],"type":"Point"}
}