{
  "type": "Feature",
  "properties": {
    "iso:country":"US",
    "sg:address":"73 Center St",
    "sg:city":"Geneseo",
    "sg:classifiers":[
        {
            "category":"Building & Trades",
            "subcategory":"Landscaping Services",
            "type":"Services"
        }
    ],
    "sg:phone":"+1 585 243 4922",
    "sg:postcode":"14454",
    "sg:province":"NY",
    "sg:tags":[
        "landscape",
        "contractor"
    ],
    "sg:website":"http://www.smithlandscapingny.com",
    "wof:name":"Smith Landscaping",
    "wof:placetype":"venue"
},
  "geometry": {"coordinates":[-77.809421,42.795379],"type":"Point"}
}