{
  "type": "Feature",
  "properties": {
    "addr:full":"6848 Erie Rd Derby NY 14047",
    "addr:housenumber":"6848",
    "addr:postcode":"14047",
    "addr:street":"Erie Rd",
    "iso:country":"US",
    "sg:address":"6848 Erie Rd",
    "sg:city":"Derby",
    "sg:classifiers":[
        {
            "category":"Bars & Pubs",
            "type":"Food & Drink"
        },
        {
            "category":"Restaurant",
            "type":"Food & Drink"
        }
    ],
    "sg:phone":"+1 716 947 9386",
    "sg:postcode":"14047",
    "sg:province":"NY",
    "wof:name":"Meadowbrook Restrnt & Bar",
    "wof:placetype":"venue"
},
  "geometry": {"coordinates":[-78.98115900000001,42.70082],"type":"Point"}
}