{
  "type": "Feature",
  "properties": {
    "iso:country":"US",
    "sg:address":"350 Leland Ave",
    "sg:city":"Utica",
    "sg:classifiers":[
        {
            "category":"Professional",
            "type":"Services"
        }
    ],
    "sg:phone":"+1 315 733 6350",
    "sg:postcode":"13502",
    "sg:province":"NY",
    "sg:tags":[
        "establishment"
    ],
    "wof:name":"My Best Kept Secret",
    "wof:placetype":"venue"
},
  "geometry": {"coordinates":[-75.20679199999999,43.113183],"type":"Point"}
}