{
  "type": "Feature",
  "properties": {
    "addr:full":"87 Violet Dr Pearl River NY 10965",
    "addr:housenumber":"87",
    "addr:postcode":"10965",
    "addr:street":"Violet Dr",
    "iso:country":"US",
    "sg:address":"87 Violet Dr",
    "sg:city":"Pearl River",
    "sg:classifiers":[
        {
            "category":"Banks & Credit Unions",
            "subcategory":"Financial Services",
            "type":"Services"
        }
    ],
    "sg:phone":"+1 845 623 7637",
    "sg:postcode":"10965",
    "sg:province":"NY",
    "sg:tags":[
        "advisory",
        "management",
        "open",
        "investment"
    ],
    "wof:name":"Volumetric Advisers Inc",
    "wof:placetype":"venue"
},
  "geometry": {"coordinates":[-74.005292,41.07657],"type":"Point"}
}