{
  "type": "Feature",
  "properties": {
    "iso:country":"US",
    "sg:address":"380 Lexington Ave",
    "sg:city":"New York",
    "sg:classifiers":[
        {
            "category":"Communications",
            "type":"Services"
        }
    ],
    "sg:phone":"+1 212 265 5636",
    "sg:postcode":"10168",
    "sg:province":"NY",
    "sg:tags":[
        "recording",
        "rehearsal",
        "studio"
    ],
    "wof:name":"TRUTONE REPLICATION",
    "wof:placetype":"venue"
},
  "geometry": {"coordinates":[-73.976204,40.751543],"type":"Point"}
}