{
  "type": "Feature",
  "properties": {
    "addr:full":"145 Albany Ave Amityville NY 11701",
    "addr:housenumber":"145",
    "addr:postcode":"11701",
    "addr:street":"Albany Ave",
    "iso:country":"US",
    "sg:address":"145 Albany Ave",
    "sg:city":"Amityville",
    "sg:classifiers":[
        {
            "category":"Retail",
            "subcategory":"Auto Repair",
            "type":"Services"
        }
    ],
    "sg:phone":"+1 631 789 2009",
    "sg:postcode":"11701",
    "sg:province":"NY",
    "sg:tags":[
        "repairing",
        "automobile"
    ],
    "wof:name":"Atlantic Toyota",
    "wof:placetype":"venue"
},
  "geometry": {"coordinates":[-73.41371599999999,40.687594],"type":"Point"}
}