{
  "type": "Feature",
  "properties": {
    "iso:country":"US",
    "sg:address":"572 W Caswell Ave",
    "sg:city":"Staten Island",
    "sg:classifiers":[
        {
            "category":"Farming",
            "subcategory":"Nursery",
            "type":"Manufacturing & Wholesale Goods"
        }
    ],
    "sg:phone":"+1 718 761 7398",
    "sg:postcode":"10314",
    "sg:province":"NY",
    "sg:tags":[
        "floral",
        "product",
        "greenhouse",
        "for",
        "st"
    ],
    "wof:name":"Santacroce Greenhouses Inc",
    "wof:placetype":"venue"
},
  "geometry": {"coordinates":[-74.155547,40.616086],"type":"Point"}
}