{
  "type": "Feature",
  "properties": {
    "addr:full":"935 Morris Park Avenue Bronx NY 10462",
    "addr:housenumber":"935",
    "addr:postcode":"10462",
    "addr:street":"Morris Park Avenue",
    "iso:country":"US",
    "sg:address":"935 Morris Park Avenue",
    "sg:city":"Bronx",
    "sg:classifiers":[
        {
            "category":"Personal",
            "subcategory":"Barber",
            "type":"Services"
        }
    ],
    "sg:phone":"+1 718 239 2345",
    "sg:postcode":"10462",
    "sg:province":"NY",
    "wof:name":"Sha's Big Time Barber Shop",
    "wof:placetype":"venue"
},
  "geometry": {"coordinates":[-73.858188,40.847219],"type":"Point"}
}