{
  "type": "Feature",
  "properties": {
    "addr:full":"152 E 65th Street New York NY 10021",
    "addr:housenumber":"152",
    "addr:postcode":"10021",
    "addr:street":"E 65Th Street",
    "iso:country":"US",
    "sg:address":"152 E 65th Street",
    "sg:city":"New York",
    "sg:classifiers":[
        {
            "category":"Arts & Performance",
            "subcategory":"Art Gallery",
            "type":"Entertainment"
        }
    ],
    "sg:phone":"+1 212 452 1094",
    "sg:postcode":"10021",
    "sg:province":"NY",
    "sg:website":"www.perezcelis.com",
    "wof:name":"Shapolsky Anita Gallery",
    "wof:placetype":"venue"
},
  "geometry": {"coordinates":[-73.96507,40.765688],"type":"Point"}
}