{
  "type": "Feature",
  "properties": {
    "addr:full":"94 S Union St Spencerport NY 14559",
    "addr:housenumber":"94",
    "addr:postcode":"14559",
    "addr:street":"S Union St",
    "iso:country":"US",
    "sg:address":"94 S Union St",
    "sg:city":"Spencerport",
    "sg:classifiers":[
        {
            "category":"Restaurant",
            "type":"Food & Drink"
        }
    ],
    "sg:phone":"+1 585 352 9100",
    "sg:postcode":"14559",
    "sg:province":"NY",
    "wof:name":"Steuey's Sweet Shop",
    "wof:placetype":"venue"
},
  "geometry": {"coordinates":[-77.800477,43.192921],"type":"Point"}
}