{
  "type": "Feature",
  "properties": {
    "addr:full":"23 Oswego Pl West Babylon NY 11704",
    "addr:housenumber":"23",
    "addr:postcode":"11704",
    "addr:street":"Oswego Pl",
    "iso:country":"US",
    "sg:address":"23 Oswego Pl",
    "sg:city":"West Babylon",
    "sg:classifiers":[
        {
            "category":"Organizations",
            "subcategory":"Religious Organization",
            "type":"Services"
        }
    ],
    "sg:phone":"+1 631 491 3445",
    "sg:postcode":"11704",
    "sg:province":"NY",
    "sg:tags":[
        "clergy"
    ],
    "wof:name":"Margrie Lewter Simmons",
    "wof:placetype":"venue"
},
  "geometry": {"coordinates":[-73.353328,40.739873],"type":"Point"}
}