{
  "type": "Feature",
  "properties": {
    "addr:full":"750 E 179th St Bronx NY 10457",
    "addr:housenumber":"750",
    "addr:postcode":"10457",
    "addr:street":"E 179Th St",
    "iso:country":"US",
    "sg:address":"750 E 179th St",
    "sg:city":"Bronx",
    "sg:classifiers":[
        {
            "category":"Retail",
            "subcategory":"Repair Shop",
            "type":"Services"
        }
    ],
    "sg:phone":"+1 718 231 9161",
    "sg:postcode":"10457",
    "sg:province":"NY",
    "sg:tags":[
        "lock",
        "locksmith"
    ],
    "wof:name":"24/7 Affordable Locksmith",
    "wof:placetype":"venue"
},
  "geometry": {"coordinates":[-73.888463,40.846066],"type":"Point"}
}