{
  "type": "Feature",
  "properties": {
    "iso:country":"US",
    "sg:address":"3331 S Salina St",
    "sg:city":"Syracuse",
    "sg:classifiers":[
        {
            "category":"Food & Beverages",
            "subcategory":"Groceries & Convenience Stores",
            "type":"Retail Goods"
        }
    ],
    "sg:phone":"+1 315 492 2842",
    "sg:postcode":"13205",
    "sg:province":"NY",
    "sg:tags":[
        "gas"
    ],
    "sg:website":"http://www.unionfacts.com",
    "wof:name":"Kwik - Fill",
    "wof:placetype":"venue"
},
  "geometry": {"coordinates":[-76.14116300000001,43.015804],"type":"Point"}
}