{
  "type": "Feature",
  "properties": {
    "iso:country":"US",
    "sg:address":"425 5th Ave",
    "sg:city":"New York",
    "sg:classifiers":[
        {
            "category":"Professional",
            "subcategory":"Lawyer & Legal Services",
            "type":"Services"
        }
    ],
    "sg:phone":"+1 212 239 6745",
    "sg:postcode":"10016",
    "sg:province":"NY",
    "sg:tags":[
        "attorney"
    ],
    "wof:name":"Jae Ung Choe Attorney",
    "wof:placetype":"venue"
},
  "geometry": {"coordinates":[-73.982252,40.751464],"type":"Point"}
}