{
  "type": "Feature",
  "properties": {
    "iso:country":"US",
    "sg:address":"685 Flower St",
    "sg:city":"Watertown",
    "sg:classifiers":[
        {
            "category":"Retail",
            "subcategory":"Repair Shop",
            "type":"Services"
        }
    ],
    "sg:phone":"+1 315 782 4068",
    "sg:postcode":"13601",
    "sg:province":"NY",
    "sg:tags":[
        "welding"
    ],
    "wof:name":"Bartlett's Welding Svc",
    "wof:placetype":"venue"
},
  "geometry": {"coordinates":[-75.88768399999999,43.983993],"type":"Point"}
}