{
  "type": "Feature",
  "properties": {
    "iso:country":"US",
    "sg:address":"725 Main St",
    "sg:city":"Buffalo",
    "sg:classifiers":[
        {
            "category":"Professional",
            "subcategory":"Business Services",
            "type":"Services"
        }
    ],
    "sg:phone":"+1 716 675 2821",
    "sg:postcode":"14203",
    "sg:province":"NY",
    "sg:tags":[
        "international",
        "consultant",
        "trade"
    ],
    "wof:name":"Buffalo Niagara International Trade Foundation",
    "wof:placetype":"venue"
},
  "geometry": {"coordinates":[-78.871802,42.893585],"type":"Point"}
}