{
  "type": "Feature",
  "properties": {
    "iso:country":"US",
    "sg:address":"801 Bartholdi St",
    "sg:city":"Bronx",
    "sg:classifiers":[
        {
            "category":"Social Services",
            "subcategory":"Child Care",
            "type":"Services"
        }
    ],
    "sg:phone":"+1 718 944 0958",
    "sg:postcode":"10467",
    "sg:province":"NY",
    "sg:tags":[
        "day"
    ],
    "wof:name":"Learning Tree School",
    "wof:placetype":"venue"
},
  "geometry": {"coordinates":[-73.861306,40.873673],"type":"Point"}
}