{
  "type": "Feature",
  "properties": {
    "iso:country":"US",
    "sg:address":"389 Middle Country Rd",
    "sg:city":"Selden",
    "sg:classifiers":[
        {
            "category":"Restaurant",
            "type":"Food & Drink"
        }
    ],
    "sg:phone":"+1 631 736 7670",
    "sg:postcode":"11784",
    "sg:province":"NY",
    "sg:tags":[
        "chinese"
    ],
    "wof:name":"Main City Chinese Kitchen",
    "wof:placetype":"venue"
},
  "geometry": {"coordinates":[-73.03420300000001,40.8666],"type":"Point"}
}