{
  "type": "Feature",
  "properties": {
    "addr:full":"161 Atlantic Ave Brooklyn NY 11201",
    "addr:housenumber":"161",
    "addr:postcode":"11201",
    "addr:street":"Atlantic Ave",
    "iso:country":"US",
    "sg:address":"161 Atlantic Ave",
    "sg:city":"Brooklyn",
    "sg:classifiers":[
        {
            "category":"Health Services",
            "subcategory":"Clinic",
            "type":"Services"
        }
    ],
    "sg:phone":"+1   ",
    "sg:postcode":"11201",
    "sg:province":"NY",
    "wof:name":"Atlantic Medical Arts",
    "wof:placetype":"venue"
},
  "geometry": {"coordinates":[-73.99557,40.69076],"type":"Point"}
}