{
  "type": "Feature",
  "properties": {
    "iso:country":"US",
    "sg:address":"98 Sand Dock Rd",
    "sg:city":"Poughkeepsie",
    "sg:classifiers":[
        {
            "category":"Utilities",
            "subcategory":"Refuse",
            "type":"Services"
        }
    ],
    "sg:phone":"+1 845 462 4650",
    "sg:postcode":"12601",
    "sg:province":"NY",
    "sg:tags":[
        "garbage",
        "generation",
        "collection",
        "electricity",
        "operation",
        "incinerator"
    ],
    "sg:website":"www.montenaydutchess.com",
    "wof:name":"Montenay Dutchess LLC",
    "wof:placetype":"venue"
},
  "geometry": {"coordinates":[-73.940854,41.647316],"type":"Point"}
}