{
  "type": "Feature",
  "properties": {
    "addr:full":"2350 Broadway New York NY 10024",
    "addr:housenumber":"2350",
    "addr:postcode":"10024",
    "addr:street":"Broadway",
    "iso:country":"US",
    "sg:address":"2350 Broadway",
    "sg:city":"New York",
    "sg:classifiers":[
        {
            "category":"Personal",
            "subcategory":"Nail Salon",
            "type":"Services"
        }
    ],
    "sg:phone":"+1 212 496 1133",
    "sg:postcode":"10024",
    "sg:province":"NY",
    "wof:name":"Picasso Nails",
    "wof:placetype":"venue"
},
  "geometry": {"coordinates":[-73.976601,40.7878],"type":"Point"}
}