{
  "type": "Feature",
  "properties": {
    "addr:full":"90 Freeman Ave Islip NY 11751",
    "addr:housenumber":"90",
    "addr:postcode":"11751",
    "addr:street":"Freeman Ave",
    "iso:country":"US",
    "sg:address":"90 Freeman Ave",
    "sg:city":"Islip",
    "sg:classifiers":[
        {
            "category":"Professional",
            "type":"Services"
        }
    ],
    "sg:phone":"+1   ",
    "sg:postcode":"11751",
    "sg:province":"NY",
    "wof:name":"Robert A Desimone Inc",
    "wof:placetype":"venue"
},
  "geometry": {"coordinates":[-73.21281999999999,40.745862],"type":"Point"}
}