{
  "type": "Feature",
  "properties": {
    "addr:full":"222 Broadway New York NY 10038",
    "addr:housenumber":"222",
    "addr:postcode":"10038",
    "addr:street":"Broadway",
    "iso:country":"US",
    "sg:address":"222 Broadway",
    "sg:city":"New York",
    "sg:classifiers":[
        {
            "category":"Restaurant",
            "type":"Food & Drink"
        },
        {
            "category":"Bakery",
            "type":"Food & Drink"
        }
    ],
    "sg:menulink":"http://www.allmenus.com/ny/new-york/108758-au-bon-pain/menu/",
    "sg:phone":"+1 212 962 8453",
    "sg:postcode":"10038",
    "sg:province":"NY",
    "sg:tags":[
        "american",
        "bakery",
        "pastry"
    ],
    "wof:name":"Au Bon Pain",
    "wof:placetype":"venue"
},
  "geometry": {"coordinates":[-74.008368,40.711679],"type":"Point"}
}