{
  "type": "Feature",
  "properties": {
    "iso:country":"US",
    "sg:address":"38 Barrows St",
    "sg:city":"Jamestown",
    "sg:classifiers":[
        {
            "category":"Building & Trades",
            "subcategory":"Construction",
            "type":"Services"
        }
    ],
    "sg:phone":"+1 716 484 0399",
    "sg:postcode":"14701",
    "sg:province":"NY",
    "sg:tags":[
        "contractor"
    ],
    "wof:name":"MNJ Contracting",
    "wof:placetype":"venue"
},
  "geometry": {"coordinates":[-79.226654,42.093954],"type":"Point"}
}