{
  "type": "Feature",
  "properties": {
    "addr:full":"46 Barclay Dr Sag Harbor NY 11963",
    "addr:housenumber":"46",
    "addr:postcode":"11963",
    "addr:street":"Barclay Dr",
    "iso:country":"US",
    "sg:address":"46 Barclay Dr",
    "sg:city":"Sag Harbor",
    "sg:classifiers":[
        {
            "category":"Building & Trades",
            "subcategory":"Landscaping Services",
            "type":"Services"
        }
    ],
    "sg:phone":"+1 631 725 9127",
    "sg:postcode":"11963",
    "sg:province":"NY",
    "sg:tags":[
        "tree"
    ],
    "wof:name":"Harbor Landscaping Tree Care",
    "wof:placetype":"venue"
},
  "geometry": {"coordinates":[-72.32526300000001,41.027715],"type":"Point"}
}