{
  "type": "Feature",
  "properties": {
    "iso:country":"US",
    "sg:address":"38 Kennedy Ter",
    "sg:city":"Middletown",
    "sg:classifiers":[
        {
            "category":"Social Services",
            "type":"Services"
        }
    ],
    "sg:phone":"+1 845 344 5415",
    "sg:postcode":"10940",
    "sg:province":"NY",
    "sg:tags":[
        "agency",
        "adoption"
    ],
    "wof:name":"Allan Dickstein",
    "wof:placetype":"venue"
},
  "geometry": {"coordinates":[-74.42155,41.463958],"type":"Point"}
}