{
  "type": "Feature",
  "properties": {
    "addr:full":"240 Porspect Park W Brooklyn NY 11205",
    "addr:housenumber":"240",
    "addr:postcode":"11205",
    "addr:street":"Porspect Park W",
    "iso:country":"US",
    "sg:address":"240 Porspect Park W",
    "sg:city":"Brooklyn",
    "sg:classifiers":[
        {
            "category":"Shopping",
            "subcategory":"Pets & Pet Supplies",
            "type":"Retail Goods"
        }
    ],
    "sg:phone":"+1 718 875 1661",
    "sg:postcode":"11205",
    "sg:province":"NY",
    "sg:tags":[
        "store"
    ],
    "sg:website":"www.abcpetsupply.com/",
    "wof:name":"ABC Pet Supply.com",
    "wof:placetype":"venue"
},
  "geometry": {"coordinates":[-73.981526,40.659457],"type":"Point"}
}