{
  "type": "Feature",
  "properties": {
    "addr:full":"8319 Brewerton Rd Cicero NY 13039",
    "addr:housenumber":"8319",
    "addr:postcode":"13039",
    "addr:street":"Brewerton Rd",
    "iso:country":"US",
    "sg:address":"8319 Brewerton Rd",
    "sg:city":"Cicero",
    "sg:classifiers":[
        {
            "category":"Restaurant",
            "type":"Food & Drink"
        }
    ],
    "sg:phone":"+1 315 698 1805",
    "sg:postcode":"13039",
    "sg:province":"NY",
    "wof:name":"Al & Bren's Cicero Diner",
    "wof:placetype":"venue"
},
  "geometry": {"coordinates":[-76.118663,43.173801],"type":"Point"}
}