{
  "type": "Feature",
  "properties": {
    "addr:full":"328 Doherty Ave Elmont NY 11003",
    "addr:housenumber":"328",
    "addr:postcode":"11003",
    "addr:street":"Doherty Ave",
    "iso:country":"US",
    "sg:address":"328 Doherty Ave",
    "sg:city":"Elmont",
    "sg:classifiers":[
        {
            "category":"Professional",
            "subcategory":"Accounting & Tax Preparation",
            "type":"Services"
        }
    ],
    "sg:phone":"+1   ",
    "sg:postcode":"11003",
    "sg:province":"NY",
    "wof:name":"Alliance Medical Billing Inc",
    "wof:placetype":"venue"
},
  "geometry": {"coordinates":[-73.696724,40.698666],"type":"Point"}
}