{
  "type": "Feature",
  "properties": {
    "addr:full":"129 Jarmain Rd Monroe NY 10950",
    "addr:housenumber":"129",
    "addr:postcode":"10950",
    "addr:street":"Jarmain Rd",
    "iso:country":"US",
    "sg:address":"129 Jarmain Rd",
    "sg:city":"Monroe",
    "sg:classifiers":[
        {
            "category":"Building & Trades",
            "subcategory":"Construction",
            "type":"Services"
        }
    ],
    "sg:phone":"+1 845 987 1900",
    "sg:postcode":"10950",
    "sg:province":"NY",
    "sg:tags":[
        "house"
    ],
    "wof:name":"Kilduff John Construction",
    "wof:placetype":"venue"
},
  "geometry": {"coordinates":[-74.273443,41.248241],"type":"Point"}
}