{
  "type": "Feature",
  "properties": {
    "addr:full":"206 Elwood Ave Hawthorne NY 10532",
    "addr:housenumber":"206",
    "addr:postcode":"10532",
    "addr:street":"Elwood Ave",
    "iso:country":"US",
    "sg:address":"206 Elwood Ave",
    "sg:city":"Hawthorne",
    "sg:classifiers":[
        {
            "category":"Building & Trades",
            "subcategory":"Cleaning & Sanitation",
            "type":"Services"
        }
    ],
    "sg:phone":"+1 914 747 8985",
    "sg:postcode":"10532",
    "sg:province":"NY",
    "wof:name":"Exceptional Cleaning Corp",
    "wof:placetype":"venue"
},
  "geometry": {"coordinates":[-73.79371399999999,41.100678],"type":"Point"}
}