{
  "type": "Feature",
  "properties": {
    "addr:full":"421 Lafayette St New York NY 10003",
    "addr:housenumber":"421",
    "addr:postcode":"10003",
    "addr:street":"Lafayette St",
    "iso:country":"US",
    "sg:address":"421 Lafayette St",
    "sg:city":"New York",
    "sg:classifiers":[
        {
            "category":"Building & Trades",
            "subcategory":"Locksmith",
            "type":"Services"
        }
    ],
    "sg:phone":"+1 212 721 1119",
    "sg:postcode":"10003",
    "sg:province":"NY",
    "sg:tags":[
        "key"
    ],
    "wof:name":"The General Locksmith",
    "wof:placetype":"venue"
},
  "geometry": {"coordinates":[-73.992203,40.729099],"type":"Point"}
}