{
  "type": "Feature",
  "properties": {
    "iso:country":"US",
    "sg:address":"7607 Oswego Rd",
    "sg:city":"Liverpool",
    "sg:classifiers":[
        {
            "category":"Professional",
            "subcategory":"Business Services",
            "type":"Services"
        }
    ],
    "sg:phone":"+1   ",
    "sg:postcode":"13090",
    "sg:province":"NY",
    "sg:tags":[
        "specialty",
        "mfg"
    ],
    "wof:name":"Charles Signs Inc",
    "wof:placetype":"venue"
},
  "geometry": {"coordinates":[-76.226361,43.137921],"type":"Point"}
}