{
  "type": "Feature",
  "properties": {
    "addr:full":"9225 Union Hall St Jamaica NY 11433",
    "addr:housenumber":"9225",
    "addr:postcode":"11433",
    "addr:street":"Union Hall St",
    "iso:country":"US",
    "sg:address":"9225 Union Hall St",
    "sg:city":"Jamaica",
    "sg:classifiers":[
        {
            "category":"Health Services",
            "subcategory":"Health Practitioner",
            "type":"Services"
        }
    ],
    "sg:phone":"+1 718 206 4020",
    "sg:postcode":"11433",
    "sg:province":"NY",
    "sg:tags":[
        "nutritionist",
        "dietitian"
    ],
    "wof:name":"New York Golden Nutrition Ctr",
    "wof:placetype":"venue"
},
  "geometry": {"coordinates":[-73.797786,40.703945],"type":"Point"}
}