{
  "type": "Feature",
  "properties": {
    "iso:country":"US",
    "sg:address":"1 Pine West Rd",
    "sg:city":"Albany",
    "sg:classifiers":[
        {
            "category":"Professional",
            "subcategory":"Management & Consulting",
            "type":"Services"
        }
    ],
    "sg:phone":"+1 518 464 3603",
    "sg:postcode":"12205",
    "sg:province":"NY",
    "sg:tags":[
        "fuel"
    ],
    "wof:name":"Avion Management",
    "wof:placetype":"venue"
},
  "geometry": {"coordinates":[-73.86757,42.7108],"type":"Point"}
}