{
  "type": "Feature",
  "properties": {
    "iso:country":"US",
    "sg:address":"37 James Ln",
    "sg:city":"Levittown",
    "sg:classifiers":[
        {
            "category":"Professional",
            "subcategory":"Business Services",
            "type":"Services"
        }
    ],
    "sg:phone":"+1   ",
    "sg:postcode":"11756",
    "sg:province":"NY",
    "wof:name":"Integra Solutions Inc",
    "wof:placetype":"venue"
},
  "geometry": {"coordinates":[-73.53346500000001,40.726613],"type":"Point"}
}