{
  "type": "Feature",
  "properties": {
    "iso:country":"US",
    "sg:address":"3045 E Henrietta Rd",
    "sg:city":"Henrietta",
    "sg:classifiers":[
        {
            "category":"Building & Trades",
            "subcategory":"Construction",
            "type":"Services"
        }
    ],
    "sg:phone":"+1 585 359 4885",
    "sg:postcode":"14467",
    "sg:province":"NY",
    "sg:tags":[
        "designer"
    ],
    "wof:name":"Elm Construction Inc",
    "wof:placetype":"venue"
},
  "geometry": {"coordinates":[-77.612233,43.060105],"type":"Point"}
}