{
  "type": "Feature",
  "properties": {
    "addr:full":"18 Deer Ln East Setauket NY 11733",
    "addr:housenumber":"18",
    "addr:postcode":"11733",
    "addr:street":"Deer Ln East",
    "iso:country":"US",
    "sg:address":"18 Deer Ln",
    "sg:city":"East Setauket",
    "sg:classifiers":[
        {
            "category":"Freight",
            "type":"Transportation"
        }
    ],
    "sg:phone":"+1   ",
    "sg:postcode":"11733",
    "sg:province":"NY",
    "wof:name":"Chris Dee Trnsp Long Island",
    "wof:placetype":"venue"
},
  "geometry": {"coordinates":[-73.07185699999999,40.911856],"type":"Point"}
}