{
  "type": "Feature",
  "properties": {
    "addr:full":"21 Dutch Mill Rd Ithaca NY 14850",
    "addr:housenumber":"21",
    "addr:postcode":"14850",
    "addr:street":"Dutch Mill Rd",
    "iso:country":"US",
    "sg:address":"21 Dutch Mill Rd",
    "sg:city":"Ithaca",
    "sg:classifiers":[
        {
            "category":"Shopping",
            "subcategory":"Computers & Home Electronics",
            "type":"Retail Goods"
        }
    ],
    "sg:phone":"+1 607 257 7279",
    "sg:postcode":"14850",
    "sg:province":"NY",
    "sg:tags":[
        "equipment",
        "dealer"
    ],
    "wof:name":"Global Phoenix Computer Tech",
    "wof:placetype":"venue"
},
  "geometry": {"coordinates":[-76.467202,42.50798],"type":"Point"}
}