{
  "type": "Feature",
  "properties": {
    "iso:country":"US",
    "sg:address":"706 Amsterdam Ave",
    "sg:city":"New York",
    "sg:classifiers":[
        {
            "category":"Cafe",
            "type":"Food & Drink"
        },
        {
            "category":"Restaurant",
            "type":"Food & Drink"
        }
    ],
    "sg:menulink":"http://www.allmenus.com/ny/new-york/7785-ayurveda-cafe/menu/",
    "sg:phone":"+1 212 932 2400",
    "sg:postcode":"10025",
    "sg:province":"NY",
    "sg:tags":[
        "indian",
        "asian"
    ],
    "wof:name":"Ayurveda Cafe",
    "wof:placetype":"venue"
},
  "geometry": {"coordinates":[-73.971442,40.793119],"type":"Point"}
}