{
  "type": "Feature",
  "properties": {
    "addr:full":"130 Marine St Farmingdale NY 11735",
    "addr:housenumber":"130",
    "addr:postcode":"11735",
    "addr:street":"Marine St",
    "iso:country":"US",
    "sg:address":"130 Marine St",
    "sg:city":"Farmingdale",
    "sg:classifiers":[
        {
            "category":"Building & Trades",
            "subcategory":"Construction",
            "type":"Services"
        }
    ],
    "sg:phone":"+1 516 799 2900",
    "sg:postcode":"11735",
    "sg:province":"NY",
    "sg:tags":[
        "contractor",
        "product",
        "wood",
        "carpentry",
        "mfg"
    ],
    "wof:name":"Red Star Cabinet Co",
    "wof:placetype":"venue"
},
  "geometry": {"coordinates":[-73.41870900000001,40.714656],"type":"Point"}
}