{
  "type": "Feature",
  "properties": {
    "addr:full":"2035 E 16th St Brooklyn NY 11229",
    "addr:housenumber":"2035",
    "addr:postcode":"11229",
    "addr:street":"E 16Th St",
    "iso:country":"US",
    "sg:address":"2035 E 16th St",
    "sg:city":"Brooklyn",
    "sg:classifiers":[
        {
            "category":"Professional",
            "subcategory":"Computer Services",
            "type":"Services"
        }
    ],
    "sg:phone":"+1   ",
    "sg:postcode":"11229",
    "sg:province":"NY",
    "sg:tags":[
        "programing",
        "custom"
    ],
    "wof:name":"Smart Step Software Dev",
    "wof:placetype":"venue"
},
  "geometry": {"coordinates":[-73.95551399999999,40.59973],"type":"Point"}
}