{
  "type": "Feature",
  "properties": {
    "addr:full":"89 East 161 Street Bronx NY 10451",
    "addr:housenumber":"89",
    "addr:postcode":"10451",
    "addr:street":"East 161 Street",
    "iso:country":"US",
    "sg:address":"89 East 161 Street",
    "sg:city":"Bronx",
    "sg:classifiers":[
        {
            "category":"Juice Bar",
            "subcategory":"None",
            "type":"Food & Drink"
        },
        {
            "category":"Food & Beverages",
            "subcategory":"Specialty",
            "type":"Retail Goods"
        }
    ],
    "sg:phone":"+1 718 618 7228",
    "sg:postcode":"10451",
    "sg:province":"NY",
    "sg:tags":[
        "smoothy",
        "live/raw"
    ],
    "sg:website":"www.juicefactorycafe.com",
    "wof:name":"Juice Factory",
    "wof:placetype":"venue"
},
  "geometry": {"coordinates":[-73.924752,40.827476],"type":"Point"}
}