{
  "type": "Feature",
  "properties": {
    "iso:country":"US",
    "sg:address":"150 Stahl Rd",
    "sg:city":"Getzville",
    "sg:classifiers":[
        {
            "category":"Education",
            "subcategory":"School",
            "type":"Public Place"
        }
    ],
    "sg:phone":"+1 716 629 3400",
    "sg:postcode":"14068",
    "sg:province":"NY",
    "sg:website":"www.summiteducational.org",
    "wof:name":"Summit Educational Resources",
    "wof:placetype":"venue"
},
  "geometry": {"coordinates":[-78.76816599999999,43.013977],"type":"Point"}
}