{
  "type": "Feature",
  "properties": {
    "addr:full":"44 9th Ave New York NY 10011",
    "addr:housenumber":"44",
    "addr:postcode":"10011",
    "addr:street":"9Th Ave",
    "iso:country":"US",
    "sg:address":"44 9th Ave",
    "sg:city":"New York",
    "sg:classifiers":[
        {
            "category":"Restaurant",
            "type":"Food & Drink"
        }
    ],
    "sg:phone":"+1 212 929 2807",
    "sg:postcode":"10011",
    "sg:province":"NY",
    "wof:name":"Nicks City Kitchen",
    "wof:placetype":"venue"
},
  "geometry": {"coordinates":[-74.004898,40.741299],"type":"Point"}
}