{
  "type": "Feature",
  "properties": {
    "addr:full":"304 Park Ave S Manhattan NY 10012",
    "addr:housenumber":"304",
    "addr:postcode":"10012",
    "addr:street":"Park Ave S",
    "iso:country":"US",
    "sg:address":"304 Park Ave S",
    "sg:city":"Manhattan",
    "sg:classifiers":[
        {
            "category":"Restaurant",
            "type":"Food & Drink"
        }
    ],
    "sg:phone":"+1 212 475 9025",
    "sg:postcode":"10012",
    "sg:province":"NY",
    "sg:tags":[
        "tea",
        "coffee",
        "eating"
    ],
    "sg:website":"www.starbucks.com",
    "wof:name":"Starbucks",
    "wof:placetype":"venue"
},
  "geometry": {"coordinates":[-73.987103,40.740322],"type":"Point"}
}