{
  "type": "Feature",
  "properties": {
    "addr:full":"40 Elizabeth St New York NY 10013",
    "addr:housenumber":"40",
    "addr:postcode":"10013",
    "addr:street":"Elizabeth St",
    "iso:country":"US",
    "sg:address":"40 Elizabeth St",
    "sg:city":"New York",
    "sg:classifiers":[
        {
            "category":"Health Services",
            "subcategory":"Doctor",
            "type":"Services"
        }
    ],
    "sg:phone":"+1 212 219 0127",
    "sg:postcode":"10013",
    "sg:province":"NY",
    "wof:name":"Ny Medical",
    "wof:placetype":"venue"
},
  "geometry": {"coordinates":[-73.996696,40.716702],"type":"Point"}
}