{
  "type": "Feature",
  "properties": {
    "addr:full":"1835 Merrick Rd Merrick NY 11566",
    "addr:housenumber":"1835",
    "addr:postcode":"11566",
    "addr:street":"Merrick Rd",
    "iso:country":"US",
    "sg:address":"1835 Merrick Rd",
    "sg:city":"Merrick",
    "sg:classifiers":[
        {
            "category":"Personal",
            "subcategory":"Beauty Salon",
            "type":"Services"
        }
    ],
    "sg:phone":"+1 516 377 0118",
    "sg:postcode":"11566",
    "sg:province":"NY",
    "wof:name":"Sorellas Beauty Salon",
    "wof:placetype":"venue"
},
  "geometry": {"coordinates":[-73.55367699999999,40.654207],"type":"Point"}
}