{
  "type": "Feature",
  "properties": {
    "addr:full":"329 Canal Pl Bronx NY 10451",
    "addr:housenumber":"329",
    "addr:postcode":"10451",
    "addr:street":"Canal Pl",
    "iso:country":"US",
    "sg:address":"329 Canal Pl",
    "sg:city":"Bronx",
    "sg:classifiers":[
        {
            "category":"Utilities",
            "subcategory":"Refuse",
            "type":"Services"
        }
    ],
    "sg:phone":"+1 718 292 4431",
    "sg:postcode":"10451",
    "sg:province":"NY",
    "sg:tags":[
        "garbage",
        "collection"
    ],
    "wof:name":"Iesi Of New York",
    "wof:placetype":"venue"
},
  "geometry": {"coordinates":[-73.92676,40.814405],"type":"Point"}
}