{
  "type": "Feature",
  "properties": {
    "addr:full":"1029 Route 112 Port Jefferson Sta NY 11776",
    "addr:housenumber":"1029",
    "addr:postcode":"11776",
    "addr:street":"Route 112",
    "iso:country":"US",
    "sg:address":"1029 Route 112",
    "sg:city":"Port Jefferson Sta",
    "sg:classifiers":[
        {
            "category":"Arts & Performance",
            "subcategory":"Arts Center",
            "type":"Entertainment"
        },
        {
            "category":"Sports & Exercise",
            "subcategory":"Gym",
            "type":"Entertainment"
        }
    ],
    "sg:phone":"+1 631 331 5766",
    "sg:postcode":"11776",
    "sg:province":"NY",
    "sg:tags":[
        "trainer",
        "performing"
    ],
    "sg:website":"www.backstagestudioofdance.com",
    "wof:name":"Backstage Studio of Dance Inc",
    "wof:placetype":"venue"
},
  "geometry": {"coordinates":[-73.03679700000001,40.917599],"type":"Point"}
}