{
  "type": "Feature",
  "properties": {
    "iso:country":"US",
    "sg:address":"515 North Ave",
    "sg:city":"New Rochelle",
    "sg:classifiers":[
        {
            "category":"Building & Trades",
            "subcategory":"Plumbing",
            "type":"Services"
        }
    ],
    "sg:phone":"+1 914 654 2037",
    "sg:postcode":"10801",
    "sg:province":"NY",
    "sg:tags":[
        "contractor"
    ],
    "wof:name":"Bureau of Building",
    "wof:placetype":"venue"
},
  "geometry": {"coordinates":[-73.786767,40.919655],"type":"Point"}
}