{
  "type": "Feature",
  "properties": {
    "iso:country":"US",
    "sg:address":"4765 Cottage Rd",
    "sg:city":"Gasport",
    "sg:classifiers":[
        {
            "category":"Shopping",
            "subcategory":"Computers & Home Electronics",
            "type":"Retail Goods"
        }
    ],
    "sg:phone":"+1   ",
    "sg:postcode":"14067",
    "sg:province":"NY",
    "sg:tags":[
        "store",
        "software"
    ],
    "wof:name":"Trex Computer Products",
    "wof:placetype":"venue"
},
  "geometry": {"coordinates":[-78.612982,43.183847],"type":"Point"}
}