{
  "type": "Feature",
  "properties": {
    "addr:full":"5687 Main St Williamsville NY 14221",
    "addr:housenumber":"5687",
    "addr:postcode":"14221",
    "addr:street":"Main St",
    "iso:country":"US",
    "sg:address":"5687 Main St",
    "sg:city":"Williamsville",
    "sg:classifiers":[
        {
            "category":"Insurance",
            "subcategory":"Insurance Agent",
            "type":"Services"
        }
    ],
    "sg:phone":"+1 716 634 2876",
    "sg:postcode":"14221",
    "sg:province":"NY",
    "sg:tags":[
        "consultant"
    ],
    "wof:name":"Self-Funding Inc",
    "wof:placetype":"venue"
},
  "geometry": {"coordinates":[-78.740404,42.963469],"type":"Point"}
}