{
  "type": "Feature",
  "properties": {
    "iso:country":"US",
    "sg:address":"11 Nott Rd",
    "sg:city":"Rexford",
    "sg:classifiers":[
        {
            "category":"Arts & Performance",
            "subcategory":"Music",
            "type":"Entertainment"
        }
    ],
    "sg:phone":"+1 518 399 7451",
    "sg:postcode":"12148",
    "sg:province":"NY",
    "sg:tags":[
        "dj"
    ],
    "sg:website":"www.imadj.com",
    "wof:name":"Cap Capello",
    "wof:placetype":"venue"
},
  "geometry": {"coordinates":[-73.87960099999999,42.851501],"type":"Point"}
}