{
  "type": "Feature",
  "properties": {
    "addr:full":"1 Mcdonald Ln Rensselaer NY 12144",
    "addr:housenumber":"1",
    "addr:postcode":"12144",
    "addr:street":"Mcdonald Ln",
    "iso:country":"US",
    "sg:address":"1 Mcdonald Ln",
    "sg:city":"Rensselaer",
    "sg:classifiers":[
        {
            "category":"Restaurant",
            "type":"Food & Drink"
        }
    ],
    "sg:phone":"+1 518 477 4038",
    "sg:postcode":"12144",
    "sg:province":"NY",
    "sg:tags":[
        "grill",
        "bar"
    ],
    "wof:name":"Coach's Gridiron Grill",
    "wof:placetype":"venue"
},
  "geometry": {"coordinates":[-73.717079,42.620781],"type":"Point"}
}