{
  "type": "Feature",
  "properties": {
    "addr:full":"843 Union Ave New Windsor NY 12553",
    "addr:housenumber":"843",
    "addr:postcode":"12553",
    "addr:street":"Union Ave",
    "iso:country":"US",
    "sg:address":"843 Union Ave",
    "sg:city":"New Windsor",
    "sg:classifiers":[
        {
            "category":"Government",
            "subcategory":"Office",
            "type":"Public Place"
        }
    ],
    "sg:phone":"+1 845 567 3262",
    "sg:postcode":"12553",
    "sg:province":"NY",
    "sg:tags":[
        "state",
        "resource"
    ],
    "wof:name":"Children & Family Svc Office",
    "wof:placetype":"venue"
},
  "geometry": {"coordinates":[-74.075839,41.492541],"type":"Point"}
}