{
  "type": "Feature",
  "properties": {
    "addr:full":"822 Samsonville Rd Kerhonkson NY 12446",
    "addr:housenumber":"822",
    "addr:postcode":"12446",
    "addr:street":"Samsonville Rd",
    "iso:country":"US",
    "sg:address":"822 Samsonville Rd",
    "sg:city":"Kerhonkson",
    "sg:classifiers":[
        {
            "category":"Professional",
            "subcategory":"Printing & Photocopies",
            "type":"Services"
        }
    ],
    "sg:phone":"+1 845 750 6042",
    "sg:postcode":"12446",
    "sg:province":"NY",
    "sg:tags":[
        "lithographer"
    ],
    "wof:name":"Faithful Design & Print",
    "wof:placetype":"venue"
},
  "geometry": {"coordinates":[-74.30098700000001,41.85009],"type":"Point"}
}