{
  "type": "Feature",
  "properties": {
    "addr:full":"8441 Button Rd Cicero NY 13039",
    "addr:housenumber":"8441",
    "addr:postcode":"13039",
    "addr:street":"Button Rd",
    "iso:country":"US",
    "sg:address":"8441 Button Rd",
    "sg:city":"Cicero",
    "sg:classifiers":[
        {
            "category":"Building & Trades",
            "subcategory":"Construction",
            "type":"Services"
        }
    ],
    "sg:phone":"+1 315 569 1044",
    "sg:postcode":"13039",
    "sg:province":"NY",
    "sg:tags":[
        "home",
        "improvement"
    ],
    "wof:name":"EHS Home Improvements",
    "wof:placetype":"venue"
},
  "geometry": {"coordinates":[-76.087461,43.180736],"type":"Point"}
}