{
  "type": "Feature",
  "properties": {
    "addr:full":"1415 Richmond Avenue Staten Island NY 10314",
    "addr:housenumber":"1415",
    "addr:postcode":"10314",
    "addr:street":"Richmond Avenue",
    "iso:country":"US",
    "sg:address":"1415 Richmond Avenue",
    "sg:city":"Staten Island",
    "sg:classifiers":[
        {
            "category":"Travel",
            "subcategory":"Hotels & Motels",
            "type":"Entertainment"
        },
        {
            "category":"Restaurant",
            "type":"Food & Drink"
        }
    ],
    "sg:phone":"+1 718 698 5000",
    "sg:postcode":"10314",
    "sg:province":"NY",
    "wof:name":"Stanley's Restaurant At the Staten Island Hotel",
    "wof:placetype":"venue"
},
  "geometry": {"coordinates":[-74.157991,40.613541],"type":"Point"}
}