{
  "type": "Feature",
  "properties": {
    "addr:full":"3336 190th St Flushing NY 11358",
    "addr:housenumber":"3336",
    "addr:postcode":"11358",
    "addr:street":"190Th St",
    "iso:country":"US",
    "sg:address":"3336 190th St",
    "sg:city":"Flushing",
    "sg:classifiers":[
        {
            "category":"Wholesale",
            "subcategory":"Plants",
            "type":"Manufacturing & Wholesale Goods"
        },
        {
            "category":"Shopping",
            "subcategory":"Crafts & Fabrics",
            "type":"Retail Goods"
        }
    ],
    "sg:phone":"+1 718 762 5196",
    "sg:postcode":"11358",
    "sg:province":"NY",
    "sg:tags":[
        "florists'",
        "supply",
        "florists-wholesale",
        "florist",
        "supplies-wholesale",
        "manufacturer"
    ],
    "wof:name":"Vasilias Whol Florist",
    "wof:placetype":"venue"
},
  "geometry": {"coordinates":[-73.791815,40.766612],"type":"Point"}
}