{
  "type": "Feature",
  "properties": {
    "addr:full":"767 3 Ave New York NY 10017",
    "addr:housenumber":"767",
    "addr:postcode":"10017",
    "addr:street":"3 Ave",
    "iso:country":"US",
    "sg:address":"767 3 Ave",
    "sg:city":"New York",
    "sg:classifiers":[
        {
            "category":"Professional",
            "subcategory":"Lawyer & Legal Services",
            "type":"Services"
        }
    ],
    "sg:phone":"+1 212 588 1818",
    "sg:postcode":"10017",
    "sg:province":"NY",
    "wof:name":"Chazen & Fox Law Offices",
    "wof:placetype":"venue"
},
  "geometry": {"coordinates":[-73.974935,40.7501],"type":"Point"}
}