{
  "type": "Feature",
  "properties": {
    "addr:full":"157 E 55th St New York NY 10022",
    "addr:housenumber":"157",
    "addr:postcode":"10022",
    "addr:street":"E 55Th St",
    "iso:country":"US",
    "sg:address":"157 E 55th St",
    "sg:city":"New York",
    "sg:classifiers":[
        {
            "category":"Restaurant",
            "type":"Food & Drink"
        }
    ],
    "sg:phone":"+1 212 751 4600",
    "sg:postcode":"10022",
    "sg:province":"NY",
    "sg:tags":[
        "indian"
    ],
    "sg:website":"darbargrill.com/",
    "wof:name":"Darbar Grill",
    "wof:placetype":"venue"
},
  "geometry": {"coordinates":[-73.968813,40.759351],"type":"Point"}
}