{
  "type": "Feature",
  "properties": {
    "iso:country":"US",
    "sg:address":"130 Main St",
    "sg:city":"Islip",
    "sg:classifiers":[
        {
            "category":"Home & Garden",
            "subcategory":"Building Materials",
            "type":"Retail Goods"
        }
    ],
    "sg:phone":"+1 631 277 9327",
    "sg:postcode":"11751",
    "sg:province":"NY",
    "sg:tags":[
        "lumber"
    ],
    "sg:website":"www.commerciallumber.com",
    "wof:name":"Commercial Lumber & Bldg Supl",
    "wof:placetype":"venue"
},
  "geometry": {"coordinates":[-73.22203,40.727934],"type":"Point"}
}