{
  "type": "Feature",
  "properties": {
    "iso:country":"US",
    "sg:address":"15 Cornell Rd Ste 2",
    "sg:city":"Latham",
    "sg:classifiers":[
        {
            "category":"Banks & Credit Unions",
            "subcategory":"Investment Brokerage",
            "type":"Services"
        },
        {
            "category":"Insurance",
            "subcategory":"Hazard Insurance",
            "type":"Services"
        }
    ],
    "sg:phone":"+1 518 220 7200",
    "sg:postcode":"12110",
    "sg:province":"NY",
    "sg:tags":[
        "agent",
        "resume"
    ],
    "wof:name":"Aig",
    "wof:placetype":"venue"
},
  "geometry": {"coordinates":[-73.82197600000001,42.75856],"type":"Point"}
}