{
  "type": "Feature",
  "properties": {
    "iso:country":"US",
    "sg:address":"42 High St",
    "sg:city":"Huntington",
    "sg:classifiers":[
        {
            "category":"Professional",
            "subcategory":"Accounting & Tax Preparation",
            "type":"Services"
        }
    ],
    "sg:phone":"+1 631 425 9747",
    "sg:postcode":"11743",
    "sg:province":"NY",
    "sg:tags":[
        "accountant"
    ],
    "wof:name":"Leone Melchior",
    "wof:placetype":"venue"
},
  "geometry": {"coordinates":[-73.427976,40.867259],"type":"Point"}
}