{
  "type": "Feature",
  "properties": {
    "addr:full":"790 Exchange St Rochester NY 14608",
    "addr:housenumber":"790",
    "addr:postcode":"14608",
    "addr:street":"Exchange St",
    "iso:country":"US",
    "sg:address":"790 Exchange St",
    "sg:city":"Rochester",
    "sg:classifiers":[
        {
            "category":"Organizations",
            "subcategory":"Religious Organization",
            "type":"Services"
        }
    ],
    "sg:phone":"+1 585 436 4983",
    "sg:postcode":"14608",
    "sg:province":"NY",
    "sg:tags":[
        "clergy"
    ],
    "wof:name":"F Ethridge Reeves",
    "wof:placetype":"venue"
},
  "geometry": {"coordinates":[-77.616579,43.142591],"type":"Point"}
}