{
  "type": "Feature",
  "properties": {
    "addr:full":"138 E 65 St New York NY 10065",
    "addr:housenumber":"138;65",
    "addr:postcode":"10065",
    "addr:street":"E;St",
    "iso:country":"US",
    "sg:address":"138 E 65 St",
    "sg:city":"New York",
    "sg:classifiers":[
        {
            "category":"Banks & Credit Unions",
            "subcategory":"Investment Brokerage",
            "type":"Services"
        }
    ],
    "sg:phone":"+1 212 879 9143",
    "sg:postcode":"10065",
    "sg:province":"NY",
    "sg:tags":[
        "advisory",
        "financial"
    ],
    "wof:name":"Bransford Investment Partners",
    "wof:placetype":"venue"
},
  "geometry": {"coordinates":[-73.963843,40.765308],"type":"Point"}
}