{
  "type": "Feature",
  "properties": {
    "addr:full":"2186 Atlantic Ave Brooklyn NY 11233",
    "addr:housenumber":"2186",
    "addr:postcode":"11233",
    "addr:street":"Atlantic Ave",
    "iso:country":"US",
    "sg:address":"2186 Atlantic Ave",
    "sg:city":"Brooklyn",
    "sg:classifiers":[
        {
            "category":"Restaurant",
            "type":"Food & Drink"
        }
    ],
    "sg:phone":"+1 718 566 1585",
    "sg:postcode":"11233",
    "sg:province":"NY",
    "wof:name":"New Peking Chinese Restaurant",
    "wof:placetype":"venue"
},
  "geometry": {"coordinates":[-73.914314,40.676469],"type":"Point"}
}