{
  "type": "Feature",
  "properties": {
    "addr:full":"555 E Fordham Rd Bronx NY 10458",
    "addr:housenumber":"555",
    "addr:postcode":"10458",
    "addr:street":"E Fordham Rd",
    "iso:country":"US",
    "sg:address":"555 E Fordham Rd",
    "sg:city":"Bronx",
    "sg:classifiers":[
        {
            "category":"Autos & Motor Vehicles",
            "subcategory":"Auto Supplies",
            "type":"Retail Goods"
        }
    ],
    "sg:phone":"+1 718 584 0812",
    "sg:postcode":"10458",
    "sg:province":"NY",
    "sg:tags":[
        "tire"
    ],
    "wof:name":"H Jaffess Tire Co Inc",
    "wof:placetype":"venue"
},
  "geometry": {"coordinates":[-73.887457,40.859625],"type":"Point"}
}