{
  "type": "Feature",
  "properties": {
    "iso:country":"US",
    "sg:address":"67 Horizon Dr",
    "sg:city":"Rochester",
    "sg:classifiers":[
        {
            "category":"Autos & Motor Vehicles",
            "subcategory":"Automobile Sales",
            "type":"Retail Goods"
        }
    ],
    "sg:phone":"+1   ",
    "sg:postcode":"14625",
    "sg:province":"NY",
    "sg:tags":[
        "used"
    ],
    "wof:name":"Carfinder",
    "wof:placetype":"venue"
},
  "geometry": {"coordinates":[-77.49285399999999,43.159282],"type":"Point"}
}