{
  "type": "Feature",
  "properties": {
    "addr:full":"450 7 Ave New York NY 10123",
    "addr:housenumber":"450",
    "addr:postcode":"10123",
    "addr:street":"7 Ave",
    "iso:country":"US",
    "sg:address":"450 7 Ave",
    "sg:city":"New York",
    "sg:classifiers":[
        {
            "category":"Professional",
            "type":"Services"
        }
    ],
    "sg:phone":"+1 212 897 3474",
    "sg:postcode":"10123",
    "sg:province":"NY",
    "sg:tags":[
        "establishment"
    ],
    "wof:name":"Arctic Prime Intl",
    "wof:placetype":"venue"
},
  "geometry": {"coordinates":[-73.990134,40.751659],"type":"Point"}
}