{
  "type": "Feature",
  "properties": {
    "addr:full":"31 Centre Dr Central Valley NY 10917",
    "addr:housenumber":"31",
    "addr:postcode":"10917",
    "addr:street":"Centre Dr",
    "iso:country":"US",
    "sg:address":"31 Centre Dr",
    "sg:city":"Central Valley",
    "sg:classifiers":[
        {
            "category":"Shopping",
            "subcategory":"Stationery & Office Supplies",
            "type":"Retail Goods"
        }
    ],
    "sg:phone":"+1 845 783 5951",
    "sg:postcode":"10917",
    "sg:province":"NY",
    "sg:tags":[
        "equipment"
    ],
    "wof:name":"Staples",
    "wof:placetype":"venue"
},
  "geometry": {"coordinates":[-74.132107,41.313678],"type":"Point"}
}