{
  "type": "Feature",
  "properties": {
    "iso:country":"US",
    "sg:address":"288 New York Ave",
    "sg:city":"Huntington",
    "sg:classifiers":[
        {
            "category":"Retail",
            "subcategory":"Repair Shop",
            "type":"Services"
        }
    ],
    "sg:phone":"+1 631 549 9336",
    "sg:postcode":"11743",
    "sg:province":"NY",
    "sg:tags":[
        "electronics",
        "electrical"
    ],
    "sg:website":"www.videson.com",
    "wof:name":"Videson Electronics Inc",
    "wof:placetype":"venue"
},
  "geometry": {"coordinates":[-73.425697,40.8731],"type":"Point"}
}