{
  "type": "Feature",
  "properties": {
    "iso:country":"US",
    "sg:address":"3801 Mills Rd",
    "sg:city":"Avoca",
    "sg:classifiers":[
        {
            "category":"Manufacturing",
            "subcategory":"Buildings",
            "type":"Manufacturing & Wholesale Goods"
        },
        {
            "category":"Wholesale",
            "subcategory":"Construction Materials",
            "type":"Manufacturing & Wholesale Goods"
        },
        {
            "category":"Building & Trades",
            "subcategory":"Construction",
            "type":"Services"
        }
    ],
    "sg:phone":"+1 607 566 3422",
    "sg:postcode":"14809",
    "sg:province":"NY",
    "sg:tags":[
        "supply",
        "builder",
        "contractor",
        "equipment",
        "home",
        "masonry"
    ],
    "wof:name":"Blades Construction Products Corp.",
    "wof:placetype":"venue"
},
  "geometry": {"coordinates":[-77.41546099999999,42.436585],"type":"Point"}
}