{
  "type": "Feature",
  "properties": {
    "addr:full":"485 Park Ave New York NY 10022",
    "addr:housenumber":"485",
    "addr:postcode":"10022",
    "addr:street":"Park Ave",
    "iso:country":"US",
    "sg:address":"485 Park Ave",
    "sg:city":"New York",
    "sg:classifiers":[
        {
            "category":"Food & Beverages",
            "subcategory":"Candy",
            "type":"Retail Goods"
        },
        {
            "category":"Food & Beverages",
            "subcategory":"Chocolate",
            "type":"Retail Goods"
        }
    ],
    "sg:phone":"+1 212 755 5150",
    "sg:postcode":"10022",
    "sg:province":"NY",
    "sg:tags":[
        "shop",
        "dessert",
        "chocolatiers"
    ],
    "sg:website":"www.borneconfections.com/",
    "wof:name":"Borne Confections",
    "wof:placetype":"venue"
},
  "geometry": {"coordinates":[-73.969936,40.762224],"type":"Point"}
}