{
  "type": "Feature",
  "properties": {
    "addr:full":"132 Ocean Ave Massapequa NY 11758",
    "addr:housenumber":"132",
    "addr:postcode":"11758",
    "addr:street":"Ocean Ave",
    "iso:country":"US",
    "sg:address":"132 Ocean Ave",
    "sg:city":"Massapequa",
    "sg:classifiers":[
        {
            "category":"Building & Trades",
            "subcategory":"Construction",
            "type":"Services"
        }
    ],
    "sg:phone":"+1 516 798 6183",
    "sg:postcode":"11758",
    "sg:province":"NY",
    "sg:tags":[
        "general",
        "contractor"
    ],
    "wof:name":"Corin Contracting Corp",
    "wof:placetype":"venue"
},
  "geometry": {"coordinates":[-73.472448,40.661948],"type":"Point"}
}