{
  "type": "Feature",
  "properties": {
    "iso:country":"US",
    "sg:address":"446 Coney Island Ave",
    "sg:city":"Brooklyn",
    "sg:classifiers":[
        {
            "category":"Building & Trades",
            "subcategory":"Plumbing",
            "type":"Services"
        }
    ],
    "sg:phone":"+1 718 287 5927",
    "sg:postcode":"11218",
    "sg:province":"NY",
    "sg:tags":[
        "conditioning",
        "air",
        "system",
        "contractor"
    ],
    "wof:name":"Carrier Northeast",
    "wof:placetype":"venue"
},
  "geometry": {"coordinates":[-73.97104899999999,40.646958],"type":"Point"}
}