{
  "type": "Feature",
  "properties": {
    "iso:country":"US",
    "sg:address":"1 High Point Dr",
    "sg:city":"Spencerport",
    "sg:classifiers":[
        {
            "category":"Social Services",
            "type":"Services"
        }
    ],
    "sg:phone":"+1   ",
    "sg:postcode":"14559",
    "sg:province":"NY",
    "sg:tags":[
        "medical"
    ],
    "wof:name":"Jeremiah Donigian Ded",
    "wof:placetype":"venue"
},
  "geometry": {"coordinates":[-77.850746,43.22191],"type":"Point"}
}