{
  "type": "Feature",
  "properties": {
    "iso:country":"US",
    "sg:address":"37 7th Ave",
    "sg:city":"New York",
    "sg:classifiers":[
        {
            "category":"Food & Beverages",
            "subcategory":"Bakery",
            "type":"Retail Goods"
        }
    ],
    "sg:phone":"+1 212 691 2929",
    "sg:postcode":"10011",
    "sg:province":"NY",
    "sg:tags":[
        "sandwich"
    ],
    "wof:name":"Subway Sandwiches",
    "wof:placetype":"venue"
},
  "geometry": {"coordinates":[-74.93728,40.737706],"type":"Point"}
}