{
  "type": "Feature",
  "properties": {
    "addr:full":"6318 Clinton Street Rd Bergen NY 14416",
    "addr:housenumber":"6318",
    "addr:postcode":"14416",
    "addr:street":"Clinton Street Rd",
    "iso:country":"US",
    "sg:address":"6318 Clinton Street Rd",
    "sg:city":"Bergen",
    "sg:classifiers":[
        {
            "category":"Food & Beverages",
            "subcategory":"Groceries & Convenience Stores",
            "type":"Retail Goods"
        }
    ],
    "sg:phone":"+1   ",
    "sg:postcode":"14416",
    "sg:province":"NY",
    "wof:name":"Douglas Farm Market",
    "wof:placetype":"venue"
},
  "geometry": {"coordinates":[-77.941385,43.081662],"type":"Point"}
}