{
  "type": "Feature",
  "properties": {
    "iso:country":"US",
    "sg:address":"759 E 132nd St",
    "sg:city":"Bronx",
    "sg:classifiers":[
        {
            "category":"Arts & Performance",
            "subcategory":"Theater",
            "type":"Entertainment"
        }
    ],
    "sg:phone":"+1 718 401 3329",
    "sg:postcode":"10454",
    "sg:province":"NY",
    "sg:tags":[
        "equipment",
        "theatrical",
        "supply"
    ],
    "wof:name":"Carbon Stage Machinery",
    "wof:placetype":"venue"
},
  "geometry": {"coordinates":[-73.916021,40.80146],"type":"Point"}
}