{
  "type": "Feature",
  "properties": {
    "addr:full":"109 S 4th Ave Mt Vernon NY 10550",
    "addr:housenumber":"109",
    "addr:postcode":"10550",
    "addr:street":"S 4Th Ave",
    "iso:country":"US",
    "sg:address":"109 S 4th Ave",
    "sg:city":"Mt Vernon",
    "sg:classifiers":[
        {
            "category":"Personal",
            "subcategory":"Beauty Salon",
            "type":"Services"
        }
    ],
    "sg:phone":"+1 914 663 8341",
    "sg:postcode":"10550",
    "sg:province":"NY",
    "wof:name":"Corneli's Beauty Salon",
    "wof:placetype":"venue"
},
  "geometry": {"coordinates":[-73.83525400000001,40.907028],"type":"Point"}
}