{
  "type": "Feature",
  "properties": {
    "iso:country":"US",
    "sg:address":"7 Grand Blvd",
    "sg:city":"Brentwood",
    "sg:classifiers":[
        {
            "category":"Freight",
            "type":"Transportation"
        }
    ],
    "sg:phone":"+1 631 952 1557",
    "sg:postcode":"11717",
    "sg:province":"NY",
    "sg:tags":[
        "delivery"
    ],
    "wof:name":"Wiltrim Delivery",
    "wof:placetype":"venue"
},
  "geometry": {"coordinates":[-73.226018,40.783941],"type":"Point"}
}