{
  "type": "Feature",
  "properties": {
    "iso:country":"US",
    "sg:address":"742 Veterans Memorial Hwy",
    "sg:city":"Hauppauge",
    "sg:classifiers":[
        {
            "category":"Professional",
            "subcategory":"Lawyer & Legal Services",
            "type":"Services"
        }
    ],
    "sg:phone":"+1   ",
    "sg:postcode":"11788",
    "sg:province":"NY",
    "wof:name":"Ernest E Ranalli Esq",
    "wof:placetype":"venue"
},
  "geometry": {"coordinates":[-73.23152399999999,40.824652],"type":"Point"}
}