{
  "type": "Feature",
  "properties": {
    "addr:full":"2951 Grand Concourse Bronx NY 10468",
    "addr:housenumber":"2951",
    "addr:postcode":"10468",
    "addr:street":"Grand Concourse",
    "iso:country":"US",
    "sg:address":"2951 Grand Concourse",
    "sg:city":"Bronx",
    "sg:classifiers":[
        {
            "category":"Health Services",
            "subcategory":"Doctor",
            "type":"Services"
        }
    ],
    "sg:phone":"+1 718 561 0773",
    "sg:postcode":"10468",
    "sg:province":"NY",
    "sg:tags":[
        "dentist"
    ],
    "wof:name":"Felix J Rodriguez Dental Ofc",
    "wof:placetype":"venue"
},
  "geometry": {"coordinates":[-73.887377,40.872723],"type":"Point"}
}