{
  "type": "Feature",
  "properties": {
    "addr:full":"4336 Rushford Dr Hamburg NY 14075",
    "addr:housenumber":"4336",
    "addr:postcode":"14075",
    "addr:street":"Rushford Dr",
    "iso:country":"US",
    "sg:address":"4336 Rushford Dr",
    "sg:city":"Hamburg",
    "sg:classifiers":[
        {
            "category":"Shopping",
            "type":"Retail Goods"
        }
    ],
    "sg:phone":"+1   ",
    "sg:postcode":"14075",
    "sg:province":"NY",
    "sg:tags":[
        "merchandise"
    ],
    "wof:name":"Hop Shop 2 Inc",
    "wof:placetype":"venue"
},
  "geometry": {"coordinates":[-78.815578,42.746355],"type":"Point"}
}