{
  "type": "Feature",
  "properties": {
    "addr:full":"232 Gibson St Buffalo NY 14212",
    "addr:housenumber":"232",
    "addr:postcode":"14212",
    "addr:street":"Gibson St",
    "iso:country":"US",
    "sg:address":"232 Gibson St",
    "sg:city":"Buffalo",
    "sg:classifiers":[
        {
            "category":"Bars & Pubs",
            "type":"Food & Drink"
        }
    ],
    "sg:phone":"+1   ",
    "sg:postcode":"14212",
    "sg:province":"NY",
    "sg:tags":[
        "drinking"
    ],
    "wof:name":"Market Bar & Grill",
    "wof:placetype":"venue"
},
  "geometry": {"coordinates":[-78.838173,42.8909],"type":"Point"}
}