{
  "type": "Feature",
  "properties": {
    "iso:country":"US",
    "sg:address":"2351 Ralph Avenue",
    "sg:city":"Brooklyn",
    "sg:classifiers":[
        {
            "category":"Building & Trades",
            "subcategory":"Locksmith",
            "type":"Services"
        }
    ],
    "sg:phone":"+1 718 766 2402",
    "sg:postcode":"11234",
    "sg:province":"NY",
    "sg:tags":[
        "key"
    ],
    "wof:name":"0 Emergency A Locksmith",
    "wof:placetype":"venue"
},
  "geometry": {"coordinates":[-73.917225,40.620626],"type":"Point"}
}