{
  "type": "Feature",
  "properties": {
    "iso:country":"US",
    "sg:address":"153 10 Ave",
    "sg:city":"New York",
    "sg:classifiers":[
        {
            "category":"Retail",
            "subcategory":"Auto Rental",
            "type":"Services"
        }
    ],
    "sg:phone":"+1 212 255 0150",
    "sg:postcode":"10011",
    "sg:province":"NY",
    "sg:tags":[
        "renting",
        "truck",
        "leasing"
    ],
    "sg:website":"www.mendonleasing.com",
    "wof:name":"Mendon Truck Renting Co",
    "wof:placetype":"venue"
},
  "geometry": {"coordinates":[-74.007705,40.742833],"type":"Point"}
}