{
  "type": "Feature",
  "properties": {
    "iso:country":"US",
    "sg:address":"185 Bethpage-Sweet Hollow Rd",
    "sg:city":"Old Bethpage",
    "sg:classifiers":[
        {
            "category":"Professional",
            "subcategory":"Business Services",
            "type":"Services"
        }
    ],
    "sg:phone":"+1 516 694 9850",
    "sg:postcode":"11804",
    "sg:province":"NY",
    "sg:tags":[
        "shop",
        "metal"
    ],
    "wof:name":"Atlantic Coast Metalizing",
    "wof:placetype":"venue"
},
  "geometry": {"coordinates":[-73.452423,40.762805],"type":"Point"}
}