{
  "type": "Feature",
  "properties": {
    "addr:full":"10 Asbury St Deer Park NY 11729",
    "addr:housenumber":"10",
    "addr:postcode":"11729",
    "addr:street":"Asbury St",
    "iso:country":"US",
    "sg:address":"10 Asbury St",
    "sg:city":"Deer Park",
    "sg:classifiers":[
        {
            "category":"Organizations",
            "subcategory":"Religious Organization",
            "type":"Services"
        }
    ],
    "sg:phone":"+1 631 586 8214",
    "sg:postcode":"11729",
    "sg:province":"NY",
    "sg:tags":[
        "clergy"
    ],
    "wof:name":"Dennis O'Rourke",
    "wof:placetype":"venue"
},
  "geometry": {"coordinates":[-73.31304900000001,40.777619],"type":"Point"}
}