{
  "type": "Feature",
  "properties": {
    "iso:country":"US",
    "sg:address":"513 Washington St",
    "sg:city":"Watertown",
    "sg:classifiers":[
        {
            "category":"Health Services",
            "subcategory":"Doctor",
            "type":"Services"
        }
    ],
    "sg:phone":"+1 315 788 2211",
    "sg:postcode":"13601",
    "sg:province":"NY",
    "sg:tags":[
        "medical"
    ],
    "wof:name":"Child & Adolescent Hlth Assoc",
    "wof:placetype":"venue"
},
  "geometry": {"coordinates":[-75.91173999999999,43.969657],"type":"Point"}
}