{
  "type": "Feature",
  "properties": {
    "iso:country":"US",
    "sg:address":"115 Jericho Tpke",
    "sg:city":"Mineola",
    "sg:classifiers":[
        {
            "category":"Organizations",
            "subcategory":"Community Association",
            "type":"Services"
        }
    ],
    "sg:phone":"+1 516 746 9699",
    "sg:postcode":"11501",
    "sg:province":"NY",
    "sg:tags":[
        "club"
    ],
    "wof:name":"Italian American Civic Assn",
    "wof:placetype":"venue"
},
  "geometry": {"coordinates":[-73.64023400000001,40.749467],"type":"Point"}
}