{
  "type": "Feature",
  "properties": {
    "iso:country":"US",
    "sg:address":"225 Overlook Rd",
    "sg:city":"New Rochelle",
    "sg:classifiers":[
        {
            "category":"Real Estate",
            "subcategory":"Architect",
            "type":"Services"
        }
    ],
    "sg:phone":"+1 914 633 4588",
    "sg:postcode":"10804",
    "sg:province":"NY",
    "wof:name":"Herbert Feuerstein",
    "wof:placetype":"venue"
},
  "geometry": {"coordinates":[-73.785015,40.941003],"type":"Point"}
}