{
  "type": "Feature",
  "properties": {
    "addr:full":"469 Main St Arcade NY 14009",
    "addr:housenumber":"469",
    "addr:postcode":"14009",
    "addr:street":"Main St",
    "iso:country":"US",
    "sg:address":"469 Main St",
    "sg:city":"Arcade",
    "sg:classifiers":[
        {
            "category":"Food & Beverages",
            "subcategory":"Groceries & Convenience Stores",
            "type":"Retail Goods"
        }
    ],
    "sg:phone":"+1   ",
    "sg:postcode":"14009",
    "sg:province":"NY",
    "sg:tags":[
        "station",
        "gasoline"
    ],
    "wof:name":"Arcade E-Z Shop",
    "wof:placetype":"venue"
},
  "geometry": {"coordinates":[-78.44995400000001,42.532468],"type":"Point"}
}