{
  "type": "Feature",
  "properties": {
    "addr:full":"7016 51st Ave Woodside NY 11377",
    "addr:housenumber":"7016",
    "addr:postcode":"11377",
    "addr:street":"51St Ave",
    "iso:country":"US",
    "sg:address":"7016 51st Ave",
    "sg:city":"Woodside",
    "sg:classifiers":[
        {
            "category":"Retail",
            "subcategory":"Auto Repair",
            "type":"Services"
        }
    ],
    "sg:phone":"+1 718 507 0945",
    "sg:postcode":"11377",
    "sg:province":"NY",
    "wof:name":"D C S Transmission Auto Repr Corp",
    "wof:placetype":"venue"
},
  "geometry": {"coordinates":[-73.893501,40.7356],"type":"Point"}
}