{
  "type": "Feature",
  "properties": {
    "addr:full":"35 E 13th St New York NY 10003",
    "addr:housenumber":"35",
    "addr:postcode":"10003",
    "addr:street":"E 13Th St",
    "iso:country":"US",
    "sg:address":"35 E 13th St",
    "sg:city":"New York",
    "sg:classifiers":[
        {
            "category":"Bars & Pubs",
            "subcategory":"Lounge",
            "type":"Food & Drink"
        },
        {
            "category":"Recreation",
            "subcategory":"Dance Hall",
            "type":"Entertainment"
        }
    ],
    "sg:phone":"+1 212 979 6677",
    "sg:postcode":"10003",
    "sg:province":"NY",
    "sg:tags":[
        "club"
    ],
    "sg:website":"www.bar13.com",
    "wof:name":"Bar 13",
    "wof:placetype":"venue"
},
  "geometry": {"coordinates":[-73.992203,40.7346],"type":"Point"}
}