{
  "type": "Feature",
  "properties": {
    "addr:full":"936 Co Rd 49 Winthrop NY 13697",
    "addr:housenumber":"936;49",
    "addr:postcode":"13697",
    "addr:street":"Co Rd",
    "iso:country":"US",
    "sg:address":"936 Co Rd 49",
    "sg:city":"Winthrop",
    "sg:classifiers":[
        {
            "category":"Farming",
            "subcategory":"Farm",
            "type":"Manufacturing & Wholesale Goods"
        }
    ],
    "sg:phone":"+1 315 328 5388",
    "sg:postcode":"13697",
    "sg:province":"NY",
    "wof:name":"Stauffer Farms",
    "wof:placetype":"venue"
},
  "geometry": {"coordinates":[-74.814975,44.795676],"type":"Point"}
}