{
  "type": "Feature",
  "properties": {
    "iso:country":"US",
    "sg:address":"19 E 54th Street",
    "sg:city":"New York",
    "sg:classifiers":[
        {
            "category":"Banks & Credit Unions",
            "subcategory":"Bank",
            "type":"Services"
        }
    ],
    "sg:phone":"+1 212 833 1000",
    "sg:postcode":"10022",
    "sg:province":"NY",
    "wof:name":"Bank Audi",
    "wof:placetype":"venue"
},
  "geometry": {"coordinates":[-73.97474099999999,40.760903],"type":"Point"}
}