{
  "type": "Feature",
  "properties": {
    "iso:country":"US",
    "sg:address":"171 York St",
    "sg:city":"Rochester",
    "sg:classifiers":[
        {
            "category":"Wholesale",
            "subcategory":"Auto Parts",
            "type":"Manufacturing & Wholesale Goods"
        }
    ],
    "sg:phone":"+1 585 328 4720",
    "sg:postcode":"14611",
    "sg:province":"NY",
    "sg:tags":[
        "tire"
    ],
    "wof:name":"Tyldin Corp",
    "wof:placetype":"venue"
},
  "geometry": {"coordinates":[-77.637601,43.152966],"type":"Point"}
}