{
  "type": "Feature",
  "properties": {
    "iso:country":"US",
    "sg:address":"155 Co Rd 24",
    "sg:city":"Malone",
    "sg:classifiers":[
        {
            "category":"Freight",
            "type":"Transportation"
        }
    ],
    "sg:phone":"+1   ",
    "sg:postcode":"12992",
    "sg:province":"NY",
    "sg:tags":[
        "trucking"
    ],
    "wof:name":"Collins & Company",
    "wof:placetype":"venue"
},
  "geometry": {"coordinates":[-73.503816,44.821153],"type":"Point"}
}