{
  "type": "Feature",
  "properties": {
    "addr:full":"45 E 85th St New York NY 10028",
    "addr:housenumber":"45",
    "addr:postcode":"10028",
    "addr:street":"E 85Th St",
    "iso:country":"US",
    "sg:address":"45 E 85th St",
    "sg:city":"New York",
    "sg:classifiers":[
        {
            "category":"Health Services",
            "subcategory":"Doctor",
            "type":"Services"
        }
    ],
    "sg:phone":"+1 212 472 7370",
    "sg:postcode":"10028",
    "sg:province":"NY",
    "sg:tags":[
        "physician",
        "surgeon"
    ],
    "wof:name":"Fisher Cardiology",
    "wof:placetype":"venue"
},
  "geometry": {"coordinates":[-73.95785600000001,40.779666],"type":"Point"}
}