{
  "type": "Feature",
  "properties": {
    "iso:country":"US",
    "sg:address":"38 Ross Ln",
    "sg:city":"Mount Sinai",
    "sg:classifiers":[
        {
            "category":"Building & Trades",
            "subcategory":"Landscaping Services",
            "type":"Services"
        }
    ],
    "sg:phone":"+1 631 331 0836",
    "sg:postcode":"11766",
    "sg:province":"NY",
    "sg:tags":[
        "landscape"
    ],
    "wof:name":"Stravino Enterprises Inc",
    "wof:placetype":"venue"
},
  "geometry": {"coordinates":[-73.006362,40.926306],"type":"Point"}
}