{
  "type": "Feature",
  "properties": {
    "addr:full":"32 Hillside Ave Williston Park NY 11596",
    "addr:housenumber":"32",
    "addr:postcode":"11596",
    "addr:street":"Hillside Ave",
    "iso:country":"US",
    "sg:address":"32 Hillside Ave",
    "sg:city":"Williston Park",
    "sg:classifiers":[
        {
            "category":"Utilities",
            "subcategory":"Mobile Phone",
            "type":"Services"
        }
    ],
    "sg:phone":"+1 516 873 7979",
    "sg:postcode":"11596",
    "sg:province":"NY",
    "sg:tags":[
        "communication",
        "radiotelephone"
    ],
    "sg:website":"www.wirelessplus.com",
    "wof:name":"Wireless Plus",
    "wof:placetype":"venue"
},
  "geometry": {"coordinates":[-73.64070100000001,40.757702],"type":"Point"}
}