{
  "type": "Feature",
  "properties": {
    "iso:country":"US",
    "sg:address":"147 Washington Ave",
    "sg:city":"Endicott",
    "sg:classifiers":[
        {
            "category":"Real Estate",
            "subcategory":"Real Estate Agent",
            "type":"Services"
        }
    ],
    "sg:phone":"+1 607 748 3303",
    "sg:postcode":"13760",
    "sg:province":"NY",
    "sg:tags":[
        "auction",
        "business"
    ],
    "wof:name":"All American Auctioneers",
    "wof:placetype":"venue"
},
  "geometry": {"coordinates":[-76.048113,42.101645],"type":"Point"}
}