{
  "type": "Feature",
  "properties": {
    "iso:country":"US",
    "sg:address":"3871 State Highway 30",
    "sg:city":"Amsterdam",
    "sg:classifiers":[
        {
            "category":"Shopping",
            "subcategory":"Clothing, Apparel, & Fashions",
            "type":"Retail Goods"
        },
        {
            "category":"Shopping",
            "subcategory":"Party Supplies",
            "type":"Retail Goods"
        },
        {
            "category":"Shopping",
            "subcategory":"Bridal",
            "type":"Retail Goods"
        }
    ],
    "sg:phone":"+1 518 883 5600",
    "sg:postcode":"12010",
    "sg:province":"NY",
    "sg:tags":[
        "shop",
        "tuxedo",
        "sale",
        "wear",
        "wedding",
        "rental",
        "formal"
    ],
    "wof:name":"Belles N Beaus Inc",
    "wof:placetype":"venue"
},
  "geometry": {"coordinates":[-74.204767,43.036581],"type":"Point"}
}