{
  "type": "Feature",
  "properties": {
    "iso:country":"US",
    "sg:address":"56 Clifton Country Rd",
    "sg:city":"Clifton Park",
    "sg:classifiers":[
        {
            "category":"Professional",
            "type":"Services"
        }
    ],
    "sg:phone":"+1 518 371 0977",
    "sg:postcode":"12065",
    "sg:province":"NY",
    "sg:tags":[
        "establishment"
    ],
    "wof:name":"Tom James Co",
    "wof:placetype":"venue"
},
  "geometry": {"coordinates":[-73.783102,42.857219],"type":"Point"}
}