{
  "type": "Feature",
  "properties": {
    "addr:full":"117 W 58th St New York NY 10019",
    "addr:housenumber":"117",
    "addr:postcode":"10019",
    "addr:street":"W 58Th St",
    "iso:country":"US",
    "sg:address":"117 W 58th St",
    "sg:city":"New York",
    "sg:classifiers":[
        {
            "category":"Restaurant",
            "type":"Food & Drink"
        }
    ],
    "sg:menulink":"http://www.allmenus.com/ny/new-york/247589-ninos-tuscany-ristorante-italiano/menu/",
    "sg:phone":"+1 212 757 8630",
    "sg:postcode":"10019",
    "sg:province":"NY",
    "sg:tags":[
        "italian"
    ],
    "wof:name":"Nino's Tuscany Ristorante Italiano",
    "wof:placetype":"venue"
},
  "geometry": {"coordinates":[-73.97731899999999,40.765535],"type":"Point"}
}