{
  "type": "Feature",
  "properties": {
    "iso:country":"US",
    "sg:address":"33 Squaw Rd",
    "sg:city":"East Hampton",
    "sg:classifiers":[
        {
            "category":"Building & Trades",
            "subcategory":"Construction",
            "type":"Services"
        }
    ],
    "sg:phone":"+1 631 324 2881",
    "sg:postcode":"11937",
    "sg:province":"NY",
    "sg:tags":[
        "general",
        "contractor"
    ],
    "wof:name":"Karl Avallone Builder LTD",
    "wof:placetype":"venue"
},
  "geometry": {"coordinates":[-72.179332,41.022389],"type":"Point"}
}