{
  "type": "Feature",
  "properties": {
    "iso:country":"US",
    "sg:address":"1865 Palmer Ave Ste 108",
    "sg:city":"Larchmont",
    "sg:classifiers":[
        {
            "category":"Banks & Credit Unions",
            "subcategory":"Financial Services",
            "type":"Services"
        }
    ],
    "sg:phone":"+1 914 834 0180",
    "sg:postcode":"10538",
    "sg:province":"NY",
    "sg:tags":[
        "management",
        "investment"
    ],
    "wof:name":"Gavrin Associates",
    "wof:placetype":"venue"
},
  "geometry": {"coordinates":[-73.757273,40.93382],"type":"Point"}
}