{
  "type": "Feature",
  "properties": {
    "addr:full":"269 New York Ave Huntington NY 11743",
    "addr:housenumber":"269",
    "addr:postcode":"11743",
    "addr:street":"New York Ave",
    "iso:country":"US",
    "sg:address":"269 New York Ave",
    "sg:city":"Huntington",
    "sg:classifiers":[
        {
            "category":"Restaurant",
            "type":"Food & Drink"
        }
    ],
    "sg:phone":"+1 631 673 8188",
    "sg:postcode":"11743",
    "sg:province":"NY",
    "sg:tags":[
        "chinese"
    ],
    "wof:name":"Mandarin Gourmet Chinese Cuisine",
    "wof:placetype":"venue"
},
  "geometry": {"coordinates":[-73.424896,40.874199],"type":"Point"}
}