{
  "type": "Feature",
  "properties": {
    "addr:full":"32 Robinson Hollow Way Stephentown NY 12168",
    "addr:housenumber":"32",
    "addr:postcode":"12168",
    "addr:street":"Robinson Hollow Way",
    "iso:country":"US",
    "sg:address":"32 Robinson Hollow Way",
    "sg:city":"Stephentown",
    "sg:classifiers":[
        {
            "category":"Professional",
            "subcategory":"Research",
            "type":"Services"
        }
    ],
    "sg:phone":"+1   ",
    "sg:postcode":"12168",
    "sg:province":"NY",
    "sg:tags":[
        "nonphysical",
        "commercial"
    ],
    "wof:name":"Lee & Assoc",
    "wof:placetype":"venue"
},
  "geometry": {"coordinates":[-73.353054,42.602582],"type":"Point"}
}