{
  "type": "Feature",
  "properties": {
    "addr:full":"114 E Steuben St Bath NY 14810",
    "addr:housenumber":"114",
    "addr:postcode":"14810",
    "addr:street":"E Steuben St",
    "iso:country":"US",
    "sg:address":"114 E Steuben St",
    "sg:city":"Bath",
    "sg:classifiers":[
        {
            "category":"Wholesale",
            "subcategory":"Construction Materials",
            "type":"Manufacturing & Wholesale Goods"
        },
        {
            "category":"Wholesale",
            "subcategory":"Durable Goods & Equipment",
            "type":"Manufacturing & Wholesale Goods"
        }
    ],
    "sg:phone":"+1 607 776 9453",
    "sg:postcode":"14810",
    "sg:province":"NY",
    "sg:tags":[
        "timberland",
        "company",
        "timber"
    ],
    "wof:name":"Krenn Bridge Co-New York",
    "wof:placetype":"venue"
},
  "geometry": {"coordinates":[-77.314334,42.333203],"type":"Point"}
}