{
  "type": "Feature",
  "properties": {
    "iso:country":"US",
    "sg:address":"71 2nd St",
    "sg:city":"Athens",
    "sg:classifiers":[
        {
            "category":"Health Services",
            "subcategory":"Nursing And Care Facility",
            "type":"Services"
        }
    ],
    "sg:phone":"+1 518 945 1673",
    "sg:postcode":"12015",
    "sg:province":"NY",
    "sg:tags":[
        "residential"
    ],
    "wof:name":"Home Sweet Home Of Athens",
    "wof:placetype":"venue"
},
  "geometry": {"coordinates":[-73.814415,42.262728],"type":"Point"}
}