{
  "type": "Feature",
  "properties": {
    "addr:full":"1223 Nepperhan Ave Yonkers NY 10703",
    "addr:housenumber":"1223",
    "addr:postcode":"10703",
    "addr:street":"Nepperhan Ave",
    "iso:country":"US",
    "sg:address":"1223 Nepperhan Ave",
    "sg:city":"Yonkers",
    "sg:classifiers":[
        {
            "category":"Restaurant",
            "type":"Food & Drink"
        }
    ],
    "sg:menulink":"http://www.allmenus.com/ny/yonkers/107146-soup-man/menu/",
    "sg:phone":"+1 914 476 9521",
    "sg:postcode":"10703",
    "sg:province":"NY",
    "sg:tags":[
        "soup",
        "american",
        "salad"
    ],
    "wof:name":"Soup Man",
    "wof:placetype":"venue"
},
  "geometry": {"coordinates":[-73.87240199999999,40.965734],"type":"Point"}
}