{
  "type": "Feature",
  "properties": {
    "iso:country":"US",
    "sg:address":"2770 Union Rd",
    "sg:city":"Cheektowaga",
    "sg:classifiers":[
        {
            "category":"Restaurant",
            "type":"Food & Drink"
        }
    ],
    "sg:phone":"+1 716 681 8440",
    "sg:postcode":"14227",
    "sg:province":"NY",
    "sg:tags":[
        "eating",
        "pizza"
    ],
    "sg:website":"http://www.tonyspizzeriaonline.com",
    "wof:name":"Tony's Pizzeria & Pasta",
    "wof:placetype":"venue"
},
  "geometry": {"coordinates":[-78.75456,42.887673],"type":"Point"}
}