{
  "type": "Feature",
  "properties": {
    "iso:country":"US",
    "sg:address":"492 William Floyd Pkwy",
    "sg:city":"Shirley",
    "sg:classifiers":[
        {
            "category":"Restaurant",
            "type":"Food & Drink"
        }
    ],
    "sg:phone":"+1   ",
    "sg:postcode":"11967",
    "sg:province":"NY",
    "sg:tags":[
        "eating",
        "product",
        "dairy"
    ],
    "wof:name":"Carvel Ice Cream",
    "wof:placetype":"venue"
},
  "geometry": {"coordinates":[-72.864464,40.791031],"type":"Point"}
}