{
  "type": "Feature",
  "properties": {
    "iso:country":"US",
    "sg:address":"1 Lyon Farm Ct",
    "sg:city":"Port Chester",
    "sg:classifiers":[
        {
            "category":"Professional",
            "subcategory":"Advertising",
            "type":"Services"
        }
    ],
    "sg:phone":"+1 914 939 1355",
    "sg:postcode":"10573",
    "sg:province":"NY",
    "sg:tags":[
        "distribution"
    ],
    "wof:name":"Plant Integration Assoc Inc",
    "wof:placetype":"venue"
},
  "geometry": {"coordinates":[-73.664247,41.01036],"type":"Point"}
}