{
  "type": "Feature",
  "properties": {
    "iso:country":"US",
    "sg:address":"440 State Route 17M",
    "sg:city":"Monroe",
    "sg:classifiers":[
        {
            "category":"Education",
            "subcategory":"Kindergarten",
            "type":"Public Place"
        }
    ],
    "sg:phone":"+1 845 781 8087",
    "sg:postcode":"10950",
    "sg:province":"NY",
    "sg:tags":[
        "school",
        "driving"
    ],
    "sg:website":"www.safetycourses.com/daytonadri...",
    "wof:name":"Daytona Driving School",
    "wof:placetype":"venue"
},
  "geometry": {"coordinates":[-74.172997,41.3176],"type":"Point"}
}