{
  "type": "Feature",
  "properties": {
    "iso:country":"US",
    "sg:address":"203 Dahlgreen Pl",
    "sg:city":"Brooklyn",
    "sg:classifiers":[
        {
            "category":"Shopping",
            "subcategory":"Catalog Store",
            "type":"Retail Goods"
        }
    ],
    "sg:phone":"+1   ",
    "sg:postcode":"11228",
    "sg:province":"NY",
    "sg:tags":[
        "house",
        "mail"
    ],
    "wof:name":"La Postina",
    "wof:placetype":"venue"
},
  "geometry": {"coordinates":[-74.026062,40.615076],"type":"Point"}
}