{
  "type": "Feature",
  "properties": {
    "iso:country":"US",
    "sg:address":"109 Harpington Dr",
    "sg:city":"Rochester",
    "sg:classifiers":[
        {
            "category":"Professional",
            "subcategory":"Business Services",
            "type":"Services"
        },
        {
            "category":"Professional",
            "subcategory":"Computer Services",
            "type":"Services"
        }
    ],
    "sg:phone":"+1 585 473 4639",
    "sg:postcode":"14624",
    "sg:province":"NY",
    "sg:tags":[
        "coach",
        "consultant",
        "designer",
        "system"
    ],
    "sg:website":"http://www.judgekaren.com",
    "wof:name":"Ross Consulting",
    "wof:placetype":"venue"
},
  "geometry": {"coordinates":[-77.716374,43.126534],"type":"Point"}
}