{
  "type": "Feature",
  "properties": {
    "addr:full":"15 Oceanview Ln Staten Island NY 10301",
    "addr:housenumber":"15",
    "addr:postcode":"10301",
    "addr:street":"Oceanview Ln",
    "iso:country":"US",
    "sg:address":"15 Oceanview Ln",
    "sg:city":"Staten Island",
    "sg:classifiers":[
        {
            "category":"Health Services",
            "subcategory":"Doctor",
            "type":"Services"
        }
    ],
    "sg:phone":"+1 718 816 1769",
    "sg:postcode":"10301",
    "sg:province":"NY",
    "sg:tags":[
        "medical"
    ],
    "wof:name":"Hamilton Bayridge",
    "wof:placetype":"venue"
},
  "geometry": {"coordinates":[-74.102464,40.603331],"type":"Point"}
}