{
  "type": "Feature",
  "properties": {
    "addr:full":"26 Soundview Cir White Plains NY 10606",
    "addr:housenumber":"26",
    "addr:postcode":"10606",
    "addr:street":"Soundview Cir",
    "iso:country":"US",
    "sg:address":"26 Soundview Cir",
    "sg:city":"White Plains",
    "sg:classifiers":[
        {
            "category":"Real Estate",
            "subcategory":"Architect",
            "type":"Services"
        }
    ],
    "sg:phone":"+1 914 949 7272",
    "sg:postcode":"10606",
    "sg:province":"NY",
    "wof:name":"William W Meyer",
    "wof:placetype":"venue"
},
  "geometry": {"coordinates":[-73.765176,41.006297],"type":"Point"}
}