{
  "type": "Feature",
  "properties": {
    "iso:country":"US",
    "sg:address":"34 Easy St",
    "sg:city":"Sayville",
    "sg:classifiers":[
        {
            "category":"Building & Trades",
            "subcategory":"Construction",
            "type":"Services"
        }
    ],
    "sg:phone":"+1 631 589 5152",
    "sg:postcode":"11782",
    "sg:province":"NY",
    "sg:tags":[
        "contractor"
    ],
    "wof:name":"Mjr Contracting Inc",
    "wof:placetype":"venue"
},
  "geometry": {"coordinates":[-73.08963,40.741405],"type":"Point"}
}