{
  "type": "Feature",
  "properties": {
    "iso:country":"US",
    "sg:address":"7 Austin Pl",
    "sg:city":"Great Neck",
    "sg:classifiers":[
        {
            "category":"Building & Trades",
            "subcategory":"Construction",
            "type":"Services"
        }
    ],
    "sg:phone":"+1 516 466 6460",
    "sg:postcode":"11020",
    "sg:province":"NY",
    "sg:tags":[
        "home",
        "family"
    ],
    "wof:name":"Irastan Inc",
    "wof:placetype":"venue"
},
  "geometry": {"coordinates":[-73.71292699999999,40.7786],"type":"Point"}
}