{
  "type": "Feature",
  "properties": {
    "addr:full":"43 Vitti St New Canaan NY 06840",
    "addr:housenumber":"43",
    "addr:postcode":"06840",
    "addr:street":"Vitti St",
    "iso:country":"US",
    "sg:address":"43 Vitti St",
    "sg:city":"New Canaan",
    "sg:classifiers":[
        {
            "category":"Organizations",
            "subcategory":"Community Association",
            "type":"Services"
        }
    ],
    "sg:phone":"+1   ",
    "sg:postcode":"06840",
    "sg:province":"NY",
    "wof:name":"Columbus Center Of New Canaan",
    "wof:placetype":"venue"
},
  "geometry": {"coordinates":[-73.489079,41.148524],"type":"Point"}
}