{
  "type": "Feature",
  "properties": {
    "iso:country":"US",
    "sg:address":"1 Babcock St",
    "sg:city":"Buffalo",
    "sg:classifiers":[
        {
            "category":"Manufacturing",
            "subcategory":"Electronics",
            "type":"Manufacturing & Wholesale Goods"
        }
    ],
    "sg:phone":"+1 716 821 9595",
    "sg:postcode":"14210",
    "sg:province":"NY",
    "wof:name":"Comet Flasher",
    "wof:placetype":"venue"
},
  "geometry": {"coordinates":[-78.83678999999999,42.864461],"type":"Point"}
}