{
  "type": "Feature",
  "properties": {
    "addr:full":"64 Jones Rd East Quogue NY 11942",
    "addr:housenumber":"64",
    "addr:postcode":"11942",
    "addr:street":"Jones Rd",
    "iso:country":"US",
    "sg:address":"64 Jones Rd",
    "sg:city":"East Quogue",
    "sg:classifiers":[
        {
            "category":"Professional",
            "subcategory":"Lawyer & Legal Services",
            "type":"Services"
        }
    ],
    "sg:phone":"+1 631 723 1246",
    "sg:postcode":"11942",
    "sg:province":"NY",
    "sg:tags":[
        "attorney"
    ],
    "wof:name":"Joan M Dorazio",
    "wof:placetype":"venue"
},
  "geometry": {"coordinates":[-72.55587,40.85102],"type":"Point"}
}