{
  "type": "Feature",
  "properties": {
    "iso:country":"US",
    "sg:address":"120 Capen Blvd",
    "sg:city":"Buffalo",
    "sg:classifiers":[
        {
            "category":"Home & Garden",
            "subcategory":"Building Materials",
            "type":"Retail Goods"
        }
    ],
    "sg:phone":"+1 716 837 0407",
    "sg:postcode":"14226",
    "sg:province":"NY",
    "sg:tags":[
        "glass",
        "shape",
        "leaded",
        "circle",
        "special"
    ],
    "wof:name":"R. Js A Touch Of Glass",
    "wof:placetype":"venue"
},
  "geometry": {"coordinates":[-78.82096199999999,42.959313],"type":"Point"}
}