{
  "type": "Feature",
  "properties": {
    "iso:country":"US",
    "sg:address":"411 Ballston Rd",
    "sg:city":"Schenectady",
    "sg:classifiers":[
        {
            "category":"Communications",
            "subcategory":"Newspaper",
            "type":"Services"
        }
    ],
    "sg:phone":"+1 518 399 9133",
    "sg:postcode":"12302",
    "sg:province":"NY",
    "sg:tags":[
        "print",
        "medium"
    ],
    "wof:name":"The Weekly",
    "wof:placetype":"venue"
},
  "geometry": {"coordinates":[-73.947998,42.844209],"type":"Point"}
}