{
  "type": "Feature",
  "properties": {
    "iso:country":"US",
    "sg:address":"23 Woodside Ln",
    "sg:city":"Depew",
    "sg:classifiers":[
        {
            "category":"Restaurant",
            "type":"Food & Drink"
        }
    ],
    "sg:phone":"+1 716 651 0690",
    "sg:postcode":"14043",
    "sg:province":"NY",
    "wof:name":"Elma Inn",
    "wof:placetype":"venue"
},
  "geometry": {"coordinates":[-78.710404,42.886871],"type":"Point"}
}