{
  "type": "Feature",
  "properties": {
    "addr:full":"330 N Highland Ave Nyack NY 10960",
    "addr:housenumber":"330",
    "addr:postcode":"10960",
    "addr:street":"N Highland Ave",
    "iso:country":"US",
    "sg:address":"330 N Highland Ave",
    "sg:city":"Nyack",
    "sg:classifiers":[
        {
            "category":"Education",
            "subcategory":"Library",
            "type":"Public Place"
        }
    ],
    "sg:phone":"+1 845 358 2248",
    "sg:postcode":"10960",
    "sg:province":"NY",
    "sg:tags":[
        "organization",
        "religious"
    ],
    "sg:website":"www.templebethtorah.org",
    "wof:name":"Temple Beth Torah",
    "wof:placetype":"venue"
},
  "geometry": {"coordinates":[-73.92614399999999,41.100114],"type":"Point"}
}