{
  "type": "Feature",
  "properties": {
    "addr:full":"3924 Fort Hamilton Pkwy Brooklyn NY 11218",
    "addr:housenumber":"3924",
    "addr:postcode":"11218",
    "addr:street":"Fort Hamilton Pkwy",
    "iso:country":"US",
    "sg:address":"3924 Fort Hamilton Pkwy",
    "sg:city":"Brooklyn",
    "sg:classifiers":[
        {
            "category":"Restaurant",
            "type":"Food & Drink"
        }
    ],
    "sg:phone":"+1 718 853 8126",
    "sg:postcode":"11218",
    "sg:province":"NY",
    "sg:tags":[
        "delicatessen"
    ],
    "wof:name":"Sunflower Grocery Inc",
    "wof:placetype":"venue"
},
  "geometry": {"coordinates":[-73.991129,40.642859],"type":"Point"}
}