{
  "type": "Feature",
  "properties": {
    "addr:full":"785 5th Ave New York NY 10022",
    "addr:housenumber":"785",
    "addr:postcode":"10022",
    "addr:street":"5Th Ave",
    "iso:country":"US",
    "sg:address":"785 5th Ave",
    "sg:city":"New York",
    "sg:classifiers":[
        {
            "category":"Professional",
            "subcategory":"Business Services",
            "type":"Services"
        }
    ],
    "sg:phone":"+1 212 751 5350",
    "sg:postcode":"10022",
    "sg:province":"NY",
    "sg:tags":[
        "interior",
        "consultant",
        "design",
        "decorator"
    ],
    "wof:name":"Lynford Limited",
    "wof:placetype":"venue"
},
  "geometry": {"coordinates":[-73.97275,40.764396],"type":"Point"}
}