{
  "type": "Feature",
  "properties": {
    "addr:full":"1202 Surf Avenue Brooklyn NY 11224",
    "addr:housenumber":"1202",
    "addr:postcode":"11224",
    "addr:street":"Surf Avenue",
    "iso:country":"US",
    "sg:address":"1202 Surf Avenue",
    "sg:city":"Brooklyn",
    "sg:classifiers":[
        {
            "category":"Food & Beverages",
            "subcategory":"Groceries & Convenience Stores",
            "type":"Retail Goods"
        }
    ],
    "sg:phone":"+1 718 449 6258",
    "sg:postcode":"11224",
    "sg:province":"NY",
    "wof:name":"Surf Convenience",
    "wof:placetype":"venue"
},
  "geometry": {"coordinates":[-73.979873,40.575647],"type":"Point"}
}