{
  "type": "Feature",
  "properties": {
    "addr:full":"820 Columbus Ave New York NY 10025",
    "addr:housenumber":"820",
    "addr:postcode":"10025",
    "addr:street":"Columbus Ave",
    "iso:country":"US",
    "sg:address":"820 Columbus Ave",
    "sg:city":"New York",
    "sg:classifiers":[
        {
            "category":"Social Services",
            "subcategory":"Child Care",
            "type":"Services"
        }
    ],
    "sg:phone":"+1 212 749 5572",
    "sg:postcode":"10025",
    "sg:province":"NY",
    "sg:tags":[
        "day"
    ],
    "wof:name":"Open Door Child Care Cntr",
    "wof:placetype":"venue"
},
  "geometry": {"coordinates":[-73.965103,40.795898],"type":"Point"}
}