{
  "type": "Feature",
  "properties": {
    "iso:country":"US",
    "sg:address":"168 Auringer Rd",
    "sg:city":"Constantia",
    "sg:classifiers":[
        {
            "category":"Building & Trades",
            "subcategory":"Construction",
            "type":"Services"
        }
    ],
    "sg:phone":"+1 315 623 9005",
    "sg:postcode":"13044",
    "sg:province":"NY",
    "sg:tags":[
        "hanging",
        "contractor"
    ],
    "wof:name":"David Schwalm Painting",
    "wof:placetype":"venue"
},
  "geometry": {"coordinates":[-76.00656600000001,43.271595],"type":"Point"}
}