{
  "type": "Feature",
  "properties": {
    "addr:full":"167 Ave B New York NY 10009",
    "addr:housenumber":"167",
    "addr:postcode":"10009",
    "addr:street":"Ave B",
    "iso:country":"US",
    "sg:address":"167 Ave B",
    "sg:city":"New York",
    "sg:classifiers":[
        {
            "category":"Communications",
            "subcategory":"Film & Video Production",
            "type":"Services"
        }
    ],
    "sg:phone":"+1 212 598 4084",
    "sg:postcode":"10009",
    "sg:province":"NY",
    "sg:tags":[
        "taping"
    ],
    "wof:name":"Media Dream Productions",
    "wof:placetype":"venue"
},
  "geometry": {"coordinates":[-73.97959299999999,40.727087],"type":"Point"}
}