{
  "type": "Feature",
  "properties": {
    "iso:country":"US",
    "sg:address":"21590 Reed Rd",
    "sg:city":"Watertown",
    "sg:classifiers":[
        {
            "category":"Building & Trades",
            "subcategory":"Plumbing",
            "type":"Services"
        }
    ],
    "sg:phone":"+1 315 782 8022",
    "sg:postcode":"13601",
    "sg:province":"NY",
    "sg:tags":[
        "plumbing",
        "contractor"
    ],
    "wof:name":"Freeman Mechanical Svc",
    "wof:placetype":"venue"
},
  "geometry": {"coordinates":[-75.934967,44.025925],"type":"Point"}
}