{
  "type": "Feature",
  "properties": {
    "iso:country":"US",
    "sg:address":"1990 State Hwy 284",
    "sg:city":"Slate Hill",
    "sg:classifiers":[
        {
            "category":"Government",
            "subcategory":"Post Office",
            "type":"Public Place"
        }
    ],
    "sg:phone":"+1   ",
    "sg:postcode":"10973",
    "sg:province":"NY",
    "sg:tags":[
        "postal",
        "us"
    ],
    "wof:name":"Slate Hill Main Office",
    "wof:placetype":"venue"
},
  "geometry": {"coordinates":[-74.489338,41.376574],"type":"Point"}
}