{
  "type": "Feature",
  "properties": {
    "addr:full":"2146 Forest Ave Staten Island NY 10303",
    "addr:housenumber":"2146",
    "addr:postcode":"10303",
    "addr:street":"Forest Ave",
    "iso:country":"US",
    "sg:address":"2146 Forest Ave",
    "sg:city":"Staten Island",
    "sg:classifiers":[
        {
            "category":"Restaurant",
            "type":"Food & Drink"
        }
    ],
    "sg:menulink":"http://www.allmenus.com/ny/staten-island/54628-mama-rosaria/menu/",
    "sg:phone":"+1 718 815 0557",
    "sg:postcode":"10303",
    "sg:province":"NY",
    "sg:tags":[
        "american",
        "pizza"
    ],
    "wof:name":"Mama Rosaria",
    "wof:placetype":"venue"
},
  "geometry": {"coordinates":[-74.16093499999999,40.626509],"type":"Point"}
}