{
  "type": "Feature",
  "properties": {
    "iso:country":"US",
    "sg:address":"2669 Milburn Ave",
    "sg:city":"Baldwin",
    "sg:classifiers":[
        {
            "category":"Retail",
            "subcategory":"Repair Shop",
            "type":"Services"
        }
    ],
    "sg:phone":"+1 516 379 8098",
    "sg:postcode":"11510",
    "sg:province":"NY",
    "sg:tags":[
        "plumbing",
        "drain",
        "cleaning",
        "sewer"
    ],
    "wof:name":"Bakal Plumbing & Heating",
    "wof:placetype":"venue"
},
  "geometry": {"coordinates":[-73.605515,40.64354],"type":"Point"}
}