{
  "type": "Feature",
  "properties": {
    "addr:full":"1540 3 Ave New York NY 10028",
    "addr:housenumber":"1540",
    "addr:postcode":"10028",
    "addr:street":"3 Ave",
    "iso:country":"US",
    "sg:address":"1540 3 Ave",
    "sg:city":"New York",
    "sg:classifiers":[
        {
            "category":"Retail",
            "subcategory":"Repair Shop",
            "type":"Services"
        }
    ],
    "sg:phone":"+1 212 937 2974",
    "sg:postcode":"10028",
    "sg:province":"NY",
    "sg:tags":[
        "lock",
        "locksmith"
    ],
    "wof:name":"3 Ave Locksmith",
    "wof:placetype":"venue"
},
  "geometry": {"coordinates":[-73.956334,40.7756],"type":"Point"}
}