{
  "type": "Feature",
  "properties": {
    "addr:full":"16 Heritage Dr New City NY 10956",
    "addr:housenumber":"16",
    "addr:postcode":"10956",
    "addr:street":"Heritage Dr",
    "iso:country":"US",
    "sg:address":"16 Heritage Dr",
    "sg:city":"New City",
    "sg:classifiers":[
        {
            "category":"Building & Trades",
            "subcategory":"Plumbing",
            "type":"Services"
        }
    ],
    "sg:phone":"+1 845 634 5453",
    "sg:postcode":"10956",
    "sg:province":"NY",
    "sg:tags":[
        "contractor"
    ],
    "wof:name":"Yukos Heating & AC",
    "wof:placetype":"venue"
},
  "geometry": {"coordinates":[-73.98361,41.159313],"type":"Point"}
}