{
  "type": "Feature",
  "properties": {
    "addr:full":"418 E 105th St New York NY 10029",
    "addr:housenumber":"418",
    "addr:postcode":"10029",
    "addr:street":"E 105Th St",
    "iso:country":"US",
    "sg:address":"418 E 105th St",
    "sg:city":"New York",
    "sg:classifiers":[
        {
            "category":"Government",
            "subcategory":"Office",
            "type":"Public Place"
        }
    ],
    "sg:phone":"+1 212 876 6900",
    "sg:postcode":"10029",
    "sg:province":"NY",
    "sg:tags":[
        "housing",
        "authority"
    ],
    "wof:name":"East River Housing",
    "wof:placetype":"venue"
},
  "geometry": {"coordinates":[-73.940331,40.788809],"type":"Point"}
}