{
  "type": "Feature",
  "properties": {
    "addr:full":"347 Warren St Hudson NY 12534",
    "addr:housenumber":"347",
    "addr:postcode":"12534",
    "addr:street":"Warren St",
    "iso:country":"US",
    "sg:address":"347 Warren St",
    "sg:city":"Hudson",
    "sg:classifiers":[
        {
            "category":"Retail",
            "subcategory":"Repair Shop",
            "type":"Services"
        }
    ],
    "sg:phone":"+1 518 828 0538",
    "sg:postcode":"12534",
    "sg:province":"NY",
    "sg:tags":[
        "equipment",
        "key",
        "locksmith"
    ],
    "wof:name":"City Locksmith",
    "wof:placetype":"venue"
},
  "geometry": {"coordinates":[-73.789101,42.251598],"type":"Point"}
}