{
  "type": "Feature",
  "properties": {
    "iso:country":"US",
    "sg:address":"13395 Railroad St",
    "sg:city":"Alden",
    "sg:classifiers":[
        {
            "category":"Government",
            "subcategory":"Office",
            "type":"Public Place"
        }
    ],
    "sg:phone":"+1 716 937 7392",
    "sg:postcode":"14004",
    "sg:province":"NY",
    "sg:tags":[
        "executive"
    ],
    "wof:name":"Village of Alden Garage",
    "wof:placetype":"venue"
},
  "geometry": {"coordinates":[-78.490683,42.896308],"type":"Point"}
}