{
  "type": "Feature",
  "properties": {
    "addr:full":"26 Upper Shad Rd Pound Ridge NY 10576",
    "addr:housenumber":"26",
    "addr:postcode":"10576",
    "addr:street":"Upper Shad Rd",
    "iso:country":"US",
    "sg:address":"26 Upper Shad Rd",
    "sg:city":"Pound Ridge",
    "sg:classifiers":[
        {
            "category":"Building & Trades",
            "subcategory":"Construction",
            "type":"Services"
        }
    ],
    "sg:phone":"+1 914 242 0207",
    "sg:postcode":"10576",
    "sg:province":"NY",
    "sg:tags":[
        "general",
        "contractor"
    ],
    "wof:name":"Nordic Construction Inc",
    "wof:placetype":"venue"
},
  "geometry": {"coordinates":[-73.560897,41.189185],"type":"Point"}
}