{
  "type": "Feature",
  "properties": {
    "addr:full":"2319 3 Ave New York NY 10035",
    "addr:housenumber":"2319",
    "addr:postcode":"10035",
    "addr:street":"3 Ave",
    "iso:country":"US",
    "sg:address":"2319 3 Ave",
    "sg:city":"New York",
    "sg:classifiers":[
        {
            "category":"Manufacturing",
            "subcategory":"Metals",
            "type":"Manufacturing & Wholesale Goods"
        }
    ],
    "sg:phone":"+1 212 876 3780",
    "sg:postcode":"10035",
    "sg:province":"NY",
    "sg:tags":[
        "fabricator",
        "sheet"
    ],
    "wof:name":"Fried Industries Inc",
    "wof:placetype":"venue"
},
  "geometry": {"coordinates":[-73.939522,40.798625],"type":"Point"}
}