{
  "type": "Feature",
  "properties": {
    "addr:full":"120 Cedar Dr E Scarborough NY 10510",
    "addr:housenumber":"120",
    "addr:postcode":"10510",
    "addr:street":"Cedar Dr E",
    "iso:country":"US",
    "sg:address":"120 Cedar Dr E",
    "sg:city":"Scarborough",
    "sg:classifiers":[
        {
            "category":"Manufacturing",
            "subcategory":"Retail Goods",
            "type":"Manufacturing & Wholesale Goods"
        }
    ],
    "sg:phone":"+1 716 891 5782",
    "sg:postcode":"10510",
    "sg:province":"NY",
    "sg:tags":[
        "manufacturer"
    ],
    "sg:website":"www.motoradusa.com",
    "wof:name":"Transcedar Industries",
    "wof:placetype":"venue"
},
  "geometry": {"coordinates":[-73.82757700000001,41.12816],"type":"Point"}
}