{
  "type": "Feature",
  "properties": {
    "addr:full":"105 5th Ave Frnt 1 New York NY 10003",
    "addr:housenumber":"105;1",
    "addr:postcode":"10003",
    "addr:street":"5Th Ave Frnt",
    "iso:country":"US",
    "sg:address":"105 5th Ave Frnt 1",
    "sg:city":"New York",
    "sg:classifiers":[
        {
            "category":"Communications",
            "subcategory":"Newspaper",
            "type":"Services"
        }
    ],
    "sg:phone":"+1 212 807 0099",
    "sg:postcode":"10003",
    "sg:province":"NY",
    "sg:tags":[
        "magazine"
    ],
    "sg:website":"www.barnesandnoble.com",
    "wof:name":"Barnes & Noble Bookstore",
    "wof:placetype":"venue"
},
  "geometry": {"coordinates":[-73.99164399999999,40.738398],"type":"Point"}
}