{
  "type": "Feature",
  "properties": {
    "iso:country":"US",
    "sg:address":"7 Fox St",
    "sg:city":"Poughkeepsie",
    "sg:classifiers":[
        {
            "category":"Health Services",
            "subcategory":"Doctor",
            "type":"Services"
        }
    ],
    "sg:phone":"+1 845 473 2200",
    "sg:postcode":"12601",
    "sg:province":"NY",
    "sg:tags":[
        "physician",
        "surgeon"
    ],
    "wof:name":"Hudson Center-Psychotherapies",
    "wof:placetype":"venue"
},
  "geometry": {"coordinates":[-73.936008,41.690931],"type":"Point"}
}