{
  "type": "Feature",
  "properties": {
    "iso:country":"US",
    "sg:address":"385 Knickerbocker Ave",
    "sg:city":"Brooklyn",
    "sg:classifiers":[
        {
            "category":"Health Services",
            "subcategory":"Dentist",
            "type":"Services"
        }
    ],
    "sg:phone":"+1 718 574 0527",
    "sg:postcode":"11237",
    "sg:province":"NY",
    "wof:name":"Knickerbocker Family Dental",
    "wof:placetype":"venue"
},
  "geometry": {"coordinates":[-73.917503,40.701302],"type":"Point"}
}