{
  "type": "Feature",
  "properties": {
    "addr:full":"124 W 30 St New York NY 10001",
    "addr:housenumber":"124",
    "addr:postcode":"10001",
    "addr:street":"W 30 St",
    "iso:country":"US",
    "sg:address":"124 W 30 St",
    "sg:city":"New York",
    "sg:classifiers":[
        {
            "category":"Wholesale",
            "subcategory":"Durable Goods & Equipment",
            "type":"Manufacturing & Wholesale Goods"
        }
    ],
    "sg:phone":"+1 212 760 0892",
    "sg:postcode":"10001",
    "sg:province":"NY",
    "sg:tags":[
        "installation",
        "medium",
        "video",
        "system",
        "audio"
    ],
    "wof:name":"Soundsight Technologies Inc",
    "wof:placetype":"venue"
},
  "geometry": {"coordinates":[-73.99197100000001,40.748111],"type":"Point"}
}