{
  "type": "Feature",
  "properties": {
    "addr:full":"4511 Ave K Brooklyn NY 11234",
    "addr:housenumber":"4511",
    "addr:postcode":"11234",
    "addr:street":"Ave K",
    "iso:country":"US",
    "sg:address":"4511 Ave K",
    "sg:city":"Brooklyn",
    "sg:classifiers":[
        {
            "category":"Manufacturing",
            "subcategory":"Printing",
            "type":"Manufacturing & Wholesale Goods"
        }
    ],
    "sg:phone":"+1   ",
    "sg:postcode":"11234",
    "sg:province":"NY",
    "sg:tags":[
        "literary",
        "works",
        "publishing"
    ],
    "wof:name":"Black Print Publishing Inc",
    "wof:placetype":"venue"
},
  "geometry": {"coordinates":[-73.931573,40.625662],"type":"Point"}
}