{
  "type": "Feature",
  "properties": {
    "addr:full":"73 Spring Street Rm 602 New York NY 10012",
    "addr:housenumber":"73;602",
    "addr:postcode":"10012",
    "addr:street":"Spring Street Rm",
    "iso:country":"US",
    "sg:address":"73 Spring Street Rm 602",
    "sg:city":"New York",
    "sg:classifiers":[
        {
            "category":"Organizations",
            "subcategory":"Non-profit Organization",
            "type":"Services"
        }
    ],
    "sg:phone":"+1 212 343 0043",
    "sg:postcode":"10012",
    "sg:province":"NY",
    "sg:tags":[
        "service/non-profit",
        "community"
    ],
    "wof:name":"Red Hot Organization",
    "wof:placetype":"venue"
},
  "geometry": {"coordinates":[-73.99785,40.722605],"type":"Point"}
}