{
  "type": "Feature",
  "properties": {
    "iso:country":"US",
    "sg:address":"108 Bentley Dr",
    "sg:city":"Latham",
    "sg:classifiers":[
        {
            "category":"Professional",
            "subcategory":"Employment Agencies",
            "type":"Services"
        }
    ],
    "sg:phone":"+1 518 783 7790",
    "sg:postcode":"12110",
    "sg:province":"NY",
    "sg:tags":[
        "help",
        "supply"
    ],
    "wof:name":"Good Maids",
    "wof:placetype":"venue"
},
  "geometry": {"coordinates":[-73.745294,42.725247],"type":"Point"}
}