{
  "type": "Feature",
  "properties": {
    "addr:full":"85 Cortlandt St Tarrytown NY 10591",
    "addr:housenumber":"85",
    "addr:postcode":"10591",
    "addr:street":"Cortlandt St",
    "iso:country":"US",
    "sg:address":"85 Cortlandt St",
    "sg:city":"Tarrytown",
    "sg:classifiers":[
        {
            "category":"Food & Beverages",
            "subcategory":"Meat & Fish",
            "type":"Retail Goods"
        }
    ],
    "sg:phone":"+1   ",
    "sg:postcode":"10591",
    "sg:province":"NY",
    "sg:tags":[
        "grocery",
        "market",
        "store"
    ],
    "wof:name":"Latin Market",
    "wof:placetype":"venue"
},
  "geometry": {"coordinates":[-73.86452800000001,41.078849],"type":"Point"}
}