{
  "type": "Feature",
  "properties": {
    "iso:country":"US",
    "sg:address":"156 Canal St",
    "sg:city":"New York",
    "sg:classifiers":[
        {
            "category":"Recreation",
            "subcategory":"Dance Hall",
            "type":"Entertainment"
        }
    ],
    "sg:phone":"+1 212 233 4860",
    "sg:postcode":"10013",
    "sg:province":"NY",
    "sg:tags":[
        "club"
    ],
    "wof:name":"China Tour Club",
    "wof:placetype":"venue"
},
  "geometry": {"coordinates":[-73.998001,40.716801],"type":"Point"}
}