{
  "type": "Feature",
  "properties": {
    "iso:country":"US",
    "sg:address":"9752 State Rte 230",
    "sg:city":"Dundee",
    "sg:classifiers":[
        {
            "category":"Farming",
            "subcategory":"Dairy Farm",
            "type":"Manufacturing & Wholesale Goods"
        }
    ],
    "sg:phone":"+1 607 292 3840",
    "sg:postcode":"14893",
    "sg:province":"NY",
    "wof:name":"James Hoover Farm",
    "wof:placetype":"venue"
},
  "geometry": {"coordinates":[-77.075065,42.476337],"type":"Point"}
}