{
  "type": "Feature",
  "properties": {
    "addr:full":"2767 State Hwy 32 Kingston NY 12401",
    "addr:housenumber":"2767",
    "addr:postcode":"12401",
    "addr:street":"State Hwy 32",
    "iso:country":"US",
    "sg:address":"2767 State Hwy 32",
    "sg:city":"Kingston",
    "sg:classifiers":[
        {
            "category":"Local Transit",
            "type":"Transportation"
        }
    ],
    "sg:phone":"+1   ",
    "sg:postcode":"12401",
    "sg:province":"NY",
    "sg:tags":[
        "passenger"
    ],
    "wof:name":"Hutchins-Sutton Transportation",
    "wof:placetype":"venue"
},
  "geometry": {"coordinates":[-74.041448,41.89036],"type":"Point"}
}