{
  "type": "Feature",
  "properties": {
    "addr:full":"8651 Boston State Rd Boston NY 14025",
    "addr:housenumber":"8651",
    "addr:postcode":"14025",
    "addr:street":"Boston State Rd",
    "iso:country":"US",
    "sg:address":"8651 Boston State Rd",
    "sg:city":"Boston",
    "sg:classifiers":[
        {
            "category":"Organizations",
            "subcategory":"Religious Organization",
            "type":"Services"
        }
    ],
    "sg:phone":"+1 716 941 3529",
    "sg:postcode":"14025",
    "sg:province":"NY",
    "sg:tags":[
        "church"
    ],
    "wof:name":"Faith United Church Of Christ",
    "wof:placetype":"venue"
},
  "geometry": {"coordinates":[-78.741866,42.647542],"type":"Point"}
}