{
  "type": "Feature",
  "properties": {
    "iso:country":"US",
    "sg:address":"7910 13th Ave",
    "sg:city":"Brooklyn",
    "sg:classifiers":[
        {
            "category":"Personal",
            "subcategory":"Massage",
            "type":"Services"
        },
        {
            "category":"Personal",
            "subcategory":"Hair Removal",
            "type":"Services"
        }
    ],
    "sg:phone":"+1 718 833 7728",
    "sg:postcode":"11228",
    "sg:province":"NY",
    "sg:tags":[
        "laser"
    ],
    "sg:website":"www.spavanany.com",
    "wof:name":"Spavana Day Spa & Laser Center",
    "wof:placetype":"venue"
},
  "geometry": {"coordinates":[-74.01028700000001,40.617941],"type":"Point"}
}