{
  "type": "Feature",
  "properties": {
    "addr:full":"150 Enterprise Rd Johnstown NY 12095",
    "addr:housenumber":"150",
    "addr:postcode":"12095",
    "addr:street":"Enterprise Rd",
    "iso:country":"US",
    "sg:address":"150 Enterprise Rd",
    "sg:city":"Johnstown",
    "sg:classifiers":[
        {
            "category":"Wholesale",
            "subcategory":"Chemicals & Plastics",
            "type":"Manufacturing & Wholesale Goods"
        }
    ],
    "sg:phone":"+1 518 861 8375",
    "sg:postcode":"12095",
    "sg:province":"NY",
    "sg:website":"www.univarusa.com",
    "wof:name":"Univar USA",
    "wof:placetype":"venue"
},
  "geometry": {"coordinates":[-74.396652,42.988813],"type":"Point"}
}