{
  "type": "Feature",
  "properties": {
    "iso:country":"US",
    "sg:address":"197 Richmond Ave",
    "sg:city":"Amityville",
    "sg:classifiers":[
        {
            "category":"Real Estate",
            "subcategory":"Real Estate Agent",
            "type":"Services"
        }
    ],
    "sg:phone":"+1 631 598 0375",
    "sg:postcode":"11701",
    "sg:province":"NY",
    "wof:name":"Mp Paladino Realty Inc",
    "wof:placetype":"venue"
},
  "geometry": {"coordinates":[-73.41914,40.66371],"type":"Point"}
}