{
  "type": "Feature",
  "properties": {
    "addr:full":"666 10th St Brooklyn NY 11215",
    "addr:housenumber":"666",
    "addr:postcode":"11215",
    "addr:street":"10Th St",
    "iso:country":"US",
    "sg:address":"666 10th St",
    "sg:city":"Brooklyn",
    "sg:classifiers":[
        {
            "category":"Professional",
            "subcategory":"Computer Services",
            "type":"Services"
        }
    ],
    "sg:phone":"+1 718 926 0124",
    "sg:postcode":"11215",
    "sg:province":"NY",
    "sg:tags":[
        "programing",
        "custom"
    ],
    "wof:name":"Red Spark Inc",
    "wof:placetype":"venue"
},
  "geometry": {"coordinates":[-73.978189,40.66446],"type":"Point"}
}