{
  "type": "Feature",
  "properties": {
    "addr:full":"3299 Beltagh Ave Wantagh NY 11793",
    "addr:housenumber":"3299",
    "addr:postcode":"11793",
    "addr:street":"Beltagh Ave",
    "iso:country":"US",
    "sg:address":"3299 Beltagh Ave",
    "sg:city":"Wantagh",
    "sg:classifiers":[
        {
            "category":"Education",
            "subcategory":"School",
            "type":"Public Place"
        }
    ],
    "sg:phone":"+1 516 679 6350",
    "sg:postcode":"11793",
    "sg:province":"NY",
    "wof:name":"Wantagh Middle School",
    "wof:placetype":"venue"
},
  "geometry": {"coordinates":[-73.520375,40.691083],"type":"Point"}
}