{
  "type": "Feature",
  "properties": {
    "addr:full":"6194 US Hwy 209 Kerhonkson NY 12446",
    "addr:housenumber":"6194",
    "addr:postcode":"12446",
    "addr:street":"Us Hwy 209",
    "iso:country":"US",
    "sg:address":"6194 US Hwy 209",
    "sg:city":"Kerhonkson",
    "sg:classifiers":[
        {
            "category":"Health Services",
            "subcategory":"Chiropractor",
            "type":"Services"
        }
    ],
    "sg:phone":"+1 845 626 8600",
    "sg:postcode":"12446",
    "sg:province":"NY",
    "wof:name":"Holly Elliott DC",
    "wof:placetype":"venue"
},
  "geometry": {"coordinates":[-74.26320200000001,41.78919],"type":"Point"}
}