{
  "type": "Feature",
  "properties": {
    "addr:full":"239 E 14 St New York NY 10003",
    "addr:housenumber":"239;14",
    "addr:postcode":"10003",
    "addr:street":"E",
    "iso:country":"US",
    "sg:address":"239 E 14 St",
    "sg:city":"New York",
    "sg:classifiers":[
        {
            "category":"Retail",
            "subcategory":"Laundry & Dry Cleaning",
            "type":"Services"
        }
    ],
    "sg:phone":"+1 212 358 1914",
    "sg:postcode":"10003",
    "sg:province":"NY",
    "sg:tags":[
        "power"
    ],
    "wof:name":"Prime Time Cleaners & Ldrers",
    "wof:placetype":"venue"
},
  "geometry": {"coordinates":[-73.985562,40.732779],"type":"Point"}
}