{
  "type": "Feature",
  "properties": {
    "iso:country":"US",
    "sg:address":"4706 Oak Orchard Rd",
    "sg:city":"Albion",
    "sg:classifiers":[
        {
            "category":"Organizations",
            "subcategory":"Religious Organization",
            "type":"Services"
        }
    ],
    "sg:phone":"+1 585 589 9639",
    "sg:postcode":"14411",
    "sg:province":"NY",
    "sg:tags":[
        "church"
    ],
    "wof:name":"Barre Center Presbyterian Chr",
    "wof:placetype":"venue"
},
  "geometry": {"coordinates":[-78.194389,43.184945],"type":"Point"}
}