{
  "type": "Feature",
  "properties": {
    "addr:full":"245 W 17th Street New York NY 10011",
    "addr:housenumber":"245",
    "addr:postcode":"10011",
    "addr:street":"W 17Th Street",
    "iso:country":"US",
    "sg:address":"245 W 17th Street",
    "sg:city":"New York",
    "sg:classifiers":[
        {
            "category":"Communications",
            "subcategory":"Newspaper",
            "type":"Services"
        }
    ],
    "sg:phone":"+1 212 242 8100",
    "sg:postcode":"10011",
    "sg:province":"NY",
    "sg:tags":[
        "print",
        "medium"
    ],
    "sg:website":"www.out.com",
    "wof:name":"Out Magazine",
    "wof:placetype":"venue"
},
  "geometry": {"coordinates":[-73.99965,40.74143],"type":"Point"}
}