{
  "type": "Feature",
  "properties": {
    "iso:country":"US",
    "sg:address":"2886 3rd Ave",
    "sg:city":"Bronx",
    "sg:classifiers":[
        {
            "category":"Shopping",
            "subcategory":"Clothing, Apparel, & Fashions",
            "type":"Retail Goods"
        }
    ],
    "sg:phone":"+1 718 402 9655",
    "sg:postcode":"10455",
    "sg:province":"NY",
    "sg:tags":[
        "item",
        "boutique"
    ],
    "wof:name":"Revolution Boutique",
    "wof:placetype":"venue"
},
  "geometry": {"coordinates":[-73.916028,40.817056],"type":"Point"}
}