{
  "type": "Feature",
  "properties": {
    "addr:full":"527 S Ocean Ave Freeport NY 11520",
    "addr:housenumber":"527",
    "addr:postcode":"11520",
    "addr:street":"S Ocean Ave",
    "iso:country":"US",
    "sg:address":"527 S Ocean Ave",
    "sg:city":"Freeport",
    "sg:classifiers":[
        {
            "category":"Professional",
            "subcategory":"Management & Consulting",
            "type":"Services"
        }
    ],
    "sg:phone":"+1 516 379 1980",
    "sg:postcode":"11520",
    "sg:province":"NY",
    "sg:tags":[
        "computer",
        "custom"
    ],
    "wof:name":"Applied Data Corp",
    "wof:placetype":"venue"
},
  "geometry": {"coordinates":[-73.583657,40.638269],"type":"Point"}
}