{
  "type": "Feature",
  "properties": {
    "addr:full":"640 Cary Ave Staten Island NY 10310",
    "addr:housenumber":"640",
    "addr:postcode":"10310",
    "addr:street":"Cary Ave",
    "iso:country":"US",
    "sg:address":"640 Cary Ave",
    "sg:city":"Staten Island",
    "sg:classifiers":[
        {
            "category":"Wholesale",
            "subcategory":"Machinery & Supplies",
            "type":"Manufacturing & Wholesale Goods"
        }
    ],
    "sg:phone":"+1 718 815 5161",
    "sg:postcode":"10310",
    "sg:province":"NY",
    "sg:tags":[
        "contractor"
    ],
    "sg:website":"www.skcabling.com",
    "wof:name":"S K Cabling Systems",
    "wof:placetype":"venue"
},
  "geometry": {"coordinates":[-74.12374,40.631777],"type":"Point"}
}