{
  "type": "Feature",
  "properties": {
    "iso:country":"US",
    "sg:address":"13 Paul Dr",
    "sg:city":"Binghamton",
    "sg:classifiers":[
        {
            "category":"Wholesale",
            "subcategory":"Machinery & Supplies",
            "type":"Manufacturing & Wholesale Goods"
        }
    ],
    "sg:phone":"+1 607 648 3261",
    "sg:postcode":"13901",
    "sg:province":"NY",
    "sg:tags":[
        "packaging",
        "sales"
    ],
    "wof:name":"Dynamic Packg Solutions LLC",
    "wof:placetype":"venue"
},
  "geometry": {"coordinates":[-75.83515800000001,42.183146],"type":"Point"}
}