{
  "type": "Feature",
  "properties": {
    "iso:country":"US",
    "sg:address":"878 Conklin Rd",
    "sg:city":"Binghamton",
    "sg:classifiers":[
        {
            "category":"Retail",
            "subcategory":"Auto Repair",
            "type":"Services"
        }
    ],
    "sg:phone":"+1 607 722 3338",
    "sg:postcode":"13903",
    "sg:province":"NY",
    "sg:tags":[
        "body",
        "automobile",
        "painting"
    ],
    "wof:name":"Yager's Body Shop",
    "wof:placetype":"venue"
},
  "geometry": {"coordinates":[-75.835587,42.092642],"type":"Point"}
}