{
  "type": "Feature",
  "properties": {
    "addr:full":"3231 White Plains Rd Bronx NY 10467",
    "addr:housenumber":"3231",
    "addr:postcode":"10467",
    "addr:street":"White Plains Rd",
    "iso:country":"US",
    "sg:address":"3231 White Plains Rd",
    "sg:city":"Bronx",
    "sg:classifiers":[
        {
            "category":"Retail",
            "subcategory":"Auto Rental",
            "type":"Services"
        }
    ],
    "sg:phone":"+1 718 655 9844",
    "sg:postcode":"10467",
    "sg:province":"NY",
    "sg:tags":[
        "automobile",
        "leasing"
    ],
    "wof:name":"Lukes Motor Svc",
    "wof:placetype":"venue"
},
  "geometry": {"coordinates":[-73.867186,40.872673],"type":"Point"}
}