{
  "type": "Feature",
  "properties": {
    "addr:full":"64 Reade St Fl 2 New York NY 10007",
    "addr:housenumber":"64;2",
    "addr:postcode":"10007",
    "addr:street":"Reade St",
    "iso:country":"US",
    "sg:address":"64 Reade St Fl 2",
    "sg:city":"New York",
    "sg:classifiers":[
        {
            "category":"Shopping",
            "subcategory":"Jewelry",
            "type":"Retail Goods"
        }
    ],
    "sg:phone":"+1 212 227 3310",
    "sg:postcode":"10007",
    "sg:province":"NY",
    "sg:tags":[
        "watch"
    ],
    "wof:name":"National Time & Signal Corp",
    "wof:placetype":"venue"
},
  "geometry": {"coordinates":[-74.780962,40.715249],"type":"Point"}
}