{
  "type": "Feature",
  "properties": {
    "addr:full":"399 William Floyd Pkwy #1282 Shirley NY 11967",
    "addr:housenumber":"399",
    "addr:postcode":"11967",
    "addr:street":"William Floyd Pkwy # 1282",
    "iso:country":"US",
    "sg:address":"399 William Floyd Pkwy #1282",
    "sg:city":"Shirley",
    "sg:classifiers":[
        {
            "category":"Home & Garden",
            "subcategory":"Hardware",
            "type":"Retail Goods"
        }
    ],
    "sg:postcode":"11967",
    "sg:province":"NY",
    "sg:tags":[
        "store"
    ],
    "wof:name":"The Home Depot",
    "wof:placetype":"venue"
},
  "geometry": {"coordinates":[-72.85252300000001,40.768097],"type":"Point"}
}