{
  "type": "Feature",
  "properties": {
    "iso:country":"US",
    "sg:address":"34 street 6 Ave",
    "sg:city":"New York",
    "sg:classifiers":[
        {
            "category":"Personal",
            "subcategory":"Massage",
            "type":"Services"
        }
    ],
    "sg:phone":"+1 718 915 0655",
    "sg:postcode":"10001",
    "sg:province":"NY",
    "wof:name":"Traditional Thai Massage",
    "wof:placetype":"venue"
},
  "geometry": {"coordinates":[-74.005168,40.72011],"type":"Point"}
}