{
  "type": "Feature",
  "properties": {
    "addr:full":"2676 Pitkin Ave Brooklyn NY 11208",
    "addr:housenumber":"2676",
    "addr:postcode":"11208",
    "addr:street":"Pitkin Ave",
    "iso:country":"US",
    "sg:address":"2676 Pitkin Ave",
    "sg:city":"Brooklyn",
    "sg:classifiers":[
        {
            "category":"Wholesale",
            "subcategory":"Groceries",
            "type":"Manufacturing & Wholesale Goods"
        }
    ],
    "sg:phone":"+1 718 827 6233",
    "sg:postcode":"11208",
    "sg:province":"NY",
    "wof:name":"Sonar Bangle Grocery",
    "wof:placetype":"venue"
},
  "geometry": {"coordinates":[-73.87309999999999,40.675098],"type":"Point"}
}