{
  "type": "Feature",
  "properties": {
    "iso:country":"US",
    "sg:address":"315 Rockaway Tpke",
    "sg:city":"Lawrence",
    "sg:classifiers":[
        {
            "category":"Food & Beverages",
            "subcategory":"Groceries & Convenience Stores",
            "type":"Retail Goods"
        }
    ],
    "sg:phone":"+1 516 371 6213",
    "sg:postcode":"11559",
    "sg:province":"NY",
    "wof:name":"Turnpike Smokeshop Inc",
    "wof:placetype":"venue"
},
  "geometry": {"coordinates":[-73.73380299999999,40.621601],"type":"Point"}
}