{
  "type": "Feature",
  "properties": {
    "addr:full":"108 Northampton Rd Amsterdam NY 12010",
    "addr:housenumber":"108",
    "addr:postcode":"12010",
    "addr:street":"Northampton Rd",
    "iso:country":"US",
    "sg:address":"108 Northampton Rd",
    "sg:city":"Amsterdam",
    "sg:classifiers":[
        {
            "category":"Professional",
            "subcategory":"Business Services",
            "type":"Services"
        }
    ],
    "sg:phone":"+1 518 627 0631",
    "sg:postcode":"12010",
    "sg:province":"NY",
    "wof:name":"Executive Accomodations",
    "wof:placetype":"venue"
},
  "geometry": {"coordinates":[-74.185743,42.955799],"type":"Point"}
}