{
  "type": "Feature",
  "properties": {
    "iso:country":"US",
    "sg:address":"90 Depot Pl",
    "sg:city":"Nyack",
    "sg:classifiers":[
        {
            "category":"Government",
            "subcategory":"Fire Station",
            "type":"Public Place"
        }
    ],
    "sg:phone":"+1 845 358 9751",
    "sg:postcode":"10960",
    "sg:province":"NY",
    "sg:tags":[
        "department",
        "protection"
    ],
    "wof:name":"Orangetown Fire Co 1",
    "wof:placetype":"venue"
},
  "geometry": {"coordinates":[-73.92124099999999,41.086247],"type":"Point"}
}