{
  "type": "Feature",
  "properties": {
    "iso:country":"US",
    "sg:address":"349 Stone Hill Rd",
    "sg:city":"Pound Ridge",
    "sg:classifiers":[
        {
            "category":"Professional",
            "subcategory":"Research",
            "type":"Services"
        }
    ],
    "sg:phone":"+1 914 764 8337",
    "sg:postcode":"10576",
    "sg:province":"NY",
    "sg:tags":[
        "organization",
        "noncommercial"
    ],
    "wof:name":"Prince Foundation",
    "wof:placetype":"venue"
},
  "geometry": {"coordinates":[-73.588722,41.220393],"type":"Point"}
}