{
  "type": "Feature",
  "properties": {
    "addr:full":"4790 Berry Rd Fredonia NY 14063",
    "addr:housenumber":"4790",
    "addr:postcode":"14063",
    "addr:street":"Berry Rd",
    "iso:country":"US",
    "sg:address":"4790 Berry Rd",
    "sg:city":"Fredonia",
    "sg:classifiers":[
        {
            "category":"Personal",
            "type":"Services"
        }
    ],
    "sg:phone":"+1   ",
    "sg:postcode":"14063",
    "sg:province":"NY",
    "wof:name":"Sellaris Tanning Salon",
    "wof:placetype":"venue"
},
  "geometry": {"coordinates":[-79.36926200000001,42.435255],"type":"Point"}
}