{
  "type": "Feature",
  "properties": {
    "addr:full":"305 E 72 St New York NY 10021",
    "addr:housenumber":"305;72",
    "addr:postcode":"10021",
    "addr:street":"E;St",
    "iso:country":"US",
    "sg:address":"305 E 72 St",
    "sg:city":"New York",
    "sg:classifiers":[
        {
            "category":"Professional",
            "subcategory":"Business Services",
            "type":"Services"
        }
    ],
    "sg:phone":"+1 212 472 7751",
    "sg:postcode":"10021",
    "sg:province":"NY",
    "sg:tags":[
        "planning",
        "event"
    ],
    "wof:name":"In Any Event NY LLC",
    "wof:placetype":"venue"
},
  "geometry": {"coordinates":[-73.956056,40.767922],"type":"Point"}
}