{
  "type": "Feature",
  "properties": {
    "iso:country":"US",
    "sg:address":"545 Columbus Ave",
    "sg:city":"Manhattan",
    "sg:classifiers":[
        {
            "category":"Retail",
            "subcategory":"Laundry & Dry Cleaning",
            "type":"Services"
        }
    ],
    "sg:phone":"+1 212 496 6700",
    "sg:postcode":"10024",
    "sg:province":"NY",
    "wof:name":"Nordic Cleaners",
    "wof:placetype":"venue"
},
  "geometry": {"coordinates":[-73.972004,40.786677],"type":"Point"}
}