{
  "type": "Feature",
  "properties": {
    "addr:full":"450 Kimber Rd Syracuse NY 13224",
    "addr:housenumber":"450",
    "addr:postcode":"13224",
    "addr:street":"Kimber Rd",
    "iso:country":"US",
    "sg:address":"450 Kimber Rd",
    "sg:city":"Syracuse",
    "sg:classifiers":[
        {
            "category":"Organizations",
            "subcategory":"Religious Organization",
            "type":"Services"
        }
    ],
    "sg:phone":"+1 315 445 0002",
    "sg:postcode":"13224",
    "sg:province":"NY",
    "sg:tags":[
        "synagogue"
    ],
    "wof:name":"Temple Adath Yeshurun",
    "wof:placetype":"venue"
},
  "geometry": {"coordinates":[-76.093227,43.035136],"type":"Point"}
}