{
  "type": "Feature",
  "properties": {
    "addr:full":"928 Co Rte 25 Oswego NY 13126",
    "addr:housenumber":"928",
    "addr:postcode":"13126",
    "addr:street":"Co Rte 25",
    "iso:country":"US",
    "sg:address":"928 Co Rte 25",
    "sg:city":"Oswego",
    "sg:classifiers":[
        {
            "category":"Manufacturing",
            "subcategory":"Wood Products",
            "type":"Manufacturing & Wholesale Goods"
        }
    ],
    "sg:phone":"+1   ",
    "sg:postcode":"13126",
    "sg:province":"NY",
    "sg:tags":[
        "mfg"
    ],
    "wof:name":"Signed & Sealed",
    "wof:placetype":"venue"
},
  "geometry": {"coordinates":[-76.510003,43.429153],"type":"Point"}
}