{
  "type": "Feature",
  "properties": {
    "addr:full":"8 Cold Spring Rd Syosset NY 11791",
    "addr:housenumber":"8",
    "addr:postcode":"11791",
    "addr:street":"Cold Spring Rd",
    "iso:country":"US",
    "sg:address":"8 Cold Spring Rd",
    "sg:city":"Syosset",
    "sg:classifiers":[
        {
            "category":"Restaurant",
            "type":"Food & Drink"
        }
    ],
    "sg:phone":"+1 516 677 0031",
    "sg:postcode":"11791",
    "sg:province":"NY",
    "sg:tags":[
        "pizza"
    ],
    "wof:name":"Cardinali Uno Of Syosset",
    "wof:placetype":"venue"
},
  "geometry": {"coordinates":[-73.50118000000001,40.826104],"type":"Point"}
}