{
  "type": "Feature",
  "properties": {
    "addr:full":"4605 Church Avenue Brooklyn NY 11203",
    "addr:housenumber":"4605",
    "addr:postcode":"11203",
    "addr:street":"Church Avenue",
    "iso:country":"US",
    "sg:address":"4605 Church Avenue",
    "sg:city":"Brooklyn",
    "sg:classifiers":[
        {
            "category":"Restaurant",
            "type":"Food & Drink"
        }
    ],
    "sg:phone":"+1 718 826 1953",
    "sg:postcode":"11203",
    "sg:province":"NY",
    "wof:name":"De Shan Restaurant",
    "wof:placetype":"venue"
},
  "geometry": {"coordinates":[-73.93422099999999,40.651557],"type":"Point"}
}