{
  "type": "Feature",
  "properties": {
    "iso:country":"US",
    "sg:address":"609 Vine St",
    "sg:city":"Liverpool",
    "sg:classifiers":[
        {
            "category":"Health Services",
            "subcategory":"Chiropractor",
            "type":"Services"
        }
    ],
    "sg:phone":"+1 315 451 2225",
    "sg:postcode":"13088",
    "sg:province":"NY",
    "wof:name":"Walter F Kimball DC",
    "wof:placetype":"venue"
},
  "geometry": {"coordinates":[-76.20432,43.105157],"type":"Point"}
}