{
  "type": "Feature",
  "properties": {
    "addr:full":"23 W 10th St New York NY 10011",
    "addr:housenumber":"23",
    "addr:postcode":"10011",
    "addr:street":"W 10Th St",
    "iso:country":"US",
    "sg:address":"23 W 10th St",
    "sg:city":"New York",
    "sg:classifiers":[
        {
            "category":"Health Services",
            "subcategory":"Clinic",
            "type":"Services"
        }
    ],
    "sg:phone":"+1 212 475 8899",
    "sg:postcode":"10011",
    "sg:province":"NY",
    "sg:tags":[
        "counseling",
        "mental"
    ],
    "wof:name":"Smoker's Consultation Service",
    "wof:placetype":"venue"
},
  "geometry": {"coordinates":[-73.99630000000001,40.7337],"type":"Point"}
}