{
  "type": "Feature",
  "properties": {
    "addr:full":"1100 Altamont Ave Schenectady NY 12303",
    "addr:housenumber":"1100",
    "addr:postcode":"12303",
    "addr:street":"Altamont Ave",
    "iso:country":"US",
    "sg:address":"1100 Altamont Ave",
    "sg:city":"Schenectady",
    "sg:classifiers":[
        {
            "category":"Wholesale",
            "subcategory":"Computers",
            "type":"Manufacturing & Wholesale Goods"
        },
        {
            "category":"Manufacturing",
            "subcategory":"Tools & Machinery",
            "type":"Manufacturing & Wholesale Goods"
        }
    ],
    "sg:phone":"+1 518 377 3377",
    "sg:postcode":"12303",
    "sg:province":"NY",
    "sg:tags":[
        "home",
        "suppl",
        "mfg"
    ],
    "sg:website":"www.danjen.com",
    "wof:name":"Danjen Computers",
    "wof:placetype":"venue"
},
  "geometry": {"coordinates":[-73.93991699999999,42.788173],"type":"Point"}
}