{
  "type": "Feature",
  "properties": {
    "iso:country":"US",
    "sg:address":"310 E 112th St",
    "sg:city":"New York",
    "sg:classifiers":[
        {
            "category":"Personal",
            "subcategory":"Beauty Salon",
            "type":"Services"
        }
    ],
    "sg:phone":"+1 212 360 6933",
    "sg:postcode":"10029",
    "sg:province":"NY",
    "sg:tags":[
        "shop"
    ],
    "wof:name":"Geminis Unisex",
    "wof:placetype":"venue"
},
  "geometry": {"coordinates":[-73.937381,40.793452],"type":"Point"}
}