{
  "type": "Feature",
  "properties": {
    "addr:full":"556 Central Park Ave Scarsdale NY 10583",
    "addr:housenumber":"556",
    "addr:postcode":"10583",
    "addr:street":"Central Park Ave",
    "iso:country":"US",
    "sg:address":"556 Central Park Ave",
    "sg:city":"Scarsdale",
    "sg:classifiers":[
        {
            "category":"Restaurant",
            "type":"Food & Drink"
        }
    ],
    "sg:menulink":"http://www.allmenus.com/ny/greenburgh/170056-burger-king/menu/",
    "sg:phone":"+1 914 723 5388",
    "sg:postcode":"10583",
    "sg:province":"NY",
    "sg:tags":[
        "burger",
        "american"
    ],
    "wof:name":"Burger King",
    "wof:placetype":"venue"
},
  "geometry": {"coordinates":[-73.812572,41.004256],"type":"Point"}
}