{
  "type": "Feature",
  "properties": {
    "iso:country":"US",
    "sg:address":"10 Sutton Ter",
    "sg:city":"Jericho",
    "sg:classifiers":[
        {
            "category":"Professional",
            "subcategory":"Business Services",
            "type":"Services"
        }
    ],
    "sg:phone":"+1 516 935 8482",
    "sg:postcode":"11753",
    "sg:province":"NY",
    "sg:tags":[
        "blind",
        "consultant",
        "design",
        "shade",
        "interior",
        "decorator"
    ],
    "wof:name":"Intradeco",
    "wof:placetype":"venue"
},
  "geometry": {"coordinates":[-73.544403,40.780701],"type":"Point"}
}