{
  "type": "Feature",
  "properties": {
    "addr:full":"1249 Coney Island Avenue Brooklyn NY 11230",
    "addr:housenumber":"1249",
    "addr:postcode":"11230",
    "addr:street":"Coney Island Avenue",
    "iso:country":"US",
    "sg:address":"1249 Coney Island Avenue",
    "sg:city":"Brooklyn",
    "sg:classifiers":[
        {
            "category":"Autos & Motor Vehicles",
            "subcategory":"Fuel & Gas Station",
            "type":"Retail Goods"
        }
    ],
    "sg:phone":"+1 917 716 1155",
    "sg:postcode":"11230",
    "sg:province":"NY",
    "sg:website":"nacmiasmobil.com",
    "wof:name":"Nacmias Auto Sales, Service, and Repairs",
    "wof:placetype":"venue"
},
  "geometry": {"coordinates":[-73.965564,40.627185],"type":"Point"}
}