{
  "type": "Feature",
  "properties": {
    "addr:full":"2040 Williamsbridge Rd Bronx NY 10461",
    "addr:housenumber":"2040",
    "addr:postcode":"10461",
    "addr:street":"Williamsbridge Rd",
    "iso:country":"US",
    "sg:address":"2040 Williamsbridge Rd",
    "sg:city":"Bronx",
    "sg:classifiers":[
        {
            "category":"Shopping",
            "type":"Retail Goods"
        },
        {
            "category":"Personal",
            "type":"Services"
        }
    ],
    "sg:phone":"+1 718 597 5380",
    "sg:postcode":"10461",
    "sg:province":"NY",
    "sg:tags":[
        "wedding",
        "supply"
    ],
    "wof:name":"Rome West Custom Tailors",
    "wof:placetype":"venue"
},
  "geometry": {"coordinates":[-73.854995,40.854967],"type":"Point"}
}