{
  "type": "Feature",
  "properties": {
    "iso:country":"US",
    "sg:address":"107 Chatsworth Ave",
    "sg:city":"Larchmont",
    "sg:classifiers":[
        {
            "category":"Autos & Motor Vehicles",
            "subcategory":"Fuel & Gas Station",
            "type":"Retail Goods"
        }
    ],
    "sg:phone":"+1   ",
    "sg:postcode":"10538",
    "sg:province":"NY",
    "sg:tags":[
        "station"
    ],
    "wof:name":"Doms Car Care",
    "wof:placetype":"venue"
},
  "geometry": {"coordinates":[-73.75778800000001,40.932463],"type":"Point"}
}