{
  "type": "Feature",
  "properties": {
    "addr:full":"7979 Victor-Pittsford Rd Victor NY 14564",
    "addr:housenumber":"7979",
    "addr:postcode":"14564",
    "addr:street":"Victor-Pittsford Rd",
    "iso:country":"US",
    "sg:address":"7979 Victor-Pittsford Rd",
    "sg:city":"Victor",
    "sg:classifiers":[
        {
            "category":"Shopping",
            "subcategory":"Clothing, Apparel, & Fashions",
            "type":"Retail Goods"
        }
    ],
    "sg:phone":"+1 585 223 2870",
    "sg:postcode":"14564",
    "sg:province":"NY",
    "sg:tags":[
        "hat"
    ],
    "sg:website":"www.lids.com",
    "wof:name":"Lids",
    "wof:placetype":"venue"
},
  "geometry": {"coordinates":[-77.440434,43.03059],"type":"Point"}
}