{
  "type": "Feature",
  "properties": {
    "addr:full":"11920 Metropolitan Ave Kew Gardens NY 11415",
    "addr:housenumber":"11920",
    "addr:postcode":"11415",
    "addr:street":"Metropolitan Ave",
    "iso:country":"US",
    "sg:address":"11920 Metropolitan Ave",
    "sg:city":"Kew Gardens",
    "sg:classifiers":[
        {
            "category":"Food & Beverages",
            "subcategory":"Groceries & Convenience Stores",
            "type":"Retail Goods"
        }
    ],
    "sg:phone":"+1 718 805 0347",
    "sg:postcode":"11415",
    "sg:province":"NY",
    "wof:name":"Alba's Grocery",
    "wof:placetype":"venue"
},
  "geometry": {"coordinates":[-73.831497,40.705898],"type":"Point"}
}