{
  "type": "Feature",
  "properties": {
    "addr:full":"1642 54th St Brooklyn NY 11204",
    "addr:housenumber":"1642",
    "addr:postcode":"11204",
    "addr:street":"54Th St",
    "iso:country":"US",
    "sg:address":"1642 54th St",
    "sg:city":"Brooklyn",
    "sg:classifiers":[
        {
            "category":"Organizations",
            "subcategory":"Religious Organization",
            "type":"Services"
        }
    ],
    "sg:phone":"+1 718 851 7442",
    "sg:postcode":"11204",
    "sg:province":"NY",
    "sg:tags":[
        "church"
    ],
    "wof:name":"Congregation Kav Chaim",
    "wof:placetype":"venue"
},
  "geometry": {"coordinates":[-73.986813,40.627329],"type":"Point"}
}