{
  "type": "Feature",
  "properties": {
    "iso:country":"US",
    "sg:address":"857 Genesee St",
    "sg:city":"Buffalo",
    "sg:classifiers":[
        {
            "category":"Personal",
            "subcategory":"Barber",
            "type":"Services"
        }
    ],
    "sg:phone":"+1 716 896 9623",
    "sg:postcode":"14211",
    "sg:province":"NY",
    "wof:name":"Delta Carrier",
    "wof:placetype":"venue"
},
  "geometry": {"coordinates":[-78.845263,42.899657],"type":"Point"}
}