{
  "type": "Feature",
  "properties": {
    "addr:full":"23 Albany Ave Nassau NY 12123",
    "addr:housenumber":"23",
    "addr:postcode":"12123",
    "addr:street":"Albany Ave",
    "iso:country":"US",
    "sg:address":"23 Albany Ave",
    "sg:city":"Nassau",
    "sg:classifiers":[
        {
            "category":"Manufacturing",
            "subcategory":"Jewelry",
            "type":"Manufacturing & Wholesale Goods"
        }
    ],
    "sg:phone":"+1   ",
    "sg:postcode":"12123",
    "sg:province":"NY",
    "sg:tags":[
        "costume",
        "mfg"
    ],
    "wof:name":"Bumblebead Designs",
    "wof:placetype":"venue"
},
  "geometry": {"coordinates":[-73.61385799999999,42.516783],"type":"Point"}
}