{
  "type": "Feature",
  "properties": {
    "addr:full":"Flushing Meadows Corona Park 125-40 Roosevelt Avenue Flushing NY 11368",
    "addr:housenumber":"125-40",
    "addr:postcode":"11368",
    "addr:street":"Roosevelt Avenue",
    "iso:country":"US",
    "sg:address":"Flushing Meadows Corona Park 125-40 Roosevelt Avenue",
    "sg:city":"Flushing",
    "sg:classifiers":[
        {
            "category":"Sports & Exercise",
            "subcategory":"Ice Rink",
            "type":"Entertainment"
        }
    ],
    "sg:phone":"+1 718 760 9001",
    "sg:postcode":"11368",
    "sg:province":"NY",
    "sg:tags":[
        "skating"
    ],
    "sg:website":"www.WorldIce.com",
    "wof:name":"World Ice Arena",
    "wof:placetype":"venue"
},
  "geometry": {"coordinates":[-73.841408,40.755908],"type":"Point"}
}