{
  "type": "Feature",
  "properties": {
    "iso:country":"US",
    "sg:address":"77 Bleecker Street",
    "sg:city":"New York",
    "sg:classifiers":[
        {
            "category":"Health Services",
            "subcategory":"Dentist",
            "type":"Services"
        }
    ],
    "sg:phone":"+1 212 358 0172",
    "sg:postcode":"10012",
    "sg:province":"NY",
    "wof:name":"Adler Robert",
    "wof:placetype":"venue"
},
  "geometry": {"coordinates":[-73.996022,40.726614],"type":"Point"}
}