{
  "type": "Feature",
  "properties": {
    "iso:country":"US",
    "sg:address":"456 W Saugerties Rd",
    "sg:city":"Saugerties",
    "sg:classifiers":[
        {
            "category":"Building & Trades",
            "subcategory":"Construction",
            "type":"Services"
        }
    ],
    "sg:phone":"+1 845 246 1609",
    "sg:postcode":"12477",
    "sg:province":"NY",
    "sg:tags":[
        "hanging",
        "contractor"
    ],
    "wof:name":"H L Finishing",
    "wof:placetype":"venue"
},
  "geometry": {"coordinates":[-74.049537,42.113096],"type":"Point"}
}