{
  "type": "Feature",
  "properties": {
    "iso:country":"US",
    "sg:address":"2318 Falconer-Frewsburg Rd",
    "sg:city":"Jamestown",
    "sg:classifiers":[
        {
            "category":"Government",
            "subcategory":"Fire Station",
            "type":"Public Place"
        }
    ],
    "sg:phone":"+1 716 484 0890",
    "sg:postcode":"14701",
    "sg:province":"NY",
    "sg:tags":[
        "protection"
    ],
    "wof:name":"Kantone Fire Department",
    "wof:placetype":"venue"
},
  "geometry": {"coordinates":[-79.159682,42.098768],"type":"Point"}
}