{
  "type": "Feature",
  "properties": {
    "iso:country":"US",
    "sg:address":"22 Park Pl",
    "sg:city":"Bronxville",
    "sg:classifiers":[
        {
            "category":"Shopping",
            "subcategory":"Clothing, Apparel, & Fashions",
            "type":"Retail Goods"
        }
    ],
    "sg:phone":"+1 914 337 4070",
    "sg:postcode":"10708",
    "sg:province":"NY",
    "sg:tags":[
        "tuxedo"
    ],
    "wof:name":"Duleto Formal Wear",
    "wof:placetype":"venue"
},
  "geometry": {"coordinates":[-73.83441999999999,40.939768],"type":"Point"}
}