{
  "type": "Feature",
  "properties": {
    "iso:country":"US",
    "sg:address":"20 Terry St",
    "sg:city":"Hicksville",
    "sg:classifiers":[
        {
            "category":"Home & Garden",
            "subcategory":"Furniture",
            "type":"Retail Goods"
        }
    ],
    "sg:phone":"+1 516 470 1593",
    "sg:postcode":"11801",
    "sg:province":"NY",
    "sg:tags":[
        "store"
    ],
    "wof:name":"M & J Furniture",
    "wof:placetype":"venue"
},
  "geometry": {"coordinates":[-73.517084,40.749768],"type":"Point"}
}