{
  "type": "Feature",
  "properties": {
    "iso:country":"US",
    "sg:address":"42 W 48th Street Suite 1702",
    "sg:city":"New York",
    "sg:classifiers":[
        {
            "category":"Organizations",
            "subcategory":"Non-profit Organization",
            "type":"Services"
        }
    ],
    "sg:phone":"+1 212 575 3020",
    "sg:postcode":"10036",
    "sg:province":"NY",
    "sg:tags":[
        "service/non-profit",
        "community"
    ],
    "wof:name":"Tanzanite Foundation",
    "wof:placetype":"venue"
},
  "geometry": {"coordinates":[-73.97988100000001,40.758016],"type":"Point"}
}