{
  "type": "Feature",
  "properties": {
    "iso:country":"US",
    "sg:address":"6657 Erie Rd",
    "sg:city":"Derby",
    "sg:classifiers":[
        {
            "category":"Social Services",
            "type":"Services"
        }
    ],
    "sg:phone":"+1 716 562 7001",
    "sg:postcode":"14047",
    "sg:province":"NY",
    "wof:name":"Hope Nursing Company Pc",
    "wof:placetype":"venue"
},
  "geometry": {"coordinates":[-78.96848,42.706583],"type":"Point"}
}