{
  "type": "Feature",
  "properties": {
    "addr:full":"239 S Elmwood Ave Buffalo NY 14201",
    "addr:housenumber":"239",
    "addr:postcode":"14201",
    "addr:street":"S Elmwood Ave",
    "iso:country":"US",
    "sg:address":"239 S Elmwood Ave",
    "sg:city":"Buffalo",
    "sg:classifiers":[
        {
            "category":"Food & Beverages",
            "subcategory":"Groceries & Convenience Stores",
            "type":"Retail Goods"
        }
    ],
    "sg:phone":"+1 716 852 4611",
    "sg:postcode":"14201",
    "sg:province":"NY",
    "wof:name":"Best Mart",
    "wof:placetype":"venue"
},
  "geometry": {"coordinates":[-78.87840300000001,42.891399],"type":"Point"}
}