{
  "type": "Feature",
  "properties": {
    "iso:country":"US",
    "sg:address":"1684 Pitkin Ave",
    "sg:city":"Brooklyn",
    "sg:classifiers":[
        {
            "category":"Shopping",
            "subcategory":"Computers & Home Electronics",
            "type":"Retail Goods"
        }
    ],
    "sg:phone":"+1 718 495 2619",
    "sg:postcode":"11212",
    "sg:province":"NY",
    "sg:tags":[
        "equipment",
        "electronic",
        "supply"
    ],
    "wof:name":"Big Daddy Electronics",
    "wof:placetype":"venue"
},
  "geometry": {"coordinates":[-73.91117199999999,40.669524],"type":"Point"}
}