{
  "type": "Feature",
  "properties": {
    "addr:full":"1175 W Broadway Hewlett NY 11557",
    "addr:housenumber":"1175",
    "addr:postcode":"11557",
    "addr:street":"W Broadway",
    "iso:country":"US",
    "sg:address":"1175 W Broadway",
    "sg:city":"Hewlett",
    "sg:classifiers":[
        {
            "category":"Health Services",
            "subcategory":"Doctor",
            "type":"Services"
        }
    ],
    "sg:phone":"+1 516 569 1777",
    "sg:postcode":"11557",
    "sg:province":"NY",
    "sg:tags":[
        "dentist"
    ],
    "wof:name":"Weinstein & Abel",
    "wof:placetype":"venue"
},
  "geometry": {"coordinates":[-73.705252,40.638008],"type":"Point"}
}