{
  "type": "Feature",
  "properties": {
    "addr:full":"37 Crescent St Brooklyn NY 11208",
    "addr:housenumber":"37",
    "addr:postcode":"11208",
    "addr:street":"Crescent St",
    "iso:country":"US",
    "sg:address":"37 Crescent St",
    "sg:city":"Brooklyn",
    "sg:classifiers":[
        {
            "category":"Autos & Motor Vehicles",
            "subcategory":"Fuel & Gas Station",
            "type":"Retail Goods"
        },
        {
            "category":"Retail",
            "subcategory":"Auto Repair",
            "type":"Services"
        }
    ],
    "sg:phone":"+1 718 235 3085",
    "sg:postcode":"11208",
    "sg:province":"NY",
    "wof:name":"Fixed Right Auto",
    "wof:placetype":"venue"
},
  "geometry": {"coordinates":[-73.873441,40.688385],"type":"Point"}
}