{
  "type": "Feature",
  "properties": {
    "addr:full":"11 Old Westfall Dr Rochester NY 14625",
    "addr:housenumber":"11",
    "addr:postcode":"14625",
    "addr:street":"Old Westfall Dr",
    "iso:country":"US",
    "sg:address":"11 Old Westfall Dr",
    "sg:city":"Rochester",
    "sg:classifiers":[
        {
            "category":"Professional",
            "subcategory":"Management & Consulting",
            "type":"Services"
        }
    ],
    "sg:phone":"+1 585 288 5180",
    "sg:postcode":"14625",
    "sg:province":"NY",
    "sg:tags":[
        "consultant",
        "business"
    ],
    "sg:website":"www.qualitypursuit.com",
    "wof:name":"Quality Pursuit",
    "wof:placetype":"venue"
},
  "geometry": {"coordinates":[-77.52248299999999,43.171334],"type":"Point"}
}