{
  "type": "Feature",
  "properties": {
    "iso:country":"US",
    "sg:address":"7751 Treadmill Cir",
    "sg:city":"Liverpool",
    "sg:classifiers":[
        {
            "category":"Professional",
            "subcategory":"Management & Consulting",
            "type":"Services"
        }
    ],
    "sg:phone":"+1   ",
    "sg:postcode":"13090",
    "sg:province":"NY",
    "sg:tags":[
        "business"
    ],
    "wof:name":"Idea Man / Holistic Health",
    "wof:placetype":"venue"
},
  "geometry": {"coordinates":[-76.20794600000001,43.145983],"type":"Point"}
}