{
  "type": "Feature",
  "properties": {
    "iso:country":"US",
    "sg:address":"1493 Hylan Boulevard",
    "sg:city":"Staten Island",
    "sg:classifiers":[
        {
            "category":"Real Estate",
            "subcategory":"Real Estate Services",
            "type":"Services"
        }
    ],
    "sg:phone":"+1 718 835 6300",
    "sg:postcode":"10305",
    "sg:province":"NY",
    "sg:website":"www.fillmore.com",
    "wof:name":"Fillmore Real Estate",
    "wof:placetype":"venue"
},
  "geometry": {"coordinates":[-74.074816,40.601848],"type":"Point"}
}