{
  "type": "Feature",
  "properties": {
    "iso:country":"US",
    "sg:address":"1051 59th Street",
    "sg:city":"Brooklyn",
    "sg:classifiers":[
        {
            "category":"Education",
            "subcategory":"School",
            "type":"Public Place"
        }
    ],
    "sg:phone":"+1 718 438 9275",
    "sg:postcode":"11219",
    "sg:province":"NY",
    "sg:tags":[
        "high",
        "middle",
        "elementary"
    ],
    "wof:name":"Bais Simcha Pre-School",
    "wof:placetype":"venue"
},
  "geometry": {"coordinates":[-74.003176,40.632727],"type":"Point"}
}