{
  "type": "Feature",
  "properties": {
    "addr:full":"957 2nd Ave Manhattan NY 10022",
    "addr:housenumber":"957",
    "addr:postcode":"10022",
    "addr:street":"2Nd Ave",
    "iso:country":"US",
    "sg:address":"957 2nd Ave",
    "sg:city":"Manhattan",
    "sg:classifiers":[
        {
            "category":"Restaurant",
            "type":"Food & Drink"
        }
    ],
    "sg:postcode":"10022",
    "sg:province":"NY",
    "sg:tags":[
        "korean"
    ],
    "sg:website":"www.bonchonmidtown.com",
    "wof:name":"BonChon Chicken",
    "wof:placetype":"venue"
},
  "geometry": {"coordinates":[-73.968486,40.75543],"type":"Point"}
}