{
  "type": "Feature",
  "properties": {
    "addr:full":"1975 Hylan Boulevard Staten Island NY 10306",
    "addr:housenumber":"1975",
    "addr:postcode":"10306",
    "addr:street":"Hylan Boulevard",
    "iso:country":"US",
    "sg:address":"1975 Hylan Boulevard",
    "sg:city":"Staten Island",
    "sg:classifiers":[
        {
            "category":"Health Services",
            "subcategory":"Doctor",
            "type":"Services"
        }
    ],
    "sg:phone":"+1 718 979 6470",
    "sg:postcode":"10306",
    "sg:province":"NY",
    "wof:name":"Harborview Foot Care Dr Gary Sherman",
    "wof:placetype":"venue"
},
  "geometry": {"coordinates":[-74.09786200000001,40.581547],"type":"Point"}
}