{
  "type": "Feature",
  "properties": {
    "addr:full":"135 Prospect Ave Brooklyn NY 11215",
    "addr:housenumber":"135",
    "addr:postcode":"11215",
    "addr:street":"Prospect Ave",
    "iso:country":"US",
    "sg:address":"135 Prospect Ave",
    "sg:city":"Brooklyn",
    "sg:classifiers":[
        {
            "category":"Shopping",
            "type":"Retail Goods"
        }
    ],
    "sg:phone":"+1   ",
    "sg:postcode":"11215",
    "sg:province":"NY",
    "sg:tags":[
        "fire",
        "extinguisher"
    ],
    "wof:name":"Vulcan Extinguishers",
    "wof:placetype":"venue"
},
  "geometry": {"coordinates":[-73.99305,40.665829],"type":"Point"}
}