{
  "type": "Feature",
  "properties": {
    "iso:country":"US",
    "sg:address":"8575 Wheaton Rd",
    "sg:city":"Baldwinsville",
    "sg:classifiers":[
        {
            "category":"Building & Trades",
            "subcategory":"Construction",
            "type":"Services"
        }
    ],
    "sg:phone":"+1 315 638 2808",
    "sg:postcode":"13027",
    "sg:province":"NY",
    "sg:tags":[
        "contractor"
    ],
    "wof:name":"MD Contracting",
    "wof:placetype":"venue"
},
  "geometry": {"coordinates":[-76.437943,43.186062],"type":"Point"}
}