{
  "type": "Feature",
  "properties": {
    "addr:full":"309 5th Ave New York NY 10016",
    "addr:housenumber":"309",
    "addr:postcode":"10016",
    "addr:street":"5Th Ave",
    "iso:country":"US",
    "sg:address":"309 5th Ave",
    "sg:city":"New York",
    "sg:classifiers":[
        {
            "category":"Shopping",
            "subcategory":"Clothing, Apparel, & Fashions",
            "type":"Retail Goods"
        }
    ],
    "sg:phone":"+1 212 213 3202",
    "sg:postcode":"10016",
    "sg:province":"NY",
    "sg:tags":[
        "designer"
    ],
    "wof:name":"Broadway Fashion Line",
    "wof:placetype":"venue"
},
  "geometry": {"coordinates":[-73.985602,40.746808],"type":"Point"}
}