{
  "type": "Feature",
  "properties": {
    "addr:full":"240 Timber Lake Rd Shandaken NY 12480",
    "addr:housenumber":"240",
    "addr:postcode":"12480",
    "addr:street":"Timber Lake Rd",
    "iso:country":"US",
    "sg:address":"240 Timber Lake Rd",
    "sg:city":"Shandaken",
    "sg:classifiers":[
        {
            "category":"Shopping",
            "subcategory":"Gifts & Souvenirs",
            "type":"Retail Goods"
        }
    ],
    "sg:phone":"+1   ",
    "sg:postcode":"12480",
    "sg:province":"NY",
    "wof:name":"Jayro Inc",
    "wof:placetype":"venue"
},
  "geometry": {"coordinates":[-74.34369,42.139313],"type":"Point"}
}