{
  "type": "Feature",
  "properties": {
    "iso:country":"US",
    "sg:address":"120 W Ramapo Rd Ste 11",
    "sg:city":"Garnerville",
    "sg:classifiers":[
        {
            "category":"Restaurant",
            "type":"Food & Drink"
        }
    ],
    "sg:phone":"+1 845 354 2200",
    "sg:postcode":"10923",
    "sg:province":"NY",
    "wof:name":"Sabor Latino Restaurant",
    "wof:placetype":"venue"
},
  "geometry": {"coordinates":[-73.993301,41.202229],"type":"Point"}
}