{
  "type": "Feature",
  "properties": {
    "addr:full":"111 N Buffalo St Elkland NY 16920",
    "addr:housenumber":"111",
    "addr:postcode":"16920",
    "addr:street":"N Buffalo St",
    "iso:country":"US",
    "sg:address":"111 N Buffalo St",
    "sg:city":"Elkland",
    "sg:classifiers":[
        {
            "category":"Food & Beverages",
            "subcategory":"Bakery",
            "type":"Retail Goods"
        }
    ],
    "sg:phone":"+1 814 258 5159",
    "sg:postcode":"16920",
    "sg:province":"NY",
    "sg:tags":[
        "baker"
    ],
    "wof:name":"Shorts Tastee Pastries",
    "wof:placetype":"venue"
},
  "geometry": {"coordinates":[-77.31235100000001,41.988862],"type":"Point"}
}