{
  "type": "Feature",
  "properties": {
    "addr:full":"1721 Crosby Avenue Bronx NY 10461",
    "addr:housenumber":"1721",
    "addr:postcode":"10461",
    "addr:street":"Crosby Avenue",
    "iso:country":"US",
    "sg:address":"1721 Crosby Avenue",
    "sg:city":"Bronx",
    "sg:classifiers":[
        {
            "category":"Shopping",
            "subcategory":"Pharmacy",
            "type":"Retail Goods"
        }
    ],
    "sg:phone":"+1 718 823 9300",
    "sg:postcode":"10461",
    "sg:province":"NY",
    "sg:tags":[
        "drugstore"
    ],
    "sg:website":"www.totalcarepharmacy.com",
    "wof:name":"Total Care Pharmacy",
    "wof:placetype":"venue"
},
  "geometry": {"coordinates":[-73.83169599999999,40.845926],"type":"Point"}
}