{
  "type": "Feature",
  "properties": {
    "iso:country":"US",
    "sg:address":"4 E Carver St",
    "sg:city":"Huntington",
    "sg:classifiers":[
        {
            "category":"Shopping",
            "subcategory":"Antiques",
            "type":"Retail Goods"
        }
    ],
    "sg:phone":"+1 631 271 8514",
    "sg:postcode":"11743",
    "sg:province":"NY",
    "wof:name":"Delia's Divine Decadence",
    "wof:placetype":"venue"
},
  "geometry": {"coordinates":[-73.42574999999999,40.869221],"type":"Point"}
}