{
  "type": "Feature",
  "properties": {
    "iso:country":"US",
    "sg:address":"34 Center St",
    "sg:city":"Fort Plain",
    "sg:classifiers":[
        {
            "category":"Retail",
            "subcategory":"Funeral Services",
            "type":"Services"
        }
    ],
    "sg:phone":"+1 518 993 3361",
    "sg:postcode":"13339",
    "sg:province":"NY",
    "sg:tags":[
        "director"
    ],
    "wof:name":"Gray Houghtailing & Smith Home",
    "wof:placetype":"venue"
},
  "geometry": {"coordinates":[-74.625474,42.933214],"type":"Point"}
}