{
  "type": "Feature",
  "properties": {
    "addr:full":"4 Thoreau Rd North Babylon NY 11703",
    "addr:housenumber":"4",
    "addr:postcode":"11703",
    "addr:street":"Thoreau Rd",
    "iso:country":"US",
    "sg:address":"4 Thoreau Rd",
    "sg:city":"North Babylon",
    "sg:phone":"+1 631 587 3200",
    "sg:postcode":"11703",
    "sg:province":"NY",
    "sg:tags":[
        "oil"
    ],
    "sg:website":"www.codfuel.com",
    "wof:name":"CODFUEL.COM",
    "wof:placetype":"venue"
},
  "geometry": {"coordinates":[-73.316177,40.726502],"type":"Point"}
}