{
  "type": "Feature",
  "properties": {
    "addr:full":"240 Division Ave Brooklyn NY 11211",
    "addr:housenumber":"240",
    "addr:postcode":"11211",
    "addr:street":"Division Ave",
    "iso:country":"US",
    "sg:address":"240 Division Ave",
    "sg:city":"Brooklyn",
    "sg:classifiers":[
        {
            "category":"Education",
            "subcategory":"Library",
            "type":"Public Place"
        }
    ],
    "sg:phone":"+1 718 302 3485",
    "sg:postcode":"11211",
    "sg:province":"NY",
    "sg:website":"www.brooklynpubliclibrary.org/br...",
    "wof:name":"Brooklyn Public Library",
    "wof:placetype":"venue"
},
  "geometry": {"coordinates":[-73.957331,40.707158],"type":"Point"}
}