{
  "type": "Feature",
  "properties": {
    "iso:country":"US",
    "sg:address":"2465 Adam Clayton Powell Jr Blvd",
    "sg:city":"New York",
    "sg:classifiers":[
        {
            "category":"Shopping",
            "subcategory":"Optical Goods",
            "type":"Retail Goods"
        }
    ],
    "sg:phone":"+1 212 234 9774",
    "sg:postcode":"10030",
    "sg:province":"NY",
    "sg:tags":[
        "optician"
    ],
    "wof:name":"Frame USA",
    "wof:placetype":"venue"
},
  "geometry": {"coordinates":[-73.939604,40.820742],"type":"Point"}
}