{
  "type": "Feature",
  "properties": {
    "iso:country":"US",
    "sg:address":"642 South Ave",
    "sg:city":"Rochester",
    "sg:classifiers":[
        {
            "category":"Restaurant",
            "type":"Food & Drink"
        }
    ],
    "sg:phone":"+1   ",
    "sg:postcode":"14620",
    "sg:province":"NY",
    "sg:tags":[
        "eating"
    ],
    "wof:name":"Ausamgate Creations",
    "wof:placetype":"venue"
},
  "geometry": {"coordinates":[-77.60432900000001,43.142222],"type":"Point"}
}