{
  "type": "Feature",
  "properties": {
    "addr:full":"1054 Bushwick Ave Brooklyn NY 11221",
    "addr:housenumber":"1054",
    "addr:postcode":"11221",
    "addr:street":"Bushwick Ave",
    "iso:country":"US",
    "sg:address":"1054 Bushwick Ave",
    "sg:city":"Brooklyn",
    "sg:classifiers":[
        {
            "category":"Organizations",
            "subcategory":"Community Association",
            "type":"Services"
        }
    ],
    "sg:phone":"+1   ",
    "sg:postcode":"11221",
    "sg:province":"NY",
    "sg:tags":[
        "membership"
    ],
    "wof:name":"Masons",
    "wof:placetype":"venue"
},
  "geometry": {"coordinates":[-73.920008,40.690481],"type":"Point"}
}