{
  "type": "Feature",
  "properties": {
    "iso:country":"US",
    "sg:address":"278 5th Ave",
    "sg:city":"Brooklyn",
    "sg:classifiers":[
        {
            "category":"Restaurant",
            "type":"Food & Drink"
        }
    ],
    "sg:phone":"+1 718 499 1433",
    "sg:postcode":"11215",
    "sg:province":"NY",
    "wof:name":"Vaux",
    "wof:placetype":"venue"
},
  "geometry": {"coordinates":[-73.982102,40.674416],"type":"Point"}
}