{
  "type": "Feature",
  "properties": {
    "addr:full":"85 Princeton Ave Hewlett NY 11557",
    "addr:housenumber":"85",
    "addr:postcode":"11557",
    "addr:street":"Princeton Ave",
    "iso:country":"US",
    "sg:address":"85 Princeton Ave",
    "sg:city":"Hewlett",
    "sg:classifiers":[
        {
            "category":"Professional",
            "subcategory":"Management & Consulting",
            "type":"Services"
        }
    ],
    "sg:phone":"+1 516 374 1845",
    "sg:postcode":"11557",
    "sg:province":"NY",
    "sg:tags":[
        "consultant",
        "automation"
    ],
    "wof:name":"Office Automation Consulting",
    "wof:placetype":"venue"
},
  "geometry": {"coordinates":[-73.693505,40.641664],"type":"Point"}
}