{
  "type": "Feature",
  "properties": {
    "addr:full":"9805 Northern Boulevard Corona NY 11368",
    "addr:housenumber":"9805",
    "addr:postcode":"11368",
    "addr:street":"Northern Boulevard",
    "iso:country":"US",
    "sg:address":"9805 Northern Boulevard",
    "sg:city":"Corona",
    "sg:classifiers":[
        {
            "category":"Restaurant",
            "type":"Food & Drink"
        }
    ],
    "sg:phone":"+1 718 397 5934",
    "sg:postcode":"11368",
    "sg:province":"NY",
    "wof:name":"Casa Pueblo",
    "wof:placetype":"venue"
},
  "geometry": {"coordinates":[-73.869333,40.756228],"type":"Point"}
}