{
  "type": "Feature",
  "properties": {
    "addr:full":"1601 Tenbroeck Ave Bronx NY 10461",
    "addr:housenumber":"1601",
    "addr:postcode":"10461",
    "addr:street":"Tenbroeck Ave",
    "iso:country":"US",
    "sg:address":"1601 Tenbroeck Ave",
    "sg:city":"Bronx",
    "sg:classifiers":[
        {
            "category":"Health Services",
            "subcategory":"Doctor",
            "type":"Services"
        }
    ],
    "sg:phone":"+1 718 829 5999",
    "sg:postcode":"10461",
    "sg:province":"NY",
    "sg:tags":[
        "physician",
        "surgeon"
    ],
    "wof:name":"Westchester Medical Group",
    "wof:placetype":"venue"
},
  "geometry": {"coordinates":[-73.84773199999999,40.849961],"type":"Point"}
}