{
  "type": "Feature",
  "properties": {
    "iso:country":"US",
    "sg:address":"115 5th Ave",
    "sg:city":"New York",
    "sg:classifiers":[
        {
            "category":"Manufacturing",
            "subcategory":"Printing",
            "type":"Manufacturing & Wholesale Goods"
        }
    ],
    "sg:phone":"+1   ",
    "sg:postcode":"10003",
    "sg:province":"NY",
    "sg:tags":[
        "book"
    ],
    "wof:name":"International Thompson Pubg",
    "wof:placetype":"venue"
},
  "geometry": {"coordinates":[-73.99154900000001,40.738614],"type":"Point"}
}