{
  "type": "Feature",
  "properties": {
    "addr:full":"701 Noyes St Utica NY 13502",
    "addr:housenumber":"701",
    "addr:postcode":"13502",
    "addr:street":"Noyes St",
    "iso:country":"US",
    "sg:address":"701 Noyes St",
    "sg:city":"Utica",
    "sg:classifiers":[
        {
            "category":"Shopping",
            "subcategory":"Used Merchandise",
            "type":"Retail Goods"
        }
    ],
    "sg:phone":"+1   ",
    "sg:postcode":"13502",
    "sg:province":"NY",
    "sg:tags":[
        "auto"
    ],
    "wof:name":"Comeskey Stamp & Coin",
    "wof:placetype":"venue"
},
  "geometry": {"coordinates":[-75.248707,43.096835],"type":"Point"}
}