{
  "type": "Feature",
  "properties": {
    "addr:full":"140 Woodhull Rd Huntington NY 11743",
    "addr:housenumber":"140",
    "addr:postcode":"11743",
    "addr:street":"Woodhull Rd",
    "iso:country":"US",
    "sg:address":"140 Woodhull Rd",
    "sg:city":"Huntington",
    "sg:classifiers":[
        {
            "category":"Education",
            "subcategory":"School",
            "type":"Public Place"
        }
    ],
    "sg:phone":"+1 631 673 2054",
    "sg:postcode":"11743",
    "sg:province":"NY",
    "wof:name":"Huntington Union Free School District",
    "wof:placetype":"venue"
},
  "geometry": {"coordinates":[-73.41395799999999,40.869156],"type":"Point"}
}