{
  "type": "Feature",
  "properties": {
    "addr:full":"6133 jericho turnpike Commack NY 11725",
    "addr:housenumber":"6133",
    "addr:postcode":"11725",
    "addr:street":"Jericho Turnpike",
    "iso:country":"US",
    "sg:address":"6133 jericho turnpike",
    "sg:city":"Commack",
    "sg:classifiers":[
        {
            "category":"Bars & Pubs",
            "subcategory":"Sports Bar",
            "type":"Food & Drink"
        },
        {
            "category":"Arts & Performance",
            "subcategory":"Arts Center",
            "type":"Entertainment"
        }
    ],
    "sg:phone":"+1 631 623 6307",
    "sg:postcode":"11725",
    "sg:province":"NY",
    "sg:tags":[
        "hall",
        "pool"
    ],
    "sg:website":"www.feltny.com/",
    "wof:name":"Felt Billiards",
    "wof:placetype":"venue"
},
  "geometry": {"coordinates":[-73.30365399999999,40.842354],"type":"Point"}
}