{
  "type": "Feature",
  "properties": {
    "addr:full":"189 Hopkins St Fl 1 Brooklyn NY 11206",
    "addr:housenumber":"189;1",
    "addr:postcode":"11206",
    "addr:street":"Hopkins St",
    "iso:country":"US",
    "sg:address":"189 Hopkins St Fl 1",
    "sg:city":"Brooklyn",
    "sg:classifiers":[
        {
            "category":"Home & Garden",
            "subcategory":"Carpets & Floor Coverings",
            "type":"Retail Goods"
        }
    ],
    "sg:phone":"+1 718 599 0634",
    "sg:postcode":"11206",
    "sg:province":"NY",
    "sg:tags":[
        "distributor",
        "rug",
        "manufacturer"
    ],
    "wof:name":"Dakten, Tenzin",
    "wof:placetype":"venue"
},
  "geometry": {"coordinates":[-73.94575399999999,40.699526],"type":"Point"}
}