{
  "type": "Feature",
  "properties": {
    "addr:full":"184 Woodlawn Ave Saint James NY 11780",
    "addr:housenumber":"184",
    "addr:postcode":"11780",
    "addr:street":"Woodlawn Ave",
    "iso:country":"US",
    "sg:address":"184 Woodlawn Ave",
    "sg:city":"Saint James",
    "sg:classifiers":[
        {
            "category":"Organizations",
            "subcategory":"Religious Organization",
            "type":"Services"
        }
    ],
    "sg:phone":"+1 631 584 3934",
    "sg:postcode":"11780",
    "sg:province":"NY",
    "sg:tags":[
        "church"
    ],
    "wof:name":"New Jerusalem Church",
    "wof:placetype":"venue"
},
  "geometry": {"coordinates":[-73.155068,40.875573],"type":"Point"}
}