{
  "type": "Feature",
  "properties": {
    "addr:full":"58 W 56 St New York NY 10019",
    "addr:housenumber":"58",
    "addr:postcode":"10019",
    "addr:street":"W 56 St",
    "iso:country":"US",
    "sg:address":"58 W 56 St",
    "sg:city":"New York",
    "sg:classifiers":[
        {
            "category":"Retail",
            "subcategory":"Auto Repair",
            "type":"Services"
        }
    ],
    "sg:phone":"+1 917 289 3736",
    "sg:postcode":"10019",
    "sg:province":"NY",
    "sg:tags":[
        "wrecker"
    ],
    "wof:name":"7 Day Emergency 24 Hr Lcksmth",
    "wof:placetype":"venue"
},
  "geometry": {"coordinates":[-73.97629499999999,40.762791],"type":"Point"}
}