{
  "type": "Feature",
  "properties": {
    "iso:country":"US",
    "sg:address":"335 Main St",
    "sg:city":"Johnson City",
    "sg:classifiers":[
        {
            "category":"Organizations",
            "subcategory":"Labor Organization",
            "type":"Services"
        }
    ],
    "sg:phone":"+1   ",
    "sg:postcode":"13790",
    "sg:province":"NY",
    "wof:name":"Broome County Federation Labor",
    "wof:placetype":"venue"
},
  "geometry": {"coordinates":[-75.959013,42.115909],"type":"Point"}
}