{
  "type": "Feature",
  "properties": {
    "addr:full":"55 E 59th St Rm 1202 New York NY 10022",
    "addr:housenumber":"55;1202",
    "addr:postcode":"10022",
    "addr:street":"E 59Th St",
    "iso:country":"US",
    "sg:address":"55 E 59th St Rm 1202",
    "sg:city":"New York",
    "sg:classifiers":[
        {
            "category":"Banks & Credit Unions",
            "subcategory":"Investment Brokerage",
            "type":"Services"
        }
    ],
    "sg:phone":"+1 212 888 4005",
    "sg:postcode":"10022",
    "sg:province":"NY",
    "sg:tags":[
        "investing"
    ],
    "wof:name":"Lafayette Investment Management",
    "wof:placetype":"venue"
},
  "geometry": {"coordinates":[-73.970806,40.76349],"type":"Point"}
}