{
  "type": "Feature",
  "properties": {
    "addr:full":"202 Bethpage-Sweet Hollow Rd Old Bethpage NY 11804",
    "addr:housenumber":"202",
    "addr:postcode":"11804",
    "addr:street":"Bethpage-Sweet Hollow Rd",
    "iso:country":"US",
    "sg:address":"202 Bethpage-Sweet Hollow Rd",
    "sg:city":"Old Bethpage",
    "sg:classifiers":[
        {
            "category":"Autos & Motor Vehicles",
            "subcategory":"Auto Supplies",
            "type":"Retail Goods"
        }
    ],
    "sg:phone":"+1 516 752 9200",
    "sg:postcode":"11804",
    "sg:province":"NY",
    "sg:tags":[
        "tire"
    ],
    "sg:website":"www.futuretire.com",
    "wof:name":"Future Tire Inc",
    "wof:placetype":"venue"
},
  "geometry": {"coordinates":[-73.452519,40.762965],"type":"Point"}
}