{
  "type": "Feature",
  "properties": {
    "addr:full":"250 W 72 St New York NY 10023",
    "addr:housenumber":"250",
    "addr:postcode":"10023",
    "addr:street":"W 72 St",
    "iso:country":"US",
    "sg:address":"250 W 72 St",
    "sg:city":"New York",
    "sg:classifiers":[
        {
            "category":"Restaurant",
            "type":"Food & Drink"
        }
    ],
    "sg:phone":"+1   ",
    "sg:postcode":"10023",
    "sg:province":"NY",
    "sg:tags":[
        "drinking",
        "eating"
    ],
    "wof:name":"All State Cafe",
    "wof:placetype":"venue"
},
  "geometry": {"coordinates":[-73.983552,40.77921],"type":"Point"}
}