{
  "type": "Feature",
  "properties": {
    "addr:full":"4024 White Plains Rd Bronx NY 10466",
    "addr:housenumber":"4024",
    "addr:postcode":"10466",
    "addr:street":"White Plains Rd",
    "iso:country":"US",
    "sg:address":"4024 White Plains Rd",
    "sg:city":"Bronx",
    "sg:classifiers":[
        {
            "category":"Retail",
            "subcategory":"Repair Shop",
            "type":"Services"
        }
    ],
    "sg:phone":"+1 347 332 2809",
    "sg:postcode":"10466",
    "sg:province":"NY",
    "sg:tags":[
        "lock",
        "locksmith"
    ],
    "wof:name":"24 Hour Locksmith",
    "wof:placetype":"venue"
},
  "geometry": {"coordinates":[-73.86008099999999,40.888511],"type":"Point"}
}