{
  "type": "Feature",
  "properties": {
    "iso:country":"US",
    "sg:address":"303 Main St",
    "sg:city":"Highland Falls",
    "sg:classifiers":[
        {
            "category":"Social Services",
            "type":"Services"
        }
    ],
    "sg:phone":"+1 845 446 3725",
    "sg:postcode":"10928",
    "sg:province":"NY",
    "sg:tags":[
        "organization",
        "welfare"
    ],
    "wof:name":"Big Brothers Big Sisters",
    "wof:placetype":"venue"
},
  "geometry": {"coordinates":[-73.966053,41.369436],"type":"Point"}
}