{
  "type": "Feature",
  "properties": {
    "iso:country":"US",
    "sg:address":"131 Fox Rd",
    "sg:city":"Middle Grove",
    "sg:classifiers":[
        {
            "category":"Building & Trades",
            "subcategory":"Construction",
            "type":"Services"
        }
    ],
    "sg:phone":"+1 518 882 1310",
    "sg:postcode":"12850",
    "sg:province":"NY",
    "sg:tags":[
        "carpentry",
        "contractor"
    ],
    "wof:name":"Adirondack Wood Wright",
    "wof:placetype":"venue"
},
  "geometry": {"coordinates":[-74.04389399999999,43.092719],"type":"Point"}
}