{
  "type": "Feature",
  "properties": {
    "addr:full":"3117 30th Ave Astoria NY 11102",
    "addr:housenumber":"3117",
    "addr:postcode":"11102",
    "addr:street":"30Th Ave",
    "iso:country":"US",
    "sg:address":"3117 30th Ave",
    "sg:city":"Astoria",
    "sg:classifiers":[
        {
            "category":"Coffee & Tea",
            "type":"Food & Drink"
        },
        {
            "category":"Donuts",
            "subcategory":"None",
            "type":"Food & Drink"
        }
    ],
    "sg:phone":"+1 718 956 3582",
    "sg:postcode":"11102",
    "sg:province":"NY",
    "wof:name":"Dunkin Donuts",
    "wof:placetype":"venue"
},
  "geometry": {"coordinates":[-73.920723,40.766693],"type":"Point"}
}