{
  "type": "Feature",
  "properties": {
    "iso:country":"US",
    "sg:address":"1412 Broadway",
    "sg:city":"New York",
    "sg:classifiers":[
        {
            "category":"Real Estate",
            "subcategory":"Real Estate Agent",
            "type":"Services"
        }
    ],
    "sg:phone":"+1 212 302 7020",
    "sg:postcode":"10018",
    "sg:province":"NY",
    "wof:name":"Murray Hill Properties",
    "wof:placetype":"venue"
},
  "geometry": {"coordinates":[-73.98686499999999,40.754318],"type":"Point"}
}