{
  "type": "Feature",
  "properties": {
    "addr:full":"1100 Clove Rd Staten Island NY 10301",
    "addr:housenumber":"1100",
    "addr:postcode":"10301",
    "addr:street":"Clove Rd",
    "iso:country":"US",
    "sg:address":"1100 Clove Rd",
    "sg:city":"Staten Island",
    "sg:classifiers":[
        {
            "category":"Real Estate",
            "subcategory":"Real Estate Services",
            "type":"Services"
        }
    ],
    "sg:phone":"+1 718 720 4800",
    "sg:postcode":"10301",
    "sg:province":"NY",
    "sg:tags":[
        "management",
        "property"
    ],
    "wof:name":"Agelire Anthony Rl Est",
    "wof:placetype":"venue"
},
  "geometry": {"coordinates":[-74.106499,40.619099],"type":"Point"}
}