{
  "type": "Feature",
  "properties": {
    "addr:full":"303 W 66 St New York NY 10023",
    "addr:housenumber":"303",
    "addr:postcode":"10023",
    "addr:street":"W 66 St",
    "iso:country":"US",
    "sg:address":"303 W 66 St",
    "sg:city":"New York",
    "sg:classifiers":[
        {
            "category":"Social Services",
            "type":"Services"
        }
    ],
    "sg:phone":"+1 212 875 8958",
    "sg:postcode":"10023",
    "sg:province":"NY",
    "sg:tags":[
        "senior",
        "citizen"
    ],
    "wof:name":"Lincoln House Outreach",
    "wof:placetype":"venue"
},
  "geometry": {"coordinates":[-73.98835200000001,40.776567],"type":"Point"}
}