{
  "type": "Feature",
  "properties": {
    "addr:full":"294 Fifth Ave Manhattan NY 10001",
    "addr:housenumber":"294",
    "addr:postcode":"10001",
    "addr:street":"Fifth Ave",
    "iso:country":"US",
    "sg:address":"294 Fifth Ave",
    "sg:city":"Manhattan",
    "sg:classifiers":[
        {
            "category":"Travel",
            "subcategory":"Hotels & Motels",
            "type":"Entertainment"
        }
    ],
    "sg:phone":"+1 212 564 4900",
    "sg:postcode":"10001",
    "sg:province":"NY",
    "sg:website":"newyorkhotel.com",
    "wof:name":"The Lotus Hotel",
    "wof:placetype":"venue"
},
  "geometry": {"coordinates":[-73.986383,40.746439],"type":"Point"}
}