{
  "type": "Feature",
  "properties": {
    "addr:full":"446 Park Ave Youngstown NY 14174",
    "addr:housenumber":"446",
    "addr:postcode":"14174",
    "addr:street":"Park Ave",
    "iso:country":"US",
    "sg:address":"446 Park Ave",
    "sg:city":"Youngstown",
    "sg:classifiers":[
        {
            "category":"Building & Trades",
            "subcategory":"Plumbing",
            "type":"Services"
        }
    ],
    "sg:phone":"+1 716 745 3062",
    "sg:postcode":"14174",
    "sg:province":"NY",
    "wof:name":"American Waterworks",
    "wof:placetype":"venue"
},
  "geometry": {"coordinates":[-79.043475,43.268021],"type":"Point"}
}