{
  "type": "Feature",
  "properties": {
    "addr:full":"77 Oconnor Rd Fairport NY 14450",
    "addr:housenumber":"77",
    "addr:postcode":"14450",
    "addr:street":"Oconnor Rd",
    "iso:country":"US",
    "sg:address":"77 Oconnor Rd",
    "sg:city":"Fairport",
    "sg:classifiers":[
        {
            "category":"Retail",
            "subcategory":"Car Wash",
            "type":"Services"
        }
    ],
    "sg:phone":"+1 585 388 0760",
    "sg:postcode":"14450",
    "sg:province":"NY",
    "sg:tags":[
        "automobile",
        "detail",
        "clean"
    ],
    "wof:name":"Mister Detail",
    "wof:placetype":"venue"
},
  "geometry": {"coordinates":[-77.456264,43.104773],"type":"Point"}
}