{
  "type": "Feature",
  "properties": {
    "iso:country":"US",
    "sg:address":"12 Pelham Ave",
    "sg:city":"Nanuet",
    "sg:classifiers":[
        {
            "category":"Social Services",
            "type":"Services"
        }
    ],
    "sg:phone":"+1 845 624 5802",
    "sg:postcode":"10954",
    "sg:province":"NY",
    "sg:tags":[
        "worker"
    ],
    "wof:name":"Jeanine Blumenfeld",
    "wof:placetype":"venue"
},
  "geometry": {"coordinates":[-74.00900300000001,41.087443],"type":"Point"}
}