{
  "type": "Feature",
  "properties": {
    "addr:full":"575 Stewart Ave Garden City NY 11530",
    "addr:housenumber":"575",
    "addr:postcode":"11530",
    "addr:street":"Stewart Ave",
    "iso:country":"US",
    "sg:address":"575 Stewart Ave",
    "sg:city":"Garden City",
    "sg:classifiers":[
        {
            "category":"Shopping",
            "subcategory":"Music",
            "type":"Retail Goods"
        }
    ],
    "sg:phone":"+1   ",
    "sg:postcode":"11530",
    "sg:province":"NY",
    "sg:tags":[
        "product",
        "video",
        "sm",
        "blank",
        "prerecorded",
        "tape",
        "audio"
    ],
    "wof:name":"Sam Goody 4626",
    "wof:placetype":"venue"
},
  "geometry": {"coordinates":[-73.61600199999999,40.730697],"type":"Point"}
}