{
  "type": "Feature",
  "properties": {
    "addr:full":"25 Newbridge Road Suite 420 Hicksville NY 11801",
    "addr:housenumber":"25",
    "addr:postcode":"11801",
    "addr:street":"Newbridge Road Suite 420",
    "iso:country":"US",
    "sg:address":"25 Newbridge Road Suite 420",
    "sg:city":"Hicksville",
    "sg:classifiers":[
        {
            "category":"Professional",
            "subcategory":"Computer Services",
            "type":"Services"
        }
    ],
    "sg:phone":"+1 877 923 6783",
    "sg:postcode":"11801",
    "sg:province":"NY",
    "sg:tags":[
        "adoption",
        "adopt",
        "adoptiing",
        "social-network",
        "birth-mother",
        "adoptive---parents",
        "adopt-a-child",
        "child",
        "baby"
    ],
    "sg:website":"http://DirectAdoptions.com",
    "wof:name":"DirectAdoptions.com",
    "wof:placetype":"venue"
},
  "geometry": {"coordinates":[-73.52748699999999,40.767233],"type":"Point"}
}