{
  "type": "Feature",
  "properties": {
    "iso:country":"US",
    "sg:address":"86 Calvert St",
    "sg:city":"Harrison",
    "sg:classifiers":[
        {
            "category":"Restaurant",
            "type":"Food & Drink"
        }
    ],
    "sg:phone":"+1 914 835 1230",
    "sg:postcode":"10528",
    "sg:province":"NY",
    "sg:tags":[
        "delicatessen",
        "eating",
        "grocery"
    ],
    "wof:name":"Calvert Street Deli Inc",
    "wof:placetype":"venue"
},
  "geometry": {"coordinates":[-73.71753,40.969055],"type":"Point"}
}