{
  "type": "Feature",
  "properties": {
    "iso:country":"US",
    "sg:address":"75 E End Ave",
    "sg:city":"New York",
    "sg:classifiers":[
        {
            "category":"Professional",
            "subcategory":"Business Services",
            "type":"Services"
        }
    ],
    "sg:phone":"+1 212 794 2773",
    "sg:postcode":"10028",
    "sg:province":"NY",
    "sg:tags":[
        "event"
    ],
    "wof:name":"D'Affaires Charge",
    "wof:placetype":"venue"
},
  "geometry": {"coordinates":[-73.946434,40.772394],"type":"Point"}
}