{
  "type": "Feature",
  "properties": {
    "addr:full":"9 Highland Rd Glen Cove NY 11542",
    "addr:housenumber":"9",
    "addr:postcode":"11542",
    "addr:street":"Highland Rd",
    "iso:country":"US",
    "sg:address":"9 Highland Rd",
    "sg:city":"Glen Cove",
    "sg:classifiers":[
        {
            "category":"Health Services",
            "subcategory":"Clinic",
            "type":"Services"
        }
    ],
    "sg:phone":"+1 516 676 1025",
    "sg:postcode":"11542",
    "sg:province":"NY",
    "sg:tags":[
        "rehabilitation",
        "center"
    ],
    "wof:name":"Melillo Center Cmnty Residence",
    "wof:placetype":"venue"
},
  "geometry": {"coordinates":[-73.629948,40.866256],"type":"Point"}
}