{
  "type": "Feature",
  "properties": {
    "addr:full":"31 Guy Lombardo Ave Freeport NY 11520",
    "addr:housenumber":"31",
    "addr:postcode":"11520",
    "addr:street":"Guy Lombardo Ave",
    "iso:country":"US",
    "sg:address":"31 Guy Lombardo Ave",
    "sg:city":"Freeport",
    "sg:classifiers":[
        {
            "category":"Personal",
            "subcategory":"Beauty Salon",
            "type":"Services"
        }
    ],
    "sg:phone":"+1 516 623 5881",
    "sg:postcode":"11520",
    "sg:province":"NY",
    "wof:name":"Janette Unisex Salon",
    "wof:placetype":"venue"
},
  "geometry": {"coordinates":[-73.58509100000001,40.656053],"type":"Point"}
}