{
  "type": "Feature",
  "properties": {
    "addr:full":"337 Main St Huntington NY 11743",
    "addr:housenumber":"337",
    "addr:postcode":"11743",
    "addr:street":"Main St",
    "iso:country":"US",
    "sg:address":"337 Main St",
    "sg:city":"Huntington",
    "sg:classifiers":[
        {
            "category":"Food & Beverages",
            "subcategory":"Bakery",
            "type":"Retail Goods"
        }
    ],
    "sg:phone":"+1 631 425 7424",
    "sg:postcode":"11743",
    "sg:province":"NY",
    "sg:tags":[
        "baker"
    ],
    "wof:name":"Cardinali Bakery",
    "wof:placetype":"venue"
},
  "geometry": {"coordinates":[-73.429416,40.870935],"type":"Point"}
}