{
  "type": "Feature",
  "properties": {
    "addr:full":"1001 Avenue N Brooklyn NY 11230",
    "addr:housenumber":"1001",
    "addr:postcode":"11230",
    "addr:street":"Avenue N",
    "iso:country":"US",
    "sg:address":"1001 Avenue N",
    "sg:city":"Brooklyn",
    "sg:classifiers":[
        {
            "category":"Professional",
            "subcategory":"Management & Consulting",
            "type":"Services"
        }
    ],
    "sg:phone":"+1 718 986 1274",
    "sg:postcode":"11230",
    "sg:province":"NY",
    "sg:tags":[
        "business"
    ],
    "wof:name":"Alpha 10 Consulting Inc",
    "wof:placetype":"venue"
},
  "geometry": {"coordinates":[-73.96335999999999,40.615204],"type":"Point"}
}