{
  "type": "Feature",
  "properties": {
    "addr:full":"310 Swansea Ave Syracuse NY 13206",
    "addr:housenumber":"310",
    "addr:postcode":"13206",
    "addr:street":"Swansea Ave",
    "iso:country":"US",
    "sg:address":"310 Swansea Ave",
    "sg:city":"Syracuse",
    "sg:classifiers":[
        {
            "category":"Building & Trades",
            "subcategory":"Construction",
            "type":"Services"
        }
    ],
    "sg:phone":"+1 315 437 0019",
    "sg:postcode":"13206",
    "sg:province":"NY",
    "sg:tags":[
        "house"
    ],
    "wof:name":"A&D Remodeling",
    "wof:placetype":"venue"
},
  "geometry": {"coordinates":[-76.11828300000001,43.07882],"type":"Point"}
}