{
  "type": "Feature",
  "properties": {
    "iso:country":"US",
    "sg:address":"3910 Goose St",
    "sg:city":"Locke",
    "sg:classifiers":[
        {
            "category":"Wholesale",
            "subcategory":"Durable Goods & Equipment",
            "type":"Manufacturing & Wholesale Goods"
        }
    ],
    "sg:phone":"+1 315 497 3463",
    "sg:postcode":"13092",
    "sg:province":"NY",
    "wof:name":"Ryan Supply",
    "wof:placetype":"venue"
},
  "geometry": {"coordinates":[-76.47682399999999,42.654751],"type":"Point"}
}