{
  "type": "Feature",
  "properties": {
    "addr:full":"132 N 1st St Brooklyn NY 11211",
    "addr:housenumber":"132",
    "addr:postcode":"11211",
    "addr:street":"N 1St St",
    "iso:country":"US",
    "sg:address":"132 N 1st St",
    "sg:city":"Brooklyn",
    "sg:classifiers":[
        {
            "category":"Shopping",
            "subcategory":"Gifts & Souvenirs",
            "type":"Retail Goods"
        }
    ],
    "sg:phone":"+1   ",
    "sg:postcode":"11211",
    "sg:province":"NY",
    "wof:name":"Ak-ME Store Inc",
    "wof:placetype":"venue"
},
  "geometry": {"coordinates":[-73.961277,40.715058],"type":"Point"}
}