{
  "type": "Feature",
  "properties": {
    "addr:full":"1083 Old Rte 9 Fishkill NY 12524",
    "addr:housenumber":"1083",
    "addr:postcode":"12524",
    "addr:street":"Old Rte 9",
    "iso:country":"US",
    "sg:address":"1083 Old Rte 9",
    "sg:city":"Fishkill",
    "sg:classifiers":[
        {
            "category":"Home & Garden",
            "subcategory":"Household Appliances",
            "type":"Retail Goods"
        }
    ],
    "sg:phone":"+1 845 297 4300",
    "sg:postcode":"12524",
    "sg:province":"NY",
    "sg:tags":[
        "cleaners",
        "vacuum"
    ],
    "sg:website":"www.oreck.com",
    "wof:name":"Oreck",
    "wof:placetype":"venue"
},
  "geometry": {"coordinates":[-73.901134,41.551499],"type":"Point"}
}