{
  "type": "Feature",
  "properties": {
    "iso:country":"US",
    "sg:address":"1550 Grand Concourse",
    "sg:city":"Bronx",
    "sg:classifiers":[
        {
            "category":"Retail",
            "subcategory":"Repair Shop",
            "type":"Services"
        }
    ],
    "sg:phone":"+1 718 685 5797",
    "sg:postcode":"10457",
    "sg:province":"NY",
    "sg:tags":[
        "lock",
        "locksmith"
    ],
    "wof:name":"Locksmith",
    "wof:placetype":"venue"
},
  "geometry": {"coordinates":[-73.91024,40.84554],"type":"Point"}
}