{
  "type": "Feature",
  "properties": {
    "addr:full":"405 Arden Ave Staten Island NY 10312",
    "addr:housenumber":"405",
    "addr:postcode":"10312",
    "addr:street":"Arden Ave",
    "iso:country":"US",
    "sg:address":"405 Arden Ave",
    "sg:city":"Staten Island",
    "sg:classifiers":[
        {
            "category":"Health Services",
            "subcategory":"Doctor",
            "type":"Services"
        }
    ],
    "sg:phone":"+1 718 608 1110",
    "sg:postcode":"10312",
    "sg:province":"NY",
    "sg:tags":[
        "physician",
        "surgeon"
    ],
    "wof:name":"George P Smith MD",
    "wof:placetype":"venue"
},
  "geometry": {"coordinates":[-74.18859999999999,40.550687],"type":"Point"}
}