{
  "type": "Feature",
  "properties": {
    "addr:full":"1251 Ave of the Americas New York NY 10020",
    "addr:housenumber":"1251",
    "addr:postcode":"10020",
    "addr:street":"Ave Of The Americas",
    "iso:country":"US",
    "sg:address":"1251 Ave of the Americas",
    "sg:city":"New York",
    "sg:classifiers":[
        {
            "category":"Banks & Credit Unions",
            "subcategory":"Investment Brokerage",
            "type":"Services"
        }
    ],
    "sg:phone":"+1 212 302 5946",
    "sg:postcode":"10020",
    "sg:province":"NY",
    "sg:tags":[
        "advisory",
        "financial"
    ],
    "wof:name":"Ernst Young National",
    "wof:placetype":"venue"
},
  "geometry": {"coordinates":[-73.980709,40.759542],"type":"Point"}
}