{
  "type": "Feature",
  "properties": {
    "addr:full":"8 Charles Ct East Patchogue NY 11772",
    "addr:housenumber":"8",
    "addr:postcode":"11772",
    "addr:street":"Charles Ct",
    "iso:country":"US",
    "sg:address":"8 Charles Ct",
    "sg:city":"East Patchogue",
    "sg:classifiers":[
        {
            "category":"Professional",
            "subcategory":"Art Services",
            "type":"Services"
        }
    ],
    "sg:phone":"+1 631 776 1324",
    "sg:postcode":"11772",
    "sg:province":"NY",
    "sg:tags":[
        "graphic",
        "designer"
    ],
    "wof:name":"Tonic Design House",
    "wof:placetype":"venue"
},
  "geometry": {"coordinates":[-72.956011,40.74787],"type":"Point"}
}