{
  "type": "Feature",
  "properties": {
    "addr:full":"99 Wall St New York NY 10005",
    "addr:housenumber":"99",
    "addr:postcode":"10005",
    "addr:street":"Wall St",
    "iso:country":"US",
    "sg:address":"99 Wall St",
    "sg:city":"New York",
    "sg:classifiers":[
        {
            "category":"Banks & Credit Unions",
            "subcategory":"Investment Brokerage",
            "type":"Services"
        }
    ],
    "sg:phone":"+1 212 514 6862",
    "sg:postcode":"10005",
    "sg:province":"NY",
    "sg:tags":[
        "consultant",
        "planning",
        "financial"
    ],
    "sg:website":"www.dahcon.com",
    "wof:name":"Dah Consulting Inc",
    "wof:placetype":"venue"
},
  "geometry": {"coordinates":[-74.007139,40.704949],"type":"Point"}
}