{
  "type": "Feature",
  "properties": {
    "iso:country":"US",
    "sg:address":"229 Manchester Rd",
    "sg:city":"Poughkeepsie",
    "sg:classifiers":[
        {
            "category":"Wholesale",
            "subcategory":"Electrical",
            "type":"Manufacturing & Wholesale Goods"
        }
    ],
    "sg:phone":"+1 845 471 7740",
    "sg:postcode":"12603",
    "sg:province":"NY",
    "sg:tags":[
        "equipment",
        "electronic",
        "supply"
    ],
    "wof:name":"Lorex Industries Inc",
    "wof:placetype":"venue"
},
  "geometry": {"coordinates":[-73.87319100000001,41.685854],"type":"Point"}
}