{
  "type": "Feature",
  "properties": {
    "iso:country":"US",
    "sg:address":"10537 64th Ave",
    "sg:city":"Forest Hills",
    "sg:classifiers":[
        {
            "category":"Personal",
            "subcategory":"Shoe Repair & Shine",
            "type":"Services"
        }
    ],
    "sg:phone":"+1 718 940 4735",
    "sg:postcode":"11375",
    "sg:province":"NY",
    "wof:name":"Gabriel Shoe Repair",
    "wof:placetype":"venue"
},
  "geometry": {"coordinates":[-73.85125499999999,40.732598],"type":"Point"}
}