{
  "type": "Feature",
  "properties": {
    "iso:country":"US",
    "sg:address":"60 Lowndes Ave",
    "sg:city":"Huntington Sta",
    "sg:classifiers":[
        {
            "category":"Building & Trades",
            "subcategory":"Construction",
            "type":"Services"
        }
    ],
    "sg:phone":"+1 631 424 5736",
    "sg:postcode":"11746",
    "sg:province":"NY",
    "sg:tags":[
        "product",
        "asphalt"
    ],
    "wof:name":"Matas's Paving & Seal Coating",
    "wof:placetype":"venue"
},
  "geometry": {"coordinates":[-73.416093,40.85757],"type":"Point"}
}