{
  "type": "Feature",
  "properties": {
    "iso:country":"US",
    "sg:address":"848 Madison Ave",
    "sg:city":"Albany",
    "sg:classifiers":[
        {
            "category":"Personal",
            "subcategory":"Tanning Parlor",
            "type":"Services"
        }
    ],
    "sg:phone":"+1 518 482 8201",
    "sg:postcode":"12208",
    "sg:province":"NY",
    "sg:tags":[
        "salon"
    ],
    "wof:name":"South Beach Tans USA",
    "wof:placetype":"venue"
},
  "geometry": {"coordinates":[-73.78415200000001,42.661768],"type":"Point"}
}