{
  "type": "Feature",
  "properties": {
    "iso:country":"US",
    "sg:address":"156 5th Ave",
    "sg:city":"New York",
    "sg:classifiers":[
        {
            "category":"Professional",
            "subcategory":"Management & Consulting",
            "type":"Services"
        }
    ],
    "sg:phone":"+1 212 541 5221",
    "sg:postcode":"10010",
    "sg:province":"NY",
    "sg:tags":[
        "picture",
        "television",
        "for",
        "motion",
        "s",
        "production"
    ],
    "wof:name":"Pete Bennett International",
    "wof:placetype":"venue"
},
  "geometry": {"coordinates":[-73.990692,40.740101],"type":"Point"}
}