{
  "type": "Feature",
  "properties": {
    "iso:country":"US",
    "sg:address":"2 Ellie Ln",
    "sg:city":"Saint James",
    "sg:classifiers":[
        {
            "category":"Professional",
            "subcategory":"Computer Services",
            "type":"Services"
        }
    ],
    "sg:phone":"+1   ",
    "sg:postcode":"11780",
    "sg:province":"NY",
    "sg:tags":[
        "prepackaged",
        "software"
    ],
    "wof:name":"Relational Management Group",
    "wof:placetype":"venue"
},
  "geometry": {"coordinates":[-73.149686,40.871745],"type":"Point"}
}