{
  "type": "Feature",
  "properties": {
    "iso:country":"US",
    "sg:address":"65 Maple Ct",
    "sg:city":"Copiague",
    "sg:classifiers":[
        {
            "category":"Retail",
            "subcategory":"Portrait Studio",
            "type":"Services"
        }
    ],
    "sg:phone":"+1 631 842 1002",
    "sg:postcode":"11726",
    "sg:province":"NY",
    "sg:tags":[
        "photographer"
    ],
    "wof:name":"Starlite Video Productions",
    "wof:placetype":"venue"
},
  "geometry": {"coordinates":[-73.391762,40.67188],"type":"Point"}
}