{
  "type": "Feature",
  "properties": {
    "iso:country":"US",
    "sg:address":"551 Madison Ave",
    "sg:city":"New York",
    "sg:classifiers":[
        {
            "category":"Real Estate",
            "subcategory":"Real Estate Agent",
            "type":"Services"
        }
    ],
    "sg:phone":"+1 212 888 2591",
    "sg:postcode":"10022",
    "sg:province":"NY",
    "sg:website":"www.nycrealty.com",
    "wof:name":"Autolist",
    "wof:placetype":"venue"
},
  "geometry": {"coordinates":[-73.972852,40.761614],"type":"Point"}
}