{
  "type": "Feature",
  "properties": {
    "iso:country":"US",
    "sg:address":"1444 Marshall St",
    "sg:city":"Elmont",
    "sg:classifiers":[
        {
            "category":"Building & Trades",
            "subcategory":"Construction",
            "type":"Services"
        }
    ],
    "sg:phone":"+1 516 775 3525",
    "sg:postcode":"11003",
    "sg:province":"NY",
    "sg:tags":[
        "installs",
        "ceramic",
        "mason",
        "also",
        "tile",
        "polish",
        "contractor",
        "marble"
    ],
    "wof:name":"Trieste Marble Inc",
    "wof:placetype":"venue"
},
  "geometry": {"coordinates":[-73.693297,40.711239],"type":"Point"}
}