{
  "type": "Feature",
  "properties": {
    "addr:full":"375 Nagel Dr Buffalo NY 14225",
    "addr:housenumber":"375",
    "addr:postcode":"14225",
    "addr:street":"Nagel Dr",
    "iso:country":"US",
    "sg:address":"375 Nagel Dr",
    "sg:city":"Buffalo",
    "sg:classifiers":[
        {
            "category":"Wholesale",
            "subcategory":"Construction Materials",
            "type":"Manufacturing & Wholesale Goods"
        }
    ],
    "sg:phone":"+1 716 685 6900",
    "sg:postcode":"14225",
    "sg:province":"NY",
    "sg:tags":[
        "building",
        "supply"
    ],
    "wof:name":"Window City Buffalo Inc",
    "wof:placetype":"venue"
},
  "geometry": {"coordinates":[-78.74697399999999,42.909827],"type":"Point"}
}