{
  "type": "Feature",
  "properties": {
    "iso:country":"US",
    "sg:address":"105 N Bourndale Rd",
    "sg:city":"Manhasset",
    "sg:classifiers":[
        {
            "category":"Banks & Credit Unions",
            "subcategory":"Investment Brokerage",
            "type":"Services"
        }
    ],
    "sg:phone":"+1 516 627 6423",
    "sg:postcode":"11030",
    "sg:province":"NY",
    "wof:name":"Eastwind Investment Co",
    "wof:placetype":"venue"
},
  "geometry": {"coordinates":[-73.70050999999999,40.802044],"type":"Point"}
}