{
  "type": "Feature",
  "properties": {
    "addr:full":"708 Cornell Rd Franklin Square NY 11010",
    "addr:housenumber":"708",
    "addr:postcode":"11010",
    "addr:street":"Cornell Rd",
    "iso:country":"US",
    "sg:address":"708 Cornell Rd",
    "sg:city":"Franklin Square",
    "sg:classifiers":[
        {
            "category":"Shopping",
            "subcategory":"Used Merchandise",
            "type":"Retail Goods"
        }
    ],
    "sg:phone":"+1   ",
    "sg:postcode":"11010",
    "sg:province":"NY",
    "wof:name":"Antique History",
    "wof:placetype":"venue"
},
  "geometry": {"coordinates":[-73.66804,40.697032],"type":"Point"}
}