{
  "type": "Feature",
  "properties": {
    "addr:full":"5224 Avenue M Brooklyn NY 11234",
    "addr:housenumber":"5224",
    "addr:postcode":"11234",
    "addr:street":"Avenue M",
    "iso:country":"US",
    "sg:address":"5224 Avenue M",
    "sg:city":"Brooklyn",
    "sg:classifiers":[
        {
            "category":"Health Services",
            "subcategory":"Optometrist",
            "type":"Services"
        }
    ],
    "sg:phone":"+1 718 951 9050",
    "sg:postcode":"11234",
    "sg:province":"NY",
    "wof:name":"Weinberger Marcel Dr",
    "wof:placetype":"venue"
},
  "geometry": {"coordinates":[-73.92440000000001,40.621399],"type":"Point"}
}