{
  "type": "Feature",
  "properties": {
    "addr:full":"501 W 168th St New York NY 10032",
    "addr:housenumber":"501",
    "addr:postcode":"10032",
    "addr:street":"W 168Th St",
    "iso:country":"US",
    "sg:address":"501 W 168th St",
    "sg:city":"New York",
    "sg:classifiers":[
        {
            "category":"Personal",
            "subcategory":"Beauty Salon",
            "type":"Services"
        }
    ],
    "sg:phone":"+1 212 568 3156",
    "sg:postcode":"10032",
    "sg:province":"NY",
    "wof:name":"Amarilis Beauty Salon",
    "wof:placetype":"venue"
},
  "geometry": {"coordinates":[-73.93836400000001,40.840486],"type":"Point"}
}