{
  "type": "Feature",
  "properties": {
    "addr:full":"99 Park Avenue Rm 1600 New York NY 10016",
    "addr:housenumber":"99;1600",
    "addr:postcode":"10016",
    "addr:street":"Park Avenue Rm",
    "iso:country":"US",
    "sg:address":"99 Park Avenue Rm 1600",
    "sg:city":"New York",
    "sg:classifiers":[
        {
            "category":"Professional",
            "subcategory":"Lawyer & Legal Services",
            "type":"Services"
        }
    ],
    "sg:phone":"+1 212 353 9587",
    "sg:postcode":"10016",
    "sg:province":"NY",
    "wof:name":"Law Offices of Jonathan Moore",
    "wof:placetype":"venue"
},
  "geometry": {"coordinates":[-73.978368,40.750838],"type":"Point"}
}