{
  "type": "Feature",
  "properties": {
    "addr:full":"80 Wisner Ave Middletown NY 10940",
    "addr:housenumber":"80",
    "addr:postcode":"10940",
    "addr:street":"Wisner Ave",
    "iso:country":"US",
    "sg:address":"80 Wisner Ave",
    "sg:city":"Middletown",
    "sg:classifiers":[
        {
            "category":"Government",
            "subcategory":"Office",
            "type":"Public Place"
        }
    ],
    "sg:phone":"+1 845 344 3122",
    "sg:postcode":"10940",
    "sg:province":"NY",
    "sg:tags":[
        "county"
    ],
    "wof:name":"Medi-Coach Orange County",
    "wof:placetype":"venue"
},
  "geometry": {"coordinates":[-74.41146000000001,41.456743],"type":"Point"}
}