{
  "type": "Feature",
  "properties": {
    "iso:country":"US",
    "sg:address":"5720 Peth Rd",
    "sg:city":"Great Valley",
    "sg:classifiers":[
        {
            "category":"Building & Trades",
            "subcategory":"Construction",
            "type":"Services"
        }
    ],
    "sg:phone":"+1 716 945 2673",
    "sg:postcode":"14741",
    "sg:province":"NY",
    "sg:tags":[
        "house"
    ],
    "wof:name":"Frank Clark Construction",
    "wof:placetype":"venue"
},
  "geometry": {"coordinates":[-78.623902,42.19858],"type":"Point"}
}