{
  "type": "Feature",
  "properties": {
    "addr:full":"3929 White Plains Rd Bronx NY 10466",
    "addr:housenumber":"3929",
    "addr:postcode":"10466",
    "addr:street":"White Plains Rd",
    "iso:country":"US",
    "sg:address":"3929 White Plains Rd",
    "sg:city":"Bronx",
    "sg:classifiers":[
        {
            "category":"Restaurant",
            "type":"Food & Drink"
        }
    ],
    "sg:phone":"+1   ",
    "sg:postcode":"10466",
    "sg:province":"NY",
    "sg:tags":[
        "jamaica"
    ],
    "wof:name":"Island Breeze Restaurant",
    "wof:placetype":"venue"
},
  "geometry": {"coordinates":[-73.860984,40.886998],"type":"Point"}
}