{
  "type": "Feature",
  "properties": {
    "addr:full":"19 Demott St Lacona NY 13083",
    "addr:housenumber":"19",
    "addr:postcode":"13083",
    "addr:street":"Demott St",
    "iso:country":"US",
    "sg:address":"19 Demott St",
    "sg:city":"Lacona",
    "sg:classifiers":[
        {
            "category":"Wholesale",
            "subcategory":"Stationery",
            "type":"Manufacturing & Wholesale Goods"
        }
    ],
    "sg:phone":"+1   ",
    "sg:postcode":"13083",
    "sg:province":"NY",
    "sg:tags":[
        "warehouse"
    ],
    "wof:name":"Mc Grann Paper Corporation",
    "wof:placetype":"venue"
},
  "geometry": {"coordinates":[-76.071173,43.641769],"type":"Point"}
}