{
  "type": "Feature",
  "properties": {
    "iso:country":"US",
    "sg:address":"2205 Hopkins Rd",
    "sg:city":"Getzville",
    "sg:classifiers":[
        {
            "category":"Professional",
            "type":"Services"
        }
    ],
    "sg:phone":"+1   ",
    "sg:postcode":"14068",
    "sg:province":"NY",
    "wof:name":"Giordano Real Estate Services",
    "wof:placetype":"venue"
},
  "geometry": {"coordinates":[-78.737797,43.041503],"type":"Point"}
}