{
  "type": "Feature",
  "properties": {
    "addr:full":"3417 Linda Ln Baldwinsville NY 13027",
    "addr:housenumber":"3417",
    "addr:postcode":"13027",
    "addr:street":"Linda Ln",
    "iso:country":"US",
    "sg:address":"3417 Linda Ln",
    "sg:city":"Baldwinsville",
    "sg:classifiers":[
        {
            "category":"Professional",
            "subcategory":"Accounting & Tax Preparation",
            "type":"Services"
        }
    ],
    "sg:phone":"+1 315 409 0080",
    "sg:postcode":"13027",
    "sg:province":"NY",
    "sg:tags":[
        "payroll",
        "bookkeeping",
        "return",
        "preparation-business"
    ],
    "sg:website":"http://www.cnybsvc.com",
    "wof:name":"Complete Small Business Service",
    "wof:placetype":"venue"
},
  "geometry": {"coordinates":[-76.275795,43.184819],"type":"Point"}
}