{
  "type": "Feature",
  "properties": {
    "iso:country":"US",
    "sg:address":"225 Ballard Rd",
    "sg:city":"Gansevoort",
    "sg:classifiers":[
        {
            "category":"Food & Beverages",
            "subcategory":"Groceries & Convenience Stores",
            "type":"Retail Goods"
        }
    ],
    "sg:phone":"+1 518 584 8830",
    "sg:postcode":"12831",
    "sg:province":"NY",
    "wof:name":"Stewart's Shops",
    "wof:placetype":"venue"
},
  "geometry": {"coordinates":[-73.71757100000001,43.171201],"type":"Point"}
}