{
  "type": "Feature",
  "properties": {
    "addr:full":"418 E 173rd St Bronx NY 10457",
    "addr:housenumber":"418",
    "addr:postcode":"10457",
    "addr:street":"E 173Rd St",
    "iso:country":"US",
    "sg:address":"418 E 173rd St",
    "sg:city":"Bronx",
    "sg:classifiers":[
        {
            "category":"Professional",
            "subcategory":"Management & Consulting",
            "type":"Services"
        }
    ],
    "sg:phone":"+1   ",
    "sg:postcode":"10457",
    "sg:province":"NY",
    "sg:tags":[
        "retail",
        "direct",
        "sales"
    ],
    "wof:name":"Maria Pena & Jose Alonzo",
    "wof:placetype":"venue"
},
  "geometry": {"coordinates":[-73.903576,40.843004],"type":"Point"}
}