{
  "type": "Feature",
  "properties": {
    "iso:country":"US",
    "sg:address":"1136 Route 9",
    "sg:city":"Wappingers Falls",
    "sg:classifiers":[
        {
            "category":"Professional",
            "subcategory":"Lawyer & Legal Services",
            "type":"Services"
        }
    ],
    "sg:phone":"+1 845 298 2000",
    "sg:postcode":"12590",
    "sg:province":"NY",
    "sg:tags":[
        "personal",
        "injury"
    ],
    "wof:name":"Viglotti Louis J Atty",
    "wof:placetype":"venue"
},
  "geometry": {"coordinates":[-73.90619700000001,41.565498],"type":"Point"}
}