{
  "type": "Feature",
  "properties": {
    "addr:full":"2604 8th Ave New York NY 10030",
    "addr:housenumber":"2604",
    "addr:postcode":"10030",
    "addr:street":"8Th Ave",
    "iso:country":"US",
    "sg:address":"2604 8th Ave",
    "sg:city":"New York",
    "sg:classifiers":[
        {
            "category":"Personal",
            "subcategory":"Beauty Salon",
            "type":"Services"
        }
    ],
    "sg:phone":"+1   ",
    "sg:postcode":"10030",
    "sg:province":"NY",
    "sg:tags":[
        "shop"
    ],
    "wof:name":"Tear Drops of Elegance Beauty",
    "wof:placetype":"venue"
},
  "geometry": {"coordinates":[-73.94492099999999,40.818466],"type":"Point"}
}