{
  "type": "Feature",
  "properties": {
    "iso:country":"US",
    "sg:address":"101 E State St",
    "sg:city":"Gloversville",
    "sg:classifiers":[
        {
            "category":"Health Services",
            "subcategory":"Doctor",
            "type":"Services"
        }
    ],
    "sg:phone":"+1 518 725 4216",
    "sg:postcode":"12078",
    "sg:province":"NY",
    "sg:tags":[
        "dentist"
    ],
    "wof:name":"John M Fox DDS",
    "wof:placetype":"venue"
},
  "geometry": {"coordinates":[-74.328322,43.068296],"type":"Point"}
}