{
  "type": "Feature",
  "properties": {
    "iso:country":"US",
    "sg:address":"569 Lexington Ave",
    "sg:city":"New York",
    "sg:classifiers":[
        {
            "category":"Personal",
            "subcategory":"Nail Salon",
            "type":"Services"
        }
    ],
    "sg:phone":"+1 212 813 2437",
    "sg:postcode":"10022",
    "sg:province":"NY",
    "wof:name":"Tiffany Nails Inc",
    "wof:placetype":"venue"
},
  "geometry": {"coordinates":[-73.97199999999999,40.757],"type":"Point"}
}