{
  "type": "Feature",
  "properties": {
    "addr:full":"23 Great Oak Ln Pittsford NY 14534",
    "addr:housenumber":"23",
    "addr:postcode":"14534",
    "addr:street":"Great Oak Ln",
    "iso:country":"US",
    "sg:address":"23 Great Oak Ln",
    "sg:city":"Pittsford",
    "sg:classifiers":[
        {
            "category":"Home & Garden",
            "subcategory":"Garden Supply",
            "type":"Retail Goods"
        }
    ],
    "sg:phone":"+1   ",
    "sg:postcode":"14534",
    "sg:province":"NY",
    "wof:name":"Oriental Garden Supply LLC",
    "wof:placetype":"venue"
},
  "geometry": {"coordinates":[-77.480423,43.059977],"type":"Point"}
}