{
  "type": "Feature",
  "properties": {
    "iso:country":"US",
    "sg:address":"1233 E 2nd St",
    "sg:city":"Jamestown",
    "sg:classifiers":[
        {
            "category":"Autos & Motor Vehicles",
            "subcategory":"Fuel & Gas Station",
            "type":"Retail Goods"
        }
    ],
    "sg:phone":"+1   ",
    "sg:postcode":"14701",
    "sg:province":"NY",
    "sg:tags":[
        "automobile",
        "station",
        "gasoline",
        "used"
    ],
    "wof:name":"Crescent Motors Inc",
    "wof:placetype":"venue"
},
  "geometry": {"coordinates":[-79.21789200000001,42.11151],"type":"Point"}
}