{
  "type": "Feature",
  "properties": {
    "iso:country":"US",
    "sg:address":"268 Middle Country Rd",
    "sg:city":"Coram",
    "sg:classifiers":[
        {
            "category":"Food & Beverages",
            "subcategory":"Liquor & Beverages",
            "type":"Retail Goods"
        }
    ],
    "sg:phone":"+1 631 698 1500",
    "sg:postcode":"11727",
    "sg:province":"NY",
    "sg:tags":[
        "beer",
        "spirit",
        "wine"
    ],
    "wof:name":"Path Liquors Inc",
    "wof:placetype":"venue"
},
  "geometry": {"coordinates":[-72.996696,40.870701],"type":"Point"}
}