{
  "type": "Feature",
  "properties": {
    "addr:full":"80 John Bay Rd Livingston NY 12526",
    "addr:housenumber":"80",
    "addr:postcode":"12526",
    "addr:street":"John Bay Rd",
    "iso:country":"US",
    "sg:address":"80 John Bay Rd",
    "sg:city":"Livingston",
    "sg:classifiers":[
        {
            "category":"Shopping",
            "subcategory":"Discount & Variety Stores",
            "type":"Retail Goods"
        },
        {
            "category":"Communications",
            "subcategory":"Film & Video Production",
            "type":"Services"
        }
    ],
    "sg:phone":"+1 518 537 5133",
    "sg:postcode":"12526",
    "sg:province":"NY",
    "sg:tags":[
        "motion",
        "merchandise",
        "general"
    ],
    "wof:name":"Blue Stores Films",
    "wof:placetype":"venue"
},
  "geometry": {"coordinates":[-73.82643899999999,42.119082],"type":"Point"}
}