{
  "type": "Feature",
  "properties": {
    "addr:full":"3940 Slusaric Rd North Tonawanda NY 14120",
    "addr:housenumber":"3940",
    "addr:postcode":"14120",
    "addr:street":"Slusaric Rd",
    "iso:country":"US",
    "sg:address":"3940 Slusaric Rd",
    "sg:city":"North Tonawanda",
    "sg:classifiers":[
        {
            "category":"Manufacturing",
            "subcategory":"Glass & Minerals",
            "type":"Manufacturing & Wholesale Goods"
        }
    ],
    "sg:phone":"+1   ",
    "sg:postcode":"14120",
    "sg:province":"NY",
    "sg:tags":[
        "mfg"
    ],
    "wof:name":"Crafts By Tami",
    "wof:placetype":"venue"
},
  "geometry": {"coordinates":[-78.829063,43.106102],"type":"Point"}
}