{
  "type": "Feature",
  "properties": {
    "addr:full":"26 Pine St Franklinville NY 14737",
    "addr:housenumber":"26",
    "addr:postcode":"14737",
    "addr:street":"Pine St",
    "iso:country":"US",
    "sg:address":"26 Pine St",
    "sg:city":"Franklinville",
    "sg:classifiers":[
        {
            "category":"Building & Trades",
            "subcategory":"Construction",
            "type":"Services"
        }
    ],
    "sg:phone":"+1 716 676 3662",
    "sg:postcode":"14737",
    "sg:province":"NY",
    "sg:tags":[
        "contractor"
    ],
    "wof:name":"L B Tiling Inc",
    "wof:placetype":"venue"
},
  "geometry": {"coordinates":[-78.456941,42.337782],"type":"Point"}
}