{
  "type": "Feature",
  "properties": {
    "addr:full":"614 Wythe Ave Brooklyn NY 11211",
    "addr:housenumber":"614",
    "addr:postcode":"11211",
    "addr:street":"Wythe Ave",
    "iso:country":"US",
    "sg:address":"614 Wythe Ave",
    "sg:city":"Brooklyn",
    "sg:classifiers":[
        {
            "category":"Local Transit",
            "type":"Transportation"
        }
    ],
    "sg:phone":"+1 718 388 5367",
    "sg:postcode":"11211",
    "sg:province":"NY",
    "sg:tags":[
        "bus",
        "line"
    ],
    "wof:name":"Schwartz Buses",
    "wof:placetype":"venue"
},
  "geometry": {"coordinates":[-73.966122,40.704655],"type":"Point"}
}