{
  "type": "Feature",
  "properties": {
    "wof:name":"Statue of Liberty",
    "wof:placetype":"venue"
},
  "geometry": {"coordinates":[-74.044526,40.689303],"type":"Point"}
}