{
  "type": "Feature",
  "properties": {
    "iso:country":"US",
    "sg:address":"273 Guy Lombardo Ave",
    "sg:city":"Freeport",
    "sg:classifiers":[
        {
            "category":"Building & Trades",
            "subcategory":"Construction",
            "type":"Services"
        }
    ],
    "sg:phone":"+1 516 623 0453",
    "sg:postcode":"11520",
    "sg:province":"NY",
    "sg:tags":[
        "general",
        "contractor"
    ],
    "wof:name":"Ace Construction",
    "wof:placetype":"venue"
},
  "geometry": {"coordinates":[-73.583438,40.648178],"type":"Point"}
}