{
  "type": "Feature",
  "properties": {
    "iso:country":"US",
    "sg:address":"217 Elridge St.",
    "sg:city":"New York",
    "sg:classifiers":[
        {
            "category":"Restaurant",
            "type":"Food & Drink"
        }
    ],
    "sg:menulink":"http://www.allmenus.com/ny/new-york/268113-apizz/menu/",
    "sg:phone":"+1 212 253 9199",
    "sg:postcode":"10002",
    "sg:province":"NY",
    "sg:tags":[
        "italian"
    ],
    "wof:name":"Apizz",
    "wof:placetype":"venue"
},
  "geometry": {"coordinates":[-73.989929,40.722128],"type":"Point"}
}