{
  "type": "Feature",
  "properties": {
    "addr:full":"18 Grant St Jamestown NY 14701",
    "addr:housenumber":"18",
    "addr:postcode":"14701",
    "addr:street":"Grant St",
    "iso:country":"US",
    "sg:address":"18 Grant St",
    "sg:city":"Jamestown",
    "sg:classifiers":[
        {
            "category":"Manufacturing",
            "subcategory":"Signs",
            "type":"Manufacturing & Wholesale Goods"
        }
    ],
    "sg:phone":"+1 716 664 9700",
    "sg:postcode":"14701",
    "sg:province":"NY",
    "wof:name":"Jamestown Sign Co LLC",
    "wof:placetype":"venue"
},
  "geometry": {"coordinates":[-79.23316800000001,42.10059],"type":"Point"}
}