{
  "type": "Feature",
  "properties": {
    "iso:country":"US",
    "sg:address":"120 Ball Cir",
    "sg:city":"Syracuse",
    "sg:classifiers":[
        {
            "category":"Building & Trades",
            "subcategory":"Construction",
            "type":"Services"
        }
    ],
    "sg:phone":"+1 315 477 0029",
    "sg:postcode":"13210",
    "sg:province":"NY",
    "sg:tags":[
        "commercial",
        "painting",
        "painter",
        "contractor"
    ],
    "wof:name":"Commercial & Residential Pntng",
    "wof:placetype":"venue"
},
  "geometry": {"coordinates":[-76.132532,43.011732],"type":"Point"}
}