{
  "type": "Feature",
  "properties": {
    "iso:country":"US",
    "sg:address":"41 Farries Ave",
    "sg:city":"Florida",
    "sg:classifiers":[
        {
            "category":"Building & Trades",
            "subcategory":"Landscaping Services",
            "type":"Services"
        }
    ],
    "sg:phone":"+1 845 651 7579",
    "sg:postcode":"10921",
    "sg:province":"NY",
    "sg:tags":[
        "consultant",
        "designer",
        "landscape",
        "contractor"
    ],
    "wof:name":"Czubak's Lookin' Good Landscape Inc",
    "wof:placetype":"venue"
},
  "geometry": {"coordinates":[-74.353644,41.335743],"type":"Point"}
}