{
  "type": "Feature",
  "properties": {
    "addr:full":"221 Ice Pond Rd Brewster NY 10509",
    "addr:housenumber":"221",
    "addr:postcode":"10509",
    "addr:street":"Ice Pond Rd",
    "iso:country":"US",
    "sg:address":"221 Ice Pond Rd",
    "sg:city":"Brewster",
    "sg:classifiers":[
        {
            "category":"Building & Trades",
            "subcategory":"Electrical",
            "type":"Services"
        }
    ],
    "sg:phone":"+1 845 878 7100",
    "sg:postcode":"10509",
    "sg:province":"NY",
    "sg:tags":[
        "electrician"
    ],
    "wof:name":"Independent Electric Corp",
    "wof:placetype":"venue"
},
  "geometry": {"coordinates":[-73.618229,41.443382],"type":"Point"}
}