{
  "type": "Feature",
  "properties": {
    "addr:full":"4532 Sunrise Hwy Oakdale NY 11769",
    "addr:housenumber":"4532",
    "addr:postcode":"11769",
    "addr:street":"Sunrise Hwy",
    "iso:country":"US",
    "sg:address":"4532 Sunrise Hwy",
    "sg:city":"Oakdale",
    "sg:classifiers":[
        {
            "category":"Restaurant",
            "type":"Food & Drink"
        }
    ],
    "sg:phone":"+1 631 589 1740",
    "sg:postcode":"11769",
    "sg:province":"NY",
    "sg:tags":[
        "pizza"
    ],
    "wof:name":"Village Pizza",
    "wof:placetype":"venue"
},
  "geometry": {"coordinates":[-73.11859,40.75323],"type":"Point"}
}