{
  "type": "Feature",
  "properties": {
    "iso:country":"US",
    "sg:address":"108 Church St",
    "sg:city":"Hermon",
    "sg:classifiers":[
        {
            "category":"Food & Beverages",
            "subcategory":"Groceries & Convenience Stores",
            "type":"Retail Goods"
        }
    ],
    "sg:phone":"+1 315 347 4822",
    "sg:postcode":"13652",
    "sg:province":"NY",
    "sg:tags":[
        "grocer"
    ],
    "wof:name":"IGA Store",
    "wof:placetype":"venue"
},
  "geometry": {"coordinates":[-75.230513,44.465316],"type":"Point"}
}