{
  "type": "Feature",
  "properties": {
    "addr:full":"52 Railroad St Victor NY 14564",
    "addr:housenumber":"52",
    "addr:postcode":"14564",
    "addr:street":"Railroad St",
    "iso:country":"US",
    "sg:address":"52 Railroad St",
    "sg:city":"Victor",
    "sg:classifiers":[
        {
            "category":"Personal",
            "subcategory":"Beauty Salon",
            "type":"Services"
        }
    ],
    "sg:phone":"+1 585 377 9320",
    "sg:postcode":"14564",
    "sg:province":"NY",
    "wof:name":"Zava Hair Studio",
    "wof:placetype":"venue"
},
  "geometry": {"coordinates":[-77.410568,42.974372],"type":"Point"}
}