{
  "type": "Feature",
  "properties": {
    "iso:country":"US",
    "sg:address":"390 Park Ave",
    "sg:city":"New York",
    "sg:classifiers":[
        {
            "category":"Wholesale",
            "subcategory":"Durable Goods & Equipment",
            "type":"Manufacturing & Wholesale Goods"
        }
    ],
    "sg:phone":"+1 212 610 3820",
    "sg:postcode":"10022",
    "sg:province":"NY",
    "sg:tags":[
        "optical"
    ],
    "wof:name":"Eid-Eyewear Intl Dist USA LLC",
    "wof:placetype":"venue"
},
  "geometry": {"coordinates":[-73.97242900000001,40.759344],"type":"Point"}
}