{
  "type": "Feature",
  "properties": {
    "addr:full":"21 S Franklin Ave Valley Stream NY 11580",
    "addr:housenumber":"21",
    "addr:postcode":"11580",
    "addr:street":"S Franklin Ave",
    "iso:country":"US",
    "sg:address":"21 S Franklin Ave",
    "sg:city":"Valley Stream",
    "sg:classifiers":[
        {
            "category":"Social Services",
            "subcategory":"Child Care",
            "type":"Services"
        }
    ],
    "sg:phone":"+1 516 825 1182",
    "sg:postcode":"11580",
    "sg:province":"NY",
    "sg:tags":[
        "day"
    ],
    "sg:website":"www.umc.org",
    "wof:name":"Grace United Methodist Church of Valley Stream",
    "wof:placetype":"venue"
},
  "geometry": {"coordinates":[-73.701302,40.6647],"type":"Point"}
}