{
  "type": "Feature",
  "properties": {
    "iso:country":"US",
    "sg:address":"51 Colony Rd",
    "sg:city":"Port Jeffrsn Sta",
    "sg:classifiers":[
        {
            "category":"Professional",
            "subcategory":"Testing Lab",
            "type":"Services"
        }
    ],
    "sg:phone":"+1 631 473 3516",
    "sg:postcode":"11776",
    "sg:province":"NY",
    "sg:tags":[
        "calibration"
    ],
    "wof:name":"Herold Calibration & Welding",
    "wof:placetype":"venue"
},
  "geometry": {"coordinates":[-73.048754,40.897556],"type":"Point"}
}