{
  "type": "Feature",
  "properties": {
    "addr:full":"302 W 40th Street New York NY 10018",
    "addr:housenumber":"302",
    "addr:postcode":"10018",
    "addr:street":"W 40Th Street",
    "iso:country":"US",
    "sg:address":"302 W 40th Street",
    "sg:city":"New York",
    "sg:classifiers":[
        {
            "category":"Food & Beverages",
            "subcategory":"Liquor & Beverages",
            "type":"Retail Goods"
        }
    ],
    "sg:phone":"+1 212 279 3865",
    "sg:postcode":"10018",
    "sg:province":"NY",
    "sg:tags":[
        "beer",
        "spirit",
        "wine"
    ],
    "wof:name":"Athens Wine & Liquor",
    "wof:placetype":"venue"
},
  "geometry": {"coordinates":[-73.990773,40.755954],"type":"Point"}
}