{
  "type": "Feature",
  "properties": {
    "addr:full":"298 Jericho Tpke Floral Park NY 11001",
    "addr:housenumber":"298",
    "addr:postcode":"11001",
    "addr:street":"Jericho Tpke",
    "iso:country":"US",
    "sg:address":"298 Jericho Tpke",
    "sg:city":"Floral Park",
    "sg:classifiers":[
        {
            "category":"Retail",
            "subcategory":"Repair Shop",
            "type":"Services"
        }
    ],
    "sg:phone":"+1 718 301 7334",
    "sg:postcode":"11001",
    "sg:province":"NY",
    "sg:tags":[
        "lock",
        "locksmith"
    ],
    "wof:name":"7 Day Always Emergency Lcksmth",
    "wof:placetype":"venue"
},
  "geometry": {"coordinates":[-73.69944099999999,40.729551],"type":"Point"}
}