{
  "type": "Feature",
  "properties": {
    "addr:full":"7 Paerdegat 6th St Brooklyn NY 11236",
    "addr:housenumber":"7",
    "addr:postcode":"11236",
    "addr:street":"Paerdegat 6Th St",
    "iso:country":"US",
    "sg:address":"7 Paerdegat 6th St",
    "sg:city":"Brooklyn",
    "sg:classifiers":[
        {
            "category":"Organizations",
            "subcategory":"Religious Organization",
            "type":"Services"
        }
    ],
    "sg:phone":"+1 718 444 4672",
    "sg:postcode":"11236",
    "sg:province":"NY",
    "sg:tags":[
        "clergy"
    ],
    "wof:name":"Josef Portowicz",
    "wof:placetype":"venue"
},
  "geometry": {"coordinates":[-73.908328,40.631107],"type":"Point"}
}