{
  "type": "Feature",
  "properties": {
    "addr:full":"882 Atlantic Ave Brooklyn NY 11238",
    "addr:housenumber":"882",
    "addr:postcode":"11238",
    "addr:street":"Atlantic Ave",
    "iso:country":"US",
    "sg:address":"882 Atlantic Ave",
    "sg:city":"Brooklyn",
    "sg:classifiers":[
        {
            "category":"Organizations",
            "subcategory":"Non-profit Organization",
            "type":"Services"
        }
    ],
    "sg:phone":"+1 718 230 5770",
    "sg:postcode":"11238",
    "sg:province":"NY",
    "sg:tags":[
        "medical",
        "management"
    ],
    "wof:name":"Rapid Medical Management Inc",
    "wof:placetype":"venue"
},
  "geometry": {"coordinates":[-73.966244,40.681468],"type":"Point"}
}