{
  "type": "Feature",
  "properties": {
    "addr:full":"286 Conklin Ave Binghamton NY 13903",
    "addr:housenumber":"286",
    "addr:postcode":"13903",
    "addr:street":"Conklin Ave",
    "iso:country":"US",
    "sg:address":"286 Conklin Ave",
    "sg:city":"Binghamton",
    "sg:classifiers":[
        {
            "category":"Restaurant",
            "type":"Food & Drink"
        }
    ],
    "sg:phone":"+1   ",
    "sg:postcode":"13903",
    "sg:province":"NY",
    "sg:tags":[
        "pizzeria"
    ],
    "wof:name":"Nandos Pizza & Subs",
    "wof:placetype":"venue"
},
  "geometry": {"coordinates":[-75.88982,42.095812],"type":"Point"}
}