{
  "type": "Feature",
  "properties": {
    "iso:country":"US",
    "sg:address":"365 W 28th Street Ofc",
    "sg:city":"New York",
    "sg:classifiers":[
        {
            "category":"Health Services",
            "subcategory":"Doctor",
            "type":"Services"
        }
    ],
    "sg:phone":"+1 212 645 1087",
    "sg:postcode":"10001",
    "sg:province":"NY",
    "sg:tags":[
        "medicine",
        "internal"
    ],
    "wof:name":"Ny Healthcare Geriatrics Internal Medicine",
    "wof:placetype":"venue"
},
  "geometry": {"coordinates":[-73.998508,40.749486],"type":"Point"}
}