{
  "type": "Feature",
  "properties": {
    "addr:full":"192 Stowe Dr Poughquag NY 12570",
    "addr:housenumber":"192",
    "addr:postcode":"12570",
    "addr:street":"Stowe Dr",
    "iso:country":"US",
    "sg:address":"192 Stowe Dr",
    "sg:city":"Poughquag",
    "sg:classifiers":[
        {
            "category":"Real Estate",
            "subcategory":"Real Estate Agent",
            "type":"Services"
        }
    ],
    "sg:phone":"+1 845 724 3065",
    "sg:postcode":"12570",
    "sg:province":"NY",
    "wof:name":"Benmar Realty Ltd",
    "wof:placetype":"venue"
},
  "geometry": {"coordinates":[-73.65254299999999,41.62883],"type":"Point"}
}