{
  "type": "Feature",
  "properties": {
    "addr:full":"1610 Bathgate Ave Bronx NY 10457",
    "addr:housenumber":"1610",
    "addr:postcode":"10457",
    "addr:street":"Bathgate Ave",
    "iso:country":"US",
    "sg:address":"1610 Bathgate Ave",
    "sg:city":"Bronx",
    "sg:classifiers":[
        {
            "category":"Building & Trades",
            "subcategory":"Construction",
            "type":"Services"
        }
    ],
    "sg:phone":"+1 718 294 5300",
    "sg:postcode":"10457",
    "sg:province":"NY",
    "sg:tags":[
        "house",
        "landscape"
    ],
    "wof:name":"Bronx Base Construction",
    "wof:placetype":"venue"
},
  "geometry": {"coordinates":[-73.901398,40.838608],"type":"Point"}
}