{
  "type": "Feature",
  "properties": {
    "iso:country":"US",
    "sg:address":"434 State St",
    "sg:city":"Schenectady",
    "sg:classifiers":[
        {
            "category":"Travel",
            "subcategory":"Hotels & Motels",
            "type":"Entertainment"
        }
    ],
    "sg:phone":"+1 518 688 1001",
    "sg:postcode":"12305",
    "sg:province":"NY",
    "sg:tags":[
        "operation",
        "business"
    ],
    "wof:name":"Parker Inn",
    "wof:placetype":"venue"
},
  "geometry": {"coordinates":[-73.94261299999999,42.813275],"type":"Point"}
}