{
  "type": "Feature",
  "properties": {
    "addr:full":"9 Wheeler Rd Florida NY 10921",
    "addr:housenumber":"9",
    "addr:postcode":"10921",
    "addr:street":"Wheeler Rd",
    "iso:country":"US",
    "sg:address":"9 Wheeler Rd",
    "sg:city":"Florida",
    "sg:classifiers":[
        {
            "category":"Freight",
            "type":"Transportation"
        }
    ],
    "sg:phone":"+1 845 651 8103",
    "sg:postcode":"10921",
    "sg:province":"NY",
    "sg:tags":[
        "trucking"
    ],
    "wof:name":"JDT Trucking Inc",
    "wof:placetype":"venue"
},
  "geometry": {"coordinates":[-74.36166900000001,41.32815],"type":"Point"}
}