{
  "type": "Feature",
  "properties": {
    "addr:full":"1220 Old Country Rd Westbury NY 11590",
    "addr:housenumber":"1220",
    "addr:postcode":"11590",
    "addr:street":"Old Country Rd",
    "iso:country":"US",
    "sg:address":"1220 Old Country Rd",
    "sg:city":"Westbury",
    "sg:classifiers":[
        {
            "category":"Shopping",
            "subcategory":"Mobile Phones",
            "type":"Retail Goods"
        }
    ],
    "sg:phone":"+1 516 683 8053",
    "sg:postcode":"11590",
    "sg:province":"NY",
    "sg:website":"www.diebold.com",
    "wof:name":"Diebold",
    "wof:placetype":"venue"
},
  "geometry": {"coordinates":[-73.601052,40.745441],"type":"Point"}
}