{
  "type": "Feature",
  "properties": {
    "addr:full":"506 E 74 St New York NY 10021",
    "addr:housenumber":"506;74",
    "addr:postcode":"10021",
    "addr:street":"E;St",
    "iso:country":"US",
    "sg:address":"506 E 74 St",
    "sg:city":"New York",
    "sg:classifiers":[
        {
            "category":"Shopping",
            "subcategory":"Used Merchandise",
            "type":"Retail Goods"
        }
    ],
    "sg:phone":"+1   ",
    "sg:postcode":"10021",
    "sg:province":"NY",
    "wof:name":"Woodard & Greenstein Antiques",
    "wof:placetype":"venue"
},
  "geometry": {"coordinates":[-73.9504,40.7671],"type":"Point"}
}