{
  "type": "Feature",
  "properties": {
    "iso:country":"US",
    "sg:address":"800 Spencerport Rd",
    "sg:city":"Rochester",
    "sg:classifiers":[
        {
            "category":"Health Services",
            "subcategory":"Doctor",
            "type":"Services"
        }
    ],
    "sg:phone":"+1 585 426 4880",
    "sg:postcode":"14606",
    "sg:province":"NY",
    "sg:tags":[
        "physician",
        "surgeon"
    ],
    "wof:name":"Eleanor B Mendoza MD",
    "wof:placetype":"venue"
},
  "geometry": {"coordinates":[-77.712913,43.172049],"type":"Point"}
}