{
  "type": "Feature",
  "properties": {
    "addr:full":"31 W 27 St New York NY 10001",
    "addr:housenumber":"31",
    "addr:postcode":"10001",
    "addr:street":"W 27 St",
    "iso:country":"US",
    "sg:address":"31 W 27 St",
    "sg:city":"New York",
    "sg:classifiers":[
        {
            "category":"Communications",
            "subcategory":"Film & Video Production",
            "type":"Services"
        }
    ],
    "sg:phone":"+1 212 867 4030",
    "sg:postcode":"10001",
    "sg:province":"NY",
    "sg:tags":[
        "motion",
        "picture",
        "studio",
        "producer"
    ],
    "wof:name":"Highway 61",
    "wof:placetype":"venue"
},
  "geometry": {"coordinates":[-73.99075499999999,40.745388],"type":"Point"}
}