{
  "type": "Feature",
  "properties": {
    "addr:full":"1530 College Point Blvd College Point NY 11356",
    "addr:housenumber":"1530",
    "addr:postcode":"11356",
    "addr:street":"College Point Blvd",
    "iso:country":"US",
    "sg:address":"1530 College Point Blvd",
    "sg:city":"College Point",
    "sg:classifiers":[
        {
            "category":"Building & Trades",
            "subcategory":"Locksmith",
            "type":"Services"
        }
    ],
    "sg:phone":"+1 718 785 3610",
    "sg:postcode":"11356",
    "sg:province":"NY",
    "sg:tags":[
        "key"
    ],
    "wof:name":"24 Hr AA Locksmith",
    "wof:placetype":"venue"
},
  "geometry": {"coordinates":[-73.846001,40.783901],"type":"Point"}
}