{
  "type": "Feature",
  "properties": {
    "addr:full":"18 Oxford St Northport NY 11768",
    "addr:housenumber":"18",
    "addr:postcode":"11768",
    "addr:street":"Oxford St",
    "iso:country":"US",
    "sg:address":"18 Oxford St",
    "sg:city":"Northport",
    "sg:classifiers":[
        {
            "category":"Professional",
            "type":"Services"
        }
    ],
    "sg:phone":"+1 631 757 7225",
    "sg:postcode":"11768",
    "sg:province":"NY",
    "sg:tags":[
        "establishment"
    ],
    "wof:name":"Brands & Stragegies",
    "wof:placetype":"venue"
},
  "geometry": {"coordinates":[-73.334371,40.903367],"type":"Point"}
}