{
  "type": "Feature",
  "properties": {
    "addr:full":"5395 Skinner Rd Marion NY 14505",
    "addr:housenumber":"5395",
    "addr:postcode":"14505",
    "addr:street":"Skinner Rd",
    "iso:country":"US",
    "sg:address":"5395 Skinner Rd",
    "sg:city":"Marion",
    "sg:classifiers":[
        {
            "category":"Manufacturing",
            "subcategory":"Wood Products",
            "type":"Manufacturing & Wholesale Goods"
        }
    ],
    "sg:phone":"+1 315 331 2850",
    "sg:postcode":"14505",
    "sg:province":"NY",
    "sg:tags":[
        "pallet",
        "skid"
    ],
    "wof:name":"Peter C Herman Inc",
    "wof:placetype":"venue"
},
  "geometry": {"coordinates":[-77.12662899999999,43.149522],"type":"Point"}
}