{
  "type": "Feature",
  "properties": {
    "addr:full":"973 Columbus Ave New York NY 10025",
    "addr:housenumber":"973",
    "addr:postcode":"10025",
    "addr:street":"Columbus Ave",
    "iso:country":"US",
    "sg:address":"973 Columbus Ave",
    "sg:city":"New York",
    "sg:classifiers":[
        {
            "category":"Utilities",
            "subcategory":"Mobile Phone",
            "type":"Services"
        }
    ],
    "sg:phone":"+1   ",
    "sg:postcode":"10025",
    "sg:province":"NY",
    "sg:tags":[
        "communication",
        "radiotelephone"
    ],
    "wof:name":"Prestige Telbeecom",
    "wof:placetype":"venue"
},
  "geometry": {"coordinates":[-73.96212199999999,40.800018],"type":"Point"}
}