{
  "type": "Feature",
  "properties": {
    "addr:full":"493 McDonald Ave Brooklyn NY 11218",
    "addr:housenumber":"493",
    "addr:postcode":"11218",
    "addr:street":"Mcdonald Ave",
    "iso:country":"US",
    "sg:address":"493 McDonald Ave",
    "sg:city":"Brooklyn",
    "sg:classifiers":[
        {
            "category":"Professional",
            "subcategory":"Accounting & Tax Preparation",
            "type":"Services"
        }
    ],
    "sg:phone":"+1 718 436 4601",
    "sg:postcode":"11218",
    "sg:province":"NY",
    "sg:tags":[
        "accountant"
    ],
    "wof:name":"Salam Sarwar",
    "wof:placetype":"venue"
},
  "geometry": {"coordinates":[-73.979161,40.641413],"type":"Point"}
}