{
  "type": "Feature",
  "properties": {
    "addr:full":"12 Liberty St Arcade NY 14009",
    "addr:housenumber":"12",
    "addr:postcode":"14009",
    "addr:street":"Liberty St",
    "iso:country":"US",
    "sg:address":"12 Liberty St",
    "sg:city":"Arcade",
    "sg:classifiers":[
        {
            "category":"Retail",
            "subcategory":"Laundry & Dry Cleaning",
            "type":"Services"
        }
    ],
    "sg:phone":"+1 716 492 4900",
    "sg:postcode":"14009",
    "sg:province":"NY",
    "wof:name":"Arcade Laundry",
    "wof:placetype":"venue"
},
  "geometry": {"coordinates":[-78.422738,42.533893],"type":"Point"}
}