{
  "type": "Feature",
  "properties": {
    "addr:full":"920 Knollwood Rd White Plains NY 10603",
    "addr:housenumber":"920",
    "addr:postcode":"10603",
    "addr:street":"Knollwood Rd",
    "iso:country":"US",
    "sg:address":"920 Knollwood Rd",
    "sg:city":"White Plains",
    "sg:classifiers":[
        {
            "category":"Building & Trades",
            "subcategory":"Construction",
            "type":"Services"
        }
    ],
    "sg:phone":"+1 914 592 2344",
    "sg:postcode":"10603",
    "sg:province":"NY",
    "sg:tags":[
        "stone",
        "masonry",
        "work",
        "other"
    ],
    "wof:name":"MFA Stonework and Masonry",
    "wof:placetype":"venue"
},
  "geometry": {"coordinates":[-73.799477,41.062708],"type":"Point"}
}