{
  "type": "Feature",
  "properties": {
    "addr:full":"119 Mackenzie St Brooklyn NY 11235",
    "addr:housenumber":"119",
    "addr:postcode":"11235",
    "addr:street":"Mackenzie St",
    "iso:country":"US",
    "sg:address":"119 Mackenzie St",
    "sg:city":"Brooklyn",
    "sg:classifiers":[
        {
            "category":"Wholesale",
            "subcategory":"Computers",
            "type":"Manufacturing & Wholesale Goods"
        }
    ],
    "sg:phone":"+1 718 648 1822",
    "sg:postcode":"11235",
    "sg:province":"NY",
    "sg:tags":[
        "computer-wholesale",
        "manufacturer"
    ],
    "wof:name":"Steinberg Corporation",
    "wof:placetype":"venue"
},
  "geometry": {"coordinates":[-73.939998,40.579354],"type":"Point"}
}