{
  "type": "Feature",
  "properties": {
    "addr:full":"59 Bayville Ave Bayville NY 11709",
    "addr:housenumber":"59",
    "addr:postcode":"11709",
    "addr:street":"Bayville Ave",
    "iso:country":"US",
    "sg:address":"59 Bayville Ave",
    "sg:city":"Bayville",
    "sg:classifiers":[
        {
            "category":"Health Services",
            "subcategory":"Nursing And Care Facility",
            "type":"Services"
        }
    ],
    "sg:phone":"+1 516 628 1350",
    "sg:postcode":"11709",
    "sg:province":"NY",
    "sg:tags":[
        "home",
        "convalescent"
    ],
    "sg:website":"www.jonesmanor.com",
    "wof:name":"Jones Manor On The Sound",
    "wof:placetype":"venue"
},
  "geometry": {"coordinates":[-73.573279,40.910544],"type":"Point"}
}