{
  "type": "Feature",
  "properties": {
    "addr:full":"875 Ave of the Americas New York NY 10001",
    "addr:housenumber":"875",
    "addr:postcode":"10001",
    "addr:street":"Ave Of The Americas",
    "iso:country":"US",
    "sg:address":"875 Ave of the Americas",
    "sg:city":"New York",
    "sg:classifiers":[
        {
            "category":"Health Services",
            "subcategory":"Clinic",
            "type":"Services"
        }
    ],
    "sg:phone":"+1 212 331 6300",
    "sg:postcode":"10001",
    "sg:province":"NY",
    "wof:name":"Healthcare Capital Resources",
    "wof:placetype":"venue"
},
  "geometry": {"coordinates":[-73.988714,40.748512],"type":"Point"}
}