{
  "type": "Feature",
  "properties": {
    "iso:country":"US",
    "sg:address":"1099 Spring St",
    "sg:city":"Catskill",
    "sg:classifiers":[
        {
            "category":"Autos & Motor Vehicles",
            "subcategory":"Fuel & Gas Station",
            "type":"Retail Goods"
        }
    ],
    "sg:phone":"+1   ",
    "sg:postcode":"12414",
    "sg:province":"NY",
    "sg:tags":[
        "convenience",
        "station",
        "store"
    ],
    "wof:name":"Getty Food Mart",
    "wof:placetype":"venue"
},
  "geometry": {"coordinates":[-73.861857,42.227282],"type":"Point"}
}