{
  "type": "Feature",
  "properties": {
    "iso:country":"US",
    "sg:address":"3594 Nostrand Ave",
    "sg:city":"Brooklyn",
    "sg:classifiers":[
        {
            "category":"Ice Cream",
            "type":"Food & Drink"
        }
    ],
    "sg:phone":"+1 718 934 8200",
    "sg:postcode":"11229",
    "sg:province":"NY",
    "sg:tags":[
        "frozen",
        "yogurt"
    ],
    "sg:website":"www.carvel.com/home.html",
    "wof:name":"Carvel",
    "wof:placetype":"venue"
},
  "geometry": {"coordinates":[-73.941176,40.596324],"type":"Point"}
}