{
  "type": "Feature",
  "properties": {
    "addr:full":"61 Old Tappan Rd Tappan NY 10983",
    "addr:housenumber":"61",
    "addr:postcode":"10983",
    "addr:street":"Old Tappan Rd",
    "iso:country":"US",
    "sg:address":"61 Old Tappan Rd",
    "sg:city":"Tappan",
    "sg:classifiers":[
        {
            "category":"Retail",
            "subcategory":"Laundry & Dry Cleaning",
            "type":"Services"
        }
    ],
    "sg:phone":"+1 845 398 2612",
    "sg:postcode":"10983",
    "sg:province":"NY",
    "sg:tags":[
        "cleaners"
    ],
    "wof:name":"Stateline Cleaners",
    "wof:placetype":"venue"
},
  "geometry": {"coordinates":[-73.949186,41.022173],"type":"Point"}
}