{
  "type": "Feature",
  "properties": {
    "addr:full":"1740 Rockaway Ave Hewlett NY 11557",
    "addr:housenumber":"1740",
    "addr:postcode":"11557",
    "addr:street":"Rockaway Ave",
    "iso:country":"US",
    "sg:address":"1740 Rockaway Ave",
    "sg:city":"Hewlett",
    "sg:classifiers":[
        {
            "category":"Building & Trades",
            "subcategory":"Construction",
            "type":"Services"
        }
    ],
    "sg:phone":"+1 516 742 4291",
    "sg:postcode":"11557",
    "sg:province":"NY",
    "sg:tags":[
        "general",
        "contractor"
    ],
    "wof:name":"Northeastern Building & Dev Co",
    "wof:placetype":"venue"
},
  "geometry": {"coordinates":[-73.69019400000001,40.647538],"type":"Point"}
}