{
  "type": "Feature",
  "properties": {
    "addr:full":"19 Brown Rd Plattsburgh NY 12901",
    "addr:housenumber":"19",
    "addr:postcode":"12901",
    "addr:street":"Brown Rd",
    "iso:country":"US",
    "sg:address":"19 Brown Rd",
    "sg:city":"Plattsburgh",
    "sg:classifiers":[
        {
            "category":"Utilities",
            "subcategory":"Fuel Oil & Lpg",
            "type":"Services"
        }
    ],
    "sg:phone":"+1 518 561 4797",
    "sg:postcode":"12901",
    "sg:province":"NY",
    "sg:tags":[
        "dealer",
        "supply"
    ],
    "wof:name":"Albert J Brown Co",
    "wof:placetype":"venue"
},
  "geometry": {"coordinates":[-73.51054999999999,44.675228],"type":"Point"}
}