{
  "type": "Feature",
  "properties": {
    "addr:full":"97 Lawrence Hill Rd Huntington NY 11724",
    "addr:housenumber":"97",
    "addr:postcode":"11724",
    "addr:street":"Lawrence Hill Rd",
    "iso:country":"US",
    "sg:address":"97 Lawrence Hill Rd",
    "sg:city":"Huntington",
    "sg:classifiers":[
        {
            "category":"Real Estate",
            "subcategory":"Developer",
            "type":"Services"
        }
    ],
    "sg:phone":"+1 631 547 1200",
    "sg:postcode":"11724",
    "sg:province":"NY",
    "wof:name":"Harmon Development Corp",
    "wof:placetype":"venue"
},
  "geometry": {"coordinates":[-73.442329,40.865817],"type":"Point"}
}