{
  "type": "Feature",
  "properties": {
    "iso:country":"US",
    "sg:address":"379 Bleecker St",
    "sg:city":"New York",
    "sg:classifiers":[
        {
            "category":"Shopping",
            "subcategory":"Clothing, Apparel, & Fashions",
            "type":"Retail Goods"
        }
    ],
    "sg:phone":"+1 212 627 9202",
    "sg:postcode":"10014",
    "sg:province":"NY",
    "sg:tags":[
        "men's",
        "clothing",
        "women's"
    ],
    "wof:name":"Brunello Cucinelli",
    "wof:placetype":"venue"
},
  "geometry": {"coordinates":[-74.004867,40.735096],"type":"Point"}
}