{
  "type": "Feature",
  "properties": {
    "addr:full":"847 11th St Ronkonkoma NY 11779",
    "addr:housenumber":"847",
    "addr:postcode":"11779",
    "addr:street":"11Th St",
    "iso:country":"US",
    "sg:address":"847 11th St",
    "sg:city":"Ronkonkoma",
    "sg:classifiers":[
        {
            "category":"Building & Trades",
            "subcategory":"Plumbing",
            "type":"Services"
        }
    ],
    "sg:phone":"+1 516 921 0644",
    "sg:postcode":"11779",
    "sg:province":"NY",
    "sg:tags":[
        "septic"
    ],
    "wof:name":"Emergency Cesspool",
    "wof:placetype":"venue"
},
  "geometry": {"coordinates":[-73.116229,40.792437],"type":"Point"}
}