{
  "type": "Feature",
  "properties": {
    "addr:full":"719 Washington Ave Brooklyn NY 11238",
    "addr:housenumber":"719",
    "addr:postcode":"11238",
    "addr:street":"Washington Ave",
    "iso:country":"US",
    "sg:address":"719 Washington Ave",
    "sg:city":"Brooklyn",
    "sg:classifiers":[
        {
            "category":"Health Services",
            "subcategory":"Health Practitioner",
            "type":"Services"
        }
    ],
    "sg:phone":"+1 718 636 8200",
    "sg:postcode":"11238",
    "sg:province":"NY",
    "sg:tags":[
        "nurse",
        "registry"
    ],
    "wof:name":"STAT Nurses Agency Inc",
    "wof:placetype":"venue"
},
  "geometry": {"coordinates":[-73.963206,40.675321],"type":"Point"}
}