{
  "type": "Feature",
  "properties": {
    "iso:country":"US",
    "sg:address":"213 Stony Point Rd",
    "sg:city":"Rochester",
    "sg:classifiers":[
        {
            "category":"Building & Trades",
            "subcategory":"Construction",
            "type":"Services"
        }
    ],
    "sg:phone":"+1 585 594 4172",
    "sg:postcode":"14624",
    "sg:province":"NY",
    "sg:tags":[
        "house"
    ],
    "wof:name":"General Remodeling By Jovan To",
    "wof:placetype":"venue"
},
  "geometry": {"coordinates":[-77.794471,43.135807],"type":"Point"}
}