{
  "type": "Feature",
  "properties": {
    "addr:full":"158 W 44th St New York NY 10036",
    "addr:housenumber":"158",
    "addr:postcode":"10036",
    "addr:street":"W 44Th St",
    "iso:country":"US",
    "sg:address":"158 W 44th St",
    "sg:city":"New York",
    "sg:classifiers":[
        {
            "category":"Deli",
            "type":"Food & Drink"
        }
    ],
    "sg:phone":"+1 212 944 1234",
    "sg:postcode":"10036",
    "sg:province":"NY",
    "wof:name":"Times Deli Inc",
    "wof:placetype":"venue"
},
  "geometry": {"coordinates":[-73.98539700000001,40.757099],"type":"Point"}
}