{
  "type": "Feature",
  "properties": {
    "iso:country":"US",
    "sg:address":"143 Algonquin Park Rd",
    "sg:city":"Plattsburgh",
    "sg:classifiers":[
        {
            "category":"Professional",
            "subcategory":"Accounting & Tax Preparation",
            "type":"Services"
        }
    ],
    "sg:phone":"+1 518 563 8290",
    "sg:postcode":"12901",
    "sg:province":"NY",
    "sg:tags":[
        "billing"
    ],
    "wof:name":"Advantage Physician Rmbrsmnt",
    "wof:placetype":"venue"
},
  "geometry": {"coordinates":[-73.394007,44.731308],"type":"Point"}
}