{
  "type": "Feature",
  "properties": {
    "addr:full":"3240 Henry Hudson Pkwy E Bronx NY 10463",
    "addr:housenumber":"3240",
    "addr:postcode":"10463",
    "addr:street":"Henry Hudson Pkwy E",
    "iso:country":"US",
    "sg:address":"3240 Henry Hudson Pkwy E",
    "sg:city":"Bronx",
    "sg:classifiers":[
        {
            "category":"Professional",
            "subcategory":"Detective & Security Services",
            "type":"Services"
        }
    ],
    "sg:phone":"+1 718 601 6542",
    "sg:postcode":"10463",
    "sg:province":"NY",
    "wof:name":"PMH Consulting",
    "wof:placetype":"venue"
},
  "geometry": {"coordinates":[-73.91247799999999,40.886068],"type":"Point"}
}