{
  "type": "Feature",
  "properties": {
    "addr:full":"15 W 36 St New York NY 10018",
    "addr:housenumber":"15",
    "addr:postcode":"10018",
    "addr:street":"W 36 St",
    "iso:country":"US",
    "sg:address":"15 W 36 St",
    "sg:city":"New York",
    "sg:classifiers":[
        {
            "category":"Professional",
            "type":"Services"
        }
    ],
    "sg:phone":"+1 212 244 0132",
    "sg:postcode":"10018",
    "sg:province":"NY",
    "sg:tags":[
        "establishment"
    ],
    "wof:name":"Ammy Car",
    "wof:placetype":"venue"
},
  "geometry": {"coordinates":[-73.986463,40.750954],"type":"Point"}
}