{
  "type": "Feature",
  "properties": {
    "addr:full":"292 5th Ave New York NY 10001",
    "addr:housenumber":"292",
    "addr:postcode":"10001",
    "addr:street":"5Th Ave",
    "iso:country":"US",
    "sg:address":"292 5th Ave",
    "sg:city":"New York",
    "sg:classifiers":[
        {
            "category":"Travel",
            "subcategory":"Travel Agent",
            "type":"Entertainment"
        }
    ],
    "sg:phone":"+1   ",
    "sg:postcode":"10001",
    "sg:province":"NY",
    "sg:tags":[
        "agency"
    ],
    "wof:name":"A&C Travel Agency",
    "wof:placetype":"venue"
},
  "geometry": {"coordinates":[-73.986206,40.74622],"type":"Point"}
}