{
  "type": "Feature",
  "properties": {
    "iso:country":"US",
    "sg:address":"350 Lexington Ave",
    "sg:city":"New York",
    "sg:classifiers":[
        {
            "category":"Real Estate",
            "subcategory":"Real Estate Agent",
            "type":"Services"
        }
    ],
    "sg:phone":"+1 212 661 9299",
    "sg:postcode":"10016",
    "sg:province":"NY",
    "wof:name":"JC Strougo Realty",
    "wof:placetype":"venue"
},
  "geometry": {"coordinates":[-73.977435,40.749539],"type":"Point"}
}