{
  "type": "Feature",
  "properties": {
    "iso:country":"US",
    "sg:address":"27 Masten Ave",
    "sg:city":"Buffalo",
    "sg:classifiers":[
        {
            "category":"Government",
            "subcategory":"Office",
            "type":"Public Place"
        }
    ],
    "sg:phone":"+1 716 881 7417",
    "sg:postcode":"14209",
    "sg:province":"NY",
    "wof:name":"NYS Dmna",
    "wof:placetype":"venue"
},
  "geometry": {"coordinates":[-78.85967599999999,42.903168],"type":"Point"}
}