{
  "type": "Feature",
  "properties": {
    "addr:full":"6 Winners Cir Albany NY 12205",
    "addr:housenumber":"6",
    "addr:postcode":"12205",
    "addr:street":"Winners Cir",
    "iso:country":"US",
    "sg:address":"6 Winners Cir",
    "sg:city":"Albany",
    "sg:classifiers":[
        {
            "category":"Government",
            "subcategory":"Office",
            "type":"Public Place"
        }
    ],
    "sg:phone":"+1 518 459 2516",
    "sg:postcode":"12205",
    "sg:province":"NY",
    "sg:tags":[
        "village"
    ],
    "wof:name":"Colonie Town Nurse",
    "wof:placetype":"venue"
},
  "geometry": {"coordinates":[-73.798897,42.718448],"type":"Point"}
}