{
  "type": "Feature",
  "properties": {
    "addr:full":"1425 Amsterdam Ave New York NY 10027",
    "addr:housenumber":"1425",
    "addr:postcode":"10027",
    "addr:street":"Amsterdam Ave",
    "iso:country":"US",
    "sg:address":"1425 Amsterdam Ave",
    "sg:city":"New York",
    "sg:classifiers":[
        {
            "category":"Wholesale",
            "subcategory":"Machinery & Supplies",
            "type":"Manufacturing & Wholesale Goods"
        }
    ],
    "sg:phone":"+1 212 690 4937",
    "sg:postcode":"10027",
    "sg:province":"NY",
    "sg:tags":[
        "security",
        "industrial",
        "guard"
    ],
    "wof:name":"Preferred Security Services Co",
    "wof:placetype":"venue"
},
  "geometry": {"coordinates":[-73.954122,40.816146],"type":"Point"}
}