{
  "type": "Feature",
  "properties": {
    "addr:full":"424 Main St Buffalo NY 14202",
    "addr:housenumber":"424",
    "addr:postcode":"14202",
    "addr:street":"Main St",
    "iso:country":"US",
    "sg:address":"424 Main St",
    "sg:city":"Buffalo",
    "sg:classifiers":[
        {
            "category":"Shopping",
            "subcategory":"Clothing, Apparel, & Fashions",
            "type":"Retail Goods"
        }
    ],
    "sg:phone":"+1   ",
    "sg:postcode":"14202",
    "sg:province":"NY",
    "wof:name":"Tom James of Buffalo 249",
    "wof:placetype":"venue"
},
  "geometry": {"coordinates":[-78.874478,42.885571],"type":"Point"}
}