{
  "type": "Feature",
  "properties": {
    "addr:full":"3504 Church Ave Brooklyn NY 11203",
    "addr:housenumber":"3504",
    "addr:postcode":"11203",
    "addr:street":"Church Ave",
    "iso:country":"US",
    "sg:address":"3504 Church Ave",
    "sg:city":"Brooklyn",
    "sg:classifiers":[
        {
            "category":"Social Services",
            "subcategory":"Child Care",
            "type":"Services"
        }
    ],
    "sg:phone":"+1 718 941 1102",
    "sg:postcode":"11203",
    "sg:province":"NY",
    "sg:tags":[
        "day"
    ],
    "sg:website":"www.pbchildrensacademy.com",
    "wof:name":"P B Children's Academy",
    "wof:placetype":"venue"
},
  "geometry": {"coordinates":[-73.94450399999999,40.651001],"type":"Point"}
}