{
  "type": "Feature",
  "properties": {
    "addr:full":"6758 E Eden Rd Hamburg NY 14075",
    "addr:housenumber":"6758",
    "addr:postcode":"14075",
    "addr:street":"E Eden Rd",
    "iso:country":"US",
    "sg:address":"6758 E Eden Rd",
    "sg:city":"Hamburg",
    "sg:classifiers":[
        {
            "category":"Wholesale",
            "subcategory":"Sporting Goods",
            "type":"Manufacturing & Wholesale Goods"
        }
    ],
    "sg:phone":"+1 716 648 6456",
    "sg:postcode":"14075",
    "sg:province":"NY",
    "wof:name":"Elite Fitness Service",
    "wof:placetype":"venue"
},
  "geometry": {"coordinates":[-78.832322,42.704945],"type":"Point"}
}