{
  "type": "Feature",
  "properties": {
    "addr:full":"470 W Water St Elmira NY 14905",
    "addr:housenumber":"470",
    "addr:postcode":"14905",
    "addr:street":"W Water St",
    "iso:country":"US",
    "sg:address":"470 W Water St",
    "sg:city":"Elmira",
    "sg:classifiers":[
        {
            "category":"Health Services",
            "subcategory":"Optometrist",
            "type":"Services"
        }
    ],
    "sg:phone":"+1 607 734 1679",
    "sg:postcode":"14905",
    "sg:province":"NY",
    "sg:tags":[
        "optical",
        "good"
    ],
    "wof:name":"David P Dozack OD",
    "wof:placetype":"venue"
},
  "geometry": {"coordinates":[-76.815916,42.085556],"type":"Point"}
}