{
  "type": "Feature",
  "properties": {
    "iso:country":"US",
    "sg:address":"12 Steven Dr",
    "sg:city":"Ossining",
    "sg:classifiers":[
        {
            "category":"Professional",
            "subcategory":"Management & Consulting",
            "type":"Services"
        }
    ],
    "sg:phone":"+1 914 923 0021",
    "sg:postcode":"10562",
    "sg:province":"NY",
    "sg:tags":[
        "consultant",
        "lighting"
    ],
    "wof:name":"Whitehouse Lighting Design",
    "wof:placetype":"venue"
},
  "geometry": {"coordinates":[-73.864435,41.185602],"type":"Point"}
}