{
  "type": "Feature",
  "properties": {
    "addr:full":"130 Fort Washington Ave New York NY 10032",
    "addr:housenumber":"130",
    "addr:postcode":"10032",
    "addr:street":"Fort Washington Ave",
    "iso:country":"US",
    "sg:address":"130 Fort Washington Ave",
    "sg:city":"New York",
    "sg:classifiers":[
        {
            "category":"Local Transit",
            "type":"Transportation"
        }
    ],
    "sg:phone":"+1   ",
    "sg:postcode":"10032",
    "sg:province":"NY",
    "sg:tags":[
        "passenger"
    ],
    "wof:name":"Country Wide Transportation",
    "wof:placetype":"venue"
},
  "geometry": {"coordinates":[-73.943123,40.839735],"type":"Point"}
}