{
  "type": "Feature",
  "properties": {
    "addr:full":"2007 Syosset Dr Cazenovia NY 13035",
    "addr:housenumber":"2007",
    "addr:postcode":"13035",
    "addr:street":"Syosset Dr",
    "iso:country":"US",
    "sg:address":"2007 Syosset Dr",
    "sg:city":"Cazenovia",
    "sg:classifiers":[
        {
            "category":"Manufacturing",
            "subcategory":"Printing",
            "type":"Manufacturing & Wholesale Goods"
        }
    ],
    "sg:phone":"+1 315 655 8499",
    "sg:postcode":"13035",
    "sg:province":"NY",
    "sg:tags":[
        "publisher"
    ],
    "wof:name":"Book Source Magazine",
    "wof:placetype":"venue"
},
  "geometry": {"coordinates":[-75.848505,42.942123],"type":"Point"}
}