{
  "type": "Feature",
  "properties": {
    "addr:full":"200 Union Ave Exd Johnstown NY 12095",
    "addr:housenumber":"200",
    "addr:postcode":"12095",
    "addr:street":"Union Ave Exd",
    "iso:country":"US",
    "sg:address":"200 Union Ave Exd",
    "sg:city":"Johnstown",
    "sg:classifiers":[
        {
            "category":"Building & Trades",
            "subcategory":"Construction",
            "type":"Services"
        }
    ],
    "sg:phone":"+1 518 762 5526",
    "sg:postcode":"12095",
    "sg:province":"NY",
    "sg:tags":[
        "commercial",
        "window",
        "installation"
    ],
    "wof:name":"Pioneer Manufacturing",
    "wof:placetype":"venue"
},
  "geometry": {"coordinates":[-74.398338,42.993146],"type":"Point"}
}