{
  "type": "Feature",
  "properties": {
    "iso:country":"US",
    "sg:address":"221 Park Ave S",
    "sg:city":"New York",
    "sg:classifiers":[
        {
            "category":"Retail",
            "subcategory":"Auto Repair",
            "type":"Services"
        }
    ],
    "sg:phone":"+1 212 993 8285",
    "sg:postcode":"10003",
    "sg:province":"NY",
    "sg:tags":[
        "automotive",
        "electric",
        "automobile"
    ],
    "wof:name":"2u2u 24 Hour Auto Repair",
    "wof:placetype":"venue"
},
  "geometry": {"coordinates":[-73.988159,40.737732],"type":"Point"}
}