{
  "type": "Feature",
  "properties": {
    "iso:country":"US",
    "sg:address":"2488 Montauk Hwy",
    "sg:city":"Bridgehampton",
    "sg:classifiers":[
        {
            "category":"Restaurant",
            "type":"Food & Drink"
        }
    ],
    "sg:phone":"+1   ",
    "sg:postcode":"11932",
    "sg:province":"NY",
    "sg:tags":[
        "eating"
    ],
    "wof:name":"Starbucks",
    "wof:placetype":"venue"
},
  "geometry": {"coordinates":[-72.30462900000001,40.936066],"type":"Point"}
}