{
  "type": "Feature",
  "properties": {
    "iso:country":"US",
    "sg:address":"88 E Marie St",
    "sg:city":"Hicksville",
    "sg:classifiers":[
        {
            "category":"Building & Trades",
            "subcategory":"Construction",
            "type":"Services"
        }
    ],
    "sg:phone":"+1 516 938 6131",
    "sg:postcode":"11801",
    "sg:province":"NY",
    "sg:tags":[
        "house",
        "contractor"
    ],
    "wof:name":"Creative Pools & Landscapes",
    "wof:placetype":"venue"
},
  "geometry": {"coordinates":[-73.518992,40.768257],"type":"Point"}
}