{
  "type": "Feature",
  "properties": {
    "iso:country":"US",
    "sg:address":"1335 Jonathan Ln",
    "sg:city":"Wantagh",
    "sg:classifiers":[
        {
            "category":"Building & Trades",
            "subcategory":"Construction",
            "type":"Services"
        }
    ],
    "sg:phone":"+1 516 785 3696",
    "sg:postcode":"11793",
    "sg:province":"NY",
    "sg:tags":[
        "contractor"
    ],
    "wof:name":"Custom Window Fashions LLC",
    "wof:placetype":"venue"
},
  "geometry": {"coordinates":[-73.51848699999999,40.690392],"type":"Point"}
}