{
  "type": "Feature",
  "properties": {
    "addr:full":"2101 Pine Ave Niagara Falls NY 14301",
    "addr:housenumber":"2101",
    "addr:postcode":"14301",
    "addr:street":"Pine Ave",
    "iso:country":"US",
    "sg:address":"2101 Pine Ave",
    "sg:city":"Niagara Falls",
    "sg:classifiers":[
        {
            "category":"Shopping",
            "subcategory":"Used Merchandise",
            "type":"Retail Goods"
        }
    ],
    "sg:phone":"+1 716 278 0283",
    "sg:postcode":"14301",
    "sg:province":"NY",
    "sg:tags":[
        "pawnbroker"
    ],
    "wof:name":"Niagara Tools & Pawn",
    "wof:placetype":"venue"
},
  "geometry": {"coordinates":[-79.03618299999999,43.095099],"type":"Point"}
}