{
  "type": "Feature",
  "properties": {
    "addr:full":"4498 Sunrise Hwy Oakdale NY 11769",
    "addr:housenumber":"4498",
    "addr:postcode":"11769",
    "addr:street":"Sunrise Hwy",
    "iso:country":"US",
    "sg:address":"4498 Sunrise Hwy",
    "sg:city":"Oakdale",
    "sg:classifiers":[
        {
            "category":"Restaurant",
            "type":"Food & Drink"
        }
    ],
    "sg:menulink":"http://www.allmenus.com/ny/islip/189153-mcdonalds/menu/",
    "sg:phone":"+1 631 567 0364",
    "sg:postcode":"11769",
    "sg:province":"NY",
    "sg:tags":[
        "burger",
        "american"
    ],
    "wof:name":"McDonald's",
    "wof:placetype":"venue"
},
  "geometry": {"coordinates":[-73.119529,40.7529],"type":"Point"}
}