{
  "type": "Feature",
  "properties": {
    "addr:full":"60 Greenmeadow Rd Pleasantville NY 10570",
    "addr:housenumber":"60",
    "addr:postcode":"10570",
    "addr:street":"Greenmeadow Rd",
    "iso:country":"US",
    "sg:address":"60 Greenmeadow Rd",
    "sg:city":"Pleasantville",
    "sg:classifiers":[
        {
            "category":"Professional",
            "subcategory":"Art Services",
            "type":"Services"
        }
    ],
    "sg:phone":"+1   ",
    "sg:postcode":"10570",
    "sg:province":"NY",
    "sg:tags":[
        "commercial",
        "design"
    ],
    "wof:name":"K B Design Studios",
    "wof:placetype":"venue"
},
  "geometry": {"coordinates":[-73.775845,41.140769],"type":"Point"}
}