{
  "type": "Feature",
  "properties": {
    "addr:full":"261 W 35th Street Lbby New York NY 10001",
    "addr:housenumber":"261",
    "addr:postcode":"10001",
    "addr:street":"W 35Th Street",
    "iso:country":"US",
    "sg:address":"261 W 35th Street Lbby",
    "sg:city":"New York",
    "sg:classifiers":[
        {
            "category":"Casinos & Gambling",
            "type":"Entertainment"
        }
    ],
    "sg:phone":"+1 212 563 1111",
    "sg:postcode":"10001",
    "sg:province":"NY",
    "wof:name":"Casino Professionals of Ny",
    "wof:placetype":"venue"
},
  "geometry": {"coordinates":[-73.99203300000001,40.752457],"type":"Point"}
}