{
  "type": "Feature",
  "properties": {
    "addr:full":"13701 83rd Ave Apt 1B Jamaica NY 11435",
    "addr:housenumber":"13701;1b",
    "addr:postcode":"11435",
    "addr:street":"83Rd Ave Apt",
    "iso:country":"US",
    "sg:address":"13701 83rd Ave Apt 1B",
    "sg:city":"Jamaica",
    "sg:classifiers":[
        {
            "category":"Health Services",
            "subcategory":"Doctor",
            "type":"Services"
        }
    ],
    "sg:phone":"+1 718 847 3501",
    "sg:postcode":"11435",
    "sg:province":"NY",
    "wof:name":"Hermogenes Patricia",
    "wof:placetype":"venue"
},
  "geometry": {"coordinates":[-73.810204,40.702],"type":"Point"}
}