{
  "type": "Feature",
  "properties": {
    "iso:country":"US",
    "sg:address":"8712 4th Ave",
    "sg:city":"Brooklyn",
    "sg:classifiers":[
        {
            "category":"Organizations",
            "subcategory":"Non-profit Organization",
            "type":"Services"
        }
    ],
    "sg:phone":"+1 718 630 5515",
    "sg:postcode":"11209",
    "sg:province":"NY",
    "sg:tags":[
        "information",
        "alcoholism",
        "treatment"
    ],
    "sg:website":"www.seafieldcenter.com",
    "wof:name":"Seafield Svc",
    "wof:placetype":"venue"
},
  "geometry": {"coordinates":[-74.02897299999999,40.621499],"type":"Point"}
}