{
  "type": "Feature",
  "properties": {
    "addr:full":"2020 Hillside Ave New Hyde Park NY 11040",
    "addr:housenumber":"2020",
    "addr:postcode":"11040",
    "addr:street":"Hillside Ave",
    "iso:country":"US",
    "sg:address":"2020 Hillside Ave",
    "sg:city":"New Hyde Park",
    "sg:classifiers":[
        {
            "category":"Real Estate",
            "subcategory":"Real Estate Services",
            "type":"Services"
        },
        {
            "category":"Professional",
            "subcategory":"Lawyer & Legal Services",
            "type":"Services"
        }
    ],
    "sg:phone":"+1 516 437 3353",
    "sg:postcode":"11040",
    "sg:province":"NY",
    "sg:tags":[
        "management",
        "property",
        "notary"
    ],
    "sg:website":"www.peterbensonrealestate.com",
    "wof:name":"Benson Peter H Inc",
    "wof:placetype":"venue"
},
  "geometry": {"coordinates":[-73.67559799999999,40.751099],"type":"Point"}
}