{
  "type": "Feature",
  "properties": {
    "addr:full":"1225 Curry Rd Schenectady NY 12306",
    "addr:housenumber":"1225",
    "addr:postcode":"12306",
    "addr:street":"Curry Rd",
    "iso:country":"US",
    "sg:address":"1225 Curry Rd",
    "sg:city":"Schenectady",
    "sg:classifiers":[
        {
            "category":"Wholesale",
            "subcategory":"Auto Parts",
            "type":"Manufacturing & Wholesale Goods"
        }
    ],
    "sg:phone":"+1 518 355 3120",
    "sg:postcode":"12306",
    "sg:province":"NY",
    "sg:tags":[
        "supply"
    ],
    "wof:name":"Randys Auto Parts Inc",
    "wof:placetype":"venue"
},
  "geometry": {"coordinates":[-73.965451,42.784839],"type":"Point"}
}