{
  "type": "Feature",
  "properties": {
    "iso:country":"US",
    "sg:address":"6608 Shawnee Rd",
    "sg:city":"North Tonawanda",
    "sg:classifiers":[
        {
            "category":"Wholesale",
            "subcategory":"Durable Goods & Equipment",
            "type":"Manufacturing & Wholesale Goods"
        }
    ],
    "sg:phone":"+1 716 731 2314",
    "sg:postcode":"14120",
    "sg:province":"NY",
    "wof:name":"Tea Time Antiquities",
    "wof:placetype":"venue"
},
  "geometry": {"coordinates":[-78.837281,43.113878],"type":"Point"}
}