{
  "type": "Feature",
  "properties": {
    "addr:full":"64 Stewart Ave Ste C Roscoe NY 12776",
    "addr:housenumber":"64",
    "addr:postcode":"12776",
    "addr:street":"Stewart Ave Ste C Roscoe",
    "iso:country":"US",
    "sg:address":"64 Stewart Ave Ste C",
    "sg:city":"Roscoe",
    "sg:classifiers":[
        {
            "category":"Food & Beverages",
            "subcategory":"Specialty",
            "type":"Retail Goods"
        }
    ],
    "sg:phone":"+1 607 498 4149",
    "sg:postcode":"12776",
    "sg:province":"NY",
    "sg:tags":[
        "gourmet",
        "shop"
    ],
    "wof:name":"Buffalo Zachs",
    "wof:placetype":"venue"
},
  "geometry": {"coordinates":[-74.913028,41.932845],"type":"Point"}
}