{
  "type": "Feature",
  "properties": {
    "addr:full":"266 Hooker Ave Poughkeepsie NY 12603",
    "addr:housenumber":"266",
    "addr:postcode":"12603",
    "addr:street":"Hooker Ave",
    "iso:country":"US",
    "sg:address":"266 Hooker Ave",
    "sg:city":"Poughkeepsie",
    "sg:classifiers":[
        {
            "category":"Food & Beverages",
            "subcategory":"Groceries & Convenience Stores",
            "type":"Retail Goods"
        }
    ],
    "sg:phone":"+1 845 485 2977",
    "sg:postcode":"12603",
    "sg:province":"NY",
    "sg:website":"www.7-eleven.com",
    "wof:name":"7-Eleven",
    "wof:placetype":"venue"
},
  "geometry": {"coordinates":[-73.909888,41.685988],"type":"Point"}
}