{
  "type": "Feature",
  "properties": {
    "addr:full":"1672 Victory Boulevard Staten Island NY 10314",
    "addr:housenumber":"1672",
    "addr:postcode":"10314",
    "addr:street":"Victory Boulevard",
    "iso:country":"US",
    "sg:address":"1672 Victory Boulevard",
    "sg:city":"Staten Island",
    "sg:classifiers":[
        {
            "category":"Shopping",
            "subcategory":"Florist",
            "type":"Retail Goods"
        }
    ],
    "sg:phone":"+1 718 816 6253",
    "sg:postcode":"10314",
    "sg:province":"NY",
    "wof:name":"Julian's Garden",
    "wof:placetype":"venue"
},
  "geometry": {"coordinates":[-74.120031,40.613379],"type":"Point"}
}