{
  "type": "Feature",
  "properties": {
    "addr:full":"5814 Main St Glenfield NY 13343",
    "addr:housenumber":"5814",
    "addr:postcode":"13343",
    "addr:street":"Main St",
    "iso:country":"US",
    "sg:address":"5814 Main St",
    "sg:city":"Glenfield",
    "sg:classifiers":[
        {
            "category":"Building & Trades",
            "subcategory":"Construction",
            "type":"Services"
        },
        {
            "category":"Building & Trades",
            "subcategory":"Electrical",
            "type":"Services"
        }
    ],
    "sg:phone":"+1 315 376 6834",
    "sg:postcode":"13343",
    "sg:province":"NY",
    "sg:tags":[
        "industrial",
        "electrician",
        "electric",
        "specialty",
        "heating",
        "contractors-commercial",
        "contractor"
    ],
    "wof:name":"J J Domagala Electric",
    "wof:placetype":"venue"
},
  "geometry": {"coordinates":[-75.404757,43.708624],"type":"Point"}
}