{
  "type": "Feature",
  "properties": {
    "iso:country":"US",
    "sg:address":"59 Hawxhurst Rd",
    "sg:city":"Cold Spring Harbor",
    "sg:classifiers":[
        {
            "category":"Building & Trades",
            "subcategory":"Construction",
            "type":"Services"
        }
    ],
    "sg:phone":"+1 631 421 1434",
    "sg:postcode":"11724",
    "sg:province":"NY",
    "sg:tags":[
        "home",
        "speculative",
        "builder"
    ],
    "wof:name":"Greenbrier Homes Inc",
    "wof:placetype":"venue"
},
  "geometry": {"coordinates":[-73.43891499999999,40.856618],"type":"Point"}
}