{
  "type": "Feature",
  "properties": {
    "addr:full":"8706 3rd Ave Brooklyn NY 11209",
    "addr:housenumber":"8706",
    "addr:postcode":"11209",
    "addr:street":"3Rd Ave",
    "iso:country":"US",
    "sg:address":"8706 3rd Ave",
    "sg:city":"Brooklyn",
    "sg:classifiers":[
        {
            "category":"Personal",
            "subcategory":"Nail Salon",
            "type":"Services"
        }
    ],
    "sg:phone":"+1 718 680 8680",
    "sg:postcode":"11209",
    "sg:province":"NY",
    "wof:name":"Mimi Nails",
    "wof:placetype":"venue"
},
  "geometry": {"coordinates":[-74.15345499999999,40.622749],"type":"Point"}
}