{
  "type": "Feature",
  "properties": {
    "addr:full":"305 Hurley Ave Kingston NY 12401",
    "addr:housenumber":"305",
    "addr:postcode":"12401",
    "addr:street":"Hurley Ave",
    "iso:country":"US",
    "sg:address":"305 Hurley Ave",
    "sg:city":"Kingston",
    "sg:classifiers":[
        {
            "category":"Food & Beverages",
            "subcategory":"Liquor & Beverages",
            "type":"Retail Goods"
        }
    ],
    "sg:phone":"+1   ",
    "sg:postcode":"12401",
    "sg:province":"NY",
    "sg:tags":[
        "wine"
    ],
    "wof:name":"Value Thru",
    "wof:placetype":"venue"
},
  "geometry": {"coordinates":[-74.03812000000001,41.938947],"type":"Point"}
}