{
  "type": "Feature",
  "properties": {
    "iso:country":"US",
    "sg:address":"1906 Oriskany St W",
    "sg:city":"Utica",
    "sg:classifiers":[
        {
            "category":"Home & Garden",
            "subcategory":"Carpets & Floor Coverings",
            "type":"Retail Goods"
        }
    ],
    "sg:phone":"+1   ",
    "sg:postcode":"13502",
    "sg:province":"NY",
    "sg:tags":[
        "store"
    ],
    "wof:name":"A&M Quality Floors Service",
    "wof:placetype":"venue"
},
  "geometry": {"coordinates":[-75.262244,43.111959],"type":"Point"}
}