{
  "type": "Feature",
  "properties": {
    "addr:full":"373 Kings Hwy Brooklyn NY 11223",
    "addr:housenumber":"373",
    "addr:postcode":"11223",
    "addr:street":"Kings Hwy",
    "iso:country":"US",
    "sg:address":"373 Kings Hwy",
    "sg:city":"Brooklyn",
    "sg:classifiers":[
        {
            "category":"Bagels",
            "type":"Food & Drink"
        },
        {
            "category":"Coffee & Tea",
            "type":"Food & Drink"
        },
        {
            "category":"Food & Beverages",
            "subcategory":"Bakery",
            "type":"Retail Goods"
        },
        {
            "category":"Bakery",
            "type":"Food & Drink"
        },
        {
            "category":"Donuts",
            "type":"Food & Drink"
        }
    ],
    "sg:menulink":"http://www.allmenus.com/ny/brooklyn/138276-dunkin-donuts/menu/",
    "sg:phone":"+1 518 492 9901",
    "sg:postcode":"11223",
    "sg:province":"NY",
    "sg:tags":[
        "coffee",
        "tea",
        "american",
        "bagel",
        "bakery",
        "pastry"
    ],
    "wof:name":"Dunkin' Donuts",
    "wof:placetype":"venue"
},
  "geometry": {"coordinates":[-73.976336,40.60468],"type":"Point"}
}