{
  "type": "Feature",
  "properties": {
    "addr:full":"4035 Bedford Ave Brooklyn NY 11229",
    "addr:housenumber":"4035",
    "addr:postcode":"11229",
    "addr:street":"Bedford Ave",
    "iso:country":"US",
    "sg:address":"4035 Bedford Ave",
    "sg:city":"Brooklyn",
    "sg:classifiers":[
        {
            "category":"Professional",
            "type":"Services"
        }
    ],
    "sg:phone":"+1 718 336 3828",
    "sg:postcode":"11229",
    "sg:province":"NY",
    "sg:tags":[
        "establishment"
    ],
    "wof:name":"Run Inc",
    "wof:placetype":"venue"
},
  "geometry": {"coordinates":[-73.947115,40.603075],"type":"Point"}
}