{
  "type": "Feature",
  "properties": {
    "addr:full":"2 Warren St New York NY 10007",
    "addr:housenumber":"2",
    "addr:postcode":"10007",
    "addr:street":"Warren St",
    "iso:country":"US",
    "sg:address":"2 Warren St",
    "sg:city":"New York",
    "sg:classifiers":[
        {
            "category":"Personal",
            "type":"Services"
        }
    ],
    "sg:phone":"+1 646 237 9359",
    "sg:postcode":"10007",
    "sg:province":"NY",
    "sg:tags":[
        "towing"
    ],
    "wof:name":"Emergency Anytime Towing",
    "wof:placetype":"venue"
},
  "geometry": {"coordinates":[-74.00720200000001,40.714001],"type":"Point"}
}