{
  "type": "Feature",
  "properties": {
    "iso:country":"US",
    "sg:address":"4434 Co Rd 121",
    "sg:city":"Romulus",
    "sg:classifiers":[
        {
            "category":"Restaurant",
            "type":"Food & Drink"
        },
        {
            "category":"Bars & Pubs",
            "type":"Food & Drink"
        }
    ],
    "sg:phone":"+1 315 585 6029",
    "sg:postcode":"14541",
    "sg:province":"NY",
    "sg:tags":[
        "eating"
    ],
    "wof:name":"Uncle Duke's",
    "wof:placetype":"venue"
},
  "geometry": {"coordinates":[-76.879668,42.808239],"type":"Point"}
}