{
  "type": "Feature",
  "properties": {
    "iso:country":"US",
    "sg:address":"148-62 Hillside Ave",
    "sg:city":"New York",
    "sg:classifiers":[
        {
            "category":"Restaurant",
            "type":"Food & Drink"
        }
    ],
    "sg:phone":"+1 718 657 1929",
    "sg:postcode":"11418",
    "sg:province":"NY",
    "sg:tags":[
        "american",
        "latin"
    ],
    "wof:name":"El Comal",
    "wof:placetype":"venue"
},
  "geometry": {"coordinates":[-73.83183,40.701228],"type":"Point"}
}