{
  "type": "Feature",
  "properties": {
    "addr:full":"142 Orchard St New York NY 10002",
    "addr:housenumber":"142",
    "addr:postcode":"10002",
    "addr:street":"Orchard St",
    "iso:country":"US",
    "sg:address":"142 Orchard St",
    "sg:city":"New York",
    "sg:classifiers":[
        {
            "category":"Manufacturing",
            "subcategory":"Leather Goods",
            "type":"Manufacturing & Wholesale Goods"
        }
    ],
    "sg:phone":"+1 212 420 8038",
    "sg:postcode":"10002",
    "sg:province":"NY",
    "wof:name":"Leather Friend",
    "wof:placetype":"venue"
},
  "geometry": {"coordinates":[-73.989098,40.720001],"type":"Point"}
}