{
  "type": "Feature",
  "properties": {
    "addr:full":"4419 Broadway New York NY 10040",
    "addr:housenumber":"4419",
    "addr:postcode":"10040",
    "addr:street":"Broadway",
    "iso:country":"US",
    "sg:address":"4419 Broadway",
    "sg:city":"New York",
    "sg:classifiers":[
        {
            "category":"Shopping",
            "subcategory":"Florist",
            "type":"Retail Goods"
        }
    ],
    "sg:phone":"+1 212 304 8440",
    "sg:postcode":"10040",
    "sg:province":"NY",
    "wof:name":"Guerrero's Flower Shop",
    "wof:placetype":"venue"
},
  "geometry": {"coordinates":[-73.933091,40.855877],"type":"Point"}
}