{
  "type": "Feature",
  "properties": {
    "iso:country":"US",
    "sg:address":"15 Dew Line Rd",
    "sg:city":"Liverpool",
    "sg:classifiers":[
        {
            "category":"Building & Trades",
            "subcategory":"Construction",
            "type":"Services"
        }
    ],
    "sg:phone":"+1 315 652 5895",
    "sg:postcode":"13090",
    "sg:province":"NY",
    "sg:tags":[
        "home",
        "general",
        "family",
        "contractor"
    ],
    "wof:name":"Palumbo Painting & Decorating",
    "wof:placetype":"venue"
},
  "geometry": {"coordinates":[-76.213131,43.13399],"type":"Point"}
}