{
  "type": "Feature",
  "properties": {
    "addr:full":"131 Wood Ave Staten Island NY 10307",
    "addr:housenumber":"131",
    "addr:postcode":"10307",
    "addr:street":"Wood Ave",
    "iso:country":"US",
    "sg:address":"131 Wood Ave",
    "sg:city":"Staten Island",
    "sg:classifiers":[
        {
            "category":"Professional",
            "subcategory":"Advertising",
            "type":"Services"
        }
    ],
    "sg:phone":"+1 718 967 3507",
    "sg:postcode":"10307",
    "sg:province":"NY",
    "sg:tags":[
        "counselor"
    ],
    "wof:name":"LBC Advertising Inc",
    "wof:placetype":"venue"
},
  "geometry": {"coordinates":[-74.24478499999999,40.514173],"type":"Point"}
}