{
  "type": "Feature",
  "properties": {
    "addr:full":"39 E Mall Plainview NY 11803",
    "addr:housenumber":"39",
    "addr:postcode":"11803",
    "addr:street":"E Mall",
    "iso:country":"US",
    "sg:address":"39 E Mall",
    "sg:city":"Plainview",
    "sg:classifiers":[
        {
            "category":"Wholesale",
            "subcategory":"Furniture",
            "type":"Manufacturing & Wholesale Goods"
        }
    ],
    "sg:phone":"+1 516 752 7036",
    "sg:postcode":"11803",
    "sg:province":"NY",
    "wof:name":"Suburban Office Supply Co",
    "wof:placetype":"venue"
},
  "geometry": {"coordinates":[-73.451798,40.7838],"type":"Point"}
}