{
  "type": "Feature",
  "properties": {
    "addr:full":"267 Merrick Rd Lynbrook NY 11563",
    "addr:housenumber":"267",
    "addr:postcode":"11563",
    "addr:street":"Merrick Rd",
    "iso:country":"US",
    "sg:address":"267 Merrick Rd",
    "sg:city":"Lynbrook",
    "sg:classifiers":[
        {
            "category":"Freight",
            "type":"Transportation"
        }
    ],
    "sg:phone":"+1   ",
    "sg:postcode":"11563",
    "sg:province":"NY",
    "sg:tags":[
        "operator",
        "local",
        "trucking"
    ],
    "wof:name":"A & P Mansour Corporation",
    "wof:placetype":"venue"
},
  "geometry": {"coordinates":[-73.669207,40.657664],"type":"Point"}
}