{
  "type": "Feature",
  "properties": {
    "iso:country":"US",
    "sg:address":"365 Co Rd 39A",
    "sg:city":"Southampton",
    "sg:classifiers":[
        {
            "category":"Shopping",
            "type":"Retail Goods"
        }
    ],
    "sg:phone":"+1 631 287 9226",
    "sg:postcode":"11968",
    "sg:province":"NY",
    "sg:tags":[
        "hearing",
        "equipment",
        "supply",
        "impaired"
    ],
    "wof:name":"Mc Guire's Hearing Aids",
    "wof:placetype":"venue"
},
  "geometry": {"coordinates":[-72.377872,40.900195],"type":"Point"}
}