{
  "type": "Feature",
  "properties": {
    "addr:full":"160 Rogers Avenue Brooklyn NY 11216",
    "addr:housenumber":"160",
    "addr:postcode":"11216",
    "addr:street":"Rogers Avenue",
    "iso:country":"US",
    "sg:address":"160 Rogers Avenue",
    "sg:city":"Brooklyn",
    "sg:classifiers":[
        {
            "category":"Real Estate",
            "subcategory":"Real Estate Services",
            "type":"Services"
        },
        {
            "category":"Real Estate",
            "subcategory":"Real Estate Agent",
            "type":"Services"
        },
        {
            "category":"Real Estate",
            "subcategory":"Real Estate Operator",
            "type":"Services"
        }
    ],
    "sg:phone":"+1 718 735 8453",
    "sg:postcode":"11216",
    "sg:province":"NY",
    "sg:tags":[
        "apartment"
    ],
    "wof:name":"B Belinda Realty",
    "wof:placetype":"venue"
},
  "geometry": {"coordinates":[-73.953298,40.671117],"type":"Point"}
}