{
  "type": "Feature",
  "properties": {
    "iso:country":"US",
    "sg:address":"95 New York Ave",
    "sg:city":"Huntington",
    "sg:classifiers":[
        {
            "category":"Professional",
            "type":"Services"
        }
    ],
    "sg:phone":"+1 631 271 5600",
    "sg:postcode":"11743",
    "sg:province":"NY",
    "sg:tags":[
        "caterer"
    ],
    "wof:name":"Harbor Club",
    "wof:placetype":"venue"
},
  "geometry": {"coordinates":[-73.419601,40.882599],"type":"Point"}
}