{
  "type": "Feature",
  "properties": {
    "iso:country":"US",
    "sg:address":"1988 Clinton Ave S",
    "sg:city":"Rochester",
    "sg:classifiers":[
        {
            "category":"Wholesale",
            "subcategory":"Chemicals & Plastics",
            "type":"Manufacturing & Wholesale Goods"
        }
    ],
    "sg:phone":"+1 585 271 1140",
    "sg:postcode":"14618",
    "sg:province":"NY",
    "sg:tags":[
        "oxygen"
    ],
    "wof:name":"Monroe Oxygen & Respiratory Cr",
    "wof:placetype":"venue"
},
  "geometry": {"coordinates":[-77.594629,43.121875],"type":"Point"}
}