{
  "type": "Feature",
  "properties": {
    "addr:full":"2134 Dean St Brooklyn NY 11233",
    "addr:housenumber":"2134",
    "addr:postcode":"11233",
    "addr:street":"Dean St",
    "iso:country":"US",
    "sg:address":"2134 Dean St",
    "sg:city":"Brooklyn",
    "sg:classifiers":[
        {
            "category":"Organizations",
            "subcategory":"Religious Organization",
            "type":"Services"
        }
    ],
    "sg:phone":"+1 718 345 2644",
    "sg:postcode":"11233",
    "sg:province":"NY",
    "wof:name":"Glover Memorial Baptist Church",
    "wof:placetype":"venue"
},
  "geometry": {"coordinates":[-73.918511,40.675123],"type":"Point"}
}