{
  "type": "Feature",
  "properties": {
    "addr:full":"207 E 110th St New York NY 10029",
    "addr:housenumber":"207",
    "addr:postcode":"10029",
    "addr:street":"E 110Th St",
    "iso:country":"US",
    "sg:address":"207 E 110th St",
    "sg:city":"New York",
    "sg:classifiers":[
        {
            "category":"Manufacturing",
            "subcategory":"Glass & Minerals",
            "type":"Manufacturing & Wholesale Goods"
        }
    ],
    "sg:phone":"+1 212 534 2307",
    "sg:postcode":"10029",
    "sg:province":"NY",
    "sg:tags":[
        "stone",
        "cut",
        "product"
    ],
    "wof:name":"Empire State Marble Mfg Corp",
    "wof:placetype":"venue"
},
  "geometry": {"coordinates":[-73.94063,40.793311],"type":"Point"}
}