{
  "type": "Feature",
  "properties": {
    "iso:country":"US",
    "sg:address":"5 Riverview Dr",
    "sg:city":"Fishkill",
    "sg:classifiers":[
        {
            "category":"Health Services",
            "subcategory":"Dentist",
            "type":"Services"
        }
    ],
    "sg:phone":"+1 845 897 5770",
    "sg:postcode":"12524",
    "sg:province":"NY",
    "wof:name":"Dental Health Associates",
    "wof:placetype":"venue"
},
  "geometry": {"coordinates":[-73.86460099999999,41.547798],"type":"Point"}
}