{
  "type": "Feature",
  "properties": {
    "addr:full":"61 S 8th Street # 4D Brooklyn NY 11211",
    "addr:housenumber":"61;4d",
    "addr:postcode":"11211",
    "addr:street":"S 8Th Street #",
    "iso:country":"US",
    "sg:address":"61 S 8th Street # 4D",
    "sg:city":"Brooklyn",
    "sg:classifiers":[
        {
            "category":"Building & Trades",
            "subcategory":"Plumbing",
            "type":"Services"
        }
    ],
    "sg:phone":"+1 718 387 1887",
    "sg:postcode":"11211",
    "sg:province":"NY",
    "wof:name":"Bmw Plumbing Supply",
    "wof:placetype":"venue"
},
  "geometry": {"coordinates":[-73.967106,40.709986],"type":"Point"}
}