{
  "type": "Feature",
  "properties": {
    "addr:full":"1360 Kings Hwy Chester NY 10918",
    "addr:housenumber":"1360",
    "addr:postcode":"10918",
    "addr:street":"Kings Hwy",
    "iso:country":"US",
    "sg:address":"1360 Kings Hwy",
    "sg:city":"Chester",
    "sg:classifiers":[
        {
            "category":"Shopping",
            "subcategory":"Gifts & Souvenirs",
            "type":"Retail Goods"
        }
    ],
    "sg:phone":"+1 845 469 6789",
    "sg:postcode":"10918",
    "sg:province":"NY",
    "sg:tags":[
        "shop"
    ],
    "wof:name":"Enchanting Gifts Inc",
    "wof:placetype":"venue"
},
  "geometry": {"coordinates":[-74.286743,41.32038],"type":"Point"}
}