{
  "type": "Feature",
  "properties": {
    "iso:country":"US",
    "sg:address":"88 Continental Ave",
    "sg:city":"Forest Hills",
    "sg:classifiers":[
        {
            "category":"Wholesale",
            "subcategory":"Non-durable Goods",
            "type":"Manufacturing & Wholesale Goods"
        }
    ],
    "sg:phone":"+1 718 263 9200",
    "sg:postcode":"11375",
    "sg:province":"NY",
    "wof:name":"A A A Stretch Inc",
    "wof:placetype":"venue"
},
  "geometry": {"coordinates":[-73.84689899999999,40.716543],"type":"Point"}
}