{
  "type": "Feature",
  "properties": {
    "addr:full":"11 Kendall Ave Binghamton NY 13903",
    "addr:housenumber":"11",
    "addr:postcode":"13903",
    "addr:street":"Kendall Ave",
    "iso:country":"US",
    "sg:address":"11 Kendall Ave",
    "sg:city":"Binghamton",
    "sg:classifiers":[
        {
            "category":"Professional",
            "subcategory":"Management & Consulting",
            "type":"Services"
        }
    ],
    "sg:phone":"+1 607 724 9498",
    "sg:postcode":"13903",
    "sg:province":"NY",
    "wof:name":"Electronic Data Systems Corp",
    "wof:placetype":"venue"
},
  "geometry": {"coordinates":[-75.92075,42.085174],"type":"Point"}
}