{
  "type": "Feature",
  "properties": {
    "iso:country":"US",
    "sg:address":"1 Plaza Rd",
    "sg:city":"Greenvale",
    "sg:classifiers":[
        {
            "category":"Building & Trades",
            "subcategory":"Equipment Rental",
            "type":"Services"
        }
    ],
    "sg:phone":"+1 516 621 4400",
    "sg:postcode":"11548",
    "sg:province":"NY",
    "sg:tags":[
        "leasing"
    ],
    "wof:name":"Auric Capital Corp",
    "wof:placetype":"venue"
},
  "geometry": {"coordinates":[-73.628467,40.813835],"type":"Point"}
}