{
  "type": "Feature",
  "properties": {
    "addr:full":"6604 Hardscrabble Rd Kill Buck NY 14748",
    "addr:housenumber":"6604",
    "addr:postcode":"14748",
    "addr:street":"Hardscrabble Rd",
    "iso:country":"US",
    "sg:address":"6604 Hardscrabble Rd",
    "sg:city":"Kill Buck",
    "sg:classifiers":[
        {
            "category":"Government",
            "subcategory":"Office",
            "type":"Public Place"
        }
    ],
    "sg:phone":"+1 716 945 5314",
    "sg:postcode":"14748",
    "sg:province":"NY",
    "sg:tags":[
        "federal"
    ],
    "wof:name":"US Transportation Dept",
    "wof:placetype":"venue"
},
  "geometry": {"coordinates":[-78.662251,42.157706],"type":"Point"}
}