{
  "type": "Feature",
  "properties": {
    "iso:country":"US",
    "sg:address":"4520 12th Ave",
    "sg:city":"Brooklyn",
    "sg:classifiers":[
        {
            "category":"Building & Trades",
            "subcategory":"Plumbing",
            "type":"Services"
        }
    ],
    "sg:phone":"+1 718 854 8449",
    "sg:postcode":"11219",
    "sg:province":"NY",
    "sg:tags":[
        "contractor"
    ],
    "wof:name":"Bracha Piping & Heating",
    "wof:placetype":"venue"
},
  "geometry": {"coordinates":[-73.992541,40.638195],"type":"Point"}
}