{
  "type": "Feature",
  "properties": {
    "iso:country":"US",
    "sg:address":"2 Driftwood Dr",
    "sg:city":"Port Washington",
    "sg:classifiers":[
        {
            "category":"Wholesale",
            "subcategory":"Durable Goods & Equipment",
            "type":"Manufacturing & Wholesale Goods"
        }
    ],
    "sg:phone":"+1 516 767 2870",
    "sg:postcode":"11050",
    "sg:province":"NY",
    "sg:tags":[
        "representative",
        "manufacturer"
    ],
    "wof:name":"Gross Transportion Consulting",
    "wof:placetype":"venue"
},
  "geometry": {"coordinates":[-73.70511500000001,40.846278],"type":"Point"}
}