{
  "type": "Feature",
  "properties": {
    "addr:full":"929 Elmwood Ave Buffalo NY 14222",
    "addr:housenumber":"929",
    "addr:postcode":"14222",
    "addr:street":"Elmwood Ave",
    "iso:country":"US",
    "sg:address":"929 Elmwood Ave",
    "sg:city":"Buffalo",
    "sg:classifiers":[
        {
            "category":"Restaurant",
            "type":"Food & Drink"
        }
    ],
    "sg:phone":"+1 716 885 4400",
    "sg:postcode":"14222",
    "sg:province":"NY",
    "sg:website":"www.mezzabuffalo.com/",
    "wof:name":"Mezza",
    "wof:placetype":"venue"
},
  "geometry": {"coordinates":[-78.87668600000001,42.922505],"type":"Point"}
}