{
  "type": "Feature",
  "properties": {
    "addr:full":"10714 Guy R Brewer Blvd Jamaica NY 11433",
    "addr:housenumber":"10714",
    "addr:postcode":"11433",
    "addr:street":"Guy R Brewer Blvd",
    "iso:country":"US",
    "sg:address":"10714 Guy R Brewer Blvd",
    "sg:city":"Jamaica",
    "sg:classifiers":[
        {
            "category":"Food & Beverages",
            "subcategory":"Groceries & Convenience Stores",
            "type":"Retail Goods"
        }
    ],
    "sg:phone":"+1 718 206 1594",
    "sg:postcode":"11433",
    "sg:province":"NY",
    "wof:name":"Queens African Market",
    "wof:placetype":"venue"
},
  "geometry": {"coordinates":[-73.792373,40.697845],"type":"Point"}
}