{
  "type": "Feature",
  "properties": {
    "iso:country":"US",
    "sg:address":"132 Larchmont Avenue",
    "sg:city":"Larchmont",
    "sg:classifiers":[
        {
            "category":"Communications",
            "subcategory":"Film & Video Production",
            "type":"Services"
        },
        {
            "category":"Professional",
            "subcategory":"Art Services",
            "type":"Services"
        }
    ],
    "sg:phone":"+1 646 369 6185",
    "sg:postcode":"10538",
    "sg:province":"NY",
    "sg:tags":[
        "picture",
        "videography",
        "photography",
        "services-commercial",
        "motion",
        "tape",
        "editing"
    ],
    "wof:name":"Chris Fig Productions - Westchester Country Wedding Videography",
    "wof:placetype":"venue"
},
  "geometry": {"coordinates":[-73.752155,40.92816],"type":"Point"}
}