{
  "type": "Feature",
  "properties": {
    "iso:country":"US",
    "sg:address":"390 Golf Dr",
    "sg:city":"Oceanside",
    "sg:classifiers":[
        {
            "category":"Professional",
            "subcategory":"Accounting & Tax Preparation",
            "type":"Services"
        }
    ],
    "sg:phone":"+1 516 766 7188",
    "sg:postcode":"11572",
    "sg:province":"NY",
    "sg:tags":[
        "accountant"
    ],
    "wof:name":"William Price CPA",
    "wof:placetype":"venue"
},
  "geometry": {"coordinates":[-73.625601,40.624915],"type":"Point"}
}