{
  "type": "Feature",
  "properties": {
    "iso:country":"US",
    "sg:address":"1372 York Ave",
    "sg:city":"New York",
    "sg:classifiers":[
        {
            "category":"Restaurant",
            "type":"Food & Drink"
        }
    ],
    "sg:menulink":"http://www.allmenus.com/ny/new-york/39408-tropicalia/menu/",
    "sg:phone":"+1 212 717 7179",
    "sg:postcode":"10021",
    "sg:province":"NY",
    "sg:tags":[
        "american"
    ],
    "wof:name":"Tropicalia",
    "wof:placetype":"venue"
},
  "geometry": {"coordinates":[-73.952754,40.767567],"type":"Point"}
}