{
  "type": "Feature",
  "properties": {
    "addr:full":"26 Pennington Way Spring Valley NY 10977",
    "addr:housenumber":"26",
    "addr:postcode":"10977",
    "addr:street":"Pennington Way",
    "iso:country":"US",
    "sg:address":"26 Pennington Way",
    "sg:city":"Spring Valley",
    "sg:classifiers":[
        {
            "category":"Building & Trades",
            "subcategory":"Construction",
            "type":"Services"
        }
    ],
    "sg:phone":"+1 845 362 6039",
    "sg:postcode":"10977",
    "sg:province":"NY",
    "sg:tags":[
        "contractor"
    ],
    "wof:name":"Flamingo Pools & Fence",
    "wof:placetype":"venue"
},
  "geometry": {"coordinates":[-74.051002,41.155152],"type":"Point"}
}