{
  "type": "Feature",
  "properties": {
    "iso:country":"US",
    "sg:address":"447 Hempstead Ave",
    "sg:city":"West Hempstead",
    "sg:classifiers":[
        {
            "category":"Retail",
            "subcategory":"Portrait Studio",
            "type":"Services"
        },
        {
            "category":"Professional",
            "subcategory":"Art Services",
            "type":"Services"
        }
    ],
    "sg:phone":"+1 516 483 5481",
    "sg:postcode":"11552",
    "sg:province":"NY",
    "sg:tags":[
        "photographer",
        "photography",
        "store"
    ],
    "wof:name":"True Image Photo",
    "wof:placetype":"venue"
},
  "geometry": {"coordinates":[-73.65208199999999,40.698785],"type":"Point"}
}