{
  "type": "Feature",
  "properties": {
    "iso:country":"US",
    "sg:address":"525 Titus Ave",
    "sg:city":"Rochester",
    "sg:classifiers":[
        {
            "category":"Shopping",
            "subcategory":"Computers & Home Electronics",
            "type":"Retail Goods"
        }
    ],
    "sg:phone":"+1 585 266 5770",
    "sg:postcode":"14617",
    "sg:province":"NY",
    "sg:tags":[
        "equipment",
        "dealer"
    ],
    "wof:name":"PC Corner",
    "wof:placetype":"venue"
},
  "geometry": {"coordinates":[-77.60272999999999,43.210483],"type":"Point"}
}