{
  "type": "Feature",
  "properties": {
    "addr:full":"1608 US Hwy 9w Selkirk NY 12158",
    "addr:housenumber":"1608",
    "addr:postcode":"12158",
    "addr:street":"Us Hwy 9W",
    "iso:country":"US",
    "sg:address":"1608 US Hwy 9w",
    "sg:city":"Selkirk",
    "sg:classifiers":[
        {
            "category":"Home & Garden",
            "subcategory":"Building Materials",
            "type":"Retail Goods"
        }
    ],
    "sg:phone":"+1 518 767 3500",
    "sg:postcode":"12158",
    "sg:province":"NY",
    "sg:tags":[
        "modular"
    ],
    "wof:name":"Meilak's Mobile Court",
    "wof:placetype":"venue"
},
  "geometry": {"coordinates":[-73.811149,42.52103],"type":"Point"}
}