{
  "type": "Feature",
  "properties": {
    "iso:country":"US",
    "sg:address":"10 Woods Xing",
    "sg:city":"Glen Head",
    "sg:classifiers":[
        {
            "category":"Professional",
            "type":"Services"
        }
    ],
    "sg:phone":"+1   ",
    "sg:postcode":"11545",
    "sg:province":"NY",
    "wof:name":"Peter Ward",
    "wof:placetype":"venue"
},
  "geometry": {"coordinates":[-73.572706,40.810109],"type":"Point"}
}