{
  "type": "Feature",
  "properties": {
    "iso:country":"US",
    "sg:address":"530 Hicksville Rd",
    "sg:city":"Bethpage",
    "sg:classifiers":[
        {
            "category":"Health Services",
            "subcategory":"Hospital",
            "type":"Services"
        },
        {
            "category":"Community Center",
            "type":"Public Place"
        }
    ],
    "sg:phone":"+1 516 576 1803",
    "sg:postcode":"11714",
    "sg:province":"NY",
    "sg:tags":[
        "medical"
    ],
    "wof:name":"Winthrop University Hospital",
    "wof:placetype":"venue"
},
  "geometry": {"coordinates":[-73.49722300000001,40.742741],"type":"Point"}
}