{
  "type": "Feature",
  "properties": {
    "addr:full":"45 Huntington Hill S Rochester NY 14622",
    "addr:housenumber":"45",
    "addr:postcode":"14622",
    "addr:street":"Huntington Hill S",
    "iso:country":"US",
    "sg:address":"45 Huntington Hill S",
    "sg:city":"Rochester",
    "sg:classifiers":[
        {
            "category":"Shopping",
            "subcategory":"Clothing, Apparel, & Fashions",
            "type":"Retail Goods"
        }
    ],
    "sg:phone":"+1   ",
    "sg:postcode":"14622",
    "sg:province":"NY",
    "wof:name":"Pro Official Inc",
    "wof:placetype":"venue"
},
  "geometry": {"coordinates":[-77.564807,43.220845],"type":"Point"}
}