{
  "type": "Feature",
  "properties": {
    "iso:country":"US",
    "sg:address":"179 Sullys Trl",
    "sg:city":"Pittsford",
    "sg:classifiers":[
        {
            "category":"Professional",
            "subcategory":"Business Services",
            "type":"Services"
        }
    ],
    "sg:phone":"+1 585 244 6636",
    "sg:postcode":"14534",
    "sg:province":"NY",
    "sg:tags":[
        "appraiser"
    ],
    "wof:name":"RLH Appraisals",
    "wof:placetype":"venue"
},
  "geometry": {"coordinates":[-77.466747,43.057366],"type":"Point"}
}