{
  "type": "Feature",
  "properties": {
    "iso:country":"US",
    "sg:address":"17016 73rd Ave",
    "sg:city":"Flushing",
    "sg:classifiers":[
        {
            "category":"Social Services",
            "subcategory":"Child Care",
            "type":"Services"
        }
    ],
    "sg:phone":"+1 718 380 5611",
    "sg:postcode":"11366",
    "sg:province":"NY",
    "wof:name":"Keren Ohr Day Care Ctr",
    "wof:placetype":"venue"
},
  "geometry": {"coordinates":[-73.79954600000001,40.728583],"type":"Point"}
}