{
  "type": "Feature",
  "properties": {
    "iso:country":"US",
    "sg:address":"403 Portage Rd",
    "sg:city":"Niagara Falls",
    "sg:classifiers":[
        {
            "category":"Food & Beverages",
            "subcategory":"Groceries & Convenience Stores",
            "type":"Retail Goods"
        }
    ],
    "sg:phone":"+1   ",
    "sg:postcode":"14303",
    "sg:province":"NY",
    "wof:name":"H & R Deli",
    "wof:placetype":"venue"
},
  "geometry": {"coordinates":[-79.043964,43.088959],"type":"Point"}
}