{
  "type": "Feature",
  "properties": {
    "iso:country":"US",
    "sg:address":"23 Crown St",
    "sg:city":"Kingston",
    "sg:classifiers":[
        {
            "category":"Professional",
            "subcategory":"Lawyer & Legal Services",
            "type":"Services"
        }
    ],
    "sg:phone":"+1 845 338 9571",
    "sg:postcode":"12401",
    "sg:province":"NY",
    "sg:tags":[
        "attorney"
    ],
    "wof:name":"Gaffney & Gaffney Law Office",
    "wof:placetype":"venue"
},
  "geometry": {"coordinates":[-74.021016,41.932945],"type":"Point"}
}