{
  "type": "Feature",
  "properties": {
    "iso:country":"US",
    "sg:address":"1440 Route 9",
    "sg:city":"Wappingers Falls",
    "sg:classifiers":[
        {
            "category":"Food & Beverages",
            "subcategory":"Groceries & Convenience Stores",
            "type":"Retail Goods"
        }
    ],
    "sg:phone":"+1 888 297 4040",
    "sg:postcode":"12590",
    "sg:province":"NY",
    "wof:name":"Sentry",
    "wof:placetype":"venue"
},
  "geometry": {"coordinates":[-73.907481,41.587188],"type":"Point"}
}