{
  "type": "Feature",
  "properties": {
    "addr:full":"303 Elizabeth St New York NY 10012",
    "addr:housenumber":"303",
    "addr:postcode":"10012",
    "addr:street":"Elizabeth St",
    "iso:country":"US",
    "sg:address":"303 Elizabeth St",
    "sg:city":"New York",
    "sg:classifiers":[
        {
            "category":"Parking",
            "type":"Transportation"
        }
    ],
    "sg:phone":"+1 212 219 9562",
    "sg:postcode":"10012",
    "sg:province":"NY",
    "sg:tags":[
        "garage"
    ],
    "wof:name":"Mallah Organization Inc",
    "wof:placetype":"venue"
},
  "geometry": {"coordinates":[-73.99315900000001,40.725329],"type":"Point"}
}