{
  "type": "Feature",
  "properties": {
    "addr:full":"6801 E Genesee St Fayetteville NY 13066",
    "addr:housenumber":"6801",
    "addr:postcode":"13066",
    "addr:street":"E Genesee St",
    "iso:country":"US",
    "sg:address":"6801 E Genesee St",
    "sg:city":"Fayetteville",
    "sg:classifiers":[
        {
            "category":"Banks & Credit Unions",
            "subcategory":"Bank",
            "type":"Services"
        }
    ],
    "sg:phone":"+1 315 446 8481",
    "sg:postcode":"13066",
    "sg:province":"NY",
    "sg:tags":[
        "state",
        "commercial"
    ],
    "wof:name":"Fleet",
    "wof:placetype":"venue"
},
  "geometry": {"coordinates":[-76.049823,43.030386],"type":"Point"}
}