{
  "type": "Feature",
  "properties": {
    "iso:country":"US",
    "sg:address":"181 Lafayette Rd",
    "sg:city":"West Babylon",
    "sg:classifiers":[
        {
            "category":"Building & Trades",
            "subcategory":"Construction",
            "type":"Services"
        }
    ],
    "sg:phone":"+1 800 830 7732",
    "sg:postcode":"11704",
    "sg:province":"NY",
    "sg:tags":[
        "carpentry",
        "contractor"
    ],
    "wof:name":"Spectron Appraisers Ltd",
    "wof:placetype":"venue"
},
  "geometry": {"coordinates":[-73.33842199999999,40.72031],"type":"Point"}
}