{
  "type": "Feature",
  "properties": {
    "iso:country":"US",
    "sg:address":"85 Main St",
    "sg:city":"Irvington",
    "sg:classifiers":[
        {
            "category":"Government",
            "subcategory":"Office",
            "type":"Public Place"
        }
    ],
    "sg:phone":"+1 914 591 5930",
    "sg:postcode":"10533",
    "sg:province":"NY",
    "sg:tags":[
        "village"
    ],
    "wof:name":"Irvington Youth Officer",
    "wof:placetype":"venue"
},
  "geometry": {"coordinates":[-73.86770199999999,41.039257],"type":"Point"}
}