{
  "type": "Feature",
  "properties": {
    "addr:full":"65 W 11 St New York NY 10011",
    "addr:housenumber":"65",
    "addr:postcode":"10011",
    "addr:street":"W 11 St",
    "iso:country":"US",
    "sg:address":"65 W 11 St",
    "sg:city":"New York",
    "sg:classifiers":[
        {
            "category":"Professional",
            "subcategory":"Management & Consulting",
            "type":"Services"
        }
    ],
    "sg:phone":"+1   ",
    "sg:postcode":"10011",
    "sg:province":"NY",
    "sg:tags":[
        "retail",
        "direct",
        "sales"
    ],
    "wof:name":"Chartwells Inc",
    "wof:placetype":"venue"
},
  "geometry": {"coordinates":[-73.99664199999999,40.73457],"type":"Point"}
}