{
  "type": "Feature",
  "properties": {
    "addr:full":"2401 S Salina St Syracuse NY 13205",
    "addr:housenumber":"2401",
    "addr:postcode":"13205",
    "addr:street":"S Salina St",
    "iso:country":"US",
    "sg:address":"2401 S Salina St",
    "sg:city":"Syracuse",
    "sg:classifiers":[
        {
            "category":"Retail",
            "subcategory":"Auto Repair",
            "type":"Services"
        }
    ],
    "sg:phone":"+1 315 424 9223",
    "sg:postcode":"13205",
    "sg:province":"NY",
    "sg:tags":[
        "repairing",
        "automobile"
    ],
    "wof:name":"LA Solucions Auto Repair",
    "wof:placetype":"venue"
},
  "geometry": {"coordinates":[-76.144161,43.023157],"type":"Point"}
}