{
  "type": "Feature",
  "properties": {
    "iso:country":"US",
    "sg:address":"177 Niagara Frontier Foo",
    "sg:city":"Buffalo",
    "sg:classifiers":[
        {
            "category":"Wholesale",
            "subcategory":"Fruits & Vegetables",
            "type":"Manufacturing & Wholesale Goods"
        }
    ],
    "sg:phone":"+1 716 824 1011",
    "sg:postcode":"14206",
    "sg:province":"NY",
    "wof:name":"C-M General Brokerage Co Inc",
    "wof:placetype":"venue"
},
  "geometry": {"coordinates":[-78.821307,42.872844],"type":"Point"}
}