{
  "type": "Feature",
  "properties": {
    "iso:country":"US",
    "sg:address":"39 Neptune Avenue",
    "sg:city":"Brooklyn",
    "sg:classifiers":[
        {
            "category":"Retail",
            "subcategory":"Auto Rental",
            "type":"Services"
        }
    ],
    "sg:phone":"+1 718 934 4823",
    "sg:postcode":"11235",
    "sg:province":"NY",
    "sg:tags":[
        "car"
    ],
    "wof:name":"Not Nu",
    "wof:placetype":"venue"
},
  "geometry": {"coordinates":[-73.955384,40.582754],"type":"Point"}
}