{
  "type": "Feature",
  "properties": {
    "addr:full":"193 North 9th St. Brooklyn NY 11211",
    "addr:housenumber":"193",
    "addr:postcode":"11211",
    "addr:street":"North 9Th St.",
    "iso:country":"US",
    "sg:address":"193 North 9th St.",
    "sg:city":"Brooklyn",
    "sg:classifiers":[
        {
            "category":"Sports & Exercise",
            "subcategory":"Gym",
            "type":"Entertainment"
        }
    ],
    "sg:phone":"+1 917 992 1101",
    "sg:postcode":"11211",
    "sg:province":"NY",
    "sg:tags":[
        "trainer"
    ],
    "sg:website":"www.betzmethod.com",
    "wof:name":"Betz Method Personal Training",
    "wof:placetype":"venue"
},
  "geometry": {"coordinates":[-73.95529399999999,40.718551],"type":"Point"}
}