{
  "type": "Feature",
  "properties": {
    "addr:full":"89 5th Avenue New York NY 10003",
    "addr:housenumber":"89",
    "addr:postcode":"10003",
    "addr:street":"5Th Avenue",
    "iso:country":"US",
    "sg:address":"89 5th Avenue",
    "sg:city":"New York",
    "sg:classifiers":[
        {
            "category":"Restaurant",
            "type":"Food & Drink"
        }
    ],
    "sg:phone":"+1 212 929 1285",
    "sg:postcode":"10003",
    "sg:province":"NY",
    "wof:name":"Dezer Properties Company",
    "wof:placetype":"venue"
},
  "geometry": {"coordinates":[-73.992508,40.737701],"type":"Point"}
}