{
  "type": "Feature",
  "properties": {
    "addr:full":"25 Lacon Ct Brooklyn NY 11229",
    "addr:housenumber":"25",
    "addr:postcode":"11229",
    "addr:street":"Lacon Ct",
    "iso:country":"US",
    "sg:address":"25 Lacon Ct",
    "sg:city":"Brooklyn",
    "sg:classifiers":[
        {
            "category":"Retail",
            "subcategory":"Repair Shop",
            "type":"Services"
        }
    ],
    "sg:phone":"+1   ",
    "sg:postcode":"11229",
    "sg:province":"NY",
    "sg:tags":[
        "boat"
    ],
    "wof:name":"Sea Power Marine Ltd",
    "wof:placetype":"venue"
},
  "geometry": {"coordinates":[-73.93023599999999,40.590401],"type":"Point"}
}