{
  "type": "Feature",
  "properties": {
    "iso:country":"US",
    "sg:address":"437 Main St",
    "sg:city":"Medina",
    "sg:classifiers":[
        {
            "category":"Professional",
            "subcategory":"Accounting & Tax Preparation",
            "type":"Services"
        }
    ],
    "sg:phone":"+1 585 798 2636",
    "sg:postcode":"14103",
    "sg:province":"NY",
    "sg:tags":[
        "return",
        "filing"
    ],
    "wof:name":"H & R Block Tax Svc",
    "wof:placetype":"venue"
},
  "geometry": {"coordinates":[-78.386866,43.220729],"type":"Point"}
}