{
  "type": "Feature",
  "properties": {
    "iso:country":"US",
    "sg:address":"43 Drexel Dr",
    "sg:city":"Bay Shore",
    "sg:classifiers":[
        {
            "category":"Manufacturing",
            "subcategory":"Textiles",
            "type":"Manufacturing & Wholesale Goods"
        }
    ],
    "sg:phone":"+1   ",
    "sg:postcode":"11706",
    "sg:province":"NY",
    "sg:tags":[
        "mill",
        "fabric",
        "cotton"
    ],
    "wof:name":"Eppy Corp",
    "wof:placetype":"venue"
},
  "geometry": {"coordinates":[-73.26402,40.760653],"type":"Point"}
}