{
  "type": "Feature",
  "properties": {
    "addr:full":"2050 Western Ave Guilderland NY 12084",
    "addr:housenumber":"2050",
    "addr:postcode":"12084",
    "addr:street":"Western Ave",
    "iso:country":"US",
    "sg:address":"2050 Western Ave",
    "sg:city":"Guilderland",
    "sg:classifiers":[
        {
            "category":"Personal",
            "subcategory":"Tanning Parlor",
            "type":"Services"
        }
    ],
    "sg:phone":"+1 518 869 8260",
    "sg:postcode":"12084",
    "sg:province":"NY",
    "sg:tags":[
        "salon"
    ],
    "wof:name":"Tan Shop",
    "wof:placetype":"venue"
},
  "geometry": {"coordinates":[-73.893242,42.698854],"type":"Point"}
}