{
  "type": "Feature",
  "properties": {
    "iso:country":"US",
    "sg:address":"5 Old Mamaroneck Rd",
    "sg:city":"White Plains",
    "sg:classifiers":[
        {
            "category":"Health Services",
            "subcategory":"Health Practitioner",
            "type":"Services"
        }
    ],
    "sg:phone":"+1 914 686 0862",
    "sg:postcode":"10605",
    "sg:province":"NY",
    "sg:tags":[
        "psychologist"
    ],
    "wof:name":"Jay Schlesinger PHD",
    "wof:placetype":"venue"
},
  "geometry": {"coordinates":[-73.761544,41.022273],"type":"Point"}
}