{
  "type": "Feature",
  "properties": {
    "addr:full":"11519 Liberty Ave South Richmond Hill NY 11419",
    "addr:housenumber":"11519",
    "addr:postcode":"11419",
    "addr:street":"Liberty Ave South",
    "iso:country":"US",
    "sg:address":"11519 Liberty Ave",
    "sg:city":"South Richmond Hill",
    "sg:classifiers":[
        {
            "category":"Shopping",
            "subcategory":"Mobile Phones",
            "type":"Retail Goods"
        }
    ],
    "sg:phone":"+1 718 848 1124",
    "sg:postcode":"11419",
    "sg:province":"NY",
    "sg:website":"www.libertywireless.com",
    "wof:name":"Liberty Wireless",
    "wof:placetype":"venue"
},
  "geometry": {"coordinates":[-73.827586,40.685894],"type":"Point"}
}