{
  "type": "Feature",
  "properties": {
    "iso:country":"US",
    "sg:address":"440 State Hwy 66",
    "sg:city":"Hudson",
    "sg:classifiers":[
        {
            "category":"Real Estate",
            "subcategory":"Real Estate Operator",
            "type":"Services"
        }
    ],
    "sg:phone":"+1   ",
    "sg:postcode":"12534",
    "sg:province":"NY",
    "sg:tags":[
        "mobile",
        "residential",
        "mobil",
        "site",
        "home"
    ],
    "wof:name":"Homes Sales & Service",
    "wof:placetype":"venue"
},
  "geometry": {"coordinates":[-73.741733,42.261944],"type":"Point"}
}