{
  "type": "Feature",
  "properties": {
    "addr:full":"19 Indian Hill Dr Rochester NY 14624",
    "addr:housenumber":"19",
    "addr:postcode":"14624",
    "addr:street":"Indian Hill Dr",
    "iso:country":"US",
    "sg:address":"19 Indian Hill Dr",
    "sg:city":"Rochester",
    "sg:classifiers":[
        {
            "category":"Professional",
            "subcategory":"Management & Consulting",
            "type":"Services"
        }
    ],
    "sg:phone":"+1 585 594 3710",
    "sg:postcode":"14624",
    "sg:province":"NY",
    "wof:name":"Association Resources",
    "wof:placetype":"venue"
},
  "geometry": {"coordinates":[-77.792625,43.095583],"type":"Point"}
}