{
  "type": "Feature",
  "properties": {
    "iso:country":"US",
    "sg:address":"2613 W Henrietta Rd",
    "sg:city":"Rochester",
    "sg:classifiers":[
        {
            "category":"Cinema",
            "subcategory":"Movie Theater",
            "type":"Entertainment"
        }
    ],
    "sg:phone":"+1 585 292 5840",
    "sg:postcode":"14623",
    "sg:province":"NY",
    "wof:name":"Movies 10",
    "wof:placetype":"venue"
},
  "geometry": {"coordinates":[-77.629823,43.10171],"type":"Point"}
}