{
  "type": "Feature",
  "properties": {
    "iso:country":"US",
    "sg:address":"5012 State Hwy 12",
    "sg:city":"Norwich",
    "sg:classifiers":[
        {
            "category":"Autos & Motor Vehicles",
            "subcategory":"Automobile Sales",
            "type":"Retail Goods"
        },
        {
            "category":"Retail",
            "subcategory":"Auto Repair",
            "type":"Services"
        }
    ],
    "sg:phone":"+1 607 334 3773",
    "sg:postcode":"13815",
    "sg:province":"NY",
    "sg:tags":[
        "car",
        "used",
        "dealer",
        "general"
    ],
    "wof:name":"Mid Way Auto Sales",
    "wof:placetype":"venue"
},
  "geometry": {"coordinates":[-75.528797,42.558191],"type":"Point"}
}