{
  "type": "Feature",
  "properties": {
    "iso:country":"US",
    "sg:address":"1467 Co Rd 39",
    "sg:city":"Bainbridge",
    "sg:classifiers":[
        {
            "category":"Personal",
            "subcategory":"Beauty Salon",
            "type":"Services"
        }
    ],
    "sg:phone":"+1 607 967 2016",
    "sg:postcode":"13733",
    "sg:province":"NY",
    "wof:name":"Harmor",
    "wof:placetype":"venue"
},
  "geometry": {"coordinates":[-75.42621800000001,42.296773],"type":"Point"}
}