{
  "type": "Feature",
  "properties": {
    "addr:full":"18 Perrin St Fairport NY 14450",
    "addr:housenumber":"18",
    "addr:postcode":"14450",
    "addr:street":"Perrin St",
    "iso:country":"US",
    "sg:address":"18 Perrin St",
    "sg:city":"Fairport",
    "sg:classifiers":[
        {
            "category":"Museum",
            "type":"Entertainment"
        }
    ],
    "sg:phone":"+1 585 223 3989",
    "sg:postcode":"14450",
    "sg:province":"NY",
    "wof:name":"Fairport Historical Museum",
    "wof:placetype":"venue"
},
  "geometry": {"coordinates":[-77.443988,43.098896],"type":"Point"}
}