{
  "type": "Feature",
  "properties": {
    "iso:country":"US",
    "sg:address":"402 Grace Ave",
    "sg:city":"Newark",
    "sg:classifiers":[
        {
            "category":"Health Services",
            "subcategory":"Clinic",
            "type":"Services"
        }
    ],
    "sg:phone":"+1 315 331 6831",
    "sg:postcode":"14513",
    "sg:province":"NY",
    "sg:tags":[
        "outpatient"
    ],
    "wof:name":"Houser Associates",
    "wof:placetype":"venue"
},
  "geometry": {"coordinates":[-77.09937499999999,43.030258],"type":"Point"}
}