{
  "type": "Feature",
  "properties": {
    "addr:full":"107 Lenox Ave New York NY 10026",
    "addr:housenumber":"107",
    "addr:postcode":"10026",
    "addr:street":"Lenox Ave",
    "iso:country":"US",
    "sg:address":"107 Lenox Ave",
    "sg:city":"New York",
    "sg:classifiers":[
        {
            "category":"Shopping",
            "subcategory":"Department Store",
            "type":"Retail Goods"
        }
    ],
    "sg:phone":"+1 212 663 0393",
    "sg:postcode":"10026",
    "sg:province":"NY",
    "sg:tags":[
        "shop"
    ],
    "wof:name":"Mareb 99 Cent Plus Enterprise",
    "wof:placetype":"venue"
},
  "geometry": {"coordinates":[-73.949899,40.801783],"type":"Point"}
}