{
  "type": "Feature",
  "properties": {
    "iso:country":"US",
    "sg:address":"704 W Buffalo St",
    "sg:city":"Ithaca",
    "sg:classifiers":[
        {
            "category":"Shopping",
            "type":"Retail Goods"
        }
    ],
    "sg:phone":"+1 607 273 1235",
    "sg:postcode":"14850",
    "sg:province":"NY",
    "sg:tags":[
        "assistive",
        "supply",
        "hearing",
        "equipment",
        "aid",
        "device",
        "impaired"
    ],
    "wof:name":"Audio Hearing Aid Center",
    "wof:placetype":"venue"
},
  "geometry": {"coordinates":[-76.510977,42.440942],"type":"Point"}
}