{
  "type": "Feature",
  "properties": {
    "addr:full":"19 Church St Cortland NY 13045",
    "addr:housenumber":"19",
    "addr:postcode":"13045",
    "addr:street":"Church St",
    "iso:country":"US",
    "sg:address":"19 Church St",
    "sg:city":"Cortland",
    "sg:classifiers":[
        {
            "category":"Social Services",
            "type":"Services"
        }
    ],
    "sg:phone":"+1 607 758 3339",
    "sg:postcode":"13045",
    "sg:province":"NY",
    "sg:tags":[
        "counselor",
        "marriage",
        "family"
    ],
    "wof:name":"Family Counseling Ministries",
    "wof:placetype":"venue"
},
  "geometry": {"coordinates":[-76.17787300000001,42.600518],"type":"Point"}
}