{
  "type": "Feature",
  "properties": {
    "iso:country":"US",
    "sg:address":"9124 3rd Ave",
    "sg:city":"Brooklyn",
    "sg:classifiers":[
        {
            "category":"Restaurant",
            "type":"Food & Drink"
        }
    ],
    "sg:menulink":"http://www.allmenus.com/ny/brooklyn/54691-paneantico/menu/",
    "sg:phone":"+1 718 680 2347",
    "sg:postcode":"11209",
    "sg:province":"NY",
    "sg:tags":[
        "wrap",
        "american",
        "sandwich"
    ],
    "wof:name":"Paneantico",
    "wof:placetype":"venue"
},
  "geometry": {"coordinates":[-74.03260400000001,40.619708],"type":"Point"}
}