{
  "type": "Feature",
  "properties": {
    "iso:country":"US",
    "sg:address":"66 Watervliet Ave",
    "sg:city":"Albany",
    "sg:classifiers":[
        {
            "category":"Building & Trades",
            "subcategory":"Electrical",
            "type":"Services"
        }
    ],
    "sg:phone":"+1 518 489 5304",
    "sg:postcode":"12206",
    "sg:province":"NY",
    "sg:tags":[
        "electric",
        "contractor"
    ],
    "wof:name":"PSS Electric",
    "wof:placetype":"venue"
},
  "geometry": {"coordinates":[-73.781361,42.678044],"type":"Point"}
}