{
  "type": "Feature",
  "properties": {
    "iso:country":"US",
    "sg:address":"19 Lois Pl",
    "sg:city":"Valley Stream",
    "sg:classifiers":[
        {
            "category":"Building & Trades",
            "subcategory":"Construction",
            "type":"Services"
        }
    ],
    "sg:phone":"+1 516 872 3314",
    "sg:postcode":"11580",
    "sg:province":"NY",
    "sg:tags":[
        "contractor"
    ],
    "wof:name":"Prestige Marble & Granite",
    "wof:placetype":"venue"
},
  "geometry": {"coordinates":[-73.689379,40.661607],"type":"Point"}
}