{
  "type": "Feature",
  "properties": {
    "iso:country":"US",
    "sg:address":"224 Bayside Ave",
    "sg:city":"Oceanside",
    "sg:classifiers":[
        {
            "category":"Retail",
            "subcategory":"Repair Shop",
            "type":"Services"
        },
        {
            "category":"Wholesale",
            "subcategory":"Electrical",
            "type":"Manufacturing & Wholesale Goods"
        }
    ],
    "sg:phone":"+1 516 766 5655",
    "sg:postcode":"11572",
    "sg:province":"NY",
    "sg:tags":[
        "electronic",
        "intercommunication",
        "contractor"
    ],
    "wof:name":"No Bell Telephone & Alarm Co",
    "wof:placetype":"venue"
},
  "geometry": {"coordinates":[-73.649051,40.639229],"type":"Point"}
}