{
  "type": "Feature",
  "properties": {
    "iso:country":"US",
    "sg:address":"1751 Lake Rd",
    "sg:city":"Youngstown",
    "sg:classifiers":[
        {
            "category":"Building & Trades",
            "subcategory":"Electrical",
            "type":"Services"
        }
    ],
    "sg:phone":"+1 716 745 3554",
    "sg:postcode":"14174",
    "sg:province":"NY",
    "sg:tags":[
        "electrician"
    ],
    "wof:name":"Reed Electric Co",
    "wof:placetype":"venue"
},
  "geometry": {"coordinates":[-78.964651,43.280961],"type":"Point"}
}