{
  "type": "Feature",
  "properties": {
    "iso:country":"US",
    "sg:address":"16 Westwood Dr",
    "sg:city":"East Rochester",
    "sg:classifiers":[
        {
            "category":"Shopping",
            "subcategory":"Clothing, Apparel, & Fashions",
            "type":"Retail Goods"
        }
    ],
    "sg:phone":"+1   ",
    "sg:postcode":"14445",
    "sg:province":"NY",
    "wof:name":"Waverly Place",
    "wof:placetype":"venue"
},
  "geometry": {"coordinates":[-77.484329,43.106501],"type":"Point"}
}