{
  "type": "Feature",
  "properties": {
    "iso:country":"US",
    "sg:address":"29 Leroy St",
    "sg:city":"Potsdam",
    "sg:classifiers":[
        {
            "category":"Education",
            "subcategory":"School",
            "type":"Public Place"
        }
    ],
    "sg:phone":"+1 315 265 2003",
    "sg:postcode":"13676",
    "sg:province":"NY",
    "wof:name":"Lawrence Ave Elementary School",
    "wof:placetype":"venue"
},
  "geometry": {"coordinates":[-74.981353,44.674376],"type":"Point"}
}