{
  "type": "Feature",
  "properties": {
    "addr:full":"3172 Main St Buffalo NY 14214",
    "addr:housenumber":"3172",
    "addr:postcode":"14214",
    "addr:street":"Main St",
    "iso:country":"US",
    "sg:address":"3172 Main St",
    "sg:city":"Buffalo",
    "sg:classifiers":[
        {
            "category":"Deli",
            "type":"Food & Drink"
        },
        {
            "category":"Restaurant",
            "type":"Food & Drink"
        }
    ],
    "sg:menulink":"http://www.allmenus.com/ny/buffalo/245654-just--pizza/menu/",
    "sg:phone":"+1 716 831 9979",
    "sg:postcode":"14214",
    "sg:province":"NY",
    "sg:tags":[
        "deli",
        "american"
    ],
    "wof:name":"Just  Pizza",
    "wof:placetype":"venue"
},
  "geometry": {"coordinates":[-78.826331,42.950786],"type":"Point"}
}