{
  "type": "Feature",
  "properties": {
    "iso:country":"US",
    "sg:address":"9019 Renshaw Bay Rd",
    "sg:city":"Mannsville",
    "sg:classifiers":[
        {
            "category":"Building & Trades",
            "subcategory":"Construction",
            "type":"Services"
        }
    ],
    "sg:phone":"+1 315 387 5878",
    "sg:postcode":"13661",
    "sg:province":"NY",
    "sg:tags":[
        "floor",
        "laying",
        "contractor"
    ],
    "wof:name":"Locys Hardwood Floors",
    "wof:placetype":"venue"
},
  "geometry": {"coordinates":[-76.186874,43.683417],"type":"Point"}
}