{
  "type": "Feature",
  "properties": {
    "iso:country":"US",
    "sg:address":"4940 Southwestern Blvd",
    "sg:city":"Hamburg",
    "sg:classifiers":[
        {
            "category":"Autos & Motor Vehicles",
            "subcategory":"Auto Supplies",
            "type":"Retail Goods"
        }
    ],
    "sg:phone":"+1 716 649 1555",
    "sg:postcode":"14075",
    "sg:province":"NY",
    "sg:tags":[
        "tire"
    ],
    "wof:name":"Jarrell Tire",
    "wof:placetype":"venue"
},
  "geometry": {"coordinates":[-78.85150899999999,42.751335],"type":"Point"}
}