{
  "type": "Feature",
  "properties": {
    "iso:country":"US",
    "sg:address":"10 Old State Rd",
    "sg:city":"Castleton On Hudson",
    "sg:classifiers":[
        {
            "category":"Utilities",
            "subcategory":"Telephone",
            "type":"Services"
        }
    ],
    "sg:phone":"+1   ",
    "sg:postcode":"12057",
    "sg:province":"NY",
    "sg:tags":[
        "videoconferencing"
    ],
    "wof:name":"Aanet",
    "wof:placetype":"venue"
},
  "geometry": {"coordinates":[-73.38494300000001,42.951149],"type":"Point"}
}