{
  "type": "Feature",
  "properties": {
    "iso:country":"US",
    "sg:address":"4755 State Hwy 30",
    "sg:city":"Amsterdam",
    "sg:classifiers":[
        {
            "category":"Home & Garden",
            "subcategory":"Furniture",
            "type":"Retail Goods"
        }
    ],
    "sg:phone":"+1 518 842 5575",
    "sg:postcode":"12010",
    "sg:province":"NY",
    "sg:tags":[
        "mattress"
    ],
    "wof:name":"Sleep King",
    "wof:placetype":"venue"
},
  "geometry": {"coordinates":[-74.188712,42.978933],"type":"Point"}
}