{
  "type": "Feature",
  "properties": {
    "addr:full":"140 Lewis St Buffalo NY 14206",
    "addr:housenumber":"140",
    "addr:postcode":"14206",
    "addr:street":"Lewis St",
    "iso:country":"US",
    "sg:address":"140 Lewis St",
    "sg:city":"Buffalo",
    "sg:classifiers":[
        {
            "category":"Organizations",
            "subcategory":"Religious Organization",
            "type":"Services"
        }
    ],
    "sg:phone":"+1 716 854 4623",
    "sg:postcode":"14206",
    "sg:province":"NY",
    "sg:tags":[
        "church"
    ],
    "wof:name":"Precious Blood",
    "wof:placetype":"venue"
},
  "geometry": {"coordinates":[-78.832449,42.88139],"type":"Point"}
}