{
  "type": "Feature",
  "properties": {
    "iso:country":"US",
    "sg:address":"194 Guy Park Ave",
    "sg:city":"Amsterdam",
    "sg:classifiers":[
        {
            "category":"Restaurant",
            "type":"Food & Drink"
        }
    ],
    "sg:phone":"+1 518 843 8150",
    "sg:postcode":"12010",
    "sg:province":"NY",
    "wof:name":"T J Minnitti's",
    "wof:placetype":"venue"
},
  "geometry": {"coordinates":[-74.201247,42.946279],"type":"Point"}
}