{
  "type": "Feature",
  "properties": {
    "addr:full":"384 Savage Farm Dr Ithaca NY 14850",
    "addr:housenumber":"384",
    "addr:postcode":"14850",
    "addr:street":"Savage Farm Dr",
    "iso:country":"US",
    "sg:address":"384 Savage Farm Dr",
    "sg:city":"Ithaca",
    "sg:classifiers":[
        {
            "category":"Shopping",
            "subcategory":"Crafts & Fabrics",
            "type":"Retail Goods"
        }
    ],
    "sg:phone":"+1   ",
    "sg:postcode":"14850",
    "sg:province":"NY",
    "sg:tags":[
        "sewing"
    ],
    "wof:name":"Elmer Plastic Fabrics Corp",
    "wof:placetype":"venue"
},
  "geometry": {"coordinates":[-76.48464199999999,42.475084],"type":"Point"}
}