{
  "type": "Feature",
  "properties": {
    "addr:full":"2052 Tillotson Ave Bronx NY 10475",
    "addr:housenumber":"2052",
    "addr:postcode":"10475",
    "addr:street":"Tillotson Ave",
    "iso:country":"US",
    "sg:address":"2052 Tillotson Ave",
    "sg:city":"Bronx",
    "sg:classifiers":[
        {
            "category":"Health Services",
            "subcategory":"Clinic",
            "type":"Services"
        }
    ],
    "sg:phone":"+1 718 671 2100",
    "sg:postcode":"10475",
    "sg:province":"NY",
    "sg:tags":[
        "home",
        "care"
    ],
    "wof:name":"Pioneer Homecare Inc",
    "wof:placetype":"venue"
},
  "geometry": {"coordinates":[-73.83488,40.879898],"type":"Point"}
}