{
  "type": "Feature",
  "properties": {
    "iso:country":"US",
    "sg:address":"427 7th Avenue",
    "sg:city":"New York",
    "sg:classifiers":[
        {
            "category":"Restaurant",
            "type":"Food & Drink"
        }
    ],
    "sg:phone":"+1 212 563 3559",
    "sg:postcode":"10001",
    "sg:province":"NY",
    "sg:tags":[
        "chinese"
    ],
    "wof:name":"Chinatown Express",
    "wof:placetype":"venue"
},
  "geometry": {"coordinates":[-73.990982,40.750715],"type":"Point"}
}