{
  "type": "Feature",
  "properties": {
    "iso:country":"US",
    "sg:address":"81 Main St",
    "sg:city":"Hamburg",
    "sg:classifiers":[
        {
            "category":"Shopping",
            "type":"Retail Goods"
        }
    ],
    "sg:phone":"+1 716 648 0513",
    "sg:postcode":"14075",
    "sg:province":"NY",
    "sg:tags":[
        "coin",
        "dealer",
        "supply"
    ],
    "wof:name":"J C Enterprises",
    "wof:placetype":"venue"
},
  "geometry": {"coordinates":[-78.831602,42.716053],"type":"Point"}
}