{
  "type": "Feature",
  "properties": {
    "addr:full":"81 Chrystie St New York NY 10002",
    "addr:housenumber":"81",
    "addr:postcode":"10002",
    "addr:street":"Chrystie St",
    "iso:country":"US",
    "sg:address":"81 Chrystie St",
    "sg:city":"New York",
    "sg:classifiers":[
        {
            "category":"Restaurant",
            "type":"Food & Drink"
        }
    ],
    "sg:phone":"+1 212 343 3388",
    "sg:postcode":"10002",
    "sg:province":"NY",
    "sg:website":"www.nyvilla.com",
    "wof:name":"New York Villa Inc",
    "wof:placetype":"venue"
},
  "geometry": {"coordinates":[-73.994027,40.717835],"type":"Point"}
}