{
  "type": "Feature",
  "properties": {
    "addr:full":"507 Clinton St Brooklyn NY 11231",
    "addr:housenumber":"507",
    "addr:postcode":"11231",
    "addr:street":"Clinton St",
    "iso:country":"US",
    "sg:address":"507 Clinton St",
    "sg:city":"Brooklyn",
    "sg:classifiers":[
        {
            "category":"Food & Beverages",
            "subcategory":"Groceries & Convenience Stores",
            "type":"Retail Goods"
        }
    ],
    "sg:phone":"+1 718 852 6852",
    "sg:postcode":"11231",
    "sg:province":"NY",
    "wof:name":"Clinton Grocery",
    "wof:placetype":"venue"
},
  "geometry": {"coordinates":[-73.99990099999999,40.679001],"type":"Point"}
}