{
  "type": "Feature",
  "properties": {
    "iso:country":"US",
    "sg:address":"2735 21st St",
    "sg:city":"Astoria",
    "sg:classifiers":[
        {
            "category":"Real Estate",
            "subcategory":"Real Estate Services",
            "type":"Services"
        },
        {
            "category":"Real Estate",
            "subcategory":"Real Estate Agent",
            "type":"Services"
        }
    ],
    "sg:phone":"+1 347 642 8210",
    "sg:postcode":"11102",
    "sg:province":"NY",
    "sg:tags":[
        "buyer",
        "management",
        "broker"
    ],
    "wof:name":"San Vito Realty Holding",
    "wof:placetype":"venue"
},
  "geometry": {"coordinates":[-73.926624,40.771385],"type":"Point"}
}