{
  "type": "Feature",
  "properties": {
    "addr:full":"79-15 Main St Queens NY 11367",
    "addr:housenumber":"79-15",
    "addr:postcode":"11367",
    "addr:street":"Main St",
    "iso:country":"US",
    "sg:address":"79-15 Main St",
    "sg:city":"Queens",
    "sg:classifiers":[
        {
            "category":"Food & Beverages",
            "subcategory":"Groceries & Convenience Stores",
            "type":"Retail Goods"
        }
    ],
    "sg:phone":"+1 718 380 5159",
    "sg:postcode":"11367",
    "sg:province":"NY",
    "wof:name":"Key Food Supermarket",
    "wof:placetype":"venue"
},
  "geometry": {"coordinates":[-73.81761299999999,40.718509],"type":"Point"}
}