{
  "type": "Feature",
  "properties": {
    "iso:country":"US",
    "sg:address":"1887 State Hwy 90",
    "sg:city":"King Ferry",
    "sg:classifiers":[
        {
            "category":"Shopping",
            "subcategory":"Gifts & Souvenirs",
            "type":"Retail Goods"
        }
    ],
    "sg:phone":"+1 315 364 7908",
    "sg:postcode":"13081",
    "sg:province":"NY",
    "sg:tags":[
        "shop"
    ],
    "wof:name":"Kron Enterprises Inc",
    "wof:placetype":"venue"
},
  "geometry": {"coordinates":[-76.59845199999999,42.66577],"type":"Point"}
}