{
  "type": "Feature",
  "properties": {
    "iso:country":"US",
    "sg:address":"730 Ave Z",
    "sg:city":"Brooklyn",
    "sg:classifiers":[
        {
            "category":"Building & Trades",
            "subcategory":"Construction",
            "type":"Services"
        }
    ],
    "sg:phone":"+1 718 743 1621",
    "sg:postcode":"11223",
    "sg:province":"NY",
    "sg:tags":[
        "contractor"
    ],
    "wof:name":"Mf Roofing Co Inc",
    "wof:placetype":"venue"
},
  "geometry": {"coordinates":[-73.96676100000001,40.586508],"type":"Point"}
}