{
  "type": "Feature",
  "properties": {
    "iso:country":"US",
    "sg:address":"321 Co Rte 14",
    "sg:city":"Fulton",
    "sg:phone":"+1 315 592 7080",
    "sg:postcode":"13069",
    "sg:province":"NY",
    "sg:tags":[
        "oil"
    ],
    "wof:name":"Bill's Oil Svc",
    "wof:placetype":"venue"
},
  "geometry": {"coordinates":[-76.40458099999999,43.252722],"type":"Point"}
}