{
  "type": "Feature",
  "properties": {
    "addr:full":"124 West St Albany NY 12206",
    "addr:housenumber":"124",
    "addr:postcode":"12206",
    "addr:street":"West St",
    "iso:country":"US",
    "sg:address":"124 West St",
    "sg:city":"Albany",
    "sg:classifiers":[
        {
            "category":"Retail",
            "subcategory":"Auto Repair",
            "type":"Services"
        }
    ],
    "sg:phone":"+1 518 434 3711",
    "sg:postcode":"12206",
    "sg:province":"NY",
    "sg:tags":[
        "body",
        "automobile",
        "painting"
    ],
    "wof:name":"Cannistraci Auto Inc",
    "wof:placetype":"venue"
},
  "geometry": {"coordinates":[-73.77591200000001,42.665807],"type":"Point"}
}