{
  "type": "Feature",
  "properties": {
    "addr:full":"1650 Metropolitan Ave Bronx NY 10462",
    "addr:housenumber":"1650",
    "addr:postcode":"10462",
    "addr:street":"Metropolitan Ave",
    "iso:country":"US",
    "sg:address":"1650 Metropolitan Ave",
    "sg:city":"Bronx",
    "sg:classifiers":[
        {
            "category":"Professional",
            "subcategory":"Computer Services",
            "type":"Services"
        }
    ],
    "sg:phone":"+1 718 415 6311",
    "sg:postcode":"10462",
    "sg:province":"NY",
    "sg:tags":[
        "website",
        "design"
    ],
    "wof:name":"B2bu",
    "wof:placetype":"venue"
},
  "geometry": {"coordinates":[-73.855818,40.840333],"type":"Point"}
}