{
  "type": "Feature",
  "properties": {
    "addr:full":"6104 S Transit Rd Lockport NY 14094",
    "addr:housenumber":"6104",
    "addr:postcode":"14094",
    "addr:street":"S Transit Rd",
    "iso:country":"US",
    "sg:address":"6104 S Transit Rd",
    "sg:city":"Lockport",
    "sg:classifiers":[
        {
            "category":"Personal",
            "type":"Services"
        },
        {
            "category":"Retail",
            "subcategory":"Storage",
            "type":"Services"
        }
    ],
    "sg:phone":"+1 866 320 6309",
    "sg:postcode":"14094",
    "sg:province":"NY",
    "sg:tags":[
        "full",
        "self",
        "commercial",
        "mover",
        "household"
    ],
    "sg:website":"http://www.unclebobs.com/stores/UB340/?source=Yellowpages.com&howheard=ISM",
    "wof:name":"Uncle Bob's Self Storage",
    "wof:placetype":"venue"
},
  "geometry": {"coordinates":[-78.696899,43.128546],"type":"Point"}
}