{
  "type": "Feature",
  "properties": {
    "addr:full":"31 Sullivan Rd Lake George NY 12845",
    "addr:housenumber":"31",
    "addr:postcode":"12845",
    "addr:street":"Sullivan Rd",
    "iso:country":"US",
    "sg:address":"31 Sullivan Rd",
    "sg:city":"Lake George",
    "sg:classifiers":[
        {
            "category":"Building & Trades",
            "subcategory":"Construction",
            "type":"Services"
        }
    ],
    "sg:phone":"+1 518 792 3863",
    "sg:postcode":"12845",
    "sg:province":"NY",
    "sg:tags":[
        "hanging",
        "contractor"
    ],
    "wof:name":"Glen Lake Painters",
    "wof:placetype":"venue"
},
  "geometry": {"coordinates":[-73.680544,43.365646],"type":"Point"}
}