{
  "type": "Feature",
  "properties": {
    "addr:full":"17192 Roosevelt Hwy Kendall NY 14476",
    "addr:housenumber":"17192",
    "addr:postcode":"14476",
    "addr:street":"Roosevelt Hwy",
    "iso:country":"US",
    "sg:address":"17192 Roosevelt Hwy",
    "sg:city":"Kendall",
    "sg:classifiers":[
        {
            "category":"Real Estate",
            "subcategory":"Real Estate Agent",
            "type":"Services"
        }
    ],
    "sg:phone":"+1 585 659 2814",
    "sg:postcode":"14476",
    "sg:province":"NY",
    "wof:name":"Kts Noon Realty Associates LLC",
    "wof:placetype":"venue"
},
  "geometry": {"coordinates":[-78.010807,43.318566],"type":"Point"}
}