{
  "type": "Feature",
  "properties": {
    "addr:full":"6279 Lakeshore Rd Cicero NY 13039",
    "addr:housenumber":"6279",
    "addr:postcode":"13039",
    "addr:street":"Lakeshore Rd",
    "iso:country":"US",
    "sg:address":"6279 Lakeshore Rd",
    "sg:city":"Cicero",
    "sg:classifiers":[
        {
            "category":"Building & Trades",
            "subcategory":"Electrical",
            "type":"Services"
        }
    ],
    "sg:phone":"+1 315 699 7120",
    "sg:postcode":"13039",
    "sg:province":"NY",
    "sg:tags":[
        "electrical",
        "contractor"
    ],
    "wof:name":"A B C Electrical Service",
    "wof:placetype":"venue"
},
  "geometry": {"coordinates":[-76.089279,43.186377],"type":"Point"}
}