{
  "type": "Feature",
  "properties": {
    "addr:full":"1496 Inwood Avenue Bronx NY 10452",
    "addr:housenumber":"1496",
    "addr:postcode":"10452",
    "addr:street":"Inwood Avenue",
    "iso:country":"US",
    "sg:address":"1496 Inwood Avenue",
    "sg:city":"Bronx",
    "sg:classifiers":[
        {
            "category":"Retail",
            "subcategory":"Auto Repair",
            "type":"Services"
        }
    ],
    "sg:phone":"+1 718 294 5509",
    "sg:postcode":"10452",
    "sg:province":"NY",
    "wof:name":"Lalo's Auto Service Center",
    "wof:placetype":"venue"
},
  "geometry": {"coordinates":[-73.917204,40.842648],"type":"Point"}
}