{
  "type": "Feature",
  "properties": {
    "iso:country":"US",
    "sg:address":"4038 Sunrise Hwy",
    "sg:city":"Oakdale",
    "sg:classifiers":[
        {
            "category":"Shopping",
            "type":"Retail Goods"
        }
    ],
    "sg:phone":"+1 631 563 7200",
    "sg:postcode":"11769",
    "sg:province":"NY",
    "sg:tags":[
        "professional",
        "video",
        "equipment"
    ],
    "wof:name":"Islip Video & Electronics Inc",
    "wof:placetype":"venue"
},
  "geometry": {"coordinates":[-73.144637,40.748066],"type":"Point"}
}