{
  "type": "Feature",
  "properties": {
    "iso:country":"US",
    "sg:address":"1341 Kensington Ave",
    "sg:city":"Buffalo",
    "sg:classifiers":[
        {
            "category":"Bars & Pubs",
            "type":"Food & Drink"
        }
    ],
    "sg:phone":"+1 716 837 4102",
    "sg:postcode":"14215",
    "sg:province":"NY",
    "wof:name":"Stop Inn",
    "wof:placetype":"venue"
},
  "geometry": {"coordinates":[-78.805904,42.941003],"type":"Point"}
}