{
  "type": "Feature",
  "properties": {
    "addr:full":"5721 6th Ave Brooklyn NY 11220",
    "addr:housenumber":"5721",
    "addr:postcode":"11220",
    "addr:street":"6Th Ave",
    "iso:country":"US",
    "sg:address":"5721 6th Ave",
    "sg:city":"Brooklyn",
    "sg:classifiers":[
        {
            "category":"Organizations",
            "subcategory":"Religious Organization",
            "type":"Services"
        }
    ],
    "sg:phone":"+1 718 439 9795",
    "sg:postcode":"11220",
    "sg:province":"NY",
    "sg:tags":[
        "church"
    ],
    "wof:name":"Our Lady Of Perpetual Help",
    "wof:placetype":"venue"
},
  "geometry": {"coordinates":[-74.01262699999999,40.639363],"type":"Point"}
}