{
  "type": "Feature",
  "properties": {
    "addr:full":"143 Walden Galleria Buffalo NY 14225",
    "addr:housenumber":"143",
    "addr:postcode":"14225",
    "addr:street":"Walden Galleria",
    "iso:country":"US",
    "sg:address":"143 Walden Galleria",
    "sg:city":"Buffalo",
    "sg:classifiers":[
        {
            "category":"Shopping",
            "subcategory":"Clothing, Apparel, & Fashions",
            "type":"Retail Goods"
        }
    ],
    "sg:phone":"+1 716 683 2530",
    "sg:postcode":"14225",
    "sg:province":"NY",
    "sg:tags":[
        "men's",
        "women's",
        "apparel",
        "accessory",
        "clothing",
        "store"
    ],
    "sg:website":"http://www.abercrombie.com",
    "wof:name":"Abercrombie & Fitch",
    "wof:placetype":"venue"
},
  "geometry": {"coordinates":[-78.76190200000001,42.909592],"type":"Point"}
}