{
  "type": "Feature",
  "properties": {
    "addr:full":"9769 US Hwy 9 Chazy NY 12921",
    "addr:housenumber":"9769",
    "addr:postcode":"12921",
    "addr:street":"Us Hwy 9 Chazy",
    "iso:country":"US",
    "sg:address":"9769 US Hwy 9",
    "sg:city":"Chazy",
    "sg:classifiers":[
        {
            "category":"Health Services",
            "subcategory":"Health Practitioner",
            "type":"Services"
        }
    ],
    "sg:phone":"+1 518 846 3900",
    "sg:postcode":"12921",
    "sg:province":"NY",
    "sg:tags":[
        "therapist",
        "physical"
    ],
    "wof:name":"North Country Physical Therapy",
    "wof:placetype":"venue"
},
  "geometry": {"coordinates":[-73.43748100000001,44.908262],"type":"Point"}
}