{
  "type": "Feature",
  "properties": {
    "addr:full":"2779 3rd Ave Bronx NY 10455",
    "addr:housenumber":"2779",
    "addr:postcode":"10455",
    "addr:street":"3Rd Ave",
    "iso:country":"US",
    "sg:address":"2779 3rd Ave",
    "sg:city":"Bronx",
    "sg:classifiers":[
        {
            "category":"Health Services",
            "subcategory":"Doctor",
            "type":"Services"
        }
    ],
    "sg:phone":"+1   ",
    "sg:postcode":"10455",
    "sg:province":"NY",
    "wof:name":"Dental Management & Dev",
    "wof:placetype":"venue"
},
  "geometry": {"coordinates":[-73.919636,40.815051],"type":"Point"}
}