{
  "type": "Feature",
  "properties": {
    "iso:country":"US",
    "sg:address":"30 Hart St",
    "sg:city":"Rochester",
    "sg:classifiers":[
        {
            "category":"Education",
            "subcategory":"School",
            "type":"Public Place"
        }
    ],
    "sg:phone":"+1 585 325 0935",
    "sg:postcode":"14605",
    "sg:province":"NY",
    "sg:tags":[
        "high"
    ],
    "sg:website":"http://www.easthighschool.net",
    "wof:name":"Senior High Alt Program Shape",
    "wof:placetype":"venue"
},
  "geometry": {"coordinates":[-77.618354,43.170964],"type":"Point"}
}