{
  "type": "Feature",
  "properties": {
    "addr:full":"504 Warren St Fayetteville NY 13066",
    "addr:housenumber":"504",
    "addr:postcode":"13066",
    "addr:street":"Warren St",
    "iso:country":"US",
    "sg:address":"504 Warren St",
    "sg:city":"Fayetteville",
    "sg:classifiers":[
        {
            "category":"Shopping",
            "subcategory":"Gifts & Souvenirs",
            "type":"Retail Goods"
        }
    ],
    "sg:phone":"+1   ",
    "sg:postcode":"13066",
    "sg:province":"NY",
    "wof:name":"Bindle The",
    "wof:placetype":"venue"
},
  "geometry": {"coordinates":[-76.009131,43.024551],"type":"Point"}
}