{
  "type": "Feature",
  "properties": {
    "addr:full":"16 Greenvalley Dr Big Flats NY 14814",
    "addr:housenumber":"16",
    "addr:postcode":"14814",
    "addr:street":"Greenvalley Dr Big",
    "iso:country":"US",
    "sg:address":"16 Greenvalley Dr",
    "sg:city":"Big Flats",
    "sg:classifiers":[
        {
            "category":"Professional",
            "subcategory":"Engineering",
            "type":"Services"
        }
    ],
    "sg:phone":"+1 607 562 3141",
    "sg:postcode":"14814",
    "sg:province":"NY",
    "sg:tags":[
        "engineer"
    ],
    "wof:name":"Pathways To Performance Exclnc",
    "wof:placetype":"venue"
},
  "geometry": {"coordinates":[-76.94524,42.143911],"type":"Point"}
}