{
  "type": "Feature",
  "properties": {
    "addr:full":"66 Church St Spring Valley NY 10977",
    "addr:housenumber":"66",
    "addr:postcode":"10977",
    "addr:street":"Church St",
    "iso:country":"US",
    "sg:address":"66 Church St",
    "sg:city":"Spring Valley",
    "sg:classifiers":[
        {
            "category":"Real Estate",
            "subcategory":"Real Estate Agent",
            "type":"Services"
        }
    ],
    "sg:phone":"+1 845 356 4555",
    "sg:postcode":"10977",
    "sg:province":"NY",
    "wof:name":"Y & T Real Estate Management",
    "wof:placetype":"venue"
},
  "geometry": {"coordinates":[-74.051682,41.113335],"type":"Point"}
}