{
  "type": "Feature",
  "properties": {
    "iso:country":"US",
    "sg:address":"50 N Bayles Ave",
    "sg:city":"Port Washington",
    "sg:classifiers":[
        {
            "category":"Professional",
            "subcategory":"Computer Services",
            "type":"Services"
        }
    ],
    "sg:phone":"+1 516 883 2459",
    "sg:postcode":"11050",
    "sg:province":"NY",
    "sg:tags":[
        "prepackaged",
        "software",
        "custom"
    ],
    "wof:name":"Intelligent Software Products",
    "wof:placetype":"venue"
},
  "geometry": {"coordinates":[-73.687793,40.833981],"type":"Point"}
}