{
  "type": "Feature",
  "properties": {
    "iso:country":"US",
    "sg:address":"243 Broadway",
    "sg:city":"Huntington Sta",
    "sg:classifiers":[
        {
            "category":"Retail",
            "subcategory":"Repair Shop",
            "type":"Services"
        }
    ],
    "sg:phone":"+1 631 223 0594",
    "sg:postcode":"11746",
    "sg:province":"NY",
    "sg:tags":[
        "lock",
        "locksmith"
    ],
    "wof:name":"24 Hour Locksmith",
    "wof:placetype":"venue"
},
  "geometry": {"coordinates":[-73.40249799999999,40.856498],"type":"Point"}
}