{
  "type": "Feature",
  "properties": {
    "addr:full":"6060 Co Rd 32 Norwich NY 13815",
    "addr:housenumber":"6060;32",
    "addr:postcode":"13815",
    "addr:street":"Co Rd",
    "iso:country":"US",
    "sg:address":"6060 Co Rd 32",
    "sg:city":"Norwich",
    "sg:classifiers":[
        {
            "category":"Building & Trades",
            "subcategory":"Landscaping Services",
            "type":"Services"
        }
    ],
    "sg:phone":"+1 607 336 1848",
    "sg:postcode":"13815",
    "sg:province":"NY",
    "sg:tags":[
        "landscape",
        "contractor"
    ],
    "wof:name":"Gray's Landscaping",
    "wof:placetype":"venue"
},
  "geometry": {"coordinates":[-75.509411,42.540516],"type":"Point"}
}