{
  "type": "Feature",
  "properties": {
    "iso:country":"US",
    "sg:address":"309 Union St",
    "sg:city":"Schenectady",
    "sg:classifiers":[
        {
            "category":"Professional",
            "type":"Services"
        }
    ],
    "sg:phone":"+1 518 346 6692",
    "sg:postcode":"12305",
    "sg:province":"NY",
    "sg:tags":[
        "establishment"
    ],
    "wof:name":"USA Recovery",
    "wof:placetype":"venue"
},
  "geometry": {"coordinates":[-73.94071099999999,42.816296],"type":"Point"}
}