{
  "type": "Feature",
  "properties": {
    "addr:full":"2058 Allen St Exd Falconer NY 14701",
    "addr:housenumber":"2058",
    "addr:postcode":"14701",
    "addr:street":"Allen St Exd",
    "iso:country":"US",
    "sg:address":"2058 Allen St Exd",
    "sg:city":"Falconer",
    "sg:classifiers":[
        {
            "category":"Wholesale",
            "subcategory":"Groceries",
            "type":"Manufacturing & Wholesale Goods"
        }
    ],
    "sg:phone":"+1 716 665 5600",
    "sg:postcode":"14701",
    "sg:province":"NY",
    "sg:tags":[
        "food",
        "product"
    ],
    "sg:website":"www.sysco.com",
    "wof:name":"Sysco Food Svc Of Jamestown",
    "wof:placetype":"venue"
},
  "geometry": {"coordinates":[-79.193365,42.113156],"type":"Point"}
}