{
  "type": "Feature",
  "properties": {
    "iso:country":"US",
    "sg:address":"4923 16th Ave",
    "sg:city":"Brooklyn",
    "sg:classifiers":[
        {
            "category":"Shopping",
            "subcategory":"Clothing, Apparel, & Fashions",
            "type":"Retail Goods"
        }
    ],
    "sg:phone":"+1   ",
    "sg:postcode":"11204",
    "sg:province":"NY",
    "sg:tags":[
        "lingerie"
    ],
    "wof:name":"Fantasy Lingerie",
    "wof:placetype":"venue"
},
  "geometry": {"coordinates":[-73.985935,40.630557],"type":"Point"}
}