{
  "type": "Feature",
  "properties": {
    "addr:full":"18 Corporate Cir Ste 2 Albany NY 12203",
    "addr:housenumber":"18",
    "addr:postcode":"12203",
    "addr:street":"Corporate Cir Ste 2",
    "iso:country":"US",
    "sg:address":"18 Corporate Cir Ste 2",
    "sg:city":"Albany",
    "sg:classifiers":[
        {
            "category":"Professional",
            "subcategory":"Lawyer & Legal Services",
            "type":"Services"
        }
    ],
    "sg:phone":"+1 518 434 1300",
    "sg:postcode":"12203",
    "sg:province":"NY",
    "sg:tags":[
        "information",
        "attorney",
        "referral"
    ],
    "wof:name":"Goldberger, Franklin H Law Offices Of",
    "wof:placetype":"venue"
},
  "geometry": {"coordinates":[-73.877054,42.70191],"type":"Point"}
}