{
  "type": "Feature",
  "properties": {
    "addr:full":"220 Elk St Buffalo NY 14210",
    "addr:housenumber":"220",
    "addr:postcode":"14210",
    "addr:street":"Elk St",
    "iso:country":"US",
    "sg:address":"220 Elk St",
    "sg:city":"Buffalo",
    "sg:classifiers":[
        {
            "category":"Building & Trades",
            "subcategory":"Electrical",
            "type":"Services"
        }
    ],
    "sg:phone":"+1 716 822 7233",
    "sg:postcode":"14210",
    "sg:province":"NY",
    "sg:tags":[
        "electrical",
        "contractor"
    ],
    "wof:name":"Safe One Security LLC",
    "wof:placetype":"venue"
},
  "geometry": {"coordinates":[-78.844533,42.868297],"type":"Point"}
}