{
  "type": "Feature",
  "properties": {
    "addr:full":"12712 Vaughn St Springville NY 14141",
    "addr:housenumber":"12712",
    "addr:postcode":"14141",
    "addr:street":"Vaughn St",
    "iso:country":"US",
    "sg:address":"12712 Vaughn St",
    "sg:city":"Springville",
    "sg:classifiers":[
        {
            "category":"Personal",
            "subcategory":"Beauty Salon",
            "type":"Services"
        }
    ],
    "sg:phone":"+1 716 592 3545",
    "sg:postcode":"14141",
    "sg:province":"NY",
    "wof:name":"A Cut Above The Rest",
    "wof:placetype":"venue"
},
  "geometry": {"coordinates":[-78.64073399999999,42.51867],"type":"Point"}
}