{
  "type": "Feature",
  "properties": {
    "addr:full":"15 Golf Course Rd E Shandaken NY 12480",
    "addr:housenumber":"15",
    "addr:postcode":"12480",
    "addr:street":"Golf Course Rd E",
    "iso:country":"US",
    "sg:address":"15 Golf Course Rd E",
    "sg:city":"Shandaken",
    "sg:classifiers":[
        {
            "category":"Building & Trades",
            "subcategory":"Electrical",
            "type":"Services"
        }
    ],
    "sg:phone":"+1 845 688 2009",
    "sg:postcode":"12480",
    "sg:province":"NY",
    "sg:tags":[
        "electrical",
        "contractor"
    ],
    "wof:name":"Doug Thornton",
    "wof:placetype":"venue"
},
  "geometry": {"coordinates":[-74.409802,42.117554],"type":"Point"}
}