{
  "type": "Feature",
  "properties": {
    "addr:full":"43 Harriet Pl Lynbrook NY 11563",
    "addr:housenumber":"43",
    "addr:postcode":"11563",
    "addr:street":"Harriet Pl",
    "iso:country":"US",
    "sg:address":"43 Harriet Pl",
    "sg:city":"Lynbrook",
    "sg:classifiers":[
        {
            "category":"Manufacturing",
            "subcategory":"Tools & Machinery",
            "type":"Manufacturing & Wholesale Goods"
        }
    ],
    "sg:phone":"+1 516 887 5180",
    "sg:postcode":"11563",
    "sg:province":"NY",
    "sg:tags":[
        "equipment",
        "hospital",
        "supply"
    ],
    "wof:name":"R C Svc",
    "wof:placetype":"venue"
},
  "geometry": {"coordinates":[-73.66442600000001,40.65723],"type":"Point"}
}