{
  "type": "Feature",
  "properties": {
    "iso:country":"US",
    "sg:address":"2291 Union Rd",
    "sg:city":"Buffalo",
    "sg:classifiers":[
        {
            "category":"Health Services",
            "subcategory":"Chiropractor",
            "type":"Services"
        }
    ],
    "sg:phone":"+1 716 668 4205",
    "sg:postcode":"14224",
    "sg:province":"NY",
    "wof:name":"Michael J Prentice DC",
    "wof:placetype":"venue"
},
  "geometry": {"coordinates":[-78.754356,42.863234],"type":"Point"}
}