{
  "type": "Feature",
  "properties": {
    "addr:full":"630 Old Country Rd Garden City NY 11530",
    "addr:housenumber":"630",
    "addr:postcode":"11530",
    "addr:street":"Old Country Rd",
    "iso:country":"US",
    "sg:address":"630 Old Country Rd",
    "sg:city":"Garden City",
    "sg:classifiers":[
        {
            "category":"Bakery",
            "type":"Food & Drink"
        }
    ],
    "sg:menulink":"http://www.allmenus.com/ny/garden-city/220076-auntie-annes-pretzels/menu/",
    "sg:phone":"+1 516 739 8200",
    "sg:postcode":"11530",
    "sg:province":"NY",
    "sg:tags":[
        "american",
        "pastry"
    ],
    "wof:name":"Auntie Anne's Pretzels",
    "wof:placetype":"venue"
},
  "geometry": {"coordinates":[-73.61414000000001,40.743159],"type":"Point"}
}