{
  "type": "Feature",
  "properties": {
    "iso:country":"US",
    "sg:address":"35 Lombardy St",
    "sg:city":"Lancaster",
    "sg:classifiers":[
        {
            "category":"Wholesale",
            "subcategory":"Motor Vehicles",
            "type":"Manufacturing & Wholesale Goods"
        }
    ],
    "sg:phone":"+1 716 685 4839",
    "sg:postcode":"14086",
    "sg:province":"NY",
    "wof:name":"Scherrer",
    "wof:placetype":"venue"
},
  "geometry": {"coordinates":[-78.66482499999999,42.897102],"type":"Point"}
}