{
  "type": "Feature",
  "properties": {
    "addr:full":"423 Atlantic Ave Brooklyn NY 11217",
    "addr:housenumber":"423",
    "addr:postcode":"11217",
    "addr:street":"Atlantic Ave",
    "iso:country":"US",
    "sg:address":"423 Atlantic Ave",
    "sg:city":"Brooklyn",
    "sg:classifiers":[
        {
            "category":"Arts & Performance",
            "subcategory":"Theater",
            "type":"Entertainment"
        }
    ],
    "sg:phone":"+1 718 875 4498",
    "sg:postcode":"11217",
    "sg:province":"NY",
    "sg:tags":[
        "musician",
        "group"
    ],
    "sg:website":"www.robineubanks.com",
    "wof:name":"Robin Eubanks Music",
    "wof:placetype":"venue"
},
  "geometry": {"coordinates":[-73.983322,40.686509],"type":"Point"}
}