{
  "type": "Feature",
  "properties": {
    "addr:full":"2513 Penfield Rd Fairport NY 14450",
    "addr:housenumber":"2513",
    "addr:postcode":"14450",
    "addr:street":"Penfield Rd",
    "iso:country":"US",
    "sg:address":"2513 Penfield Rd",
    "sg:city":"Fairport",
    "sg:classifiers":[
        {
            "category":"Travel",
            "subcategory":"Hotels & Motels",
            "type":"Entertainment"
        }
    ],
    "sg:phone":"+1 585 388 9442",
    "sg:postcode":"14450",
    "sg:province":"NY",
    "sg:tags":[
        "breakfast",
        "accommodation",
        "bed"
    ],
    "wof:name":"Clematis Inn",
    "wof:placetype":"venue"
},
  "geometry": {"coordinates":[-77.404971,43.130443],"type":"Point"}
}