{
  "type": "Feature",
  "properties": {
    "addr:full":"179 Brady Ave Hawthorne NY 10532",
    "addr:housenumber":"179",
    "addr:postcode":"10532",
    "addr:street":"Brady Ave",
    "iso:country":"US",
    "sg:address":"179 Brady Ave",
    "sg:city":"Hawthorne",
    "sg:classifiers":[
        {
            "category":"Retail",
            "subcategory":"Auto Repair",
            "type":"Services"
        }
    ],
    "sg:phone":"+1 914 769 7447",
    "sg:postcode":"10532",
    "sg:province":"NY",
    "wof:name":"Auto Action",
    "wof:placetype":"venue"
},
  "geometry": {"coordinates":[-73.794296,41.0993],"type":"Point"}
}