{
  "type": "Feature",
  "properties": {
    "addr:full":"16 Mueller Dr Selden NY 11784",
    "addr:housenumber":"16",
    "addr:postcode":"11784",
    "addr:street":"Mueller Dr",
    "iso:country":"US",
    "sg:address":"16 Mueller Dr",
    "sg:city":"Selden",
    "sg:classifiers":[
        {
            "category":"Manufacturing",
            "subcategory":"Tools & Machinery",
            "type":"Manufacturing & Wholesale Goods"
        }
    ],
    "sg:phone":"+1   ",
    "sg:postcode":"11784",
    "sg:province":"NY",
    "sg:tags":[
        "recording",
        "medium",
        "mfg"
    ],
    "wof:name":"Transpower Inc",
    "wof:placetype":"venue"
},
  "geometry": {"coordinates":[-73.056617,40.853401],"type":"Point"}
}