{
  "type": "Feature",
  "properties": {
    "addr:full":"315 Middle Country Rd Middle Island NY 11953",
    "addr:housenumber":"315",
    "addr:postcode":"11953",
    "addr:street":"Middle Country Rd Middle Island",
    "iso:country":"US",
    "sg:address":"315 Middle Country Rd",
    "sg:city":"Middle Island",
    "sg:classifiers":[
        {
            "category":"Recreation",
            "type":"Entertainment"
        }
    ],
    "sg:phone":"+1 631 345 0100",
    "sg:postcode":"11953",
    "sg:province":"NY",
    "sg:tags":[
        "martial",
        "arts",
        "instruction"
    ],
    "wof:name":"AFC Kickboxing",
    "wof:placetype":"venue"
},
  "geometry": {"coordinates":[-72.966246,40.878017],"type":"Point"}
}