{
  "type": "Feature",
  "properties": {
    "iso:country":"US",
    "sg:address":"16 Mc Kenzie St",
    "sg:city":"Huntington",
    "sg:classifiers":[
        {
            "category":"Shopping",
            "subcategory":"Optical Goods",
            "type":"Retail Goods"
        }
    ],
    "sg:phone":"+1   ",
    "sg:postcode":"11743",
    "sg:province":"NY",
    "wof:name":"Raven Optical",
    "wof:placetype":"venue"
},
  "geometry": {"coordinates":[-73.43059700000001,40.894697],"type":"Point"}
}