{
  "type": "Feature",
  "properties": {
    "iso:country":"US",
    "sg:address":"65 W 55th St",
    "sg:city":"New York",
    "sg:classifiers":[
        {
            "category":"Building & Trades",
            "subcategory":"Construction",
            "type":"Services"
        }
    ],
    "sg:phone":"+1 212 397 8929",
    "sg:postcode":"10019",
    "sg:province":"NY",
    "sg:tags":[
        "contractor"
    ],
    "wof:name":"Fmg Construction",
    "wof:placetype":"venue"
},
  "geometry": {"coordinates":[-73.976997,40.7626],"type":"Point"}
}