{
  "type": "Feature",
  "properties": {
    "iso:country":"US",
    "sg:address":"1234 Yonkers Ave",
    "sg:city":"Yonkers",
    "sg:classifiers":[
        {
            "category":"Bars & Pubs",
            "type":"Food & Drink"
        }
    ],
    "sg:phone":"+1 914 237 9815",
    "sg:postcode":"10704",
    "sg:province":"NY",
    "sg:tags":[
        "drinking"
    ],
    "wof:name":"White Heather Pub Inc",
    "wof:placetype":"venue"
},
  "geometry": {"coordinates":[-73.85102000000001,40.914675],"type":"Point"}
}