{
  "type": "Feature",
  "properties": {
    "addr:full":"13 McWhorter St Brentwood NY 11717",
    "addr:housenumber":"13",
    "addr:postcode":"11717",
    "addr:street":"Mcwhorter St",
    "iso:country":"US",
    "sg:address":"13 McWhorter St",
    "sg:city":"Brentwood",
    "sg:classifiers":[
        {
            "category":"Social Services",
            "type":"Services"
        }
    ],
    "sg:phone":"+1 631 231 4333",
    "sg:postcode":"11717",
    "sg:province":"NY",
    "sg:tags":[
        "counseling"
    ],
    "wof:name":"Brentwood Youth Development",
    "wof:placetype":"venue"
},
  "geometry": {"coordinates":[-73.246809,40.78226],"type":"Point"}
}