{
  "type": "Feature",
  "properties": {
    "addr:full":"1101 E Tremont Ave #3 Bronx NY 10460",
    "addr:housenumber":"1101",
    "addr:postcode":"10460",
    "addr:street":"E Tremont Ave # 3",
    "iso:country":"US",
    "sg:address":"1101 E Tremont Ave #3",
    "sg:city":"Bronx",
    "sg:classifiers":[
        {
            "category":"Building & Trades",
            "subcategory":"Locksmith",
            "type":"Services"
        },
        {
            "category":"Building & Trades",
            "subcategory":"Construction",
            "type":"Services"
        }
    ],
    "sg:phone":"+1 917 677 5190",
    "sg:postcode":"10460",
    "sg:province":"NY",
    "sg:tags":[
        "key",
        "contractor"
    ],
    "wof:name":"Remote Controlled Door Opener",
    "wof:placetype":"venue"
},
  "geometry": {"coordinates":[-73.876892,40.84037],"type":"Point"}
}