{
  "type": "Feature",
  "properties": {
    "addr:full":"10 Leroy St Staten Island NY 10314",
    "addr:housenumber":"10",
    "addr:postcode":"10314",
    "addr:street":"Leroy St",
    "iso:country":"US",
    "sg:address":"10 Leroy St",
    "sg:city":"Staten Island",
    "sg:classifiers":[
        {
            "category":"Shopping",
            "subcategory":"Computers & Home Electronics",
            "type":"Retail Goods"
        }
    ],
    "sg:phone":"+1   ",
    "sg:postcode":"10314",
    "sg:province":"NY",
    "wof:name":"A-Tech Computers",
    "wof:placetype":"venue"
},
  "geometry": {"coordinates":[-74.18714900000001,40.594368],"type":"Point"}
}