{
  "type": "Feature",
  "properties": {
    "iso:country":"US",
    "sg:address":"1259 Veterans Hwy",
    "sg:city":"Hauppauge",
    "sg:classifiers":[
        {
            "category":"Shopping",
            "subcategory":"Stationery & Office Supplies",
            "type":"Retail Goods"
        }
    ],
    "sg:phone":"+1 631 979 8030",
    "sg:postcode":"11788",
    "sg:province":"NY",
    "sg:tags":[
        "equipment"
    ],
    "wof:name":"Card Fanatics Inc",
    "wof:placetype":"venue"
},
  "geometry": {"coordinates":[-73.1931,40.815701],"type":"Point"}
}