{
  "type": "Feature",
  "properties": {
    "addr:full":"230 E 79 St New York NY 10075",
    "addr:housenumber":"230;79",
    "addr:postcode":"10075",
    "addr:street":"E;St",
    "iso:country":"US",
    "sg:address":"230 E 79 St",
    "sg:city":"New York",
    "sg:classifiers":[
        {
            "category":"Banks & Credit Unions",
            "subcategory":"Financial Services",
            "type":"Services"
        }
    ],
    "sg:phone":"+1 212 585 1668",
    "sg:postcode":"10075",
    "sg:province":"NY",
    "sg:tags":[
        "trust",
        "management"
    ],
    "wof:name":"Ageless Foundation",
    "wof:placetype":"venue"
},
  "geometry": {"coordinates":[-73.955055,40.773337],"type":"Point"}
}