{
  "type": "Feature",
  "properties": {
    "addr:full":"404 Park Ave S Fl 5 New York NY 10016",
    "addr:housenumber":"404;5",
    "addr:postcode":"10016",
    "addr:street":"Park Ave S Fl",
    "iso:country":"US",
    "sg:address":"404 Park Ave S Fl 5",
    "sg:city":"New York",
    "sg:classifiers":[
        {
            "category":"Banks & Credit Unions",
            "subcategory":"Investment Brokerage",
            "type":"Services"
        }
    ],
    "sg:phone":"+1 646 957 9100",
    "sg:postcode":"10016",
    "sg:province":"NY",
    "sg:tags":[
        "investing"
    ],
    "wof:name":"Dinosaur Securities",
    "wof:placetype":"venue"
},
  "geometry": {"coordinates":[-73.984295,40.743431],"type":"Point"}
}