{
  "type": "Feature",
  "properties": {
    "addr:full":"8523 Fort Hamilton Pkwy Brooklyn NY 11209",
    "addr:housenumber":"8523",
    "addr:postcode":"11209",
    "addr:street":"Fort Hamilton Pkwy",
    "iso:country":"US",
    "sg:address":"8523 Fort Hamilton Pkwy",
    "sg:city":"Brooklyn",
    "sg:classifiers":[
        {
            "category":"Health Services",
            "subcategory":"Health Practitioner",
            "type":"Services"
        }
    ],
    "sg:phone":"+1 718 418 7171",
    "sg:postcode":"11209",
    "sg:province":"NY",
    "sg:tags":[
        "therapist",
        "physical"
    ],
    "wof:name":"Physical Therapy Of Queeens",
    "wof:placetype":"venue"
},
  "geometry": {"coordinates":[-74.02428399999999,40.620495],"type":"Point"}
}