{
  "type": "Feature",
  "properties": {
    "iso:country":"US",
    "sg:address":"243 Hoke Ave",
    "sg:city":"Oceanside",
    "sg:classifiers":[
        {
            "category":"Professional",
            "subcategory":"Management & Consulting",
            "type":"Services"
        }
    ],
    "sg:phone":"+1   ",
    "sg:postcode":"11572",
    "sg:province":"NY",
    "wof:name":"342 Quentin Management Corp",
    "wof:placetype":"venue"
},
  "geometry": {"coordinates":[-73.64888000000001,40.638038],"type":"Point"}
}