{
  "type": "Feature",
  "properties": {
    "addr:full":"24 Humboldt St Brooklyn NY 11206",
    "addr:housenumber":"24",
    "addr:postcode":"11206",
    "addr:street":"Humboldt St",
    "iso:country":"US",
    "sg:address":"24 Humboldt St",
    "sg:city":"Brooklyn",
    "sg:classifiers":[
        {
            "category":"Food & Beverages",
            "subcategory":"Fruits & Vegetables",
            "type":"Retail Goods"
        }
    ],
    "sg:phone":"+1   ",
    "sg:postcode":"11206",
    "sg:province":"NY",
    "wof:name":"Moore 3 Market",
    "wof:placetype":"venue"
},
  "geometry": {"coordinates":[-73.94068900000001,40.703103],"type":"Point"}
}