{
  "type": "Feature",
  "properties": {
    "addr:full":"926 Post Ave Staten Island NY 10302",
    "addr:housenumber":"926",
    "addr:postcode":"10302",
    "addr:street":"Post Ave",
    "iso:country":"US",
    "sg:address":"926 Post Ave",
    "sg:city":"Staten Island",
    "sg:classifiers":[
        {
            "category":"Professional",
            "type":"Services"
        }
    ],
    "sg:phone":"+1 718 816 9428",
    "sg:postcode":"10302",
    "sg:province":"NY",
    "sg:tags":[
        "establishment"
    ],
    "wof:name":"Abdelnaser Shalabi",
    "wof:placetype":"venue"
},
  "geometry": {"coordinates":[-74.131568,40.631266],"type":"Point"}
}