{
  "type": "Feature",
  "properties": {
    "addr:full":"1655 Elmwood Ave Rochester NY 14620",
    "addr:housenumber":"1655",
    "addr:postcode":"14620",
    "addr:street":"Elmwood Ave",
    "iso:country":"US",
    "sg:address":"1655 Elmwood Ave",
    "sg:city":"Rochester",
    "sg:classifiers":[
        {
            "category":"Health Services",
            "subcategory":"Doctor",
            "type":"Services"
        }
    ],
    "sg:phone":"+1 585 214 4673",
    "sg:postcode":"14620",
    "sg:province":"NY",
    "sg:tags":[
        "physician",
        "surgeon"
    ],
    "wof:name":"Pamela Sloan MD",
    "wof:placetype":"venue"
},
  "geometry": {"coordinates":[-77.589843,43.125626],"type":"Point"}
}