{
  "type": "Feature",
  "properties": {
    "iso:country":"US",
    "sg:address":"402 Rosevale Ave",
    "sg:city":"Ronkonkoma",
    "sg:classifiers":[
        {
            "category":"Professional",
            "type":"Services"
        }
    ],
    "sg:phone":"+1 631 738 0684",
    "sg:postcode":"11779",
    "sg:province":"NY",
    "sg:tags":[
        "establishment"
    ],
    "wof:name":"Global NA Ps",
    "wof:placetype":"venue"
},
  "geometry": {"coordinates":[-73.1306,40.823692],"type":"Point"}
}