{
  "type": "Feature",
  "properties": {
    "iso:country":"US",
    "sg:address":"31 W 47 St",
    "sg:city":"New York",
    "sg:classifiers":[
        {
            "category":"Shopping",
            "subcategory":"Jewelry",
            "type":"Retail Goods"
        }
    ],
    "sg:phone":"+1 212 382 2949",
    "sg:postcode":"10036",
    "sg:province":"NY",
    "sg:tags":[
        "jeweler"
    ],
    "wof:name":"Jewelers Assay Inc",
    "wof:placetype":"venue"
},
  "geometry": {"coordinates":[-73.981009,40.757668],"type":"Point"}
}