{
  "type": "Feature",
  "properties": {
    "addr:full":"99 Tulip Ave Ste 109 & 302 Floral Park NY 11001",
    "addr:housenumber":"99;302",
    "addr:postcode":"11001",
    "addr:street":"Tulip Ave Ste 109 &",
    "iso:country":"US",
    "sg:address":"99 Tulip Ave Ste 109 & 302",
    "sg:city":"Floral Park",
    "sg:classifiers":[
        {
            "category":"Real Estate",
            "subcategory":"Real Estate Services",
            "type":"Services"
        }
    ],
    "sg:phone":"+1 718 721 0700",
    "sg:postcode":"11001",
    "sg:province":"NY",
    "sg:tags":[
        "management",
        "property"
    ],
    "sg:website":"aarsny.com/",
    "wof:name":"All Area Realty Services",
    "wof:placetype":"venue"
},
  "geometry": {"coordinates":[-73.705333,40.725169],"type":"Point"}
}