{
  "type": "Feature",
  "properties": {
    "iso:country":"US",
    "sg:address":"33 S Rossler Ave",
    "sg:city":"Buffalo",
    "sg:classifiers":[
        {
            "category":"Personal",
            "type":"Services"
        }
    ],
    "sg:phone":"+1 716 826 4646",
    "sg:postcode":"14206",
    "sg:province":"NY",
    "wof:name":"Curves For Woman",
    "wof:placetype":"venue"
},
  "geometry": {"coordinates":[-78.794871,42.873391],"type":"Point"}
}