{
  "type": "Feature",
  "properties": {
    "addr:full":"2 N Chemung St Waverly NY 14892",
    "addr:housenumber":"2",
    "addr:postcode":"14892",
    "addr:street":"N Chemung St",
    "iso:country":"US",
    "sg:address":"2 N Chemung St",
    "sg:city":"Waverly",
    "sg:classifiers":[
        {
            "category":"Restaurant",
            "type":"Food & Drink"
        }
    ],
    "sg:phone":"+1 607 565 8265",
    "sg:postcode":"14892",
    "sg:province":"NY",
    "wof:name":"Tank",
    "wof:placetype":"venue"
},
  "geometry": {"coordinates":[-76.528938,42.00971],"type":"Point"}
}