{
  "type": "Feature",
  "properties": {
    "addr:full":"65 Bryant Woods S Buffalo NY 14228",
    "addr:housenumber":"65",
    "addr:postcode":"14228",
    "addr:street":"Bryant Woods",
    "iso:country":"US",
    "sg:address":"65 Bryant Woods S",
    "sg:city":"Buffalo",
    "sg:classifiers":[
        {
            "category":"Insurance",
            "subcategory":"Insurance Agent",
            "type":"Services"
        }
    ],
    "sg:phone":"+1 716 625 8890",
    "sg:postcode":"14228",
    "sg:province":"NY",
    "wof:name":"Chrislauer",
    "wof:placetype":"venue"
},
  "geometry": {"coordinates":[-78.78716,43.020019],"type":"Point"}
}