{
  "type": "Feature",
  "properties": {
    "addr:full":"211 Burrs Ln Huntington Station NY 11746",
    "addr:housenumber":"211",
    "addr:postcode":"11746",
    "addr:street":"Burrs Ln Huntington",
    "iso:country":"US",
    "sg:address":"211 Burrs Ln",
    "sg:city":"Huntington Station",
    "sg:classifiers":[
        {
            "category":"Building & Trades",
            "subcategory":"Landscaping Services",
            "type":"Services"
        }
    ],
    "sg:phone":"+1 631 643 3418",
    "sg:postcode":"11746",
    "sg:province":"NY",
    "sg:tags":[
        "architect",
        "landscape"
    ],
    "wof:name":"Surban Water Gardens",
    "wof:placetype":"venue"
},
  "geometry": {"coordinates":[-73.355794,40.772074],"type":"Point"}
}