{
  "type": "Feature",
  "properties": {
    "addr:full":"30 Lincoln Center Plz New York NY 10023",
    "addr:housenumber":"30",
    "addr:postcode":"10023",
    "addr:street":"Lincoln Center Plz",
    "iso:country":"US",
    "sg:address":"30 Lincoln Center Plz",
    "sg:city":"New York",
    "sg:classifiers":[
        {
            "category":"Shopping",
            "subcategory":"Clothing, Apparel, & Fashions",
            "type":"Retail Goods"
        }
    ],
    "sg:phone":"+1   ",
    "sg:postcode":"10023",
    "sg:province":"NY",
    "sg:tags":[
        "baby"
    ],
    "wof:name":"Bonne Nuit Bebe",
    "wof:placetype":"venue"
},
  "geometry": {"coordinates":[-73.982032,40.771237],"type":"Point"}
}