{
  "type": "Feature",
  "properties": {
    "iso:country":"US",
    "sg:address":"4713 5th Ave",
    "sg:city":"Brooklyn",
    "sg:classifiers":[
        {
            "category":"Food & Beverages",
            "subcategory":"Meat & Fish",
            "type":"Retail Goods"
        }
    ],
    "sg:phone":"+1   ",
    "sg:postcode":"11220",
    "sg:province":"NY",
    "wof:name":"Gambino Angelo",
    "wof:placetype":"venue"
},
  "geometry": {"coordinates":[-74.00904,40.646248],"type":"Point"}
}