{
  "type": "Feature",
  "properties": {
    "iso:country":"US",
    "sg:address":"246 E 46th St",
    "sg:city":"New York",
    "sg:classifiers":[
        {
            "category":"Health Services",
            "subcategory":"Doctor",
            "type":"Services"
        }
    ],
    "sg:phone":"+1 212 697 2814",
    "sg:postcode":"10017",
    "sg:province":"NY",
    "sg:tags":[
        "dentist"
    ],
    "wof:name":"Dental Emergency",
    "wof:placetype":"venue"
},
  "geometry": {"coordinates":[-73.971176,40.752754],"type":"Point"}
}