{
  "type": "Feature",
  "properties": {
    "addr:full":"155 State St Manchester NY 14504",
    "addr:housenumber":"155",
    "addr:postcode":"14504",
    "addr:street":"State St",
    "iso:country":"US",
    "sg:address":"155 State St",
    "sg:city":"Manchester",
    "sg:classifiers":[
        {
            "category":"Manufacturing",
            "subcategory":"Glass & Minerals",
            "type":"Manufacturing & Wholesale Goods"
        }
    ],
    "sg:phone":"+1   ",
    "sg:postcode":"14504",
    "sg:province":"NY",
    "sg:tags":[
        "concrete",
        "product",
        "mfg"
    ],
    "wof:name":"Spancrete Northeast",
    "wof:placetype":"venue"
},
  "geometry": {"coordinates":[-77.244229,42.96727],"type":"Point"}
}