{
  "type": "Feature",
  "properties": {
    "iso:country":"US",
    "sg:address":"14 Berkshire Dr",
    "sg:city":"Albany",
    "sg:classifiers":[
        {
            "category":"Building & Trades",
            "subcategory":"Construction",
            "type":"Services"
        }
    ],
    "sg:phone":"+1 518 438 1319",
    "sg:postcode":"12205",
    "sg:province":"NY",
    "sg:tags":[
        "house",
        "contractor"
    ],
    "wof:name":"J A Drahushuk Remodeling",
    "wof:placetype":"venue"
},
  "geometry": {"coordinates":[-73.799831,42.708823],"type":"Point"}
}