{
  "type": "Feature",
  "properties": {
    "addr:full":"3285 Westchester Ave Bronx NY 10461",
    "addr:housenumber":"3285",
    "addr:postcode":"10461",
    "addr:street":"Westchester Ave",
    "iso:country":"US",
    "sg:address":"3285 Westchester Ave",
    "sg:city":"Bronx",
    "sg:classifiers":[
        {
            "category":"Retail",
            "subcategory":"Repair Shop",
            "type":"Services"
        }
    ],
    "sg:phone":"+1 718 685 5949",
    "sg:postcode":"10461",
    "sg:province":"NY",
    "sg:tags":[
        "lock",
        "locksmith"
    ],
    "wof:name":"A & A 24 7 Locksmith",
    "wof:placetype":"venue"
},
  "geometry": {"coordinates":[-73.827557,40.852788],"type":"Point"}
}