{
  "type": "Feature",
  "properties": {
    "addr:full":"914 Remsen Ave Brooklyn NY 11236",
    "addr:housenumber":"914",
    "addr:postcode":"11236",
    "addr:street":"Remsen Ave",
    "iso:country":"US",
    "sg:address":"914 Remsen Ave",
    "sg:city":"Brooklyn",
    "sg:classifiers":[
        {
            "category":"Autos & Motor Vehicles",
            "subcategory":"Fuel & Gas Station",
            "type":"Retail Goods"
        }
    ],
    "sg:phone":"+1 718 498 0724",
    "sg:postcode":"11236",
    "sg:province":"NY",
    "sg:tags":[
        "oil"
    ],
    "wof:name":"914 Re Svc Inc",
    "wof:placetype":"venue"
},
  "geometry": {"coordinates":[-73.912498,40.646],"type":"Point"}
}