{
  "type": "Feature",
  "properties": {
    "iso:country":"US",
    "sg:address":"182 Co Rd 21",
    "sg:city":"Hermon",
    "sg:classifiers":[
        {
            "category":"Farming",
            "subcategory":"Farm",
            "type":"Manufacturing & Wholesale Goods"
        }
    ],
    "sg:phone":"+1 315 562 3498",
    "sg:postcode":"13617",
    "sg:province":"NY",
    "sg:tags":[
        "crop",
        "general"
    ],
    "wof:name":"Gotham Family Farm LLC",
    "wof:placetype":"venue"
},
  "geometry": {"coordinates":[-75.225458,44.477382],"type":"Point"}
}