{
  "type": "Feature",
  "properties": {
    "addr:full":"2436 Rockville Center Pkwy Oceanside NY 11572",
    "addr:housenumber":"2436",
    "addr:postcode":"11572",
    "addr:street":"Rockville Center Pkwy",
    "iso:country":"US",
    "sg:address":"2436 Rockville Center Pkwy",
    "sg:city":"Oceanside",
    "sg:classifiers":[
        {
            "category":"Professional",
            "type":"Services"
        }
    ],
    "sg:phone":"+1 516 536 6794",
    "sg:postcode":"11572",
    "sg:province":"NY",
    "sg:tags":[
        "establishment"
    ],
    "wof:name":"J Frank & Sons Inc",
    "wof:placetype":"venue"
},
  "geometry": {"coordinates":[-73.62810899999999,40.651843],"type":"Point"}
}