{
  "type": "Feature",
  "properties": {
    "iso:country":"US",
    "sg:address":"22 Sherbrooke Rd",
    "sg:city":"Lindenhurst",
    "sg:classifiers":[
        {
            "category":"Shopping",
            "subcategory":"Hobbies, Toys, & Games",
            "type":"Retail Goods"
        }
    ],
    "sg:phone":"+1 631 664 3074",
    "sg:postcode":"11757",
    "sg:province":"NY",
    "sg:tags":[
        "games-wholesale",
        "video",
        "supplies-wholesale",
        "manufacturer"
    ],
    "wof:name":"Computer Bay",
    "wof:placetype":"venue"
},
  "geometry": {"coordinates":[-73.39417299999999,40.704903],"type":"Point"}
}