{
  "type": "Feature",
  "properties": {
    "addr:full":"542 E 82nd St New York NY 10028",
    "addr:housenumber":"542",
    "addr:postcode":"10028",
    "addr:street":"E 82Nd St",
    "iso:country":"US",
    "sg:address":"542 E 82nd St",
    "sg:city":"New York",
    "sg:classifiers":[
        {
            "category":"Health Services",
            "subcategory":"Doctor",
            "type":"Services"
        }
    ],
    "sg:phone":"+1 212 879 6642",
    "sg:postcode":"10028",
    "sg:province":"NY",
    "sg:tags":[
        "medical"
    ],
    "wof:name":"Bhamre Shrikant Dr",
    "wof:placetype":"venue"
},
  "geometry": {"coordinates":[-73.94707,40.772496],"type":"Point"}
}