{
  "type": "Feature",
  "properties": {
    "addr:full":"190 S 8th St Brooklyn NY 11211",
    "addr:housenumber":"190",
    "addr:postcode":"11211",
    "addr:street":"S 8Th St",
    "iso:country":"US",
    "sg:address":"190 S 8th St",
    "sg:city":"Brooklyn",
    "sg:classifiers":[
        {
            "category":"Building & Trades",
            "subcategory":"Construction",
            "type":"Services"
        }
    ],
    "sg:phone":"+1 718 388 6343",
    "sg:postcode":"11211",
    "sg:province":"NY",
    "sg:tags":[
        "marble",
        "contractor"
    ],
    "sg:website":"www.gregorymullerassoc.com",
    "wof:name":"Gregory Muller Assoc Inc",
    "wof:placetype":"venue"
},
  "geometry": {"coordinates":[-73.96155899999999,40.709204],"type":"Point"}
}