{
  "type": "Feature",
  "properties": {
    "addr:full":"313 W 4th Street New York NY 10014",
    "addr:housenumber":"313",
    "addr:postcode":"10014",
    "addr:street":"W 4Th Street",
    "iso:country":"US",
    "sg:address":"313 W 4th Street",
    "sg:city":"New York",
    "sg:classifiers":[
        {
            "category":"Arts & Performance",
            "subcategory":"Art Gallery",
            "type":"Entertainment"
        }
    ],
    "sg:phone":"+1 212 229 2757",
    "sg:postcode":"10014",
    "sg:province":"NY",
    "wof:name":"Tracy Williams Ltd",
    "wof:placetype":"venue"
},
  "geometry": {"coordinates":[-74.00396499999999,40.737333],"type":"Point"}
}