{
  "type": "Feature",
  "properties": {
    "iso:country":"US",
    "sg:address":"30 Meadowbrook Dr",
    "sg:city":"Albion",
    "sg:classifiers":[
        {
            "category":"Real Estate",
            "subcategory":"Real Estate Operator",
            "type":"Services"
        }
    ],
    "sg:phone":"+1 585 589 7281",
    "sg:postcode":"14411",
    "sg:province":"NY",
    "sg:tags":[
        "building",
        "apartment"
    ],
    "wof:name":"Gary Derwick Construction",
    "wof:placetype":"venue"
},
  "geometry": {"coordinates":[-78.188158,43.238618],"type":"Point"}
}