{
  "type": "Feature",
  "properties": {
    "iso:country":"US",
    "sg:address":"333 Washington Ave",
    "sg:city":"Cedarhurst",
    "sg:classifiers":[
        {
            "category":"Food & Beverages",
            "subcategory":"Groceries & Convenience Stores",
            "type":"Retail Goods"
        }
    ],
    "sg:phone":"+1   ",
    "sg:postcode":"11516",
    "sg:province":"NY",
    "wof:name":"Tamburinos Cedrhrst Ital Amer",
    "wof:placetype":"venue"
},
  "geometry": {"coordinates":[-73.730127,40.626094],"type":"Point"}
}