{
  "type": "Feature",
  "properties": {
    "iso:country":"US",
    "sg:address":"620 Erie Blvd W",
    "sg:city":"Syracuse",
    "sg:classifiers":[
        {
            "category":"Health Services",
            "subcategory":"Hospital",
            "type":"Services"
        }
    ],
    "sg:phone":"+1 315 425 8066",
    "sg:postcode":"13204",
    "sg:province":"NY",
    "sg:website":"www.goarmy.com",
    "wof:name":"Us Army Health Care",
    "wof:placetype":"venue"
},
  "geometry": {"coordinates":[-76.165707,43.048951],"type":"Point"}
}