{
  "type": "Feature",
  "properties": {
    "addr:full":"343 Lexington Ave New York NY 10016",
    "addr:housenumber":"343",
    "addr:postcode":"10016",
    "addr:street":"Lexington Ave",
    "iso:country":"US",
    "sg:address":"343 Lexington Ave",
    "sg:city":"New York",
    "sg:classifiers":[
        {
            "category":"Personal",
            "subcategory":"Nail Salon",
            "type":"Services"
        }
    ],
    "sg:phone":"+1 212 682 6844",
    "sg:postcode":"10016",
    "sg:province":"NY",
    "wof:name":"Sappho Spa Nail Corp",
    "wof:placetype":"venue"
},
  "geometry": {"coordinates":[-73.97708299999999,40.749735],"type":"Point"}
}