{
  "type": "Feature",
  "properties": {
    "iso:country":"US",
    "sg:address":"271 State Hwy 6n",
    "sg:city":"Mahopac",
    "sg:classifiers":[
        {
            "category":"Autos & Motor Vehicles",
            "subcategory":"Automobile Sales",
            "type":"Retail Goods"
        }
    ],
    "sg:phone":"+1 845 621 4123",
    "sg:postcode":"10541",
    "sg:province":"NY",
    "sg:tags":[
        "car",
        "dealer"
    ],
    "wof:name":"Frank & Sons Auto Inc",
    "wof:placetype":"venue"
},
  "geometry": {"coordinates":[-73.77631599999999,41.35411],"type":"Point"}
}