{
  "type": "Feature",
  "properties": {
    "addr:full":"9 South St Manorville NY 11949",
    "addr:housenumber":"9",
    "addr:postcode":"11949",
    "addr:street":"South St",
    "iso:country":"US",
    "sg:address":"9 South St",
    "sg:city":"Manorville",
    "sg:classifiers":[
        {
            "category":"Education",
            "subcategory":"School",
            "type":"Public Place"
        }
    ],
    "sg:phone":"+1 631 878 4900",
    "sg:postcode":"11949",
    "sg:province":"NY",
    "sg:tags":[
        "high",
        "middle",
        "elementary"
    ],
    "wof:name":"South Manor School Dist",
    "wof:placetype":"venue"
},
  "geometry": {"coordinates":[-72.79223,40.849737],"type":"Point"}
}