{
  "type": "Feature",
  "properties": {
    "addr:full":"35 Lawrence St Spring Valley NY 10977",
    "addr:housenumber":"35",
    "addr:postcode":"10977",
    "addr:street":"Lawrence St",
    "iso:country":"US",
    "sg:address":"35 Lawrence St",
    "sg:city":"Spring Valley",
    "sg:classifiers":[
        {
            "category":"Retail",
            "subcategory":"Car Wash",
            "type":"Services"
        }
    ],
    "sg:phone":"+1 845 426 2886",
    "sg:postcode":"10977",
    "sg:province":"NY",
    "sg:tags":[
        "polishing",
        "washing"
    ],
    "wof:name":"Pete's Econo Tint & Car Care",
    "wof:placetype":"venue"
},
  "geometry": {"coordinates":[-74.04474999999999,41.11257],"type":"Point"}
}