{
  "type": "Feature",
  "properties": {
    "iso:country":"US",
    "sg:address":"26 Argyle Dr",
    "sg:city":"Northport",
    "sg:classifiers":[
        {
            "category":"Building & Trades",
            "subcategory":"Landscaping Services",
            "type":"Services"
        }
    ],
    "sg:phone":"+1 631 261 5442",
    "sg:postcode":"11768",
    "sg:province":"NY",
    "sg:tags":[
        "designer",
        "landscape"
    ],
    "wof:name":"Clayton W Steen",
    "wof:placetype":"venue"
},
  "geometry": {"coordinates":[-73.402896,40.932512],"type":"Point"}
}