{
  "type": "Feature",
  "properties": {
    "iso:country":"US",
    "sg:address":"1799 Brentwood Rd",
    "sg:city":"Brentwood",
    "sg:classifiers":[
        {
            "category":"Health Services",
            "subcategory":"Chiropractor",
            "type":"Services"
        }
    ],
    "sg:phone":"+1 631 434 6685",
    "sg:postcode":"11717",
    "sg:province":"NY",
    "sg:tags":[
        "chiropractic"
    ],
    "wof:name":"Brent City Chiropractic Llp",
    "wof:placetype":"venue"
},
  "geometry": {"coordinates":[-73.24630000000001,40.778099],"type":"Point"}
}