{
  "type": "Feature",
  "properties": {
    "iso:country":"US",
    "sg:address":"824 Humboldt St",
    "sg:city":"Brooklyn",
    "sg:classifiers":[
        {
            "category":"Wholesale",
            "subcategory":"Chemicals & Plastics",
            "type":"Manufacturing & Wholesale Goods"
        }
    ],
    "sg:phone":"+1 718 349 6290",
    "sg:postcode":"11222",
    "sg:province":"NY",
    "sg:tags":[
        "adhesive",
        "glue"
    ],
    "wof:name":"Bedrock Supplies",
    "wof:placetype":"venue"
},
  "geometry": {"coordinates":[-73.946111,40.730015],"type":"Point"}
}