{
  "type": "Feature",
  "properties": {
    "iso:country":"US",
    "sg:address":"242 W 30th St",
    "sg:city":"New York",
    "sg:classifiers":[
        {
            "category":"Communications",
            "subcategory":"Newspaper",
            "type":"Services"
        }
    ],
    "sg:phone":"+1 212 268 8600",
    "sg:postcode":"10001",
    "sg:province":"NY",
    "sg:tags":[
        "print",
        "medium"
    ],
    "wof:name":"News Communications Newspapers",
    "wof:placetype":"venue"
},
  "geometry": {"coordinates":[-73.993599,40.7491],"type":"Point"}
}