{
  "type": "Feature",
  "properties": {
    "addr:full":"13911 Foch Blvd Jamaica NY 11436",
    "addr:housenumber":"13911",
    "addr:postcode":"11436",
    "addr:street":"Foch Blvd",
    "iso:country":"US",
    "sg:address":"13911 Foch Blvd",
    "sg:city":"Jamaica",
    "sg:classifiers":[
        {
            "category":"Structure",
            "subcategory":"Warehouse",
            "type":"Public Place"
        },
        {
            "category":"Retail",
            "subcategory":"Storage",
            "type":"Services"
        }
    ],
    "sg:phone":"+1 718 323 9229",
    "sg:postcode":"11436",
    "sg:province":"NY",
    "sg:tags":[
        "self",
        "warehouses-public-commercial"
    ],
    "wof:name":"Wiltech Inc",
    "wof:placetype":"venue"
},
  "geometry": {"coordinates":[-73.803162,40.677689],"type":"Point"}
}