{
  "type": "Feature",
  "properties": {
    "iso:country":"US",
    "sg:address":"649 Washington Ave",
    "sg:city":"Albany",
    "sg:classifiers":[
        {
            "category":"Retail",
            "subcategory":"Funeral Services",
            "type":"Services"
        }
    ],
    "sg:phone":"+1 518 438 1002",
    "sg:postcode":"12206",
    "sg:province":"NY",
    "sg:tags":[
        "director"
    ],
    "wof:name":"Levine Memorial Chapel Inc",
    "wof:placetype":"venue"
},
  "geometry": {"coordinates":[-73.780807,42.666737],"type":"Point"}
}