{
  "type": "Feature",
  "properties": {
    "iso:country":"US",
    "sg:address":"3111 Two Rod Rd",
    "sg:city":"East Aurora",
    "sg:classifiers":[
        {
            "category":"Farming",
            "subcategory":"Dairy Farm",
            "type":"Manufacturing & Wholesale Goods"
        }
    ],
    "sg:phone":"+1 716 655 0224",
    "sg:postcode":"14052",
    "sg:province":"NY",
    "wof:name":"Richard Janiga",
    "wof:placetype":"venue"
},
  "geometry": {"coordinates":[-78.554163,42.805905],"type":"Point"}
}