{
  "type": "Feature",
  "properties": {
    "iso:country":"US",
    "sg:address":"321 Gifford St",
    "sg:city":"Syracuse",
    "sg:classifiers":[
        {
            "category":"Food & Beverages",
            "subcategory":"Groceries & Convenience Stores",
            "type":"Retail Goods"
        }
    ],
    "sg:phone":"+1 315 475 1909",
    "sg:postcode":"13204",
    "sg:province":"NY",
    "sg:tags":[
        "grocer"
    ],
    "wof:name":"Nojaims Supermarket",
    "wof:placetype":"venue"
},
  "geometry": {"coordinates":[-76.16030000000001,43.043274],"type":"Point"}
}