{
  "type": "Feature",
  "properties": {
    "iso:country":"US",
    "sg:address":"2656 State Hwy 302",
    "sg:city":"Middletown",
    "sg:classifiers":[
        {
            "category":"Professional",
            "subcategory":"Engineering",
            "type":"Services"
        }
    ],
    "sg:phone":"+1 845 361 5421",
    "sg:postcode":"10941",
    "sg:province":"NY",
    "sg:tags":[
        "surveying",
        "engineer"
    ],
    "wof:name":"T M Depuy Engineering & Land",
    "wof:placetype":"venue"
},
  "geometry": {"coordinates":[-74.40909499999999,41.490558],"type":"Point"}
}