{
  "type": "Feature",
  "properties": {
    "iso:country":"US",
    "sg:address":"435 Cleveland Dr",
    "sg:city":"Buffalo",
    "sg:classifiers":[
        {
            "category":"Education",
            "subcategory":"Dance Studio",
            "type":"Public Place"
        }
    ],
    "sg:phone":"+1 716 832 3835",
    "sg:postcode":"14225",
    "sg:province":"NY",
    "sg:tags":[
        "art",
        "performing",
        "instruction",
        "dancing"
    ],
    "wof:name":"Ballet Arts of Buffalo",
    "wof:placetype":"venue"
},
  "geometry": {"coordinates":[-78.78330200000001,42.945],"type":"Point"}
}