{
  "type": "Feature",
  "properties": {
    "iso:country":"US",
    "sg:address":"6 Mohawk Dr",
    "sg:city":"Massapequa",
    "sg:classifiers":[
        {
            "category":"Building & Trades",
            "subcategory":"Construction",
            "type":"Services"
        }
    ],
    "sg:phone":"+1 516 579 2184",
    "sg:postcode":"11758",
    "sg:province":"NY",
    "sg:tags":[
        "carpentry",
        "contractor"
    ],
    "wof:name":"Vadco Contr Corp",
    "wof:placetype":"venue"
},
  "geometry": {"coordinates":[-73.480075,40.717113],"type":"Point"}
}