{
  "type": "Feature",
  "properties": {
    "addr:full":"2875 W 8th St Brooklyn NY 11224",
    "addr:housenumber":"2875",
    "addr:postcode":"11224",
    "addr:street":"W 8Th St",
    "iso:country":"US",
    "sg:address":"2875 W 8th St",
    "sg:city":"Brooklyn",
    "sg:classifiers":[
        {
            "category":"Retail",
            "subcategory":"Repair Shop",
            "type":"Services"
        }
    ],
    "sg:phone":"+1 718 301 7680",
    "sg:postcode":"11224",
    "sg:province":"NY",
    "sg:tags":[
        "lock",
        "locksmith"
    ],
    "wof:name":"24 Hour 7 Day Emerg Locksmith",
    "wof:placetype":"venue"
},
  "geometry": {"coordinates":[-73.97639700000001,40.577111],"type":"Point"}
}