{
  "type": "Feature",
  "properties": {
    "addr:full":"315 Exchange Ave Endicott NY 13760",
    "addr:housenumber":"315",
    "addr:postcode":"13760",
    "addr:street":"Exchange Ave",
    "iso:country":"US",
    "sg:address":"315 Exchange Ave",
    "sg:city":"Endicott",
    "sg:classifiers":[
        {
            "category":"Personal",
            "subcategory":"Beauty Salon",
            "type":"Services"
        }
    ],
    "sg:phone":"+1 607 785 5847",
    "sg:postcode":"13760",
    "sg:province":"NY",
    "sg:tags":[
        "shop"
    ],
    "wof:name":"Hair Mate The",
    "wof:placetype":"venue"
},
  "geometry": {"coordinates":[-76.065196,42.094096],"type":"Point"}
}