{
  "type": "Feature",
  "properties": {
    "addr:full":"32 Jamaica Ave Brooklyn NY 11207",
    "addr:housenumber":"32",
    "addr:postcode":"11207",
    "addr:street":"Jamaica Ave",
    "iso:country":"US",
    "sg:address":"32 Jamaica Ave",
    "sg:city":"Brooklyn",
    "sg:classifiers":[
        {
            "category":"Autos & Motor Vehicles",
            "subcategory":"Fuel & Gas Station",
            "type":"Retail Goods"
        }
    ],
    "sg:phone":"+1   ",
    "sg:postcode":"11207",
    "sg:province":"NY",
    "sg:tags":[
        "station",
        "gasoline"
    ],
    "wof:name":"Amoco",
    "wof:placetype":"venue"
},
  "geometry": {"coordinates":[-73.898832,40.677447],"type":"Point"}
}