{
  "type": "Feature",
  "properties": {
    "addr:full":"644 Mac Donough St Brooklyn NY 11233",
    "addr:housenumber":"644",
    "addr:postcode":"11233",
    "addr:street":"Mac Donough St",
    "iso:country":"US",
    "sg:address":"644 Mac Donough St",
    "sg:city":"Brooklyn",
    "sg:classifiers":[
        {
            "category":"Education",
            "subcategory":"School",
            "type":"Public Place"
        }
    ],
    "sg:phone":"+1 718 452 4567",
    "sg:postcode":"11233",
    "sg:province":"NY",
    "wof:name":"Clear Pool Children School",
    "wof:placetype":"venue"
},
  "geometry": {"coordinates":[-73.921882,40.683383],"type":"Point"}
}