{
  "type": "Feature",
  "properties": {
    "addr:full":"325 E 64 St New York NY 10065",
    "addr:housenumber":"325;64",
    "addr:postcode":"10065",
    "addr:street":"E;St",
    "iso:country":"US",
    "sg:address":"325 E 64 St",
    "sg:city":"New York",
    "sg:classifiers":[
        {
            "category":"Professional",
            "subcategory":"Lawyer & Legal Services",
            "type":"Services"
        }
    ],
    "sg:phone":"+1 212 517 6666",
    "sg:postcode":"10065",
    "sg:province":"NY",
    "sg:tags":[
        "attorney"
    ],
    "wof:name":"Lawrence Beckenstien",
    "wof:placetype":"venue"
},
  "geometry": {"coordinates":[-73.960098,40.763049],"type":"Point"}
}