{
  "type": "Feature",
  "properties": {
    "addr:full":"26 Dartmouth Dr Deer Park NY 11729",
    "addr:housenumber":"26",
    "addr:postcode":"11729",
    "addr:street":"Dartmouth Dr",
    "iso:country":"US",
    "sg:address":"26 Dartmouth Dr",
    "sg:city":"Deer Park",
    "sg:classifiers":[
        {
            "category":"Real Estate",
            "subcategory":"Real Estate Agent",
            "type":"Services"
        }
    ],
    "sg:phone":"+1 631 586 5053",
    "sg:postcode":"11729",
    "sg:province":"NY",
    "wof:name":"Jk & L Properties",
    "wof:placetype":"venue"
},
  "geometry": {"coordinates":[-73.34501400000001,40.769335],"type":"Point"}
}