{
  "type": "Feature",
  "properties": {
    "iso:country":"US",
    "sg:address":"49 W 37th St",
    "sg:city":"New York",
    "sg:classifiers":[
        {
            "category":"Arts & Performance",
            "subcategory":"Theater",
            "type":"Entertainment"
        }
    ],
    "sg:phone":"+1 212 206 8115",
    "sg:postcode":"10018",
    "sg:province":"NY",
    "sg:tags":[
        "bureau"
    ],
    "wof:name":"Axial Entertainment",
    "wof:placetype":"venue"
},
  "geometry": {"coordinates":[-73.98516499999999,40.7511],"type":"Point"}
}