{
  "type": "Feature",
  "properties": {
    "iso:country":"US",
    "sg:address":"2156 Sheridan Dr",
    "sg:city":"Buffalo",
    "sg:classifiers":[
        {
            "category":"Health Services",
            "subcategory":"Doctor",
            "type":"Services"
        }
    ],
    "sg:phone":"+1 716 873 7227",
    "sg:postcode":"14217",
    "sg:province":"NY",
    "sg:tags":[
        "physician",
        "medical",
        "surgeon"
    ],
    "wof:name":"James F Twist MD PC",
    "wof:placetype":"venue"
},
  "geometry": {"coordinates":[-78.858587,42.980883],"type":"Point"}
}