{
  "type": "Feature",
  "properties": {
    "addr:full":"323 Greenwich St New York NY 10013",
    "addr:housenumber":"323",
    "addr:postcode":"10013",
    "addr:street":"Greenwich St",
    "iso:country":"US",
    "sg:address":"323 Greenwich St",
    "sg:city":"New York",
    "sg:classifiers":[
        {
            "category":"Restaurant",
            "type":"Food & Drink"
        }
    ],
    "sg:phone":"+1 212 431 1112",
    "sg:postcode":"10013",
    "sg:province":"NY",
    "sg:tags":[
        "italian"
    ],
    "sg:website":"www.gigino-trattoria.com",
    "wof:name":"Gigino Restaurant",
    "wof:placetype":"venue"
},
  "geometry": {"coordinates":[-74.010597,40.717602],"type":"Point"}
}