{
  "type": "Feature",
  "properties": {
    "addr:full":"3023 3rd Ave Bronx NY 10455",
    "addr:housenumber":"3023",
    "addr:postcode":"10455",
    "addr:street":"3Rd Ave",
    "iso:country":"US",
    "sg:address":"3023 3rd Ave",
    "sg:city":"Bronx",
    "sg:classifiers":[
        {
            "category":"Shopping",
            "subcategory":"Hobbies, Toys, & Games",
            "type":"Retail Goods"
        }
    ],
    "sg:phone":"+1 718 904 7105",
    "sg:postcode":"10455",
    "sg:province":"NY",
    "sg:tags":[
        "shop",
        "hobby"
    ],
    "wof:name":"Collectibles By Armada",
    "wof:placetype":"venue"
},
  "geometry": {"coordinates":[-73.913623,40.819776],"type":"Point"}
}