{
  "type": "Feature",
  "properties": {
    "iso:country":"US",
    "sg:address":"172 Champlain Ave",
    "sg:city":"Ticonderoga",
    "sg:classifiers":[
        {
            "category":"Retail",
            "subcategory":"Animal Services",
            "type":"Services"
        }
    ],
    "sg:phone":"+1 518 585 2680",
    "sg:postcode":"12883",
    "sg:province":"NY",
    "sg:tags":[
        "pet",
        "grooming",
        "washing"
    ],
    "wof:name":"Puppy Patch Grooming",
    "wof:placetype":"venue"
},
  "geometry": {"coordinates":[-73.42317300000001,43.848015],"type":"Point"}
}