{
  "type": "Feature",
  "properties": {
    "addr:full":"1320 Jackson Ave Long Island City NY 11101",
    "addr:housenumber":"1320",
    "addr:postcode":"11101",
    "addr:street":"Jackson Ave",
    "iso:country":"US",
    "sg:address":"1320 Jackson Ave",
    "sg:city":"Long Island City",
    "sg:classifiers":[
        {
            "category":"Autos & Motor Vehicles",
            "subcategory":"Fuel & Gas Station",
            "type":"Retail Goods"
        }
    ],
    "sg:phone":"+1 718 729 3333",
    "sg:postcode":"11101",
    "sg:province":"NY",
    "wof:name":"T & A Auto Repair",
    "wof:placetype":"venue"
},
  "geometry": {"coordinates":[-73.949203,40.744202],"type":"Point"}
}