{
  "type": "Feature",
  "properties": {
    "iso:country":"US",
    "sg:address":"3549 Foster Rd",
    "sg:city":"Gowanda",
    "sg:classifiers":[
        {
            "category":"Education",
            "subcategory":"Special Training",
            "type":"Public Place"
        }
    ],
    "sg:phone":"+1 716 532 1888",
    "sg:postcode":"14070",
    "sg:province":"NY",
    "sg:tags":[
        "center"
    ],
    "wof:name":"Pennywise Learning",
    "wof:placetype":"venue"
},
  "geometry": {"coordinates":[-78.85246100000001,42.471359],"type":"Point"}
}