{
  "type": "Feature",
  "properties": {
    "addr:full":"142 Mineola Ave Ste 3C Roslyn Heights NY 11577",
    "addr:housenumber":"142",
    "addr:postcode":"11577",
    "addr:street":"Mineola Ave Ste 3C",
    "iso:country":"US",
    "sg:address":"142 Mineola Ave Ste 3C",
    "sg:city":"Roslyn Heights",
    "sg:classifiers":[
        {
            "category":"Professional",
            "subcategory":"Accounting & Tax Preparation",
            "type":"Services"
        }
    ],
    "sg:phone":"+1 516 484 4130",
    "sg:postcode":"11577",
    "sg:province":"NY",
    "sg:tags":[
        "accountant"
    ],
    "wof:name":"Bachman Steve",
    "wof:placetype":"venue"
},
  "geometry": {"coordinates":[-73.65010100000001,40.7873],"type":"Point"}
}