{
  "type": "Feature",
  "properties": {
    "addr:full":"480 Hamilton St Albany NY 12203",
    "addr:housenumber":"480",
    "addr:postcode":"12203",
    "addr:street":"Hamilton St",
    "iso:country":"US",
    "sg:address":"480 Hamilton St",
    "sg:city":"Albany",
    "sg:classifiers":[
        {
            "category":"Building & Trades",
            "subcategory":"Construction",
            "type":"Services"
        }
    ],
    "sg:phone":"+1 518 434 0185",
    "sg:postcode":"12203",
    "sg:province":"NY",
    "sg:tags":[
        "roofing",
        "work",
        "sheet",
        "metal"
    ],
    "wof:name":"Varden Bros Roofing Co Inc",
    "wof:placetype":"venue"
},
  "geometry": {"coordinates":[-73.780012,42.66037],"type":"Point"}
}