{
  "type": "Feature",
  "properties": {
    "addr:full":"284 Main St Eastchester NY 10709",
    "addr:housenumber":"284",
    "addr:postcode":"10709",
    "addr:street":"Main St",
    "iso:country":"US",
    "sg:address":"284 Main St",
    "sg:city":"Eastchester",
    "sg:classifiers":[
        {
            "category":"Autos & Motor Vehicles",
            "subcategory":"Fuel & Gas Station",
            "type":"Retail Goods"
        }
    ],
    "sg:phone":"+1 914 961 3895",
    "sg:postcode":"10709",
    "sg:province":"NY",
    "sg:tags":[
        "oil"
    ],
    "wof:name":"J & E Sunoco",
    "wof:placetype":"venue"
},
  "geometry": {"coordinates":[-73.81655000000001,40.952393],"type":"Point"}
}