{
  "type": "Feature",
  "properties": {
    "addr:full":"9 Christopher St New York NY 10014",
    "addr:housenumber":"9",
    "addr:postcode":"10014",
    "addr:street":"Christopher St",
    "iso:country":"US",
    "sg:address":"9 Christopher St",
    "sg:city":"New York",
    "sg:classifiers":[
        {
            "category":"Shopping",
            "subcategory":"Beauty & Cosmetics",
            "type":"Retail Goods"
        }
    ],
    "sg:phone":"+1 212 206 8674",
    "sg:postcode":"10014",
    "sg:province":"NY",
    "sg:tags":[
        "supply"
    ],
    "sg:website":"www.aedes.com",
    "wof:name":"Aedes De Venustas",
    "wof:placetype":"venue"
},
  "geometry": {"coordinates":[-74.000192,40.733987],"type":"Point"}
}