{
  "type": "Feature",
  "properties": {
    "iso:country":"US",
    "sg:address":"25 S Main St",
    "sg:city":"Spring Valley",
    "sg:classifiers":[
        {
            "category":"Health Services",
            "subcategory":"Doctor",
            "type":"Services"
        }
    ],
    "sg:phone":"+1 845 352 0297",
    "sg:postcode":"10977",
    "sg:province":"NY",
    "sg:tags":[
        "clinic"
    ],
    "wof:name":"Spring Valley Medical",
    "wof:placetype":"venue"
},
  "geometry": {"coordinates":[-74.04497499999999,41.111343],"type":"Point"}
}