{
  "type": "Feature",
  "properties": {
    "iso:country":"US",
    "sg:address":"1 Pinnacle Pl",
    "sg:city":"Albany",
    "sg:classifiers":[
        {
            "category":"Social Services",
            "type":"Services"
        },
        {
            "category":"Personal",
            "type":"Services"
        },
        {
            "category":"Health Services",
            "subcategory":"Health Practitioner",
            "type":"Services"
        }
    ],
    "sg:phone":"+1 518 225 6317",
    "sg:postcode":"12203",
    "sg:province":"NY",
    "sg:tags":[
        "family",
        "psychotherapist",
        "worker",
        "individual",
        "marriage",
        "child",
        "counseling",
        "counselor"
    ],
    "sg:website":"http://www.relationshiphealingandwellness.com",
    "wof:name":"Lorrie R Golden,LCSW",
    "wof:placetype":"venue"
},
  "geometry": {"coordinates":[-73.835854,42.677349],"type":"Point"}
}