{
  "type": "Feature",
  "properties": {
    "iso:country":"US",
    "sg:address":"67 Grand St",
    "sg:city":"Albany",
    "sg:classifiers":[
        {
            "category":"Food & Beverages",
            "subcategory":"Liquor & Beverages",
            "type":"Retail Goods"
        }
    ],
    "sg:phone":"+1 518 449 3840",
    "sg:postcode":"12202",
    "sg:province":"NY",
    "wof:name":"Diana Discount Wine & Liquor",
    "wof:placetype":"venue"
},
  "geometry": {"coordinates":[-73.7569,42.645662],"type":"Point"}
}