{
  "type": "Feature",
  "properties": {
    "addr:full":"2821 Elmwood Ave Rochester NY 14618",
    "addr:housenumber":"2821",
    "addr:postcode":"14618",
    "addr:street":"Elmwood Ave",
    "iso:country":"US",
    "sg:address":"2821 Elmwood Ave",
    "sg:city":"Rochester",
    "sg:classifiers":[
        {
            "category":"Professional",
            "subcategory":"Detective & Security Services",
            "type":"Services"
        }
    ],
    "sg:phone":"+1   ",
    "sg:postcode":"14618",
    "sg:province":"NY",
    "sg:tags":[
        "consultant"
    ],
    "wof:name":"Acallahan SEC Conslt Refferal",
    "wof:placetype":"venue"
},
  "geometry": {"coordinates":[-77.55990799999999,43.126539],"type":"Point"}
}