{
  "type": "Feature",
  "properties": {
    "addr:full":"300 E 71 St New York NY 10021",
    "addr:housenumber":"300;71",
    "addr:postcode":"10021",
    "addr:street":"E;St",
    "iso:country":"US",
    "sg:address":"300 E 71 St",
    "sg:city":"New York",
    "sg:classifiers":[
        {
            "category":"Professional",
            "subcategory":"Management & Consulting",
            "type":"Services"
        }
    ],
    "sg:phone":"+1 212 737 1295",
    "sg:postcode":"10021",
    "sg:province":"NY",
    "sg:tags":[
        "promotion",
        "sales"
    ],
    "wof:name":"Lloyd Duvall & Miller",
    "wof:placetype":"venue"
},
  "geometry": {"coordinates":[-73.95835599999999,40.767906],"type":"Point"}
}