{
  "type": "Feature",
  "properties": {
    "iso:country":"US",
    "sg:address":"933 Norrisville Rd",
    "sg:city":"Schuyler Falls",
    "sg:classifiers":[
        {
            "category":"Food & Beverages",
            "subcategory":"Groceries & Convenience Stores",
            "type":"Retail Goods"
        }
    ],
    "sg:phone":"+1 518 643 7134",
    "sg:postcode":"12985",
    "sg:province":"NY",
    "sg:tags":[
        "grocer"
    ],
    "wof:name":"M & M Country Store Inc",
    "wof:placetype":"venue"
},
  "geometry": {"coordinates":[-73.63867399999999,44.613055],"type":"Point"}
}