{
  "type": "Feature",
  "properties": {
    "addr:full":"21 Wallace Dr Plainview NY 11803",
    "addr:housenumber":"21",
    "addr:postcode":"11803",
    "addr:street":"Wallace Dr",
    "iso:country":"US",
    "sg:address":"21 Wallace Dr",
    "sg:city":"Plainview",
    "sg:classifiers":[
        {
            "category":"Professional",
            "type":"Services"
        }
    ],
    "sg:phone":"+1   ",
    "sg:postcode":"11803",
    "sg:province":"NY",
    "wof:name":"Megaforce",
    "wof:placetype":"venue"
},
  "geometry": {"coordinates":[-73.48454599999999,40.784],"type":"Point"}
}