{
  "type": "Feature",
  "properties": {
    "addr:full":"8385 Geneva St Interlaken NY 14847",
    "addr:housenumber":"8385",
    "addr:postcode":"14847",
    "addr:street":"Geneva St",
    "iso:country":"US",
    "sg:address":"8385 Geneva St",
    "sg:city":"Interlaken",
    "sg:classifiers":[
        {
            "category":"Autos & Motor Vehicles",
            "subcategory":"Automobile Sales",
            "type":"Retail Goods"
        }
    ],
    "sg:phone":"+1 607 532 8590",
    "sg:postcode":"14847",
    "sg:province":"NY",
    "sg:tags":[
        "car",
        "dealer"
    ],
    "wof:name":"V C Auto",
    "wof:placetype":"venue"
},
  "geometry": {"coordinates":[-76.720028,42.618848],"type":"Point"}
}