{
  "type": "Feature",
  "properties": {
    "addr:full":"3520 147th Street Flushing NY 11354",
    "addr:housenumber":"3520",
    "addr:postcode":"11354",
    "addr:street":"147Th Street",
    "iso:country":"US",
    "sg:address":"3520 147th Street",
    "sg:city":"Flushing",
    "sg:classifiers":[
        {
            "category":"Social Services",
            "subcategory":"Child Care",
            "type":"Services"
        }
    ],
    "sg:phone":"+1 718 961 5977",
    "sg:postcode":"11354",
    "sg:province":"NY",
    "sg:tags":[
        "day"
    ],
    "wof:name":"Salomon Academy Corporation",
    "wof:placetype":"venue"
},
  "geometry": {"coordinates":[-73.81956599999999,40.76559],"type":"Point"}
}