{
  "type": "Feature",
  "properties": {
    "addr:full":"295 Main St Buffalo NY 14203",
    "addr:housenumber":"295",
    "addr:postcode":"14203",
    "addr:street":"Main St",
    "iso:country":"US",
    "sg:address":"295 Main St",
    "sg:city":"Buffalo",
    "sg:classifiers":[
        {
            "category":"Professional",
            "subcategory":"Employment Agencies",
            "type":"Services"
        }
    ],
    "sg:phone":"+1 716 854 8282",
    "sg:postcode":"14203",
    "sg:province":"NY",
    "sg:tags":[
        "opportunity"
    ],
    "sg:website":"www.snelling.com",
    "wof:name":"Snelling Personnel Svc",
    "wof:placetype":"venue"
},
  "geometry": {"coordinates":[-78.87536799999999,42.882251],"type":"Point"}
}