{
  "type": "Feature",
  "properties": {
    "addr:full":"594 Broadway Ste 310 New York NY 10012",
    "addr:housenumber":"594;310",
    "addr:postcode":"10012",
    "addr:street":"Broadway Ste",
    "iso:country":"US",
    "sg:address":"594 Broadway Ste 310",
    "sg:city":"New York",
    "sg:classifiers":[
        {
            "category":"Health Services",
            "subcategory":"Doctor",
            "type":"Services"
        }
    ],
    "sg:phone":"+1 212 219 8858",
    "sg:postcode":"10012",
    "sg:province":"NY",
    "sg:tags":[
        "medicine",
        "internal"
    ],
    "wof:name":"Dr. Stuart Lewis, MD",
    "wof:placetype":"venue"
},
  "geometry": {"coordinates":[-73.997035,40.724945],"type":"Point"}
}