{
  "type": "Feature",
  "properties": {
    "iso:country":"US",
    "sg:address":"101 E Shore Rd",
    "sg:city":"Manhasset",
    "sg:classifiers":[
        {
            "category":"Retail",
            "subcategory":"Auto Repair",
            "type":"Services"
        }
    ],
    "sg:phone":"+1 516 869 3300",
    "sg:postcode":"11030",
    "sg:province":"NY",
    "sg:tags":[
        "body",
        "shop"
    ],
    "wof:name":"North Shore Auto & Detailing Inc",
    "wof:placetype":"venue"
},
  "geometry": {"coordinates":[-73.711899,40.793098],"type":"Point"}
}