{
  "type": "Feature",
  "properties": {
    "addr:full":"334 Grand Concourse Bronx NY 10451",
    "addr:housenumber":"334",
    "addr:postcode":"10451",
    "addr:street":"Grand Concourse",
    "iso:country":"US",
    "sg:address":"334 Grand Concourse",
    "sg:city":"Bronx",
    "sg:classifiers":[
        {
            "category":"Real Estate",
            "subcategory":"Real Estate Agent",
            "type":"Services"
        }
    ],
    "sg:phone":"+1 718 588 8500",
    "sg:postcode":"10451",
    "sg:province":"NY",
    "sg:tags":[
        "management"
    ],
    "wof:name":"Tax Credit Property Management",
    "wof:placetype":"venue"
},
  "geometry": {"coordinates":[-73.92927299999999,40.813697],"type":"Point"}
}