{
  "type": "Feature",
  "properties": {
    "iso:country":"US",
    "sg:address":"51 Parkside Ct",
    "sg:city":"Buffalo",
    "sg:classifiers":[
        {
            "category":"Organizations",
            "subcategory":"Professional Association",
            "type":"Services"
        }
    ],
    "sg:phone":"+1 716 823 9757",
    "sg:postcode":"14214",
    "sg:province":"NY",
    "sg:website":"www.cao.com",
    "wof:name":"CAO Headstart-St John",
    "wof:placetype":"venue"
},
  "geometry": {"coordinates":[-78.834659,42.950003],"type":"Point"}
}