{
  "type": "Feature",
  "properties": {
    "addr:full":"935 Park Ave New York NY 10028",
    "addr:housenumber":"935",
    "addr:postcode":"10028",
    "addr:street":"Park Ave",
    "iso:country":"US",
    "sg:address":"935 Park Ave",
    "sg:city":"New York",
    "sg:classifiers":[
        {
            "category":"Health Services",
            "subcategory":"Health Practitioner",
            "type":"Services"
        }
    ],
    "sg:phone":"+1 212 585 1886",
    "sg:postcode":"10028",
    "sg:province":"NY",
    "sg:tags":[
        "pathologist",
        "speech"
    ],
    "wof:name":"Beth Brenzel",
    "wof:placetype":"venue"
},
  "geometry": {"coordinates":[-73.959795,40.776366],"type":"Point"}
}