{
  "type": "Feature",
  "properties": {
    "iso:country":"US",
    "sg:address":"44 Lispenard Street",
    "sg:city":"New York",
    "sg:classifiers":[
        {
            "category":"Health Services",
            "subcategory":"Dentist",
            "type":"Services"
        }
    ],
    "sg:phone":"+1 212 473 4444",
    "sg:postcode":"10013",
    "sg:province":"NY",
    "wof:name":"Tribeca Smiles DMD PC",
    "wof:placetype":"venue"
},
  "geometry": {"coordinates":[-74.003367,40.719767],"type":"Point"}
}