{
  "type": "Feature",
  "properties": {
    "iso:country":"US",
    "sg:address":"90 Old Peruville Rd",
    "sg:city":"Groton",
    "sg:classifiers":[
        {
            "category":"Recreation",
            "type":"Entertainment"
        }
    ],
    "sg:phone":"+1 607 898 3808",
    "sg:postcode":"13073",
    "sg:province":"NY",
    "sg:tags":[
        "stable"
    ],
    "wof:name":"Patchwork Therapeutic Riding",
    "wof:placetype":"venue"
},
  "geometry": {"coordinates":[-76.370392,42.55088],"type":"Point"}
}