{
  "type": "Feature",
  "properties": {
    "addr:full":"1818 W 11th St Brooklyn NY 11223",
    "addr:housenumber":"1818",
    "addr:postcode":"11223",
    "addr:street":"W 11Th St",
    "iso:country":"US",
    "sg:address":"1818 W 11th St",
    "sg:city":"Brooklyn",
    "sg:classifiers":[
        {
            "category":"Manufacturing",
            "subcategory":"Printing",
            "type":"Manufacturing & Wholesale Goods"
        }
    ],
    "sg:phone":"+1   ",
    "sg:postcode":"11223",
    "sg:province":"NY",
    "sg:tags":[
        "commercial"
    ],
    "wof:name":"Cama Graphics",
    "wof:placetype":"venue"
},
  "geometry": {"coordinates":[-73.983228,40.60105],"type":"Point"}
}