{
  "type": "Feature",
  "properties": {
    "iso:country":"US",
    "sg:address":"34 S Main St",
    "sg:city":"Newark Valley",
    "sg:classifiers":[
        {
            "category":"Organizations",
            "subcategory":"Religious Organization",
            "type":"Services"
        }
    ],
    "sg:phone":"+1 607 642 5520",
    "sg:postcode":"13811",
    "sg:province":"NY",
    "sg:tags":[
        "church"
    ],
    "wof:name":"Congregational Study",
    "wof:placetype":"venue"
},
  "geometry": {"coordinates":[-76.185295,42.221922],"type":"Point"}
}