{
  "type": "Feature",
  "properties": {
    "addr:full":"899 Jerusalem Ave Uniondale NY 11553",
    "addr:housenumber":"899",
    "addr:postcode":"11553",
    "addr:street":"Jerusalem Ave",
    "iso:country":"US",
    "sg:address":"899 Jerusalem Ave",
    "sg:city":"Uniondale",
    "sg:classifiers":[
        {
            "category":"Government",
            "subcategory":"Fire Station",
            "type":"Public Place"
        }
    ],
    "sg:phone":"+1 516 572 1000",
    "sg:postcode":"11553",
    "sg:province":"NY",
    "sg:tags":[
        "protection"
    ],
    "wof:name":"Fire Commission",
    "wof:placetype":"venue"
},
  "geometry": {"coordinates":[-73.58113400000001,40.694954],"type":"Point"}
}