{
  "type": "Feature",
  "properties": {
    "addr:full":"69 7th Ave S New York NY 10014",
    "addr:housenumber":"69",
    "addr:postcode":"10014",
    "addr:street":"7Th Ave S",
    "iso:country":"US",
    "sg:address":"69 7th Ave S",
    "sg:city":"New York",
    "sg:classifiers":[
        {
            "category":"Restaurant",
            "type":"Food & Drink"
        }
    ],
    "sg:phone":"+1 212 924 4466",
    "sg:postcode":"10014",
    "sg:province":"NY",
    "sg:tags":[
        "pizza"
    ],
    "sg:website":"www.bleeckerstreetpizzeria.com",
    "wof:name":"Bleecker Street Pizza",
    "wof:placetype":"venue"
},
  "geometry": {"coordinates":[-74.00371699999999,40.731972],"type":"Point"}
}