{
  "type": "Feature",
  "properties": {
    "addr:full":"100 Airport Blvd Syracuse NY 13212",
    "addr:housenumber":"100",
    "addr:postcode":"13212",
    "addr:street":"Airport Blvd",
    "iso:country":"US",
    "sg:address":"100 Airport Blvd",
    "sg:city":"Syracuse",
    "sg:classifiers":[
        {
            "category":"Personal",
            "subcategory":"Barber",
            "type":"Services"
        }
    ],
    "sg:phone":"+1   ",
    "sg:postcode":"13212",
    "sg:province":"NY",
    "sg:tags":[
        "shop",
        "eating"
    ],
    "wof:name":"Airport Barber Shop",
    "wof:placetype":"venue"
},
  "geometry": {"coordinates":[-76.141125,43.118018],"type":"Point"}
}