{
  "type": "Feature",
  "properties": {
    "addr:full":"71 Parkway Rochester NY 14608",
    "addr:housenumber":"71",
    "addr:postcode":"14608",
    "addr:street":"Parkway",
    "iso:country":"US",
    "sg:address":"71 Parkway",
    "sg:city":"Rochester",
    "sg:classifiers":[
        {
            "category":"Social Services",
            "subcategory":"Child Care",
            "type":"Services"
        }
    ],
    "sg:phone":"+1 585 458 0910",
    "sg:postcode":"14608",
    "sg:province":"NY",
    "sg:tags":[
        "kindergarten",
        "academic",
        "school"
    ],
    "wof:name":"Head Start",
    "wof:placetype":"venue"
},
  "geometry": {"coordinates":[-77.632572,43.166739],"type":"Point"}
}