{
  "type": "Feature",
  "properties": {
    "addr:full":"40 Railroad Ave Glen Head NY 11545",
    "addr:housenumber":"40",
    "addr:postcode":"11545",
    "addr:street":"Railroad Ave Glen",
    "iso:country":"US",
    "sg:address":"40 Railroad Ave",
    "sg:city":"Glen Head",
    "sg:classifiers":[
        {
            "category":"Education",
            "subcategory":"School",
            "type":"Public Place"
        }
    ],
    "sg:phone":"+1 516 759 9337",
    "sg:postcode":"11545",
    "sg:province":"NY",
    "wof:name":"North Shore Schools Fed Emplys",
    "wof:placetype":"venue"
},
  "geometry": {"coordinates":[-73.62605600000001,40.833741],"type":"Point"}
}