{
  "type": "Feature",
  "properties": {
    "addr:full":"653 Old Country Rd Westbury NY 11590",
    "addr:housenumber":"653",
    "addr:postcode":"11590",
    "addr:street":"Old Country Rd",
    "iso:country":"US",
    "sg:address":"653 Old Country Rd",
    "sg:city":"Westbury",
    "sg:classifiers":[
        {
            "category":"Travel",
            "subcategory":"Travel Agent",
            "type":"Entertainment"
        }
    ],
    "sg:phone":"+1 516 333 4810",
    "sg:postcode":"11590",
    "sg:province":"NY",
    "sg:tags":[
        "agency",
        "bureau"
    ],
    "wof:name":"Travel The World",
    "wof:placetype":"venue"
},
  "geometry": {"coordinates":[-73.574366,40.750557],"type":"Point"}
}