{
  "type": "Feature",
  "properties": {
    "iso:country":"US",
    "sg:address":"9700 Main St",
    "sg:city":"Clarence",
    "sg:classifiers":[
        {
            "category":"Professional",
            "subcategory":"Business Services",
            "type":"Services"
        },
        {
            "category":"Professional",
            "subcategory":"Credit Reporting & Collection",
            "type":"Services"
        }
    ],
    "sg:phone":"+1 716 759 8184",
    "sg:postcode":"14031",
    "sg:province":"NY",
    "sg:tags":[
        "skip",
        "tracing"
    ],
    "wof:name":"Northstar Location Services",
    "wof:placetype":"venue"
},
  "geometry": {"coordinates":[-78.629451,42.973659],"type":"Point"}
}