{
  "type": "Feature",
  "properties": {
    "iso:country":"US",
    "sg:address":"2370 Coney Island Avenue",
    "sg:city":"Brooklyn",
    "sg:classifiers":[
        {
            "category":"Sports & Exercise",
            "subcategory":"Gym",
            "type":"Entertainment"
        }
    ],
    "sg:phone":"+1 718 336 6110",
    "sg:postcode":"11223",
    "sg:province":"NY",
    "wof:name":"Rapid Results Personal Training",
    "wof:placetype":"venue"
},
  "geometry": {"coordinates":[-73.961598,40.599128],"type":"Point"}
}