{
  "type": "Feature",
  "properties": {
    "addr:full":"3766 Broadway New York NY 10032",
    "addr:housenumber":"3766",
    "addr:postcode":"10032",
    "addr:street":"Broadway",
    "iso:country":"US",
    "sg:address":"3766 Broadway",
    "sg:city":"New York",
    "sg:classifiers":[
        {
            "category":"Personal",
            "subcategory":"Beauty Salon",
            "type":"Services"
        }
    ],
    "sg:phone":"+1 212 283 9272",
    "sg:postcode":"10032",
    "sg:province":"NY",
    "sg:tags":[
        "hair"
    ],
    "wof:name":"Riley Mavis Mrs Hairdrsr",
    "wof:placetype":"venue"
},
  "geometry": {"coordinates":[-73.94499999999999,40.8335],"type":"Point"}
}