{
  "type": "Feature",
  "properties": {
    "addr:full":"721 Columbus Ave New York NY 10025",
    "addr:housenumber":"721",
    "addr:postcode":"10025",
    "addr:street":"Columbus Ave",
    "iso:country":"US",
    "sg:address":"721 Columbus Ave",
    "sg:city":"New York",
    "sg:classifiers":[
        {
            "category":"Professional",
            "type":"Services"
        }
    ],
    "sg:phone":"+1 917 595 3219",
    "sg:postcode":"10025",
    "sg:province":"NY",
    "sg:tags":[
        "establishment"
    ],
    "wof:name":"Any All",
    "wof:placetype":"venue"
},
  "geometry": {"coordinates":[-73.9675,40.792745],"type":"Point"}
}