{
  "type": "Feature",
  "properties": {
    "iso:country":"US",
    "sg:address":"1000 Franklin Ave",
    "sg:city":"Garden City",
    "sg:classifiers":[
        {
            "category":"Professional",
            "subcategory":"Lawyer & Legal Services",
            "type":"Services"
        }
    ],
    "sg:phone":"+1 516 747 1141",
    "sg:postcode":"11530",
    "sg:province":"NY",
    "wof:name":"Jones Tunnicliffe Lwyr",
    "wof:placetype":"venue"
},
  "geometry": {"coordinates":[-73.63629899999999,40.731098],"type":"Point"}
}