{
  "type": "Feature",
  "properties": {
    "addr:full":"95 Maher Ln Harriman NY 10926",
    "addr:housenumber":"95",
    "addr:postcode":"10926",
    "addr:street":"Maher Ln",
    "iso:country":"US",
    "sg:address":"95 Maher Ln",
    "sg:city":"Harriman",
    "sg:classifiers":[
        {
            "category":"Bars & Pubs",
            "subcategory":"Sports Bar",
            "type":"Food & Drink"
        }
    ],
    "sg:phone":"+1 845 492 2167",
    "sg:postcode":"10926",
    "sg:province":"NY",
    "sg:tags":[
        "hall",
        "pool"
    ],
    "wof:name":"J & J Orange County Billiards",
    "wof:placetype":"venue"
},
  "geometry": {"coordinates":[-74.139099,41.313599],"type":"Point"}
}