{
  "type": "Feature",
  "properties": {
    "iso:country":"US",
    "sg:address":"109 Ann St",
    "sg:city":"Boonville",
    "sg:classifiers":[
        {
            "category":"Health Services",
            "subcategory":"Dentist",
            "type":"Services"
        }
    ],
    "sg:phone":"+1 315 942 4000",
    "sg:postcode":"13309",
    "sg:province":"NY",
    "wof:name":"Bruce Renders Dds Pc",
    "wof:placetype":"venue"
},
  "geometry": {"coordinates":[-75.33189,43.482676],"type":"Point"}
}