{
  "type": "Feature",
  "properties": {
    "addr:full":"45-16 Queens Blvd Sunnyside NY 11104",
    "addr:housenumber":"45-16",
    "addr:postcode":"11104",
    "addr:street":"Queens Blvd",
    "iso:country":"US",
    "sg:address":"45-16 Queens Blvd",
    "sg:city":"Sunnyside",
    "sg:classifiers":[
        {
            "category":"Restaurant",
            "type":"Food & Drink"
        },
        {
            "category":"Donuts",
            "subcategory":"None",
            "type":"Food & Drink"
        }
    ],
    "sg:postcode":"11104",
    "sg:province":"NY",
    "sg:tags":[
        "diner"
    ],
    "wof:name":"Alpha Donuts",
    "wof:placetype":"venue"
},
  "geometry": {"coordinates":[-73.91894499999999,40.742556],"type":"Point"}
}