{
  "type": "Feature",
  "properties": {
    "iso:country":"US",
    "sg:address":"45-16 Queens Blvd",
    "sg:city":"Sunnyside",
    "sg:classifiers":[
        {
            "category":"Restaurant",
            "type":"Food & Drink"
        },
        {
            "category":"Donuts",
            "subcategory":"None",
            "type":"Food & Drink"
        }
    ],
    "sg:postcode":"11104",
    "sg:province":"NY",
    "sg:tags":[
        "diner"
    ],
    "wof:name":"Alpha Donuts",
    "wof:placetype":"venue"
},
  "geometry": {"coordinates":[-73.919496,40.743108],"type":"Point"}
}