{
  "type": "Feature",
  "properties": {
    "addr:full":"25 Cedar St East Hampton NY 11937",
    "addr:housenumber":"25",
    "addr:postcode":"11937",
    "addr:street":"Cedar St",
    "iso:country":"US",
    "sg:address":"25 Cedar St",
    "sg:city":"East Hampton",
    "sg:classifiers":[
        {
            "category":"Home & Garden",
            "subcategory":"Furniture",
            "type":"Retail Goods"
        }
    ],
    "sg:phone":"+1 631 329 7122",
    "sg:postcode":"11937",
    "sg:province":"NY",
    "sg:tags":[
        "equipment",
        "kitchen",
        "cabinet"
    ],
    "wof:name":"Smith River Kitchens",
    "wof:placetype":"venue"
},
  "geometry": {"coordinates":[-72.184067,40.969891],"type":"Point"}
}