{
  "type": "Feature",
  "properties": {
    "iso:country":"US",
    "sg:address":"10 Elm St",
    "sg:city":"Cornwall",
    "sg:classifiers":[
        {
            "category":"Health Services",
            "subcategory":"Doctor",
            "type":"Services"
        }
    ],
    "sg:phone":"+1 845 534 7817",
    "sg:postcode":"12518",
    "sg:province":"NY",
    "sg:tags":[
        "physician",
        "surgeon"
    ],
    "wof:name":"David M Mendelson Md",
    "wof:placetype":"venue"
},
  "geometry": {"coordinates":[-74.04070400000001,41.434342],"type":"Point"}
}