{
  "type": "Feature",
  "properties": {
    "addr:full":"2 Lower Byrdcliffe Rd Woodstock NY 12498",
    "addr:housenumber":"2",
    "addr:postcode":"12498",
    "addr:street":"Lower Byrdcliffe Rd",
    "iso:country":"US",
    "sg:address":"2 Lower Byrdcliffe Rd",
    "sg:city":"Woodstock",
    "sg:classifiers":[
        {
            "category":"Travel",
            "subcategory":"Hotels & Motels",
            "type":"Entertainment"
        }
    ],
    "sg:phone":"+1   ",
    "sg:postcode":"12498",
    "sg:province":"NY",
    "sg:tags":[
        "operation",
        "merchandise"
    ],
    "wof:name":"Parnassus Square",
    "wof:placetype":"venue"
},
  "geometry": {"coordinates":[-74.119501,42.046515],"type":"Point"}
}