{
  "type": "Feature",
  "properties": {
    "iso:country":"US",
    "sg:address":"829A Carman Ave",
    "sg:city":"Westbury",
    "sg:classifiers":[
        {
            "category":"Arts & Performance",
            "subcategory":"Arts Center",
            "type":"Entertainment"
        },
        {
            "category":"Education",
            "subcategory":"School",
            "type":"Public Place"
        }
    ],
    "sg:phone":"+1 516 333 3480",
    "sg:postcode":"11590",
    "sg:province":"NY",
    "sg:tags":[
        "performing"
    ],
    "wof:name":"Westbury Academy of Dance",
    "wof:placetype":"venue"
},
  "geometry": {"coordinates":[-73.55229300000001,40.747062],"type":"Point"}
}