{
  "type": "Feature",
  "properties": {
    "addr:full":"90 Bryant Woods S Buffalo NY 14228",
    "addr:housenumber":"90",
    "addr:postcode":"14228",
    "addr:street":"Bryant Woods",
    "iso:country":"US",
    "sg:address":"90 Bryant Woods S",
    "sg:city":"Buffalo",
    "sg:classifiers":[
        {
            "category":"Insurance",
            "subcategory":"Insurance Agent",
            "type":"Services"
        }
    ],
    "sg:phone":"+1 716 835 2525",
    "sg:postcode":"14228",
    "sg:province":"NY",
    "wof:name":"Mulhern Heightzhaus Agency",
    "wof:placetype":"venue"
},
  "geometry": {"coordinates":[-78.786736,43.019359],"type":"Point"}
}