{
  "type": "Feature",
  "properties": {
    "iso:country":"US",
    "sg:address":"42333 State Hwy 12",
    "sg:city":"Alexandria Bay",
    "sg:classifiers":[
        {
            "category":"Social Services",
            "type":"Services"
        }
    ],
    "sg:phone":"+1 315 686 6094",
    "sg:postcode":"13624",
    "sg:province":"NY",
    "sg:tags":[
        "counselor",
        "marriage",
        "family"
    ],
    "wof:name":"Deborah Schryver Counseling",
    "wof:placetype":"venue"
},
  "geometry": {"coordinates":[-76.000254,44.272759],"type":"Point"}
}