{
  "type": "Feature",
  "properties": {
    "addr:full":"41 Nicole Way Mahopac NY 10541",
    "addr:housenumber":"41",
    "addr:postcode":"10541",
    "addr:street":"Nicole Way",
    "iso:country":"US",
    "sg:address":"41 Nicole Way",
    "sg:city":"Mahopac",
    "sg:classifiers":[
        {
            "category":"Insurance",
            "subcategory":"Hazard Insurance",
            "type":"Services"
        }
    ],
    "sg:phone":"+1 845 621 6543",
    "sg:postcode":"10541",
    "sg:province":"NY",
    "wof:name":"Robert A Simone Ins Brokers In",
    "wof:placetype":"venue"
},
  "geometry": {"coordinates":[-73.716311,41.396358],"type":"Point"}
}