{
  "type": "Feature",
  "properties": {
    "iso:country":"US",
    "sg:address":"30 Hilee Rd",
    "sg:city":"Rhinebeck",
    "sg:classifiers":[
        {
            "category":"Wholesale",
            "subcategory":"Wine & Distilled Alcoholic Beverages",
            "type":"Manufacturing & Wholesale Goods"
        }
    ],
    "sg:phone":"+1 845 876 0549",
    "sg:postcode":"12572",
    "sg:province":"NY",
    "wof:name":"Lauber Imports LTD",
    "wof:placetype":"venue"
},
  "geometry": {"coordinates":[-73.88158300000001,41.92799],"type":"Point"}
}