{
  "type": "Feature",
  "properties": {
    "addr:full":"3635 New Rd Ransomville NY 14131",
    "addr:housenumber":"3635",
    "addr:postcode":"14131",
    "addr:street":"New Rd",
    "iso:country":"US",
    "sg:address":"3635 New Rd",
    "sg:city":"Ransomville",
    "sg:classifiers":[
        {
            "category":"Home & Garden",
            "subcategory":"Mobile Homes",
            "type":"Retail Goods"
        }
    ],
    "sg:phone":"+1   ",
    "sg:postcode":"14131",
    "sg:province":"NY",
    "sg:tags":[
        "park"
    ],
    "wof:name":"Dorwood Mobile Home Park",
    "wof:placetype":"venue"
},
  "geometry": {"coordinates":[-78.82572999999999,43.242472],"type":"Point"}
}