{
  "type": "Feature",
  "properties": {
    "addr:full":"306 W 94th St New York NY 10025",
    "addr:housenumber":"306",
    "addr:postcode":"10025",
    "addr:street":"W 94Th St",
    "iso:country":"US",
    "sg:address":"306 W 94th St",
    "sg:city":"New York",
    "sg:classifiers":[
        {
            "category":"Building & Trades",
            "subcategory":"Construction",
            "type":"Services"
        }
    ],
    "sg:phone":"+1 212 961 9249",
    "sg:postcode":"10025",
    "sg:province":"NY",
    "sg:tags":[
        "contractor"
    ],
    "wof:name":"Empire Gen Construction",
    "wof:placetype":"venue"
},
  "geometry": {"coordinates":[-73.974356,40.793876],"type":"Point"}
}