{
  "type": "Feature",
  "properties": {
    "addr:full":"2563 Union Rd Ste 800 Cheektowaga NY 14227",
    "addr:housenumber":"2563",
    "addr:postcode":"14227",
    "addr:street":"Union Rd Ste 800",
    "iso:country":"US",
    "sg:address":"2563 Union Rd Ste 800",
    "sg:city":"Cheektowaga",
    "sg:classifiers":[
        {
            "category":"Education",
            "subcategory":"Special Training",
            "type":"Public Place"
        }
    ],
    "sg:phone":"+1 716 668 7622",
    "sg:postcode":"14227",
    "sg:province":"NY",
    "sg:tags":[
        "educational"
    ],
    "wof:name":"Horizon Health Services",
    "wof:placetype":"venue"
},
  "geometry": {"coordinates":[-78.75404,42.882346],"type":"Point"}
}