{
  "type": "Feature",
  "properties": {
    "addr:full":"154 Court St Watertown NY 13601",
    "addr:housenumber":"154",
    "addr:postcode":"13601",
    "addr:street":"Court St",
    "iso:country":"US",
    "sg:address":"154 Court St",
    "sg:city":"Watertown",
    "sg:classifiers":[
        {
            "category":"Shopping",
            "subcategory":"Musical Instruments",
            "type":"Retail Goods"
        }
    ],
    "sg:phone":"+1   ",
    "sg:postcode":"13601",
    "sg:province":"NY",
    "sg:website":"www.drguitarmusic.com",
    "wof:name":"Dr Guitar",
    "wof:placetype":"venue"
},
  "geometry": {"coordinates":[-75.911691,43.975534],"type":"Point"}
}