{
  "type": "Feature",
  "properties": {
    "addr:full":"101 W Kingsbridge Rd Bronx NY 10468",
    "addr:housenumber":"101",
    "addr:postcode":"10468",
    "addr:street":"W Kingsbridge Rd",
    "iso:country":"US",
    "sg:address":"101 W Kingsbridge Rd",
    "sg:city":"Bronx",
    "sg:classifiers":[
        {
            "category":"Retail",
            "subcategory":"Laundry & Dry Cleaning",
            "type":"Services"
        }
    ],
    "sg:phone":"+1 718 708 7553",
    "sg:postcode":"10468",
    "sg:province":"NY",
    "wof:name":"All Day Cleaners",
    "wof:placetype":"venue"
},
  "geometry": {"coordinates":[-73.9011891279,40.8684531347],"type":"Point"}
}