{
  "type": "Feature",
  "properties": {
    "addr:full":"37 135th St Richmond Hill NY 11418",
    "addr:housenumber":"37",
    "addr:postcode":"11418",
    "addr:street":"135Th St",
    "iso:country":"US",
    "sg:address":"37 135th St",
    "sg:city":"Richmond Hill",
    "sg:classifiers":[
        {
            "category":"Building & Trades",
            "subcategory":"Construction",
            "type":"Services"
        }
    ],
    "sg:phone":"+1 718 206 2478",
    "sg:postcode":"11418",
    "sg:province":"NY",
    "wof:name":"Cousins Development Inc",
    "wof:placetype":"venue"
},
  "geometry": {"coordinates":[-73.820166,40.705363],"type":"Point"}
}