{
  "type": "Feature",
  "properties": {
    "addr:full":"322 W 108th St New York NY 10025",
    "addr:housenumber":"322",
    "addr:postcode":"10025",
    "addr:street":"W 108Th St",
    "iso:country":"US",
    "sg:address":"322 W 108th St",
    "sg:city":"New York",
    "sg:classifiers":[
        {
            "category":"Professional",
            "subcategory":"Research",
            "type":"Services"
        }
    ],
    "sg:phone":"+1 212 749 0100",
    "sg:postcode":"10025",
    "sg:province":"NY",
    "sg:tags":[
        "foundation",
        "philanthropic"
    ],
    "wof:name":"Nour Foundation",
    "wof:placetype":"venue"
},
  "geometry": {"coordinates":[-73.968895,40.803355],"type":"Point"}
}