{
  "type": "Feature",
  "properties": {
    "addr:full":"50 Schmidt Rd Ghent NY 12075",
    "addr:housenumber":"50",
    "addr:postcode":"12075",
    "addr:street":"Schmidt Rd",
    "iso:country":"US",
    "sg:address":"50 Schmidt Rd",
    "sg:city":"Ghent",
    "sg:classifiers":[
        {
            "category":"Retail",
            "subcategory":"Laundry & Dry Cleaning",
            "type":"Services"
        }
    ],
    "sg:phone":"+1   ",
    "sg:postcode":"12075",
    "sg:province":"NY",
    "wof:name":"B & B Sewing & Alterations",
    "wof:placetype":"venue"
},
  "geometry": {"coordinates":[-73.65401300000001,42.317507],"type":"Point"}
}