{
  "type": "Feature",
  "properties": {
    "addr:full":"671 Morris Park Ave Bronx NY 10462",
    "addr:housenumber":"671",
    "addr:postcode":"10462",
    "addr:street":"Morris Park Ave",
    "iso:country":"US",
    "sg:address":"671 Morris Park Ave",
    "sg:city":"Bronx",
    "sg:classifiers":[
        {
            "category":"Building & Trades",
            "subcategory":"Plumbing",
            "type":"Services"
        }
    ],
    "sg:phone":"+1 718 543 6900",
    "sg:postcode":"10462",
    "sg:province":"NY",
    "sg:tags":[
        "repair",
        "temp",
        "installs",
        "heating",
        "contractor",
        "plumbing"
    ],
    "wof:name":"Howard Plumbing & Heating Inc",
    "wof:placetype":"venue"
},
  "geometry": {"coordinates":[-73.867524,40.844964],"type":"Point"}
}