{
  "type": "Feature",
  "properties": {
    "addr:full":"1001 Lehigh Station Rd Henrietta NY 14467",
    "addr:housenumber":"1001",
    "addr:postcode":"14467",
    "addr:street":"Lehigh Station Rd",
    "iso:country":"US",
    "sg:address":"1001 Lehigh Station Rd",
    "sg:city":"Henrietta",
    "sg:classifiers":[
        {
            "category":"Structure",
            "subcategory":"Office Building",
            "type":"Public Place"
        }
    ],
    "sg:phone":"+1 585 334 3867",
    "sg:postcode":"14467",
    "sg:province":"NY",
    "sg:tags":[
        "park"
    ],
    "wof:name":"H M Hansen Properties Inc",
    "wof:placetype":"venue"
},
  "geometry": {"coordinates":[-77.644386,43.058788],"type":"Point"}
}