{
  "type": "Feature",
  "properties": {
    "addr:full":"10915 Jamaica Ave Richmond Hill NY 11418",
    "addr:housenumber":"10915",
    "addr:postcode":"11418",
    "addr:street":"Jamaica Ave",
    "iso:country":"US",
    "sg:address":"10915 Jamaica Ave",
    "sg:city":"Richmond Hill",
    "sg:classifiers":[
        {
            "category":"Education",
            "subcategory":"Vocational School",
            "type":"Public Place"
        }
    ],
    "sg:phone":"+1 718 846 7241",
    "sg:postcode":"11418",
    "sg:province":"NY",
    "sg:tags":[
        "cosmetology"
    ],
    "wof:name":"Elida's Hair Salon",
    "wof:placetype":"venue"
},
  "geometry": {"coordinates":[-73.838624,40.696088],"type":"Point"}
}