{
  "type": "Feature",
  "properties": {
    "addr:full":"42 Jasper Dr Buffalo NY 14226",
    "addr:housenumber":"42",
    "addr:postcode":"14226",
    "addr:street":"Jasper Dr",
    "iso:country":"US",
    "sg:address":"42 Jasper Dr",
    "sg:city":"Buffalo",
    "sg:classifiers":[
        {
            "category":"Restaurant",
            "type":"Food & Drink"
        }
    ],
    "sg:phone":"+1   ",
    "sg:postcode":"14226",
    "sg:province":"NY",
    "sg:tags":[
        "eating"
    ],
    "wof:name":"For Petes Sake",
    "wof:placetype":"venue"
},
  "geometry": {"coordinates":[-78.80880500000001,42.950655],"type":"Point"}
}