{
  "type": "Feature",
  "properties": {
    "addr:full":"JFK Airport Terminal 2 Queens NY 11422",
    "addr:housenumber":"jfk;2",
    "addr:postcode":"11422",
    "iso:country":"US",
    "sg:address":"JFK Airport Terminal 2",
    "sg:city":"Queens",
    "sg:classifiers":[
        {
            "category":"Restaurant",
            "type":"Food & Drink"
        }
    ],
    "sg:postcode":"11422",
    "sg:province":"NY",
    "sg:tags":[
        "french"
    ],
    "wof:name":"Croque Madame",
    "wof:placetype":"venue"
},
  "geometry": {"coordinates":[-73.788901,40.641321],"type":"Point"}
}