{
  "type": "Feature",
  "properties": {
    "addr:full":"558 Broad St Salamanca NY 14779",
    "addr:housenumber":"558",
    "addr:postcode":"14779",
    "addr:street":"Broad St",
    "iso:country":"US",
    "sg:address":"558 Broad St",
    "sg:city":"Salamanca",
    "sg:classifiers":[
        {
            "category":"Shopping",
            "subcategory":"Tobacco",
            "type":"Retail Goods"
        }
    ],
    "sg:phone":"+1 716 945 2131",
    "sg:postcode":"14779",
    "sg:province":"NY",
    "sg:tags":[
        "cigarette",
        "cigar",
        "dealer"
    ],
    "wof:name":"Snakes Smokes",
    "wof:placetype":"venue"
},
  "geometry": {"coordinates":[-78.73615100000001,42.158375],"type":"Point"}
}