{
  "type": "Feature",
  "properties": {
    "addr:full":"267 E 10th St New York NY 10009",
    "addr:housenumber":"267",
    "addr:postcode":"10009",
    "addr:street":"E 10Th St",
    "iso:country":"US",
    "sg:address":"267 E 10th St",
    "sg:city":"New York",
    "sg:classifiers":[
        {
            "category":"Personal",
            "subcategory":"Beauty Salon",
            "type":"Services"
        }
    ],
    "sg:phone":"+1 212 477 0631",
    "sg:postcode":"10009",
    "sg:province":"NY",
    "sg:tags":[
        "hair"
    ],
    "sg:website":"www.whistlesalon.com/",
    "wof:name":"Whistle",
    "wof:placetype":"venue"
},
  "geometry": {"coordinates":[-73.983097,40.728455],"type":"Point"}
}