{
  "type": "Feature",
  "properties": {
    "addr:full":"250 46th St Brooklyn NY 11220",
    "addr:housenumber":"250",
    "addr:postcode":"11220",
    "addr:street":"46Th St",
    "iso:country":"US",
    "sg:address":"250 46th St",
    "sg:city":"Brooklyn",
    "sg:classifiers":[
        {
            "category":"Building & Trades",
            "subcategory":"Construction",
            "type":"Services"
        }
    ],
    "sg:phone":"+1 718 439 7163",
    "sg:postcode":"11220",
    "sg:province":"NY",
    "sg:tags":[
        "spray",
        "hanging",
        "painting",
        "finishing",
        "contractor"
    ],
    "wof:name":"Ray's Spray Shop",
    "wof:placetype":"venue"
},
  "geometry": {"coordinates":[-74.01323499999999,40.650595],"type":"Point"}
}