{
  "type": "Feature",
  "properties": {
    "iso:country":"US",
    "sg:address":"3623 Wilson Cambria Rd",
    "sg:city":"Wilson",
    "sg:classifiers":[
        {
            "category":"Shopping",
            "subcategory":"Hobbies, Toys, & Games",
            "type":"Retail Goods"
        }
    ],
    "sg:phone":"+1 716 751 9392",
    "sg:postcode":"14172",
    "sg:province":"NY",
    "wof:name":"Kenzel Toys",
    "wof:placetype":"venue"
},
  "geometry": {"coordinates":[-78.82559000000001,43.235387],"type":"Point"}
}