{
  "type": "Feature",
  "properties": {
    "addr:full":"25 Veldor Park Rochester NY 14612",
    "addr:housenumber":"25",
    "addr:postcode":"14612",
    "addr:street":"Veldor Park",
    "iso:country":"US",
    "sg:address":"25 Veldor Park",
    "sg:city":"Rochester",
    "sg:classifiers":[
        {
            "category":"Real Estate",
            "subcategory":"Real Estate Operator",
            "type":"Services"
        }
    ],
    "sg:phone":"+1 585 663 8196",
    "sg:postcode":"14612",
    "sg:province":"NY",
    "sg:tags":[
        "condominium"
    ],
    "wof:name":"Lakewood Shores Condominiums",
    "wof:placetype":"venue"
},
  "geometry": {"coordinates":[-77.62831799999999,43.262268],"type":"Point"}
}