{
  "type": "Feature",
  "properties": {
    "addr:full":"45 Harrison St New Rochelle NY 10801",
    "addr:housenumber":"45",
    "addr:postcode":"10801",
    "addr:street":"Harrison St",
    "iso:country":"US",
    "sg:address":"45 Harrison St",
    "sg:city":"New Rochelle",
    "sg:classifiers":[
        {
            "category":"Local Transit",
            "type":"Transportation"
        }
    ],
    "sg:phone":"+1 914 235 4656",
    "sg:postcode":"10801",
    "sg:province":"NY",
    "sg:tags":[
        "ambulance"
    ],
    "wof:name":"Transcare Ny",
    "wof:placetype":"venue"
},
  "geometry": {"coordinates":[-73.77948499999999,40.913055],"type":"Point"}
}