{
  "type": "Feature",
  "properties": {
    "addr:full":"149 Westchester Ave Port Chester NY 10573",
    "addr:housenumber":"149",
    "addr:postcode":"10573",
    "addr:street":"Westchester Ave",
    "iso:country":"US",
    "sg:address":"149 Westchester Ave",
    "sg:city":"Port Chester",
    "sg:classifiers":[
        {
            "category":"Restaurant",
            "type":"Food & Drink"
        }
    ],
    "sg:phone":"+1 914 935 0794",
    "sg:postcode":"10573",
    "sg:province":"NY",
    "wof:name":"Wendy's",
    "wof:placetype":"venue"
},
  "geometry": {"coordinates":[-73.665198,41.001051],"type":"Point"}
}