{
  "type": "Feature",
  "properties": {
    "addr:full":"65 Main St Yonkers NY 10701",
    "addr:housenumber":"65",
    "addr:postcode":"10701",
    "addr:street":"Main St",
    "iso:country":"US",
    "sg:address":"65 Main St",
    "sg:city":"Yonkers",
    "sg:classifiers":[
        {
            "category":"Home & Garden",
            "subcategory":"Building Materials",
            "type":"Retail Goods"
        }
    ],
    "sg:phone":"+1 914 963 9090",
    "sg:postcode":"10701",
    "sg:province":"NY",
    "wof:name":"Rubin Bros",
    "wof:placetype":"venue"
},
  "geometry": {"coordinates":[-73.900098,40.934546],"type":"Point"}
}