{
  "type": "Feature",
  "properties": {
    "iso:country":"US",
    "sg:address":"31 2nd St",
    "sg:city":"Troy",
    "sg:classifiers":[
        {
            "category":"Real Estate",
            "subcategory":"Real Estate Agent",
            "type":"Services"
        }
    ],
    "sg:phone":"+1 518 687 0661",
    "sg:postcode":"12180",
    "sg:province":"NY",
    "wof:name":"Baer Real Estate",
    "wof:placetype":"venue"
},
  "geometry": {"coordinates":[-73.691654,42.731139],"type":"Point"}
}