{
  "type": "Feature",
  "properties": {
    "iso:country":"US",
    "sg:address":"4549 Main St",
    "sg:city":"Amherst",
    "sg:classifiers":[
        {
            "category":"Professional",
            "subcategory":"Accounting & Tax Preparation",
            "type":"Services"
        }
    ],
    "sg:phone":"+1 716 839 9001",
    "sg:postcode":"14226",
    "sg:province":"NY",
    "sg:tags":[
        "accountant"
    ],
    "sg:website":"www.sjgoodmancpa.com",
    "wof:name":"Steven J Goodman CPA",
    "wof:placetype":"venue"
},
  "geometry": {"coordinates":[-78.781741,42.962655],"type":"Point"}
}