{
  "type": "Feature",
  "properties": {
    "addr:full":"7463 Buckley Rd North Syracuse NY 13212",
    "addr:housenumber":"7463",
    "addr:postcode":"13212",
    "addr:street":"Buckley Rd",
    "iso:country":"US",
    "sg:address":"7463 Buckley Rd",
    "sg:city":"North Syracuse",
    "sg:classifiers":[
        {
            "category":"Organizations",
            "subcategory":"Religious Organization",
            "type":"Services"
        }
    ],
    "sg:phone":"+1 315 458 0896",
    "sg:postcode":"13212",
    "sg:province":"NY",
    "sg:tags":[
        "church"
    ],
    "wof:name":"North Central Assembly of God",
    "wof:placetype":"venue"
},
  "geometry": {"coordinates":[-76.16549500000001,43.132777],"type":"Point"}
}