{
  "type": "Feature",
  "properties": {
    "addr:full":"615 Avenue L Brooklyn NY 11230",
    "addr:housenumber":"615",
    "addr:postcode":"11230",
    "addr:street":"Avenue L",
    "iso:country":"US",
    "sg:address":"615 Avenue L",
    "sg:city":"Brooklyn",
    "sg:classifiers":[
        {
            "category":"Health Services",
            "subcategory":"Doctor",
            "type":"Services"
        }
    ],
    "sg:phone":"+1 718 377 5164",
    "sg:postcode":"11230",
    "sg:province":"NY",
    "wof:name":"Cohen Saml MD PC",
    "wof:placetype":"venue"
},
  "geometry": {"coordinates":[-73.969121,40.619463],"type":"Point"}
}