{
  "type": "Feature",
  "properties": {
    "iso:country":"US",
    "sg:address":"567 Suffolk St",
    "sg:city":"Buffalo",
    "sg:classifiers":[
        {
            "category":"Retail",
            "subcategory":"Laundry & Dry Cleaning",
            "type":"Services"
        }
    ],
    "sg:phone":"+1 716 838 4764",
    "sg:postcode":"14215",
    "sg:province":"NY",
    "wof:name":"Suffolk Coin Operated Laundry",
    "wof:placetype":"venue"
},
  "geometry": {"coordinates":[-78.81035799999999,42.93831],"type":"Point"}
}