{
  "type": "Feature",
  "properties": {
    "addr:full":"3657 Kingsbridge Ave Bronx NY 10463",
    "addr:housenumber":"3657",
    "addr:postcode":"10463",
    "addr:street":"Kingsbridge Ave",
    "iso:country":"US",
    "sg:address":"3657 Kingsbridge Ave",
    "sg:city":"Bronx",
    "sg:classifiers":[
        {
            "category":"Restaurant",
            "type":"Food & Drink"
        }
    ],
    "sg:phone":"+1   ",
    "sg:postcode":"10463",
    "sg:province":"NY",
    "sg:tags":[
        "diner"
    ],
    "wof:name":"Riverdale Diner",
    "wof:placetype":"venue"
},
  "geometry": {"coordinates":[-73.901403,40.884854],"type":"Point"}
}