{
  "type": "Feature",
  "properties": {
    "iso:country":"US",
    "sg:address":"168 State Hwy 59",
    "sg:city":"Suffern",
    "sg:classifiers":[
        {
            "category":"Professional",
            "subcategory":"Management & Consulting",
            "type":"Services"
        }
    ],
    "sg:phone":"+1 845 369 6200",
    "sg:postcode":"10901",
    "sg:province":"NY",
    "sg:tags":[
        "consultant",
        "waste"
    ],
    "wof:name":"Automated Waste Svc Inc",
    "wof:placetype":"venue"
},
  "geometry": {"coordinates":[-74.144058,41.115054],"type":"Point"}
}