{
  "type": "Feature",
  "properties": {
    "addr:full":"265 Portage Rd Lewiston NY 14092",
    "addr:housenumber":"265",
    "addr:postcode":"14092",
    "addr:street":"Portage Rd",
    "iso:country":"US",
    "sg:address":"265 Portage Rd",
    "sg:city":"Lewiston",
    "sg:classifiers":[
        {
            "category":"Personal",
            "type":"Services"
        }
    ],
    "sg:phone":"+1   ",
    "sg:postcode":"14092",
    "sg:province":"NY",
    "sg:tags":[
        "sewing"
    ],
    "wof:name":"Accu-Stitch Enterprises Inc",
    "wof:placetype":"venue"
},
  "geometry": {"coordinates":[-79.032833,43.170325],"type":"Point"}
}