{
  "type": "Feature",
  "properties": {
    "iso:country":"US",
    "sg:address":"240 Smithtown Blvd",
    "sg:city":"Nesconset",
    "sg:classifiers":[
        {
            "category":"Restaurant",
            "type":"Food & Drink"
        }
    ],
    "sg:phone":"+1 631 265 4063",
    "sg:postcode":"11767",
    "sg:province":"NY",
    "sg:tags":[
        "delicatessen"
    ],
    "wof:name":"New York Gourmet Deli Inc",
    "wof:placetype":"venue"
},
  "geometry": {"coordinates":[-73.147741,40.83332],"type":"Point"}
}