{
  "type": "Feature",
  "properties": {
    "addr:full":"83 Riverside Dr New York NY 10024",
    "addr:housenumber":"83",
    "addr:postcode":"10024",
    "addr:street":"Riverside Dr",
    "iso:country":"US",
    "sg:address":"83 Riverside Dr",
    "sg:city":"New York",
    "sg:classifiers":[
        {
            "category":"Arts & Performance",
            "subcategory":"Theater",
            "type":"Entertainment"
        }
    ],
    "sg:phone":"+1 212 877 0400",
    "sg:postcode":"10024",
    "sg:province":"NY",
    "sg:tags":[
        "bureau"
    ],
    "wof:name":"Das Communications",
    "wof:placetype":"venue"
},
  "geometry": {"coordinates":[-73.98150699999999,40.785971],"type":"Point"}
}