{
  "type": "Feature",
  "properties": {
    "iso:country":"US",
    "sg:address":"1283 Arsenal St.",
    "sg:city":"Watertown",
    "sg:classifiers":[
        {
            "category":"Shopping",
            "subcategory":"Computers & Home Electronics",
            "type":"Retail Goods"
        },
        {
            "category":"Wholesale",
            "subcategory":"Office Equipment",
            "type":"Manufacturing & Wholesale Goods"
        },
        {
            "category":"Professional",
            "subcategory":"Printing & Photocopies",
            "type":"Services"
        },
        {
            "category":"Professional",
            "subcategory":"Computer Services",
            "type":"Services"
        },
        {
            "category":"Shopping",
            "subcategory":"Stationery & Office Supplies",
            "type":"Retail Goods"
        },
        {
            "category":"Wholesale",
            "subcategory":"Computers",
            "type":"Manufacturing & Wholesale Goods"
        }
    ],
    "sg:phone":"+1 315 782 2019",
    "sg:postcode":"13601",
    "sg:province":"NY",
    "sg:tags":[
        "printer",
        "register",
        "autographic",
        "duplicating",
        "hardware",
        "copying",
        "software",
        "furniture"
    ],
    "sg:website":"http://www.staples.com/",
    "wof:name":"Staples",
    "wof:placetype":"venue"
},
  "geometry": {"coordinates":[-75.94653,43.976072],"type":"Point"}
}