{
  "type": "Feature",
  "properties": {
    "iso:country":"US",
    "sg:address":"214 Merrick Rd",
    "sg:city":"Lynbrook",
    "sg:classifiers":[
        {
            "category":"Retail",
            "subcategory":"Auto Repair",
            "type":"Services"
        }
    ],
    "sg:phone":"+1 516 593 3636",
    "sg:postcode":"11563",
    "sg:province":"NY",
    "sg:tags":[
        "body",
        "automobile",
        "towing",
        "painting",
        "automotive"
    ],
    "sg:website":"www.merrickroadcollision.com",
    "wof:name":"Merrick Rd Collision Corp",
    "wof:placetype":"venue"
},
  "geometry": {"coordinates":[-73.66680100000001,40.658199],"type":"Point"}
}