{
  "type": "Feature",
  "properties": {
    "addr:full":"14 Brimsdown Cir Fairport NY 14450",
    "addr:housenumber":"14",
    "addr:postcode":"14450",
    "addr:street":"Brimsdown Cir",
    "iso:country":"US",
    "sg:address":"14 Brimsdown Cir",
    "sg:city":"Fairport",
    "sg:classifiers":[
        {
            "category":"Wholesale",
            "subcategory":"Electrical",
            "type":"Manufacturing & Wholesale Goods"
        }
    ],
    "sg:phone":"+1 585 223 2497",
    "sg:postcode":"14450",
    "sg:province":"NY",
    "sg:tags":[
        "transmission",
        "equipment",
        "power"
    ],
    "wof:name":"Fairport Products",
    "wof:placetype":"venue"
},
  "geometry": {"coordinates":[-77.422712,43.097868],"type":"Point"}
}