{
  "type": "Feature",
  "properties": {
    "iso:country":"US",
    "sg:address":"843 N Salina St",
    "sg:city":"Syracuse",
    "sg:classifiers":[
        {
            "category":"Professional",
            "subcategory":"Employment Agencies",
            "type":"Services"
        }
    ],
    "sg:phone":"+1 315 424 7823",
    "sg:postcode":"13208",
    "sg:province":"NY",
    "sg:tags":[
        "opportunity"
    ],
    "wof:name":"Chuck It",
    "wof:placetype":"venue"
},
  "geometry": {"coordinates":[-76.15482,43.062395],"type":"Point"}
}