{
  "type": "Feature",
  "properties": {
    "iso:country":"US",
    "sg:address":"86 Phelps St",
    "sg:city":"Lyons",
    "sg:classifiers":[
        {
            "category":"Building & Trades",
            "subcategory":"Construction",
            "type":"Services"
        }
    ],
    "sg:phone":"+1 315 946 3383",
    "sg:postcode":"14489",
    "sg:province":"NY",
    "sg:tags":[
        "painter"
    ],
    "wof:name":"Dobbins Painting & Contracting",
    "wof:placetype":"venue"
},
  "geometry": {"coordinates":[-76.98938699999999,43.070705],"type":"Point"}
}