{
  "type": "Feature",
  "properties": {
    "addr:full":"50 W 139th St New York NY 10037",
    "addr:housenumber":"50",
    "addr:postcode":"10037",
    "addr:street":"W 139Th St",
    "iso:country":"US",
    "sg:address":"50 W 139th St",
    "sg:city":"New York",
    "sg:classifiers":[
        {
            "category":"Shopping",
            "subcategory":"Discount & Variety Stores",
            "type":"Retail Goods"
        }
    ],
    "sg:phone":"+1 212 491 0311",
    "sg:postcode":"10037",
    "sg:province":"NY",
    "sg:tags":[
        "merchandise",
        "general"
    ],
    "wof:name":"Call Melanie Specializing",
    "wof:placetype":"venue"
},
  "geometry": {"coordinates":[-73.938974,40.816568],"type":"Point"}
}