{
  "type": "Feature",
  "properties": {
    "iso:country":"US",
    "sg:address":"10 Cottonwood Ct",
    "sg:city":"Nanuet",
    "sg:classifiers":[
        {
            "category":"Building & Trades",
            "subcategory":"Construction",
            "type":"Services"
        }
    ],
    "sg:phone":"+1 845 624 2251",
    "sg:postcode":"10954",
    "sg:province":"NY",
    "sg:tags":[
        "residential"
    ],
    "wof:name":"Rockland Residential Renovatio",
    "wof:placetype":"venue"
},
  "geometry": {"coordinates":[-73.99834199999999,41.114354],"type":"Point"}
}