{
  "type": "Feature",
  "properties": {
    "addr:full":"138 12th St Brooklyn NY 11215",
    "addr:housenumber":"138",
    "addr:postcode":"11215",
    "addr:street":"12Th St",
    "iso:country":"US",
    "sg:address":"138 12th St",
    "sg:city":"Brooklyn",
    "sg:classifiers":[
        {
            "category":"Food & Beverages",
            "subcategory":"Groceries & Convenience Stores",
            "type":"Retail Goods"
        }
    ],
    "sg:phone":"+1 718 499 4499",
    "sg:postcode":"11215",
    "sg:province":"NY",
    "sg:tags":[
        "product"
    ],
    "wof:name":"Prima Food LLC",
    "wof:placetype":"venue"
},
  "geometry": {"coordinates":[-73.99394100000001,40.67046],"type":"Point"}
}