{
  "type": "Feature",
  "properties": {
    "iso:country":"US",
    "sg:address":"5532 Rte 474",
    "sg:city":"Ashville",
    "sg:classifiers":[
        {
            "category":"Bars & Pubs",
            "type":"Food & Drink"
        }
    ],
    "sg:phone":"+1   ",
    "sg:postcode":"14710",
    "sg:province":"NY",
    "sg:tags":[
        "shop",
        "drinking",
        "beauty"
    ],
    "wof:name":"Jamie Halpainy",
    "wof:placetype":"venue"
},
  "geometry": {"coordinates":[-79.43457600000001,42.084376],"type":"Point"}
}