{
  "type": "Feature",
  "properties": {
    "iso:country":"US",
    "sg:address":"150 W 87 St",
    "sg:city":"New York",
    "sg:classifiers":[
        {
            "category":"Professional",
            "type":"Services"
        }
    ],
    "sg:phone":"+1   ",
    "sg:postcode":"10024",
    "sg:province":"NY",
    "wof:name":"Parizma Ltd",
    "wof:placetype":"venue"
},
  "geometry": {"coordinates":[-73.973461,40.787684],"type":"Point"}
}