{
  "type": "Feature",
  "properties": {
    "addr:full":"759 4th St Niagara Falls NY 14301",
    "addr:housenumber":"759",
    "addr:postcode":"14301",
    "addr:street":"4Th St",
    "iso:country":"US",
    "sg:address":"759 4th St",
    "sg:city":"Niagara Falls",
    "sg:classifiers":[
        {
            "category":"Local Transit",
            "type":"Transportation"
        }
    ],
    "sg:phone":"+1 716 284 7040",
    "sg:postcode":"14301",
    "sg:province":"NY",
    "sg:tags":[
        "limousine"
    ],
    "wof:name":"Magic Mist Limousine Svc",
    "wof:placetype":"venue"
},
  "geometry": {"coordinates":[-79.05828,43.095194],"type":"Point"}
}