{
  "type": "Feature",
  "properties": {
    "addr:full":"72 Hunt Ave Pearl River NY 10965",
    "addr:housenumber":"72",
    "addr:postcode":"10965",
    "addr:street":"Hunt Ave",
    "iso:country":"US",
    "sg:address":"72 Hunt Ave",
    "sg:city":"Pearl River",
    "sg:classifiers":[
        {
            "category":"Arts & Performance",
            "subcategory":"Theater",
            "type":"Entertainment"
        }
    ],
    "sg:phone":"+1 845 732 8186",
    "sg:postcode":"10965",
    "sg:province":"NY",
    "wof:name":"Hudson Vagabond Puppets",
    "wof:placetype":"venue"
},
  "geometry": {"coordinates":[-74.01328700000001,41.063238],"type":"Point"}
}