{
  "type": "Feature",
  "properties": {
    "addr:full":"37 Koeppel Ave Catskill NY 12414",
    "addr:housenumber":"37",
    "addr:postcode":"12414",
    "addr:street":"Koeppel Ave",
    "iso:country":"US",
    "sg:address":"37 Koeppel Ave",
    "sg:city":"Catskill",
    "sg:classifiers":[
        {
            "category":"Manufacturing",
            "subcategory":"Motor Vehicles & Parts",
            "type":"Manufacturing & Wholesale Goods"
        }
    ],
    "sg:phone":"+1   ",
    "sg:postcode":"12414",
    "sg:province":"NY",
    "sg:tags":[
        "body",
        "mfg"
    ],
    "wof:name":"Aggressive Connection",
    "wof:placetype":"venue"
},
  "geometry": {"coordinates":[-73.877414,42.210501],"type":"Point"}
}