{
  "type": "Feature",
  "properties": {
    "iso:country":"US",
    "sg:address":"3739 James St",
    "sg:city":"Buffalo",
    "sg:classifiers":[
        {
            "category":"Professional",
            "subcategory":"Advertising",
            "type":"Services"
        }
    ],
    "sg:phone":"+1   ",
    "sg:postcode":"14219",
    "sg:province":"NY",
    "wof:name":"Bergrand Records Inc",
    "wof:placetype":"venue"
},
  "geometry": {"coordinates":[-78.821479,42.783203],"type":"Point"}
}