{
  "type": "Feature",
  "properties": {
    "addr:full":"12 Huntley Rd Eastchester NY 10709",
    "addr:housenumber":"12",
    "addr:postcode":"10709",
    "addr:street":"Huntley Rd",
    "iso:country":"US",
    "sg:address":"12 Huntley Rd",
    "sg:city":"Eastchester",
    "sg:classifiers":[
        {
            "category":"Manufacturing",
            "subcategory":"Printing",
            "type":"Manufacturing & Wholesale Goods"
        }
    ],
    "sg:phone":"+1 914 337 0454",
    "sg:postcode":"10709",
    "sg:province":"NY",
    "sg:tags":[
        "publisher"
    ],
    "wof:name":"RTH Publishing Co",
    "wof:placetype":"venue"
},
  "geometry": {"coordinates":[-73.81247399999999,40.95503],"type":"Point"}
}