{
  "type": "Feature",
  "properties": {
    "iso:country":"US",
    "sg:address":"55 Price St",
    "sg:city":"Dobbs Ferry",
    "sg:classifiers":[
        {
            "category":"Organizations",
            "subcategory":"Religious Organization",
            "type":"Services"
        }
    ],
    "sg:phone":"+1 914 693 6361",
    "sg:postcode":"10522",
    "sg:province":"NY",
    "sg:tags":[
        "clergy"
    ],
    "wof:name":"Paul Riss",
    "wof:placetype":"venue"
},
  "geometry": {"coordinates":[-73.857069,41.009958],"type":"Point"}
}