{
  "type": "Feature",
  "properties": {
    "addr:full":"460 E 79th Street New York NY 10021",
    "addr:housenumber":"460",
    "addr:postcode":"10021",
    "addr:street":"E 79Th Street",
    "iso:country":"US",
    "sg:address":"460 E 79th Street",
    "sg:city":"New York",
    "sg:classifiers":[
        {
            "category":"Health Services",
            "subcategory":"Doctor",
            "type":"Services"
        }
    ],
    "sg:phone":"+1 212 535 7785",
    "sg:postcode":"10021",
    "sg:province":"NY",
    "wof:name":"Gahr Herbert MD",
    "wof:placetype":"venue"
},
  "geometry": {"coordinates":[-73.951442,40.771751],"type":"Point"}
}