{
  "type": "Feature",
  "properties": {
    "iso:country":"US",
    "sg:address":"211 Ross St",
    "sg:city":"Brooklyn",
    "sg:classifiers":[
        {
            "category":"Professional",
            "subcategory":"Lawyer & Legal Services",
            "type":"Services"
        }
    ],
    "sg:phone":"+1 718 782 1500",
    "sg:postcode":"11211",
    "sg:province":"NY",
    "wof:name":"Breuer David M Atty",
    "wof:placetype":"venue"
},
  "geometry": {"coordinates":[-73.959801,40.7062],"type":"Point"}
}