{
  "type": "Feature",
  "properties": {
    "iso:country":"US",
    "sg:address":"6702 14th Ave",
    "sg:city":"Brooklyn",
    "sg:classifiers":[
        {
            "category":"Personal",
            "subcategory":"Barber",
            "type":"Services"
        }
    ],
    "sg:phone":"+1 718 837 0982",
    "sg:postcode":"11219",
    "sg:province":"NY",
    "wof:name":"Joe's Place Haircutters",
    "wof:placetype":"venue"
},
  "geometry": {"coordinates":[-74.000801,40.623402],"type":"Point"}
}