{
  "type": "Feature",
  "properties": {
    "iso:country":"US",
    "sg:address":"1525 Lake Ave",
    "sg:city":"Rochester",
    "sg:classifiers":[
        {
            "category":"Food & Beverages",
            "subcategory":"Bakery",
            "type":"Retail Goods"
        }
    ],
    "sg:phone":"+1 585 254 6470",
    "sg:postcode":"14615",
    "sg:province":"NY",
    "sg:tags":[
        "doughnut"
    ],
    "sg:website":"www.timhortons.com",
    "wof:name":"Tim Hortons",
    "wof:placetype":"venue"
},
  "geometry": {"coordinates":[-77.628865,43.194573],"type":"Point"}
}