{
  "type": "Feature",
  "properties": {
    "iso:country":"US",
    "sg:address":"622 Route 109 Ste A",
    "sg:city":"Lindenhurst",
    "sg:classifiers":[
        {
            "category":"Food & Beverages",
            "subcategory":"Liquor & Beverages",
            "type":"Retail Goods"
        },
        {
            "category":"Wholesale",
            "subcategory":"Wine & Distilled Alcoholic Beverages",
            "type":"Manufacturing & Wholesale Goods"
        }
    ],
    "sg:phone":"+1 631 576 4679",
    "sg:postcode":"11757",
    "sg:province":"NY",
    "sg:tags":[
        "broker"
    ],
    "wof:name":"All Aboard Limousine, Ltd.",
    "wof:placetype":"venue"
},
  "geometry": {"coordinates":[-73.377724,40.713669],"type":"Point"}
}