{
  "type": "Feature",
  "properties": {
    "iso:country":"US",
    "sg:address":"403 W 51st St",
    "sg:city":"New York",
    "sg:classifiers":[
        {
            "category":"Wholesale",
            "subcategory":"Groceries",
            "type":"Manufacturing & Wholesale Goods"
        }
    ],
    "sg:phone":"+1 212 956 4608",
    "sg:postcode":"10019",
    "sg:province":"NY",
    "sg:tags":[
        "prod",
        "natural",
        "solution",
        "provider"
    ],
    "wof:name":"Mount Spring International",
    "wof:placetype":"venue"
},
  "geometry": {"coordinates":[-73.991253,40.765351],"type":"Point"}
}