{
  "type": "Feature",
  "properties": {
    "iso:country":"US",
    "sg:address":"4055 Merrick Rd",
    "sg:city":"Seaford",
    "sg:classifiers":[
        {
            "category":"Restaurant",
            "type":"Food & Drink"
        }
    ],
    "sg:menulink":"http://www.allmenus.com/ny/seaford/107252-soup-man/menu/",
    "sg:phone":"+1 516 826 4090",
    "sg:postcode":"11783",
    "sg:province":"NY",
    "sg:tags":[
        "soup",
        "american",
        "salad"
    ],
    "wof:name":"Soup Man",
    "wof:placetype":"venue"
},
  "geometry": {"coordinates":[-73.483358,40.666641],"type":"Point"}
}