{
  "type": "Feature",
  "properties": {
    "addr:full":"150 S Main St Gloversville NY 12078",
    "addr:housenumber":"150",
    "addr:postcode":"12078",
    "addr:street":"S Main St",
    "iso:country":"US",
    "sg:address":"150 S Main St",
    "sg:city":"Gloversville",
    "sg:classifiers":[
        {
            "category":"Retail",
            "subcategory":"Funeral Services",
            "type":"Services"
        }
    ],
    "sg:phone":"+1   ",
    "sg:postcode":"12078",
    "sg:province":"NY",
    "sg:tags":[
        "parlor"
    ],
    "wof:name":"Amico Funeral Home",
    "wof:placetype":"venue"
},
  "geometry": {"coordinates":[-74.348809,43.045969],"type":"Point"}
}