{
  "type": "Feature",
  "properties": {
    "addr:full":"1045 Brighton Beach Avenue Brooklyn NY 11235",
    "addr:housenumber":"1045",
    "addr:postcode":"11235",
    "addr:street":"Brighton Beach Avenue",
    "iso:country":"US",
    "sg:address":"1045 Brighton Beach Avenue",
    "sg:city":"Brooklyn",
    "sg:classifiers":[
        {
            "category":"Building & Trades",
            "subcategory":"Locksmith",
            "type":"Services"
        }
    ],
    "sg:phone":"+1 347 576 2618",
    "sg:postcode":"11235",
    "sg:province":"NY",
    "sg:tags":[
        "key"
    ],
    "wof:name":"1 Locksmith 24 Hrs",
    "wof:placetype":"venue"
},
  "geometry": {"coordinates":[-73.95799599999999,40.57838],"type":"Point"}
}