{
  "type": "Feature",
  "properties": {
    "addr:full":"10 Rte 25A East Setauket NY 11733",
    "addr:housenumber":"10",
    "addr:postcode":"11733",
    "addr:street":"Rte 25A East",
    "iso:country":"US",
    "sg:address":"10 Rte 25A",
    "sg:city":"East Setauket",
    "sg:classifiers":[
        {
            "category":"Banks & Credit Unions",
            "subcategory":"Bank",
            "type":"Services"
        }
    ],
    "sg:phone":"+1 631 751 7000",
    "sg:postcode":"11733",
    "sg:province":"NY",
    "sg:tags":[
        "savings",
        "institution"
    ],
    "wof:name":"Apple Bank",
    "wof:placetype":"venue"
},
  "geometry": {"coordinates":[-73.10607,40.941467],"type":"Point"}
}