{
  "type": "Feature",
  "properties": {
    "addr:full":"207 Madison St New York NY 10002",
    "addr:housenumber":"207",
    "addr:postcode":"10002",
    "addr:street":"Madison St",
    "iso:country":"US",
    "sg:address":"207 Madison St",
    "sg:city":"New York",
    "sg:classifiers":[
        {
            "category":"Restaurant",
            "type":"Food & Drink"
        }
    ],
    "sg:phone":"+1 212 227 2892",
    "sg:postcode":"10002",
    "sg:province":"NY",
    "wof:name":"Madison Restaurant Inc",
    "wof:placetype":"venue"
},
  "geometry": {"coordinates":[-73.989627,40.712741],"type":"Point"}
}