{
  "type": "Feature",
  "properties": {
    "iso:country":"US",
    "sg:address":"100 Independent Way Ste C",
    "sg:city":"Brewster",
    "sg:classifiers":[
        {
            "category":"Shopping",
            "subcategory":"Department Store",
            "type":"Retail Goods"
        }
    ],
    "sg:phone":"+1 845 940 1740",
    "sg:postcode":"10509",
    "sg:province":"NY",
    "sg:website":"www.marshallsonline.com",
    "wof:name":"Marshalls",
    "wof:placetype":"venue"
},
  "geometry": {"coordinates":[-73.629497,41.420353],"type":"Point"}
}