{
  "type": "Feature",
  "properties": {
    "addr:full":"321 E 60 St New York NY 10022",
    "addr:housenumber":"321;60",
    "addr:postcode":"10022",
    "addr:street":"E",
    "iso:country":"US",
    "sg:address":"321 E 60 St",
    "sg:city":"New York",
    "sg:classifiers":[
        {
            "category":"Retail",
            "subcategory":"Auto Repair",
            "type":"Services"
        }
    ],
    "sg:phone":"+1 212 838 0626",
    "sg:postcode":"10022",
    "sg:province":"NY",
    "sg:tags":[
        "towing"
    ],
    "wof:name":"A Aaaaaaaaaaaaa Towing",
    "wof:placetype":"venue"
},
  "geometry": {"coordinates":[-73.961522,40.760231],"type":"Point"}
}