{
  "type": "Feature",
  "properties": {
    "addr:full":"28 Contessa Ct Port Jefferson NY 11777",
    "addr:housenumber":"28",
    "addr:postcode":"11777",
    "addr:street":"Contessa Ct",
    "iso:country":"US",
    "sg:address":"28 Contessa Ct",
    "sg:city":"Port Jefferson",
    "sg:classifiers":[
        {
            "category":"Professional",
            "type":"Services"
        }
    ],
    "sg:phone":"+1   ",
    "sg:postcode":"11777",
    "sg:province":"NY",
    "wof:name":"Professional Grounds Inc",
    "wof:placetype":"venue"
},
  "geometry": {"coordinates":[-73.04468300000001,40.947916],"type":"Point"}
}