{
  "type": "Feature",
  "properties": {
    "iso:country":"US",
    "sg:address":"7448 E Main St",
    "sg:city":"Westmoreland",
    "sg:classifiers":[
        {
            "category":"Local Transit",
            "type":"Transportation"
        }
    ],
    "sg:phone":"+1   ",
    "sg:postcode":"13490",
    "sg:province":"NY",
    "sg:tags":[
        "passenger"
    ],
    "wof:name":"Carriage Limousine",
    "wof:placetype":"venue"
},
  "geometry": {"coordinates":[-75.40057899999999,43.117066],"type":"Point"}
}