{
  "type": "Feature",
  "properties": {
    "iso:country":"US",
    "sg:address":"9 Plumwood Ct",
    "sg:city":"East Amherst",
    "sg:classifiers":[
        {
            "category":"Shopping",
            "subcategory":"Bicycles & Sporting Goods",
            "type":"Retail Goods"
        }
    ],
    "sg:phone":"+1   ",
    "sg:postcode":"14051",
    "sg:province":"NY",
    "wof:name":"Zipline Golf LLC",
    "wof:placetype":"venue"
},
  "geometry": {"coordinates":[-78.720332,43.019376],"type":"Point"}
}