{
  "type": "Feature",
  "properties": {
    "addr:full":"121 Madison Ave New York NY 10016",
    "addr:housenumber":"121",
    "addr:postcode":"10016",
    "addr:street":"Madison Ave",
    "iso:country":"US",
    "sg:address":"121 Madison Ave",
    "sg:city":"New York",
    "sg:classifiers":[
        {
            "category":"Communications",
            "subcategory":"Film & Video Production",
            "type":"Services"
        }
    ],
    "sg:phone":"+1   ",
    "sg:postcode":"10016",
    "sg:province":"NY",
    "sg:tags":[
        "motion",
        "picture"
    ],
    "wof:name":"Tomboy Films Ltd",
    "wof:placetype":"venue"
},
  "geometry": {"coordinates":[-73.984335,40.745722],"type":"Point"}
}