{
  "type": "Feature",
  "properties": {
    "addr:full":"1322 Ave M Brooklyn NY 11230",
    "addr:postcode":"11230",
    "addr:street":"1322 Ave M",
    "iso:country":"US",
    "sg:address":"1322 Ave M",
    "sg:city":"Brooklyn",
    "sg:classifiers":[
        {
            "category":"Manufacturing",
            "subcategory":"Tools & Machinery",
            "type":"Manufacturing & Wholesale Goods"
        }
    ],
    "sg:phone":"+1   ",
    "sg:postcode":"11230",
    "sg:province":"NY",
    "sg:tags":[
        "residential",
        "lighting",
        "fixture",
        "mfg"
    ],
    "wof:name":"Chandaliers By Bibi",
    "wof:placetype":"venue"
},
  "geometry": {"coordinates":[-73.96111000000001,40.617809],"type":"Point"}
}