{
  "type": "Feature",
  "properties": {
    "iso:country":"US",
    "sg:address":"404 W 50th St",
    "sg:city":"New York",
    "sg:classifiers":[
        {
            "category":"Real Estate",
            "subcategory":"Real Estate Agent",
            "type":"Services"
        }
    ],
    "sg:phone":"+1 212 265 5790",
    "sg:postcode":"10019",
    "sg:province":"NY",
    "wof:name":"Macau Property Management",
    "wof:placetype":"venue"
},
  "geometry": {"coordinates":[-73.991737,40.764569],"type":"Point"}
}