{
  "type": "Feature",
  "properties": {
    "iso:country":"US",
    "sg:address":"11208 Rockaway Beach Blvd",
    "sg:city":"Far Rockaway",
    "sg:classifiers":[
        {
            "category":"Bars & Pubs",
            "type":"Food & Drink"
        }
    ],
    "sg:phone":"+1 718 474 9564",
    "sg:postcode":"11694",
    "sg:province":"NY",
    "wof:name":"Blackwater Inn",
    "wof:placetype":"venue"
},
  "geometry": {"coordinates":[-73.794676,40.59071],"type":"Point"}
}