{
  "type": "Feature",
  "properties": {
    "addr:full":"334 Route 32 Central Valley NY 10917",
    "addr:housenumber":"334",
    "addr:postcode":"10917",
    "addr:street":"Route 32 Central",
    "iso:country":"US",
    "sg:address":"334 Route 32",
    "sg:city":"Central Valley",
    "sg:classifiers":[
        {
            "category":"Shopping",
            "subcategory":"Pharmacy",
            "type":"Retail Goods"
        }
    ],
    "sg:phone":"+1 845 928 2002",
    "sg:postcode":"10917",
    "sg:province":"NY",
    "sg:tags":[
        "drugstore"
    ],
    "wof:name":"Woodbury Pharmacy",
    "wof:placetype":"venue"
},
  "geometry": {"coordinates":[-74.124071,41.334953],"type":"Point"}
}