{
  "type": "Feature",
  "properties": {
    "iso:country":"US",
    "sg:address":"575 Lexington Ave",
    "sg:city":"New York",
    "sg:classifiers":[
        {
            "category":"Communications",
            "subcategory":"Film & Video Production",
            "type":"Services"
        }
    ],
    "sg:phone":"+1 212 832 2565",
    "sg:postcode":"10022",
    "sg:province":"NY",
    "sg:tags":[
        "taping"
    ],
    "wof:name":"Alan Bernhard Creative Ents",
    "wof:placetype":"venue"
},
  "geometry": {"coordinates":[-73.971451,40.757749],"type":"Point"}
}