{
  "type": "Feature",
  "properties": {
    "addr:full":"1 Atlantic Ave Eastport NY 11946",
    "addr:housenumber":"1",
    "addr:postcode":"11946",
    "addr:street":"Atlantic Ave",
    "iso:country":"US",
    "sg:address":"1 Atlantic Ave",
    "sg:city":"Eastport",
    "sg:classifiers":[
        {
            "category":"Real Estate",
            "subcategory":"Real Estate Agent",
            "type":"Services"
        }
    ],
    "sg:phone":"+1 631 325 1616",
    "sg:postcode":"11946",
    "sg:province":"NY",
    "sg:website":"www.wcicommunities.com",
    "wof:name":"Encore Atlantic Shores",
    "wof:placetype":"venue"
},
  "geometry": {"coordinates":[-72.529325,40.871024],"type":"Point"}
}