{
  "type": "Feature",
  "properties": {
    "iso:country":"US",
    "sg:address":"17 Douglaston Pkwy",
    "sg:city":"Little Neck",
    "sg:classifiers":[
        {
            "category":"Restaurant",
            "type":"Food & Drink"
        }
    ],
    "sg:phone":"+1   ",
    "sg:postcode":"11363",
    "sg:province":"NY",
    "sg:tags":[
        "eating"
    ],
    "wof:name":"Napoli Pizza & Restrnt II",
    "wof:placetype":"venue"
},
  "geometry": {"coordinates":[-73.749655,40.769947],"type":"Point"}
}