{
  "type": "Feature",
  "properties": {
    "iso:country":"US",
    "sg:address":"55 Broadway",
    "sg:city":"Amityville",
    "sg:classifiers":[
        {
            "category":"Professional",
            "subcategory":"Accounting & Tax Preparation",
            "type":"Services"
        }
    ],
    "sg:phone":"+1   ",
    "sg:postcode":"11701",
    "sg:province":"NY",
    "wof:name":"David Van Nostrand CPA",
    "wof:placetype":"venue"
},
  "geometry": {"coordinates":[-73.416147,40.673657],"type":"Point"}
}