{
  "type": "Feature",
  "properties": {
    "addr:full":"471 Myrtle Ave Brooklyn NY 11205",
    "addr:housenumber":"471",
    "addr:postcode":"11205",
    "addr:street":"Myrtle Ave",
    "iso:country":"US",
    "sg:address":"471 Myrtle Ave",
    "sg:city":"Brooklyn",
    "sg:classifiers":[
        {
            "category":"Wholesale",
            "subcategory":"Hardware",
            "type":"Manufacturing & Wholesale Goods"
        }
    ],
    "sg:phone":"+1 718 230 4618",
    "sg:postcode":"11205",
    "sg:province":"NY",
    "sg:tags":[
        "picture",
        "hanger"
    ],
    "wof:name":"Whispers One Hour Photo",
    "wof:placetype":"venue"
},
  "geometry": {"coordinates":[-73.96624300000001,40.693467],"type":"Point"}
}