{
  "type": "Feature",
  "properties": {
    "addr:full":"210 Roebling St Brooklyn NY 11211",
    "addr:housenumber":"210",
    "addr:postcode":"11211",
    "addr:street":"Roebling St",
    "iso:country":"US",
    "sg:address":"210 Roebling St",
    "sg:city":"Brooklyn",
    "sg:classifiers":[
        {
            "category":"Building & Trades",
            "subcategory":"Construction",
            "type":"Services"
        }
    ],
    "sg:phone":"+1 718 486 5372",
    "sg:postcode":"11211",
    "sg:province":"NY",
    "sg:tags":[
        "carpentry",
        "contractor"
    ],
    "wof:name":"Almighty Builders Corp",
    "wof:placetype":"venue"
},
  "geometry": {"coordinates":[-73.958896,40.712688],"type":"Point"}
}