{
  "type": "Feature",
  "properties": {
    "iso:country":"US",
    "sg:address":"40 Wall St",
    "sg:city":"New York",
    "sg:classifiers":[
        {
            "category":"Marine",
            "type":"Transportation"
        }
    ],
    "sg:phone":"+1   ",
    "sg:postcode":"10005",
    "sg:province":"NY",
    "sg:tags":[
        "ship",
        "scrapping"
    ],
    "wof:name":"Post- Svc Rmdtion Partners LLC",
    "wof:placetype":"venue"
},
  "geometry": {"coordinates":[-74.010122,40.70699],"type":"Point"}
}