{
  "type": "Feature",
  "properties": {
    "iso:country":"US",
    "sg:address":"534 Willow Ave",
    "sg:city":"Cedarhurst",
    "sg:classifiers":[
        {
            "category":"Real Estate",
            "subcategory":"Real Estate Agent",
            "type":"Services"
        }
    ],
    "sg:phone":"+1 516 265 6800",
    "sg:postcode":"11516",
    "sg:province":"NY",
    "wof:name":"Richard Brock Real Estate",
    "wof:placetype":"venue"
},
  "geometry": {"coordinates":[-73.722692,40.623462],"type":"Point"}
}