{
  "type": "Feature",
  "properties": {
    "iso:country":"US",
    "sg:address":"450 Sunrise Hwy",
    "sg:city":"Rockville Centre",
    "sg:classifiers":[
        {
            "category":"Professional",
            "subcategory":"Management & Consulting",
            "type":"Services"
        }
    ],
    "sg:phone":"+1 516 678 3870",
    "sg:postcode":"11570",
    "sg:province":"NY",
    "sg:tags":[
        "consultant",
        "security",
        "system"
    ],
    "wof:name":"O'Grady Noone Kerning & Assoc",
    "wof:placetype":"venue"
},
  "geometry": {"coordinates":[-73.64067900000001,40.656965],"type":"Point"}
}