{
  "type": "Feature",
  "properties": {
    "iso:country":"US",
    "sg:address":"335 Woodhull Ave",
    "sg:city":"Port Jefferson Station",
    "sg:classifiers":[
        {
            "category":"Building & Trades",
            "subcategory":"Landscaping Services",
            "type":"Services"
        }
    ],
    "sg:phone":"+1 631 331 0908",
    "sg:postcode":"11776",
    "sg:province":"NY",
    "sg:tags":[
        "landscape",
        "contractor"
    ],
    "wof:name":"Peace of Mind Ldscp & Design",
    "wof:placetype":"venue"
},
  "geometry": {"coordinates":[-73.05881599999999,40.917552],"type":"Point"}
}