{
  "type": "Feature",
  "properties": {
    "addr:full":"4 Beverly Rd Great Neck NY 11021",
    "addr:housenumber":"4",
    "addr:postcode":"11021",
    "addr:street":"Beverly Rd",
    "iso:country":"US",
    "sg:address":"4 Beverly Rd",
    "sg:city":"Great Neck",
    "sg:classifiers":[
        {
            "category":"Banks & Credit Unions",
            "subcategory":"Investment Brokerage",
            "type":"Services"
        }
    ],
    "sg:phone":"+1 516 466 3374",
    "sg:postcode":"11021",
    "sg:province":"NY",
    "sg:tags":[
        "security"
    ],
    "wof:name":"Rindmart Publications",
    "wof:placetype":"venue"
},
  "geometry": {"coordinates":[-73.72830399999999,40.791899],"type":"Point"}
}