{
  "type": "Feature",
  "properties": {
    "addr:full":"10 School St Glens Falls NY 12801",
    "addr:housenumber":"10",
    "addr:postcode":"12801",
    "addr:street":"School St",
    "iso:country":"US",
    "sg:address":"10 School St",
    "sg:city":"Glens Falls",
    "sg:classifiers":[
        {
            "category":"Local Transit",
            "type":"Transportation"
        }
    ],
    "sg:phone":"+1 518 623 4527",
    "sg:postcode":"12801",
    "sg:province":"NY",
    "sg:tags":[
        "airport"
    ],
    "sg:website":"www.hollywoodlimousines.net",
    "wof:name":"Hollywood Limousine",
    "wof:placetype":"venue"
},
  "geometry": {"coordinates":[-73.646772,43.308123],"type":"Point"}
}