{
  "type": "Feature",
  "properties": {
    "addr:full":"2235 Empire Blvd Webster NY 14580",
    "addr:housenumber":"2235",
    "addr:postcode":"14580",
    "addr:street":"Empire Blvd",
    "iso:country":"US",
    "sg:address":"2235 Empire Blvd",
    "sg:city":"Webster",
    "sg:classifiers":[
        {
            "category":"Bars & Pubs",
            "type":"Food & Drink"
        }
    ],
    "sg:phone":"+1 585 671 5359",
    "sg:postcode":"14580",
    "sg:province":"NY",
    "wof:name":"Millennium",
    "wof:placetype":"venue"
},
  "geometry": {"coordinates":[-77.493667,43.203655],"type":"Point"}
}