{
  "type": "Feature",
  "properties": {
    "addr:full":"105 Stevens Ave Mt Vernon NY 10550",
    "addr:housenumber":"105",
    "addr:postcode":"10550",
    "addr:street":"Stevens Ave",
    "iso:country":"US",
    "sg:address":"105 Stevens Ave",
    "sg:city":"Mt Vernon",
    "sg:classifiers":[
        {
            "category":"Health Services",
            "subcategory":"Doctor",
            "type":"Services"
        }
    ],
    "sg:phone":"+1 914 668 1212",
    "sg:postcode":"10550",
    "sg:province":"NY",
    "sg:tags":[
        "physician",
        "surgeon"
    ],
    "wof:name":"Silburn Thomas MD",
    "wof:placetype":"venue"
},
  "geometry": {"coordinates":[-73.840712,40.911184],"type":"Point"}
}