{
  "type": "Feature",
  "properties": {
    "addr:full":"315 N Forest Rd Buffalo NY 14221",
    "addr:housenumber":"315",
    "addr:postcode":"14221",
    "addr:street":"N Forest Rd",
    "iso:country":"US",
    "sg:address":"315 N Forest Rd",
    "sg:city":"Buffalo",
    "sg:classifiers":[
        {
            "category":"Professional",
            "subcategory":"Business Services",
            "type":"Services"
        }
    ],
    "sg:phone":"+1 716 332 6158",
    "sg:postcode":"14221",
    "sg:province":"NY",
    "sg:tags":[
        "consultant",
        "coach",
        "broker"
    ],
    "sg:website":"http://www.sunbeltnetwork.com",
    "wof:name":"Sunbelt Business Brokers",
    "wof:placetype":"venue"
},
  "geometry": {"coordinates":[-78.75968899999999,42.968765],"type":"Point"}
}