{
  "type": "Feature",
  "properties": {
    "addr:full":"6938 Myrtle Avenue Glendale NY 11385",
    "addr:housenumber":"6938",
    "addr:postcode":"11385",
    "addr:street":"Myrtle Avenue",
    "iso:country":"US",
    "sg:address":"6938 Myrtle Avenue",
    "sg:city":"Glendale",
    "sg:classifiers":[
        {
            "category":"Professional",
            "subcategory":"Lawyer & Legal Services",
            "type":"Services"
        }
    ],
    "sg:phone":"+1 718 366 6418",
    "sg:postcode":"11385",
    "sg:province":"NY",
    "sg:tags":[
        "divorce",
        "law",
        "family"
    ],
    "wof:name":"Joseph Alan H Attorney At Law",
    "wof:placetype":"venue"
},
  "geometry": {"coordinates":[-73.881519,40.701775],"type":"Point"}
}