{
  "type": "Feature",
  "properties": {
    "addr:full":"17 E Main St Honeoye NY 14471",
    "addr:housenumber":"17",
    "addr:postcode":"14471",
    "addr:street":"E Main St",
    "iso:country":"US",
    "sg:address":"17 E Main St",
    "sg:city":"Honeoye",
    "sg:classifiers":[
        {
            "category":"Food & Beverages",
            "subcategory":"Dairy",
            "type":"Retail Goods"
        }
    ],
    "sg:phone":"+1   ",
    "sg:postcode":"14471",
    "sg:province":"NY",
    "sg:tags":[
        "product"
    ],
    "wof:name":"Harlees",
    "wof:placetype":"venue"
},
  "geometry": {"coordinates":[-77.51439999999999,42.789648],"type":"Point"}
}