{
  "type": "Feature",
  "properties": {
    "iso:country":"US",
    "sg:address":"135 Westchester Sq",
    "sg:city":"Bronx",
    "sg:classifiers":[
        {
            "category":"Education",
            "subcategory":"Music School",
            "type":"Public Place"
        }
    ],
    "sg:phone":"+1 347 851 3021",
    "sg:postcode":"10461",
    "sg:province":"NY",
    "sg:tags":[
        "instrument",
        "teacher",
        "musical"
    ],
    "wof:name":"Still Diggin Music",
    "wof:placetype":"venue"
},
  "geometry": {"coordinates":[-73.841684,40.840769],"type":"Point"}
}