{
  "type": "Feature",
  "properties": {
    "iso:country":"US",
    "sg:address":"2 W 32 St",
    "sg:city":"New York",
    "sg:classifiers":[
        {
            "category":"Professional",
            "subcategory":"Advertising",
            "type":"Services"
        }
    ],
    "sg:phone":"+1 212 279 2263",
    "sg:postcode":"10001",
    "sg:province":"NY",
    "sg:tags":[
        "graphic",
        "design"
    ],
    "wof:name":"Acme Design Group Inc",
    "wof:placetype":"venue"
},
  "geometry": {"coordinates":[-73.98817699999999,40.748289],"type":"Point"}
}