{
  "type": "Feature",
  "properties": {
    "addr:full":"50 Pierrepont St Brooklyn NY 11201",
    "addr:housenumber":"50",
    "addr:postcode":"11201",
    "addr:street":"Pierrepont St",
    "iso:country":"US",
    "sg:address":"50 Pierrepont St",
    "sg:city":"Brooklyn",
    "sg:classifiers":[
        {
            "category":"Professional",
            "subcategory":"Business Services",
            "type":"Services"
        }
    ],
    "sg:phone":"+1 718 624 4718",
    "sg:postcode":"11201",
    "sg:province":"NY",
    "sg:tags":[
        "interior",
        "design"
    ],
    "wof:name":"Falkener-Stuetley Interiors",
    "wof:placetype":"venue"
},
  "geometry": {"coordinates":[-73.994274,40.69549],"type":"Point"}
}