{
  "type": "Feature",
  "properties": {
    "iso:country":"US",
    "sg:address":"356 Greece Ridge Center Dr",
    "sg:city":"Rochester",
    "sg:classifiers":[
        {
            "category":"Personal",
            "subcategory":"Beauty Salon",
            "type":"Services"
        }
    ],
    "sg:phone":"+1 585 227 6070",
    "sg:postcode":"14626",
    "sg:province":"NY",
    "sg:tags":[
        "shop"
    ],
    "wof:name":"Cuts Unlimited",
    "wof:placetype":"venue"
},
  "geometry": {"coordinates":[-77.695369,43.204666],"type":"Point"}
}