{
  "type": "Feature",
  "properties": {
    "iso:country":"US",
    "sg:address":"14 High Ridge Rd",
    "sg:city":"Plainview",
    "sg:classifiers":[
        {
            "category":"Professional",
            "subcategory":"Management & Consulting",
            "type":"Services"
        }
    ],
    "sg:phone":"+1   ",
    "sg:postcode":"11803",
    "sg:province":"NY",
    "sg:tags":[
        "public",
        "relations"
    ],
    "wof:name":"Corporate Authority Comm",
    "wof:placetype":"venue"
},
  "geometry": {"coordinates":[-73.45698400000001,40.793916],"type":"Point"}
}