{
  "type": "Feature",
  "properties": {
    "iso:country":"US",
    "sg:address":"74 N Main St",
    "sg:city":"Brockport",
    "sg:classifiers":[
        {
            "category":"Professional",
            "subcategory":"Computer Services",
            "type":"Services"
        }
    ],
    "sg:phone":"+1 585 637 3240",
    "sg:postcode":"14420",
    "sg:province":"NY",
    "sg:tags":[
        "repair"
    ],
    "wof:name":"P & Np COMPUTER Svc",
    "wof:placetype":"venue"
},
  "geometry": {"coordinates":[-77.937145,43.219592],"type":"Point"}
}