{
  "type": "Feature",
  "properties": {
    "iso:country":"US",
    "sg:address":"21 S Washington St",
    "sg:city":"Binghamton",
    "sg:classifiers":[
        {
            "category":"Shopping",
            "type":"Retail Goods"
        }
    ],
    "sg:phone":"+1 607 724 5680",
    "sg:postcode":"13903",
    "sg:province":"NY",
    "sg:tags":[
        "repair",
        "pa",
        "electronic",
        "merchandise"
    ],
    "wof:name":"IKON Office Solutions",
    "wof:placetype":"venue"
},
  "geometry": {"coordinates":[-75.91434,42.091404],"type":"Point"}
}