{
  "type": "Feature",
  "properties": {
    "iso:country":"US",
    "sg:address":"1234 E 87th St",
    "sg:city":"Brooklyn",
    "sg:classifiers":[
        {
            "category":"Social Services",
            "subcategory":"Child Care",
            "type":"Services"
        }
    ],
    "sg:phone":"+1 718 444 3535",
    "sg:postcode":"11236",
    "sg:province":"NY",
    "wof:name":"Rising Stars Daycare",
    "wof:placetype":"venue"
},
  "geometry": {"coordinates":[-73.90141,40.632779],"type":"Point"}
}