{
  "type": "Feature",
  "properties": {
    "iso:country":"US",
    "sg:address":"50 Ridge Rd",
    "sg:city":"Buffalo",
    "sg:classifiers":[
        {
            "category":"Professional",
            "subcategory":"Lawyer & Legal Services",
            "type":"Services"
        }
    ],
    "sg:phone":"+1 716 821 7718",
    "sg:postcode":"14218",
    "sg:province":"NY",
    "wof:name":"Lenahan Danielle",
    "wof:placetype":"venue"
},
  "geometry": {"coordinates":[-78.850071,42.827947],"type":"Point"}
}