{
  "type": "Feature",
  "properties": {
    "addr:full":"12 Monroe St Schenectady NY 12305",
    "addr:housenumber":"12",
    "addr:postcode":"12305",
    "addr:street":"Monroe St",
    "iso:country":"US",
    "sg:address":"12 Monroe St",
    "sg:city":"Schenectady",
    "sg:classifiers":[
        {
            "category":"Building & Trades",
            "subcategory":"Construction",
            "type":"Services"
        }
    ],
    "sg:phone":"+1 518 384 0204",
    "sg:postcode":"12305",
    "sg:province":"NY",
    "sg:tags":[
        "remodeling",
        "contractor"
    ],
    "wof:name":"Advanced Roofing & Siding",
    "wof:placetype":"venue"
},
  "geometry": {"coordinates":[-73.939351,42.820554],"type":"Point"}
}