{
  "type": "Feature",
  "properties": {
    "iso:country":"US",
    "sg:address":"280 N Central Ave",
    "sg:city":"Hartsdale",
    "sg:classifiers":[
        {
            "category":"Professional",
            "subcategory":"Accounting & Tax Preparation",
            "type":"Services"
        }
    ],
    "sg:phone":"+1 914 997 6431",
    "sg:postcode":"10530",
    "sg:province":"NY",
    "sg:tags":[
        "accountant"
    ],
    "wof:name":"Barry R Charles CPA",
    "wof:placetype":"venue"
},
  "geometry": {"coordinates":[-73.794364,41.022989],"type":"Point"}
}