{
  "type": "Feature",
  "properties": {
    "addr:full":"14420 226th St Springfield Gardens NY 11413",
    "addr:housenumber":"14420",
    "addr:postcode":"11413",
    "addr:street":"226Th St",
    "iso:country":"US",
    "sg:address":"14420 226th St",
    "sg:city":"Springfield Gardens",
    "sg:classifiers":[
        {
            "category":"Shopping",
            "subcategory":"Clothing, Apparel, & Fashions",
            "type":"Retail Goods"
        },
        {
            "category":"Social Services",
            "subcategory":"Child Care",
            "type":"Services"
        }
    ],
    "sg:phone":"+1 718 712 1400",
    "sg:postcode":"11413",
    "sg:province":"NY",
    "sg:tags":[
        "children's",
        "clothing",
        "day"
    ],
    "wof:name":"Kiddie Korner Inc",
    "wof:placetype":"venue"
},
  "geometry": {"coordinates":[-73.752465,40.664055],"type":"Point"}
}