{
  "type": "Feature",
  "properties": {
    "addr:full":"60 Echo Ave Miller Place NY 11764",
    "addr:housenumber":"60",
    "addr:postcode":"11764",
    "addr:street":"Echo Ave",
    "iso:country":"US",
    "sg:address":"60 Echo Ave",
    "sg:city":"Miller Place",
    "sg:classifiers":[
        {
            "category":"Wholesale",
            "subcategory":"Medical Equipment & Supplies",
            "type":"Manufacturing & Wholesale Goods"
        }
    ],
    "sg:phone":"+1 631 476 8230",
    "sg:postcode":"11764",
    "sg:province":"NY",
    "sg:tags":[
        "physician",
        "surgeon"
    ],
    "wof:name":"Echo Medical & Surgical Supply",
    "wof:placetype":"venue"
},
  "geometry": {"coordinates":[-73.000303,40.943181],"type":"Point"}
}