{
  "type": "Feature",
  "properties": {
    "iso:country":"US",
    "sg:address":"12 Grand Blvd",
    "sg:city":"Brentwood",
    "sg:classifiers":[
        {
            "category":"Manufacturing",
            "subcategory":"Tools & Machinery",
            "type":"Manufacturing & Wholesale Goods"
        }
    ],
    "sg:phone":"+1 631 273 1177",
    "sg:postcode":"11717",
    "sg:province":"NY",
    "sg:tags":[
        "equipment",
        "fixture",
        "lighting"
    ],
    "sg:website":"www.coronetchandelier.com",
    "wof:name":"Coronet Chandelier Originals",
    "wof:placetype":"venue"
},
  "geometry": {"coordinates":[-73.226097,40.783798],"type":"Point"}
}