{
  "type": "Feature",
  "properties": {
    "iso:country":"US",
    "sg:address":"241 Sheridan Blvd",
    "sg:city":"Inwood",
    "sg:classifiers":[
        {
            "category":"Retail",
            "subcategory":"Auto Repair",
            "type":"Services"
        }
    ],
    "sg:phone":"+1 516 239 8311",
    "sg:postcode":"11096",
    "sg:province":"NY",
    "wof:name":"Circle Auto Radiators & Air Conditioning Inc",
    "wof:placetype":"venue"
},
  "geometry": {"coordinates":[-73.75147800000001,40.61821],"type":"Point"}
}