{
  "type": "Feature",
  "properties": {
    "iso:country":"US",
    "sg:address":"1084 Morton Blvd",
    "sg:city":"Kingston",
    "sg:classifiers":[
        {
            "category":"Shopping",
            "subcategory":"Bicycles & Sporting Goods",
            "type":"Retail Goods"
        }
    ],
    "sg:phone":"+1 845 336 9341",
    "sg:postcode":"12401",
    "sg:province":"NY",
    "sg:tags":[
        "equipment",
        "golf",
        "supply"
    ],
    "wof:name":"Gallagher Golf Direct",
    "wof:placetype":"venue"
},
  "geometry": {"coordinates":[-73.99296200000001,41.960992],"type":"Point"}
}