{
  "type": "Feature",
  "properties": {
    "addr:full":"591 Lexington Ave New York NY 10022",
    "addr:housenumber":"591",
    "addr:postcode":"10022",
    "addr:street":"Lexington Ave",
    "iso:country":"US",
    "sg:address":"591 Lexington Ave",
    "sg:city":"New York",
    "sg:classifiers":[
        {
            "category":"Professional",
            "type":"Services"
        }
    ],
    "sg:phone":"+1 212 759 7435",
    "sg:postcode":"10022",
    "sg:province":"NY",
    "sg:tags":[
        "establishment"
    ],
    "wof:name":"Jarrett Enterprises",
    "wof:placetype":"venue"
},
  "geometry": {"coordinates":[-73.971692,40.757157],"type":"Point"}
}