{
  "type": "Feature",
  "properties": {
    "addr:full":"243 State Hwy 59 West Nyack NY 10994",
    "addr:housenumber":"243",
    "addr:postcode":"10994",
    "addr:street":"State Hwy 59",
    "iso:country":"US",
    "sg:address":"243 State Hwy 59",
    "sg:city":"West Nyack",
    "sg:classifiers":[
        {
            "category":"Shopping",
            "subcategory":"Pharmacy",
            "type":"Retail Goods"
        }
    ],
    "sg:phone":"+1 845 353 4949",
    "sg:postcode":"10994",
    "sg:province":"NY",
    "sg:website":"www.shoprite.com",
    "wof:name":"Shop Rite Supermarket",
    "wof:placetype":"venue"
},
  "geometry": {"coordinates":[-73.96209399999999,41.094259],"type":"Point"}
}