{
  "type": "Feature",
  "properties": {
    "addr:full":"125 New Dorp Ln Staten Island NY 10306",
    "addr:housenumber":"125",
    "addr:postcode":"10306",
    "addr:street":"New Dorp Ln",
    "iso:country":"US",
    "sg:address":"125 New Dorp Ln",
    "sg:city":"Staten Island",
    "sg:classifiers":[
        {
            "category":"Retail",
            "subcategory":"Veterinary Services",
            "type":"Services"
        },
        {
            "category":"Retail",
            "subcategory":"Pet Boarding",
            "type":"Services"
        }
    ],
    "sg:phone":"+1 718 980 2600",
    "sg:postcode":"10306",
    "sg:province":"NY",
    "sg:tags":[
        "veterinarian",
        "boarding/pet",
        "sitting"
    ],
    "sg:website":"www.southshoreanimalhospital.com",
    "wof:name":"Archer Dexter",
    "wof:placetype":"venue"
},
  "geometry": {"coordinates":[-74.116096,40.574001],"type":"Point"}
}