{
  "type": "Feature",
  "properties": {
    "addr:full":"329 Ave of the Americas New York NY 10014",
    "addr:housenumber":"329",
    "addr:postcode":"10014",
    "addr:street":"Ave Of The Americas",
    "iso:country":"US",
    "sg:address":"329 Ave of the Americas",
    "sg:city":"New York",
    "sg:classifiers":[
        {
            "category":"Personal",
            "subcategory":"Tattoo Parlor",
            "type":"Services"
        }
    ],
    "sg:phone":"+1 212 929 9541",
    "sg:postcode":"10014",
    "sg:province":"NY",
    "wof:name":"Kingdom Tattoo the",
    "wof:placetype":"venue"
},
  "geometry": {"coordinates":[-74.00129699999999,40.7314],"type":"Point"}
}