{
  "type": "Feature",
  "properties": {
    "iso:country":"US",
    "sg:address":"880 Morris Ave",
    "sg:city":"Bronx",
    "sg:classifiers":[
        {
            "category":"Health Services",
            "subcategory":"Hospital",
            "type":"Services"
        },
        {
            "category":"Health Services",
            "subcategory":"Clinic",
            "type":"Services"
        }
    ],
    "sg:phone":"+1 718 665 9340",
    "sg:postcode":"10451",
    "sg:province":"NY",
    "sg:tags":[
        "medical",
        "group",
        "specialty",
        "outpatient"
    ],
    "wof:name":"Concourse Medical P C",
    "wof:placetype":"venue"
},
  "geometry": {"coordinates":[-73.918049,40.826055],"type":"Point"}
}