{
  "type": "Feature",
  "properties": {
    "addr:full":"21 W 46th St New York NY 10036",
    "addr:housenumber":"21",
    "addr:postcode":"10036",
    "addr:street":"W 46Th St",
    "iso:country":"US",
    "sg:address":"21 W 46th St",
    "sg:city":"New York",
    "sg:classifiers":[
        {
            "category":"Real Estate",
            "subcategory":"Real Estate Agent",
            "type":"Services"
        }
    ],
    "sg:phone":"+1 212 398 2998",
    "sg:postcode":"10036",
    "sg:province":"NY",
    "wof:name":"W T Gallagher & Associates",
    "wof:placetype":"venue"
},
  "geometry": {"coordinates":[-73.981719,40.757176],"type":"Point"}
}