{
  "type": "Feature",
  "properties": {
    "addr:full":"8026 Northern Boulevard Jackson Heights NY 11372",
    "addr:housenumber":"8026",
    "addr:postcode":"11372",
    "addr:street":"Northern Boulevard",
    "iso:country":"US",
    "sg:address":"8026 Northern Boulevard",
    "sg:city":"Jackson Heights",
    "sg:classifiers":[
        {
            "category":"Retail",
            "subcategory":"Portrait Studio",
            "type":"Services"
        },
        {
            "category":"Professional",
            "subcategory":"Art Services",
            "type":"Services"
        }
    ],
    "sg:phone":"+1 718 335 6868",
    "sg:postcode":"11372",
    "sg:province":"NY",
    "sg:tags":[
        "photographer",
        "photography",
        "store"
    ],
    "wof:name":"First Choice Photo",
    "wof:placetype":"venue"
},
  "geometry": {"coordinates":[-73.886422,40.755335],"type":"Point"}
}