{
  "type": "Feature",
  "properties": {
    "iso:country":"US",
    "sg:address":"194 Field St",
    "sg:city":"Rochester",
    "sg:classifiers":[
        {
            "category":"Education",
            "subcategory":"School",
            "type":"Public Place"
        }
    ],
    "sg:phone":"+1 585 271 4583",
    "sg:postcode":"14620",
    "sg:province":"NY",
    "wof:name":"School District 35 Elementary",
    "wof:placetype":"venue"
},
  "geometry": {"coordinates":[-77.58884999999999,43.138285],"type":"Point"}
}