{
  "type": "Feature",
  "properties": {
    "addr:full":"824 Ridge Rd E Rochester NY 14621",
    "addr:housenumber":"824",
    "addr:postcode":"14621",
    "addr:street":"Ridge Rd E",
    "iso:country":"US",
    "sg:address":"824 Ridge Rd E",
    "sg:city":"Rochester",
    "sg:classifiers":[
        {
            "category":"Professional",
            "subcategory":"Accounting & Tax Preparation",
            "type":"Services"
        }
    ],
    "sg:phone":"+1 585 266 8767",
    "sg:postcode":"14621",
    "sg:province":"NY",
    "sg:tags":[
        "return",
        "filing"
    ],
    "wof:name":"E Z Income Tax Svc",
    "wof:placetype":"venue"
},
  "geometry": {"coordinates":[-77.592508,43.197126],"type":"Point"}
}