{
  "type": "Feature",
  "properties": {
    "addr:full":"169 Main St Port Washington NY 11050",
    "addr:housenumber":"169",
    "addr:postcode":"11050",
    "addr:street":"Main St",
    "iso:country":"US",
    "sg:address":"169 Main St",
    "sg:city":"Port Washington",
    "sg:classifiers":[
        {
            "category":"Personal",
            "subcategory":"Beauty Salon",
            "type":"Services"
        }
    ],
    "sg:phone":"+1 516 883 2363",
    "sg:postcode":"11050",
    "sg:province":"NY",
    "wof:name":"Farfalla Salon",
    "wof:placetype":"venue"
},
  "geometry": {"coordinates":[-73.69351899999999,40.830777],"type":"Point"}
}