{
  "type": "Feature",
  "properties": {
    "iso:country":"US",
    "sg:address":"265 Prospect Park W",
    "sg:city":"Brooklyn",
    "sg:classifiers":[
        {
            "category":"Organizations",
            "subcategory":"Religious Organization",
            "type":"Services"
        }
    ],
    "sg:phone":"+1 718 788 2273",
    "sg:postcode":"11215",
    "sg:province":"NY",
    "sg:website":"www.parkslopechristiancenter.com",
    "wof:name":"Park Slope Christian Center",
    "wof:placetype":"venue"
},
  "geometry": {"coordinates":[-73.981972,40.658535],"type":"Point"}
}