{
  "type": "Feature",
  "properties": {
    "iso:country":"US",
    "sg:address":"1988 Central Ave",
    "sg:city":"Albany",
    "sg:classifiers":[
        {
            "category":"Building & Trades",
            "subcategory":"Cleaning & Sanitation",
            "type":"Services"
        }
    ],
    "sg:phone":"+1 518 464 8963",
    "sg:postcode":"12205",
    "sg:province":"NY",
    "sg:tags":[
        "house"
    ],
    "wof:name":"Maids",
    "wof:placetype":"venue"
},
  "geometry": {"coordinates":[-73.86251300000001,42.743618],"type":"Point"}
}