{
  "type": "Feature",
  "properties": {
    "iso:country":"US",
    "sg:address":"38 Ralph Ave",
    "sg:city":"Brooklyn",
    "sg:classifiers":[
        {
            "category":"Health Services",
            "subcategory":"Clinic",
            "type":"Services"
        }
    ],
    "sg:phone":"+1 718 455 7855",
    "sg:postcode":"11221",
    "sg:province":"NY",
    "wof:name":"Interfaith Medical Center Hosp",
    "wof:placetype":"venue"
},
  "geometry": {"coordinates":[-73.92394,40.688739],"type":"Point"}
}