{
  "type": "Feature",
  "properties": {
    "iso:country":"US",
    "sg:address":"56 Madison Ave",
    "sg:city":"Roosevelt",
    "sg:classifiers":[
        {
            "category":"Real Estate",
            "subcategory":"Real Estate Agent",
            "type":"Services"
        }
    ],
    "sg:phone":"+1 516 867 1953",
    "sg:postcode":"11575",
    "sg:province":"NY",
    "wof:name":"New Visions Realty",
    "wof:placetype":"venue"
},
  "geometry": {"coordinates":[-73.576981,40.671529],"type":"Point"}
}