{
  "type": "Feature",
  "properties": {
    "addr:full":"1277 Sterling Place Apt 2A Brooklyn NY 11213",
    "addr:housenumber":"1277;2a",
    "addr:postcode":"11213",
    "addr:street":"Sterling Place Apt",
    "iso:country":"US",
    "sg:address":"1277 Sterling Place Apt 2A",
    "sg:city":"Brooklyn",
    "sg:classifiers":[
        {
            "category":"Social Services",
            "subcategory":"Child Care",
            "type":"Services"
        }
    ],
    "sg:phone":"+1 718 363 2033",
    "sg:postcode":"11213",
    "sg:province":"NY",
    "sg:tags":[
        "day"
    ],
    "wof:name":"Sunshine Infant-Toddler Program",
    "wof:placetype":"venue"
},
  "geometry": {"coordinates":[-73.936324,40.671765],"type":"Point"}
}