{
  "type": "Feature",
  "properties": {
    "addr:full":"385 Goodwill Rd Montgomery NY 12549",
    "addr:housenumber":"385",
    "addr:postcode":"12549",
    "addr:street":"Goodwill Rd",
    "iso:country":"US",
    "sg:address":"385 Goodwill Rd",
    "sg:city":"Montgomery",
    "sg:classifiers":[
        {
            "category":"Professional",
            "subcategory":"Management & Consulting",
            "type":"Services"
        }
    ],
    "sg:phone":"+1   ",
    "sg:postcode":"12549",
    "sg:province":"NY",
    "wof:name":"Stoph Enterprises",
    "wof:placetype":"venue"
},
  "geometry": {"coordinates":[-74.21832499999999,41.515787],"type":"Point"}
}