{
  "type": "Feature",
  "properties": {
    "addr:full":"295 Woodbine St Brooklyn NY 11237",
    "addr:housenumber":"295",
    "addr:postcode":"11237",
    "addr:street":"Woodbine St",
    "iso:country":"US",
    "sg:address":"295 Woodbine St",
    "sg:city":"Brooklyn",
    "sg:classifiers":[
        {
            "category":"Social Services",
            "subcategory":"Child Care",
            "type":"Services"
        }
    ],
    "sg:phone":"+1 718 821 3432",
    "sg:postcode":"11237",
    "sg:province":"NY",
    "sg:tags":[
        "day"
    ],
    "wof:name":"New Life Child Development Center",
    "wof:placetype":"venue"
},
  "geometry": {"coordinates":[-73.91330000000001,40.696201],"type":"Point"}
}