{
  "type": "Feature",
  "properties": {
    "addr:full":"1068 Nostrand Ave Brooklyn NY 11225",
    "addr:housenumber":"1068",
    "addr:postcode":"11225",
    "addr:street":"Nostrand Ave",
    "iso:country":"US",
    "sg:address":"1068 Nostrand Ave",
    "sg:city":"Brooklyn",
    "sg:classifiers":[
        {
            "category":"Banks & Credit Unions",
            "subcategory":"Bank",
            "type":"Services"
        }
    ],
    "sg:phone":"+1 718 941 1680",
    "sg:postcode":"11225",
    "sg:province":"NY",
    "wof:name":"Crown Atm",
    "wof:placetype":"venue"
},
  "geometry": {"coordinates":[-73.950943,40.661977],"type":"Point"}
}