{
  "type": "Feature",
  "properties": {
    "addr:full":"215 North Ave New Rochelle NY 10801",
    "addr:housenumber":"215",
    "addr:postcode":"10801",
    "addr:street":"North Ave",
    "iso:country":"US",
    "sg:address":"215 North Ave",
    "sg:city":"New Rochelle",
    "sg:classifiers":[
        {
            "category":"Restaurant",
            "type":"Food & Drink"
        }
    ],
    "sg:menulink":"http://www.allmenus.com/ny/new-rochelle/144747-subway/menu/",
    "sg:phone":"+1 914 633 4099",
    "sg:postcode":"10801",
    "sg:province":"NY",
    "sg:tags":[
        "american",
        "sandwich"
    ],
    "wof:name":"Subway",
    "wof:placetype":"venue"
},
  "geometry": {"coordinates":[-73.78101100000001,40.910209],"type":"Point"}
}