{
  "type": "Feature",
  "properties": {
    "addr:full":"61 Trudo Rd Plattsburgh NY 12910",
    "addr:housenumber":"61",
    "addr:postcode":"12910",
    "addr:street":"Trudo Rd",
    "iso:country":"US",
    "sg:address":"61 Trudo Rd",
    "sg:city":"Plattsburgh",
    "sg:classifiers":[
        {
            "category":"Manufacturing",
            "subcategory":"Metals",
            "type":"Manufacturing & Wholesale Goods"
        }
    ],
    "sg:phone":"+1   ",
    "sg:postcode":"12910",
    "sg:province":"NY",
    "sg:tags":[
        "fabrication",
        "structural"
    ],
    "wof:name":"H & M Steel",
    "wof:placetype":"venue"
},
  "geometry": {"coordinates":[-73.651128,44.79672],"type":"Point"}
}