{
  "type": "Feature",
  "properties": {
    "addr:full":"210 E 21st Street New York NY 10010",
    "addr:housenumber":"210",
    "addr:postcode":"10010",
    "addr:street":"E 21St Street",
    "iso:country":"US",
    "sg:address":"210 E 21st Street",
    "sg:city":"New York",
    "sg:classifiers":[
        {
            "category":"Personal",
            "subcategory":"Beauty Salon",
            "type":"Services"
        }
    ],
    "sg:phone":"+1 212 673 2800",
    "sg:postcode":"10010",
    "sg:province":"NY",
    "sg:tags":[
        "hair"
    ],
    "wof:name":"Oly's Hair Salon",
    "wof:placetype":"venue"
},
  "geometry": {"coordinates":[-73.982832,40.736992],"type":"Point"}
}