{
  "type": "Feature",
  "properties": {
    "addr:full":"375 E Main St Ste 26 Bay Shore NY 11706",
    "addr:housenumber":"375;26",
    "addr:postcode":"11706",
    "addr:street":"E Main St Ste",
    "iso:country":"US",
    "sg:address":"375 E Main St Ste 26",
    "sg:city":"Bay Shore",
    "sg:classifiers":[
        {
            "category":"Health Services",
            "subcategory":"Doctor",
            "type":"Services"
        }
    ],
    "sg:phone":"+1 631 665 5000",
    "sg:postcode":"11706",
    "sg:province":"NY",
    "wof:name":"Gallagher John F PC",
    "wof:placetype":"venue"
},
  "geometry": {"coordinates":[-73.236198,40.726299],"type":"Point"}
}