{
  "type": "Feature",
  "properties": {
    "iso:country":"US",
    "sg:address":"23 College St",
    "sg:city":"Gowanda",
    "sg:classifiers":[
        {
            "category":"Building & Trades",
            "subcategory":"Construction",
            "type":"Services"
        }
    ],
    "sg:phone":"+1 716 532 2427",
    "sg:postcode":"14070",
    "sg:province":"NY",
    "wof:name":"Mw Offhaus & Sons Inc",
    "wof:placetype":"venue"
},
  "geometry": {"coordinates":[-78.940381,42.465348],"type":"Point"}
}