{
  "type": "Feature",
  "properties": {
    "iso:country":"US",
    "sg:address":"5501 Camp Rd",
    "sg:city":"Hamburg",
    "sg:phone":"+1 800 275 8777",
    "sg:postcode":"14075",
    "sg:province":"NY",
    "sg:website":"http://www.usps.com",
    "wof:name":"USPS - United States Post Office - Hamburg Main Office",
    "wof:placetype":"venue"
},
  "geometry": {"coordinates":[-78.842889,42.737073],"type":"Point"}
}