{
  "type": "Feature",
  "properties": {
    "addr:full":"21 Pecksland Rd Greenwich NY 06831",
    "addr:housenumber":"21",
    "addr:postcode":"06831",
    "addr:street":"Pecksland Rd",
    "iso:country":"US",
    "sg:address":"21 Pecksland Rd",
    "sg:city":"Greenwich",
    "sg:classifiers":[
        {
            "category":"Professional",
            "subcategory":"Management & Consulting",
            "type":"Services"
        }
    ],
    "sg:phone":"+1 203 629 1800",
    "sg:postcode":"06831",
    "sg:province":"NY",
    "sg:tags":[
        "marketing",
        "consultant"
    ],
    "wof:name":"Greenwich Marketing Group Inc",
    "wof:placetype":"venue"
},
  "geometry": {"coordinates":[-73.64863800000001,41.061226],"type":"Point"}
}