{
  "type": "Feature",
  "properties": {
    "addr:full":"511 E 164th St Bronx NY 10456",
    "addr:housenumber":"511",
    "addr:postcode":"10456",
    "addr:street":"E 164Th St",
    "iso:country":"US",
    "sg:address":"511 E 164th St",
    "sg:city":"Bronx",
    "sg:classifiers":[
        {
            "category":"Real Estate",
            "subcategory":"Real Estate Agent",
            "type":"Services"
        }
    ],
    "sg:phone":"+1 718 402 4200",
    "sg:postcode":"10456",
    "sg:province":"NY",
    "wof:name":"Explorer Realty Inc",
    "wof:placetype":"venue"
},
  "geometry": {"coordinates":[-73.90875200000001,40.825619],"type":"Point"}
}