{
  "type": "Feature",
  "properties": {
    "iso:country":"US",
    "sg:address":"4713 Onondaga Blvd",
    "sg:city":"Syracuse",
    "sg:classifiers":[
        {
            "category":"Wholesale",
            "subcategory":"Machinery & Supplies",
            "type":"Manufacturing & Wholesale Goods"
        }
    ],
    "sg:phone":"+1 315 424 8447",
    "sg:postcode":"13219",
    "sg:province":"NY",
    "sg:tags":[
        "salon",
        "beauty"
    ],
    "wof:name":"Sally Beauty Supply",
    "wof:placetype":"venue"
},
  "geometry": {"coordinates":[-76.193895,43.032275],"type":"Point"}
}