{
  "type": "Feature",
  "properties": {
    "iso:country":"US",
    "sg:address":"300 Allens Creek Rd",
    "sg:city":"Rochester",
    "sg:classifiers":[
        {
            "category":"Professional",
            "subcategory":"Management & Consulting",
            "type":"Services"
        }
    ],
    "sg:phone":"+1 585 244 3435",
    "sg:postcode":"14618",
    "sg:province":"NY",
    "wof:name":"I M Aviation Services Inc",
    "wof:placetype":"venue"
},
  "geometry": {"coordinates":[-77.545159,43.116847],"type":"Point"}
}