{
  "type": "Feature",
  "properties": {
    "iso:country":"US",
    "sg:address":"106 N Ballston Ave",
    "sg:city":"Scotia",
    "sg:classifiers":[
        {
            "category":"Health Services",
            "subcategory":"Doctor",
            "type":"Services"
        }
    ],
    "sg:phone":"+1 518 395 9127",
    "sg:postcode":"12302",
    "sg:province":"NY",
    "sg:tags":[
        "dentist"
    ],
    "wof:name":"Stuart M Kraut DDS",
    "wof:placetype":"venue"
},
  "geometry": {"coordinates":[-73.961112,42.826343],"type":"Point"}
}