{
  "type": "Feature",
  "properties": {
    "iso:country":"US",
    "sg:address":"320 Margaret St",
    "sg:city":"Plattsburgh",
    "sg:classifiers":[
        {
            "category":"Health Services",
            "subcategory":"Medical Lab",
            "type":"Services"
        }
    ],
    "sg:phone":"+1 518 566 0081",
    "sg:postcode":"12901",
    "sg:province":"NY",
    "sg:tags":[
        "laboratory"
    ],
    "wof:name":"Laboratory Corp Of America",
    "wof:placetype":"venue"
},
  "geometry": {"coordinates":[-73.451669,44.708862],"type":"Point"}
}