{
  "type": "Feature",
  "properties": {
    "iso:country":"US",
    "sg:address":"55 Jericho Tpke Ste 202",
    "sg:city":"Jericho",
    "sg:classifiers":[
        {
            "category":"Professional",
            "subcategory":"Lawyer & Legal Services",
            "type":"Services"
        }
    ],
    "sg:phone":"+1 631 264 2300",
    "sg:postcode":"11753",
    "sg:province":"NY",
    "sg:website":"www.amerilawyer.com",
    "wof:name":"Amerilawyer Com",
    "wof:placetype":"venue"
},
  "geometry": {"coordinates":[-73.563671,40.778066],"type":"Point"}
}