{
  "type": "Feature",
  "properties": {
    "addr:full":"1565 Grand Concourse Bronx NY 10452",
    "addr:housenumber":"1565",
    "addr:postcode":"10452",
    "addr:street":"Grand Concourse",
    "iso:country":"US",
    "sg:address":"1565 Grand Concourse",
    "sg:city":"Bronx",
    "sg:classifiers":[
        {
            "category":"Personal",
            "subcategory":"Beauty Salon",
            "type":"Services"
        }
    ],
    "sg:phone":"+1 718 299 4288",
    "sg:postcode":"10452",
    "sg:province":"NY",
    "sg:tags":[
        "spa"
    ],
    "wof:name":"Concourse II Party Shop & Beauty Salon",
    "wof:placetype":"venue"
},
  "geometry": {"coordinates":[-73.912498,40.8423],"type":"Point"}
}