{
  "type": "Feature",
  "properties": {
    "addr:full":"200 2nd Ave New York NY 10003",
    "addr:housenumber":"200",
    "addr:postcode":"10003",
    "addr:street":"2Nd Ave",
    "iso:country":"US",
    "sg:address":"200 2nd Ave",
    "sg:city":"New York",
    "sg:classifiers":[
        {
            "category":"Restaurant",
            "type":"Food & Drink"
        }
    ],
    "sg:phone":"+1 212 777 9728",
    "sg:postcode":"10003",
    "sg:province":"NY",
    "sg:tags":[
        "polish",
        "diner"
    ],
    "wof:name":"Little Poland",
    "wof:placetype":"venue"
},
  "geometry": {"coordinates":[-73.985659,40.731323],"type":"Point"}
}