{
  "type": "Feature",
  "properties": {
    "addr:full":"142 Greene St Ste 4 New York NY 10012",
    "addr:housenumber":"142",
    "addr:postcode":"10012",
    "addr:street":"Greene St Ste 4",
    "iso:country":"US",
    "sg:address":"142 Greene St Ste 4",
    "sg:city":"New York",
    "sg:classifiers":[
        {
            "category":"Retail",
            "subcategory":"Portrait Studio",
            "type":"Services"
        },
        {
            "category":"Professional",
            "subcategory":"Art Services",
            "type":"Services"
        }
    ],
    "sg:phone":"+1 212 614 9500",
    "sg:postcode":"10012",
    "sg:province":"NY",
    "sg:tags":[
        "photographer",
        "photography",
        "store"
    ],
    "wof:name":"Wilson-Wenzel",
    "wof:placetype":"venue"
},
  "geometry": {"coordinates":[-73.998503,40.72561],"type":"Point"}
}