{
  "type": "Feature",
  "properties": {
    "iso:country":"US",
    "sg:address":"498 Warren St",
    "sg:city":"Brooklyn",
    "sg:classifiers":[
        {
            "category":"Professional",
            "type":"Services"
        }
    ],
    "sg:phone":"+1   ",
    "sg:postcode":"11217",
    "sg:province":"NY",
    "wof:name":"Acugranny",
    "wof:placetype":"venue"
},
  "geometry": {"coordinates":[-73.986133,40.683511],"type":"Point"}
}