{
  "type": "Feature",
  "properties": {
    "addr:full":"242 W 36 St New York NY 10018",
    "addr:housenumber":"242",
    "addr:postcode":"10018",
    "addr:street":"W 36 St",
    "iso:country":"US",
    "sg:address":"242 W 36 St",
    "sg:city":"New York",
    "sg:classifiers":[
        {
            "category":"Manufacturing",
            "subcategory":"Apparel",
            "type":"Manufacturing & Wholesale Goods"
        }
    ],
    "sg:phone":"+1 212 268 5682",
    "sg:postcode":"10018",
    "sg:province":"NY",
    "sg:tags":[
        "sewing",
        "contractor"
    ],
    "wof:name":"Arel Studio",
    "wof:placetype":"venue"
},
  "geometry": {"coordinates":[-73.99164399999999,40.752897],"type":"Point"}
}