{
  "type": "Feature",
  "properties": {
    "addr:full":"39 Lincoln Ave Ossining NY 10562",
    "addr:housenumber":"39",
    "addr:postcode":"10562",
    "addr:street":"Lincoln Ave",
    "iso:country":"US",
    "sg:address":"39 Lincoln Ave",
    "sg:city":"Ossining",
    "sg:classifiers":[
        {
            "category":"Real Estate",
            "subcategory":"Real Estate Agent",
            "type":"Services"
        }
    ],
    "sg:phone":"+1 914 923 4146",
    "sg:postcode":"10562",
    "sg:province":"NY",
    "sg:tags":[
        "management"
    ],
    "wof:name":"Irvine Realty Group Inc",
    "wof:placetype":"venue"
},
  "geometry": {"coordinates":[-73.848086,41.17371],"type":"Point"}
}