{
  "type": "Feature",
  "properties": {
    "iso:country":"US",
    "sg:address":"7 Normandie Ln",
    "sg:city":"East Moriches",
    "sg:classifiers":[
        {
            "category":"Sports & Exercise",
            "subcategory":"Gym",
            "type":"Entertainment"
        }
    ],
    "sg:phone":"+1 631 874 8822",
    "sg:postcode":"11940",
    "sg:province":"NY",
    "sg:tags":[
        "trainer"
    ],
    "sg:website":"www.jazzercise.com",
    "wof:name":"Jazzercise",
    "wof:placetype":"venue"
},
  "geometry": {"coordinates":[-72.738899,40.809898],"type":"Point"}
}