{
  "type": "Feature",
  "properties": {
    "addr:full":"565 E 187th St Bronx NY 10458",
    "addr:housenumber":"565",
    "addr:postcode":"10458",
    "addr:street":"E 187Th St",
    "iso:country":"US",
    "sg:address":"565 E 187th St",
    "sg:city":"Bronx",
    "sg:classifiers":[
        {
            "category":"Food & Beverages",
            "subcategory":"Meat & Fish",
            "type":"Retail Goods"
        }
    ],
    "sg:phone":"+1   ",
    "sg:postcode":"10458",
    "sg:province":"NY",
    "wof:name":"Mergimtari Meat Store",
    "wof:placetype":"venue"
},
  "geometry": {"coordinates":[-73.88885000000001,40.856394],"type":"Point"}
}