{
  "type": "Feature",
  "properties": {
    "addr:full":"4432 Bay View Rd Hamburg NY 14075",
    "addr:housenumber":"4432",
    "addr:postcode":"14075",
    "addr:street":"Bay View Rd",
    "iso:country":"US",
    "sg:address":"4432 Bay View Rd",
    "sg:city":"Hamburg",
    "sg:classifiers":[
        {
            "category":"Education",
            "subcategory":"School",
            "type":"Public Place"
        }
    ],
    "sg:phone":"+1 716 926 1720",
    "sg:postcode":"14075",
    "sg:province":"NY",
    "sg:tags":[
        "high"
    ],
    "wof:name":"Frontier Central High School",
    "wof:placetype":"venue"
},
  "geometry": {"coordinates":[-78.827872,42.766389],"type":"Point"}
}