{
  "type": "Feature",
  "properties": {
    "addr:full":"13 Cortland Blvd Clifton Park NY 12065",
    "addr:housenumber":"13",
    "addr:postcode":"12065",
    "addr:street":"Cortland Blvd",
    "iso:country":"US",
    "sg:address":"13 Cortland Blvd",
    "sg:city":"Clifton Park",
    "sg:classifiers":[
        {
            "category":"Building & Trades",
            "subcategory":"Landscaping Services",
            "type":"Services"
        }
    ],
    "sg:phone":"+1 518 371 0508",
    "sg:postcode":"12065",
    "sg:province":"NY",
    "sg:tags":[
        "landscape",
        "contractor"
    ],
    "wof:name":"Saratoga Turf Care",
    "wof:placetype":"venue"
},
  "geometry": {"coordinates":[-73.789965,42.810769],"type":"Point"}
}