{
  "type": "Feature",
  "properties": {
    "iso:country":"US",
    "sg:address":"156 E 79th St",
    "sg:city":"New York",
    "sg:classifiers":[
        {
            "category":"Real Estate",
            "subcategory":"Real Estate Operator",
            "type":"Services"
        }
    ],
    "sg:phone":"+1 212 988 2083",
    "sg:postcode":"10021",
    "sg:province":"NY",
    "sg:tags":[
        "apartment"
    ],
    "wof:name":"156 E 79 St Corp",
    "wof:placetype":"venue"
},
  "geometry": {"coordinates":[-73.958504,40.774799],"type":"Point"}
}