{
  "type": "Feature",
  "properties": {
    "iso:country":"US",
    "sg:address":"904 Broad Hollow Rd",
    "sg:city":"Farmingdale",
    "sg:classifiers":[
        {
            "category":"Home & Garden",
            "subcategory":"Carpets & Floor Coverings",
            "type":"Retail Goods"
        }
    ],
    "sg:phone":"+1   ",
    "sg:postcode":"11735",
    "sg:province":"NY",
    "sg:tags":[
        "store"
    ],
    "wof:name":"The Floor Store",
    "wof:placetype":"venue"
},
  "geometry": {"coordinates":[-73.424038,40.726069],"type":"Point"}
}