{
  "type": "Feature",
  "properties": {
    "addr:full":"540 Adams St Centerport NY 11721",
    "addr:housenumber":"540",
    "addr:postcode":"11721",
    "addr:street":"Adams St",
    "iso:country":"US",
    "sg:address":"540 Adams St",
    "sg:city":"Centerport",
    "sg:classifiers":[
        {
            "category":"Professional",
            "subcategory":"Employment Agencies",
            "type":"Services"
        },
        {
            "category":"Organizations",
            "subcategory":"Professional Association",
            "type":"Services"
        }
    ],
    "sg:phone":"+1 631 427 4222",
    "sg:postcode":"11721",
    "sg:province":"NY",
    "sg:tags":[
        "employer",
        "business",
        "trade"
    ],
    "wof:name":"Huntington Beach Community Assn",
    "wof:placetype":"venue"
},
  "geometry": {"coordinates":[-73.382677,40.899638],"type":"Point"}
}