{
  "type": "Feature",
  "properties": {
    "addr:full":"2542 Marion Ave Bronx NY 10458",
    "addr:housenumber":"2542",
    "addr:postcode":"10458",
    "addr:street":"Marion Ave",
    "iso:country":"US",
    "sg:address":"2542 Marion Ave",
    "sg:city":"Bronx",
    "sg:classifiers":[
        {
            "category":"Food & Beverages",
            "subcategory":"Groceries & Convenience Stores",
            "type":"Retail Goods"
        }
    ],
    "sg:phone":"+1   ",
    "sg:postcode":"10458",
    "sg:province":"NY",
    "wof:name":"Las Flores Grocery Store",
    "wof:placetype":"venue"
},
  "geometry": {"coordinates":[-73.89233900000001,40.86246],"type":"Point"}
}