{
  "type": "Feature",
  "properties": {
    "iso:country":"US",
    "sg:address":"7 W 45th St 2nd Fl",
    "sg:city":"New York",
    "sg:classifiers":[
        {
            "category":"Health Services",
            "subcategory":"Dentist",
            "type":"Services"
        }
    ],
    "sg:phone":"+1 212 382 3782",
    "sg:postcode":"10036",
    "sg:province":"NY",
    "sg:website":"www.theferreiradentalgroup.com",
    "wof:name":"The Ferreira Dental Group",
    "wof:placetype":"venue"
},
  "geometry": {"coordinates":[-73.98006599999999,40.75591],"type":"Point"}
}