{
  "type": "Feature",
  "properties": {
    "addr:full":"243 Bowery New York NY 10002",
    "addr:housenumber":"243",
    "addr:postcode":"10002",
    "addr:street":"Bowery",
    "iso:country":"US",
    "sg:address":"243 Bowery",
    "sg:city":"New York",
    "sg:classifiers":[
        {
            "category":"Home & Garden",
            "subcategory":"Home Furnishings",
            "type":"Retail Goods"
        }
    ],
    "sg:phone":"+1 212 925 3785",
    "sg:postcode":"10002",
    "sg:province":"NY",
    "sg:tags":[
        "bath",
        "kitchen"
    ],
    "wof:name":"Bari Restaurant Equipment Corp",
    "wof:placetype":"venue"
},
  "geometry": {"coordinates":[-73.99294500000001,40.722448],"type":"Point"}
}