{
  "type": "Feature",
  "properties": {
    "addr:full":"268 Cable Rd Williamstown NY 13493",
    "addr:housenumber":"268",
    "addr:postcode":"13493",
    "addr:street":"Cable Rd",
    "iso:country":"US",
    "sg:address":"268 Cable Rd",
    "sg:city":"Williamstown",
    "sg:classifiers":[
        {
            "category":"Autos & Motor Vehicles",
            "subcategory":"Automobile Sales",
            "type":"Retail Goods"
        }
    ],
    "sg:phone":"+1 315 964 2577",
    "sg:postcode":"13493",
    "sg:province":"NY",
    "sg:tags":[
        "parts",
        "snowmobile",
        "accessory"
    ],
    "wof:name":"Sled Shed",
    "wof:placetype":"venue"
},
  "geometry": {"coordinates":[-75.91892799999999,43.353418],"type":"Point"}
}