{
  "type": "Feature",
  "properties": {
    "addr:full":"552 McDonald Ave Brooklyn NY 11218",
    "addr:housenumber":"552",
    "addr:postcode":"11218",
    "addr:street":"Mcdonald Ave",
    "iso:country":"US",
    "sg:address":"552 McDonald Ave",
    "sg:city":"Brooklyn",
    "sg:classifiers":[
        {
            "category":"Autos & Motor Vehicles",
            "subcategory":"Fuel & Gas Station",
            "type":"Retail Goods"
        }
    ],
    "sg:phone":"+1 718 438 3086",
    "sg:postcode":"11218",
    "sg:province":"NY",
    "wof:name":"Shalmoni's Service Station",
    "wof:placetype":"venue"
},
  "geometry": {"coordinates":[-73.979343,40.640737],"type":"Point"}
}