{
  "type": "Feature",
  "properties": {
    "addr:full":"4317 Fuller Hollow Rd Vestal NY 13850",
    "addr:housenumber":"4317",
    "addr:postcode":"13850",
    "addr:street":"Fuller Hollow Rd",
    "iso:country":"US",
    "sg:address":"4317 Fuller Hollow Rd",
    "sg:city":"Vestal",
    "sg:classifiers":[
        {
            "category":"Professional",
            "subcategory":"Business Services",
            "type":"Services"
        }
    ],
    "sg:phone":"+1 607 724 4837",
    "sg:postcode":"13850",
    "sg:province":"NY",
    "wof:name":"Center For Business",
    "wof:placetype":"venue"
},
  "geometry": {"coordinates":[-75.955753,42.072695],"type":"Point"}
}