{
  "type": "Feature",
  "properties": {
    "addr:full":"6003 S Salina St Ste 6 Syracuse NY 13205",
    "addr:housenumber":"6003",
    "addr:postcode":"13205",
    "addr:street":"S Salina St Ste 6",
    "iso:country":"US",
    "sg:address":"6003 S Salina St Ste 6",
    "sg:city":"Syracuse",
    "sg:classifiers":[
        {
            "category":"Personal",
            "subcategory":"Beauty Salon",
            "type":"Services"
        }
    ],
    "sg:phone":"+1 315 492 4440",
    "sg:postcode":"13205",
    "sg:province":"NY",
    "sg:tags":[
        "hair",
        "stylist"
    ],
    "wof:name":"Valley Hair Connection",
    "wof:placetype":"venue"
},
  "geometry": {"coordinates":[-76.14319999999999,42.983603],"type":"Point"}
}