{
  "type": "Feature",
  "properties": {
    "addr:full":"5715 14th Ave Brooklyn NY 11219",
    "addr:housenumber":"5715",
    "addr:postcode":"11219",
    "addr:street":"14Th Ave",
    "iso:country":"US",
    "sg:address":"5715 14th Ave",
    "sg:city":"Brooklyn",
    "sg:classifiers":[
        {
            "category":"Manufacturing",
            "subcategory":"Tools & Machinery",
            "type":"Manufacturing & Wholesale Goods"
        }
    ],
    "sg:phone":"+1 718 851 7251",
    "sg:postcode":"11219",
    "sg:province":"NY",
    "sg:tags":[
        "diamond"
    ],
    "wof:name":"American Diamond Tool & Wheel",
    "wof:placetype":"venue"
},
  "geometry": {"coordinates":[-73.99503900000001,40.628689],"type":"Point"}
}