{
  "type": "Feature",
  "properties": {
    "iso:country":"US",
    "sg:address":"413 Brighton Beach Ave",
    "sg:city":"Brooklyn",
    "sg:classifiers":[
        {
            "category":"Food & Beverages",
            "subcategory":"Fruits & Vegetables",
            "type":"Retail Goods"
        }
    ],
    "sg:phone":"+1 718 891 8549",
    "sg:postcode":"11235",
    "sg:province":"NY",
    "sg:tags":[
        "produce"
    ],
    "wof:name":"Jane Corp",
    "wof:placetype":"venue"
},
  "geometry": {"coordinates":[-73.96247,40.577459],"type":"Point"}
}