{
  "type": "Feature",
  "properties": {
    "addr:full":"23 Oakwood Rd Huntington NY 11743",
    "addr:housenumber":"23",
    "addr:postcode":"11743",
    "addr:street":"Oakwood Rd",
    "iso:country":"US",
    "sg:address":"23 Oakwood Rd",
    "sg:city":"Huntington",
    "sg:classifiers":[
        {
            "category":"Insurance",
            "subcategory":"Insurance Agent",
            "type":"Services"
        }
    ],
    "sg:phone":"+1 631 421 4284",
    "sg:postcode":"11743",
    "sg:province":"NY",
    "sg:tags":[
        "agency"
    ],
    "wof:name":"La Sorsa Michael A Insurance",
    "wof:placetype":"venue"
},
  "geometry": {"coordinates":[-73.427734,40.867186],"type":"Point"}
}