{
  "type": "Feature",
  "properties": {
    "addr:full":"1067 Metropolitan Ave Brooklyn NY 11211",
    "addr:housenumber":"1067",
    "addr:postcode":"11211",
    "addr:street":"Metropolitan Ave",
    "iso:country":"US",
    "sg:address":"1067 Metropolitan Ave",
    "sg:city":"Brooklyn",
    "sg:classifiers":[
        {
            "category":"Retail",
            "subcategory":"Repair Shop",
            "type":"Services"
        }
    ],
    "sg:phone":"+1 718 782 0447",
    "sg:postcode":"11211",
    "sg:province":"NY",
    "sg:tags":[
        "welding"
    ],
    "wof:name":"T & E Iron Works",
    "wof:placetype":"venue"
},
  "geometry": {"coordinates":[-73.93421600000001,40.714499],"type":"Point"}
}