{
  "type": "Feature",
  "properties": {
    "addr:full":"300 Voice Rd Carle Place NY 11514",
    "addr:housenumber":"300",
    "addr:postcode":"11514",
    "addr:street":"Voice Rd",
    "iso:country":"US",
    "sg:address":"300 Voice Rd",
    "sg:city":"Carle Place",
    "sg:classifiers":[
        {
            "category":"Shopping",
            "subcategory":"Clothing, Apparel, & Fashions",
            "type":"Retail Goods"
        }
    ],
    "sg:phone":"+1 516 294 8926",
    "sg:postcode":"11514",
    "sg:province":"NY",
    "sg:tags":[
        "infant",
        "wear"
    ],
    "wof:name":"Carter's Childrenswear",
    "wof:placetype":"venue"
},
  "geometry": {"coordinates":[-73.617535,40.747457],"type":"Point"}
}