{
  "type": "Feature",
  "properties": {
    "addr:full":"4 N Ledge Loop Croton On Hudson NY 10520",
    "addr:housenumber":"4",
    "addr:postcode":"10520",
    "addr:street":"N Ledge Loop",
    "iso:country":"US",
    "sg:address":"4 N Ledge Loop",
    "sg:city":"Croton On Hudson",
    "sg:classifiers":[
        {
            "category":"Professional",
            "subcategory":"Lawyer & Legal Services",
            "type":"Services"
        }
    ],
    "sg:phone":"+1 914 271 2200",
    "sg:postcode":"10520",
    "sg:province":"NY",
    "sg:tags":[
        "attorney"
    ],
    "wof:name":"Amy Attias",
    "wof:placetype":"venue"
},
  "geometry": {"coordinates":[-73.876884,41.214993],"type":"Point"}
}