{
  "type": "Feature",
  "properties": {
    "iso:country":"US",
    "sg:address":"132 Midvale Dr",
    "sg:city":"Fairport",
    "sg:classifiers":[
        {
            "category":"Building & Trades",
            "subcategory":"Landscaping Services",
            "type":"Services"
        }
    ],
    "sg:phone":"+1 585 586 5314",
    "sg:postcode":"14450",
    "sg:province":"NY",
    "wof:name":"Pioneer Tree Co",
    "wof:placetype":"venue"
},
  "geometry": {"coordinates":[-77.467472,43.10856],"type":"Point"}
}