{
  "type": "Feature",
  "properties": {
    "addr:full":"12250 State Hwy 176 Cato NY 13033",
    "addr:housenumber":"12250",
    "addr:postcode":"13033",
    "addr:street":"State Hwy 176",
    "iso:country":"US",
    "sg:address":"12250 State Hwy 176",
    "sg:city":"Cato",
    "sg:classifiers":[
        {
            "category":"Building & Trades",
            "subcategory":"Construction",
            "type":"Services"
        }
    ],
    "sg:phone":"+1 315 626 6966",
    "sg:postcode":"13033",
    "sg:province":"NY",
    "sg:tags":[
        "sandblasting"
    ],
    "wof:name":"B T & T Inc",
    "wof:placetype":"venue"
},
  "geometry": {"coordinates":[-76.52101999999999,43.206128],"type":"Point"}
}