{
  "type": "Feature",
  "properties": {
    "iso:country":"US",
    "sg:address":"2 Mohican Trl",
    "sg:city":"Scarsdale",
    "sg:classifiers":[
        {
            "category":"Professional",
            "type":"Services"
        }
    ],
    "sg:phone":"+1   ",
    "sg:postcode":"10583",
    "sg:province":"NY",
    "wof:name":"Kaye Wilma",
    "wof:placetype":"venue"
},
  "geometry": {"coordinates":[-73.77558999999999,40.995573],"type":"Point"}
}