{
  "type": "Feature",
  "properties": {
    "addr:full":"309 S Franklin St Syracuse NY 13202",
    "addr:housenumber":"309",
    "addr:postcode":"13202",
    "addr:street":"S Franklin St",
    "iso:country":"US",
    "sg:address":"309 S Franklin St",
    "sg:city":"Syracuse",
    "sg:classifiers":[
        {
            "category":"Professional",
            "subcategory":"Computer Services",
            "type":"Services"
        }
    ],
    "sg:phone":"+1 315 471 5751",
    "sg:postcode":"13202",
    "sg:province":"NY",
    "sg:tags":[
        "processing",
        "datum"
    ],
    "wof:name":"Data Concepts Inc",
    "wof:placetype":"venue"
},
  "geometry": {"coordinates":[-76.15545400000001,43.048025],"type":"Point"}
}