{
  "type": "Feature",
  "properties": {
    "iso:country":"US",
    "sg:address":"101 W State St",
    "sg:city":"Herkimer",
    "sg:classifiers":[
        {
            "category":"Food & Beverages",
            "subcategory":"Groceries & Convenience Stores",
            "type":"Retail Goods"
        }
    ],
    "sg:phone":"+1   ",
    "sg:postcode":"13350",
    "sg:province":"NY",
    "wof:name":"Fast Tracks",
    "wof:placetype":"venue"
},
  "geometry": {"coordinates":[-74.984409,43.025994],"type":"Point"}
}