{
  "type": "Feature",
  "properties": {
    "addr:full":"574 Bay Street Staten Island NY 10304",
    "addr:housenumber":"574",
    "addr:postcode":"10304",
    "addr:street":"Bay Street",
    "iso:country":"US",
    "sg:address":"574 Bay Street",
    "sg:city":"Staten Island",
    "sg:classifiers":[
        {
            "category":"Restaurant",
            "type":"Food & Drink"
        }
    ],
    "sg:phone":"+1 718 715 9539",
    "sg:postcode":"10304",
    "sg:province":"NY",
    "wof:name":"Bay House Bistro",
    "wof:placetype":"venue"
},
  "geometry": {"coordinates":[-74.076584,40.627914],"type":"Point"}
}