{
  "type": "Feature",
  "properties": {
    "iso:country":"US",
    "sg:address":"2795 Richmond Ave",
    "sg:city":"Staten Island",
    "sg:classifiers":[
        {
            "category":"Personal",
            "subcategory":"Beauty Salon",
            "type":"Services"
        }
    ],
    "sg:phone":"+1 718 494 7200",
    "sg:postcode":"10314",
    "sg:province":"NY",
    "wof:name":"Supercuts",
    "wof:placetype":"venue"
},
  "geometry": {"coordinates":[-74.169285,40.579401],"type":"Point"}
}