{
  "type": "Feature",
  "properties": {
    "addr:full":"13 Davidge Rd Middletown NY 10940",
    "addr:housenumber":"13",
    "addr:postcode":"10940",
    "addr:street":"Davidge Rd",
    "iso:country":"US",
    "sg:address":"13 Davidge Rd",
    "sg:city":"Middletown",
    "sg:classifiers":[
        {
            "category":"Real Estate",
            "subcategory":"Real Estate Operator",
            "type":"Services"
        }
    ],
    "sg:phone":"+1 845 342 1400",
    "sg:postcode":"10940",
    "sg:province":"NY",
    "sg:tags":[
        "building",
        "nonresidential"
    ],
    "wof:name":"Eastview Properties",
    "wof:placetype":"venue"
},
  "geometry": {"coordinates":[-74.428421,41.461105],"type":"Point"}
}