{
  "type": "Feature",
  "properties": {
    "iso:country":"US",
    "sg:address":"650 Moseley Rd",
    "sg:city":"Fairport",
    "sg:classifiers":[
        {
            "category":"Autos & Motor Vehicles",
            "subcategory":"Fuel & Gas Station",
            "type":"Retail Goods"
        }
    ],
    "sg:phone":"+1 585 223 6138",
    "sg:postcode":"14450",
    "sg:province":"NY",
    "sg:tags":[
        "oil"
    ],
    "wof:name":"650 Moseley Road Inc",
    "wof:placetype":"venue"
},
  "geometry": {"coordinates":[-77.442386,43.066359],"type":"Point"}
}