{
  "type": "Feature",
  "properties": {
    "addr:full":"425 Tarrytown Rd White Plains NY 10607",
    "addr:housenumber":"425",
    "addr:postcode":"10607",
    "addr:street":"Tarrytown Rd",
    "iso:country":"US",
    "sg:address":"425 Tarrytown Rd",
    "sg:city":"White Plains",
    "sg:classifiers":[
        {
            "category":"Restaurant",
            "type":"Food & Drink"
        }
    ],
    "sg:phone":"+1   ",
    "sg:postcode":"10607",
    "sg:province":"NY",
    "sg:tags":[
        "eating"
    ],
    "wof:name":"Super Buffet",
    "wof:placetype":"venue"
},
  "geometry": {"coordinates":[-73.79868399999999,41.043301],"type":"Point"}
}