{
  "type": "Feature",
  "properties": {
    "addr:full":"146 5th Ave Pelham NY 10803",
    "addr:housenumber":"146",
    "addr:postcode":"10803",
    "addr:street":"5Th Ave",
    "iso:country":"US",
    "sg:address":"146 5th Ave",
    "sg:city":"Pelham",
    "sg:classifiers":[
        {
            "category":"Food & Beverages",
            "subcategory":"Fruits & Vegetables",
            "type":"Retail Goods"
        }
    ],
    "sg:phone":"+1   ",
    "sg:postcode":"10803",
    "sg:province":"NY",
    "wof:name":"Depot Market",
    "wof:placetype":"venue"
},
  "geometry": {"coordinates":[-73.80855,40.913196],"type":"Point"}
}