{
  "type": "Feature",
  "properties": {
    "addr:full":"1344 Pennsylvania Ave Brooklyn NY 11239",
    "addr:housenumber":"1344",
    "addr:postcode":"11239",
    "addr:street":"Pennsylvania Ave",
    "iso:country":"US",
    "sg:address":"1344 Pennsylvania Ave",
    "sg:city":"Brooklyn",
    "sg:classifiers":[
        {
            "category":"Professional",
            "subcategory":"Management & Consulting",
            "type":"Services"
        }
    ],
    "sg:phone":"+1 718 642 7000",
    "sg:postcode":"11239",
    "sg:province":"NY",
    "sg:tags":[
        "fuel"
    ],
    "wof:name":"Starrett City Management",
    "wof:placetype":"venue"
},
  "geometry": {"coordinates":[-73.884557,40.6505],"type":"Point"}
}