{
  "type": "Feature",
  "properties": {
    "addr:full":"1675 Sunrise Hwy Bay Shore NY 11706",
    "addr:housenumber":"1675",
    "addr:postcode":"11706",
    "addr:street":"Sunrise Hwy",
    "iso:country":"US",
    "sg:address":"1675 Sunrise Hwy",
    "sg:city":"Bay Shore",
    "sg:classifiers":[
        {
            "category":"Professional",
            "subcategory":"Computer Services",
            "type":"Services"
        }
    ],
    "sg:phone":"+1 631 969 9235",
    "sg:postcode":"11706",
    "sg:province":"NY",
    "sg:tags":[
        "stereo",
        "installation"
    ],
    "wof:name":"Circuit City",
    "wof:placetype":"venue"
},
  "geometry": {"coordinates":[-73.24700199999999,40.736],"type":"Point"}
}