{
  "type": "Feature",
  "properties": {
    "iso:country":"US",
    "sg:address":"3124 Perry Ave",
    "sg:city":"Bronx",
    "sg:classifiers":[
        {
            "category":"Food & Beverages",
            "subcategory":"Meat & Fish",
            "type":"Retail Goods"
        }
    ],
    "sg:phone":"+1   ",
    "sg:postcode":"10467",
    "sg:province":"NY",
    "wof:name":"Shobuge Bangla",
    "wof:placetype":"venue"
},
  "geometry": {"coordinates":[-73.877708,40.873769],"type":"Point"}
}