{
  "type": "Feature",
  "properties": {
    "addr:full":"10 Laura Ct Mount Sinai NY 11766",
    "addr:housenumber":"10",
    "addr:postcode":"11766",
    "addr:street":"Laura Ct",
    "iso:country":"US",
    "sg:address":"10 Laura Ct",
    "sg:city":"Mount Sinai",
    "sg:classifiers":[
        {
            "category":"Building & Trades",
            "subcategory":"Construction",
            "type":"Services"
        }
    ],
    "sg:phone":"+1 631 331 5547",
    "sg:postcode":"11766",
    "sg:province":"NY",
    "sg:tags":[
        "painter"
    ],
    "wof:name":"Touch of Class Painting & Paper Hanging",
    "wof:placetype":"venue"
},
  "geometry": {"coordinates":[-73.00749999999999,40.934898],"type":"Point"}
}