{
  "type": "Feature",
  "properties": {
    "addr:full":"5 Michael Ln New Hyde Park NY 11040",
    "addr:housenumber":"5",
    "addr:postcode":"11040",
    "addr:street":"Michael Ln",
    "iso:country":"US",
    "sg:address":"5 Michael Ln",
    "sg:city":"New Hyde Park",
    "sg:classifiers":[
        {
            "category":"Professional",
            "subcategory":"Accounting & Tax Preparation",
            "type":"Services"
        }
    ],
    "sg:phone":"+1 516 488 0290",
    "sg:postcode":"11040",
    "sg:province":"NY",
    "sg:tags":[
        "accountant"
    ],
    "wof:name":"Parnes Michael H CPA",
    "wof:placetype":"venue"
},
  "geometry": {"coordinates":[-73.696198,40.743099],"type":"Point"}
}