{
  "type": "Feature",
  "properties": {
    "iso:country":"US",
    "sg:address":"8163 Gore Rd",
    "sg:city":"Rome",
    "sg:classifiers":[
        {
            "category":"Organizations",
            "subcategory":"Non-profit Organization",
            "type":"Services"
        }
    ],
    "sg:phone":"+1 315 337 1034",
    "sg:postcode":"13440",
    "sg:province":"NY",
    "wof:name":"Rome Day Svc",
    "wof:placetype":"venue"
},
  "geometry": {"coordinates":[-75.530046,43.264415],"type":"Point"}
}