{
  "type": "Feature",
  "properties": {
    "iso:country":"US",
    "sg:address":"55 Lincoln Ave",
    "sg:city":"Johnson City",
    "sg:classifiers":[
        {
            "category":"Organizations",
            "subcategory":"Religious Organization",
            "type":"Services"
        }
    ],
    "sg:phone":"+1 607 798 0614",
    "sg:postcode":"13790",
    "sg:province":"NY",
    "sg:tags":[
        "clergy"
    ],
    "wof:name":"Carl Lewis",
    "wof:placetype":"venue"
},
  "geometry": {"coordinates":[-75.951081,42.107659],"type":"Point"}
}