{
  "type": "Feature",
  "properties": {
    "addr:full":"100 S Shore Dr Clayton NY 13624",
    "addr:housenumber":"100",
    "addr:postcode":"13624",
    "addr:street":"S Shore Dr",
    "iso:country":"US",
    "sg:address":"100 S Shore Dr",
    "sg:city":"Clayton",
    "sg:classifiers":[
        {
            "category":"Professional",
            "subcategory":"Accounting & Tax Preparation",
            "type":"Services"
        }
    ],
    "sg:phone":"+1 315 686 9807",
    "sg:postcode":"13624",
    "sg:province":"NY",
    "sg:tags":[
        "return",
        "filing"
    ],
    "wof:name":"Myron G Butler",
    "wof:placetype":"venue"
},
  "geometry": {"coordinates":[-76.099746,44.234245],"type":"Point"}
}