{
  "type": "Feature",
  "properties": {
    "addr:full":"340 E 49th St New York NY 10017",
    "addr:housenumber":"340",
    "addr:postcode":"10017",
    "addr:street":"E 49Th St",
    "iso:country":"US",
    "sg:address":"340 E 49th St",
    "sg:city":"New York",
    "sg:classifiers":[
        {
            "category":"Health Services",
            "subcategory":"Doctor",
            "type":"Services"
        }
    ],
    "sg:phone":"+1 212 751 5414",
    "sg:postcode":"10017",
    "sg:province":"NY",
    "sg:tags":[
        "ophthalmologist",
        "medical",
        "surgeon",
        "physician"
    ],
    "wof:name":"Susan G Margolis, MD PC",
    "wof:placetype":"venue"
},
  "geometry": {"coordinates":[-73.967434,40.753584],"type":"Point"}
}