{
  "type": "Feature",
  "properties": {
    "iso:country":"US",
    "sg:address":"26 Court St",
    "sg:city":"Canton",
    "sg:classifiers":[
        {
            "category":"Local Transit",
            "type":"Transportation"
        }
    ],
    "sg:phone":"+1   ",
    "sg:postcode":"13617",
    "sg:province":"NY",
    "sg:tags":[
        "bus",
        "line"
    ],
    "wof:name":"Adirondack Trailways",
    "wof:placetype":"venue"
},
  "geometry": {"coordinates":[-75.169301,44.596165],"type":"Point"}
}