{
  "type": "Feature",
  "properties": {
    "iso:country":"US",
    "sg:address":"121 E 24th St",
    "sg:city":"New York",
    "sg:classifiers":[
        {
            "category":"Building & Trades",
            "subcategory":"Construction",
            "type":"Services"
        },
        {
            "category":"Professional",
            "subcategory":"Management & Consulting",
            "type":"Services"
        }
    ],
    "sg:phone":"+1 212 674 4151",
    "sg:postcode":"10010",
    "sg:province":"NY",
    "sg:tags":[
        "general",
        "contractor"
    ],
    "sg:website":"www.ameribuild.com",
    "wof:name":"Ameribuild Construction Mgmt",
    "wof:placetype":"venue"
},
  "geometry": {"coordinates":[-73.98499099999999,40.740663],"type":"Point"}
}