{
  "type": "Feature",
  "properties": {
    "addr:full":"500 Rushmore Ave Mamaroneck NY 10543",
    "addr:housenumber":"500",
    "addr:postcode":"10543",
    "addr:street":"Rushmore Ave",
    "iso:country":"US",
    "sg:address":"500 Rushmore Ave",
    "sg:city":"Mamaroneck",
    "sg:classifiers":[
        {
            "category":"Recreation",
            "subcategory":"Marina",
            "type":"Entertainment"
        }
    ],
    "sg:phone":"+1 914 698 6065",
    "sg:postcode":"10543",
    "sg:province":"NY",
    "sg:tags":[
        "repair",
        "operation"
    ],
    "wof:name":"Nichols Yacht Yards Inc",
    "wof:placetype":"venue"
},
  "geometry": {"coordinates":[-73.732585,40.940767],"type":"Point"}
}