{
  "type": "Feature",
  "properties": {
    "iso:country":"US",
    "sg:address":"712 9th Ave",
    "sg:city":"New York",
    "sg:classifiers":[
        {
            "category":"Building & Trades",
            "subcategory":"Locksmith",
            "type":"Services"
        }
    ],
    "sg:phone":"+1 646 720 7138",
    "sg:postcode":"10019",
    "sg:province":"NY",
    "sg:tags":[
        "key"
    ],
    "wof:name":"0 1 Al L O C K Smith",
    "wof:placetype":"venue"
},
  "geometry": {"coordinates":[-73.989392,40.76257],"type":"Point"}
}