{
  "type": "Feature",
  "properties": {
    "iso:country":"US",
    "sg:address":"181 Center St",
    "sg:city":"Ithaca",
    "sg:classifiers":[
        {
            "category":"Retail",
            "subcategory":"Veterinary Services",
            "type":"Services"
        }
    ],
    "sg:phone":"+1 607 253 3404",
    "sg:postcode":"14850",
    "sg:province":"NY",
    "wof:name":"Cornell Veterinary College",
    "wof:placetype":"venue"
},
  "geometry": {"coordinates":[-76.5021,42.435492],"type":"Point"}
}