{
  "type": "Feature",
  "properties": {
    "iso:country":"US",
    "sg:address":"33 Winkle Point Dr",
    "sg:city":"Northport",
    "sg:classifiers":[
        {
            "category":"Manufacturing",
            "subcategory":"Leather Goods",
            "type":"Manufacturing & Wholesale Goods"
        }
    ],
    "sg:phone":"+1 631 912 9210",
    "sg:postcode":"11768",
    "sg:province":"NY",
    "wof:name":"Bosselli Studio",
    "wof:placetype":"venue"
},
  "geometry": {"coordinates":[-73.394096,40.929501],"type":"Point"}
}