{
  "type": "Feature",
  "properties": {
    "addr:full":"60-02 Laurel Hill Blvd Woodside NY 11377",
    "addr:housenumber":"60-02",
    "addr:postcode":"11377",
    "addr:street":"Laurel Hill Blvd",
    "iso:country":"US",
    "sg:address":"60-02 Laurel Hill Blvd",
    "sg:city":"Woodside",
    "sg:classifiers":[
        {
            "category":"Landmark",
            "subcategory":"Historic",
            "type":"Public Place"
        }
    ],
    "sg:postcode":"11377",
    "sg:province":"NY",
    "sg:tags":[
        "building",
        "historical"
    ],
    "sg:website":"718-786-8000",
    "wof:name":"New Calvary Cemetery",
    "wof:placetype":"venue"
},
  "geometry": {"coordinates":[-73.904618,40.73763],"type":"Point"}
}