{
  "type": "Feature",
  "properties": {
    "iso:country":"US",
    "sg:address":"4906 16th Ave",
    "sg:city":"Brooklyn",
    "sg:classifiers":[
        {
            "category":"Shopping",
            "subcategory":"Clothing, Apparel, & Fashions",
            "type":"Retail Goods"
        }
    ],
    "sg:phone":"+1 718 851 5819",
    "sg:postcode":"11204",
    "sg:province":"NY",
    "sg:tags":[
        "store"
    ],
    "wof:name":"Zoldan's For Men & Boys",
    "wof:placetype":"venue"
},
  "geometry": {"coordinates":[-73.986125,40.630559],"type":"Point"}
}