{
  "type": "Feature",
  "properties": {
    "addr:full":"542 6th St Niagara Falls NY 14301",
    "addr:housenumber":"542",
    "addr:postcode":"14301",
    "addr:street":"6Th St",
    "iso:country":"US",
    "sg:address":"542 6th St",
    "sg:city":"Niagara Falls",
    "sg:classifiers":[
        {
            "category":"Building & Trades",
            "subcategory":"Construction",
            "type":"Services"
        }
    ],
    "sg:phone":"+1 716 278 0288",
    "sg:postcode":"14301",
    "sg:province":"NY",
    "sg:tags":[
        "general",
        "contractor"
    ],
    "wof:name":"Calamar Construction",
    "wof:placetype":"venue"
},
  "geometry": {"coordinates":[-79.05560800000001,43.091998],"type":"Point"}
}