{
  "type": "Feature",
  "properties": {
    "iso:country":"US",
    "sg:address":"638 West End Ave",
    "sg:city":"New York",
    "sg:classifiers":[
        {
            "category":"Professional",
            "subcategory":"Art Services",
            "type":"Services"
        }
    ],
    "sg:phone":"+1 646 707 3479",
    "sg:postcode":"10184",
    "sg:province":"NY",
    "sg:tags":[
        "graphic",
        "design"
    ],
    "sg:website":"www.emtmarketing.com",
    "wof:name":"Efficient Marketing Tools",
    "wof:placetype":"venue"
},
  "geometry": {"coordinates":[-73.97534400000001,40.791865],"type":"Point"}
}