{
  "type": "Feature",
  "properties": {
    "addr:full":"230 S Dunton Ave Patchogue NY 11772",
    "addr:housenumber":"230",
    "addr:postcode":"11772",
    "addr:street":"S Dunton Ave",
    "iso:country":"US",
    "sg:address":"230 S Dunton Ave",
    "sg:city":"Patchogue",
    "sg:classifiers":[
        {
            "category":"Building & Trades",
            "subcategory":"Landscaping Services",
            "type":"Services"
        }
    ],
    "sg:phone":"+1 631 207 5921",
    "sg:postcode":"11772",
    "sg:province":"NY",
    "wof:name":"A & B Ground Force",
    "wof:placetype":"venue"
},
  "geometry": {"coordinates":[-72.96772199999999,40.750315],"type":"Point"}
}