{
  "type": "Feature",
  "properties": {
    "iso:country":"US",
    "sg:address":"1 Columbia St",
    "sg:city":"Poughkeepsie",
    "sg:classifiers":[
        {
            "category":"Professional",
            "type":"Services"
        }
    ],
    "sg:phone":"+1 845 454 1005",
    "sg:postcode":"12601",
    "sg:province":"NY",
    "sg:tags":[
        "establishment"
    ],
    "wof:name":"MDS Hudson Valley",
    "wof:placetype":"venue"
},
  "geometry": {"coordinates":[-73.936459,41.695876],"type":"Point"}
}