{
  "type": "Feature",
  "properties": {
    "addr:full":"24 Hickory Cir Staten Island NY 10312",
    "addr:housenumber":"24",
    "addr:postcode":"10312",
    "addr:street":"Hickory Cir",
    "iso:country":"US",
    "sg:address":"24 Hickory Cir",
    "sg:city":"Staten Island",
    "sg:classifiers":[
        {
            "category":"Professional",
            "subcategory":"Business Services",
            "type":"Services"
        }
    ],
    "sg:phone":"+1 718 745 1034",
    "sg:postcode":"10312",
    "sg:province":"NY",
    "wof:name":"Nyc Computerguy LLC",
    "wof:placetype":"venue"
},
  "geometry": {"coordinates":[-74.192139,40.551836],"type":"Point"}
}