{
  "type": "Feature",
  "properties": {
    "iso:country":"US",
    "sg:address":"711 Edgecreek Trl",
    "sg:city":"Rochester",
    "sg:classifiers":[
        {
            "category":"Shopping",
            "subcategory":"Clothing, Apparel, & Fashions",
            "type":"Retail Goods"
        }
    ],
    "sg:phone":"+1   ",
    "sg:postcode":"14609",
    "sg:province":"NY",
    "wof:name":"Twiggie",
    "wof:placetype":"venue"
},
  "geometry": {"coordinates":[-77.54539,43.189752],"type":"Point"}
}