{
  "type": "Feature",
  "properties": {
    "iso:country":"US",
    "sg:address":"4086 Nesconset Hwy",
    "sg:city":"East Setauket",
    "sg:classifiers":[
        {
            "category":"Wholesale",
            "subcategory":"Machinery & Supplies",
            "type":"Manufacturing & Wholesale Goods"
        }
    ],
    "sg:phone":"+1 631 474 8808",
    "sg:postcode":"11733",
    "sg:province":"NY",
    "sg:tags":[
        "salon",
        "beauty"
    ],
    "wof:name":"Sally Beauty Supply",
    "wof:placetype":"venue"
},
  "geometry": {"coordinates":[-73.06996599999999,40.906115],"type":"Point"}
}