{
  "type": "Feature",
  "properties": {
    "iso:country":"US",
    "sg:address":"34 W 38th St Fl 5",
    "sg:city":"New York",
    "sg:classifiers":[
        {
            "category":"Education",
            "subcategory":"School",
            "type":"Public Place"
        }
    ],
    "sg:phone":"+1 212 764 4955",
    "sg:postcode":"10018",
    "sg:province":"NY",
    "sg:website":"www.mediatrainingworldwide.com",
    "wof:name":"Media Training Worldwide",
    "wof:placetype":"venue"
},
  "geometry": {"coordinates":[-73.98446,40.751441],"type":"Point"}
}