{
  "type": "Feature",
  "properties": {
    "addr:full":"542 Route 25A Saint James NY 11780",
    "addr:housenumber":"542",
    "addr:postcode":"11780",
    "addr:street":"Route 25A",
    "iso:country":"US",
    "sg:address":"542 Route 25A",
    "sg:city":"Saint James",
    "sg:classifiers":[
        {
            "category":"Professional",
            "subcategory":"Lawyer & Legal Services",
            "type":"Services"
        }
    ],
    "sg:phone":"+1 631 360 7272",
    "sg:postcode":"11780",
    "sg:province":"NY",
    "wof:name":"Fitzgerald Kevin J Atty",
    "wof:placetype":"venue"
},
  "geometry": {"coordinates":[-73.16239899999999,40.884998],"type":"Point"}
}