{
  "type": "Feature",
  "properties": {
    "addr:full":"62 Millpond Pkwy Monroe NY 10950",
    "addr:housenumber":"62",
    "addr:postcode":"10950",
    "addr:street":"Millpond Pkwy",
    "iso:country":"US",
    "sg:address":"62 Millpond Pkwy",
    "sg:city":"Monroe",
    "sg:classifiers":[
        {
            "category":"Personal",
            "subcategory":"Barber",
            "type":"Services"
        }
    ],
    "sg:phone":"+1 845 782 2283",
    "sg:postcode":"10950",
    "sg:province":"NY",
    "wof:name":"Millpond Barber Shop",
    "wof:placetype":"venue"
},
  "geometry": {"coordinates":[-74.19155600000001,41.333561],"type":"Point"}
}