{
  "type": "Feature",
  "properties": {
    "iso:country":"US",
    "sg:address":"250 Veterans Hwy",
    "sg:city":"Hauppauge",
    "sg:classifiers":[
        {
            "category":"Government",
            "subcategory":"Office",
            "type":"Public Place"
        }
    ],
    "sg:phone":"+1 631 952 6579",
    "sg:postcode":"11788",
    "sg:province":"NY",
    "sg:tags":[
        "state",
        "inspection"
    ],
    "sg:website":"www.dos.state.ny.us",
    "wof:name":"State Dept-Licensing Svc",
    "wof:placetype":"venue"
},
  "geometry": {"coordinates":[-73.219021,40.824512],"type":"Point"}
}