{
  "type": "Feature",
  "properties": {
    "addr:full":"1048 Sheridan Ave Apt 2C Bronx NY 10456",
    "addr:housenumber":"1048",
    "addr:postcode":"10456",
    "addr:street":"Sheridan Ave Apt 2C",
    "iso:country":"US",
    "sg:address":"1048 Sheridan Ave Apt 2C",
    "sg:city":"Bronx",
    "sg:classifiers":[
        {
            "category":"Health Services",
            "subcategory":"Podiatrist",
            "type":"Services"
        }
    ],
    "sg:phone":"+1 718 590 1366",
    "sg:postcode":"10456",
    "sg:province":"NY",
    "sg:tags":[
        "equipment",
        "supply"
    ],
    "wof:name":"Sam S Medical Supply Inc",
    "wof:placetype":"venue"
},
  "geometry": {"coordinates":[-73.918729,40.830701],"type":"Point"}
}