{
  "type": "Feature",
  "properties": {
    "addr:full":"2880 W Lake Rd Wilson NY 14172",
    "addr:housenumber":"2880",
    "addr:postcode":"14172",
    "addr:street":"W Lake Rd",
    "iso:country":"US",
    "sg:address":"2880 W Lake Rd",
    "sg:city":"Wilson",
    "sg:classifiers":[
        {
            "category":"Utilities",
            "subcategory":"Electric",
            "type":"Services"
        }
    ],
    "sg:phone":"+1 716 751 6187",
    "sg:postcode":"14172",
    "sg:province":"NY",
    "sg:tags":[
        "equipment-repair"
    ],
    "wof:name":"Geh Electronics",
    "wof:placetype":"venue"
},
  "geometry": {"coordinates":[-78.884248,43.302321],"type":"Point"}
}