{
  "type": "Feature",
  "properties": {
    "addr:full":"1383 Wayneport Rd Macedon NY 14502",
    "addr:housenumber":"1383",
    "addr:postcode":"14502",
    "addr:street":"Wayneport Rd",
    "iso:country":"US",
    "sg:address":"1383 Wayneport Rd",
    "sg:city":"Macedon",
    "sg:classifiers":[
        {
            "category":"Retail",
            "subcategory":"Animal Services",
            "type":"Services"
        }
    ],
    "sg:phone":"+1 315 986 3934",
    "sg:postcode":"14502",
    "sg:province":"NY",
    "wof:name":"Tail Waggers Kennel",
    "wof:placetype":"venue"
},
  "geometry": {"coordinates":[-77.361065,43.062397],"type":"Point"}
}