{
  "type": "Feature",
  "properties": {
    "addr:full":"1 Hudson Ter Dobbs Ferry NY 10522",
    "addr:housenumber":"1",
    "addr:postcode":"10522",
    "addr:street":"Hudson Ter;Ferry",
    "iso:country":"US",
    "sg:address":"1 Hudson Ter",
    "sg:city":"Dobbs Ferry",
    "sg:classifiers":[
        {
            "category":"Professional",
            "subcategory":"Management & Consulting",
            "type":"Services"
        }
    ],
    "sg:phone":"+1 914 674 2257",
    "sg:postcode":"10522",
    "sg:province":"NY",
    "sg:tags":[
        "consultant"
    ],
    "wof:name":"TLS Consulting",
    "wof:placetype":"venue"
},
  "geometry": {"coordinates":[-73.87713599999999,41.013463],"type":"Point"}
}