{
  "type": "Feature",
  "properties": {
    "addr:full":"6379 Wolcottsville Rd Akron NY 14001",
    "addr:housenumber":"6379",
    "addr:postcode":"14001",
    "addr:street":"Wolcottsville Rd",
    "iso:country":"US",
    "sg:address":"6379 Wolcottsville Rd",
    "sg:city":"Akron",
    "sg:classifiers":[
        {
            "category":"Place Of Worship",
            "subcategory":"Church",
            "type":"Public Place"
        },
        {
            "category":"Place Of Worship",
            "type":"Public Place"
        }
    ],
    "sg:phone":"+1 716 542 2886",
    "sg:postcode":"14001",
    "sg:province":"NY",
    "sg:tags":[
        "lutheran",
        "america",
        "churches-lutheran",
        "churches-lutheran-evangelical"
    ],
    "wof:name":"Saint Michaels Lutheran Church",
    "wof:placetype":"venue"
},
  "geometry": {"coordinates":[-78.51786,43.11227],"type":"Point"}
}