{
  "type": "Feature",
  "properties": {
    "addr:full":"1 Jericho Tpke Floral Park NY 11001",
    "addr:housenumber":"1",
    "addr:postcode":"11001",
    "addr:street":"Jericho Tpke",
    "iso:country":"US",
    "sg:address":"1 Jericho Tpke",
    "sg:city":"Floral Park",
    "sg:classifiers":[
        {
            "category":"Autos & Motor Vehicles",
            "subcategory":"Automobile Sales",
            "type":"Retail Goods"
        },
        {
            "category":"Retail",
            "subcategory":"Auto Repair",
            "type":"Services"
        }
    ],
    "sg:phone":"+1 718 343 2244",
    "sg:postcode":"11001",
    "sg:province":"NY",
    "sg:tags":[
        "body",
        "shop",
        "car"
    ],
    "wof:name":"G C Volkswagen",
    "wof:placetype":"venue"
},
  "geometry": {"coordinates":[-73.707703,40.728001],"type":"Point"}
}