{
  "type": "Feature",
  "properties": {
    "addr:full":"965 Lexington Ave New York NY 10021",
    "addr:housenumber":"965",
    "addr:postcode":"10021",
    "addr:street":"Lexington Ave",
    "iso:country":"US",
    "sg:address":"965 Lexington Ave",
    "sg:city":"New York",
    "sg:classifiers":[
        {
            "category":"Retail",
            "subcategory":"Repair Shop",
            "type":"Services"
        }
    ],
    "sg:phone":"+1 212 903 0430",
    "sg:postcode":"10021",
    "sg:province":"NY",
    "sg:tags":[
        "lock",
        "locksmith"
    ],
    "wof:name":"24 Hour 7 Day Emergency Towing",
    "wof:placetype":"venue"
},
  "geometry": {"coordinates":[-73.962673,40.76964],"type":"Point"}
}