{
  "type": "Feature",
  "properties": {
    "iso:country":"US",
    "sg:address":"8122 Transit Rd",
    "sg:city":"Buffalo",
    "sg:classifiers":[
        {
            "category":"Utilities",
            "subcategory":"Mobile Phone",
            "type":"Services"
        }
    ],
    "sg:phone":"+1 716 689 6250",
    "sg:postcode":"14221",
    "sg:province":"NY",
    "sg:tags":[
        "telephone",
        "cellular"
    ],
    "wof:name":"Nextel Retail",
    "wof:placetype":"venue"
},
  "geometry": {"coordinates":[-78.697017,42.992546],"type":"Point"}
}