{
  "type": "Feature",
  "properties": {
    "addr:full":"190 W Montauk Hwy Hampton Bays NY 11946",
    "addr:housenumber":"190",
    "addr:postcode":"11946",
    "addr:street":"W Montauk Hwy",
    "iso:country":"US",
    "sg:address":"190 W Montauk Hwy",
    "sg:city":"Hampton Bays",
    "sg:classifiers":[
        {
            "category":"Restaurant",
            "type":"Food & Drink"
        }
    ],
    "sg:phone":"+1 631 728 3700",
    "sg:postcode":"11946",
    "sg:province":"NY",
    "sg:tags":[
        "pizza"
    ],
    "wof:name":"Michelangelo Pizzeria & Rstrnt",
    "wof:placetype":"venue"
},
  "geometry": {"coordinates":[-72.539186,40.872568],"type":"Point"}
}