{
  "type": "Feature",
  "properties": {
    "addr:full":"3046 Hempstead Tpke Levittown NY 11756",
    "addr:housenumber":"3046",
    "addr:postcode":"11756",
    "addr:street":"Hempstead Tpke",
    "iso:country":"US",
    "sg:address":"3046 Hempstead Tpke",
    "sg:city":"Levittown",
    "sg:classifiers":[
        {
            "category":"Restaurant",
            "type":"Food & Drink"
        }
    ],
    "sg:phone":"+1 516 731 5711",
    "sg:postcode":"11756",
    "sg:province":"NY",
    "wof:name":"Nathan Famous Inc",
    "wof:placetype":"venue"
},
  "geometry": {"coordinates":[-73.523697,40.724602],"type":"Point"}
}