{
  "type": "Feature",
  "properties": {
    "addr:full":"11 A Cline Rd Binghamton NY 13903",
    "addr:housenumber":"11",
    "addr:postcode":"13903",
    "addr:street":"A Cline Rd",
    "iso:country":"US",
    "sg:address":"11 A Cline Rd",
    "sg:city":"Binghamton",
    "sg:classifiers":[
        {
            "category":"Recreation",
            "type":"Entertainment"
        }
    ],
    "sg:phone":"+1   ",
    "sg:postcode":"13903",
    "sg:province":"NY",
    "wof:name":"Crooked Creek Farm",
    "wof:placetype":"venue"
},
  "geometry": {"coordinates":[-75.878023,42.003519],"type":"Point"}
}