{
  "type": "Feature",
  "properties": {
    "addr:full":"700 5th Ave 23rd Fl New York NY 10019",
    "addr:housenumber":"700",
    "addr:postcode":"10019",
    "addr:street":"5Th Ave",
    "iso:country":"US",
    "sg:address":"700 5th Ave 23rd Fl",
    "sg:city":"New York",
    "sg:classifiers":[
        {
            "category":"Bars & Pubs",
            "subcategory":"Lounge",
            "type":"Food & Drink"
        }
    ],
    "sg:phone":"+1 212 956 2888",
    "sg:postcode":"10019",
    "sg:province":"NY",
    "sg:website":"newyork.peninsula.com/pny/dining...",
    "wof:name":"Salon de Ning",
    "wof:placetype":"venue"
},
  "geometry": {"coordinates":[-73.974873,40.761695],"type":"Point"}
}