{
  "type": "Feature",
  "properties": {
    "addr:full":"5 Nancy Pl Bronxville NY 10708",
    "addr:housenumber":"5",
    "addr:postcode":"10708",
    "addr:street":"Nancy Pl",
    "iso:country":"US",
    "sg:address":"5 Nancy Pl",
    "sg:city":"Bronxville",
    "sg:classifiers":[
        {
            "category":"Shopping",
            "subcategory":"Clothing, Apparel, & Fashions",
            "type":"Retail Goods"
        }
    ],
    "sg:phone":"+1   ",
    "sg:postcode":"10708",
    "sg:province":"NY",
    "wof:name":"Up Front Axle Corp",
    "wof:placetype":"venue"
},
  "geometry": {"coordinates":[-73.81466399999999,40.93094],"type":"Point"}
}