{
  "type": "Feature",
  "properties": {
    "iso:country":"US",
    "sg:address":"236 Perinton Pkwy",
    "sg:city":"Fairport",
    "sg:classifiers":[
        {
            "category":"Manufacturing",
            "subcategory":"Retail Goods",
            "type":"Manufacturing & Wholesale Goods"
        },
        {
            "category":"Manufacturing",
            "subcategory":"Rubber & Plastics",
            "type":"Manufacturing & Wholesale Goods"
        }
    ],
    "sg:phone":"+1 585 421 1500",
    "sg:postcode":"14450",
    "sg:province":"NY",
    "sg:tags":[
        "product",
        "manufacturer",
        "mfg"
    ],
    "wof:name":"Moll Industries Inc",
    "wof:placetype":"venue"
},
  "geometry": {"coordinates":[-77.392437,43.091184],"type":"Point"}
}