{
  "type": "Feature",
  "properties": {
    "addr:full":"320 Park St Sherrill NY 13461",
    "addr:housenumber":"320",
    "addr:postcode":"13461",
    "addr:street":"Park St",
    "iso:country":"US",
    "sg:address":"320 Park St",
    "sg:city":"Sherrill",
    "sg:classifiers":[
        {
            "category":"Social Services",
            "subcategory":"Child Care",
            "type":"Services"
        }
    ],
    "sg:phone":"+1 315 366 3417",
    "sg:postcode":"13461",
    "sg:province":"NY",
    "sg:tags":[
        "kindergarten",
        "academic",
        "school"
    ],
    "wof:name":"Cornue's Children's Corner",
    "wof:placetype":"venue"
},
  "geometry": {"coordinates":[-75.59860999999999,43.069409],"type":"Point"}
}