{
  "type": "Feature",
  "properties": {
    "addr:full":"151 S Main St New City NY 10956",
    "addr:housenumber":"151",
    "addr:postcode":"10956",
    "addr:street":"S Main St",
    "iso:country":"US",
    "sg:address":"151 S Main St",
    "sg:city":"New City",
    "sg:classifiers":[
        {
            "category":"Professional",
            "subcategory":"Lawyer & Legal Services",
            "type":"Services"
        }
    ],
    "sg:phone":"+1 845 639 3470",
    "sg:postcode":"10956",
    "sg:province":"NY",
    "sg:tags":[
        "attorney"
    ],
    "wof:name":"Larry Gantt & Assoc",
    "wof:placetype":"venue"
},
  "geometry": {"coordinates":[-73.990398,41.142418],"type":"Point"}
}