{
  "type": "Feature",
  "properties": {
    "iso:country":"US",
    "sg:address":"1155 Avenue of the Americas Fl 5",
    "sg:city":"New York",
    "sg:classifiers":[
        {
            "category":"Banks & Credit Unions",
            "subcategory":"Investment Brokerage",
            "type":"Services"
        }
    ],
    "sg:phone":"+1 212 597 5600",
    "sg:postcode":"10036",
    "sg:province":"NY",
    "sg:tags":[
        "investing"
    ],
    "wof:name":"Dow Jones and Co Inc",
    "wof:placetype":"venue"
},
  "geometry": {"coordinates":[-73.983346,40.756617],"type":"Point"}
}