{
  "type": "Feature",
  "properties": {
    "iso:country":"US",
    "sg:address":"180 E Main St",
    "sg:city":"Gouverneur",
    "sg:classifiers":[
        {
            "category":"Banks & Credit Unions",
            "subcategory":"Investment Brokerage",
            "type":"Services"
        }
    ],
    "sg:phone":"+1 315 287 0136",
    "sg:postcode":"13642",
    "sg:province":"NY",
    "sg:tags":[
        "tape",
        "video",
        "sale",
        "dvds-rental"
    ],
    "wof:name":"Movie Gallery",
    "wof:placetype":"venue"
},
  "geometry": {"coordinates":[-75.463303,44.336781],"type":"Point"}
}