{
  "type": "Feature",
  "properties": {
    "iso:country":"US",
    "sg:address":"6448 Grimble Rd",
    "sg:city":"Canandaigua",
    "sg:classifiers":[
        {
            "category":"Retail",
            "subcategory":"Repair Shop",
            "type":"Services"
        }
    ],
    "sg:phone":"+1 585 657 6103",
    "sg:postcode":"14424",
    "sg:province":"NY",
    "sg:tags":[
        "taxidermist"
    ],
    "wof:name":"Custom Taxidermy-Phil Hershey",
    "wof:placetype":"venue"
},
  "geometry": {"coordinates":[-77.379445,42.862361],"type":"Point"}
}