{
  "type": "Feature",
  "properties": {
    "iso:country":"US",
    "sg:address":"3910 Buffalo Rd",
    "sg:city":"Rochester",
    "sg:classifiers":[
        {
            "category":"Education",
            "subcategory":"Dance Studio",
            "type":"Public Place"
        }
    ],
    "sg:phone":"+1 585 594 3455",
    "sg:postcode":"14624",
    "sg:province":"NY",
    "sg:tags":[
        "instruction",
        "dancing"
    ],
    "wof:name":"Allstar Dance Academy",
    "wof:placetype":"venue"
},
  "geometry": {"coordinates":[-77.769734,43.137025],"type":"Point"}
}