{
  "type": "Feature",
  "properties": {
    "addr:full":"235 8th Avenue New York NY 10011",
    "addr:housenumber":"235",
    "addr:postcode":"10011",
    "addr:street":"8Th Avenue",
    "iso:country":"US",
    "sg:address":"235 8th Avenue",
    "sg:city":"New York",
    "sg:classifiers":[
        {
            "category":"Arts & Performance",
            "subcategory":"Art Gallery",
            "type":"Entertainment"
        }
    ],
    "sg:phone":"+1 646 486 3781",
    "sg:postcode":"10011",
    "sg:province":"NY",
    "wof:name":"Av Art Gallery & Custom Framing",
    "wof:placetype":"venue"
},
  "geometry": {"coordinates":[-73.999157,40.744575],"type":"Point"}
}