{
  "type": "Feature",
  "properties": {
    "addr:full":"119 S Pearl St Pearl River NY 10965",
    "addr:housenumber":"119",
    "addr:postcode":"10965",
    "addr:street":"S Pearl St",
    "iso:country":"US",
    "sg:address":"119 S Pearl St",
    "sg:city":"Pearl River",
    "sg:classifiers":[
        {
            "category":"Health Services",
            "subcategory":"Doctor",
            "type":"Services"
        }
    ],
    "sg:phone":"+1 845 735 4100",
    "sg:postcode":"10965",
    "sg:province":"NY",
    "sg:tags":[
        "clinic",
        "medical"
    ],
    "wof:name":"Arthur E Appel MD",
    "wof:placetype":"venue"
},
  "geometry": {"coordinates":[-74.025203,41.053253],"type":"Point"}
}