{
  "type": "Feature",
  "properties": {
    "iso:country":"US",
    "sg:address":"136 Chestnut St",
    "sg:city":"Albany",
    "sg:classifiers":[
        {
            "category":"Professional",
            "subcategory":"Management & Consulting",
            "type":"Services"
        }
    ],
    "sg:phone":"+1 518 436 8110",
    "sg:postcode":"12210",
    "sg:province":"NY",
    "sg:tags":[
        "consultant",
        "business"
    ],
    "wof:name":"Winovia LLC",
    "wof:placetype":"venue"
},
  "geometry": {"coordinates":[-73.764442,42.654964],"type":"Point"}
}