{
  "type": "Feature",
  "properties": {
    "addr:full":"24 E 12th St Ste 601 Manhattan NY 10003",
    "addr:housenumber":"24",
    "addr:postcode":"10003",
    "addr:street":"E 12Th St Ste 601",
    "iso:country":"US",
    "sg:address":"24 E 12th St Ste 601",
    "sg:city":"Manhattan",
    "sg:classifiers":[
        {
            "category":"Health Services",
            "subcategory":"Clinic",
            "type":"Services"
        },
        {
            "category":"Organizations",
            "subcategory":"Non-profit Organization",
            "type":"Services"
        }
    ],
    "sg:phone":"+1 877 733 3769",
    "sg:postcode":"10003",
    "sg:province":"NY",
    "sg:tags":[
        "counseling",
        "community",
        "mental",
        "service/non-profit"
    ],
    "sg:website":"www.nypsychotherapycooperative.com",
    "wof:name":"New York Psychotherapy Cooperative",
    "wof:placetype":"venue"
},
  "geometry": {"coordinates":[-73.993269,40.734024],"type":"Point"}
}