{
  "type": "Feature",
  "properties": {
    "iso:country":"US",
    "sg:address":"175A Main St",
    "sg:city":"Afton",
    "sg:classifiers":[
        {
            "category":"Food & Beverages",
            "subcategory":"Meat & Fish",
            "type":"Retail Goods"
        }
    ],
    "sg:phone":"+1 607 639 1280",
    "sg:postcode":"13730",
    "sg:province":"NY",
    "sg:tags":[
        "market"
    ],
    "wof:name":"Afton Custom Meats",
    "wof:placetype":"venue"
},
  "geometry": {"coordinates":[-75.526212,42.228112],"type":"Point"}
}