{
  "type": "Feature",
  "properties": {
    "addr:full":"48 Redfield Pkwy Batavia NY 14020",
    "addr:housenumber":"48",
    "addr:postcode":"14020",
    "addr:street":"Redfield Pkwy",
    "iso:country":"US",
    "sg:address":"48 Redfield Pkwy",
    "sg:city":"Batavia",
    "sg:classifiers":[
        {
            "category":"Real Estate",
            "subcategory":"Real Estate Agent",
            "type":"Services"
        }
    ],
    "sg:phone":"+1 585 343 7873",
    "sg:postcode":"14020",
    "sg:province":"NY",
    "sg:tags":[
        "inspection"
    ],
    "wof:name":"Dwell Sure Home Inspections",
    "wof:placetype":"venue"
},
  "geometry": {"coordinates":[-78.20096100000001,43.00747],"type":"Point"}
}