{
  "type": "Feature",
  "properties": {
    "addr:full":"17 Flower Ave Floral Park NY 11001",
    "addr:housenumber":"17",
    "addr:postcode":"11001",
    "addr:street":"Flower Ave",
    "iso:country":"US",
    "sg:address":"17 Flower Ave",
    "sg:city":"Floral Park",
    "sg:classifiers":[
        {
            "category":"Building & Trades",
            "subcategory":"Construction",
            "type":"Services"
        }
    ],
    "sg:phone":"+1 516 616 9191",
    "sg:postcode":"11001",
    "sg:province":"NY",
    "sg:tags":[
        "contractor"
    ],
    "wof:name":"Tri State Renovations Inc",
    "wof:placetype":"venue"
},
  "geometry": {"coordinates":[-73.702912,40.727631],"type":"Point"}
}