{
  "type": "Feature",
  "properties": {
    "addr:full":"1122 Westchester Avenue Bronx NY 10459",
    "addr:housenumber":"1122",
    "addr:postcode":"10459",
    "addr:street":"Westchester Avenue",
    "iso:country":"US",
    "sg:address":"1122 Westchester Avenue",
    "sg:city":"Bronx",
    "sg:classifiers":[
        {
            "category":"Shopping",
            "subcategory":"Jewelry",
            "type":"Retail Goods"
        }
    ],
    "sg:phone":"+1 718 842 2322",
    "sg:postcode":"10459",
    "sg:province":"NY",
    "wof:name":"Westchester Jewelry Shop",
    "wof:placetype":"venue"
},
  "geometry": {"coordinates":[-73.890264,40.825631],"type":"Point"}
}