{
  "type": "Feature",
  "properties": {
    "addr:full":"760 New Scotland Ave Albany NY 12208",
    "addr:housenumber":"760",
    "addr:postcode":"12208",
    "addr:street":"New Scotland Ave",
    "iso:country":"US",
    "sg:address":"760 New Scotland Ave",
    "sg:city":"Albany",
    "sg:classifiers":[
        {
            "category":"Organizations",
            "subcategory":"Religious Organization",
            "type":"Services"
        }
    ],
    "sg:phone":"+1 518 482 7998",
    "sg:postcode":"12208",
    "sg:province":"NY",
    "sg:tags":[
        "america",
        "churches-reformed",
        "reformed",
        "church"
    ],
    "wof:name":"Bethany Reformed Church",
    "wof:placetype":"venue"
},
  "geometry": {"coordinates":[-73.812247,42.658928],"type":"Point"}
}