{
  "type": "Feature",
  "properties": {
    "iso:country":"US",
    "sg:address":"300 Dewittshire Rd S",
    "sg:city":"Syracuse",
    "sg:classifiers":[
        {
            "category":"Shopping",
            "subcategory":"Gifts & Souvenirs",
            "type":"Retail Goods"
        }
    ],
    "sg:phone":"+1 315 446 2505",
    "sg:postcode":"13214",
    "sg:province":"NY",
    "sg:tags":[
        "cards",
        "greeting"
    ],
    "wof:name":"Kisses To You Greetings",
    "wof:placetype":"venue"
},
  "geometry": {"coordinates":[-76.066661,43.030925],"type":"Point"}
}