{
  "type": "Feature",
  "properties": {
    "iso:country":"US",
    "sg:address":"349 W Main St",
    "sg:city":"Goshen",
    "sg:classifiers":[
        {
            "category":"Building & Trades",
            "subcategory":"Construction",
            "type":"Services"
        }
    ],
    "sg:phone":"+1 845 294 6990",
    "sg:postcode":"10924",
    "sg:province":"NY",
    "sg:tags":[
        "manufactured",
        "housing-communities"
    ],
    "wof:name":"Thomas S Gerace",
    "wof:placetype":"venue"
},
  "geometry": {"coordinates":[-74.334954,41.399746],"type":"Point"}
}