{
  "type": "Feature",
  "properties": {
    "addr:full":"130 N Bedford Rd Mount Kisco NY 10549",
    "addr:housenumber":"130",
    "addr:postcode":"10549",
    "addr:street":"N Bedford Rd",
    "iso:country":"US",
    "sg:address":"130 N Bedford Rd",
    "sg:city":"Mount Kisco",
    "sg:classifiers":[
        {
            "category":"Food & Beverages",
            "subcategory":"Bakery",
            "type":"Retail Goods"
        }
    ],
    "sg:phone":"+1   ",
    "sg:postcode":"10549",
    "sg:province":"NY",
    "wof:name":"LAnjou Patisserie Francaise",
    "wof:placetype":"venue"
},
  "geometry": {"coordinates":[-73.720219,41.214583],"type":"Point"}
}