{
  "type": "Feature",
  "properties": {
    "addr:full":"100 Mc Guffey Ln Delmar NY 12054",
    "addr:housenumber":"100",
    "addr:postcode":"12054",
    "addr:street":"Mc Guffey Ln",
    "iso:country":"US",
    "sg:address":"100 Mc Guffey Ln",
    "sg:city":"Delmar",
    "sg:classifiers":[
        {
            "category":"Shopping",
            "subcategory":"Clothing, Apparel, & Fashions",
            "type":"Retail Goods"
        }
    ],
    "sg:phone":"+1   ",
    "sg:postcode":"12054",
    "sg:province":"NY",
    "sg:tags":[
        "family"
    ],
    "wof:name":"Bad Dog Products",
    "wof:placetype":"venue"
},
  "geometry": {"coordinates":[-73.823319,42.609881],"type":"Point"}
}