{
  "type": "Feature",
  "properties": {
    "addr:full":"4533 E Henrietta Rd Henrietta NY 14467",
    "addr:housenumber":"4533",
    "addr:postcode":"14467",
    "addr:street":"E Henrietta Rd",
    "iso:country":"US",
    "sg:address":"4533 E Henrietta Rd",
    "sg:city":"Henrietta",
    "sg:classifiers":[
        {
            "category":"Building & Trades",
            "subcategory":"Construction",
            "type":"Services"
        }
    ],
    "sg:phone":"+1 585 334 0161",
    "sg:postcode":"14467",
    "sg:province":"NY",
    "sg:tags":[
        "hanging",
        "contractor"
    ],
    "wof:name":"Neil Gates Painting",
    "wof:placetype":"venue"
},
  "geometry": {"coordinates":[-77.62755,43.031338],"type":"Point"}
}