{
  "type": "Feature",
  "properties": {
    "iso:country":"US",
    "sg:address":"600 Old Country Rd Rm 530",
    "sg:city":"Garden City",
    "sg:classifiers":[
        {
            "category":"Professional",
            "subcategory":"Lawyer & Legal Services",
            "type":"Services"
        }
    ],
    "sg:phone":"+1 516 794 4700",
    "sg:postcode":"11530",
    "sg:province":"NY",
    "wof:name":"Liotti Thomas F Atty",
    "wof:placetype":"venue"
},
  "geometry": {"coordinates":[-73.6241,40.741699],"type":"Point"}
}