{
  "type": "Feature",
  "properties": {
    "iso:country":"US",
    "sg:address":"175 Buckley Rd",
    "sg:city":"Whitehall",
    "sg:classifiers":[
        {
            "category":"Shopping",
            "subcategory":"Used Merchandise",
            "type":"Retail Goods"
        }
    ],
    "sg:phone":"+1 518 499 2799",
    "sg:postcode":"12887",
    "sg:province":"NY",
    "sg:tags":[
        "antique"
    ],
    "wof:name":"Nicholas Auctions",
    "wof:placetype":"venue"
},
  "geometry": {"coordinates":[-73.356348,43.56473],"type":"Point"}
}