{
  "type": "Feature",
  "properties": {
    "iso:country":"US",
    "sg:address":"8 Pleasant St",
    "sg:city":"Potsdam",
    "sg:classifiers":[
        {
            "category":"Retail",
            "subcategory":"Veterinary Services",
            "type":"Services"
        }
    ],
    "sg:phone":"+1 315 265 1615",
    "sg:postcode":"13676",
    "sg:province":"NY",
    "wof:name":"Dr Paul Cole",
    "wof:placetype":"venue"
},
  "geometry": {"coordinates":[-74.98603300000001,44.673046],"type":"Point"}
}