{
  "type": "Feature",
  "properties": {
    "addr:full":"390 Plandome Rd Manhasset NY 11030",
    "addr:housenumber":"390",
    "addr:postcode":"11030",
    "addr:street":"Plandome Rd",
    "iso:country":"US",
    "sg:address":"390 Plandome Rd",
    "sg:city":"Manhasset",
    "sg:classifiers":[
        {
            "category":"Wholesale",
            "subcategory":"Wine & Distilled Alcoholic Beverages",
            "type":"Manufacturing & Wholesale Goods"
        }
    ],
    "sg:phone":"+1 516 365 8002",
    "sg:postcode":"11030",
    "sg:province":"NY",
    "sg:tags":[
        "liquors-wholesale"
    ],
    "wof:name":"Mediterranean Import Co",
    "wof:placetype":"venue"
},
  "geometry": {"coordinates":[-73.699791,40.797829],"type":"Point"}
}