{
  "type": "Feature",
  "properties": {
    "iso:country":"US",
    "sg:address":"67 Mountain View Dr",
    "sg:city":"Pine City",
    "sg:classifiers":[
        {
            "category":"Government",
            "subcategory":"Office",
            "type":"Public Place"
        }
    ],
    "sg:phone":"+1 607 733 5467",
    "sg:postcode":"14871",
    "sg:province":"NY",
    "sg:tags":[
        "village"
    ],
    "wof:name":"Highway Garage",
    "wof:placetype":"venue"
},
  "geometry": {"coordinates":[-76.843388,42.054564],"type":"Point"}
}