{
  "type": "Feature",
  "properties": {
    "addr:full":"6405 Yorktown Cir East Syracuse NY 13057",
    "addr:housenumber":"6405",
    "addr:postcode":"13057",
    "addr:street":"Yorktown Cir",
    "iso:country":"US",
    "sg:address":"6405 Yorktown Cir",
    "sg:city":"East Syracuse",
    "sg:classifiers":[
        {
            "category":"Restaurant",
            "type":"Food & Drink"
        }
    ],
    "sg:menulink":"http://www.allmenus.com/ny/de-witt/103841-ruby-tuesdays/menu/",
    "sg:phone":"+1 315 414 0450",
    "sg:postcode":"13057",
    "sg:province":"NY",
    "sg:tags":[
        "burger",
        "american"
    ],
    "wof:name":"Ruby Tuesdays",
    "wof:placetype":"venue"
},
  "geometry": {"coordinates":[-76.08568,43.09148],"type":"Point"}
}