{
  "type": "Feature",
  "properties": {
    "addr:full":"16 Antwerp St Philadelphia NY 13673",
    "addr:housenumber":"16",
    "addr:postcode":"13673",
    "addr:street":"Antwerp St",
    "iso:country":"US",
    "sg:address":"16 Antwerp St",
    "sg:city":"Philadelphia",
    "sg:classifiers":[
        {
            "category":"Retail",
            "subcategory":"Funeral Services",
            "type":"Services"
        }
    ],
    "sg:phone":"+1 315 642 3413",
    "sg:postcode":"13673",
    "sg:province":"NY",
    "wof:name":"Frederick Brothers Funeral Hm",
    "wof:placetype":"venue"
},
  "geometry": {"coordinates":[-75.70262099999999,44.158635],"type":"Point"}
}