{
  "type": "Feature",
  "properties": {
    "iso:country":"US",
    "sg:address":"308 Merrick Ave",
    "sg:city":"Merrick",
    "sg:classifiers":[
        {
            "category":"Building & Trades",
            "subcategory":"Construction",
            "type":"Services"
        }
    ],
    "sg:phone":"+1 516 867 6021",
    "sg:postcode":"11566",
    "sg:province":"NY",
    "sg:tags":[
        "contractor"
    ],
    "wof:name":"Tosell Construction Corp",
    "wof:placetype":"venue"
},
  "geometry": {"coordinates":[-73.564499,40.693298],"type":"Point"}
}