{
  "type": "Feature",
  "properties": {
    "iso:country":"US",
    "sg:address":"1104 Smithtown Ave",
    "sg:city":"Bohemia",
    "sg:classifiers":[
        {
            "category":"Building & Trades",
            "subcategory":"Plumbing",
            "type":"Services"
        }
    ],
    "sg:phone":"+1 631 589 3260",
    "sg:postcode":"11716",
    "sg:province":"NY",
    "sg:tags":[
        "conditioning",
        "air",
        "system",
        "contractor"
    ],
    "wof:name":"Total Air Comfort Inc",
    "wof:placetype":"venue"
},
  "geometry": {"coordinates":[-73.10909100000001,40.770998],"type":"Point"}
}