{
  "type": "Feature",
  "properties": {
    "iso:country":"US",
    "sg:address":"46-I Gerard St",
    "sg:city":"Huntington",
    "sg:classifiers":[
        {
            "category":"Food & Beverages",
            "subcategory":"Candy",
            "type":"Retail Goods"
        }
    ],
    "sg:phone":"+1 631 683 4100",
    "sg:postcode":"11743",
    "sg:province":"NY",
    "sg:tags":[
        "dessert"
    ],
    "sg:website":"www.cupcakegourmet.com/",
    "wof:name":"Cupcake Gourmet",
    "wof:placetype":"venue"
},
  "geometry": {"coordinates":[-73.42841799999999,40.872116],"type":"Point"}
}