{
  "type": "Feature",
  "properties": {
    "iso:country":"US",
    "sg:address":"100 S Hudson St",
    "sg:city":"Mechanicville",
    "sg:classifiers":[
        {
            "category":"Utilities",
            "subcategory":"Fuel Oil & Lpg",
            "type":"Services"
        }
    ],
    "sg:phone":"+1 518 664 7331",
    "sg:postcode":"12118",
    "sg:province":"NY",
    "sg:tags":[
        "gasoline",
        "dealer",
        "store"
    ],
    "wof:name":"Wever Petroleum Inc",
    "wof:placetype":"venue"
},
  "geometry": {"coordinates":[-73.681563,42.899892],"type":"Point"}
}