{
  "type": "Feature",
  "properties": {
    "addr:full":"10 Stirrup Ln Northport NY 11768",
    "addr:housenumber":"10",
    "addr:postcode":"11768",
    "addr:street":"Stirrup Ln",
    "iso:country":"US",
    "sg:address":"10 Stirrup Ln",
    "sg:city":"Northport",
    "sg:classifiers":[
        {
            "category":"Social Services",
            "type":"Services"
        }
    ],
    "sg:phone":"+1   ",
    "sg:postcode":"11768",
    "sg:province":"NY",
    "wof:name":"Phyllis-Terri Gold",
    "wof:placetype":"venue"
},
  "geometry": {"coordinates":[-73.275283,40.885529],"type":"Point"}
}