{
  "type": "Feature",
  "properties": {
    "iso:country":"US",
    "sg:address":"220 Powell Ave",
    "sg:city":"Newburgh",
    "sg:classifiers":[
        {
            "category":"Health Services",
            "subcategory":"Nursing And Care Facility",
            "type":"Services"
        }
    ],
    "sg:phone":"+1 845 561 2237",
    "sg:postcode":"12550",
    "sg:province":"NY",
    "sg:tags":[
        "home",
        "convalescent"
    ],
    "wof:name":"Nazareth Senior Sisters",
    "wof:placetype":"venue"
},
  "geometry": {"coordinates":[-74.01499,41.510486],"type":"Point"}
}