{
  "type": "Feature",
  "properties": {
    "iso:country":"US",
    "sg:address":"55 Holland Ave",
    "sg:city":"Buffalo",
    "sg:classifiers":[
        {
            "category":"Wholesale",
            "subcategory":"Metals & Minerals",
            "type":"Manufacturing & Wholesale Goods"
        }
    ],
    "sg:phone":"+1 716 655 4992",
    "sg:postcode":"14224",
    "sg:province":"NY",
    "sg:tags":[
        "center"
    ],
    "wof:name":"L J L Associates",
    "wof:placetype":"venue"
},
  "geometry": {"coordinates":[-78.755267,42.837457],"type":"Point"}
}