{
  "type": "Feature",
  "properties": {
    "iso:country":"US",
    "sg:address":"2 Nassau Blvd",
    "sg:city":"Garden City",
    "sg:classifiers":[
        {
            "category":"Shopping",
            "subcategory":"Pharmacy",
            "type":"Retail Goods"
        }
    ],
    "sg:phone":"+1 516 486 1114",
    "sg:postcode":"11530",
    "sg:province":"NY",
    "sg:tags":[
        "pharmaceutical",
        "consultant"
    ],
    "wof:name":"Whelan's Nassau Blvd Pharmacy",
    "wof:placetype":"venue"
},
  "geometry": {"coordinates":[-73.660753,40.71917],"type":"Point"}
}