{
  "type": "Feature",
  "properties": {
    "addr:full":"15 Brower Court Staten Island NY 10308",
    "addr:housenumber":"15",
    "addr:postcode":"10308",
    "addr:street":"Brower Court",
    "iso:country":"US",
    "sg:address":"15 Brower Court",
    "sg:city":"Staten Island",
    "sg:classifiers":[
        {
            "category":"Ice Cream",
            "type":"Food & Drink"
        }
    ],
    "sg:phone":"+1 718 605 0056",
    "sg:postcode":"10308",
    "sg:province":"NY",
    "sg:tags":[
        "frozen",
        "yogurt"
    ],
    "wof:name":"Uncle Louie G's",
    "wof:placetype":"venue"
},
  "geometry": {"coordinates":[-74.15070799999999,40.551038],"type":"Point"}
}