{
  "type": "Feature",
  "properties": {
    "addr:full":"523 W 24th St New York NY 10011",
    "addr:housenumber":"523",
    "addr:postcode":"10011",
    "addr:street":"W 24Th St",
    "iso:country":"US",
    "sg:address":"523 W 24th St",
    "sg:city":"New York",
    "sg:classifiers":[
        {
            "category":"Arts & Performance",
            "subcategory":"Art Gallery",
            "type":"Entertainment"
        }
    ],
    "sg:phone":"+1 212 243 0200",
    "sg:postcode":"10011",
    "sg:province":"NY",
    "sg:website":"www.matthewmarks.com",
    "wof:name":"Matthew Marks Gallery",
    "wof:placetype":"venue"
},
  "geometry": {"coordinates":[-74.00509599999999,40.748798],"type":"Point"}
}