{
  "type": "Feature",
  "properties": {
    "addr:full":"425 Robinson St Binghamton NY 13901",
    "addr:housenumber":"425",
    "addr:postcode":"13901",
    "addr:street":"Robinson St",
    "iso:country":"US",
    "sg:address":"425 Robinson St",
    "sg:city":"Binghamton",
    "sg:classifiers":[
        {
            "category":"Health Services",
            "subcategory":"Hospital",
            "type":"Services"
        }
    ],
    "sg:phone":"+1 607 772 3522",
    "sg:postcode":"13901",
    "sg:province":"NY",
    "sg:tags":[
        "general"
    ],
    "wof:name":"Suny Upstate Medical Univ",
    "wof:placetype":"venue"
},
  "geometry": {"coordinates":[-75.86691999999999,42.108574],"type":"Point"}
}