{
  "type": "Feature",
  "properties": {
    "addr:full":"633 Co Rd 1 Pine Island NY 10969",
    "addr:housenumber":"633;1",
    "addr:postcode":"10969",
    "addr:street":"Co Rd;Island",
    "iso:country":"US",
    "sg:address":"633 Co Rd 1",
    "sg:city":"Pine Island",
    "sg:classifiers":[
        {
            "category":"Restaurant",
            "type":"Food & Drink"
        }
    ],
    "sg:phone":"+1 845 258 3060",
    "sg:postcode":"10969",
    "sg:province":"NY",
    "wof:name":"Harvest Luncheonette",
    "wof:placetype":"venue"
},
  "geometry": {"coordinates":[-74.46241000000001,41.296271],"type":"Point"}
}