{
  "type": "Feature",
  "properties": {
    "iso:country":"US",
    "sg:address":"1000 Lemoyne Ave",
    "sg:city":"Syracuse",
    "sg:classifiers":[
        {
            "category":"Insurance",
            "subcategory":"Insurance Agent",
            "type":"Services"
        }
    ],
    "sg:phone":"+1 315 475 0701",
    "sg:postcode":"13208",
    "sg:province":"NY",
    "wof:name":"Harbinger Financial Svc",
    "wof:placetype":"venue"
},
  "geometry": {"coordinates":[-76.156581,43.078702],"type":"Point"}
}