{
  "type": "Feature",
  "properties": {
    "iso:country":"US",
    "sg:address":"275 Mile Square Rd",
    "sg:city":"Yonkers",
    "sg:classifiers":[
        {
            "category":"Building & Trades",
            "subcategory":"Construction",
            "type":"Services"
        }
    ],
    "sg:phone":"+1 914 969 2178",
    "sg:postcode":"10701",
    "sg:province":"NY",
    "sg:tags":[
        "house"
    ],
    "wof:name":"Willow Electric Inc",
    "wof:placetype":"venue"
},
  "geometry": {"coordinates":[-73.861079,40.944932],"type":"Point"}
}