{
  "type": "Feature",
  "properties": {
    "addr:full":"409 Prospect Ave Syracuse NY 13203",
    "addr:housenumber":"409",
    "addr:postcode":"13203",
    "addr:street":"Prospect Ave",
    "iso:country":"US",
    "sg:address":"409 Prospect Ave",
    "sg:city":"Syracuse",
    "sg:classifiers":[
        {
            "category":"Travel",
            "subcategory":"Travel Agent",
            "type":"Entertainment"
        }
    ],
    "sg:phone":"+1   ",
    "sg:postcode":"13203",
    "sg:province":"NY",
    "sg:tags":[
        "operator",
        "tour"
    ],
    "wof:name":"Robot & Wild Assn Tour",
    "wof:placetype":"venue"
},
  "geometry": {"coordinates":[-76.151178,43.057934],"type":"Point"}
}