{
  "type": "Feature",
  "properties": {
    "addr:full":"214 Carlton Ave Brooklyn NY 11205",
    "addr:housenumber":"214",
    "addr:postcode":"11205",
    "addr:street":"Carlton Ave",
    "iso:country":"US",
    "sg:address":"214 Carlton Ave",
    "sg:city":"Brooklyn",
    "sg:classifiers":[
        {
            "category":"Real Estate",
            "subcategory":"Real Estate Services",
            "type":"Services"
        }
    ],
    "sg:phone":"+1 718 875 5635",
    "sg:postcode":"11205",
    "sg:province":"NY",
    "sg:tags":[
        "abstract",
        "title"
    ],
    "wof:name":"Abstract Factory",
    "wof:placetype":"venue"
},
  "geometry": {"coordinates":[-73.972272,40.68999],"type":"Point"}
}