{
  "type": "Feature",
  "properties": {
    "addr:full":"57 E 167th St Bronx NY 10452",
    "addr:housenumber":"57",
    "addr:postcode":"10452",
    "addr:street":"E 167Th St",
    "iso:country":"US",
    "sg:address":"57 E 167th St",
    "sg:city":"Bronx",
    "sg:classifiers":[
        {
            "category":"Communications",
            "type":"Services"
        }
    ],
    "sg:phone":"+1 718 293 6399",
    "sg:postcode":"10452",
    "sg:province":"NY",
    "wof:name":"Dominican Communications",
    "wof:placetype":"venue"
},
  "geometry": {"coordinates":[-73.920804,40.835699],"type":"Point"}
}