{
  "type": "Feature",
  "properties": {
    "addr:full":"2655 Richmond Ave Staten Island NY 10314",
    "addr:housenumber":"2655",
    "addr:postcode":"10314",
    "addr:street":"Richmond Ave",
    "iso:country":"US",
    "sg:address":"2655 Richmond Ave",
    "sg:city":"Staten Island",
    "sg:classifiers":[
        {
            "category":"Restaurant",
            "type":"Food & Drink"
        }
    ],
    "sg:phone":"+1 718 982 7801",
    "sg:postcode":"10314",
    "sg:province":"NY",
    "sg:tags":[
        "traditional",
        "american"
    ],
    "wof:name":"TGI Fridays",
    "wof:placetype":"venue"
},
  "geometry": {"coordinates":[-74.16914199999999,40.580893],"type":"Point"}
}