{
  "type": "Feature",
  "properties": {
    "addr:full":"8221 Lewiston Rd Batavia NY 14020",
    "addr:housenumber":"8221",
    "addr:postcode":"14020",
    "addr:street":"Lewiston Rd",
    "iso:country":"US",
    "sg:address":"8221 Lewiston Rd",
    "sg:city":"Batavia",
    "sg:classifiers":[
        {
            "category":"Organizations",
            "subcategory":"Religious Organization",
            "type":"Services"
        }
    ],
    "sg:phone":"+1 585 345 0268",
    "sg:postcode":"14020",
    "sg:province":"NY",
    "sg:tags":[
        "church"
    ],
    "wof:name":"First United Mthdst Chr Study",
    "wof:placetype":"venue"
},
  "geometry": {"coordinates":[-78.217282,43.016736],"type":"Point"}
}