{
  "type": "Feature",
  "properties": {
    "addr:full":"2253 3rd Avenue New York NY 10035",
    "addr:housenumber":"2253",
    "addr:postcode":"10035",
    "addr:street":"3Rd Avenue",
    "iso:country":"US",
    "sg:address":"2253 3rd Avenue",
    "sg:city":"New York",
    "sg:classifiers":[
        {
            "category":"Professional",
            "subcategory":"Accounting & Tax Preparation",
            "type":"Services"
        }
    ],
    "sg:phone":"+1 212 348 4961",
    "sg:postcode":"10035",
    "sg:province":"NY",
    "sg:tags":[
        "accountant"
    ],
    "wof:name":"Colon Jennifer CPA",
    "wof:placetype":"venue"
},
  "geometry": {"coordinates":[-73.936846,40.802174],"type":"Point"}
}