{
  "type": "Feature",
  "properties": {
    "addr:full":"716 Hoosick Rd Troy NY 12180",
    "addr:housenumber":"716",
    "addr:postcode":"12180",
    "addr:street":"Hoosick Rd",
    "iso:country":"US",
    "sg:address":"716 Hoosick Rd",
    "sg:city":"Troy",
    "sg:classifiers":[
        {
            "category":"Shopping",
            "subcategory":"Florist",
            "type":"Retail Goods"
        }
    ],
    "sg:phone":"+1   ",
    "sg:postcode":"12180",
    "sg:province":"NY",
    "wof:name":"Floral Shoppe & Gifts Brun",
    "wof:placetype":"venue"
},
  "geometry": {"coordinates":[-73.644666,42.743933],"type":"Point"}
}