{
  "type": "Feature",
  "properties": {
    "iso:country":"US",
    "sg:address":"1203 Stockbridge Rd",
    "sg:city":"Webster",
    "sg:classifiers":[
        {
            "category":"Building & Trades",
            "subcategory":"Construction",
            "type":"Services"
        }
    ],
    "sg:phone":"+1 585 872 5680",
    "sg:postcode":"14580",
    "sg:province":"NY",
    "sg:tags":[
        "residential"
    ],
    "wof:name":"Gilliland Construction",
    "wof:placetype":"venue"
},
  "geometry": {"coordinates":[-77.44176299999999,43.250723],"type":"Point"}
}