{
  "type": "Feature",
  "properties": {
    "iso:country":"US",
    "sg:address":"3952 Albany St",
    "sg:city":"Schenectady",
    "sg:classifiers":[
        {
            "category":"Retail",
            "subcategory":"Repair Shop",
            "type":"Services"
        }
    ],
    "sg:phone":"+1 518 346 5936",
    "sg:postcode":"12304",
    "sg:province":"NY",
    "sg:tags":[
        "upholsterer"
    ],
    "wof:name":"Hines Upholstery",
    "wof:placetype":"venue"
},
  "geometry": {"coordinates":[-73.888306,42.762207],"type":"Point"}
}