{
  "type": "Feature",
  "properties": {
    "iso:country":"US",
    "sg:address":"22 American Ave",
    "sg:city":"Coram",
    "sg:classifiers":[
        {
            "category":"Real Estate",
            "subcategory":"Surveying",
            "type":"Services"
        }
    ],
    "sg:phone":"+1   ",
    "sg:postcode":"11727",
    "sg:province":"NY",
    "wof:name":"Metes & Bounds Surveying Inc",
    "wof:placetype":"venue"
},
  "geometry": {"coordinates":[-72.989154,40.883768],"type":"Point"}
}