{
  "type": "Feature",
  "properties": {
    "addr:full":"27 Elmira St Deer Park NY 11729",
    "addr:housenumber":"27",
    "addr:postcode":"11729",
    "addr:street":"Elmira St",
    "iso:country":"US",
    "sg:address":"27 Elmira St",
    "sg:city":"Deer Park",
    "sg:classifiers":[
        {
            "category":"Building & Trades",
            "subcategory":"Plumbing",
            "type":"Services"
        }
    ],
    "sg:phone":"+1 631 586 4018",
    "sg:postcode":"11729",
    "sg:province":"NY",
    "sg:tags":[
        "plumbing",
        "contractor"
    ],
    "wof:name":"Nick Lombardo Plumbing",
    "wof:placetype":"venue"
},
  "geometry": {"coordinates":[-73.318752,40.775012],"type":"Point"}
}