{
  "type": "Feature",
  "properties": {
    "iso:country":"US",
    "sg:address":"575 Colfax St",
    "sg:city":"Rochester",
    "sg:classifiers":[
        {
            "category":"School Buses",
            "type":"Transportation"
        }
    ],
    "sg:phone":"+1   ",
    "sg:postcode":"14606",
    "sg:province":"NY",
    "wof:name":"National School Bus Garage",
    "wof:placetype":"venue"
},
  "geometry": {"coordinates":[-77.669793,43.170932],"type":"Point"}
}