{
  "type": "Feature",
  "properties": {
    "iso:country":"US",
    "sg:address":"13 Orchard St",
    "sg:city":"Rensselaer",
    "sg:classifiers":[
        {
            "category":"Building & Trades",
            "subcategory":"Construction",
            "type":"Services"
        }
    ],
    "sg:phone":"+1 518 477 8505",
    "sg:postcode":"12144",
    "sg:province":"NY",
    "sg:tags":[
        "house"
    ],
    "wof:name":"R Stone Contg & Property Svcs",
    "wof:placetype":"venue"
},
  "geometry": {"coordinates":[-73.73396700000001,42.615601],"type":"Point"}
}