{
  "type": "Feature",
  "properties": {
    "iso:country":"US",
    "sg:address":"162 Williamsburg St E",
    "sg:city":"Brooklyn",
    "sg:classifiers":[
        {
            "category":"Shopping",
            "subcategory":"Gifts & Souvenirs",
            "type":"Retail Goods"
        }
    ],
    "sg:phone":"+1 718 388 1222",
    "sg:postcode":"11211",
    "sg:province":"NY",
    "sg:tags":[
        "party",
        "supply"
    ],
    "wof:name":"A & S Chair Rental",
    "wof:placetype":"venue"
},
  "geometry": {"coordinates":[-73.95917799999999,40.703863],"type":"Point"}
}