{
  "type": "Feature",
  "properties": {
    "addr:full":"383 Raecrest Cir Elmira NY 14904",
    "addr:housenumber":"383",
    "addr:postcode":"14904",
    "addr:street":"Raecrest Cir",
    "iso:country":"US",
    "sg:address":"383 Raecrest Cir",
    "sg:city":"Elmira",
    "sg:classifiers":[
        {
            "category":"Building & Trades",
            "subcategory":"Construction",
            "type":"Services"
        }
    ],
    "sg:phone":"+1 607 732 0529",
    "sg:postcode":"14904",
    "sg:province":"NY",
    "sg:tags":[
        "contractor"
    ],
    "wof:name":"Callahan Construction",
    "wof:placetype":"venue"
},
  "geometry": {"coordinates":[-76.786575,42.06598],"type":"Point"}
}