{
  "type": "Feature",
  "properties": {
    "iso:country":"US",
    "sg:address":"513 E Main St",
    "sg:city":"Palmyra",
    "sg:classifiers":[
        {
            "category":"Autos & Motor Vehicles",
            "subcategory":"Fuel & Gas Station",
            "type":"Retail Goods"
        }
    ],
    "sg:phone":"+1 315 597 5853",
    "sg:postcode":"14522",
    "sg:province":"NY",
    "sg:tags":[
        "oil"
    ],
    "wof:name":"Newcomb Palmyra Station",
    "wof:placetype":"venue"
},
  "geometry": {"coordinates":[-77.226218,43.063546],"type":"Point"}
}