{
  "type": "Feature",
  "properties": {
    "iso:country":"US",
    "sg:address":"74 Kean St",
    "sg:city":"West Babylon",
    "sg:classifiers":[
        {
            "category":"Professional",
            "subcategory":"Art Services",
            "type":"Services"
        }
    ],
    "sg:phone":"+1 631 643 1850",
    "sg:postcode":"11704",
    "sg:province":"NY",
    "sg:tags":[
        "commercial",
        "design"
    ],
    "wof:name":"Design Air",
    "wof:placetype":"venue"
},
  "geometry": {"coordinates":[-73.38061500000001,40.73781],"type":"Point"}
}