{
  "type": "Feature",
  "properties": {
    "iso:country":"US",
    "sg:address":"568 Columbus Ave",
    "sg:city":"New York",
    "sg:classifiers":[
        {
            "category":"Retail",
            "subcategory":"Veterinary Services",
            "type":"Services"
        }
    ],
    "sg:phone":"+1 212 501 8750",
    "sg:postcode":"10024",
    "sg:province":"NY",
    "sg:tags":[
        "veterinarian"
    ],
    "sg:website":"www.avianandexoticvets.com/",
    "wof:name":"Center For Avian & Exotic Medicine",
    "wof:placetype":"venue"
},
  "geometry": {"coordinates":[-73.971405,40.787571],"type":"Point"}
}