{
  "type": "Feature",
  "properties": {
    "addr:full":"5904 13th Ave Brooklyn NY 11219",
    "addr:housenumber":"5904",
    "addr:postcode":"11219",
    "addr:street":"13Th Ave",
    "iso:country":"US",
    "sg:address":"5904 13th Ave",
    "sg:city":"Brooklyn",
    "sg:classifiers":[
        {
            "category":"Health Services",
            "subcategory":"Hospital",
            "type":"Services"
        }
    ],
    "sg:phone":"+1 718 431 9501",
    "sg:postcode":"11219",
    "sg:province":"NY",
    "sg:tags":[
        "mental"
    ],
    "wof:name":"Relief Resources Inc",
    "wof:placetype":"venue"
},
  "geometry": {"coordinates":[-73.99858500000001,40.628915],"type":"Point"}
}