{
  "type": "Feature",
  "properties": {
    "addr:full":"682 Carman Ave Westbury NY 11590",
    "addr:housenumber":"682",
    "addr:postcode":"11590",
    "addr:street":"Carman Ave",
    "iso:country":"US",
    "sg:address":"682 Carman Ave",
    "sg:city":"Westbury",
    "sg:classifiers":[
        {
            "category":"Health Services",
            "subcategory":"Chiropractor",
            "type":"Services"
        }
    ],
    "sg:phone":"+1 516 334 7622",
    "sg:postcode":"11590",
    "sg:province":"NY",
    "wof:name":"Altebrando Frank Chiropractor",
    "wof:placetype":"venue"
},
  "geometry": {"coordinates":[-73.55210099999999,40.746201],"type":"Point"}
}