{
  "type": "Feature",
  "properties": {
    "addr:full":"1 Astor Pl Ste #11H New York NY 10003",
    "addr:housenumber":"1;11h",
    "addr:postcode":"10003",
    "addr:street":"Astor Pl Ste #",
    "iso:country":"US",
    "sg:address":"1 Astor Pl Ste #11H",
    "sg:city":"New York",
    "sg:classifiers":[
        {
            "category":"Shopping",
            "subcategory":"Computers & Home Electronics",
            "type":"Retail Goods"
        }
    ],
    "sg:phone":"+1 212 260 2939",
    "sg:postcode":"10003",
    "sg:province":"NY",
    "sg:website":"audioarts.co",
    "wof:name":"Audioarts",
    "wof:placetype":"venue"
},
  "geometry": {"coordinates":[-73.992255,40.730023],"type":"Point"}
}