{
  "type": "Feature",
  "properties": {
    "addr:full":"7 W 36 St New York NY 10018",
    "addr:housenumber":"7",
    "addr:postcode":"10018",
    "addr:street":"W 36 St",
    "iso:country":"US",
    "sg:address":"7 W 36 St",
    "sg:city":"New York",
    "sg:classifiers":[
        {
            "category":"Wholesale",
            "subcategory":"Jewelry",
            "type":"Manufacturing & Wholesale Goods"
        }
    ],
    "sg:phone":"+1 212 239 1800",
    "sg:postcode":"10018",
    "sg:province":"NY",
    "sg:tags":[
        "stone"
    ],
    "wof:name":"Carmicl",
    "wof:placetype":"venue"
},
  "geometry": {"coordinates":[-73.98666299999999,40.751064],"type":"Point"}
}