{
  "type": "Feature",
  "properties": {
    "iso:country":"US",
    "sg:address":"214 Berkeley St",
    "sg:city":"Rochester",
    "sg:classifiers":[
        {
            "category":"Professional",
            "subcategory":"Lawyer & Legal Services",
            "type":"Services"
        }
    ],
    "sg:phone":"+1 585 461 1237",
    "sg:postcode":"14607",
    "sg:province":"NY",
    "sg:tags":[
        "attorney"
    ],
    "wof:name":"Hugh S Silberstein",
    "wof:placetype":"venue"
},
  "geometry": {"coordinates":[-77.578755,43.146436],"type":"Point"}
}