{
  "type": "Feature",
  "properties": {
    "iso:country":"US",
    "sg:address":"332 Grange St",
    "sg:city":"Franklin Square",
    "sg:classifiers":[
        {
            "category":"Building & Trades",
            "subcategory":"Electrical",
            "type":"Services"
        }
    ],
    "sg:phone":"+1 516 486 5964",
    "sg:postcode":"11010",
    "sg:province":"NY",
    "sg:tags":[
        "electrical",
        "contractor"
    ],
    "wof:name":"Full Force Electric Inc",
    "wof:placetype":"venue"
},
  "geometry": {"coordinates":[-73.667812,40.700449],"type":"Point"}
}