{
  "type": "Feature",
  "properties": {
    "iso:country":"US",
    "sg:address":"47 E 32nd Street",
    "sg:city":"Brooklyn",
    "sg:classifiers":[
        {
            "category":"Health Services",
            "subcategory":"Dentist",
            "type":"Services"
        }
    ],
    "sg:phone":"+1 718 856 9603",
    "sg:postcode":"11226",
    "sg:province":"NY",
    "wof:name":"Abellard Beauvoir DDS",
    "wof:placetype":"venue"
},
  "geometry": {"coordinates":[-73.94740899999999,40.649984],"type":"Point"}
}