{
  "type": "Feature",
  "properties": {
    "iso:country":"US",
    "sg:address":"235 Co Rd 405",
    "sg:city":"Greenville",
    "sg:classifiers":[
        {
            "category":"Shopping",
            "subcategory":"Bicycles & Sporting Goods",
            "type":"Retail Goods"
        }
    ],
    "sg:phone":"+1 518 966 8752",
    "sg:postcode":"12083",
    "sg:province":"NY",
    "sg:tags":[
        "gun",
        "gunsmith"
    ],
    "wof:name":"South Wings",
    "wof:placetype":"venue"
},
  "geometry": {"coordinates":[-74.021303,42.443157],"type":"Point"}
}