{
  "type": "Feature",
  "properties": {
    "addr:full":"26193 State Hwy 283 Watertown NY 13616",
    "addr:housenumber":"26193",
    "addr:postcode":"13616",
    "addr:street":"State Hwy 283",
    "iso:country":"US",
    "sg:address":"26193 State Hwy 283",
    "sg:city":"Watertown",
    "sg:classifiers":[
        {
            "category":"Restaurant",
            "type":"Food & Drink"
        }
    ],
    "sg:phone":"+1 315 788 6688",
    "sg:postcode":"13616",
    "sg:province":"NY",
    "sg:tags":[
        "banquet",
        "rooms"
    ],
    "wof:name":"Thailand Restaurant",
    "wof:placetype":"venue"
},
  "geometry": {"coordinates":[-75.85261199999999,44.00296],"type":"Point"}
}