{
  "type": "Feature",
  "properties": {
    "iso:country":"US",
    "sg:address":"111 Broadway Lbby",
    "sg:city":"New York",
    "sg:classifiers":[
        {
            "category":"Personal",
            "subcategory":"Tanning Parlor",
            "type":"Services"
        }
    ],
    "sg:phone":"+1 212 797 1303",
    "sg:postcode":"10006",
    "sg:province":"NY",
    "wof:name":"Tan Ron",
    "wof:placetype":"venue"
},
  "geometry": {"coordinates":[-74.011171,40.708395],"type":"Point"}
}