{
  "type": "Feature",
  "properties": {
    "iso:country":"US",
    "sg:address":"1780 N Forest Rd",
    "sg:city":"Buffalo",
    "sg:classifiers":[
        {
            "category":"Shopping",
            "subcategory":"Florist",
            "type":"Retail Goods"
        }
    ],
    "sg:phone":"+1 716 875 3749",
    "sg:postcode":"14221",
    "sg:province":"NY",
    "sg:website":"www.bouquetshoppe.net",
    "wof:name":"Bouquet Shoppe",
    "wof:placetype":"venue"
},
  "geometry": {"coordinates":[-78.760644,43.003322],"type":"Point"}
}