{
  "type": "Feature",
  "properties": {
    "addr:full":"260 W 36 St New York NY 10018",
    "addr:housenumber":"260",
    "addr:postcode":"10018",
    "addr:street":"W 36 St",
    "iso:country":"US",
    "sg:address":"260 W 36 St",
    "sg:city":"New York",
    "sg:classifiers":[
        {
            "category":"Manufacturing",
            "subcategory":"Tools & Machinery",
            "type":"Manufacturing & Wholesale Goods"
        }
    ],
    "sg:phone":"+1 212 563 5480",
    "sg:postcode":"10018",
    "sg:province":"NY",
    "sg:tags":[
        "model",
        "maker"
    ],
    "sg:website":"www.awadarchitectural.com",
    "wof:name":"Awad Architects",
    "wof:placetype":"venue"
},
  "geometry": {"coordinates":[-73.99124999999999,40.752677],"type":"Point"}
}