{
  "type": "Feature",
  "properties": {
    "addr:full":"306 East 119th St New York NY 10035",
    "addr:housenumber":"306",
    "addr:postcode":"10035",
    "addr:street":"East 119Th St",
    "iso:country":"US",
    "sg:address":"306 East 119th St",
    "sg:city":"New York",
    "sg:classifiers":[
        {
            "category":"Building & Trades",
            "subcategory":"Construction",
            "type":"Services"
        }
    ],
    "sg:phone":"+1 212 738 9395",
    "sg:postcode":"10035",
    "sg:province":"NY",
    "sg:tags":[
        "contractor"
    ],
    "wof:name":"Ny Hc Services Inc",
    "wof:placetype":"venue"
},
  "geometry": {"coordinates":[-73.935947,40.798573],"type":"Point"}
}