{
  "type": "Feature",
  "properties": {
    "addr:full":"673 Elton St Brooklyn NY 11208",
    "addr:housenumber":"673",
    "addr:postcode":"11208",
    "addr:street":"Elton St",
    "iso:country":"US",
    "sg:address":"673 Elton St",
    "sg:city":"Brooklyn",
    "sg:classifiers":[
        {
            "category":"Retail",
            "subcategory":"Repair Shop",
            "type":"Services"
        }
    ],
    "sg:phone":"+1 718 766 2659",
    "sg:postcode":"11208",
    "sg:province":"NY",
    "sg:tags":[
        "lock",
        "locksmith"
    ],
    "wof:name":"24 Hour Emergency Locksmith",
    "wof:placetype":"venue"
},
  "geometry": {"coordinates":[-73.88042799999999,40.665385],"type":"Point"}
}