{
  "type": "Feature",
  "properties": {
    "addr:full":"226 E 79th St New York NY 10075",
    "addr:housenumber":"226",
    "addr:postcode":"10075",
    "addr:street":"E 79Th St",
    "iso:country":"US",
    "sg:address":"226 E 79th St",
    "sg:city":"New York",
    "sg:classifiers":[
        {
            "category":"Home & Garden",
            "subcategory":"Furniture",
            "type":"Retail Goods"
        }
    ],
    "sg:phone":"+1 212 327 4714",
    "sg:postcode":"10075",
    "sg:province":"NY",
    "sg:tags":[
        "store"
    ],
    "wof:name":"Belongings",
    "wof:placetype":"venue"
},
  "geometry": {"coordinates":[-73.956751,40.773904],"type":"Point"}
}