{
  "type": "Feature",
  "properties": {
    "addr:full":"8994 Plainville Rd Baldwinsville NY 13027",
    "addr:housenumber":"8994",
    "addr:postcode":"13027",
    "addr:street":"Plainville Rd",
    "iso:country":"US",
    "sg:address":"8994 Plainville Rd",
    "sg:city":"Baldwinsville",
    "sg:classifiers":[
        {
            "category":"Building & Trades",
            "subcategory":"Construction",
            "type":"Services"
        }
    ],
    "sg:phone":"+1 315 678 2174",
    "sg:postcode":"13027",
    "sg:province":"NY",
    "sg:tags":[
        "contractor"
    ],
    "wof:name":"Marty Collins Construction",
    "wof:placetype":"venue"
},
  "geometry": {"coordinates":[-76.458372,43.199648],"type":"Point"}
}