{
  "type": "Feature",
  "properties": {
    "addr:full":"513 Wilson Ave Brooklyn NY 11221",
    "addr:housenumber":"513",
    "addr:postcode":"11221",
    "addr:street":"Wilson Ave",
    "iso:country":"US",
    "sg:address":"513 Wilson Ave",
    "sg:city":"Brooklyn",
    "sg:classifiers":[
        {
            "category":"Travel",
            "subcategory":"Travel Agent",
            "type":"Entertainment"
        }
    ],
    "sg:phone":"+1   ",
    "sg:postcode":"11221",
    "sg:province":"NY",
    "sg:tags":[
        "agency"
    ],
    "wof:name":"John Tours & Services Inc",
    "wof:placetype":"venue"
},
  "geometry": {"coordinates":[-73.91038,40.692085],"type":"Point"}
}