{
  "type": "Feature",
  "properties": {
    "iso:country":"US",
    "sg:address":"339 Jerusalem Ave",
    "sg:city":"Hicksville",
    "sg:classifiers":[
        {
            "category":"Personal",
            "subcategory":"Beauty Salon",
            "type":"Services"
        }
    ],
    "sg:phone":"+1 516 933 1112",
    "sg:postcode":"11801",
    "sg:province":"NY",
    "sg:tags":[
        "nail",
        "shop",
        "manicuring"
    ],
    "wof:name":"Grace's Nail Studio Inc",
    "wof:placetype":"venue"
},
  "geometry": {"coordinates":[-73.520523,40.754397],"type":"Point"}
}