{
  "type": "Feature",
  "properties": {
    "iso:country":"US",
    "sg:address":"2785 Dewey Ave",
    "sg:city":"Rochester",
    "sg:classifiers":[
        {
            "category":"Personal",
            "subcategory":"Beauty Salon",
            "type":"Services"
        }
    ],
    "sg:phone":"+1 585 254 4049",
    "sg:postcode":"14616",
    "sg:province":"NY",
    "wof:name":"Jim & Company Hair Design",
    "wof:placetype":"venue"
},
  "geometry": {"coordinates":[-77.641355,43.220391],"type":"Point"}
}