{
  "type": "Feature",
  "properties": {
    "addr:full":"786 E Tremont Ave Bronx NY 10460",
    "addr:housenumber":"786",
    "addr:postcode":"10460",
    "addr:street":"E Tremont Ave",
    "iso:country":"US",
    "sg:address":"786 E Tremont Ave",
    "sg:city":"Bronx",
    "sg:classifiers":[
        {
            "category":"Home & Garden",
            "subcategory":"Household Appliances",
            "type":"Retail Goods"
        }
    ],
    "sg:phone":"+1 718 294 0963",
    "sg:postcode":"10460",
    "sg:province":"NY",
    "wof:name":"Top Shop Appliances 2000 Inc",
    "wof:placetype":"venue"
},
  "geometry": {"coordinates":[-73.888248,40.843836],"type":"Point"}
}