{
  "type": "Feature",
  "properties": {
    "iso:country":"US",
    "sg:address":"226 Bay Street",
    "sg:city":"Staten Island",
    "sg:classifiers":[
        {
            "category":"Real Estate",
            "subcategory":"Real Estate Services",
            "type":"Services"
        },
        {
            "category":"Building & Trades",
            "subcategory":"Pest Control",
            "type":"Services"
        }
    ],
    "sg:phone":"+1 718 447 1234",
    "sg:postcode":"10301",
    "sg:province":"NY",
    "sg:tags":[
        "home",
        "inspector"
    ],
    "wof:name":"Loffredo Fred Extrmtr",
    "wof:placetype":"venue"
},
  "geometry": {"coordinates":[-74.076285,40.636466],"type":"Point"}
}