{
  "type": "Feature",
  "properties": {
    "iso:country":"US",
    "sg:address":"416 W 14 St",
    "sg:city":"New York",
    "sg:classifiers":[
        {
            "category":"Professional",
            "subcategory":"Computer Services",
            "type":"Services"
        }
    ],
    "sg:phone":"+1 212 243 7777",
    "sg:postcode":"10014",
    "sg:province":"NY",
    "sg:tags":[
        "internet"
    ],
    "wof:name":"Catalyst Group Inc",
    "wof:placetype":"venue"
},
  "geometry": {"coordinates":[-74.006495,40.741275],"type":"Point"}
}