{
  "type": "Feature",
  "properties": {
    "iso:country":"US",
    "sg:address":"8804 Roosevelt Avenue",
    "sg:city":"Jackson Heights",
    "sg:classifiers":[
        {
            "category":"Personal",
            "subcategory":"Barber",
            "type":"Services"
        }
    ],
    "sg:phone":"+1 718 533 7700",
    "sg:postcode":"11372",
    "sg:province":"NY",
    "wof:name":"Peluqueria Puebla Unisex",
    "wof:placetype":"venue"
},
  "geometry": {"coordinates":[-73.87777800000001,40.748171],"type":"Point"}
}