{
  "type": "Feature",
  "properties": {
    "iso:country":"US",
    "sg:address":"3722 Scottsville Rd",
    "sg:city":"Scottsville",
    "sg:classifiers":[
        {
            "category":"Autos & Motor Vehicles",
            "subcategory":"Automobile Sales",
            "type":"Retail Goods"
        }
    ],
    "sg:phone":"+1 585 889 1201",
    "sg:postcode":"14546",
    "sg:province":"NY",
    "sg:tags":[
        "car",
        "dealer"
    ],
    "wof:name":"Riverside Chevrolet-GEO",
    "wof:placetype":"venue"
},
  "geometry": {"coordinates":[-77.738874,43.035515],"type":"Point"}
}