{
  "type": "Feature",
  "properties": {
    "addr:full":"261 Mill Rd East Aurora NY 14052",
    "addr:housenumber":"261",
    "addr:postcode":"14052",
    "addr:street":"Mill Rd",
    "iso:country":"US",
    "sg:address":"261 Mill Rd",
    "sg:city":"East Aurora",
    "sg:classifiers":[
        {
            "category":"Professional",
            "subcategory":"Business Services",
            "type":"Services"
        }
    ],
    "sg:phone":"+1 716 655 5100",
    "sg:postcode":"14052",
    "sg:province":"NY",
    "sg:tags":[
        "interior",
        "consultant",
        "design",
        "decorator"
    ],
    "sg:website":"www.decoratingden.com",
    "wof:name":"Interiors By Decorating Den",
    "wof:placetype":"venue"
},
  "geometry": {"coordinates":[-78.630123,42.760491],"type":"Point"}
}