{
  "type": "Feature",
  "properties": {
    "addr:full":"666 E 181st St Bronx NY 10457",
    "addr:housenumber":"666",
    "addr:postcode":"10457",
    "addr:street":"E 181St St",
    "iso:country":"US",
    "sg:address":"666 E 181st St",
    "sg:city":"Bronx",
    "sg:classifiers":[
        {
            "category":"Professional",
            "type":"Services"
        }
    ],
    "sg:phone":"+1 718 220 0347",
    "sg:postcode":"10457",
    "sg:province":"NY",
    "sg:tags":[
        "establishment"
    ],
    "wof:name":"666 6 181 Street LLC",
    "wof:placetype":"venue"
},
  "geometry": {"coordinates":[-73.88832600000001,40.848952],"type":"Point"}
}