{
  "type": "Feature",
  "properties": {
    "iso:country":"US",
    "sg:address":"157 Atlantic Ave",
    "sg:city":"Oceanside",
    "sg:classifiers":[
        {
            "category":"Shopping",
            "subcategory":"Used Merchandise",
            "type":"Retail Goods"
        }
    ],
    "sg:phone":"+1 516 766 6090",
    "sg:postcode":"11572",
    "sg:province":"NY",
    "sg:tags":[
        "antique"
    ],
    "wof:name":"Daisy O'Day",
    "wof:placetype":"venue"
},
  "geometry": {"coordinates":[-73.645546,40.639733],"type":"Point"}
}