{
  "type": "Feature",
  "properties": {
    "iso:country":"US",
    "sg:address":"472 58th St",
    "sg:city":"Brooklyn",
    "sg:classifiers":[
        {
            "category":"Health Services",
            "subcategory":"Doctor",
            "type":"Services"
        }
    ],
    "sg:phone":"+1 718 492 9211",
    "sg:postcode":"11220",
    "sg:province":"NY",
    "sg:tags":[
        "dentist"
    ],
    "wof:name":"Decent Dental Svc",
    "wof:placetype":"venue"
},
  "geometry": {"coordinates":[-74.016284,40.641567],"type":"Point"}
}