{
  "type": "Feature",
  "properties": {
    "addr:full":"271 Vanderbilt Ave Brooklyn NY 11205",
    "addr:housenumber":"271",
    "addr:postcode":"11205",
    "addr:street":"Vanderbilt Ave",
    "iso:country":"US",
    "sg:address":"271 Vanderbilt Ave",
    "sg:city":"Brooklyn",
    "sg:classifiers":[
        {
            "category":"Manufacturing",
            "subcategory":"Electronics",
            "type":"Manufacturing & Wholesale Goods"
        },
        {
            "category":"Shopping",
            "subcategory":"Computers & Home Electronics",
            "type":"Retail Goods"
        }
    ],
    "sg:phone":"+1 718 783 6099",
    "sg:postcode":"11205",
    "sg:province":"NY",
    "sg:tags":[
        "equipment-wholesale",
        "manufacturer",
        "theater",
        "system",
        "audio-visual"
    ],
    "wof:name":"Power Supply",
    "wof:placetype":"venue"
},
  "geometry": {"coordinates":[-73.96921,40.689944],"type":"Point"}
}