{
  "type": "Feature",
  "properties": {
    "addr:full":"39 Northern Pines Rd Gansevoort NY 12831",
    "addr:housenumber":"39",
    "addr:postcode":"12831",
    "addr:street":"Northern Pines Rd",
    "iso:country":"US",
    "sg:address":"39 Northern Pines Rd",
    "sg:city":"Gansevoort",
    "sg:classifiers":[
        {
            "category":"Food & Beverages",
            "subcategory":"Groceries & Convenience Stores",
            "type":"Retail Goods"
        }
    ],
    "sg:phone":"+1 518 584 4036",
    "sg:postcode":"12831",
    "sg:province":"NY",
    "sg:tags":[
        "product"
    ],
    "wof:name":"Greenfield's Greatest Food Co",
    "wof:placetype":"venue"
},
  "geometry": {"coordinates":[-73.743512,43.175336],"type":"Point"}
}