{
  "type": "Feature",
  "properties": {
    "addr:full":"57 Greenleaf Ave Staten Island NY 10310",
    "addr:housenumber":"57",
    "addr:postcode":"10310",
    "addr:street":"Greenleaf Ave",
    "iso:country":"US",
    "sg:address":"57 Greenleaf Ave",
    "sg:city":"Staten Island",
    "sg:classifiers":[
        {
            "category":"Wholesale",
            "subcategory":"Machinery & Supplies",
            "type":"Manufacturing & Wholesale Goods"
        }
    ],
    "sg:phone":"+1 718 816 8785",
    "sg:postcode":"10310",
    "sg:province":"NY",
    "sg:tags":[
        "equipment",
        "printing"
    ],
    "wof:name":"JB Printing",
    "wof:placetype":"venue"
},
  "geometry": {"coordinates":[-74.12740599999999,40.631061],"type":"Point"}
}