{
  "type": "Feature",
  "properties": {
    "addr:full":"2608 Broadway Manhattan NY 10025",
    "addr:housenumber":"2608",
    "addr:postcode":"10025",
    "addr:street":"Broadway",
    "iso:country":"US",
    "sg:address":"2608 Broadway",
    "sg:city":"Manhattan",
    "sg:classifiers":[
        {
            "category":"Restaurant",
            "type":"Food & Drink"
        }
    ],
    "sg:phone":"+1 212 222 1554",
    "sg:postcode":"10025",
    "sg:province":"NY",
    "sg:tags":[
        "middle",
        "vegetarian",
        "eastern"
    ],
    "sg:website":"hummusplace.com",
    "wof:name":"Hummus Place",
    "wof:placetype":"venue"
},
  "geometry": {"coordinates":[-73.97053,40.796202],"type":"Point"}
}