{
  "type": "Feature",
  "properties": {
    "addr:full":"625 Fulton St Brooklyn NY 11201",
    "addr:housenumber":"625",
    "addr:postcode":"11201",
    "addr:street":"Fulton St",
    "iso:country":"US",
    "sg:address":"625 Fulton St",
    "sg:city":"Brooklyn",
    "sg:classifiers":[
        {
            "category":"Government",
            "subcategory":"Office",
            "type":"Public Place"
        }
    ],
    "sg:phone":"+1 718 488 2080",
    "sg:postcode":"11201",
    "sg:province":"NY",
    "sg:tags":[
        "federal",
        "taxation"
    ],
    "wof:name":"US Internal Revenue Svc",
    "wof:placetype":"venue"
},
  "geometry": {"coordinates":[-73.98209799999999,40.689358],"type":"Point"}
}