{
  "type": "Feature",
  "properties": {
    "addr:full":"778 Washington Ave Brooklyn NY 11238",
    "addr:housenumber":"778",
    "addr:postcode":"11238",
    "addr:street":"Washington Ave",
    "iso:country":"US",
    "sg:address":"778 Washington Ave",
    "sg:city":"Brooklyn",
    "sg:classifiers":[
        {
            "category":"Health Services",
            "subcategory":"Clinic",
            "type":"Services"
        }
    ],
    "sg:phone":"+1 718 399 7649",
    "sg:postcode":"11238",
    "sg:province":"NY",
    "sg:tags":[
        "osteopathic"
    ],
    "wof:name":"Desmond Brown Md",
    "wof:placetype":"venue"
},
  "geometry": {"coordinates":[-73.963162,40.67463],"type":"Point"}
}