{
  "type": "Feature",
  "properties": {
    "iso:country":"US",
    "sg:address":"17 Wyckoff Ave",
    "sg:city":"Port Jefferson Station",
    "sg:classifiers":[
        {
            "category":"Building & Trades",
            "subcategory":"Construction",
            "type":"Services"
        }
    ],
    "sg:phone":"+1 631 928 5325",
    "sg:postcode":"11776",
    "sg:province":"NY",
    "sg:tags":[
        "hanging",
        "contractor"
    ],
    "wof:name":"GL Painting",
    "wof:placetype":"venue"
},
  "geometry": {"coordinates":[-73.04826799999999,40.927814],"type":"Point"}
}