{
  "type": "Feature",
  "properties": {
    "addr:full":"305 1st Ave Frnt A New York NY 10003",
    "addr:housenumber":"305",
    "addr:postcode":"10003",
    "addr:street":"1St Ave;A",
    "iso:country":"US",
    "sg:address":"305 1st Ave Frnt A",
    "sg:city":"New York",
    "sg:classifiers":[
        {
            "category":"Health Services",
            "subcategory":"Doctor",
            "type":"Services"
        },
        {
            "category":"Health Services",
            "subcategory":"Hospital",
            "type":"Services"
        }
    ],
    "sg:phone":"+1 212 420 4383",
    "sg:postcode":"10003",
    "sg:province":"NY",
    "wof:name":"Beth Israel Medical Center",
    "wof:placetype":"venue"
},
  "geometry": {"coordinates":[-73.981088,40.733638],"type":"Point"}
}