{
  "type": "Feature",
  "properties": {
    "iso:country":"US",
    "sg:address":"58 State Hwy 59",
    "sg:city":"Monsey",
    "sg:classifiers":[
        {
            "category":"Home & Garden",
            "subcategory":"Furniture",
            "type":"Retail Goods"
        }
    ],
    "sg:phone":"+1 845 425 7444",
    "sg:postcode":"10952",
    "sg:province":"NY",
    "sg:tags":[
        "juvenile"
    ],
    "wof:name":"Braun's Juvenile Furniture",
    "wof:placetype":"venue"
},
  "geometry": {"coordinates":[-74.065775,41.107726],"type":"Point"}
}