{
  "type": "Feature",
  "properties": {
    "addr:full":"3159 E Brutus St Weedsport NY 13166",
    "addr:housenumber":"3159",
    "addr:postcode":"13166",
    "addr:street":"E Brutus St",
    "iso:country":"US",
    "sg:address":"3159 E Brutus St",
    "sg:city":"Weedsport",
    "sg:classifiers":[
        {
            "category":"Farming",
            "subcategory":"Dairy Farm",
            "type":"Manufacturing & Wholesale Goods"
        }
    ],
    "sg:phone":"+1 315 834 9510",
    "sg:postcode":"13166",
    "sg:province":"NY",
    "wof:name":"Oconnor Farm",
    "wof:placetype":"venue"
},
  "geometry": {"coordinates":[-76.527264,43.040291],"type":"Point"}
}