{
  "type": "Feature",
  "properties": {
    "addr:full":"166 Main St Nyack NY 10960",
    "addr:housenumber":"166",
    "addr:postcode":"10960",
    "addr:street":"Main St",
    "iso:country":"US",
    "sg:address":"166 Main St",
    "sg:city":"Nyack",
    "sg:classifiers":[
        {
            "category":"Restaurant",
            "type":"Food & Drink"
        }
    ],
    "sg:menulink":"http://www.allmenus.com/ny/orangetown/60855-golden-krust/menu/",
    "sg:phone":"+1 845 348 1625",
    "sg:postcode":"10960",
    "sg:province":"NY",
    "sg:tags":[
        "caribbean"
    ],
    "wof:name":"Golden Krust",
    "wof:placetype":"venue"
},
  "geometry": {"coordinates":[-73.92274500000001,41.091657],"type":"Point"}
}