{
  "type": "Feature",
  "properties": {
    "addr:full":"151 W 40 St New York NY 10018",
    "addr:housenumber":"151",
    "addr:postcode":"10018",
    "addr:street":"W 40 St",
    "iso:country":"US",
    "sg:address":"151 W 40 St",
    "sg:city":"New York",
    "sg:classifiers":[
        {
            "category":"Professional",
            "type":"Services"
        }
    ],
    "sg:phone":"+1 212 221 0235",
    "sg:postcode":"10018",
    "sg:province":"NY",
    "sg:tags":[
        "establishment"
    ],
    "wof:name":"Data Basics Corp",
    "wof:placetype":"venue"
},
  "geometry": {"coordinates":[-73.987661,40.754708],"type":"Point"}
}