{
  "type": "Feature",
  "properties": {
    "iso:country":"US",
    "sg:address":"6 Vikings Ct",
    "sg:city":"Bohemia",
    "sg:classifiers":[
        {
            "category":"Building & Trades",
            "subcategory":"Electrical",
            "type":"Services"
        }
    ],
    "sg:phone":"+1 631 225 7890",
    "sg:postcode":"11716",
    "sg:province":"NY",
    "sg:tags":[
        "electric",
        "contractor"
    ],
    "wof:name":"Northstar Electrical Svc",
    "wof:placetype":"venue"
},
  "geometry": {"coordinates":[-73.12134,40.754578],"type":"Point"}
}