{
  "type": "Feature",
  "properties": {
    "addr:full":"735 Mulberry Pl Valley Stream NY 11581",
    "addr:housenumber":"735",
    "addr:postcode":"11581",
    "addr:street":"Mulberry Pl",
    "iso:country":"US",
    "sg:address":"735 Mulberry Pl",
    "sg:city":"Valley Stream",
    "sg:classifiers":[
        {
            "category":"Professional",
            "subcategory":"Advertising",
            "type":"Services"
        }
    ],
    "sg:phone":"+1 516 791 6788",
    "sg:postcode":"11581",
    "sg:province":"NY",
    "sg:tags":[
        "medium",
        "buying"
    ],
    "wof:name":"All Media Inc",
    "wof:placetype":"venue"
},
  "geometry": {"coordinates":[-73.728178,40.648135],"type":"Point"}
}