{
  "type": "Feature",
  "properties": {
    "addr:full":"7201 Schuyler Rd East Syracuse NY 13057",
    "addr:housenumber":"7201",
    "addr:postcode":"13057",
    "addr:street":"Schuyler Rd",
    "iso:country":"US",
    "sg:address":"7201 Schuyler Rd",
    "sg:city":"East Syracuse",
    "sg:classifiers":[
        {
            "category":"Freight",
            "type":"Transportation"
        }
    ],
    "sg:phone":"+1 315 452 5611",
    "sg:postcode":"13057",
    "sg:province":"NY",
    "sg:tags":[
        "trucking"
    ],
    "sg:website":"www.nemf.com",
    "wof:name":"New England Motor Freight",
    "wof:placetype":"venue"
},
  "geometry": {"coordinates":[-76.07339,43.121188],"type":"Point"}
}