{
  "type": "Feature",
  "properties": {
    "addr:full":"1 Commons Dr Lake Katrine NY 12449",
    "addr:housenumber":"1",
    "addr:postcode":"12449",
    "addr:street":"Commons Dr",
    "iso:country":"US",
    "sg:address":"1 Commons Dr",
    "sg:city":"Lake Katrine",
    "sg:classifiers":[
        {
            "category":"Real Estate",
            "subcategory":"Developer",
            "type":"Services"
        }
    ],
    "sg:phone":"+1 845 336 6666",
    "sg:postcode":"12449",
    "sg:province":"NY",
    "sg:website":"www.tenbroeckcommons.com",
    "wof:name":"Ten Broeck Commons",
    "wof:placetype":"venue"
},
  "geometry": {"coordinates":[-73.99615799999999,41.991943],"type":"Point"}
}