{
  "type": "Feature",
  "properties": {
    "addr:full":"2108 Merrick Ave Merrick NY 11566",
    "addr:housenumber":"2108",
    "addr:postcode":"11566",
    "addr:street":"Merrick Ave",
    "iso:country":"US",
    "sg:address":"2108 Merrick Ave",
    "sg:city":"Merrick",
    "sg:classifiers":[
        {
            "category":"Health Services",
            "subcategory":"Health Practitioner",
            "type":"Services"
        }
    ],
    "sg:phone":"+1 516 868 5302",
    "sg:postcode":"11566",
    "sg:province":"NY",
    "sg:tags":[
        "occupational",
        "therapist"
    ],
    "wof:name":"South Shore Hand Therapy",
    "wof:placetype":"venue"
},
  "geometry": {"coordinates":[-73.553833,40.667759],"type":"Point"}
}