{
  "type": "Feature",
  "properties": {
    "addr:full":"172 8th Ave New York NY 10011",
    "addr:housenumber":"172",
    "addr:postcode":"10011",
    "addr:street":"8Th Ave",
    "iso:country":"US",
    "sg:address":"172 8th Ave",
    "sg:city":"New York",
    "sg:classifiers":[
        {
            "category":"Restaurant",
            "type":"Food & Drink"
        }
    ],
    "sg:menulink":"http://www.allmenus.com/ny/new-york/19661-thai-restaurant/menu/",
    "sg:phone":"+1 212 243 2153",
    "sg:postcode":"10011",
    "sg:province":"NY",
    "sg:tags":[
        "thai",
        "asian"
    ],
    "wof:name":"Thai Restaurant",
    "wof:placetype":"venue"
},
  "geometry": {"coordinates":[-74.000124,40.742495],"type":"Point"}
}