{
  "type": "Feature",
  "properties": {
    "addr:full":"2161 Starling Ave Bronx NY 10462",
    "addr:housenumber":"2161",
    "addr:postcode":"10462",
    "addr:street":"Starling Ave",
    "iso:country":"US",
    "sg:address":"2161 Starling Ave",
    "sg:city":"Bronx",
    "sg:classifiers":[
        {
            "category":"Professional",
            "type":"Services"
        }
    ],
    "sg:phone":"+1   ",
    "sg:postcode":"10462",
    "sg:province":"NY",
    "wof:name":"Lened Corporation",
    "wof:placetype":"venue"
},
  "geometry": {"coordinates":[-73.85220700000001,40.836347],"type":"Point"}
}