{
  "type": "Feature",
  "properties": {
    "iso:country":"US",
    "sg:address":"476 Expressway Dr S",
    "sg:city":"Medford",
    "sg:classifiers":[
        {
            "category":"Real Estate",
            "subcategory":"Architect",
            "type":"Services"
        }
    ],
    "sg:phone":"+1 631 654 4949",
    "sg:postcode":"11763",
    "sg:province":"NY",
    "sg:tags":[
        "architectural"
    ],
    "wof:name":"Robert J Gruber Architect",
    "wof:placetype":"venue"
},
  "geometry": {"coordinates":[-72.989929,40.822942],"type":"Point"}
}