{
  "type": "Feature",
  "properties": {
    "iso:country":"US",
    "sg:address":"4 Cord Dr",
    "sg:city":"Latham",
    "sg:classifiers":[
        {
            "category":"Restaurant",
            "type":"Food & Drink"
        }
    ],
    "sg:phone":"+1 518 237 0747",
    "sg:postcode":"12110",
    "sg:province":"NY",
    "wof:name":"Reeher Enterprises",
    "wof:placetype":"venue"
},
  "geometry": {"coordinates":[-73.738287,42.751958],"type":"Point"}
}