{
  "type": "Feature",
  "properties": {
    "iso:country":"US",
    "sg:address":"265 Union St",
    "sg:city":"Hamburg",
    "sg:classifiers":[
        {
            "category":"Professional",
            "subcategory":"Secretarial Services",
            "type":"Services"
        }
    ],
    "sg:phone":"+1 716 649 0094",
    "sg:postcode":"14075",
    "sg:province":"NY",
    "sg:tags":[
        "resume"
    ],
    "wof:name":"Orison Services",
    "wof:placetype":"venue"
},
  "geometry": {"coordinates":[-78.84147400000001,42.718674],"type":"Point"}
}