{
  "type": "Feature",
  "properties": {
    "addr:full":"320 E 59 St New York NY 10022",
    "addr:housenumber":"320;59",
    "addr:postcode":"10022",
    "addr:street":"E;St",
    "iso:country":"US",
    "sg:address":"320 E 59 St",
    "sg:city":"New York",
    "sg:classifiers":[
        {
            "category":"Wholesale",
            "subcategory":"Construction Materials",
            "type":"Manufacturing & Wholesale Goods"
        }
    ],
    "sg:phone":"+1 212 906 1970",
    "sg:postcode":"10022",
    "sg:province":"NY",
    "sg:tags":[
        "granite",
        "marble"
    ],
    "wof:name":"Stonebridge At 59th",
    "wof:placetype":"venue"
},
  "geometry": {"coordinates":[-73.962087,40.759601],"type":"Point"}
}