{
  "type": "Feature",
  "properties": {
    "addr:full":"173 Circular St Saratoga Springs NY 12866",
    "addr:housenumber":"173",
    "addr:postcode":"12866",
    "addr:street":"Circular St",
    "iso:country":"US",
    "sg:address":"173 Circular St",
    "sg:city":"Saratoga Springs",
    "sg:classifiers":[
        {
            "category":"Museum",
            "type":"Entertainment"
        }
    ],
    "sg:phone":"+1   ",
    "sg:postcode":"12866",
    "sg:province":"NY",
    "sg:tags":[
        "consulting",
        "gallery",
        "business"
    ],
    "wof:name":"Anne Diggory",
    "wof:placetype":"venue"
},
  "geometry": {"coordinates":[-73.779668,43.083731],"type":"Point"}
}