{
  "type": "Feature",
  "properties": {
    "addr:full":"308 W Bloomfield St Rome NY 13440",
    "addr:housenumber":"308",
    "addr:postcode":"13440",
    "addr:street":"W Bloomfield St",
    "iso:country":"US",
    "sg:address":"308 W Bloomfield St",
    "sg:city":"Rome",
    "sg:classifiers":[
        {
            "category":"Organizations",
            "subcategory":"Non-profit Organization",
            "type":"Services"
        },
        {
            "category":"Museum",
            "type":"Entertainment"
        }
    ],
    "sg:phone":"+1 315 336 1040",
    "sg:postcode":"13440",
    "sg:province":"NY",
    "sg:tags":[
        "gallery",
        "gift"
    ],
    "wof:name":"Rome Art & Community Center",
    "wof:placetype":"venue"
},
  "geometry": {"coordinates":[-75.458139,43.220037],"type":"Point"}
}