{
  "type": "Feature",
  "properties": {
    "iso:country":"US",
    "sg:address":"206 Beach 116th St",
    "sg:city":"Rockaway Park",
    "sg:classifiers":[
        {
            "category":"Shopping",
            "subcategory":"Tobacco",
            "type":"Retail Goods"
        },
        {
            "category":"Food & Beverages",
            "subcategory":"Groceries & Convenience Stores",
            "type":"Retail Goods"
        }
    ],
    "sg:phone":"+1 718 634 1684",
    "sg:postcode":"11694",
    "sg:province":"NY",
    "sg:tags":[
        "shop"
    ],
    "wof:name":"116 Rockaway Park Stationers Inc",
    "wof:placetype":"venue"
},
  "geometry": {"coordinates":[-73.837097,40.580002],"type":"Point"}
}