{
  "type": "Feature",
  "properties": {
    "addr:full":"47 Genesee Country Mall Batavia NY 14020",
    "addr:housenumber":"47",
    "addr:postcode":"14020",
    "addr:street":"Genesee Country Mall",
    "iso:country":"US",
    "sg:address":"47 Genesee Country Mall",
    "sg:city":"Batavia",
    "sg:classifiers":[
        {
            "category":"Health Services",
            "subcategory":"Doctor",
            "type":"Services"
        }
    ],
    "sg:phone":"+1 585 343 2611",
    "sg:postcode":"14020",
    "sg:province":"NY",
    "sg:tags":[
        "physician",
        "surgeon",
        "medical"
    ],
    "wof:name":"Batavia Pediatrics",
    "wof:placetype":"venue"
},
  "geometry": {"coordinates":[-78.185047,42.998614],"type":"Point"}
}