{
  "type": "Feature",
  "properties": {
    "iso:country":"US",
    "sg:address":"145 Wolf Rd",
    "sg:city":"Albany",
    "sg:classifiers":[
        {
            "category":"Organizations",
            "subcategory":"Religious Organization",
            "type":"Services"
        }
    ],
    "sg:phone":"+1 518 459 2854",
    "sg:postcode":"12205",
    "sg:province":"NY",
    "wof:name":"Saint Francis Chapel",
    "wof:placetype":"venue"
},
  "geometry": {"coordinates":[-73.805801,42.718993],"type":"Point"}
}