{
  "type": "Feature",
  "properties": {
    "addr:full":"112 Graham Ave Brooklyn NY 11206",
    "addr:housenumber":"112",
    "addr:postcode":"11206",
    "addr:street":"Graham Ave",
    "iso:country":"US",
    "sg:address":"112 Graham Ave",
    "sg:city":"Brooklyn",
    "sg:classifiers":[
        {
            "category":"Home & Garden",
            "subcategory":"Home Furnishings",
            "type":"Retail Goods"
        }
    ],
    "sg:phone":"+1   ",
    "sg:postcode":"11206",
    "sg:province":"NY",
    "sg:tags":[
        "department",
        "store"
    ],
    "wof:name":"Casabrata",
    "wof:placetype":"venue"
},
  "geometry": {"coordinates":[-73.942699,40.704571],"type":"Point"}
}