{
  "type": "Feature",
  "properties": {
    "addr:full":"3 Hamilton Pl Clinton NY 13323",
    "addr:housenumber":"3",
    "addr:postcode":"13323",
    "addr:street":"Hamilton Pl",
    "iso:country":"US",
    "sg:address":"3 Hamilton Pl",
    "sg:city":"Clinton",
    "sg:classifiers":[
        {
            "category":"Wholesale",
            "subcategory":"Non-durable Goods",
            "type":"Manufacturing & Wholesale Goods"
        }
    ],
    "sg:phone":"+1 315 853 4437",
    "sg:postcode":"13323",
    "sg:province":"NY",
    "wof:name":"Impressions Unlimited",
    "wof:placetype":"venue"
},
  "geometry": {"coordinates":[-75.385004,43.048247],"type":"Point"}
}