{
  "type": "Feature",
  "properties": {
    "addr:full":"41 State Hwy 210 Stony Point NY 10980",
    "addr:housenumber":"41",
    "addr:postcode":"10980",
    "addr:street":"State Hwy 210",
    "iso:country":"US",
    "sg:address":"41 State Hwy 210",
    "sg:city":"Stony Point",
    "sg:classifiers":[
        {
            "category":"Building & Trades",
            "subcategory":"Construction",
            "type":"Services"
        }
    ],
    "sg:phone":"+1 845 429 1787",
    "sg:postcode":"10980",
    "sg:province":"NY",
    "sg:tags":[
        "carpentry",
        "contractor"
    ],
    "wof:name":"Kevin ODell Carpentry",
    "wof:placetype":"venue"
},
  "geometry": {"coordinates":[-73.988348,41.22627],"type":"Point"}
}