{
  "type": "Feature",
  "properties": {
    "addr:full":"581 Stewart Ave Garden City NY 11530",
    "addr:housenumber":"581",
    "addr:postcode":"11530",
    "addr:street":"Stewart Ave",
    "iso:country":"US",
    "sg:address":"581 Stewart Ave",
    "sg:city":"Garden City",
    "sg:classifiers":[
        {
            "category":"Professional",
            "subcategory":"Printing & Photocopies",
            "type":"Services"
        }
    ],
    "sg:phone":"+1   ",
    "sg:postcode":"11530",
    "sg:province":"NY",
    "sg:tags":[
        "photocopying",
        "work"
    ],
    "wof:name":"Kinkos",
    "wof:placetype":"venue"
},
  "geometry": {"coordinates":[-73.61612100000001,40.730662],"type":"Point"}
}