{
  "type": "Feature",
  "properties": {
    "addr:full":"259 E Broadway New York NY 10002",
    "addr:housenumber":"259",
    "addr:postcode":"10002",
    "addr:street":"E Broadway",
    "iso:country":"US",
    "sg:address":"259 E Broadway",
    "sg:city":"New York",
    "sg:classifiers":[
        {
            "category":"Retail",
            "subcategory":"Repair Shop",
            "type":"Services"
        }
    ],
    "sg:phone":"+1 212 518 2603",
    "sg:postcode":"10002",
    "sg:province":"NY",
    "sg:tags":[
        "lock",
        "key",
        "locksmith"
    ],
    "wof:name":"24 Hour Emergency Locksmith",
    "wof:placetype":"venue"
},
  "geometry": {"coordinates":[-73.985867,40.714524],"type":"Point"}
}