{
  "type": "Feature",
  "properties": {
    "addr:full":"20 E 53 St New York NY 10022",
    "addr:housenumber":"20;53",
    "addr:postcode":"10022",
    "addr:street":"E",
    "iso:country":"US",
    "sg:address":"20 E 53 St",
    "sg:city":"New York",
    "sg:classifiers":[
        {
            "category":"Shopping",
            "subcategory":"Clothing, Apparel, & Fashions",
            "type":"Retail Goods"
        }
    ],
    "sg:phone":"+1   ",
    "sg:postcode":"10022",
    "sg:province":"NY",
    "wof:name":"Duca Sartoria",
    "wof:placetype":"venue"
},
  "geometry": {"coordinates":[-73.975256,40.760229],"type":"Point"}
}