{
  "type": "Feature",
  "properties": {
    "addr:full":"652 Central Park Ave Yonkers NY 10704",
    "addr:housenumber":"652",
    "addr:postcode":"10704",
    "addr:street":"Central Park Ave",
    "iso:country":"US",
    "sg:address":"652 Central Park Ave",
    "sg:city":"Yonkers",
    "sg:classifiers":[
        {
            "category":"Food & Beverages",
            "subcategory":"Groceries & Convenience Stores",
            "type":"Retail Goods"
        }
    ],
    "sg:phone":"+1 914 375 1722",
    "sg:postcode":"10704",
    "sg:province":"NY",
    "sg:tags":[
        "grocer"
    ],
    "wof:name":"T S Thai Grocery",
    "wof:placetype":"venue"
},
  "geometry": {"coordinates":[-73.86007499999999,40.922918],"type":"Point"}
}