{
  "type": "Feature",
  "properties": {
    "addr:full":"5 S Allen St Albany NY 12208",
    "addr:housenumber":"5",
    "addr:postcode":"12208",
    "addr:street":"S Allen St",
    "iso:country":"US",
    "sg:address":"5 S Allen St",
    "sg:city":"Albany",
    "sg:classifiers":[
        {
            "category":"Manufacturing",
            "subcategory":"Retail Goods",
            "type":"Manufacturing & Wholesale Goods"
        }
    ],
    "sg:phone":"+1 518 435 1609",
    "sg:postcode":"12208",
    "sg:province":"NY",
    "sg:tags":[
        "equipment",
        "fingerprinting"
    ],
    "sg:website":"www.fingerprintamerica.com",
    "wof:name":"Fingerprint America",
    "wof:placetype":"venue"
},
  "geometry": {"coordinates":[-73.79256700000001,42.66597],"type":"Point"}
}