{
  "type": "Feature",
  "properties": {
    "addr:full":"86 Hatch Rd Hermon NY 13652",
    "addr:housenumber":"86",
    "addr:postcode":"13652",
    "addr:street":"Hatch Rd",
    "iso:country":"US",
    "sg:address":"86 Hatch Rd",
    "sg:city":"Hermon",
    "sg:classifiers":[
        {
            "category":"Organizations",
            "subcategory":"Religious Organization",
            "type":"Services"
        }
    ],
    "sg:phone":"+1 315 347 3728",
    "sg:postcode":"13652",
    "sg:province":"NY",
    "wof:name":"Christian Retreat",
    "wof:placetype":"venue"
},
  "geometry": {"coordinates":[-75.19300699999999,44.400358],"type":"Point"}
}