{
  "type": "Feature",
  "properties": {
    "iso:country":"US",
    "sg:address":"6721 Woodside Ave",
    "sg:city":"Woodside",
    "sg:classifiers":[
        {
            "category":"Restaurant",
            "type":"Food & Drink"
        }
    ],
    "sg:phone":"+1 718 458 8588",
    "sg:postcode":"11377",
    "sg:province":"NY",
    "sg:tags":[
        "chinese"
    ],
    "sg:website":"www.chuyingwoodside.com",
    "wof:name":"Chu Ying Chinese Restaurant",
    "wof:placetype":"venue"
},
  "geometry": {"coordinates":[-73.897199,40.743044],"type":"Point"}
}