{
  "type": "Feature",
  "properties": {
    "addr:full":"65 Steuben St Brooklyn NY 11205",
    "addr:housenumber":"65",
    "addr:postcode":"11205",
    "addr:street":"Steuben St",
    "iso:country":"US",
    "sg:address":"65 Steuben St",
    "sg:city":"Brooklyn",
    "sg:classifiers":[
        {
            "category":"Manufacturing",
            "subcategory":"Food",
            "type":"Manufacturing & Wholesale Goods"
        }
    ],
    "sg:phone":"+1   ",
    "sg:postcode":"11205",
    "sg:province":"NY",
    "sg:tags":[
        "grocery",
        "mfg"
    ],
    "wof:name":"Chuster Noodle Packaging Corp",
    "wof:placetype":"venue"
},
  "geometry": {"coordinates":[-73.96308999999999,40.693963],"type":"Point"}
}