{
  "type": "Feature",
  "properties": {
    "addr:full":"2096 Madison Ave New York NY 10037",
    "addr:housenumber":"2096",
    "addr:postcode":"10037",
    "addr:street":"Madison Ave",
    "iso:country":"US",
    "sg:address":"2096 Madison Ave",
    "sg:city":"New York",
    "sg:classifiers":[
        {
            "category":"Food & Beverages",
            "subcategory":"Groceries & Convenience Stores",
            "type":"Retail Goods"
        }
    ],
    "sg:phone":"+1 212 283 1213",
    "sg:postcode":"10037",
    "sg:province":"NY",
    "sg:tags":[
        "market"
    ],
    "wof:name":"Madison Deli Food Market Inc",
    "wof:placetype":"venue"
},
  "geometry": {"coordinates":[-73.93740099999999,40.809898],"type":"Point"}
}