{
  "type": "Feature",
  "properties": {
    "addr:full":"2880 Grand Ave Baldwin NY 11510",
    "addr:housenumber":"2880",
    "addr:postcode":"11510",
    "addr:street":"Grand Ave",
    "iso:country":"US",
    "sg:address":"2880 Grand Ave",
    "sg:city":"Baldwin",
    "sg:classifiers":[
        {
            "category":"Restaurant",
            "type":"Food & Drink"
        }
    ],
    "sg:menulink":"http://www.allmenus.com/ny/baldwin/241343-wander-inn/menu/",
    "sg:phone":"+1 516 223 5925",
    "sg:postcode":"11510",
    "sg:province":"NY",
    "sg:tags":[
        "italian"
    ],
    "wof:name":"Wander Inn",
    "wof:placetype":"venue"
},
  "geometry": {"coordinates":[-73.61290700000001,40.639084],"type":"Point"}
}