{
  "type": "Feature",
  "properties": {
    "addr:full":"3120 Quentin Rd Brooklyn NY 11234",
    "addr:housenumber":"3120",
    "addr:postcode":"11234",
    "addr:street":"Quentin Rd",
    "iso:country":"US",
    "sg:address":"3120 Quentin Rd",
    "sg:city":"Brooklyn",
    "sg:classifiers":[
        {
            "category":"Retail",
            "subcategory":"Laundry & Dry Cleaning",
            "type":"Services"
        }
    ],
    "sg:phone":"+1 718 998 5152",
    "sg:postcode":"11234",
    "sg:province":"NY",
    "sg:tags":[
        "cleaner",
        "plant",
        "drycleaning"
    ],
    "wof:name":"Cleo's Alterations",
    "wof:placetype":"venue"
},
  "geometry": {"coordinates":[-73.939697,40.612598],"type":"Point"}
}