{
  "type": "Feature",
  "properties": {
    "iso:country":"US",
    "sg:address":"90 Bridge St",
    "sg:city":"Carthage",
    "sg:classifiers":[
        {
            "category":"Food & Beverages",
            "subcategory":"Groceries & Convenience Stores",
            "type":"Retail Goods"
        }
    ],
    "sg:phone":"+1 315 493 6077",
    "sg:postcode":"13619",
    "sg:province":"NY",
    "wof:name":"Nice N Easy",
    "wof:placetype":"venue"
},
  "geometry": {"coordinates":[-75.621787,43.968378],"type":"Point"}
}