{
  "type": "Feature",
  "properties": {
    "iso:country":"US",
    "sg:address":"134 Dawnbrook Ln",
    "sg:city":"Buffalo",
    "sg:classifiers":[
        {
            "category":"Wholesale",
            "subcategory":"Sporting Goods",
            "type":"Manufacturing & Wholesale Goods"
        }
    ],
    "sg:phone":"+1 716 634 1533",
    "sg:postcode":"14221",
    "sg:province":"NY",
    "wof:name":"Howard W Georger Inc",
    "wof:placetype":"venue"
},
  "geometry": {"coordinates":[-78.770477,42.975498],"type":"Point"}
}