{
  "type": "Feature",
  "properties": {
    "iso:country":"US",
    "sg:address":"135 Oak St",
    "sg:city":"Yonkers",
    "sg:classifiers":[
        {
            "category":"Retail",
            "subcategory":"Auto Repair",
            "type":"Services"
        }
    ],
    "sg:phone":"+1 914 423 6789",
    "sg:postcode":"10701",
    "sg:province":"NY",
    "sg:tags":[
        "repairing",
        "automobile"
    ],
    "wof:name":"R-C Auto Repairs",
    "wof:placetype":"venue"
},
  "geometry": {"coordinates":[-73.89083599999999,40.929773],"type":"Point"}
}