{
  "type": "Feature",
  "properties": {
    "addr:full":"1948 State Hwy 7b Harpursville NY 13787",
    "addr:housenumber":"1948",
    "addr:postcode":"13787",
    "addr:street":"State Hwy 7B",
    "iso:country":"US",
    "sg:address":"1948 State Hwy 7b",
    "sg:city":"Harpursville",
    "sg:classifiers":[
        {
            "category":"Social Services",
            "subcategory":"Child Care",
            "type":"Services"
        }
    ],
    "sg:phone":"+1   ",
    "sg:postcode":"13787",
    "sg:province":"NY",
    "sg:tags":[
        "retail",
        "direct",
        "day",
        "sales"
    ],
    "wof:name":"Sabrina D Bixby",
    "wof:placetype":"venue"
},
  "geometry": {"coordinates":[-75.69000200000001,42.199891],"type":"Point"}
}