{
  "type": "Feature",
  "properties": {
    "addr:full":"9231 57th Avenue Elmhurst NY 11373",
    "addr:housenumber":"9231",
    "addr:postcode":"11373",
    "addr:street":"57Th Avenue",
    "iso:country":"US",
    "sg:address":"9231 57th Avenue",
    "sg:city":"Elmhurst",
    "sg:classifiers":[
        {
            "category":"Health Services",
            "subcategory":"Doctor",
            "type":"Services"
        }
    ],
    "sg:phone":"+1 718 592 1731",
    "sg:postcode":"11373",
    "sg:province":"NY",
    "wof:name":"Gontzes Peter MD PC",
    "wof:placetype":"venue"
},
  "geometry": {"coordinates":[-73.86932899999999,40.735714],"type":"Point"}
}