{
  "type": "Feature",
  "properties": {
    "iso:country":"US",
    "sg:address":"2005 Lyell Ave",
    "sg:city":"Rochester",
    "sg:classifiers":[
        {
            "category":"Health Services",
            "subcategory":"Doctor",
            "type":"Services"
        }
    ],
    "sg:phone":"+1   ",
    "sg:postcode":"14606",
    "sg:province":"NY",
    "sg:tags":[
        "clinic",
        "dentist"
    ],
    "wof:name":"Wm E Ciluffo DDS",
    "wof:placetype":"venue"
},
  "geometry": {"coordinates":[-77.678382,43.164619],"type":"Point"}
}