{
  "type": "Feature",
  "properties": {
    "addr:full":"10170 Lefferts Blvd South Richmond Hill NY 11419",
    "addr:housenumber":"10170",
    "addr:postcode":"11419",
    "addr:street":"Lefferts Blvd South",
    "iso:country":"US",
    "sg:address":"10170 Lefferts Blvd",
    "sg:city":"South Richmond Hill",
    "sg:classifiers":[
        {
            "category":"Professional",
            "subcategory":"Lawyer & Legal Services",
            "type":"Services"
        }
    ],
    "sg:phone":"+1 718 850 1952",
    "sg:postcode":"11419",
    "sg:province":"NY",
    "wof:name":"Law Offices Anand Ahuja",
    "wof:placetype":"venue"
},
  "geometry": {"coordinates":[-73.82579800000001,40.689301],"type":"Point"}
}