{
  "type": "Feature",
  "properties": {
    "iso:country":"US",
    "sg:address":"120 Debucks Dr",
    "sg:city":"Pine Island",
    "sg:classifiers":[
        {
            "category":"Farming",
            "subcategory":"Farm",
            "type":"Manufacturing & Wholesale Goods"
        }
    ],
    "sg:phone":"+1 845 258 4131",
    "sg:postcode":"10969",
    "sg:province":"NY",
    "sg:tags":[
        "food",
        "covered",
        "crop"
    ],
    "wof:name":"Debucks Sod Farm",
    "wof:placetype":"venue"
},
  "geometry": {"coordinates":[-74.504525,41.291042],"type":"Point"}
}