{
  "type": "Feature",
  "properties": {
    "addr:full":"8 N Main St Lyndonville NY 14098",
    "addr:housenumber":"8",
    "addr:postcode":"14098",
    "addr:street":"N Main St",
    "iso:country":"US",
    "sg:address":"8 N Main St",
    "sg:city":"Lyndonville",
    "sg:classifiers":[
        {
            "category":"Restaurant",
            "type":"Food & Drink"
        }
    ],
    "sg:phone":"+1 585 765 2893",
    "sg:postcode":"14098",
    "sg:province":"NY",
    "wof:name":"Bill's Sub Shop",
    "wof:placetype":"venue"
},
  "geometry": {"coordinates":[-78.38869800000001,43.322195],"type":"Point"}
}