{
  "type": "Feature",
  "properties": {
    "iso:country":"US",
    "sg:address":"615 E Hamilton Ave",
    "sg:city":"Sherrill",
    "sg:classifiers":[
        {
            "category":"Wholesale",
            "subcategory":"Toys & Hobbies",
            "type":"Manufacturing & Wholesale Goods"
        }
    ],
    "sg:phone":"+1 315 363 4923",
    "sg:postcode":"13461",
    "sg:province":"NY",
    "wof:name":"Hotaling Imports Inc",
    "wof:placetype":"venue"
},
  "geometry": {"coordinates":[-75.594566,43.061003],"type":"Point"}
}