{
  "type": "Feature",
  "properties": {
    "addr:full":"1800 Popham Avenue Lbby Bronx NY 10453",
    "addr:housenumber":"1800",
    "addr:postcode":"10453",
    "addr:street":"Popham Avenue",
    "iso:country":"US",
    "sg:address":"1800 Popham Avenue Lbby",
    "sg:city":"Bronx",
    "sg:classifiers":[
        {
            "category":"Real Estate",
            "subcategory":"Real Estate Operator",
            "type":"Services"
        }
    ],
    "sg:phone":"+1 718 731 4331",
    "sg:postcode":"10453",
    "sg:province":"NY",
    "sg:tags":[
        "apartment"
    ],
    "wof:name":"Andrews Plaza",
    "wof:placetype":"venue"
},
  "geometry": {"coordinates":[-73.91812299999999,40.851478],"type":"Point"}
}