{
  "type": "Feature",
  "properties": {
    "addr:full":"844 Flatbush Ave Brooklyn NY 11226",
    "addr:housenumber":"844",
    "addr:postcode":"11226",
    "addr:street":"Flatbush Ave",
    "iso:country":"US",
    "sg:address":"844 Flatbush Ave",
    "sg:city":"Brooklyn",
    "sg:classifiers":[
        {
            "category":"Personal",
            "subcategory":"Beauty Salon",
            "type":"Services"
        }
    ],
    "sg:phone":"+1 718 462 9853",
    "sg:postcode":"11226",
    "sg:province":"NY",
    "wof:name":"Elite Salon",
    "wof:placetype":"venue"
},
  "geometry": {"coordinates":[-73.95905999999999,40.651532],"type":"Point"}
}