{
  "type": "Feature",
  "properties": {
    "addr:full":"367 W 48 St New York NY 10036",
    "addr:housenumber":"367",
    "addr:postcode":"10036",
    "addr:street":"W 48 St",
    "iso:country":"US",
    "sg:address":"367 W 48 St",
    "sg:city":"New York",
    "sg:classifiers":[
        {
            "category":"Travel",
            "subcategory":"Travel Agent",
            "type":"Entertainment"
        }
    ],
    "sg:phone":"+1 212 757 9450",
    "sg:postcode":"10036",
    "sg:province":"NY",
    "sg:tags":[
        "agency",
        "bureau"
    ],
    "wof:name":"Dante Travel Designs",
    "wof:placetype":"venue"
},
  "geometry": {"coordinates":[-73.98837399999999,40.761494],"type":"Point"}
}