{
  "type": "Feature",
  "properties": {
    "addr:full":"671 Lishakill Rd Schenectady NY 12309",
    "addr:housenumber":"671",
    "addr:postcode":"12309",
    "addr:street":"Lishakill Rd",
    "iso:country":"US",
    "sg:address":"671 Lishakill Rd",
    "sg:city":"Schenectady",
    "sg:classifiers":[
        {
            "category":"Home & Garden",
            "subcategory":"Building Materials",
            "type":"Retail Goods"
        }
    ],
    "sg:phone":"+1 518 782 1902",
    "sg:postcode":"12309",
    "sg:province":"NY",
    "wof:name":"C G I Silver Cote",
    "wof:placetype":"venue"
},
  "geometry": {"coordinates":[-73.853551,42.771894],"type":"Point"}
}