{
  "type": "Feature",
  "properties": {
    "addr:full":"134 West 29th Street Suite 1010 New York City NY 10001",
    "addr:housenumber":"134",
    "addr:postcode":"10001",
    "addr:street":"West 29Th Street Suite 1010",
    "iso:country":"US",
    "sg:address":"134 West 29th Street Suite 1010",
    "sg:city":"New York City",
    "sg:classifiers":[
        {
            "category":"Arts & Performance",
            "subcategory":"Art Gallery",
            "type":"Entertainment"
        }
    ],
    "sg:phone":"+1 212 673 1168",
    "sg:postcode":"10001",
    "sg:province":"NY",
    "sg:website":"www.a-forestgallery.com",
    "wof:name":"A Forest Galley",
    "wof:placetype":"venue"
},
  "geometry": {"coordinates":[-73.991203,40.747002],"type":"Point"}
}