{
  "type": "Feature",
  "properties": {
    "addr:full":"2500 Niagara Falls Blvd Niagara Falls NY 14304",
    "addr:housenumber":"2500",
    "addr:postcode":"14304",
    "addr:street":"Niagara Falls Blvd",
    "iso:country":"US",
    "sg:address":"2500 Niagara Falls Blvd",
    "sg:city":"Niagara Falls",
    "sg:classifiers":[
        {
            "category":"Personal",
            "subcategory":"Beauty Salon",
            "type":"Services"
        }
    ],
    "sg:phone":"+1 716 731 2600",
    "sg:postcode":"14304",
    "sg:province":"NY",
    "wof:name":"Total Solutions",
    "wof:placetype":"venue"
},
  "geometry": {"coordinates":[-78.90142899999999,43.091076],"type":"Point"}
}