{
  "type": "Feature",
  "properties": {
    "addr:full":"7 Petrus Ave Staten Island NY 10312",
    "addr:housenumber":"7",
    "addr:postcode":"10312",
    "addr:street":"Petrus Ave",
    "iso:country":"US",
    "sg:address":"7 Petrus Ave",
    "sg:city":"Staten Island",
    "sg:classifiers":[
        {
            "category":"Personal",
            "subcategory":"Day Spa",
            "type":"Services"
        }
    ],
    "sg:phone":"+1 718 227 3819",
    "sg:postcode":"10312",
    "sg:province":"NY",
    "wof:name":"Feeling Fascial Spa Incorporated",
    "wof:placetype":"venue"
},
  "geometry": {"coordinates":[-74.166405,40.547225],"type":"Point"}
}