{
  "type": "Feature",
  "properties": {
    "addr:full":"3 Stephens Pl Spring Valley NY 10977",
    "addr:housenumber":"3",
    "addr:postcode":"10977",
    "addr:street":"Stephens Pl",
    "iso:country":"US",
    "sg:address":"3 Stephens Pl",
    "sg:city":"Spring Valley",
    "sg:classifiers":[
        {
            "category":"Home & Garden",
            "subcategory":"Home Furnishings",
            "type":"Retail Goods"
        }
    ],
    "sg:phone":"+1   ",
    "sg:postcode":"10977",
    "sg:province":"NY",
    "wof:name":"911 Bulbs Inc",
    "wof:placetype":"venue"
},
  "geometry": {"coordinates":[-74.054174,41.114551],"type":"Point"}
}