{
  "type": "Feature",
  "properties": {
    "addr:full":"6515 Transit Rd Bowmansville NY 14026",
    "addr:housenumber":"6515",
    "addr:postcode":"14026",
    "addr:street":"Transit Rd",
    "iso:country":"US",
    "sg:address":"6515 Transit Rd",
    "sg:city":"Bowmansville",
    "sg:classifiers":[
        {
            "category":"Shopping",
            "type":"Retail Goods"
        }
    ],
    "sg:phone":"+1 716 681 6986",
    "sg:postcode":"14026",
    "sg:province":"NY",
    "sg:tags":[
        "pet",
        "food",
        "supply"
    ],
    "wof:name":"Golden Tails",
    "wof:placetype":"venue"
},
  "geometry": {"coordinates":[-78.696926,42.940403],"type":"Point"}
}