{
  "type": "Feature",
  "properties": {
    "iso:country":"US",
    "sg:address":"54 Main St",
    "sg:city":"Greenwich",
    "sg:classifiers":[
        {
            "category":"Restaurant",
            "type":"Food & Drink"
        }
    ],
    "sg:phone":"+1   ",
    "sg:postcode":"12834",
    "sg:province":"NY",
    "sg:tags":[
        "drinking",
        "eating"
    ],
    "wof:name":"Wallies of Greenwich",
    "wof:placetype":"venue"
},
  "geometry": {"coordinates":[-73.49927,43.090066],"type":"Point"}
}