{
  "type": "Feature",
  "properties": {
    "iso:country":"US",
    "sg:address":"624 3rd Ave",
    "sg:city":"Watervliet",
    "sg:classifiers":[
        {
            "category":"Manufacturing",
            "subcategory":"Tools & Machinery",
            "type":"Manufacturing & Wholesale Goods"
        }
    ],
    "sg:phone":"+1   ",
    "sg:postcode":"12189",
    "sg:province":"NY",
    "sg:tags":[
        "surgical",
        "mfg"
    ],
    "wof:name":"William Dickinson",
    "wof:placetype":"venue"
},
  "geometry": {"coordinates":[-73.706439,42.714009],"type":"Point"}
}