{
  "type": "Feature",
  "properties": {
    "iso:country":"US",
    "sg:address":"286 Clermont Ave",
    "sg:city":"Brooklyn",
    "sg:classifiers":[
        {
            "category":"Professional",
            "subcategory":"Management & Consulting",
            "type":"Services"
        }
    ],
    "sg:phone":"+1 718 852 5004",
    "sg:postcode":"11205",
    "sg:province":"NY",
    "sg:tags":[
        "consultant",
        "business"
    ],
    "wof:name":"Wek 1933",
    "wof:placetype":"venue"
},
  "geometry": {"coordinates":[-73.96988399999999,40.687921],"type":"Point"}
}