{
  "type": "Feature",
  "properties": {
    "iso:country":"US",
    "sg:address":"274 Broadway St",
    "sg:city":"Fort Edward",
    "sg:classifiers":[
        {
            "category":"Real Estate",
            "subcategory":"Real Estate Agent",
            "type":"Services"
        }
    ],
    "sg:phone":"+1 518 747 0525",
    "sg:postcode":"12828",
    "sg:province":"NY",
    "wof:name":"Thoroughbred Realty",
    "wof:placetype":"venue"
},
  "geometry": {"coordinates":[-73.586291,43.278103],"type":"Point"}
}