{
  "type": "Feature",
  "properties": {
    "addr:full":"289 New Dorp Lane Staten Island NY 10306",
    "addr:housenumber":"289",
    "addr:postcode":"10306",
    "addr:street":"New Dorp Lane",
    "iso:country":"US",
    "sg:address":"289 New Dorp Lane",
    "sg:city":"Staten Island",
    "sg:classifiers":[
        {
            "category":"Restaurant",
            "type":"Food & Drink"
        }
    ],
    "sg:phone":"+1 718 980 7725",
    "sg:postcode":"10306",
    "sg:province":"NY",
    "wof:name":"Lento's Restaurant",
    "wof:placetype":"venue"
},
  "geometry": {"coordinates":[-74.111572,40.571573],"type":"Point"}
}