{
  "type": "Feature",
  "properties": {
    "addr:full":"4 Georgetown Oval New City NY 10956",
    "addr:housenumber":"4",
    "addr:postcode":"10956",
    "addr:street":"Georgetown Oval",
    "iso:country":"US",
    "sg:address":"4 Georgetown Oval",
    "sg:city":"New City",
    "sg:classifiers":[
        {
            "category":"Wholesale",
            "subcategory":"Machinery & Supplies",
            "type":"Manufacturing & Wholesale Goods"
        }
    ],
    "sg:phone":"+1 845 638 2470",
    "sg:postcode":"10956",
    "sg:province":"NY",
    "sg:tags":[
        "industrial"
    ],
    "wof:name":"Global Diamond Prods Inc",
    "wof:placetype":"venue"
},
  "geometry": {"coordinates":[-73.96583699999999,41.153883],"type":"Point"}
}