{
  "type": "Feature",
  "properties": {
    "iso:country":"US",
    "sg:address":"8309 White Cedar Cir",
    "sg:city":"Liverpool",
    "sg:classifiers":[
        {
            "category":"Real Estate",
            "subcategory":"Architect",
            "type":"Services"
        }
    ],
    "sg:phone":"+1 315 622 2586",
    "sg:postcode":"13090",
    "sg:province":"NY",
    "sg:tags":[
        "architects'",
        "specification",
        "construction",
        "builders'",
        "architectural"
    ],
    "wof:name":"Mak Assoc",
    "wof:placetype":"venue"
},
  "geometry": {"coordinates":[-76.23071299999999,43.171421],"type":"Point"}
}