{
  "type": "Feature",
  "properties": {
    "iso:country":"US",
    "sg:address":"2018 Belmont Ave",
    "sg:city":"Elmont",
    "sg:classifiers":[
        {
            "category":"Shopping",
            "type":"Retail Goods"
        }
    ],
    "sg:phone":"+1   ",
    "sg:postcode":"11003",
    "sg:province":"NY",
    "sg:tags":[
        "merchandise"
    ],
    "wof:name":"Nassau Rare Coins",
    "wof:placetype":"venue"
},
  "geometry": {"coordinates":[-73.71504400000001,40.699709],"type":"Point"}
}