{
  "type": "Feature",
  "properties": {
    "addr:full":"159 W 96th St New York NY 10025",
    "addr:housenumber":"159",
    "addr:postcode":"10025",
    "addr:street":"W 96Th St",
    "iso:country":"US",
    "sg:address":"159 W 96th St",
    "sg:city":"New York",
    "sg:classifiers":[
        {
            "category":"Building & Trades",
            "subcategory":"Plumbing",
            "type":"Services"
        }
    ],
    "sg:phone":"+1 866 359 0184",
    "sg:postcode":"10025",
    "sg:province":"NY",
    "wof:name":"A Soho Eighth Avenue Plumbing",
    "wof:placetype":"venue"
},
  "geometry": {"coordinates":[-73.96912,40.79369],"type":"Point"}
}