{
  "type": "Feature",
  "properties": {
    "addr:full":"195 Kisco Ave Mt Kisco NY 10549",
    "addr:housenumber":"195",
    "addr:postcode":"10549",
    "addr:street":"Kisco Ave Mt Kisco",
    "iso:country":"US",
    "sg:address":"195 Kisco Ave",
    "sg:city":"Mt Kisco",
    "sg:classifiers":[
        {
            "category":"Shopping",
            "subcategory":"Jewelry",
            "type":"Retail Goods"
        }
    ],
    "sg:phone":"+1 914 244 0648",
    "sg:postcode":"10549",
    "sg:province":"NY",
    "sg:tags":[
        "jeweler"
    ],
    "wof:name":"Jewelry Den",
    "wof:placetype":"venue"
},
  "geometry": {"coordinates":[-73.727805,41.211898],"type":"Point"}
}