{
  "type": "Feature",
  "properties": {
    "addr:full":"3567 Hempstead Tpke Levittown NY 11756",
    "addr:housenumber":"3567",
    "addr:postcode":"11756",
    "addr:street":"Hempstead Tpke",
    "iso:country":"US",
    "sg:address":"3567 Hempstead Tpke",
    "sg:city":"Levittown",
    "sg:classifiers":[
        {
            "category":"Shopping",
            "subcategory":"Hobbies, Toys, & Games",
            "type":"Retail Goods"
        }
    ],
    "sg:phone":"+1 516 796 8800",
    "sg:postcode":"11756",
    "sg:province":"NY",
    "sg:tags":[
        "craft",
        "supply"
    ],
    "sg:website":"www.michaels.com",
    "wof:name":"Michaels Stores",
    "wof:placetype":"venue"
},
  "geometry": {"coordinates":[-73.505737,40.725634],"type":"Point"}
}