{
  "type": "Feature",
  "properties": {
    "addr:full":"513 W Main St Ste 1 Cobleskill NY 12043",
    "addr:housenumber":"513",
    "addr:postcode":"12043",
    "addr:street":"W Main St Ste 1",
    "iso:country":"US",
    "sg:address":"513 W Main St Ste 1",
    "sg:city":"Cobleskill",
    "sg:classifiers":[
        {
            "category":"Shopping",
            "subcategory":"Florist",
            "type":"Retail Goods"
        }
    ],
    "sg:phone":"+1 518 234 4391",
    "sg:postcode":"12043",
    "sg:province":"NY",
    "wof:name":"Speedling Florist Inc",
    "wof:placetype":"venue"
},
  "geometry": {"coordinates":[-74.487353,42.67756],"type":"Point"}
}