{
  "type": "Feature",
  "properties": {
    "addr:full":"2 Macon St Brooklyn NY 11216",
    "addr:housenumber":"2",
    "addr:postcode":"11216",
    "addr:street":"Macon St",
    "iso:country":"US",
    "sg:address":"2 Macon St",
    "sg:city":"Brooklyn",
    "sg:classifiers":[
        {
            "category":"Wholesale",
            "subcategory":"Apparel",
            "type":"Manufacturing & Wholesale Goods"
        }
    ],
    "sg:phone":"+1 718 783 8568",
    "sg:postcode":"11216",
    "sg:province":"NY",
    "wof:name":"Piccadilly Fashions",
    "wof:placetype":"venue"
},
  "geometry": {"coordinates":[-73.949715,40.68107],"type":"Point"}
}