{
  "type": "Feature",
  "properties": {
    "addr:full":"1374 York Ave Manhattan NY 10021",
    "addr:housenumber":"1374",
    "addr:postcode":"10021",
    "addr:street":"York Ave",
    "iso:country":"US",
    "sg:address":"1374 York Ave",
    "sg:city":"Manhattan",
    "sg:classifiers":[
        {
            "category":"Travel",
            "subcategory":"Hostel",
            "type":"Entertainment"
        }
    ],
    "sg:phone":"+1 877 414 7707",
    "sg:postcode":"10021",
    "sg:province":"NY",
    "sg:website":"www.extendedstaybookers.com",
    "wof:name":"East 73rd and York Ave Apartments",
    "wof:placetype":"venue"
},
  "geometry": {"coordinates":[-73.9529,40.767709],"type":"Point"}
}