{
  "type": "Feature",
  "properties": {
    "iso:country":"US",
    "sg:address":"1324 Motor Pkwy",
    "sg:city":"Islandia",
    "sg:classifiers":[
        {
            "category":"Manufacturing",
            "subcategory":"Electronics",
            "type":"Manufacturing & Wholesale Goods"
        }
    ],
    "sg:phone":"+1 631 234 2727",
    "sg:postcode":"11749",
    "sg:province":"NY",
    "sg:tags":[
        "equipment",
        "electronic",
        "supply"
    ],
    "sg:website":"www.nutelwireless.com",
    "wof:name":"Nutel Electronics Inc",
    "wof:placetype":"venue"
},
  "geometry": {"coordinates":[-73.194777,40.805798],"type":"Point"}
}