{
  "type": "Feature",
  "properties": {
    "addr:full":"380 Columbus Ave New York NY 10024",
    "addr:housenumber":"380",
    "addr:postcode":"10024",
    "addr:street":"Columbus Ave",
    "iso:country":"US",
    "sg:address":"380 Columbus Ave",
    "sg:city":"New York",
    "sg:classifiers":[
        {
            "category":"Real Estate",
            "subcategory":"Real Estate Operator",
            "type":"Services"
        }
    ],
    "sg:phone":"+1 212 582 3038",
    "sg:postcode":"10024",
    "sg:province":"NY",
    "sg:tags":[
        "building",
        "apartment"
    ],
    "wof:name":"Joben Realty Associates",
    "wof:placetype":"venue"
},
  "geometry": {"coordinates":[-73.97547900000001,40.781951],"type":"Point"}
}