{
  "type": "Feature",
  "properties": {
    "addr:full":"51 N Main St Albion NY 14411",
    "addr:housenumber":"51",
    "addr:postcode":"14411",
    "addr:street":"N Main St",
    "iso:country":"US",
    "sg:address":"51 N Main St",
    "sg:city":"Albion",
    "sg:classifiers":[
        {
            "category":"Professional",
            "subcategory":"Lawyer & Legal Services",
            "type":"Services"
        }
    ],
    "sg:phone":"+1 585 589 5623",
    "sg:postcode":"14411",
    "sg:province":"NY",
    "sg:tags":[
        "attorney"
    ],
    "wof:name":"Lyman & Lyman LLC",
    "wof:placetype":"venue"
},
  "geometry": {"coordinates":[-78.19365000000001,43.247042],"type":"Point"}
}