{
  "type": "Feature",
  "properties": {
    "addr:full":"54 Halstead Ave Yonkers NY 10704",
    "addr:housenumber":"54",
    "addr:postcode":"10704",
    "addr:street":"Halstead Ave",
    "iso:country":"US",
    "sg:address":"54 Halstead Ave",
    "sg:city":"Yonkers",
    "sg:classifiers":[
        {
            "category":"Professional",
            "subcategory":"Accounting & Tax Preparation",
            "type":"Services"
        }
    ],
    "sg:phone":"+1   ",
    "sg:postcode":"10704",
    "sg:province":"NY",
    "wof:name":"A-Plus Bookkeeping",
    "wof:placetype":"venue"
},
  "geometry": {"coordinates":[-73.865561,40.913269],"type":"Point"}
}