{
  "type": "Feature",
  "properties": {
    "iso:country":"US",
    "sg:address":"178 Verbeck Ave",
    "sg:city":"Schaghticoke",
    "sg:classifiers":[
        {
            "category":"Professional",
            "type":"Services"
        }
    ],
    "sg:phone":"+1   ",
    "sg:postcode":"12154",
    "sg:province":"NY",
    "wof:name":"Rebecca Mackenzie",
    "wof:placetype":"venue"
},
  "geometry": {"coordinates":[-73.61164599999999,42.937421],"type":"Point"}
}