{
  "type": "Feature",
  "properties": {
    "addr:full":"1313 3rd Ave Ste 4RS New York NY 10021",
    "addr:housenumber":"1313",
    "addr:postcode":"10021",
    "addr:street":"3Rd Ave Ste 4Rs",
    "iso:country":"US",
    "sg:address":"1313 3rd Ave Ste 4RS",
    "sg:city":"New York",
    "sg:classifiers":[
        {
            "category":"Communications",
            "type":"Services"
        },
        {
            "category":"Professional",
            "subcategory":"Computer Services",
            "type":"Services"
        }
    ],
    "sg:phone":"+1 917 318 5659",
    "sg:postcode":"10021",
    "sg:province":"NY",
    "sg:tags":[
        "repair",
        "design",
        "web"
    ],
    "sg:website":"jayshapirocomputers.com/",
    "wof:name":"Jay Shapiro Computers",
    "wof:placetype":"venue"
},
  "geometry": {"coordinates":[-73.95873400000001,40.771733],"type":"Point"}
}