{
  "type": "Feature",
  "properties": {
    "addr:full":"23 Elm St Westfield NY 14787",
    "addr:housenumber":"23",
    "addr:postcode":"14787",
    "addr:street":"Elm St",
    "iso:country":"US",
    "sg:address":"23 Elm St",
    "sg:city":"Westfield",
    "sg:classifiers":[
        {
            "category":"Building & Trades",
            "subcategory":"Construction",
            "type":"Services"
        }
    ],
    "sg:phone":"+1 716 326 3014",
    "sg:postcode":"14787",
    "sg:province":"NY",
    "sg:tags":[
        "marking",
        "maintenance",
        "parking"
    ],
    "wof:name":"Westfield Highway Dept",
    "wof:placetype":"venue"
},
  "geometry": {"coordinates":[-79.576211,42.321799],"type":"Point"}
}