{
  "type": "Feature",
  "properties": {
    "addr:full":"62 Heitman Dr Spring Valley NY 10977",
    "addr:housenumber":"62",
    "addr:postcode":"10977",
    "addr:street":"Heitman Dr",
    "iso:country":"US",
    "sg:address":"62 Heitman Dr",
    "sg:city":"Spring Valley",
    "sg:classifiers":[
        {
            "category":"Utilities",
            "subcategory":"Mobile Phone",
            "type":"Services"
        }
    ],
    "sg:phone":"+1 845 357 7881",
    "sg:postcode":"10977",
    "sg:province":"NY",
    "sg:tags":[
        "telephone",
        "cellular"
    ],
    "wof:name":"Cellular Financials",
    "wof:placetype":"venue"
},
  "geometry": {"coordinates":[-74.056552,41.104964],"type":"Point"}
}