{
  "type": "Feature",
  "properties": {
    "iso:country":"US",
    "sg:address":"545 State Route 143",
    "sg:city":"Ravena",
    "sg:classifiers":[
        {
            "category":"Personal",
            "type":"Services"
        }
    ],
    "sg:phone":"+1 518 756 2616",
    "sg:postcode":"12143",
    "sg:province":"NY",
    "sg:tags":[
        "towing"
    ],
    "wof:name":"Boomer's Garage",
    "wof:placetype":"venue"
},
  "geometry": {"coordinates":[-73.837031,42.461483],"type":"Point"}
}