{
  "type": "Feature",
  "properties": {
    "addr:full":"104 Williams Rd Lockwood NY 14859",
    "addr:housenumber":"104",
    "addr:postcode":"14859",
    "addr:street":"Williams Rd",
    "iso:country":"US",
    "sg:address":"104 Williams Rd",
    "sg:city":"Lockwood",
    "sg:classifiers":[
        {
            "category":"Retail",
            "subcategory":"Car Wash",
            "type":"Services"
        }
    ],
    "sg:phone":"+1   ",
    "sg:postcode":"14859",
    "sg:province":"NY",
    "sg:tags":[
        "carwash"
    ],
    "wof:name":"JV Mobile Wash",
    "wof:placetype":"venue"
},
  "geometry": {"coordinates":[-76.50164100000001,42.099809],"type":"Point"}
}