{
  "type": "Feature",
  "properties": {
    "iso:country":"US",
    "sg:address":"83 W Broadway",
    "sg:city":"New York",
    "sg:classifiers":[
        {
            "category":"Home & Garden",
            "subcategory":"Furniture",
            "type":"Retail Goods"
        }
    ],
    "sg:phone":"+1   ",
    "sg:postcode":"10007",
    "sg:province":"NY",
    "wof:name":"Butter & Eggs",
    "wof:placetype":"venue"
},
  "geometry": {"coordinates":[-74.00922199999999,40.7154],"type":"Point"}
}