{
  "type": "Feature",
  "properties": {
    "addr:full":"1 Atlantic Ave Garden City NY 11530",
    "addr:housenumber":"1",
    "addr:postcode":"11530",
    "addr:street":"Atlantic Ave",
    "iso:country":"US",
    "sg:address":"1 Atlantic Ave",
    "sg:city":"Garden City",
    "sg:classifiers":[
        {
            "category":"Professional",
            "subcategory":"Lawyer & Legal Services",
            "type":"Services"
        }
    ],
    "sg:phone":"+1 516 248 5570",
    "sg:postcode":"11530",
    "sg:province":"NY",
    "sg:tags":[
        "attorney"
    ],
    "wof:name":"Herbert J Hummers",
    "wof:placetype":"venue"
},
  "geometry": {"coordinates":[-73.63875,40.714498],"type":"Point"}
}