{
  "type": "Feature",
  "properties": {
    "iso:country":"US",
    "sg:address":"377 Windsor Hwy",
    "sg:city":"New Windsor",
    "sg:classifiers":[
        {
            "category":"Restaurant",
            "type":"Food & Drink"
        }
    ],
    "sg:phone":"+1 845 561 0018",
    "sg:postcode":"12553",
    "sg:province":"NY",
    "wof:name":"Osaka Restaurants",
    "wof:placetype":"venue"
},
  "geometry": {"coordinates":[-74.055134,41.458041],"type":"Point"}
}