{
  "type": "Feature",
  "properties": {
    "iso:country":"US",
    "sg:address":"300 Cranberry Landing Dr",
    "sg:city":"Rochester",
    "sg:classifiers":[
        {
            "category":"Social Services",
            "subcategory":"Adult Care",
            "type":"Services"
        }
    ],
    "sg:phone":"+1 585 244 3630",
    "sg:postcode":"14609",
    "sg:province":"NY",
    "sg:tags":[
        "home",
        "residential"
    ],
    "wof:name":"Legacy Senior Communities",
    "wof:placetype":"venue"
},
  "geometry": {"coordinates":[-77.54876299999999,43.188559],"type":"Point"}
}