{
  "type": "Feature",
  "properties": {
    "addr:full":"2500 Williamsbridge Rd Bronx NY 10469",
    "addr:housenumber":"2500",
    "addr:postcode":"10469",
    "addr:street":"Williamsbridge Rd",
    "iso:country":"US",
    "sg:address":"2500 Williamsbridge Rd",
    "sg:city":"Bronx",
    "sg:classifiers":[
        {
            "category":"Real Estate",
            "subcategory":"Real Estate Services",
            "type":"Services"
        }
    ],
    "sg:phone":"+1 718 654 2900",
    "sg:postcode":"10469",
    "sg:province":"NY",
    "sg:tags":[
        "company",
        "title"
    ],
    "sg:website":"www.easternabstractny.com",
    "wof:name":"Eastern Abstract Corp",
    "wof:placetype":"venue"
},
  "geometry": {"coordinates":[-73.858712,40.864252],"type":"Point"}
}