{
  "type": "Feature",
  "properties": {
    "addr:full":"73-01 25th Ave #6844 East Elmhurst NY 11369",
    "addr:housenumber":"73-01",
    "addr:postcode":"11369",
    "addr:street":"25Th Ave # 6844",
    "iso:country":"US",
    "sg:address":"73-01 25th Ave #6844",
    "sg:city":"East Elmhurst",
    "sg:classifiers":[
        {
            "category":"Home & Garden",
            "subcategory":"Hardware",
            "type":"Retail Goods"
        }
    ],
    "sg:phone":"+1 718 507 9007",
    "sg:postcode":"11369",
    "sg:province":"NY",
    "sg:tags":[
        "store"
    ],
    "sg:website":"www.homedepot.com",
    "wof:name":"The Home Depot",
    "wof:placetype":"venue"
},
  "geometry": {"coordinates":[-73.89133,40.762577],"type":"Point"}
}