{
  "type": "Feature",
  "properties": {
    "iso:country":"US",
    "sg:address":"11829A Metropolitan Ave",
    "sg:city":"Kew Gardens",
    "sg:classifiers":[
        {
            "category":"Shopping",
            "subcategory":"Pharmacy",
            "type":"Retail Goods"
        }
    ],
    "sg:phone":"+1 718 487 8100",
    "sg:postcode":"11415",
    "sg:province":"NY",
    "sg:tags":[
        "drugstore"
    ],
    "wof:name":"N & B Pharmacy Inc",
    "wof:placetype":"venue"
},
  "geometry": {"coordinates":[-73.83260300000001,40.706501],"type":"Point"}
}