{
  "type": "Feature",
  "properties": {
    "addr:full":"279 E Houston St New York NY 10002",
    "addr:housenumber":"279",
    "addr:postcode":"10002",
    "addr:street":"E Houston St",
    "iso:country":"US",
    "sg:address":"279 E Houston St",
    "sg:city":"New York",
    "sg:classifiers":[
        {
            "category":"Professional",
            "type":"Services"
        }
    ],
    "sg:phone":"+1   ",
    "sg:postcode":"10002",
    "sg:province":"NY",
    "wof:name":"Words and Moves Corp",
    "wof:placetype":"venue"
},
  "geometry": {"coordinates":[-73.98406799999999,40.721488],"type":"Point"}
}