{
  "type": "Feature",
  "properties": {
    "iso:country":"US",
    "sg:address":"208 W Genesee St",
    "sg:city":"Syracuse",
    "sg:classifiers":[
        {
            "category":"Restaurant",
            "type":"Food & Drink"
        }
    ],
    "sg:menulink":"http://www.allmenus.com/ny/syracuse/251317-lao-village-laotian--thai-restaurant/menu/",
    "sg:phone":"+1 315 435 8151",
    "sg:postcode":"13202",
    "sg:province":"NY",
    "sg:tags":[
        "thai",
        "asian"
    ],
    "wof:name":"Lao Village Laotian & Thai Restaurant",
    "wof:placetype":"venue"
},
  "geometry": {"coordinates":[-76.153657,43.051355],"type":"Point"}
}