{
  "type": "Feature",
  "properties": {
    "addr:full":"80 Cameron Ave Hempstead NY 11550",
    "addr:housenumber":"80",
    "addr:postcode":"11550",
    "addr:street":"Cameron Ave",
    "iso:country":"US",
    "sg:address":"80 Cameron Ave",
    "sg:city":"Hempstead",
    "sg:classifiers":[
        {
            "category":"Building & Trades",
            "subcategory":"Plumbing",
            "type":"Services"
        }
    ],
    "sg:phone":"+1 516 538 5868",
    "sg:postcode":"11550",
    "sg:province":"NY",
    "sg:tags":[
        "plumbing",
        "heating",
        "contractor"
    ],
    "wof:name":"A & M Castro Plumbing",
    "wof:placetype":"venue"
},
  "geometry": {"coordinates":[-73.60745900000001,40.711077],"type":"Point"}
}