{
  "type": "Feature",
  "properties": {
    "addr:full":"1049 5th Ave New York NY 10028",
    "addr:housenumber":"1049",
    "addr:postcode":"10028",
    "addr:street":"5Th Ave",
    "iso:country":"US",
    "sg:address":"1049 5th Ave",
    "sg:city":"New York",
    "sg:classifiers":[
        {
            "category":"Shopping",
            "type":"Retail Goods"
        },
        {
            "category":"Health Services",
            "subcategory":"Doctor",
            "type":"Services"
        }
    ],
    "sg:phone":"+1 212 517 3546",
    "sg:postcode":"10028",
    "sg:province":"NY",
    "sg:tags":[
        "medical",
        "orthopedic",
        "appliance"
    ],
    "sg:website":"www.hanger.com",
    "wof:name":"Hanger Prosthetics & Orthotics",
    "wof:placetype":"venue"
},
  "geometry": {"coordinates":[-73.95992099999999,40.782213],"type":"Point"}
}