{
  "type": "Feature",
  "properties": {
    "addr:full":"103 Moyer St Canajoharie NY 13317",
    "addr:housenumber":"103",
    "addr:postcode":"13317",
    "addr:street":"Moyer St",
    "iso:country":"US",
    "sg:address":"103 Moyer St",
    "sg:city":"Canajoharie",
    "sg:classifiers":[
        {
            "category":"Farming",
            "subcategory":"Farm",
            "type":"Manufacturing & Wholesale Goods"
        }
    ],
    "sg:phone":"+1 518 993 2044",
    "sg:postcode":"13317",
    "sg:province":"NY",
    "wof:name":"Walter Bergen",
    "wof:placetype":"venue"
},
  "geometry": {"coordinates":[-74.572524,42.901514],"type":"Point"}
}