{
  "type": "Feature",
  "properties": {
    "iso:country":"US",
    "sg:address":"15 Sackett St",
    "sg:city":"Seneca Falls",
    "sg:classifiers":[
        {
            "category":"Social Services",
            "type":"Services"
        }
    ],
    "sg:phone":"+1 315 568 1596",
    "sg:postcode":"13148",
    "sg:province":"NY",
    "wof:name":"Seneca Cayuga Counties Chapter",
    "wof:placetype":"venue"
},
  "geometry": {"coordinates":[-76.80641300000001,42.906296],"type":"Point"}
}