{
  "type": "Feature",
  "properties": {
    "iso:country":"US",
    "sg:address":"28 Cheslan Ct",
    "sg:city":"Oceanside",
    "sg:classifiers":[
        {
            "category":"Home & Garden",
            "subcategory":"Building Materials",
            "type":"Retail Goods"
        }
    ],
    "sg:phone":"+1 516 255 9358",
    "sg:postcode":"11572",
    "sg:province":"NY",
    "sg:tags":[
        "windows"
    ],
    "wof:name":"S & G Windows",
    "wof:placetype":"venue"
},
  "geometry": {"coordinates":[-73.638685,40.637035],"type":"Point"}
}