{
  "type": "Feature",
  "properties": {
    "addr:full":"240 E 39th Street New York NY 10016",
    "addr:housenumber":"240",
    "addr:postcode":"10016",
    "addr:street":"E 39Th Street",
    "iso:country":"US",
    "sg:address":"240 E 39th Street",
    "sg:city":"New York",
    "sg:classifiers":[
        {
            "category":"Shopping",
            "subcategory":"Jewelry",
            "type":"Retail Goods"
        }
    ],
    "sg:phone":"+1 212 682 8647",
    "sg:postcode":"10016",
    "sg:province":"NY",
    "wof:name":"Hi Hopes",
    "wof:placetype":"venue"
},
  "geometry": {"coordinates":[-73.974693,40.748348],"type":"Point"}
}