{
  "type": "Feature",
  "properties": {
    "iso:country":"US",
    "sg:address":"1626 Brentwood Rd",
    "sg:city":"Brentwood",
    "sg:classifiers":[
        {
            "category":"Food & Beverages",
            "subcategory":"Groceries & Convenience Stores",
            "type":"Retail Goods"
        }
    ],
    "sg:phone":"+1   ",
    "sg:postcode":"11717",
    "sg:province":"NY",
    "sg:tags":[
        "supermarket"
    ],
    "wof:name":"Johathan Food Corp",
    "wof:placetype":"venue"
},
  "geometry": {"coordinates":[-73.24627700000001,40.76508],"type":"Point"}
}