{
  "type": "Feature",
  "properties": {
    "iso:country":"US",
    "sg:address":"225 E 64th St",
    "sg:city":"New York",
    "sg:classifiers":[
        {
            "category":"Health Services",
            "subcategory":"Doctor",
            "type":"Services"
        }
    ],
    "sg:phone":"+1 212 308 4988",
    "sg:postcode":"10021",
    "sg:province":"NY",
    "sg:tags":[
        "obstetrician",
        "gynecologist"
    ],
    "wof:name":"Den Tiberius Gynecology",
    "wof:placetype":"venue"
},
  "geometry": {"coordinates":[-73.962898,40.764198],"type":"Point"}
}