{
  "type": "Feature",
  "properties": {
    "iso:country":"US",
    "sg:address":"200 David Whites Ln",
    "sg:city":"Southampton",
    "sg:classifiers":[
        {
            "category":"Building & Trades",
            "subcategory":"Landscaping Services",
            "type":"Services"
        }
    ],
    "sg:phone":"+1 631 287 6800",
    "sg:postcode":"11968",
    "sg:province":"NY",
    "sg:tags":[
        "landscape",
        "contractor"
    ],
    "wof:name":"Creative Touch Landscaping",
    "wof:placetype":"venue"
},
  "geometry": {"coordinates":[-72.382139,40.897235],"type":"Point"}
}