{
  "type": "Feature",
  "properties": {
    "iso:country":"US",
    "sg:address":"36 Elizabeth Ln",
    "sg:city":"Queensbury",
    "sg:classifiers":[
        {
            "category":"Building & Trades",
            "subcategory":"Construction",
            "type":"Services"
        }
    ],
    "sg:phone":"+1 518 798 0812",
    "sg:postcode":"12804",
    "sg:province":"NY",
    "sg:tags":[
        "house"
    ],
    "wof:name":"Worth Home Improvement",
    "wof:placetype":"venue"
},
  "geometry": {"coordinates":[-73.69582699999999,43.314891],"type":"Point"}
}