{
  "type": "Feature",
  "properties": {
    "addr:full":"2541 30th Rd Apt 1H Astoria NY 11102",
    "addr:housenumber":"2541",
    "addr:postcode":"11102",
    "addr:street":"30Th Rd Apt",
    "iso:country":"US",
    "sg:address":"2541 30th Rd Apt 1H",
    "sg:city":"Astoria",
    "sg:classifiers":[
        {
            "category":"Professional",
            "subcategory":"Art Services",
            "type":"Services"
        }
    ],
    "sg:phone":"+1 917 627 9385",
    "sg:postcode":"11102",
    "sg:province":"NY",
    "sg:tags":[
        "creative",
        "audio-visual"
    ],
    "wof:name":"Maria Colon",
    "wof:placetype":"venue"
},
  "geometry": {"coordinates":[-73.92538399999999,40.767879],"type":"Point"}
}