{
  "type": "Feature",
  "properties": {
    "iso:country":"US",
    "sg:address":"10 Walker Way",
    "sg:city":"Albany",
    "sg:classifiers":[
        {
            "category":"Wholesale",
            "subcategory":"Medical Equipment & Supplies",
            "type":"Manufacturing & Wholesale Goods"
        }
    ],
    "sg:phone":"+1 518 456 6192",
    "sg:postcode":"12205",
    "sg:province":"NY",
    "wof:name":"Prime Care Medical Supplies",
    "wof:placetype":"venue"
},
  "geometry": {"coordinates":[-73.838251,42.718824],"type":"Point"}
}