{
  "type": "Feature",
  "properties": {
    "iso:country":"US",
    "sg:address":"152 Washington Ave",
    "sg:city":"Albany",
    "sg:classifiers":[
        {
            "category":"Professional",
            "subcategory":"Management & Consulting",
            "type":"Services"
        },
        {
            "category":"Manufacturing",
            "subcategory":"Printing",
            "type":"Manufacturing & Wholesale Goods"
        }
    ],
    "sg:phone":"+1 518 426 5935",
    "sg:postcode":"12210",
    "sg:province":"NY",
    "sg:tags":[
        "book",
        "business"
    ],
    "sg:website":"www.mountidapress.com",
    "wof:name":"Mount Ida Press LTD",
    "wof:placetype":"venue"
},
  "geometry": {"coordinates":[-73.758982,42.654273],"type":"Point"}
}