{
  "type": "Feature",
  "properties": {
    "addr:full":"1875 State St Schenectady NY 12304",
    "addr:housenumber":"1875",
    "addr:postcode":"12304",
    "addr:street":"State St",
    "iso:country":"US",
    "sg:address":"1875 State St",
    "sg:city":"Schenectady",
    "sg:classifiers":[
        {
            "category":"Home & Garden",
            "subcategory":"Building Materials",
            "type":"Retail Goods"
        }
    ],
    "sg:phone":"+1   ",
    "sg:postcode":"12304",
    "sg:province":"NY",
    "wof:name":"Latham Paint",
    "wof:placetype":"venue"
},
  "geometry": {"coordinates":[-73.90152,42.778471],"type":"Point"}
}