{
  "type": "Feature",
  "properties": {
    "iso:country":"US",
    "sg:address":"565 Route 6",
    "sg:city":"Mahopac",
    "sg:classifiers":[
        {
            "category":"Deli",
            "type":"Food & Drink"
        },
        {
            "category":"Restaurant",
            "type":"Food & Drink"
        }
    ],
    "sg:phone":"+1 845 228 8071",
    "sg:postcode":"10541",
    "sg:province":"NY",
    "sg:tags":[
        "delicatessen"
    ],
    "wof:name":"Delicja Polish Deli",
    "wof:placetype":"venue"
},
  "geometry": {"coordinates":[-73.738787,41.369651],"type":"Point"}
}