{
  "type": "Feature",
  "properties": {
    "addr:full":"105 W Main St Ilion NY 13357",
    "addr:housenumber":"105",
    "addr:postcode":"13357",
    "addr:street":"W Main St",
    "iso:country":"US",
    "sg:address":"105 W Main St",
    "sg:city":"Ilion",
    "sg:classifiers":[
        {
            "category":"Insurance",
            "subcategory":"Insurance Agent",
            "type":"Services"
        },
        {
            "category":"Insurance",
            "subcategory":"Hazard Insurance",
            "type":"Services"
        },
        {
            "category":"Insurance",
            "subcategory":"Title Insurance",
            "type":"Services"
        },
        {
            "category":"Insurance",
            "subcategory":"Life Insurance",
            "type":"Services"
        }
    ],
    "sg:phone":"+1 315 894 1747",
    "sg:postcode":"13357",
    "sg:province":"NY",
    "sg:tags":[
        "business",
        "auto",
        "commercial",
        "homeowner",
        "motorcycle",
        "renter"
    ],
    "wof:name":"Allstate Insurance Company - Frederick Northup",
    "wof:placetype":"venue"
},
  "geometry": {"coordinates":[-75.038307,43.016491],"type":"Point"}
}