{
  "type": "Feature",
  "properties": {
    "iso:country":"US",
    "sg:address":"7375 Oswego Rd",
    "sg:city":"Liverpool",
    "sg:classifiers":[
        {
            "category":"Restaurant",
            "type":"Food & Drink"
        }
    ],
    "sg:menulink":"http://www.allmenus.com/ny/clay/97435-salsaritas/menu/",
    "sg:phone":"+1 315 413 0180",
    "sg:postcode":"13090",
    "sg:province":"NY",
    "sg:tags":[
        "mexican"
    ],
    "wof:name":"Salsarita's",
    "wof:placetype":"venue"
},
  "geometry": {"coordinates":[-76.218773,43.128373],"type":"Point"}
}