{
  "type": "Feature",
  "properties": {
    "addr:full":"200 Knickerbocker Ave Brooklyn NY 11237",
    "addr:housenumber":"200",
    "addr:postcode":"11237",
    "addr:street":"Knickerbocker Ave",
    "iso:country":"US",
    "sg:address":"200 Knickerbocker Ave",
    "sg:city":"Brooklyn",
    "sg:classifiers":[
        {
            "category":"Retail",
            "subcategory":"Repair Shop",
            "type":"Services"
        }
    ],
    "sg:phone":"+1 718 535 9417",
    "sg:postcode":"11237",
    "sg:province":"NY",
    "sg:tags":[
        "lock",
        "locksmith"
    ],
    "wof:name":"24 Hour 7 Day Emerg Lcksmth",
    "wof:placetype":"venue"
},
  "geometry": {"coordinates":[-73.92634,40.703295],"type":"Point"}
}