{
  "type": "Feature",
  "properties": {
    "addr:full":"2427 Kayron Ln Bellmore NY 11710",
    "addr:housenumber":"2427",
    "addr:postcode":"11710",
    "addr:street":"Kayron Ln",
    "iso:country":"US",
    "sg:address":"2427 Kayron Ln",
    "sg:city":"Bellmore",
    "sg:classifiers":[
        {
            "category":"Banks & Credit Unions",
            "subcategory":"Financial Services",
            "type":"Services"
        }
    ],
    "sg:phone":"+1 516 783 0443",
    "sg:postcode":"11710",
    "sg:province":"NY",
    "sg:tags":[
        "company",
        "holding"
    ],
    "wof:name":"Adlie Assoc LLC",
    "wof:placetype":"venue"
},
  "geometry": {"coordinates":[-73.54352,40.688544],"type":"Point"}
}