{
  "type": "Feature",
  "properties": {
    "addr:full":"172 Aurora Dr Buffalo NY 14215",
    "addr:housenumber":"172",
    "addr:postcode":"14215",
    "addr:street":"Aurora Dr",
    "iso:country":"US",
    "sg:address":"172 Aurora Dr",
    "sg:city":"Buffalo",
    "sg:classifiers":[
        {
            "category":"Place Of Worship",
            "type":"Public Place"
        }
    ],
    "sg:phone":"+1 716 834 3661",
    "sg:postcode":"14215",
    "sg:province":"NY",
    "sg:tags":[
        "church"
    ],
    "wof:name":"Robert Hutchinson",
    "wof:placetype":"venue"
},
  "geometry": {"coordinates":[-78.790368,42.94312],"type":"Point"}
}