{
  "type": "Feature",
  "properties": {
    "addr:full":"91 Bennington Ave Freeport NY 11520",
    "addr:housenumber":"91",
    "addr:postcode":"11520",
    "addr:street":"Bennington Ave",
    "iso:country":"US",
    "sg:address":"91 Bennington Ave",
    "sg:city":"Freeport",
    "sg:classifiers":[
        {
            "category":"Wholesale",
            "subcategory":"Scrap",
            "type":"Manufacturing & Wholesale Goods"
        }
    ],
    "sg:phone":"+1 516 379 2470",
    "sg:postcode":"11520",
    "sg:province":"NY",
    "sg:tags":[
        "plastic"
    ],
    "sg:website":"www.plasticscommerce.com/debco",
    "wof:name":"Debco Plastics Inc",
    "wof:placetype":"venue"
},
  "geometry": {"coordinates":[-73.57398999999999,40.658228],"type":"Point"}
}