{
  "type": "Feature",
  "properties": {
    "iso:country":"US",
    "sg:address":"1 Baiting Place Rd",
    "sg:city":"Farmingdale",
    "sg:classifiers":[
        {
            "category":"Real Estate",
            "subcategory":"Real Estate Operator",
            "type":"Services"
        },
        {
            "category":"Wholesale",
            "subcategory":"Durable Goods & Equipment",
            "type":"Manufacturing & Wholesale Goods"
        }
    ],
    "sg:phone":"+1 631 293 8282",
    "sg:postcode":"11735",
    "sg:province":"NY",
    "sg:tags":[
        "building",
        "nonresidential",
        "automobile",
        "mfg",
        "importer",
        "parts"
    ],
    "wof:name":"Giant Industrial Corporation",
    "wof:placetype":"venue"
},
  "geometry": {"coordinates":[-73.4242,40.714355],"type":"Point"}
}