{
  "type": "Feature",
  "properties": {
    "iso:country":"US",
    "sg:address":"72 E Main St",
    "sg:city":"Babylon",
    "sg:classifiers":[
        {
            "category":"Professional",
            "subcategory":"Business Services",
            "type":"Services"
        }
    ],
    "sg:phone":"+1 631 422 6946",
    "sg:postcode":"11702",
    "sg:province":"NY",
    "sg:tags":[
        "importer"
    ],
    "wof:name":"Omnibus Imports Inc",
    "wof:placetype":"venue"
},
  "geometry": {"coordinates":[-73.321523,40.696914],"type":"Point"}
}