{
  "type": "Feature",
  "properties": {
    "addr:full":"14 Roxbury St Staten Island NY 10303",
    "addr:housenumber":"14",
    "addr:postcode":"10303",
    "addr:street":"Roxbury St",
    "iso:country":"US",
    "sg:address":"14 Roxbury St",
    "sg:city":"Staten Island",
    "sg:classifiers":[
        {
            "category":"Communications",
            "subcategory":"Film & Video Production",
            "type":"Services"
        }
    ],
    "sg:phone":"+1 718 370 2625",
    "sg:postcode":"10303",
    "sg:province":"NY",
    "sg:tags":[
        "motion"
    ],
    "wof:name":"Music Magazine Television Prod",
    "wof:placetype":"venue"
},
  "geometry": {"coordinates":[-74.164805,40.633369],"type":"Point"}
}