{
  "type": "Feature",
  "properties": {
    "iso:country":"US",
    "sg:address":"589 Crescent St",
    "sg:city":"Brooklyn",
    "sg:classifiers":[
        {
            "category":"Shopping",
            "subcategory":"Pharmacy",
            "type":"Retail Goods"
        }
    ],
    "sg:phone":"+1   ",
    "sg:postcode":"11208",
    "sg:province":"NY",
    "sg:tags":[
        "drugstore"
    ],
    "wof:name":"Krutick Pharmacy Inc",
    "wof:placetype":"venue"
},
  "geometry": {"coordinates":[-73.869564,40.674197],"type":"Point"}
}