{
  "type": "Feature",
  "properties": {
    "addr:full":"230 Park Ave, Ste 808, New York NY 10169",
    "addr:housenumber":"230;808",
    "addr:postcode":"10169",
    "addr:street":"Park Ave Ste",
    "iso:country":"US",
    "sg:address":"230 Park Ave, Ste 808,",
    "sg:city":"New York",
    "sg:classifiers":[
        {
            "category":"Banks & Credit Unions",
            "subcategory":"Investment Brokerage",
            "type":"Services"
        },
        {
            "category":"Banks & Credit Unions",
            "subcategory":"Financial Services",
            "type":"Services"
        }
    ],
    "sg:phone":"+1 888 255 5519",
    "sg:postcode":"10169",
    "sg:province":"NY",
    "sg:tags":[
        "investing",
        "advising"
    ],
    "sg:website":"www.ameripriseadvisors.com/micha...",
    "wof:name":"Michael Weston - Ameriprise Financial Advisor",
    "wof:placetype":"venue"
},
  "geometry": {"coordinates":[-73.97562499999999,40.754572],"type":"Point"}
}