{
  "type": "Feature",
  "properties": {
    "addr:full":"3418 Quentin Rd Brooklyn NY 11234",
    "addr:housenumber":"3418",
    "addr:postcode":"11234",
    "addr:street":"Quentin Rd",
    "iso:country":"US",
    "sg:address":"3418 Quentin Rd",
    "sg:city":"Brooklyn",
    "sg:classifiers":[
        {
            "category":"Personal",
            "subcategory":"Beauty Salon",
            "type":"Services"
        }
    ],
    "sg:phone":"+1 718 627 0709",
    "sg:postcode":"11234",
    "sg:province":"NY",
    "wof:name":"Hair I AM Unisex",
    "wof:placetype":"venue"
},
  "geometry": {"coordinates":[-73.937592,40.614023],"type":"Point"}
}