{
  "type": "Feature",
  "properties": {
    "addr:full":"146 Jerome Ave Mineola NY 11501",
    "addr:housenumber":"146",
    "addr:postcode":"11501",
    "addr:street":"Jerome Ave",
    "iso:country":"US",
    "sg:address":"146 Jerome Ave",
    "sg:city":"Mineola",
    "sg:classifiers":[
        {
            "category":"Utilities",
            "subcategory":"Sewage",
            "type":"Services"
        }
    ],
    "sg:phone":"+1 516 741 2952",
    "sg:postcode":"11501",
    "sg:province":"NY",
    "sg:tags":[
        "systems-cleaning",
        "tank",
        "septic"
    ],
    "wof:name":"J D & Sons Cesspool Svce",
    "wof:placetype":"venue"
},
  "geometry": {"coordinates":[-73.62840300000001,40.74965],"type":"Point"}
}