{
  "type": "Feature",
  "properties": {
    "addr:full":"26 Elmdorf Ave Rochester NY 14619",
    "addr:housenumber":"26",
    "addr:postcode":"14619",
    "addr:street":"Elmdorf Ave",
    "iso:country":"US",
    "sg:address":"26 Elmdorf Ave",
    "sg:city":"Rochester",
    "sg:classifiers":[
        {
            "category":"Organizations",
            "subcategory":"Religious Organization",
            "type":"Services"
        }
    ],
    "sg:phone":"+1 585 473 0220",
    "sg:postcode":"14619",
    "sg:province":"NY",
    "sg:tags":[
        "church"
    ],
    "wof:name":"Rochester Area Mennonite",
    "wof:placetype":"venue"
},
  "geometry": {"coordinates":[-77.640241,43.136736],"type":"Point"}
}