{
  "type": "Feature",
  "properties": {
    "addr:full":"4221 Broadway New York NY 10033",
    "addr:housenumber":"4221",
    "addr:postcode":"10033",
    "addr:street":"Broadway",
    "iso:country":"US",
    "sg:address":"4221 Broadway",
    "sg:city":"New York",
    "sg:classifiers":[
        {
            "category":"Building & Trades",
            "subcategory":"Construction",
            "type":"Services"
        }
    ],
    "sg:phone":"+1 212 795 2513",
    "sg:postcode":"10033",
    "sg:province":"NY",
    "sg:tags":[
        "contractor"
    ],
    "wof:name":"AT&T CITS",
    "wof:placetype":"venue"
},
  "geometry": {"coordinates":[-73.9372,40.849012],"type":"Point"}
}