{
  "type": "Feature",
  "properties": {
    "addr:full":"2751 Westinghouse Rd Horseheads NY 14845",
    "addr:housenumber":"2751",
    "addr:postcode":"14845",
    "addr:street":"Westinghouse Rd",
    "iso:country":"US",
    "sg:address":"2751 Westinghouse Rd",
    "sg:city":"Horseheads",
    "sg:classifiers":[
        {
            "category":"Health Services",
            "subcategory":"Optometrist",
            "type":"Services"
        }
    ],
    "sg:phone":"+1   ",
    "sg:postcode":"14845",
    "sg:province":"NY",
    "sg:tags":[
        "optical",
        "good"
    ],
    "wof:name":"Brent D Arnold OD",
    "wof:placetype":"venue"
},
  "geometry": {"coordinates":[-76.840065,42.164885],"type":"Point"}
}