{
  "type": "Feature",
  "properties": {
    "addr:full":"350 E 30th St New York NY 10016",
    "addr:housenumber":"350",
    "addr:postcode":"10016",
    "addr:street":"E 30Th St",
    "iso:country":"US",
    "sg:address":"350 E 30th St",
    "sg:city":"New York",
    "sg:classifiers":[
        {
            "category":"Health Services",
            "subcategory":"Doctor",
            "type":"Services"
        }
    ],
    "sg:phone":"+1 917 512 5919",
    "sg:postcode":"10016",
    "sg:province":"NY",
    "wof:name":"Brown Lance H Md Pllc",
    "wof:placetype":"venue"
},
  "geometry": {"coordinates":[-73.97656000000001,40.741641],"type":"Point"}
}