{
  "type": "Feature",
  "properties": {
    "addr:full":"2529 E 27th St Brooklyn NY 11235",
    "addr:housenumber":"2529",
    "addr:postcode":"11235",
    "addr:street":"E 27Th St",
    "iso:country":"US",
    "sg:address":"2529 E 27th St",
    "sg:city":"Brooklyn",
    "sg:classifiers":[
        {
            "category":"Building & Trades",
            "subcategory":"Electrical",
            "type":"Services"
        }
    ],
    "sg:phone":"+1 718 367 7569",
    "sg:postcode":"11235",
    "sg:province":"NY",
    "sg:tags":[
        "electric",
        "contractor"
    ],
    "wof:name":"Practical Electrical Co",
    "wof:placetype":"venue"
},
  "geometry": {"coordinates":[-73.942694,40.589863],"type":"Point"}
}