{
  "type": "Feature",
  "properties": {
    "iso:country":"US",
    "sg:address":"6512 Fort Hamilton Pkwy",
    "sg:city":"Brooklyn",
    "sg:classifiers":[
        {
            "category":"Home & Garden",
            "subcategory":"Building Materials",
            "type":"Retail Goods"
        }
    ],
    "sg:phone":"+1   ",
    "sg:postcode":"11219",
    "sg:province":"NY",
    "sg:tags":[
        "wood",
        "preserving"
    ],
    "wof:name":"Bari Building Supply Inc",
    "wof:placetype":"venue"
},
  "geometry": {"coordinates":[-74.009981,40.630233],"type":"Point"}
}