{
  "type": "Feature",
  "properties": {
    "iso:country":"US",
    "sg:address":"725 Rogers Ave",
    "sg:city":"Brooklyn",
    "sg:classifiers":[
        {
            "category":"Shopping",
            "subcategory":"Computers & Home Electronics",
            "type":"Retail Goods"
        }
    ],
    "sg:phone":"+1   ",
    "sg:postcode":"11226",
    "sg:province":"NY",
    "wof:name":"Millennium Computer Training",
    "wof:placetype":"venue"
},
  "geometry": {"coordinates":[-73.95262099999999,40.652884],"type":"Point"}
}