{
  "type": "Feature",
  "properties": {
    "iso:country":"US",
    "sg:address":"926 Nassau Rd",
    "sg:city":"Uniondale",
    "sg:classifiers":[
        {
            "category":"Manufacturing",
            "subcategory":"Food",
            "type":"Manufacturing & Wholesale Goods"
        }
    ],
    "sg:phone":"+1 516 485 3100",
    "sg:postcode":"11553",
    "sg:province":"NY",
    "sg:tags":[
        "beverage"
    ],
    "wof:name":"Angela's Beverages",
    "wof:placetype":"venue"
},
  "geometry": {"coordinates":[-73.596124,40.688511],"type":"Point"}
}