{
  "type": "Feature",
  "properties": {
    "iso:country":"US",
    "sg:address":"44 Park Ave",
    "sg:city":"Wellsville",
    "sg:classifiers":[
        {
            "category":"Food & Beverages",
            "subcategory":"Groceries & Convenience Stores",
            "type":"Retail Goods"
        }
    ],
    "sg:phone":"+1 585 593 4586",
    "sg:postcode":"14895",
    "sg:province":"NY",
    "sg:tags":[
        "grocer"
    ],
    "wof:name":"Giant Food Mart Bakery & Deli",
    "wof:placetype":"venue"
},
  "geometry": {"coordinates":[-77.94738700000001,42.120395],"type":"Point"}
}