{
  "type": "Feature",
  "properties": {
    "addr:full":"305 Canal St New York NY 10013",
    "addr:housenumber":"305",
    "addr:postcode":"10013",
    "addr:street":"Canal St",
    "iso:country":"US",
    "sg:address":"305 Canal St",
    "sg:city":"New York",
    "sg:classifiers":[
        {
            "category":"Organizations",
            "subcategory":"Professional Association",
            "type":"Services"
        }
    ],
    "sg:phone":"+1 212 274 8009",
    "sg:postcode":"10013",
    "sg:province":"NY",
    "sg:tags":[
        "polishing",
        "car",
        "washing"
    ],
    "wof:name":"Canal Street Car Stereo Hq",
    "wof:placetype":"venue"
},
  "geometry": {"coordinates":[-74.00218700000001,40.719621],"type":"Point"}
}