{
  "type": "Feature",
  "properties": {
    "addr:full":"1138 Lexington Ave New York NY 10021",
    "addr:housenumber":"1138",
    "addr:postcode":"10021",
    "addr:street":"Lexington Ave",
    "iso:country":"US",
    "sg:address":"1138 Lexington Ave",
    "sg:city":"New York",
    "sg:classifiers":[
        {
            "category":"Building & Trades",
            "subcategory":"Locksmith",
            "type":"Services"
        }
    ],
    "sg:phone":"+1 212 360 6000",
    "sg:postcode":"10021",
    "sg:province":"NY",
    "sg:tags":[
        "key"
    ],
    "wof:name":"Associated Locksmith",
    "wof:placetype":"venue"
},
  "geometry": {"coordinates":[-73.9589,40.7747],"type":"Point"}
}