{
  "type": "Feature",
  "properties": {
    "addr:full":"2217 Jerusalem Ave Merrick NY 11566",
    "addr:housenumber":"2217",
    "addr:postcode":"11566",
    "addr:street":"Jerusalem Ave",
    "iso:country":"US",
    "sg:address":"2217 Jerusalem Ave",
    "sg:city":"Merrick",
    "sg:classifiers":[
        {
            "category":"Retail",
            "subcategory":"Self-service Laundry",
            "type":"Services"
        }
    ],
    "sg:phone":"+1 516 783 7913",
    "sg:postcode":"11566",
    "sg:province":"NY",
    "wof:name":"Cecelia's Laundromat & Dry",
    "wof:placetype":"venue"
},
  "geometry": {"coordinates":[-73.55003499999999,40.690534],"type":"Point"}
}