{
  "type": "Feature",
  "properties": {
    "addr:full":"270 W 45 St New York NY 10036",
    "addr:housenumber":"270",
    "addr:postcode":"10036",
    "addr:street":"W 45 St",
    "iso:country":"US",
    "sg:address":"270 W 45 St",
    "sg:city":"New York",
    "sg:classifiers":[
        {
            "category":"Travel",
            "subcategory":"Hotels & Motels",
            "type":"Entertainment"
        }
    ],
    "sg:phone":"+1   ",
    "sg:postcode":"10036",
    "sg:province":"NY",
    "sg:tags":[
        "operation",
        "eating",
        "drinking"
    ],
    "sg:website":"www.milfordplaza.com",
    "wof:name":"Milford Plaza Hotel",
    "wof:placetype":"venue"
},
  "geometry": {"coordinates":[-73.987898,40.758802],"type":"Point"}
}