{
  "type": "Feature",
  "properties": {
    "addr:full":"2 Clinton St New York NY 10002",
    "addr:housenumber":"2",
    "addr:postcode":"10002",
    "addr:street":"Clinton St",
    "iso:country":"US",
    "sg:address":"2 Clinton St",
    "sg:city":"New York",
    "sg:classifiers":[
        {
            "category":"Food & Beverages",
            "subcategory":"Groceries & Convenience Stores",
            "type":"Retail Goods"
        }
    ],
    "sg:phone":"+1   ",
    "sg:postcode":"10002",
    "sg:province":"NY",
    "wof:name":"Deli Grocery Store",
    "wof:placetype":"venue"
},
  "geometry": {"coordinates":[-73.984477,40.720234],"type":"Point"}
}