{
  "type": "Feature",
  "properties": {
    "addr:full":"1372 39th St Brooklyn NY 11218",
    "addr:housenumber":"1372",
    "addr:postcode":"11218",
    "addr:street":"39Th St",
    "iso:country":"US",
    "sg:address":"1372 39th St",
    "sg:city":"Brooklyn",
    "sg:classifiers":[
        {
            "category":"Home & Garden",
            "subcategory":"Building Materials",
            "type":"Retail Goods"
        }
    ],
    "sg:phone":"+1 718 871 2200",
    "sg:postcode":"11218",
    "sg:province":"NY",
    "sg:tags":[
        "door",
        "contractor"
    ],
    "sg:website":"www.granddoors.com",
    "wof:name":"Grand Doors",
    "wof:placetype":"venue"
},
  "geometry": {"coordinates":[-73.98468,40.639648],"type":"Point"}
}