{
  "type": "Feature",
  "properties": {
    "iso:country":"US",
    "sg:address":"1239 Broadway",
    "sg:city":"Brooklyn",
    "sg:classifiers":[
        {
            "category":"Shopping",
            "subcategory":"Jewelry",
            "type":"Retail Goods"
        }
    ],
    "sg:phone":"+1   ",
    "sg:postcode":"11221",
    "sg:province":"NY",
    "wof:name":"Gateway Trading",
    "wof:placetype":"venue"
},
  "geometry": {"coordinates":[-73.925973,40.6919],"type":"Point"}
}