{
  "type": "Feature",
  "properties": {
    "addr:full":"115 Smith St Brooklyn NY 11201",
    "addr:housenumber":"115",
    "addr:postcode":"11201",
    "addr:street":"Smith St",
    "iso:country":"US",
    "sg:address":"115 Smith St",
    "sg:city":"Brooklyn",
    "sg:classifiers":[
        {
            "category":"Restaurant",
            "type":"Food & Drink"
        }
    ],
    "sg:phone":"+1 718 522 5888",
    "sg:postcode":"11201",
    "sg:province":"NY",
    "sg:tags":[
        "sushi",
        "bar",
        "japanese"
    ],
    "wof:name":"Kyoto Sushi",
    "wof:placetype":"venue"
},
  "geometry": {"coordinates":[-73.98967500000001,40.687897],"type":"Point"}
}