{
  "type": "Feature",
  "properties": {
    "iso:country":"US",
    "sg:address":"11 E Main St",
    "sg:city":"Washingtonville",
    "sg:classifiers":[
        {
            "category":"Professional",
            "subcategory":"Lawyer & Legal Services",
            "type":"Services"
        }
    ],
    "sg:phone":"+1 845 497 7265",
    "sg:postcode":"10992",
    "sg:province":"NY",
    "wof:name":"Tompkins Jeanne",
    "wof:placetype":"venue"
},
  "geometry": {"coordinates":[-74.16619900000001,41.427696],"type":"Point"}
}