{
  "type": "Feature",
  "properties": {
    "iso:country":"US",
    "sg:address":"3580 Mount Read Blvd",
    "sg:city":"Rochester",
    "sg:classifiers":[
        {
            "category":"Autos & Motor Vehicles",
            "subcategory":"Auto Supplies",
            "type":"Retail Goods"
        }
    ],
    "sg:phone":"+1 585 663 0410",
    "sg:postcode":"14616",
    "sg:province":"NY",
    "sg:tags":[
        "tire"
    ],
    "wof:name":"Metro Tire and Auto Svc Ctr",
    "wof:placetype":"venue"
},
  "geometry": {"coordinates":[-77.658914,43.218743],"type":"Point"}
}