{
  "type": "Feature",
  "properties": {
    "iso:country":"US",
    "sg:address":"415 Bay Ridge Parkway",
    "sg:city":"Brooklyn",
    "sg:classifiers":[
        {
            "category":"Health Services",
            "subcategory":"Dentist",
            "type":"Services"
        }
    ],
    "sg:phone":"+1 718 748 5545",
    "sg:postcode":"11209",
    "sg:province":"NY",
    "wof:name":"Ferrari Lawrence DDS",
    "wof:placetype":"venue"
},
  "geometry": {"coordinates":[-74.02500499999999,40.630958],"type":"Point"}
}