{
  "type": "Feature",
  "properties": {
    "addr:full":"299 Broadway New York NY 10007",
    "addr:housenumber":"299",
    "addr:postcode":"10007",
    "addr:street":"Broadway",
    "iso:country":"US",
    "sg:address":"299 Broadway",
    "sg:city":"New York",
    "sg:classifiers":[
        {
            "category":"Professional",
            "subcategory":"Lawyer & Legal Services",
            "type":"Services"
        }
    ],
    "sg:phone":"+1 212 233 8500",
    "sg:postcode":"10007",
    "sg:province":"NY",
    "sg:tags":[
        "attorney"
    ],
    "wof:name":"The Law Offices of Robert Weiss",
    "wof:placetype":"venue"
},
  "geometry": {"coordinates":[-74.00540700000001,40.715226],"type":"Point"}
}