{
  "type": "Feature",
  "properties": {
    "iso:country":"US",
    "sg:address":"13 Clark Pl",
    "sg:city":"Utica",
    "sg:classifiers":[
        {
            "category":"Social Services",
            "subcategory":"Child Care",
            "type":"Services"
        }
    ],
    "sg:phone":"+1 315 735 7534",
    "sg:postcode":"13501",
    "sg:province":"NY",
    "sg:tags":[
        "day"
    ],
    "wof:name":"Tabernacle Baptist Church NC",
    "wof:placetype":"venue"
},
  "geometry": {"coordinates":[-75.23393299999999,43.097746],"type":"Point"}
}