{
  "type": "Feature",
  "properties": {
    "iso:country":"US",
    "sg:address":"512 W Lawrence St",
    "sg:city":"Albany",
    "sg:classifiers":[
        {
            "category":"Building & Trades",
            "subcategory":"Construction",
            "type":"Services"
        }
    ],
    "sg:phone":"+1 518 365 1515",
    "sg:postcode":"12208",
    "sg:province":"NY",
    "wof:name":"Yefim General Contractor",
    "wof:placetype":"venue"
},
  "geometry": {"coordinates":[-73.800552,42.65627],"type":"Point"}
}