{
  "type": "Feature",
  "properties": {
    "addr:full":"3650 State Hwy 2 Cropseyville NY 12052",
    "addr:housenumber":"3650",
    "addr:postcode":"12052",
    "addr:street":"State Hwy 2",
    "iso:country":"US",
    "sg:address":"3650 State Hwy 2",
    "sg:city":"Cropseyville",
    "sg:classifiers":[
        {
            "category":"Retail",
            "subcategory":"Auto Repair",
            "type":"Services"
        }
    ],
    "sg:phone":"+1   ",
    "sg:postcode":"12052",
    "sg:province":"NY",
    "sg:tags":[
        "general"
    ],
    "wof:name":"Pleasant Valley Garage",
    "wof:placetype":"venue"
},
  "geometry": {"coordinates":[-73.551705,42.747234],"type":"Point"}
}