{
  "type": "Feature",
  "properties": {
    "iso:country":"US",
    "sg:address":"722 Varick St",
    "sg:city":"Utica",
    "sg:classifiers":[
        {
            "category":"Food & Beverages",
            "subcategory":"Specialty",
            "type":"Retail Goods"
        }
    ],
    "sg:phone":"+1   ",
    "sg:postcode":"13502",
    "sg:province":"NY",
    "sg:tags":[
        "alcoholic"
    ],
    "wof:name":"Wine Seller",
    "wof:placetype":"venue"
},
  "geometry": {"coordinates":[-75.243559,43.1036],"type":"Point"}
}