{
  "type": "Feature",
  "properties": {
    "addr:full":"769 Dublin Hill Rd Aurora NY 13026",
    "addr:housenumber":"769",
    "addr:postcode":"13026",
    "addr:street":"Dublin Hill Rd",
    "iso:country":"US",
    "sg:address":"769 Dublin Hill Rd",
    "sg:city":"Aurora",
    "sg:classifiers":[
        {
            "category":"Freight",
            "type":"Transportation"
        }
    ],
    "sg:phone":"+1   ",
    "sg:postcode":"13026",
    "sg:province":"NY",
    "sg:tags":[
        "operator",
        "local",
        "trucking"
    ],
    "wof:name":"Nolan Trucking",
    "wof:placetype":"venue"
},
  "geometry": {"coordinates":[-76.689369,42.751079],"type":"Point"}
}