{
  "type": "Feature",
  "properties": {
    "addr:full":"925 Post Ave Staten Island NY 10302",
    "addr:housenumber":"925",
    "addr:postcode":"10302",
    "addr:street":"Post Ave",
    "iso:country":"US",
    "sg:address":"925 Post Ave",
    "sg:city":"Staten Island",
    "sg:classifiers":[
        {
            "category":"Recreation",
            "type":"Entertainment"
        }
    ],
    "sg:phone":"+1 718 720 5111",
    "sg:postcode":"10302",
    "sg:province":"NY",
    "sg:tags":[
        "martial art",
        "instruction"
    ],
    "wof:name":"Shaolin Kung Fu Temple",
    "wof:placetype":"venue"
},
  "geometry": {"coordinates":[-74.131699,40.631401],"type":"Point"}
}