{
  "type": "Feature",
  "properties": {
    "addr:full":"1020 W Jericho Tpke Smithtown NY 11787",
    "addr:housenumber":"1020",
    "addr:postcode":"11787",
    "addr:street":"W Jericho Tpke",
    "iso:country":"US",
    "sg:address":"1020 W Jericho Tpke",
    "sg:city":"Smithtown",
    "sg:classifiers":[
        {
            "category":"Restaurant",
            "type":"Food & Drink"
        }
    ],
    "sg:menulink":"http://www.allmenus.com/ny/smithtown/142477-subway/menu/",
    "sg:phone":"+1 631 543 2832",
    "sg:postcode":"11787",
    "sg:province":"NY",
    "sg:tags":[
        "american",
        "sandwich"
    ],
    "wof:name":"Subway",
    "wof:placetype":"venue"
},
  "geometry": {"coordinates":[-73.253147,40.847241],"type":"Point"}
}