{
  "type": "Feature",
  "properties": {
    "iso:country":"US",
    "sg:address":"38 Urban Dr",
    "sg:city":"Selden",
    "sg:classifiers":[
        {
            "category":"Freight",
            "type":"Transportation"
        }
    ],
    "sg:phone":"+1   ",
    "sg:postcode":"11784",
    "sg:province":"NY",
    "sg:tags":[
        "operator",
        "trucking"
    ],
    "wof:name":"Atlantic Trucking",
    "wof:placetype":"venue"
},
  "geometry": {"coordinates":[-73.055087,40.856303],"type":"Point"}
}