{
  "type": "Feature",
  "properties": {
    "iso:country":"US",
    "sg:address":"122 Cain Dr",
    "sg:city":"Brentwood",
    "sg:classifiers":[
        {
            "category":"Professional",
            "subcategory":"Research",
            "type":"Services"
        }
    ],
    "sg:phone":"+1 631 434 8944",
    "sg:postcode":"11717",
    "sg:province":"NY",
    "sg:tags":[
        "development",
        "marketing",
        "product"
    ],
    "wof:name":"Product Development Labs Inc",
    "wof:placetype":"venue"
},
  "geometry": {"coordinates":[-73.248527,40.806778],"type":"Point"}
}