{
  "type": "Feature",
  "properties": {
    "iso:country":"US",
    "sg:address":"12 Winthrop Ave",
    "sg:city":"Liberty",
    "sg:classifiers":[
        {
            "category":"Shopping",
            "subcategory":"Bicycles & Sporting Goods",
            "type":"Retail Goods"
        }
    ],
    "sg:phone":"+1   ",
    "sg:postcode":"12754",
    "sg:province":"NY",
    "sg:tags":[
        "archery",
        "supply"
    ],
    "wof:name":"Travis Archery",
    "wof:placetype":"venue"
},
  "geometry": {"coordinates":[-74.75078499999999,41.806659],"type":"Point"}
}