{
  "type": "Feature",
  "properties": {
    "addr:full":"512 W Broadway Fulton NY 13069",
    "addr:housenumber":"512",
    "addr:postcode":"13069",
    "addr:street":"W Broadway",
    "iso:country":"US",
    "sg:address":"512 W Broadway",
    "sg:city":"Fulton",
    "sg:classifiers":[
        {
            "category":"Retail",
            "subcategory":"Auto Repair",
            "type":"Services"
        }
    ],
    "sg:phone":"+1 315 593 2038",
    "sg:postcode":"13069",
    "sg:province":"NY",
    "sg:tags":[
        "body",
        "automobile",
        "painting"
    ],
    "wof:name":"St Onge Auto Body & Collision",
    "wof:placetype":"venue"
},
  "geometry": {"coordinates":[-76.42308199999999,43.314635],"type":"Point"}
}