{
  "type": "Feature",
  "properties": {
    "iso:country":"US",
    "sg:address":"79 Grand Ave",
    "sg:city":"Massapequa",
    "sg:classifiers":[
        {
            "category":"Health Services",
            "subcategory":"Doctor",
            "type":"Services"
        }
    ],
    "sg:phone":"+1 516 798 3376",
    "sg:postcode":"11758",
    "sg:province":"NY",
    "sg:tags":[
        "medical"
    ],
    "wof:name":"Lucks Diane",
    "wof:placetype":"venue"
},
  "geometry": {"coordinates":[-73.47367800000001,40.677756],"type":"Point"}
}