{
  "type": "Feature",
  "properties": {
    "addr:full":"241 W 37th St New York NY 10018",
    "addr:housenumber":"241",
    "addr:postcode":"10018",
    "addr:street":"W 37Th St",
    "iso:country":"US",
    "sg:address":"241 W 37th St",
    "sg:city":"New York",
    "sg:classifiers":[
        {
            "category":"Professional",
            "type":"Services"
        }
    ],
    "sg:phone":"+1 212 221 3080",
    "sg:postcode":"10018",
    "sg:province":"NY",
    "sg:tags":[
        "establishment"
    ],
    "wof:name":"Now Corporaton",
    "wof:placetype":"venue"
},
  "geometry": {"coordinates":[-73.991165,40.753667],"type":"Point"}
}