{
  "type": "Feature",
  "properties": {
    "addr:full":"57 W 42nd St New York NY 10110",
    "addr:housenumber":"57",
    "addr:postcode":"10110",
    "addr:street":"W 42Nd St",
    "iso:country":"US",
    "sg:address":"57 W 42nd St",
    "sg:city":"New York",
    "sg:classifiers":[
        {
            "category":"Shopping",
            "subcategory":"Mobile Phones",
            "type":"Retail Goods"
        }
    ],
    "sg:phone":"+1 212 730 4727",
    "sg:postcode":"10110",
    "sg:province":"NY",
    "sg:website":"www.sprint.com",
    "wof:name":"Sprint Store",
    "wof:placetype":"venue"
},
  "geometry": {"coordinates":[-73.983704,40.754696],"type":"Point"}
}