{
  "type": "Feature",
  "properties": {
    "addr:full":"12 Berkley Dr Lockport NY 14094",
    "addr:housenumber":"12",
    "addr:postcode":"14094",
    "addr:street":"Berkley Dr",
    "iso:country":"US",
    "sg:address":"12 Berkley Dr",
    "sg:city":"Lockport",
    "sg:classifiers":[
        {
            "category":"Health Services",
            "subcategory":"Doctor",
            "type":"Services"
        }
    ],
    "sg:phone":"+1 716 439 8357",
    "sg:postcode":"14094",
    "sg:province":"NY",
    "sg:tags":[
        "dentist"
    ],
    "wof:name":"Mascari Peter P DDS PC",
    "wof:placetype":"venue"
},
  "geometry": {"coordinates":[-78.688655,43.155091],"type":"Point"}
}