{
  "type": "Feature",
  "properties": {
    "addr:full":"24 Stever Dr Binghamton NY 13901",
    "addr:housenumber":"24",
    "addr:postcode":"13901",
    "addr:street":"Stever Dr",
    "iso:country":"US",
    "sg:address":"24 Stever Dr",
    "sg:city":"Binghamton",
    "sg:classifiers":[
        {
            "category":"Professional",
            "subcategory":"Art Services",
            "type":"Services"
        }
    ],
    "sg:phone":"+1 607 648 7666",
    "sg:postcode":"13901",
    "sg:province":"NY",
    "sg:tags":[
        "graphic",
        "designer"
    ],
    "wof:name":"Bob Sloan Illustration",
    "wof:placetype":"venue"
},
  "geometry": {"coordinates":[-75.862596,42.170729],"type":"Point"}
}