{
  "type": "Feature",
  "properties": {
    "addr:full":"4470 Wickham Ave Mattituck NY 11952",
    "addr:housenumber":"4470",
    "addr:postcode":"11952",
    "addr:street":"Wickham Ave",
    "iso:country":"US",
    "sg:address":"4470 Wickham Ave",
    "sg:city":"Mattituck",
    "sg:classifiers":[
        {
            "category":"Wholesale",
            "subcategory":"Books, Periodicals, & Newspapers",
            "type":"Manufacturing & Wholesale Goods"
        }
    ],
    "sg:phone":"+1 631 298 5100",
    "sg:postcode":"11952",
    "sg:province":"NY",
    "sg:tags":[
        "publisher",
        "book"
    ],
    "wof:name":"Amereon LTD",
    "wof:placetype":"venue"
},
  "geometry": {"coordinates":[-72.531875,41.003061],"type":"Point"}
}