{
  "type": "Feature",
  "properties": {
    "addr:full":"597 Central Park Ave Yonkers NY 10704",
    "addr:housenumber":"597",
    "addr:postcode":"10704",
    "addr:street":"Central Park Ave",
    "iso:country":"US",
    "sg:address":"597 Central Park Ave",
    "sg:city":"Yonkers",
    "sg:classifiers":[
        {
            "category":"Shopping",
            "type":"Retail Goods"
        }
    ],
    "sg:phone":"+1 914 963 6557",
    "sg:postcode":"10704",
    "sg:province":"NY",
    "sg:tags":[
        "pet",
        "shop"
    ],
    "wof:name":"Exotic Pet Warehouse Co",
    "wof:placetype":"venue"
},
  "geometry": {"coordinates":[-73.865256,40.9204],"type":"Point"}
}