{
  "type": "Feature",
  "properties": {
    "addr:full":"608 Clinton Ave S Rochester NY 14620",
    "addr:housenumber":"608",
    "addr:postcode":"14620",
    "addr:street":"Clinton Ave S",
    "iso:country":"US",
    "sg:address":"608 Clinton Ave S",
    "sg:city":"Rochester",
    "sg:classifiers":[
        {
            "category":"Health Services",
            "subcategory":"Clinic",
            "type":"Services"
        }
    ],
    "sg:phone":"+1 585 473 0154",
    "sg:postcode":"14620",
    "sg:province":"NY",
    "sg:tags":[
        "rehabilitation",
        "center"
    ],
    "wof:name":"ARC Works",
    "wof:placetype":"venue"
},
  "geometry": {"coordinates":[-77.601169,43.145003],"type":"Point"}
}