{
  "type": "Feature",
  "properties": {
    "addr:full":"10 W 65 St New York NY 10023",
    "addr:housenumber":"10",
    "addr:postcode":"10023",
    "addr:street":"W 65 St",
    "iso:country":"US",
    "sg:address":"10 W 65 St",
    "sg:city":"New York",
    "sg:classifiers":[
        {
            "category":"Professional",
            "subcategory":"Computer Services",
            "type":"Services"
        }
    ],
    "sg:phone":"+1 212 344 9266",
    "sg:postcode":"10023",
    "sg:province":"NY",
    "sg:tags":[
        "website",
        "design"
    ],
    "wof:name":"Complex",
    "wof:placetype":"venue"
},
  "geometry": {"coordinates":[-73.981927,40.772822],"type":"Point"}
}