{
  "type": "Feature",
  "properties": {
    "addr:full":"598 Tuckahoe Rd Yonkers NY 10710",
    "addr:housenumber":"598",
    "addr:postcode":"10710",
    "addr:street":"Tuckahoe Rd",
    "iso:country":"US",
    "sg:address":"598 Tuckahoe Rd",
    "sg:city":"Yonkers",
    "sg:classifiers":[
        {
            "category":"Insurance",
            "subcategory":"Insurance Agent",
            "type":"Services"
        }
    ],
    "sg:phone":"+1 914 779 0554",
    "sg:postcode":"10710",
    "sg:province":"NY",
    "wof:name":"Stuart Greenfield Agency",
    "wof:placetype":"venue"
},
  "geometry": {"coordinates":[-73.846148,40.953609],"type":"Point"}
}