{
  "type": "Feature",
  "properties": {
    "addr:full":"53 E 167th St Bronx NY 10452",
    "addr:housenumber":"53",
    "addr:postcode":"10452",
    "addr:street":"E 167Th St",
    "iso:country":"US",
    "sg:address":"53 E 167th St",
    "sg:city":"Bronx",
    "sg:classifiers":[
        {
            "category":"Restaurant",
            "type":"Food & Drink"
        }
    ],
    "sg:phone":"+1   ",
    "sg:postcode":"10452",
    "sg:province":"NY",
    "sg:tags":[
        "eating"
    ],
    "wof:name":"Gus Restaurant",
    "wof:placetype":"venue"
},
  "geometry": {"coordinates":[-73.920733,40.835668],"type":"Point"}
}