{
  "type": "Feature",
  "properties": {
    "iso:country":"US",
    "sg:address":"10 Euclid Ave",
    "sg:city":"Hamburg",
    "sg:classifiers":[
        {
            "category":"Food & Beverages",
            "subcategory":"Dairy",
            "type":"Retail Goods"
        }
    ],
    "sg:phone":"+1   ",
    "sg:postcode":"14075",
    "sg:province":"NY",
    "sg:tags":[
        "product",
        "desert",
        "ice",
        "mfg"
    ],
    "wof:name":"Nick Charlaps",
    "wof:placetype":"venue"
},
  "geometry": {"coordinates":[-78.82201000000001,42.7252],"type":"Point"}
}