{
  "type": "Feature",
  "properties": {
    "addr:full":"215 E 6th Street New York NY 10003",
    "addr:housenumber":"215",
    "addr:postcode":"10003",
    "addr:street":"E 6Th Street",
    "iso:country":"US",
    "sg:address":"215 E 6th Street",
    "sg:city":"New York",
    "sg:classifiers":[
        {
            "category":"Education",
            "subcategory":"School",
            "type":"Public Place"
        }
    ],
    "sg:phone":"+1 212 473 3130",
    "sg:postcode":"10003",
    "sg:province":"NY",
    "sg:tags":[
        "high",
        "middle",
        "elementary"
    ],
    "wof:name":"St George Catholic School",
    "wof:placetype":"venue"
},
  "geometry": {"coordinates":[-73.989818,40.728059],"type":"Point"}
}