{
  "type": "Feature",
  "properties": {
    "iso:country":"US",
    "sg:address":"639 Merrick Rd",
    "sg:city":"Lynbrook",
    "sg:classifiers":[
        {
            "category":"Autos & Motor Vehicles",
            "subcategory":"Automobile Sales",
            "type":"Retail Goods"
        },
        {
            "category":"Retail",
            "subcategory":"Auto Repair",
            "type":"Services"
        }
    ],
    "sg:phone":"+1 516 887 8600",
    "sg:postcode":"11563",
    "sg:province":"NY",
    "sg:tags":[
        "body",
        "shop",
        "car"
    ],
    "wof:name":"South Shore Jeep Eagle Subaru",
    "wof:placetype":"venue"
},
  "geometry": {"coordinates":[-73.685799,40.661098],"type":"Point"}
}