{
  "type": "Feature",
  "properties": {
    "addr:full":"1550 McDonald Ave Brooklyn NY 11230",
    "addr:housenumber":"1550",
    "addr:postcode":"11230",
    "addr:street":"Mcdonald Ave",
    "iso:country":"US",
    "sg:address":"1550 McDonald Ave",
    "sg:city":"Brooklyn",
    "sg:classifiers":[
        {
            "category":"Health Services",
            "subcategory":"Medical Lab",
            "type":"Services"
        }
    ],
    "sg:phone":"+1 718 382 6203",
    "sg:postcode":"11230",
    "sg:province":"NY",
    "sg:tags":[
        "laboratory"
    ],
    "wof:name":"A & S Dental Lab",
    "wof:placetype":"venue"
},
  "geometry": {"coordinates":[-73.974242,40.615239],"type":"Point"}
}