{
  "type": "Feature",
  "properties": {
    "addr:full":"2210 Church Ave Brooklyn NY 11226",
    "addr:housenumber":"2210",
    "addr:postcode":"11226",
    "addr:street":"Church Ave",
    "iso:country":"US",
    "sg:address":"2210 Church Ave",
    "sg:city":"Brooklyn",
    "sg:classifiers":[
        {
            "category":"Restaurant",
            "type":"Food & Drink"
        }
    ],
    "sg:phone":"+1 718 469 9049",
    "sg:postcode":"11226",
    "sg:province":"NY",
    "sg:website":"www.sybilsbakery.com",
    "wof:name":"Sybil's Bakery & Restaurant",
    "wof:placetype":"venue"
},
  "geometry": {"coordinates":[-73.958558,40.650408],"type":"Point"}
}