{
  "type": "Feature",
  "properties": {
    "addr:full":"361 Woodrow Rd Staten Island NY 10312",
    "addr:housenumber":"361",
    "addr:postcode":"10312",
    "addr:street":"Woodrow Rd",
    "iso:country":"US",
    "sg:address":"361 Woodrow Rd",
    "sg:city":"Staten Island",
    "sg:classifiers":[
        {
            "category":"Wholesale",
            "subcategory":"Computers",
            "type":"Manufacturing & Wholesale Goods"
        }
    ],
    "sg:phone":"+1 718 569 3578",
    "sg:postcode":"10312",
    "sg:province":"NY",
    "wof:name":"Monsterware Custom Computers Inc",
    "wof:placetype":"venue"
},
  "geometry": {"coordinates":[-74.18249400000001,40.556172],"type":"Point"}
}