{
  "type": "Feature",
  "properties": {
    "addr:full":"3915 Main Street Flushing NY 11354",
    "addr:housenumber":"3915",
    "addr:postcode":"11354",
    "addr:street":"Main Street",
    "iso:country":"US",
    "sg:address":"3915 Main Street",
    "sg:city":"Flushing",
    "sg:classifiers":[
        {
            "category":"Banks & Credit Unions",
            "subcategory":"Financial Services",
            "type":"Services"
        }
    ],
    "sg:phone":"+1 718 353 2974",
    "sg:postcode":"11354",
    "sg:province":"NY",
    "sg:tags":[
        "broker",
        "mortgage"
    ],
    "wof:name":"Upland Financial Equities",
    "wof:placetype":"venue"
},
  "geometry": {"coordinates":[-73.830477,40.760234],"type":"Point"}
}