{
  "type": "Feature",
  "properties": {
    "addr:full":"43 E 93 St New York NY 10128",
    "addr:housenumber":"43;93",
    "addr:postcode":"10128",
    "addr:street":"E;St",
    "iso:country":"US",
    "sg:address":"43 E 93 St",
    "sg:city":"New York",
    "sg:classifiers":[
        {
            "category":"Retail",
            "subcategory":"Auto Repair",
            "type":"Services"
        }
    ],
    "sg:phone":"+1 212 792 7438",
    "sg:postcode":"10128",
    "sg:province":"NY",
    "sg:tags":[
        "wrecker"
    ],
    "wof:name":"A A Always Towing",
    "wof:placetype":"venue"
},
  "geometry": {"coordinates":[-73.956591,40.785963],"type":"Point"}
}