{
  "type": "Feature",
  "properties": {
    "iso:country":"US",
    "sg:address":"135 Main St",
    "sg:city":"Islip",
    "sg:classifiers":[
        {
            "category":"Social Services",
            "subcategory":"Child Care",
            "type":"Services"
        }
    ],
    "sg:phone":"+1   ",
    "sg:postcode":"11751",
    "sg:province":"NY",
    "sg:tags":[
        "day"
    ],
    "wof:name":"ABC 123 Preschool Learning Ctr",
    "wof:placetype":"venue"
},
  "geometry": {"coordinates":[-73.22203,40.727934],"type":"Point"}
}