{
  "type": "Feature",
  "properties": {
    "iso:country":"US",
    "sg:address":"2419 State Rte 66",
    "sg:city":"Chatham",
    "sg:classifiers":[
        {
            "category":"Home & Garden",
            "subcategory":"Garden Supply",
            "type":"Retail Goods"
        }
    ],
    "sg:phone":"+1 518 392 2011",
    "sg:postcode":"12037",
    "sg:province":"NY",
    "sg:tags":[
        "lawn",
        "mower"
    ],
    "wof:name":"Bob's Lawn & Garden LTD",
    "wof:placetype":"venue"
},
  "geometry": {"coordinates":[-73.611322,42.332763],"type":"Point"}
}