{
  "type": "Feature",
  "properties": {
    "iso:country":"US",
    "sg:address":"9 Madison Ave",
    "sg:city":"Bay Shore",
    "sg:classifiers":[
        {
            "category":"Autos & Motor Vehicles",
            "subcategory":"Auto Supplies",
            "type":"Retail Goods"
        }
    ],
    "sg:phone":"+1 631 242 8864",
    "sg:postcode":"11706",
    "sg:province":"NY",
    "sg:tags":[
        "tire"
    ],
    "wof:name":"Roadside Wholesale Tires",
    "wof:placetype":"venue"
},
  "geometry": {"coordinates":[-73.23581,40.742099],"type":"Point"}
}