{
  "type": "Feature",
  "properties": {
    "addr:full":"39 Wyandanch Ave Wyandanch NY 11798",
    "addr:housenumber":"39",
    "addr:postcode":"11798",
    "addr:street":"Wyandanch Ave",
    "iso:country":"US",
    "sg:address":"39 Wyandanch Ave",
    "sg:city":"Wyandanch",
    "sg:classifiers":[
        {
            "category":"Wholesale",
            "subcategory":"Construction Materials",
            "type":"Manufacturing & Wholesale Goods"
        }
    ],
    "sg:phone":"+1 631 643 5067",
    "sg:postcode":"11798",
    "sg:province":"NY",
    "sg:tags":[
        "marble"
    ],
    "wof:name":"Silestone New York",
    "wof:placetype":"venue"
},
  "geometry": {"coordinates":[-73.364351,40.741675],"type":"Point"}
}