{
  "type": "Feature",
  "properties": {
    "addr:full":"4241 Hylan Blvd Staten Island NY 10312",
    "addr:housenumber":"4241",
    "addr:postcode":"10312",
    "addr:street":"Hylan Blvd",
    "iso:country":"US",
    "sg:address":"4241 Hylan Blvd",
    "sg:city":"Staten Island",
    "sg:classifiers":[
        {
            "category":"Health Services",
            "subcategory":"Doctor",
            "type":"Services"
        },
        {
            "category":"Health Services",
            "subcategory":"Chiropractor",
            "type":"Services"
        }
    ],
    "sg:phone":"+1 718 967 7016",
    "sg:postcode":"10312",
    "sg:province":"NY",
    "wof:name":"Shakhanova Alla Dr",
    "wof:placetype":"venue"
},
  "geometry": {"coordinates":[-74.150902,40.5368],"type":"Point"}
}