{
  "type": "Feature",
  "properties": {
    "addr:full":"15 Division St New York NY 10002",
    "addr:housenumber":"15",
    "addr:postcode":"10002",
    "addr:street":"Division St",
    "iso:country":"US",
    "sg:address":"15 Division St",
    "sg:city":"New York",
    "sg:classifiers":[
        {
            "category":"Professional",
            "subcategory":"Lawyer & Legal Services",
            "type":"Services"
        }
    ],
    "sg:phone":"+1 212 966 9812",
    "sg:postcode":"10002",
    "sg:province":"NY",
    "wof:name":"Wendys",
    "wof:placetype":"venue"
},
  "geometry": {"coordinates":[-73.99533,40.714082],"type":"Point"}
}