{
  "type": "Feature",
  "properties": {
    "addr:full":"1027 Texas Valley Rd Marathon NY 13803",
    "addr:housenumber":"1027",
    "addr:postcode":"13803",
    "addr:street":"Texas Valley Rd",
    "iso:country":"US",
    "sg:address":"1027 Texas Valley Rd",
    "sg:city":"Marathon",
    "sg:classifiers":[
        {
            "category":"Farming",
            "subcategory":"Dairy Farm",
            "type":"Manufacturing & Wholesale Goods"
        }
    ],
    "sg:phone":"+1 607 849 3783",
    "sg:postcode":"13803",
    "sg:province":"NY",
    "wof:name":"David Swan",
    "wof:placetype":"venue"
},
  "geometry": {"coordinates":[-75.988845,42.460595],"type":"Point"}
}