{
  "type": "Feature",
  "properties": {
    "addr:full":"139 Erie Blvd Schenectady NY 12305",
    "addr:housenumber":"139",
    "addr:postcode":"12305",
    "addr:street":"Erie Blvd",
    "iso:country":"US",
    "sg:address":"139 Erie Blvd",
    "sg:city":"Schenectady",
    "sg:classifiers":[
        {
            "category":"Shopping",
            "type":"Retail Goods"
        },
        {
            "category":"Shopping",
            "subcategory":"Computers & Home Electronics",
            "type":"Retail Goods"
        }
    ],
    "sg:phone":"+1 518 377 8000",
    "sg:postcode":"12305",
    "sg:province":"NY",
    "sg:tags":[
        "stationery",
        "wholesale",
        "merchandise",
        "equipment"
    ],
    "sg:website":"http://www.easternoffice.com",
    "wof:name":"Eastern Office Supply",
    "wof:placetype":"venue"
},
  "geometry": {"coordinates":[-73.94728499999999,42.812685],"type":"Point"}
}