{
  "type": "Feature",
  "properties": {
    "iso:country":"US",
    "sg:address":"111 W 40 St",
    "sg:city":"New York",
    "sg:classifiers":[
        {
            "category":"Professional",
            "type":"Services"
        }
    ],
    "sg:phone":"+1 212 730 4300",
    "sg:postcode":"10018",
    "sg:province":"NY",
    "sg:tags":[
        "establishment"
    ],
    "wof:name":"Badische Corp",
    "wof:placetype":"venue"
},
  "geometry": {"coordinates":[-73.986397,40.754145],"type":"Point"}
}