{
  "type": "Feature",
  "properties": {
    "iso:country":"US",
    "sg:address":"130 W Fordham Rd",
    "sg:city":"Bronx",
    "sg:classifiers":[
        {
            "category":"Food & Beverages",
            "subcategory":"Groceries & Convenience Stores",
            "type":"Retail Goods"
        }
    ],
    "sg:phone":"+1   ",
    "sg:postcode":"10468",
    "sg:province":"NY",
    "wof:name":"Muniz Grocery",
    "wof:placetype":"venue"
},
  "geometry": {"coordinates":[-73.907049,40.862722],"type":"Point"}
}