{
  "type": "Feature",
  "properties": {
    "addr:full":"211 Royal Pl Mamaroneck NY 10543",
    "addr:housenumber":"211",
    "addr:postcode":"10543",
    "addr:street":"Royal Pl",
    "iso:country":"US",
    "sg:address":"211 Royal Pl",
    "sg:city":"Mamaroneck",
    "sg:classifiers":[
        {
            "category":"Professional",
            "subcategory":"Lawyer & Legal Services",
            "type":"Services"
        }
    ],
    "sg:phone":"+1 914 777 5457",
    "sg:postcode":"10543",
    "sg:province":"NY",
    "sg:tags":[
        "attorney",
        "practice"
    ],
    "wof:name":"Michael Grenthal",
    "wof:placetype":"venue"
},
  "geometry": {"coordinates":[-73.740235,40.941644],"type":"Point"}
}