{
  "type": "Feature",
  "properties": {
    "iso:country":"US",
    "sg:address":"68 South St",
    "sg:city":"Goshen",
    "sg:classifiers":[
        {
            "category":"Building & Trades",
            "subcategory":"Landscaping Services",
            "type":"Services"
        }
    ],
    "sg:phone":"+1 845 294 8119",
    "sg:postcode":"10924",
    "sg:province":"NY",
    "sg:tags":[
        "consultant",
        "designer",
        "landscape",
        "contractor"
    ],
    "sg:website":"http://www.allegrolandscaping.com",
    "wof:name":"Allegro Landscaping",
    "wof:placetype":"venue"
},
  "geometry": {"coordinates":[-74.322052,41.39505],"type":"Point"}
}