{
  "type": "Feature",
  "properties": {
    "addr:full":"448 Broadway New York NY 10013",
    "addr:housenumber":"448",
    "addr:postcode":"10013",
    "addr:street":"Broadway",
    "iso:country":"US",
    "sg:address":"448 Broadway",
    "sg:city":"New York",
    "sg:classifiers":[
        {
            "category":"Shopping",
            "subcategory":"Clothing, Apparel, & Fashions",
            "type":"Retail Goods"
        }
    ],
    "sg:postcode":"10013",
    "sg:province":"NY",
    "sg:tags":[
        "men's",
        "clothing"
    ],
    "wof:name":"Xios",
    "wof:placetype":"venue"
},
  "geometry": {"coordinates":[-74.001017,40.720373],"type":"Point"}
}