{
  "type": "Feature",
  "properties": {
    "iso:country":"US",
    "sg:address":"141 W 28 St",
    "sg:city":"New York",
    "sg:classifiers":[
        {
            "category":"Health Services",
            "subcategory":"Health Practitioner",
            "type":"Services"
        }
    ],
    "sg:phone":"+1   ",
    "sg:postcode":"10001",
    "sg:province":"NY",
    "wof:name":"Victor Novotny Csw",
    "wof:placetype":"venue"
},
  "geometry": {"coordinates":[-73.99244400000001,40.746812],"type":"Point"}
}