{
  "type": "Feature",
  "properties": {
    "addr:full":"120 Elgar Pl Bronx NY 10475",
    "addr:housenumber":"120",
    "addr:postcode":"10475",
    "addr:street":"Elgar Pl",
    "iso:country":"US",
    "sg:address":"120 Elgar Pl",
    "sg:city":"Bronx",
    "sg:classifiers":[
        {
            "category":"Health Services",
            "subcategory":"Doctor",
            "type":"Services"
        }
    ],
    "sg:phone":"+1 718 320 0344",
    "sg:postcode":"10475",
    "sg:province":"NY",
    "sg:tags":[
        "dentist"
    ],
    "wof:name":"Nazma Miah DDS",
    "wof:placetype":"venue"
},
  "geometry": {"coordinates":[-73.82173400000001,40.863544],"type":"Point"}
}