{
  "type": "Feature",
  "properties": {
    "addr:full":"2561 Hylan Blvd Staten Island NY 10306",
    "addr:housenumber":"2561",
    "addr:postcode":"10306",
    "addr:street":"Hylan Blvd",
    "iso:country":"US",
    "sg:address":"2561 Hylan Blvd",
    "sg:city":"Staten Island",
    "sg:classifiers":[
        {
            "category":"Autos & Motor Vehicles",
            "subcategory":"Auto Supplies",
            "type":"Retail Goods"
        }
    ],
    "sg:phone":"+1 718 979 7300",
    "sg:postcode":"10306",
    "sg:province":"NY",
    "sg:tags":[
        "tire"
    ],
    "wof:name":"Firestone Tire & Service Centers",
    "wof:placetype":"venue"
},
  "geometry": {"coordinates":[-74.116997,40.567501],"type":"Point"}
}