{
  "type": "Feature",
  "properties": {
    "iso:country":"US",
    "sg:address":"6452 Hope Ln",
    "sg:city":"Lockport",
    "sg:classifiers":[
        {
            "category":"Building & Trades",
            "subcategory":"Landscaping Services",
            "type":"Services"
        }
    ],
    "sg:phone":"+1 716 434 4921",
    "sg:postcode":"14094",
    "sg:province":"NY",
    "wof:name":"Pine Ledge Landscaping",
    "wof:placetype":"venue"
},
  "geometry": {"coordinates":[-78.67941999999999,43.230718],"type":"Point"}
}