{
  "type": "Feature",
  "properties": {
    "addr:full":"125-10 Queens Blvd Ste 307 Kew Gardens NY 11415",
    "addr:housenumber":"125-10",
    "addr:postcode":"11415",
    "addr:street":"Queens Blvd Ste 307",
    "iso:country":"US",
    "sg:address":"125-10 Queens Blvd Ste 307",
    "sg:city":"Kew Gardens",
    "sg:classifiers":[
        {
            "category":"Personal",
            "type":"Services"
        }
    ],
    "sg:phone":"+1 888 932 2458",
    "sg:postcode":"11415",
    "sg:province":"NY",
    "sg:tags":[
        "local"
    ],
    "sg:website":"www.affordablebailbondsnewyork.com",
    "wof:name":"Affordable Bail Bonds",
    "wof:placetype":"venue"
},
  "geometry": {"coordinates":[-73.826538,40.712348],"type":"Point"}
}