{
  "type": "Feature",
  "properties": {
    "addr:full":"7314 Fifth Avenue Brooklyn NY 11209",
    "addr:housenumber":"7314",
    "addr:postcode":"11209",
    "addr:street":"Fifth Avenue",
    "iso:country":"US",
    "sg:address":"7314 Fifth Avenue",
    "sg:city":"Brooklyn",
    "sg:classifiers":[
        {
            "category":"Bars & Pubs",
            "type":"Food & Drink"
        }
    ],
    "sg:phone":"+1 718 630 5266",
    "sg:postcode":"11209",
    "sg:province":"NY",
    "wof:name":"Ski Bar",
    "wof:placetype":"venue"
},
  "geometry": {"coordinates":[-74.022074,40.630895],"type":"Point"}
}