{
  "type": "Feature",
  "properties": {
    "addr:full":"River Rd Montgomery NY 12549",
    "addr:postcode":"12549",
    "addr:street":"River Rd",
    "iso:country":"US",
    "sg:address":"River Rd",
    "sg:city":"Montgomery",
    "sg:classifiers":[
        {
            "category":"Retail",
            "subcategory":"Veterinary Services",
            "type":"Services"
        }
    ],
    "sg:phone":"+1 845 457 4082",
    "sg:postcode":"12549",
    "sg:province":"NY",
    "sg:tags":[
        "veterinarian"
    ],
    "wof:name":"Stone Cottage & Montgomery Animal Hospital",
    "wof:placetype":"venue"
},
  "geometry": {"coordinates":[-74.237801,41.524799],"type":"Point"}
}