{
  "type": "Feature",
  "properties": {
    "iso:country":"US",
    "sg:address":"1183 Co Rd 17",
    "sg:city":"Russell",
    "sg:classifiers":[
        {
            "category":"Restaurant",
            "type":"Food & Drink"
        }
    ],
    "sg:phone":"+1 315 562 2000",
    "sg:postcode":"13684",
    "sg:province":"NY",
    "wof:name":"Little Brook Diner",
    "wof:placetype":"venue"
},
  "geometry": {"coordinates":[-75.155039,44.403139],"type":"Point"}
}