{
  "type": "Feature",
  "properties": {
    "addr:full":"2835 Heath Ave Bronx NY 10463",
    "addr:housenumber":"2835",
    "addr:postcode":"10463",
    "addr:street":"Heath Ave",
    "iso:country":"US",
    "sg:address":"2835 Heath Ave",
    "sg:city":"Bronx",
    "sg:classifiers":[
        {
            "category":"Parking",
            "type":"Transportation"
        }
    ],
    "sg:phone":"+1 718 548 5439",
    "sg:postcode":"10463",
    "sg:province":"NY",
    "sg:tags":[
        "garage"
    ],
    "wof:name":"Heath Parking Inc",
    "wof:placetype":"venue"
},
  "geometry": {"coordinates":[-73.904205,40.873342],"type":"Point"}
}