{
  "type": "Feature",
  "properties": {
    "addr:full":"650 Madison Ave New York NY 10022",
    "addr:housenumber":"650",
    "addr:postcode":"10022",
    "addr:street":"Madison Ave",
    "iso:country":"US",
    "sg:address":"650 Madison Ave",
    "sg:city":"New York",
    "sg:classifiers":[
        {
            "category":"Shopping",
            "subcategory":"Clothing, Apparel, & Fashions",
            "type":"Retail Goods"
        },
        {
            "category":"Manufacturing",
            "subcategory":"Leather Goods",
            "type":"Manufacturing & Wholesale Goods"
        },
        {
            "category":"Shopping",
            "subcategory":"Shoes",
            "type":"Retail Goods"
        }
    ],
    "sg:phone":"+1 212 644 5945",
    "sg:postcode":"10022",
    "sg:province":"NY",
    "sg:tags":[
        "store",
        "accessory"
    ],
    "sg:website":"www.tods.com",
    "wof:name":"Tod's",
    "wof:placetype":"venue"
},
  "geometry": {"coordinates":[-73.971001,40.764198],"type":"Point"}
}