{
  "type": "Feature",
  "properties": {
    "iso:country":"US",
    "sg:address":"36 Long Aly",
    "sg:city":"Saratoga Springs",
    "sg:classifiers":[
        {
            "category":"Real Estate",
            "subcategory":"Architect",
            "type":"Services"
        }
    ],
    "sg:phone":"+1 518 583 9004",
    "sg:postcode":"12866",
    "sg:province":"NY",
    "wof:name":"Olsen Associates",
    "wof:placetype":"venue"
},
  "geometry": {"coordinates":[-73.785583,43.083427],"type":"Point"}
}