{
  "type": "Feature",
  "properties": {
    "iso:country":"US",
    "sg:address":"112 Washington St",
    "sg:city":"Manlius",
    "sg:classifiers":[
        {
            "category":"Retail",
            "subcategory":"Repair Shop",
            "type":"Services"
        }
    ],
    "sg:phone":"+1 315 682 8267",
    "sg:postcode":"13104",
    "sg:province":"NY",
    "sg:tags":[
        "plumbing",
        "drain",
        "cleaning",
        "sewer"
    ],
    "wof:name":"Gary Terpstra Sewer & Drain",
    "wof:placetype":"venue"
},
  "geometry": {"coordinates":[-75.97516,43.001509],"type":"Point"}
}