{
  "type": "Feature",
  "properties": {
    "iso:country":"US",
    "sg:address":"202 Cold Spring Rd",
    "sg:city":"Hudson",
    "sg:classifiers":[
        {
            "category":"Arts & Performance",
            "subcategory":"Theater",
            "type":"Entertainment"
        }
    ],
    "sg:phone":"+1 518 828 0918",
    "sg:postcode":"12534",
    "sg:province":"NY",
    "sg:tags":[
        "talent",
        "agency",
        "casting"
    ],
    "wof:name":"Birch Street Design LTD",
    "wof:placetype":"venue"
},
  "geometry": {"coordinates":[-73.804649,42.167419],"type":"Point"}
}