{
  "type": "Feature",
  "properties": {
    "iso:country":"US",
    "sg:address":"222 Bloomingdale Rd Ste 311",
    "sg:city":"White Plains",
    "sg:classifiers":[
        {
            "category":"Professional",
            "subcategory":"Lawyer & Legal Services",
            "type":"Services"
        }
    ],
    "sg:phone":"+1 914 328 5600",
    "sg:postcode":"10605",
    "sg:province":"NY",
    "wof:name":"Wood & Scher",
    "wof:placetype":"venue"
},
  "geometry": {"coordinates":[-73.758241,41.356948],"type":"Point"}
}