{
  "type": "Feature",
  "properties": {
    "addr:full":"3411 Highland Ave Niagara Falls NY 14305",
    "addr:housenumber":"3411",
    "addr:postcode":"14305",
    "addr:street":"Highland Ave",
    "iso:country":"US",
    "sg:address":"3411 Highland Ave",
    "sg:city":"Niagara Falls",
    "sg:classifiers":[
        {
            "category":"Manufacturing",
            "subcategory":"Metals",
            "type":"Manufacturing & Wholesale Goods"
        }
    ],
    "sg:phone":"+1 716 282 6101",
    "sg:postcode":"14305",
    "sg:province":"NY",
    "sg:tags":[
        "wire"
    ],
    "sg:website":"www.braungroup.com",
    "wof:name":"Braun Horticulture Inc",
    "wof:placetype":"venue"
},
  "geometry": {"coordinates":[-79.046212,43.118743],"type":"Point"}
}