{
  "type": "Feature",
  "properties": {
    "addr:full":"14 Von Braun Ave Staten Island NY 10312",
    "addr:housenumber":"14",
    "addr:postcode":"10312",
    "addr:street":"Von Braun Ave",
    "iso:country":"US",
    "sg:address":"14 Von Braun Ave",
    "sg:city":"Staten Island",
    "sg:classifiers":[
        {
            "category":"Wholesale",
            "subcategory":"Furniture",
            "type":"Manufacturing & Wholesale Goods"
        }
    ],
    "sg:phone":"+1 917 797 9847",
    "sg:postcode":"10312",
    "sg:province":"NY",
    "wof:name":"Partitions Plus Inc",
    "wof:placetype":"venue"
},
  "geometry": {"coordinates":[-74.17966199999999,40.556244],"type":"Point"}
}