{
  "type": "Feature",
  "properties": {
    "iso:country":"US",
    "sg:address":"959 W Beech St",
    "sg:city":"Long Beach",
    "sg:classifiers":[
        {
            "category":"Bars & Pubs",
            "type":"Food & Drink"
        },
        {
            "category":"Restaurant",
            "type":"Food & Drink"
        }
    ],
    "sg:phone":"+1 516 432 4080",
    "sg:postcode":"11561",
    "sg:province":"NY",
    "sg:tags":[
        "traditional",
        "american"
    ],
    "sg:website":"minnesotaslb.com/",
    "wof:name":"Minnesota's Grill & Bar",
    "wof:placetype":"venue"
},
  "geometry": {"coordinates":[-73.694801,40.585899],"type":"Point"}
}