{
  "type": "Feature",
  "properties": {
    "addr:full":"23 Joyce Rd Plainview NY 11803",
    "addr:housenumber":"23",
    "addr:postcode":"11803",
    "addr:street":"Joyce Rd",
    "iso:country":"US",
    "sg:address":"23 Joyce Rd",
    "sg:city":"Plainview",
    "sg:classifiers":[
        {
            "category":"Building & Trades",
            "subcategory":"Landscaping Services",
            "type":"Services"
        }
    ],
    "sg:phone":"+1 516 931 7939",
    "sg:postcode":"11803",
    "sg:province":"NY",
    "wof:name":"Brandy Wine Tree Service",
    "wof:placetype":"venue"
},
  "geometry": {"coordinates":[-73.469898,40.777609],"type":"Point"}
}