{
  "type": "Feature",
  "properties": {
    "addr:full":"24 Gramercy Park S New York NY 10003",
    "addr:housenumber":"24",
    "addr:postcode":"10003",
    "addr:street":"Gramercy Park S",
    "iso:country":"US",
    "sg:address":"24 Gramercy Park S",
    "sg:city":"New York",
    "sg:classifiers":[
        {
            "category":"Food & Beverages",
            "subcategory":"Specialty",
            "type":"Retail Goods"
        }
    ],
    "sg:phone":"+1   ",
    "sg:postcode":"10003",
    "sg:province":"NY",
    "sg:tags":[
        "gourmet",
        "import"
    ],
    "wof:name":"Tea Together USA LLC",
    "wof:placetype":"venue"
},
  "geometry": {"coordinates":[-73.98628100000001,40.737643],"type":"Point"}
}