{
  "type": "Feature",
  "properties": {
    "iso:country":"US",
    "sg:address":"4 Fair Acres Rd",
    "sg:city":"Nyack",
    "sg:classifiers":[
        {
            "category":"Building & Trades",
            "subcategory":"Construction",
            "type":"Services"
        }
    ],
    "sg:phone":"+1 845 358 5848",
    "sg:postcode":"10960",
    "sg:province":"NY",
    "sg:tags":[
        "contractor"
    ],
    "wof:name":"Edward Corey Roofing",
    "wof:placetype":"venue"
},
  "geometry": {"coordinates":[-73.946873,41.091952],"type":"Point"}
}