{
  "type": "Feature",
  "properties": {
    "addr:full":"226 Sleepy Hollow Rd Briarcliff Manor NY 10510",
    "addr:housenumber":"226",
    "addr:postcode":"10510",
    "addr:street":"Sleepy Hollow Rd",
    "iso:country":"US",
    "sg:address":"226 Sleepy Hollow Rd",
    "sg:city":"Briarcliff Manor",
    "sg:classifiers":[
        {
            "category":"Professional",
            "type":"Services"
        }
    ],
    "sg:phone":"+1 914 509 6800",
    "sg:postcode":"10510",
    "sg:province":"NY",
    "sg:tags":[
        "establishment"
    ],
    "wof:name":"Richard L Ellis Assoc",
    "wof:placetype":"venue"
},
  "geometry": {"coordinates":[-73.83907600000001,41.13803],"type":"Point"}
}