{
  "type": "Feature",
  "properties": {
    "addr:full":"6545 State Hwy 26 Rome NY 13440",
    "addr:housenumber":"6545",
    "addr:postcode":"13440",
    "addr:street":"State Hwy 26",
    "iso:country":"US",
    "sg:address":"6545 State Hwy 26",
    "sg:city":"Rome",
    "sg:classifiers":[
        {
            "category":"Organizations",
            "subcategory":"Non-profit Organization",
            "type":"Services"
        }
    ],
    "sg:phone":"+1 315 339 6800",
    "sg:postcode":"13440",
    "sg:province":"NY",
    "sg:tags":[
        "disability"
    ],
    "wof:name":"Central NEW York Dso",
    "wof:placetype":"venue"
},
  "geometry": {"coordinates":[-75.488192,43.185066],"type":"Point"}
}