{
  "type": "Feature",
  "properties": {
    "iso:country":"US",
    "sg:address":"5910 20th Avenue",
    "sg:city":"Brooklyn",
    "sg:classifiers":[
        {
            "category":"Food & Beverages",
            "subcategory":"Groceries & Convenience Stores",
            "type":"Retail Goods"
        }
    ],
    "sg:phone":"+1 718 837 2500",
    "sg:postcode":"11204",
    "sg:province":"NY",
    "wof:name":"Bps",
    "wof:placetype":"venue"
},
  "geometry": {"coordinates":[-73.98249,40.619932],"type":"Point"}
}