{
  "type": "Feature",
  "properties": {
    "addr:full":"2989 Glenwood Ct Oceanside NY 11572",
    "addr:housenumber":"2989",
    "addr:postcode":"11572",
    "addr:street":"Glenwood Ct",
    "iso:country":"US",
    "sg:address":"2989 Glenwood Ct",
    "sg:city":"Oceanside",
    "sg:classifiers":[
        {
            "category":"Real Estate",
            "subcategory":"Real Estate Agent",
            "type":"Services"
        }
    ],
    "sg:phone":"+1 516 536 0220",
    "sg:postcode":"11572",
    "sg:province":"NY",
    "wof:name":"Precision Rsidential Appraisal",
    "wof:placetype":"venue"
},
  "geometry": {"coordinates":[-73.649074,40.645661],"type":"Point"}
}