{
  "type": "Feature",
  "properties": {
    "iso:country":"US",
    "sg:address":"560 Vanderbilt Ave",
    "sg:city":"Brooklyn",
    "sg:classifiers":[
        {
            "category":"Shopping",
            "subcategory":"Bicycles & Sporting Goods",
            "type":"Retail Goods"
        }
    ],
    "sg:phone":"+1 347 295 2339",
    "sg:postcode":"11238",
    "sg:province":"NY",
    "sg:tags":[
        "bike"
    ],
    "sg:website":"brooklynbikeandboard.com",
    "wof:name":"Brooklyn Bike and Board",
    "wof:placetype":"venue"
},
  "geometry": {"coordinates":[-73.96841000000001,40.679891],"type":"Point"}
}