{
  "type": "Feature",
  "properties": {
    "iso:country":"US",
    "sg:address":"57 Upland St",
    "sg:city":"Port Chester",
    "sg:classifiers":[
        {
            "category":"Wholesale",
            "subcategory":"Construction Materials",
            "type":"Manufacturing & Wholesale Goods"
        },
        {
            "category":"Home & Garden",
            "subcategory":"Furniture",
            "type":"Retail Goods"
        }
    ],
    "sg:phone":"+1 914 935 3957",
    "sg:postcode":"10573",
    "sg:province":"NY",
    "sg:tags":[
        "equipment",
        "cabinet",
        "contractor",
        "kitchen",
        "trade"
    ],
    "wof:name":"All The Options Kitchens Baths",
    "wof:placetype":"venue"
},
  "geometry": {"coordinates":[-73.66815099999999,41.021087],"type":"Point"}
}