{
  "type": "Feature",
  "properties": {
    "addr:full":"899 Park Ave Ofc New York NY 10021",
    "addr:housenumber":"899",
    "addr:postcode":"10021",
    "addr:street":"Park Ave",
    "iso:country":"US",
    "sg:address":"899 Park Ave Ofc",
    "sg:city":"New York",
    "sg:classifiers":[
        {
            "category":"Health Services",
            "subcategory":"Doctor",
            "type":"Services"
        }
    ],
    "sg:phone":"+1 212 288 1735",
    "sg:postcode":"10021",
    "sg:province":"NY",
    "wof:name":"Cohen Abraham MD",
    "wof:placetype":"venue"
},
  "geometry": {"coordinates":[-73.960403,40.775299],"type":"Point"}
}