{
  "type": "Feature",
  "properties": {
    "addr:full":"130 E 35th St New York NY 10016",
    "addr:housenumber":"130",
    "addr:postcode":"10016",
    "addr:street":"E 35Th St",
    "iso:country":"US",
    "sg:address":"130 E 35th St",
    "sg:city":"New York",
    "sg:classifiers":[
        {
            "category":"Health Services",
            "subcategory":"Doctor",
            "type":"Services"
        }
    ],
    "sg:phone":"+1 212 481 3600",
    "sg:postcode":"10016",
    "sg:province":"NY",
    "wof:name":"Eric Lutsky, MD",
    "wof:placetype":"venue"
},
  "geometry": {"coordinates":[-73.979786,40.747037],"type":"Point"}
}