{
  "type": "Feature",
  "properties": {
    "addr:full":"45 James St Homer NY 13077",
    "addr:housenumber":"45",
    "addr:postcode":"13077",
    "addr:street":"James St",
    "iso:country":"US",
    "sg:address":"45 James St",
    "sg:city":"Homer",
    "sg:classifiers":[
        {
            "category":"Shopping",
            "subcategory":"Used Merchandise",
            "type":"Retail Goods"
        },
        {
            "category":"Home & Garden",
            "subcategory":"Building Materials",
            "type":"Retail Goods"
        }
    ],
    "sg:phone":"+1 607 749 8889",
    "sg:postcode":"13077",
    "sg:province":"NY",
    "wof:name":"Building Preservation Works",
    "wof:placetype":"venue"
},
  "geometry": {"coordinates":[-76.183699,42.636915],"type":"Point"}
}