{
  "type": "Feature",
  "properties": {
    "addr:full":"2640 State Hwy 31 Canastota NY 13032",
    "addr:housenumber":"2640",
    "addr:postcode":"13032",
    "addr:street":"State Hwy 31",
    "iso:country":"US",
    "sg:address":"2640 State Hwy 31",
    "sg:city":"Canastota",
    "sg:classifiers":[
        {
            "category":"Farming",
            "subcategory":"Farm",
            "type":"Manufacturing & Wholesale Goods"
        }
    ],
    "sg:phone":"+1 315 697 2797",
    "sg:postcode":"13032",
    "sg:province":"NY",
    "wof:name":"Shooting Star Farms",
    "wof:placetype":"venue"
},
  "geometry": {"coordinates":[-75.81446800000001,43.156864],"type":"Point"}
}