{
  "type": "Feature",
  "properties": {
    "iso:country":"US",
    "sg:address":"142 Baldwin Ave",
    "sg:city":"Syracuse",
    "sg:classifiers":[
        {
            "category":"Autos & Motor Vehicles",
            "subcategory":"Automobile Sales",
            "type":"Retail Goods"
        }
    ],
    "sg:phone":"+1 315 478 6021",
    "sg:postcode":"13205",
    "sg:province":"NY",
    "sg:tags":[
        "performance",
        "race",
        "dealer"
    ],
    "wof:name":"Hile Motorsports",
    "wof:placetype":"venue"
},
  "geometry": {"coordinates":[-76.15526699999999,43.015221],"type":"Point"}
}