{
  "type": "Feature",
  "properties": {
    "addr:full":"396 Saint Marks Pl Staten Island NY 10301",
    "addr:housenumber":"396",
    "addr:postcode":"10301",
    "addr:street":"Saint Marks Pl",
    "iso:country":"US",
    "sg:address":"396 Saint Marks Pl",
    "sg:city":"Staten Island",
    "sg:classifiers":[
        {
            "category":"Professional",
            "subcategory":"Lawyer & Legal Services",
            "type":"Services"
        }
    ],
    "sg:phone":"+1 718 935 9699",
    "sg:postcode":"10301",
    "sg:province":"NY",
    "wof:name":"Law Offices of Richard P Neimark",
    "wof:placetype":"venue"
},
  "geometry": {"coordinates":[-74.077698,40.640301],"type":"Point"}
}