{
  "type": "Feature",
  "properties": {
    "addr:full":"70 Pattonwood Dr Rochester NY 14617",
    "addr:housenumber":"70",
    "addr:postcode":"14617",
    "addr:street":"Pattonwood Dr",
    "iso:country":"US",
    "sg:address":"70 Pattonwood Dr",
    "sg:city":"Rochester",
    "sg:classifiers":[
        {
            "category":"Manufacturing",
            "subcategory":"Apparel",
            "type":"Manufacturing & Wholesale Goods"
        }
    ],
    "sg:phone":"+1 585 544 7150",
    "sg:postcode":"14617",
    "sg:province":"NY",
    "sg:tags":[
        "canvas",
        "product",
        "related"
    ],
    "wof:name":"Canvas Ma'Am LTD",
    "wof:placetype":"venue"
},
  "geometry": {"coordinates":[-77.608622,43.24835],"type":"Point"}
}