{
  "type": "Feature",
  "properties": {
    "iso:country":"US",
    "sg:address":"1170 1st Ave",
    "sg:city":"New York",
    "sg:classifiers":[
        {
            "category":"Retail",
            "subcategory":"Laundry & Dry Cleaning",
            "type":"Services"
        }
    ],
    "sg:phone":"+1 212 472 4949",
    "sg:postcode":"10021",
    "sg:province":"NY",
    "wof:name":"Ptv Corp",
    "wof:placetype":"venue"
},
  "geometry": {"coordinates":[-73.959503,40.763199],"type":"Point"}
}