{
  "type": "Feature",
  "properties": {
    "addr:full":"7701 Packard Rd Niagara Falls NY 14304",
    "addr:housenumber":"7701",
    "addr:postcode":"14304",
    "addr:street":"Packard Rd",
    "iso:country":"US",
    "sg:address":"7701 Packard Rd",
    "sg:city":"Niagara Falls",
    "sg:classifiers":[
        {
            "category":"Autos & Motor Vehicles",
            "subcategory":"Automobile Sales",
            "type":"Retail Goods"
        }
    ],
    "sg:phone":"+1   ",
    "sg:postcode":"14304",
    "sg:province":"NY",
    "wof:name":"Charliess Repair Service",
    "wof:placetype":"venue"
},
  "geometry": {"coordinates":[-78.97521,43.113311],"type":"Point"}
}