{
  "type": "Feature",
  "properties": {
    "addr:full":"107 Hemmer Rd Livingston Manor NY 12758",
    "addr:housenumber":"107",
    "addr:postcode":"12758",
    "addr:street":"Hemmer Rd",
    "iso:country":"US",
    "sg:address":"107 Hemmer Rd",
    "sg:city":"Livingston Manor",
    "sg:classifiers":[
        {
            "category":"Real Estate",
            "subcategory":"Real Estate Agent",
            "type":"Services"
        }
    ],
    "sg:phone":"+1 845 482 5681",
    "sg:postcode":"12758",
    "sg:province":"NY",
    "wof:name":"G & C Properties",
    "wof:placetype":"venue"
},
  "geometry": {"coordinates":[-74.92221600000001,41.800586],"type":"Point"}
}