{
  "type": "Feature",
  "properties": {
    "iso:country":"US",
    "sg:address":"141-20 Holly Ave",
    "sg:city":"Flushing",
    "sg:classifiers":[
        {
            "category":"Restaurant",
            "type":"Food & Drink"
        }
    ],
    "sg:phone":"+1 718 353 5070",
    "sg:postcode":"11355",
    "sg:province":"NY",
    "sg:tags":[
        "pizza"
    ],
    "sg:website":"www.armanospizzeria.com",
    "wof:name":"Armano's Pizzeria & Restaurant",
    "wof:placetype":"venue"
},
  "geometry": {"coordinates":[-73.817851,40.751446],"type":"Point"}
}