{
  "type": "Feature",
  "properties": {
    "iso:country":"US",
    "sg:address":"584 Broadway",
    "sg:city":"Kingston",
    "sg:classifiers":[
        {
            "category":"Food & Beverages",
            "subcategory":"Bakery",
            "type":"Retail Goods"
        }
    ],
    "sg:phone":"+1   ",
    "sg:postcode":"12401",
    "sg:province":"NY",
    "sg:tags":[
        "eating"
    ],
    "wof:name":"Deisings Bky & Cof Sp Midtown",
    "wof:placetype":"venue"
},
  "geometry": {"coordinates":[-74.003604,41.929193],"type":"Point"}
}