{
  "type": "Feature",
  "properties": {
    "addr:full":"155 E 93rd St New York NY 10128",
    "addr:housenumber":"155",
    "addr:postcode":"10128",
    "addr:street":"E 93Rd St",
    "iso:country":"US",
    "sg:address":"155 E 93rd St",
    "sg:city":"New York",
    "sg:classifiers":[
        {
            "category":"Professional",
            "subcategory":"Accounting & Tax Preparation",
            "type":"Services"
        }
    ],
    "sg:phone":"+1 212 683 3711",
    "sg:postcode":"10128",
    "sg:province":"NY",
    "sg:tags":[
        "accountant"
    ],
    "wof:name":"Goldman Morris PC",
    "wof:placetype":"venue"
},
  "geometry": {"coordinates":[-73.95230100000001,40.783901],"type":"Point"}
}