{
  "type": "Feature",
  "properties": {
    "addr:full":"3155 Amboy Rd Ste 2 Staten Island NY 10306",
    "addr:housenumber":"3155",
    "addr:postcode":"10306",
    "addr:street":"Amboy Rd Ste 2",
    "iso:country":"US",
    "sg:address":"3155 Amboy Rd Ste 2",
    "sg:city":"Staten Island",
    "sg:classifiers":[
        {
            "category":"Banks & Credit Unions",
            "subcategory":"Bank",
            "type":"Services"
        }
    ],
    "sg:phone":"+1 718 668 1526",
    "sg:postcode":"10306",
    "sg:province":"NY",
    "wof:name":"Chase",
    "wof:placetype":"venue"
},
  "geometry": {"coordinates":[-74.131877,40.564638],"type":"Point"}
}