{
  "type": "Feature",
  "properties": {
    "addr:full":"3406 73rd Street Jackson Heights NY 11372",
    "addr:housenumber":"3406",
    "addr:postcode":"11372",
    "addr:street":"73Rd Street",
    "iso:country":"US",
    "sg:address":"3406 73rd Street",
    "sg:city":"Jackson Heights",
    "sg:classifiers":[
        {
            "category":"Health Services",
            "subcategory":"Doctor",
            "type":"Services"
        }
    ],
    "sg:phone":"+1 718 205 7307",
    "sg:postcode":"11372",
    "sg:province":"NY",
    "wof:name":"Positive Health Management",
    "wof:placetype":"venue"
},
  "geometry": {"coordinates":[-73.8934,40.752754],"type":"Point"}
}