{
  "type": "Feature",
  "properties": {
    "iso:country":"US",
    "sg:address":"318 Park Ave",
    "sg:city":"Corning",
    "sg:classifiers":[
        {
            "category":"Education",
            "subcategory":"College",
            "type":"Public Place"
        }
    ],
    "sg:phone":"+1 607 962 1421",
    "sg:postcode":"14830",
    "sg:province":"NY",
    "wof:name":"Empire State College",
    "wof:placetype":"venue"
},
  "geometry": {"coordinates":[-77.03686500000001,42.133533],"type":"Point"}
}