{
  "type": "Feature",
  "properties": {
    "addr:full":"624 Peconic Ave West Babylon NY 11704",
    "addr:housenumber":"624",
    "addr:postcode":"11704",
    "addr:street":"Peconic Ave",
    "iso:country":"US",
    "sg:address":"624 Peconic Ave",
    "sg:city":"West Babylon",
    "sg:classifiers":[
        {
            "category":"Manufacturing",
            "subcategory":"Signs",
            "type":"Manufacturing & Wholesale Goods"
        }
    ],
    "sg:phone":"+1   ",
    "sg:postcode":"11704",
    "sg:province":"NY",
    "sg:tags":[
        "specialty",
        "mfg"
    ],
    "wof:name":"JAM Signs",
    "wof:placetype":"venue"
},
  "geometry": {"coordinates":[-73.35284799999999,40.716845],"type":"Point"}
}