{
  "type": "Feature",
  "properties": {
    "addr:full":"344 W 38th St Fl 2 New York NY 10018",
    "addr:housenumber":"344;2",
    "addr:postcode":"10018",
    "addr:street":"W 38Th St",
    "iso:country":"US",
    "sg:address":"344 W 38th St Fl 2",
    "sg:city":"New York",
    "sg:classifiers":[
        {
            "category":"Education",
            "subcategory":"School",
            "type":"Public Place"
        }
    ],
    "sg:phone":"+1 212 643 2614",
    "sg:postcode":"10018",
    "sg:province":"NY",
    "wof:name":"Penny Templeton Studio",
    "wof:placetype":"venue"
},
  "geometry": {"coordinates":[-73.993853,40.755403],"type":"Point"}
}