{
  "type": "Feature",
  "properties": {
    "iso:country":"US",
    "sg:address":"41 Lloyd Harbor Rd",
    "sg:city":"Lloyd Harbor",
    "sg:classifiers":[
        {
            "category":"Organizations",
            "subcategory":"Membership Organization",
            "type":"Services"
        },
        {
            "category":"Recreation",
            "type":"Entertainment"
        }
    ],
    "sg:phone":"+1 631 424 6110",
    "sg:postcode":"11743",
    "sg:province":"NY",
    "sg:tags":[
        "society",
        "historical"
    ],
    "wof:name":"Lloyd Harbor Historical Soc",
    "wof:placetype":"venue"
},
  "geometry": {"coordinates":[-73.469284,40.914287],"type":"Point"}
}