{
  "type": "Feature",
  "properties": {
    "addr:full":"350 Fairview Ave Hudson NY 12534",
    "addr:housenumber":"350",
    "addr:postcode":"12534",
    "addr:street":"Fairview Ave",
    "iso:country":"US",
    "sg:address":"350 Fairview Ave",
    "sg:city":"Hudson",
    "sg:classifiers":[
        {
            "category":"Personal",
            "subcategory":"Beauty Salon",
            "type":"Services"
        }
    ],
    "sg:phone":"+1 518 828 4560",
    "sg:postcode":"12534",
    "sg:province":"NY",
    "sg:tags":[
        "manicuring"
    ],
    "wof:name":"Nail 7",
    "wof:placetype":"venue"
},
  "geometry": {"coordinates":[-73.761213,42.269543],"type":"Point"}
}