{
  "type": "Feature",
  "properties": {
    "addr:full":"160 Pearl St New York NY 10005",
    "addr:housenumber":"160",
    "addr:postcode":"10005",
    "addr:street":"Pearl St",
    "iso:country":"US",
    "sg:address":"160 Pearl St",
    "sg:city":"New York",
    "sg:classifiers":[
        {
            "category":"Communications",
            "subcategory":"Film & Video Production",
            "type":"Services"
        }
    ],
    "sg:phone":"+1 212 269 8740",
    "sg:postcode":"10005",
    "sg:province":"NY",
    "sg:tags":[
        "television",
        "commercial"
    ],
    "wof:name":"Front Page New York",
    "wof:placetype":"venue"
},
  "geometry": {"coordinates":[-74.007452,40.70605],"type":"Point"}
}