{
  "type": "Feature",
  "properties": {
    "addr:full":"101 Glenwood Ave Syracuse NY 13207",
    "addr:housenumber":"101",
    "addr:postcode":"13207",
    "addr:street":"Glenwood Ave",
    "iso:country":"US",
    "sg:address":"101 Glenwood Ave",
    "sg:city":"Syracuse",
    "sg:classifiers":[
        {
            "category":"Food & Beverages",
            "subcategory":"Groceries & Convenience Stores",
            "type":"Retail Goods"
        }
    ],
    "sg:phone":"+1 315 471 0050",
    "sg:postcode":"13207",
    "sg:province":"NY",
    "wof:name":"Omega Boss Market",
    "wof:placetype":"venue"
},
  "geometry": {"coordinates":[-76.16164999999999,43.018985],"type":"Point"}
}