{
  "type": "Feature",
  "properties": {
    "addr:full":"1193 3rd Avenue New York NY 10021",
    "addr:housenumber":"1193",
    "addr:postcode":"10021",
    "addr:street":"3Rd Avenue",
    "iso:country":"US",
    "sg:address":"1193 3rd Avenue",
    "sg:city":"New York",
    "sg:classifiers":[
        {
            "category":"Insurance",
            "subcategory":"Health Insurance",
            "type":"Services"
        }
    ],
    "sg:phone":"+1 212 288 6053",
    "sg:postcode":"10021",
    "sg:province":"NY",
    "sg:tags":[
        "market"
    ],
    "sg:website":"www.vitaminshoppe.com/",
    "wof:name":"The Vitamin Shoppe",
    "wof:placetype":"venue"
},
  "geometry": {"coordinates":[-73.961868,40.767988],"type":"Point"}
}