{
  "type": "Feature",
  "properties": {
    "iso:country":"US",
    "sg:address":"15 Hunt Ln",
    "sg:city":"Levittown",
    "sg:classifiers":[
        {
            "category":"Wholesale",
            "subcategory":"Machinery & Supplies",
            "type":"Manufacturing & Wholesale Goods"
        }
    ],
    "sg:phone":"+1 516 796 1760",
    "sg:postcode":"11756",
    "sg:province":"NY",
    "sg:tags":[
        "instrument",
        "scientific",
        "apparatus"
    ],
    "wof:name":"The Sextant Group Inc",
    "wof:placetype":"venue"
},
  "geometry": {"coordinates":[-73.517954,40.715971],"type":"Point"}
}