{
  "type": "Feature",
  "properties": {
    "addr:full":"111 W 40 St New York NY 10018",
    "addr:housenumber":"111",
    "addr:postcode":"10018",
    "addr:street":"W 40 St",
    "iso:country":"US",
    "sg:address":"111 W 40 St",
    "sg:city":"New York",
    "sg:classifiers":[
        {
            "category":"Insurance",
            "subcategory":"Insurance Agent",
            "type":"Services"
        }
    ],
    "sg:phone":"+1 212 338 2000",
    "sg:postcode":"10018",
    "sg:province":"NY",
    "sg:tags":[
        "company"
    ],
    "sg:website":"www.kayegroup.com",
    "wof:name":"HUB International Northeast",
    "wof:placetype":"venue"
},
  "geometry": {"coordinates":[-73.986397,40.754145],"type":"Point"}
}