{
  "type": "Feature",
  "properties": {
    "iso:country":"US",
    "sg:address":"883 Pulaski Hwy",
    "sg:city":"Goshen",
    "sg:classifiers":[
        {
            "category":"Manufacturing",
            "subcategory":"Glass & Minerals",
            "type":"Manufacturing & Wholesale Goods"
        }
    ],
    "sg:phone":"+1   ",
    "sg:postcode":"10924",
    "sg:province":"NY",
    "sg:tags":[
        "product",
        "mfg"
    ],
    "wof:name":"Fox Enterprises",
    "wof:placetype":"venue"
},
  "geometry": {"coordinates":[-74.398984,41.340052],"type":"Point"}
}