{
  "type": "Feature",
  "properties": {
    "iso:country":"US",
    "sg:address":"942 Monroe Ave",
    "sg:city":"Rochester",
    "sg:classifiers":[
        {
            "category":"Shopping",
            "subcategory":"Jewelry",
            "type":"Retail Goods"
        }
    ],
    "sg:phone":"+1   ",
    "sg:postcode":"14620",
    "sg:province":"NY",
    "wof:name":"Hecates Pupil",
    "wof:placetype":"venue"
},
  "geometry": {"coordinates":[-77.58324,43.140721],"type":"Point"}
}