{
  "type": "Feature",
  "properties": {
    "addr:full":"7767 Oswego Rd Liverpool NY 13090",
    "addr:housenumber":"7767",
    "addr:postcode":"13090",
    "addr:street":"Oswego Rd",
    "iso:country":"US",
    "sg:address":"7767 Oswego Rd",
    "sg:city":"Liverpool",
    "sg:classifiers":[
        {
            "category":"Professional",
            "subcategory":"Lawyer & Legal Services",
            "type":"Services"
        }
    ],
    "sg:phone":"+1 315 471 9686",
    "sg:postcode":"13090",
    "sg:province":"NY",
    "sg:tags":[
        "attorney"
    ],
    "wof:name":"Robert C Paltz & Affiliates",
    "wof:placetype":"venue"
},
  "geometry": {"coordinates":[-76.229805,43.14955],"type":"Point"}
}