{
  "type": "Feature",
  "properties": {
    "iso:country":"US",
    "sg:address":"76 Main St",
    "sg:city":"Cold Spring",
    "sg:classifiers":[
        {
            "category":"Restaurant",
            "type":"Food & Drink"
        }
    ],
    "sg:phone":"+1 845 265 7676",
    "sg:postcode":"10516",
    "sg:province":"NY",
    "wof:name":"Brasserie Le Bouchon Rstrnts",
    "wof:placetype":"venue"
},
  "geometry": {"coordinates":[-73.958372,41.417831],"type":"Point"}
}