{
  "type": "Feature",
  "properties": {
    "addr:full":"5656 State Hwy 5 Vernon NY 13476",
    "addr:housenumber":"5656",
    "addr:postcode":"13476",
    "addr:street":"State Hwy 5",
    "iso:country":"US",
    "sg:address":"5656 State Hwy 5",
    "sg:city":"Vernon",
    "sg:classifiers":[
        {
            "category":"Restaurant",
            "type":"Food & Drink"
        }
    ],
    "sg:phone":"+1 315 829 2203",
    "sg:postcode":"13476",
    "sg:province":"NY",
    "wof:name":"Black Stallion",
    "wof:placetype":"venue"
},
  "geometry": {"coordinates":[-75.50727999999999,43.073326],"type":"Point"}
}