{
  "type": "Feature",
  "properties": {
    "iso:country":"US",
    "sg:address":"66 Co Rd 70",
    "sg:city":"Stillwater",
    "sg:classifiers":[
        {
            "category":"Wholesale",
            "subcategory":"Motor Vehicles",
            "type":"Manufacturing & Wholesale Goods"
        }
    ],
    "sg:phone":"+1 518 584 5371",
    "sg:postcode":"12170",
    "sg:province":"NY",
    "wof:name":"George Dale Used Cars",
    "wof:placetype":"venue"
},
  "geometry": {"coordinates":[-73.707567,43.001519],"type":"Point"}
}