{
  "type": "Feature",
  "properties": {
    "iso:country":"US",
    "sg:address":"255 E 94th St",
    "sg:city":"Brooklyn",
    "sg:classifiers":[
        {
            "category":"Personal",
            "subcategory":"Beauty Salon",
            "type":"Services"
        }
    ],
    "sg:phone":"+1   ",
    "sg:postcode":"11212",
    "sg:province":"NY",
    "sg:tags":[
        "shop"
    ],
    "wof:name":"Marva Hair Studio",
    "wof:placetype":"venue"
},
  "geometry": {"coordinates":[-73.923655,40.661052],"type":"Point"}
}