{
  "type": "Feature",
  "properties": {
    "iso:country":"US",
    "sg:address":"3303 Long Beach Rd",
    "sg:city":"Oceanside",
    "sg:classifiers":[
        {
            "category":"Wholesale",
            "subcategory":"Machinery & Supplies",
            "type":"Manufacturing & Wholesale Goods"
        }
    ],
    "sg:phone":"+1 516 763 2783",
    "sg:postcode":"11572",
    "sg:province":"NY",
    "sg:tags":[
        "equipment",
        "establishment"
    ],
    "wof:name":"Arties Salon & Day Spa",
    "wof:placetype":"venue"
},
  "geometry": {"coordinates":[-73.640855,40.630708],"type":"Point"}
}