{
  "type": "Feature",
  "properties": {
    "addr:full":"15 Maiden Ln Ste 1108 New York NY 10038",
    "addr:housenumber":"15",
    "addr:postcode":"10038",
    "addr:street":"Maiden Ln Ste 1108",
    "iso:country":"US",
    "sg:address":"15 Maiden Ln Ste 1108",
    "sg:city":"New York",
    "sg:classifiers":[
        {
            "category":"Professional",
            "subcategory":"Lawyer & Legal Services",
            "type":"Services"
        }
    ],
    "sg:phone":"+1 212 528 1500",
    "sg:postcode":"10038",
    "sg:province":"NY",
    "wof:name":"Fromme Douglas L Atty",
    "wof:placetype":"venue"
},
  "geometry": {"coordinates":[-74.0093,40.7094],"type":"Point"}
}