{
  "type": "Feature",
  "properties": {
    "addr:full":"8609 Bay 16th Street Apt. D-2 Brooklyn NY 11214",
    "addr:housenumber":"8609",
    "addr:postcode":"11214",
    "addr:street":"Bay 16Th Street Apt. D-2",
    "iso:country":"US",
    "sg:address":"8609 Bay 16th Street Apt. D-2",
    "sg:city":"Brooklyn",
    "sg:classifiers":[
        {
            "category":"Building & Trades",
            "subcategory":"Construction",
            "type":"Services"
        }
    ],
    "sg:phone":"+1 718 331 7266",
    "sg:postcode":"11214",
    "sg:province":"NY",
    "sg:tags":[
        "painter"
    ],
    "sg:website":"www.khanpainting.net",
    "wof:name":"Khan Painting",
    "wof:placetype":"venue"
},
  "geometry": {"coordinates":[-74.004256,40.60765],"type":"Point"}
}