{
  "type": "Feature",
  "properties": {
    "addr:full":"157 State Hwy 303 Valley Cottage NY 10989",
    "addr:housenumber":"157",
    "addr:postcode":"10989",
    "addr:street":"State Hwy 303 Valley",
    "iso:country":"US",
    "sg:address":"157 State Hwy 303",
    "sg:city":"Valley Cottage",
    "sg:classifiers":[
        {
            "category":"Shopping",
            "subcategory":"Discount & Variety Stores",
            "type":"Retail Goods"
        }
    ],
    "sg:phone":"+1   ",
    "sg:postcode":"10989",
    "sg:province":"NY",
    "sg:tags":[
        "merchandise",
        "general"
    ],
    "wof:name":"BJs Wholesale Club",
    "wof:placetype":"venue"
},
  "geometry": {"coordinates":[-73.942117,41.123214],"type":"Point"}
}