{
  "type": "Feature",
  "properties": {
    "iso:country":"US",
    "sg:address":"475 State Route 17M Ste 18",
    "sg:city":"Monroe",
    "sg:classifiers":[
        {
            "category":"Personal",
            "type":"Services"
        },
        {
            "category":"Retail",
            "subcategory":"Laundry & Dry Cleaning",
            "type":"Services"
        }
    ],
    "sg:phone":"+1 845 783 3317",
    "sg:postcode":"10950",
    "sg:province":"NY",
    "sg:tags":[
        "sewing",
        "alteration"
    ],
    "sg:website":"www.monroecleaners.com",
    "wof:name":"Monroe Cleaners",
    "wof:placetype":"venue"
},
  "geometry": {"coordinates":[-74.17474199999999,41.315392],"type":"Point"}
}