{
  "type": "Feature",
  "properties": {
    "addr:full":"115 Bi County Blvd Farmingdale NY 11735",
    "addr:housenumber":"115",
    "addr:postcode":"11735",
    "addr:street":"Bi County Blvd",
    "iso:country":"US",
    "sg:address":"115 Bi County Blvd",
    "sg:city":"Farmingdale",
    "sg:classifiers":[
        {
            "category":"Professional",
            "subcategory":"Accounting & Tax Preparation",
            "type":"Services"
        }
    ],
    "sg:phone":"+1 631 293 3030",
    "sg:postcode":"11735",
    "sg:province":"NY",
    "sg:tags":[
        "billing"
    ],
    "sg:website":"www.datalineinc.com",
    "wof:name":"Dataline Inc",
    "wof:placetype":"venue"
},
  "geometry": {"coordinates":[-73.428271,40.725887],"type":"Point"}
}