{
  "type": "Feature",
  "properties": {
    "addr:full":"30 Dorris Dr Elma NY 14059",
    "addr:housenumber":"30",
    "addr:postcode":"14059",
    "addr:street":"Dorris Dr",
    "iso:country":"US",
    "sg:address":"30 Dorris Dr",
    "sg:city":"Elma",
    "sg:classifiers":[
        {
            "category":"Building & Trades",
            "subcategory":"Construction",
            "type":"Services"
        }
    ],
    "sg:phone":"+1 716 652 1191",
    "sg:postcode":"14059",
    "sg:province":"NY",
    "sg:tags":[
        "house"
    ],
    "wof:name":"Backwoods Construction",
    "wof:placetype":"venue"
},
  "geometry": {"coordinates":[-78.628981,42.829269],"type":"Point"}
}