{
  "type": "Feature",
  "properties": {
    "addr:full":"141 Front St Brooklyn NY 11201",
    "addr:housenumber":"141",
    "addr:postcode":"11201",
    "addr:street":"Front St",
    "iso:country":"US",
    "sg:address":"141 Front St",
    "sg:city":"Brooklyn",
    "sg:classifiers":[
        {
            "category":"Food & Beverages",
            "subcategory":"Candy",
            "type":"Retail Goods"
        }
    ],
    "sg:phone":"+1 718 422 1333",
    "sg:postcode":"11201",
    "sg:province":"NY",
    "sg:tags":[
        "store"
    ],
    "sg:website":"deweyscandy.com",
    "wof:name":"Dewey's Candy",
    "wof:placetype":"venue"
},
  "geometry": {"coordinates":[-73.987599,40.702469],"type":"Point"}
}