{
  "type": "Feature",
  "properties": {
    "addr:full":"175 Wickham Ave Middletown NY 10940",
    "addr:housenumber":"175",
    "addr:postcode":"10940",
    "addr:street":"Wickham Ave",
    "iso:country":"US",
    "sg:address":"175 Wickham Ave",
    "sg:city":"Middletown",
    "sg:classifiers":[
        {
            "category":"Building & Trades",
            "subcategory":"Construction",
            "type":"Services"
        }
    ],
    "sg:phone":"+1 845 343 3550",
    "sg:postcode":"10940",
    "sg:province":"NY",
    "sg:tags":[
        "home",
        "improvement"
    ],
    "wof:name":"Empire Improvement Co",
    "wof:placetype":"venue"
},
  "geometry": {"coordinates":[-74.409862,41.452077],"type":"Point"}
}