{
  "type": "Feature",
  "properties": {
    "addr:full":"112 W 34th Street  Suite 827 New York NY 10001",
    "addr:housenumber":"112;827",
    "addr:postcode":"10001",
    "addr:street":"W 34Th Street Suite",
    "iso:country":"US",
    "sg:address":"112 W 34th Street  Suite 827",
    "sg:city":"New York",
    "sg:classifiers":[
        {
            "category":"Professional",
            "subcategory":"Advertising",
            "type":"Services"
        }
    ],
    "sg:postcode":"10001",
    "sg:province":"NY",
    "sg:tags":[
        "brand-advertising-performance",
        "digital-media-metrics",
        "brand-optimization",
        "brand-analytics",
        "real-time-metrics"
    ],
    "sg:website":"http://www.brandlift.com",
    "wof:name":"Vizu Corporation",
    "wof:placetype":"venue"
},
  "geometry": {"coordinates":[-73.99056899999999,40.750876],"type":"Point"}
}