{
  "type": "Feature",
  "properties": {
    "addr:full":"3115 Long Beach Rd Ste 2 Oceanside NY 11572",
    "addr:housenumber":"3115",
    "addr:postcode":"11572",
    "addr:street":"Long Beach Rd Ste 2",
    "iso:country":"US",
    "sg:address":"3115 Long Beach Rd Ste 2",
    "sg:city":"Oceanside",
    "sg:classifiers":[
        {
            "category":"Real Estate",
            "subcategory":"Real Estate Services",
            "type":"Services"
        }
    ],
    "sg:phone":"+1 516 764 3006",
    "sg:postcode":"11572",
    "sg:province":"NY",
    "wof:name":"Deblat and Garrett Real Estate Corp",
    "wof:placetype":"venue"
},
  "geometry": {"coordinates":[-73.640112,40.636071],"type":"Point"}
}