{
  "type": "Feature",
  "properties": {
    "iso:country":"US",
    "sg:address":"7011 Fresh Pond Road",
    "sg:city":"Ridgewood",
    "sg:classifiers":[
        {
            "category":"Professional",
            "subcategory":"Lawyer & Legal Services",
            "type":"Services"
        }
    ],
    "sg:phone":"+1 718 366 0464",
    "sg:postcode":"11385",
    "sg:province":"NY",
    "sg:tags":[
        "personal",
        "injury"
    ],
    "wof:name":"Bushlow Bruce E Atty",
    "wof:placetype":"venue"
},
  "geometry": {"coordinates":[-73.894919,40.702232],"type":"Point"}
}