{
  "type": "Feature",
  "properties": {
    "iso:country":"US",
    "sg:address":"5 Prospect Ave W",
    "sg:city":"White Plains",
    "sg:classifiers":[
        {
            "category":"Organizations",
            "subcategory":"Non-profit Organization",
            "type":"Services"
        }
    ],
    "sg:phone":"+1 914 761 8264",
    "sg:postcode":"10607",
    "sg:province":"NY",
    "sg:tags":[
        "info",
        "addiction",
        "abuse",
        "treatment",
        "drug"
    ],
    "wof:name":"Open Door Drug Program",
    "wof:placetype":"venue"
},
  "geometry": {"coordinates":[-73.792559,41.039963],"type":"Point"}
}