{
  "type": "Feature",
  "properties": {
    "addr:full":"2853 Steinway St Astoria NY 11103",
    "addr:housenumber":"2853",
    "addr:postcode":"11103",
    "addr:street":"Steinway St",
    "iso:country":"US",
    "sg:address":"2853 Steinway St",
    "sg:city":"Astoria",
    "sg:classifiers":[
        {
            "category":"Shopping",
            "subcategory":"Jewelry",
            "type":"Retail Goods"
        }
    ],
    "sg:phone":"+1 718 267 0132",
    "sg:postcode":"11103",
    "sg:province":"NY",
    "wof:name":"Treasures",
    "wof:placetype":"venue"
},
  "geometry": {"coordinates":[-73.91389100000001,40.764975],"type":"Point"}
}