{
  "type": "Feature",
  "properties": {
    "addr:full":"1 Watkins Ter Amityville NY 11701",
    "addr:housenumber":"1",
    "addr:postcode":"11701",
    "addr:street":"Watkins Ter Amityville",
    "iso:country":"US",
    "sg:address":"1 Watkins Ter",
    "sg:city":"Amityville",
    "sg:classifiers":[
        {
            "category":"Professional",
            "subcategory":"Engineering",
            "type":"Services"
        }
    ],
    "sg:phone":"+1 516 921 4906",
    "sg:postcode":"11701",
    "sg:province":"NY",
    "sg:tags":[
        "aircraft",
        "maintenance"
    ],
    "wof:name":"Pat S Cesspool",
    "wof:placetype":"venue"
},
  "geometry": {"coordinates":[-73.400429,40.714779],"type":"Point"}
}