{
  "type": "Feature",
  "properties": {
    "iso:country":"US",
    "sg:address":"931 Conklin St Ste B",
    "sg:city":"Farmingdale",
    "sg:classifiers":[
        {
            "category":"Real Estate",
            "subcategory":"Real Estate Services",
            "type":"Services"
        },
        {
            "category":"Real Estate",
            "subcategory":"Real Estate Agent",
            "type":"Services"
        }
    ],
    "sg:phone":"+1 631 420 0070",
    "sg:postcode":"11735",
    "sg:province":"NY",
    "sg:tags":[
        "buyer",
        "broker"
    ],
    "wof:name":"Brent Assoc Inc",
    "wof:placetype":"venue"
},
  "geometry": {"coordinates":[-73.427393,40.737285],"type":"Point"}
}