{
  "type": "Feature",
  "properties": {
    "addr:full":"2084 E 26th St Brooklyn NY 11229",
    "addr:housenumber":"2084",
    "addr:postcode":"11229",
    "addr:street":"E 26Th St",
    "iso:country":"US",
    "sg:address":"2084 E 26th St",
    "sg:city":"Brooklyn",
    "sg:classifiers":[
        {
            "category":"Shopping",
            "subcategory":"Bicycles & Sporting Goods",
            "type":"Retail Goods"
        }
    ],
    "sg:phone":"+1   ",
    "sg:postcode":"11229",
    "sg:province":"NY",
    "wof:name":"Starting Block Inc",
    "wof:placetype":"venue"
},
  "geometry": {"coordinates":[-73.946021,40.601937],"type":"Point"}
}