{
  "type": "Feature",
  "properties": {
    "addr:full":"96 State St Manchester NY 14504",
    "addr:housenumber":"96",
    "addr:postcode":"14504",
    "addr:street":"State St",
    "iso:country":"US",
    "sg:address":"96 State St",
    "sg:city":"Manchester",
    "sg:classifiers":[
        {
            "category":"Building & Trades",
            "subcategory":"Construction",
            "type":"Services"
        }
    ],
    "sg:phone":"+1 585 289 6198",
    "sg:postcode":"14504",
    "sg:province":"NY",
    "sg:tags":[
        "general",
        "contractor"
    ],
    "wof:name":"David Schlossnagle Building",
    "wof:placetype":"venue"
},
  "geometry": {"coordinates":[-77.240317,42.967973],"type":"Point"}
}