{
  "type": "Feature",
  "properties": {
    "addr:full":"1155 6 Ave New York NY 10036",
    "addr:housenumber":"1155",
    "addr:postcode":"10036",
    "addr:street":"6 Ave",
    "iso:country":"US",
    "sg:address":"1155 6 Ave",
    "sg:city":"New York",
    "sg:classifiers":[
        {
            "category":"Utilities",
            "subcategory":"Mobile Phone",
            "type":"Services"
        }
    ],
    "sg:phone":"+1   ",
    "sg:postcode":"10036",
    "sg:province":"NY",
    "sg:tags":[
        "communication",
        "radiotelephone"
    ],
    "wof:name":"MCI",
    "wof:placetype":"venue"
},
  "geometry": {"coordinates":[-73.98362299999999,40.755516],"type":"Point"}
}