{
  "type": "Feature",
  "properties": {
    "addr:full":"121 Meserole Ave Brooklyn NY 11222",
    "addr:housenumber":"121",
    "addr:postcode":"11222",
    "addr:street":"Meserole Ave",
    "iso:country":"US",
    "sg:address":"121 Meserole Ave",
    "sg:city":"Brooklyn",
    "sg:classifiers":[
        {
            "category":"Travel",
            "subcategory":"Travel Agent",
            "type":"Entertainment"
        }
    ],
    "sg:phone":"+1   ",
    "sg:postcode":"11222",
    "sg:province":"NY",
    "sg:tags":[
        "agency"
    ],
    "sg:website":"www.jantary.com",
    "wof:name":"Jantar Travel Agency",
    "wof:placetype":"venue"
},
  "geometry": {"coordinates":[-73.952178,40.72731],"type":"Point"}
}