{
  "type": "Feature",
  "properties": {
    "addr:full":"2317 Richmond Avenue Staten Island NY 10314",
    "addr:housenumber":"2317",
    "addr:postcode":"10314",
    "addr:street":"Richmond Avenue",
    "iso:country":"US",
    "sg:address":"2317 Richmond Avenue",
    "sg:city":"Staten Island",
    "sg:classifiers":[
        {
            "category":"Restaurant",
            "type":"Food & Drink"
        }
    ],
    "sg:phone":"+1 718 370 0102",
    "sg:postcode":"10314",
    "sg:province":"NY",
    "sg:tags":[
        "pizza"
    ],
    "wof:name":"Mr Pizza's Pasta House",
    "wof:placetype":"venue"
},
  "geometry": {"coordinates":[-74.164878,40.591084],"type":"Point"}
}