{
  "type": "Feature",
  "properties": {
    "iso:country":"US",
    "sg:address":"9 Woodside Ave",
    "sg:city":"Northport",
    "sg:classifiers":[
        {
            "category":"Government",
            "subcategory":"Office",
            "type":"Public Place"
        }
    ],
    "sg:phone":"+1 631 261 7508",
    "sg:postcode":"11768",
    "sg:province":"NY",
    "sg:tags":[
        "department",
        "highway"
    ],
    "wof:name":"Highway Department",
    "wof:placetype":"venue"
},
  "geometry": {"coordinates":[-73.346358,40.902267],"type":"Point"}
}