{
  "type": "Feature",
  "properties": {
    "addr:full":"237 W 35 St New York NY 10001",
    "addr:housenumber":"237",
    "addr:postcode":"10001",
    "addr:street":"W 35 St",
    "iso:country":"US",
    "sg:address":"237 W 35 St",
    "sg:city":"New York",
    "sg:classifiers":[
        {
            "category":"Professional",
            "subcategory":"Management & Consulting",
            "type":"Services"
        }
    ],
    "sg:phone":"+1 212 736 5850",
    "sg:postcode":"10001",
    "sg:province":"NY",
    "sg:tags":[
        "consultant",
        "rate",
        "electric"
    ],
    "wof:name":"Electric Meter Co",
    "wof:placetype":"venue"
},
  "geometry": {"coordinates":[-73.99215,40.752481],"type":"Point"}
}