{
  "type": "Feature",
  "properties": {
    "addr:full":"115 Ledgewood Dr Smithtown NY 11787",
    "addr:housenumber":"115",
    "addr:postcode":"11787",
    "addr:street":"Ledgewood Dr",
    "iso:country":"US",
    "sg:address":"115 Ledgewood Dr",
    "sg:city":"Smithtown",
    "sg:classifiers":[
        {
            "category":"Building & Trades",
            "subcategory":"Landscaping Services",
            "type":"Services"
        }
    ],
    "sg:phone":"+1 631 864 3613",
    "sg:postcode":"11787",
    "sg:province":"NY",
    "sg:tags":[
        "tree"
    ],
    "wof:name":"Castor Lawn & Tree Care",
    "wof:placetype":"venue"
},
  "geometry": {"coordinates":[-73.24504899999999,40.83316],"type":"Point"}
}