{
  "type": "Feature",
  "properties": {
    "addr:full":"8008 Surrey Pl Jamaica NY 11432",
    "addr:housenumber":"8008",
    "addr:postcode":"11432",
    "addr:street":"Surrey Pl",
    "iso:country":"US",
    "sg:address":"8008 Surrey Pl",
    "sg:city":"Jamaica",
    "sg:classifiers":[
        {
            "category":"Restaurant",
            "type":"Food & Drink"
        }
    ],
    "sg:menulink":"http://www.allmenus.com/ny/queens/107357-sushi-zone-/menu/",
    "sg:phone":"+1 718 380 1818",
    "sg:postcode":"11432",
    "sg:province":"NY",
    "sg:tags":[
        "japanese",
        "asian"
    ],
    "wof:name":"Sushi Zone ",
    "wof:placetype":"venue"
},
  "geometry": {"coordinates":[-73.78925700000001,40.726366],"type":"Point"}
}