{
  "type": "Feature",
  "properties": {
    "iso:country":"US",
    "sg:address":"2 Church St",
    "sg:city":"Ossining",
    "sg:classifiers":[
        {
            "category":"Education",
            "subcategory":"School",
            "type":"Public Place"
        }
    ],
    "sg:phone":"+1 914 941 5446",
    "sg:postcode":"10562",
    "sg:province":"NY",
    "wof:name":"Ossining Satellite",
    "wof:placetype":"venue"
},
  "geometry": {"coordinates":[-73.862337,41.161242],"type":"Point"}
}