{
  "type": "Feature",
  "properties": {
    "iso:country":"US",
    "sg:address":"5 E 64 St",
    "sg:city":"New York",
    "sg:classifiers":[
        {
            "category":"Building & Trades",
            "subcategory":"Construction",
            "type":"Services"
        }
    ],
    "sg:phone":"+1 212 744 0865",
    "sg:postcode":"10065",
    "sg:province":"NY",
    "sg:tags":[
        "contractor"
    ],
    "wof:name":"J F Roesemann Builders Inc",
    "wof:placetype":"venue"
},
  "geometry": {"coordinates":[-73.969129,40.766715],"type":"Point"}
}