{
  "type": "Feature",
  "properties": {
    "addr:full":"489 Prospect Pl Brooklyn NY 11238",
    "addr:housenumber":"489",
    "addr:postcode":"11238",
    "addr:street":"Prospect Pl",
    "iso:country":"US",
    "sg:address":"489 Prospect Pl",
    "sg:city":"Brooklyn",
    "sg:classifiers":[
        {
            "category":"Utilities",
            "subcategory":"Telephone",
            "type":"Services"
        }
    ],
    "sg:phone":"+1   ",
    "sg:postcode":"11238",
    "sg:province":"NY",
    "sg:tags":[
        "mall",
        "shopping"
    ],
    "wof:name":"Mall2kcom",
    "wof:placetype":"venue"
},
  "geometry": {"coordinates":[-73.9618,40.676397],"type":"Point"}
}