{
  "type": "Feature",
  "properties": {
    "iso:country":"US",
    "sg:address":"93 Merchants Path",
    "sg:city":"Bridgehampton",
    "sg:classifiers":[
        {
            "category":"Professional",
            "type":"Services"
        }
    ],
    "sg:phone":"+1 631 537 7335",
    "sg:postcode":"11962",
    "sg:province":"NY",
    "sg:tags":[
        "establishment"
    ],
    "wof:name":"Amaryllis Equine Rescue",
    "wof:placetype":"venue"
},
  "geometry": {"coordinates":[-72.27302400000001,40.960345],"type":"Point"}
}