{
  "type": "Feature",
  "properties": {
    "addr:full":"1264 3rd Avenue New York NY 10021",
    "addr:housenumber":"1264",
    "addr:postcode":"10021",
    "addr:street":"3Rd Avenue",
    "iso:country":"US",
    "sg:address":"1264 3rd Avenue",
    "sg:city":"New York",
    "sg:classifiers":[
        {
            "category":"Shopping",
            "subcategory":"Optician",
            "type":"Retail Goods"
        }
    ],
    "sg:phone":"+1 212 535 1222",
    "sg:postcode":"10021",
    "sg:province":"NY",
    "sg:tags":[
        "eyewear"
    ],
    "sg:website":"www.leonardopticians.com",
    "wof:name":"Leonard Opticians",
    "wof:placetype":"venue"
},
  "geometry": {"coordinates":[-73.960178,40.770095],"type":"Point"}
}