{
  "type": "Feature",
  "properties": {
    "iso:country":"US",
    "sg:address":"118 N 11th St",
    "sg:city":"Brooklyn",
    "sg:classifiers":[
        {
            "category":"Museum",
            "subcategory":"Zoo",
            "type":"Entertainment"
        },
        {
            "category":"Museum",
            "subcategory":"Botanical Garden",
            "type":"Entertainment"
        }
    ],
    "sg:phone":"+1 718 302 2263",
    "sg:postcode":"11211",
    "sg:province":"NY",
    "wof:name":"Acme World Zoo",
    "wof:placetype":"venue"
},
  "geometry": {"coordinates":[-73.95673499999999,40.720723],"type":"Point"}
}