{
  "type": "Feature",
  "properties": {
    "iso:country":"US",
    "sg:address":"2115 Mott Ave",
    "sg:city":"Far Rockaway",
    "sg:classifiers":[
        {
            "category":"Deli",
            "type":"Food & Drink"
        },
        {
            "category":"Food & Beverages",
            "subcategory":"Bakery",
            "type":"Retail Goods"
        }
    ],
    "sg:phone":"+1 718 471 8986",
    "sg:postcode":"11691",
    "sg:province":"NY",
    "sg:tags":[
        "sandwich"
    ],
    "wof:name":"The Last Stop Deli",
    "wof:placetype":"venue"
},
  "geometry": {"coordinates":[-73.754065,40.604655],"type":"Point"}
}