{
  "type": "Feature",
  "properties": {
    "addr:full":"67 Irving Place Bsmt New York NY 10003",
    "addr:housenumber":"67",
    "addr:postcode":"10003",
    "addr:street":"Irving Place",
    "iso:country":"US",
    "sg:address":"67 Irving Place Bsmt",
    "sg:city":"New York",
    "sg:classifiers":[
        {
            "category":"Building & Trades",
            "subcategory":"Construction",
            "type":"Services"
        }
    ],
    "sg:phone":"+1 212 995 9290",
    "sg:postcode":"10003",
    "sg:province":"NY",
    "sg:tags":[
        "contractor"
    ],
    "wof:name":"Puble N V",
    "wof:placetype":"venue"
},
  "geometry": {"coordinates":[-73.98675900000001,40.736483],"type":"Point"}
}