{
  "type": "Feature",
  "properties": {
    "iso:country":"US",
    "sg:address":"7 Norman Dr",
    "sg:city":"Albany",
    "sg:classifiers":[
        {
            "category":"Retail",
            "subcategory":"Auto Rental",
            "type":"Services"
        }
    ],
    "sg:phone":"+1 518 456 3114",
    "sg:postcode":"12205",
    "sg:province":"NY",
    "sg:tags":[
        "renting",
        "leasing",
        "trailer"
    ],
    "wof:name":"GE Trailer Fleet Svc",
    "wof:placetype":"venue"
},
  "geometry": {"coordinates":[-73.852979,42.722461],"type":"Point"}
}