{
  "type": "Feature",
  "properties": {
    "addr:full":"45 Hall Ave Eastchester NY 10709",
    "addr:housenumber":"45",
    "addr:postcode":"10709",
    "addr:street":"Hall Ave",
    "iso:country":"US",
    "sg:address":"45 Hall Ave",
    "sg:city":"Eastchester",
    "sg:classifiers":[
        {
            "category":"Education",
            "subcategory":"School",
            "type":"Public Place"
        }
    ],
    "sg:phone":"+1 914 793 6130",
    "sg:postcode":"10709",
    "sg:province":"NY",
    "sg:website":"www.eastchester.k12.ny.us",
    "wof:name":"Waverly School",
    "wof:placetype":"venue"
},
  "geometry": {"coordinates":[-73.81667400000001,40.95257],"type":"Point"}
}