{
  "type": "Feature",
  "properties": {
    "iso:country":"US",
    "sg:address":"60 Pine St",
    "sg:city":"New York",
    "sg:classifiers":[
        {
            "category":"Organizations",
            "subcategory":"Community Association",
            "type":"Services"
        }
    ],
    "sg:phone":"+1 212 422 1982",
    "sg:postcode":"10005",
    "sg:province":"NY",
    "sg:tags":[
        "club",
        "lunch",
        "membership",
        "bar",
        "private"
    ],
    "sg:website":"www.thedowntownassociation.com",
    "wof:name":"Down Town Assn",
    "wof:placetype":"venue"
},
  "geometry": {"coordinates":[-74.007452,40.70605],"type":"Point"}
}