{
  "type": "Feature",
  "properties": {
    "iso:country":"US",
    "sg:address":"280 Vista Dr",
    "sg:city":"Jericho",
    "sg:classifiers":[
        {
            "category":"Professional",
            "subcategory":"Management & Consulting",
            "type":"Services"
        }
    ],
    "sg:phone":"+1 516 937 1712",
    "sg:postcode":"11753",
    "sg:province":"NY",
    "sg:tags":[
        "magazine",
        "agent"
    ],
    "wof:name":"Knickerbocker Magazine Agency",
    "wof:placetype":"venue"
},
  "geometry": {"coordinates":[-73.564802,40.78414],"type":"Point"}
}