{
  "type": "Feature",
  "properties": {
    "addr:full":"945 Little East Neck Rd N West Babylon NY 11704",
    "addr:housenumber":"945",
    "addr:postcode":"11704",
    "addr:street":"Little East Neck Rd N",
    "iso:country":"US",
    "sg:address":"945 Little East Neck Rd N",
    "sg:city":"West Babylon",
    "sg:classifiers":[
        {
            "category":"Autos & Motor Vehicles",
            "subcategory":"Fuel & Gas Station",
            "type":"Retail Goods"
        }
    ],
    "sg:phone":"+1   ",
    "sg:postcode":"11704",
    "sg:province":"NY",
    "sg:tags":[
        "station",
        "gasoline"
    ],
    "wof:name":"Good Corner Inc",
    "wof:placetype":"venue"
},
  "geometry": {"coordinates":[-73.355964,40.720477],"type":"Point"}
}