{
  "type": "Feature",
  "properties": {
    "addr:full":"720 W Court St Ithaca NY 14850",
    "addr:housenumber":"720",
    "addr:postcode":"14850",
    "addr:street":"W Court St",
    "iso:country":"US",
    "sg:address":"720 W Court St",
    "sg:city":"Ithaca",
    "sg:classifiers":[
        {
            "category":"Personal",
            "type":"Services"
        },
        {
            "category":"Retail",
            "subcategory":"Auto Repair",
            "type":"Services"
        }
    ],
    "sg:phone":"+1 607 277 7775",
    "sg:postcode":"14850",
    "sg:province":"NY",
    "sg:tags":[
        "body",
        "classic",
        "automobile",
        "dent",
        "towing",
        "removal",
        "painting",
        "repairing",
        "restoration-antique"
    ],
    "sg:website":"http://winksbodyshop.com",
    "wof:name":"Wink's Body Shop",
    "wof:placetype":"venue"
},
  "geometry": {"coordinates":[-76.509415,42.442303],"type":"Point"}
}