{
  "type": "Feature",
  "properties": {
    "addr:full":"1125 Oxford Pl Schenectady NY 12308",
    "addr:housenumber":"1125",
    "addr:postcode":"12308",
    "addr:street":"Oxford Pl",
    "iso:country":"US",
    "sg:address":"1125 Oxford Pl",
    "sg:city":"Schenectady",
    "sg:classifiers":[
        {
            "category":"Manufacturing",
            "subcategory":"Printing",
            "type":"Manufacturing & Wholesale Goods"
        }
    ],
    "sg:phone":"+1   ",
    "sg:postcode":"12308",
    "sg:province":"NY",
    "sg:tags":[
        "book"
    ],
    "wof:name":"L Davis Press",
    "wof:placetype":"venue"
},
  "geometry": {"coordinates":[-73.922093,42.814199],"type":"Point"}
}