{
  "type": "Feature",
  "properties": {
    "addr:full":"709 Lafayette Avenue Brooklyn NY 11221",
    "addr:housenumber":"709",
    "addr:postcode":"11221",
    "addr:street":"Lafayette Avenue",
    "iso:country":"US",
    "sg:address":"709 Lafayette Avenue",
    "sg:city":"Brooklyn",
    "sg:classifiers":[
        {
            "category":"Food & Beverages",
            "subcategory":"Groceries & Convenience Stores",
            "type":"Retail Goods"
        }
    ],
    "sg:phone":"+1 718 384 4743",
    "sg:postcode":"11221",
    "sg:province":"NY",
    "wof:name":"Food First Hdfc",
    "wof:placetype":"venue"
},
  "geometry": {"coordinates":[-73.92496,40.690662],"type":"Point"}
}