{
  "type": "Feature",
  "properties": {
    "iso:country":"US",
    "sg:address":"23 Applegate Dr",
    "sg:city":"Mastic",
    "sg:classifiers":[
        {
            "category":"Personal",
            "subcategory":"Nail Salon",
            "type":"Services"
        }
    ],
    "sg:phone":"+1 631 399 7787",
    "sg:postcode":"11950",
    "sg:province":"NY",
    "wof:name":"Paula's Perfect Nails & Co Inc",
    "wof:placetype":"venue"
},
  "geometry": {"coordinates":[-72.861088,40.824663],"type":"Point"}
}