{
  "type": "Feature",
  "properties": {
    "iso:country":"US",
    "sg:address":"73 Susquehanna Ave",
    "sg:city":"Great Neck",
    "sg:classifiers":[
        {
            "category":"Banks & Credit Unions",
            "subcategory":"Investment Brokerage",
            "type":"Services"
        }
    ],
    "sg:phone":"+1 516 829 4346",
    "sg:postcode":"11021",
    "sg:province":"NY",
    "sg:tags":[
        "advisory"
    ],
    "wof:name":"Money Talks",
    "wof:placetype":"venue"
},
  "geometry": {"coordinates":[-73.720208,40.784216],"type":"Point"}
}