{
  "type": "Feature",
  "properties": {
    "iso:country":"US",
    "sg:address":"3653 Main St",
    "sg:city":"Flushing",
    "sg:classifiers":[
        {
            "category":"Health Services",
            "subcategory":"Health Practitioner",
            "type":"Services"
        }
    ],
    "sg:phone":"+1 718 939 2021",
    "sg:postcode":"11354",
    "sg:province":"NY",
    "sg:tags":[
        "acupuncture"
    ],
    "wof:name":"Ag Chinese Medical Center",
    "wof:placetype":"venue"
},
  "geometry": {"coordinates":[-73.8312,40.761902],"type":"Point"}
}