{
  "type": "Feature",
  "properties": {
    "iso:country":"US",
    "sg:address":"379 White Oak Shade Rd",
    "sg:city":"New Canaan",
    "sg:classifiers":[
        {
            "category":"Professional",
            "type":"Services"
        }
    ],
    "sg:phone":"+1 203 972 7966",
    "sg:postcode":"06840",
    "sg:province":"NY",
    "wof:name":"George C Devol III",
    "wof:placetype":"venue"
},
  "geometry": {"coordinates":[-73.474064,41.124539],"type":"Point"}
}