{
  "type": "Feature",
  "properties": {
    "iso:country":"US",
    "sg:address":"186 Co Rte 23",
    "sg:city":"Constantia",
    "sg:classifiers":[
        {
            "category":"Farming",
            "subcategory":"Farm",
            "type":"Manufacturing & Wholesale Goods"
        }
    ],
    "sg:phone":"+1 315 623 7265",
    "sg:postcode":"13044",
    "sg:province":"NY",
    "sg:tags":[
        "crop",
        "general"
    ],
    "wof:name":"Deborah Koehler",
    "wof:placetype":"venue"
},
  "geometry": {"coordinates":[-76.00013300000001,43.258253],"type":"Point"}
}