{
  "type": "Feature",
  "properties": {
    "addr:full":"1240 2nd Ave New York NY 10021",
    "addr:housenumber":"1240",
    "addr:postcode":"10021",
    "addr:street":"2Nd Ave",
    "iso:country":"US",
    "sg:address":"1240 2nd Ave",
    "sg:city":"New York",
    "sg:classifiers":[
        {
            "category":"Retail",
            "subcategory":"Auto Repair",
            "type":"Services"
        }
    ],
    "sg:phone":"+1 646 237 1193",
    "sg:postcode":"10021",
    "sg:province":"NY",
    "wof:name":"Second Av Collision Repair",
    "wof:placetype":"venue"
},
  "geometry": {"coordinates":[-73.961601,40.764099],"type":"Point"}
}