{
  "type": "Feature",
  "properties": {
    "iso:country":"US",
    "sg:address":"1430 Thieriot Ave",
    "sg:city":"Bronx",
    "sg:classifiers":[
        {
            "category":"Organizations",
            "subcategory":"Religious Organization",
            "type":"Services"
        }
    ],
    "sg:phone":"+1 718 824 5357",
    "sg:postcode":"10460",
    "sg:province":"NY",
    "sg:tags":[
        "church"
    ],
    "wof:name":"Christian Church Body-Christ",
    "wof:placetype":"venue"
},
  "geometry": {"coordinates":[-73.865092,40.836066],"type":"Point"}
}