{
  "type": "Feature",
  "properties": {
    "addr:full":"548 US Hwy 11 Marathon NY 13803",
    "addr:housenumber":"548",
    "addr:postcode":"13803",
    "addr:street":"Us Hwy 11",
    "iso:country":"US",
    "sg:address":"548 US Hwy 11",
    "sg:city":"Marathon",
    "sg:classifiers":[
        {
            "category":"Shopping",
            "subcategory":"Gifts & Souvenirs",
            "type":"Retail Goods"
        }
    ],
    "sg:phone":"+1 607 849 3054",
    "sg:postcode":"13803",
    "sg:province":"NY",
    "sg:tags":[
        "novelty"
    ],
    "wof:name":"Little Shop",
    "wof:placetype":"venue"
},
  "geometry": {"coordinates":[-76.02407700000001,42.42967],"type":"Point"}
}