{
  "type": "Feature",
  "properties": {
    "addr:full":"303 E 8 St New York NY 10009",
    "addr:housenumber":"303;8",
    "addr:postcode":"10009",
    "addr:street":"E;St",
    "iso:country":"US",
    "sg:address":"303 E 8 St",
    "sg:city":"New York",
    "sg:classifiers":[
        {
            "category":"Building & Trades",
            "subcategory":"Construction",
            "type":"Services"
        }
    ],
    "sg:phone":"+1 212 529 6770",
    "sg:postcode":"10009",
    "sg:province":"NY",
    "sg:tags":[
        "nonresidential"
    ],
    "wof:name":"Nayso Inc",
    "wof:placetype":"venue"
},
  "geometry": {"coordinates":[-73.97873300000001,40.724956],"type":"Point"}
}