{
  "type": "Feature",
  "properties": {
    "addr:full":"5 Central Ave Schenectady NY 12304",
    "addr:housenumber":"5",
    "addr:postcode":"12304",
    "addr:street":"Central Ave",
    "iso:country":"US",
    "sg:address":"5 Central Ave",
    "sg:city":"Schenectady",
    "sg:classifiers":[
        {
            "category":"Shopping",
            "subcategory":"Pharmacy",
            "type":"Retail Goods"
        }
    ],
    "sg:phone":"+1   ",
    "sg:postcode":"12304",
    "sg:province":"NY",
    "sg:tags":[
        "drug",
        "store"
    ],
    "wof:name":"CVS",
    "wof:placetype":"venue"
},
  "geometry": {"coordinates":[-73.889152,42.770887],"type":"Point"}
}