{
  "type": "Feature",
  "properties": {
    "iso:country":"US",
    "sg:address":"71 California Ave",
    "sg:city":"Freeport",
    "sg:classifiers":[
        {
            "category":"Professional",
            "subcategory":"Management & Consulting",
            "type":"Services"
        },
        {
            "category":"Professional",
            "subcategory":"Computer Services",
            "type":"Services"
        }
    ],
    "sg:phone":"+1 917 662 7480",
    "sg:postcode":"11520",
    "sg:province":"NY",
    "sg:tags":[
        "rooms-installation",
        "facility",
        "consultant",
        "space",
        "equipment",
        "planning"
    ],
    "wof:name":"Ghtex",
    "wof:placetype":"venue"
},
  "geometry": {"coordinates":[-73.595927,40.666262],"type":"Point"}
}