{
  "type": "Feature",
  "properties": {
    "addr:full":"6558 Canton St Warners NY 13164",
    "addr:housenumber":"6558",
    "addr:postcode":"13164",
    "addr:street":"Canton St",
    "iso:country":"US",
    "sg:address":"6558 Canton St",
    "sg:city":"Warners",
    "sg:classifiers":[
        {
            "category":"Real Estate",
            "subcategory":"Real Estate Agent",
            "type":"Services"
        }
    ],
    "sg:phone":"+1 315 672 5359",
    "sg:postcode":"13164",
    "sg:province":"NY",
    "wof:name":"Doris Halko",
    "wof:placetype":"venue"
},
  "geometry": {"coordinates":[-76.329373,43.08805],"type":"Point"}
}