{
  "type": "Feature",
  "properties": {
    "addr:full":"70 Park Rd Riverhead NY 11901",
    "addr:housenumber":"70",
    "addr:postcode":"11901",
    "addr:street":"Park Rd",
    "iso:country":"US",
    "sg:address":"70 Park Rd",
    "sg:city":"Riverhead",
    "sg:classifiers":[
        {
            "category":"Manufacturing",
            "subcategory":"Signs",
            "type":"Manufacturing & Wholesale Goods"
        }
    ],
    "sg:phone":"+1 631 728 7052",
    "sg:postcode":"11901",
    "sg:province":"NY",
    "sg:tags":[
        "advertising",
        "specialty"
    ],
    "wof:name":"Vinyl Answer",
    "wof:placetype":"venue"
},
  "geometry": {"coordinates":[-72.70958400000001,40.968427],"type":"Point"}
}