{
  "type": "Feature",
  "properties": {
    "addr:full":"2264 4th Ave Lakewood NY 14750",
    "addr:housenumber":"2264",
    "addr:postcode":"14750",
    "addr:street":"4Th Ave",
    "iso:country":"US",
    "sg:address":"2264 4th Ave",
    "sg:city":"Lakewood",
    "sg:classifiers":[
        {
            "category":"Building & Trades",
            "subcategory":"Pest Control",
            "type":"Services"
        }
    ],
    "sg:phone":"+1 716 763 8310",
    "sg:postcode":"14750",
    "sg:province":"NY",
    "wof:name":"A 1 Pest Control Maintenance",
    "wof:placetype":"venue"
},
  "geometry": {"coordinates":[-79.35238699999999,42.098904],"type":"Point"}
}