{
  "type": "Feature",
  "properties": {
    "addr:full":"128 Saint Marys Ave Staten Island NY 10305",
    "addr:housenumber":"128",
    "addr:postcode":"10305",
    "addr:street":"Saint Marys Ave",
    "iso:country":"US",
    "sg:address":"128 Saint Marys Ave",
    "sg:city":"Staten Island",
    "sg:classifiers":[
        {
            "category":"Wholesale",
            "subcategory":"Vending Machines",
            "type":"Manufacturing & Wholesale Goods"
        }
    ],
    "sg:phone":"+1   ",
    "sg:postcode":"10305",
    "sg:province":"NY",
    "wof:name":"Euro Enterprises Inc",
    "wof:placetype":"venue"
},
  "geometry": {"coordinates":[-74.07167200000001,40.614471],"type":"Point"}
}