{
  "type": "Feature",
  "properties": {
    "addr:full":"244 Roebling St Apt 1 Brooklyn NY 11211",
    "addr:housenumber":"244;1",
    "addr:postcode":"11211",
    "addr:street":"Roebling St Apt",
    "iso:country":"US",
    "sg:address":"244 Roebling St Apt 1",
    "sg:city":"Brooklyn",
    "sg:classifiers":[
        {
            "category":"Shopping",
            "subcategory":"Pharmacy",
            "type":"Retail Goods"
        }
    ],
    "sg:phone":"+1 718 387 9772",
    "sg:postcode":"11211",
    "sg:province":"NY",
    "sg:tags":[
        "drugstore"
    ],
    "wof:name":"WILLIAMSBURG PHARMACY AND SURGICAL SUPPLY",
    "wof:placetype":"venue"
},
  "geometry": {"coordinates":[-73.959626,40.711308],"type":"Point"}
}