{
  "type": "Feature",
  "properties": {
    "addr:full":"1637 York Avenue New York NY 10028",
    "addr:housenumber":"1637",
    "addr:postcode":"10028",
    "addr:street":"York Avenue",
    "iso:country":"US",
    "sg:address":"1637 York Avenue",
    "sg:city":"New York",
    "sg:classifiers":[
        {
            "category":"Food & Beverages",
            "subcategory":"Groceries & Convenience Stores",
            "type":"Retail Goods"
        }
    ],
    "sg:phone":"+1 212 876 5648",
    "sg:postcode":"10028",
    "sg:province":"NY",
    "wof:name":"Sloan's Supermarket",
    "wof:placetype":"venue"
},
  "geometry": {"coordinates":[-73.946917,40.776422],"type":"Point"}
}