{
  "type": "Feature",
  "properties": {
    "addr:full":"2615 Carmel Ave Brewster NY 10509",
    "addr:housenumber":"2615",
    "addr:postcode":"10509",
    "addr:street":"Carmel Ave",
    "iso:country":"US",
    "sg:address":"2615 Carmel Ave",
    "sg:city":"Brewster",
    "sg:classifiers":[
        {
            "category":"Manufacturing",
            "subcategory":"Food",
            "type":"Manufacturing & Wholesale Goods"
        }
    ],
    "sg:phone":"+1 914 338 8931",
    "sg:postcode":"10509",
    "sg:province":"NY",
    "sg:tags":[
        "removal",
        "animal",
        "carcass"
    ],
    "wof:name":"Westchester Wildlife LLC",
    "wof:placetype":"venue"
},
  "geometry": {"coordinates":[-73.622276,41.39867],"type":"Point"}
}