{
  "type": "Feature",
  "properties": {
    "addr:full":"907 Pennsylvania Ave Elmira NY 14904",
    "addr:housenumber":"907",
    "addr:postcode":"14904",
    "addr:street":"Pennsylvania Ave",
    "iso:country":"US",
    "sg:address":"907 Pennsylvania Ave",
    "sg:city":"Elmira",
    "sg:classifiers":[
        {
            "category":"Health Services",
            "subcategory":"Doctor",
            "type":"Services"
        }
    ],
    "sg:phone":"+1 607 733 5199",
    "sg:postcode":"14904",
    "sg:province":"NY",
    "sg:tags":[
        "dentist"
    ],
    "wof:name":"Family Dental Care",
    "wof:placetype":"venue"
},
  "geometry": {"coordinates":[-76.80855699999999,42.063405],"type":"Point"}
}