{
  "type": "Feature",
  "properties": {
    "iso:country":"US",
    "sg:address":"1527 Brentwood Rd",
    "sg:city":"Bay Shore",
    "sg:classifiers":[
        {
            "category":"Restaurant",
            "type":"Food & Drink"
        }
    ],
    "sg:menulink":"http://www.allmenus.com/ny/islip/54812-hong-hing/menu/",
    "sg:phone":"+1 631 968 9441",
    "sg:postcode":"11706",
    "sg:province":"NY",
    "sg:tags":[
        "asian",
        "chinese"
    ],
    "wof:name":"Hong Hing",
    "wof:placetype":"venue"
},
  "geometry": {"coordinates":[-73.244866,40.756053],"type":"Point"}
}