{
  "type": "Feature",
  "properties": {
    "iso:country":"US",
    "sg:address":"48 W 48th Street",
    "sg:city":"New York",
    "sg:classifiers":[
        {
            "category":"Shopping",
            "subcategory":"Jewelry",
            "type":"Retail Goods"
        }
    ],
    "sg:phone":"+1 212 730 5413",
    "sg:postcode":"10036",
    "sg:province":"NY",
    "sg:website":"www.cj-creations.com",
    "wof:name":"Channel Jewelry Creation",
    "wof:placetype":"venue"
},
  "geometry": {"coordinates":[-73.980028,40.758102],"type":"Point"}
}