{
  "type": "Feature",
  "properties": {
    "addr:full":"11215 Jamaica Avenue Richmond Hill NY 11418",
    "addr:housenumber":"11215",
    "addr:postcode":"11418",
    "addr:street":"Jamaica Avenue",
    "iso:country":"US",
    "sg:address":"11215 Jamaica Avenue",
    "sg:city":"Richmond Hill",
    "sg:classifiers":[
        {
            "category":"Home & Garden",
            "subcategory":"Hardware",
            "type":"Retail Goods"
        },
        {
            "category":"Building & Trades",
            "subcategory":"Locksmith",
            "type":"Services"
        }
    ],
    "sg:phone":"+1 718 849 8121",
    "sg:postcode":"11418",
    "sg:province":"NY",
    "sg:tags":[
        "store",
        "key"
    ],
    "wof:name":"Brite Hardware",
    "wof:placetype":"venue"
},
  "geometry": {"coordinates":[-73.83601400000001,40.697764],"type":"Point"}
}