{
  "type": "Feature",
  "properties": {
    "iso:country":"US",
    "sg:address":"646 Medford Ave",
    "sg:city":"Patchogue",
    "sg:classifiers":[
        {
            "category":"Building & Trades",
            "subcategory":"Landscaping Services",
            "type":"Services"
        }
    ],
    "sg:phone":"+1 631 207 9780",
    "sg:postcode":"11772",
    "sg:province":"NY",
    "sg:tags":[
        "landscape",
        "contractor"
    ],
    "wof:name":"Four Leaf Landscaping",
    "wof:placetype":"venue"
},
  "geometry": {"coordinates":[-73.008448,40.790684],"type":"Point"}
}