{
  "type": "Feature",
  "properties": {
    "addr:full":"135 W 28th St New York NY 10001",
    "addr:housenumber":"135",
    "addr:postcode":"10001",
    "addr:street":"W 28Th St",
    "iso:country":"US",
    "sg:address":"135 W 28th St",
    "sg:city":"New York",
    "sg:classifiers":[
        {
            "category":"Sports & Exercise",
            "subcategory":"Bicycle Rental",
            "type":"Entertainment"
        }
    ],
    "sg:phone":"+1 212 494 0003",
    "sg:postcode":"10001",
    "sg:province":"NY",
    "sg:tags":[
        "wear"
    ],
    "wof:name":"MDH Sportwear Inc",
    "wof:placetype":"venue"
},
  "geometry": {"coordinates":[-73.991429,40.746584],"type":"Point"}
}