{
  "type": "Feature",
  "properties": {
    "addr:full":"638 Longfellow Ave Bronx NY 10474",
    "addr:housenumber":"638",
    "addr:postcode":"10474",
    "addr:street":"Longfellow Ave",
    "iso:country":"US",
    "sg:address":"638 Longfellow Ave",
    "sg:city":"Bronx",
    "sg:classifiers":[
        {
            "category":"School Buses",
            "type":"Transportation"
        }
    ],
    "sg:phone":"+1 718 860 5770",
    "sg:postcode":"10474",
    "sg:province":"NY",
    "wof:name":"Jodi Bus Co",
    "wof:placetype":"venue"
},
  "geometry": {"coordinates":[-73.88443100000001,40.814086],"type":"Point"}
}