{
  "type": "Feature",
  "properties": {
    "iso:country":"US",
    "sg:address":"257 Battle Ave",
    "sg:city":"White Plains",
    "sg:classifiers":[
        {
            "category":"Food & Beverages",
            "subcategory":"Groceries & Convenience Stores",
            "type":"Retail Goods"
        }
    ],
    "sg:phone":"+1   ",
    "sg:postcode":"10606",
    "sg:province":"NY",
    "wof:name":"Battle Hill Deli & Grocery",
    "wof:placetype":"venue"
},
  "geometry": {"coordinates":[-73.78688200000001,41.029668],"type":"Point"}
}