{
  "type": "Feature",
  "properties": {
    "addr:full":"1695 Merrick Rd North Merrick NY 11566",
    "addr:housenumber":"1695",
    "addr:postcode":"11566",
    "addr:street":"Merrick Rd",
    "iso:country":"US",
    "sg:address":"1695 Merrick Rd",
    "sg:city":"North Merrick",
    "sg:classifiers":[
        {
            "category":"Health Services",
            "subcategory":"Doctor",
            "type":"Services"
        }
    ],
    "sg:phone":"+1 516 867 2568",
    "sg:postcode":"11566",
    "sg:province":"NY",
    "sg:tags":[
        "physician",
        "surgeon"
    ],
    "wof:name":"Lewis Medical Office",
    "wof:placetype":"venue"
},
  "geometry": {"coordinates":[-73.559207,40.653943],"type":"Point"}
}