{
  "type": "Feature",
  "properties": {
    "addr:full":"7 Johnston St Newburgh NY 12550",
    "addr:housenumber":"7",
    "addr:postcode":"12550",
    "addr:street":"Johnston St",
    "iso:country":"US",
    "sg:address":"7 Johnston St",
    "sg:city":"Newburgh",
    "sg:classifiers":[
        {
            "category":"Real Estate",
            "subcategory":"Real Estate Agent",
            "type":"Services"
        }
    ],
    "sg:phone":"+1 845 561 3780",
    "sg:postcode":"12550",
    "sg:province":"NY",
    "sg:tags":[
        "management"
    ],
    "wof:name":"7 S Johnston St Inc",
    "wof:placetype":"venue"
},
  "geometry": {"coordinates":[-74.013412,41.502162],"type":"Point"}
}