{
  "type": "Feature",
  "properties": {
    "addr:full":"1 Stalker Ln East Setauket NY 11733",
    "addr:housenumber":"1",
    "addr:postcode":"11733",
    "addr:street":"Stalker Ln East",
    "iso:country":"US",
    "sg:address":"1 Stalker Ln",
    "sg:city":"East Setauket",
    "sg:classifiers":[
        {
            "category":"Building & Trades",
            "subcategory":"Construction",
            "type":"Services"
        }
    ],
    "sg:phone":"+1 631 331 2630",
    "sg:postcode":"11733",
    "sg:province":"NY",
    "sg:tags":[
        "contractor"
    ],
    "wof:name":"In Island Combined Contracting",
    "wof:placetype":"venue"
},
  "geometry": {"coordinates":[-73.07431099999999,40.909881],"type":"Point"}
}