{
  "type": "Feature",
  "properties": {
    "addr:full":"179 Vincent Ave Lynbrook NY 11563",
    "addr:housenumber":"179",
    "addr:postcode":"11563",
    "addr:street":"Vincent Ave",
    "iso:country":"US",
    "sg:address":"179 Vincent Ave",
    "sg:city":"Lynbrook",
    "sg:classifiers":[
        {
            "category":"Social Services",
            "subcategory":"Child Care",
            "type":"Services"
        }
    ],
    "sg:phone":"+1   ",
    "sg:postcode":"11563",
    "sg:province":"NY",
    "sg:tags":[
        "personal",
        "day"
    ],
    "wof:name":"Mimis Creative Kids",
    "wof:placetype":"venue"
},
  "geometry": {"coordinates":[-73.667339,40.656756],"type":"Point"}
}