{
  "type": "Feature",
  "properties": {
    "addr:full":"764 School Dr North Baldwin NY 11510",
    "addr:housenumber":"764",
    "addr:postcode":"11510",
    "addr:street":"School Dr North",
    "iso:country":"US",
    "sg:address":"764 School Dr",
    "sg:city":"North Baldwin",
    "sg:classifiers":[
        {
            "category":"Building & Trades",
            "subcategory":"Construction",
            "type":"Services"
        }
    ],
    "sg:phone":"+1 516 280 4459",
    "sg:postcode":"11510",
    "sg:province":"NY",
    "sg:tags":[
        "contractor"
    ],
    "wof:name":"S K B Construction",
    "wof:placetype":"venue"
},
  "geometry": {"coordinates":[-73.61242900000001,40.684223],"type":"Point"}
}