{
  "type": "Feature",
  "properties": {
    "addr:full":"71 Jenny Ln Lancaster NY 14086",
    "addr:housenumber":"71",
    "addr:postcode":"14086",
    "addr:street":"Jenny Ln",
    "iso:country":"US",
    "sg:address":"71 Jenny Ln",
    "sg:city":"Lancaster",
    "sg:classifiers":[
        {
            "category":"Retail",
            "subcategory":"Repair Shop",
            "type":"Services"
        },
        {
            "category":"Manufacturing",
            "subcategory":"Apparel",
            "type":"Manufacturing & Wholesale Goods"
        }
    ],
    "sg:phone":"+1 716 681 7535",
    "sg:postcode":"14086",
    "sg:province":"NY",
    "sg:tags":[
        "leather",
        "clothing",
        "mfg"
    ],
    "sg:website":"www.gypsyleather.com",
    "wof:name":"Gypsy Leather Inc",
    "wof:placetype":"venue"
},
  "geometry": {"coordinates":[-78.647031,42.90057],"type":"Point"}
}