{
  "type": "Feature",
  "properties": {
    "iso:country":"US",
    "sg:address":"30 McGregor Ave",
    "sg:city":"Maine",
    "sg:classifiers":[
        {
            "category":"Building & Trades",
            "subcategory":"Construction",
            "type":"Services"
        }
    ],
    "sg:phone":"+1 607 862 4577",
    "sg:postcode":"13802",
    "sg:province":"NY",
    "sg:tags":[
        "house"
    ],
    "wof:name":"Synergy Building Systems",
    "wof:placetype":"venue"
},
  "geometry": {"coordinates":[-76.061904,42.197354],"type":"Point"}
}