{
  "type": "Feature",
  "properties": {
    "addr:full":"350 West 51st St Manhattan NY 10019",
    "addr:housenumber":"350",
    "addr:postcode":"10019",
    "addr:street":"West 51St St",
    "iso:country":"US",
    "sg:address":"350 West 51st St",
    "sg:city":"Manhattan",
    "sg:classifiers":[
        {
            "category":"Shopping",
            "subcategory":"Pets & Pet Supplies",
            "type":"Retail Goods"
        }
    ],
    "sg:phone":"+1 347 490 0384",
    "sg:postcode":"10019",
    "sg:province":"NY",
    "sg:tags":[
        "walker",
        "dog"
    ],
    "sg:website":"www.hk--smalldogwalker.webs.com",
    "wof:name":"Little Imps Dog Walking Service",
    "wof:placetype":"venue"
},
  "geometry": {"coordinates":[-73.987616,40.763601],"type":"Point"}
}