{
  "type": "Feature",
  "properties": {
    "iso:country":"US",
    "sg:address":"77 Bennett St",
    "sg:city":"Staten Island",
    "sg:classifiers":[
        {
            "category":"Professional",
            "type":"Services"
        }
    ],
    "sg:phone":"+1 718 442 6336",
    "sg:postcode":"10302",
    "sg:province":"NY",
    "sg:tags":[
        "establishment"
    ],
    "wof:name":"William A Epps Community",
    "wof:placetype":"venue"
},
  "geometry": {"coordinates":[-74.13198800000001,40.637758],"type":"Point"}
}