{
  "type": "Feature",
  "properties": {
    "addr:full":"403 W 43rd St New York NY 10036",
    "addr:housenumber":"403",
    "addr:postcode":"10036",
    "addr:street":"W 43Rd St",
    "iso:country":"US",
    "sg:address":"403 W 43rd St",
    "sg:city":"New York",
    "sg:classifiers":[
        {
            "category":"Restaurant",
            "type":"Food & Drink"
        }
    ],
    "sg:phone":"+1   ",
    "sg:postcode":"10036",
    "sg:province":"NY",
    "sg:tags":[
        "country",
        "french"
    ],
    "wof:name":"Le Madeleine",
    "wof:placetype":"venue"
},
  "geometry": {"coordinates":[-73.994902,40.760341],"type":"Point"}
}