{
  "type": "Feature",
  "properties": {
    "iso:country":"US",
    "sg:address":"235 Baker Ave",
    "sg:city":"Syracuse",
    "sg:classifiers":[
        {
            "category":"Building & Trades",
            "subcategory":"Plumbing",
            "type":"Services"
        }
    ],
    "sg:phone":"+1 315 422 1250",
    "sg:postcode":"13205",
    "sg:province":"NY",
    "sg:tags":[
        "mechanical",
        "heating",
        "contractor"
    ],
    "wof:name":"Gomez Mechanical Contractors",
    "wof:placetype":"venue"
},
  "geometry": {"coordinates":[-76.143394,43.028826],"type":"Point"}
}