{
  "type": "Feature",
  "properties": {
    "iso:country":"US",
    "sg:address":"5407 Keeney Rd",
    "sg:city":"Warsaw",
    "sg:classifiers":[
        {
            "category":"Farming",
            "subcategory":"Livestock Farm",
            "type":"Manufacturing & Wholesale Goods"
        }
    ],
    "sg:phone":"+1 585 786 8798",
    "sg:postcode":"14569",
    "sg:province":"NY",
    "sg:tags":[
        "beef",
        "feedlot",
        "cattle"
    ],
    "wof:name":"Warren Goodenow",
    "wof:placetype":"venue"
},
  "geometry": {"coordinates":[-78.124849,42.715134],"type":"Point"}
}