{
  "type": "Feature",
  "properties": {
    "addr:full":"1230 Erie Blvd W Rome NY 13440",
    "addr:housenumber":"1230",
    "addr:postcode":"13440",
    "addr:street":"Erie Blvd W",
    "iso:country":"US",
    "sg:address":"1230 Erie Blvd W",
    "sg:city":"Rome",
    "sg:classifiers":[
        {
            "category":"Home & Garden",
            "subcategory":"Building Materials",
            "type":"Retail Goods"
        }
    ],
    "sg:phone":"+1 315 709 3000",
    "sg:postcode":"13440",
    "sg:province":"NY",
    "sg:tags":[
        "center"
    ],
    "wof:name":"Lowe's",
    "wof:placetype":"venue"
},
  "geometry": {"coordinates":[-75.485157,43.224325],"type":"Point"}
}