{
  "type": "Feature",
  "properties": {
    "addr:full":"409 Tarrytown Rd White Plains NY 10607",
    "addr:housenumber":"409",
    "addr:postcode":"10607",
    "addr:street":"Tarrytown Rd",
    "iso:country":"US",
    "sg:address":"409 Tarrytown Rd",
    "sg:city":"White Plains",
    "sg:classifiers":[
        {
            "category":"Food & Beverages",
            "subcategory":"Specialty",
            "type":"Retail Goods"
        }
    ],
    "sg:phone":"+1 914 948 0803",
    "sg:postcode":"10607",
    "sg:province":"NY",
    "sg:tags":[
        "health",
        "diet"
    ],
    "wof:name":"Vitamin Quota Inc",
    "wof:placetype":"venue"
},
  "geometry": {"coordinates":[-73.796378,41.04275],"type":"Point"}
}