{
  "type": "Feature",
  "properties": {
    "addr:full":"1 Van Voorhis Rd Pittsford NY 14534",
    "addr:housenumber":"1",
    "addr:postcode":"14534",
    "addr:street":"Van Voorhis Rd",
    "iso:country":"US",
    "sg:address":"1 Van Voorhis Rd",
    "sg:city":"Pittsford",
    "sg:classifiers":[
        {
            "category":"Professional",
            "subcategory":"Management & Consulting",
            "type":"Services"
        }
    ],
    "sg:phone":"+1 585 586 5790",
    "sg:postcode":"14534",
    "sg:province":"NY",
    "sg:tags":[
        "consultant"
    ],
    "wof:name":"Scientific Consulting",
    "wof:placetype":"venue"
},
  "geometry": {"coordinates":[-77.511892,43.044376],"type":"Point"}
}