{
  "type": "Feature",
  "properties": {
    "addr:full":"700 Hillside Ave New Hyde Park NY 11040",
    "addr:housenumber":"700",
    "addr:postcode":"11040",
    "addr:street":"Hillside Ave",
    "iso:country":"US",
    "sg:address":"700 Hillside Ave",
    "sg:city":"New Hyde Park",
    "sg:classifiers":[
        {
            "category":"Health Services",
            "subcategory":"Dentist",
            "type":"Services"
        }
    ],
    "sg:phone":"+1 516 775 7080",
    "sg:postcode":"11040",
    "sg:province":"NY",
    "wof:name":"Harvey W Glicker DDS PC",
    "wof:placetype":"venue"
},
  "geometry": {"coordinates":[-73.694199,40.742699],"type":"Point"}
}