{
  "type": "Feature",
  "properties": {
    "addr:full":"39 Nugent St Southampton NY 11968",
    "addr:housenumber":"39",
    "addr:postcode":"11968",
    "addr:street":"Nugent St",
    "iso:country":"US",
    "sg:address":"39 Nugent St",
    "sg:city":"Southampton",
    "sg:classifiers":[
        {
            "category":"Government",
            "subcategory":"Office",
            "type":"Public Place"
        }
    ],
    "sg:phone":"+1 631 283 0268",
    "sg:postcode":"11968",
    "sg:province":"NY",
    "sg:tags":[
        "federal",
        "affairs"
    ],
    "wof:name":"US Passport Acceptance",
    "wof:placetype":"venue"
},
  "geometry": {"coordinates":[-72.38963699999999,40.887063],"type":"Point"}
}