{
  "type": "Feature",
  "properties": {
    "addr:full":"91 Tillary St Brooklyn NY 11201",
    "addr:housenumber":"91",
    "addr:postcode":"11201",
    "addr:street":"Tillary St",
    "iso:country":"US",
    "sg:address":"91 Tillary St",
    "sg:city":"Brooklyn",
    "sg:classifiers":[
        {
            "category":"Food & Beverages",
            "subcategory":"Groceries & Convenience Stores",
            "type":"Retail Goods"
        }
    ],
    "sg:phone":"+1   ",
    "sg:postcode":"11201",
    "sg:province":"NY",
    "sg:tags":[
        "supermarket"
    ],
    "wof:name":"Associated",
    "wof:placetype":"venue"
},
  "geometry": {"coordinates":[-73.985084,40.696052],"type":"Point"}
}