{
  "type": "Feature",
  "properties": {
    "iso:country":"US",
    "sg:address":"21 Schiavone Rd",
    "sg:city":"New Windsor",
    "sg:classifiers":[
        {
            "category":"Building & Trades",
            "subcategory":"Construction",
            "type":"Services"
        }
    ],
    "sg:phone":"+1 845 496 6899",
    "sg:postcode":"12553",
    "sg:province":"NY",
    "sg:tags":[
        "hanging",
        "co",
        "contractor"
    ],
    "wof:name":"Fine Arts Painting",
    "wof:placetype":"venue"
},
  "geometry": {"coordinates":[-74.108673,41.452078],"type":"Point"}
}