{
  "type": "Feature",
  "properties": {
    "addr:full":"5925 Riverdale Ave Bronx NY 10471",
    "addr:housenumber":"5925",
    "addr:postcode":"10471",
    "addr:street":"Riverdale Ave",
    "iso:country":"US",
    "sg:address":"5925 Riverdale Ave",
    "sg:city":"Bronx",
    "sg:classifiers":[
        {
            "category":"Organizations",
            "subcategory":"Non-profit Organization",
            "type":"Services"
        }
    ],
    "sg:phone":"+1 718 601 6935",
    "sg:postcode":"10471",
    "sg:province":"NY",
    "wof:name":"Special Citizen Future",
    "wof:placetype":"venue"
},
  "geometry": {"coordinates":[-73.903786,40.90826],"type":"Point"}
}