{
  "type": "Feature",
  "properties": {
    "addr:full":"3885 Lake Ave Rochester NY 14612",
    "addr:housenumber":"3885",
    "addr:postcode":"14612",
    "addr:street":"Lake Ave",
    "iso:country":"US",
    "sg:address":"3885 Lake Ave",
    "sg:city":"Rochester",
    "sg:classifiers":[
        {
            "category":"Retail",
            "subcategory":"Auto Repair",
            "type":"Services"
        }
    ],
    "sg:phone":"+1 585 621 1225",
    "sg:postcode":"14612",
    "sg:province":"NY",
    "sg:tags":[
        "repairing",
        "automobile"
    ],
    "wof:name":"Frank's Auto Care",
    "wof:placetype":"venue"
},
  "geometry": {"coordinates":[-77.621059,43.240331],"type":"Point"}
}