{
  "type": "Feature",
  "properties": {
    "addr:full":"31 Wildwood Rd Hartsdale NY 10530",
    "addr:housenumber":"31",
    "addr:postcode":"10530",
    "addr:street":"Wildwood Rd",
    "iso:country":"US",
    "sg:address":"31 Wildwood Rd",
    "sg:city":"Hartsdale",
    "sg:classifiers":[
        {
            "category":"Professional",
            "subcategory":"Lawyer & Legal Services",
            "type":"Services"
        }
    ],
    "sg:phone":"+1 914 949 0431",
    "sg:postcode":"10530",
    "sg:province":"NY",
    "sg:tags":[
        "attorney"
    ],
    "wof:name":"Sharon S Hernstadt",
    "wof:placetype":"venue"
},
  "geometry": {"coordinates":[-73.800074,41.025965],"type":"Point"}
}