{
  "type": "Feature",
  "properties": {
    "addr:full":"1 Henry Close Warwick NY 10990",
    "addr:housenumber":"1",
    "addr:postcode":"10990",
    "addr:street":"Henry Close",
    "iso:country":"US",
    "sg:address":"1 Henry Close",
    "sg:city":"Warwick",
    "sg:classifiers":[
        {
            "category":"Building & Trades",
            "subcategory":"Construction",
            "type":"Services"
        }
    ],
    "sg:phone":"+1 845 988 1722",
    "sg:postcode":"10990",
    "sg:province":"NY",
    "sg:tags":[
        "wallcoverings-installation",
        "wallpaper",
        "painting",
        "contractor"
    ],
    "wof:name":"Dun Rite Powerwashing & Painting",
    "wof:placetype":"venue"
},
  "geometry": {"coordinates":[-74.35723900000001,41.241116],"type":"Point"}
}