{
  "type": "Feature",
  "properties": {
    "addr:full":"1604 Cortelyou Rd Brooklyn NY 11226",
    "addr:housenumber":"1604",
    "addr:postcode":"11226",
    "addr:street":"Cortelyou Rd",
    "iso:country":"US",
    "sg:address":"1604 Cortelyou Rd",
    "sg:city":"Brooklyn",
    "sg:classifiers":[
        {
            "category":"Shopping",
            "subcategory":"Stationery & Office Supplies",
            "type":"Retail Goods"
        }
    ],
    "sg:phone":"+1   ",
    "sg:postcode":"11226",
    "sg:province":"NY",
    "sg:tags":[
        "business"
    ],
    "wof:name":"M & S Stationery",
    "wof:placetype":"venue"
},
  "geometry": {"coordinates":[-73.962641,40.641935],"type":"Point"}
}