{
  "type": "Feature",
  "properties": {
    "iso:country":"US",
    "sg:address":"2425 Jerusalem Ave",
    "sg:city":"Bellmore",
    "sg:classifiers":[
        {
            "category":"Autos & Motor Vehicles",
            "subcategory":"Fuel & Gas Station",
            "type":"Retail Goods"
        }
    ],
    "sg:phone":"+1   ",
    "sg:postcode":"11710",
    "sg:province":"NY",
    "sg:tags":[
        "station",
        "gasoline"
    ],
    "wof:name":"Gas N Go Inc",
    "wof:placetype":"venue"
},
  "geometry": {"coordinates":[-73.544707,40.690999],"type":"Point"}
}