{
  "type": "Feature",
  "properties": {
    "addr:full":"441 E 180th St Bronx NY 10457",
    "addr:housenumber":"441",
    "addr:postcode":"10457",
    "addr:street":"E 180Th St",
    "iso:country":"US",
    "sg:address":"441 E 180th St",
    "sg:city":"Bronx",
    "sg:classifiers":[
        {
            "category":"Retail",
            "subcategory":"Repair Shop",
            "type":"Services"
        }
    ],
    "sg:phone":"+1 347 576 2804",
    "sg:postcode":"10457",
    "sg:province":"NY",
    "sg:tags":[
        "lock",
        "locksmith"
    ],
    "wof:name":"180 St Locksmith & Cheap Flat",
    "wof:placetype":"venue"
},
  "geometry": {"coordinates":[-73.895613,40.851572],"type":"Point"}
}