{
  "type": "Feature",
  "properties": {
    "addr:full":"1205 47th St Brooklyn NY 11219",
    "addr:housenumber":"1205",
    "addr:postcode":"11219",
    "addr:street":"47Th St",
    "iso:country":"US",
    "sg:address":"1205 47th St",
    "sg:city":"Brooklyn",
    "sg:classifiers":[
        {
            "category":"Real Estate",
            "subcategory":"Real Estate Services",
            "type":"Services"
        }
    ],
    "sg:phone":"+1 718 851 4773",
    "sg:postcode":"11219",
    "sg:province":"NY",
    "sg:tags":[
        "management",
        "property"
    ],
    "wof:name":"Pacific 1154 Llc",
    "wof:placetype":"venue"
},
  "geometry": {"coordinates":[-73.992699,40.637299],"type":"Point"}
}