{
  "type": "Feature",
  "properties": {
    "iso:country":"US",
    "sg:address":"21 Main St",
    "sg:city":"Addison",
    "sg:classifiers":[
        {
            "category":"Organizations",
            "subcategory":"Labor Organization",
            "type":"Services"
        }
    ],
    "sg:phone":"+1   ",
    "sg:postcode":"14801",
    "sg:province":"NY",
    "wof:name":"Carpenters Local Union 700",
    "wof:placetype":"venue"
},
  "geometry": {"coordinates":[-77.233857,42.106584],"type":"Point"}
}