{
  "type": "Feature",
  "properties": {
    "addr:full":"85 Center St Ellenville NY 12428",
    "addr:housenumber":"85",
    "addr:postcode":"12428",
    "addr:street":"Center St",
    "iso:country":"US",
    "sg:address":"85 Center St",
    "sg:city":"Ellenville",
    "sg:classifiers":[
        {
            "category":"Organizations",
            "subcategory":"Non-profit Organization",
            "type":"Services"
        }
    ],
    "sg:phone":"+1 845 647 6061",
    "sg:postcode":"12428",
    "sg:province":"NY",
    "sg:tags":[
        "social"
    ],
    "wof:name":"Ellenville Comm Action",
    "wof:placetype":"venue"
},
  "geometry": {"coordinates":[-74.394077,41.716063],"type":"Point"}
}