{
  "type": "Feature",
  "properties": {
    "addr:full":"339 Chestnut St Liberty NY 12754",
    "addr:housenumber":"339",
    "addr:postcode":"12754",
    "addr:street":"Chestnut St",
    "iso:country":"US",
    "sg:address":"339 Chestnut St",
    "sg:city":"Liberty",
    "sg:classifiers":[
        {
            "category":"Manufacturing",
            "subcategory":"Wood Products",
            "type":"Manufacturing & Wholesale Goods"
        }
    ],
    "sg:phone":"+1   ",
    "sg:postcode":"12754",
    "sg:province":"NY",
    "sg:tags":[
        "mfg"
    ],
    "wof:name":"B & F Cabinets",
    "wof:placetype":"venue"
},
  "geometry": {"coordinates":[-74.757927,41.800865],"type":"Point"}
}