{
  "type": "Feature",
  "properties": {
    "iso:country":"US",
    "sg:address":"18 Mayhew Ave",
    "sg:city":"Larchmont",
    "sg:classifiers":[
        {
            "category":"Shopping",
            "subcategory":"Used Merchandise",
            "type":"Retail Goods"
        }
    ],
    "sg:phone":"+1   ",
    "sg:postcode":"10538",
    "sg:province":"NY",
    "wof:name":"Antiques Brokerage House LTD",
    "wof:placetype":"venue"
},
  "geometry": {"coordinates":[-73.757655,40.92742],"type":"Point"}
}