{
  "type": "Feature",
  "properties": {
    "addr:full":"44 Glen Ln Kings Park NY 11754",
    "addr:housenumber":"44",
    "addr:postcode":"11754",
    "addr:street":"Glen Ln",
    "iso:country":"US",
    "sg:address":"44 Glen Ln",
    "sg:city":"Kings Park",
    "sg:classifiers":[
        {
            "category":"Shopping",
            "subcategory":"Computers & Home Electronics",
            "type":"Retail Goods"
        }
    ],
    "sg:phone":"+1   ",
    "sg:postcode":"11754",
    "sg:province":"NY",
    "wof:name":"Morning Star Satellite",
    "wof:placetype":"venue"
},
  "geometry": {"coordinates":[-73.275606,40.883336],"type":"Point"}
}