{
  "type": "Feature",
  "properties": {
    "addr:full":"114 Van Duzer St Staten Island NY 10301",
    "addr:housenumber":"114",
    "addr:postcode":"10301",
    "addr:street":"Van Duzer St",
    "iso:country":"US",
    "sg:address":"114 Van Duzer St",
    "sg:city":"Staten Island",
    "sg:classifiers":[
        {
            "category":"Retail",
            "subcategory":"Auto Repair",
            "type":"Services"
        }
    ],
    "sg:phone":"+1 718 420 0924",
    "sg:postcode":"10301",
    "sg:province":"NY",
    "sg:tags":[
        "repairing",
        "automobile"
    ],
    "wof:name":"Stadium Collision & Auto Ctr",
    "wof:placetype":"venue"
},
  "geometry": {"coordinates":[-74.076713,40.63537],"type":"Point"}
}