{
  "type": "Feature",
  "properties": {
    "addr:full":"2395 Washington Ave Bronx NY 10458",
    "addr:housenumber":"2395",
    "addr:postcode":"10458",
    "addr:street":"Washington Ave",
    "iso:country":"US",
    "sg:address":"2395 Washington Ave",
    "sg:city":"Bronx",
    "sg:classifiers":[
        {
            "category":"Wholesale",
            "subcategory":"Hardware",
            "type":"Manufacturing & Wholesale Goods"
        }
    ],
    "sg:phone":"+1 718 295 3500",
    "sg:postcode":"10458",
    "sg:province":"NY",
    "sg:tags":[
        "plumbing",
        "c"
    ],
    "sg:website":"www.wymbs.com",
    "wof:name":"Hev-E-Oil Burner Distributors",
    "wof:placetype":"venue"
},
  "geometry": {"coordinates":[-73.89111200000001,40.857851],"type":"Point"}
}