{
  "type": "Feature",
  "properties": {
    "iso:country":"US",
    "sg:address":"364 Warren St",
    "sg:city":"Hudson",
    "sg:classifiers":[
        {
            "category":"Communications",
            "subcategory":"Newspaper",
            "type":"Services"
        }
    ],
    "sg:phone":"+1 518 828 1616",
    "sg:postcode":"12534",
    "sg:province":"NY",
    "sg:tags":[
        "print",
        "medium"
    ],
    "sg:website":"www.registerstar.com",
    "wof:name":"Register-Star",
    "wof:placetype":"venue"
},
  "geometry": {"coordinates":[-73.789001,42.251202],"type":"Point"}
}