{
  "type": "Feature",
  "properties": {
    "addr:full":"200 E Campbell Rd Schenectady NY 12303",
    "addr:housenumber":"200",
    "addr:postcode":"12303",
    "addr:street":"E Campbell Rd",
    "iso:country":"US",
    "sg:address":"200 E Campbell Rd",
    "sg:city":"Schenectady",
    "sg:classifiers":[
        {
            "category":"Insurance",
            "subcategory":"Insurance Agent",
            "type":"Services"
        }
    ],
    "sg:phone":"+1 518 355 0045",
    "sg:postcode":"12303",
    "sg:province":"NY",
    "sg:tags":[
        "real",
        "life",
        "accident",
        "fire",
        "agency",
        "est",
        "health"
    ],
    "wof:name":"Genie Insurance Agency & RE",
    "wof:placetype":"venue"
},
  "geometry": {"coordinates":[-73.933358,42.775065],"type":"Point"}
}