{
  "type": "Feature",
  "properties": {
    "addr:full":"55 92nd St Brooklyn NY 11209",
    "addr:housenumber":"55",
    "addr:postcode":"11209",
    "addr:street":"92Nd St",
    "iso:country":"US",
    "sg:address":"55 92nd St",
    "sg:city":"Brooklyn",
    "sg:classifiers":[
        {
            "category":"Home & Garden",
            "subcategory":"Carpets & Floor Coverings",
            "type":"Retail Goods"
        }
    ],
    "sg:phone":"+1   ",
    "sg:postcode":"11209",
    "sg:province":"NY",
    "wof:name":"Mikes Floor Service",
    "wof:placetype":"venue"
},
  "geometry": {"coordinates":[-74.039052,40.620963],"type":"Point"}
}