{
  "type": "Feature",
  "properties": {
    "addr:full":"6632 3rd Ave Brooklyn NY 11220",
    "addr:housenumber":"6632",
    "addr:postcode":"11220",
    "addr:street":"3Rd Ave",
    "iso:country":"US",
    "sg:address":"6632 3rd Ave",
    "sg:city":"Brooklyn",
    "sg:classifiers":[
        {
            "category":"Retail",
            "subcategory":"Laundry & Dry Cleaning",
            "type":"Services"
        }
    ],
    "sg:phone":"+1 718 492 0999",
    "sg:postcode":"11220",
    "sg:province":"NY",
    "sg:tags":[
        "duct",
        "furniture",
        "rug",
        "air"
    ],
    "wof:name":"Sears Carpet Cleaning Service",
    "wof:placetype":"venue"
},
  "geometry": {"coordinates":[-74.025127,40.637867],"type":"Point"}
}