{
  "type": "Feature",
  "properties": {
    "iso:country":"US",
    "sg:address":"36 Cooper Sq",
    "sg:city":"New York",
    "sg:classifiers":[
        {
            "category":"Real Estate",
            "subcategory":"Architect",
            "type":"Services"
        }
    ],
    "sg:phone":"+1   ",
    "sg:postcode":"10003",
    "sg:province":"NY",
    "sg:tags":[
        "artist"
    ],
    "wof:name":"Diller & Scofidio",
    "wof:placetype":"venue"
},
  "geometry": {"coordinates":[-73.990996,40.729175],"type":"Point"}
}