{
  "type": "Feature",
  "properties": {
    "iso:country":"US",
    "sg:address":"324 E 23 St",
    "sg:city":"New York",
    "sg:classifiers":[
        {
            "category":"Health Services",
            "subcategory":"Clinic",
            "type":"Services"
        }
    ],
    "sg:phone":"+1 212 460 7800",
    "sg:postcode":"10010",
    "sg:province":"NY",
    "sg:tags":[
        "medical",
        "group"
    ],
    "wof:name":"New York Medical Group",
    "wof:placetype":"venue"
},
  "geometry": {"coordinates":[-73.97900300000001,40.737044],"type":"Point"}
}