{
  "type": "Feature",
  "properties": {
    "iso:country":"US",
    "sg:address":"225 W 57th St",
    "sg:city":"New York",
    "sg:classifiers":[
        {
            "category":"Food & Beverages",
            "subcategory":"Groceries & Convenience Stores",
            "type":"Retail Goods"
        }
    ],
    "sg:phone":"+1 212 581 7200",
    "sg:postcode":"10019",
    "sg:province":"NY",
    "wof:name":"Associated Supermarket",
    "wof:placetype":"venue"
},
  "geometry": {"coordinates":[-73.98159800000001,40.766201],"type":"Point"}
}