{
  "type": "Feature",
  "properties": {
    "iso:country":"US",
    "sg:address":"4791 Limehill Dr",
    "sg:city":"Syracuse",
    "sg:classifiers":[
        {
            "category":"Professional",
            "subcategory":"Accounting & Tax Preparation",
            "type":"Services"
        }
    ],
    "sg:phone":"+1 315 488 2521",
    "sg:postcode":"13215",
    "sg:province":"NY",
    "sg:tags":[
        "public",
        "accountants-certified"
    ],
    "wof:name":"David Moynihan Cpa",
    "wof:placetype":"venue"
},
  "geometry": {"coordinates":[-76.211578,43.004743],"type":"Point"}
}