{
  "type": "Feature",
  "properties": {
    "iso:country":"US",
    "sg:address":"284 Sunrise Hwy",
    "sg:city":"Rockville Centre",
    "sg:classifiers":[
        {
            "category":"Professional",
            "subcategory":"Printing & Photocopies",
            "type":"Services"
        }
    ],
    "sg:phone":"+1 516 536 3301",
    "sg:postcode":"11570",
    "sg:province":"NY",
    "sg:website":"www.printingdynamics.net",
    "wof:name":"Printing Dynamics",
    "wof:placetype":"venue"
},
  "geometry": {"coordinates":[-73.641701,40.657001],"type":"Point"}
}