{
  "type": "Feature",
  "properties": {
    "iso:country":"US",
    "sg:address":"920 Mohawk St",
    "sg:city":"Lewiston",
    "sg:classifiers":[
        {
            "category":"Real Estate",
            "subcategory":"Real Estate Operator",
            "type":"Services"
        }
    ],
    "sg:phone":"+1 716 754 8151",
    "sg:postcode":"14092",
    "sg:province":"NY",
    "sg:tags":[
        "apartment"
    ],
    "wof:name":"Historical Square Apartments",
    "wof:placetype":"venue"
},
  "geometry": {"coordinates":[-79.030475,43.176801],"type":"Point"}
}