{
  "type": "Feature",
  "properties": {
    "addr:full":"301 W 45th St Apt 6F New York NY 10036",
    "addr:housenumber":"301",
    "addr:postcode":"10036",
    "addr:street":"W 45Th St Apt 6F",
    "iso:country":"US",
    "sg:address":"301 W 45th St Apt 6F",
    "sg:city":"New York",
    "sg:classifiers":[
        {
            "category":"Arts & Performance",
            "subcategory":"Arts Center",
            "type":"Entertainment"
        }
    ],
    "sg:phone":"+1 212 664 0096",
    "sg:postcode":"10036",
    "sg:province":"NY",
    "sg:tags":[
        "performing"
    ],
    "wof:name":"Downtown Ballet Co Inc",
    "wof:placetype":"venue"
},
  "geometry": {"coordinates":[-73.99099699999999,40.7607],"type":"Point"}
}