{
  "type": "Feature",
  "properties": {
    "iso:country":"US",
    "sg:address":"103 Market St",
    "sg:city":"Poughkeepsie",
    "sg:classifiers":[
        {
            "category":"Education",
            "subcategory":"Library",
            "type":"Public Place"
        }
    ],
    "sg:phone":"+1 845 471 6060",
    "sg:postcode":"12601",
    "sg:province":"NY",
    "wof:name":"Mid-Hudson Library System",
    "wof:placetype":"venue"
},
  "geometry": {"coordinates":[-73.93087,41.700491],"type":"Point"}
}