{
  "type": "Feature",
  "properties": {
    "addr:full":"1301 Ave of the Americas New York NY 10019",
    "addr:housenumber":"1301",
    "addr:postcode":"10019",
    "addr:street":"Ave Of The Americas",
    "iso:country":"US",
    "sg:address":"1301 Ave of the Americas",
    "sg:city":"New York",
    "sg:classifiers":[
        {
            "category":"Banks & Credit Unions",
            "subcategory":"Investment Brokerage",
            "type":"Services"
        }
    ],
    "sg:phone":"+1 212 798 6100",
    "sg:postcode":"10019",
    "sg:province":"NY",
    "sg:tags":[
        "investing"
    ],
    "wof:name":"Fortress Investment Group",
    "wof:placetype":"venue"
},
  "geometry": {"coordinates":[-73.9795,40.7612],"type":"Point"}
}