{
  "type": "Feature",
  "properties": {
    "addr:full":"15 State School Rd Warwick NY 10990",
    "addr:housenumber":"15",
    "addr:postcode":"10990",
    "addr:street":"State School Rd",
    "iso:country":"US",
    "sg:address":"15 State School Rd",
    "sg:city":"Warwick",
    "sg:classifiers":[
        {
            "category":"Farming",
            "subcategory":"Farm",
            "type":"Manufacturing & Wholesale Goods"
        }
    ],
    "sg:phone":"+1 845 988 5414",
    "sg:postcode":"10990",
    "sg:province":"NY",
    "wof:name":"Bellvale Farms",
    "wof:placetype":"venue"
},
  "geometry": {"coordinates":[-74.300455,41.263766],"type":"Point"}
}