{
  "type": "Feature",
  "properties": {
    "iso:country":"US",
    "sg:address":"189 Franklin St",
    "sg:city":"New York",
    "sg:classifiers":[
        {
            "category":"Professional",
            "subcategory":"Business Services",
            "type":"Services"
        }
    ],
    "sg:phone":"+1 212 966 0635",
    "sg:postcode":"10013",
    "sg:province":"NY",
    "wof:name":"Good Films Inc",
    "wof:placetype":"venue"
},
  "geometry": {"coordinates":[-74.009497,40.719273],"type":"Point"}
}