{
  "type": "Feature",
  "properties": {
    "addr:full":"954 Spencer St Syracuse NY 13204",
    "addr:housenumber":"954",
    "addr:postcode":"13204",
    "addr:street":"Spencer St",
    "iso:country":"US",
    "sg:address":"954 Spencer St",
    "sg:city":"Syracuse",
    "sg:classifiers":[
        {
            "category":"Wholesale",
            "subcategory":"Vending Machines",
            "type":"Manufacturing & Wholesale Goods"
        }
    ],
    "sg:phone":"+1 315 472 9311",
    "sg:postcode":"13204",
    "sg:province":"NY",
    "wof:name":"Tom's Vending",
    "wof:placetype":"venue"
},
  "geometry": {"coordinates":[-76.17806299999999,43.058564],"type":"Point"}
}