{
  "type": "Feature",
  "properties": {
    "iso:country":"US",
    "sg:address":"14 Chestnut Dr",
    "sg:city":"Plainview",
    "sg:classifiers":[
        {
            "category":"Professional",
            "subcategory":"Accounting & Tax Preparation",
            "type":"Services"
        }
    ],
    "sg:phone":"+1   ",
    "sg:postcode":"11803",
    "sg:province":"NY",
    "wof:name":"Amoroso Anthony John",
    "wof:placetype":"venue"
},
  "geometry": {"coordinates":[-73.495076,40.786556],"type":"Point"}
}