{
  "type": "Feature",
  "properties": {
    "addr:full":"4845 Transit Rd Depew NY 14043",
    "addr:housenumber":"4845",
    "addr:postcode":"14043",
    "addr:street":"Transit Rd",
    "iso:country":"US",
    "sg:address":"4845 Transit Rd",
    "sg:city":"Depew",
    "sg:classifiers":[
        {
            "category":"Insurance",
            "subcategory":"Insurance Agent",
            "type":"Services"
        },
        {
            "category":"Insurance",
            "subcategory":"Hazard Insurance",
            "type":"Services"
        },
        {
            "category":"Banks & Credit Unions",
            "subcategory":"Financial Services",
            "type":"Services"
        },
        {
            "category":"Professional",
            "subcategory":"Credit Reporting & Collection",
            "type":"Services"
        }
    ],
    "sg:phone":"+1 716 634 8612",
    "sg:postcode":"14043",
    "sg:province":"NY",
    "sg:tags":[
        "debt",
        "adjuster",
        "agency"
    ],
    "wof:name":"Arbitrage Adjusting Services Wmsvl",
    "wof:placetype":"venue"
},
  "geometry": {"coordinates":[-78.696939,42.873888],"type":"Point"}
}