{
  "type": "Feature",
  "properties": {
    "iso:country":"US",
    "sg:address":"421 E 2nd St",
    "sg:city":"Jamestown",
    "sg:classifiers":[
        {
            "category":"Professional",
            "subcategory":"Engineering",
            "type":"Services"
        }
    ],
    "sg:phone":"+1 716 484 1366",
    "sg:postcode":"14701",
    "sg:province":"NY",
    "sg:tags":[
        "civil"
    ],
    "wof:name":"Tolman Engineering Pllc",
    "wof:placetype":"venue"
},
  "geometry": {"coordinates":[-79.23527,42.097065],"type":"Point"}
}