{
  "type": "Feature",
  "properties": {
    "iso:country":"US",
    "sg:address":"43 Farmstead Ln",
    "sg:city":"Water Mill",
    "sg:classifiers":[
        {
            "category":"Professional",
            "type":"Services"
        }
    ],
    "sg:phone":"+1 631 726 2588",
    "sg:postcode":"11976",
    "sg:province":"NY",
    "sg:tags":[
        "establishment"
    ],
    "wof:name":"Farmstead Inc",
    "wof:placetype":"venue"
},
  "geometry": {"coordinates":[-72.359427,40.941197],"type":"Point"}
}