{
  "type": "Feature",
  "properties": {
    "addr:full":"2043 Erie Blvd E Syracuse NY 13224",
    "addr:housenumber":"2043",
    "addr:postcode":"13224",
    "addr:street":"Erie Blvd E",
    "iso:country":"US",
    "sg:address":"2043 Erie Blvd E",
    "sg:city":"Syracuse",
    "sg:classifiers":[
        {
            "category":"Home & Garden",
            "subcategory":"Furniture",
            "type":"Retail Goods"
        }
    ],
    "sg:phone":"+1   ",
    "sg:postcode":"13224",
    "sg:province":"NY",
    "sg:tags":[
        "carpet",
        "cleaning",
        "supply"
    ],
    "wof:name":"International Furniture Outlet",
    "wof:placetype":"venue"
},
  "geometry": {"coordinates":[-76.11431,43.051584],"type":"Point"}
}