{
  "type": "Feature",
  "properties": {
    "iso:country":"US",
    "sg:address":"4783 Southwestern Blvd",
    "sg:city":"Hamburg",
    "sg:classifiers":[
        {
            "category":"Shopping",
            "subcategory":"Bicycles & Sporting Goods",
            "type":"Retail Goods"
        }
    ],
    "sg:phone":"+1 716 646 5606",
    "sg:postcode":"14075",
    "sg:province":"NY",
    "sg:tags":[
        "gun",
        "gunsmith"
    ],
    "wof:name":"Johnson's Country Store",
    "wof:placetype":"venue"
},
  "geometry": {"coordinates":[-78.849591,42.752413],"type":"Point"}
}