{
  "type": "Feature",
  "properties": {
    "iso:country":"US",
    "sg:address":"333 Massachusetts Ave",
    "sg:city":"Buffalo",
    "sg:classifiers":[
        {
            "category":"Organizations",
            "subcategory":"Religious Organization",
            "type":"Services"
        }
    ],
    "sg:phone":"+1 716 885 2289",
    "sg:postcode":"14213",
    "sg:province":"NY",
    "sg:tags":[
        "church"
    ],
    "wof:name":"Congregation Of Israel",
    "wof:placetype":"venue"
},
  "geometry": {"coordinates":[-78.88944499999999,42.9118],"type":"Point"}
}