{
  "type": "Feature",
  "properties": {
    "addr:full":"313 E 53rd St New York NY 10022",
    "addr:housenumber":"313",
    "addr:postcode":"10022",
    "addr:street":"E 53Rd St",
    "iso:country":"US",
    "sg:address":"313 E 53rd St",
    "sg:city":"New York",
    "sg:classifiers":[
        {
            "category":"Insurance",
            "subcategory":"Health Insurance",
            "type":"Services"
        }
    ],
    "sg:phone":"+1 800 464 7917",
    "sg:postcode":"10022",
    "sg:province":"NY",
    "sg:tags":[
        "market"
    ],
    "wof:name":"Vegetarian Pots Health Food",
    "wof:placetype":"venue"
},
  "geometry": {"coordinates":[-73.96677,40.756745],"type":"Point"}
}