{
  "type": "Feature",
  "properties": {
    "iso:country":"US",
    "sg:address":"19 Herbert St",
    "sg:city":"Geneva",
    "sg:classifiers":[
        {
            "category":"Home & Garden",
            "subcategory":"Garden Supply",
            "type":"Retail Goods"
        }
    ],
    "sg:phone":"+1 315 789 5194",
    "sg:postcode":"14456",
    "sg:province":"NY",
    "sg:tags":[
        "house",
        "bird",
        "feeder"
    ],
    "wof:name":"Marsh Creek Mfg",
    "wof:placetype":"venue"
},
  "geometry": {"coordinates":[-76.976288,42.875184],"type":"Point"}
}