{
  "type": "Feature",
  "properties": {
    "iso:country":"US",
    "sg:address":"5450 Ernest Rd",
    "sg:city":"Lockport",
    "sg:classifiers":[
        {
            "category":"Utilities",
            "subcategory":"Water",
            "type":"Services"
        }
    ],
    "sg:phone":"+1 716 434 8835",
    "sg:postcode":"14094",
    "sg:province":"NY",
    "sg:tags":[
        "company",
        "sewage"
    ],
    "wof:name":"Niagara County Water District",
    "wof:placetype":"venue"
},
  "geometry": {"coordinates":[-78.64868,43.156784],"type":"Point"}
}