{
  "type": "Feature",
  "properties": {
    "addr:full":"309 Avenue C New York NY 10009",
    "addr:housenumber":"309",
    "addr:postcode":"10009",
    "addr:street":"Avenue C",
    "iso:country":"US",
    "sg:address":"309 Avenue C",
    "sg:city":"New York",
    "sg:classifiers":[
        {
            "category":"Building & Trades",
            "subcategory":"Construction",
            "type":"Services"
        },
        {
            "category":"Building & Trades",
            "subcategory":"Locksmith",
            "type":"Services"
        }
    ],
    "sg:phone":"+1 212 799 9490",
    "sg:postcode":"10009",
    "sg:province":"NY",
    "sg:tags":[
        "key",
        "painter"
    ],
    "wof:name":"Prompt Locksmith",
    "wof:placetype":"venue"
},
  "geometry": {"coordinates":[-73.974197,40.731602],"type":"Point"}
}