{
  "type": "Feature",
  "properties": {
    "addr:full":"105 Button Shores Rd Baldwinsville NY 13027",
    "addr:housenumber":"105",
    "addr:postcode":"13027",
    "addr:street":"Button Shores Rd",
    "iso:country":"US",
    "sg:address":"105 Button Shores Rd",
    "sg:city":"Baldwinsville",
    "sg:classifiers":[
        {
            "category":"Building & Trades",
            "subcategory":"Landscaping Services",
            "type":"Services"
        }
    ],
    "sg:phone":"+1 315 635 2603",
    "sg:postcode":"13027",
    "sg:province":"NY",
    "sg:tags":[
        "landscape",
        "contractor"
    ],
    "wof:name":"Shute Landscaping & Nursery",
    "wof:placetype":"venue"
},
  "geometry": {"coordinates":[-76.39878299999999,43.160736],"type":"Point"}
}