{
  "type": "Feature",
  "properties": {
    "addr:full":"98 Roa Hook Rd Cortlandt Manor NY 10567",
    "addr:housenumber":"98",
    "addr:postcode":"10567",
    "addr:street":"Roa Hook Rd",
    "iso:country":"US",
    "sg:address":"98 Roa Hook Rd",
    "sg:city":"Cortlandt Manor",
    "sg:classifiers":[
        {
            "category":"Food & Beverages",
            "subcategory":"Bakery",
            "type":"Retail Goods"
        }
    ],
    "sg:phone":"+1 914 734 4171",
    "sg:postcode":"10567",
    "sg:province":"NY",
    "sg:tags":[
        "doughnut"
    ],
    "wof:name":"Annsville Circle Doughnuts LLC",
    "wof:placetype":"venue"
},
  "geometry": {"coordinates":[-73.948488,41.298061],"type":"Point"}
}