{
  "type": "Feature",
  "properties": {
    "addr:full":"190A East 98th Street Brooklyn NY 11212",
    "addr:housenumber":"190a",
    "addr:postcode":"11212",
    "addr:street":"East 98Th Street",
    "iso:country":"US",
    "sg:address":"190A East 98th Street",
    "sg:city":"Brooklyn",
    "sg:classifiers":[
        {
            "category":"Home & Garden",
            "subcategory":"Carpets & Floor Coverings",
            "type":"Retail Goods"
        }
    ],
    "sg:phone":"+1 347 274 0675",
    "sg:postcode":"11212",
    "sg:province":"NY",
    "sg:tags":[
        "mattress"
    ],
    "sg:website":"www.sleepys.com/",
    "wof:name":"Sleepy's, The Mattress Professionals",
    "wof:placetype":"venue"
},
  "geometry": {"coordinates":[-73.920536,40.662827],"type":"Point"}
}