{
  "type": "Feature",
  "properties": {
    "addr:full":"593 Meeker Ave Brooklyn NY 11222",
    "addr:housenumber":"593",
    "addr:postcode":"11222",
    "addr:street":"Meeker Ave",
    "iso:country":"US",
    "sg:address":"593 Meeker Ave",
    "sg:city":"Brooklyn",
    "sg:classifiers":[
        {
            "category":"Restaurant",
            "type":"Food & Drink"
        }
    ],
    "sg:phone":"+1 718 349 2777",
    "sg:postcode":"11222",
    "sg:province":"NY",
    "sg:tags":[
        "diner"
    ],
    "wof:name":"Sunset Restaurant Diner",
    "wof:placetype":"venue"
},
  "geometry": {"coordinates":[-73.94229900000001,40.7216],"type":"Point"}
}