{
  "type": "Feature",
  "properties": {
    "iso:country":"US",
    "sg:address":"777 Westchester Ave",
    "sg:city":"White Plains",
    "sg:classifiers":[
        {
            "category":"Food & Beverages",
            "subcategory":"Liquor & Beverages",
            "type":"Retail Goods"
        }
    ],
    "sg:phone":"+1 914 539 4500",
    "sg:postcode":"10604",
    "sg:province":"NY",
    "sg:tags":[
        "beer",
        "spirit",
        "wine"
    ],
    "wof:name":"Wild Turkey Distillery The",
    "wof:placetype":"venue"
},
  "geometry": {"coordinates":[-73.73129,41.399765],"type":"Point"}
}