{
  "type": "Feature",
  "properties": {
    "addr:full":"73 Battery Pl New York NY 10280",
    "addr:housenumber":"73",
    "addr:postcode":"10280",
    "addr:street":"Battery Pl",
    "iso:country":"US",
    "sg:address":"73 Battery Pl",
    "sg:city":"New York",
    "sg:classifiers":[
        {
            "category":"Building & Trades",
            "subcategory":"Locksmith",
            "type":"Services"
        }
    ],
    "sg:phone":"+1 917 423 3871",
    "sg:postcode":"10280",
    "sg:province":"NY",
    "sg:tags":[
        "key"
    ],
    "sg:website":"www.locksmith-manhattan.biz/",
    "wof:name":"Manhattan Locksmith",
    "wof:placetype":"venue"
},
  "geometry": {"coordinates":[-74.01734399999999,40.707147],"type":"Point"}
}