{
  "type": "Feature",
  "properties": {
    "iso:country":"US",
    "sg:address":"1488 Schenectady Ave",
    "sg:city":"Brooklyn",
    "sg:classifiers":[
        {
            "category":"Manufacturing",
            "subcategory":"Glass & Minerals",
            "type":"Manufacturing & Wholesale Goods"
        },
        {
            "category":"Retail",
            "subcategory":"Auto Repair",
            "type":"Services"
        }
    ],
    "sg:phone":"+1 347 374 4864",
    "sg:postcode":"11203",
    "sg:province":"NY",
    "sg:tags":[
        "plate",
        "shape",
        "glass-wholesale",
        "window",
        "special",
        "circle",
        "windshield",
        "glass-auto",
        "manufacturer"
    ],
    "wof:name":"A A Auto Glass",
    "wof:placetype":"venue"
},
  "geometry": {"coordinates":[-73.931673,40.636471],"type":"Point"}
}