{
  "type": "Feature",
  "properties": {
    "iso:country":"US",
    "sg:address":"7832 Duanesburg Rd",
    "sg:city":"Delanson",
    "sg:classifiers":[
        {
            "category":"Home & Garden",
            "subcategory":"Building Materials",
            "type":"Retail Goods"
        }
    ],
    "sg:phone":"+1   ",
    "sg:postcode":"12053",
    "sg:province":"NY",
    "wof:name":"Turnpike Glass",
    "wof:placetype":"venue"
},
  "geometry": {"coordinates":[-74.14627299999999,42.754501],"type":"Point"}
}