{
  "type": "Feature",
  "properties": {
    "iso:country":"US",
    "sg:address":"330 Alabama Ave",
    "sg:city":"Brooklyn",
    "sg:classifiers":[
        {
            "category":"Education",
            "subcategory":"School",
            "type":"Public Place"
        }
    ],
    "sg:phone":"+1 718 342 3268",
    "sg:postcode":"11207",
    "sg:province":"NY",
    "wof:name":"Council Jennes Jr",
    "wof:placetype":"venue"
},
  "geometry": {"coordinates":[-73.897993,40.668119],"type":"Point"}
}