{
  "type": "Feature",
  "properties": {
    "addr:full":"2157 Main St Buffalo NY 14214",
    "addr:housenumber":"2157",
    "addr:postcode":"14214",
    "addr:street":"Main St",
    "iso:country":"US",
    "sg:address":"2157 Main St",
    "sg:city":"Buffalo",
    "sg:classifiers":[
        {
            "category":"Health Services",
            "subcategory":"Medical Lab",
            "type":"Services"
        }
    ],
    "sg:phone":"+1 716 834 2691",
    "sg:postcode":"14214",
    "sg:province":"NY",
    "sg:tags":[
        "laboratory"
    ],
    "wof:name":"Quest Diagnotics",
    "wof:placetype":"venue"
},
  "geometry": {"coordinates":[-78.850905,42.928091],"type":"Point"}
}