{
  "type": "Feature",
  "properties": {
    "addr:full":"129 Roxbury Rd Garden City NY 11530",
    "addr:housenumber":"129",
    "addr:postcode":"11530",
    "addr:street":"Roxbury Rd",
    "iso:country":"US",
    "sg:address":"129 Roxbury Rd",
    "sg:city":"Garden City",
    "sg:classifiers":[
        {
            "category":"Professional",
            "subcategory":"Lawyer & Legal Services",
            "type":"Services"
        }
    ],
    "sg:phone":"+1 516 741 9880",
    "sg:postcode":"11530",
    "sg:province":"NY",
    "sg:tags":[
        "attorney"
    ],
    "wof:name":"James P O'Neill",
    "wof:placetype":"venue"
},
  "geometry": {"coordinates":[-73.663608,40.724914],"type":"Point"}
}