{
  "type": "Feature",
  "properties": {
    "iso:country":"US",
    "sg:address":"52 Pioneer St",
    "sg:city":"Cooperstown",
    "sg:classifiers":[
        {
            "category":"Wholesale",
            "subcategory":"Durable Goods & Equipment",
            "type":"Manufacturing & Wholesale Goods"
        }
    ],
    "sg:phone":"+1 607 547 8184",
    "sg:postcode":"13326",
    "sg:province":"NY",
    "sg:tags":[
        "importer"
    ],
    "wof:name":"Vanburg & Dewulf",
    "wof:placetype":"venue"
},
  "geometry": {"coordinates":[-74.92465199999999,42.699632],"type":"Point"}
}