{
  "type": "Feature",
  "properties": {
    "iso:country":"US",
    "sg:address":"3960 Monticello Ave",
    "sg:city":"Bronx",
    "sg:classifiers":[
        {
            "category":"Personal",
            "subcategory":"Beauty Salon",
            "type":"Services"
        }
    ],
    "sg:phone":"+1   ",
    "sg:postcode":"10466",
    "sg:province":"NY",
    "sg:tags":[
        "shop"
    ],
    "wof:name":"Vern Nail & Skin Care Spa",
    "wof:placetype":"venue"
},
  "geometry": {"coordinates":[-73.837738,40.889687],"type":"Point"}
}