{
  "type": "Feature",
  "properties": {
    "addr:full":"224 W 36 St New York NY 10018",
    "addr:housenumber":"224",
    "addr:postcode":"10018",
    "addr:street":"W 36 St",
    "iso:country":"US",
    "sg:address":"224 W 36 St",
    "sg:city":"New York",
    "sg:classifiers":[
        {
            "category":"Professional",
            "subcategory":"Employment Agencies",
            "type":"Services"
        }
    ],
    "sg:phone":"+1 212 838 5454",
    "sg:postcode":"10018",
    "sg:province":"NY",
    "sg:tags":[
        "modeling"
    ],
    "wof:name":"Model Club Inc",
    "wof:placetype":"venue"
},
  "geometry": {"coordinates":[-73.99203900000001,40.753116],"type":"Point"}
}