{
  "type": "Feature",
  "properties": {
    "addr:full":"179 Sheets Ave Holbrook NY 11741",
    "addr:housenumber":"179",
    "addr:postcode":"11741",
    "addr:street":"Sheets Ave",
    "iso:country":"US",
    "sg:address":"179 Sheets Ave",
    "sg:city":"Holbrook",
    "sg:classifiers":[
        {
            "category":"Home & Garden",
            "subcategory":"Home Furnishings",
            "type":"Retail Goods"
        }
    ],
    "sg:phone":"+1 631 471 0161",
    "sg:postcode":"11741",
    "sg:province":"NY",
    "sg:tags":[
        "blind",
        "window",
        "treatment",
        "shade"
    ],
    "wof:name":"Master Carrier Window Treatments",
    "wof:placetype":"venue"
},
  "geometry": {"coordinates":[-73.081299,40.802299],"type":"Point"}
}