{
  "type": "Feature",
  "properties": {
    "iso:country":"US",
    "sg:address":"69 Juniper St",
    "sg:city":"Lockport",
    "sg:classifiers":[
        {
            "category":"Professional",
            "subcategory":"Detective & Security Services",
            "type":"Services"
        }
    ],
    "sg:phone":"+1 716 439 4792",
    "sg:postcode":"14094",
    "sg:province":"NY",
    "sg:tags":[
        "information",
        "bureau"
    ],
    "wof:name":"Income Tax Services",
    "wof:placetype":"venue"
},
  "geometry": {"coordinates":[-78.676185,43.173528],"type":"Point"}
}