{
  "type": "Feature",
  "properties": {
    "addr:full":"26 Calvert Dr Monsey NY 10952",
    "addr:housenumber":"26",
    "addr:postcode":"10952",
    "addr:street":"Calvert Dr",
    "iso:country":"US",
    "sg:address":"26 Calvert Dr",
    "sg:city":"Monsey",
    "sg:classifiers":[
        {
            "category":"Professional",
            "subcategory":"Lawyer & Legal Services",
            "type":"Services"
        }
    ],
    "sg:phone":"+1 845 290 1106",
    "sg:postcode":"10952",
    "sg:province":"NY",
    "sg:tags":[
        "information",
        "attorney",
        "referral"
    ],
    "wof:name":"Frieman",
    "wof:placetype":"venue"
},
  "geometry": {"coordinates":[-74.07122,41.125921],"type":"Point"}
}