{
  "type": "Feature",
  "properties": {
    "addr:full":"1254 Southern Blvd Bronx NY 10459",
    "addr:housenumber":"1254",
    "addr:postcode":"10459",
    "addr:street":"Southern Blvd",
    "iso:country":"US",
    "sg:address":"1254 Southern Blvd",
    "sg:city":"Bronx",
    "sg:classifiers":[
        {
            "category":"Retail",
            "subcategory":"Self-service Laundry",
            "type":"Services"
        }
    ],
    "sg:phone":"+1 718 991 2550",
    "sg:postcode":"10459",
    "sg:province":"NY",
    "wof:name":"Super Brothers Laundromat Inc",
    "wof:placetype":"venue"
},
  "geometry": {"coordinates":[-73.89180899999999,40.829036],"type":"Point"}
}