{
  "type": "Feature",
  "properties": {
    "iso:country":"US",
    "sg:address":"41 Gaymore Rd",
    "sg:city":"Port Jefferson Sta",
    "sg:classifiers":[
        {
            "category":"Building & Trades",
            "subcategory":"Electrical",
            "type":"Services"
        }
    ],
    "sg:phone":"+1 631 331 4504",
    "sg:postcode":"11776",
    "sg:province":"NY",
    "sg:tags":[
        "electrician",
        "electric",
        "contractor"
    ],
    "wof:name":"Csf Electric Inc",
    "wof:placetype":"venue"
},
  "geometry": {"coordinates":[-73.055099,40.928398],"type":"Point"}
}