{
  "type": "Feature",
  "properties": {
    "iso:country":"US",
    "sg:address":"1732 South Ave",
    "sg:city":"Rochester",
    "sg:classifiers":[
        {
            "category":"Health Services",
            "subcategory":"Hospital",
            "type":"Services"
        }
    ],
    "sg:phone":"+1 585 461 0410",
    "sg:postcode":"14620",
    "sg:province":"NY",
    "sg:tags":[
        "psychiatric"
    ],
    "wof:name":"Norris John L Addiction",
    "wof:placetype":"venue"
},
  "geometry": {"coordinates":[-77.616131,43.120236],"type":"Point"}
}