{
  "type": "Feature",
  "properties": {
    "iso:country":"US",
    "sg:address":"62 June Rd",
    "sg:city":"North Salem",
    "sg:classifiers":[
        {
            "category":"Building & Trades",
            "subcategory":"Construction",
            "type":"Services"
        }
    ],
    "sg:phone":"+1 914 669 5838",
    "sg:postcode":"10560",
    "sg:province":"NY",
    "sg:tags":[
        "contractor"
    ],
    "wof:name":"David Contracting Inc",
    "wof:placetype":"venue"
},
  "geometry": {"coordinates":[-73.590537,41.32627],"type":"Point"}
}