{
  "type": "Feature",
  "properties": {
    "addr:full":"2075 Scottsville Rd Rochester NY 14623",
    "addr:housenumber":"2075",
    "addr:postcode":"14623",
    "addr:street":"Scottsville Rd",
    "iso:country":"US",
    "sg:address":"2075 Scottsville Rd",
    "sg:city":"Rochester",
    "sg:classifiers":[
        {
            "category":"Social Services",
            "subcategory":"Child Care",
            "type":"Services"
        }
    ],
    "sg:phone":"+1 585 429 2700",
    "sg:postcode":"14623",
    "sg:province":"NY",
    "sg:tags":[
        "nursery",
        "day"
    ],
    "wof:name":"Crestwood Children's Center Inc",
    "wof:placetype":"venue"
},
  "geometry": {"coordinates":[-77.70611100000001,43.076272],"type":"Point"}
}