{
  "type": "Feature",
  "properties": {
    "iso:country":"US",
    "sg:address":"501 W 145th St",
    "sg:city":"New York",
    "sg:classifiers":[
        {
            "category":"Restaurant",
            "type":"Food & Drink"
        }
    ],
    "sg:menulink":"http://www.allmenus.com/ny/new-york/47425-jesus-taco/menu/",
    "sg:phone":"+1 212 234 3330",
    "sg:postcode":"10031",
    "sg:province":"NY",
    "sg:tags":[
        "mexican",
        "tex-mex",
        "southwestern"
    ],
    "wof:name":"Jesus Taco",
    "wof:placetype":"venue"
},
  "geometry": {"coordinates":[-73.947632,40.82525],"type":"Point"}
}