{
  "type": "Feature",
  "properties": {
    "addr:full":"517 W 46th St New York NY 10036",
    "addr:housenumber":"517",
    "addr:postcode":"10036",
    "addr:street":"W 46Th St",
    "iso:country":"US",
    "sg:address":"517 W 46th St",
    "sg:city":"New York",
    "sg:classifiers":[
        {
            "category":"Professional",
            "subcategory":"Lawyer & Legal Services",
            "type":"Services"
        }
    ],
    "sg:phone":"+1 212 374 9590",
    "sg:postcode":"10036",
    "sg:province":"NY",
    "wof:name":"Law Office of Victor A Worms",
    "wof:placetype":"venue"
},
  "geometry": {"coordinates":[-73.994648,40.762869],"type":"Point"}
}