{
  "type": "Feature",
  "properties": {
    "addr:full":"258 Brighton Beach Ave Brooklyn NY 11235",
    "addr:housenumber":"258",
    "addr:postcode":"11235",
    "addr:street":"Brighton Beach Ave",
    "iso:country":"US",
    "sg:address":"258 Brighton Beach Ave",
    "sg:city":"Brooklyn",
    "sg:classifiers":[
        {
            "category":"Bakery",
            "type":"Food & Drink"
        }
    ],
    "sg:phone":"+1 718 934 1246",
    "sg:postcode":"11235",
    "sg:province":"NY",
    "wof:name":"Goldfield Bakery",
    "wof:placetype":"venue"
},
  "geometry": {"coordinates":[-73.965401,40.576698],"type":"Point"}
}