{
  "type": "Feature",
  "properties": {
    "iso:country":"US",
    "sg:address":"900 Jefferson Rd",
    "sg:city":"Rochester",
    "sg:classifiers":[
        {
            "category":"Food & Beverages",
            "subcategory":"Bakery",
            "type":"Retail Goods"
        }
    ],
    "sg:phone":"+1   ",
    "sg:postcode":"14623",
    "sg:province":"NY",
    "wof:name":"Pepperidge Farm Incorporated",
    "wof:placetype":"venue"
},
  "geometry": {"coordinates":[-77.615908,43.087248],"type":"Point"}
}