{
  "type": "Feature",
  "properties": {
    "iso:country":"US",
    "sg:address":"3 Davis St",
    "sg:city":"Whitehall",
    "sg:classifiers":[
        {
            "category":"Shopping",
            "subcategory":"Computers & Home Electronics",
            "type":"Retail Goods"
        }
    ],
    "sg:phone":"+1 518 499 0533",
    "sg:postcode":"12887",
    "sg:province":"NY",
    "sg:tags":[
        "equipment",
        "dealer"
    ],
    "wof:name":"Joe's PC Sales & Svc",
    "wof:placetype":"venue"
},
  "geometry": {"coordinates":[-73.394096,43.550087],"type":"Point"}
}