{
  "type": "Feature",
  "properties": {
    "addr:full":"1185 Ave of the Americas New York NY 10036",
    "addr:housenumber":"1185",
    "addr:postcode":"10036",
    "addr:street":"Ave Of The Americas",
    "iso:country":"US",
    "sg:address":"1185 Ave of the Americas",
    "sg:city":"New York",
    "sg:classifiers":[
        {
            "category":"Professional",
            "subcategory":"Accounting & Tax Preparation",
            "type":"Services"
        }
    ],
    "sg:phone":"+1 212 372 1261",
    "sg:postcode":"10036",
    "sg:province":"NY",
    "sg:tags":[
        "accountant",
        "bookkeeping",
        "general"
    ],
    "wof:name":"American Express Tax",
    "wof:placetype":"venue"
},
  "geometry": {"coordinates":[-73.981937,40.757916],"type":"Point"}
}