{
  "type": "Feature",
  "properties": {
    "iso:country":"US",
    "sg:address":"820 2nd Ave Ste 7A",
    "sg:city":"New York",
    "sg:classifiers":[
        {
            "category":"Health Services",
            "subcategory":"Doctor",
            "type":"Services"
        }
    ],
    "sg:phone":"+1 212 883 8868",
    "sg:postcode":"10017",
    "sg:province":"NY",
    "sg:tags":[
        "orthopedist"
    ],
    "sg:website":"www.StieberMD.com",
    "wof:name":"Jonathan R. Stieber, M.D. ? Spine and Scoliosis Surgery",
    "wof:placetype":"venue"
},
  "geometry": {"coordinates":[-73.971001,40.75071],"type":"Point"}
}