{
  "type": "Feature",
  "properties": {
    "addr:full":"1 Beaver Blvd Niagara Falls NY 14305",
    "addr:housenumber":"1",
    "addr:postcode":"14305",
    "addr:street":"Beaver Blvd",
    "iso:country":"US",
    "sg:address":"1 Beaver Blvd",
    "sg:city":"Niagara Falls",
    "sg:classifiers":[
        {
            "category":"Manufacturing",
            "subcategory":"Lumber",
            "type":"Manufacturing & Wholesale Goods"
        }
    ],
    "sg:phone":"+1   ",
    "sg:postcode":"14305",
    "sg:province":"NY",
    "sg:tags":[
        "hardwood",
        "mfr",
        "floor"
    ],
    "wof:name":"Beaver Hardwood Flrg Systems",
    "wof:placetype":"venue"
},
  "geometry": {"coordinates":[-79.01657899999999,43.127461],"type":"Point"}
}