{
  "type": "Feature",
  "properties": {
    "addr:full":"16 Elizabeth St Auburn NY 13021",
    "addr:housenumber":"16",
    "addr:postcode":"13021",
    "addr:street":"Elizabeth St",
    "iso:country":"US",
    "sg:address":"16 Elizabeth St",
    "sg:city":"Auburn",
    "sg:classifiers":[
        {
            "category":"Health Services",
            "subcategory":"Doctor",
            "type":"Services"
        }
    ],
    "sg:phone":"+1 315 253 4620",
    "sg:postcode":"13021",
    "sg:province":"NY",
    "sg:tags":[
        "physician",
        "surgeon"
    ],
    "wof:name":"Donahue Thomas J Dr Dntst",
    "wof:placetype":"venue"
},
  "geometry": {"coordinates":[-76.56448,42.925752],"type":"Point"}
}