{
  "type": "Feature",
  "properties": {
    "addr:full":"920 Grapevine Ct Central Valley NY 10917",
    "addr:housenumber":"920",
    "addr:postcode":"10917",
    "addr:street":"Grapevine Ct",
    "iso:country":"US",
    "sg:address":"920 Grapevine Ct",
    "sg:city":"Central Valley",
    "sg:classifiers":[
        {
            "category":"Shopping",
            "subcategory":"Discount & Variety Stores",
            "type":"Retail Goods"
        }
    ],
    "sg:phone":"+1 845 928 4393",
    "sg:postcode":"10917",
    "sg:province":"NY",
    "sg:tags":[
        "outlet"
    ],
    "wof:name":"Godiva Chocolates Woodbury Common Premium Outlet",
    "wof:placetype":"venue"
},
  "geometry": {"coordinates":[-74.127899,41.317299],"type":"Point"}
}