{
  "type": "Feature",
  "properties": {
    "iso:country":"US",
    "sg:address":"802 Columbia St",
    "sg:city":"Hudson",
    "sg:classifiers":[
        {
            "category":"Organizations",
            "subcategory":"Non-profit Organization",
            "type":"Services"
        }
    ],
    "sg:phone":"+1 518 828 2851",
    "sg:postcode":"12534",
    "sg:province":"NY",
    "sg:tags":[
        "agency",
        "human"
    ],
    "wof:name":"Columbia Opportunities Inc",
    "wof:placetype":"venue"
},
  "geometry": {"coordinates":[-73.780542,42.247422],"type":"Point"}
}