{
  "type": "Feature",
  "properties": {
    "iso:country":"US",
    "sg:address":"102 Bus Park Dr",
    "sg:city":"Utica",
    "sg:classifiers":[
        {
            "category":"Banks & Credit Unions",
            "subcategory":"Investment Brokerage",
            "type":"Services"
        }
    ],
    "sg:phone":"+1 315 738 9100",
    "sg:postcode":"13502",
    "sg:province":"NY",
    "sg:tags":[
        "security",
        "management",
        "consulting"
    ],
    "sg:website":"www.ml.com",
    "wof:name":"Merrill Lynch",
    "wof:placetype":"venue"
},
  "geometry": {"coordinates":[-75.28563200000001,43.093424],"type":"Point"}
}