{
  "type": "Feature",
  "properties": {
    "iso:country":"US",
    "sg:address":"400 Jericho Tpke Ste 318",
    "sg:city":"Jericho",
    "sg:classifiers":[
        {
            "category":"Professional",
            "subcategory":"Lawyer & Legal Services",
            "type":"Services"
        }
    ],
    "sg:phone":"+1 516 470 1379",
    "sg:postcode":"11753",
    "sg:province":"NY",
    "wof:name":"Dicresci Trivedi",
    "wof:placetype":"venue"
},
  "geometry": {"coordinates":[-73.535312,40.795009],"type":"Point"}
}