{
  "type": "Feature",
  "properties": {
    "iso:country":"US",
    "sg:address":"405 W Glenville Rd",
    "sg:city":"Schenectady",
    "sg:classifiers":[
        {
            "category":"Professional",
            "subcategory":"Business Services",
            "type":"Services"
        }
    ],
    "sg:phone":"+1 518 377 9900",
    "sg:postcode":"12302",
    "sg:province":"NY",
    "sg:website":"www.electronicsrecycler.com",
    "wof:name":"ECO-Tech Electronics",
    "wof:placetype":"venue"
},
  "geometry": {"coordinates":[-74.018398,42.926487],"type":"Point"}
}