{
  "type": "Feature",
  "properties": {
    "addr:full":"35 Mason St Geneva NY 14456",
    "addr:housenumber":"35",
    "addr:postcode":"14456",
    "addr:street":"Mason St",
    "iso:country":"US",
    "sg:address":"35 Mason St",
    "sg:city":"Geneva",
    "sg:classifiers":[
        {
            "category":"Health Services",
            "subcategory":"Doctor",
            "type":"Services"
        }
    ],
    "sg:phone":"+1 315 789 8486",
    "sg:postcode":"14456",
    "sg:province":"NY",
    "sg:tags":[
        "medical"
    ],
    "wof:name":"Richard J Amsel Dr",
    "wof:placetype":"venue"
},
  "geometry": {"coordinates":[-76.987056,42.876019],"type":"Point"}
}