{
  "type": "Feature",
  "properties": {
    "addr:full":"470 Chenango St Binghamton NY 13901",
    "addr:housenumber":"470",
    "addr:postcode":"13901",
    "addr:street":"Chenango St",
    "iso:country":"US",
    "sg:address":"470 Chenango St",
    "sg:city":"Binghamton",
    "sg:classifiers":[
        {
            "category":"Personal",
            "subcategory":"Beauty Salon",
            "type":"Services"
        }
    ],
    "sg:phone":"+1 607 722 4706",
    "sg:postcode":"13901",
    "sg:province":"NY",
    "wof:name":"470 Hair Design",
    "wof:placetype":"venue"
},
  "geometry": {"coordinates":[-75.90232899999999,42.1142],"type":"Point"}
}