{
  "type": "Feature",
  "properties": {
    "iso:country":"US",
    "sg:address":"17 Main St",
    "sg:city":"Highland Falls",
    "sg:classifiers":[
        {
            "category":"Travel",
            "subcategory":"Hotels & Motels",
            "type":"Entertainment"
        }
    ],
    "sg:phone":"+1 845 446 9400",
    "sg:postcode":"10928",
    "sg:province":"NY",
    "wof:name":"Palisade Motel",
    "wof:placetype":"venue"
},
  "geometry": {"coordinates":[-73.972217,41.355741],"type":"Point"}
}