{
  "type": "Feature",
  "properties": {
    "iso:country":"US",
    "sg:address":"775 Nostrand Ave",
    "sg:city":"Brooklyn",
    "sg:classifiers":[
        {
            "category":"Shopping",
            "subcategory":"Beauty & Cosmetics",
            "type":"Retail Goods"
        }
    ],
    "sg:phone":"+1 718 735 7369",
    "sg:postcode":"11216",
    "sg:province":"NY",
    "sg:tags":[
        "supply"
    ],
    "wof:name":"Crown Heights Beauty Supply",
    "wof:placetype":"venue"
},
  "geometry": {"coordinates":[-73.95030199999999,40.670799],"type":"Point"}
}