{
  "type": "Feature",
  "properties": {
    "addr:full":"2 Windward Ave White Plains NY 10605",
    "addr:housenumber":"2",
    "addr:postcode":"10605",
    "addr:street":"Windward Ave",
    "iso:country":"US",
    "sg:address":"2 Windward Ave",
    "sg:city":"White Plains",
    "sg:classifiers":[
        {
            "category":"Organizations",
            "subcategory":"Religious Organization",
            "type":"Services"
        }
    ],
    "sg:phone":"+1 914 644 8733",
    "sg:postcode":"10605",
    "sg:province":"NY",
    "sg:tags":[
        "clergy"
    ],
    "wof:name":"David Holtz",
    "wof:placetype":"venue"
},
  "geometry": {"coordinates":[-73.738332,40.991068],"type":"Point"}
}