{
  "type": "Feature",
  "properties": {
    "addr:full":"500 N George St Rome NY 13440",
    "addr:housenumber":"500",
    "addr:postcode":"13440",
    "addr:street":"N George St",
    "iso:country":"US",
    "sg:address":"500 N George St",
    "sg:city":"Rome",
    "sg:classifiers":[
        {
            "category":"Health Services",
            "subcategory":"Doctor",
            "type":"Services"
        }
    ],
    "sg:phone":"+1 315 336 3270",
    "sg:postcode":"13440",
    "sg:province":"NY",
    "wof:name":"Gordon J Ruff DDS",
    "wof:placetype":"venue"
},
  "geometry": {"coordinates":[-75.45634200000001,43.2188],"type":"Point"}
}