{
  "type": "Feature",
  "properties": {
    "iso:country":"US",
    "sg:address":"4709 30th St Ste 504",
    "sg:city":"Long Island City",
    "sg:classifiers":[
        {
            "category":"Shopping",
            "subcategory":"Jewelry",
            "type":"Retail Goods"
        }
    ],
    "sg:phone":"+1 718 349 9900",
    "sg:postcode":"11101",
    "sg:province":"NY",
    "wof:name":"Altex Industries Inc",
    "wof:placetype":"venue"
},
  "geometry": {"coordinates":[-73.93749099999999,40.743122],"type":"Point"}
}