{
  "type": "Feature",
  "properties": {
    "iso:country":"US",
    "sg:address":"3047 W Henrietta Rd",
    "sg:city":"Rochester",
    "sg:classifiers":[
        {
            "category":"Manufacturing",
            "subcategory":"Metals",
            "type":"Manufacturing & Wholesale Goods"
        },
        {
            "category":"Shopping",
            "subcategory":"Gifts & Souvenirs",
            "type":"Retail Goods"
        }
    ],
    "sg:phone":"+1 585 427 0330",
    "sg:postcode":"14623",
    "sg:province":"NY",
    "sg:tags":[
        "collectible",
        "medieval",
        "accessory"
    ],
    "wof:name":"Steel Source",
    "wof:placetype":"venue"
},
  "geometry": {"coordinates":[-77.634569,43.091519],"type":"Point"}
}