{
  "type": "Feature",
  "properties": {
    "addr:full":"249 Hooker Ave Poughkeepsie NY 12603",
    "addr:housenumber":"249",
    "addr:postcode":"12603",
    "addr:street":"Hooker Ave",
    "iso:country":"US",
    "sg:address":"249 Hooker Ave",
    "sg:city":"Poughkeepsie",
    "sg:classifiers":[
        {
            "category":"Organizations",
            "subcategory":"Non-profit Organization",
            "type":"Services"
        }
    ],
    "sg:phone":"+1 845 454 0595",
    "sg:postcode":"12603",
    "sg:province":"NY",
    "sg:website":"www.child-abuse-prevention.org",
    "wof:name":"Child Abuse Prevention Ctr",
    "wof:placetype":"venue"
},
  "geometry": {"coordinates":[-73.911254,41.686271],"type":"Point"}
}