{
  "type": "Feature",
  "properties": {
    "iso:country":"US",
    "sg:address":"7 Chardavoyne Rd",
    "sg:city":"Warwick",
    "sg:classifiers":[
        {
            "category":"Shopping",
            "subcategory":"Hobbies, Toys, & Games",
            "type":"Retail Goods"
        }
    ],
    "sg:phone":"+1 845 258 4732",
    "sg:postcode":"10990",
    "sg:province":"NY",
    "sg:tags":[
        "craft",
        "supply"
    ],
    "wof:name":"Jacques Hemsi",
    "wof:placetype":"venue"
},
  "geometry": {"coordinates":[-74.42659500000001,41.28764],"type":"Point"}
}