{
  "type": "Feature",
  "properties": {
    "iso:country":"US",
    "sg:address":"108 Sheffield Ln",
    "sg:city":"Fayetteville",
    "sg:classifiers":[
        {
            "category":"Manufacturing",
            "subcategory":"Tools & Machinery",
            "type":"Manufacturing & Wholesale Goods"
        },
        {
            "category":"Manufacturing",
            "subcategory":"Electronics",
            "type":"Manufacturing & Wholesale Goods"
        }
    ],
    "sg:phone":"+1 315 637 3976",
    "sg:postcode":"13066",
    "sg:province":"NY",
    "sg:tags":[
        "mfg",
        "devices",
        "semiconductor",
        "equipment",
        "lighting",
        "vehicle"
    ],
    "sg:website":"www.semiconductors.philips.com",
    "wof:name":"Philips Semiconductors Inc",
    "wof:placetype":"venue"
},
  "geometry": {"coordinates":[-75.99661399999999,43.023112],"type":"Point"}
}