{
  "type": "Feature",
  "properties": {
    "addr:full":"2309 Union Blvd Islip NY 11751",
    "addr:housenumber":"2309",
    "addr:postcode":"11751",
    "addr:street":"Union Blvd",
    "iso:country":"US",
    "sg:address":"2309 Union Blvd",
    "sg:city":"Islip",
    "sg:classifiers":[
        {
            "category":"Professional",
            "subcategory":"Management & Consulting",
            "type":"Services"
        }
    ],
    "sg:phone":"+1 631 589 4887",
    "sg:postcode":"11751",
    "sg:province":"NY",
    "sg:tags":[
        "party",
        "planning"
    ],
    "wof:name":"Make A Friend",
    "wof:placetype":"venue"
},
  "geometry": {"coordinates":[-73.225251,40.731401],"type":"Point"}
}