{
  "type": "Feature",
  "properties": {
    "iso:country":"US",
    "sg:address":"451 US Hwy 9w",
    "sg:city":"Congers",
    "sg:classifiers":[
        {
            "category":"Building & Trades",
            "subcategory":"Plumbing",
            "type":"Services"
        }
    ],
    "sg:phone":"+1 845 268 2400",
    "sg:postcode":"10920",
    "sg:province":"NY",
    "sg:tags":[
        "contractor"
    ],
    "wof:name":"Air Kool Mechanical Contrctng",
    "wof:placetype":"venue"
},
  "geometry": {"coordinates":[-73.943479,41.170828],"type":"Point"}
}