{
  "type": "Feature",
  "properties": {
    "addr:full":"84 E Main St Kings Park NY 11754",
    "addr:housenumber":"84",
    "addr:postcode":"11754",
    "addr:street":"E Main St",
    "iso:country":"US",
    "sg:address":"84 E Main St",
    "sg:city":"Kings Park",
    "sg:classifiers":[
        {
            "category":"Home & Garden",
            "subcategory":"Garden Supply",
            "type":"Retail Goods"
        }
    ],
    "sg:phone":"+1 631 269 1080",
    "sg:postcode":"11754",
    "sg:province":"NY",
    "sg:tags":[
        "lawn",
        "mower"
    ],
    "wof:name":"D Provenzano's Power Equipment",
    "wof:placetype":"venue"
},
  "geometry": {"coordinates":[-73.25026099999999,40.884223],"type":"Point"}
}