{
  "type": "Feature",
  "properties": {
    "addr:full":"229 W 36 St New York NY 10018",
    "addr:housenumber":"229",
    "addr:postcode":"10018",
    "addr:street":"W 36 St",
    "iso:country":"US",
    "sg:address":"229 W 36 St",
    "sg:city":"New York",
    "sg:classifiers":[
        {
            "category":"Real Estate",
            "subcategory":"Real Estate Agent",
            "type":"Services"
        }
    ],
    "sg:phone":"+1 212 868 8626",
    "sg:postcode":"10018",
    "sg:province":"NY",
    "sg:tags":[
        "management"
    ],
    "wof:name":"Handro Properties",
    "wof:placetype":"venue"
},
  "geometry": {"coordinates":[-73.991878,40.753198],"type":"Point"}
}