{
  "type": "Feature",
  "properties": {
    "addr:full":"653 Amsterdam Avenue New York NY 10025",
    "addr:housenumber":"653",
    "addr:postcode":"10025",
    "addr:street":"Amsterdam Avenue",
    "iso:country":"US",
    "sg:address":"653 Amsterdam Avenue",
    "sg:city":"New York",
    "sg:classifiers":[
        {
            "category":"Building & Trades",
            "subcategory":"Plumbing",
            "type":"Services"
        }
    ],
    "sg:phone":"+1 212 362 7062",
    "sg:postcode":"10025",
    "sg:province":"NY",
    "wof:name":"Wynne Plumbing & Heating Company",
    "wof:placetype":"venue"
},
  "geometry": {"coordinates":[-73.97257500000001,40.791231],"type":"Point"}
}