{
  "type": "Feature",
  "properties": {
    "addr:full":"6 Sam Law Dr Monsey NY 10952",
    "addr:housenumber":"6",
    "addr:postcode":"10952",
    "addr:street":"Sam Law Dr",
    "iso:country":"US",
    "sg:address":"6 Sam Law Dr",
    "sg:city":"Monsey",
    "sg:classifiers":[
        {
            "category":"Organizations",
            "subcategory":"Religious Organization",
            "type":"Services"
        }
    ],
    "sg:phone":"+1 845 425 9089",
    "sg:postcode":"10952",
    "sg:province":"NY",
    "sg:tags":[
        "synagogue"
    ],
    "wof:name":"K'Hal Adath Jeshurun",
    "wof:placetype":"venue"
},
  "geometry": {"coordinates":[-74.059753,41.125282],"type":"Point"}
}