{
  "type": "Feature",
  "properties": {
    "addr:full":"2125 Mill Ave Brooklyn NY 11234",
    "addr:housenumber":"2125",
    "addr:postcode":"11234",
    "addr:street":"Mill Ave",
    "iso:country":"US",
    "sg:address":"2125 Mill Ave",
    "sg:city":"Brooklyn",
    "sg:phone":"+1 718 629 0900",
    "sg:postcode":"11234",
    "sg:province":"NY",
    "sg:tags":[
        "oil"
    ],
    "wof:name":"Pasternack Fuel",
    "wof:placetype":"venue"
},
  "geometry": {"coordinates":[-73.913456,40.615049],"type":"Point"}
}