{
  "type": "Feature",
  "properties": {
    "addr:full":"20 W 55 St New York NY 10019",
    "addr:housenumber":"20",
    "addr:postcode":"10019",
    "addr:street":"W 55 St",
    "iso:country":"US",
    "sg:address":"20 W 55 St",
    "sg:city":"New York",
    "sg:classifiers":[
        {
            "category":"Professional",
            "subcategory":"Management & Consulting",
            "type":"Services"
        }
    ],
    "sg:phone":"+1 212 486 4444",
    "sg:postcode":"10019",
    "sg:province":"NY",
    "sg:tags":[
        "consultant",
        "designer",
        "bank"
    ],
    "wof:name":"Mitchell & Co",
    "wof:placetype":"venue"
},
  "geometry": {"coordinates":[-73.977718,40.762704],"type":"Point"}
}