{
  "type": "Feature",
  "properties": {
    "iso:country":"US",
    "sg:address":"110 W 125th St",
    "sg:city":"New York",
    "sg:classifiers":[
        {
            "category":"Retail",
            "subcategory":"Repair Shop",
            "type":"Services"
        }
    ],
    "sg:phone":"+1 212 961 1100",
    "sg:postcode":"10027",
    "sg:province":"NY",
    "sg:tags":[
        "store"
    ],
    "wof:name":"Sun Light Video & Electronics",
    "wof:placetype":"venue"
},
  "geometry": {"coordinates":[-73.948143,40.808784],"type":"Point"}
}