{
  "type": "Feature",
  "properties": {
    "addr:full":"85 Mac Dougal St New York NY 10012",
    "addr:housenumber":"85",
    "addr:postcode":"10012",
    "addr:street":"Mac Dougal St",
    "iso:country":"US",
    "sg:address":"85 Mac Dougal St",
    "sg:city":"New York",
    "sg:classifiers":[
        {
            "category":"Restaurant",
            "type":"Food & Drink"
        }
    ],
    "sg:phone":"+1   ",
    "sg:postcode":"10012",
    "sg:province":"NY",
    "wof:name":"Camag Restaurant",
    "wof:placetype":"venue"
},
  "geometry": {"coordinates":[-74.001876,40.728237],"type":"Point"}
}