{
  "type": "Feature",
  "properties": {
    "iso:country":"US",
    "sg:address":"53 Varick Avenue",
    "sg:city":"Brooklyn",
    "sg:classifiers":[
        {
            "category":"Food & Beverages",
            "subcategory":"Candy",
            "type":"Retail Goods"
        }
    ],
    "sg:phone":"+1 718 497 0170",
    "sg:postcode":"11237",
    "sg:province":"NY",
    "sg:tags":[
        "store"
    ],
    "wof:name":"Joyva Corporation",
    "wof:placetype":"venue"
},
  "geometry": {"coordinates":[-73.927295,40.707588],"type":"Point"}
}