{
  "type": "Feature",
  "properties": {
    "addr:full":"1546 Union Center Maine Hwy Endicott NY 13760",
    "addr:housenumber":"1546",
    "addr:postcode":"13760",
    "addr:street":"Union Center Maine Hwy",
    "iso:country":"US",
    "sg:address":"1546 Union Center Maine Hwy",
    "sg:city":"Endicott",
    "sg:classifiers":[
        {
            "category":"Manufacturing",
            "subcategory":"Tools & Machinery",
            "type":"Manufacturing & Wholesale Goods"
        }
    ],
    "sg:phone":"+1   ",
    "sg:postcode":"13760",
    "sg:province":"NY",
    "sg:tags":[
        "industrial",
        "mfg"
    ],
    "wof:name":"JD Tool Car",
    "wof:placetype":"venue"
},
  "geometry": {"coordinates":[-76.064987,42.129077],"type":"Point"}
}