{
  "type": "Feature",
  "properties": {
    "addr:full":"35 Sunny Ridge Rd Harrison NY 10528",
    "addr:housenumber":"35",
    "addr:postcode":"10528",
    "addr:street":"Sunny Ridge Rd",
    "iso:country":"US",
    "sg:address":"35 Sunny Ridge Rd",
    "sg:city":"Harrison",
    "sg:classifiers":[
        {
            "category":"Organizations",
            "subcategory":"Religious Organization",
            "type":"Services"
        }
    ],
    "sg:phone":"+1 914 967 4251",
    "sg:postcode":"10528",
    "sg:province":"NY",
    "sg:tags":[
        "clergy"
    ],
    "wof:name":"Norton D Shargel",
    "wof:placetype":"venue"
},
  "geometry": {"coordinates":[-73.710294,40.977016],"type":"Point"}
}