{
  "type": "Feature",
  "properties": {
    "iso:country":"US",
    "sg:address":"111 Wall St",
    "sg:city":"New York",
    "sg:classifiers":[
        {
            "category":"Banks & Credit Unions",
            "subcategory":"Bank",
            "type":"Services"
        }
    ],
    "sg:phone":"+1 212 809 1270",
    "sg:postcode":"10005",
    "sg:province":"NY",
    "wof:name":"Citigroup Technology Incorporated",
    "wof:placetype":"venue"
},
  "geometry": {"coordinates":[-74.988764,40.70463],"type":"Point"}
}