{
  "type": "Feature",
  "properties": {
    "addr:full":"8101 Flatlands Ave Brooklyn NY 11236",
    "addr:housenumber":"8101",
    "addr:postcode":"11236",
    "addr:street":"Flatlands Ave",
    "iso:country":"US",
    "sg:address":"8101 Flatlands Ave",
    "sg:city":"Brooklyn",
    "sg:classifiers":[
        {
            "category":"Shopping",
            "subcategory":"Department Store",
            "type":"Retail Goods"
        }
    ],
    "sg:phone":"+1 347 462 2294",
    "sg:postcode":"11236",
    "sg:province":"NY",
    "wof:name":"Super Discount",
    "wof:placetype":"venue"
},
  "geometry": {"coordinates":[-73.91263600000001,40.636165],"type":"Point"}
}