{
  "type": "Feature",
  "properties": {
    "addr:full":"34 Center St New Paltz NY 12561",
    "addr:housenumber":"34",
    "addr:postcode":"12561",
    "addr:street":"Center St",
    "iso:country":"US",
    "sg:address":"34 Center St",
    "sg:city":"New Paltz",
    "sg:classifiers":[
        {
            "category":"Wholesale",
            "subcategory":"Non-durable Goods",
            "type":"Manufacturing & Wholesale Goods"
        }
    ],
    "sg:phone":"+1 845 255 0562",
    "sg:postcode":"12561",
    "sg:province":"NY",
    "wof:name":"Quality String Imports Inc",
    "wof:placetype":"venue"
},
  "geometry": {"coordinates":[-74.079967,41.74557],"type":"Point"}
}