{
  "type": "Feature",
  "properties": {
    "addr:full":"314 State St Auburn NY 13021",
    "addr:housenumber":"314",
    "addr:postcode":"13021",
    "addr:street":"State St",
    "iso:country":"US",
    "sg:address":"314 State St",
    "sg:city":"Auburn",
    "sg:classifiers":[
        {
            "category":"Organizations",
            "subcategory":"Community Association",
            "type":"Services"
        }
    ],
    "sg:phone":"+1 315 252 4351",
    "sg:postcode":"13021",
    "sg:province":"NY",
    "sg:tags":[
        "fraternal"
    ],
    "wof:name":"Elks Lodge",
    "wof:placetype":"venue"
},
  "geometry": {"coordinates":[-76.579587,42.953911],"type":"Point"}
}