{
  "type": "Feature",
  "properties": {
    "iso:country":"US",
    "sg:address":"1201 Troy Schenectady Rd # 3",
    "sg:city":"Latham",
    "sg:classifiers":[
        {
            "category":"Health Services",
            "subcategory":"Clinic",
            "type":"Services"
        }
    ],
    "sg:phone":"+1 518 783 3110",
    "sg:postcode":"12110",
    "sg:province":"NY",
    "sg:tags":[
        "osteopathic"
    ],
    "wof:name":"Esposito Russell Do",
    "wof:placetype":"venue"
},
  "geometry": {"coordinates":[-73.822548,42.77153],"type":"Point"}
}