{
  "type": "Feature",
  "properties": {
    "addr:full":"60 Corbin Ave Bay Shore NY 11706",
    "addr:housenumber":"60",
    "addr:postcode":"11706",
    "addr:street":"Corbin Ave",
    "iso:country":"US",
    "sg:address":"60 Corbin Ave",
    "sg:city":"Bay Shore",
    "sg:classifiers":[
        {
            "category":"Wholesale",
            "subcategory":"Electrical",
            "type":"Manufacturing & Wholesale Goods"
        }
    ],
    "sg:phone":"+1 631 242 8657",
    "sg:postcode":"11706",
    "sg:province":"NY",
    "sg:tags":[
        "communication",
        "radio",
        "system"
    ],
    "wof:name":"Bay Village Communications",
    "wof:placetype":"venue"
},
  "geometry": {"coordinates":[-73.292097,40.766834],"type":"Point"}
}