{
  "type": "Feature",
  "properties": {
    "addr:full":"636 Broadway Suite 1004 New York NY 10012",
    "addr:housenumber":"636",
    "addr:postcode":"10012",
    "addr:street":"Broadway Suite 1004",
    "iso:country":"US",
    "sg:address":"636 Broadway Suite 1004",
    "sg:city":"New York",
    "sg:classifiers":[
        {
            "category":"Personal",
            "subcategory":"Massage",
            "type":"Services"
        }
    ],
    "sg:phone":"+1 646 203 4333",
    "sg:postcode":"10012",
    "sg:province":"NY",
    "sg:website":"www.hiraihealing.com",
    "wof:name":"Hirai Healing",
    "wof:placetype":"venue"
},
  "geometry": {"coordinates":[-73.995977,40.726334],"type":"Point"}
}