{
  "type": "Feature",
  "properties": {
    "iso:country":"US",
    "sg:address":"641 Lydig Ave",
    "sg:city":"Bronx",
    "sg:classifiers":[
        {
            "category":"Restaurant",
            "type":"Food & Drink"
        }
    ],
    "sg:menulink":"http://www.allmenus.com/ny/bronx/59174-rawal-ravali-restaurant/menu/",
    "sg:phone":"+1 718 319 8688",
    "sg:postcode":"10462",
    "sg:province":"NY",
    "sg:tags":[
        "indian",
        "asian"
    ],
    "wof:name":"Rawal Ravali Restaurant",
    "wof:placetype":"venue"
},
  "geometry": {"coordinates":[-73.868287,40.854418],"type":"Point"}
}