{
  "type": "Feature",
  "properties": {
    "iso:country":"US",
    "sg:address":"100 Main St",
    "sg:city":"Port Washington",
    "sg:classifiers":[
        {
            "category":"Shopping",
            "type":"Retail Goods"
        }
    ],
    "sg:phone":"+1 516 944 3136",
    "sg:postcode":"11050",
    "sg:province":"NY",
    "sg:tags":[
        "art",
        "gallery",
        "dealer"
    ],
    "wof:name":"Contemporary Art & Cllctbls",
    "wof:placetype":"venue"
},
  "geometry": {"coordinates":[-73.689685,40.830401],"type":"Point"}
}