{
  "type": "Feature",
  "properties": {
    "addr:full":"33 Evergreen Ave Clifton Park NY 12065",
    "addr:housenumber":"33",
    "addr:postcode":"12065",
    "addr:street":"Evergreen Ave",
    "iso:country":"US",
    "sg:address":"33 Evergreen Ave",
    "sg:city":"Clifton Park",
    "sg:classifiers":[
        {
            "category":"Personal",
            "subcategory":"Beauty Salon",
            "type":"Services"
        }
    ],
    "sg:phone":"+1   ",
    "sg:postcode":"12065",
    "sg:province":"NY",
    "sg:tags":[
        "shop"
    ],
    "wof:name":"Kathryn Prof Hair Remov & Skin",
    "wof:placetype":"venue"
},
  "geometry": {"coordinates":[-73.781277,42.845752],"type":"Point"}
}