{
  "type": "Feature",
  "properties": {
    "addr:full":"412 Ave C Brooklyn NY 11218",
    "addr:housenumber":"412",
    "addr:postcode":"11218",
    "addr:street":"Ave C",
    "iso:country":"US",
    "sg:address":"412 Ave C",
    "sg:city":"Brooklyn",
    "sg:classifiers":[
        {
            "category":"Organizations",
            "subcategory":"Religious Organization",
            "type":"Services"
        }
    ],
    "sg:phone":"+1 718 853 6016",
    "sg:postcode":"11218",
    "sg:province":"NY",
    "sg:tags":[
        "clergy"
    ],
    "wof:name":"Yitzchok Goodman",
    "wof:placetype":"venue"
},
  "geometry": {"coordinates":[-73.97509100000001,40.640674],"type":"Point"}
}