{
  "type": "Feature",
  "properties": {
    "iso:country":"US",
    "sg:address":"4 Buttonwood Path",
    "sg:city":"Smithtown",
    "sg:classifiers":[
        {
            "category":"Professional",
            "subcategory":"Accounting & Tax Preparation",
            "type":"Services"
        }
    ],
    "sg:phone":"+1   ",
    "sg:postcode":"11787",
    "sg:province":"NY",
    "sg:tags":[
        "return"
    ],
    "wof:name":"Triple Check Income Tax",
    "wof:placetype":"venue"
},
  "geometry": {"coordinates":[-73.198916,40.839306],"type":"Point"}
}