{
  "type": "Feature",
  "properties": {
    "iso:country":"US",
    "sg:address":"317 Harrison Ave",
    "sg:city":"Endicott",
    "sg:classifiers":[
        {
            "category":"Building & Trades",
            "subcategory":"Cleaning & Sanitation",
            "type":"Services"
        }
    ],
    "sg:phone":"+1 607 757 9578",
    "sg:postcode":"13760",
    "sg:province":"NY",
    "wof:name":"Around The Clock Maintenance",
    "wof:placetype":"venue"
},
  "geometry": {"coordinates":[-76.05346,42.096564],"type":"Point"}
}