{
  "type": "Feature",
  "properties": {
    "addr:full":"77-05 Woodside Ave Elmhurst NY 11373",
    "addr:housenumber":"77-05",
    "addr:postcode":"11373",
    "addr:street":"Woodside Ave",
    "iso:country":"US",
    "sg:address":"77-05 Woodside Ave",
    "sg:city":"Elmhurst",
    "sg:classifiers":[
        {
            "category":"Restaurant",
            "type":"Food & Drink"
        }
    ],
    "sg:phone":"+1 718 672 5266",
    "sg:postcode":"11373",
    "sg:province":"NY",
    "sg:tags":[
        "thai",
        "japanese"
    ],
    "sg:website":"www.spicyshallot.com",
    "wof:name":"Spicy Shallot",
    "wof:placetype":"venue"
},
  "geometry": {"coordinates":[-73.887941,40.74356],"type":"Point"}
}