{
  "type": "Feature",
  "properties": {
    "addr:full":"6305 State Hwy 96 Victor NY 14564",
    "addr:housenumber":"6305",
    "addr:postcode":"14564",
    "addr:street":"State Hwy 96",
    "iso:country":"US",
    "sg:address":"6305 State Hwy 96",
    "sg:city":"Victor",
    "sg:classifiers":[
        {
            "category":"Personal",
            "subcategory":"Beauty Salon",
            "type":"Services"
        }
    ],
    "sg:phone":"+1 585 924 0560",
    "sg:postcode":"14564",
    "sg:province":"NY",
    "wof:name":"Gino's Hair Design",
    "wof:placetype":"venue"
},
  "geometry": {"coordinates":[-77.371745,42.974262],"type":"Point"}
}