{
  "type": "Feature",
  "properties": {
    "iso:country":"US",
    "sg:address":"6507 Wheeler Rd",
    "sg:city":"Lockport",
    "sg:classifiers":[
        {
            "category":"Health Services",
            "subcategory":"Doctor",
            "type":"Services"
        }
    ],
    "sg:phone":"+1 716 439 4340",
    "sg:postcode":"14094",
    "sg:province":"NY",
    "sg:tags":[
        "physician",
        "surgeon"
    ],
    "wof:name":"Robert W Hodge MD",
    "wof:placetype":"venue"
},
  "geometry": {"coordinates":[-78.66694099999999,43.222264],"type":"Point"}
}