{
  "type": "Feature",
  "properties": {
    "iso:country":"US",
    "sg:address":"230 Lake Ave",
    "sg:city":"Saint James",
    "sg:classifiers":[
        {
            "category":"Restaurant",
            "type":"Food & Drink"
        }
    ],
    "sg:phone":"+1 631 584 6367",
    "sg:postcode":"11780",
    "sg:province":"NY",
    "sg:tags":[
        "pizza"
    ],
    "wof:name":"Casa Buono Inc",
    "wof:placetype":"venue"
},
  "geometry": {"coordinates":[-73.15645499999999,40.875739],"type":"Point"}
}