{
  "type": "Feature",
  "properties": {
    "addr:full":"786 Courtlandt Ave Bronx NY 10451",
    "addr:housenumber":"786",
    "addr:postcode":"10451",
    "addr:street":"Courtlandt Ave",
    "iso:country":"US",
    "sg:address":"786 Courtlandt Ave",
    "sg:city":"Bronx",
    "sg:classifiers":[
        {
            "category":"Deli",
            "type":"Food & Drink"
        },
        {
            "category":"Food & Beverages",
            "subcategory":"Bakery",
            "type":"Retail Goods"
        }
    ],
    "sg:phone":"+1 646 401 7557",
    "sg:postcode":"10451",
    "sg:province":"NY",
    "sg:tags":[
        "sandwich"
    ],
    "wof:name":"One Hundred Fifty Seven Gourmet Deli",
    "wof:placetype":"venue"
},
  "geometry": {"coordinates":[-73.916618,40.822393],"type":"Point"}
}