{
  "type": "Feature",
  "properties": {
    "addr:full":"211 63rd St Brooklyn NY 11220",
    "addr:housenumber":"211",
    "addr:postcode":"11220",
    "addr:street":"63Rd St",
    "iso:country":"US",
    "sg:address":"211 63rd St",
    "sg:city":"Brooklyn",
    "sg:classifiers":[
        {
            "category":"Retail",
            "subcategory":"Auto Rental",
            "type":"Services"
        }
    ],
    "sg:phone":"+1 718 439 3515",
    "sg:postcode":"11220",
    "sg:province":"NY",
    "sg:tags":[
        "renting",
        "automobile"
    ],
    "wof:name":"All Car Rent A Car",
    "wof:placetype":"venue"
},
  "geometry": {"coordinates":[-74.022559,40.6408],"type":"Point"}
}