{
  "type": "Feature",
  "properties": {
    "iso:country":"US",
    "sg:address":"203 2nd Ave",
    "sg:city":"Frankfort",
    "sg:classifiers":[
        {
            "category":"Retail",
            "subcategory":"Funeral Services",
            "type":"Services"
        }
    ],
    "sg:phone":"+1 315 894 2211",
    "sg:postcode":"13340",
    "sg:province":"NY",
    "sg:tags":[
        "director"
    ],
    "wof:name":"V J Iocovozzi Funeral Home Inc",
    "wof:placetype":"venue"
},
  "geometry": {"coordinates":[-75.071792,43.035305],"type":"Point"}
}