{
  "type": "Feature",
  "properties": {
    "iso:country":"US",
    "sg:address":"8 Olympic Dr",
    "sg:city":"Orangeburg",
    "sg:classifiers":[
        {
            "category":"Manufacturing",
            "subcategory":"Tools & Machinery",
            "type":"Manufacturing & Wholesale Goods"
        }
    ],
    "sg:phone":"+1   ",
    "sg:postcode":"10962",
    "sg:province":"NY",
    "sg:tags":[
        "mfg",
        "engineering",
        "distributes",
        "computer",
        "scan"
    ],
    "sg:website":"www.opticon.com",
    "wof:name":"Opticon Inc",
    "wof:placetype":"venue"
},
  "geometry": {"coordinates":[-73.983661,41.035312],"type":"Point"}
}