{
  "type": "Feature",
  "properties": {
    "addr:full":"795 Canandaigua Rd Geneva NY 14456",
    "addr:housenumber":"795",
    "addr:postcode":"14456",
    "addr:street":"Canandaigua Rd",
    "iso:country":"US",
    "sg:address":"795 Canandaigua Rd",
    "sg:city":"Geneva",
    "sg:classifiers":[
        {
            "category":"Shopping",
            "subcategory":"Discount & Variety Stores",
            "type":"Retail Goods"
        }
    ],
    "sg:phone":"+1 315 789 0273",
    "sg:postcode":"14456",
    "sg:province":"NY",
    "sg:website":"www.biglots.com",
    "wof:name":"Big Lots",
    "wof:placetype":"venue"
},
  "geometry": {"coordinates":[-77.010824,42.85659],"type":"Point"}
}