{
  "type": "Feature",
  "properties": {
    "iso:country":"US",
    "sg:address":"268 Smith St",
    "sg:city":"Brooklyn",
    "sg:classifiers":[
        {
            "category":"Organizations",
            "subcategory":"Non-profit Organization",
            "type":"Services"
        }
    ],
    "sg:phone":"+1 718 852 0328",
    "sg:postcode":"11231",
    "sg:province":"NY",
    "wof:name":"South Brooklyn Local Dev",
    "wof:placetype":"venue"
},
  "geometry": {"coordinates":[-73.993438,40.68252],"type":"Point"}
}