{
  "type": "Feature",
  "properties": {
    "addr:full":"7 High St Huntington NY 11743",
    "addr:housenumber":"7",
    "addr:postcode":"11743",
    "addr:street":"High St",
    "iso:country":"US",
    "sg:address":"7 High St",
    "sg:city":"Huntington",
    "sg:classifiers":[
        {
            "category":"Organizations",
            "subcategory":"Non-profit Organization",
            "type":"Services"
        }
    ],
    "sg:phone":"+1 631 547 5161",
    "sg:postcode":"11743",
    "sg:province":"NY",
    "sg:tags":[
        "fund",
        "counselor",
        "raising"
    ],
    "wof:name":"Levy Philanthropic Counsel",
    "wof:placetype":"venue"
},
  "geometry": {"coordinates":[-73.425749,40.868162],"type":"Point"}
}