{
  "type": "Feature",
  "properties": {
    "iso:country":"US",
    "sg:address":"7 Purdy St",
    "sg:city":"Harrison",
    "sg:classifiers":[
        {
            "category":"Bars & Pubs",
            "type":"Food & Drink"
        }
    ],
    "sg:menulink":"http://www.allmenus.com/ny/harrison/146621-trinity---a-grill--bar/menu/",
    "sg:phone":"+1 914 835 5920",
    "sg:postcode":"10528",
    "sg:province":"NY",
    "sg:tags":[
        "american"
    ],
    "wof:name":"Trinity - A Grill & Bar",
    "wof:placetype":"venue"
},
  "geometry": {"coordinates":[-73.711214,40.966857],"type":"Point"}
}