{
  "type": "Feature",
  "properties": {
    "iso:country":"US",
    "sg:address":"2380 Ralph Ave",
    "sg:city":"Brooklyn",
    "sg:classifiers":[
        {
            "category":"Banks & Credit Unions",
            "subcategory":"Bank",
            "type":"Services"
        }
    ],
    "sg:phone":"+1 718 251 4040",
    "sg:postcode":"11234",
    "sg:province":"NY",
    "sg:tags":[
        "mortgage",
        "loan",
        "broker",
        "real estate"
    ],
    "wof:name":"Mortgage Enterprise Ltd",
    "wof:placetype":"venue"
},
  "geometry": {"coordinates":[-73.917418,40.620529],"type":"Point"}
}