{
  "type": "Feature",
  "properties": {
    "addr:full":"5410 New Utrecht Avenue Brooklyn NY 11219",
    "addr:housenumber":"5410",
    "addr:postcode":"11219",
    "addr:street":"New Utrecht Avenue",
    "iso:country":"US",
    "sg:address":"5410 New Utrecht Avenue",
    "sg:city":"Brooklyn",
    "sg:classifiers":[
        {
            "category":"Food & Beverages",
            "subcategory":"Meat & Fish",
            "type":"Retail Goods"
        }
    ],
    "sg:phone":"+1 718 436 2265",
    "sg:postcode":"11219",
    "sg:province":"NY",
    "sg:tags":[
        "shop"
    ],
    "wof:name":"Meisner Take Home Food",
    "wof:placetype":"venue"
},
  "geometry": {"coordinates":[-73.995486,40.632151],"type":"Point"}
}