{
  "type": "Feature",
  "properties": {
    "addr:full":"330 W 58th St Manhattan NY 10019",
    "addr:housenumber":"330",
    "addr:postcode":"10019",
    "addr:street":"W 58Th St",
    "iso:country":"US",
    "sg:address":"330 W 58th St",
    "sg:city":"Manhattan",
    "sg:classifiers":[
        {
            "category":"Building & Trades",
            "subcategory":"Cleaning & Sanitation",
            "type":"Services"
        }
    ],
    "sg:phone":"+1 646 688 3529",
    "sg:postcode":"10019",
    "sg:province":"NY",
    "sg:tags":[
        "carpet"
    ],
    "sg:website":"www.carpet-cleaning-new-york.com...",
    "wof:name":"Wood Floor Refinishing New York - Carpet Cleaning New York",
    "wof:placetype":"venue"
},
  "geometry": {"coordinates":[-73.983586,40.767876],"type":"Point"}
}