{
  "type": "Feature",
  "properties": {
    "addr:full":"1240 Union Ave Bronx NY 10459",
    "addr:housenumber":"1240",
    "addr:postcode":"10459",
    "addr:street":"Union Ave",
    "iso:country":"US",
    "sg:address":"1240 Union Ave",
    "sg:city":"Bronx",
    "sg:classifiers":[
        {
            "category":"Food & Beverages",
            "subcategory":"Groceries & Convenience Stores",
            "type":"Retail Goods"
        }
    ],
    "sg:phone":"+1   ",
    "sg:postcode":"10459",
    "sg:province":"NY",
    "wof:name":"Top Deli Grocery",
    "wof:placetype":"venue"
},
  "geometry": {"coordinates":[-73.898802,40.829833],"type":"Point"}
}