{
  "type": "Feature",
  "properties": {
    "addr:full":"179 Front St Binghamton NY 13905",
    "addr:housenumber":"179",
    "addr:postcode":"13905",
    "addr:street":"Front St",
    "iso:country":"US",
    "sg:address":"179 Front St",
    "sg:city":"Binghamton",
    "sg:classifiers":[
        {
            "category":"Autos & Motor Vehicles",
            "subcategory":"Automobile Sales",
            "type":"Retail Goods"
        },
        {
            "category":"Autos & Motor Vehicles",
            "subcategory":"Auto Supplies",
            "type":"Retail Goods"
        }
    ],
    "sg:phone":"+1 607 723 8971",
    "sg:postcode":"13905",
    "sg:province":"NY",
    "sg:tags":[
        "car",
        "part",
        "new",
        "accessory"
    ],
    "sg:website":"http://www.chevrolet.com",
    "wof:name":"Botnick-Chevrolet Geo",
    "wof:placetype":"venue"
},
  "geometry": {"coordinates":[-75.91667,42.101524],"type":"Point"}
}