{
  "type": "Feature",
  "properties": {
    "addr:full":"171 W 4th St New York NY 10014",
    "addr:housenumber":"171",
    "addr:postcode":"10014",
    "addr:street":"W 4Th St",
    "iso:country":"US",
    "sg:address":"171 W 4th St",
    "sg:city":"New York",
    "sg:classifiers":[
        {
            "category":"Bakery",
            "type":"Food & Drink"
        }
    ],
    "sg:menulink":"http://www.allmenus.com/ny/new-york/250240-marys-marvelous-ice-cream-cakes/menu/",
    "sg:phone":"+1 914 907 9086",
    "sg:postcode":"10014",
    "sg:province":"NY",
    "sg:tags":[
        "american",
        "pastry"
    ],
    "wof:name":"Mary's Marvelous Ice Cream Cakes",
    "wof:placetype":"venue"
},
  "geometry": {"coordinates":[-74.00138200000001,40.73232],"type":"Point"}
}