{
  "type": "Feature",
  "properties": {
    "addr:full":"5 Court St Norwich NY 13815",
    "addr:housenumber":"5",
    "addr:postcode":"13815",
    "addr:street":"Court St",
    "iso:country":"US",
    "sg:address":"5 Court St",
    "sg:city":"Norwich",
    "sg:classifiers":[
        {
            "category":"Government",
            "subcategory":"Office",
            "type":"Public Place"
        }
    ],
    "sg:phone":"+1 607 337 1494",
    "sg:postcode":"13815",
    "sg:province":"NY",
    "sg:tags":[
        "preparation",
        "return",
        "taxation",
        "tax",
        "county"
    ],
    "wof:name":"Tax Map",
    "wof:placetype":"venue"
},
  "geometry": {"coordinates":[-75.525087,42.531317],"type":"Point"}
}