{
  "type": "Feature",
  "properties": {
    "iso:country":"US",
    "sg:address":"436 Nostrand Ave",
    "sg:city":"Brooklyn",
    "sg:classifiers":[
        {
            "category":"Real Estate",
            "subcategory":"Architect",
            "type":"Services"
        }
    ],
    "sg:phone":"+1 718 230 8320",
    "sg:postcode":"11216",
    "sg:province":"NY",
    "sg:tags":[
        "home",
        "planning",
        "design"
    ],
    "wof:name":"Star Homes Design & Mgmt Inc",
    "wof:placetype":"venue"
},
  "geometry": {"coordinates":[-73.950469,40.684619],"type":"Point"}
}