{
  "type": "Feature",
  "properties": {
    "addr:full":"114 Byron Ct Cornwall NY 12518",
    "addr:housenumber":"114",
    "addr:postcode":"12518",
    "addr:street":"Byron Ct",
    "iso:country":"US",
    "sg:address":"114 Byron Ct",
    "sg:city":"Cornwall",
    "sg:classifiers":[
        {
            "category":"Real Estate",
            "subcategory":"Real Estate Agent",
            "type":"Services"
        }
    ],
    "sg:phone":"+1 845 534 8572",
    "sg:postcode":"12518",
    "sg:province":"NY",
    "wof:name":"Gann Realty Svcs",
    "wof:placetype":"venue"
},
  "geometry": {"coordinates":[-74.048473,41.440119],"type":"Point"}
}