{
  "type": "Feature",
  "properties": {
    "addr:full":"6759 152nd St Flushing NY 11367",
    "addr:housenumber":"6759",
    "addr:postcode":"11367",
    "addr:street":"152Nd St",
    "iso:country":"US",
    "sg:address":"6759 152nd St",
    "sg:city":"Flushing",
    "sg:classifiers":[
        {
            "category":"Education",
            "subcategory":"Special Training",
            "type":"Public Place"
        }
    ],
    "sg:phone":"+1 718 793 1785",
    "sg:postcode":"11367",
    "sg:province":"NY",
    "sg:tags":[
        "career",
        "counseling",
        "vocational"
    ],
    "wof:name":"Wisdom Tree",
    "wof:placetype":"venue"
},
  "geometry": {"coordinates":[-73.811459,40.719255],"type":"Point"}
}