{
  "type": "Feature",
  "properties": {
    "addr:full":"510 Laguardia Pl New York NY 10012",
    "addr:housenumber":"510",
    "addr:postcode":"10012",
    "addr:street":"Laguardia Pl",
    "iso:country":"US",
    "sg:address":"510 Laguardia Pl",
    "sg:city":"New York",
    "sg:classifiers":[
        {
            "category":"Professional",
            "type":"Services"
        }
    ],
    "sg:phone":"+1 212 780 5737",
    "sg:postcode":"10012",
    "sg:province":"NY",
    "sg:tags":[
        "establishment"
    ],
    "wof:name":"Caipirnha Productions",
    "wof:placetype":"venue"
},
  "geometry": {"coordinates":[-73.99955199999999,40.727278],"type":"Point"}
}