{
  "type": "Feature",
  "properties": {
    "iso:country":"US",
    "sg:address":"30 Virginia Rd",
    "sg:city":"White Plains",
    "sg:classifiers":[
        {
            "category":"Professional",
            "subcategory":"Business Services",
            "type":"Services"
        },
        {
            "category":"Wholesale",
            "subcategory":"Painting Supplies",
            "type":"Manufacturing & Wholesale Goods"
        }
    ],
    "sg:phone":"+1 914 948 4000",
    "sg:postcode":"10603",
    "sg:province":"NY",
    "sg:tags":[
        "consultant",
        "paint",
        "design",
        "decorator",
        "interior",
        "retail",
        "painter"
    ],
    "sg:website":"www.wallauer.com",
    "wof:name":"Wallauer Decorating Stores",
    "wof:placetype":"venue"
},
  "geometry": {"coordinates":[-73.76921,41.053915],"type":"Point"}
}