{
  "type": "Feature",
  "properties": {
    "addr:full":"450 Fashion Ave Fl 39 New York NY 10123",
    "addr:housenumber":"450;39",
    "addr:postcode":"10123",
    "addr:street":"Fashion Ave Fl",
    "iso:country":"US",
    "sg:address":"450 Fashion Ave Fl 39",
    "sg:city":"New York",
    "sg:classifiers":[
        {
            "category":"Professional",
            "subcategory":"Lawyer & Legal Services",
            "type":"Services"
        }
    ],
    "sg:phone":"+1 646 840 3397",
    "sg:postcode":"10123",
    "sg:province":"NY",
    "wof:name":"Fischer Eugene B Atty",
    "wof:placetype":"venue"
},
  "geometry": {"coordinates":[-73.990649,40.751386],"type":"Point"}
}