{
  "type": "Feature",
  "properties": {
    "addr:full":"3445 Winton Pl Rochester NY 14623",
    "addr:housenumber":"3445",
    "addr:postcode":"14623",
    "addr:street":"Winton Pl",
    "iso:country":"US",
    "sg:address":"3445 Winton Pl",
    "sg:city":"Rochester",
    "sg:classifiers":[
        {
            "category":"Professional",
            "subcategory":"Computer Services",
            "type":"Services"
        }
    ],
    "sg:phone":"+1 585 797 2932",
    "sg:postcode":"14623",
    "sg:province":"NY",
    "sg:tags":[
        "consultant",
        "designer",
        "programming",
        "custom"
    ],
    "wof:name":"Web Harmonics Inc",
    "wof:placetype":"venue"
},
  "geometry": {"coordinates":[-77.57769500000001,43.09606],"type":"Point"}
}