{
  "type": "Feature",
  "properties": {
    "addr:full":"374 Central Ave Brooklyn NY 11221",
    "addr:housenumber":"374",
    "addr:postcode":"11221",
    "addr:street":"Central Ave",
    "iso:country":"US",
    "sg:address":"374 Central Ave",
    "sg:city":"Brooklyn",
    "sg:classifiers":[
        {
            "category":"Retail",
            "subcategory":"Repair Shop",
            "type":"Services"
        }
    ],
    "sg:phone":"+1 718 301 7637",
    "sg:postcode":"11221",
    "sg:province":"NY",
    "sg:tags":[
        "lock",
        "locksmith"
    ],
    "wof:name":"24 Hour 7 Day Emerg Locksmith",
    "wof:placetype":"venue"
},
  "geometry": {"coordinates":[-73.917761,40.693877],"type":"Point"}
}