{
  "type": "Feature",
  "properties": {
    "iso:country":"US",
    "sg:address":"83 Comsewogue Rd Ste D",
    "sg:city":"East Setauket",
    "sg:classifiers":[
        {
            "category":"Retail",
            "subcategory":"Auto Repair",
            "type":"Services"
        }
    ],
    "sg:phone":"+1 631 473 9725",
    "sg:postcode":"11733",
    "sg:province":"NY",
    "wof:name":"Accurate Alignment & Automotive Inc",
    "wof:placetype":"venue"
},
  "geometry": {"coordinates":[-73.087,40.934598],"type":"Point"}
}