{
  "type": "Feature",
  "properties": {
    "addr:full":"167 Avenue B Frnt New York NY 10009",
    "addr:housenumber":"167",
    "addr:postcode":"10009",
    "addr:street":"Avenue B Frnt",
    "iso:country":"US",
    "sg:address":"167 Avenue B Frnt",
    "sg:city":"New York",
    "sg:classifiers":[
        {
            "category":"Retail",
            "subcategory":"Laundry & Dry Cleaning",
            "type":"Services"
        }
    ],
    "sg:phone":"+1 212 529 8455",
    "sg:postcode":"10009",
    "sg:province":"NY",
    "wof:name":"Mercury 1 Dry Cleaning",
    "wof:placetype":"venue"
},
  "geometry": {"coordinates":[-73.9795,40.727299],"type":"Point"}
}