{
  "type": "Feature",
  "properties": {
    "addr:full":"333 E 14th St New York NY 10003",
    "addr:housenumber":"333",
    "addr:postcode":"10003",
    "addr:street":"E 14Th St",
    "iso:country":"US",
    "sg:address":"333 E 14th St",
    "sg:city":"New York",
    "sg:classifiers":[
        {
            "category":"Building & Trades",
            "subcategory":"Locksmith",
            "type":"Services"
        }
    ],
    "sg:phone":"+1 212 725 3717",
    "sg:postcode":"10003",
    "sg:province":"NY",
    "sg:tags":[
        "key"
    ],
    "wof:name":"Nyc Locksmith",
    "wof:placetype":"venue"
},
  "geometry": {"coordinates":[-73.9841,40.731998],"type":"Point"}
}