{
  "type": "Feature",
  "properties": {
    "addr:full":"91 Crosby Street New York NY 10079",
    "addr:housenumber":"91",
    "addr:postcode":"10079",
    "addr:street":"Crosby Street",
    "iso:country":"US",
    "sg:address":"91 Crosby Street",
    "sg:city":"New York",
    "sg:classifiers":[
        {
            "category":"Wholesale",
            "subcategory":"Stationery",
            "type":"Manufacturing & Wholesale Goods"
        }
    ],
    "sg:phone":"+1 212 620 0300",
    "sg:postcode":"10079",
    "sg:province":"NY",
    "sg:tags":[
        "card"
    ],
    "wof:name":"Industries Stationery",
    "wof:placetype":"venue"
},
  "geometry": {"coordinates":[-73.997299,40.723301],"type":"Point"}
}