{
  "type": "Feature",
  "properties": {
    "addr:full":"7719 Lander Rd Hornell NY 14843",
    "addr:housenumber":"7719",
    "addr:postcode":"14843",
    "addr:street":"Lander Rd",
    "iso:country":"US",
    "sg:address":"7719 Lander Rd",
    "sg:city":"Hornell",
    "sg:classifiers":[
        {
            "category":"Building & Trades",
            "subcategory":"Landscaping Services",
            "type":"Services"
        }
    ],
    "sg:phone":"+1 607 324 3596",
    "sg:postcode":"14843",
    "sg:province":"NY",
    "sg:tags":[
        "tree"
    ],
    "wof:name":"Hess Tree Service",
    "wof:placetype":"venue"
},
  "geometry": {"coordinates":[-77.54326399999999,42.375565],"type":"Point"}
}