{
  "type": "Feature",
  "properties": {
    "addr:full":"9 John St Bay Shore NY 11706",
    "addr:housenumber":"9",
    "addr:postcode":"11706",
    "addr:street":"John St",
    "iso:country":"US",
    "sg:address":"9 John St",
    "sg:city":"Bay Shore",
    "sg:classifiers":[
        {
            "category":"Restaurant",
            "type":"Food & Drink"
        }
    ],
    "sg:phone":"+1 631 665 7628",
    "sg:postcode":"11706",
    "sg:province":"NY",
    "sg:tags":[
        "deli",
        "delicatessen"
    ],
    "wof:name":"Spices West Indian American Store",
    "wof:placetype":"venue"
},
  "geometry": {"coordinates":[-73.256798,40.726601],"type":"Point"}
}