{
  "type": "Feature",
  "properties": {
    "addr:full":"112 Hampton St Sag Harbor NY 11963",
    "addr:housenumber":"112",
    "addr:postcode":"11963",
    "addr:street":"Hampton St",
    "iso:country":"US",
    "sg:address":"112 Hampton St",
    "sg:city":"Sag Harbor",
    "sg:classifiers":[
        {
            "category":"Shopping",
            "subcategory":"Used Merchandise",
            "type":"Retail Goods"
        }
    ],
    "sg:phone":"+1   ",
    "sg:postcode":"11963",
    "sg:province":"NY",
    "wof:name":"Liza Sherman Antiques",
    "wof:placetype":"venue"
},
  "geometry": {"coordinates":[-72.28577799999999,40.996525],"type":"Point"}
}