{
  "type": "Feature",
  "properties": {
    "addr:full":"1520 Route 9 Wappingers Falls NY 12590",
    "addr:housenumber":"1520",
    "addr:postcode":"12590",
    "addr:street":"Route 9",
    "iso:country":"US",
    "sg:address":"1520 Route 9",
    "sg:city":"Wappingers Falls",
    "sg:classifiers":[
        {
            "category":"Retail",
            "subcategory":"Car Wash",
            "type":"Services"
        }
    ],
    "sg:phone":"+1 845 297 8648",
    "sg:postcode":"12590",
    "sg:province":"NY",
    "wof:name":"Foam & Wash Car Washes",
    "wof:placetype":"venue"
},
  "geometry": {"coordinates":[-73.90860000000001,41.592098],"type":"Point"}
}