{
  "type": "Feature",
  "properties": {
    "iso:country":"US",
    "sg:address":"57 W 84 St",
    "sg:city":"New York",
    "sg:classifiers":[
        {
            "category":"Retail",
            "subcategory":"Laundry & Dry Cleaning",
            "type":"Services"
        }
    ],
    "sg:phone":"+1 212 873 0666",
    "sg:postcode":"10024",
    "sg:province":"NY",
    "wof:name":"A & L Dry Cleaners & Laundry",
    "wof:placetype":"venue"
},
  "geometry": {"coordinates":[-73.97187099999999,40.784553],"type":"Point"}
}