{
  "type": "Feature",
  "properties": {
    "addr:full":"373 Pressler Rd Wallkill NY 12589",
    "addr:housenumber":"373",
    "addr:postcode":"12589",
    "addr:street":"Pressler Rd",
    "iso:country":"US",
    "sg:address":"373 Pressler Rd",
    "sg:city":"Wallkill",
    "sg:classifiers":[
        {
            "category":"Building & Trades",
            "subcategory":"Plumbing",
            "type":"Services"
        }
    ],
    "sg:phone":"+1 845 566 7700",
    "sg:postcode":"12589",
    "sg:province":"NY",
    "wof:name":"Prime Plumbing & Heating Inc",
    "wof:placetype":"venue"
},
  "geometry": {"coordinates":[-74.05410000000001,41.568802],"type":"Point"}
}