{
  "type": "Feature",
  "properties": {
    "addr:full":"280 Grand St New York NY 10002",
    "addr:housenumber":"280",
    "addr:postcode":"10002",
    "addr:street":"Grand St",
    "iso:country":"US",
    "sg:address":"280 Grand St",
    "sg:city":"New York",
    "sg:classifiers":[
        {
            "category":"Food & Beverages",
            "subcategory":"Bakery",
            "type":"Retail Goods"
        }
    ],
    "sg:phone":"+1   ",
    "sg:postcode":"10002",
    "sg:province":"NY",
    "wof:name":"Lucky China Bakery Inc",
    "wof:placetype":"venue"
},
  "geometry": {"coordinates":[-73.99256099999999,40.717874],"type":"Point"}
}