{
  "type": "Feature",
  "properties": {
    "addr:full":"484 Amsterdam Ave New York NY 10024",
    "addr:housenumber":"484",
    "addr:postcode":"10024",
    "addr:street":"Amsterdam Ave",
    "iso:country":"US",
    "sg:address":"484 Amsterdam Ave",
    "sg:city":"New York",
    "sg:classifiers":[
        {
            "category":"Professional",
            "type":"Services"
        }
    ],
    "sg:phone":"+1 646 418 3203",
    "sg:postcode":"10024",
    "sg:province":"NY",
    "sg:tags":[
        "writer"
    ],
    "wof:name":"Blueberry Communications Inc",
    "wof:placetype":"venue"
},
  "geometry": {"coordinates":[-73.976129,40.786246],"type":"Point"}
}