{
  "type": "Feature",
  "properties": {
    "addr:full":"1881 Ridge Rd Buffalo NY 14224",
    "addr:housenumber":"1881",
    "addr:postcode":"14224",
    "addr:street":"Ridge Rd",
    "iso:country":"US",
    "sg:address":"1881 Ridge Rd",
    "sg:city":"Buffalo",
    "sg:classifiers":[
        {
            "category":"Restaurant",
            "type":"Food & Drink"
        }
    ],
    "sg:menulink":"http://www.allmenus.com/ny/west-seneca/11526-dennys/menu/",
    "sg:phone":"+1 716 675 7148",
    "sg:postcode":"14224",
    "sg:province":"NY",
    "sg:tags":[
        "american",
        "diner"
    ],
    "wof:name":"Denny's",
    "wof:placetype":"venue"
},
  "geometry": {"coordinates":[-78.784882,42.828693],"type":"Point"}
}