{
  "type": "Feature",
  "properties": {
    "iso:country":"US",
    "sg:address":"1525 E 12th St",
    "sg:city":"Brooklyn",
    "sg:classifiers":[
        {
            "category":"Organizations",
            "subcategory":"Religious Organization",
            "type":"Services"
        }
    ],
    "sg:phone":"+1 718 339 2828",
    "sg:postcode":"11230",
    "sg:province":"NY",
    "sg:tags":[
        "church"
    ],
    "wof:name":"St Brendan's Catholic Church",
    "wof:placetype":"venue"
},
  "geometry": {"coordinates":[-73.961389,40.610735],"type":"Point"}
}