{
  "type": "Feature",
  "properties": {
    "addr:full":"5601 13th Ave Brooklyn NY 11219",
    "addr:housenumber":"5601",
    "addr:postcode":"11219",
    "addr:street":"13Th Ave",
    "iso:country":"US",
    "sg:address":"5601 13th Ave",
    "sg:city":"Brooklyn",
    "sg:classifiers":[
        {
            "category":"Health Services",
            "subcategory":"Doctor",
            "type":"Services"
        }
    ],
    "sg:phone":"+1 718 436 7447",
    "sg:postcode":"11219",
    "sg:province":"NY",
    "sg:tags":[
        "physician",
        "medical",
        "surgeon"
    ],
    "wof:name":"Ivan I Lebovits MD",
    "wof:placetype":"venue"
},
  "geometry": {"coordinates":[-73.995722,40.631589],"type":"Point"}
}