{
  "type": "Feature",
  "properties": {
    "addr:full":"12 Sally Ln Ridge NY 11961",
    "addr:housenumber":"12",
    "addr:postcode":"11961",
    "addr:street":"Sally Ln",
    "iso:country":"US",
    "sg:address":"12 Sally Ln",
    "sg:city":"Ridge",
    "sg:classifiers":[
        {
            "category":"Professional",
            "type":"Services"
        }
    ],
    "sg:phone":"+1 631 345 0410",
    "sg:postcode":"11961",
    "sg:province":"NY",
    "sg:tags":[
        "establishment"
    ],
    "wof:name":"Mini Travelers Inc",
    "wof:placetype":"venue"
},
  "geometry": {"coordinates":[-72.88611,40.894306],"type":"Point"}
}