{
  "type": "Feature",
  "properties": {
    "addr:full":"3690 3rd Avenue Bronx NY 10456",
    "addr:housenumber":"3690",
    "addr:postcode":"10456",
    "addr:street":"3Rd Avenue",
    "iso:country":"US",
    "sg:address":"3690 3rd Avenue",
    "sg:city":"Bronx",
    "sg:classifiers":[
        {
            "category":"Food & Beverages",
            "subcategory":"Groceries & Convenience Stores",
            "type":"Retail Goods"
        }
    ],
    "sg:phone":"+1 718 681 6680",
    "sg:postcode":"10456",
    "sg:province":"NY",
    "wof:name":"C-Town",
    "wof:placetype":"venue"
},
  "geometry": {"coordinates":[-73.903488,40.83481],"type":"Point"}
}