{
  "type": "Feature",
  "properties": {
    "addr:full":"7619 Roosevelt Ave Jackson Heights NY 11372",
    "addr:housenumber":"7619",
    "addr:postcode":"11372",
    "addr:street":"Roosevelt Ave",
    "iso:country":"US",
    "sg:address":"7619 Roosevelt Ave",
    "sg:city":"Jackson Heights",
    "sg:classifiers":[
        {
            "category":"Recreation",
            "subcategory":"Dance Hall",
            "type":"Entertainment"
        }
    ],
    "sg:phone":"+1 718 457 3939",
    "sg:postcode":"11372",
    "sg:province":"NY",
    "sg:tags":[
        "club"
    ],
    "sg:website":"www.clubatlantisnyc.com/",
    "wof:name":"Atlantis 2010",
    "wof:placetype":"venue"
},
  "geometry": {"coordinates":[-73.889403,40.747057],"type":"Point"}
}