{
  "type": "Feature",
  "properties": {
    "addr:full":"1301 43rd St Brooklyn NY 11219",
    "addr:housenumber":"1301",
    "addr:postcode":"11219",
    "addr:street":"43Rd St",
    "iso:country":"US",
    "sg:address":"1301 43rd St",
    "sg:city":"Brooklyn",
    "sg:classifiers":[
        {
            "category":"Personal",
            "type":"Services"
        }
    ],
    "sg:phone":"+1 718 435 6041",
    "sg:postcode":"11219",
    "sg:province":"NY",
    "sg:tags":[
        "sewing",
        "alteration"
    ],
    "wof:name":"European Expert Tailoring",
    "wof:placetype":"venue"
},
  "geometry": {"coordinates":[-73.98840300000001,40.638401],"type":"Point"}
}