{
  "type": "Feature",
  "properties": {
    "iso:country":"US",
    "sg:address":"486 Sunrise Hwy",
    "sg:city":"Babylon",
    "sg:classifiers":[
        {
            "category":"Building & Trades",
            "subcategory":"Plumbing",
            "type":"Services"
        }
    ],
    "sg:phone":"+1 631 422 0212",
    "sg:postcode":"11704",
    "sg:province":"NY",
    "sg:tags":[
        "mechanical",
        "contractor"
    ],
    "wof:name":"Expert Mechanical Contracting",
    "wof:placetype":"venue"
},
  "geometry": {"coordinates":[-73.354697,40.713325],"type":"Point"}
}