{
  "type": "Feature",
  "properties": {
    "iso:country":"US",
    "sg:address":"41 Homer Ave",
    "sg:city":"Deer Park",
    "sg:classifiers":[
        {
            "category":"Social Services",
            "type":"Services"
        }
    ],
    "sg:phone":"+1 631 667 6665",
    "sg:postcode":"11729",
    "sg:province":"NY",
    "wof:name":"Deer Park Cmnty Organization",
    "wof:placetype":"venue"
},
  "geometry": {"coordinates":[-73.312642,40.770108],"type":"Point"}
}