{
  "type": "Feature",
  "properties": {
    "addr:full":"45 Kensico Dr Mount Kisco NY 10549",
    "addr:housenumber":"45",
    "addr:postcode":"10549",
    "addr:street":"Kensico Dr",
    "iso:country":"US",
    "sg:address":"45 Kensico Dr",
    "sg:city":"Mount Kisco",
    "sg:classifiers":[
        {
            "category":"Professional",
            "subcategory":"Lawyer & Legal Services",
            "type":"Services"
        }
    ],
    "sg:phone":"+1 914 666 8100",
    "sg:postcode":"10549",
    "sg:province":"NY",
    "wof:name":"Houslanger & Associates",
    "wof:placetype":"venue"
},
  "geometry": {"coordinates":[-73.723208,41.219536],"type":"Point"}
}