{
  "type": "Feature",
  "properties": {
    "addr:full":"780 Harry L Dr Johnson City NY 13790",
    "addr:housenumber":"780",
    "addr:postcode":"13790",
    "addr:street":"Harry L Dr",
    "iso:country":"US",
    "sg:address":"780 Harry L Dr",
    "sg:city":"Johnson City",
    "sg:classifiers":[
        {
            "category":"Social Services",
            "type":"Services"
        }
    ],
    "sg:phone":"+1   ",
    "sg:postcode":"13790",
    "sg:province":"NY",
    "sg:website":"www.calvarycommunity.cx",
    "wof:name":"Calvary Community Church",
    "wof:placetype":"venue"
},
  "geometry": {"coordinates":[-75.980513,42.121462],"type":"Point"}
}