{
  "type": "Feature",
  "properties": {
    "iso:country":"US",
    "sg:address":"13 King St",
    "sg:city":"Chappaqua",
    "sg:classifiers":[
        {
            "category":"Restaurant",
            "type":"Food & Drink"
        }
    ],
    "sg:phone":"+1 914 238 3858",
    "sg:postcode":"10514",
    "sg:province":"NY",
    "sg:tags":[
        "eating",
        "pizza"
    ],
    "wof:name":"Mario's Pizzeria",
    "wof:placetype":"venue"
},
  "geometry": {"coordinates":[-73.773003,41.159401],"type":"Point"}
}