{
  "type": "Feature",
  "properties": {
    "iso:country":"US",
    "sg:address":"23 W 73rd St",
    "sg:city":"Manhattan",
    "sg:classifiers":[
        {
            "category":"Sports & Exercise",
            "subcategory":"Gym",
            "type":"Entertainment"
        },
        {
            "category":"Arena",
            "subcategory":"Sports Club",
            "type":"Entertainment"
        }
    ],
    "sg:phone":"+1 212 496 6300",
    "sg:postcode":"10023",
    "sg:province":"NY",
    "sg:website":"www.mysportsclubs.com/regions/NY...",
    "wof:name":"New York Sports Club",
    "wof:placetype":"venue"
},
  "geometry": {"coordinates":[-73.976741,40.777422],"type":"Point"}
}