{
  "type": "Feature",
  "properties": {
    "addr:full":"247 Mather St Syracuse NY 13203",
    "addr:housenumber":"247",
    "addr:postcode":"13203",
    "addr:street":"Mather St",
    "iso:country":"US",
    "sg:address":"247 Mather St",
    "sg:city":"Syracuse",
    "sg:classifiers":[
        {
            "category":"Professional",
            "subcategory":"Secretarial Services",
            "type":"Services"
        },
        {
            "category":"Professional",
            "subcategory":"Employment Agencies",
            "type":"Services"
        }
    ],
    "sg:phone":"+1 315 423 0742",
    "sg:postcode":"13203",
    "sg:province":"NY",
    "sg:tags":[
        "typing"
    ],
    "wof:name":"Cny Typing & Medical Transcription",
    "wof:placetype":"venue"
},
  "geometry": {"coordinates":[-76.128907,43.056598],"type":"Point"}
}