{
  "type": "Feature",
  "properties": {
    "iso:country":"US",
    "sg:address":"95 Sailly Ave",
    "sg:city":"Plattsburgh",
    "sg:classifiers":[
        {
            "category":"Manufacturing",
            "subcategory":"Metals",
            "type":"Manufacturing & Wholesale Goods"
        },
        {
            "category":"Building & Trades",
            "subcategory":"Plumbing",
            "type":"Services"
        }
    ],
    "sg:phone":"+1 518 561 4930",
    "sg:postcode":"12901",
    "sg:province":"NY",
    "sg:tags":[
        "ventilating",
        "fabricator",
        "sheet",
        "heating",
        "contractor"
    ],
    "wof:name":"Plattsburgh Sheet Metal Inc",
    "wof:placetype":"venue"
},
  "geometry": {"coordinates":[-73.450884,44.704301],"type":"Point"}
}