{
  "type": "Feature",
  "properties": {
    "addr:full":"15 W 49th St New York NY 10020",
    "addr:housenumber":"15",
    "addr:postcode":"10020",
    "addr:street":"W 49Th St",
    "iso:country":"US",
    "sg:address":"15 W 49th St",
    "sg:city":"New York",
    "sg:classifiers":[
        {
            "category":"Museum",
            "type":"Entertainment"
        }
    ],
    "sg:phone":"+1 212 332 1360",
    "sg:postcode":"10020",
    "sg:province":"NY",
    "wof:name":"City of New York",
    "wof:placetype":"venue"
},
  "geometry": {"coordinates":[-73.977743,40.758112],"type":"Point"}
}