{
  "type": "Feature",
  "properties": {
    "addr:full":"1927 Kings Hwy Brooklyn NY 11229",
    "addr:housenumber":"1927",
    "addr:postcode":"11229",
    "addr:street":"Kings Hwy",
    "iso:country":"US",
    "sg:address":"1927 Kings Hwy",
    "sg:city":"Brooklyn",
    "sg:classifiers":[
        {
            "category":"Health Services",
            "subcategory":"Doctor",
            "type":"Services"
        }
    ],
    "sg:phone":"+1 718 382 1439",
    "sg:postcode":"11229",
    "sg:province":"NY",
    "sg:tags":[
        "clinic"
    ],
    "wof:name":"Pennsylvania Medical",
    "wof:placetype":"venue"
},
  "geometry": {"coordinates":[-73.953806,40.610619],"type":"Point"}
}