{
  "type": "Feature",
  "properties": {
    "addr:full":"1029 W Park Ave Long Beach NY 11561",
    "addr:housenumber":"1029",
    "addr:postcode":"11561",
    "addr:street":"W Park Ave",
    "iso:country":"US",
    "sg:address":"1029 W Park Ave",
    "sg:city":"Long Beach",
    "sg:classifiers":[
        {
            "category":"Building & Trades",
            "subcategory":"Construction",
            "type":"Services"
        }
    ],
    "sg:phone":"+1 516 889 7405",
    "sg:postcode":"11561",
    "sg:province":"NY",
    "sg:tags":[
        "roofing",
        "contractor"
    ],
    "wof:name":"South Shore Roofing & Siding",
    "wof:placetype":"venue"
},
  "geometry": {"coordinates":[-73.696369,40.588578],"type":"Point"}
}