{
  "type": "Feature",
  "properties": {
    "addr:full":"100 California Ave Albany NY 12205",
    "addr:housenumber":"100",
    "addr:postcode":"12205",
    "addr:street":"California Ave",
    "iso:country":"US",
    "sg:address":"100 California Ave",
    "sg:city":"Albany",
    "sg:classifiers":[
        {
            "category":"Education",
            "subcategory":"School",
            "type":"Public Place"
        }
    ],
    "sg:phone":"+1 518 459 2157",
    "sg:postcode":"12205",
    "sg:province":"NY",
    "sg:website":"www.southcolonieschools.org",
    "wof:name":"Roessleville Elementary School",
    "wof:placetype":"venue"
},
  "geometry": {"coordinates":[-73.814031,42.703303],"type":"Point"}
}