{
  "type": "Feature",
  "properties": {
    "addr:full":"201 E 118th Street New York NY 10035",
    "addr:housenumber":"201",
    "addr:postcode":"10035",
    "addr:street":"E 118Th Street",
    "iso:country":"US",
    "sg:address":"201 E 118th Street",
    "sg:city":"New York",
    "sg:classifiers":[
        {
            "category":"Restaurant",
            "type":"Food & Drink"
        }
    ],
    "sg:phone":"+1 212 876 8838",
    "sg:postcode":"10035",
    "sg:province":"NY",
    "wof:name":"La Pachanga Restaurant",
    "wof:placetype":"venue"
},
  "geometry": {"coordinates":[-73.939047,40.79927],"type":"Point"}
}