{
  "type": "Feature",
  "properties": {
    "iso:country":"US",
    "sg:address":"217 Westchester Ave",
    "sg:city":"Port Chester",
    "sg:classifiers":[
        {
            "category":"Food & Beverages",
            "subcategory":"Bakery",
            "type":"Retail Goods"
        }
    ],
    "sg:phone":"+1 914 937 5305",
    "sg:postcode":"10573",
    "sg:province":"NY",
    "sg:tags":[
        "baker"
    ],
    "wof:name":"LA Flor De Jalisco Bakery",
    "wof:placetype":"venue"
},
  "geometry": {"coordinates":[-73.666804,41.002387],"type":"Point"}
}