{
  "type": "Feature",
  "properties": {
    "iso:country":"US",
    "sg:address":"2353 86th St",
    "sg:city":"Brooklyn",
    "sg:classifiers":[
        {
            "category":"Personal",
            "subcategory":"Beauty Salon",
            "type":"Services"
        }
    ],
    "sg:phone":"+1 718 266 5918",
    "sg:postcode":"11214",
    "sg:province":"NY",
    "wof:name":"A & G Beauty Salon Inc",
    "wof:placetype":"venue"
},
  "geometry": {"coordinates":[-73.990568,40.600132],"type":"Point"}
}