{
  "type": "Feature",
  "properties": {
    "addr:full":"214 West Ave Albion NY 14411",
    "addr:housenumber":"214",
    "addr:postcode":"14411",
    "addr:street":"West Ave",
    "iso:country":"US",
    "sg:address":"214 West Ave",
    "sg:city":"Albion",
    "sg:classifiers":[
        {
            "category":"Retail",
            "subcategory":"Auto Repair",
            "type":"Services"
        }
    ],
    "sg:phone":"+1 585 589 1048",
    "sg:postcode":"14411",
    "sg:province":"NY",
    "sg:tags":[
        "repairing",
        "automotive",
        "brake",
        "automobile"
    ],
    "sg:website":"http://www.monro.com",
    "wof:name":"Monro Muffler Brake & Service",
    "wof:placetype":"venue"
},
  "geometry": {"coordinates":[-78.199412,43.240891],"type":"Point"}
}