{
  "type": "Feature",
  "properties": {
    "addr:full":"1 Lark St Albany NY 12210",
    "addr:housenumber":"1",
    "addr:postcode":"12210",
    "addr:street":"Lark St",
    "iso:country":"US",
    "sg:address":"1 Lark St",
    "sg:city":"Albany",
    "sg:classifiers":[
        {
            "category":"Building & Trades",
            "subcategory":"Plumbing",
            "type":"Services"
        }
    ],
    "sg:phone":"+1 518 436 8881",
    "sg:postcode":"12210",
    "sg:province":"NY",
    "sg:tags":[
        "mechanical",
        "contractor"
    ],
    "wof:name":"Ny State Council Of Mech",
    "wof:placetype":"venue"
},
  "geometry": {"coordinates":[-73.754949,42.663872],"type":"Point"}
}