{
  "type": "Feature",
  "properties": {
    "addr:full":"9015 Queens Blvd Ste 2053 Elmhurst NY 11373",
    "addr:housenumber":"9015",
    "addr:postcode":"11373",
    "addr:street":"Queens Blvd Ste 2053",
    "iso:country":"US",
    "sg:address":"9015 Queens Blvd Ste 2053",
    "sg:city":"Elmhurst",
    "sg:classifiers":[
        {
            "category":"Shopping",
            "subcategory":"Clothing, Apparel, & Fashions",
            "type":"Retail Goods"
        }
    ],
    "sg:phone":"+1 718 271 2323",
    "sg:postcode":"11373",
    "sg:province":"NY",
    "sg:tags":[
        "accessory",
        "clothing",
        "women's"
    ],
    "wof:name":"bebe",
    "wof:placetype":"venue"
},
  "geometry": {"coordinates":[-73.87123699999999,40.734121],"type":"Point"}
}