{
  "type": "Feature",
  "properties": {
    "addr:full":"104 Adams St Ithaca NY 14850",
    "addr:housenumber":"104",
    "addr:postcode":"14850",
    "addr:street":"Adams St",
    "iso:country":"US",
    "sg:address":"104 Adams St",
    "sg:city":"Ithaca",
    "sg:classifiers":[
        {
            "category":"Shopping",
            "subcategory":"Musical Instruments",
            "type":"Retail Goods"
        }
    ],
    "sg:phone":"+1 607 272 8262",
    "sg:postcode":"14850",
    "sg:province":"NY",
    "sg:tags":[
        "music",
        "dealer"
    ],
    "sg:website":"www.hickeys.com",
    "wof:name":"Hickey's Music Ctr",
    "wof:placetype":"venue"
},
  "geometry": {"coordinates":[-76.500871,42.449628],"type":"Point"}
}