{
  "type": "Feature",
  "properties": {
    "addr:full":"1360 Richland Blvd Bay Shore NY 11706",
    "addr:housenumber":"1360",
    "addr:postcode":"11706",
    "addr:street":"Richland Blvd",
    "iso:country":"US",
    "sg:address":"1360 Richland Blvd",
    "sg:city":"Bay Shore",
    "sg:classifiers":[
        {
            "category":"Freight",
            "type":"Transportation"
        }
    ],
    "sg:phone":"+1   ",
    "sg:postcode":"11706",
    "sg:province":"NY",
    "sg:tags":[
        "operator",
        "trucking"
    ],
    "wof:name":"Buckhide Trucking",
    "wof:placetype":"venue"
},
  "geometry": {"coordinates":[-73.26885299999999,40.737752],"type":"Point"}
}