{
  "type": "Feature",
  "properties": {
    "addr:full":"9605 Crooked Hill Rd Clayville NY 13322",
    "addr:housenumber":"9605",
    "addr:postcode":"13322",
    "addr:street":"Crooked Hill Rd",
    "iso:country":"US",
    "sg:address":"9605 Crooked Hill Rd",
    "sg:city":"Clayville",
    "sg:classifiers":[
        {
            "category":"Personal",
            "subcategory":"Beauty Salon",
            "type":"Services"
        }
    ],
    "sg:phone":"+1 315 839 5147",
    "sg:postcode":"13322",
    "sg:province":"NY",
    "sg:tags":[
        "manicuring"
    ],
    "wof:name":"Heavenly Hands Nail Salon",
    "wof:placetype":"venue"
},
  "geometry": {"coordinates":[-75.254424,42.962934],"type":"Point"}
}