{
  "type": "Feature",
  "properties": {
    "iso:country":"US",
    "sg:address":"20 State Hwy 304",
    "sg:city":"Nanuet",
    "sg:classifiers":[
        {
            "category":"Autos & Motor Vehicles",
            "subcategory":"Fuel & Gas Station",
            "type":"Retail Goods"
        }
    ],
    "sg:phone":"+1 845 623 7091",
    "sg:postcode":"10954",
    "sg:province":"NY",
    "sg:tags":[
        "oil"
    ],
    "wof:name":"Route 304 Auto Svc",
    "wof:placetype":"venue"
},
  "geometry": {"coordinates":[-73.9979,41.09809],"type":"Point"}
}