{
  "type": "Feature",
  "properties": {
    "iso:country":"US",
    "sg:address":"24 Main St",
    "sg:city":"Chester",
    "sg:classifiers":[
        {
            "category":"Insurance",
            "subcategory":"Insurance Agent",
            "type":"Services"
        }
    ],
    "sg:phone":"+1 845 469 6750",
    "sg:postcode":"10918",
    "sg:province":"NY",
    "sg:tags":[
        "consulting",
        "management"
    ],
    "wof:name":"Bridgeside Insurance Agency",
    "wof:placetype":"venue"
},
  "geometry": {"coordinates":[-74.271894,41.362391],"type":"Point"}
}