{
  "type": "Feature",
  "properties": {
    "addr:full":"887 Grapevine Ct Central Valley NY 10917",
    "addr:housenumber":"887",
    "addr:postcode":"10917",
    "addr:street":"Grapevine Ct",
    "iso:country":"US",
    "sg:address":"887 Grapevine Ct",
    "sg:city":"Central Valley",
    "sg:classifiers":[
        {
            "category":"Shopping",
            "subcategory":"Shoes",
            "type":"Retail Goods"
        }
    ],
    "sg:phone":"+1 845 928 2639",
    "sg:postcode":"10917",
    "sg:province":"NY",
    "sg:tags":[
        "store"
    ],
    "wof:name":"Skechers",
    "wof:placetype":"venue"
},
  "geometry": {"coordinates":[-74.12471499999999,41.317689],"type":"Point"}
}