{
  "type": "Feature",
  "properties": {
    "addr:full":"50 Hudson Ave Brooklyn NY 11201",
    "addr:housenumber":"50",
    "addr:postcode":"11201",
    "addr:street":"Hudson Ave",
    "iso:country":"US",
    "sg:address":"50 Hudson Ave",
    "sg:city":"Brooklyn",
    "sg:classifiers":[
        {
            "category":"Real Estate",
            "subcategory":"Real Estate Agent",
            "type":"Services"
        }
    ],
    "sg:phone":"+1 718 722 7600",
    "sg:postcode":"11201",
    "sg:province":"NY",
    "wof:name":"Alpine Warehouse Corp",
    "wof:placetype":"venue"
},
  "geometry": {"coordinates":[-73.981182,40.703131],"type":"Point"}
}