{
  "type": "Feature",
  "properties": {
    "addr:full":"850 State Route 50 Burnt Hills NY 12027",
    "addr:housenumber":"850",
    "addr:postcode":"12027",
    "addr:street":"State Route 50 Burnt",
    "iso:country":"US",
    "sg:address":"850 State Route 50",
    "sg:city":"Burnt Hills",
    "sg:classifiers":[
        {
            "category":"Real Estate",
            "subcategory":"Real Estate Services",
            "type":"Services"
        }
    ],
    "sg:phone":"+1 518 399 1881",
    "sg:postcode":"12027",
    "sg:province":"NY",
    "sg:tags":[
        "home",
        "inspector"
    ],
    "wof:name":"Schrader and Company Inc",
    "wof:placetype":"venue"
},
  "geometry": {"coordinates":[-73.892799,42.916401],"type":"Point"}
}