{
  "type": "Feature",
  "properties": {
    "addr:full":"117 Ralph Ave Bellmore NY 11710",
    "addr:housenumber":"117",
    "addr:postcode":"11710",
    "addr:street":"Ralph Ave",
    "iso:country":"US",
    "sg:address":"117 Ralph Ave",
    "sg:city":"Bellmore",
    "sg:classifiers":[
        {
            "category":"Building & Trades",
            "subcategory":"Plumbing",
            "type":"Services"
        }
    ],
    "sg:phone":"+1 516 781 7039",
    "sg:postcode":"11710",
    "sg:province":"NY",
    "sg:tags":[
        "contractor"
    ],
    "wof:name":"Dfh Mechanical",
    "wof:placetype":"venue"
},
  "geometry": {"coordinates":[-73.533692,40.685307],"type":"Point"}
}