{
  "type": "Feature",
  "properties": {
    "addr:full":"7907 13th Ave Brooklyn NY 11228",
    "addr:housenumber":"7907",
    "addr:postcode":"11228",
    "addr:street":"13Th Ave",
    "iso:country":"US",
    "sg:address":"7907 13th Ave",
    "sg:city":"Brooklyn",
    "sg:classifiers":[
        {
            "category":"Food & Beverages",
            "subcategory":"Groceries & Convenience Stores",
            "type":"Retail Goods"
        }
    ],
    "sg:phone":"+1 718 331 0050",
    "sg:postcode":"11228",
    "sg:province":"NY",
    "sg:tags":[
        "grocer"
    ],
    "wof:name":"C Town Supermarket",
    "wof:placetype":"venue"
},
  "geometry": {"coordinates":[-74.009821,40.617836],"type":"Point"}
}