{
  "type": "Feature",
  "properties": {
    "iso:country":"US",
    "sg:address":"400 State St",
    "sg:city":"Hudson",
    "sg:classifiers":[
        {
            "category":"Education",
            "subcategory":"School",
            "type":"Public Place"
        }
    ],
    "sg:phone":"+1 518 828 9495",
    "sg:postcode":"12534",
    "sg:province":"NY",
    "sg:tags":[
        "educational",
        "administrative"
    ],
    "wof:name":"John L Edwards Elementary Schl",
    "wof:placetype":"venue"
},
  "geometry": {"coordinates":[-73.78684,42.252216],"type":"Point"}
}