{
  "type": "Feature",
  "properties": {
    "iso:country":"US",
    "sg:address":"655 Garden Ave",
    "sg:city":"Mt Vernon",
    "sg:classifiers":[
        {
            "category":"Recreation",
            "type":"Entertainment"
        }
    ],
    "sg:phone":"+1 914 668 1165",
    "sg:postcode":"10550",
    "sg:province":"NY",
    "sg:tags":[
        "range",
        "baseball",
        "batting"
    ],
    "wof:name":"Home Run City",
    "wof:placetype":"venue"
},
  "geometry": {"coordinates":[-73.818941,40.899524],"type":"Point"}
}