{
  "type": "Feature",
  "properties": {
    "addr:full":"5662 Main St Buffalo NY 14221",
    "addr:housenumber":"5662",
    "addr:postcode":"14221",
    "addr:street":"Main St",
    "iso:country":"US",
    "sg:address":"5662 Main St",
    "sg:city":"Buffalo",
    "sg:classifiers":[
        {
            "category":"Professional",
            "subcategory":"Lawyer & Legal Services",
            "type":"Services"
        }
    ],
    "sg:phone":"+1 716 634 3924",
    "sg:postcode":"14221",
    "sg:province":"NY",
    "sg:tags":[
        "attorney"
    ],
    "wof:name":"E Joseph Peprone",
    "wof:placetype":"venue"
},
  "geometry": {"coordinates":[-78.742486,42.963269],"type":"Point"}
}