{
  "type": "Feature",
  "properties": {
    "iso:country":"US",
    "sg:address":"63-14 Broadway",
    "sg:city":"Woodside",
    "sg:classifiers":[
        {
            "category":"Restaurant",
            "type":"Food & Drink"
        }
    ],
    "sg:phone":"+1 718 205 1616",
    "sg:postcode":"11377",
    "sg:province":"NY",
    "sg:tags":[
        "american",
        "latin"
    ],
    "sg:website":"elrinconcitowoodside.com",
    "wof:name":"El Rinconcito de Mama",
    "wof:placetype":"venue"
},
  "geometry": {"coordinates":[-73.89910500000001,40.749952],"type":"Point"}
}