{
  "type": "Feature",
  "properties": {
    "addr:full":"756 Salmon Creek Rd Brockport NY 14420",
    "addr:housenumber":"756",
    "addr:postcode":"14420",
    "addr:street":"Salmon Creek Rd",
    "iso:country":"US",
    "sg:address":"756 Salmon Creek Rd",
    "sg:city":"Brockport",
    "sg:classifiers":[
        {
            "category":"Home & Garden",
            "subcategory":"Building Materials",
            "type":"Retail Goods"
        }
    ],
    "sg:phone":"+1   ",
    "sg:postcode":"14420",
    "sg:province":"NY",
    "wof:name":"Otto Garage Doors",
    "wof:placetype":"venue"
},
  "geometry": {"coordinates":[-77.902429,43.166418],"type":"Point"}
}