{
  "type": "Feature",
  "properties": {
    "addr:full":"1149 Webster Ave Bronx NY 10456",
    "addr:housenumber":"1149",
    "addr:postcode":"10456",
    "addr:street":"Webster Ave",
    "iso:country":"US",
    "sg:address":"1149 Webster Ave",
    "sg:city":"Bronx",
    "sg:classifiers":[
        {
            "category":"Wholesale",
            "subcategory":"Auto Parts",
            "type":"Manufacturing & Wholesale Goods"
        }
    ],
    "sg:phone":"+1 718 992 5050",
    "sg:postcode":"10456",
    "sg:province":"NY",
    "sg:tags":[
        "automobile",
        "supply"
    ],
    "wof:name":"Veteran Auto Parts Co",
    "wof:placetype":"venue"
},
  "geometry": {"coordinates":[-73.911123,40.829443],"type":"Point"}
}