{
  "type": "Feature",
  "properties": {
    "iso:country":"US",
    "sg:address":"165 Sears St",
    "sg:city":"Buffalo",
    "sg:classifiers":[
        {
            "category":"Real Estate",
            "subcategory":"Real Estate Operator",
            "type":"Services"
        }
    ],
    "sg:phone":"+1 716 896 9302",
    "sg:postcode":"14212",
    "sg:province":"NY",
    "sg:tags":[
        "building",
        "nonresidential"
    ],
    "wof:name":"Corpus Christi Church Hall",
    "wof:placetype":"venue"
},
  "geometry": {"coordinates":[-78.835256,42.89],"type":"Point"}
}