{
  "type": "Feature",
  "properties": {
    "addr:full":"1 N Galleria Dr Middletown NY 10941",
    "addr:housenumber":"1",
    "addr:postcode":"10941",
    "addr:street":"N Galleria Dr",
    "iso:country":"US",
    "sg:address":"1 N Galleria Dr",
    "sg:city":"Middletown",
    "sg:classifiers":[
        {
            "category":"Sports & Exercise",
            "subcategory":"Gym",
            "type":"Entertainment"
        }
    ],
    "sg:phone":"+1 845 692 4009",
    "sg:postcode":"10941",
    "sg:province":"NY",
    "sg:tags":[
        "trainer"
    ],
    "wof:name":"Gymboree Store",
    "wof:placetype":"venue"
},
  "geometry": {"coordinates":[-74.36489899999999,41.4538],"type":"Point"}
}