{
  "type": "Feature",
  "properties": {
    "addr:full":"12 Eunice Pl Staten Island NY 10303",
    "addr:housenumber":"12",
    "addr:postcode":"10303",
    "addr:street":"Eunice Pl",
    "iso:country":"US",
    "sg:address":"12 Eunice Pl",
    "sg:city":"Staten Island",
    "sg:classifiers":[
        {
            "category":"Organizations",
            "subcategory":"Religious Organization",
            "type":"Services"
        }
    ],
    "sg:phone":"+1 718 442 2023",
    "sg:postcode":"10303",
    "sg:province":"NY",
    "sg:tags":[
        "clergy"
    ],
    "wof:name":"Emily B Hall",
    "wof:placetype":"venue"
},
  "geometry": {"coordinates":[-74.152721,40.624635],"type":"Point"}
}