{
  "type": "Feature",
  "properties": {
    "iso:country":"US",
    "sg:address":"74 Revolutionary Rd",
    "sg:city":"Ossining",
    "sg:classifiers":[
        {
            "category":"Organizations",
            "subcategory":"Membership Organization",
            "type":"Services"
        }
    ],
    "sg:phone":"+1 914 944 3446",
    "sg:postcode":"10562",
    "sg:province":"NY",
    "sg:tags":[
        "protection",
        "animal"
    ],
    "wof:name":"Animal Welfare Trust",
    "wof:placetype":"venue"
},
  "geometry": {"coordinates":[-73.86382999999999,41.14476],"type":"Point"}
}