{
  "type": "Feature",
  "properties": {
    "iso:country":"US",
    "sg:address":"126 Waverly Pl",
    "sg:city":"New York",
    "sg:classifiers":[
        {
            "category":"Professional",
            "subcategory":"Lawyer & Legal Services",
            "type":"Services"
        }
    ],
    "sg:phone":"+1 212 475 3655",
    "sg:postcode":"10011",
    "sg:province":"NY",
    "wof:name":"Moon & Ikeda",
    "wof:placetype":"venue"
},
  "geometry": {"coordinates":[-73.999211,40.732286],"type":"Point"}
}