{
  "type": "Feature",
  "properties": {
    "addr:full":"3459 Broadway New York NY 10031",
    "addr:housenumber":"3459",
    "addr:postcode":"10031",
    "addr:street":"Broadway",
    "iso:country":"US",
    "sg:address":"3459 Broadway",
    "sg:city":"New York",
    "sg:classifiers":[
        {
            "category":"Travel",
            "subcategory":"Travel Agent",
            "type":"Entertainment"
        }
    ],
    "sg:phone":"+1 212 507 1353",
    "sg:postcode":"10031",
    "sg:province":"NY",
    "sg:tags":[
        "agency",
        "bureau"
    ],
    "wof:name":"Money Travel Svc Inc",
    "wof:placetype":"venue"
},
  "geometry": {"coordinates":[-73.95276200000001,40.823263],"type":"Point"}
}