{
  "type": "Feature",
  "properties": {
    "addr:full":"2929 Upper Mountain Rd Sanborn NY 14132",
    "addr:housenumber":"2929",
    "addr:postcode":"14132",
    "addr:street":"Upper Mountain Rd",
    "iso:country":"US",
    "sg:address":"2929 Upper Mountain Rd",
    "sg:city":"Sanborn",
    "sg:classifiers":[
        {
            "category":"Real Estate",
            "subcategory":"Real Estate Agent",
            "type":"Services"
        }
    ],
    "sg:phone":"+1 716 731 5575",
    "sg:postcode":"14132",
    "sg:province":"NY",
    "wof:name":"Peter Curione",
    "wof:placetype":"venue"
},
  "geometry": {"coordinates":[-78.885867,43.168179],"type":"Point"}
}