{
  "type": "Feature",
  "properties": {
    "iso:country":"US",
    "sg:address":"1500 Front St",
    "sg:city":"Yorktown Heights",
    "sg:classifiers":[
        {
            "category":"Professional",
            "subcategory":"Lawyer & Legal Services",
            "type":"Services"
        }
    ],
    "sg:phone":"+1   ",
    "sg:postcode":"10598",
    "sg:province":"NY",
    "wof:name":"Derevlany Michael",
    "wof:placetype":"venue"
},
  "geometry": {"coordinates":[-73.77725,41.264462],"type":"Point"}
}