{
  "type": "Feature",
  "properties": {
    "iso:country":"US",
    "sg:address":"282 Main St",
    "sg:city":"Eastchester",
    "sg:classifiers":[
        {
            "category":"Manufacturing",
            "subcategory":"Wood Products",
            "type":"Manufacturing & Wholesale Goods"
        }
    ],
    "sg:phone":"+1   ",
    "sg:postcode":"10709",
    "sg:province":"NY",
    "sg:tags":[
        "merchandise",
        "mfg"
    ],
    "sg:website":"www.claudegallery.com",
    "wof:name":"Claude Gallery Frames",
    "wof:placetype":"venue"
},
  "geometry": {"coordinates":[-73.81655000000001,40.952393],"type":"Point"}
}