{
  "type": "Feature",
  "properties": {
    "addr:full":"1476 Union Tpke New Hyde Park NY 11040",
    "addr:housenumber":"1476",
    "addr:postcode":"11040",
    "addr:street":"Union Tpke;Hyde Park",
    "iso:country":"US",
    "sg:address":"1476 Union Tpke",
    "sg:city":"New Hyde Park",
    "sg:classifiers":[
        {
            "category":"Shopping",
            "subcategory":"Hobbies, Toys, & Games",
            "type":"Retail Goods"
        }
    ],
    "sg:phone":"+1   ",
    "sg:postcode":"11040",
    "sg:province":"NY",
    "sg:tags":[
        "item"
    ],
    "wof:name":"KB Toys",
    "wof:placetype":"venue"
},
  "geometry": {"coordinates":[-73.693952,40.753952],"type":"Point"}
}