{
  "type": "Feature",
  "properties": {
    "addr:full":"1375 Mayflower Ave Bronx NY 10461",
    "addr:housenumber":"1375",
    "addr:postcode":"10461",
    "addr:street":"Mayflower Ave",
    "iso:country":"US",
    "sg:address":"1375 Mayflower Ave",
    "sg:city":"Bronx",
    "sg:classifiers":[
        {
            "category":"Retail",
            "subcategory":"Self-service Laundry",
            "type":"Services"
        }
    ],
    "sg:phone":"+1   ",
    "sg:postcode":"10461",
    "sg:province":"NY",
    "sg:tags":[
        "coin"
    ],
    "wof:name":"S & P Laundromat Inc",
    "wof:placetype":"venue"
},
  "geometry": {"coordinates":[-73.833152,40.838562],"type":"Point"}
}