{
  "type": "Feature",
  "properties": {
    "iso:country":"US",
    "sg:address":"795 Hampton Rd",
    "sg:city":"Woodmere",
    "sg:classifiers":[
        {
            "category":"Professional",
            "subcategory":"Art Services",
            "type":"Services"
        }
    ],
    "sg:phone":"+1 516 295 1501",
    "sg:postcode":"11598",
    "sg:province":"NY",
    "sg:tags":[
        "photographer"
    ],
    "wof:name":"Renoir Photography",
    "wof:placetype":"venue"
},
  "geometry": {"coordinates":[-73.716983,40.629287],"type":"Point"}
}