{
  "type": "Feature",
  "properties": {
    "addr:full":"115 Orchard Ave Owego NY 13827",
    "addr:housenumber":"115",
    "addr:postcode":"13827",
    "addr:street":"Orchard Ave",
    "iso:country":"US",
    "sg:address":"115 Orchard Ave",
    "sg:city":"Owego",
    "sg:classifiers":[
        {
            "category":"Communications",
            "subcategory":"Film & Video Production",
            "type":"Services"
        }
    ],
    "sg:phone":"+1 607 687 6409",
    "sg:postcode":"13827",
    "sg:province":"NY",
    "sg:tags":[
        "editing",
        "tape"
    ],
    "wof:name":"Versatile Video",
    "wof:placetype":"venue"
},
  "geometry": {"coordinates":[-76.255263,42.095039],"type":"Point"}
}