{
  "type": "Feature",
  "properties": {
    "iso:country":"US",
    "sg:address":"141 Croyden Ln",
    "sg:city":"Syracuse",
    "sg:classifiers":[
        {
            "category":"Shopping",
            "subcategory":"Clothing, Apparel, & Fashions",
            "type":"Retail Goods"
        }
    ],
    "sg:phone":"+1 315 251 2530",
    "sg:postcode":"13224",
    "sg:province":"NY",
    "sg:tags":[
        "clothing",
        "store"
    ],
    "wof:name":"Pcx",
    "wof:placetype":"venue"
},
  "geometry": {"coordinates":[-76.108133,43.029309],"type":"Point"}
}