{
  "type": "Feature",
  "properties": {
    "addr:full":"3619 Walden Ave Lancaster NY 14086",
    "addr:housenumber":"3619",
    "addr:postcode":"14086",
    "addr:street":"Walden Ave",
    "iso:country":"US",
    "sg:address":"3619 Walden Ave",
    "sg:city":"Lancaster",
    "sg:classifiers":[
        {
            "category":"Bars & Pubs",
            "type":"Food & Drink"
        }
    ],
    "sg:phone":"+1   ",
    "sg:postcode":"14086",
    "sg:province":"NY",
    "sg:tags":[
        "drinking"
    ],
    "wof:name":"Dillingers Tavern Inc",
    "wof:placetype":"venue"
},
  "geometry": {"coordinates":[-78.670418,42.916032],"type":"Point"}
}