{
  "type": "Feature",
  "properties": {
    "addr:full":"57 W Oakdale St Bay Shore NY 11706",
    "addr:housenumber":"57",
    "addr:postcode":"11706",
    "addr:street":"W Oakdale St",
    "iso:country":"US",
    "sg:address":"57 W Oakdale St",
    "sg:city":"Bay Shore",
    "sg:classifiers":[
        {
            "category":"Building & Trades",
            "subcategory":"Plumbing",
            "type":"Services"
        }
    ],
    "sg:phone":"+1 631 667 2267",
    "sg:postcode":"11706",
    "sg:province":"NY",
    "sg:tags":[
        "septic"
    ],
    "wof:name":"Campy's Cesspool Svc",
    "wof:placetype":"venue"
},
  "geometry": {"coordinates":[-73.30234400000001,40.743326],"type":"Point"}
}