{
  "type": "Feature",
  "properties": {
    "addr:full":"115 Broadway New York NY 10006",
    "addr:housenumber":"115",
    "addr:postcode":"10006",
    "addr:street":"Broadway",
    "iso:country":"US",
    "sg:address":"115 Broadway",
    "sg:city":"New York",
    "sg:classifiers":[
        {
            "category":"Shopping",
            "subcategory":"Clothing, Apparel, & Fashions",
            "type":"Retail Goods"
        }
    ],
    "sg:phone":"+1 212 233 0675",
    "sg:postcode":"10006",
    "sg:province":"NY",
    "sg:tags":[
        "shoe",
        "store"
    ],
    "sg:website":"www.menswearhouse.com",
    "wof:name":"The Men's Wearhouse",
    "wof:placetype":"venue"
},
  "geometry": {"coordinates":[-74.01112000000001,40.708459],"type":"Point"}
}