{
  "type": "Feature",
  "properties": {
    "addr:full":"174 Hudson St Fl 6 New York NY 10013",
    "addr:housenumber":"174;6",
    "addr:postcode":"10013",
    "addr:street":"Hudson St",
    "iso:country":"US",
    "sg:address":"174 Hudson St Fl 6",
    "sg:city":"New York",
    "sg:classifiers":[
        {
            "category":"Shopping",
            "subcategory":"Clothing, Apparel, & Fashions",
            "type":"Retail Goods"
        }
    ],
    "sg:phone":"+1 212 965 0274",
    "sg:postcode":"10013",
    "sg:province":"NY",
    "sg:tags":[
        "clothing",
        "women's"
    ],
    "wof:name":"Cole Systems",
    "wof:placetype":"venue"
},
  "geometry": {"coordinates":[-74.96742399999999,40.722373],"type":"Point"}
}