{
  "type": "Feature",
  "properties": {
    "addr:full":"744 Berriman St Brooklyn NY 11208",
    "addr:housenumber":"744",
    "addr:postcode":"11208",
    "addr:street":"Berriman St",
    "iso:country":"US",
    "sg:address":"744 Berriman St",
    "sg:city":"Brooklyn",
    "sg:classifiers":[
        {
            "category":"Manufacturing",
            "subcategory":"Signs",
            "type":"Manufacturing & Wholesale Goods"
        }
    ],
    "sg:phone":"+1   ",
    "sg:postcode":"11208",
    "sg:province":"NY",
    "sg:tags":[
        "purchase",
        "point",
        "f",
        "metal",
        "advertising",
        "display"
    ],
    "wof:name":"Brand Manufacturing Corp",
    "wof:placetype":"venue"
},
  "geometry": {"coordinates":[-73.873287,40.661443],"type":"Point"}
}