{
  "type": "Feature",
  "properties": {
    "addr:full":"575 Madison Avenue New York NY 10022",
    "addr:housenumber":"575",
    "addr:postcode":"10022",
    "addr:street":"Madison Avenue",
    "iso:country":"US",
    "sg:address":"575 Madison Avenue",
    "sg:city":"New York",
    "sg:classifiers":[
        {
            "category":"Food & Beverages",
            "subcategory":"Liquor & Beverages",
            "type":"Retail Goods"
        }
    ],
    "sg:phone":"+1 212 605 0478",
    "sg:postcode":"10022",
    "sg:province":"NY",
    "sg:tags":[
        "beer",
        "spirit",
        "wine"
    ],
    "wof:name":"Yarden",
    "wof:placetype":"venue"
},
  "geometry": {"coordinates":[-73.97261399999999,40.761806],"type":"Point"}
}