{
  "type": "Feature",
  "properties": {
    "iso:country":"US",
    "sg:address":"98 S Fulton Ave",
    "sg:city":"Mt Vernon",
    "sg:classifiers":[
        {
            "category":"Manufacturing",
            "subcategory":"Printing",
            "type":"Manufacturing & Wholesale Goods"
        }
    ],
    "sg:phone":"+1 914 668 4067",
    "sg:postcode":"10550",
    "sg:province":"NY",
    "sg:tags":[
        "publisher"
    ],
    "wof:name":"Focal Vision Publishing",
    "wof:placetype":"venue"
},
  "geometry": {"coordinates":[-73.828768,40.910493],"type":"Point"}
}