{
  "type": "Feature",
  "properties": {
    "iso:country":"US",
    "sg:address":"420 State Hwy 59",
    "sg:city":"Airmont",
    "sg:classifiers":[
        {
            "category":"Professional",
            "subcategory":"Lawyer & Legal Services",
            "type":"Services"
        }
    ],
    "sg:phone":"+1 845 425 4200",
    "sg:postcode":"10952",
    "sg:province":"NY",
    "sg:tags":[
        "attorney"
    ],
    "wof:name":"Jack Schloss Law Office",
    "wof:placetype":"venue"
},
  "geometry": {"coordinates":[-74.087338,41.10953],"type":"Point"}
}