{
  "type": "Feature",
  "properties": {
    "addr:full":"12 Roe Ave Albany NY 12205",
    "addr:housenumber":"12",
    "addr:postcode":"12205",
    "addr:street":"Roe Ave",
    "iso:country":"US",
    "sg:address":"12 Roe Ave",
    "sg:city":"Albany",
    "sg:classifiers":[
        {
            "category":"Wholesale",
            "subcategory":"Machinery & Supplies",
            "type":"Manufacturing & Wholesale Goods"
        }
    ],
    "sg:phone":"+1 518 438 6171",
    "sg:postcode":"12205",
    "sg:province":"NY",
    "sg:tags":[
        "contractor"
    ],
    "wof:name":"J C Smith Inc",
    "wof:placetype":"venue"
},
  "geometry": {"coordinates":[-73.800459,42.701348],"type":"Point"}
}