{
  "type": "Feature",
  "properties": {
    "addr:full":"69 E Jericho Tpke Mineola NY 11501",
    "addr:housenumber":"69",
    "addr:postcode":"11501",
    "addr:street":"E Jericho Tpke",
    "iso:country":"US",
    "sg:address":"69 E Jericho Tpke",
    "sg:city":"Mineola",
    "sg:classifiers":[
        {
            "category":"Real Estate",
            "subcategory":"Real Estate Services",
            "type":"Services"
        }
    ],
    "sg:phone":"+1 516 248 4840",
    "sg:postcode":"11501",
    "sg:province":"NY",
    "sg:tags":[
        "abstract",
        "title"
    ],
    "wof:name":"Boundary Title Services",
    "wof:placetype":"venue"
},
  "geometry": {"coordinates":[-73.632694,40.751831],"type":"Point"}
}