{
  "type": "Feature",
  "properties": {
    "addr:full":"690 E 147th St Bronx NY 10455",
    "addr:housenumber":"690",
    "addr:postcode":"10455",
    "addr:street":"E 147Th St",
    "iso:country":"US",
    "sg:address":"690 E 147th St",
    "sg:city":"Bronx",
    "sg:classifiers":[
        {
            "category":"Education",
            "subcategory":"College",
            "type":"Public Place"
        }
    ],
    "sg:phone":"+1 718 401 8196",
    "sg:postcode":"10455",
    "sg:province":"NY",
    "sg:tags":[
        "academic",
        "school"
    ],
    "wof:name":"University Consultation Ctr",
    "wof:placetype":"venue"
},
  "geometry": {"coordinates":[-73.90970900000001,40.811734],"type":"Point"}
}