{
  "type": "Feature",
  "properties": {
    "iso:country":"US",
    "sg:address":"2537 6th Ave",
    "sg:city":"East Meadow",
    "sg:classifiers":[
        {
            "category":"Wholesale",
            "subcategory":"Stationery",
            "type":"Manufacturing & Wholesale Goods"
        },
        {
            "category":"Retail",
            "subcategory":"Repair Shop",
            "type":"Services"
        }
    ],
    "sg:phone":"+1 516 826 6084",
    "sg:postcode":"11554",
    "sg:province":"NY",
    "sg:tags":[
        "pencil",
        "pen",
        "parts"
    ],
    "wof:name":"Miran's Pen Repair",
    "wof:placetype":"venue"
},
  "geometry": {"coordinates":[-73.541681,40.716098],"type":"Point"}
}