{
  "type": "Feature",
  "properties": {
    "addr:full":"2320 86th St Brooklyn NY 11214",
    "addr:housenumber":"2320",
    "addr:postcode":"11214",
    "addr:street":"86Th St",
    "iso:country":"US",
    "sg:address":"2320 86th St",
    "sg:city":"Brooklyn",
    "sg:classifiers":[
        {
            "category":"Cinema",
            "subcategory":"Movie Rental",
            "type":"Entertainment"
        }
    ],
    "sg:phone":"+1 718 265 2348",
    "sg:postcode":"11214",
    "sg:province":"NY",
    "sg:tags":[
        "video",
        "game",
        "leasing"
    ],
    "wof:name":"S & L Intl Video",
    "wof:placetype":"venue"
},
  "geometry": {"coordinates":[-73.991283,40.600373],"type":"Point"}
}