{
  "type": "Feature",
  "properties": {
    "addr:full":"8278 Oswego Rd Liverpool NY 13090",
    "addr:housenumber":"8278",
    "addr:postcode":"13090",
    "addr:street":"Oswego Rd",
    "iso:country":"US",
    "sg:address":"8278 Oswego Rd",
    "sg:city":"Liverpool",
    "sg:classifiers":[
        {
            "category":"Organizations",
            "subcategory":"Religious Organization",
            "type":"Services"
        }
    ],
    "sg:phone":"+1 315 622 2077",
    "sg:postcode":"13090",
    "sg:province":"NY",
    "sg:website":"www.kingofkings-ny.org",
    "wof:name":"King Of Kings Lutheran Church",
    "wof:placetype":"venue"
},
  "geometry": {"coordinates":[-76.251138,43.175748],"type":"Point"}
}