{
  "type": "Feature",
  "properties": {
    "addr:full":"1597 Manatuck Blvd Bay Shore NY 11706",
    "addr:housenumber":"1597",
    "addr:postcode":"11706",
    "addr:street":"Manatuck Blvd",
    "iso:country":"US",
    "sg:address":"1597 Manatuck Blvd",
    "sg:city":"Bay Shore",
    "sg:classifiers":[
        {
            "category":"Deli",
            "type":"Food & Drink"
        }
    ],
    "sg:phone":"+1 631 666 7674",
    "sg:postcode":"11706",
    "sg:province":"NY",
    "wof:name":"Britt Deli Inc",
    "wof:placetype":"venue"
},
  "geometry": {"coordinates":[-73.270798,40.755501],"type":"Point"}
}