{
  "type": "Feature",
  "properties": {
    "iso:country":"US",
    "sg:address":"1440 54th St",
    "sg:city":"Brooklyn",
    "sg:classifiers":[
        {
            "category":"Wholesale",
            "subcategory":"Machinery & Supplies",
            "type":"Manufacturing & Wholesale Goods"
        }
    ],
    "sg:phone":"+1 718 851 8188",
    "sg:postcode":"11219",
    "sg:province":"NY",
    "sg:tags":[
        "industrial"
    ],
    "wof:name":"M Rashba Associates",
    "wof:placetype":"venue"
},
  "geometry": {"coordinates":[-73.99135200000001,40.630049],"type":"Point"}
}