{
  "type": "Feature",
  "properties": {
    "iso:country":"US",
    "sg:address":"1 S 1st St",
    "sg:city":"Fulton",
    "sg:classifiers":[
        {
            "category":"Banks & Credit Unions",
            "subcategory":"Bank",
            "type":"Services"
        }
    ],
    "sg:phone":"+1 315 592 4234",
    "sg:postcode":"13069",
    "sg:province":"NY",
    "wof:name":"Hsbc Bank USA",
    "wof:placetype":"venue"
},
  "geometry": {"coordinates":[-76.41771300000001,43.324486],"type":"Point"}
}