{
  "type": "Feature",
  "properties": {
    "iso:country":"US",
    "sg:address":"142 Standart Ave",
    "sg:city":"Auburn",
    "sg:classifiers":[
        {
            "category":"Home & Garden",
            "subcategory":"Household Appliances",
            "type":"Retail Goods"
        }
    ],
    "sg:phone":"+1 315 253 7691",
    "sg:postcode":"13021",
    "sg:province":"NY",
    "wof:name":"Balcom's Appliance Repair",
    "wof:placetype":"venue"
},
  "geometry": {"coordinates":[-76.55220799999999,42.944276],"type":"Point"}
}