{
  "type": "Feature",
  "properties": {
    "iso:country":"US",
    "sg:address":"1483 Wyoming Ave",
    "sg:city":"Schenectady",
    "sg:classifiers":[
        {
            "category":"Manufacturing",
            "subcategory":"Retail Goods",
            "type":"Manufacturing & Wholesale Goods"
        }
    ],
    "sg:phone":"+1   ",
    "sg:postcode":"12308",
    "sg:province":"NY",
    "sg:tags":[
        "product",
        "mfg"
    ],
    "wof:name":"Mid Ocean Industries",
    "wof:placetype":"venue"
},
  "geometry": {"coordinates":[-73.905528,42.821823],"type":"Point"}
}