{
  "type": "Feature",
  "properties": {
    "addr:full":"2 Fisher Ave Tuckahoe NY 10707",
    "addr:housenumber":"2",
    "addr:postcode":"10707",
    "addr:street":"Fisher Ave",
    "iso:country":"US",
    "sg:address":"2 Fisher Ave",
    "sg:city":"Tuckahoe",
    "sg:classifiers":[
        {
            "category":"Personal",
            "subcategory":"Beauty Salon",
            "type":"Services"
        }
    ],
    "sg:phone":"+1 914 961 5150",
    "sg:postcode":"10707",
    "sg:province":"NY",
    "sg:tags":[
        "manicuring"
    ],
    "wof:name":"Ran Nails Inc",
    "wof:placetype":"venue"
},
  "geometry": {"coordinates":[-73.819463,40.958464],"type":"Point"}
}