{
  "type": "Feature",
  "properties": {
    "iso:country":"US",
    "sg:address":"26 Pheasant Ln",
    "sg:city":"Staten Island",
    "sg:classifiers":[
        {
            "category":"Professional",
            "subcategory":"Management & Consulting",
            "type":"Services"
        }
    ],
    "sg:phone":"+1 718 984 6498",
    "sg:postcode":"10309",
    "sg:province":"NY",
    "wof:name":"Refund Systems Management",
    "wof:placetype":"venue"
},
  "geometry": {"coordinates":[-74.22240600000001,40.53221],"type":"Point"}
}