{
  "type": "Feature",
  "properties": {
    "addr:full":"125 Virgil Ave Buffalo NY 14216",
    "addr:housenumber":"125",
    "addr:postcode":"14216",
    "addr:street":"Virgil Ave",
    "iso:country":"US",
    "sg:address":"125 Virgil Ave",
    "sg:city":"Buffalo",
    "sg:classifiers":[
        {
            "category":"Manufacturing",
            "subcategory":"Tobacco Products",
            "type":"Manufacturing & Wholesale Goods"
        }
    ],
    "sg:phone":"+1 716 877 2983",
    "sg:postcode":"14216",
    "sg:province":"NY",
    "sg:tags":[
        "cigarette",
        "cigar"
    ],
    "sg:website":"www.altcigs.com",
    "wof:name":"Alternative Cigarettes Inc",
    "wof:placetype":"venue"
},
  "geometry": {"coordinates":[-78.864476,42.947877],"type":"Point"}
}