{
  "type": "Feature",
  "properties": {
    "iso:country":"US",
    "sg:address":"1280 Montauk Hwy",
    "sg:city":"Mastic",
    "sg:classifiers":[
        {
            "category":"Manufacturing",
            "subcategory":"Metals",
            "type":"Manufacturing & Wholesale Goods"
        }
    ],
    "sg:phone":"+1 631 395 1652",
    "sg:postcode":"11950",
    "sg:province":"NY",
    "sg:tags":[
        "burner"
    ],
    "wof:name":"Quality Fuel & Heating",
    "wof:placetype":"venue"
},
  "geometry": {"coordinates":[-72.84943,40.804676],"type":"Point"}
}