{
  "type": "Feature",
  "properties": {
    "iso:country":"US",
    "sg:address":"11 Addison St",
    "sg:city":"Larchmont",
    "sg:classifiers":[
        {
            "category":"Manufacturing",
            "subcategory":"Printing",
            "type":"Manufacturing & Wholesale Goods"
        }
    ],
    "sg:phone":"+1 914 834 7774",
    "sg:postcode":"10538",
    "sg:province":"NY",
    "sg:tags":[
        "equipment",
        "loose",
        "leaf"
    ],
    "wof:name":"Custom Looseleaf Co",
    "wof:placetype":"venue"
},
  "geometry": {"coordinates":[-73.75261500000001,40.929564],"type":"Point"}
}