{
  "type": "Feature",
  "properties": {
    "iso:country":"US",
    "sg:address":"1241 Mamaroneck Ave",
    "sg:city":"White Plains",
    "sg:classifiers":[
        {
            "category":"Health Services",
            "subcategory":"Doctor",
            "type":"Services"
        }
    ],
    "sg:phone":"+1 914 421 1500",
    "sg:postcode":"10605",
    "sg:province":"NY",
    "sg:tags":[
        "clinic"
    ],
    "wof:name":"Center For Nutritional Medicin",
    "wof:placetype":"venue"
},
  "geometry": {"coordinates":[-73.74600700000001,40.991352],"type":"Point"}
}