{
  "type": "Feature",
  "properties": {
    "addr:full":"166 N Portage St Westfield NY 14787",
    "addr:housenumber":"166",
    "addr:postcode":"14787",
    "addr:street":"N Portage St",
    "iso:country":"US",
    "sg:address":"166 N Portage St",
    "sg:city":"Westfield",
    "sg:classifiers":[
        {
            "category":"Building & Trades",
            "subcategory":"Construction",
            "type":"Services"
        }
    ],
    "sg:phone":"+1 716 326 3850",
    "sg:postcode":"14787",
    "sg:province":"NY",
    "sg:tags":[
        "general",
        "contractor"
    ],
    "wof:name":"Raynor Construction",
    "wof:placetype":"venue"
},
  "geometry": {"coordinates":[-79.586354,42.33076],"type":"Point"}
}