{
  "type": "Feature",
  "properties": {
    "addr:full":"7935 N Pembroke Rd East Pembroke NY 14020",
    "addr:housenumber":"7935",
    "addr:postcode":"14020",
    "addr:street":"N Pembroke Rd",
    "iso:country":"US",
    "sg:address":"7935 N Pembroke Rd",
    "sg:city":"East Pembroke",
    "sg:classifiers":[
        {
            "category":"Building & Trades",
            "subcategory":"Construction",
            "type":"Services"
        }
    ],
    "sg:phone":"+1 585 762 8454",
    "sg:postcode":"14020",
    "sg:province":"NY",
    "sg:tags":[
        "excavating",
        "contractor"
    ],
    "wof:name":"Dibble Bros",
    "wof:placetype":"venue"
},
  "geometry": {"coordinates":[-78.336029,43.028892],"type":"Point"}
}