{
  "type": "Feature",
  "properties": {
    "addr:full":"438 Utica Ave Brooklyn NY 11213",
    "addr:housenumber":"438",
    "addr:postcode":"11213",
    "addr:street":"Utica Ave",
    "iso:country":"US",
    "sg:address":"438 Utica Ave",
    "sg:city":"Brooklyn",
    "sg:classifiers":[
        {
            "category":"Shopping",
            "subcategory":"Clothing, Apparel, & Fashions",
            "type":"Retail Goods"
        }
    ],
    "sg:phone":"+1 718 363 7251",
    "sg:postcode":"11213",
    "sg:province":"NY",
    "sg:website":"www.danicestores.com",
    "wof:name":"Danice Stores",
    "wof:placetype":"venue"
},
  "geometry": {"coordinates":[-73.931539,40.664342],"type":"Point"}
}