{
  "type": "Feature",
  "properties": {
    "addr:full":"810 Midwood St Brooklyn NY 11203",
    "addr:housenumber":"810",
    "addr:postcode":"11203",
    "addr:street":"Midwood St",
    "iso:country":"US",
    "sg:address":"810 Midwood St",
    "sg:city":"Brooklyn",
    "sg:classifiers":[
        {
            "category":"Professional",
            "type":"Services"
        }
    ],
    "sg:phone":"+1 718 467 2783",
    "sg:postcode":"11203",
    "sg:province":"NY",
    "sg:tags":[
        "establishment"
    ],
    "wof:name":"Harry Siaover Housing Co",
    "wof:placetype":"venue"
},
  "geometry": {"coordinates":[-73.934316,40.661148],"type":"Point"}
}