{
  "type": "Feature",
  "properties": {
    "addr:full":"100 Corporate Woods Rochester NY 14623",
    "addr:housenumber":"100",
    "addr:postcode":"14623",
    "addr:street":"Corporate Woods",
    "iso:country":"US",
    "sg:address":"100 Corporate Woods",
    "sg:city":"Rochester",
    "sg:classifiers":[
        {
            "category":"Professional",
            "subcategory":"Employment Agencies",
            "type":"Services"
        }
    ],
    "sg:phone":"+1 877 237 4790",
    "sg:postcode":"14623",
    "sg:province":"NY",
    "sg:tags":[
        "consultant",
        "temporary",
        "opportunity",
        "contractor"
    ],
    "sg:website":"http://www-aerotek-com.netsolads.com/?LEC-6UM982376821&_nsag=33207",
    "wof:name":"Aerotek",
    "wof:placetype":"venue"
},
  "geometry": {"coordinates":[-77.621875,43.108452],"type":"Point"}
}