{
  "type": "Feature",
  "properties": {
    "addr:full":"117 MacDougal Street New York NY 10012",
    "addr:housenumber":"117",
    "addr:postcode":"10012",
    "addr:street":"Macdougal Street",
    "iso:country":"US",
    "sg:address":"117 MacDougal Street",
    "sg:city":"New York",
    "sg:classifiers":[
        {
            "category":"Restaurant",
            "type":"Food & Drink"
        }
    ],
    "sg:phone":"+1 212 777 8596",
    "sg:postcode":"10012",
    "sg:province":"NY",
    "wof:name":"Levantine-Olive Tree Cafe",
    "wof:placetype":"venue"
},
  "geometry": {"coordinates":[-74.00038600000001,40.730131],"type":"Point"}
}