{
  "type": "Feature",
  "properties": {
    "addr:full":"6154 Hawkins Corners Rd Lee Center NY 13363",
    "addr:housenumber":"6154",
    "addr:postcode":"13363",
    "addr:street":"Hawkins Corners Rd",
    "iso:country":"US",
    "sg:address":"6154 Hawkins Corners Rd",
    "sg:city":"Lee Center",
    "sg:classifiers":[
        {
            "category":"Building & Trades",
            "subcategory":"Construction",
            "type":"Services"
        }
    ],
    "sg:phone":"+1 315 337 7703",
    "sg:postcode":"13363",
    "sg:province":"NY",
    "sg:tags":[
        "general",
        "contractor"
    ],
    "wof:name":"Charles Kotary Jr Construction",
    "wof:placetype":"venue"
},
  "geometry": {"coordinates":[-75.479546,43.284793],"type":"Point"}
}