{
  "type": "Feature",
  "properties": {
    "addr:full":"431 Union School Rd Middletown NY 10941",
    "addr:housenumber":"431",
    "addr:postcode":"10941",
    "addr:street":"Union School Rd",
    "iso:country":"US",
    "sg:address":"431 Union School Rd",
    "sg:city":"Middletown",
    "sg:classifiers":[
        {
            "category":"Shopping",
            "subcategory":"Crafts & Fabrics",
            "type":"Retail Goods"
        }
    ],
    "sg:phone":"+1   ",
    "sg:postcode":"10941",
    "sg:province":"NY",
    "sg:tags":[
        "sewing"
    ],
    "wof:name":"Stitches",
    "wof:placetype":"venue"
},
  "geometry": {"coordinates":[-74.31743899999999,41.526485],"type":"Point"}
}