{
  "type": "Feature",
  "properties": {
    "addr:full":"160 W 71st Street New York NY 10023",
    "addr:housenumber":"160",
    "addr:postcode":"10023",
    "addr:street":"W 71St Street",
    "iso:country":"US",
    "sg:address":"160 W 71st Street",
    "sg:city":"New York",
    "sg:classifiers":[
        {
            "category":"Building & Trades",
            "subcategory":"Plumbing",
            "type":"Services"
        }
    ],
    "sg:phone":"+1 212 874 1274",
    "sg:postcode":"10023",
    "sg:province":"NY",
    "wof:name":"Aljer Plumbing Heating",
    "wof:placetype":"venue"
},
  "geometry": {"coordinates":[-73.98105099999999,40.777418],"type":"Point"}
}