{
  "type": "Feature",
  "properties": {
    "addr:full":"207 Airport Plaza Blvd Farmingdale NY 11735",
    "addr:housenumber":"207",
    "addr:postcode":"11735",
    "addr:street":"Airport Plaza Blvd",
    "iso:country":"US",
    "sg:address":"207 Airport Plaza Blvd",
    "sg:city":"Farmingdale",
    "sg:classifiers":[
        {
            "category":"Home & Garden",
            "subcategory":"Furniture",
            "type":"Retail Goods"
        }
    ],
    "sg:phone":"+1 631 843 0391",
    "sg:postcode":"11735",
    "sg:province":"NY",
    "sg:tags":[
        "mattress"
    ],
    "sg:website":"www.sleepys.com",
    "wof:name":"Sleepy's",
    "wof:placetype":"venue"
},
  "geometry": {"coordinates":[-73.415643,40.738025],"type":"Point"}
}