{
  "type": "Feature",
  "properties": {
    "addr:full":"23 E 22 St New York NY 10010",
    "addr:housenumber":"23;22",
    "addr:postcode":"10010",
    "addr:street":"E",
    "iso:country":"US",
    "sg:address":"23 E 22 St",
    "sg:city":"New York",
    "sg:classifiers":[
        {
            "category":"Real Estate",
            "subcategory":"Real Estate Operator",
            "type":"Services"
        }
    ],
    "sg:phone":"+1 516 569 1525",
    "sg:postcode":"10010",
    "sg:province":"NY",
    "sg:tags":[
        "building"
    ],
    "wof:name":"204 West 43rd St Corp",
    "wof:placetype":"venue"
},
  "geometry": {"coordinates":[-73.98724799999999,40.73983],"type":"Point"}
}