{
  "type": "Feature",
  "properties": {
    "iso:country":"US",
    "sg:address":"3201 Grand Concourse",
    "sg:city":"Bronx",
    "sg:classifiers":[
        {
            "category":"Health Services",
            "subcategory":"Doctor",
            "type":"Services"
        }
    ],
    "sg:phone":"+1 718 367 7400",
    "sg:postcode":"10468",
    "sg:province":"NY",
    "sg:tags":[
        "physician",
        "surgeon"
    ],
    "wof:name":"Selig Eisenberg MD",
    "wof:placetype":"venue"
},
  "geometry": {"coordinates":[-73.885668,40.876578],"type":"Point"}
}