{
  "type": "Feature",
  "properties": {
    "addr:full":"169 Hawthorne Rd Kings Park NY 11754",
    "addr:housenumber":"169",
    "addr:postcode":"11754",
    "addr:street":"Hawthorne Rd",
    "iso:country":"US",
    "sg:address":"169 Hawthorne Rd",
    "sg:city":"Kings Park",
    "sg:classifiers":[
        {
            "category":"Banks & Credit Unions",
            "subcategory":"Bank",
            "type":"Services"
        }
    ],
    "sg:phone":"+1 631 360 1798",
    "sg:postcode":"11754",
    "sg:province":"NY",
    "sg:tags":[
        "broker",
        "mortgage"
    ],
    "wof:name":"LI Funding Corp",
    "wof:placetype":"venue"
},
  "geometry": {"coordinates":[-73.223567,40.889255],"type":"Point"}
}