{
  "type": "Feature",
  "properties": {
    "iso:country":"US",
    "sg:address":"241 W 26th St",
    "sg:city":"New York",
    "sg:classifiers":[
        {
            "category":"Parking",
            "type":"Transportation"
        }
    ],
    "sg:phone":"+1   ",
    "sg:postcode":"10001",
    "sg:province":"NY",
    "sg:tags":[
        "garage"
    ],
    "wof:name":"241 Parking Corp",
    "wof:placetype":"venue"
},
  "geometry": {"coordinates":[-73.996184,40.74678],"type":"Point"}
}