{
  "type": "Feature",
  "properties": {
    "addr:full":"419 W 145th St New York NY 10031",
    "addr:housenumber":"419",
    "addr:postcode":"10031",
    "addr:street":"W 145Th St",
    "iso:country":"US",
    "sg:address":"419 W 145th St",
    "sg:city":"New York",
    "sg:classifiers":[
        {
            "category":"Government",
            "subcategory":"Office",
            "type":"Public Place"
        }
    ],
    "sg:phone":"+1 212 690 0410",
    "sg:postcode":"10031",
    "sg:province":"NY",
    "sg:tags":[
        "village"
    ],
    "wof:name":"New York City Juvenile Justice",
    "wof:placetype":"venue"
},
  "geometry": {"coordinates":[-73.945891,40.824553],"type":"Point"}
}