{
  "type": "Feature",
  "properties": {
    "iso:country":"US",
    "sg:address":"333 N Bedford Rd",
    "sg:city":"Mt Kisco",
    "sg:classifiers":[
        {
            "category":"Restaurant",
            "type":"Food & Drink"
        },
        {
            "category":"Recreation",
            "subcategory":"Go Karts",
            "type":"Entertainment"
        }
    ],
    "sg:phone":"+1 914 241 3131",
    "sg:postcode":"10549",
    "sg:province":"NY",
    "sg:website":"www.gpny.com",
    "wof:name":"Grand Prix New York",
    "wof:placetype":"venue"
},
  "geometry": {"coordinates":[-73.71730700000001,41.219227],"type":"Point"}
}