{
  "type": "Feature",
  "properties": {
    "addr:full":"1200 Waters Place Bronx NY 10461",
    "addr:housenumber":"1200",
    "addr:postcode":"10461",
    "addr:street":"Waters Place",
    "iso:country":"US",
    "sg:address":"1200 Waters Place",
    "sg:city":"Bronx",
    "sg:classifiers":[
        {
            "category":"Shopping",
            "subcategory":"Books",
            "type":"Retail Goods"
        }
    ],
    "sg:phone":"+1 718 863 9318",
    "sg:postcode":"10461",
    "sg:province":"NY",
    "sg:tags":[
        "bookstore"
    ],
    "wof:name":"Mercy College Bookstore",
    "wof:placetype":"venue"
},
  "geometry": {"coordinates":[-73.838374,40.842658],"type":"Point"}
}