{
  "type": "Feature",
  "properties": {
    "iso:country":"US",
    "sg:address":"18 Oakdale Pl",
    "sg:city":"Massapequa Park",
    "sg:classifiers":[
        {
            "category":"Shopping",
            "subcategory":"Gifts & Souvenirs",
            "type":"Retail Goods"
        }
    ],
    "sg:phone":"+1   ",
    "sg:postcode":"11762",
    "sg:province":"NY",
    "wof:name":"Unbearably You Country Crafts",
    "wof:placetype":"venue"
},
  "geometry": {"coordinates":[-73.435209,40.68924],"type":"Point"}
}