{
  "type": "Feature",
  "properties": {
    "addr:full":"2140 Matthews Ave Bronx NY 10462",
    "addr:housenumber":"2140",
    "addr:postcode":"10462",
    "addr:street":"Matthews Ave",
    "iso:country":"US",
    "sg:address":"2140 Matthews Ave",
    "sg:city":"Bronx",
    "sg:classifiers":[
        {
            "category":"Organizations",
            "subcategory":"Religious Organization",
            "type":"Services"
        }
    ],
    "sg:phone":"+1 718 319 1559",
    "sg:postcode":"10462",
    "sg:province":"NY",
    "sg:tags":[
        "clergy"
    ],
    "wof:name":"Rubin Sculem",
    "wof:placetype":"venue"
},
  "geometry": {"coordinates":[-73.862797,40.856198],"type":"Point"}
}