{
  "type": "Feature",
  "properties": {
    "iso:country":"US",
    "sg:address":"764 Seneca Ave",
    "sg:city":"Ridgewood",
    "sg:classifiers":[
        {
            "category":"Education",
            "subcategory":"Special Training",
            "type":"Public Place"
        }
    ],
    "sg:phone":"+1 718 417 6226",
    "sg:postcode":"11385",
    "sg:province":"NY",
    "sg:tags":[
        "school",
        "driving"
    ],
    "wof:name":"Robco Driving School",
    "wof:placetype":"venue"
},
  "geometry": {"coordinates":[-73.9067,40.702099],"type":"Point"}
}