{
  "type": "Feature",
  "properties": {
    "iso:country":"US",
    "sg:address":"519 Chauncey Ln",
    "sg:city":"Lawrence",
    "sg:classifiers":[
        {
            "category":"Banks & Credit Unions",
            "subcategory":"Financial Services",
            "type":"Services"
        }
    ],
    "sg:phone":"+1 516 374 4001",
    "sg:postcode":"11559",
    "sg:province":"NY",
    "sg:tags":[
        "company",
        "holding"
    ],
    "wof:name":"Frontier Holdings LLC",
    "wof:placetype":"venue"
},
  "geometry": {"coordinates":[-73.712446,40.616121],"type":"Point"}
}