{
  "type": "Feature",
  "properties": {
    "addr:full":"2115 Richmond Ter Staten Island NY 10302",
    "addr:housenumber":"2115",
    "addr:postcode":"10302",
    "addr:street":"Richmond Ter",
    "iso:country":"US",
    "sg:address":"2115 Richmond Ter",
    "sg:city":"Staten Island",
    "sg:classifiers":[
        {
            "category":"Retail",
            "subcategory":"Auto Repair",
            "type":"Services"
        }
    ],
    "sg:phone":"+1 718 727 6663",
    "sg:postcode":"10302",
    "sg:province":"NY",
    "sg:tags":[
        "automobile",
        "used"
    ],
    "wof:name":"D T V Imported Cars Ltd",
    "wof:placetype":"venue"
},
  "geometry": {"coordinates":[-74.133809,40.640183],"type":"Point"}
}