{
  "type": "Feature",
  "properties": {
    "addr:full":"448 E 134th St Bronx NY 10454",
    "addr:housenumber":"448",
    "addr:postcode":"10454",
    "addr:street":"E 134Th St",
    "iso:country":"US",
    "sg:address":"448 E 134th St",
    "sg:city":"Bronx",
    "sg:classifiers":[
        {
            "category":"Freight",
            "type":"Transportation"
        }
    ],
    "sg:phone":"+1 718 665 6960",
    "sg:postcode":"10454",
    "sg:province":"NY",
    "sg:tags":[
        "mover"
    ],
    "wof:name":"M & S Movers Packers Storage",
    "wof:placetype":"venue"
},
  "geometry": {"coordinates":[-73.92474300000001,40.806554],"type":"Point"}
}