{
  "type": "Feature",
  "properties": {
    "iso:country":"US",
    "sg:address":"418 Church Ave",
    "sg:city":"Brooklyn",
    "sg:classifiers":[
        {
            "category":"Shopping",
            "subcategory":"Optical Goods",
            "type":"Retail Goods"
        }
    ],
    "sg:phone":"+1 718 851 5040",
    "sg:postcode":"11218",
    "sg:province":"NY",
    "wof:name":"City Optical Eyewear",
    "wof:placetype":"venue"
},
  "geometry": {"coordinates":[-73.975782,40.644239],"type":"Point"}
}