{
  "type": "Feature",
  "properties": {
    "addr:full":"16 Orchard Dr Northport NY 11768",
    "addr:housenumber":"16",
    "addr:postcode":"11768",
    "addr:street":"Orchard Dr",
    "iso:country":"US",
    "sg:address":"16 Orchard Dr",
    "sg:city":"Northport",
    "sg:classifiers":[
        {
            "category":"Building & Trades",
            "subcategory":"Construction",
            "type":"Services"
        }
    ],
    "sg:phone":"+1 631 544 1056",
    "sg:postcode":"11768",
    "sg:province":"NY",
    "sg:tags":[
        "contractor"
    ],
    "wof:name":"Seery J Construction",
    "wof:placetype":"venue"
},
  "geometry": {"coordinates":[-73.287598,40.885899],"type":"Point"}
}