{
  "type": "Feature",
  "properties": {
    "addr:full":"515 Madison Avenue Lbby New York NY 10022",
    "addr:housenumber":"515",
    "addr:postcode":"10022",
    "addr:street":"Madison Avenue",
    "iso:country":"US",
    "sg:address":"515 Madison Avenue Lbby",
    "sg:city":"New York",
    "sg:classifiers":[
        {
            "category":"Shopping",
            "subcategory":"Beauty & Cosmetics",
            "type":"Retail Goods"
        }
    ],
    "sg:phone":"+1 212 644 1911",
    "sg:postcode":"10022",
    "sg:province":"NY",
    "sg:tags":[
        "supply"
    ],
    "wof:name":"Cosmetics Plus Madison Ave Ltd",
    "wof:placetype":"venue"
},
  "geometry": {"coordinates":[-73.97410499999999,40.759856],"type":"Point"}
}