{
  "type": "Feature",
  "properties": {
    "iso:country":"US",
    "sg:address":"26 Fowler St",
    "sg:city":"Port Jervis",
    "sg:classifiers":[
        {
            "category":"Insurance",
            "subcategory":"Insurance Agent",
            "type":"Services"
        }
    ],
    "sg:phone":"+1 845 856 3666",
    "sg:postcode":"12771",
    "sg:province":"NY",
    "wof:name":"Primerica Financial Svc",
    "wof:placetype":"venue"
},
  "geometry": {"coordinates":[-74.68933,41.373196],"type":"Point"}
}