{
  "type": "Feature",
  "properties": {
    "addr:full":"61 Ludington Ct Carmel NY 10512",
    "addr:housenumber":"61",
    "addr:postcode":"10512",
    "addr:street":"Ludington Ct",
    "iso:country":"US",
    "sg:address":"61 Ludington Ct",
    "sg:city":"Carmel",
    "sg:classifiers":[
        {
            "category":"Home & Garden",
            "subcategory":"Garden Supply",
            "type":"Retail Goods"
        }
    ],
    "sg:phone":"+1 845 225 7766",
    "sg:postcode":"10512",
    "sg:province":"NY",
    "sg:tags":[
        "nurseryman",
        "nursery"
    ],
    "wof:name":"Kent Countryside Nursery",
    "wof:placetype":"venue"
},
  "geometry": {"coordinates":[-73.65493600000001,41.471571],"type":"Point"}
}