{
  "type": "Feature",
  "properties": {
    "addr:full":"1048 Getman Rd Alden NY 14004",
    "addr:housenumber":"1048",
    "addr:postcode":"14004",
    "addr:street":"Getman Rd",
    "iso:country":"US",
    "sg:address":"1048 Getman Rd",
    "sg:city":"Alden",
    "sg:classifiers":[
        {
            "category":"Autos & Motor Vehicles",
            "subcategory":"Auto Supplies",
            "type":"Retail Goods"
        }
    ],
    "sg:phone":"+1   ",
    "sg:postcode":"14004",
    "sg:province":"NY",
    "sg:tags":[
        "sporting"
    ],
    "wof:name":"Arcese Enterprise",
    "wof:placetype":"venue"
},
  "geometry": {"coordinates":[-78.411007,42.862478],"type":"Point"}
}