{
  "type": "Feature",
  "properties": {
    "addr:full":"1300 Burke Ave Bronx NY 10469",
    "addr:housenumber":"1300",
    "addr:postcode":"10469",
    "addr:street":"Burke Ave",
    "iso:country":"US",
    "sg:address":"1300 Burke Ave",
    "sg:city":"Bronx",
    "sg:classifiers":[
        {
            "category":"Personal",
            "subcategory":"Beauty Salon",
            "type":"Services"
        }
    ],
    "sg:phone":"+1 718 547 4648",
    "sg:postcode":"10469",
    "sg:province":"NY",
    "wof:name":"Just In Time Unisex Beauty",
    "wof:placetype":"venue"
},
  "geometry": {"coordinates":[-73.848597,40.871669],"type":"Point"}
}