{
  "type": "Feature",
  "properties": {
    "addr:full":"8416 Flatlands Ave Brooklyn NY 11236",
    "addr:housenumber":"8416",
    "addr:postcode":"11236",
    "addr:street":"Flatlands Ave",
    "iso:country":"US",
    "sg:address":"8416 Flatlands Ave",
    "sg:city":"Brooklyn",
    "sg:classifiers":[
        {
            "category":"Real Estate",
            "subcategory":"Real Estate Agent",
            "type":"Services"
        }
    ],
    "sg:phone":"+1 718 444 6350",
    "sg:postcode":"11236",
    "sg:province":"NY",
    "wof:name":"IGT Real Estate Holdings",
    "wof:placetype":"venue"
},
  "geometry": {"coordinates":[-73.909667,40.637736],"type":"Point"}
}