{
  "type": "Feature",
  "properties": {
    "addr:full":"200 Niagara St Tonawanda NY 14150",
    "addr:housenumber":"200",
    "addr:postcode":"14150",
    "addr:street":"Niagara St",
    "iso:country":"US",
    "sg:address":"200 Niagara St",
    "sg:city":"Tonawanda",
    "sg:classifiers":[
        {
            "category":"Government",
            "subcategory":"Office",
            "type":"Public Place"
        }
    ],
    "sg:phone":"+1 716 695 8637",
    "sg:postcode":"14150",
    "sg:province":"NY",
    "sg:tags":[
        "policy",
        "taxation",
        "finance",
        "monetary"
    ],
    "wof:name":"Treasurers Office",
    "wof:placetype":"venue"
},
  "geometry": {"coordinates":[-78.88624,43.018995],"type":"Point"}
}