{
  "type": "Feature",
  "properties": {
    "iso:country":"US",
    "sg:address":"5562 Bear Rd",
    "sg:city":"Syracuse",
    "sg:classifiers":[
        {
            "category":"Social Services",
            "type":"Services"
        }
    ],
    "sg:phone":"+1 315 458 6520",
    "sg:postcode":"13212",
    "sg:province":"NY",
    "wof:name":"Day Neesha's Care",
    "wof:placetype":"venue"
},
  "geometry": {"coordinates":[-76.133769,43.1444],"type":"Point"}
}