{
  "type": "Feature",
  "properties": {
    "addr:full":"268 Floral Pkwy Floral Park NY 11001",
    "addr:housenumber":"268",
    "addr:postcode":"11001",
    "addr:street":"Floral Pkwy",
    "iso:country":"US",
    "sg:address":"268 Floral Pkwy",
    "sg:city":"Floral Park",
    "sg:classifiers":[
        {
            "category":"Real Estate",
            "subcategory":"Real Estate Agent",
            "type":"Services"
        }
    ],
    "sg:phone":"+1 516 775 2285",
    "sg:postcode":"11001",
    "sg:province":"NY",
    "sg:tags":[
        "company",
        "realty"
    ],
    "wof:name":"Nirman Realty Co",
    "wof:placetype":"venue"
},
  "geometry": {"coordinates":[-73.697965,40.715999],"type":"Point"}
}