{
  "type": "Feature",
  "properties": {
    "iso:country":"US",
    "sg:address":"1 Van Houten St",
    "sg:city":"Nyack",
    "sg:classifiers":[
        {
            "category":"Retail",
            "subcategory":"Repair Shop",
            "type":"Services"
        }
    ],
    "sg:phone":"+1 845 358 4439",
    "sg:postcode":"10960",
    "sg:province":"NY",
    "sg:tags":[
        "glass",
        "fiber"
    ],
    "wof:name":"Dolphin Marine Fiberglass Spec",
    "wof:placetype":"venue"
},
  "geometry": {"coordinates":[-73.915937,41.100136],"type":"Point"}
}