{
  "type": "Feature",
  "properties": {
    "iso:country":"US",
    "sg:address":"111 Broadway",
    "sg:city":"New York",
    "sg:classifiers":[
        {
            "category":"Health Services",
            "subcategory":"Dentist",
            "type":"Services"
        }
    ],
    "sg:phone":"+1 212 267 1884",
    "sg:postcode":"10006",
    "sg:province":"NY",
    "wof:name":"Sellinger Ryan DMD",
    "wof:placetype":"venue"
},
  "geometry": {"coordinates":[-74.13063,40.7085],"type":"Point"}
}