{
  "type": "Feature",
  "properties": {
    "addr:full":"1229 Avenue U Brooklyn NY 11229",
    "addr:housenumber":"1229",
    "addr:postcode":"11229",
    "addr:street":"Avenue U",
    "iso:country":"US",
    "sg:address":"1229 Avenue U",
    "sg:city":"Brooklyn",
    "sg:classifiers":[
        {
            "category":"Home & Garden",
            "subcategory":"Hardware",
            "type":"Retail Goods"
        }
    ],
    "sg:phone":"+1 718 787 1855",
    "sg:postcode":"11229",
    "sg:province":"NY",
    "sg:tags":[
        "store"
    ],
    "wof:name":"Eric Blunbint & Hardware Supply",
    "wof:placetype":"venue"
},
  "geometry": {"coordinates":[-73.95904400000001,40.598656],"type":"Point"}
}