{
  "type": "Feature",
  "properties": {
    "addr:full":"39 Ann Dr E Freeport NY 11520",
    "addr:housenumber":"39",
    "addr:postcode":"11520",
    "addr:street":"Ann Dr E",
    "iso:country":"US",
    "sg:address":"39 Ann Dr E",
    "sg:city":"Freeport",
    "sg:classifiers":[
        {
            "category":"Personal",
            "subcategory":"Beauty Salon",
            "type":"Services"
        }
    ],
    "sg:phone":"+1 516 623 2212",
    "sg:postcode":"11520",
    "sg:province":"NY",
    "wof:name":"Lockness Diveboat",
    "wof:placetype":"venue"
},
  "geometry": {"coordinates":[-73.568971,40.640655],"type":"Point"}
}