{
  "type": "Feature",
  "properties": {
    "iso:country":"US",
    "sg:address":"1431 Route 300",
    "sg:city":"Newburgh",
    "sg:classifiers":[
        {
            "category":"Shopping",
            "subcategory":"Mobile Phones",
            "type":"Retail Goods"
        }
    ],
    "sg:phone":"+1 845 564 6520",
    "sg:postcode":"12550",
    "sg:province":"NY",
    "wof:name":"AT&T",
    "wof:placetype":"venue"
},
  "geometry": {"coordinates":[-74.04557800000001,41.524084],"type":"Point"}
}