{
  "type": "Feature",
  "properties": {
    "iso:country":"US",
    "sg:address":"125 W Main St",
    "sg:city":"Endicott",
    "sg:classifiers":[
        {
            "category":"Shopping",
            "subcategory":"Books",
            "type":"Retail Goods"
        }
    ],
    "sg:phone":"+1 607 748 5165",
    "sg:postcode":"13760",
    "sg:province":"NY",
    "sg:tags":[
        "comic"
    ],
    "wof:name":"Center Field Cards & Comics",
    "wof:placetype":"venue"
},
  "geometry": {"coordinates":[-76.06682499999999,42.095239],"type":"Point"}
}