{
  "type": "Feature",
  "properties": {
    "iso:country":"US",
    "sg:address":"213 Saint Anns Ave Frnt A",
    "sg:city":"Bronx",
    "sg:classifiers":[
        {
            "category":"Shopping",
            "subcategory":"Pharmacy",
            "type":"Retail Goods"
        }
    ],
    "sg:phone":"+1 718 993 8032",
    "sg:postcode":"10454",
    "sg:province":"NY",
    "sg:tags":[
        "medicines-patent",
        "proprietary"
    ],
    "wof:name":"Best For Less Store Inc",
    "wof:placetype":"venue"
},
  "geometry": {"coordinates":[-73.917841,40.806291],"type":"Point"}
}