{
  "type": "Feature",
  "properties": {
    "addr:full":"378 Kings Hwy Warwick NY 10990",
    "addr:housenumber":"378",
    "addr:postcode":"10990",
    "addr:street":"Kings Hwy",
    "iso:country":"US",
    "sg:address":"378 Kings Hwy",
    "sg:city":"Warwick",
    "sg:classifiers":[
        {
            "category":"Personal",
            "subcategory":"Beauty Salon",
            "type":"Services"
        }
    ],
    "sg:phone":"+1   ",
    "sg:postcode":"10990",
    "sg:province":"NY",
    "sg:tags":[
        "shop"
    ],
    "wof:name":"Dragon Nails",
    "wof:placetype":"venue"
},
  "geometry": {"coordinates":[-74.296527,41.290721],"type":"Point"}
}