{
  "type": "Feature",
  "properties": {
    "addr:full":"49 Walnut St Chenango Forks NY 13746",
    "addr:housenumber":"49",
    "addr:postcode":"13746",
    "addr:street":"Walnut St",
    "iso:country":"US",
    "sg:address":"49 Walnut St",
    "sg:city":"Chenango Forks",
    "sg:classifiers":[
        {
            "category":"Professional",
            "subcategory":"Management & Consulting",
            "type":"Services"
        }
    ],
    "sg:phone":"+1   ",
    "sg:postcode":"13746",
    "sg:province":"NY",
    "sg:tags":[
        "printing",
        "supply"
    ],
    "wof:name":"Russell L Card III",
    "wof:placetype":"venue"
},
  "geometry": {"coordinates":[-75.825025,42.220358],"type":"Point"}
}