{
  "type": "Feature",
  "properties": {
    "addr:full":"121 Sunset Rd Mamaroneck NY 10543",
    "addr:housenumber":"121",
    "addr:postcode":"10543",
    "addr:street":"Sunset Rd",
    "iso:country":"US",
    "sg:address":"121 Sunset Rd",
    "sg:city":"Mamaroneck",
    "sg:classifiers":[
        {
            "category":"Home & Garden",
            "subcategory":"Building Materials",
            "type":"Retail Goods"
        }
    ],
    "sg:phone":"+1   ",
    "sg:postcode":"10543",
    "sg:province":"NY",
    "wof:name":"Pyrok Inc",
    "wof:placetype":"venue"
},
  "geometry": {"coordinates":[-73.73843599999999,40.96676],"type":"Point"}
}