{
  "type": "Feature",
  "properties": {
    "addr:full":"209 Lincoln Pl Apt 2B Brooklyn NY 11217",
    "addr:housenumber":"209",
    "addr:postcode":"11217",
    "addr:street":"Lincoln Pl Apt",
    "iso:country":"US",
    "sg:address":"209 Lincoln Pl Apt 2B",
    "sg:city":"Brooklyn",
    "sg:classifiers":[
        {
            "category":"Professional",
            "subcategory":"Art Services",
            "type":"Services"
        }
    ],
    "sg:phone":"+1 718 230 0240",
    "sg:postcode":"11217",
    "sg:province":"NY",
    "sg:tags":[
        "designer",
        "display",
        "producer"
    ],
    "wof:name":"Lns Design",
    "wof:placetype":"venue"
},
  "geometry": {"coordinates":[-73.97338499999999,40.675248],"type":"Point"}
}