{
  "type": "Feature",
  "properties": {
    "addr:full":"1 E Post Rd White Plains NY 10601",
    "addr:housenumber":"1",
    "addr:postcode":"10601",
    "addr:street":"E Post Rd",
    "iso:country":"US",
    "sg:address":"1 E Post Rd",
    "sg:city":"White Plains",
    "sg:classifiers":[
        {
            "category":"Professional",
            "type":"Services"
        }
    ],
    "sg:phone":"+1 914 684 1640",
    "sg:postcode":"10601",
    "sg:province":"NY",
    "sg:tags":[
        "establishment"
    ],
    "wof:name":"Akio Co",
    "wof:placetype":"venue"
},
  "geometry": {"coordinates":[-73.770495,41.025866],"type":"Point"}
}