{
  "type": "Feature",
  "properties": {
    "iso:country":"US",
    "sg:address":"338 Northern Blvd",
    "sg:city":"Great Neck",
    "sg:classifiers":[
        {
            "category":"Recreation",
            "type":"Entertainment"
        }
    ],
    "sg:phone":"+1 516 482 3105",
    "sg:postcode":"11021",
    "sg:province":"NY",
    "wof:name":"Maxine Lucille Fiel",
    "wof:placetype":"venue"
},
  "geometry": {"coordinates":[-73.725452,40.777735],"type":"Point"}
}