{
  "type": "Feature",
  "properties": {
    "iso:country":"US",
    "sg:address":"1186 Hylan Blvd",
    "sg:city":"Staten Island",
    "sg:classifiers":[
        {
            "category":"Real Estate",
            "subcategory":"Real Estate Agent",
            "type":"Services"
        }
    ],
    "sg:phone":"+1 718 447 9493",
    "sg:postcode":"10305",
    "sg:province":"NY",
    "wof:name":"Greenwich Home Mortgage",
    "wof:placetype":"venue"
},
  "geometry": {"coordinates":[-74.08336,40.59795],"type":"Point"}
}