{
  "type": "Feature",
  "properties": {
    "addr:full":"115 Grand St New York NY 10013",
    "addr:housenumber":"115",
    "addr:postcode":"10013",
    "addr:street":"Grand St",
    "iso:country":"US",
    "sg:address":"115 Grand St",
    "sg:city":"New York",
    "sg:classifiers":[
        {
            "category":"Shopping",
            "subcategory":"Clothing, Apparel, & Fashions",
            "type":"Retail Goods"
        }
    ],
    "sg:phone":"+1 212 431 2576",
    "sg:postcode":"10013",
    "sg:province":"NY",
    "sg:tags":[
        "clothing",
        "women's"
    ],
    "wof:name":"Sac Boutique",
    "wof:placetype":"venue"
},
  "geometry": {"coordinates":[-74.0009,40.720901],"type":"Point"}
}