{
  "type": "Feature",
  "properties": {
    "iso:country":"US",
    "sg:address":"15 Lawrence Rd",
    "sg:city":"Poestenkill",
    "sg:classifiers":[
        {
            "category":"Shopping",
            "subcategory":"Crafts & Fabrics",
            "type":"Retail Goods"
        }
    ],
    "sg:phone":"+1   ",
    "sg:postcode":"12140",
    "sg:province":"NY",
    "sg:tags":[
        "sewing"
    ],
    "wof:name":"Wooly Acres Farm",
    "wof:placetype":"venue"
},
  "geometry": {"coordinates":[-73.585819,42.696003],"type":"Point"}
}