{
  "type": "Feature",
  "properties": {
    "addr:full":"610 Salt Rd Webster NY 14580",
    "addr:housenumber":"610",
    "addr:postcode":"14580",
    "addr:street":"Salt Rd",
    "iso:country":"US",
    "sg:address":"610 Salt Rd",
    "sg:city":"Webster",
    "sg:classifiers":[
        {
            "category":"Building & Trades",
            "subcategory":"Plumbing",
            "type":"Services"
        }
    ],
    "sg:phone":"+1 585 265 3510",
    "sg:postcode":"14580",
    "sg:province":"NY",
    "sg:tags":[
        "product",
        "management",
        "energy",
        "system"
    ],
    "wof:name":"Lighthouse Energy LLC",
    "wof:placetype":"venue"
},
  "geometry": {"coordinates":[-77.400409,43.240246],"type":"Point"}
}