{
  "type": "Feature",
  "properties": {
    "iso:country":"US",
    "sg:address":"1150 Penfield Rd",
    "sg:city":"Rochester",
    "sg:classifiers":[
        {
            "category":"Manufacturing",
            "subcategory":"Petroleum Products",
            "type":"Manufacturing & Wholesale Goods"
        }
    ],
    "sg:phone":"+1 585 381 7010",
    "sg:postcode":"14625",
    "sg:province":"NY",
    "sg:tags":[
        "asphalt"
    ],
    "wof:name":"Dolomite Products Co Inc",
    "wof:placetype":"venue"
},
  "geometry": {"coordinates":[-77.50605400000001,43.135383],"type":"Point"}
}