{
  "type": "Feature",
  "properties": {
    "addr:full":"904 Conklin St Farmingdale NY 11735",
    "addr:housenumber":"904",
    "addr:postcode":"11735",
    "addr:street":"Conklin St",
    "iso:country":"US",
    "sg:address":"904 Conklin St",
    "sg:city":"Farmingdale",
    "sg:classifiers":[
        {
            "category":"Retail",
            "subcategory":"Laundry & Dry Cleaning",
            "type":"Services"
        }
    ],
    "sg:phone":"+1 631 694 7504",
    "sg:postcode":"11735",
    "sg:province":"NY",
    "wof:name":"Tir Laundromat",
    "wof:placetype":"venue"
},
  "geometry": {"coordinates":[-73.428072,40.736955],"type":"Point"}
}