{
  "type": "Feature",
  "properties": {
    "iso:country":"US",
    "sg:address":"118 Co Rd 202",
    "sg:city":"Pomona",
    "sg:classifiers":[
        {
            "category":"Food & Beverages",
            "subcategory":"Groceries & Convenience Stores",
            "type":"Retail Goods"
        }
    ],
    "sg:phone":"+1 845 354 1744",
    "sg:postcode":"10970",
    "sg:province":"NY",
    "sg:tags":[
        "grocer"
    ],
    "wof:name":"Ramapo Food & News",
    "wof:placetype":"venue"
},
  "geometry": {"coordinates":[-74.068145,41.184206],"type":"Point"}
}