{
  "type": "Feature",
  "properties": {
    "iso:country":"US",
    "sg:address":"6800 Pittsford Palmyra Rd",
    "sg:city":"Fairport",
    "sg:classifiers":[
        {
            "category":"Social Services",
            "subcategory":"Child Care",
            "type":"Services"
        }
    ],
    "sg:phone":"+1 585 223 5860",
    "sg:postcode":"14450",
    "sg:province":"NY",
    "wof:name":"Villani & Grow",
    "wof:placetype":"venue"
},
  "geometry": {"coordinates":[-77.437212,43.069043],"type":"Point"}
}