{
  "type": "Feature",
  "properties": {
    "iso:country":"US",
    "sg:address":"249 Main St",
    "sg:city":"Huntington",
    "sg:classifiers":[
        {
            "category":"Social Services",
            "type":"Services"
        }
    ],
    "sg:phone":"+1 631 423 5725",
    "sg:postcode":"11743",
    "sg:province":"NY",
    "sg:tags":[
        "counselor",
        "marriage",
        "family"
    ],
    "wof:name":"Michael Shepherd",
    "wof:placetype":"venue"
},
  "geometry": {"coordinates":[-73.425585,40.871391],"type":"Point"}
}