{
  "type": "Feature",
  "properties": {
    "addr:full":"303 Smith St Farmingdale NY 11735",
    "addr:housenumber":"303",
    "addr:postcode":"11735",
    "addr:street":"Smith St",
    "iso:country":"US",
    "sg:address":"303 Smith St",
    "sg:city":"Farmingdale",
    "sg:classifiers":[
        {
            "category":"Freight",
            "type":"Transportation"
        }
    ],
    "sg:phone":"+1   ",
    "sg:postcode":"11735",
    "sg:province":"NY",
    "sg:tags":[
        "newspaper",
        "delivery"
    ],
    "wof:name":"City & Suburban Delivery",
    "wof:placetype":"venue"
},
  "geometry": {"coordinates":[-73.406194,40.757143],"type":"Point"}
}