{
  "type": "Feature",
  "properties": {
    "iso:country":"US",
    "sg:address":"4 Kenilworth Ln",
    "sg:city":"Warwick",
    "sg:classifiers":[
        {
            "category":"Banks & Credit Unions",
            "subcategory":"Investment Brokerage",
            "type":"Services"
        }
    ],
    "sg:phone":"+1 845 987 1422",
    "sg:postcode":"10990",
    "sg:province":"NY",
    "sg:tags":[
        "advisory"
    ],
    "wof:name":"Cfp",
    "wof:placetype":"venue"
},
  "geometry": {"coordinates":[-74.356492,41.239248],"type":"Point"}
}