{
  "type": "Feature",
  "properties": {
    "iso:country":"US",
    "sg:address":"20 Arden Ln",
    "sg:city":"Farmingville",
    "sg:classifiers":[
        {
            "category":"Building & Trades",
            "subcategory":"Landscaping Services",
            "type":"Services"
        }
    ],
    "sg:phone":"+1 631 585 5752",
    "sg:postcode":"11738",
    "sg:province":"NY",
    "sg:tags":[
        "landscape"
    ],
    "wof:name":"Greenscene Designs",
    "wof:placetype":"venue"
},
  "geometry": {"coordinates":[-73.071443,40.842784],"type":"Point"}
}