{
  "type": "Feature",
  "properties": {
    "iso:country":"US",
    "sg:address":"8231 Niagara Falls Blvd",
    "sg:city":"Niagara Falls",
    "sg:classifiers":[
        {
            "category":"Personal",
            "subcategory":"Beauty Salon",
            "type":"Services"
        }
    ],
    "sg:phone":"+1 716 283 3348",
    "sg:postcode":"14304",
    "sg:province":"NY",
    "sg:tags":[
        "manicuring"
    ],
    "wof:name":"Super Nails",
    "wof:placetype":"venue"
},
  "geometry": {"coordinates":[-78.96807800000001,43.090119],"type":"Point"}
}