{
  "type": "Feature",
  "properties": {
    "addr:full":"59 Burnside Dr Hastings On Hudson NY 10706",
    "addr:housenumber":"59",
    "addr:postcode":"10706",
    "addr:street":"Burnside Dr",
    "iso:country":"US",
    "sg:address":"59 Burnside Dr",
    "sg:city":"Hastings On Hudson",
    "sg:classifiers":[
        {
            "category":"Real Estate",
            "subcategory":"Architect",
            "type":"Services"
        }
    ],
    "sg:phone":"+1 914 478 4346",
    "sg:postcode":"10706",
    "sg:province":"NY",
    "sg:tags":[
        "architectural"
    ],
    "wof:name":"Wong Architects",
    "wof:placetype":"venue"
},
  "geometry": {"coordinates":[-73.87591,40.989089],"type":"Point"}
}