{
  "type": "Feature",
  "properties": {
    "addr:full":"62 Allen St Buffalo NY 14202",
    "addr:housenumber":"62",
    "addr:postcode":"14202",
    "addr:street":"Allen St",
    "iso:country":"US",
    "sg:address":"62 Allen St",
    "sg:city":"Buffalo",
    "sg:classifiers":[
        {
            "category":"Restaurant",
            "type":"Food & Drink"
        }
    ],
    "sg:menulink":"http://www.allmenus.com/ny/buffalo/253615-fiddle-heads-restaurant/menu/",
    "sg:phone":"+1 716 883 4166",
    "sg:postcode":"14202",
    "sg:province":"NY",
    "sg:tags":[
        "seafood",
        "steakhouse",
        "american",
        "salad",
        "pizza"
    ],
    "wof:name":"Fiddle Heads Restaurant",
    "wof:placetype":"venue"
},
  "geometry": {"coordinates":[-78.87237399999999,42.899408],"type":"Point"}
}