{
  "type": "Feature",
  "properties": {
    "addr:full":"1157 Fulton Ave Bronx NY 10456",
    "addr:housenumber":"1157",
    "addr:postcode":"10456",
    "addr:street":"Fulton Ave",
    "iso:country":"US",
    "sg:address":"1157 Fulton Ave",
    "sg:city":"Bronx",
    "sg:classifiers":[
        {
            "category":"Social Services",
            "subcategory":"Adult Care",
            "type":"Services"
        }
    ],
    "sg:phone":"+1 718 328 8620",
    "sg:postcode":"10456",
    "sg:province":"NY",
    "sg:tags":[
        "residential"
    ],
    "wof:name":"Good Council",
    "wof:placetype":"venue"
},
  "geometry": {"coordinates":[-73.90463699999999,40.830532],"type":"Point"}
}