{
  "type": "Feature",
  "properties": {
    "addr:full":"1765 Madison Ave New York NY 10029",
    "addr:housenumber":"1765",
    "addr:postcode":"10029",
    "addr:street":"Madison Ave",
    "iso:country":"US",
    "sg:address":"1765 Madison Ave",
    "sg:city":"New York",
    "sg:classifiers":[
        {
            "category":"Organizations",
            "subcategory":"Religious Organization",
            "type":"Services"
        }
    ],
    "sg:phone":"+1 212 369 6643",
    "sg:postcode":"10029",
    "sg:province":"NY",
    "sg:tags":[
        "church"
    ],
    "wof:name":"Mt Zion AME Church",
    "wof:placetype":"venue"
},
  "geometry": {"coordinates":[-73.945359,40.799287],"type":"Point"}
}