{
  "type": "Feature",
  "properties": {
    "addr:full":"1 Chase Manhattan Plz New York NY 10005",
    "addr:housenumber":"1",
    "addr:postcode":"10005",
    "addr:street":"Chase Manhattan Plz",
    "iso:country":"US",
    "sg:address":"1 Chase Manhattan Plz",
    "sg:city":"New York",
    "sg:classifiers":[
        {
            "category":"Professional",
            "subcategory":"Lawyer & Legal Services",
            "type":"Services"
        }
    ],
    "sg:phone":"+1 212 530 5296",
    "sg:postcode":"10005",
    "sg:province":"NY",
    "wof:name":"Ponikvar Dale L Lwyr",
    "wof:placetype":"venue"
},
  "geometry": {"coordinates":[-74.008432,40.707802],"type":"Point"}
}