{
  "type": "Feature",
  "properties": {
    "addr:full":"3 Pulaski St Altmar NY 13302",
    "addr:housenumber":"3",
    "addr:postcode":"13302",
    "addr:street":"Pulaski St",
    "iso:country":"US",
    "sg:address":"3 Pulaski St",
    "sg:city":"Altmar",
    "sg:classifiers":[
        {
            "category":"Travel",
            "subcategory":"Hotels & Motels",
            "type":"Entertainment"
        }
    ],
    "sg:phone":"+1 315 298 2993",
    "sg:postcode":"13302",
    "sg:province":"NY",
    "wof:name":"Malinda's Fly-Tackle Shp-Lodge",
    "wof:placetype":"venue"
},
  "geometry": {"coordinates":[-76.001929,43.511474],"type":"Point"}
}