{
  "type": "Feature",
  "properties": {
    "iso:country":"US",
    "sg:address":"1282 Menard St",
    "sg:city":"Uniondale",
    "sg:classifiers":[
        {
            "category":"Autos & Motor Vehicles",
            "subcategory":"Fuel & Gas Station",
            "type":"Retail Goods"
        }
    ],
    "sg:phone":"+1 516 489 1009",
    "sg:postcode":"11553",
    "sg:province":"NY",
    "sg:tags":[
        "oil"
    ],
    "wof:name":"Island Express Inc",
    "wof:placetype":"venue"
},
  "geometry": {"coordinates":[-73.58354799999999,40.717924],"type":"Point"}
}