{
  "type": "Feature",
  "properties": {
    "iso:country":"US",
    "sg:address":"117 E 24th St",
    "sg:city":"New York",
    "sg:classifiers":[
        {
            "category":"Arts & Performance",
            "subcategory":"Theater",
            "type":"Entertainment"
        }
    ],
    "sg:phone":"+1 212 674 2000",
    "sg:postcode":"10010",
    "sg:province":"NY",
    "sg:tags":[
        "production",
        "corporate",
        "event"
    ],
    "wof:name":"DSA Productions Inc",
    "wof:placetype":"venue"
},
  "geometry": {"coordinates":[-73.984838,40.740578],"type":"Point"}
}