{
  "type": "Feature",
  "properties": {
    "addr:full":"11 State St Rochester NY 14614",
    "addr:housenumber":"11",
    "addr:postcode":"14614",
    "addr:street":"State St",
    "iso:country":"US",
    "sg:address":"11 State St",
    "sg:city":"Rochester",
    "sg:classifiers":[
        {
            "category":"Shopping",
            "subcategory":"Gifts & Souvenirs",
            "type":"Retail Goods"
        }
    ],
    "sg:phone":"+1 585 232 2950",
    "sg:postcode":"14614",
    "sg:province":"NY",
    "sg:tags":[
        "cards",
        "greeting"
    ],
    "wof:name":"Scott's Cards & Gifts",
    "wof:placetype":"venue"
},
  "geometry": {"coordinates":[-77.612905,43.156061],"type":"Point"}
}