{
  "type": "Feature",
  "properties": {
    "addr:full":"40 W 31 St New York NY 10001",
    "addr:housenumber":"40",
    "addr:postcode":"10001",
    "addr:street":"W 31 St",
    "iso:country":"US",
    "sg:address":"40 W 31 St",
    "sg:city":"New York",
    "sg:classifiers":[
        {
            "category":"Wholesale",
            "subcategory":"Drugs",
            "type":"Manufacturing & Wholesale Goods"
        }
    ],
    "sg:phone":"+1 212 502 0052",
    "sg:postcode":"10001",
    "sg:province":"NY",
    "sg:tags":[
        "aid",
        "product",
        "health",
        "beauty"
    ],
    "wof:name":"BHB Trading Inc",
    "wof:placetype":"venue"
},
  "geometry": {"coordinates":[-73.986799,40.746607],"type":"Point"}
}