{
  "type": "Feature",
  "properties": {
    "iso:country":"US",
    "sg:address":"1238 Cross Bay Blvd",
    "sg:city":"Broad Channel",
    "sg:classifiers":[
        {
            "category":"Retail",
            "subcategory":"Funeral Services",
            "type":"Services"
        }
    ],
    "sg:phone":"+1 718 318 1683",
    "sg:postcode":"11693",
    "sg:province":"NY",
    "sg:tags":[
        "cemetery"
    ],
    "wof:name":"Hillebrand Funeral Homes Inc",
    "wof:placetype":"venue"
},
  "geometry": {"coordinates":[-73.820099,40.6031],"type":"Point"}
}