{
  "type": "Feature",
  "properties": {
    "iso:country":"US",
    "sg:address":"2770 US Hwy 20",
    "sg:city":"Cazenovia",
    "sg:classifiers":[
        {
            "category":"Wholesale",
            "subcategory":"Machinery & Supplies",
            "type":"Manufacturing & Wholesale Goods"
        }
    ],
    "sg:phone":"+1 315 655 2639",
    "sg:postcode":"13035",
    "sg:province":"NY",
    "sg:tags":[
        "janitorial"
    ],
    "wof:name":"Hughes Distributors",
    "wof:placetype":"venue"
},
  "geometry": {"coordinates":[-75.812118,42.919596],"type":"Point"}
}