{
  "type": "Feature",
  "properties": {
    "iso:country":"US",
    "sg:address":"17 Old Dock Rd",
    "sg:city":"Yaphank",
    "sg:classifiers":[
        {
            "category":"Autos & Motor Vehicles",
            "subcategory":"Auto Supplies",
            "type":"Retail Goods"
        }
    ],
    "sg:phone":"+1 631 924 1110",
    "sg:postcode":"11980",
    "sg:province":"NY",
    "sg:tags":[
        "lube",
        "oil"
    ],
    "wof:name":"Indy 3000 Of Mastic, Inc.",
    "wof:placetype":"venue"
},
  "geometry": {"coordinates":[-72.943682,40.819952],"type":"Point"}
}