{
  "type": "Feature",
  "properties": {
    "addr:full":"5910 8th Ave Brooklyn NY 11220",
    "addr:housenumber":"5910",
    "addr:postcode":"11220",
    "addr:street":"8Th Ave",
    "iso:country":"US",
    "sg:address":"5910 8th Ave",
    "sg:city":"Brooklyn",
    "sg:classifiers":[
        {
            "category":"Utilities",
            "subcategory":"Mobile Phone",
            "type":"Services"
        }
    ],
    "sg:phone":"+1 718 567 8222",
    "sg:postcode":"11220",
    "sg:province":"NY",
    "sg:tags":[
        "telephone",
        "cellular"
    ],
    "wof:name":"P F Wireless",
    "wof:placetype":"venue"
},
  "geometry": {"coordinates":[-74.009569,40.635599],"type":"Point"}
}