{
  "type": "Feature",
  "properties": {
    "addr:full":"321 Broadway Fl 3 New York NY 10007",
    "addr:housenumber":"321;3",
    "addr:postcode":"10007",
    "addr:street":"Broadway",
    "iso:country":"US",
    "sg:address":"321 Broadway Fl 3",
    "sg:city":"New York",
    "sg:classifiers":[
        {
            "category":"Professional",
            "subcategory":"Lawyer & Legal Services",
            "type":"Services"
        }
    ],
    "sg:phone":"+1 212 619 2723",
    "sg:postcode":"10007",
    "sg:province":"NY",
    "wof:name":"Okun Jeffrey Law Office of",
    "wof:placetype":"venue"
},
  "geometry": {"coordinates":[-74.004913,40.715835],"type":"Point"}
}