{
  "type": "Feature",
  "properties": {
    "iso:country":"US",
    "sg:address":"135 Division St",
    "sg:city":"New York",
    "sg:classifiers":[
        {
            "category":"Professional",
            "subcategory":"Computer Services",
            "type":"Services"
        }
    ],
    "sg:phone":"+1 212 923 6733",
    "sg:postcode":"10002",
    "sg:province":"NY",
    "wof:name":"Computer TROUBLESHOOTERS-Ms",
    "wof:placetype":"venue"
},
  "geometry": {"coordinates":[-73.991677,40.714368],"type":"Point"}
}