{
  "type": "Feature",
  "properties": {
    "iso:country":"US",
    "sg:address":"116 Colon Ave",
    "sg:city":"Staten Island",
    "sg:classifiers":[
        {
            "category":"Professional",
            "subcategory":"Computer Services",
            "type":"Services"
        }
    ],
    "sg:phone":"+1 646 256 6971",
    "sg:postcode":"10308",
    "sg:province":"NY",
    "sg:tags":[
        "consulting"
    ],
    "wof:name":"Ostrosoft Corp",
    "wof:placetype":"venue"
},
  "geometry": {"coordinates":[-74.15483,40.551913],"type":"Point"}
}