{
  "type": "Feature",
  "properties": {
    "iso:country":"US",
    "sg:address":"263 7th Ave",
    "sg:city":"Brooklyn",
    "sg:classifiers":[
        {
            "category":"Health Services",
            "subcategory":"Doctor",
            "type":"Services"
        }
    ],
    "sg:phone":"+1 718 369 6900",
    "sg:postcode":"11215",
    "sg:province":"NY",
    "sg:tags":[
        "physician",
        "surgeon"
    ],
    "wof:name":"Motahedeh Faraj MD",
    "wof:placetype":"venue"
},
  "geometry": {"coordinates":[-73.979797,40.6689],"type":"Point"}
}