{
  "type": "Feature",
  "properties": {
    "iso:country":"US",
    "sg:address":"2053 Grand Central Ave",
    "sg:city":"Horseheads",
    "sg:classifiers":[
        {
            "category":"Professional",
            "subcategory":"Business Services",
            "type":"Services"
        }
    ],
    "sg:phone":"+1 607 796 9116",
    "sg:postcode":"14845",
    "sg:province":"NY",
    "sg:tags":[
        "painter",
        "sign"
    ],
    "wof:name":"W A Tunis Signs",
    "wof:placetype":"venue"
},
  "geometry": {"coordinates":[-76.82094499999999,42.148424],"type":"Point"}
}