{
  "type": "Feature",
  "properties": {
    "addr:full":"1842 131st St College Point NY 11356",
    "addr:housenumber":"1842",
    "addr:postcode":"11356",
    "addr:street":"131St St",
    "iso:country":"US",
    "sg:address":"1842 131st St",
    "sg:city":"College Point",
    "sg:classifiers":[
        {
            "category":"Retail",
            "subcategory":"Car Wash",
            "type":"Services"
        }
    ],
    "sg:phone":"+1 718 661 2535",
    "sg:postcode":"11356",
    "sg:province":"NY",
    "wof:name":"B Q Carwash And Lube Inc",
    "wof:placetype":"venue"
},
  "geometry": {"coordinates":[-73.837932,40.781948],"type":"Point"}
}