{
  "type": "Feature",
  "properties": {
    "iso:country":"US",
    "sg:address":"911 Urf Rd",
    "sg:city":"Cowlesville",
    "sg:phone":"+1 585 937 7586",
    "sg:postcode":"14037",
    "sg:province":"NY",
    "sg:tags":[
        "farm",
        "corn"
    ],
    "wof:name":"Roland Lamb",
    "wof:placetype":"venue"
},
  "geometry": {"coordinates":[-78.46876899999999,42.837764],"type":"Point"}
}