{
  "type": "Feature",
  "properties": {
    "iso:country":"US",
    "sg:address":"1663 Bath Avenue",
    "sg:city":"Brooklyn",
    "sg:classifiers":[
        {
            "category":"Education",
            "subcategory":"School",
            "type":"Public Place"
        }
    ],
    "sg:phone":"+1 718 256 4699",
    "sg:postcode":"11214",
    "sg:province":"NY",
    "wof:name":"Chang's Center",
    "wof:placetype":"venue"
},
  "geometry": {"coordinates":[-74.008551,40.605471],"type":"Point"}
}