{
  "type": "Feature",
  "properties": {
    "addr:full":"824 9th Ave New York NY 10019",
    "addr:housenumber":"824",
    "addr:postcode":"10019",
    "addr:street":"9Th Ave",
    "iso:country":"US",
    "sg:address":"824 9th Ave",
    "sg:city":"New York",
    "sg:classifiers":[
        {
            "category":"Restaurant",
            "type":"Food & Drink"
        }
    ],
    "sg:phone":"+1 646 763 6585",
    "sg:postcode":"10019",
    "sg:province":"NY",
    "sg:tags":[
        "mexican"
    ],
    "sg:website":"www.elcentro-nyc.com/",
    "wof:name":"El Centro",
    "wof:placetype":"venue"
},
  "geometry": {"coordinates":[-73.98687700000001,40.765914],"type":"Point"}
}