{
  "type": "Feature",
  "properties": {
    "wof:name":"Gowanus Canal Dolphin Memorial Bridge",
    "wof:placetype":"venue"
},
  "geometry": {"coordinates":[-73.98836300000001,40.679477],"type":"Point"}
}