{
  "type": "Feature",
  "properties": {
    "addr:website":"http://www.nytimes.com/2013/01/26/nyregion/dolphin-in-gowanus-canal.html",
    "iso:country":"US",
    "wof:name":"Gowanus Canal Dolphin Memorial Bridge",
    "wof:placetype":"venue"
},
  "geometry": {"coordinates":[-73.98836300000001,40.679477],"type":"Point"}
}