{
  "type": "Feature",
  "properties": {
    "iso:country":"US",
    "sg:address":"9 Vaughn Rd",
    "sg:city":"Morrisonville",
    "sg:classifiers":[
        {
            "category":"Social Services",
            "subcategory":"Child Care",
            "type":"Services"
        }
    ],
    "sg:phone":"+1 518 562 3658",
    "sg:postcode":"12962",
    "sg:province":"NY",
    "sg:tags":[
        "day"
    ],
    "wof:name":"Jceo Headstart",
    "wof:placetype":"venue"
},
  "geometry": {"coordinates":[-73.562834,44.712194],"type":"Point"}
}