{
  "type": "Feature",
  "properties": {
    "addr:full":"1460 Manatuck Blvd Bay Shore NY 11706",
    "addr:housenumber":"1460",
    "addr:postcode":"11706",
    "addr:street":"Manatuck Blvd",
    "iso:country":"US",
    "sg:address":"1460 Manatuck Blvd",
    "sg:city":"Bay Shore",
    "sg:classifiers":[
        {
            "category":"Professional",
            "type":"Services"
        }
    ],
    "sg:phone":"+1   ",
    "sg:postcode":"11706",
    "sg:province":"NY",
    "wof:name":"Reliable Removals Inc",
    "wof:placetype":"venue"
},
  "geometry": {"coordinates":[-73.26978099999999,40.746254],"type":"Point"}
}