{
  "type": "Feature",
  "properties": {
    "addr:full":"20 Dunton Ave Deer Park NY 11729",
    "addr:housenumber":"20",
    "addr:postcode":"11729",
    "addr:street":"Dunton Ave",
    "iso:country":"US",
    "sg:address":"20 Dunton Ave",
    "sg:city":"Deer Park",
    "sg:classifiers":[
        {
            "category":"Manufacturing",
            "subcategory":"Chemicals & Compounds",
            "type":"Manufacturing & Wholesale Goods"
        }
    ],
    "sg:phone":"+1 631 586 3666",
    "sg:postcode":"11729",
    "sg:province":"NY",
    "sg:tags":[
        "printing",
        "ink"
    ],
    "sg:website":"www.specialtyink.com",
    "wof:name":"Specialty Ink Co Inc",
    "wof:placetype":"venue"
},
  "geometry": {"coordinates":[-73.293807,40.768883],"type":"Point"}
}