{
  "type": "Feature",
  "properties": {
    "iso:country":"US",
    "sg:address":"2521 Palisade Ave",
    "sg:city":"Bronx",
    "sg:classifiers":[
        {
            "category":"Real Estate",
            "subcategory":"Architect",
            "type":"Services"
        }
    ],
    "sg:phone":"+1 718 548 2226",
    "sg:postcode":"10463",
    "sg:province":"NY",
    "wof:name":"LA Rive Condominium",
    "wof:placetype":"venue"
},
  "geometry": {"coordinates":[-73.92215400000001,40.880022],"type":"Point"}
}