{
  "type": "Feature",
  "properties": {
    "iso:country":"US",
    "sg:address":"725 Broadway Ave",
    "sg:city":"Holbrook",
    "sg:classifiers":[
        {
            "category":"Freight",
            "type":"Transportation"
        }
    ],
    "sg:phone":"+1   ",
    "sg:postcode":"11741",
    "sg:province":"NY",
    "sg:tags":[
        "warehouse",
        "furniture"
    ],
    "wof:name":"REA Leasing Co",
    "wof:placetype":"venue"
},
  "geometry": {"coordinates":[-73.066971,40.777929],"type":"Point"}
}