{
  "type": "Feature",
  "properties": {
    "iso:country":"US",
    "sg:address":"234 Mill St",
    "sg:city":"Rochester",
    "sg:classifiers":[
        {
            "category":"Professional",
            "subcategory":"Advertising",
            "type":"Services"
        }
    ],
    "sg:phone":"+1 585 232 1180",
    "sg:postcode":"14614",
    "sg:province":"NY",
    "sg:tags":[
        "counselor"
    ],
    "sg:website":"www.mill-race.com",
    "wof:name":"Millrace Design Assoc",
    "wof:placetype":"venue"
},
  "geometry": {"coordinates":[-77.617028,43.160677],"type":"Point"}
}