{
  "type": "Feature",
  "properties": {
    "addr:full":"445 Central Ave Cedarhurst NY 11516",
    "addr:housenumber":"445",
    "addr:postcode":"11516",
    "addr:street":"Central Ave",
    "iso:country":"US",
    "sg:address":"445 Central Ave",
    "sg:city":"Cedarhurst",
    "sg:classifiers":[
        {
            "category":"Professional",
            "subcategory":"Research",
            "type":"Services"
        }
    ],
    "sg:phone":"+1 516 385 4442",
    "sg:postcode":"11516",
    "sg:province":"NY",
    "sg:tags":[
        "laboratory"
    ],
    "wof:name":"INC Be Labs",
    "wof:placetype":"venue"
},
  "geometry": {"coordinates":[-73.725148,40.620559],"type":"Point"}
}