{
  "type": "Feature",
  "properties": {
    "iso:country":"US",
    "sg:address":"1333 Wayneport Rd",
    "sg:city":"Macedon",
    "sg:classifiers":[
        {
            "category":"Home & Garden",
            "subcategory":"Building Materials",
            "type":"Retail Goods"
        }
    ],
    "sg:phone":"+1   ",
    "sg:postcode":"14502",
    "sg:province":"NY",
    "wof:name":"Cabinet Trends",
    "wof:placetype":"venue"
},
  "geometry": {"coordinates":[-77.358617,43.045346],"type":"Point"}
}