{
  "type": "Feature",
  "properties": {
    "addr:full":"301 Mill St Rome NY 13440",
    "addr:housenumber":"301",
    "addr:postcode":"13440",
    "addr:street":"Mill St",
    "iso:country":"US",
    "sg:address":"301 Mill St",
    "sg:city":"Rome",
    "sg:classifiers":[
        {
            "category":"Manufacturing",
            "subcategory":"Printing",
            "type":"Manufacturing & Wholesale Goods"
        }
    ],
    "sg:phone":"+1 315 337 5900",
    "sg:postcode":"13440",
    "sg:province":"NY",
    "sg:tags":[
        "printer"
    ],
    "sg:website":"www.canterburypress.com",
    "wof:name":"Canterbury Press",
    "wof:placetype":"venue"
},
  "geometry": {"coordinates":[-75.448994,43.203657],"type":"Point"}
}