{
  "type": "Feature",
  "properties": {
    "addr:full":"208 Montcalm St Ticonderoga NY 12883",
    "addr:housenumber":"208",
    "addr:postcode":"12883",
    "addr:street":"Montcalm St",
    "iso:country":"US",
    "sg:address":"208 Montcalm St",
    "sg:city":"Ticonderoga",
    "sg:classifiers":[
        {
            "category":"Shopping",
            "subcategory":"Optical Goods",
            "type":"Retail Goods"
        }
    ],
    "sg:phone":"+1   ",
    "sg:postcode":"12883",
    "sg:province":"NY",
    "wof:name":"Adirondack Optical Outfitter",
    "wof:placetype":"venue"
},
  "geometry": {"coordinates":[-73.427465,43.848244],"type":"Point"}
}