{
  "type": "Feature",
  "properties": {
    "addr:full":"215 E 4 St New York NY 10009",
    "addr:housenumber":"215;4",
    "addr:postcode":"10009",
    "addr:street":"E;St",
    "iso:country":"US",
    "sg:address":"215 E 4 St",
    "sg:city":"New York",
    "sg:classifiers":[
        {
            "category":"Professional",
            "type":"Services"
        }
    ],
    "sg:phone":"+1 212 529 0666",
    "sg:postcode":"10009",
    "sg:province":"NY",
    "sg:tags":[
        "establishment"
    ],
    "wof:name":"Last Rites",
    "wof:placetype":"venue"
},
  "geometry": {"coordinates":[-73.983065,40.72367],"type":"Point"}
}