{
  "type": "Feature",
  "properties": {
    "addr:full":"339 Atlantic Ave Brooklyn NY 11201",
    "addr:housenumber":"339",
    "addr:postcode":"11201",
    "addr:street":"Atlantic Ave",
    "iso:country":"US",
    "sg:address":"339 Atlantic Ave",
    "sg:city":"Brooklyn",
    "sg:classifiers":[
        {
            "category":"Health Services",
            "subcategory":"Doctor",
            "type":"Services"
        }
    ],
    "sg:phone":"+1 718 780 1520",
    "sg:postcode":"11201",
    "sg:province":"NY",
    "sg:tags":[
        "medical"
    ],
    "wof:name":"Mark Irwin MD Facs",
    "wof:placetype":"venue"
},
  "geometry": {"coordinates":[-73.98841899999999,40.688585],"type":"Point"}
}