{
  "type": "Feature",
  "properties": {
    "addr:full":"250 Hempstead Ave Malverne NY 11565",
    "addr:housenumber":"250",
    "addr:postcode":"11565",
    "addr:street":"Hempstead Ave",
    "iso:country":"US",
    "sg:address":"250 Hempstead Ave",
    "sg:city":"Malverne",
    "sg:classifiers":[
        {
            "category":"Professional",
            "subcategory":"Lawyer & Legal Services",
            "type":"Services"
        }
    ],
    "sg:phone":"+1 516 887 1800",
    "sg:postcode":"11565",
    "sg:province":"NY",
    "sg:tags":[
        "attorney"
    ],
    "sg:website":"www.taxesnewyork.com",
    "wof:name":"Stephen B KASS Law Ofc",
    "wof:placetype":"venue"
},
  "geometry": {"coordinates":[-73.670005,40.674667],"type":"Point"}
}