{
  "type": "Feature",
  "properties": {
    "iso:country":"US",
    "sg:address":"627 Broadway",
    "sg:city":"New York",
    "sg:classifiers":[
        {
            "category":"Shopping",
            "subcategory":"Computers & Home Electronics",
            "type":"Retail Goods"
        }
    ],
    "sg:phone":"+1 212 505 1111",
    "sg:postcode":"10012",
    "sg:province":"NY",
    "sg:tags":[
        "equipment",
        "audio",
        "video",
        "rent",
        "new"
    ],
    "sg:website":"www.stereoexchange.com/",
    "wof:name":"Stereo Exchange",
    "wof:placetype":"venue"
},
  "geometry": {"coordinates":[-73.996145,40.726148],"type":"Point"}
}