{
  "type": "Feature",
  "properties": {
    "iso:country":"US",
    "sg:address":"9420 Snipery Rd",
    "sg:city":"Corfu",
    "sg:classifiers":[
        {
            "category":"Building & Trades",
            "subcategory":"Construction",
            "type":"Services"
        }
    ],
    "sg:phone":"+1 585 599 3211",
    "sg:postcode":"14036",
    "sg:province":"NY",
    "sg:tags":[
        "house",
        "remodeling"
    ],
    "wof:name":"McQueen Home Improvements",
    "wof:placetype":"venue"
},
  "geometry": {"coordinates":[-78.38841600000001,42.956987],"type":"Point"}
}