{
  "type": "Feature",
  "properties": {
    "addr:full":"3 Wilma Dr Port Jefferson Station NY 11776",
    "addr:housenumber":"3",
    "addr:postcode":"11776",
    "addr:street":"Wilma Dr",
    "iso:country":"US",
    "sg:address":"3 Wilma Dr",
    "sg:city":"Port Jefferson Station",
    "sg:classifiers":[
        {
            "category":"Building & Trades",
            "subcategory":"Construction",
            "type":"Services"
        }
    ],
    "sg:phone":"+1 631 474 3893",
    "sg:postcode":"11776",
    "sg:province":"NY",
    "sg:tags":[
        "general",
        "remodeling",
        "contractor"
    ],
    "wof:name":"D and L Bathrooms Remodeling",
    "wof:placetype":"venue"
},
  "geometry": {"coordinates":[-73.037688,40.895938],"type":"Point"}
}