{
  "type": "Feature",
  "properties": {
    "iso:country":"US",
    "sg:address":"3609 State Hwy 5",
    "sg:city":"Frankfort",
    "sg:classifiers":[
        {
            "category":"Freight",
            "type":"Transportation"
        }
    ],
    "sg:phone":"+1   ",
    "sg:postcode":"13340",
    "sg:province":"NY",
    "sg:tags":[
        "local",
        "without",
        "storage",
        "dump",
        "trucking"
    ],
    "wof:name":"Juliano Sand & Gravel",
    "wof:placetype":"venue"
},
  "geometry": {"coordinates":[-75.074134,43.053658],"type":"Point"}
}