{
  "type": "Feature",
  "properties": {
    "addr:full":"47 N Plank Rd Newburgh NY 12550",
    "addr:housenumber":"47",
    "addr:postcode":"12550",
    "addr:street":"N Plank Rd",
    "iso:country":"US",
    "sg:address":"47 N Plank Rd",
    "sg:city":"Newburgh",
    "sg:classifiers":[
        {
            "category":"Health Services",
            "subcategory":"Doctor",
            "type":"Services"
        }
    ],
    "sg:phone":"+1 845 562 3600",
    "sg:postcode":"12550",
    "sg:province":"NY",
    "sg:tags":[
        "podiatrist"
    ],
    "wof:name":"Hudson View Medical Offices",
    "wof:placetype":"venue"
},
  "geometry": {"coordinates":[-74.030602,41.5238],"type":"Point"}
}