{
  "type": "Feature",
  "properties": {
    "addr:full":"257 Park Avenue South New York NY 10010",
    "addr:housenumber":"257",
    "addr:postcode":"10010",
    "addr:street":"Park Avenue South",
    "iso:country":"US",
    "sg:address":"257 Park Avenue South",
    "sg:city":"New York",
    "sg:classifiers":[
        {
            "category":"Professional",
            "subcategory":"Computer Services",
            "type":"Services"
        }
    ],
    "sg:phone":"+1 212 924 6800",
    "sg:postcode":"10010",
    "sg:province":"NY",
    "sg:website":"http://www.spafinder.com/",
    "wof:name":"Spa Finder",
    "wof:placetype":"venue"
},
  "geometry": {"coordinates":[-73.987357,40.738647],"type":"Point"}
}