{
  "type": "Feature",
  "properties": {
    "addr:full":"3281 Hull Ave Bronx NY 10467",
    "addr:housenumber":"3281",
    "addr:postcode":"10467",
    "addr:street":"Hull Ave",
    "iso:country":"US",
    "sg:address":"3281 Hull Ave",
    "sg:city":"Bronx",
    "sg:classifiers":[
        {
            "category":"Building & Trades",
            "subcategory":"Pest Control",
            "type":"Services"
        }
    ],
    "sg:phone":"+1 718 519 9400",
    "sg:postcode":"10467",
    "sg:province":"NY",
    "wof:name":"City Wide Exterminating",
    "wof:placetype":"venue"
},
  "geometry": {"coordinates":[-73.8751,40.875784],"type":"Point"}
}