{
  "type": "Feature",
  "properties": {
    "addr:full":"2203 Jackson Ave Long Island City NY 11101",
    "addr:housenumber":"2203",
    "addr:postcode":"11101",
    "addr:street":"Jackson Ave",
    "iso:country":"US",
    "sg:address":"2203 Jackson Ave",
    "sg:city":"Long Island City",
    "sg:classifiers":[
        {
            "category":"Home & Garden",
            "subcategory":"Hardware",
            "type":"Retail Goods"
        }
    ],
    "sg:phone":"+1 800 498 9138",
    "sg:postcode":"11101",
    "sg:province":"NY",
    "sg:tags":[
        "store"
    ],
    "wof:name":"Van Alst Hardware P Supl Co",
    "wof:placetype":"venue"
},
  "geometry": {"coordinates":[-73.947444,40.745268],"type":"Point"}
}