{
  "type": "Feature",
  "properties": {
    "addr:full":"104 River St Oneonta NY 13820",
    "addr:housenumber":"104",
    "addr:postcode":"13820",
    "addr:street":"River St",
    "iso:country":"US",
    "sg:address":"104 River St",
    "sg:city":"Oneonta",
    "sg:classifiers":[
        {
            "category":"Real Estate",
            "subcategory":"Real Estate Operator",
            "type":"Services"
        }
    ],
    "sg:phone":"+1 607 432 6473",
    "sg:postcode":"13820",
    "sg:province":"NY",
    "sg:tags":[
        "mobile",
        "manufactured",
        "housing-communities",
        "community",
        "home"
    ],
    "wof:name":"Greenacre Mobile Home Park",
    "wof:placetype":"venue"
},
  "geometry": {"coordinates":[-75.073441,42.446251],"type":"Point"}
}