{
  "type": "Feature",
  "properties": {
    "iso:country":"US",
    "sg:address":"11 Half Moon Pond Rd",
    "sg:city":"Ridge",
    "sg:classifiers":[
        {
            "category":"Building & Trades",
            "subcategory":"Construction",
            "type":"Services"
        }
    ],
    "sg:phone":"+1 631 924 6459",
    "sg:postcode":"11961",
    "sg:province":"NY",
    "sg:tags":[
        "floor",
        "laying",
        "contractor"
    ],
    "wof:name":"Bills Floor Sanding",
    "wof:placetype":"venue"
},
  "geometry": {"coordinates":[-72.87517099999999,40.896128],"type":"Point"}
}