{
  "type": "Feature",
  "properties": {
    "addr:full":"37 Mercury Ave Patchogue NY 11772",
    "addr:housenumber":"37",
    "addr:postcode":"11772",
    "addr:street":"Mercury Ave",
    "iso:country":"US",
    "sg:address":"37 Mercury Ave",
    "sg:city":"Patchogue",
    "sg:classifiers":[
        {
            "category":"Restaurant",
            "type":"Food & Drink"
        }
    ],
    "sg:phone":"+1   ",
    "sg:postcode":"11772",
    "sg:province":"NY",
    "sg:tags":[
        "drinking",
        "eating"
    ],
    "wof:name":"Lallaco Inc",
    "wof:placetype":"venue"
},
  "geometry": {"coordinates":[-72.96077,40.794205],"type":"Point"}
}