{
  "type": "Feature",
  "properties": {
    "addr:full":"875 3rd Ave New York NY 10022",
    "addr:housenumber":"875",
    "addr:postcode":"10022",
    "addr:street":"3Rd Ave",
    "iso:country":"US",
    "sg:address":"875 3rd Ave",
    "sg:city":"New York",
    "sg:classifiers":[
        {
            "category":"Wholesale",
            "subcategory":"Stationery",
            "type":"Manufacturing & Wholesale Goods"
        }
    ],
    "sg:phone":"+1 212 421 4168",
    "sg:postcode":"10022",
    "sg:province":"NY",
    "sg:tags":[
        "card"
    ],
    "wof:name":"Diamonds Hallmark",
    "wof:placetype":"venue"
},
  "geometry": {"coordinates":[-73.969488,40.757319],"type":"Point"}
}