{
  "type": "Feature",
  "properties": {
    "addr:full":"609 William St Utica NY 13502",
    "addr:housenumber":"609",
    "addr:postcode":"13502",
    "addr:street":"William St",
    "iso:country":"US",
    "sg:address":"609 William St",
    "sg:city":"Utica",
    "sg:classifiers":[
        {
            "category":"Shopping",
            "subcategory":"Hobbies, Toys, & Games",
            "type":"Retail Goods"
        }
    ],
    "sg:phone":"+1 315 735 6761",
    "sg:postcode":"13502",
    "sg:province":"NY",
    "sg:tags":[
        "craft"
    ],
    "wof:name":"Conley's Creations",
    "wof:placetype":"venue"
},
  "geometry": {"coordinates":[-75.24427900000001,43.099239],"type":"Point"}
}