{
  "type": "Feature",
  "properties": {
    "addr:full":"4010 State Hwy 21 Wayland NY 14572",
    "addr:housenumber":"4010",
    "addr:postcode":"14572",
    "addr:street":"State Hwy 21",
    "iso:country":"US",
    "sg:address":"4010 State Hwy 21",
    "sg:city":"Wayland",
    "sg:classifiers":[
        {
            "category":"Farming",
            "subcategory":"Dairy Farm",
            "type":"Manufacturing & Wholesale Goods"
        }
    ],
    "sg:phone":"+1 585 534 5446",
    "sg:postcode":"14572",
    "sg:province":"NY",
    "wof:name":"Deusenbery Farms",
    "wof:placetype":"venue"
},
  "geometry": {"coordinates":[-77.49785199999999,42.564297],"type":"Point"}
}