{
  "type": "Feature",
  "properties": {
    "addr:full":"410 Park Avenue 15th Floor, Suite 1530 New York NY NY 10022",
    "addr:housenumber":"410;15th floor suite 1530",
    "addr:postcode":"10022",
    "addr:street":"Park Avenue",
    "iso:country":"US",
    "sg:address":"410 Park Avenue 15th Floor, Suite 1530",
    "sg:city":"New York",
    "sg:classifiers":[
        {
            "category":"Professional",
            "subcategory":"Business Services",
            "type":"Services"
        }
    ],
    "sg:phone":"+44 20 7952 7500",
    "sg:postcode":"NY 10022",
    "sg:province":"NY",
    "sg:tags":[
        "translation-services",
        "translation-company",
        "localisation",
        "translation-agency",
        "transcreation",
        "first-draft-translation"
    ],
    "sg:website":"http://www.lingo24.com",
    "wof:name":"Lingo24",
    "wof:placetype":"venue"
},
  "geometry": {"coordinates":[-73.971979,40.759954],"type":"Point"}
}