{
  "type": "Feature",
  "properties": {
    "addr:full":"424 E 149th St Bronx NY 10455",
    "addr:housenumber":"424",
    "addr:postcode":"10455",
    "addr:street":"E 149Th St",
    "iso:country":"US",
    "sg:address":"424 E 149th St",
    "sg:city":"Bronx",
    "sg:classifiers":[
        {
            "category":"Restaurant",
            "type":"Food & Drink"
        }
    ],
    "sg:phone":"+1 718 401 1059",
    "sg:postcode":"10455",
    "sg:province":"NY",
    "wof:name":"Laloma Restaurant",
    "wof:placetype":"venue"
},
  "geometry": {"coordinates":[-73.915082,40.814922],"type":"Point"}
}