{
  "type": "Feature",
  "properties": {
    "iso:country":"US",
    "sg:address":"2 Mott St",
    "sg:city":"New York",
    "sg:classifiers":[
        {
            "category":"Professional",
            "subcategory":"Business Services",
            "type":"Services"
        }
    ],
    "sg:phone":"+1 212 732 6405",
    "sg:postcode":"10013",
    "sg:province":"NY",
    "wof:name":"Kitty & Gift",
    "wof:placetype":"venue"
},
  "geometry": {"coordinates":[-73.998796,40.714501],"type":"Point"}
}