{
  "type": "Feature",
  "properties": {
    "addr:full":"20 Maplewood Pl Staten Island NY 10306",
    "addr:housenumber":"20",
    "addr:postcode":"10306",
    "addr:street":"Maplewood Pl",
    "iso:country":"US",
    "sg:address":"20 Maplewood Pl",
    "sg:city":"Staten Island",
    "sg:classifiers":[
        {
            "category":"Building & Trades",
            "subcategory":"Construction",
            "type":"Services"
        }
    ],
    "sg:phone":"+1 718 980 1883",
    "sg:postcode":"10306",
    "sg:province":"NY",
    "sg:tags":[
        "contractor"
    ],
    "wof:name":"Frankie & Johnnys Fence",
    "wof:placetype":"venue"
},
  "geometry": {"coordinates":[-74.104223,40.574595],"type":"Point"}
}