{
  "type": "Feature",
  "properties": {
    "addr:full":"411 George St Ghent NY 12075",
    "addr:housenumber":"411",
    "addr:postcode":"12075",
    "addr:street":"George St",
    "iso:country":"US",
    "sg:address":"411 George St",
    "sg:city":"Ghent",
    "sg:classifiers":[
        {
            "category":"Building & Trades",
            "subcategory":"Electrical",
            "type":"Services"
        }
    ],
    "sg:phone":"+1 518 392 5394",
    "sg:postcode":"12075",
    "sg:province":"NY",
    "sg:tags":[
        "electric",
        "contractor"
    ],
    "wof:name":"David Harris Electrical Contr",
    "wof:placetype":"venue"
},
  "geometry": {"coordinates":[-73.618022,42.325316],"type":"Point"}
}