{
  "type": "Feature",
  "properties": {
    "addr:full":"57 American Ave Coram NY 11727",
    "addr:housenumber":"57",
    "addr:postcode":"11727",
    "addr:street":"American Ave",
    "iso:country":"US",
    "sg:address":"57 American Ave",
    "sg:city":"Coram",
    "sg:classifiers":[
        {
            "category":"Organizations",
            "subcategory":"Professional Association",
            "type":"Services"
        }
    ],
    "sg:phone":"+1 631 698 9321",
    "sg:postcode":"11727",
    "sg:province":"NY",
    "wof:name":"Northast Cram Civic Assioation",
    "wof:placetype":"venue"
},
  "geometry": {"coordinates":[-72.986948,40.887751],"type":"Point"}
}