{
  "type": "Feature",
  "properties": {
    "addr:full":"582 Sand Hill Rd Caledonia NY 14423",
    "addr:housenumber":"582",
    "addr:postcode":"14423",
    "addr:street":"Sand Hill Rd",
    "iso:country":"US",
    "sg:address":"582 Sand Hill Rd",
    "sg:city":"Caledonia",
    "sg:classifiers":[
        {
            "category":"Professional",
            "subcategory":"Business Services",
            "type":"Services"
        }
    ],
    "sg:phone":"+1 585 538 2939",
    "sg:postcode":"14423",
    "sg:province":"NY",
    "sg:tags":[
        "auction"
    ],
    "wof:name":"Pat Hanley Auction Co",
    "wof:placetype":"venue"
},
  "geometry": {"coordinates":[-77.85826900000001,42.960094],"type":"Point"}
}