{
  "type": "Feature",
  "properties": {
    "addr:full":"600 W John St Hicksville NY 11801",
    "addr:housenumber":"600",
    "addr:postcode":"11801",
    "addr:street":"W John St",
    "iso:country":"US",
    "sg:address":"600 W John St",
    "sg:city":"Hicksville",
    "sg:classifiers":[
        {
            "category":"Professional",
            "subcategory":"Management & Consulting",
            "type":"Services"
        }
    ],
    "sg:phone":"+1 516 933 3327",
    "sg:postcode":"11801",
    "sg:province":"NY",
    "sg:tags":[
        "newspaper",
        "delivery"
    ],
    "wof:name":"North Shore News Inc",
    "wof:placetype":"venue"
},
  "geometry": {"coordinates":[-73.54789599999999,40.765333],"type":"Point"}
}