{
  "type": "Feature",
  "properties": {
    "addr:full":"8 Lincoln St Farmingdale NY 11735",
    "addr:housenumber":"8",
    "addr:postcode":"11735",
    "addr:street":"Lincoln St",
    "iso:country":"US",
    "sg:address":"8 Lincoln St",
    "sg:city":"Farmingdale",
    "sg:classifiers":[
        {
            "category":"Travel",
            "subcategory":"Travel Agent",
            "type":"Entertainment"
        }
    ],
    "sg:phone":"+1 516 753 9235",
    "sg:postcode":"11735",
    "sg:province":"NY",
    "sg:tags":[
        "agency",
        "bureau"
    ],
    "wof:name":"Enchantment Travel",
    "wof:placetype":"venue"
},
  "geometry": {"coordinates":[-73.434189,40.708358],"type":"Point"}
}