{
  "type": "Feature",
  "properties": {
    "addr:full":"20 Ellicott Pl Batavia NY 14020",
    "addr:housenumber":"20",
    "addr:postcode":"14020",
    "addr:street":"Ellicott Pl",
    "iso:country":"US",
    "sg:address":"20 Ellicott Pl",
    "sg:city":"Batavia",
    "sg:classifiers":[
        {
            "category":"Retail",
            "subcategory":"Laundry & Dry Cleaning",
            "type":"Services"
        }
    ],
    "sg:phone":"+1 585 343 0912",
    "sg:postcode":"14020",
    "sg:province":"NY",
    "sg:tags":[
        "linen",
        "supply"
    ],
    "wof:name":"Uniform Shop The",
    "wof:placetype":"venue"
},
  "geometry": {"coordinates":[-78.175234,42.991144],"type":"Point"}
}