{
  "type": "Feature",
  "properties": {
    "addr:full":"1 River Rd Bronx NY 10463",
    "addr:housenumber":"1",
    "addr:postcode":"10463",
    "addr:street":"River Rd",
    "iso:country":"US",
    "sg:address":"1 River Rd",
    "sg:city":"Bronx",
    "sg:classifiers":[
        {
            "category":"Government",
            "subcategory":"Office",
            "type":"Public Place"
        }
    ],
    "sg:phone":"+1 718 379 8347",
    "sg:postcode":"10463",
    "sg:province":"NY",
    "sg:tags":[
        "village"
    ],
    "wof:name":"Haffen Park Play Ctr",
    "wof:placetype":"venue"
},
  "geometry": {"coordinates":[-73.919687,40.885785],"type":"Point"}
}