{
  "type": "Feature",
  "properties": {
    "addr:full":"89 Hidden Brook Dr Beacon NY 12538",
    "addr:housenumber":"89",
    "addr:postcode":"12538",
    "addr:street":"Hidden Brook Dr",
    "iso:country":"US",
    "sg:address":"89 Hidden Brook Dr",
    "sg:city":"Beacon",
    "sg:classifiers":[
        {
            "category":"Organizations",
            "subcategory":"Religious Organization",
            "type":"Services"
        }
    ],
    "sg:phone":"+1 845 831 5572",
    "sg:postcode":"12538",
    "sg:province":"NY",
    "wof:name":"Discalced Nuns of Carmelite",
    "wof:placetype":"venue"
},
  "geometry": {"coordinates":[-73.907376,41.780469],"type":"Point"}
}