{
  "type": "Feature",
  "properties": {
    "iso:country":"US",
    "sg:address":"91 Broadway",
    "sg:city":"Greenlawn",
    "sg:classifiers":[
        {
            "category":"Shopping",
            "subcategory":"Musical Instruments",
            "type":"Retail Goods"
        }
    ],
    "sg:phone":"+1 631 754 4100",
    "sg:postcode":"11740",
    "sg:province":"NY",
    "sg:tags":[
        "teacher"
    ],
    "wof:name":"Piano Studio the",
    "wof:placetype":"venue"
},
  "geometry": {"coordinates":[-73.364403,40.866299],"type":"Point"}
}