{
  "type": "Feature",
  "properties": {
    "iso:country":"US",
    "sg:address":"482 Sills Rd",
    "sg:city":"Yaphank",
    "sg:classifiers":[
        {
            "category":"Autos & Motor Vehicles",
            "subcategory":"Fuel & Gas Station",
            "type":"Retail Goods"
        }
    ],
    "sg:phone":"+1   ",
    "sg:postcode":"11980",
    "sg:province":"NY",
    "sg:tags":[
        "station",
        "gasoline"
    ],
    "wof:name":"Star Advantage Management",
    "wof:placetype":"venue"
},
  "geometry": {"coordinates":[-72.95716,40.805029],"type":"Point"}
}