{
  "type": "Feature",
  "properties": {
    "iso:country":"US",
    "sg:address":"6375 Furnace Rd",
    "sg:city":"Ontario",
    "sg:classifiers":[
        {
            "category":"Building & Trades",
            "subcategory":"Construction",
            "type":"Services"
        }
    ],
    "sg:phone":"+1 315 524 4674",
    "sg:postcode":"14519",
    "sg:province":"NY",
    "sg:tags":[
        "excavating",
        "contractor"
    ],
    "wof:name":"Burrows Brothers",
    "wof:placetype":"venue"
},
  "geometry": {"coordinates":[-77.278143,43.230694],"type":"Point"}
}