{
  "type": "Feature",
  "properties": {
    "addr:full":"7 Gale Dr Valley Stream NY 11581",
    "addr:housenumber":"7",
    "addr:postcode":"11581",
    "addr:street":"Gale Dr",
    "iso:country":"US",
    "sg:address":"7 Gale Dr",
    "sg:city":"Valley Stream",
    "sg:classifiers":[
        {
            "category":"Organizations",
            "subcategory":"Non-profit Organization",
            "type":"Services"
        }
    ],
    "sg:phone":"+1 516 374 1130",
    "sg:postcode":"11581",
    "sg:province":"NY",
    "sg:tags":[
        "fund",
        "counselor",
        "raising"
    ],
    "wof:name":"25th Century Communications",
    "wof:placetype":"venue"
},
  "geometry": {"coordinates":[-73.720421,40.645362],"type":"Point"}
}