{
  "type": "Feature",
  "properties": {
    "addr:full":"391 Eggert Rd Buffalo NY 14215",
    "addr:housenumber":"391",
    "addr:postcode":"14215",
    "addr:street":"Eggert Rd",
    "iso:country":"US",
    "sg:address":"391 Eggert Rd",
    "sg:city":"Buffalo",
    "sg:classifiers":[
        {
            "category":"Real Estate",
            "subcategory":"Real Estate Services",
            "type":"Services"
        },
        {
            "category":"Real Estate",
            "subcategory":"Real Estate Operator",
            "type":"Services"
        },
        {
            "category":"Travel",
            "subcategory":"Hotels & Motels",
            "type":"Entertainment"
        }
    ],
    "sg:phone":"+1 716 833 3700",
    "sg:postcode":"14215",
    "sg:province":"NY",
    "sg:tags":[
        "boarding",
        "house",
        "apartment",
        "hotels-apartment"
    ],
    "sg:website":"http://www.cvwny.com",
    "wof:name":"Collegiate Village",
    "wof:placetype":"venue"
},
  "geometry": {"coordinates":[-78.799088,42.938011],"type":"Point"}
}