{
  "type": "Feature",
  "properties": {
    "iso:country":"US",
    "sg:address":"282 Main St",
    "sg:city":"Johnson City",
    "sg:classifiers":[
        {
            "category":"Personal",
            "subcategory":"Barber",
            "type":"Services"
        }
    ],
    "sg:phone":"+1 607 729 8390",
    "sg:postcode":"13790",
    "sg:province":"NY",
    "wof:name":"New York Styles",
    "wof:placetype":"venue"
},
  "geometry": {"coordinates":[-75.956327,42.115437],"type":"Point"}
}