{
  "type": "Feature",
  "properties": {
    "iso:country":"US",
    "sg:address":"14 Crestview Dr",
    "sg:city":"Northport",
    "sg:classifiers":[
        {
            "category":"Professional",
            "subcategory":"Advertising",
            "type":"Services"
        }
    ],
    "sg:phone":"+1   ",
    "sg:postcode":"11768",
    "sg:province":"NY",
    "sg:tags":[
        "agency",
        "business"
    ],
    "wof:name":"Advertising Svs of Long Island",
    "wof:placetype":"venue"
},
  "geometry": {"coordinates":[-73.29832,40.903619],"type":"Point"}
}