{
  "type": "Feature",
  "properties": {
    "iso:country":"US",
    "sg:address":"438 Main St",
    "sg:city":"Medina",
    "sg:classifiers":[
        {
            "category":"Shopping",
            "subcategory":"Shoes",
            "type":"Retail Goods"
        }
    ],
    "sg:phone":"+1 585 798 3550",
    "sg:postcode":"14103",
    "sg:province":"NY",
    "wof:name":"Baughn's Shoe Store",
    "wof:placetype":"venue"
},
  "geometry": {"coordinates":[-78.38701500000001,43.220659],"type":"Point"}
}