{
  "type": "Feature",
  "properties": {
    "iso:country":"US",
    "sg:address":"711 Troy Schenectady Rd Ste 212",
    "sg:city":"Latham",
    "sg:classifiers":[
        {
            "category":"Manufacturing",
            "subcategory":"Chemicals & Compounds",
            "type":"Manufacturing & Wholesale Goods"
        },
        {
            "category":"Personal",
            "subcategory":"Beauty Salon",
            "type":"Services"
        },
        {
            "category":"Shopping",
            "subcategory":"Beauty & Cosmetics",
            "type":"Retail Goods"
        }
    ],
    "sg:phone":"+1 518 782 1919",
    "sg:postcode":"12110",
    "sg:province":"NY",
    "sg:tags":[
        "hair",
        "electrolysis",
        "stylist",
        "perfume"
    ],
    "wof:name":"Hair Goes Inc",
    "wof:placetype":"venue"
},
  "geometry": {"coordinates":[-73.777103,42.7565],"type":"Point"}
}