{
  "type": "Feature",
  "properties": {
    "addr:full":"502 Avenue P Brooklyn NY 11223",
    "addr:housenumber":"502",
    "addr:postcode":"11223",
    "addr:street":"Avenue P",
    "iso:country":"US",
    "sg:address":"502 Avenue P",
    "sg:city":"Brooklyn",
    "sg:classifiers":[
        {
            "category":"Retail",
            "subcategory":"Auto Repair",
            "type":"Services"
        }
    ],
    "sg:phone":"+1 718 998 9113",
    "sg:postcode":"11223",
    "sg:province":"NY",
    "wof:name":"Avenue P Auto Collision Repair Inc",
    "wof:placetype":"venue"
},
  "geometry": {"coordinates":[-73.968597,40.6092],"type":"Point"}
}