{
  "type": "Feature",
  "properties": {
    "iso:country":"US",
    "sg:address":"203 S Columbus Ave",
    "sg:city":"Mount Vernon",
    "sg:classifiers":[
        {
            "category":"Real Estate",
            "subcategory":"Real Estate Operator",
            "type":"Services"
        }
    ],
    "sg:phone":"+1 914 664 7336",
    "sg:postcode":"10553",
    "sg:province":"NY",
    "sg:tags":[
        "building",
        "ope",
        "apartment",
        "nonresidential"
    ],
    "wof:name":"Cocozza Association Inc",
    "wof:placetype":"venue"
},
  "geometry": {"coordinates":[-73.822092,40.91036],"type":"Point"}
}