{
  "type": "Feature",
  "properties": {
    "addr:full":"768 Bedford Ave Brooklyn NY 11205",
    "addr:housenumber":"768",
    "addr:postcode":"11205",
    "addr:street":"Bedford Ave",
    "iso:country":"US",
    "sg:address":"768 Bedford Ave",
    "sg:city":"Brooklyn",
    "sg:classifiers":[
        {
            "category":"Professional",
            "subcategory":"Accounting & Tax Preparation",
            "type":"Services"
        }
    ],
    "sg:phone":"+1 718 522 2000",
    "sg:postcode":"11205",
    "sg:province":"NY",
    "sg:tags":[
        "payroll"
    ],
    "sg:website":"www.bdbpayroll.com",
    "wof:name":"Broadway Database Inc",
    "wof:placetype":"venue"
},
  "geometry": {"coordinates":[-73.95680900000001,40.697784],"type":"Point"}
}