{
  "type": "Feature",
  "properties": {
    "iso:country":"US",
    "sg:address":"15 Hill Rd",
    "sg:city":"Stillwater",
    "sg:classifiers":[
        {
            "category":"Professional",
            "subcategory":"Management & Consulting",
            "type":"Services"
        }
    ],
    "sg:phone":"+1 518 584 7715",
    "sg:postcode":"12170",
    "sg:province":"NY",
    "sg:tags":[
        "business"
    ],
    "wof:name":"Profit Planning Associates",
    "wof:placetype":"venue"
},
  "geometry": {"coordinates":[-73.715036,43.028672],"type":"Point"}
}