{
  "type": "Feature",
  "properties": {
    "addr:full":"2347 Central Park Ave Yonkers NY 10710",
    "addr:housenumber":"2347",
    "addr:postcode":"10710",
    "addr:street":"Central Park Ave",
    "iso:country":"US",
    "sg:address":"2347 Central Park Ave",
    "sg:city":"Yonkers",
    "sg:classifiers":[
        {
            "category":"Shopping",
            "subcategory":"Computers & Home Electronics",
            "type":"Retail Goods"
        }
    ],
    "sg:phone":"+1   ",
    "sg:postcode":"10710",
    "sg:province":"NY",
    "sg:website":"www.gamestop.com",
    "wof:name":"Gamestop",
    "wof:placetype":"venue"
},
  "geometry": {"coordinates":[-73.830579,40.979151],"type":"Point"}
}