{
  "type": "Feature",
  "properties": {
    "iso:country":"US",
    "sg:address":"97 Broadway",
    "sg:city":"Greenlawn",
    "sg:classifiers":[
        {
            "category":"Real Estate",
            "subcategory":"Real Estate Services",
            "type":"Services"
        }
    ],
    "sg:phone":"+1 631 262 1826",
    "sg:postcode":"11740",
    "sg:province":"NY",
    "sg:tags":[
        "abstract",
        "title"
    ],
    "wof:name":"GSk Associates Inc",
    "wof:placetype":"venue"
},
  "geometry": {"coordinates":[-73.36443199999999,40.865852],"type":"Point"}
}