{
  "type": "Feature",
  "properties": {
    "addr:full":"106 Forsyth St New York NY 10002",
    "addr:housenumber":"106",
    "addr:postcode":"10002",
    "addr:street":"Forsyth St",
    "iso:country":"US",
    "sg:address":"106 Forsyth St",
    "sg:city":"New York",
    "sg:classifiers":[
        {
            "category":"Professional",
            "type":"Services"
        }
    ],
    "sg:phone":"+1 212 966 8782",
    "sg:postcode":"10002",
    "sg:province":"NY",
    "sg:tags":[
        "establishment"
    ],
    "wof:name":"Crust Bakery & Cafe",
    "wof:placetype":"venue"
},
  "geometry": {"coordinates":[-73.99286499999999,40.718011],"type":"Point"}
}