{
  "type": "Feature",
  "properties": {
    "iso:country":"US",
    "sg:address":"2963 Main St",
    "sg:city":"Buffalo",
    "sg:classifiers":[
        {
            "category":"Government",
            "subcategory":"Office",
            "type":"Public Place"
        }
    ],
    "sg:phone":"+1 716 834 4270",
    "sg:postcode":"14214",
    "sg:province":"NY",
    "sg:tags":[
        "affair",
        "c",
        "administrative",
        "outpatient",
        "specialty"
    ],
    "sg:website":"http://www.va.gov/health/",
    "wof:name":"V A Day Treatment Center",
    "wof:placetype":"venue"
},
  "geometry": {"coordinates":[-78.831309,42.94632],"type":"Point"}
}