{
  "type": "Feature",
  "properties": {
    "addr:full":"110-15 101 Ave New York NY 11419",
    "addr:housenumber":"110-15",
    "addr:postcode":"11419",
    "addr:street":"101 Ave",
    "iso:country":"US",
    "sg:address":"110-15 101 Ave",
    "sg:city":"New York",
    "sg:classifiers":[
        {
            "category":"Restaurant",
            "type":"Food & Drink"
        }
    ],
    "sg:phone":"+1 718 441 5484",
    "sg:postcode":"11419",
    "sg:province":"NY",
    "sg:tags":[
        "indian"
    ],
    "sg:website":"www.noveltyny.com",
    "wof:name":"Novelty Indian Restaurant",
    "wof:placetype":"venue"
},
  "geometry": {"coordinates":[-73.83324399999999,40.688142],"type":"Point"}
}