{
  "type": "Feature",
  "properties": {
    "iso:country":"US",
    "sg:address":"2 Depot St",
    "sg:city":"Friendship",
    "sg:classifiers":[
        {
            "category":"Personal",
            "subcategory":"Beauty Salon",
            "type":"Services"
        }
    ],
    "sg:phone":"+1 585 973 3359",
    "sg:postcode":"14739",
    "sg:province":"NY",
    "wof:name":"Pure Magic",
    "wof:placetype":"venue"
},
  "geometry": {"coordinates":[-78.13449199999999,42.208847],"type":"Point"}
}