{
  "type": "Feature",
  "properties": {
    "iso:country":"US",
    "sg:address":"8133 Navona Ln",
    "sg:city":"Clay",
    "sg:classifiers":[
        {
            "category":"Professional",
            "subcategory":"Management & Consulting",
            "type":"Services"
        }
    ],
    "sg:phone":"+1   ",
    "sg:postcode":"13041",
    "sg:province":"NY",
    "sg:tags":[
        "retail",
        "direct",
        "sales"
    ],
    "wof:name":"Cynthia L Dromms",
    "wof:placetype":"venue"
},
  "geometry": {"coordinates":[-76.136331,43.164115],"type":"Point"}
}