{
  "type": "Feature",
  "properties": {
    "addr:full":"301 N Broadway Jericho NY 11753",
    "addr:housenumber":"301",
    "addr:postcode":"11753",
    "addr:street":"N Broadway",
    "iso:country":"US",
    "sg:address":"301 N Broadway",
    "sg:city":"Jericho",
    "sg:classifiers":[
        {
            "category":"Professional",
            "subcategory":"Lawyer & Legal Services",
            "type":"Services"
        }
    ],
    "sg:phone":"+1 516 938 6700",
    "sg:postcode":"11753",
    "sg:province":"NY",
    "sg:tags":[
        "attorney"
    ],
    "wof:name":"KAUR Krishna & Sharley",
    "wof:placetype":"venue"
},
  "geometry": {"coordinates":[-73.537042,40.789983],"type":"Point"}
}