{
  "type": "Feature",
  "properties": {
    "iso:country":"US",
    "sg:address":"320 Main St",
    "sg:city":"Mt Kisco",
    "sg:classifiers":[
        {
            "category":"Autos & Motor Vehicles",
            "subcategory":"Automobile Sales",
            "type":"Retail Goods"
        }
    ],
    "sg:phone":"+1 914 666 9031",
    "sg:postcode":"10549",
    "sg:province":"NY",
    "sg:tags":[
        "car",
        "dealer"
    ],
    "wof:name":"Jacksons Auto Radiators",
    "wof:placetype":"venue"
},
  "geometry": {"coordinates":[-73.725117,41.199074],"type":"Point"}
}