{
  "type": "Feature",
  "properties": {
    "iso:country":"US",
    "sg:address":"13967 Four Mile Level Rd",
    "sg:city":"Gowanda",
    "sg:classifiers":[
        {
            "category":"Shopping",
            "subcategory":"Tobacco",
            "type":"Retail Goods"
        }
    ],
    "sg:phone":"+1 716 532 5941",
    "sg:postcode":"14070",
    "sg:province":"NY",
    "sg:tags":[
        "cigarette",
        "cigar",
        "dealer"
    ],
    "wof:name":"R K Kartons",
    "wof:placetype":"venue"
},
  "geometry": {"coordinates":[-78.94091400000001,42.480113],"type":"Point"}
}