{
  "type": "Feature",
  "properties": {
    "addr:full":"285 Bond St Brooklyn NY 11217",
    "addr:housenumber":"285",
    "addr:postcode":"11217",
    "addr:street":"Bond St",
    "iso:country":"US",
    "sg:address":"285 Bond St",
    "sg:city":"Brooklyn",
    "sg:phone":"+1 718 875 9462",
    "sg:postcode":"11217",
    "sg:province":"NY",
    "sg:tags":[
        "oil"
    ],
    "wof:name":"Bayside Fuel Corp",
    "wof:placetype":"venue"
},
  "geometry": {"coordinates":[-73.988699,40.681217],"type":"Point"}
}