{
  "type": "Feature",
  "properties": {
    "addr:full":"1641 Metropolitan Ave Bronx NY 10462",
    "addr:housenumber":"1641",
    "addr:postcode":"10462",
    "addr:street":"Metropolitan Ave",
    "iso:country":"US",
    "sg:address":"1641 Metropolitan Ave",
    "sg:city":"Bronx",
    "sg:classifiers":[
        {
            "category":"Real Estate",
            "subcategory":"Real Estate Services",
            "type":"Services"
        },
        {
            "category":"Real Estate",
            "subcategory":"Real Estate Agent",
            "type":"Services"
        }
    ],
    "sg:phone":"+1 718 892 7601",
    "sg:postcode":"10462",
    "sg:province":"NY",
    "sg:tags":[
        "buyer",
        "broker"
    ],
    "wof:name":"Grenadier Realty Corporation",
    "wof:placetype":"venue"
},
  "geometry": {"coordinates":[-73.85586600000001,40.840488],"type":"Point"}
}