{
  "type": "Feature",
  "properties": {
    "addr:full":"7892 Oak Orchard Rd Batavia NY 14020",
    "addr:housenumber":"7892",
    "addr:postcode":"14020",
    "addr:street":"Oak Orchard Rd",
    "iso:country":"US",
    "sg:address":"7892 Oak Orchard Rd",
    "sg:city":"Batavia",
    "sg:classifiers":[
        {
            "category":"Professional",
            "type":"Services"
        }
    ],
    "sg:phone":"+1 585 343 1855",
    "sg:postcode":"14020",
    "sg:province":"NY",
    "sg:tags":[
        "establishment"
    ],
    "wof:name":"Offhaus",
    "wof:placetype":"venue"
},
  "geometry": {"coordinates":[-78.19236600000001,43.030544],"type":"Point"}
}