{
  "type": "Feature",
  "properties": {
    "addr:full":"1333 Flushing Ave Brooklyn NY 11237",
    "addr:housenumber":"1333",
    "addr:postcode":"11237",
    "addr:street":"Flushing Ave",
    "iso:country":"US",
    "sg:address":"1333 Flushing Ave",
    "sg:city":"Brooklyn",
    "sg:classifiers":[
        {
            "category":"Shopping",
            "subcategory":"Discount & Variety Stores",
            "type":"Retail Goods"
        }
    ],
    "sg:phone":"+1 718 456 4567",
    "sg:postcode":"11237",
    "sg:province":"NY",
    "sg:tags":[
        "merchandise",
        "general"
    ],
    "wof:name":"Air Side Products Sales",
    "wof:placetype":"venue"
},
  "geometry": {"coordinates":[-73.921367,40.709707],"type":"Point"}
}