{
  "type": "Feature",
  "properties": {
    "iso:country":"US",
    "sg:address":"1408 Chestnut St",
    "sg:city":"Watervliet",
    "sg:classifiers":[
        {
            "category":"Building & Trades",
            "subcategory":"Construction",
            "type":"Services"
        }
    ],
    "sg:phone":"+1 518 271 6540",
    "sg:postcode":"12189",
    "sg:province":"NY",
    "sg:tags":[
        "house"
    ],
    "wof:name":"Popular Builders",
    "wof:placetype":"venue"
},
  "geometry": {"coordinates":[-73.711359,42.727404],"type":"Point"}
}