{
  "type": "Feature",
  "properties": {
    "addr:full":"2 Bird Ln Hicksville NY 11801",
    "addr:housenumber":"2",
    "addr:postcode":"11801",
    "addr:street":"Bird Ln",
    "iso:country":"US",
    "sg:address":"2 Bird Ln",
    "sg:city":"Hicksville",
    "sg:classifiers":[
        {
            "category":"Building & Trades",
            "subcategory":"Landscaping Services",
            "type":"Services"
        }
    ],
    "sg:phone":"+1 516 933 2627",
    "sg:postcode":"11801",
    "sg:province":"NY",
    "wof:name":"Imperial Ldscpg of Long Island",
    "wof:placetype":"venue"
},
  "geometry": {"coordinates":[-73.53592999999999,40.748152],"type":"Point"}
}