{
  "type": "Feature",
  "properties": {
    "addr:full":"8645 Roll Rd Clarence Center NY 14032",
    "addr:housenumber":"8645",
    "addr:postcode":"14032",
    "addr:street":"Roll Rd",
    "iso:country":"US",
    "sg:address":"8645 Roll Rd",
    "sg:city":"Clarence Center",
    "sg:classifiers":[
        {
            "category":"Manufacturing",
            "subcategory":"Rubber & Plastics",
            "type":"Manufacturing & Wholesale Goods"
        }
    ],
    "sg:phone":"+1   ",
    "sg:postcode":"14032",
    "sg:province":"NY",
    "sg:tags":[
        "building",
        "mfg",
        "material",
        "sid",
        "gutter"
    ],
    "wof:name":"Stockmohr Company",
    "wof:placetype":"venue"
},
  "geometry": {"coordinates":[-78.672309,43.000182],"type":"Point"}
}