{
  "type": "Feature",
  "properties": {
    "addr:full":"5508 Sunrise Hwy Massapequa NY 11758",
    "addr:housenumber":"5508",
    "addr:postcode":"11758",
    "addr:street":"Sunrise Hwy",
    "iso:country":"US",
    "sg:address":"5508 Sunrise Hwy",
    "sg:city":"Massapequa",
    "sg:classifiers":[
        {
            "category":"Shopping",
            "subcategory":"Clothing, Apparel, & Fashions",
            "type":"Retail Goods"
        }
    ],
    "sg:phone":"+1   ",
    "sg:postcode":"11758",
    "sg:province":"NY",
    "wof:name":"Zoeys",
    "wof:placetype":"venue"
},
  "geometry": {"coordinates":[-73.432624,40.679766],"type":"Point"}
}