{
  "type": "Feature",
  "properties": {
    "addr:full":"8309 State Hwy 20A Honeoye NY 14471",
    "addr:housenumber":"8309",
    "addr:postcode":"14471",
    "addr:street":"State Hwy 20A",
    "iso:country":"US",
    "sg:address":"8309 State Hwy 20A",
    "sg:city":"Honeoye",
    "sg:classifiers":[
        {
            "category":"Retail",
            "subcategory":"Portrait Studio",
            "type":"Services"
        }
    ],
    "sg:phone":"+1 585 229 5553",
    "sg:postcode":"14471",
    "sg:province":"NY",
    "sg:tags":[
        "photographer"
    ],
    "wof:name":"Angel Lite Images",
    "wof:placetype":"venue"
},
  "geometry": {"coordinates":[-77.491106,42.796254],"type":"Point"}
}