{
  "type": "Feature",
  "properties": {
    "addr:full":"3200 Elmwood Ave Buffalo NY 14217",
    "addr:housenumber":"3200",
    "addr:postcode":"14217",
    "addr:street":"Elmwood Ave",
    "iso:country":"US",
    "sg:address":"3200 Elmwood Ave",
    "sg:city":"Buffalo",
    "sg:classifiers":[
        {
            "category":"Government",
            "subcategory":"Office",
            "type":"Public Place"
        }
    ],
    "sg:phone":"+1 716 877 3986",
    "sg:postcode":"14217",
    "sg:province":"NY",
    "sg:tags":[
        "general"
    ],
    "wof:name":"Charles M Swanick Erie",
    "wof:placetype":"venue"
},
  "geometry": {"coordinates":[-78.87871800000001,42.984164],"type":"Point"}
}