{
  "type": "Feature",
  "properties": {
    "iso:country":"US",
    "sg:address":"526 Grooms Rd",
    "sg:city":"Clifton Park",
    "sg:classifiers":[
        {
            "category":"Autos & Motor Vehicles",
            "subcategory":"Automobile Sales",
            "type":"Retail Goods"
        }
    ],
    "sg:phone":"+1 518 371 1373",
    "sg:postcode":"12065",
    "sg:province":"NY",
    "sg:tags":[
        "wholesale",
        "used"
    ],
    "wof:name":"J R Used Cars",
    "wof:placetype":"venue"
},
  "geometry": {"coordinates":[-73.789258,42.839853],"type":"Point"}
}