{
  "type": "Feature",
  "properties": {
    "addr:full":"1650 Broadway Suite 607 New York NY 10019",
    "addr:housenumber":"1650;suite 607",
    "addr:postcode":"10019",
    "addr:street":"Broadway",
    "iso:country":"US",
    "sg:address":"1650 Broadway Suite 607",
    "sg:city":"New York",
    "sg:classifiers":[
        {
            "category":"Professional",
            "subcategory":"Computer Services",
            "type":"Services"
        }
    ],
    "sg:phone":"+1 212 765 9555",
    "sg:postcode":"10019",
    "sg:province":"NY",
    "sg:tags":[
        "repair"
    ],
    "sg:website":"www.pc-doctor911.com",
    "wof:name":"PC Doctor",
    "wof:placetype":"venue"
},
  "geometry": {"coordinates":[-73.983549,40.761942],"type":"Point"}
}