{
  "type": "Feature",
  "properties": {
    "iso:country":"US",
    "sg:address":"14234 Ridge Rd W",
    "sg:city":"Albion",
    "sg:classifiers":[
        {
            "category":"Freight",
            "type":"Transportation"
        }
    ],
    "sg:phone":"+1 585 589 7695",
    "sg:postcode":"14411",
    "sg:province":"NY",
    "sg:tags":[
        "warehouse",
        "storage"
    ],
    "wof:name":"Lake Ontario Fruit Inc",
    "wof:placetype":"venue"
},
  "geometry": {"coordinates":[-78.193079,43.286657],"type":"Point"}
}