{
  "type": "Feature",
  "properties": {
    "addr:full":"94 Virginia Rd White Plains NY 10603",
    "addr:housenumber":"94",
    "addr:postcode":"10603",
    "addr:street":"Virginia Rd",
    "iso:country":"US",
    "sg:address":"94 Virginia Rd",
    "sg:city":"White Plains",
    "sg:classifiers":[
        {
            "category":"Food & Beverages",
            "subcategory":"Liquor & Beverages",
            "type":"Retail Goods"
        }
    ],
    "sg:phone":"+1 914 428 8540",
    "sg:postcode":"10603",
    "sg:province":"NY",
    "sg:tags":[
        "beer",
        "spirit",
        "wine"
    ],
    "sg:website":"www.aspiritforeveryseason.com",
    "wof:name":"A Spirit For Every Season",
    "wof:placetype":"venue"
},
  "geometry": {"coordinates":[-73.77798799999999,41.472333],"type":"Point"}
}