{
  "type": "Feature",
  "properties": {
    "iso:country":"US",
    "sg:address":"7936 Seneca Tpke",
    "sg:city":"Clinton",
    "sg:classifiers":[
        {
            "category":"Wholesale",
            "subcategory":"Electrical",
            "type":"Manufacturing & Wholesale Goods"
        }
    ],
    "sg:phone":"+1 315 738 9722",
    "sg:postcode":"13323",
    "sg:province":"NY",
    "sg:tags":[
        "equipment",
        "security",
        "system"
    ],
    "wof:name":"Simplex Time Recorder 199",
    "wof:placetype":"venue"
},
  "geometry": {"coordinates":[-75.338937,43.084066],"type":"Point"}
}