{
  "type": "Feature",
  "properties": {
    "addr:full":"628 Fulton Ave Angola NY 14006",
    "addr:housenumber":"628",
    "addr:postcode":"14006",
    "addr:street":"Fulton Ave",
    "iso:country":"US",
    "sg:address":"628 Fulton Ave",
    "sg:city":"Angola",
    "sg:classifiers":[
        {
            "category":"Professional",
            "subcategory":"Lawyer & Legal Services",
            "type":"Services"
        }
    ],
    "sg:phone":"+1 716 549 5020",
    "sg:postcode":"14006",
    "sg:province":"NY",
    "sg:tags":[
        "attorney"
    ],
    "wof:name":"Maloney Joan E Atty Summer",
    "wof:placetype":"venue"
},
  "geometry": {"coordinates":[-79.061702,42.653252],"type":"Point"}
}