{
  "type": "Feature",
  "properties": {
    "iso:country":"US",
    "sg:address":"227 Knickerbocker Ave",
    "sg:city":"Bohemia",
    "sg:classifiers":[
        {
            "category":"Food & Beverages",
            "subcategory":"Groceries & Convenience Stores",
            "type":"Retail Goods"
        }
    ],
    "sg:phone":"+1 631 589 5250",
    "sg:postcode":"11716",
    "sg:province":"NY",
    "sg:tags":[
        "product"
    ],
    "wof:name":"Odyssey Foods Inc",
    "wof:placetype":"venue"
},
  "geometry": {"coordinates":[-73.087254,40.776204],"type":"Point"}
}