{
  "type": "Feature",
  "properties": {
    "addr:full":"270 W 17 St New York NY 10011",
    "addr:housenumber":"270",
    "addr:postcode":"10011",
    "addr:street":"W 17 St",
    "iso:country":"US",
    "sg:address":"270 W 17 St",
    "sg:city":"New York",
    "sg:classifiers":[
        {
            "category":"Health Services",
            "subcategory":"Doctor",
            "type":"Services"
        }
    ],
    "sg:phone":"+1   ",
    "sg:postcode":"10011",
    "sg:province":"NY",
    "wof:name":"Andre J Singer",
    "wof:placetype":"venue"
},
  "geometry": {"coordinates":[-73.99962600000001,40.740746],"type":"Point"}
}