{
  "type": "Feature",
  "properties": {
    "iso:country":"US",
    "sg:address":"299 Park Ave Fl 28",
    "sg:city":"New York",
    "sg:classifiers":[
        {
            "category":"Food & Beverages",
            "subcategory":"Groceries & Convenience Stores",
            "type":"Retail Goods"
        }
    ],
    "sg:phone":"+1 212 888 8590",
    "sg:postcode":"10171",
    "sg:province":"NY",
    "wof:name":"Marketaxess",
    "wof:placetype":"venue"
},
  "geometry": {"coordinates":[-73.974493,40.756173],"type":"Point"}
}