{
  "type": "Feature",
  "properties": {
    "addr:full":"3 Kisco Ave Mt Kisco NY 10549",
    "addr:housenumber":"3",
    "addr:postcode":"10549",
    "addr:street":"Kisco Ave Mt Kisco",
    "iso:country":"US",
    "sg:address":"3 Kisco Ave",
    "sg:city":"Mt Kisco",
    "sg:classifiers":[
        {
            "category":"Organizations",
            "subcategory":"Religious Organization",
            "type":"Services"
        }
    ],
    "sg:phone":"+1 914 244 7235",
    "sg:postcode":"10549",
    "sg:province":"NY",
    "sg:tags":[
        "church"
    ],
    "wof:name":"St Francis AME Zion Church",
    "wof:placetype":"venue"
},
  "geometry": {"coordinates":[-73.728886,41.210058],"type":"Point"}
}