{
  "type": "Feature",
  "properties": {
    "addr:full":"47 E Deer Park Rd Dix Hills NY 11746",
    "addr:housenumber":"47",
    "addr:postcode":"11746",
    "addr:street":"E Deer Park Rd",
    "iso:country":"US",
    "sg:address":"47 E Deer Park Rd",
    "sg:city":"Dix Hills",
    "sg:classifiers":[
        {
            "category":"Utilities",
            "subcategory":"Fuel Oil & Lpg",
            "type":"Services"
        }
    ],
    "sg:phone":"+1 631 395 9835",
    "sg:postcode":"11746",
    "sg:province":"NY",
    "sg:tags":[
        "firewood"
    ],
    "wof:name":"Prune-A-Tree",
    "wof:placetype":"venue"
},
  "geometry": {"coordinates":[-73.336585,40.833507],"type":"Point"}
}