{
  "type": "Feature",
  "properties": {
    "iso:country":"US",
    "sg:address":"2799 Southwestern Blvd",
    "sg:city":"Orchard Park",
    "sg:classifiers":[
        {
            "category":"Shopping",
            "subcategory":"Gifts & Souvenirs",
            "type":"Retail Goods"
        }
    ],
    "sg:phone":"+1 716 675 1986",
    "sg:postcode":"14127",
    "sg:province":"NY",
    "sg:tags":[
        "shop"
    ],
    "wof:name":"Animal Kingdom Supplies & Gift",
    "wof:placetype":"venue"
},
  "geometry": {"coordinates":[-78.72224300000001,42.811191],"type":"Point"}
}