{
  "type": "Feature",
  "properties": {
    "iso:country":"US",
    "sg:address":"3526 150th Pl",
    "sg:city":"Flushing",
    "sg:classifiers":[
        {
            "category":"Real Estate",
            "subcategory":"Real Estate Services",
            "type":"Services"
        }
    ],
    "sg:phone":"+1 718 939 3799",
    "sg:postcode":"11354",
    "sg:province":"NY",
    "sg:tags":[
        "management",
        "property"
    ],
    "wof:name":"Marica Enterprises Incorporated",
    "wof:placetype":"venue"
},
  "geometry": {"coordinates":[-73.814396,40.766222],"type":"Point"}
}