{
  "type": "Feature",
  "properties": {
    "addr:full":"101 Eastwood Blvd Centereach NY 11720",
    "addr:housenumber":"101",
    "addr:postcode":"11720",
    "addr:street":"Eastwood Blvd",
    "iso:country":"US",
    "sg:address":"101 Eastwood Blvd",
    "sg:city":"Centereach",
    "sg:classifiers":[
        {
            "category":"Organizations",
            "subcategory":"Non-profit Organization",
            "type":"Services"
        }
    ],
    "sg:phone":"+1 631 585 9393",
    "sg:postcode":"11720",
    "sg:province":"NY",
    "sg:tags":[
        "fund",
        "raising"
    ],
    "wof:name":"Mcl Foundation",
    "wof:placetype":"venue"
},
  "geometry": {"coordinates":[-73.07920799999999,40.864761],"type":"Point"}
}