{
  "type": "Feature",
  "properties": {
    "iso:country":"US",
    "sg:address":"206 Nanuet Mall S",
    "sg:city":"Nanuet",
    "sg:classifiers":[
        {
            "category":"Restaurant",
            "type":"Food & Drink"
        }
    ],
    "sg:phone":"+1   ",
    "sg:postcode":"10954",
    "sg:province":"NY",
    "sg:tags":[
        "eating"
    ],
    "wof:name":"Burger King",
    "wof:placetype":"venue"
},
  "geometry": {"coordinates":[-74.015333,41.09339],"type":"Point"}
}