{
  "type": "Feature",
  "properties": {
    "addr:full":"160 N Midland Ave Nyack NY 10960",
    "addr:housenumber":"160",
    "addr:postcode":"10960",
    "addr:street":"N Midland Ave",
    "iso:country":"US",
    "sg:address":"160 N Midland Ave",
    "sg:city":"Nyack",
    "sg:classifiers":[
        {
            "category":"Health Services",
            "subcategory":"Medical Lab",
            "type":"Services"
        }
    ],
    "sg:phone":"+1 845 353 6667",
    "sg:postcode":"10960",
    "sg:province":"NY",
    "sg:tags":[
        "resonance",
        "magnetic",
        "imaging"
    ],
    "wof:name":"Nyack Magnetic Resonance",
    "wof:placetype":"venue"
},
  "geometry": {"coordinates":[-73.925493,41.094786],"type":"Point"}
}