{
  "type": "Feature",
  "properties": {
    "iso:country":"US",
    "sg:address":"119 Main St",
    "sg:city":"Geneseo",
    "sg:classifiers":[
        {
            "category":"Government",
            "subcategory":"Court House",
            "type":"Public Place"
        }
    ],
    "sg:phone":"+1 585 243 4530",
    "sg:postcode":"14454",
    "sg:province":"NY",
    "sg:tags":[
        "city"
    ],
    "wof:name":"Geneseo Town Justice Court",
    "wof:placetype":"venue"
},
  "geometry": {"coordinates":[-77.81697200000001,42.795136],"type":"Point"}
}