{
  "type": "Feature",
  "properties": {
    "addr:full":"58 Carmine St New York NY 10014",
    "addr:housenumber":"58",
    "addr:postcode":"10014",
    "addr:street":"Carmine St",
    "iso:country":"US",
    "sg:address":"58 Carmine St",
    "sg:city":"New York",
    "sg:classifiers":[
        {
            "category":"Food & Beverages",
            "subcategory":"Groceries & Convenience Stores",
            "type":"Retail Goods"
        }
    ],
    "sg:phone":"+1 212 620 5620",
    "sg:postcode":"10014",
    "sg:province":"NY",
    "sg:tags":[
        "grocer"
    ],
    "wof:name":"Manhattan Mini Market",
    "wof:placetype":"venue"
},
  "geometry": {"coordinates":[-74.00246799999999,40.730323],"type":"Point"}
}