{
  "type": "Feature",
  "properties": {
    "addr:full":"601 E Fordham Rd Bronx NY 10458",
    "addr:housenumber":"601",
    "addr:postcode":"10458",
    "addr:street":"E Fordham Rd",
    "iso:country":"US",
    "sg:address":"601 E Fordham Rd",
    "sg:city":"Bronx",
    "sg:classifiers":[
        {
            "category":"Autos & Motor Vehicles",
            "subcategory":"Fuel & Gas Station",
            "type":"Retail Goods"
        }
    ],
    "sg:phone":"+1 718 563 5950",
    "sg:postcode":"10458",
    "sg:province":"NY",
    "sg:tags":[
        "oil"
    ],
    "wof:name":"Warex Terminals Corp",
    "wof:placetype":"venue"
},
  "geometry": {"coordinates":[-73.88557299999999,40.858825],"type":"Point"}
}