{
  "type": "Feature",
  "properties": {
    "addr:full":"125 Riverside Dr New York NY 10024",
    "addr:housenumber":"125",
    "addr:postcode":"10024",
    "addr:street":"Riverside Dr",
    "iso:country":"US",
    "sg:address":"125 Riverside Dr",
    "sg:city":"New York",
    "sg:classifiers":[
        {
            "category":"Social Services",
            "type":"Services"
        }
    ],
    "sg:phone":"+1   ",
    "sg:postcode":"10024",
    "sg:province":"NY",
    "wof:name":"Joan D Winograd",
    "wof:placetype":"venue"
},
  "geometry": {"coordinates":[-73.980859,40.788864],"type":"Point"}
}