{
  "type": "Feature",
  "properties": {
    "iso:country":"US",
    "sg:address":"920 Rte 25",
    "sg:city":"Ridge",
    "sg:classifiers":[
        {
            "category":"Retail",
            "subcategory":"Auto Repair",
            "type":"Services"
        }
    ],
    "sg:phone":"+1 631 924 5200",
    "sg:postcode":"11961",
    "sg:province":"NY",
    "sg:tags":[
        "body",
        "automobile",
        "painting"
    ],
    "wof:name":"Ridge Collision Ctr",
    "wof:placetype":"venue"
},
  "geometry": {"coordinates":[-72.872238,40.899344],"type":"Point"}
}