{
  "type": "Feature",
  "properties": {
    "iso:country":"US",
    "sg:address":"218 W 234th St",
    "sg:city":"Bronx",
    "sg:classifiers":[
        {
            "category":"Shopping",
            "subcategory":"Clothing, Apparel, & Fashions",
            "type":"Retail Goods"
        }
    ],
    "sg:phone":"+1 718 543 1447",
    "sg:postcode":"10463",
    "sg:province":"NY",
    "wof:name":"Annie Sez",
    "wof:placetype":"venue"
},
  "geometry": {"coordinates":[-73.903763,40.882062],"type":"Point"}
}