{
  "type": "Feature",
  "properties": {
    "iso:country":"US",
    "sg:address":"1084 Wickerton Ln",
    "sg:city":"Webster",
    "sg:classifiers":[
        {
            "category":"Manufacturing",
            "subcategory":"Signs",
            "type":"Manufacturing & Wholesale Goods"
        }
    ],
    "sg:phone":"+1   ",
    "sg:postcode":"14580",
    "sg:province":"NY",
    "sg:tags":[
        "specialty",
        "mfg"
    ],
    "wof:name":"Router Works",
    "wof:placetype":"venue"
},
  "geometry": {"coordinates":[-77.44484199999999,43.204461],"type":"Point"}
}