{
  "type": "Feature",
  "properties": {
    "addr:full":"8405 Fort Hamilton Parkway Brooklyn NY 11209",
    "addr:housenumber":"8405",
    "addr:postcode":"11209",
    "addr:street":"Fort Hamilton Parkway",
    "iso:country":"US",
    "sg:address":"8405 Fort Hamilton Parkway",
    "sg:city":"Brooklyn",
    "sg:classifiers":[
        {
            "category":"Health Services",
            "subcategory":"Doctor",
            "type":"Services"
        }
    ],
    "sg:phone":"+1 718 745 6500",
    "sg:postcode":"11209",
    "sg:province":"NY",
    "wof:name":"Wehbeh Hassan MD",
    "wof:placetype":"venue"
},
  "geometry": {"coordinates":[-74.02318,40.621148],"type":"Point"}
}