{
  "type": "Feature",
  "properties": {
    "addr:full":"138 Rockland Plz Nanuet NY 10954",
    "addr:housenumber":"138",
    "addr:postcode":"10954",
    "addr:street":"Rockland Plz",
    "iso:country":"US",
    "sg:address":"138 Rockland Plz",
    "sg:city":"Nanuet",
    "sg:classifiers":[
        {
            "category":"Real Estate",
            "subcategory":"Real Estate Services",
            "type":"Services"
        },
        {
            "category":"Real Estate",
            "subcategory":"Real Estate Agent",
            "type":"Services"
        }
    ],
    "sg:phone":"+1 845 624 3202",
    "sg:postcode":"10954",
    "sg:province":"NY",
    "sg:tags":[
        "buyer",
        "broker"
    ],
    "wof:name":"New Plan Realty Trust",
    "wof:placetype":"venue"
},
  "geometry": {"coordinates":[-74.01444100000001,41.099001],"type":"Point"}
}