{
  "type": "Feature",
  "properties": {
    "addr:full":"6 Lantern Ct Spring Valley NY 10977",
    "addr:housenumber":"6",
    "addr:postcode":"10977",
    "addr:street":"Lantern Ct",
    "iso:country":"US",
    "sg:address":"6 Lantern Ct",
    "sg:city":"Spring Valley",
    "sg:classifiers":[
        {
            "category":"Professional",
            "subcategory":"Accounting & Tax Preparation",
            "type":"Services"
        }
    ],
    "sg:phone":"+1 845 623 0004",
    "sg:postcode":"10977",
    "sg:province":"NY",
    "sg:tags":[
        "return",
        "filing"
    ],
    "wof:name":"New City Tax Svc Inc",
    "wof:placetype":"venue"
},
  "geometry": {"coordinates":[-74.050141,41.158024],"type":"Point"}
}