{
  "type": "Feature",
  "properties": {
    "addr:full":"42 Ingalls St Middletown NY 10940",
    "addr:housenumber":"42",
    "addr:postcode":"10940",
    "addr:street":"Ingalls St",
    "iso:country":"US",
    "sg:address":"42 Ingalls St",
    "sg:city":"Middletown",
    "sg:classifiers":[
        {
            "category":"Building & Trades",
            "subcategory":"Construction",
            "type":"Services"
        }
    ],
    "sg:phone":"+1 845 343 3913",
    "sg:postcode":"10940",
    "sg:province":"NY",
    "sg:tags":[
        "painter"
    ],
    "wof:name":"Alpha Omega",
    "wof:placetype":"venue"
},
  "geometry": {"coordinates":[-74.427621,41.433199],"type":"Point"}
}