{
  "type": "Feature",
  "properties": {
    "addr:full":"350 Madison Ave New York NY 10017",
    "addr:housenumber":"350",
    "addr:postcode":"10017",
    "addr:street":"Madison Ave",
    "iso:country":"US",
    "sg:address":"350 Madison Ave",
    "sg:city":"New York",
    "sg:classifiers":[
        {
            "category":"Professional",
            "subcategory":"Management & Consulting",
            "type":"Services"
        }
    ],
    "sg:phone":"+1 212 490 7103",
    "sg:postcode":"10017",
    "sg:province":"NY",
    "sg:tags":[
        "fuel"
    ],
    "wof:name":"Max Capital Management Corp",
    "wof:placetype":"venue"
},
  "geometry": {"coordinates":[-73.97807899999999,40.754513],"type":"Point"}
}