{
  "type": "Feature",
  "properties": {
    "addr:full":"99 John St New York NY 10038",
    "addr:housenumber":"99",
    "addr:postcode":"10038",
    "addr:street":"John St",
    "iso:country":"US",
    "sg:address":"99 John St",
    "sg:city":"New York",
    "sg:classifiers":[
        {
            "category":"Restaurant",
            "type":"Food & Drink"
        }
    ],
    "sg:menulink":"http://www.allmenus.com/ny/new-york/249737-jubilee-market-place-catering/menu/",
    "sg:phone":"+1 212 233 0808",
    "sg:postcode":"10038",
    "sg:province":"NY",
    "sg:tags":[
        "american"
    ],
    "wof:name":"Jubilee Market Place Catering",
    "wof:placetype":"venue"
},
  "geometry": {"coordinates":[-74.00605899999999,40.707949],"type":"Point"}
}