{
  "type": "Feature",
  "properties": {
    "addr:full":"3716 State Rte 41 Alt Moravia NY 13118",
    "addr:housenumber":"3716",
    "addr:postcode":"13118",
    "addr:street":"State Rte 41 Alt Moravia",
    "iso:country":"US",
    "sg:address":"3716 State Rte 41 Alt",
    "sg:city":"Moravia",
    "sg:classifiers":[
        {
            "category":"Home & Garden",
            "subcategory":"Furniture",
            "type":"Retail Goods"
        }
    ],
    "sg:phone":"+1 315 497 3348",
    "sg:postcode":"13118",
    "sg:province":"NY",
    "sg:tags":[
        "builder",
        "custom"
    ],
    "wof:name":"New Hope Designs",
    "wof:placetype":"venue"
},
  "geometry": {"coordinates":[-76.34786699999999,42.808192],"type":"Point"}
}