{
  "type": "Feature",
  "properties": {
    "iso:country":"US",
    "sg:address":"270 Queensbury Ave",
    "sg:city":"Queensbury",
    "sg:classifiers":[
        {
            "category":"Retail",
            "subcategory":"Veterinary Services",
            "type":"Services"
        }
    ],
    "sg:phone":"+1 518 793 7083",
    "sg:postcode":"12804",
    "sg:province":"NY",
    "sg:tags":[
        "hospital",
        "animal"
    ],
    "wof:name":"Countryside Veterinary Hosp",
    "wof:placetype":"venue"
},
  "geometry": {"coordinates":[-73.601275,43.339582],"type":"Point"}
}