{
  "type": "Feature",
  "properties": {
    "iso:country":"US",
    "sg:address":"638 State Hwy 306",
    "sg:city":"Suffern",
    "sg:classifiers":[
        {
            "category":"Government",
            "subcategory":"Office",
            "type":"Public Place"
        }
    ],
    "sg:phone":"+1 845 354 6517",
    "sg:postcode":"10901",
    "sg:province":"NY",
    "sg:tags":[
        "administrative",
        "program",
        "health",
        "so"
    ],
    "wof:name":"Ira Pomona",
    "wof:placetype":"venue"
},
  "geometry": {"coordinates":[-74.06656099999999,41.180013],"type":"Point"}
}