{
  "type": "Feature",
  "properties": {
    "addr:full":"4717 Chautauqua Stedman Rd Mayville NY 14757",
    "addr:housenumber":"4717",
    "addr:postcode":"14757",
    "addr:street":"Chautauqua Stedman Rd",
    "iso:country":"US",
    "sg:address":"4717 Chautauqua Stedman Rd",
    "sg:city":"Mayville",
    "sg:classifiers":[
        {
            "category":"Food & Beverages",
            "subcategory":"Liquor & Beverages",
            "type":"Retail Goods"
        },
        {
            "category":"Wholesale",
            "subcategory":"Wine & Distilled Alcoholic Beverages",
            "type":"Manufacturing & Wholesale Goods"
        }
    ],
    "sg:phone":"+1 716 269 3000",
    "sg:postcode":"14757",
    "sg:province":"NY",
    "sg:tags":[
        "broker"
    ],
    "wof:name":"Mazza Chautauqua Cellars",
    "wof:placetype":"venue"
},
  "geometry": {"coordinates":[-79.476265,42.206257],"type":"Point"}
}