{
  "type": "Feature",
  "properties": {
    "iso:country":"US",
    "sg:address":"1560 Smith Ridge Rd",
    "sg:city":"Chittenango",
    "sg:classifiers":[
        {
            "category":"Farming",
            "subcategory":"Dairy Farm",
            "type":"Manufacturing & Wholesale Goods"
        }
    ],
    "sg:phone":"+1 315 633 9856",
    "sg:postcode":"13030",
    "sg:province":"NY",
    "wof:name":"Wesley Dines",
    "wof:placetype":"venue"
},
  "geometry": {"coordinates":[-75.880105,43.13684],"type":"Point"}
}