{
  "type": "Feature",
  "properties": {
    "addr:full":"116 Franklin St New York NY 10013",
    "addr:housenumber":"116",
    "addr:postcode":"10013",
    "addr:street":"Franklin St",
    "iso:country":"US",
    "sg:address":"116 Franklin St",
    "sg:city":"New York",
    "sg:classifiers":[
        {
            "category":"Communications",
            "subcategory":"Film & Video Production",
            "type":"Services"
        }
    ],
    "sg:phone":"+1 212 941 0121",
    "sg:postcode":"10013",
    "sg:province":"NY",
    "sg:tags":[
        "motion"
    ],
    "wof:name":"Zohe Film Production Inc",
    "wof:placetype":"venue"
},
  "geometry": {"coordinates":[-74.005976,40.718573],"type":"Point"}
}