{
  "type": "Feature",
  "properties": {
    "addr:full":"55 E 52 St New York NY 10022",
    "addr:housenumber":"55;52",
    "addr:postcode":"10022",
    "addr:street":"E;St",
    "iso:country":"US",
    "sg:address":"55 E 52 St",
    "sg:city":"New York",
    "sg:classifiers":[
        {
            "category":"Insurance",
            "subcategory":"Insurance Agent",
            "type":"Services"
        }
    ],
    "sg:phone":"+1 212 758 4030",
    "sg:postcode":"10022",
    "sg:province":"NY",
    "wof:name":"Jon Rotenstreich Consultants",
    "wof:placetype":"venue"
},
  "geometry": {"coordinates":[-73.97335699999999,40.758679],"type":"Point"}
}