{
  "type": "Feature",
  "properties": {
    "iso:country":"US",
    "sg:address":"461 13th St",
    "sg:city":"Brooklyn",
    "sg:classifiers":[
        {
            "category":"Organizations",
            "subcategory":"Religious Organization",
            "type":"Services"
        }
    ],
    "sg:phone":"+1 718 499 9369",
    "sg:postcode":"11215",
    "sg:province":"NY",
    "sg:tags":[
        "clergy"
    ],
    "wof:name":"E H Jones",
    "wof:placetype":"venue"
},
  "geometry": {"coordinates":[-73.979162,40.662487],"type":"Point"}
}