{
  "type": "Feature",
  "properties": {
    "addr:full":"215 W 28th Street New York NY 10001",
    "addr:housenumber":"215",
    "addr:postcode":"10001",
    "addr:street":"W 28Th Street",
    "iso:country":"US",
    "sg:address":"215 W 28th Street",
    "sg:city":"New York",
    "sg:classifiers":[
        {
            "category":"Restaurant",
            "type":"Food & Drink"
        }
    ],
    "sg:phone":"+1 212 643 1199",
    "sg:postcode":"10001",
    "sg:province":"NY",
    "wof:name":"Facey Home Sales",
    "wof:placetype":"venue"
},
  "geometry": {"coordinates":[-73.993746,40.747417],"type":"Point"}
}