{
  "type": "Feature",
  "properties": {
    "addr:full":"5 N Station Plz Great Neck NY 11021",
    "addr:housenumber":"5",
    "addr:postcode":"11021",
    "addr:street":"N Station Plz",
    "iso:country":"US",
    "sg:address":"5 N Station Plz",
    "sg:city":"Great Neck",
    "sg:classifiers":[
        {
            "category":"Shopping",
            "subcategory":"Gifts & Souvenirs",
            "type":"Retail Goods"
        }
    ],
    "sg:phone":"+1   ",
    "sg:postcode":"11021",
    "sg:province":"NY",
    "wof:name":"Kandi King",
    "wof:placetype":"venue"
},
  "geometry": {"coordinates":[-73.727144,40.787386],"type":"Point"}
}