{
  "type": "Feature",
  "properties": {
    "addr:full":"1415 Boston Post Rd Larchmont NY 10538",
    "addr:housenumber":"1415",
    "addr:postcode":"10538",
    "addr:street":"Boston Post Rd",
    "iso:country":"US",
    "sg:address":"1415 Boston Post Rd",
    "sg:city":"Larchmont",
    "sg:classifiers":[
        {
            "category":"Health Services",
            "subcategory":"Doctor",
            "type":"Services"
        }
    ],
    "sg:phone":"+1 914 833 1502",
    "sg:postcode":"10538",
    "sg:province":"NY",
    "sg:tags":[
        "physician",
        "surgeon"
    ],
    "wof:name":"Larchmont Pediatrics",
    "wof:placetype":"venue"
},
  "geometry": {"coordinates":[-73.748234,40.934165],"type":"Point"}
}