{
  "type": "Feature",
  "properties": {
    "iso:country":"US",
    "sg:address":"241 W Fayette St",
    "sg:city":"Syracuse",
    "sg:classifiers":[
        {
            "category":"Banks & Credit Unions",
            "subcategory":"Financial Services",
            "type":"Services"
        }
    ],
    "sg:phone":"+1 315 478 0157",
    "sg:postcode":"13202",
    "sg:province":"NY",
    "sg:tags":[
        "investor"
    ],
    "wof:name":"Onondaga Venture Capital Fund",
    "wof:placetype":"venue"
},
  "geometry": {"coordinates":[-76.154572,43.04862],"type":"Point"}
}