{
  "type": "Feature",
  "properties": {
    "iso:country":"US",
    "sg:address":"1554 Northern Blvd",
    "sg:city":"Manhasset",
    "sg:classifiers":[
        {
            "category":"Health Services",
            "subcategory":"Doctor",
            "type":"Services"
        }
    ],
    "sg:phone":"+1 516 390 1290",
    "sg:postcode":"11030",
    "sg:province":"NY",
    "wof:name":"Lonner Baron S MD",
    "wof:placetype":"venue"
},
  "geometry": {"coordinates":[-73.69016999999999,40.793679],"type":"Point"}
}