{
  "type": "Feature",
  "properties": {
    "addr:full":"645 5th Ave Brooklyn NY 11215",
    "addr:housenumber":"645",
    "addr:postcode":"11215",
    "addr:street":"5Th Ave",
    "iso:country":"US",
    "sg:address":"645 5th Ave",
    "sg:city":"Brooklyn",
    "sg:classifiers":[
        {
            "category":"Bakery",
            "type":"Food & Drink"
        }
    ],
    "sg:phone":"+1 718 832 5691",
    "sg:postcode":"11215",
    "sg:province":"NY",
    "wof:name":"Selena Bakery",
    "wof:placetype":"venue"
},
  "geometry": {"coordinates":[-73.99189800000001,40.662701],"type":"Point"}
}