{
  "type": "Feature",
  "properties": {
    "addr:full":"1815 E 92nd St Brooklyn NY 11236",
    "addr:housenumber":"1815",
    "addr:postcode":"11236",
    "addr:street":"E 92Nd St",
    "iso:country":"US",
    "sg:address":"1815 E 92nd St",
    "sg:city":"Brooklyn",
    "sg:classifiers":[
        {
            "category":"Shopping",
            "subcategory":"Clothing, Apparel, & Fashions",
            "type":"Retail Goods"
        }
    ],
    "sg:phone":"+1   ",
    "sg:postcode":"11236",
    "sg:province":"NY",
    "sg:tags":[
        "family"
    ],
    "wof:name":"Lenoke Inc",
    "wof:placetype":"venue"
},
  "geometry": {"coordinates":[-73.890753,40.630255],"type":"Point"}
}