{
  "type": "Feature",
  "properties": {
    "addr:full":"3352 Nesconset Hwy Setauket NY 11733",
    "addr:housenumber":"3352",
    "addr:postcode":"11733",
    "addr:street":"Nesconset Hwy",
    "iso:country":"US",
    "sg:address":"3352 Nesconset Hwy",
    "sg:city":"Setauket",
    "sg:classifiers":[
        {
            "category":"Real Estate",
            "subcategory":"Real Estate Agent",
            "type":"Services"
        }
    ],
    "sg:phone":"+1 631 751 2459",
    "sg:postcode":"11733",
    "sg:province":"NY",
    "sg:tags":[
        "agency",
        "rental"
    ],
    "wof:name":"Reliable Rental & Leasing",
    "wof:placetype":"venue"
},
  "geometry": {"coordinates":[-73.084998,40.896509],"type":"Point"}
}