{
  "type": "Feature",
  "properties": {
    "addr:full":"28 Co Rd 78 Middletown NY 10940",
    "addr:housenumber":"28;78",
    "addr:postcode":"10940",
    "addr:street":"Co Rd",
    "iso:country":"US",
    "sg:address":"28 Co Rd 78",
    "sg:city":"Middletown",
    "sg:classifiers":[
        {
            "category":"Autos & Motor Vehicles",
            "subcategory":"Automobile Sales",
            "type":"Retail Goods"
        }
    ],
    "sg:phone":"+1 845 343 8282",
    "sg:postcode":"10940",
    "sg:province":"NY",
    "sg:tags":[
        "car",
        "dealer"
    ],
    "wof:name":"Y Bi Nu Auto Sales LLC",
    "wof:placetype":"venue"
},
  "geometry": {"coordinates":[-74.432221,41.425002],"type":"Point"}
}