{
  "type": "Feature",
  "properties": {
    "iso:country":"US",
    "sg:address":"31 E 32 St",
    "sg:city":"New York",
    "sg:classifiers":[
        {
            "category":"Building & Trades",
            "subcategory":"Plumbing",
            "type":"Services"
        }
    ],
    "sg:phone":"+1 212 481 8484",
    "sg:postcode":"10016",
    "sg:province":"NY",
    "sg:tags":[
        "air",
        "commercial",
        "conditioning",
        "contractor"
    ],
    "wof:name":"Sterling Group Ind Inc",
    "wof:placetype":"venue"
},
  "geometry": {"coordinates":[-73.98231,40.745899],"type":"Point"}
}