{
  "type": "Feature",
  "properties": {
    "iso:country":"US",
    "sg:address":"4406 White Plains Rd",
    "sg:city":"Bronx",
    "sg:classifiers":[
        {
            "category":"Restaurant",
            "type":"Food & Drink"
        }
    ],
    "sg:phone":"+1 718 325 2381",
    "sg:postcode":"10470",
    "sg:province":"NY",
    "sg:tags":[
        "eating"
    ],
    "wof:name":"Big Daddy's Carribbean Taste",
    "wof:placetype":"venue"
},
  "geometry": {"coordinates":[-73.85300100000001,40.899856],"type":"Point"}
}