{
  "type": "Feature",
  "properties": {
    "iso:country":"US",
    "sg:address":"1844 Newbridge Rd",
    "sg:city":"Bellmore",
    "sg:classifiers":[
        {
            "category":"Wholesale",
            "subcategory":"Non-durable Goods",
            "type":"Manufacturing & Wholesale Goods"
        }
    ],
    "sg:phone":"+1 516 781 8640",
    "sg:postcode":"11710",
    "sg:province":"NY",
    "wof:name":"Jansel Fund Raising",
    "wof:placetype":"venue"
},
  "geometry": {"coordinates":[-73.53933499999999,40.677799],"type":"Point"}
}