{
  "type": "Feature",
  "properties": {
    "addr:full":"2022 College Point Blvd College Point NY 11356",
    "addr:housenumber":"2022",
    "addr:postcode":"11356",
    "addr:street":"College Point Blvd",
    "iso:country":"US",
    "sg:address":"2022 College Point Blvd",
    "sg:city":"College Point",
    "sg:classifiers":[
        {
            "category":"Retail",
            "subcategory":"Veterinary Services",
            "type":"Services"
        },
        {
            "category":"Retail",
            "subcategory":"Pet Boarding",
            "type":"Services"
        }
    ],
    "sg:phone":"+1 718 762 5505",
    "sg:postcode":"11356",
    "sg:province":"NY",
    "sg:tags":[
        "veterinarian",
        "boarding/pet",
        "sitting"
    ],
    "wof:name":"College Point Veterinary Center PC",
    "wof:placetype":"venue"
},
  "geometry": {"coordinates":[-73.84600500000001,40.780984],"type":"Point"}
}