{
  "type": "Feature",
  "properties": {
    "addr:full":"16 Norden Ln Huntington Station NY 11746",
    "addr:housenumber":"16",
    "addr:postcode":"11746",
    "addr:street":"Norden Ln Huntington",
    "iso:country":"US",
    "sg:address":"16 Norden Ln",
    "sg:city":"Huntington Station",
    "sg:classifiers":[
        {
            "category":"Professional",
            "subcategory":"Computer Services",
            "type":"Services"
        }
    ],
    "sg:phone":"+1   ",
    "sg:postcode":"11746",
    "sg:province":"NY",
    "sg:tags":[
        "prepackaged",
        "software"
    ],
    "wof:name":"Melrick Technologies",
    "wof:placetype":"venue"
},
  "geometry": {"coordinates":[-73.424509,40.840292],"type":"Point"}
}