{
  "type": "Feature",
  "properties": {
    "addr:full":"684 Morris Park Ave Bronx NY 10462",
    "addr:housenumber":"684",
    "addr:postcode":"10462",
    "addr:street":"Morris Park Ave",
    "iso:country":"US",
    "sg:address":"684 Morris Park Ave",
    "sg:city":"Bronx",
    "sg:classifiers":[
        {
            "category":"Shopping",
            "subcategory":"Department Store",
            "type":"Retail Goods"
        }
    ],
    "sg:phone":"+1 718 863 5777",
    "sg:postcode":"10462",
    "sg:province":"NY",
    "sg:tags":[
        "shop"
    ],
    "wof:name":"Archer Discount",
    "wof:placetype":"venue"
},
  "geometry": {"coordinates":[-73.866339,40.845085],"type":"Point"}
}