{
  "type": "Feature",
  "properties": {
    "iso:country":"US",
    "sg:address":"4845 Transit Rd",
    "sg:city":"Depew",
    "sg:classifiers":[
        {
            "category":"Health Services",
            "subcategory":"Doctor",
            "type":"Services"
        }
    ],
    "sg:phone":"+1 716 656 2200",
    "sg:postcode":"14043",
    "sg:province":"NY",
    "sg:tags":[
        "physician",
        "surgeon"
    ],
    "wof:name":"Smith Brian",
    "wof:placetype":"venue"
},
  "geometry": {"coordinates":[-78.696939,42.873888],"type":"Point"}
}