{
  "type": "Feature",
  "properties": {
    "iso:country":"US",
    "sg:address":"411 7th Ave",
    "sg:city":"Brooklyn",
    "sg:classifiers":[
        {
            "category":"Home & Garden",
            "subcategory":"Home Furnishings",
            "type":"Retail Goods"
        }
    ],
    "sg:phone":"+1 718 965 9200",
    "sg:postcode":"11215",
    "sg:province":"NY",
    "sg:tags":[
        "decor"
    ],
    "sg:website":"www.sweetcharitynyc.com",
    "wof:name":"Sweet Charity",
    "wof:placetype":"venue"
},
  "geometry": {"coordinates":[-73.983734,40.664305],"type":"Point"}
}