{
  "type": "Feature",
  "properties": {
    "iso:country":"US",
    "sg:address":"5 Stauderman Ave",
    "sg:city":"Lynbrook",
    "sg:classifiers":[
        {
            "category":"Health Services",
            "subcategory":"Doctor",
            "type":"Services"
        },
        {
            "category":"Health Services",
            "subcategory":"Chiropractor",
            "type":"Services"
        }
    ],
    "sg:phone":"+1 516 825 7100",
    "sg:postcode":"11563",
    "sg:province":"NY",
    "sg:website":"www.correctivechiropractic.com",
    "wof:name":"Corrective Chiropractic & Wellness",
    "wof:placetype":"venue"
},
  "geometry": {"coordinates":[-73.670433,40.655589],"type":"Point"}
}