{
  "type": "Feature",
  "properties": {
    "addr:full":"801 E Gun Hill Rd Bronx NY 10467",
    "addr:housenumber":"801",
    "addr:postcode":"10467",
    "addr:street":"E Gun Hill Rd",
    "iso:country":"US",
    "sg:address":"801 E Gun Hill Rd",
    "sg:city":"Bronx",
    "sg:classifiers":[
        {
            "category":"Health Services",
            "subcategory":"Chiropractor",
            "type":"Services"
        }
    ],
    "sg:phone":"+1 718 654 4113",
    "sg:postcode":"10467",
    "sg:province":"NY",
    "sg:tags":[
        "chiropractic"
    ],
    "wof:name":"Gregori S Pasqua Dr",
    "wof:placetype":"venue"
},
  "geometry": {"coordinates":[-73.862129,40.875999],"type":"Point"}
}