{
  "type": "Feature",
  "properties": {
    "addr:full":"46 N Main St Bainbridge NY 13733",
    "addr:housenumber":"46",
    "addr:postcode":"13733",
    "addr:street":"N Main St",
    "iso:country":"US",
    "sg:address":"46 N Main St",
    "sg:city":"Bainbridge",
    "sg:classifiers":[
        {
            "category":"Professional",
            "subcategory":"Lawyer & Legal Services",
            "type":"Services"
        }
    ],
    "sg:phone":"+1 607 967 5501",
    "sg:postcode":"13733",
    "sg:province":"NY",
    "sg:tags":[
        "attorney"
    ],
    "wof:name":"William A Denman",
    "wof:placetype":"venue"
},
  "geometry": {"coordinates":[-75.475137,42.297087],"type":"Point"}
}