{
  "type": "Feature",
  "properties": {
    "addr:full":"160 Columbus Ave New York NY 10023",
    "addr:housenumber":"160",
    "addr:postcode":"10023",
    "addr:street":"Columbus Ave",
    "iso:country":"US",
    "sg:address":"160 Columbus Ave",
    "sg:city":"New York",
    "sg:classifiers":[
        {
            "category":"Shopping",
            "subcategory":"Shoes",
            "type":"Retail Goods"
        }
    ],
    "sg:phone":"+1 212 579 1301",
    "sg:postcode":"10023",
    "sg:province":"NY",
    "sg:tags":[
        "store"
    ],
    "wof:name":"Rockport Store",
    "wof:placetype":"venue"
},
  "geometry": {"coordinates":[-73.98110200000001,40.7743],"type":"Point"}
}