{
  "type": "Feature",
  "properties": {
    "addr:full":"51 Oxford Dr Suffern NY 10901",
    "addr:housenumber":"51",
    "addr:postcode":"10901",
    "addr:street":"Oxford Dr",
    "iso:country":"US",
    "sg:address":"51 Oxford Dr",
    "sg:city":"Suffern",
    "sg:classifiers":[
        {
            "category":"Freight",
            "type":"Transportation"
        }
    ],
    "sg:phone":"+1 845 357 7733",
    "sg:postcode":"10901",
    "sg:province":"NY",
    "sg:tags":[
        "mover"
    ],
    "wof:name":"A Fazio Moving & Storage",
    "wof:placetype":"venue"
},
  "geometry": {"coordinates":[-74.105676,41.130607],"type":"Point"}
}