{
  "type": "Feature",
  "properties": {
    "addr:full":"4704 Park Avenue Bronx NY 10458",
    "addr:housenumber":"4704",
    "addr:postcode":"10458",
    "addr:street":"Park Avenue",
    "iso:country":"US",
    "sg:address":"4704 Park Avenue",
    "sg:city":"Bronx",
    "sg:classifiers":[
        {
            "category":"Retail",
            "subcategory":"Auto Repair",
            "type":"Services"
        }
    ],
    "sg:phone":"+1 718 329 4999",
    "sg:postcode":"10458",
    "sg:province":"NY",
    "wof:name":"Park Ave Auto Dealer",
    "wof:placetype":"venue"
},
  "geometry": {"coordinates":[-73.891946,40.859029],"type":"Point"}
}