{
  "type": "Feature",
  "properties": {
    "iso:country":"US",
    "sg:address":"29 Palmer Ave",
    "sg:city":"Nanuet",
    "sg:classifiers":[
        {
            "category":"Professional",
            "type":"Services"
        }
    ],
    "sg:phone":"+1   ",
    "sg:postcode":"10954",
    "sg:province":"NY",
    "wof:name":"Larry Byrnes Inc",
    "wof:placetype":"venue"
},
  "geometry": {"coordinates":[-74.007853,41.101129],"type":"Point"}
}