{
  "type": "Feature",
  "properties": {
    "addr:full":"357 Forest Ln Smithtown NY 11787",
    "addr:housenumber":"357",
    "addr:postcode":"11787",
    "addr:street":"Forest Ln",
    "iso:country":"US",
    "sg:address":"357 Forest Ln",
    "sg:city":"Smithtown",
    "sg:classifiers":[
        {
            "category":"Building & Trades",
            "subcategory":"Construction",
            "type":"Services"
        }
    ],
    "sg:phone":"+1 516 770 4489",
    "sg:postcode":"11787",
    "sg:province":"NY",
    "sg:tags":[
        "house"
    ],
    "wof:name":"Ken Skeen Construction Co",
    "wof:placetype":"venue"
},
  "geometry": {"coordinates":[-73.202485,40.83282],"type":"Point"}
}