{
  "type": "Feature",
  "properties": {
    "iso:country":"US",
    "sg:address":"741 White Plains Rd",
    "sg:city":"Scarsdale",
    "sg:classifiers":[
        {
            "category":"Retail",
            "subcategory":"Veterinary Services",
            "type":"Services"
        }
    ],
    "sg:phone":"+1 914 723 0290",
    "sg:postcode":"10583",
    "sg:province":"NY",
    "sg:tags":[
        "veterinarian"
    ],
    "wof:name":"Scarsdale Animal Hospital",
    "wof:placetype":"venue"
},
  "geometry": {"coordinates":[-73.804715,40.972162],"type":"Point"}
}