{
  "type": "Feature",
  "properties": {
    "iso:country":"US",
    "sg:address":"Buckley Rd",
    "sg:city":"Holtsville",
    "sg:classifiers":[
        {
            "category":"Park",
            "type":"Public Place"
        },
        {
            "category":"Museum",
            "subcategory":"Zoo",
            "type":"Entertainment"
        }
    ],
    "sg:phone":"+1 631 758 9664",
    "sg:postcode":"11742",
    "sg:province":"NY",
    "sg:website":"www.brookhaven.org/HighwayDepart...",
    "wof:name":"Wildlife and Ecology Center",
    "wof:placetype":"venue"
},
  "geometry": {"coordinates":[-73.03666699999999,40.793555],"type":"Point"}
}