{
  "type": "Feature",
  "properties": {
    "addr:full":"57 North St Mexico NY 13114",
    "addr:housenumber":"57",
    "addr:postcode":"13114",
    "addr:street":"North St",
    "iso:country":"US",
    "sg:address":"57 North St",
    "sg:city":"Mexico",
    "sg:classifiers":[
        {
            "category":"Health Services",
            "subcategory":"Chiropractor",
            "type":"Services"
        }
    ],
    "sg:phone":"+1   ",
    "sg:postcode":"13114",
    "sg:province":"NY",
    "wof:name":"Advanced Wellness Chiropractic",
    "wof:placetype":"venue"
},
  "geometry": {"coordinates":[-76.226107,43.459928],"type":"Point"}
}