{
  "type": "Feature",
  "properties": {
    "iso:country":"US",
    "sg:address":"70 Greenwich St",
    "sg:city":"New York",
    "sg:classifiers":[
        {
            "category":"Wholesale",
            "subcategory":"Electrical",
            "type":"Manufacturing & Wholesale Goods"
        }
    ],
    "sg:phone":"+1 718 829 1234",
    "sg:postcode":"10006",
    "sg:province":"NY",
    "sg:tags":[
        "electronic"
    ],
    "wof:name":"Lorcom Telecommunications Ltd",
    "wof:placetype":"venue"
},
  "geometry": {"coordinates":[-74.013592,40.707968],"type":"Point"}
}