{
  "type": "Feature",
  "properties": {
    "addr:full":"155 Kisco Ave Mount Kisco NY 10549",
    "addr:housenumber":"155",
    "addr:postcode":"10549",
    "addr:street":"Kisco Ave",
    "iso:country":"US",
    "sg:address":"155 Kisco Ave",
    "sg:city":"Mount Kisco",
    "sg:classifiers":[
        {
            "category":"Sports & Exercise",
            "subcategory":"Gym",
            "type":"Entertainment"
        }
    ],
    "sg:phone":"+1 914 244 0435",
    "sg:postcode":"10549",
    "sg:province":"NY",
    "sg:tags":[
        "trainer"
    ],
    "wof:name":"Monique's",
    "wof:placetype":"venue"
},
  "geometry": {"coordinates":[-73.726501,41.214401],"type":"Point"}
}