{
  "type": "Feature",
  "properties": {
    "addr:full":"6754 80th St Middle Village NY 11379",
    "addr:housenumber":"6754",
    "addr:postcode":"11379",
    "addr:street":"80Th St",
    "iso:country":"US",
    "sg:address":"6754 80th St",
    "sg:city":"Middle Village",
    "sg:classifiers":[
        {
            "category":"Education",
            "subcategory":"School",
            "type":"Public Place"
        }
    ],
    "sg:phone":"+1 718 326 8243",
    "sg:postcode":"11379",
    "sg:province":"NY",
    "sg:tags":[
        "high",
        "middle",
        "elementary"
    ],
    "wof:name":"N Y City of",
    "wof:placetype":"venue"
},
  "geometry": {"coordinates":[-73.871399,40.711899],"type":"Point"}
}