{
  "type": "Feature",
  "properties": {
    "addr:full":"15054 183rd St Jamaica NY 11413",
    "addr:housenumber":"15054",
    "addr:postcode":"11413",
    "addr:street":"183Rd St",
    "iso:country":"US",
    "sg:address":"15054 183rd St",
    "sg:city":"Jamaica",
    "sg:classifiers":[
        {
            "category":"Wholesale",
            "subcategory":"Machinery & Supplies",
            "type":"Manufacturing & Wholesale Goods"
        },
        {
            "category":"Retail",
            "subcategory":"Repair Shop",
            "type":"Services"
        }
    ],
    "sg:phone":"+1 718 995 4300",
    "sg:postcode":"11413",
    "sg:province":"NY",
    "sg:tags":[
        "contractor"
    ],
    "wof:name":"Heavy Equip Repair Corp of NY",
    "wof:placetype":"venue"
},
  "geometry": {"coordinates":[-73.764337,40.655772],"type":"Point"}
}