{
  "type": "Feature",
  "properties": {
    "iso:country":"US",
    "sg:address":"42 Floyd St",
    "sg:city":"East Hampton",
    "sg:classifiers":[
        {
            "category":"Sports & Exercise",
            "subcategory":"Gym",
            "type":"Entertainment"
        }
    ],
    "sg:phone":"+1   ",
    "sg:postcode":"11937",
    "sg:province":"NY",
    "sg:tags":[
        "fitness",
        "physical",
        "facility"
    ],
    "wof:name":"Smile Lab",
    "wof:placetype":"venue"
},
  "geometry": {"coordinates":[-72.177922,40.974864],"type":"Point"}
}