{
  "type": "Feature",
  "properties": {
    "iso:country":"US",
    "sg:address":"519 E Meadow Ave",
    "sg:city":"East Meadow",
    "sg:classifiers":[
        {
            "category":"Wholesale",
            "subcategory":"Groceries",
            "type":"Manufacturing & Wholesale Goods"
        }
    ],
    "sg:phone":"+1 516 794 2000",
    "sg:postcode":"11554",
    "sg:province":"NY",
    "sg:tags":[
        "food",
        "broker"
    ],
    "wof:name":"Edmer Sanitary Supply Co Inc",
    "wof:placetype":"venue"
},
  "geometry": {"coordinates":[-73.556453,40.711897],"type":"Point"}
}