{
  "type": "Feature",
  "properties": {
    "addr:full":"233 W 83 St New York NY 10024",
    "addr:housenumber":"233",
    "addr:postcode":"10024",
    "addr:street":"W 83 St",
    "iso:country":"US",
    "sg:address":"233 W 83 St",
    "sg:city":"New York",
    "sg:classifiers":[
        {
            "category":"Organizations",
            "subcategory":"Religious Organization",
            "type":"Services"
        }
    ],
    "sg:phone":"+1 212 724 2466",
    "sg:postcode":"10024",
    "sg:province":"NY",
    "sg:website":"www.lightoflifecommunications.com",
    "wof:name":"Light Of Life Communications",
    "wof:placetype":"venue"
},
  "geometry": {"coordinates":[-73.979288,40.786941],"type":"Point"}
}