{
  "type": "Feature",
  "properties": {
    "addr:full":"99 W Main St Stony Point NY 10980",
    "addr:housenumber":"99",
    "addr:postcode":"10980",
    "addr:street":"W Main St",
    "iso:country":"US",
    "sg:address":"99 W Main St",
    "sg:city":"Stony Point",
    "sg:classifiers":[
        {
            "category":"Shopping",
            "type":"Retail Goods"
        }
    ],
    "sg:phone":"+1 845 429 9036",
    "sg:postcode":"10980",
    "sg:province":"NY",
    "sg:tags":[
        "telephone",
        "cellular"
    ],
    "wof:name":"Chelsea Communications Inc",
    "wof:placetype":"venue"
},
  "geometry": {"coordinates":[-73.987224,41.229381],"type":"Point"}
}