{
  "type": "Feature",
  "properties": {
    "addr:full":"18 Gregg Cir Penfield NY 14526",
    "addr:housenumber":"18",
    "addr:postcode":"14526",
    "addr:street":"Gregg Cir",
    "iso:country":"US",
    "sg:address":"18 Gregg Cir",
    "sg:city":"Penfield",
    "sg:classifiers":[
        {
            "category":"Shopping",
            "subcategory":"Gifts & Souvenirs",
            "type":"Retail Goods"
        }
    ],
    "sg:phone":"+1 585 671 5186",
    "sg:postcode":"14526",
    "sg:province":"NY",
    "sg:tags":[
        "shop"
    ],
    "wof:name":"Angels Just",
    "wof:placetype":"venue"
},
  "geometry": {"coordinates":[-77.47902000000001,43.17692],"type":"Point"}
}