{
  "type": "Feature",
  "properties": {
    "addr:full":"297 Broadway Huntington Station NY 11746",
    "addr:housenumber":"297",
    "addr:postcode":"11746",
    "addr:street":"Broadway Huntington",
    "iso:country":"US",
    "sg:address":"297 Broadway",
    "sg:city":"Huntington Station",
    "sg:classifiers":[
        {
            "category":"Recreation",
            "subcategory":"Boat Charter",
            "type":"Entertainment"
        }
    ],
    "sg:phone":"+1 631 421 1465",
    "sg:postcode":"11746",
    "sg:province":"NY",
    "sg:tags":[
        "boating"
    ],
    "wof:name":"Kaiser Marine Svces",
    "wof:placetype":"venue"
},
  "geometry": {"coordinates":[-73.399429,40.859486],"type":"Point"}
}