{
  "type": "Feature",
  "properties": {
    "iso:country":"US",
    "sg:address":"176 Plandome Rd",
    "sg:city":"Manhasset",
    "sg:classifiers":[
        {
            "category":"Education",
            "subcategory":"Special Training",
            "type":"Public Place"
        }
    ],
    "sg:phone":"+1 516 365 1601",
    "sg:postcode":"11030",
    "sg:province":"NY",
    "sg:tags":[
        "educational"
    ],
    "wof:name":"Phillips Education Systems",
    "wof:placetype":"venue"
},
  "geometry": {"coordinates":[-73.698773,40.795169],"type":"Point"}
}