{
  "type": "Feature",
  "properties": {
    "addr:full":"171 Castle Ave Westbury NY 11590",
    "addr:housenumber":"171",
    "addr:postcode":"11590",
    "addr:street":"Castle Ave",
    "iso:country":"US",
    "sg:address":"171 Castle Ave",
    "sg:city":"Westbury",
    "sg:classifiers":[
        {
            "category":"Building & Trades",
            "subcategory":"Construction",
            "type":"Services"
        }
    ],
    "sg:phone":"+1 516 338 7566",
    "sg:postcode":"11590",
    "sg:province":"NY",
    "sg:tags":[
        "home",
        "improvement"
    ],
    "wof:name":"White Eagle Home Improvment",
    "wof:placetype":"venue"
},
  "geometry": {"coordinates":[-73.591534,40.761099],"type":"Point"}
}