{
  "type": "Feature",
  "properties": {
    "iso:country":"US",
    "sg:address":"8 Cahoonzie Club Rd",
    "sg:city":"Sparrow Bush",
    "sg:classifiers":[
        {
            "category":"Professional",
            "type":"Services"
        }
    ],
    "sg:phone":"+1 845 856 4630",
    "sg:postcode":"12780",
    "sg:province":"NY",
    "sg:tags":[
        "establishment"
    ],
    "wof:name":"E & D Controls Inc",
    "wof:placetype":"venue"
},
  "geometry": {"coordinates":[-74.69767299999999,41.44808],"type":"Point"}
}