{
  "type": "Feature",
  "properties": {
    "addr:full":"223 E 82nd Street New York NY 10028",
    "addr:housenumber":"223",
    "addr:postcode":"10028",
    "addr:street":"E 82Nd Street",
    "iso:country":"US",
    "sg:address":"223 E 82nd Street",
    "sg:city":"New York",
    "sg:classifiers":[
        {
            "category":"Personal",
            "subcategory":"Shoe Repair & Shine",
            "type":"Services"
        }
    ],
    "sg:phone":"+1 212 744 4097",
    "sg:postcode":"10028",
    "sg:province":"NY",
    "wof:name":"Alex Shoe Repair Shop of Ny",
    "wof:placetype":"venue"
},
  "geometry": {"coordinates":[-73.95534600000001,40.776028],"type":"Point"}
}