{
  "type": "Feature",
  "properties": {
    "addr:full":"2501 Navy Pl Bellmore NY 11710",
    "addr:housenumber":"2501",
    "addr:postcode":"11710",
    "addr:street":"Navy Pl",
    "iso:country":"US",
    "sg:address":"2501 Navy Pl",
    "sg:city":"Bellmore",
    "sg:classifiers":[
        {
            "category":"Professional",
            "subcategory":"Accounting & Tax Preparation",
            "type":"Services"
        }
    ],
    "sg:phone":"+1   ",
    "sg:postcode":"11710",
    "sg:province":"NY",
    "wof:name":"Stewart J Flum CPA",
    "wof:placetype":"venue"
},
  "geometry": {"coordinates":[-73.528797,40.653815],"type":"Point"}
}