{
  "type": "Feature",
  "properties": {
    "iso:country":"US",
    "sg:address":"496 Uniondale Ave",
    "sg:city":"Uniondale",
    "sg:classifiers":[
        {
            "category":"Real Estate",
            "subcategory":"Real Estate Agent",
            "type":"Services"
        }
    ],
    "sg:phone":"+1 516 538 1978",
    "sg:postcode":"11553",
    "sg:province":"NY",
    "wof:name":"Blue Banner",
    "wof:placetype":"venue"
},
  "geometry": {"coordinates":[-73.592945,40.703223],"type":"Point"}
}