{
  "type": "Feature",
  "properties": {
    "addr:full":"373 Argyle Rd Cedarhurst NY 11516",
    "addr:housenumber":"373",
    "addr:postcode":"11516",
    "addr:street":"Argyle Rd",
    "iso:country":"US",
    "sg:address":"373 Argyle Rd",
    "sg:city":"Cedarhurst",
    "sg:classifiers":[
        {
            "category":"Wholesale",
            "subcategory":"Non-durable Goods",
            "type":"Manufacturing & Wholesale Goods"
        }
    ],
    "sg:phone":"+1 516 374 4331",
    "sg:postcode":"11516",
    "sg:province":"NY",
    "wof:name":"Sea Nik Distributing Corp",
    "wof:placetype":"venue"
},
  "geometry": {"coordinates":[-73.73626,40.627096],"type":"Point"}
}