{
  "type": "Feature",
  "properties": {
    "iso:country":"US",
    "sg:address":"9112 Ditmas Ave",
    "sg:city":"Brooklyn",
    "sg:classifiers":[
        {
            "category":"Professional",
            "subcategory":"Lawyer & Legal Services",
            "type":"Services"
        }
    ],
    "sg:phone":"+1 718 342 9266",
    "sg:postcode":"11236",
    "sg:province":"NY",
    "wof:name":"9112 Ditmas Transmission Inc",
    "wof:placetype":"venue"
},
  "geometry": {"coordinates":[-73.913776,40.648539],"type":"Point"}
}