{
  "type": "Feature",
  "properties": {
    "addr:full":"561 Broadway New York NY 10012",
    "addr:housenumber":"561",
    "addr:postcode":"10012",
    "addr:street":"Broadway",
    "iso:country":"US",
    "sg:address":"561 Broadway",
    "sg:city":"New York",
    "sg:classifiers":[
        {
            "category":"Shopping",
            "subcategory":"Stationery & Office Supplies",
            "type":"Retail Goods"
        }
    ],
    "sg:phone":"+1 212 941 9816",
    "sg:postcode":"10012",
    "sg:province":"NY",
    "sg:tags":[
        "stationer"
    ],
    "wof:name":"Kate's Paperie LTD",
    "wof:placetype":"venue"
},
  "geometry": {"coordinates":[-73.998504,40.723252],"type":"Point"}
}