{
  "type": "Feature",
  "properties": {
    "iso:country":"US",
    "sg:address":"202 Main St",
    "sg:city":"Hamburg",
    "sg:classifiers":[
        {
            "category":"Real Estate",
            "subcategory":"Real Estate Agent",
            "type":"Services"
        }
    ],
    "sg:phone":"+1 716 649 7897",
    "sg:postcode":"14075",
    "sg:province":"NY",
    "wof:name":"Spectrum Land Co",
    "wof:placetype":"venue"
},
  "geometry": {"coordinates":[-78.83731899999999,42.716344],"type":"Point"}
}