{
  "type": "Feature",
  "properties": {
    "iso:country":"US",
    "sg:address":"5205 Bank St",
    "sg:city":"Clarence",
    "sg:classifiers":[
        {
            "category":"Building & Trades",
            "subcategory":"Equipment Rental",
            "type":"Services"
        }
    ],
    "sg:phone":"+1 716 759 1532",
    "sg:postcode":"14031",
    "sg:province":"NY",
    "sg:tags":[
        "camping"
    ],
    "wof:name":"Economy Tent Rental Inc",
    "wof:placetype":"venue"
},
  "geometry": {"coordinates":[-78.591437,42.981825],"type":"Point"}
}