{
  "type": "Feature",
  "properties": {
    "addr:full":"129 Birch Hill Rd Locust Valley NY 11560",
    "addr:housenumber":"129",
    "addr:postcode":"11560",
    "addr:street":"Birch Hill Rd",
    "iso:country":"US",
    "sg:address":"129 Birch Hill Rd",
    "sg:city":"Locust Valley",
    "sg:classifiers":[
        {
            "category":"Manufacturing",
            "subcategory":"Food",
            "type":"Manufacturing & Wholesale Goods"
        }
    ],
    "sg:phone":"+1 516 621 4580",
    "sg:postcode":"11560",
    "sg:province":"NY",
    "sg:tags":[
        "product",
        "manufacturer"
    ],
    "wof:name":"Exclusive Food Sales",
    "wof:placetype":"venue"
},
  "geometry": {"coordinates":[-73.5971,40.877551],"type":"Point"}
}