{
  "type": "Feature",
  "properties": {
    "iso:country":"US",
    "sg:address":"190 Bennington Dr",
    "sg:city":"Rochester",
    "sg:classifiers":[
        {
            "category":"Manufacturing",
            "subcategory":"Tools & Machinery",
            "type":"Manufacturing & Wholesale Goods"
        }
    ],
    "sg:phone":"+1 585 663 7230",
    "sg:postcode":"14616",
    "sg:province":"NY",
    "sg:tags":[
        "optical"
    ],
    "wof:name":"Angstrom Precision Optics",
    "wof:placetype":"venue"
},
  "geometry": {"coordinates":[-77.635463,43.219679],"type":"Point"}
}