{
  "type": "Feature",
  "properties": {
    "addr:full":"5 Apple Meadow Rd Hudson NY 12534",
    "addr:housenumber":"5",
    "addr:postcode":"12534",
    "addr:street":"Apple Meadow Rd",
    "iso:country":"US",
    "sg:address":"5 Apple Meadow Rd",
    "sg:city":"Hudson",
    "sg:classifiers":[
        {
            "category":"Shopping",
            "type":"Retail Goods"
        }
    ],
    "sg:phone":"+1 518 822 1082",
    "sg:postcode":"12534",
    "sg:province":"NY",
    "sg:tags":[
        "spa",
        "hot",
        "tub"
    ],
    "sg:website":"www.majesticpoolsandspas.com",
    "wof:name":"Majestic Pools & Spas",
    "wof:placetype":"venue"
},
  "geometry": {"coordinates":[-73.76173,42.263309],"type":"Point"}
}