{
  "type": "Feature",
  "properties": {
    "iso:country":"US",
    "sg:address":"2197 Co Rte 7",
    "sg:city":"Oswego",
    "sg:classifiers":[
        {
            "category":"Real Estate",
            "subcategory":"Real Estate Operator",
            "type":"Services"
        }
    ],
    "sg:phone":"+1 315 343 8331",
    "sg:postcode":"13126",
    "sg:province":"NY",
    "sg:tags":[
        "building",
        "apartment"
    ],
    "wof:name":"Kajo Properties",
    "wof:placetype":"venue"
},
  "geometry": {"coordinates":[-76.53473099999999,43.40277],"type":"Point"}
}