{
  "type": "Feature",
  "properties": {
    "addr:full":"1227 51st St Brooklyn NY 11219",
    "addr:housenumber":"1227",
    "addr:postcode":"11219",
    "addr:street":"51St St",
    "iso:country":"US",
    "sg:address":"1227 51st St",
    "sg:city":"Brooklyn",
    "sg:classifiers":[
        {
            "category":"Insurance",
            "subcategory":"Insurance Agent",
            "type":"Services"
        }
    ],
    "sg:phone":"+1 718 437 1591",
    "sg:postcode":"11219",
    "sg:province":"NY",
    "wof:name":"Rubin Group",
    "wof:placetype":"venue"
},
  "geometry": {"coordinates":[-73.993514,40.634184],"type":"Point"}
}