{
  "type": "Feature",
  "properties": {
    "iso:country":"US",
    "sg:address":"15 Coventry Dr",
    "sg:city":"Clifton Park",
    "sg:classifiers":[
        {
            "category":"Communications",
            "subcategory":"Newspaper",
            "type":"Services"
        }
    ],
    "sg:phone":"+1 518 877 8788",
    "sg:postcode":"12065",
    "sg:province":"NY",
    "sg:tags":[
        "print",
        "medium"
    ],
    "wof:name":"Adirondack Sports & Fitness Magazine",
    "wof:placetype":"venue"
},
  "geometry": {"coordinates":[-73.81819900000001,42.8867],"type":"Point"}
}