{
  "type": "Feature",
  "properties": {
    "iso:country":"US",
    "sg:address":"363 Hancock St",
    "sg:city":"Brentwood",
    "sg:classifiers":[
        {
            "category":"Building & Trades",
            "subcategory":"Construction",
            "type":"Services"
        }
    ],
    "sg:phone":"+1 631 831 2407",
    "sg:postcode":"11717",
    "sg:province":"NY",
    "sg:tags":[
        "demolition",
        "contractor"
    ],
    "wof:name":"Advanced Environmental Services Corp.",
    "wof:placetype":"venue"
},
  "geometry": {"coordinates":[-73.24952500000001,40.789452],"type":"Point"}
}