{
  "type": "Feature",
  "properties": {
    "iso:country":"US",
    "sg:address":"9 Burns-Holden Rd",
    "sg:city":"Fort Covington",
    "sg:classifiers":[
        {
            "category":"Professional",
            "subcategory":"Accounting & Tax Preparation",
            "type":"Services"
        }
    ],
    "sg:phone":"+1 518 358 2144",
    "sg:postcode":"12937",
    "sg:province":"NY",
    "sg:tags":[
        "return",
        "filing"
    ],
    "wof:name":"Bill Gardner's Tax Svc",
    "wof:placetype":"venue"
},
  "geometry": {"coordinates":[-74.48821599999999,44.990752],"type":"Point"}
}