{
  "type": "Feature",
  "properties": {
    "iso:country":"US",
    "sg:address":"1251 Pennsylvania Ave",
    "sg:city":"Pine City",
    "sg:classifiers":[
        {
            "category":"Shopping",
            "subcategory":"Gifts & Souvenirs",
            "type":"Retail Goods"
        }
    ],
    "sg:phone":"+1   ",
    "sg:postcode":"14871",
    "sg:province":"NY",
    "sg:tags":[
        "novelty"
    ],
    "wof:name":"Cinnamon Heart",
    "wof:placetype":"venue"
},
  "geometry": {"coordinates":[-76.829109,42.052973],"type":"Point"}
}