{
  "type": "Feature",
  "properties": {
    "addr:full":"69 State Hwy 394 Kennedy NY 14747",
    "addr:housenumber":"69",
    "addr:postcode":"14747",
    "addr:street":"State Hwy 394 Kennedy",
    "iso:country":"US",
    "sg:address":"69 State Hwy 394",
    "sg:city":"Kennedy",
    "sg:classifiers":[
        {
            "category":"Retail",
            "subcategory":"Auto Repair",
            "type":"Services"
        }
    ],
    "sg:phone":"+1 716 267 4735",
    "sg:postcode":"14747",
    "sg:province":"NY",
    "sg:tags":[
        "transmission"
    ],
    "wof:name":"Waterboro Garage",
    "wof:placetype":"venue"
},
  "geometry": {"coordinates":[-79.065485,42.170286],"type":"Point"}
}