{
  "type": "Feature",
  "properties": {
    "addr:full":"37-04 Ditmars Blvd. Cross St. 37th St. Long Island City NY 11105",
    "addr:housenumber":"37-04",
    "addr:postcode":"11105",
    "addr:street":"Ditmars Blvd. Cross St. 37Th St.",
    "iso:country":"US",
    "sg:address":"37-04 Ditmars Blvd. Cross St. 37th St.",
    "sg:city":"Long Island City",
    "sg:classifiers":[
        {
            "category":"Restaurant",
            "type":"Food & Drink"
        }
    ],
    "sg:phone":"+1 718 627 6760",
    "sg:postcode":"11105",
    "sg:province":"NY",
    "sg:tags":[
        "sushi",
        "bar",
        "japanese"
    ],
    "wof:name":"Sushi Kin",
    "wof:placetype":"venue"
},
  "geometry": {"coordinates":[-73.907448,40.773832],"type":"Point"}
}