{
  "type": "Feature",
  "properties": {
    "iso:country":"US",
    "sg:address":"2111 Union St",
    "sg:city":"Brooklyn",
    "sg:classifiers":[
        {
            "category":"Building & Trades",
            "subcategory":"Plumbing",
            "type":"Services"
        }
    ],
    "sg:phone":"+1 718 774 3047",
    "sg:postcode":"11212",
    "sg:province":"NY",
    "sg:tags":[
        "contractor"
    ],
    "wof:name":"J Phillip Heating & Air Condit",
    "wof:placetype":"venue"
},
  "geometry": {"coordinates":[-73.921052,40.664762],"type":"Point"}
}