{
  "type": "Feature",
  "properties": {
    "iso:country":"US",
    "sg:address":"20 Veterans Memorial Hwy",
    "sg:city":"Commack",
    "sg:classifiers":[
        {
            "category":"Shopping",
            "subcategory":"Jewelry",
            "type":"Retail Goods"
        }
    ],
    "sg:phone":"+1   ",
    "sg:postcode":"11725",
    "sg:province":"NY",
    "sg:tags":[
        "repair"
    ],
    "wof:name":"Davids Master Clock",
    "wof:placetype":"venue"
},
  "geometry": {"coordinates":[-73.288887,40.841965],"type":"Point"}
}