{
  "type": "Feature",
  "properties": {
    "addr:full":"122 E 27th St New York NY 10016",
    "addr:housenumber":"122",
    "addr:postcode":"10016",
    "addr:street":"E 27Th St",
    "iso:country":"US",
    "sg:address":"122 E 27th St",
    "sg:city":"New York",
    "sg:classifiers":[
        {
            "category":"Restaurant",
            "type":"Food & Drink"
        },
        {
            "category":"Bars & Pubs",
            "subcategory":"Wine Bar",
            "type":"Food & Drink"
        }
    ],
    "sg:phone":"+1 212 481 7372",
    "sg:postcode":"10016",
    "sg:province":"NY",
    "sg:tags":[
        "italian"
    ],
    "sg:website":"www.itrulli.com",
    "wof:name":"I Trulli",
    "wof:placetype":"venue"
},
  "geometry": {"coordinates":[-73.983681,40.742097],"type":"Point"}
}