{
  "type": "Feature",
  "properties": {
    "iso:country":"US",
    "sg:address":"140 Metro Park",
    "sg:city":"Rochester",
    "sg:classifiers":[
        {
            "category":"Banks & Credit Unions",
            "subcategory":"Investment Brokerage",
            "type":"Services"
        }
    ],
    "sg:phone":"+1 585 272 9970",
    "sg:postcode":"14623",
    "sg:province":"NY",
    "sg:tags":[
        "advisory",
        "financial"
    ],
    "wof:name":"Bud Gearhart Cfp",
    "wof:placetype":"venue"
},
  "geometry": {"coordinates":[-77.61730900000001,43.097637],"type":"Point"}
}