{
  "type": "Feature",
  "properties": {
    "addr:full":"17 Harrison Ave Staten Island NY 10302",
    "addr:housenumber":"17",
    "addr:postcode":"10302",
    "addr:street":"Harrison Ave",
    "iso:country":"US",
    "sg:address":"17 Harrison Ave",
    "sg:city":"Staten Island",
    "sg:classifiers":[
        {
            "category":"Bars & Pubs",
            "type":"Food & Drink"
        }
    ],
    "sg:phone":"+1   ",
    "sg:postcode":"10302",
    "sg:province":"NY",
    "sg:tags":[
        "drinking"
    ],
    "wof:name":"Buddys Wonder Bar",
    "wof:placetype":"venue"
},
  "geometry": {"coordinates":[-74.134556,40.636813],"type":"Point"}
}