{
  "type": "Feature",
  "properties": {
    "addr:full":"127 Scotchtown Rd Goshen NY 10924",
    "addr:housenumber":"127",
    "addr:postcode":"10924",
    "addr:street":"Scotchtown Rd",
    "iso:country":"US",
    "sg:address":"127 Scotchtown Rd",
    "sg:city":"Goshen",
    "sg:classifiers":[
        {
            "category":"Wholesale",
            "subcategory":"Groceries",
            "type":"Manufacturing & Wholesale Goods"
        }
    ],
    "sg:phone":"+1 845 294 6819",
    "sg:postcode":"10924",
    "sg:province":"NY",
    "wof:name":"Pepperidge Farm Cookies",
    "wof:placetype":"venue"
},
  "geometry": {"coordinates":[-74.32543200000001,41.415413],"type":"Point"}
}