{
  "type": "Feature",
  "properties": {
    "iso:country":"US",
    "sg:address":"441 8th Ave",
    "sg:city":"Troy",
    "sg:classifiers":[
        {
            "category":"Organizations",
            "subcategory":"Religious Organization",
            "type":"Services"
        }
    ],
    "sg:phone":"+1 518 235 5151",
    "sg:postcode":"12182",
    "sg:province":"NY",
    "sg:tags":[
        "monastery",
        "convent"
    ],
    "wof:name":"Sisters Of St Joseph",
    "wof:placetype":"venue"
},
  "geometry": {"coordinates":[-73.671998,42.769267],"type":"Point"}
}