{
  "type": "Feature",
  "properties": {
    "iso:country":"US",
    "sg:address":"24 Strathallan Park",
    "sg:city":"Rochester",
    "sg:classifiers":[
        {
            "category":"Wholesale",
            "subcategory":"Furniture",
            "type":"Manufacturing & Wholesale Goods"
        }
    ],
    "sg:phone":"+1 585 244 4933",
    "sg:postcode":"14607",
    "sg:province":"NY",
    "sg:tags":[
        "furniture-wholesale",
        "manufacturer"
    ],
    "sg:website":"http://www.objectmaker.net",
    "wof:name":"Object Maker",
    "wof:placetype":"venue"
},
  "geometry": {"coordinates":[-77.589234,43.154542],"type":"Point"}
}