{
  "type": "Feature",
  "properties": {
    "iso:country":"US",
    "sg:address":"7 Ash Ln",
    "sg:city":"Hyde Park",
    "sg:classifiers":[
        {
            "category":"Food & Beverages",
            "subcategory":"Groceries & Convenience Stores",
            "type":"Retail Goods"
        }
    ],
    "sg:phone":"+1   ",
    "sg:postcode":"12538",
    "sg:province":"NY",
    "sg:tags":[
        "alcoholic"
    ],
    "wof:name":"Pjs Point Grocery & Deli",
    "wof:placetype":"venue"
},
  "geometry": {"coordinates":[-73.909463,41.811008],"type":"Point"}
}