{
  "type": "Feature",
  "properties": {
    "iso:country":"US",
    "sg:address":"409 Wells Ave W",
    "sg:city":"Syracuse",
    "sg:classifiers":[
        {
            "category":"Wholesale",
            "subcategory":"Durable Goods & Equipment",
            "type":"Manufacturing & Wholesale Goods"
        }
    ],
    "sg:phone":"+1 315 452 7014",
    "sg:postcode":"13212",
    "sg:province":"NY",
    "wof:name":"Lenze Group",
    "wof:placetype":"venue"
},
  "geometry": {"coordinates":[-76.14255199999999,43.131087],"type":"Point"}
}