{
  "type": "Feature",
  "properties": {
    "addr:full":"179 Morton Blvd Plainview NY 11803",
    "addr:housenumber":"179",
    "addr:postcode":"11803",
    "addr:street":"Morton Blvd",
    "iso:country":"US",
    "sg:address":"179 Morton Blvd",
    "sg:city":"Plainview",
    "sg:classifiers":[
        {
            "category":"Health Services",
            "subcategory":"Health Practitioner",
            "type":"Services"
        }
    ],
    "sg:phone":"+1 516 938 6723",
    "sg:postcode":"11803",
    "sg:province":"NY",
    "sg:tags":[
        "psychologist"
    ],
    "wof:name":"Cynthia Pascal",
    "wof:placetype":"venue"
},
  "geometry": {"coordinates":[-73.47602999999999,40.773481],"type":"Point"}
}