{
  "type": "Feature",
  "properties": {
    "iso:country":"US",
    "sg:address":"2403 Hyde Park Blvd",
    "sg:city":"Niagara Falls",
    "sg:classifiers":[
        {
            "category":"Wholesale",
            "subcategory":"Machinery & Supplies",
            "type":"Manufacturing & Wholesale Goods"
        },
        {
            "category":"Wholesale",
            "subcategory":"Stationery",
            "type":"Manufacturing & Wholesale Goods"
        }
    ],
    "sg:phone":"+1 716 298 4444",
    "sg:postcode":"14305",
    "sg:province":"NY",
    "sg:tags":[
        "product",
        "paper",
        "whole",
        "janitorial"
    ],
    "wof:name":"Harpor Paper Company",
    "wof:placetype":"venue"
},
  "geometry": {"coordinates":[-79.031361,43.111053],"type":"Point"}
}