{
  "type": "Feature",
  "properties": {
    "iso:country":"US",
    "sg:address":"600 Pardee Rd",
    "sg:city":"Rochester",
    "sg:classifiers":[
        {
            "category":"Education",
            "subcategory":"School",
            "type":"Public Place"
        }
    ],
    "sg:phone":"+1 585 339 1370",
    "sg:postcode":"14609",
    "sg:province":"NY",
    "wof:name":"Laurelton Pardee Intermediate",
    "wof:placetype":"venue"
},
  "geometry": {"coordinates":[-77.5531,43.185633],"type":"Point"}
}