{
  "type": "Feature",
  "properties": {
    "iso:country":"US",
    "sg:address":"9 Farmingham Dr",
    "sg:city":"Penfield",
    "sg:classifiers":[
        {
            "category":"Professional",
            "subcategory":"Lawyer & Legal Services",
            "type":"Services"
        }
    ],
    "sg:phone":"+1 585 377 5487",
    "sg:postcode":"14526",
    "sg:province":"NY",
    "sg:tags":[
        "attorney"
    ],
    "sg:website":"http://jmersereaulaw.com",
    "wof:name":"Office of Julie V. Mersereau, Esq.",
    "wof:placetype":"venue"
},
  "geometry": {"coordinates":[-77.45414700000001,43.134819],"type":"Point"}
}