{
  "type": "Feature",
  "properties": {
    "addr:full":"100 W Main St Palmyra NY 14522",
    "addr:housenumber":"100",
    "addr:postcode":"14522",
    "addr:street":"W Main St",
    "iso:country":"US",
    "sg:address":"100 W Main St",
    "sg:city":"Palmyra",
    "sg:classifiers":[
        {
            "category":"Organizations",
            "subcategory":"Religious Organization",
            "type":"Services"
        }
    ],
    "sg:phone":"+1 315 597 9212",
    "sg:postcode":"14522",
    "sg:province":"NY",
    "sg:website":"http://www.abc-usa.org",
    "wof:name":"First Baptist Church",
    "wof:placetype":"venue"
},
  "geometry": {"coordinates":[-77.233414,43.063599],"type":"Point"}
}