{
  "type": "Feature",
  "properties": {
    "iso:country":"US",
    "sg:address":"1584 52nd St",
    "sg:city":"Brooklyn",
    "sg:classifiers":[
        {
            "category":"Education",
            "subcategory":"School",
            "type":"Public Place"
        }
    ],
    "sg:phone":"+1 718 854 7260",
    "sg:postcode":"11219",
    "sg:province":"NY",
    "sg:tags":[
        "high",
        "middle",
        "elementary"
    ],
    "wof:name":"American Friends of B M G",
    "wof:placetype":"venue"
},
  "geometry": {"coordinates":[-73.987448,40.629447],"type":"Point"}
}