{
  "type": "Feature",
  "properties": {
    "addr:full":"96 E Main St East Islip NY 11730",
    "addr:housenumber":"96",
    "addr:postcode":"11730",
    "addr:street":"E Main St",
    "iso:country":"US",
    "sg:address":"96 E Main St",
    "sg:city":"East Islip",
    "sg:classifiers":[
        {
            "category":"Professional",
            "subcategory":"Lawyer & Legal Services",
            "type":"Services"
        }
    ],
    "sg:phone":"+1 800 987 4999",
    "sg:postcode":"11730",
    "sg:province":"NY",
    "wof:name":"Resnikoff Michael H Law Office Of",
    "wof:placetype":"venue"
},
  "geometry": {"coordinates":[-73.186232,40.731947],"type":"Point"}
}