{
  "type": "Feature",
  "properties": {
    "iso:country":"US",
    "sg:address":"2818 Curry Rd",
    "sg:city":"Schenectady",
    "sg:classifiers":[
        {
            "category":"Professional",
            "subcategory":"Computer Services",
            "type":"Services"
        }
    ],
    "sg:phone":"+1 518 356 5160",
    "sg:postcode":"12303",
    "sg:province":"NY",
    "sg:tags":[
        "system",
        "digital",
        "medium",
        "sales",
        "cad"
    ],
    "wof:name":"Imperatives Inc",
    "wof:placetype":"venue"
},
  "geometry": {"coordinates":[-73.914306,42.749388],"type":"Point"}
}