{
  "type": "Feature",
  "properties": {
    "iso:country":"US",
    "sg:address":"5964 Rte 25A",
    "sg:city":"Wading River",
    "sg:classifiers":[
        {
            "category":"Real Estate",
            "subcategory":"Real Estate Agent",
            "type":"Services"
        }
    ],
    "sg:phone":"+1 631 929 3600",
    "sg:postcode":"11792",
    "sg:province":"NY",
    "sg:tags":[
        "consulting",
        "management"
    ],
    "sg:website":"www.landmarkrealtyli.com",
    "wof:name":"Landmark Reaty Of Long Island",
    "wof:placetype":"venue"
},
  "geometry": {"coordinates":[-72.824955,40.945368],"type":"Point"}
}