{
  "type": "Feature",
  "properties": {
    "iso:country":"US",
    "sg:address":"11159 130th Street",
    "sg:city":"South Ozone Park",
    "sg:classifiers":[
        {
            "category":"Retail",
            "subcategory":"Repair Shop",
            "type":"Services"
        }
    ],
    "sg:phone":"+1 718 641 1004",
    "sg:postcode":"11420",
    "sg:province":"NY",
    "sg:tags":[
        "reupholstery",
        "furniture"
    ],
    "wof:name":"B & S Reupholstering and Decorating",
    "wof:placetype":"venue"
},
  "geometry": {"coordinates":[-73.812068,40.682519],"type":"Point"}
}