{
  "type": "Feature",
  "properties": {
    "addr:full":"200 Searles Rd Parish NY 13131",
    "addr:housenumber":"200",
    "addr:postcode":"13131",
    "addr:street":"Searles Rd",
    "iso:country":"US",
    "sg:address":"200 Searles Rd",
    "sg:city":"Parish",
    "sg:classifiers":[
        {
            "category":"Shopping",
            "subcategory":"Bicycles & Sporting Goods",
            "type":"Retail Goods"
        }
    ],
    "sg:phone":"+1   ",
    "sg:postcode":"13131",
    "sg:province":"NY",
    "wof:name":"Buckos Pro Shop",
    "wof:placetype":"venue"
},
  "geometry": {"coordinates":[-76.083681,43.450971],"type":"Point"}
}