{
  "type": "Feature",
  "properties": {
    "addr:full":"2250 Washington Ave Seaford NY 11783",
    "addr:housenumber":"2250",
    "addr:postcode":"11783",
    "addr:street":"Washington Ave",
    "iso:country":"US",
    "sg:address":"2250 Washington Ave",
    "sg:city":"Seaford",
    "sg:classifiers":[
        {
            "category":"Insurance",
            "subcategory":"Insurance Agent",
            "type":"Services"
        }
    ],
    "sg:phone":"+1 516 409 8625",
    "sg:postcode":"11783",
    "sg:province":"NY",
    "wof:name":"Aflac",
    "wof:placetype":"venue"
},
  "geometry": {"coordinates":[-73.48474400000001,40.666665],"type":"Point"}
}