{
  "type": "Feature",
  "properties": {
    "iso:country":"US",
    "sg:address":"275 Cooper Ave",
    "sg:city":"Tonawanda",
    "sg:classifiers":[
        {
            "category":"Wholesale",
            "subcategory":"Electrical",
            "type":"Manufacturing & Wholesale Goods"
        }
    ],
    "sg:phone":"+1 716 871 8657",
    "sg:postcode":"14150",
    "sg:province":"NY",
    "sg:tags":[
        "control"
    ],
    "sg:website":"www.niatechco.com",
    "wof:name":"Niatech Co",
    "wof:placetype":"venue"
},
  "geometry": {"coordinates":[-78.908671,42.986604],"type":"Point"}
}