{
  "type": "Feature",
  "properties": {
    "addr:full":"909 49th St Brooklyn NY 11219",
    "addr:housenumber":"909",
    "addr:postcode":"11219",
    "addr:street":"49Th St",
    "iso:country":"US",
    "sg:address":"909 49th St",
    "sg:city":"Brooklyn",
    "sg:classifiers":[
        {
            "category":"Health Services",
            "subcategory":"Doctor",
            "type":"Services"
        }
    ],
    "sg:phone":"+1 718 283 7743",
    "sg:postcode":"11219",
    "sg:province":"NY",
    "sg:tags":[
        "physician",
        "surgeon"
    ],
    "wof:name":"Pediatric Urology Assoc",
    "wof:placetype":"venue"
},
  "geometry": {"coordinates":[-73.998812,40.639183],"type":"Point"}
}