{
  "type": "Feature",
  "properties": {
    "iso:country":"US",
    "sg:address":"230 Keap St",
    "sg:city":"Brooklyn",
    "sg:classifiers":[
        {
            "category":"Organizations",
            "subcategory":"Religious Organization",
            "type":"Services"
        }
    ],
    "sg:phone":"+1 718 387 2151",
    "sg:postcode":"11211",
    "sg:province":"NY",
    "sg:tags":[
        "clergy"
    ],
    "wof:name":"Jacob Berger",
    "wof:placetype":"venue"
},
  "geometry": {"coordinates":[-73.95822099999999,40.704838],"type":"Point"}
}