{
  "type": "Feature",
  "properties": {
    "iso:country":"US",
    "sg:address":"212 W 35th Street",
    "sg:city":"New York",
    "sg:classifiers":[
        {
            "category":"Shopping",
            "subcategory":"Crafts & Fabrics",
            "type":"Retail Goods"
        }
    ],
    "sg:phone":"+1 212 465 0780",
    "sg:postcode":"10001",
    "sg:province":"NY",
    "sg:tags":[
        "store"
    ],
    "wof:name":"Prime Tex",
    "wof:placetype":"venue"
},
  "geometry": {"coordinates":[-73.99046199999999,40.751785],"type":"Point"}
}