{
  "type": "Feature",
  "properties": {
    "iso:country":"US",
    "sg:address":"154 Main St",
    "sg:city":"Massena",
    "sg:classifiers":[
        {
            "category":"Health Services",
            "subcategory":"Doctor",
            "type":"Services"
        }
    ],
    "sg:phone":"+1 315 769 1667",
    "sg:postcode":"13662",
    "sg:province":"NY",
    "sg:tags":[
        "physician",
        "surgeon"
    ],
    "wof:name":"Luis I Canales MD",
    "wof:placetype":"venue"
},
  "geometry": {"coordinates":[-74.89184899999999,44.927847],"type":"Point"}
}