{
  "type": "Feature",
  "properties": {
    "addr:full":"210 River St Troy NY 12180",
    "addr:housenumber":"210",
    "addr:postcode":"12180",
    "addr:street":"River St",
    "iso:country":"US",
    "sg:address":"210 River St",
    "sg:city":"Troy",
    "sg:classifiers":[
        {
            "category":"Professional",
            "type":"Services"
        }
    ],
    "sg:phone":"+1 518 274 3050",
    "sg:postcode":"12180",
    "sg:province":"NY",
    "sg:tags":[
        "establishment"
    ],
    "sg:website":"www.tapinc.org",
    "wof:name":"TAP Inc",
    "wof:placetype":"venue"
},
  "geometry": {"coordinates":[-73.69360500000001,42.730768],"type":"Point"}
}