{
  "type": "Feature",
  "properties": {
    "addr:full":"105 Corporate Park Dr White Plains NY 10604",
    "addr:housenumber":"105",
    "addr:postcode":"10604",
    "addr:street":"Corporate Park Dr",
    "iso:country":"US",
    "sg:address":"105 Corporate Park Dr",
    "sg:city":"White Plains",
    "sg:classifiers":[
        {
            "category":"Professional",
            "type":"Services"
        }
    ],
    "sg:phone":"+1 914 251 1375",
    "sg:postcode":"10604",
    "sg:province":"NY",
    "sg:tags":[
        "establishment"
    ],
    "wof:name":"General General",
    "wof:placetype":"venue"
},
  "geometry": {"coordinates":[-73.720322,41.020098],"type":"Point"}
}