{
  "type": "Feature",
  "properties": {
    "addr:full":"2 Laurel Rd East Northport NY 11731",
    "addr:housenumber":"2",
    "addr:postcode":"11731",
    "addr:street":"Laurel Rd",
    "iso:country":"US",
    "sg:address":"2 Laurel Rd",
    "sg:city":"East Northport",
    "sg:classifiers":[
        {
            "category":"Cinema",
            "subcategory":"Movie Rental",
            "type":"Entertainment"
        }
    ],
    "sg:phone":"+1 212 754 9079",
    "sg:postcode":"11731",
    "sg:province":"NY",
    "sg:tags":[
        "leasing",
        "video",
        "disc",
        "tape"
    ],
    "wof:name":"Novell Video",
    "wof:placetype":"venue"
},
  "geometry": {"coordinates":[-73.32630399999999,40.882979],"type":"Point"}
}