{
  "type": "Feature",
  "properties": {
    "addr:full":"3593 State Hwy 281 Cortland NY 13045",
    "addr:housenumber":"3593",
    "addr:postcode":"13045",
    "addr:street":"State Hwy 281",
    "iso:country":"US",
    "sg:address":"3593 State Hwy 281",
    "sg:city":"Cortland",
    "sg:classifiers":[
        {
            "category":"Wholesale",
            "subcategory":"Machinery & Supplies",
            "type":"Manufacturing & Wholesale Goods"
        }
    ],
    "sg:phone":"+1 607 753 7077",
    "sg:postcode":"13045",
    "sg:province":"NY",
    "sg:tags":[
        "salon",
        "beauty"
    ],
    "wof:name":"Best-Way Barber & Beauty Supl",
    "wof:placetype":"venue"
},
  "geometry": {"coordinates":[-76.21413200000001,42.580036],"type":"Point"}
}