{
  "type": "Feature",
  "properties": {
    "addr:full":"41 W 47 St New York NY 10036",
    "addr:housenumber":"41",
    "addr:postcode":"10036",
    "addr:street":"W 47 St",
    "iso:country":"US",
    "sg:address":"41 W 47 St",
    "sg:city":"New York",
    "sg:classifiers":[
        {
            "category":"Shopping",
            "subcategory":"Jewelry",
            "type":"Retail Goods"
        }
    ],
    "sg:phone":"+1 212 997 1975",
    "sg:postcode":"10036",
    "sg:province":"NY",
    "sg:tags":[
        "jeweler"
    ],
    "wof:name":"Nellys Fine Jewelry Inc",
    "wof:placetype":"venue"
},
  "geometry": {"coordinates":[-73.98075900000001,40.757529],"type":"Point"}
}