{
  "type": "Feature",
  "properties": {
    "addr:full":"425 S Oyster Bay Rd Plainview NY 11803",
    "addr:housenumber":"425",
    "addr:postcode":"11803",
    "addr:street":"S Oyster Bay Rd",
    "iso:country":"US",
    "sg:address":"425 S Oyster Bay Rd",
    "sg:city":"Plainview",
    "sg:classifiers":[
        {
            "category":"Food & Beverages",
            "subcategory":"Groceries & Convenience Stores",
            "type":"Retail Goods"
        }
    ],
    "sg:phone":"+1 516 933 6900",
    "sg:postcode":"11803",
    "sg:province":"NY",
    "sg:tags":[
        "grocer"
    ],
    "sg:website":"www.traderjoes.com",
    "wof:name":"Trader Joe's",
    "wof:placetype":"venue"
},
  "geometry": {"coordinates":[-73.502741,40.781608],"type":"Point"}
}