{
  "type": "Feature",
  "properties": {
    "addr:full":"9 Albertson Ave Albertson NY 11507",
    "addr:housenumber":"9",
    "addr:postcode":"11507",
    "addr:street":"Albertson Ave",
    "iso:country":"US",
    "sg:address":"9 Albertson Ave",
    "sg:city":"Albertson",
    "sg:classifiers":[
        {
            "category":"Education",
            "subcategory":"Dance Studio",
            "type":"Public Place"
        }
    ],
    "sg:phone":"+1 516 625 1010",
    "sg:postcode":"11507",
    "sg:province":"NY",
    "sg:tags":[
        "art",
        "performing",
        "instruction",
        "dancing"
    ],
    "wof:name":"Let's Dance",
    "wof:placetype":"venue"
},
  "geometry": {"coordinates":[-73.642403,40.773102],"type":"Point"}
}