{
  "type": "Feature",
  "properties": {
    "addr:full":"969 Park Ave New York NY 10028",
    "addr:housenumber":"969",
    "addr:postcode":"10028",
    "addr:street":"Park Ave",
    "iso:country":"US",
    "sg:address":"969 Park Ave",
    "sg:city":"New York",
    "sg:classifiers":[
        {
            "category":"Shopping",
            "subcategory":"Clothing, Apparel, & Fashions",
            "type":"Retail Goods"
        }
    ],
    "sg:phone":"+1   ",
    "sg:postcode":"10028",
    "sg:province":"NY",
    "sg:tags":[
        "designer",
        "scarf"
    ],
    "wof:name":"Justine Brooke",
    "wof:placetype":"venue"
},
  "geometry": {"coordinates":[-73.958737,40.777873],"type":"Point"}
}