{
  "type": "Feature",
  "properties": {
    "addr:full":"99 Woodbury Rd Hicksville NY 11801",
    "addr:housenumber":"99",
    "addr:postcode":"11801",
    "addr:street":"Woodbury Rd",
    "iso:country":"US",
    "sg:address":"99 Woodbury Rd",
    "sg:city":"Hicksville",
    "sg:classifiers":[
        {
            "category":"Professional",
            "subcategory":"Lawyer & Legal Services",
            "type":"Services"
        }
    ],
    "sg:phone":"+1 516 806 5066",
    "sg:postcode":"11801",
    "sg:province":"NY",
    "wof:name":"PEARLMAN APAT FUTTERMAN SIROTKIN & SEINFELD LLP",
    "wof:placetype":"venue"
},
  "geometry": {"coordinates":[-73.516597,40.772516],"type":"Point"}
}