{
  "type": "Feature",
  "properties": {
    "addr:full":"123 Bayton Dr Rochester NY 14622",
    "addr:housenumber":"123",
    "addr:postcode":"14622",
    "addr:street":"Bayton Dr",
    "iso:country":"US",
    "sg:address":"123 Bayton Dr",
    "sg:city":"Rochester",
    "sg:classifiers":[
        {
            "category":"Building & Trades",
            "subcategory":"Landscaping Services",
            "type":"Services"
        }
    ],
    "sg:phone":"+1 585 467 9364",
    "sg:postcode":"14622",
    "sg:province":"NY",
    "sg:tags":[
        "tree"
    ],
    "wof:name":"Shape Shifter Tree Service",
    "wof:placetype":"venue"
},
  "geometry": {"coordinates":[-77.55000099999999,43.229166],"type":"Point"}
}