{
  "type": "Feature",
  "properties": {
    "addr:full":"674 Broadway Brooklyn NY 11206",
    "addr:housenumber":"674",
    "addr:postcode":"11206",
    "addr:street":"Broadway",
    "iso:country":"US",
    "sg:address":"674 Broadway",
    "sg:city":"Brooklyn",
    "sg:classifiers":[
        {
            "category":"Personal",
            "subcategory":"Barber",
            "type":"Services"
        },
        {
            "category":"Personal",
            "subcategory":"Nail Salon",
            "type":"Services"
        }
    ],
    "sg:phone":"+1 718 387 7031",
    "sg:postcode":"11206",
    "sg:province":"NY",
    "wof:name":"Color Nail & Beauty Salon Inc",
    "wof:placetype":"venue"
},
  "geometry": {"coordinates":[-73.944315,40.701959],"type":"Point"}
}