{
  "type": "Feature",
  "properties": {
    "addr:full":"633 3rd Avenue New York NY 10017",
    "addr:housenumber":"633",
    "addr:postcode":"10017",
    "addr:street":"3Rd Avenue",
    "iso:country":"US",
    "sg:address":"633 3rd Avenue",
    "sg:city":"New York",
    "sg:classifiers":[
        {
            "category":"Organizations",
            "subcategory":"Non-profit Organization",
            "type":"Services"
        }
    ],
    "sg:phone":"+1 212 318 6111",
    "sg:postcode":"10017",
    "sg:province":"NY",
    "sg:tags":[
        "service/non-profit",
        "community"
    ],
    "wof:name":"Conference of Presidents of Major Jewish Organizations",
    "wof:placetype":"venue"
},
  "geometry": {"coordinates":[-73.975123,40.749824],"type":"Point"}
}