{
  "type": "Feature",
  "properties": {
    "addr:full":"2964 Jerome Ave Bronx NY 10468",
    "addr:housenumber":"2964",
    "addr:postcode":"10468",
    "addr:street":"Jerome Ave",
    "iso:country":"US",
    "sg:address":"2964 Jerome Ave",
    "sg:city":"Bronx",
    "sg:classifiers":[
        {
            "category":"Shopping",
            "subcategory":"Florist",
            "type":"Retail Goods"
        }
    ],
    "sg:phone":"+1   ",
    "sg:postcode":"10468",
    "sg:province":"NY",
    "wof:name":"Enchanted Florist",
    "wof:placetype":"venue"
},
  "geometry": {"coordinates":[-73.889422,40.872995],"type":"Point"}
}