{
  "type": "Feature",
  "properties": {
    "iso:country":"US",
    "sg:address":"1476 54th St",
    "sg:city":"Brooklyn",
    "sg:classifiers":[
        {
            "category":"Building & Trades",
            "subcategory":"Construction",
            "type":"Services"
        }
    ],
    "sg:phone":"+1 718 851 8599",
    "sg:postcode":"11219",
    "sg:province":"NY",
    "sg:tags":[
        "housing"
    ],
    "wof:name":"Skyview Builders Inc",
    "wof:placetype":"venue"
},
  "geometry": {"coordinates":[-73.991967,40.630539],"type":"Point"}
}