{
  "type": "Feature",
  "properties": {
    "addr:full":"1531 Goshen Tpke Middletown NY 10941",
    "addr:housenumber":"1531",
    "addr:postcode":"10941",
    "addr:street":"Goshen Tpke",
    "iso:country":"US",
    "sg:address":"1531 Goshen Tpke",
    "sg:city":"Middletown",
    "sg:classifiers":[
        {
            "category":"Professional",
            "subcategory":"Secretarial Services",
            "type":"Services"
        }
    ],
    "sg:phone":"+1 845 692 3470",
    "sg:postcode":"10941",
    "sg:province":"NY",
    "sg:tags":[
        "transcription",
        "medical"
    ],
    "wof:name":"Transcription Plus",
    "wof:placetype":"venue"
},
  "geometry": {"coordinates":[-74.36177000000001,41.483591],"type":"Point"}
}