{
  "type": "Feature",
  "properties": {
    "iso:country":"US",
    "sg:address":"89 Washington Ave",
    "sg:city":"White Plains",
    "sg:classifiers":[
        {
            "category":"Building & Trades",
            "subcategory":"Construction",
            "type":"Services"
        }
    ],
    "sg:phone":"+1 914 421 2061",
    "sg:postcode":"10603",
    "sg:province":"NY",
    "sg:tags":[
        "painting",
        "contractor"
    ],
    "wof:name":"Mr G Painting Corp",
    "wof:placetype":"venue"
},
  "geometry": {"coordinates":[-73.797622,41.048027],"type":"Point"}
}