{
  "type": "Feature",
  "properties": {
    "iso:country":"US",
    "sg:address":"976 Bard Avenue",
    "sg:city":"Staten Island",
    "sg:classifiers":[
        {
            "category":"Health Services",
            "subcategory":"Doctor",
            "type":"Services"
        },
        {
            "category":"Health Services",
            "subcategory":"Dentist",
            "type":"Services"
        }
    ],
    "sg:phone":"+1 718 448 1866",
    "sg:postcode":"10301",
    "sg:province":"NY",
    "sg:tags":[
        "surgeon",
        "oral"
    ],
    "wof:name":"Isaac Tbeile DDS",
    "wof:placetype":"venue"
},
  "geometry": {"coordinates":[-74.11007499999999,40.620799],"type":"Point"}
}