{
  "type": "Feature",
  "properties": {
    "iso:country":"US",
    "sg:address":"5 W Main St",
    "sg:city":"Elmsford",
    "sg:classifiers":[
        {
            "category":"Professional",
            "subcategory":"Detective & Security Services",
            "type":"Services"
        }
    ],
    "sg:phone":"+1 914 347 4047",
    "sg:postcode":"10523",
    "sg:province":"NY",
    "sg:tags":[
        "information",
        "bureau"
    ],
    "wof:name":"Jucar Subscription Services, Inc.",
    "wof:placetype":"venue"
},
  "geometry": {"coordinates":[-73.821472,41.055659],"type":"Point"}
}