{
  "type": "Feature",
  "properties": {
    "addr:full":"1324 E 15th St Brooklyn NY 11230",
    "addr:housenumber":"1324",
    "addr:postcode":"11230",
    "addr:street":"E 15Th St",
    "iso:country":"US",
    "sg:address":"1324 E 15th St",
    "sg:city":"Brooklyn",
    "sg:classifiers":[
        {
            "category":"Real Estate",
            "subcategory":"Real Estate Agent",
            "type":"Services"
        }
    ],
    "sg:phone":"+1 718 627 1557",
    "sg:postcode":"11230",
    "sg:province":"NY",
    "wof:name":"656 Realty LLC",
    "wof:placetype":"venue"
},
  "geometry": {"coordinates":[-73.95971299999999,40.615996],"type":"Point"}
}