{
  "type": "Feature",
  "properties": {
    "addr:full":"170 Broadway New York NY 10038",
    "addr:housenumber":"170",
    "addr:postcode":"10038",
    "addr:street":"Broadway",
    "iso:country":"US",
    "sg:address":"170 Broadway",
    "sg:city":"New York",
    "sg:classifiers":[
        {
            "category":"Communications",
            "subcategory":"Television Station",
            "type":"Services"
        }
    ],
    "sg:phone":"+1 212 623 1092",
    "sg:postcode":"10038",
    "sg:province":"NY",
    "sg:tags":[
        "broadcasting",
        "co"
    ],
    "wof:name":"Market Report Corp",
    "wof:placetype":"venue"
},
  "geometry": {"coordinates":[-74.01010100000001,40.709702],"type":"Point"}
}