{
  "type": "Feature",
  "properties": {
    "iso:country":"US",
    "sg:address":"527 W 34th St",
    "sg:city":"New York",
    "sg:classifiers":[
        {
            "category":"Building & Trades",
            "subcategory":"Equipment Rental",
            "type":"Services"
        },
        {
            "category":"Shopping",
            "subcategory":"Computers & Home Electronics",
            "type":"Retail Goods"
        }
    ],
    "sg:phone":"+1 212 643 0040",
    "sg:postcode":"10001",
    "sg:province":"NY",
    "sg:tags":[
        "visual",
        "audio",
        "installation",
        "sale"
    ],
    "sg:website":"www.avworkshop.com",
    "wof:name":"A V Workshop",
    "wof:placetype":"venue"
},
  "geometry": {"coordinates":[-74.00144899999999,40.755398],"type":"Point"}
}