{
  "type": "Feature",
  "properties": {
    "iso:country":"US",
    "sg:address":"6115 Gillette Rd",
    "sg:city":"Cicero",
    "sg:classifiers":[
        {
            "category":"Retail",
            "subcategory":"Auto Repair",
            "type":"Services"
        }
    ],
    "sg:phone":"+1 315 698 8324",
    "sg:postcode":"13039",
    "sg:province":"NY",
    "sg:tags":[
        "transmission",
        "automotive"
    ],
    "wof:name":"Hy Tech Transmission",
    "wof:placetype":"venue"
},
  "geometry": {"coordinates":[-76.096484,43.162373],"type":"Point"}
}