{
  "type": "Feature",
  "properties": {
    "iso:country":"US",
    "sg:address":"111 Bowman Ave",
    "sg:city":"Rye Brook",
    "sg:classifiers":[
        {
            "category":"Building & Trades",
            "subcategory":"Construction",
            "type":"Services"
        }
    ],
    "sg:phone":"+1 914 937 7804",
    "sg:postcode":"10573",
    "sg:province":"NY",
    "sg:tags":[
        "contractor"
    ],
    "wof:name":"Perdikaris/Constantine Devmnt",
    "wof:placetype":"venue"
},
  "geometry": {"coordinates":[-73.69194,41.004662],"type":"Point"}
}