{
  "type": "Feature",
  "properties": {
    "addr:full":"773 Broadway Kingston NY 12401",
    "addr:housenumber":"773",
    "addr:postcode":"12401",
    "addr:street":"Broadway",
    "iso:country":"US",
    "sg:address":"773 Broadway",
    "sg:city":"Kingston",
    "sg:classifiers":[
        {
            "category":"Shopping",
            "subcategory":"Florist",
            "type":"Retail Goods"
        }
    ],
    "sg:phone":"+1 845 339 6218",
    "sg:postcode":"12401",
    "sg:province":"NY",
    "wof:name":"A Michaels Candy Corner & Flrt",
    "wof:placetype":"venue"
},
  "geometry": {"coordinates":[-74.012141,41.932306],"type":"Point"}
}