{
  "type": "Feature",
  "properties": {
    "iso:country":"US",
    "sg:address":"114 Main St",
    "sg:city":"Northport",
    "sg:classifiers":[
        {
            "category":"Shopping",
            "subcategory":"Gifts & Souvenirs",
            "type":"Retail Goods"
        }
    ],
    "sg:phone":"+1   ",
    "sg:postcode":"11768",
    "sg:province":"NY",
    "sg:tags":[
        "jewelry"
    ],
    "sg:website":"www.the-essence.com",
    "wof:name":"Essence",
    "wof:placetype":"venue"
},
  "geometry": {"coordinates":[-73.348974,40.900502],"type":"Point"}
}