{
  "type": "Feature",
  "properties": {
    "iso:country":"US",
    "sg:address":"146 Dartmouth Dr",
    "sg:city":"Hicksville",
    "sg:classifiers":[
        {
            "category":"Manufacturing",
            "subcategory":"Printing",
            "type":"Manufacturing & Wholesale Goods"
        }
    ],
    "sg:phone":"+1   ",
    "sg:postcode":"11801",
    "sg:province":"NY",
    "sg:tags":[
        "poster",
        "copy",
        "art",
        "publishing"
    ],
    "wof:name":"American Art Publishing Co",
    "wof:placetype":"venue"
},
  "geometry": {"coordinates":[-73.508094,40.777075],"type":"Point"}
}