{
  "type": "Feature",
  "properties": {
    "addr:full":"135 Delancey St New York NY 10002",
    "addr:housenumber":"135",
    "addr:postcode":"10002",
    "addr:street":"Delancey St",
    "iso:country":"US",
    "sg:address":"135 Delancey St",
    "sg:city":"New York",
    "sg:classifiers":[
        {
            "category":"Parking",
            "type":"Transportation"
        }
    ],
    "sg:phone":"+1 212 505 7153",
    "sg:postcode":"10002",
    "sg:province":"NY",
    "sg:tags":[
        "garage"
    ],
    "wof:name":"Central Parking System",
    "wof:placetype":"venue"
},
  "geometry": {"coordinates":[-73.986788,40.71801],"type":"Point"}
}