{
  "type": "Feature",
  "properties": {
    "addr:full":"1205 Surf Ave Brooklyn NY 11224",
    "addr:housenumber":"1205",
    "addr:postcode":"11224",
    "addr:street":"Surf Ave",
    "iso:country":"US",
    "sg:address":"1205 Surf Ave",
    "sg:city":"Brooklyn",
    "sg:classifiers":[
        {
            "category":"Education",
            "subcategory":"Dance Studio",
            "type":"Public Place"
        }
    ],
    "sg:phone":"+1 718 996 2000",
    "sg:postcode":"11224",
    "sg:province":"NY",
    "sg:tags":[
        "instruction",
        "dancing"
    ],
    "wof:name":"Art's House Inc",
    "wof:placetype":"venue"
},
  "geometry": {"coordinates":[-73.98053299999999,40.575636],"type":"Point"}
}