{
  "type": "Feature",
  "properties": {
    "iso:country":"US",
    "sg:address":"5440 Hinman Rd",
    "sg:city":"Lockport",
    "sg:classifiers":[
        {
            "category":"Retail",
            "subcategory":"Auto Repair",
            "type":"Services"
        }
    ],
    "sg:phone":"+1 716 434 0282",
    "sg:postcode":"14094",
    "sg:province":"NY",
    "sg:tags":[
        "repairing",
        "automobile"
    ],
    "wof:name":"Daningburgs",
    "wof:placetype":"venue"
},
  "geometry": {"coordinates":[-78.734054,43.146505],"type":"Point"}
}