{
  "type": "Feature",
  "properties": {
    "iso:country":"US",
    "sg:address":"23 Flatbush Avenue Ext",
    "sg:city":"Brooklyn",
    "sg:classifiers":[
        {
            "category":"Building & Trades",
            "subcategory":"Locksmith",
            "type":"Services"
        }
    ],
    "sg:phone":"+1 347 464 3938",
    "sg:postcode":"11201",
    "sg:province":"NY",
    "sg:tags":[
        "key"
    ],
    "wof:name":"Amazon Lock and Key",
    "wof:placetype":"venue"
},
  "geometry": {"coordinates":[-73.984832,40.697278],"type":"Point"}
}