{
  "type": "Feature",
  "properties": {
    "iso:country":"US",
    "sg:address":"4504 E Lake Rd",
    "sg:city":"Canandaigua",
    "sg:classifiers":[
        {
            "category":"Shopping",
            "subcategory":"Discount & Variety Stores",
            "type":"Retail Goods"
        }
    ],
    "sg:phone":"+1   ",
    "sg:postcode":"14424",
    "sg:province":"NY",
    "sg:tags":[
        "shop",
        "grocery",
        "pizza",
        "sub",
        "general"
    ],
    "wof:name":"Crystal Beach General Store",
    "wof:placetype":"venue"
},
  "geometry": {"coordinates":[-77.259339,42.81038],"type":"Point"}
}