{
  "type": "Feature",
  "properties": {
    "addr:full":"18 Virginia Ave Ronkonkoma NY 11779",
    "addr:housenumber":"18",
    "addr:postcode":"11779",
    "addr:street":"Virginia Ave",
    "iso:country":"US",
    "sg:address":"18 Virginia Ave",
    "sg:city":"Ronkonkoma",
    "sg:classifiers":[
        {
            "category":"Health Services",
            "subcategory":"Health Practitioner",
            "type":"Services"
        }
    ],
    "sg:phone":"+1 631 834 9719",
    "sg:postcode":"11779",
    "sg:province":"NY",
    "sg:tags":[
        "therapist",
        "physical"
    ],
    "wof:name":"Karen M Feldmann Lmt",
    "wof:placetype":"venue"
},
  "geometry": {"coordinates":[-73.105789,40.839931],"type":"Point"}
}