{
  "type": "Feature",
  "properties": {
    "iso:country":"US",
    "sg:address":"325 Broadway",
    "sg:city":"New York",
    "sg:classifiers":[
        {
            "category":"Health Services",
            "subcategory":"Doctor",
            "type":"Services"
        }
    ],
    "sg:phone":"+1 212 843 0205",
    "sg:postcode":"10007",
    "sg:province":"NY",
    "sg:tags":[
        "dentist"
    ],
    "wof:name":"Foley Square Dental",
    "wof:placetype":"venue"
},
  "geometry": {"coordinates":[-74.00476399999999,40.71606],"type":"Point"}
}