{
  "type": "Feature",
  "properties": {
    "addr:full":"252 W 29th St New York NY 10001",
    "addr:housenumber":"252",
    "addr:postcode":"10001",
    "addr:street":"W 29Th St",
    "iso:country":"US",
    "sg:address":"252 W 29th St",
    "sg:city":"New York",
    "sg:classifiers":[
        {
            "category":"Real Estate",
            "subcategory":"Real Estate Agent",
            "type":"Services"
        },
        {
            "category":"Real Estate",
            "subcategory":"Real Estate Operator",
            "type":"Services"
        }
    ],
    "sg:phone":"+1 212 947 4545",
    "sg:postcode":"10001",
    "sg:province":"NY",
    "sg:tags":[
        "commercial"
    ],
    "wof:name":"Charand Real Estate Assoc",
    "wof:placetype":"venue"
},
  "geometry": {"coordinates":[-73.99464399999999,40.748351],"type":"Point"}
}