{
  "type": "Feature",
  "properties": {
    "iso:country":"US",
    "sg:address":"102 Fulton St",
    "sg:city":"White Plains",
    "sg:classifiers":[
        {
            "category":"Building & Trades",
            "subcategory":"Construction",
            "type":"Services"
        }
    ],
    "sg:phone":"+1 914 761 5370",
    "sg:postcode":"10606",
    "sg:province":"NY",
    "sg:tags":[
        "contractor"
    ],
    "wof:name":"Mid Westchester Seal Coating",
    "wof:placetype":"venue"
},
  "geometry": {"coordinates":[-73.784825,41.034993],"type":"Point"}
}