{
  "type": "Feature",
  "properties": {
    "addr:full":"32 Eklund Blvd Nesconset NY 11767",
    "addr:housenumber":"32",
    "addr:postcode":"11767",
    "addr:street":"Eklund Blvd",
    "iso:country":"US",
    "sg:address":"32 Eklund Blvd",
    "sg:city":"Nesconset",
    "sg:classifiers":[
        {
            "category":"Professional",
            "subcategory":"Management & Consulting",
            "type":"Services"
        },
        {
            "category":"Professional",
            "subcategory":"Computer Services",
            "type":"Services"
        }
    ],
    "sg:phone":"+1 631 580 2498",
    "sg:postcode":"11767",
    "sg:province":"NY",
    "sg:tags":[
        "fuel",
        "related"
    ],
    "wof:name":"Long Island Systems Mgmt",
    "wof:placetype":"venue"
},
  "geometry": {"coordinates":[-73.131344,40.843364],"type":"Point"}
}