{
  "type": "Feature",
  "properties": {
    "addr:full":"310 Lenox Ave New York NY 10027",
    "addr:housenumber":"310",
    "addr:postcode":"10027",
    "addr:street":"Lenox Ave",
    "iso:country":"US",
    "sg:address":"310 Lenox Ave",
    "sg:city":"New York",
    "sg:classifiers":[
        {
            "category":"Wholesale",
            "subcategory":"Machinery & Supplies",
            "type":"Manufacturing & Wholesale Goods"
        }
    ],
    "sg:phone":"+1 212 860 9283",
    "sg:postcode":"10027",
    "sg:province":"NY",
    "sg:tags":[
        "printer",
        "cartridge"
    ],
    "wof:name":"Graphic Arts Enterprises",
    "wof:placetype":"venue"
},
  "geometry": {"coordinates":[-73.945159,40.807989],"type":"Point"}
}