{
  "type": "Feature",
  "properties": {
    "addr:full":"59 Church St Owego NY 13827",
    "addr:housenumber":"59",
    "addr:postcode":"13827",
    "addr:street":"Church St",
    "iso:country":"US",
    "sg:address":"59 Church St",
    "sg:city":"Owego",
    "sg:classifiers":[
        {
            "category":"Manufacturing",
            "subcategory":"Printing",
            "type":"Manufacturing & Wholesale Goods"
        }
    ],
    "sg:phone":"+1   ",
    "sg:postcode":"13827",
    "sg:province":"NY",
    "sg:tags":[
        "newspaper"
    ],
    "wof:name":"Tioga County Courier",
    "wof:placetype":"venue"
},
  "geometry": {"coordinates":[-76.262175,42.105365],"type":"Point"}
}