{
  "type": "Feature",
  "properties": {
    "iso:country":"US",
    "sg:address":"2028 N Country Rd",
    "sg:city":"Wading River",
    "sg:classifiers":[
        {
            "category":"Restaurant",
            "type":"Food & Drink"
        }
    ],
    "sg:phone":"+1 631 929 3900",
    "sg:postcode":"11792",
    "sg:province":"NY",
    "wof:name":"Andrews By The Pond",
    "wof:placetype":"venue"
},
  "geometry": {"coordinates":[-72.84554900000001,40.951511],"type":"Point"}
}