{
  "type": "Feature",
  "properties": {
    "addr:full":"1401 Franklin Ave Garden City NY 11530",
    "addr:housenumber":"1401",
    "addr:postcode":"11530",
    "addr:street":"Franklin Ave",
    "iso:country":"US",
    "sg:address":"1401 Franklin Ave",
    "sg:city":"Garden City",
    "sg:classifiers":[
        {
            "category":"Banks & Credit Unions",
            "subcategory":"Bank",
            "type":"Services"
        }
    ],
    "sg:phone":"+1 516 294 2268",
    "sg:postcode":"11530",
    "sg:province":"NY",
    "sg:website":"www.bankofny.com",
    "wof:name":"Bank Of New York",
    "wof:placetype":"venue"
},
  "geometry": {"coordinates":[-73.63860699999999,40.737302],"type":"Point"}
}