{
  "type": "Feature",
  "properties": {
    "addr:full":"18 State St Saranac Lake NY 12983",
    "addr:housenumber":"18",
    "addr:postcode":"12983",
    "addr:street":"State St",
    "iso:country":"US",
    "sg:address":"18 State St",
    "sg:city":"Saranac Lake",
    "sg:classifiers":[
        {
            "category":"Building & Trades",
            "subcategory":"Electrical",
            "type":"Services"
        }
    ],
    "sg:phone":"+1 518 891 3301",
    "sg:postcode":"12983",
    "sg:province":"NY",
    "sg:tags":[
        "electrical",
        "contractor"
    ],
    "wof:name":"Beefs Electric",
    "wof:placetype":"venue"
},
  "geometry": {"coordinates":[-74.154918,44.316654],"type":"Point"}
}