{
  "type": "Feature",
  "properties": {
    "iso:country":"US",
    "sg:address":"7 W Main St",
    "sg:city":"Middletown",
    "sg:classifiers":[
        {
            "category":"Real Estate",
            "subcategory":"Real Estate Agent",
            "type":"Services"
        }
    ],
    "sg:phone":"+1 845 344 4244",
    "sg:postcode":"10940",
    "sg:province":"NY",
    "wof:name":"Hudson Valley Property Cnslttn",
    "wof:placetype":"venue"
},
  "geometry": {"coordinates":[-74.421008,41.445052],"type":"Point"}
}