{
  "type": "Feature",
  "properties": {
    "addr:full":"249 Columbus Ave New York NY 10023",
    "addr:housenumber":"249",
    "addr:postcode":"10023",
    "addr:street":"Columbus Ave",
    "iso:country":"US",
    "sg:address":"249 Columbus Ave",
    "sg:city":"New York",
    "sg:classifiers":[
        {
            "category":"Restaurant",
            "type":"Food & Drink"
        }
    ],
    "sg:phone":"+1 212 579 9929",
    "sg:postcode":"10023",
    "sg:province":"NY",
    "sg:tags":[
        "american",
        "latin"
    ],
    "sg:website":"www.caferonda.com",
    "wof:name":"Cafe Ronda",
    "wof:placetype":"venue"
},
  "geometry": {"coordinates":[-73.97904699999999,40.777032],"type":"Point"}
}