{
  "type": "Feature",
  "properties": {
    "addr:full":"1400 Flint Town Rd Boonville NY 13309",
    "addr:housenumber":"1400",
    "addr:postcode":"13309",
    "addr:street":"Flint Town Rd",
    "iso:country":"US",
    "sg:address":"1400 Flint Town Rd",
    "sg:city":"Boonville",
    "sg:classifiers":[
        {
            "category":"Retail",
            "subcategory":"Auto Repair",
            "type":"Services"
        }
    ],
    "sg:phone":"+1 315 942 4261",
    "sg:postcode":"13309",
    "sg:province":"NY",
    "sg:tags":[
        "body",
        "automobile",
        "painting",
        "repairing"
    ],
    "wof:name":"J R Jones Auto",
    "wof:placetype":"venue"
},
  "geometry": {"coordinates":[-75.44743800000001,43.409481],"type":"Point"}
}