{
  "type": "Feature",
  "properties": {
    "iso:country":"US",
    "sg:address":"74 Vista Ave",
    "sg:city":"Staten Island",
    "sg:classifiers":[
        {
            "category":"Building & Trades",
            "subcategory":"Construction",
            "type":"Services"
        }
    ],
    "sg:phone":"+1 718 980 6921",
    "sg:postcode":"10304",
    "sg:province":"NY",
    "sg:tags":[
        "hanging",
        "contractor"
    ],
    "wof:name":"Custom Coat Painting Inc",
    "wof:placetype":"venue"
},
  "geometry": {"coordinates":[-74.0968,40.597735],"type":"Point"}
}