{
  "type": "Feature",
  "properties": {
    "addr:full":"3120 Church Ave Brooklyn NY 11226",
    "addr:housenumber":"3120",
    "addr:postcode":"11226",
    "addr:street":"Church Ave",
    "iso:country":"US",
    "sg:address":"3120 Church Ave",
    "sg:city":"Brooklyn",
    "sg:classifiers":[
        {
            "category":"Real Estate",
            "subcategory":"Real Estate Agent",
            "type":"Services"
        }
    ],
    "sg:phone":"+1 718 940 1036",
    "sg:postcode":"11226",
    "sg:province":"NY",
    "wof:name":"Hometown",
    "wof:placetype":"venue"
},
  "geometry": {"coordinates":[-73.947796,40.650814],"type":"Point"}
}