{
  "type": "Feature",
  "properties": {
    "iso:country":"US",
    "sg:address":"604 Co Rte 37",
    "sg:city":"Central Square",
    "sg:classifiers":[
        {
            "category":"Recreation",
            "subcategory":"Marina",
            "type":"Entertainment"
        }
    ],
    "sg:phone":"+1 315 676 9276",
    "sg:postcode":"13036",
    "sg:province":"NY",
    "sg:website":"www.winterharborllc.com",
    "wof:name":"Winter Harbor LLC",
    "wof:placetype":"venue"
},
  "geometry": {"coordinates":[-76.164536,43.249954],"type":"Point"}
}