{
  "type": "Feature",
  "properties": {
    "addr:full":"777 Berriman St Brooklyn NY 11208",
    "addr:housenumber":"777",
    "addr:postcode":"11208",
    "addr:street":"Berriman St",
    "iso:country":"US",
    "sg:address":"777 Berriman St",
    "sg:city":"Brooklyn",
    "sg:classifiers":[
        {
            "category":"Wholesale",
            "subcategory":"Groceries",
            "type":"Manufacturing & Wholesale Goods"
        }
    ],
    "sg:phone":"+1 718 649 2400",
    "sg:postcode":"11208",
    "sg:province":"NY",
    "sg:tags":[
        "beverage"
    ],
    "wof:name":"Pepsi-Cola Metropolitan Bottlg",
    "wof:placetype":"venue"
},
  "geometry": {"coordinates":[-73.871802,40.659542],"type":"Point"}
}