{
  "type": "Feature",
  "properties": {
    "addr:full":"6 E Hampton Dr East Hampton NY 11937",
    "addr:housenumber":"6",
    "addr:postcode":"11937",
    "addr:street":"E Hampton Dr East",
    "iso:country":"US",
    "sg:address":"6 E Hampton Dr",
    "sg:city":"East Hampton",
    "sg:classifiers":[
        {
            "category":"Health Services",
            "subcategory":"Clinic",
            "type":"Services"
        }
    ],
    "sg:phone":"+1 631 267 6107",
    "sg:postcode":"11937",
    "sg:province":"NY",
    "sg:tags":[
        "wellness",
        "program"
    ],
    "wof:name":"Jimmy Minardi Wellness Fclty",
    "wof:placetype":"venue"
},
  "geometry": {"coordinates":[-72.17363899999999,40.983636],"type":"Point"}
}