{
  "type": "Feature",
  "properties": {
    "iso:country":"US",
    "sg:address":"1003 Hawkins Ave",
    "sg:city":"Lake Grove",
    "sg:classifiers":[
        {
            "category":"Restaurant",
            "type":"Food & Drink"
        }
    ],
    "sg:phone":"+1   ",
    "sg:postcode":"11755",
    "sg:province":"NY",
    "sg:tags":[
        "delicatessen"
    ],
    "wof:name":"Bam Deli Inc",
    "wof:placetype":"venue"
},
  "geometry": {"coordinates":[-73.114898,40.852808],"type":"Point"}
}