{
  "type": "Feature",
  "properties": {
    "addr:full":"50 Main St Mount Kisco NY 10549",
    "addr:housenumber":"50",
    "addr:postcode":"10549",
    "addr:street":"Main St",
    "iso:country":"US",
    "sg:address":"50 Main St",
    "sg:city":"Mount Kisco",
    "sg:classifiers":[
        {
            "category":"Professional",
            "subcategory":"Lawyer & Legal Services",
            "type":"Services"
        }
    ],
    "sg:phone":"+1 800 472 7697",
    "sg:postcode":"10549",
    "sg:province":"NY",
    "wof:name":"Pacchiana Paul atty",
    "wof:placetype":"venue"
},
  "geometry": {"coordinates":[-73.727273,41.207672],"type":"Point"}
}