{
  "type": "Feature",
  "properties": {
    "iso:country":"US",
    "sg:address":"11 W Seneca St",
    "sg:city":"Oswego",
    "sg:classifiers":[
        {
            "category":"Travel",
            "subcategory":"Hotels & Motels",
            "type":"Entertainment"
        }
    ],
    "sg:phone":"+1 315 342 6285",
    "sg:postcode":"13126",
    "sg:province":"NY",
    "sg:tags":[
        "operation"
    ],
    "wof:name":"Crews Quarters Lodging",
    "wof:placetype":"venue"
},
  "geometry": {"coordinates":[-76.51264999999999,43.459068],"type":"Point"}
}