{
  "type": "Feature",
  "properties": {
    "iso:country":"US",
    "sg:address":"39 Sentinel Rd",
    "sg:city":"Lake Placid",
    "sg:classifiers":[
        {
            "category":"Shopping",
            "type":"Retail Goods"
        }
    ],
    "sg:phone":"+1   ",
    "sg:postcode":"12946",
    "sg:province":"NY",
    "sg:tags":[
        "trophy",
        "flag",
        "award"
    ],
    "wof:name":"Fanfare Gifts & Flags",
    "wof:placetype":"venue"
},
  "geometry": {"coordinates":[-73.97946,44.272137],"type":"Point"}
}