{
  "type": "Feature",
  "properties": {
    "iso:country":"US",
    "sg:address":"404 Empire Blvd",
    "sg:city":"Rochester",
    "sg:classifiers":[
        {
            "category":"Restaurant",
            "type":"Food & Drink"
        }
    ],
    "sg:menulink":"http://www.allmenus.com/ny/irondequoit/20442-guidas-pizzeria/menu/",
    "sg:phone":"+1 585 288 0590",
    "sg:postcode":"14609",
    "sg:province":"NY",
    "sg:tags":[
        "american",
        "pizza"
    ],
    "wof:name":"Guida's Pizzeria",
    "wof:placetype":"venue"
},
  "geometry": {"coordinates":[-77.545884,43.177032],"type":"Point"}
}