{
  "type": "Feature",
  "properties": {
    "addr:full":"903 Jefferson Ave Brooklyn NY 11221",
    "addr:housenumber":"903",
    "addr:postcode":"11221",
    "addr:street":"Jefferson Ave",
    "iso:country":"US",
    "sg:address":"903 Jefferson Ave",
    "sg:city":"Brooklyn",
    "sg:classifiers":[
        {
            "category":"Building & Trades",
            "subcategory":"Construction",
            "type":"Services"
        }
    ],
    "sg:phone":"+1 718 493 6702",
    "sg:postcode":"11221",
    "sg:province":"NY",
    "sg:tags":[
        "floor",
        "laying",
        "contractor"
    ],
    "wof:name":"Exports Flooring",
    "wof:placetype":"venue"
},
  "geometry": {"coordinates":[-73.92148400000001,40.686613],"type":"Point"}
}