{
  "type": "Feature",
  "properties": {
    "iso:country":"US",
    "sg:address":"104 Old Broadway Ave",
    "sg:city":"Sayville",
    "sg:classifiers":[
        {
            "category":"Professional",
            "subcategory":"Printing & Photocopies",
            "type":"Services"
        }
    ],
    "sg:phone":"+1 516 457 3235",
    "sg:postcode":"11782",
    "sg:province":"NY",
    "sg:tags":[
        "lithographer"
    ],
    "wof:name":"Expedition Printing Corporation",
    "wof:placetype":"venue"
},
  "geometry": {"coordinates":[-73.06404999999999,40.750973],"type":"Point"}
}