{
  "type": "Feature",
  "properties": {
    "addr:full":"696 Madison Avenue Between 62nd. and 63rd. streets New York NY 10065",
    "addr:housenumber":"696",
    "addr:postcode":"10065",
    "addr:street":"Madison Avenue Between;Streets",
    "iso:country":"US",
    "sg:address":"696 Madison Avenue Between 62nd. and 63rd. streets",
    "sg:city":"New York",
    "sg:classifiers":[
        {
            "category":"Personal",
            "subcategory":"Day Spa",
            "type":"Services"
        }
    ],
    "sg:phone":"+1 212 230 1397",
    "sg:postcode":"10065",
    "sg:province":"NY",
    "sg:website":"www.rodolfovalentin.net",
    "wof:name":"Rodolfo Valentin",
    "wof:placetype":"venue"
},
  "geometry": {"coordinates":[-73.96996799999999,40.765709],"type":"Point"}
}