{
  "type": "Feature",
  "properties": {
    "iso:country":"US",
    "sg:address":"585 Broad Hollow Rd",
    "sg:city":"Melville",
    "sg:classifiers":[
        {
            "category":"Social Services",
            "subcategory":"Adult Care",
            "type":"Services"
        }
    ],
    "sg:phone":"+1 631 847 8800",
    "sg:postcode":"11747",
    "sg:province":"NY",
    "sg:tags":[
        "disabled",
        "home",
        "for",
        "mentally"
    ],
    "wof:name":"Community Residence Program",
    "wof:placetype":"venue"
},
  "geometry": {"coordinates":[-73.423434,40.764886],"type":"Point"}
}