{
  "type": "Feature",
  "properties": {
    "addr:full":"43 Tompkins Ave Staten Island NY 10304",
    "addr:housenumber":"43",
    "addr:postcode":"10304",
    "addr:street":"Tompkins Ave",
    "iso:country":"US",
    "sg:address":"43 Tompkins Ave",
    "sg:city":"Staten Island",
    "sg:classifiers":[
        {
            "category":"Organizations",
            "subcategory":"Religious Organization",
            "type":"Services"
        }
    ],
    "sg:phone":"+1 718 815 7547",
    "sg:postcode":"10304",
    "sg:province":"NY",
    "sg:tags":[
        "clergy"
    ],
    "wof:name":"Maggie Howard",
    "wof:placetype":"venue"
},
  "geometry": {"coordinates":[-74.078205,40.622055],"type":"Point"}
}