{
  "type": "Feature",
  "properties": {
    "iso:country":"US",
    "sg:address":"2408 Amsterdam Ave",
    "sg:city":"New York",
    "sg:classifiers":[
        {
            "category":"Home & Garden",
            "subcategory":"Furniture",
            "type":"Retail Goods"
        }
    ],
    "sg:phone":"+1 212 795 2000",
    "sg:postcode":"10033",
    "sg:province":"NY",
    "wof:name":"Fleischer Juvenile Furn Corp",
    "wof:placetype":"venue"
},
  "geometry": {"coordinates":[-73.93163199999999,40.847152],"type":"Point"}
}