{
  "type": "Feature",
  "properties": {
    "iso:country":"US",
    "sg:address":"5431 Peach Orchard Pt",
    "sg:city":"Hector",
    "sg:classifiers":[
        {
            "category":"Building & Trades",
            "subcategory":"Landscaping Services",
            "type":"Services"
        }
    ],
    "sg:phone":"+1 607 738 0881",
    "sg:postcode":"14841",
    "sg:province":"NY",
    "sg:tags":[
        "lawn",
        "maintenance"
    ],
    "wof:name":"Gizmo Mowing And More",
    "wof:placetype":"venue"
},
  "geometry": {"coordinates":[-76.88796499999999,42.494371],"type":"Point"}
}