{
  "type": "Feature",
  "properties": {
    "addr:full":"206 Flatbush Ave Brooklyn NY 11217",
    "addr:housenumber":"206",
    "addr:postcode":"11217",
    "addr:street":"Flatbush Ave",
    "iso:country":"US",
    "sg:address":"206 Flatbush Ave",
    "sg:city":"Brooklyn",
    "sg:classifiers":[
        {
            "category":"Health Services",
            "subcategory":"Doctor",
            "type":"Services"
        }
    ],
    "sg:phone":"+1 718 230 3700",
    "sg:postcode":"11217",
    "sg:province":"NY",
    "sg:tags":[
        "medical",
        "hospital",
        "mental",
        "specialty"
    ],
    "sg:website":"http://www.newdirectionsbrooklyn.com",
    "wof:name":"New Directions",
    "wof:placetype":"venue"
},
  "geometry": {"coordinates":[-73.97547900000001,40.681335],"type":"Point"}
}