{
  "type": "Feature",
  "properties": {
    "addr:full":"508 Westbrook Dr Cortlandt Manor NY 10567",
    "addr:housenumber":"508",
    "addr:postcode":"10567",
    "addr:street":"Westbrook Dr Cortlandt",
    "iso:country":"US",
    "sg:address":"508 Westbrook Dr",
    "sg:city":"Cortlandt Manor",
    "sg:classifiers":[
        {
            "category":"Building & Trades",
            "subcategory":"Construction",
            "type":"Services"
        }
    ],
    "sg:phone":"+1 914 526 8184",
    "sg:postcode":"10567",
    "sg:province":"NY",
    "sg:tags":[
        "general",
        "contractor"
    ],
    "wof:name":"J A Aluminum & Siding Corp",
    "wof:placetype":"venue"
},
  "geometry": {"coordinates":[-73.88181299999999,41.314327],"type":"Point"}
}