{
  "type": "Feature",
  "properties": {
    "addr:full":"40 Violet Ave Poughkeepsie NY 12601",
    "addr:housenumber":"40",
    "addr:postcode":"12601",
    "addr:street":"Violet Ave",
    "iso:country":"US",
    "sg:address":"40 Violet Ave",
    "sg:city":"Poughkeepsie",
    "sg:classifiers":[
        {
            "category":"Manufacturing",
            "subcategory":"Tools & Machinery",
            "type":"Manufacturing & Wholesale Goods"
        }
    ],
    "sg:phone":"+1   ",
    "sg:postcode":"12601",
    "sg:province":"NY",
    "sg:tags":[
        "mfg",
        "printing",
        "trade"
    ],
    "wof:name":"Perretta Graphics Corp",
    "wof:placetype":"venue"
},
  "geometry": {"coordinates":[-73.911537,41.719284],"type":"Point"}
}