{
  "type": "Feature",
  "properties": {
    "iso:country":"US",
    "sg:address":"2 Old Albany Post Rd",
    "sg:city":"Rhinebeck",
    "sg:classifiers":[
        {
            "category":"Health Services",
            "subcategory":"Health Practitioner",
            "type":"Services"
        }
    ],
    "sg:phone":"+1 845 876 6560",
    "sg:postcode":"12572",
    "sg:province":"NY",
    "sg:tags":[
        "psychologist"
    ],
    "wof:name":"Dennis Babik",
    "wof:placetype":"venue"
},
  "geometry": {"coordinates":[-73.911484,41.882732],"type":"Point"}
}