{
  "type": "Feature",
  "properties": {
    "addr:full":"2180 Sheridan Dr Buffalo NY 14223",
    "addr:housenumber":"2180",
    "addr:postcode":"14223",
    "addr:street":"Sheridan Dr",
    "iso:country":"US",
    "sg:address":"2180 Sheridan Dr",
    "sg:city":"Buffalo",
    "sg:classifiers":[
        {
            "category":"Deli",
            "type":"Food & Drink"
        }
    ],
    "sg:menulink":"http://www.allmenus.com/ny/tonawanda/245647-jims-steakout/menu/",
    "sg:phone":"+1 716 873 0300",
    "sg:postcode":"14223",
    "sg:province":"NY",
    "sg:tags":[
        "american"
    ],
    "wof:name":"Jim's Steakout",
    "wof:placetype":"venue"
},
  "geometry": {"coordinates":[-78.853306,42.981273],"type":"Point"}
}