{
  "type": "Feature",
  "properties": {
    "addr:full":"126 Clinton St Schenectady NY 12305",
    "addr:housenumber":"126",
    "addr:postcode":"12305",
    "addr:street":"Clinton St",
    "iso:country":"US",
    "sg:address":"126 Clinton St",
    "sg:city":"Schenectady",
    "sg:classifiers":[
        {
            "category":"Professional",
            "subcategory":"Art Services",
            "type":"Services"
        }
    ],
    "sg:phone":"+1 518 381 6312",
    "sg:postcode":"12305",
    "sg:province":"NY",
    "sg:tags":[
        "graphic",
        "designer"
    ],
    "wof:name":"Rm&M Framemakers",
    "wof:placetype":"venue"
},
  "geometry": {"coordinates":[-73.939502,42.813201],"type":"Point"}
}