{
  "type": "Feature",
  "properties": {
    "addr:full":"772 Port Richmond Ave Staten Island NY 10302",
    "addr:housenumber":"772",
    "addr:postcode":"10302",
    "addr:street":"Port Richmond Ave",
    "iso:country":"US",
    "sg:address":"772 Port Richmond Ave",
    "sg:city":"Staten Island",
    "sg:classifiers":[
        {
            "category":"Organizations",
            "subcategory":"Religious Organization",
            "type":"Services"
        }
    ],
    "sg:phone":"+1 718 556 9900",
    "sg:postcode":"10302",
    "sg:province":"NY",
    "wof:name":"Wind Fire River Ministries",
    "wof:placetype":"venue"
},
  "geometry": {"coordinates":[-74.14465300000001,40.625361],"type":"Point"}
}