{
  "type": "Feature",
  "properties": {
    "iso:country":"US",
    "sg:address":"621 Main St",
    "sg:city":"Greenport",
    "sg:classifiers":[
        {
            "category":"Organizations",
            "subcategory":"Religious Organization",
            "type":"Services"
        }
    ],
    "sg:phone":"+1 631 477 0497",
    "sg:postcode":"11944",
    "sg:province":"NY",
    "sg:tags":[
        "church"
    ],
    "wof:name":"Greenport United Methodist Chr",
    "wof:placetype":"venue"
},
  "geometry": {"coordinates":[-72.361282,41.107404],"type":"Point"}
}