{
  "type": "Feature",
  "properties": {
    "iso:country":"US",
    "sg:address":"5800 Arlington Ave",
    "sg:city":"Bronx",
    "sg:classifiers":[
        {
            "category":"Education",
            "subcategory":"Special Training",
            "type":"Public Place"
        }
    ],
    "sg:phone":"+1 718 884 6837",
    "sg:postcode":"10471",
    "sg:province":"NY",
    "sg:tags":[
        "instruction",
        "music"
    ],
    "wof:name":"Amadeus Clarinet & Guitar Stds",
    "wof:placetype":"venue"
},
  "geometry": {"coordinates":[-73.9067,40.908011],"type":"Point"}
}