{
  "type": "Feature",
  "properties": {
    "iso:country":"US",
    "sg:address":"405 E 54 St",
    "sg:city":"New York",
    "sg:classifiers":[
        {
            "category":"Professional",
            "subcategory":"Lawyer & Legal Services",
            "type":"Services"
        }
    ],
    "sg:phone":"+1 212 689 8600",
    "sg:postcode":"10022",
    "sg:province":"NY",
    "sg:tags":[
        "attorney"
    ],
    "wof:name":"Meissner Kleinberg & Finkel",
    "wof:placetype":"venue"
},
  "geometry": {"coordinates":[-73.96213299999999,40.755559],"type":"Point"}
}