{
  "type": "Feature",
  "properties": {
    "addr:full":"2239 Benson Ave Brooklyn NY 11214",
    "addr:housenumber":"2239",
    "addr:postcode":"11214",
    "addr:street":"Benson Ave",
    "iso:country":"US",
    "sg:address":"2239 Benson Ave",
    "sg:city":"Brooklyn",
    "sg:classifiers":[
        {
            "category":"Building & Trades",
            "subcategory":"Construction",
            "type":"Services"
        }
    ],
    "sg:phone":"+1 718 373 1097",
    "sg:postcode":"11214",
    "sg:province":"NY",
    "sg:tags":[
        "house"
    ],
    "wof:name":"Salik Construction Co",
    "wof:placetype":"venue"
},
  "geometry": {"coordinates":[-73.994353,40.599624],"type":"Point"}
}