{
  "type": "Feature",
  "properties": {
    "addr:full":"1851 PLAZA DR OLEAN NY 14760",
    "addr:housenumber":"1851",
    "addr:postcode":"14760",
    "addr:street":"Plaza Dr",
    "iso:country":"US",
    "sg:address":"1851 PLAZA DR",
    "sg:city":"OLEAN",
    "sg:classifiers":[
        {
            "category":"Home & Garden",
            "subcategory":"Household Appliances",
            "type":"Retail Goods"
        },
        {
            "category":"Communications",
            "subcategory":"Radio Station",
            "type":"Services"
        },
        {
            "category":"Shopping",
            "subcategory":"Computers & Home Electronics",
            "type":"Retail Goods"
        },
        {
            "category":"Home & Garden",
            "subcategory":"Furniture",
            "type":"Retail Goods"
        }
    ],
    "sg:phone":"+1 716 372 6171",
    "sg:postcode":"14760",
    "sg:province":"NY",
    "sg:tags":[
        "renting",
        "television",
        "leasing",
        "radio-renting",
        "equipment",
        "rental"
    ],
    "sg:website":"http://www.rentacenter.com/",
    "wof:name":"Rent-A-Center",
    "wof:placetype":"venue"
},
  "geometry": {"coordinates":[-78.468761,42.078254],"type":"Point"}
}