{
  "type": "Feature",
  "properties": {
    "addr:full":"4825 State Highway 30 Amsterdam NY 12010",
    "addr:housenumber":"4825",
    "addr:postcode":"12010",
    "addr:street":"State Highway 30",
    "iso:country":"US",
    "sg:address":"4825 State Highway 30",
    "sg:city":"Amsterdam",
    "sg:phone":"+1 877 471 9739",
    "sg:postcode":"12010",
    "sg:province":"NY",
    "sg:website":"http://www.lowes.com",
    "wof:name":"Lowe's? Home Improvement",
    "wof:placetype":"venue"
},
  "geometry": {"coordinates":[-74.18782,42.973011],"type":"Point"}
}