{
  "type": "Feature",
  "properties": {
    "iso:country":"US",
    "sg:address":"2647 Burns Rd",
    "sg:city":"Scipio Center",
    "sg:classifiers":[
        {
            "category":"Freight",
            "type":"Transportation"
        }
    ],
    "sg:phone":"+1   ",
    "sg:postcode":"13147",
    "sg:province":"NY",
    "sg:tags":[
        "operator",
        "local",
        "trucking"
    ],
    "wof:name":"Kessler Trucking",
    "wof:placetype":"venue"
},
  "geometry": {"coordinates":[-76.527086,42.74438],"type":"Point"}
}