{
  "type": "Feature",
  "properties": {
    "addr:full":"3923 Queens Boulevard Long Island City NY 11104",
    "addr:housenumber":"3923",
    "addr:postcode":"11104",
    "addr:street":"Queens Boulevard",
    "iso:country":"US",
    "sg:address":"3923 Queens Boulevard",
    "sg:city":"Long Island City",
    "sg:classifiers":[
        {
            "category":"Restaurant",
            "type":"Food & Drink"
        }
    ],
    "sg:phone":"+1 718 482 0600",
    "sg:postcode":"11104",
    "sg:province":"NY",
    "wof:name":"Master Buffet",
    "wof:placetype":"venue"
},
  "geometry": {"coordinates":[-73.924955,40.744147],"type":"Point"}
}