{
  "type": "Feature",
  "properties": {
    "addr:full":"406 King St Port Chester NY 10573",
    "addr:housenumber":"406",
    "addr:postcode":"10573",
    "addr:street":"King St",
    "iso:country":"US",
    "sg:address":"406 King St",
    "sg:city":"Port Chester",
    "sg:classifiers":[
        {
            "category":"Organizations",
            "subcategory":"Religious Organization",
            "type":"Services"
        }
    ],
    "sg:phone":"+1 914 939 8338",
    "sg:postcode":"10573",
    "sg:province":"NY",
    "sg:tags":[
        "church"
    ],
    "wof:name":"Jehovah's Witnesses Study",
    "wof:placetype":"venue"
},
  "geometry": {"coordinates":[-73.66583,41.010321],"type":"Point"}
}