{
  "type": "Feature",
  "properties": {
    "iso:country":"US",
    "sg:address":"70 Seneca St",
    "sg:city":"Geneva",
    "sg:classifiers":[
        {
            "category":"Shopping",
            "subcategory":"Gifts & Souvenirs",
            "type":"Retail Goods"
        }
    ],
    "sg:phone":"+1   ",
    "sg:postcode":"14456",
    "sg:province":"NY",
    "wof:name":"Earthly Possessions",
    "wof:placetype":"venue"
},
  "geometry": {"coordinates":[-76.98357799999999,42.866757],"type":"Point"}
}