{
  "type": "Feature",
  "properties": {
    "addr:full":"402 Atlantic Ave Brooklyn NY 11217",
    "addr:housenumber":"402",
    "addr:postcode":"11217",
    "addr:street":"Atlantic Ave",
    "iso:country":"US",
    "sg:address":"402 Atlantic Ave",
    "sg:city":"Brooklyn",
    "sg:classifiers":[
        {
            "category":"Food & Beverages",
            "subcategory":"Liquor & Beverages",
            "type":"Retail Goods"
        },
        {
            "category":"Food & Beverages",
            "subcategory":"Bakery",
            "type":"Retail Goods"
        },
        {
            "category":"Food & Beverages",
            "subcategory":"Groceries & Convenience Stores",
            "type":"Retail Goods"
        }
    ],
    "sg:phone":"+1 718 330 0193",
    "sg:postcode":"11217",
    "sg:province":"NY",
    "sg:tags":[
        "beer",
        "sandwich",
        "spirit",
        "wine"
    ],
    "wof:name":"Jesse's Atlantic Limited",
    "wof:placetype":"venue"
},
  "geometry": {"coordinates":[-73.98486800000001,40.686944],"type":"Point"}
}