{
  "type": "Feature",
  "properties": {
    "iso:country":"US",
    "sg:address":"199 Southern Blvd",
    "sg:city":"Nesconset",
    "sg:classifiers":[
        {
            "category":"Home & Garden",
            "subcategory":"Household Appliances",
            "type":"Retail Goods"
        }
    ],
    "sg:phone":"+1 516 378 4530",
    "sg:postcode":"11767",
    "sg:province":"NY",
    "sg:tags":[
        "repair"
    ],
    "wof:name":"Aabco Appliance Repair",
    "wof:placetype":"venue"
},
  "geometry": {"coordinates":[-73.15720399999999,40.842899],"type":"Point"}
}