{
  "type": "Feature",
  "properties": {
    "iso:country":"US",
    "sg:address":"242 Glen Cove Ave",
    "sg:city":"Glen Cove",
    "sg:classifiers":[
        {
            "category":"Food & Beverages",
            "subcategory":"Groceries & Convenience Stores",
            "type":"Retail Goods"
        }
    ],
    "sg:phone":"+1   ",
    "sg:postcode":"11542",
    "sg:province":"NY",
    "sg:tags":[
        "video",
        "beer",
        "rental"
    ],
    "wof:name":"Super Food",
    "wof:placetype":"venue"
},
  "geometry": {"coordinates":[-73.635729,40.846521],"type":"Point"}
}