{
  "type": "Feature",
  "properties": {
    "addr:full":"2145 Hylan Blvd Staten Island NY 10306",
    "addr:housenumber":"2145",
    "addr:postcode":"10306",
    "addr:street":"Hylan Blvd",
    "iso:country":"US",
    "sg:address":"2145 Hylan Blvd",
    "sg:city":"Staten Island",
    "sg:classifiers":[
        {
            "category":"Shopping",
            "subcategory":"Pharmacy",
            "type":"Retail Goods"
        }
    ],
    "sg:phone":"+1 718 351 6952",
    "sg:postcode":"10306",
    "sg:province":"NY",
    "sg:tags":[
        "drugstore"
    ],
    "sg:website":"www.duanereade.com",
    "wof:name":"Duane Reade Drugs",
    "wof:placetype":"venue"
},
  "geometry": {"coordinates":[-74.10189800000001,40.578201],"type":"Point"}
}