{
  "type": "Feature",
  "properties": {
    "addr:full":"180 W 80th St New York NY 10024",
    "addr:housenumber":"180",
    "addr:postcode":"10024",
    "addr:street":"W 80Th St",
    "iso:country":"US",
    "sg:address":"180 W 80th St",
    "sg:city":"New York",
    "sg:classifiers":[
        {
            "category":"Real Estate",
            "subcategory":"Real Estate Services",
            "type":"Services"
        }
    ],
    "sg:phone":"+1 212 799 2365",
    "sg:postcode":"10024",
    "sg:province":"NY",
    "sg:tags":[
        "management",
        "property"
    ],
    "wof:name":"Veritas Property Management",
    "wof:placetype":"venue"
},
  "geometry": {"coordinates":[-73.97762,40.783593],"type":"Point"}
}