{
  "type": "Feature",
  "properties": {
    "addr:full":"2924 Fulton St Brooklyn NY 11207",
    "addr:housenumber":"2924",
    "addr:postcode":"11207",
    "addr:street":"Fulton St",
    "iso:country":"US",
    "sg:address":"2924 Fulton St",
    "sg:city":"Brooklyn",
    "sg:classifiers":[
        {
            "category":"Professional",
            "subcategory":"Management & Consulting",
            "type":"Services"
        }
    ],
    "sg:phone":"+1   ",
    "sg:postcode":"11207",
    "sg:province":"NY",
    "sg:tags":[
        "property",
        "financial"
    ],
    "wof:name":"Pueblo Property Managment",
    "wof:placetype":"venue"
},
  "geometry": {"coordinates":[-73.886819,40.679131],"type":"Point"}
}