{
  "type": "Feature",
  "properties": {
    "iso:country":"US",
    "sg:address":"523 Townline Rd",
    "sg:city":"Hauppauge",
    "sg:classifiers":[
        {
            "category":"Arts & Performance",
            "subcategory":"Theater",
            "type":"Entertainment"
        }
    ],
    "sg:phone":"+1 631 366 0200",
    "sg:postcode":"11788",
    "sg:province":"NY",
    "sg:tags":[
        "talent",
        "agency",
        "casting"
    ],
    "wof:name":"Hampton Models",
    "wof:placetype":"venue"
},
  "geometry": {"coordinates":[-73.20225000000001,40.825461],"type":"Point"}
}