{
  "type": "Feature",
  "properties": {
    "iso:country":"US",
    "sg:address":"820 E 182nd St",
    "sg:city":"Bronx",
    "sg:classifiers":[
        {
            "category":"Retail",
            "subcategory":"Auto Repair",
            "type":"Services"
        }
    ],
    "sg:phone":"+1 718 732 3970",
    "sg:postcode":"10460",
    "sg:province":"NY",
    "sg:tags":[
        "wrecker"
    ],
    "wof:name":"24 Towing Svc",
    "wof:placetype":"venue"
},
  "geometry": {"coordinates":[-73.883517,40.848507],"type":"Point"}
}