{
  "type": "Feature",
  "properties": {
    "addr:full":"15605 Rockaway Blvd Jamaica NY 11434",
    "addr:housenumber":"15605",
    "addr:postcode":"11434",
    "addr:street":"Rockaway Blvd",
    "iso:country":"US",
    "sg:address":"15605 Rockaway Blvd",
    "sg:city":"Jamaica",
    "sg:classifiers":[
        {
            "category":"Personal",
            "type":"Services"
        },
        {
            "category":"Retail",
            "subcategory":"Auto Rental",
            "type":"Services"
        },
        {
            "category":"Retail",
            "subcategory":"Storage",
            "type":"Services"
        },
        {
            "category":"Freight",
            "type":"Transportation"
        }
    ],
    "sg:phone":"+1 718 341 0700",
    "sg:postcode":"11434",
    "sg:province":"NY",
    "sg:tags":[
        "renting",
        "moving-self",
        "leasing",
        "trucking",
        "truck",
        "mover",
        "local",
        "trailer"
    ],
    "sg:website":"http://www.uhaul.com/Locations/Rentals-near-Jamaica-NY-11434/002742",
    "wof:name":"U-Haul Neighborhood Dealer - Ozone Management",
    "wof:placetype":"venue"
},
  "geometry": {"coordinates":[-73.77512400000001,40.660151],"type":"Point"}
}