{
  "type": "Feature",
  "properties": {
    "addr:full":"635 W 54 St New York NY 10019",
    "addr:housenumber":"635",
    "addr:postcode":"10019",
    "addr:street":"W 54 St",
    "iso:country":"US",
    "sg:address":"635 W 54 St",
    "sg:city":"New York",
    "sg:classifiers":[
        {
            "category":"Professional",
            "type":"Services"
        }
    ],
    "sg:phone":"+1 212 265 5607",
    "sg:postcode":"10019",
    "sg:province":"NY",
    "sg:tags":[
        "establishment"
    ],
    "wof:name":"Larstrand Corp",
    "wof:placetype":"venue"
},
  "geometry": {"coordinates":[-73.99415500000001,40.768993],"type":"Point"}
}