{
  "type": "Feature",
  "properties": {
    "iso:country":"US",
    "sg:address":"424 Main St",
    "sg:city":"Buffalo",
    "sg:classifiers":[
        {
            "category":"Professional",
            "subcategory":"Lawyer & Legal Services",
            "type":"Services"
        }
    ],
    "sg:phone":"+1 716 852 0400",
    "sg:postcode":"14202",
    "sg:province":"NY",
    "wof:name":"STRAW STEPHANIE A",
    "wof:placetype":"venue"
},
  "geometry": {"coordinates":[-78.874574,42.885627],"type":"Point"}
}