{
  "type": "Feature",
  "properties": {
    "iso:country":"US",
    "sg:address":"362 Atlantic Ave",
    "sg:city":"Brooklyn",
    "sg:classifiers":[
        {
            "category":"Shopping",
            "subcategory":"Florist",
            "type":"Retail Goods"
        }
    ],
    "sg:phone":"+1 718 643 9160",
    "sg:postcode":"11217",
    "sg:province":"NY",
    "wof:name":"Opalia Flowers",
    "wof:placetype":"venue"
},
  "geometry": {"coordinates":[-73.98528899999999,40.687082],"type":"Point"}
}