{
  "type": "Feature",
  "properties": {
    "iso:country":"US",
    "sg:address":"285 Harlemville Rd",
    "sg:city":"Hillsdale",
    "sg:classifiers":[
        {
            "category":"Building & Trades",
            "subcategory":"Construction",
            "type":"Services"
        }
    ],
    "sg:phone":"+1 518 672 7557",
    "sg:postcode":"12529",
    "sg:province":"NY",
    "sg:tags":[
        "general",
        "contractor"
    ],
    "wof:name":"George Williamson Tree Svc",
    "wof:placetype":"venue"
},
  "geometry": {"coordinates":[-73.60070899999999,42.226562],"type":"Point"}
}