{
  "type": "Feature",
  "properties": {
    "iso:country":"US",
    "sg:address":"195 Nelson Rd",
    "sg:city":"Scarsdale",
    "sg:classifiers":[
        {
            "category":"Professional",
            "subcategory":"Lawyer & Legal Services",
            "type":"Services"
        }
    ],
    "sg:phone":"+1 718 402 6364",
    "sg:postcode":"10583",
    "sg:province":"NY",
    "sg:tags":[
        "attorney"
    ],
    "wof:name":"Shemtob Jack Attorney",
    "wof:placetype":"venue"
},
  "geometry": {"coordinates":[-73.796323,40.980576],"type":"Point"}
}