{
  "type": "Feature",
  "properties": {
    "iso:country":"US",
    "sg:address":"2248 Edward Ln",
    "sg:city":"Yorktown Heights",
    "sg:classifiers":[
        {
            "category":"Building & Trades",
            "subcategory":"Landscaping Services",
            "type":"Services"
        }
    ],
    "sg:phone":"+1 914 962 2673",
    "sg:postcode":"10598",
    "sg:province":"NY",
    "sg:tags":[
        "landscape"
    ],
    "wof:name":"Perennia Landscaping",
    "wof:placetype":"venue"
},
  "geometry": {"coordinates":[-73.823714,41.28029],"type":"Point"}
}