{
  "type": "Feature",
  "properties": {
    "iso:country":"US",
    "sg:address":"7 Wren Dr",
    "sg:city":"Hauppauge",
    "sg:classifiers":[
        {
            "category":"Building & Trades",
            "subcategory":"Construction",
            "type":"Services"
        },
        {
            "category":"Manufacturing",
            "subcategory":"Building Materials",
            "type":"Manufacturing & Wholesale Goods"
        }
    ],
    "sg:phone":"+1 631 265 1716",
    "sg:postcode":"11788",
    "sg:province":"NY",
    "sg:tags":[
        "roofing",
        "sheet",
        "altering",
        "work",
        "metal",
        "contractor",
        "siding",
        "remodeling"
    ],
    "wof:name":"Grandway",
    "wof:placetype":"venue"
},
  "geometry": {"coordinates":[-73.239242,40.82435],"type":"Point"}
}