{
  "type": "Feature",
  "properties": {
    "addr:full":"258 W 97th St New York NY 10025",
    "addr:housenumber":"258",
    "addr:postcode":"10025",
    "addr:street":"W 97Th St",
    "iso:country":"US",
    "sg:address":"258 W 97th St",
    "sg:city":"New York",
    "sg:classifiers":[
        {
            "category":"Travel",
            "subcategory":"Hotels & Motels",
            "type":"Entertainment"
        }
    ],
    "sg:phone":"+1 212 222 8325",
    "sg:postcode":"10025",
    "sg:province":"NY",
    "wof:name":"Royal York Hotel",
    "wof:placetype":"venue"
},
  "geometry": {"coordinates":[-73.97229799999999,40.795898],"type":"Point"}
}