{
  "type": "Feature",
  "properties": {
    "addr:full":"238 Canal St New York NY 10013",
    "addr:housenumber":"238",
    "addr:postcode":"10013",
    "addr:street":"Canal St",
    "iso:country":"US",
    "sg:address":"238 Canal St",
    "sg:city":"New York",
    "sg:classifiers":[
        {
            "category":"Food & Beverages",
            "subcategory":"Specialty",
            "type":"Retail Goods"
        }
    ],
    "sg:phone":"+1   ",
    "sg:postcode":"10013",
    "sg:province":"NY",
    "wof:name":"Ping LI Yong",
    "wof:placetype":"venue"
},
  "geometry": {"coordinates":[-73.999313,40.717549],"type":"Point"}
}