{
  "type": "Feature",
  "properties": {
    "addr:full":"174 Brady Ave Hawthorne NY 10532",
    "addr:housenumber":"174",
    "addr:postcode":"10532",
    "addr:street":"Brady Ave",
    "iso:country":"US",
    "sg:address":"174 Brady Ave",
    "sg:city":"Hawthorne",
    "sg:classifiers":[
        {
            "category":"Professional",
            "subcategory":"Engineering",
            "type":"Services"
        }
    ],
    "sg:phone":"+1 914 741 0633",
    "sg:postcode":"10532",
    "sg:province":"NY",
    "sg:tags":[
        "engineer"
    ],
    "wof:name":"National Academy-Forensic Engr",
    "wof:placetype":"venue"
},
  "geometry": {"coordinates":[-73.794325,41.099725],"type":"Point"}
}