{
  "type": "Feature",
  "properties": {
    "addr:full":"2743 County Line Dr Big Flats NY 14814",
    "addr:housenumber":"2743",
    "addr:postcode":"14814",
    "addr:street":"County Line Dr Big",
    "iso:country":"US",
    "sg:address":"2743 County Line Dr",
    "sg:city":"Big Flats",
    "sg:classifiers":[
        {
            "category":"Building & Trades",
            "subcategory":"Construction",
            "type":"Services"
        }
    ],
    "sg:phone":"+1 607 562 3010",
    "sg:postcode":"14814",
    "sg:province":"NY",
    "sg:tags":[
        "residential"
    ],
    "wof:name":"TRW Construction Inc",
    "wof:placetype":"venue"
},
  "geometry": {"coordinates":[-76.966695,42.137809],"type":"Point"}
}