{
  "type": "Feature",
  "properties": {
    "addr:full":"184 E 70 St New York NY 10021",
    "addr:housenumber":"184;70",
    "addr:postcode":"10021",
    "addr:street":"E",
    "iso:country":"US",
    "sg:address":"184 E 70 St",
    "sg:city":"New York",
    "sg:classifiers":[
        {
            "category":"Health Services",
            "subcategory":"Doctor",
            "type":"Services"
        }
    ],
    "sg:phone":"+1 212 650 9191",
    "sg:postcode":"10021",
    "sg:province":"NY",
    "sg:tags":[
        "medical"
    ],
    "wof:name":"All Womens Hlth & Med Svcs PC",
    "wof:placetype":"venue"
},
  "geometry": {"coordinates":[-73.962469,40.768858],"type":"Point"}
}