{
  "type": "Feature",
  "properties": {
    "addr:full":"3590 Lawson Blvd Oceanside NY 11572",
    "addr:housenumber":"3590",
    "addr:postcode":"11572",
    "addr:street":"Lawson Blvd",
    "iso:country":"US",
    "sg:address":"3590 Lawson Blvd",
    "sg:city":"Oceanside",
    "sg:classifiers":[
        {
            "category":"Autos & Motor Vehicles",
            "subcategory":"Automobile Sales",
            "type":"Retail Goods"
        }
    ],
    "sg:phone":"+1 516 536 1430",
    "sg:postcode":"11572",
    "sg:province":"NY",
    "sg:tags":[
        "limo"
    ],
    "sg:website":"www.wheelsoffortuneny.com",
    "wof:name":"Wheels Of Fortune Inc",
    "wof:placetype":"venue"
},
  "geometry": {"coordinates":[-73.65060699999999,40.621622],"type":"Point"}
}