{
  "type": "Feature",
  "properties": {
    "addr:full":"450 E Brighton Ave Syracuse NY 13210",
    "addr:housenumber":"450",
    "addr:postcode":"13210",
    "addr:street":"E Brighton Ave",
    "iso:country":"US",
    "sg:address":"450 E Brighton Ave",
    "sg:city":"Syracuse",
    "sg:classifiers":[
        {
            "category":"Retail",
            "subcategory":"Auto Repair",
            "type":"Services"
        }
    ],
    "sg:phone":"+1 315 472 5330",
    "sg:postcode":"13210",
    "sg:province":"NY",
    "sg:tags":[
        "repairing",
        "automobile"
    ],
    "wof:name":"Custom Auto",
    "wof:placetype":"venue"
},
  "geometry": {"coordinates":[-76.136522,43.015909],"type":"Point"}
}