{
  "type": "Feature",
  "properties": {
    "addr:full":"1631 Kemble St Utica NY 13501",
    "addr:housenumber":"1631",
    "addr:postcode":"13501",
    "addr:street":"Kemble St",
    "iso:country":"US",
    "sg:address":"1631 Kemble St",
    "sg:city":"Utica",
    "sg:classifiers":[
        {
            "category":"Organizations",
            "subcategory":"Religious Organization",
            "type":"Services"
        }
    ],
    "sg:phone":"+1 315 732 7386",
    "sg:postcode":"13501",
    "sg:province":"NY",
    "sg:tags":[
        "church"
    ],
    "wof:name":"Jehovah's Witnesses",
    "wof:placetype":"venue"
},
  "geometry": {"coordinates":[-75.247078,43.087554],"type":"Point"}
}