{
  "type": "Feature",
  "properties": {
    "iso:country":"US",
    "sg:address":"726 Twomey Ave",
    "sg:city":"Calverton",
    "sg:phone":"+1 631 727 4861",
    "sg:postcode":"11933",
    "sg:province":"NY",
    "sg:tags":[
        "farm",
        "irish",
        "potato"
    ],
    "wof:name":"Sujecki Farms",
    "wof:placetype":"venue"
},
  "geometry": {"coordinates":[-72.748295,40.952405],"type":"Point"}
}