{
  "type": "Feature",
  "properties": {
    "iso:country":"US",
    "sg:address":"49 Sussex St",
    "sg:city":"Port Jervis",
    "sg:classifiers":[
        {
            "category":"Social Services",
            "subcategory":"Child Care",
            "type":"Services"
        }
    ],
    "sg:phone":"+1 845 856 8549",
    "sg:postcode":"12771",
    "sg:province":"NY",
    "wof:name":"Snips & Snails",
    "wof:placetype":"venue"
},
  "geometry": {"coordinates":[-74.68986,41.376264],"type":"Point"}
}