{
  "type": "Feature",
  "properties": {
    "addr:full":"74 W Raymond Ave Roosevelt NY 11575",
    "addr:housenumber":"74",
    "addr:postcode":"11575",
    "addr:street":"W Raymond Ave",
    "iso:country":"US",
    "sg:address":"74 W Raymond Ave",
    "sg:city":"Roosevelt",
    "sg:classifiers":[
        {
            "category":"Retail",
            "subcategory":"Photofinishing",
            "type":"Services"
        }
    ],
    "sg:phone":"+1   ",
    "sg:postcode":"11575",
    "sg:province":"NY",
    "sg:tags":[
        "laboratory"
    ],
    "wof:name":"Photo Studio",
    "wof:placetype":"venue"
},
  "geometry": {"coordinates":[-73.596901,40.683615],"type":"Point"}
}