{
  "type": "Feature",
  "properties": {
    "addr:full":"140 W 13 St New York NY 10011",
    "addr:housenumber":"140",
    "addr:postcode":"10011",
    "addr:street":"W 13 St",
    "iso:country":"US",
    "sg:address":"140 W 13 St",
    "sg:city":"New York",
    "sg:classifiers":[
        {
            "category":"Restaurant",
            "type":"Food & Drink"
        }
    ],
    "sg:phone":"+1 212 645 4606",
    "sg:postcode":"10011",
    "sg:province":"NY",
    "wof:name":"Gonzo Restaurant",
    "wof:placetype":"venue"
},
  "geometry": {"coordinates":[-73.99934,40.737311],"type":"Point"}
}