{
  "type": "Feature",
  "properties": {
    "iso:country":"US",
    "sg:address":"609 Bliss Gulf Rd",
    "sg:city":"Oneonta",
    "sg:classifiers":[
        {
            "category":"Shopping",
            "subcategory":"Computers & Home Electronics",
            "type":"Retail Goods"
        }
    ],
    "sg:phone":"+1   ",
    "sg:postcode":"13820",
    "sg:province":"NY",
    "wof:name":"The Computer Tutor",
    "wof:placetype":"venue"
},
  "geometry": {"coordinates":[-75.005838,42.583956],"type":"Point"}
}