{
  "type": "Feature",
  "properties": {
    "addr:full":"2571 Albany St Schenectady NY 12304",
    "addr:housenumber":"2571",
    "addr:postcode":"12304",
    "addr:street":"Albany St",
    "iso:country":"US",
    "sg:address":"2571 Albany St",
    "sg:city":"Schenectady",
    "sg:classifiers":[
        {
            "category":"Food & Beverages",
            "subcategory":"Candy",
            "type":"Retail Goods"
        }
    ],
    "sg:phone":"+1 518 372 2243",
    "sg:postcode":"12304",
    "sg:province":"NY",
    "sg:tags":[
        "confectionery"
    ],
    "wof:name":"Uncle Sam's Candy",
    "wof:placetype":"venue"
},
  "geometry": {"coordinates":[-73.911238,42.783148],"type":"Point"}
}