{
  "type": "Feature",
  "properties": {
    "name:eng_x_preferred":[
        "The Cinnamon Snail"
    ],
    "wof:name":"The Cinnamon Snail",
    "wof:placetype":"venue"
},
  "geometry": {"coordinates":[-73.99178000000001,40.75032],"type":"Point"}
}