{
  "type": "Feature",
  "properties": {
    "iso:country":"US",
    "sg:address":"805 Davis Ter",
    "sg:city":"Schenectady",
    "sg:classifiers":[
        {
            "category":"Shopping",
            "subcategory":"Computers & Home Electronics",
            "type":"Retail Goods"
        }
    ],
    "sg:phone":"+1   ",
    "sg:postcode":"12303",
    "sg:province":"NY",
    "wof:name":"Heydrick Enterprises",
    "wof:placetype":"venue"
},
  "geometry": {"coordinates":[-73.95577,42.798153],"type":"Point"}
}