{
  "type": "Feature",
  "properties": {
    "iso:country":"US",
    "sg:address":"3698 Horseblock Rd",
    "sg:city":"Medford",
    "sg:classifiers":[
        {
            "category":"Retail",
            "subcategory":"Repair Shop",
            "type":"Services"
        },
        {
            "category":"Wholesale",
            "subcategory":"Chemicals & Plastics",
            "type":"Manufacturing & Wholesale Goods"
        }
    ],
    "sg:phone":"+1 631 472 7006",
    "sg:postcode":"11763",
    "sg:province":"NY",
    "sg:tags":[
        "related"
    ],
    "wof:name":"Shawn-Mc Kee Enterprises Inc",
    "wof:placetype":"venue"
},
  "geometry": {"coordinates":[-72.960022,40.815585],"type":"Point"}
}