{
  "type": "Feature",
  "properties": {
    "addr:full":"10 Columbus Cir New York NY 10019",
    "addr:housenumber":"10",
    "addr:postcode":"10019",
    "addr:street":"Columbus Cir",
    "iso:country":"US",
    "sg:address":"10 Columbus Cir",
    "sg:city":"New York",
    "sg:classifiers":[
        {
            "category":"Restaurant",
            "type":"Food & Drink"
        }
    ],
    "sg:phone":"+1 212 823 9335",
    "sg:postcode":"10019",
    "sg:province":"NY",
    "sg:tags":[
        "french"
    ],
    "sg:website":"www.perseny.com",
    "wof:name":"Per Se",
    "wof:placetype":"venue"
},
  "geometry": {"coordinates":[-73.982302,40.767821],"type":"Point"}
}