{
  "type": "Feature",
  "properties": {
    "addr:full":"1824 State Hwy 376 Wappingers Falls NY 12590",
    "addr:housenumber":"1824",
    "addr:postcode":"12590",
    "addr:street":"State Hwy 376",
    "iso:country":"US",
    "sg:address":"1824 State Hwy 376",
    "sg:city":"Wappingers Falls",
    "sg:classifiers":[
        {
            "category":"Organizations",
            "subcategory":"Religious Organization",
            "type":"Services"
        }
    ],
    "sg:phone":"+1 845 462 3887",
    "sg:postcode":"12590",
    "sg:province":"NY",
    "sg:tags":[
        "church"
    ],
    "wof:name":"St Gregory's Orthodox Church",
    "wof:placetype":"venue"
},
  "geometry": {"coordinates":[-73.86897999999999,41.621628],"type":"Point"}
}