{
  "type": "Feature",
  "properties": {
    "iso:country":"US",
    "sg:address":"30 Saranac Ave",
    "sg:city":"Lake Placid",
    "sg:classifiers":[
        {
            "category":"Organizations",
            "subcategory":"Religious Organization",
            "type":"Services"
        }
    ],
    "sg:phone":"+1 518 523 3876",
    "sg:postcode":"12946",
    "sg:province":"NY",
    "sg:tags":[
        "synagogue"
    ],
    "wof:name":"Lake Placid Synagogue",
    "wof:placetype":"venue"
},
  "geometry": {"coordinates":[-73.989572,44.292876],"type":"Point"}
}