{
  "type": "Feature",
  "properties": {
    "addr:full":"132 Spring St Ossining NY 10562",
    "addr:housenumber":"132",
    "addr:postcode":"10562",
    "addr:street":"Spring St",
    "iso:country":"US",
    "sg:address":"132 Spring St",
    "sg:city":"Ossining",
    "sg:classifiers":[
        {
            "category":"Restaurant",
            "type":"Food & Drink"
        }
    ],
    "sg:menulink":"http://www.allmenus.com/ny/ossining/60844-golden-krust/menu/",
    "sg:phone":"+1 914 923 7300",
    "sg:postcode":"10562",
    "sg:province":"NY",
    "sg:tags":[
        "caribbean"
    ],
    "wof:name":"Golden Krust",
    "wof:placetype":"venue"
},
  "geometry": {"coordinates":[-73.863928,41.157514],"type":"Point"}
}