{
  "type": "Feature",
  "properties": {
    "iso:country":"US",
    "sg:address":"4130 State Hwy 31",
    "sg:city":"Clay",
    "sg:classifiers":[
        {
            "category":"Banks & Credit Unions",
            "subcategory":"Bank",
            "type":"Services"
        }
    ],
    "sg:phone":"+1 315 652 1600",
    "sg:postcode":"13041",
    "sg:province":"NY",
    "sg:tags":[
        "financing"
    ],
    "sg:website":"www.hfc.com",
    "wof:name":"Household Finance",
    "wof:placetype":"venue"
},
  "geometry": {"coordinates":[-76.227037,43.185718],"type":"Point"}
}