{
  "type": "Feature",
  "properties": {
    "addr:full":"645 Rte 109 West Babylon NY 11704",
    "addr:housenumber":"645",
    "addr:postcode":"11704",
    "addr:street":"Rte 109",
    "iso:country":"US",
    "sg:address":"645 Rte 109",
    "sg:city":"West Babylon",
    "sg:classifiers":[
        {
            "category":"Professional",
            "type":"Services"
        }
    ],
    "sg:phone":"+1 631 422 9700",
    "sg:postcode":"11704",
    "sg:province":"NY",
    "sg:tags":[
        "establishment"
    ],
    "wof:name":"M & A Management",
    "wof:placetype":"venue"
},
  "geometry": {"coordinates":[-73.379564,40.714281],"type":"Point"}
}