{
  "type": "Feature",
  "properties": {
    "addr:full":"85 Cotter Ave Staten Island NY 10306",
    "addr:housenumber":"85",
    "addr:postcode":"10306",
    "addr:street":"Cotter Ave",
    "iso:country":"US",
    "sg:address":"85 Cotter Ave",
    "sg:city":"Staten Island",
    "sg:classifiers":[
        {
            "category":"Health Services",
            "subcategory":"Clinic",
            "type":"Services"
        }
    ],
    "sg:phone":"+1   ",
    "sg:postcode":"10306",
    "sg:province":"NY",
    "wof:name":"Armor Safety and Health Cons",
    "wof:placetype":"venue"
},
  "geometry": {"coordinates":[-74.139618,40.566309],"type":"Point"}
}