{
  "type": "Feature",
  "properties": {
    "iso:country":"US",
    "sg:address":"134 State Hwy 80",
    "sg:city":"Fort Plain",
    "sg:classifiers":[
        {
            "category":"Government",
            "subcategory":"Office",
            "type":"Public Place"
        }
    ],
    "sg:phone":"+1 518 993 3443",
    "sg:postcode":"13339",
    "sg:province":"NY",
    "sg:tags":[
        "village"
    ],
    "wof:name":"Minden Town Historian",
    "wof:placetype":"venue"
},
  "geometry": {"coordinates":[-74.626278,42.930024],"type":"Point"}
}