{
  "type": "Feature",
  "properties": {
    "addr:full":"2226 Pitkin Ave Brooklyn NY 11207",
    "addr:housenumber":"2226",
    "addr:postcode":"11207",
    "addr:street":"Pitkin Ave",
    "iso:country":"US",
    "sg:address":"2226 Pitkin Ave",
    "sg:city":"Brooklyn",
    "sg:classifiers":[
        {
            "category":"Food & Beverages",
            "subcategory":"Liquor & Beverages",
            "type":"Retail Goods"
        }
    ],
    "sg:phone":"+1 718 385 1012",
    "sg:postcode":"11207",
    "sg:province":"NY",
    "wof:name":"Tony's Liquor Store",
    "wof:placetype":"venue"
},
  "geometry": {"coordinates":[-73.88941699999999,40.672847],"type":"Point"}
}