{
  "type": "Feature",
  "properties": {
    "addr:full":"298 Piermont Ave Nyack NY 10960",
    "addr:housenumber":"298",
    "addr:postcode":"10960",
    "addr:street":"Piermont Ave",
    "iso:country":"US",
    "sg:address":"298 Piermont Ave",
    "sg:city":"Nyack",
    "sg:classifiers":[
        {
            "category":"Real Estate",
            "subcategory":"Real Estate Operator",
            "type":"Services"
        }
    ],
    "sg:phone":"+1 845 358 0040",
    "sg:postcode":"10960",
    "sg:province":"NY",
    "sg:tags":[
        "apartment"
    ],
    "wof:name":"Bradford Mews Apartments",
    "wof:placetype":"venue"
},
  "geometry": {"coordinates":[-73.919353,41.075635],"type":"Point"}
}