{
  "type": "Feature",
  "properties": {
    "addr:full":"1304 8th Ave Brooklyn NY 11215",
    "addr:housenumber":"1304",
    "addr:postcode":"11215",
    "addr:street":"8Th Ave",
    "iso:country":"US",
    "sg:address":"1304 8th Ave",
    "sg:city":"Brooklyn",
    "sg:classifiers":[
        {
            "category":"Personal",
            "subcategory":"Massage",
            "type":"Services"
        }
    ],
    "sg:phone":"+1 917 669 9969",
    "sg:postcode":"11215",
    "sg:province":"NY",
    "sg:website":"karmamassagenyc.com/",
    "wof:name":"Karma Massage",
    "wof:placetype":"venue"
},
  "geometry": {"coordinates":[-73.981487,40.663256],"type":"Point"}
}