{
  "type": "Feature",
  "properties": {
    "addr:full":"307 Knickerbocker Ave Brooklyn NY 11237",
    "addr:housenumber":"307",
    "addr:postcode":"11237",
    "addr:street":"Knickerbocker Ave",
    "iso:country":"US",
    "sg:address":"307 Knickerbocker Ave",
    "sg:city":"Brooklyn",
    "sg:classifiers":[
        {
            "category":"Restaurant",
            "type":"Food & Drink"
        }
    ],
    "sg:menulink":"http://www.allmenus.com/ny/brooklyn/53202-da-wong-kitchen/menu/",
    "sg:phone":"+1 718 386 5869",
    "sg:postcode":"11237",
    "sg:province":"NY",
    "sg:tags":[
        "asian",
        "chinese"
    ],
    "wof:name":"Da Wong Kitchen",
    "wof:placetype":"venue"
},
  "geometry": {"coordinates":[-73.92337499999999,40.701619],"type":"Point"}
}