{
  "type": "Feature",
  "properties": {
    "iso:country":"US",
    "sg:address":"66 Hackett Blvd",
    "sg:city":"Albany",
    "sg:classifiers":[
        {
            "category":"Health Services",
            "subcategory":"Doctor",
            "type":"Services"
        }
    ],
    "sg:phone":"+1 518 462 3900",
    "sg:postcode":"12209",
    "sg:province":"NY",
    "sg:tags":[
        "medical"
    ],
    "wof:name":"Jeffrey A Altman",
    "wof:placetype":"venue"
},
  "geometry": {"coordinates":[-73.781576,42.644057],"type":"Point"}
}