{
  "type": "Feature",
  "properties": {
    "iso:country":"US",
    "sg:address":"74 Foster Ave",
    "sg:city":"Hampton Bays",
    "sg:classifiers":[
        {
            "category":"Recreation",
            "subcategory":"Marina",
            "type":"Entertainment"
        }
    ],
    "sg:phone":"+1   ",
    "sg:postcode":"11946",
    "sg:province":"NY",
    "sg:tags":[
        "yard",
        "storage",
        "boat",
        "repair"
    ],
    "wof:name":"Mill River",
    "wof:placetype":"venue"
},
  "geometry": {"coordinates":[-72.506168,40.849808],"type":"Point"}
}