{
  "type": "Feature",
  "properties": {
    "iso:country":"US",
    "sg:address":"31 Fountain Ln",
    "sg:city":"Jericho",
    "sg:classifiers":[
        {
            "category":"Food & Beverages",
            "subcategory":"Groceries & Convenience Stores",
            "type":"Retail Goods"
        }
    ],
    "sg:phone":"+1   ",
    "sg:postcode":"11753",
    "sg:province":"NY",
    "wof:name":"J&A Baked Goods Incorpora",
    "wof:placetype":"venue"
},
  "geometry": {"coordinates":[-73.52249500000001,40.799159],"type":"Point"}
}