{
  "type": "Feature",
  "properties": {
    "iso:country":"US",
    "sg:address":"322 Voorhees Ave",
    "sg:city":"Buffalo",
    "sg:classifiers":[
        {
            "category":"Deli",
            "type":"Food & Drink"
        }
    ],
    "sg:phone":"+1 716 833 3390",
    "sg:postcode":"14216",
    "sg:province":"NY",
    "wof:name":"Avenue Delicatessen",
    "wof:placetype":"venue"
},
  "geometry": {"coordinates":[-78.84139999999999,42.949699],"type":"Point"}
}