{
  "type": "Feature",
  "properties": {
    "iso:country":"US",
    "sg:address":"26 Decker Dr",
    "sg:city":"Washingtonville",
    "sg:classifiers":[
        {
            "category":"Shopping",
            "subcategory":"Gifts & Souvenirs",
            "type":"Retail Goods"
        }
    ],
    "sg:phone":"+1   ",
    "sg:postcode":"10992",
    "sg:province":"NY",
    "wof:name":"Beyond Picket Fence",
    "wof:placetype":"venue"
},
  "geometry": {"coordinates":[-74.143348,41.433828],"type":"Point"}
}