{
  "type": "Feature",
  "properties": {
    "addr:full":"3 Tremont St Albany NY 12205",
    "addr:housenumber":"3",
    "addr:postcode":"12205",
    "addr:street":"Tremont St",
    "iso:country":"US",
    "sg:address":"3 Tremont St",
    "sg:city":"Albany",
    "sg:classifiers":[
        {
            "category":"Building & Trades",
            "subcategory":"Cleaning & Sanitation",
            "type":"Services"
        }
    ],
    "sg:phone":"+1 518 482 0468",
    "sg:postcode":"12205",
    "sg:province":"NY",
    "sg:tags":[
        "janitor"
    ],
    "wof:name":"Totally Kleen",
    "wof:placetype":"venue"
},
  "geometry": {"coordinates":[-73.79819000000001,42.684406],"type":"Point"}
}