{
  "type": "Feature",
  "properties": {
    "addr:full":"36 Southdown Rd Huntington NY 11743",
    "addr:housenumber":"36",
    "addr:postcode":"11743",
    "addr:street":"Southdown Rd",
    "iso:country":"US",
    "sg:address":"36 Southdown Rd",
    "sg:city":"Huntington",
    "sg:classifiers":[
        {
            "category":"Organizations",
            "subcategory":"Religious Organization",
            "type":"Services"
        }
    ],
    "sg:phone":"+1 631 549 1792",
    "sg:postcode":"11743",
    "sg:province":"NY",
    "sg:website":"http://www.watchtower.org",
    "wof:name":"Jehovas Withness Kingdom Hall",
    "wof:placetype":"venue"
},
  "geometry": {"coordinates":[-73.428482,40.880131],"type":"Point"}
}