{
  "type": "Feature",
  "properties": {
    "addr:full":"227 E 60th St Frnt A New York NY 10022",
    "addr:housenumber":"227",
    "addr:postcode":"10022",
    "addr:street":"E 60Th St;A",
    "iso:country":"US",
    "sg:address":"227 E 60th St Frnt A",
    "sg:city":"New York",
    "sg:classifiers":[
        {
            "category":"Shopping",
            "subcategory":"Antiques",
            "type":"Retail Goods"
        }
    ],
    "sg:phone":"+1 212 627 5552",
    "sg:postcode":"10022",
    "sg:province":"NY",
    "wof:name":"Venfield Inc",
    "wof:placetype":"venue"
},
  "geometry": {"coordinates":[-73.965446,40.762051],"type":"Point"}
}