{
  "type": "Feature",
  "properties": {
    "addr:full":"6 Mirror Lake Rd Spring Valley NY 10977",
    "addr:housenumber":"6",
    "addr:postcode":"10977",
    "addr:street":"Mirror Lake Rd",
    "iso:country":"US",
    "sg:address":"6 Mirror Lake Rd",
    "sg:city":"Spring Valley",
    "sg:classifiers":[
        {
            "category":"Manufacturing",
            "subcategory":"Petroleum Products",
            "type":"Manufacturing & Wholesale Goods"
        }
    ],
    "sg:phone":"+1 845 425 6345",
    "sg:postcode":"10977",
    "sg:province":"NY",
    "wof:name":"ZSA Petroleum Inc",
    "wof:placetype":"venue"
},
  "geometry": {"coordinates":[-74.02759,41.122819],"type":"Point"}
}