{
  "type": "Feature",
  "properties": {
    "addr:full":"1076 E 23rd St Brooklyn NY 11210",
    "addr:housenumber":"1076",
    "addr:postcode":"11210",
    "addr:street":"E 23Rd St",
    "iso:country":"US",
    "sg:address":"1076 E 23rd St",
    "sg:city":"Brooklyn",
    "sg:classifiers":[
        {
            "category":"Organizations",
            "subcategory":"Religious Organization",
            "type":"Services"
        }
    ],
    "sg:phone":"+1 718 377 0937",
    "sg:postcode":"11210",
    "sg:province":"NY",
    "sg:tags":[
        "clergy"
    ],
    "wof:name":"Solomon Werdiger",
    "wof:placetype":"venue"
},
  "geometry": {"coordinates":[-73.95339300000001,40.6255],"type":"Point"}
}