{
  "type": "Feature",
  "properties": {
    "iso:country":"US",
    "sg:address":"77 Franklin St",
    "sg:city":"New York",
    "sg:classifiers":[
        {
            "category":"Home & Garden",
            "subcategory":"Furniture",
            "type":"Retail Goods"
        }
    ],
    "sg:phone":"+1 212 625 3355",
    "sg:postcode":"10013",
    "sg:province":"NY",
    "sg:tags":[
        "store"
    ],
    "wof:name":"John Kelly Furniture",
    "wof:placetype":"venue"
},
  "geometry": {"coordinates":[-74.004501,40.7178],"type":"Point"}
}