{
  "type": "Feature",
  "properties": {
    "addr:full":"1201 Webster Avenue Bronx NY 10456",
    "addr:housenumber":"1201",
    "addr:postcode":"10456",
    "addr:street":"Webster Avenue",
    "iso:country":"US",
    "sg:address":"1201 Webster Avenue",
    "sg:city":"Bronx",
    "sg:classifiers":[
        {
            "category":"Autos & Motor Vehicles",
            "subcategory":"Fuel & Gas Station",
            "type":"Retail Goods"
        }
    ],
    "sg:phone":"+1 718 681 1447",
    "sg:postcode":"10456",
    "sg:province":"NY",
    "wof:name":"Merit Oil of New York",
    "wof:placetype":"venue"
},
  "geometry": {"coordinates":[-73.90992,40.832036],"type":"Point"}
}