{
  "type": "Feature",
  "properties": {
    "addr:full":"12601 Roosevelt Avenue Corona NY 11368",
    "addr:housenumber":"12601",
    "addr:postcode":"11368",
    "addr:street":"Roosevelt Avenue",
    "iso:country":"US",
    "sg:address":"12601 Roosevelt Avenue",
    "sg:city":"Corona",
    "sg:classifiers":[
        {
            "category":"Retail",
            "subcategory":"Auto Repair",
            "type":"Services"
        }
    ],
    "sg:phone":"+1 718 457 3800",
    "sg:postcode":"11368",
    "sg:province":"NY",
    "wof:name":"AAA Glass Sales & Service",
    "wof:placetype":"venue"
},
  "geometry": {"coordinates":[-73.84264899999999,40.755634],"type":"Point"}
}