{
  "type": "Feature",
  "properties": {
    "addr:full":"300 Hylan Dr Rochester NY 14623",
    "addr:housenumber":"300",
    "addr:postcode":"14623",
    "addr:street":"Hylan Dr",
    "iso:country":"US",
    "sg:address":"300 Hylan Dr",
    "sg:city":"Rochester",
    "sg:classifiers":[
        {
            "category":"Bakery",
            "type":"Food & Drink"
        }
    ],
    "sg:menulink":"http://www.allmenus.com/ny/henrietta/105965-panera-bread/menu/",
    "sg:phone":"+1 585 272 7410",
    "sg:postcode":"14623",
    "sg:province":"NY",
    "sg:tags":[
        "american",
        "sandwich",
        "pastry"
    ],
    "wof:name":"Panera Bread",
    "wof:placetype":"venue"
},
  "geometry": {"coordinates":[-77.628069,43.08509],"type":"Point"}
}