{
  "type": "Feature",
  "properties": {
    "addr:full":"176 Cortlandt St Sleepy Hollow NY 10591",
    "addr:housenumber":"176",
    "addr:postcode":"10591",
    "addr:street":"Cortlandt St",
    "iso:country":"US",
    "sg:address":"176 Cortlandt St",
    "sg:city":"Sleepy Hollow",
    "sg:classifiers":[
        {
            "category":"Shopping",
            "subcategory":"Clothing, Apparel, & Fashions",
            "type":"Retail Goods"
        }
    ],
    "sg:phone":"+1 914 631 2846",
    "sg:postcode":"10591",
    "sg:province":"NY",
    "sg:tags":[
        "item",
        "boutique"
    ],
    "wof:name":"K & D Boutique",
    "wof:placetype":"venue"
},
  "geometry": {"coordinates":[-73.86281099999999,41.083294],"type":"Point"}
}