{
  "type": "Feature",
  "properties": {
    "addr:full":"5 Northway Ln N Latham NY 12110",
    "addr:housenumber":"5",
    "addr:postcode":"12110",
    "addr:street":"Northway Ln N",
    "iso:country":"US",
    "sg:address":"5 Northway Ln N",
    "sg:city":"Latham",
    "sg:classifiers":[
        {
            "category":"Building & Trades",
            "subcategory":"Landscaping Services",
            "type":"Services"
        }
    ],
    "sg:phone":"+1 518 785 9417",
    "sg:postcode":"12110",
    "sg:province":"NY",
    "sg:tags":[
        "tree"
    ],
    "sg:website":"www.davey.com",
    "wof:name":"Davey Tree & Lawn Care",
    "wof:placetype":"venue"
},
  "geometry": {"coordinates":[-73.797372,42.737288],"type":"Point"}
}