{
  "type": "Feature",
  "properties": {
    "addr:full":"325 Yonkers Ave Yonkers NY 10701",
    "addr:housenumber":"325",
    "addr:postcode":"10701",
    "addr:street":"Yonkers Ave",
    "iso:country":"US",
    "sg:address":"325 Yonkers Ave",
    "sg:city":"Yonkers",
    "sg:classifiers":[
        {
            "category":"Utilities",
            "subcategory":"Refuse",
            "type":"Services"
        }
    ],
    "sg:phone":"+1 914 337 2014",
    "sg:postcode":"10701",
    "sg:province":"NY",
    "sg:tags":[
        "garbage",
        "system",
        "collection"
    ],
    "wof:name":"Waste Management Inc",
    "wof:placetype":"venue"
},
  "geometry": {"coordinates":[-73.871374,40.933166],"type":"Point"}
}