{
  "type": "Feature",
  "properties": {
    "addr:full":"169 Irish Hill Rd Newfield NY 14867",
    "addr:housenumber":"169",
    "addr:postcode":"14867",
    "addr:street":"Irish Hill Rd",
    "iso:country":"US",
    "sg:address":"169 Irish Hill Rd",
    "sg:city":"Newfield",
    "sg:classifiers":[
        {
            "category":"Manufacturing",
            "subcategory":"Lumber",
            "type":"Manufacturing & Wholesale Goods"
        }
    ],
    "sg:phone":"+1 607 273 9315",
    "sg:postcode":"14867",
    "sg:province":"NY",
    "sg:tags":[
        "operation",
        "timber",
        "tract"
    ],
    "wof:name":"RB Garage",
    "wof:placetype":"venue"
},
  "geometry": {"coordinates":[-76.637156,42.294764],"type":"Point"}
}