{
  "type": "Feature",
  "properties": {
    "iso:country":"US",
    "sg:address":"2302 Mermaid Ave",
    "sg:city":"Brooklyn",
    "sg:classifiers":[
        {
            "category":"Restaurant",
            "type":"Food & Drink"
        }
    ],
    "sg:phone":"+1 718 996 3806",
    "sg:postcode":"11224",
    "sg:province":"NY",
    "wof:name":"Unico Restaurant",
    "wof:placetype":"venue"
},
  "geometry": {"coordinates":[-73.991108,40.575853],"type":"Point"}
}