{
  "type": "Feature",
  "properties": {
    "iso:country":"US",
    "sg:address":"202 Co Rd 21",
    "sg:city":"Barryville",
    "sg:classifiers":[
        {
            "category":"Building & Trades",
            "subcategory":"Plumbing",
            "type":"Services"
        }
    ],
    "sg:phone":"+1 845 557 6000",
    "sg:postcode":"12719",
    "sg:province":"NY",
    "sg:tags":[
        "plumbing",
        "contractor"
    ],
    "wof:name":"Charles Kaese Plumbing & Heati",
    "wof:placetype":"venue"
},
  "geometry": {"coordinates":[-74.92976,41.51123],"type":"Point"}
}