{
  "type": "Feature",
  "properties": {
    "iso:country":"US",
    "sg:address":"292 Herricks Rd",
    "sg:city":"Mineola",
    "sg:classifiers":[
        {
            "category":"Health Services",
            "subcategory":"Doctor",
            "type":"Services"
        }
    ],
    "sg:phone":"+1 516 877 0011",
    "sg:postcode":"11501",
    "sg:province":"NY",
    "wof:name":"Fritzhand Jason MD",
    "wof:placetype":"venue"
},
  "geometry": {"coordinates":[-73.65770000000001,40.745998],"type":"Point"}
}