{
  "type": "Feature",
  "properties": {
    "addr:full":"4 Henry St Commack NY 11714",
    "addr:housenumber":"4",
    "addr:postcode":"11714",
    "addr:street":"Henry St",
    "iso:country":"US",
    "sg:address":"4 Henry St",
    "sg:city":"Commack",
    "sg:classifiers":[
        {
            "category":"Real Estate",
            "subcategory":"Developer",
            "type":"Services"
        }
    ],
    "sg:phone":"+1 631 462 6689",
    "sg:postcode":"11714",
    "sg:province":"NY",
    "wof:name":"Pj Venture Hd LLC",
    "wof:placetype":"venue"
},
  "geometry": {"coordinates":[-73.499225,40.734652],"type":"Point"}
}