{
  "type": "Feature",
  "properties": {
    "iso:country":"US",
    "sg:address":"151 Charlotte St",
    "sg:city":"Canandaigua",
    "sg:classifiers":[
        {
            "category":"Museum",
            "subcategory":"Botanical Garden",
            "type":"Entertainment"
        }
    ],
    "sg:phone":"+1   ",
    "sg:postcode":"14424",
    "sg:province":"NY",
    "sg:tags":[
        "enjoy",
        "art",
        "estate",
        "victorian",
        "promoting",
        "display"
    ],
    "wof:name":"Sonnenberg Gardens & Mansion",
    "wof:placetype":"venue"
},
  "geometry": {"coordinates":[-77.27585999999999,42.897988],"type":"Point"}
}