{
  "type": "Feature",
  "properties": {
    "iso:country":"US",
    "sg:address":"110 Amity St",
    "sg:city":"Brooklyn",
    "sg:classifiers":[
        {
            "category":"Health Services",
            "subcategory":"Doctor",
            "type":"Services"
        }
    ],
    "sg:phone":"+1 718 780 1588",
    "sg:postcode":"11201",
    "sg:province":"NY",
    "sg:tags":[
        "physician",
        "surgeon"
    ],
    "wof:name":"Stephanie Hamarman MD",
    "wof:placetype":"venue"
},
  "geometry": {"coordinates":[-73.995001,40.688915],"type":"Point"}
}