{
  "type": "Feature",
  "properties": {
    "iso:country":"US",
    "sg:address":"2180 Brighton Henrietta Town Line Rd",
    "sg:city":"Rochester",
    "sg:classifiers":[
        {
            "category":"Manufacturing",
            "subcategory":"Paper Products",
            "type":"Manufacturing & Wholesale Goods"
        }
    ],
    "sg:phone":"+1 585 424 1210",
    "sg:postcode":"14623",
    "sg:province":"NY",
    "sg:tags":[
        "converter"
    ],
    "wof:name":"J Mac Kenzie LTD",
    "wof:placetype":"venue"
},
  "geometry": {"coordinates":[-77.616529,43.094685],"type":"Point"}
}