{
  "type": "Feature",
  "properties": {
    "addr:full":"2441 Broadway New York NY 10024",
    "addr:housenumber":"2441",
    "addr:postcode":"10024",
    "addr:street":"Broadway",
    "iso:country":"US",
    "sg:address":"2441 Broadway",
    "sg:city":"New York",
    "sg:classifiers":[
        {
            "category":"Restaurant",
            "type":"Food & Drink"
        }
    ],
    "sg:menulink":"http://www.allmenus.com/ny/new-york/251705-city-diner/menu/",
    "sg:phone":"+1 212 877 2720",
    "sg:postcode":"10024",
    "sg:province":"NY",
    "sg:tags":[
        "american",
        "diner"
    ],
    "wof:name":"City Diner",
    "wof:placetype":"venue"
},
  "geometry": {"coordinates":[-73.97483,40.791217],"type":"Point"}
}