{
  "type": "Feature",
  "properties": {
    "addr:full":"68 Orion Walk Holbrook NY 11741",
    "addr:housenumber":"68",
    "addr:postcode":"11741",
    "addr:street":"Orion Walk",
    "iso:country":"US",
    "sg:address":"68 Orion Walk",
    "sg:city":"Holbrook",
    "sg:classifiers":[
        {
            "category":"Local Transit",
            "type":"Transportation"
        }
    ],
    "sg:phone":"+1 631 589 6988",
    "sg:postcode":"11741",
    "sg:province":"NY",
    "sg:tags":[
        "limousine"
    ],
    "wof:name":"Aquarius Limousine",
    "wof:placetype":"venue"
},
  "geometry": {"coordinates":[-73.063568,40.778172],"type":"Point"}
}