{
  "type": "Feature",
  "properties": {
    "iso:country":"US",
    "sg:address":"20 Burke Dr",
    "sg:city":"Buffalo",
    "sg:classifiers":[
        {
            "category":"Building & Trades",
            "subcategory":"Construction",
            "type":"Services"
        }
    ],
    "sg:phone":"+1 716 835 1870",
    "sg:postcode":"14215",
    "sg:province":"NY",
    "sg:tags":[
        "house"
    ],
    "wof:name":"Northwoods Developers",
    "wof:placetype":"venue"
},
  "geometry": {"coordinates":[-78.802744,42.943559],"type":"Point"}
}