{
  "type": "Feature",
  "properties": {
    "iso:country":"US",
    "sg:address":"25 N Side Rd",
    "sg:city":"Jericho",
    "sg:classifiers":[
        {
            "category":"Travel",
            "subcategory":"Travel Agent",
            "type":"Entertainment"
        }
    ],
    "sg:phone":"+1   ",
    "sg:postcode":"11792",
    "sg:province":"NY",
    "sg:tags":[
        "operator",
        "organization",
        "tour",
        "religious"
    ],
    "wof:name":"Peters Way Cortial Intl",
    "wof:placetype":"venue"
},
  "geometry": {"coordinates":[-72.852283,40.964889],"type":"Point"}
}