{
  "type": "Feature",
  "properties": {
    "iso:country":"US",
    "sg:address":"1214 Lexington Ave",
    "sg:city":"New York",
    "sg:classifiers":[
        {
            "category":"Shopping",
            "subcategory":"Jewelry",
            "type":"Retail Goods"
        }
    ],
    "sg:phone":"+1   ",
    "sg:postcode":"10028",
    "sg:province":"NY",
    "wof:name":"Scintilla Jewelry Inc",
    "wof:placetype":"venue"
},
  "geometry": {"coordinates":[-73.95716299999999,40.777423],"type":"Point"}
}