{
  "type": "Feature",
  "properties": {
    "addr:full":"78 Rivington St New York NY 10002",
    "addr:housenumber":"78",
    "addr:postcode":"10002",
    "addr:street":"Rivington St",
    "iso:country":"US",
    "sg:address":"78 Rivington St",
    "sg:city":"New York",
    "sg:classifiers":[
        {
            "category":"Restaurant",
            "type":"Food & Drink"
        }
    ],
    "sg:menulink":"http://www.allmenus.com/ny/new-york/250094-kampuchea/menu/",
    "sg:phone":"+1 212 529 3901",
    "sg:postcode":"10002",
    "sg:province":"NY",
    "sg:tags":[
        "cambodian",
        "asian"
    ],
    "wof:name":"Kampuchea",
    "wof:placetype":"venue"
},
  "geometry": {"coordinates":[-73.98926299999999,40.720466],"type":"Point"}
}