{
  "type": "Feature",
  "properties": {
    "addr:full":"1319 3rd Ave New York NY 10021",
    "addr:housenumber":"1319",
    "addr:postcode":"10021",
    "addr:street":"3Rd Ave",
    "iso:country":"US",
    "sg:address":"1319 3rd Ave",
    "sg:city":"New York",
    "sg:classifiers":[
        {
            "category":"Shopping",
            "subcategory":"Clothing, Apparel, & Fashions",
            "type":"Retail Goods"
        }
    ],
    "sg:phone":"+1 212 744 0379",
    "sg:postcode":"10021",
    "sg:province":"NY",
    "sg:tags":[
        "accessory",
        "clothing",
        "women's"
    ],
    "sg:website":"www.freepeople.com/",
    "wof:name":"Free People Clothing Boutique",
    "wof:placetype":"venue"
},
  "geometry": {"coordinates":[-73.95862099999999,40.771915],"type":"Point"}
}