{
  "type": "Feature",
  "properties": {
    "iso:country":"US",
    "sg:address":"734 Broadway",
    "sg:city":"New York",
    "sg:classifiers":[
        {
            "category":"Building & Trades",
            "subcategory":"Locksmith",
            "type":"Services"
        }
    ],
    "sg:phone":"+1 212 231 7641",
    "sg:postcode":"10003",
    "sg:province":"NY",
    "sg:tags":[
        "key"
    ],
    "wof:name":"A Mitzia 24 Hr Locksmith",
    "wof:placetype":"venue"
},
  "geometry": {"coordinates":[-73.99299600000001,40.729698],"type":"Point"}
}