{
  "type": "Feature",
  "properties": {
    "iso:country":"US",
    "sg:address":"609 E Main St",
    "sg:city":"Palmyra",
    "sg:classifiers":[
        {
            "category":"Wholesale",
            "subcategory":"Scrap",
            "type":"Manufacturing & Wholesale Goods"
        }
    ],
    "sg:phone":"+1 315 597 2047",
    "sg:postcode":"14522",
    "sg:province":"NY",
    "sg:tags":[
        "recycling",
        "center"
    ],
    "wof:name":"Tomra Ny",
    "wof:placetype":"venue"
},
  "geometry": {"coordinates":[-77.22365499999999,43.063216],"type":"Point"}
}