{
  "type": "Feature",
  "properties": {
    "iso:country":"US",
    "sg:address":"25160 State Hwy 180",
    "sg:city":"Dexter",
    "sg:classifiers":[
        {
            "category":"Professional",
            "subcategory":"Testing Lab",
            "type":"Services"
        }
    ],
    "sg:phone":"+1   ",
    "sg:postcode":"13634",
    "sg:province":"NY",
    "sg:tags":[
        "laboratory"
    ],
    "wof:name":"Aj Dairy Services",
    "wof:placetype":"venue"
},
  "geometry": {"coordinates":[-76.043373,44.033725],"type":"Point"}
}