{
  "type": "Feature",
  "properties": {
    "iso:country":"US",
    "sg:address":"8 Orshava Ct Unit 302",
    "sg:city":"Monroe",
    "sg:classifiers":[
        {
            "category":"Education",
            "subcategory":"School",
            "type":"Public Place"
        }
    ],
    "sg:phone":"+1 845 782 9753",
    "sg:postcode":"10950",
    "sg:province":"NY",
    "wof:name":"Ohel Torah",
    "wof:placetype":"venue"
},
  "geometry": {"coordinates":[-74.166718,41.345078],"type":"Point"}
}