{
  "type": "Feature",
  "properties": {
    "addr:full":"322 N Aurora St Ithaca NY 14850",
    "addr:housenumber":"322",
    "addr:postcode":"14850",
    "addr:street":"N Aurora St",
    "iso:country":"US",
    "sg:address":"322 N Aurora St",
    "sg:city":"Ithaca",
    "sg:classifiers":[
        {
            "category":"Health Services",
            "subcategory":"Optometrist",
            "type":"Services"
        }
    ],
    "sg:phone":"+1 607 277 4749",
    "sg:postcode":"14850",
    "sg:province":"NY",
    "wof:name":"Larry Wallace OD",
    "wof:placetype":"venue"
},
  "geometry": {"coordinates":[-76.495857,42.442387],"type":"Point"}
}