{
  "type": "Feature",
  "properties": {
    "iso:country":"US",
    "sg:address":"259 W 34th St",
    "sg:city":"New York",
    "sg:classifiers":[
        {
            "category":"Bars & Pubs",
            "type":"Food & Drink"
        }
    ],
    "sg:phone":"+1   ",
    "sg:postcode":"10001",
    "sg:province":"NY",
    "sg:tags":[
        "drinking",
        "eating"
    ],
    "wof:name":"Blarney Stone/Douglas",
    "wof:placetype":"venue"
},
  "geometry": {"coordinates":[-73.992154,40.751547],"type":"Point"}
}