{
  "type": "Feature",
  "properties": {
    "addr:full":"48 Wesvalley Rd Lake Placid NY 12946",
    "addr:housenumber":"48",
    "addr:postcode":"12946",
    "addr:street":"Wesvalley Rd",
    "iso:country":"US",
    "sg:address":"48 Wesvalley Rd",
    "sg:city":"Lake Placid",
    "sg:classifiers":[
        {
            "category":"Autos & Motor Vehicles",
            "subcategory":"Auto Supplies",
            "type":"Retail Goods"
        }
    ],
    "sg:phone":"+1 518 523 1301",
    "sg:postcode":"12946",
    "sg:province":"NY",
    "sg:tags":[
        "automobile",
        "parts"
    ],
    "wof:name":"Olympic Auto & Truck Supply",
    "wof:placetype":"venue"
},
  "geometry": {"coordinates":[-73.992575,44.287467],"type":"Point"}
}