{
  "type": "Feature",
  "properties": {
    "iso:country":"US",
    "sg:address":"8515 4th Avenue",
    "sg:city":"Brooklyn",
    "sg:classifiers":[
        {
            "category":"Banks & Credit Unions",
            "subcategory":"Bank",
            "type":"Services"
        }
    ],
    "sg:phone":"+1 718 627 3999",
    "sg:postcode":"11209",
    "sg:province":"NY",
    "wof:name":"Citibank N A",
    "wof:placetype":"venue"
},
  "geometry": {"coordinates":[-74.028139,40.622949],"type":"Point"}
}