{
  "type": "Feature",
  "properties": {
    "iso:country":"US",
    "sg:address":"917A E 28th St",
    "sg:city":"Brooklyn",
    "sg:classifiers":[
        {
            "category":"Communications",
            "type":"Services"
        }
    ],
    "sg:phone":"+1 212 576 1155",
    "sg:postcode":"11210",
    "sg:province":"NY",
    "sg:tags":[
        "web",
        "design"
    ],
    "sg:website":"www.ajaxunion.com",
    "wof:name":"Ajax Union",
    "wof:placetype":"venue"
},
  "geometry": {"coordinates":[-73.94918,40.628544],"type":"Point"}
}