{
  "type": "Feature",
  "properties": {
    "addr:full":"129 E Main St Richfield Spgs NY 13439",
    "addr:housenumber":"129",
    "addr:postcode":"13439",
    "addr:street":"E Main St",
    "iso:country":"US",
    "sg:address":"129 E Main St",
    "sg:city":"Richfield Spgs",
    "sg:classifiers":[
        {
            "category":"Home & Garden",
            "subcategory":"Hardware",
            "type":"Retail Goods"
        }
    ],
    "sg:phone":"+1 315 858 2411",
    "sg:postcode":"13439",
    "sg:province":"NY",
    "wof:name":"Anderson's Hardware Inc",
    "wof:placetype":"venue"
},
  "geometry": {"coordinates":[-74.98481200000001,42.853277],"type":"Point"}
}