{
  "type": "Feature",
  "properties": {
    "addr:full":"1010 50th Ave. Long Island City NY 11109",
    "addr:housenumber":"1010",
    "addr:postcode":"11109",
    "addr:street":"50Th Ave.",
    "iso:country":"US",
    "sg:address":"1010 50th Ave.",
    "sg:city":"Long Island City",
    "sg:classifiers":[
        {
            "category":"Restaurant",
            "type":"Food & Drink"
        }
    ],
    "sg:phone":"+1 718 383 9315",
    "sg:postcode":"11109",
    "sg:province":"NY",
    "sg:tags":[
        "french"
    ],
    "wof:name":"Caf? Henri",
    "wof:placetype":"venue"
},
  "geometry": {"coordinates":[-73.95378100000001,40.742512],"type":"Point"}
}