{
  "type": "Feature",
  "properties": {
    "addr:full":"47 Grandview St Huntington NY 11743",
    "addr:housenumber":"47",
    "addr:postcode":"11743",
    "addr:street":"Grandview St",
    "iso:country":"US",
    "sg:address":"47 Grandview St",
    "sg:city":"Huntington",
    "sg:classifiers":[
        {
            "category":"Professional",
            "subcategory":"Computer Services",
            "type":"Services"
        }
    ],
    "sg:phone":"+1   ",
    "sg:postcode":"11743",
    "sg:province":"NY",
    "sg:tags":[
        "agency",
        "employment",
        "programing",
        "custom"
    ],
    "wof:name":"Matrix Solutions New York",
    "wof:placetype":"venue"
},
  "geometry": {"coordinates":[-73.41734700000001,40.864713],"type":"Point"}
}