{
  "type": "Feature",
  "properties": {
    "iso:country":"US",
    "sg:address":"45 Buckeye Rd",
    "sg:city":"Glen Cove",
    "sg:classifiers":[
        {
            "category":"Real Estate",
            "subcategory":"Surveying",
            "type":"Services"
        }
    ],
    "sg:phone":"+1 516 656 9089",
    "sg:postcode":"11542",
    "sg:province":"NY",
    "sg:tags":[
        "surveyor"
    ],
    "wof:name":"Apolonio Agujo Pro Land Srvyrs",
    "wof:placetype":"venue"
},
  "geometry": {"coordinates":[-73.634483,40.877572],"type":"Point"}
}