{
  "type": "Feature",
  "properties": {
    "addr:full":"438 Greece Ridge Center Dr Rochester NY 14626",
    "addr:housenumber":"438",
    "addr:postcode":"14626",
    "addr:street":"Greece Ridge Center Dr",
    "iso:country":"US",
    "sg:address":"438 Greece Ridge Center Dr",
    "sg:city":"Rochester",
    "sg:classifiers":[
        {
            "category":"Restaurant",
            "type":"Food & Drink"
        }
    ],
    "sg:phone":"+1 585 227 9890",
    "sg:postcode":"14626",
    "sg:province":"NY",
    "wof:name":"Flaming Wok",
    "wof:placetype":"venue"
},
  "geometry": {"coordinates":[-77.695516,43.204712],"type":"Point"}
}