{
  "type": "Feature",
  "properties": {
    "addr:full":"149 E 165th St Bronx NY 10452",
    "addr:housenumber":"149",
    "addr:postcode":"10452",
    "addr:street":"E 165Th St",
    "iso:country":"US",
    "sg:address":"149 E 165th St",
    "sg:city":"Bronx",
    "sg:classifiers":[
        {
            "category":"Retail",
            "subcategory":"Laundry & Dry Cleaning",
            "type":"Services"
        }
    ],
    "sg:phone":"+1 718 537 2260",
    "sg:postcode":"10452",
    "sg:province":"NY",
    "wof:name":"Liberty Laundromat LLC",
    "wof:placetype":"venue"
},
  "geometry": {"coordinates":[-73.920856,40.83118],"type":"Point"}
}