{
  "type": "Feature",
  "properties": {
    "iso:country":"US",
    "sg:address":"321 Douglas St",
    "sg:city":"Syracuse",
    "sg:classifiers":[
        {
            "category":"Freight",
            "type":"Transportation"
        }
    ],
    "sg:phone":"+1 315 474 7872",
    "sg:postcode":"13203",
    "sg:province":"NY",
    "sg:tags":[
        "trucking"
    ],
    "wof:name":"Global Transport & Buying",
    "wof:placetype":"venue"
},
  "geometry": {"coordinates":[-76.139169,43.060571],"type":"Point"}
}