{
  "type": "Feature",
  "properties": {
    "addr:full":"89 Remsen Street Brooklyn NY 11201",
    "addr:housenumber":"89",
    "addr:postcode":"11201",
    "addr:street":"Remsen Street",
    "iso:country":"US",
    "sg:address":"89 Remsen Street",
    "sg:city":"Brooklyn",
    "sg:classifiers":[
        {
            "category":"Health Services",
            "subcategory":"Dentist",
            "type":"Services"
        }
    ],
    "sg:phone":"+1 718 855 7545",
    "sg:postcode":"11201",
    "sg:province":"NY",
    "wof:name":"Moshman Stanley M DDS",
    "wof:placetype":"venue"
},
  "geometry": {"coordinates":[-73.99471699999999,40.694264],"type":"Point"}
}