{
  "type": "Feature",
  "properties": {
    "addr:full":"344 Starr Blvd Calverton NY 11933",
    "addr:housenumber":"344",
    "addr:postcode":"11933",
    "addr:street":"Starr Blvd",
    "iso:country":"US",
    "sg:address":"344 Starr Blvd",
    "sg:city":"Calverton",
    "sg:classifiers":[
        {
            "category":"Building & Trades",
            "subcategory":"Landscaping Services",
            "type":"Services"
        }
    ],
    "sg:phone":"+1 631 727 7530",
    "sg:postcode":"11933",
    "sg:province":"NY",
    "sg:tags":[
        "landscape"
    ],
    "wof:name":"O Godley Landscaping",
    "wof:placetype":"venue"
},
  "geometry": {"coordinates":[-72.71777400000001,40.897518],"type":"Point"}
}