{
  "type": "Feature",
  "properties": {
    "iso:country":"US",
    "sg:address":"15 149th St",
    "sg:city":"Whitestone",
    "sg:classifiers":[
        {
            "category":"Autos & Motor Vehicles",
            "subcategory":"Fuel & Gas Station",
            "type":"Retail Goods"
        }
    ],
    "sg:phone":"+1   ",
    "sg:postcode":"11357",
    "sg:province":"NY",
    "sg:tags":[
        "repair",
        "automotive",
        "gasoline",
        "general",
        "station",
        "se"
    ],
    "wof:name":"Norstone Service Station",
    "wof:placetype":"venue"
},
  "geometry": {"coordinates":[-73.81748399999999,40.792666],"type":"Point"}
}