{
  "type": "Feature",
  "properties": {
    "addr:full":"419 Maple St West Hempstead NY 11552",
    "addr:housenumber":"419",
    "addr:postcode":"11552",
    "addr:street":"Maple St",
    "iso:country":"US",
    "sg:address":"419 Maple St",
    "sg:city":"West Hempstead",
    "sg:classifiers":[
        {
            "category":"Communications",
            "subcategory":"Film & Video Production",
            "type":"Services"
        }
    ],
    "sg:phone":"+1 516 486 5198",
    "sg:postcode":"11552",
    "sg:province":"NY",
    "sg:tags":[
        "recording",
        "rehearsal",
        "editing",
        "studio",
        "tape"
    ],
    "wof:name":"Hyperstudio Recording",
    "wof:placetype":"venue"
},
  "geometry": {"coordinates":[-73.650299,40.690201],"type":"Point"}
}