{
  "type": "Feature",
  "properties": {
    "addr:full":"28 Centre Dr Plattsburgh NY 12901",
    "addr:housenumber":"28",
    "addr:postcode":"12901",
    "addr:street":"Centre Dr",
    "iso:country":"US",
    "sg:address":"28 Centre Dr",
    "sg:city":"Plattsburgh",
    "sg:classifiers":[
        {
            "category":"Shopping",
            "type":"Retail Goods"
        }
    ],
    "sg:phone":"+1 518 561 9325",
    "sg:postcode":"12901",
    "sg:province":"NY",
    "sg:tags":[
        "pet",
        "shop"
    ],
    "wof:name":"PETCO",
    "wof:placetype":"venue"
},
  "geometry": {"coordinates":[-73.491634,44.694204],"type":"Point"}
}