{
  "type": "Feature",
  "properties": {
    "iso:country":"US",
    "sg:address":"749 Hawkins Ave",
    "sg:city":"Ronkonkoma",
    "sg:classifiers":[
        {
            "category":"Food & Beverages",
            "subcategory":"Fruits & Vegetables",
            "type":"Retail Goods"
        }
    ],
    "sg:phone":"+1 631 981 0378",
    "sg:postcode":"11779",
    "sg:province":"NY",
    "sg:tags":[
        "produce"
    ],
    "wof:name":"Produce Warehouse",
    "wof:placetype":"venue"
},
  "geometry": {"coordinates":[-73.109514,40.835312],"type":"Point"}
}