{
  "type": "Feature",
  "properties": {
    "iso:country":"US",
    "sg:address":"6623 Fort Hamilton Pkwy",
    "sg:city":"Brooklyn",
    "sg:classifiers":[
        {
            "category":"Local Transit",
            "type":"Transportation"
        }
    ],
    "sg:phone":"+1 718 491 5900",
    "sg:postcode":"11219",
    "sg:province":"NY",
    "sg:tags":[
        "limousine"
    ],
    "wof:name":"Gal Hana Car Svc Inc",
    "wof:placetype":"venue"
},
  "geometry": {"coordinates":[-74.010532,40.629695],"type":"Point"}
}