{
  "type": "Feature",
  "properties": {
    "iso:country":"US",
    "sg:address":"2860 Richmond Ter",
    "sg:city":"Staten Island",
    "sg:classifiers":[
        {
            "category":"Wholesale",
            "subcategory":"Auto Parts",
            "type":"Manufacturing & Wholesale Goods"
        }
    ],
    "sg:phone":"+1 718 448 1774",
    "sg:postcode":"10303",
    "sg:province":"NY",
    "sg:tags":[
        "supply"
    ],
    "wof:name":"Harbor Starter & Alternator",
    "wof:placetype":"venue"
},
  "geometry": {"coordinates":[-74.15630400000001,40.636746],"type":"Point"}
}