{
  "type": "Feature",
  "properties": {
    "iso:country":"US",
    "sg:address":"3380 Lysander Rd",
    "sg:city":"Cato",
    "sg:classifiers":[
        {
            "category":"Freight",
            "type":"Transportation"
        }
    ],
    "sg:phone":"+1   ",
    "sg:postcode":"13033",
    "sg:province":"NY",
    "sg:tags":[
        "moving",
        "household",
        "including",
        "piano",
        "organ"
    ],
    "wof:name":"Carney & Blumer Trucking Inc",
    "wof:placetype":"venue"
},
  "geometry": {"coordinates":[-76.52191500000001,43.222381],"type":"Point"}
}