{
  "type": "Feature",
  "properties": {
    "iso:country":"US",
    "sg:address":"156 2nd Ave Frnt 1",
    "sg:city":"New York",
    "sg:classifiers":[
        {
            "category":"Banks & Credit Unions",
            "subcategory":"Bank",
            "type":"Services"
        }
    ],
    "sg:phone":"+1 212 923 5163",
    "sg:postcode":"10003",
    "sg:province":"NY",
    "wof:name":"Chase",
    "wof:placetype":"venue"
},
  "geometry": {"coordinates":[-73.986705,40.72959],"type":"Point"}
}