{
  "type": "Feature",
  "properties": {
    "iso:country":"US",
    "sg:address":"131 E 23rd St",
    "sg:city":"Manhattan",
    "sg:classifiers":[
        {
            "category":"Shopping",
            "subcategory":"Pharmacy",
            "type":"Retail Goods"
        }
    ],
    "sg:phone":"+1 212 674 7704",
    "sg:postcode":"10010",
    "sg:province":"NY",
    "sg:tags":[
        "drugstore"
    ],
    "sg:website":"www.duanereade.com/",
    "wof:name":"Duane Reade",
    "wof:placetype":"venue"
},
  "geometry": {"coordinates":[-73.98476700000001,40.739821],"type":"Point"}
}