{
  "type": "Feature",
  "properties": {
    "addr:full":"130 Utica Avenue Brooklyn NY 11213",
    "addr:housenumber":"130",
    "addr:postcode":"11213",
    "addr:street":"Utica Avenue",
    "iso:country":"US",
    "sg:address":"130 Utica Avenue",
    "sg:city":"Brooklyn",
    "sg:classifiers":[
        {
            "category":"Restaurant",
            "type":"Food & Drink"
        }
    ],
    "sg:phone":"+1 718 604 1875",
    "sg:postcode":"11213",
    "sg:province":"NY",
    "sg:tags":[
        "chinese"
    ],
    "wof:name":"China Garden",
    "wof:placetype":"venue"
},
  "geometry": {"coordinates":[-73.930735,40.674428],"type":"Point"}
}