{
  "type": "Feature",
  "properties": {
    "addr:full":"412 Kenwood Ave Delmar NY 12054",
    "addr:housenumber":"412",
    "addr:postcode":"12054",
    "addr:street":"Kenwood Ave",
    "iso:country":"US",
    "sg:address":"412 Kenwood Ave",
    "sg:city":"Delmar",
    "sg:classifiers":[
        {
            "category":"Personal",
            "subcategory":"Beauty Salon",
            "type":"Services"
        }
    ],
    "sg:phone":"+1   ",
    "sg:postcode":"12054",
    "sg:province":"NY",
    "sg:tags":[
        "shop"
    ],
    "wof:name":"Leonardo Hair Designers",
    "wof:placetype":"venue"
},
  "geometry": {"coordinates":[-73.834039,42.622282],"type":"Point"}
}