{
  "type": "Feature",
  "properties": {
    "iso:country":"US",
    "sg:address":"225 5th Ave",
    "sg:city":"New York",
    "sg:classifiers":[
        {
            "category":"Wholesale",
            "subcategory":"Home Furnishings",
            "type":"Manufacturing & Wholesale Goods"
        }
    ],
    "sg:phone":"+1 212 689 5152",
    "sg:postcode":"10010",
    "sg:province":"NY",
    "wof:name":"Boxer Collection Incorporated",
    "wof:placetype":"venue"
},
  "geometry": {"coordinates":[-73.98790700000001,40.74362],"type":"Point"}
}