{
  "type": "Feature",
  "properties": {
    "addr:full":"77 Clinton Ave Brooklyn NY 11205",
    "addr:housenumber":"77",
    "addr:postcode":"11205",
    "addr:street":"Clinton Ave",
    "iso:country":"US",
    "sg:address":"77 Clinton Ave",
    "sg:city":"Brooklyn",
    "sg:classifiers":[
        {
            "category":"Health Services",
            "subcategory":"Doctor",
            "type":"Services"
        }
    ],
    "sg:phone":"+1 718 834 2981",
    "sg:postcode":"11205",
    "sg:province":"NY",
    "sg:tags":[
        "clinic"
    ],
    "wof:name":"Brooklyn Plaza School Base",
    "wof:placetype":"venue"
},
  "geometry": {"coordinates":[-73.96876899999999,40.693355],"type":"Point"}
}