{
  "type": "Feature",
  "properties": {
    "iso:country":"US",
    "sg:address":"24804 S Conduit Ave",
    "sg:city":"Rosedale",
    "sg:classifiers":[
        {
            "category":"Fast Food",
            "type":"Food & Drink"
        },
        {
            "category":"Restaurant",
            "type":"Food & Drink"
        }
    ],
    "sg:phone":"+1 212 527 2425",
    "sg:postcode":"11422",
    "sg:province":"NY",
    "sg:tags":[
        "chicken"
    ],
    "sg:website":"http://www.kfc.com",
    "wof:name":"KFC",
    "wof:placetype":"venue"
},
  "geometry": {"coordinates":[-73.734619,40.665619],"type":"Point"}
}