{
  "type": "Feature",
  "properties": {
    "iso:country":"US",
    "sg:address":"276 5th Ave",
    "sg:city":"New York",
    "sg:classifiers":[
        {
            "category":"Health Services",
            "subcategory":"Health Practitioner",
            "type":"Services"
        }
    ],
    "sg:phone":"+1 212 481 1889",
    "sg:postcode":"10001",
    "sg:province":"NY",
    "sg:tags":[
        "psychotherapist"
    ],
    "wof:name":"Michael Fayne",
    "wof:placetype":"venue"
},
  "geometry": {"coordinates":[-73.98659499999999,40.745709],"type":"Point"}
}