{
  "type": "Feature",
  "properties": {
    "addr:full":"21 Railroad Ave Eastport NY 11941",
    "addr:housenumber":"21",
    "addr:postcode":"11941",
    "addr:street":"Railroad Ave",
    "iso:country":"US",
    "sg:address":"21 Railroad Ave",
    "sg:city":"Eastport",
    "sg:classifiers":[
        {
            "category":"Food & Beverages",
            "subcategory":"Specialty",
            "type":"Retail Goods"
        }
    ],
    "sg:phone":"+1 631 424 1138",
    "sg:postcode":"11941",
    "sg:province":"NY",
    "sg:tags":[
        "grocery"
    ],
    "wof:name":"Just Fruit Baskets",
    "wof:placetype":"venue"
},
  "geometry": {"coordinates":[-72.72904699999999,40.824123],"type":"Point"}
}