{
  "type": "Feature",
  "properties": {
    "iso:country":"US",
    "sg:address":"301 Union Tpke",
    "sg:city":"Hudson",
    "sg:classifiers":[
        {
            "category":"Wholesale",
            "subcategory":"Fruits & Vegetables",
            "type":"Manufacturing & Wholesale Goods"
        }
    ],
    "sg:phone":"+1 518 828 1568",
    "sg:postcode":"12534",
    "sg:province":"NY",
    "sg:tags":[
        "apple",
        "broker"
    ],
    "wof:name":"New York Apple Sales Inc",
    "wof:placetype":"venue"
},
  "geometry": {"coordinates":[-73.759069,42.252296],"type":"Point"}
}