{
  "type": "Feature",
  "properties": {
    "addr:full":"90 Finch Ln Islip NY 11751",
    "addr:housenumber":"90",
    "addr:postcode":"11751",
    "addr:street":"Finch Ln",
    "iso:country":"US",
    "sg:address":"90 Finch Ln",
    "sg:city":"Islip",
    "sg:classifiers":[
        {
            "category":"Real Estate",
            "subcategory":"Real Estate Operator",
            "type":"Services"
        }
    ],
    "sg:phone":"+1 631 581 3556",
    "sg:postcode":"11751",
    "sg:province":"NY",
    "sg:tags":[
        "apartment"
    ],
    "wof:name":"The Woodlands Apt Corp",
    "wof:placetype":"venue"
},
  "geometry": {"coordinates":[-73.204459,40.735576],"type":"Point"}
}