{
  "type": "Feature",
  "properties": {
    "iso:country":"US",
    "sg:address":"24 Long Meadow Dr",
    "sg:city":"Staatsburg",
    "sg:classifiers":[
        {
            "category":"Restaurant",
            "type":"Food & Drink"
        }
    ],
    "sg:phone":"+1 845 235 1063",
    "sg:postcode":"12580",
    "sg:province":"NY",
    "wof:name":"Gridiron Brewery",
    "wof:placetype":"venue"
},
  "geometry": {"coordinates":[-73.89763499999999,41.831259],"type":"Point"}
}