{
  "type": "Feature",
  "properties": {
    "addr:full":"2101 Jericho Tpke New Hyde Park NY 11040",
    "addr:housenumber":"2101",
    "addr:postcode":"11040",
    "addr:street":"Jericho Tpke;Hyde Park",
    "iso:country":"US",
    "sg:address":"2101 Jericho Tpke",
    "sg:city":"New Hyde Park",
    "sg:classifiers":[
        {
            "category":"Manufacturing",
            "subcategory":"Tools & Machinery",
            "type":"Manufacturing & Wholesale Goods"
        }
    ],
    "sg:phone":"+1   ",
    "sg:postcode":"11040",
    "sg:province":"NY",
    "sg:tags":[
        "speed",
        "electronic",
        "mfg"
    ],
    "wof:name":"Designatronics Inc",
    "wof:placetype":"venue"
},
  "geometry": {"coordinates":[-73.67256500000001,40.736288],"type":"Point"}
}