{
  "type": "Feature",
  "properties": {
    "addr:full":"18 Hayes Hill Dr Northport NY 11768",
    "addr:housenumber":"18",
    "addr:postcode":"11768",
    "addr:street":"Hayes Hill Dr",
    "iso:country":"US",
    "sg:address":"18 Hayes Hill Dr",
    "sg:city":"Northport",
    "sg:classifiers":[
        {
            "category":"Professional",
            "type":"Services"
        }
    ],
    "sg:phone":"+1 631 754 3319",
    "sg:postcode":"11768",
    "sg:province":"NY",
    "sg:tags":[
        "establishment"
    ],
    "wof:name":"J W Perceptions Inc",
    "wof:placetype":"venue"
},
  "geometry": {"coordinates":[-73.30855099999999,40.924736],"type":"Point"}
}