{
  "type": "Feature",
  "properties": {
    "iso:country":"US",
    "sg:address":"12 Cooley Rd Ste 442",
    "sg:city":"Parksville",
    "sg:classifiers":[
        {
            "category":"Manufacturing",
            "subcategory":"Metals",
            "type":"Manufacturing & Wholesale Goods"
        },
        {
            "category":"Manufacturing",
            "subcategory":"Jewelry",
            "type":"Manufacturing & Wholesale Goods"
        }
    ],
    "sg:phone":"+1 212 704 0770",
    "sg:postcode":"12768",
    "sg:province":"NY",
    "sg:tags":[
        "metals-precious",
        "jewelers-wholesale",
        "manufacturer"
    ],
    "wof:name":"Aaron & Son Inc",
    "wof:placetype":"venue"
},
  "geometry": {"coordinates":[-74.75808000000001,41.856479],"type":"Point"}
}