{
  "type": "Feature",
  "properties": {
    "iso:country":"US",
    "sg:address":"1015 Grand Concourse",
    "sg:city":"Bronx",
    "sg:classifiers":[
        {
            "category":"Professional",
            "subcategory":"Lawyer & Legal Services",
            "type":"Services"
        }
    ],
    "sg:phone":"+1 718 537 8171",
    "sg:postcode":"10452",
    "sg:province":"NY",
    "sg:tags":[
        "attorney"
    ],
    "wof:name":"Michael Newman",
    "wof:placetype":"venue"
},
  "geometry": {"coordinates":[-73.920694,40.830552],"type":"Point"}
}