{
  "type": "Feature",
  "properties": {
    "iso:country":"US",
    "sg:address":"371 Kennedy Ave",
    "sg:city":"Angola",
    "sg:classifiers":[
        {
            "category":"Building & Trades",
            "subcategory":"Construction",
            "type":"Services"
        }
    ],
    "sg:phone":"+1 716 983 5478",
    "sg:postcode":"14006",
    "sg:province":"NY",
    "sg:tags":[
        "house"
    ],
    "wof:name":"Kowals Construction",
    "wof:placetype":"venue"
},
  "geometry": {"coordinates":[-79.08118,42.623965],"type":"Point"}
}