{
  "type": "Feature",
  "properties": {
    "addr:full":"50 91st St Brooklyn NY 11209",
    "addr:housenumber":"50",
    "addr:postcode":"11209",
    "addr:street":"91St St",
    "iso:country":"US",
    "sg:address":"50 91st St",
    "sg:city":"Brooklyn",
    "sg:classifiers":[
        {
            "category":"Health Services",
            "subcategory":"Chiropractor",
            "type":"Services"
        }
    ],
    "sg:phone":"+1 718 680 2222",
    "sg:postcode":"11209",
    "sg:province":"NY",
    "wof:name":"Dadas Mary Suozzo",
    "wof:placetype":"venue"
},
  "geometry": {"coordinates":[-74.038101,40.621201],"type":"Point"}
}