{
  "type": "Feature",
  "properties": {
    "iso:country":"US",
    "sg:address":"284 E 3rd St",
    "sg:city":"Mount Vernon",
    "sg:classifiers":[
        {
            "category":"Restaurant",
            "type":"Food & Drink"
        }
    ],
    "sg:phone":"+1 914 668 7335",
    "sg:postcode":"10553",
    "sg:province":"NY",
    "sg:tags":[
        "eating"
    ],
    "wof:name":"King's Southern Delight",
    "wof:placetype":"venue"
},
  "geometry": {"coordinates":[-73.82515600000001,40.909053],"type":"Point"}
}