{
  "type": "Feature",
  "properties": {
    "addr:full":"150 East 42nd Street 8th Floor New York NY 10017",
    "addr:housenumber":"150;8th floor",
    "addr:postcode":"10017",
    "addr:street":"East 42Nd Street",
    "iso:country":"US",
    "sg:address":"150 East 42nd Street 8th Floor",
    "sg:city":"New York",
    "sg:classifiers":[
        {
            "category":"Professional",
            "subcategory":"Computer Services",
            "type":"Services"
        }
    ],
    "sg:postcode":"10017",
    "sg:province":"NY",
    "sg:website":"http://www.intralinks.com",
    "wof:name":"IntraLinks",
    "wof:placetype":"venue"
},
  "geometry": {"coordinates":[-73.974842,40.750899],"type":"Point"}
}