{
  "type": "Feature",
  "properties": {
    "iso:country":"US",
    "sg:address":"683 Montauk Hwy",
    "sg:city":"Bayport",
    "sg:classifiers":[
        {
            "category":"Retail",
            "subcategory":"Funeral Services",
            "type":"Services"
        }
    ],
    "sg:phone":"+1 631 472 0122",
    "sg:postcode":"11705",
    "sg:province":"NY",
    "sg:tags":[
        "director"
    ],
    "wof:name":"Bayport-Blue Funeral Homes Inc",
    "wof:placetype":"venue"
},
  "geometry": {"coordinates":[-73.05451600000001,40.74684],"type":"Point"}
}