{
  "type": "Feature",
  "properties": {
    "iso:country":"US",
    "sg:address":"991 Lexington Ave",
    "sg:city":"New York",
    "sg:classifiers":[
        {
            "category":"Building & Trades",
            "subcategory":"Locksmith",
            "type":"Services"
        }
    ],
    "sg:phone":"+1 347 226 5922",
    "sg:postcode":"10021",
    "sg:province":"NY",
    "sg:tags":[
        "key"
    ],
    "wof:name":"LocksmithShop INC",
    "wof:placetype":"venue"
},
  "geometry": {"coordinates":[-73.96239799999999,40.770114],"type":"Point"}
}