{
  "type": "Feature",
  "properties": {
    "iso:country":"US",
    "sg:address":"2142A White Plains Road",
    "sg:city":"Bronx",
    "sg:classifiers":[
        {
            "category":"Personal",
            "subcategory":"Nail Salon",
            "type":"Services"
        }
    ],
    "sg:phone":"+1 718 518 1887",
    "sg:postcode":"10462",
    "sg:province":"NY",
    "wof:name":"New Wong Nail Supplies",
    "wof:placetype":"venue"
},
  "geometry": {"coordinates":[-73.867548,40.854724],"type":"Point"}
}