{
  "type": "Feature",
  "properties": {
    "iso:country":"US",
    "sg:address":"15 Swarthmore Ln",
    "sg:city":"Huntington Station",
    "sg:classifiers":[
        {
            "category":"Wholesale",
            "subcategory":"Apparel",
            "type":"Manufacturing & Wholesale Goods"
        }
    ],
    "sg:phone":"+1 631 499 0029",
    "sg:postcode":"11746",
    "sg:province":"NY",
    "sg:tags":[
        "piece"
    ],
    "wof:name":"Button Creations Inc",
    "wof:placetype":"venue"
},
  "geometry": {"coordinates":[-73.33059799999999,40.829169],"type":"Point"}
}