{
  "type": "Feature",
  "properties": {
    "addr:full":"6 Mallory Ave Staten Island NY 10305",
    "addr:housenumber":"6",
    "addr:postcode":"10305",
    "addr:street":"Mallory Ave",
    "iso:country":"US",
    "sg:address":"6 Mallory Ave",
    "sg:city":"Staten Island",
    "sg:classifiers":[
        {
            "category":"Arena",
            "subcategory":"Sports Club",
            "type":"Entertainment"
        }
    ],
    "sg:phone":"+1 718 981 3139",
    "sg:postcode":"10305",
    "sg:province":"NY",
    "sg:tags":[
        "martial art"
    ],
    "wof:name":"Traditional Karate Center",
    "wof:placetype":"venue"
},
  "geometry": {"coordinates":[-74.080803,40.598499],"type":"Point"}
}