{
  "type": "Feature",
  "properties": {
    "iso:country":"US",
    "sg:address":"2489 Elmwood Ave",
    "sg:city":"Kenmore",
    "sg:classifiers":[
        {
            "category":"Retail",
            "subcategory":"Car Wash",
            "type":"Services"
        },
        {
            "category":"Professional",
            "subcategory":"Business Services",
            "type":"Services"
        }
    ],
    "sg:phone":"+1 716 876 5563",
    "sg:postcode":"14217",
    "sg:province":"NY",
    "sg:tags":[
        "automobile",
        "detail",
        "clean"
    ],
    "wof:name":"Clean Machines Auto Detail",
    "wof:placetype":"venue"
},
  "geometry": {"coordinates":[-78.878666,42.964572],"type":"Point"}
}