{
  "type": "Feature",
  "properties": {
    "addr:full":"216 E 167th St Bronx NY 10456",
    "addr:housenumber":"216",
    "addr:postcode":"10456",
    "addr:street":"E 167Th St",
    "iso:country":"US",
    "sg:address":"216 E 167th St",
    "sg:city":"Bronx",
    "sg:classifiers":[
        {
            "category":"Shopping",
            "subcategory":"Stationery & Office Supplies",
            "type":"Retail Goods"
        },
        {
            "category":"Shopping",
            "subcategory":"Gifts & Souvenirs",
            "type":"Retail Goods"
        }
    ],
    "sg:phone":"+1 718 293 0349",
    "sg:postcode":"10456",
    "sg:province":"NY",
    "sg:tags":[
        "stationer"
    ],
    "wof:name":"Rainbow Stationery",
    "wof:placetype":"venue"
},
  "geometry": {"coordinates":[-73.916332,40.83398],"type":"Point"}
}