{
  "type": "Feature",
  "properties": {
    "iso:country":"US",
    "sg:address":"283 Washington Ave",
    "sg:city":"Albany",
    "sg:classifiers":[
        {
            "category":"Professional",
            "subcategory":"Lawyer & Legal Services",
            "type":"Services"
        }
    ],
    "sg:phone":"+1 518 463 2705",
    "sg:postcode":"12206",
    "sg:province":"NY",
    "sg:tags":[
        "attorney",
        "bureau"
    ],
    "sg:website":"www.servico.com",
    "wof:name":"Servico Inc",
    "wof:placetype":"venue"
},
  "geometry": {"coordinates":[-73.76786199999999,42.658877],"type":"Point"}
}