{
  "type": "Feature",
  "properties": {
    "addr:full":"2795 3rd Ave Bronx NY 10455",
    "addr:housenumber":"2795",
    "addr:postcode":"10455",
    "addr:street":"3Rd Ave",
    "iso:country":"US",
    "sg:address":"2795 3rd Ave",
    "sg:city":"Bronx",
    "sg:classifiers":[
        {
            "category":"Shopping",
            "subcategory":"Bicycles & Sporting Goods",
            "type":"Retail Goods"
        }
    ],
    "sg:phone":"+1 718 665 7075",
    "sg:postcode":"10455",
    "sg:province":"NY",
    "wof:name":"Eugene De Mayo & Sons Inc",
    "wof:placetype":"venue"
},
  "geometry": {"coordinates":[-73.91989,40.814882],"type":"Point"}
}