{
  "type": "Feature",
  "properties": {
    "addr:full":"101 Creekside Dr Painted Post NY 14870",
    "addr:housenumber":"101",
    "addr:postcode":"14870",
    "addr:street":"Creekside Dr",
    "iso:country":"US",
    "sg:address":"101 Creekside Dr",
    "sg:city":"Painted Post",
    "sg:classifiers":[
        {
            "category":"Health Services",
            "subcategory":"Nursing And Care Facility",
            "type":"Services"
        }
    ],
    "sg:phone":"+1 607 936 4108",
    "sg:postcode":"14870",
    "sg:province":"NY",
    "sg:tags":[
        "skilled"
    ],
    "wof:name":"Three Rivers Health Care Ctr",
    "wof:placetype":"venue"
},
  "geometry": {"coordinates":[-77.12304,42.14369],"type":"Point"}
}