{
  "type": "Feature",
  "properties": {
    "iso:country":"US",
    "sg:address":"196 Widmer Rd",
    "sg:city":"Wappingers Falls",
    "sg:classifiers":[
        {
            "category":"Professional",
            "type":"Services"
        }
    ],
    "sg:phone":"+1 845 297 7094",
    "sg:postcode":"12590",
    "sg:province":"NY",
    "sg:tags":[
        "establishment"
    ],
    "wof:name":"Sight & Sound Technologies",
    "wof:placetype":"venue"
},
  "geometry": {"coordinates":[-73.87962400000001,41.613462],"type":"Point"}
}