{
  "type": "Feature",
  "properties": {
    "iso:country":"US",
    "sg:address":"30 Keats Ave",
    "sg:city":"Hartsdale",
    "sg:classifiers":[
        {
            "category":"Banks & Credit Unions",
            "subcategory":"Bank",
            "type":"Services"
        }
    ],
    "sg:phone":"+1 914 761 5775",
    "sg:postcode":"10530",
    "sg:province":"NY",
    "sg:tags":[
        "federally",
        "chartered"
    ],
    "wof:name":"Yonkers Teachers Federal CU",
    "wof:placetype":"venue"
},
  "geometry": {"coordinates":[-73.816502,41.030741],"type":"Point"}
}