{
  "type": "Feature",
  "properties": {
    "iso:country":"US",
    "sg:address":"3247 Delaware Ave",
    "sg:city":"Buffalo",
    "sg:classifiers":[
        {
            "category":"Health Services",
            "subcategory":"Chiropractor",
            "type":"Services"
        }
    ],
    "sg:phone":"+1 716 875 5070",
    "sg:postcode":"14217",
    "sg:province":"NY",
    "wof:name":"Ken-Ton Chiropractic Office",
    "wof:placetype":"venue"
},
  "geometry": {"coordinates":[-78.871184,42.972585],"type":"Point"}
}