{
  "type": "Feature",
  "properties": {
    "addr:full":"43 Park Pl New York NY 10007",
    "addr:housenumber":"43",
    "addr:postcode":"10007",
    "addr:street":"Park Pl",
    "iso:country":"US",
    "sg:address":"43 Park Pl",
    "sg:city":"New York",
    "sg:classifiers":[
        {
            "category":"Professional",
            "subcategory":"Advertising",
            "type":"Services"
        }
    ],
    "sg:phone":"+1 212 608 0195",
    "sg:postcode":"10007",
    "sg:province":"NY",
    "sg:website":"www.donmcdonaldandsonsinc.com",
    "wof:name":"Don Mc Donald & Sons Inc",
    "wof:placetype":"venue"
},
  "geometry": {"coordinates":[-74.010065,40.713638],"type":"Point"}
}