{
  "type": "Feature",
  "properties": {
    "iso:country":"US",
    "sg:address":"169 County Highway 130",
    "sg:city":"Northville",
    "sg:classifiers":[
        {
            "category":"Restaurant",
            "type":"Food & Drink"
        }
    ],
    "sg:phone":"+1 518 863 7016",
    "sg:postcode":"12134",
    "sg:province":"NY",
    "sg:tags":[
        "american"
    ],
    "wof:name":"Roberts",
    "wof:placetype":"venue"
},
  "geometry": {"coordinates":[-74.191007,43.236572],"type":"Point"}
}