{
  "type": "Feature",
  "properties": {
    "iso:country":"US",
    "sg:address":"22 Argyle Sq",
    "sg:city":"Babylon",
    "sg:classifiers":[
        {
            "category":"Communications",
            "subcategory":"Film & Video Production",
            "type":"Services"
        }
    ],
    "sg:phone":"+1 631 422 6755",
    "sg:postcode":"11702",
    "sg:province":"NY",
    "sg:tags":[
        "motion",
        "picture",
        "editing",
        "tape"
    ],
    "wof:name":"Q Productions LLC",
    "wof:placetype":"venue"
},
  "geometry": {"coordinates":[-73.332223,40.6956],"type":"Point"}
}