{
  "type": "Feature",
  "properties": {
    "iso:country":"US",
    "sg:address":"105 Pleasant St",
    "sg:city":"Manlius",
    "sg:classifiers":[
        {
            "category":"Professional",
            "subcategory":"Detective & Security Services",
            "type":"Services"
        }
    ],
    "sg:phone":"+1 315 682 1160",
    "sg:postcode":"13104",
    "sg:province":"NY",
    "sg:tags":[
        "investigator"
    ],
    "wof:name":"Northeast Investigations Inc",
    "wof:placetype":"venue"
},
  "geometry": {"coordinates":[-75.978657,43.002965],"type":"Point"}
}