{
  "type": "Feature",
  "properties": {
    "iso:country":"US",
    "sg:address":"3 Corson Ave",
    "sg:city":"Staten Island",
    "sg:classifiers":[
        {
            "category":"Restaurant",
            "type":"Food & Drink"
        }
    ],
    "sg:phone":"+1 718 876 9870",
    "sg:postcode":"10301",
    "sg:province":"NY",
    "wof:name":"Lakruwana",
    "wof:placetype":"venue"
},
  "geometry": {"coordinates":[-74.07966999999999,40.638237],"type":"Point"}
}