{
  "type": "Feature",
  "properties": {
    "addr:full":"1170 Moll St North Tonawanda NY 14120",
    "addr:housenumber":"1170",
    "addr:postcode":"14120",
    "addr:street":"Moll St",
    "iso:country":"US",
    "sg:address":"1170 Moll St",
    "sg:city":"North Tonawanda",
    "sg:classifiers":[
        {
            "category":"Building & Trades",
            "subcategory":"Construction",
            "type":"Services"
        }
    ],
    "sg:phone":"+1 716 693 5729",
    "sg:postcode":"14120",
    "sg:province":"NY",
    "sg:tags":[
        "residential"
    ],
    "wof:name":"Thomas R Pieperdba",
    "wof:placetype":"venue"
},
  "geometry": {"coordinates":[-78.867204,43.055314],"type":"Point"}
}