{
  "type": "Feature",
  "properties": {
    "iso:country":"US",
    "sg:address":"9921 4th Avenue",
    "sg:city":"Brooklyn",
    "sg:classifiers":[
        {
            "category":"Health Services",
            "subcategory":"Doctor",
            "type":"Services"
        },
        {
            "category":"Personal",
            "subcategory":"Hair Removal",
            "type":"Services"
        },
        {
            "category":"Personal",
            "subcategory":"Skin Care",
            "type":"Services"
        }
    ],
    "sg:phone":"+1 718 833 7616",
    "sg:postcode":"11209",
    "sg:province":"NY",
    "sg:tags":[
        "dermatologist"
    ],
    "wof:name":"Biro Laszlo MD",
    "wof:placetype":"venue"
},
  "geometry": {"coordinates":[-74.03326,40.613286],"type":"Point"}
}