{
  "type": "Feature",
  "properties": {
    "addr:full":"1025 Boardwalk W Brooklyn NY 11224",
    "addr:housenumber":"1025",
    "addr:postcode":"11224",
    "addr:street":"Boardwalk W",
    "iso:country":"US",
    "sg:address":"1025 Boardwalk W",
    "sg:city":"Brooklyn",
    "sg:classifiers":[
        {
            "category":"Restaurant",
            "type":"Food & Drink"
        }
    ],
    "sg:phone":"+1 718 372 2925",
    "sg:postcode":"11224",
    "sg:province":"NY",
    "wof:name":"Boardwalk Foods",
    "wof:placetype":"venue"
},
  "geometry": {"coordinates":[-73.978602,40.573168],"type":"Point"}
}