{
  "type": "Feature",
  "properties": {
    "addr:full":"475 5th Ave New York NY 10017",
    "addr:housenumber":"475",
    "addr:postcode":"10017",
    "addr:street":"5Th Ave",
    "iso:country":"US",
    "sg:address":"475 5th Ave",
    "sg:city":"New York",
    "sg:classifiers":[
        {
            "category":"Professional",
            "subcategory":"Management & Consulting",
            "type":"Services"
        }
    ],
    "sg:phone":"+1 212 447 7857",
    "sg:postcode":"10017",
    "sg:province":"NY",
    "sg:tags":[
        "promotion",
        "public",
        "relations",
        "sales"
    ],
    "sg:website":"www.maximumimpact.net",
    "wof:name":"Maximum Impact Inc",
    "wof:placetype":"venue"
},
  "geometry": {"coordinates":[-73.98143899999999,40.752537],"type":"Point"}
}