{
  "type": "Feature",
  "properties": {
    "addr:full":"226 E Jericho Tpke Mineola NY 11501",
    "addr:housenumber":"226",
    "addr:postcode":"11501",
    "addr:street":"E Jericho Tpke",
    "iso:country":"US",
    "sg:address":"226 E Jericho Tpke",
    "sg:city":"Mineola",
    "sg:classifiers":[
        {
            "category":"Building & Trades",
            "subcategory":"Construction",
            "type":"Services"
        }
    ],
    "sg:phone":"+1 516 742 1023",
    "sg:postcode":"11501",
    "sg:province":"NY",
    "sg:tags":[
        "contractor"
    ],
    "wof:name":"Papasidero Marble & Tile Corp",
    "wof:placetype":"venue"
},
  "geometry": {"coordinates":[-73.62864500000001,40.753324],"type":"Point"}
}