{
  "type": "Feature",
  "properties": {
    "iso:country":"US",
    "sg:address":"401 W 207th St",
    "sg:city":"New York",
    "sg:classifiers":[
        {
            "category":"Professional",
            "type":"Services"
        }
    ],
    "sg:phone":"+1 212 544 8786",
    "sg:postcode":"10034",
    "sg:province":"NY",
    "sg:tags":[
        "establishment"
    ],
    "wof:name":"Merrit Inward Inc",
    "wof:placetype":"venue"
},
  "geometry": {"coordinates":[-73.918943,40.864463],"type":"Point"}
}