{
  "type": "Feature",
  "properties": {
    "addr:full":"705 Forest Ave Staten Island NY 10310",
    "addr:housenumber":"705",
    "addr:postcode":"10310",
    "addr:street":"Forest Ave",
    "iso:country":"US",
    "sg:address":"705 Forest Ave",
    "sg:city":"Staten Island",
    "sg:classifiers":[
        {
            "category":"Restaurant",
            "type":"Food & Drink"
        }
    ],
    "sg:phone":"+1   ",
    "sg:postcode":"10310",
    "sg:province":"NY",
    "sg:tags":[
        "grocery",
        "eating"
    ],
    "wof:name":"Stanziones Bakery",
    "wof:placetype":"venue"
},
  "geometry": {"coordinates":[-74.112347,40.629611],"type":"Point"}
}