{
  "type": "Feature",
  "properties": {
    "addr:full":"1728 Stein Dr Bay Shore NY 11706",
    "addr:housenumber":"1728",
    "addr:postcode":"11706",
    "addr:street":"Stein Dr",
    "iso:country":"US",
    "sg:address":"1728 Stein Dr",
    "sg:city":"Bay Shore",
    "sg:classifiers":[
        {
            "category":"Organizations",
            "subcategory":"Religious Organization",
            "type":"Services"
        }
    ],
    "sg:phone":"+1 631 273 2707",
    "sg:postcode":"11706",
    "sg:province":"NY",
    "sg:tags":[
        "clergy"
    ],
    "wof:name":"Richard M Logan",
    "wof:placetype":"venue"
},
  "geometry": {"coordinates":[-73.257932,40.767524],"type":"Point"}
}