{
  "type": "Feature",
  "properties": {
    "addr:full":"200 W 57th St Ste 508 New York NY 10019",
    "addr:housenumber":"200;508",
    "addr:postcode":"10019",
    "addr:street":"W 57Th St Ste",
    "iso:country":"US",
    "sg:address":"200 W 57th St Ste 508",
    "sg:city":"New York",
    "sg:classifiers":[
        {
            "category":"Health Services",
            "subcategory":"Doctor",
            "type":"Services"
        }
    ],
    "sg:phone":"+1 212 581 1866",
    "sg:postcode":"10019",
    "sg:province":"NY",
    "sg:tags":[
        "dermatologist"
    ],
    "wof:name":"Samer Jaber, MD",
    "wof:placetype":"venue"
},
  "geometry": {"coordinates":[-73.98009999999999,40.765539],"type":"Point"}
}