{
  "type": "Feature",
  "properties": {
    "iso:country":"US",
    "sg:address":"108 Bridge St",
    "sg:city":"Corning",
    "sg:classifiers":[
        {
            "category":"Restaurant",
            "type":"Food & Drink"
        }
    ],
    "sg:phone":"+1   ",
    "sg:postcode":"14830",
    "sg:province":"NY",
    "wof:name":"Pizza Factory",
    "wof:placetype":"venue"
},
  "geometry": {"coordinates":[-77.060783,42.151501],"type":"Point"}
}