{
  "type": "Feature",
  "properties": {
    "iso:country":"US",
    "sg:address":"611 Warren St",
    "sg:city":"Hudson",
    "sg:classifiers":[
        {
            "category":"Professional",
            "subcategory":"Art Services",
            "type":"Services"
        }
    ],
    "sg:phone":"+1 518 671 6352",
    "sg:postcode":"12534",
    "sg:province":"NY",
    "sg:tags":[
        "photographer",
        "photography",
        "store"
    ],
    "wof:name":"Hudson Photographic Center",
    "wof:placetype":"venue"
},
  "geometry": {"coordinates":[-73.784305,42.247557],"type":"Point"}
}