{
  "type": "Feature",
  "properties": {
    "iso:country":"US",
    "sg:address":"39 S Church St",
    "sg:city":"Bedford Hills",
    "sg:classifiers":[
        {
            "category":"Building & Trades",
            "subcategory":"Landscaping Services",
            "type":"Services"
        }
    ],
    "sg:phone":"+1 914 241 2230",
    "sg:postcode":"10507",
    "sg:province":"NY",
    "wof:name":"Carozza Pasquale",
    "wof:placetype":"venue"
},
  "geometry": {"coordinates":[-73.702602,41.232327],"type":"Point"}
}