{
  "type": "Feature",
  "properties": {
    "iso:country":"US",
    "sg:address":"174 Rockaway Ave",
    "sg:city":"Valley Stream",
    "sg:classifiers":[
        {
            "category":"Food & Beverages",
            "subcategory":"Bakery",
            "type":"Retail Goods"
        }
    ],
    "sg:phone":"+1 516 568 0075",
    "sg:postcode":"11580",
    "sg:province":"NY",
    "sg:tags":[
        "baker"
    ],
    "wof:name":"San Antonio Bakery",
    "wof:placetype":"venue"
},
  "geometry": {"coordinates":[-73.699518,40.661824],"type":"Point"}
}