{
  "type": "Feature",
  "properties": {
    "addr:full":"275 Church St Manhattan NY 10013",
    "addr:housenumber":"275",
    "addr:postcode":"10013",
    "addr:street":"Church St",
    "iso:country":"US",
    "sg:address":"275 Church St",
    "sg:city":"Manhattan",
    "sg:classifiers":[
        {
            "category":"Restaurant",
            "type":"Food & Drink"
        }
    ],
    "sg:phone":"+1 212 925 8800",
    "sg:postcode":"10013",
    "sg:province":"NY",
    "sg:tags":[
        "italian"
    ],
    "wof:name":"daMikele",
    "wof:placetype":"venue"
},
  "geometry": {"coordinates":[-74.004802,40.718477],"type":"Point"}
}