{
  "type": "Feature",
  "properties": {
    "iso:country":"US",
    "sg:address":"1650 Webster Ave",
    "sg:city":"Bronx",
    "sg:classifiers":[
        {
            "category":"Retail",
            "subcategory":"Auto Repair",
            "type":"Services"
        }
    ],
    "sg:phone":"+1 718 299 4169",
    "sg:postcode":"10457",
    "sg:province":"NY",
    "sg:tags":[
        "body",
        "shop"
    ],
    "wof:name":"Branks Auto Body Inc",
    "wof:placetype":"venue"
},
  "geometry": {"coordinates":[-73.90389999999999,40.842201],"type":"Point"}
}