{
  "type": "Feature",
  "properties": {
    "addr:full":"144 Mills St Buffalo NY 14211",
    "addr:housenumber":"144",
    "addr:postcode":"14211",
    "addr:street":"Mills St",
    "iso:country":"US",
    "sg:address":"144 Mills St",
    "sg:city":"Buffalo",
    "sg:classifiers":[
        {
            "category":"Social Services",
            "subcategory":"Adult Care",
            "type":"Services"
        }
    ],
    "sg:phone":"+1   ",
    "sg:postcode":"14211",
    "sg:province":"NY",
    "sg:tags":[
        "residential"
    ],
    "wof:name":"Paradise House",
    "wof:placetype":"venue"
},
  "geometry": {"coordinates":[-78.836697,42.898016],"type":"Point"}
}