{
  "type": "Feature",
  "properties": {
    "addr:full":"31 Walgrove Ave Dobbs Ferry NY 10522",
    "addr:housenumber":"31",
    "addr:postcode":"10522",
    "addr:street":"Walgrove Ave",
    "iso:country":"US",
    "sg:address":"31 Walgrove Ave",
    "sg:city":"Dobbs Ferry",
    "sg:classifiers":[
        {
            "category":"Professional",
            "subcategory":"Management & Consulting",
            "type":"Services"
        }
    ],
    "sg:phone":"+1 914 693 7010",
    "sg:postcode":"10522",
    "sg:province":"NY",
    "sg:tags":[
        "business"
    ],
    "wof:name":"Doss Consultants",
    "wof:placetype":"venue"
},
  "geometry": {"coordinates":[-73.868959,41.015408],"type":"Point"}
}