{
  "type": "Feature",
  "properties": {
    "addr:full":"12732 Willets Point Blvd Corona NY 11368",
    "addr:housenumber":"12732",
    "addr:postcode":"11368",
    "addr:street":"Willets Point Blvd",
    "iso:country":"US",
    "sg:address":"12732 Willets Point Blvd",
    "sg:city":"Corona",
    "sg:classifiers":[
        {
            "category":"Retail",
            "subcategory":"Auto Repair",
            "type":"Services"
        }
    ],
    "sg:phone":"+1 718 457 5399",
    "sg:postcode":"11368",
    "sg:province":"NY",
    "sg:tags":[
        "body",
        "shop"
    ],
    "wof:name":"Altamirano Samuel",
    "wof:placetype":"venue"
},
  "geometry": {"coordinates":[-73.841499,40.758801],"type":"Point"}
}