{
  "type": "Feature",
  "properties": {
    "iso:country":"US",
    "sg:address":"6 Rosewood Ct",
    "sg:city":"East Setauket",
    "sg:classifiers":[
        {
            "category":"Building & Trades",
            "subcategory":"Construction",
            "type":"Services"
        }
    ],
    "sg:phone":"+1 631 689 8926",
    "sg:postcode":"11733",
    "sg:province":"NY",
    "sg:tags":[
        "carpentry",
        "contractor"
    ],
    "wof:name":"Jjge Services Inc",
    "wof:placetype":"venue"
},
  "geometry": {"coordinates":[-73.08984599999999,40.922797],"type":"Point"}
}