{
  "type": "Feature",
  "properties": {
    "iso:country":"US",
    "sg:address":"1850 Clinton St",
    "sg:city":"Buffalo",
    "sg:classifiers":[
        {
            "category":"Shopping",
            "subcategory":"Jewelry",
            "type":"Retail Goods"
        }
    ],
    "sg:phone":"+1 716 827 0770",
    "sg:postcode":"14206",
    "sg:province":"NY",
    "wof:name":"Papke Jewelers",
    "wof:placetype":"venue"
},
  "geometry": {"coordinates":[-78.807999,42.871799],"type":"Point"}
}