{
  "type": "Feature",
  "properties": {
    "iso:country":"US",
    "sg:address":"202 Midland Ave",
    "sg:city":"Tuckahoe",
    "sg:classifiers":[
        {
            "category":"Wholesale",
            "subcategory":"Vending Machines",
            "type":"Manufacturing & Wholesale Goods"
        }
    ],
    "sg:phone":"+1   ",
    "sg:postcode":"10707",
    "sg:province":"NY",
    "sg:tags":[
        "operator"
    ],
    "wof:name":"C R S Enterprises",
    "wof:placetype":"venue"
},
  "geometry": {"coordinates":[-73.822283,40.947741],"type":"Point"}
}