{
  "type": "Feature",
  "properties": {
    "iso:country":"US",
    "name:eng_x_preferred":[
        "Crescent St"
    ],
    "wof:name":"Crescent St Station",
    "wof:placetype":"venue"
},
  "geometry": {"coordinates":[-73.873785,40.683194],"type":"Point"}
}