{
  "type": "Feature",
  "properties": {
    "iso:country":"US",
    "sg:address":"22 Cottage St",
    "sg:city":"Potsdam",
    "sg:classifiers":[
        {
            "category":"Local Transit",
            "type":"Transportation"
        }
    ],
    "sg:phone":"+1 315 265 2121",
    "sg:postcode":"13676",
    "sg:province":"NY",
    "sg:tags":[
        "ambulance"
    ],
    "wof:name":"Potsdam Rescue Squad Ambulance",
    "wof:placetype":"venue"
},
  "geometry": {"coordinates":[-74.982686,44.67616],"type":"Point"}
}