{
  "type": "Feature",
  "properties": {
    "addr:full":"53 E 66 St New York NY 10065",
    "addr:housenumber":"53;66",
    "addr:postcode":"10065",
    "addr:street":"E;St",
    "iso:country":"US",
    "sg:address":"53 E 66 St",
    "sg:city":"New York",
    "sg:classifiers":[
        {
            "category":"Professional",
            "type":"Services"
        }
    ],
    "sg:phone":"+1 212 570 0918",
    "sg:postcode":"10065",
    "sg:province":"NY",
    "sg:tags":[
        "establishment"
    ],
    "wof:name":"Lauriston Inc",
    "wof:placetype":"venue"
},
  "geometry": {"coordinates":[-73.968215,40.767967],"type":"Point"}
}