{
  "type": "Feature",
  "properties": {
    "addr:full":"26 Brewster Woods Dr Brewster NY 10509",
    "addr:housenumber":"26",
    "addr:postcode":"10509",
    "addr:street":"Brewster Woods Dr",
    "iso:country":"US",
    "sg:address":"26 Brewster Woods Dr",
    "sg:city":"Brewster",
    "sg:classifiers":[
        {
            "category":"Travel",
            "subcategory":"Travel Agent",
            "type":"Entertainment"
        }
    ],
    "sg:phone":"+1   ",
    "sg:postcode":"10509",
    "sg:province":"NY",
    "sg:tags":[
        "agency"
    ],
    "wof:name":"Simplicity Travel Inc",
    "wof:placetype":"venue"
},
  "geometry": {"coordinates":[-73.57697,41.417329],"type":"Point"}
}