{
  "type": "Feature",
  "properties": {
    "iso:country":"US",
    "sg:address":"10641 Main St",
    "sg:city":"Clarence",
    "sg:classifiers":[
        {
            "category":"Food & Beverages",
            "subcategory":"Groceries & Convenience Stores",
            "type":"Retail Goods"
        }
    ],
    "sg:phone":"+1   ",
    "sg:postcode":"14031",
    "sg:province":"NY",
    "wof:name":"Clarence Deli",
    "wof:placetype":"venue"
},
  "geometry": {"coordinates":[-78.59157,42.980578],"type":"Point"}
}