{
  "type": "Feature",
  "properties": {
    "addr:full":"31 Main St East Rockaway NY 11518",
    "addr:housenumber":"31",
    "addr:postcode":"11518",
    "addr:street":"Main St East",
    "iso:country":"US",
    "sg:address":"31 Main St",
    "sg:city":"East Rockaway",
    "sg:classifiers":[
        {
            "category":"Shopping",
            "subcategory":"Used Merchandise",
            "type":"Retail Goods"
        }
    ],
    "sg:phone":"+1 516 593 2338",
    "sg:postcode":"11518",
    "sg:province":"NY",
    "sg:tags":[
        "shop",
        "thrift"
    ],
    "wof:name":"Carmela Thrift Fair",
    "wof:placetype":"venue"
},
  "geometry": {"coordinates":[-73.66127,40.639738],"type":"Point"}
}