{
  "type": "Feature",
  "properties": {
    "iso:country":"US",
    "sg:address":"250 S Clinton St",
    "sg:city":"Syracuse",
    "sg:classifiers":[
        {
            "category":"Manufacturing",
            "subcategory":"Petroleum Products",
            "type":"Manufacturing & Wholesale Goods"
        }
    ],
    "sg:phone":"+1   ",
    "sg:postcode":"13202",
    "sg:province":"NY",
    "sg:tags":[
        "company",
        "holding"
    ],
    "wof:name":"Carlisle Syntec Systems (div)",
    "wof:placetype":"venue"
},
  "geometry": {"coordinates":[-76.153638,43.049156],"type":"Point"}
}