{
  "type": "Feature",
  "properties": {
    "addr:full":"234 Court St Brooklyn NY 11201",
    "addr:housenumber":"234",
    "addr:postcode":"11201",
    "addr:street":"Court St",
    "iso:country":"US",
    "sg:address":"234 Court St",
    "sg:city":"Brooklyn",
    "sg:classifiers":[
        {
            "category":"Restaurant",
            "type":"Food & Drink"
        },
        {
            "category":"Food & Beverages",
            "subcategory":"Groceries & Convenience Stores",
            "type":"Retail Goods"
        }
    ],
    "sg:phone":"+1 347 987 4961",
    "sg:postcode":"11201",
    "sg:province":"NY",
    "sg:tags":[
        "italian"
    ],
    "sg:website":"www.brucienyc.com/",
    "wof:name":"Brucie",
    "wof:placetype":"venue"
},
  "geometry": {"coordinates":[-73.994432,40.686031],"type":"Point"}
}