{
  "type": "Feature",
  "properties": {
    "addr:full":"101 W 69 St New York NY 10023",
    "addr:housenumber":"101",
    "addr:postcode":"10023",
    "addr:street":"W 69 St",
    "iso:country":"US",
    "sg:address":"101 W 69 St",
    "sg:city":"New York",
    "sg:classifiers":[
        {
            "category":"Wholesale",
            "subcategory":"Apparel",
            "type":"Manufacturing & Wholesale Goods"
        }
    ],
    "sg:phone":"+1 646 325 7172",
    "sg:postcode":"10023",
    "sg:province":"NY",
    "sg:tags":[
        "clothing"
    ],
    "wof:name":"Jesarae",
    "wof:placetype":"venue"
},
  "geometry": {"coordinates":[-73.98213699999999,40.776297],"type":"Point"}
}