{
  "type": "Feature",
  "properties": {
    "addr:full":"10 Mayflower Ln Holtsville NY 11742",
    "addr:housenumber":"10",
    "addr:postcode":"11742",
    "addr:street":"Mayflower Ln",
    "iso:country":"US",
    "sg:address":"10 Mayflower Ln",
    "sg:city":"Holtsville",
    "sg:classifiers":[
        {
            "category":"Local Transit",
            "type":"Transportation"
        }
    ],
    "sg:phone":"+1 631 929 8888",
    "sg:postcode":"11742",
    "sg:province":"NY",
    "sg:tags":[
        "limousine"
    ],
    "wof:name":"Serenity Limousine Svc Inc",
    "wof:placetype":"venue"
},
  "geometry": {"coordinates":[-73.028156,40.809379],"type":"Point"}
}