{
  "type": "Feature",
  "properties": {
    "iso:country":"US",
    "sg:address":"176 N Village Ave Ste 2F",
    "sg:city":"Rockville Centre",
    "sg:classifiers":[
        {
            "category":"Health Services",
            "subcategory":"Dentist",
            "type":"Services"
        }
    ],
    "sg:phone":"+1 516 594 3300",
    "sg:postcode":"11570",
    "sg:province":"NY",
    "wof:name":"Winning Smile",
    "wof:placetype":"venue"
},
  "geometry": {"coordinates":[-73.64862100000001,40.662433],"type":"Point"}
}