{
  "type": "Feature",
  "properties": {
    "addr:full":"6 British American Blvd Latham NY 12110",
    "addr:housenumber":"6",
    "addr:postcode":"12110",
    "addr:street":"British American Blvd",
    "iso:country":"US",
    "sg:address":"6 British American Blvd",
    "sg:city":"Latham",
    "sg:classifiers":[
        {
            "category":"Manufacturing",
            "subcategory":"Tools & Machinery",
            "type":"Manufacturing & Wholesale Goods"
        }
    ],
    "sg:phone":"+1   ",
    "sg:postcode":"12110",
    "sg:province":"NY",
    "sg:tags":[
        "instrument",
        "mfg"
    ],
    "wof:name":"North American Medical Pdts",
    "wof:placetype":"venue"
},
  "geometry": {"coordinates":[-73.814488,42.758536],"type":"Point"}
}