{
  "type": "Feature",
  "properties": {
    "addr:full":"4818 Northern Blvd Long Island City NY 11101",
    "addr:housenumber":"4818",
    "addr:postcode":"11101",
    "addr:street":"Northern Blvd",
    "iso:country":"US",
    "sg:address":"4818 Northern Blvd",
    "sg:city":"Long Island City",
    "sg:classifiers":[
        {
            "category":"Shopping",
            "subcategory":"Department Store",
            "type":"Retail Goods"
        }
    ],
    "sg:phone":"+1 718 626 4700",
    "sg:postcode":"11101",
    "sg:province":"NY",
    "wof:name":"Marshalls",
    "wof:placetype":"venue"
},
  "geometry": {"coordinates":[-73.914597,40.753601],"type":"Point"}
}