{
  "type": "Feature",
  "properties": {
    "addr:full":"2206 Valentine Avenue Bronx NY 10457",
    "addr:housenumber":"2206",
    "addr:postcode":"10457",
    "addr:street":"Valentine Avenue",
    "iso:country":"US",
    "sg:address":"2206 Valentine Avenue",
    "sg:city":"Bronx",
    "sg:classifiers":[
        {
            "category":"Building & Trades",
            "subcategory":"Construction",
            "type":"Services"
        }
    ],
    "sg:phone":"+1 718 547 9236",
    "sg:postcode":"10457",
    "sg:province":"NY",
    "sg:tags":[
        "contractor"
    ],
    "wof:name":"Prestige Contrctng Company",
    "wof:placetype":"venue"
},
  "geometry": {"coordinates":[-73.898853,40.855141],"type":"Point"}
}