{
  "type": "Feature",
  "properties": {
    "iso:country":"US",
    "sg:address":"106 W South St",
    "sg:city":"Groton",
    "sg:classifiers":[
        {
            "category":"Personal",
            "subcategory":"Beauty Salon",
            "type":"Services"
        }
    ],
    "sg:phone":"+1 607 898 4748",
    "sg:postcode":"13073",
    "sg:province":"NY",
    "wof:name":"Kandi's Hair Nail & Tanning",
    "wof:placetype":"venue"
},
  "geometry": {"coordinates":[-76.366983,42.584877],"type":"Point"}
}