{
  "type": "Feature",
  "properties": {
    "addr:full":"87 Rolling Brook Dr Clifton Park NY 12065",
    "addr:housenumber":"87",
    "addr:postcode":"12065",
    "addr:street":"Rolling Brook Dr",
    "iso:country":"US",
    "sg:address":"87 Rolling Brook Dr",
    "sg:city":"Clifton Park",
    "sg:classifiers":[
        {
            "category":"Government",
            "subcategory":"Office",
            "type":"Public Place"
        }
    ],
    "sg:phone":"+1 518 457 7438",
    "sg:postcode":"12065",
    "sg:province":"NY",
    "sg:tags":[
        "transportation"
    ],
    "wof:name":"City of New York",
    "wof:placetype":"venue"
},
  "geometry": {"coordinates":[-73.78065700000001,42.875293],"type":"Point"}
}