{
  "type": "Feature",
  "properties": {
    "addr:full":"29 Agar St Yonkers NY 10701",
    "addr:housenumber":"29",
    "addr:postcode":"10701",
    "addr:street":"Agar St",
    "iso:country":"US",
    "sg:address":"29 Agar St",
    "sg:city":"Yonkers",
    "sg:classifiers":[
        {
            "category":"Autos & Motor Vehicles",
            "subcategory":"Boat Sales",
            "type":"Retail Goods"
        }
    ],
    "sg:phone":"+1 914 968 7000",
    "sg:postcode":"10701",
    "sg:province":"NY",
    "sg:tags":[
        "dealer",
        "sales"
    ],
    "wof:name":"Abruzese Yacht LLC",
    "wof:placetype":"venue"
},
  "geometry": {"coordinates":[-73.875057,40.949003],"type":"Point"}
}