{
  "type": "Feature",
  "properties": {
    "iso:country":"US",
    "sg:address":"682 Willis Ave",
    "sg:city":"Williston Park",
    "sg:classifiers":[
        {
            "category":"Wholesale",
            "subcategory":"Non-durable Goods",
            "type":"Manufacturing & Wholesale Goods"
        }
    ],
    "sg:phone":"+1 516 741 6057",
    "sg:postcode":"11596",
    "sg:province":"NY",
    "sg:tags":[
        "advertising",
        "specialty"
    ],
    "wof:name":"Atlas Promotional Items Inc",
    "wof:placetype":"venue"
},
  "geometry": {"coordinates":[-73.64658900000001,40.763295],"type":"Point"}
}