{
  "type": "Feature",
  "properties": {
    "addr:full":"5 Hodges Pl Staten Island NY 10314",
    "addr:housenumber":"5",
    "addr:postcode":"10314",
    "addr:street":"Hodges Pl",
    "iso:country":"US",
    "sg:address":"5 Hodges Pl",
    "sg:city":"Staten Island",
    "sg:classifiers":[
        {
            "category":"Personal",
            "subcategory":"Beauty Salon",
            "type":"Services"
        }
    ],
    "sg:phone":"+1 718 447 1650",
    "sg:postcode":"10314",
    "sg:province":"NY",
    "wof:name":"Mr Bert Hair Stylist",
    "wof:placetype":"venue"
},
  "geometry": {"coordinates":[-74.11955,40.614773],"type":"Point"}
}