{
  "type": "Feature",
  "properties": {
    "addr:full":"127 John St New York NY 10038",
    "addr:housenumber":"127",
    "addr:postcode":"10038",
    "addr:street":"John St",
    "iso:country":"US",
    "sg:address":"127 John St",
    "sg:city":"New York",
    "sg:classifiers":[
        {
            "category":"Insurance",
            "subcategory":"Insurance Agent",
            "type":"Services"
        }
    ],
    "sg:phone":"+1 212 363 5151",
    "sg:postcode":"10038",
    "sg:province":"NY",
    "wof:name":"CNA Insurance",
    "wof:placetype":"venue"
},
  "geometry": {"coordinates":[-74.005032,40.707028],"type":"Point"}
}