{
  "type": "Feature",
  "properties": {
    "addr:full":"2611 Middle Country Rd Centereach NY 11720",
    "addr:housenumber":"2611",
    "addr:postcode":"11720",
    "addr:street":"Middle Country Rd",
    "iso:country":"US",
    "sg:address":"2611 Middle Country Rd",
    "sg:city":"Centereach",
    "sg:classifiers":[
        {
            "category":"Home & Garden",
            "subcategory":"Carpets & Floor Coverings",
            "type":"Retail Goods"
        }
    ],
    "sg:phone":"+1 631 737 0638",
    "sg:postcode":"11720",
    "sg:province":"NY",
    "sg:tags":[
        "installs",
        "custom",
        "fabrication",
        "carpeting",
        "rug"
    ],
    "wof:name":"Carpet Your World",
    "wof:placetype":"venue"
},
  "geometry": {"coordinates":[-73.105001,40.858505],"type":"Point"}
}