{
  "type": "Feature",
  "properties": {
    "iso:country":"US",
    "sg:address":"6 Timber Ln",
    "sg:city":"Glenmont",
    "sg:classifiers":[
        {
            "category":"Professional",
            "subcategory":"Management & Consulting",
            "type":"Services"
        }
    ],
    "sg:phone":"+1 518 465 0752",
    "sg:postcode":"12077",
    "sg:province":"NY",
    "sg:tags":[
        "consultant",
        "medical",
        "legal"
    ],
    "wof:name":"Patricia K Gorman",
    "wof:placetype":"venue"
},
  "geometry": {"coordinates":[-73.79576299999999,42.604877],"type":"Point"}
}