{
  "type": "Feature",
  "properties": {
    "iso:country":"US",
    "sg:address":"1343 Long Pond Rd",
    "sg:city":"Rochester",
    "sg:classifiers":[
        {
            "category":"Insurance",
            "subcategory":"Insurance Agent",
            "type":"Services"
        }
    ],
    "sg:phone":"+1 585 227 7500",
    "sg:postcode":"14626",
    "sg:province":"NY",
    "sg:tags":[
        "agency",
        "general"
    ],
    "wof:name":"Lawrence Associates Agency",
    "wof:placetype":"venue"
},
  "geometry": {"coordinates":[-77.697191,43.203873],"type":"Point"}
}