{
  "type": "Feature",
  "properties": {
    "addr:full":"1600 Central Ave Far Rockaway NY 11691",
    "addr:housenumber":"1600",
    "addr:postcode":"11691",
    "addr:street":"Central Ave",
    "iso:country":"US",
    "sg:address":"1600 Central Ave",
    "sg:city":"Far Rockaway",
    "sg:classifiers":[
        {
            "category":"Professional",
            "subcategory":"Lawyer & Legal Services",
            "type":"Services"
        }
    ],
    "sg:phone":"+1 516 766 3505",
    "sg:postcode":"11691",
    "sg:province":"NY",
    "wof:name":"Branitsky Herbert Atty",
    "wof:placetype":"venue"
},
  "geometry": {"coordinates":[-73.751999,40.605301],"type":"Point"}
}