{
  "type": "Feature",
  "properties": {
    "iso:country":"US",
    "sg:address":"33 Myers Rd",
    "sg:city":"Lansing",
    "sg:classifiers":[
        {
            "category":"Social Services",
            "type":"Services"
        }
    ],
    "sg:phone":"+1 607 533 7143",
    "sg:postcode":"14882",
    "sg:province":"NY",
    "sg:tags":[
        "counselor",
        "marriage",
        "family"
    ],
    "wof:name":"Isaac Depth Psycholotherapist",
    "wof:placetype":"venue"
},
  "geometry": {"coordinates":[-76.539056,42.540069],"type":"Point"}
}