{
  "type": "Feature",
  "properties": {
    "addr:full":"832 E 166th Street Bronx NY 10459",
    "addr:housenumber":"832",
    "addr:postcode":"10459",
    "addr:street":"E 166Th Street",
    "iso:country":"US",
    "sg:address":"832 E 166th Street",
    "sg:city":"Bronx",
    "sg:classifiers":[
        {
            "category":"Communications",
            "subcategory":"Radio Station",
            "type":"Services"
        }
    ],
    "sg:phone":"+1 718 893 5881",
    "sg:postcode":"10459",
    "sg:province":"NY",
    "wof:name":"Radio Jesus",
    "wof:placetype":"venue"
},
  "geometry": {"coordinates":[-73.898983,40.825527],"type":"Point"}
}