{
  "type": "Feature",
  "properties": {
    "iso:country":"US",
    "sg:address":"17 Croft Ct",
    "sg:city":"Staten Island",
    "sg:classifiers":[
        {
            "category":"Real Estate",
            "subcategory":"Real Estate Agent",
            "type":"Services"
        }
    ],
    "sg:phone":"+1 718 987 4662",
    "sg:postcode":"10306",
    "sg:province":"NY",
    "wof:name":"E&V Realty LLC",
    "wof:placetype":"venue"
},
  "geometry": {"coordinates":[-74.13971100000001,40.562517],"type":"Point"}
}