{
  "type": "Feature",
  "properties": {
    "iso:country":"US",
    "sg:address":"606 N French Rd",
    "sg:city":"Buffalo",
    "sg:classifiers":[
        {
            "category":"Professional",
            "subcategory":"Engineering",
            "type":"Services"
        }
    ],
    "sg:phone":"+1 716 691 8600",
    "sg:postcode":"14228",
    "sg:province":"NY",
    "sg:tags":[
        "electrical",
        "mechanical"
    ],
    "wof:name":"North Star Group",
    "wof:placetype":"venue"
},
  "geometry": {"coordinates":[-78.799643,43.034763],"type":"Point"}
}