{
  "type": "Feature",
  "properties": {
    "addr:full":"720 Bedford Rd Bedford Hills NY 10507",
    "addr:housenumber":"720",
    "addr:postcode":"10507",
    "addr:street":"Bedford Rd",
    "iso:country":"US",
    "sg:address":"720 Bedford Rd",
    "sg:city":"Bedford Hills",
    "sg:classifiers":[
        {
            "category":"Shopping",
            "subcategory":"Mobile Phones",
            "type":"Retail Goods"
        }
    ],
    "sg:phone":"+1 914 241 0690",
    "sg:postcode":"10507",
    "sg:province":"NY",
    "wof:name":"Radioshack",
    "wof:placetype":"venue"
},
  "geometry": {"coordinates":[-73.71379899999999,41.2253],"type":"Point"}
}