{
  "type": "Feature",
  "properties": {
    "addr:full":"1326 Portage Rd Niagara Falls NY 14301",
    "addr:housenumber":"1326",
    "addr:postcode":"14301",
    "addr:street":"Portage Rd",
    "iso:country":"US",
    "sg:address":"1326 Portage Rd",
    "sg:city":"Niagara Falls",
    "sg:classifiers":[
        {
            "category":"Personal",
            "subcategory":"Beauty Salon",
            "type":"Services"
        }
    ],
    "sg:phone":"+1 716 285 4909",
    "sg:postcode":"14301",
    "sg:province":"NY",
    "wof:name":"Nelson's Hair Studio",
    "wof:placetype":"venue"
},
  "geometry": {"coordinates":[-79.051937,43.101764],"type":"Point"}
}