{
  "type": "Feature",
  "properties": {
    "iso:country":"US",
    "sg:address":"7812 Hunts Hollow Village",
    "sg:city":"Naples",
    "sg:classifiers":[
        {
            "category":"Manufacturing",
            "subcategory":"Lumber",
            "type":"Manufacturing & Wholesale Goods"
        }
    ],
    "sg:phone":"+1 585 374 2799",
    "sg:postcode":"14512",
    "sg:province":"NY",
    "sg:tags":[
        "company",
        "logging"
    ],
    "wof:name":"Future Forest Consulting Inc",
    "wof:placetype":"venue"
},
  "geometry": {"coordinates":[-77.481208,42.646182],"type":"Point"}
}