{
  "type": "Feature",
  "properties": {
    "iso:country":"US",
    "sg:address":"2131 46th Ave",
    "sg:city":"Long Island City",
    "sg:classifiers":[
        {
            "category":"Banks & Credit Unions",
            "subcategory":"Bank",
            "type":"Services"
        }
    ],
    "sg:phone":"+1 718 361 9800",
    "sg:postcode":"11101",
    "sg:province":"NY",
    "wof:name":"State Bank of L I",
    "wof:placetype":"venue"
},
  "geometry": {"coordinates":[-73.947304,40.745899],"type":"Point"}
}