{
  "type": "Feature",
  "properties": {
    "iso:country":"US",
    "sg:address":"59 Boniface Dr",
    "sg:city":"Pine Bush",
    "sg:classifiers":[
        {
            "category":"Real Estate",
            "subcategory":"Real Estate Agent",
            "type":"Services"
        }
    ],
    "sg:phone":"+1 845 800 8022",
    "sg:postcode":"12566",
    "sg:province":"NY",
    "wof:name":"Shelley Sakellariou",
    "wof:placetype":"venue"
},
  "geometry": {"coordinates":[-74.301435,41.602038],"type":"Point"}
}