{
  "type": "Feature",
  "properties": {
    "addr:full":"70 Havemeyer St Brooklyn NY 11211",
    "addr:housenumber":"70",
    "addr:postcode":"11211",
    "addr:street":"Havemeyer St",
    "iso:country":"US",
    "sg:address":"70 Havemeyer St",
    "sg:city":"Brooklyn",
    "sg:classifiers":[
        {
            "category":"Education",
            "subcategory":"School",
            "type":"Public Place"
        }
    ],
    "sg:phone":"+1 718 599 2100",
    "sg:postcode":"11211",
    "sg:province":"NY",
    "sg:tags":[
        "specialty"
    ],
    "wof:name":"Willimsburg Developmental Schl",
    "wof:placetype":"venue"
},
  "geometry": {"coordinates":[-73.95446,40.71488],"type":"Point"}
}