{
  "type": "Feature",
  "properties": {
    "addr:full":"98 Nott Rd Rexford NY 12148",
    "addr:housenumber":"98",
    "addr:postcode":"12148",
    "addr:street":"Nott Rd",
    "iso:country":"US",
    "sg:address":"98 Nott Rd",
    "sg:city":"Rexford",
    "sg:classifiers":[
        {
            "category":"Personal",
            "subcategory":"Beauty Salon",
            "type":"Services"
        }
    ],
    "sg:phone":"+1   ",
    "sg:postcode":"12148",
    "sg:province":"NY",
    "sg:tags":[
        "shop"
    ],
    "wof:name":"Lara Maries",
    "wof:placetype":"venue"
},
  "geometry": {"coordinates":[-73.879533,42.851312],"type":"Point"}
}