{
  "type": "Feature",
  "properties": {
    "addr:full":"141 Spencer St Brooklyn NY 11205",
    "addr:housenumber":"141",
    "addr:postcode":"11205",
    "addr:street":"Spencer St",
    "iso:country":"US",
    "sg:address":"141 Spencer St",
    "sg:city":"Brooklyn",
    "sg:classifiers":[
        {
            "category":"Arts & Performance",
            "subcategory":"Art Gallery",
            "type":"Entertainment"
        }
    ],
    "sg:phone":"+1 347 689 8795",
    "sg:postcode":"11205",
    "sg:province":"NY",
    "wof:name":"Hickson Business",
    "wof:placetype":"venue"
},
  "geometry": {"coordinates":[-73.954928,40.694256],"type":"Point"}
}