{
  "type": "Feature",
  "properties": {
    "addr:full":"462 Avenue P Brooklyn NY 11230",
    "addr:housenumber":"462",
    "addr:postcode":"11230",
    "addr:street":"Avenue P",
    "iso:country":"US",
    "sg:address":"462 Avenue P",
    "sg:city":"Brooklyn",
    "sg:classifiers":[
        {
            "category":"Restaurant",
            "type":"Food & Drink"
        }
    ],
    "sg:phone":"+1 718 336 2116",
    "sg:postcode":"11230",
    "sg:province":"NY",
    "sg:tags":[
        "chinese"
    ],
    "wof:name":"Hunan Express",
    "wof:placetype":"venue"
},
  "geometry": {"coordinates":[-73.970387,40.609114],"type":"Point"}
}