{
  "type": "Feature",
  "properties": {
    "addr:full":"58 Parkside Dr Jericho NY 11753",
    "addr:housenumber":"58",
    "addr:postcode":"11753",
    "addr:street":"Parkside Dr",
    "iso:country":"US",
    "sg:address":"58 Parkside Dr",
    "sg:city":"Jericho",
    "sg:classifiers":[
        {
            "category":"Real Estate",
            "subcategory":"Real Estate Agent",
            "type":"Services"
        }
    ],
    "sg:phone":"+1 516 644 3088",
    "sg:postcode":"11753",
    "sg:province":"NY",
    "wof:name":"Daveron Management Realty Inc",
    "wof:placetype":"venue"
},
  "geometry": {"coordinates":[-73.52638399999999,40.784679],"type":"Point"}
}