{
  "type": "Feature",
  "properties": {
    "addr:full":"121 N Main St Albion NY 14411",
    "addr:housenumber":"121",
    "addr:postcode":"14411",
    "addr:street":"N Main St",
    "iso:country":"US",
    "sg:address":"121 N Main St",
    "sg:city":"Albion",
    "sg:classifiers":[
        {
            "category":"Organizations",
            "subcategory":"Professional Association",
            "type":"Services"
        }
    ],
    "sg:phone":"+1 585 589 7727",
    "sg:postcode":"14411",
    "sg:province":"NY",
    "sg:tags":[
        "chambers",
        "commerce"
    ],
    "wof:name":"Orleans County Chamber-Cmmrc",
    "wof:placetype":"venue"
},
  "geometry": {"coordinates":[-78.19362599999999,43.24806],"type":"Point"}
}