{
  "type": "Feature",
  "properties": {
    "iso:country":"US",
    "sg:address":"649 Wyoming Ave",
    "sg:city":"Buffalo",
    "sg:classifiers":[
        {
            "category":"Building & Trades",
            "subcategory":"Electrical",
            "type":"Services"
        }
    ],
    "sg:phone":"+1 716 836 9520",
    "sg:postcode":"14215",
    "sg:province":"NY",
    "sg:tags":[
        "control",
        "regulator",
        "system",
        "controls"
    ],
    "wof:name":"Veritol",
    "wof:placetype":"venue"
},
  "geometry": {"coordinates":[-78.824293,42.932021],"type":"Point"}
}