{
  "type": "Feature",
  "properties": {
    "addr:full":"391 Main St Armonk NY 10504",
    "addr:housenumber":"391",
    "addr:postcode":"10504",
    "addr:street":"Main St",
    "iso:country":"US",
    "sg:address":"391 Main St",
    "sg:city":"Armonk",
    "sg:classifiers":[
        {
            "category":"Food & Beverages",
            "subcategory":"Bakery",
            "type":"Retail Goods"
        }
    ],
    "sg:phone":"+1   ",
    "sg:postcode":"10504",
    "sg:province":"NY",
    "wof:name":"Bagel Emporium of Armonk Inc",
    "wof:placetype":"venue"
},
  "geometry": {"coordinates":[-73.71311300000001,41.129371],"type":"Point"}
}