{
  "type": "Feature",
  "properties": {
    "iso:country":"US",
    "sg:address":"5000 14th Ave",
    "sg:city":"Brooklyn",
    "sg:classifiers":[
        {
            "category":"Education",
            "subcategory":"School",
            "type":"Public Place"
        }
    ],
    "sg:phone":"+1 718 438 3080",
    "sg:postcode":"11219",
    "sg:province":"NY",
    "wof:name":"Bnos Zion of Bobov Inc",
    "wof:placetype":"venue"
},
  "geometry": {"coordinates":[-73.99108099999999,40.632574],"type":"Point"}
}