{
  "type": "Feature",
  "properties": {
    "addr:full":"11 N Seneca St West Seneca NY 14224",
    "addr:housenumber":"11",
    "addr:postcode":"14224",
    "addr:street":"N Seneca St",
    "iso:country":"US",
    "sg:address":"11 N Seneca St",
    "sg:city":"West Seneca",
    "sg:classifiers":[
        {
            "category":"Building & Trades",
            "subcategory":"Landscaping Services",
            "type":"Services"
        }
    ],
    "sg:phone":"+1 716 677 2350",
    "sg:postcode":"14224",
    "sg:province":"NY",
    "sg:tags":[
        "landscape",
        "contractor"
    ],
    "wof:name":"Enchanted Landscapes",
    "wof:placetype":"venue"
},
  "geometry": {"coordinates":[-78.789033,42.848328],"type":"Point"}
}