{
  "type": "Feature",
  "properties": {
    "addr:full":"512A Fulton Ave Hempstead NY 11550",
    "addr:housenumber":"512a",
    "addr:postcode":"11550",
    "addr:street":"Fulton Ave",
    "iso:country":"US",
    "sg:address":"512A Fulton Ave",
    "sg:city":"Hempstead",
    "sg:classifiers":[
        {
            "category":"Deli",
            "type":"Food & Drink"
        }
    ],
    "sg:phone":"+1 516 489 9646",
    "sg:postcode":"11550",
    "sg:province":"NY",
    "wof:name":"S & B Community Deli Inc",
    "wof:placetype":"venue"
},
  "geometry": {"coordinates":[-73.62220000000001,40.708801],"type":"Point"}
}