{
  "type": "Feature",
  "properties": {
    "iso:country":"US",
    "sg:address":"25 Milford St",
    "sg:city":"Buffalo",
    "sg:classifiers":[
        {
            "category":"Professional",
            "subcategory":"Art Services",
            "type":"Services"
        },
        {
            "category":"Professional",
            "subcategory":"Printing & Photocopies",
            "type":"Services"
        }
    ],
    "sg:phone":"+1 866 909 1535",
    "sg:postcode":"14220",
    "sg:province":"NY",
    "sg:tags":[
        "photography",
        "photographers-commercial",
        "videography",
        "photographers-portrait"
    ],
    "wof:name":"Bmyhousekey Designs and Photography",
    "wof:placetype":"venue"
},
  "geometry": {"coordinates":[-78.81684199999999,42.852658],"type":"Point"}
}