{
  "type": "Feature",
  "properties": {
    "addr:full":"571 Wahlberg Rd Norwich NY 13815",
    "addr:housenumber":"571",
    "addr:postcode":"13815",
    "addr:street":"Wahlberg Rd",
    "iso:country":"US",
    "sg:address":"571 Wahlberg Rd",
    "sg:city":"Norwich",
    "sg:classifiers":[
        {
            "category":"Professional",
            "subcategory":"Accounting & Tax Preparation",
            "type":"Services"
        }
    ],
    "sg:phone":"+1 607 336 1124",
    "sg:postcode":"13815",
    "sg:province":"NY",
    "sg:tags":[
        "bookkeeping",
        "billing"
    ],
    "wof:name":"Bookkeeping Plus",
    "wof:placetype":"venue"
},
  "geometry": {"coordinates":[-75.50585700000001,42.452429],"type":"Point"}
}