{
  "type": "Feature",
  "properties": {
    "addr:full":"63 Semon Rd Huntington NY 11743",
    "addr:housenumber":"63",
    "addr:postcode":"11743",
    "addr:street":"Semon Rd",
    "iso:country":"US",
    "sg:address":"63 Semon Rd",
    "sg:city":"Huntington",
    "sg:classifiers":[
        {
            "category":"Professional",
            "type":"Services"
        }
    ],
    "sg:phone":"+1 631 409 3656",
    "sg:postcode":"11743",
    "sg:province":"NY",
    "sg:tags":[
        "establishment"
    ],
    "wof:name":"Phase One Assoc Inc",
    "wof:placetype":"venue"
},
  "geometry": {"coordinates":[-73.426011,40.859298],"type":"Point"}
}