{
  "type": "Feature",
  "properties": {
    "iso:country":"US",
    "sg:address":"76 Tompkins St",
    "sg:city":"East Northport",
    "sg:classifiers":[
        {
            "category":"Professional",
            "type":"Services"
        }
    ],
    "sg:phone":"+1   ",
    "sg:postcode":"11731",
    "sg:province":"NY",
    "wof:name":"Joel A Brenner",
    "wof:placetype":"venue"
},
  "geometry": {"coordinates":[-73.339265,40.887525],"type":"Point"}
}