{
  "type": "Feature",
  "properties": {
    "iso:country":"US",
    "sg:address":"73 Windermere Ave",
    "sg:city":"Greenwood Lake",
    "sg:classifiers":[
        {
            "category":"Personal",
            "subcategory":"Beauty Salon",
            "type":"Services"
        }
    ],
    "sg:phone":"+1 845 477 9409",
    "sg:postcode":"10925",
    "sg:province":"NY",
    "wof:name":"Shannon's Shears",
    "wof:placetype":"venue"
},
  "geometry": {"coordinates":[-74.293774,41.223216],"type":"Point"}
}