{
  "type": "Feature",
  "properties": {
    "addr:full":"2764 Route 32 Saugerties NY 12477",
    "addr:housenumber":"2764",
    "addr:postcode":"12477",
    "addr:street":"Route 32",
    "iso:country":"US",
    "sg:address":"2764 Route 32",
    "sg:city":"Saugerties",
    "sg:classifiers":[
        {
            "category":"Travel",
            "subcategory":"Hotels & Motels",
            "type":"Entertainment"
        }
    ],
    "sg:phone":"+1 845 246 9511",
    "sg:postcode":"12477",
    "sg:province":"NY",
    "sg:tags":[
        "corporate",
        "lodging"
    ],
    "sg:website":"http://www.howardjohnson.com",
    "wof:name":"Howard Johnson Inn - Saugerties, NY",
    "wof:placetype":"venue"
},
  "geometry": {"coordinates":[-73.975189,42.086277],"type":"Point"}
}