{
  "type": "Feature",
  "properties": {
    "iso:country":"US",
    "sg:address":"1696 Monroe Ave",
    "sg:city":"Rochester",
    "sg:classifiers":[
        {
            "category":"Restaurant",
            "type":"Food & Drink"
        }
    ],
    "sg:phone":"+1   ",
    "sg:postcode":"14618",
    "sg:province":"NY",
    "sg:tags":[
        "drinking",
        "eating"
    ],
    "wof:name":"Grinnells Restrnt",
    "wof:placetype":"venue"
},
  "geometry": {"coordinates":[-77.56959999999999,43.131563],"type":"Point"}
}