{
  "type": "Feature",
  "properties": {
    "addr:full":"1980 Park Ave New York NY 10037",
    "addr:housenumber":"1980",
    "addr:postcode":"10037",
    "addr:street":"Park Ave",
    "iso:country":"US",
    "sg:address":"1980 Park Ave",
    "sg:city":"New York",
    "sg:classifiers":[
        {
            "category":"Professional",
            "subcategory":"Management & Consulting",
            "type":"Services"
        }
    ],
    "sg:phone":"+1 212 491 1340",
    "sg:postcode":"10037",
    "sg:province":"NY",
    "wof:name":"Raysun Booking & Management",
    "wof:placetype":"venue"
},
  "geometry": {"coordinates":[-73.93496399999999,40.810752],"type":"Point"}
}