{
  "type": "Feature",
  "properties": {
    "iso:country":"US",
    "sg:address":"36 W 47th St Ste 511",
    "sg:city":"New York",
    "sg:classifiers":[
        {
            "category":"Shopping",
            "subcategory":"Jewelry",
            "type":"Retail Goods"
        }
    ],
    "sg:phone":"+1 212 938 1094",
    "sg:postcode":"10036",
    "sg:province":"NY",
    "wof:name":"M & S Star Jewelry Inc",
    "wof:placetype":"venue"
},
  "geometry": {"coordinates":[-73.979771,40.757016],"type":"Point"}
}