{
  "type": "Feature",
  "properties": {
    "addr:full":"120 Dayton Ave Manorville NY 11949",
    "addr:housenumber":"120",
    "addr:postcode":"11949",
    "addr:street":"Dayton Ave",
    "iso:country":"US",
    "sg:address":"120 Dayton Ave",
    "sg:city":"Manorville",
    "sg:classifiers":[
        {
            "category":"Sports & Exercise",
            "subcategory":"Stables",
            "type":"Entertainment"
        },
        {
            "category":"Arena",
            "subcategory":"Horse Racetrack",
            "type":"Entertainment"
        },
        {
            "category":"Farming",
            "subcategory":"Livestock Farm",
            "type":"Manufacturing & Wholesale Goods"
        },
        {
            "category":"Sports & Exercise",
            "subcategory":"Race Track",
            "type":"Entertainment"
        }
    ],
    "sg:phone":"+1 631 495 7429",
    "sg:postcode":"11949",
    "sg:province":"NY",
    "sg:tags":[
        "academy",
        "rental",
        "horse-boarding",
        "riding"
    ],
    "sg:website":"http://www.greenrosefarm.com",
    "wof:name":"Greenrose Farm",
    "wof:placetype":"venue"
},
  "geometry": {"coordinates":[-72.830583,40.840173],"type":"Point"}
}