{
  "type": "Feature",
  "properties": {
    "iso:country":"US",
    "sg:address":"404 Park Ave S",
    "sg:city":"New York",
    "sg:classifiers":[
        {
            "category":"Restaurant",
            "type":"Food & Drink"
        },
        {
            "category":"Banks & Credit Unions",
            "subcategory":"Bank",
            "type":"Services"
        }
    ],
    "sg:phone":"+1 212 481 9814",
    "sg:postcode":"10016",
    "sg:province":"NY",
    "sg:tags":[
        "broker",
        "mortgage"
    ],
    "wof:name":"Bahay Financing Group LLC",
    "wof:placetype":"venue"
},
  "geometry": {"coordinates":[-73.983627,40.743945],"type":"Point"}
}