{
  "type": "Feature",
  "properties": {
    "addr:full":"201 Grumman Rd W Bethpage NY 11714",
    "addr:housenumber":"201",
    "addr:postcode":"11714",
    "addr:street":"Grumman Rd W Bethpage",
    "iso:country":"US",
    "sg:address":"201 Grumman Rd W",
    "sg:city":"Bethpage",
    "sg:classifiers":[
        {
            "category":"Retail",
            "subcategory":"Auto Rental",
            "type":"Services"
        }
    ],
    "sg:phone":"+1 516 576 2034",
    "sg:postcode":"11714",
    "sg:province":"NY",
    "sg:tags":[
        "renting",
        "truck",
        "leasing"
    ],
    "sg:website":"www.penske.com",
    "wof:name":"Penske Truck Leasing",
    "wof:placetype":"venue"
},
  "geometry": {"coordinates":[-73.49422800000001,40.74688],"type":"Point"}
}