{
  "type": "Feature",
  "properties": {
    "addr:full":"5607 Broadway Bronx NY 10463",
    "addr:housenumber":"5607",
    "addr:postcode":"10463",
    "addr:street":"Broadway",
    "iso:country":"US",
    "sg:address":"5607 Broadway",
    "sg:city":"Bronx",
    "sg:classifiers":[
        {
            "category":"Shopping",
            "subcategory":"Gifts & Souvenirs",
            "type":"Retail Goods"
        }
    ],
    "sg:phone":"+1 718 884 6417",
    "sg:postcode":"10463",
    "sg:province":"NY",
    "sg:tags":[
        "shop",
        "novelty"
    ],
    "wof:name":"Jim's Gift Shop",
    "wof:placetype":"venue"
},
  "geometry": {"coordinates":[-73.90448499999999,40.879674],"type":"Point"}
}