{
  "type": "Feature",
  "properties": {
    "addr:full":"47 E 125th St New York NY 10035",
    "addr:housenumber":"47",
    "addr:postcode":"10035",
    "addr:street":"E 125Th St",
    "iso:country":"US",
    "sg:address":"47 E 125th St",
    "sg:city":"New York",
    "sg:classifiers":[
        {
            "category":"Food & Beverages",
            "subcategory":"Groceries & Convenience Stores",
            "type":"Retail Goods"
        }
    ],
    "sg:phone":"+1 212 410 4053",
    "sg:postcode":"10035",
    "sg:province":"NY",
    "sg:tags":[
        "grocer"
    ],
    "wof:name":"Mozab Grocery Store",
    "wof:placetype":"venue"
},
  "geometry": {"coordinates":[-73.941782,40.806453],"type":"Point"}
}