{
  "type": "Feature",
  "properties": {
    "iso:country":"US",
    "sg:address":"2178 Crotona Ave",
    "sg:city":"Bronx",
    "sg:classifiers":[
        {
            "category":"Restaurant",
            "type":"Food & Drink"
        }
    ],
    "sg:phone":"+1 718 561 0400",
    "sg:postcode":"10457",
    "sg:province":"NY",
    "sg:tags":[
        "delicatessen"
    ],
    "wof:name":"Gamboa Grocery",
    "wof:placetype":"venue"
},
  "geometry": {"coordinates":[-73.885728,40.850769],"type":"Point"}
}