{
  "type": "Feature",
  "properties": {
    "addr:full":"149 34th St Brooklyn NY 11232",
    "addr:housenumber":"149",
    "addr:postcode":"11232",
    "addr:street":"34Th St",
    "iso:country":"US",
    "sg:address":"149 34th St",
    "sg:city":"Brooklyn",
    "sg:phone":"+1 718 965 0900",
    "sg:postcode":"11232",
    "sg:province":"NY",
    "sg:tags":[
        "oil"
    ],
    "sg:website":"www.bluediamondfuel.com",
    "wof:name":"Blue Diamond Fuel Oil Corp",
    "wof:placetype":"venue"
},
  "geometry": {"coordinates":[-74.00386,40.656004],"type":"Point"}
}