{
  "type": "Feature",
  "properties": {
    "iso:country":"US",
    "sg:address":"316 Grand St",
    "sg:city":"Oneida",
    "sg:classifiers":[
        {
            "category":"Building & Trades",
            "subcategory":"Plumbing",
            "type":"Services"
        }
    ],
    "sg:phone":"+1 315 762 8047",
    "sg:postcode":"13421",
    "sg:province":"NY",
    "sg:tags":[
        "contractor"
    ],
    "wof:name":"L B Homewood Construction Inc",
    "wof:placetype":"venue"
},
  "geometry": {"coordinates":[-75.65836299999999,43.101717],"type":"Point"}
}