{
  "type": "Feature",
  "properties": {
    "iso:country":"US",
    "sg:address":"30 Sycamore Pl",
    "sg:city":"East Northport",
    "sg:classifiers":[
        {
            "category":"Health Services",
            "subcategory":"Clinic",
            "type":"Services"
        }
    ],
    "sg:phone":"+1 631 912 0429",
    "sg:postcode":"11731",
    "sg:province":"NY",
    "wof:name":"Everitt Consulting",
    "wof:placetype":"venue"
},
  "geometry": {"coordinates":[-73.317826,40.88458],"type":"Point"}
}