{
  "type": "Feature",
  "properties": {
    "addr:full":"733 Manhattan Avenue Brooklyn NY 11222",
    "addr:housenumber":"733",
    "addr:postcode":"11222",
    "addr:street":"Manhattan Avenue",
    "iso:country":"US",
    "sg:address":"733 Manhattan Avenue",
    "sg:city":"Brooklyn",
    "sg:classifiers":[
        {
            "category":"Health Services",
            "subcategory":"Optometrist",
            "type":"Services"
        }
    ],
    "sg:phone":"+1 718 389 6234",
    "sg:postcode":"11222",
    "sg:province":"NY",
    "wof:name":"Dr Sebastian Polizzi O D Vision Care",
    "wof:placetype":"venue"
},
  "geometry": {"coordinates":[-73.952209,40.726232],"type":"Point"}
}