{
  "type": "Feature",
  "properties": {
    "addr:full":"51 Ludlow St New York NY 10002",
    "addr:housenumber":"51",
    "addr:postcode":"10002",
    "addr:street":"Ludlow St",
    "iso:country":"US",
    "sg:address":"51 Ludlow St",
    "sg:city":"New York",
    "sg:classifiers":[
        {
            "category":"Real Estate",
            "subcategory":"Real Estate Agent",
            "type":"Services"
        }
    ],
    "sg:phone":"+1 212 226 3536",
    "sg:postcode":"10002",
    "sg:province":"NY",
    "sg:tags":[
        "building",
        "apartment",
        "operates"
    ],
    "wof:name":"Harvert Realty Corp",
    "wof:placetype":"venue"
},
  "geometry": {"coordinates":[-73.99033900000001,40.716184],"type":"Point"}
}