{
  "type": "Feature",
  "properties": {
    "iso:country":"US",
    "name:eng_x_preferred":[
        "182-183 Sts"
    ],
    "wof:name":"182-183 Sts",
    "wof:placetype":"venue"
},
  "geometry": {"coordinates":[-73.900741,40.856093],"type":"Point"}
}