{
  "type": "Feature",
  "properties": {
    "iso:country":"US",
    "sg:address":"200 Emerson Ave",
    "sg:city":"Hartsdale",
    "sg:classifiers":[
        {
            "category":"Building & Trades",
            "subcategory":"Plumbing",
            "type":"Services"
        }
    ],
    "sg:phone":"+1 914 683 6130",
    "sg:postcode":"10530",
    "sg:province":"NY",
    "sg:tags":[
        "plumbing",
        "contractor"
    ],
    "wof:name":"Westchester Mechanical Plumb",
    "wof:placetype":"venue"
},
  "geometry": {"coordinates":[-73.81541,41.026371],"type":"Point"}
}