{
  "type": "Feature",
  "properties": {
    "addr:full":"8301 4th Avenue Brooklyn NY 11209",
    "addr:housenumber":"8301",
    "addr:postcode":"11209",
    "addr:street":"4Th Avenue",
    "iso:country":"US",
    "sg:address":"8301 4th Avenue",
    "sg:city":"Brooklyn",
    "sg:classifiers":[
        {
            "category":"Health Services",
            "subcategory":"Doctor",
            "type":"Services"
        }
    ],
    "sg:phone":"+1 718 680 7419",
    "sg:postcode":"11209",
    "sg:province":"NY",
    "wof:name":"Gudi Rajashree K Dr MD",
    "wof:placetype":"venue"
},
  "geometry": {"coordinates":[-74.027362,40.62486],"type":"Point"}
}