{
  "type": "Feature",
  "properties": {
    "addr:full":"60 Center St Hornell NY 14843",
    "addr:housenumber":"60",
    "addr:postcode":"14843",
    "addr:street":"Center St",
    "iso:country":"US",
    "sg:address":"60 Center St",
    "sg:city":"Hornell",
    "sg:classifiers":[
        {
            "category":"Shopping",
            "subcategory":"Used Merchandise",
            "type":"Retail Goods"
        }
    ],
    "sg:phone":"+1 607 324 4421",
    "sg:postcode":"14843",
    "sg:province":"NY",
    "sg:tags":[
        "shop",
        "thrift"
    ],
    "wof:name":"Salvation Army Thrift Store",
    "wof:placetype":"venue"
},
  "geometry": {"coordinates":[-77.659504,42.323994],"type":"Point"}
}