{
  "type": "Feature",
  "properties": {
    "iso:country":"US",
    "sg:address":"153 W 91 St",
    "sg:city":"New York",
    "sg:classifiers":[
        {
            "category":"Health Services",
            "subcategory":"Doctor",
            "type":"Services"
        }
    ],
    "sg:phone":"+1 212 595 5100",
    "sg:postcode":"10024",
    "sg:province":"NY",
    "sg:tags":[
        "physician",
        "surgeon",
        "medical"
    ],
    "wof:name":"Stanley Greenberg MD",
    "wof:placetype":"venue"
},
  "geometry": {"coordinates":[-73.970292,40.789788],"type":"Point"}
}