{
  "type": "Feature",
  "properties": {
    "iso:country":"US",
    "sg:address":"185 Pearl St",
    "sg:city":"Batavia",
    "sg:classifiers":[
        {
            "category":"Retail",
            "subcategory":"Auto Repair",
            "type":"Services"
        }
    ],
    "sg:phone":"+1 585 343 0770",
    "sg:postcode":"14020",
    "sg:province":"NY",
    "sg:tags":[
        "body",
        "automobile",
        "painting"
    ],
    "wof:name":"LA Wall's Collision",
    "wof:placetype":"venue"
},
  "geometry": {"coordinates":[-78.20898,42.995563],"type":"Point"}
}