{
  "type": "Feature",
  "properties": {
    "iso:country":"US",
    "sg:address":"7030 E Genesee St",
    "sg:city":"Fayetteville",
    "sg:classifiers":[
        {
            "category":"Shopping",
            "subcategory":"Computers & Home Electronics",
            "type":"Retail Goods"
        }
    ],
    "sg:phone":"+1 315 449 2100",
    "sg:postcode":"13066",
    "sg:province":"NY",
    "sg:tags":[
        "software"
    ],
    "wof:name":"ABT Corp",
    "wof:placetype":"venue"
},
  "geometry": {"coordinates":[-76.038314,43.028231],"type":"Point"}
}