{
  "type": "Feature",
  "properties": {
    "addr:full":"8519 4th Ave Brooklyn NY 11209",
    "addr:housenumber":"8519",
    "addr:postcode":"11209",
    "addr:street":"4Th Ave",
    "iso:country":"US",
    "sg:address":"8519 4th Ave",
    "sg:city":"Brooklyn",
    "sg:classifiers":[
        {
            "category":"Professional",
            "subcategory":"Accounting & Tax Preparation",
            "type":"Services"
        }
    ],
    "sg:phone":"+1 718 921 1818",
    "sg:postcode":"11209",
    "sg:province":"NY",
    "sg:tags":[
        "return",
        "filing"
    ],
    "wof:name":"Kaufman Tax Professionals",
    "wof:placetype":"venue"
},
  "geometry": {"coordinates":[-74.028235,40.622919],"type":"Point"}
}