{
  "type": "Feature",
  "properties": {
    "addr:full":"1930 Veterans Hwy Islandia NY 11749",
    "addr:housenumber":"1930",
    "addr:postcode":"11749",
    "addr:street":"Veterans Hwy Islandia",
    "iso:country":"US",
    "sg:address":"1930 Veterans Hwy",
    "sg:city":"Islandia",
    "sg:classifiers":[
        {
            "category":"Insurance",
            "subcategory":"Insurance Agent",
            "type":"Services"
        },
        {
            "category":"Insurance",
            "subcategory":"Hazard Insurance",
            "type":"Services"
        },
        {
            "category":"Insurance",
            "subcategory":"Title Insurance",
            "type":"Services"
        },
        {
            "category":"Insurance",
            "subcategory":"Life Insurance",
            "type":"Services"
        }
    ],
    "sg:phone":"+1 631 234 2225",
    "sg:postcode":"11749",
    "sg:province":"NY",
    "sg:tags":[
        "business",
        "auto",
        "commercial",
        "homeowner",
        "motorcycle",
        "renter"
    ],
    "wof:name":"Allstate Insurance Company - Lois Morales",
    "wof:placetype":"venue"
},
  "geometry": {"coordinates":[-73.17459700000001,40.800386],"type":"Point"}
}