{
  "type": "Feature",
  "properties": {
    "addr:full":"Shelter Rock Rd New Hyde Park NY 11040",
    "addr:postcode":"11040",
    "addr:street":"Shelter Rock Rd",
    "iso:country":"US",
    "sg:address":"Shelter Rock Rd",
    "sg:city":"New Hyde Park",
    "sg:classifiers":[
        {
            "category":"Social Services",
            "subcategory":"Child Care",
            "type":"Services"
        }
    ],
    "sg:phone":"+1 516 248 7048",
    "sg:postcode":"11040",
    "sg:province":"NY",
    "sg:tags":[
        "day"
    ],
    "wof:name":"Harbor Child Care Center",
    "wof:placetype":"venue"
},
  "geometry": {"coordinates":[-73.681,40.743],"type":"Point"}
}