{
  "type": "Feature",
  "properties": {
    "iso:country":"US",
    "sg:address":"275 Washington St",
    "sg:city":"Buffalo",
    "sg:classifiers":[
        {
            "category":"Shopping",
            "subcategory":"Bicycles & Sporting Goods",
            "type":"Retail Goods"
        }
    ],
    "sg:phone":"+1   ",
    "sg:postcode":"14203",
    "sg:province":"NY",
    "wof:name":"Batters Box Gift Shop",
    "wof:placetype":"venue"
},
  "geometry": {"coordinates":[-78.874754,42.880708],"type":"Point"}
}