{
  "type": "Feature",
  "properties": {
    "addr:full":"346 W 46th St New York NY 10036",
    "addr:housenumber":"346",
    "addr:postcode":"10036",
    "addr:street":"W 46Th St",
    "iso:country":"US",
    "sg:address":"346 W 46th St",
    "sg:city":"New York",
    "sg:classifiers":[
        {
            "category":"Bars & Pubs",
            "type":"Food & Drink"
        },
        {
            "category":"Restaurant",
            "type":"Food & Drink"
        }
    ],
    "sg:phone":"+1 212 245 2030",
    "sg:postcode":"10036",
    "sg:province":"NY",
    "sg:tags":[
        "cajun/creole"
    ],
    "sg:website":"www.bourbonny.com",
    "wof:name":"Bourbon Street Bar & Grille",
    "wof:placetype":"venue"
},
  "geometry": {"coordinates":[-73.989245,40.760346],"type":"Point"}
}