{
  "type": "Feature",
  "properties": {
    "iso:country":"US",
    "sg:address":"1 Kenilworth Rd",
    "sg:city":"Yonkers",
    "sg:classifiers":[
        {
            "category":"Building & Trades",
            "subcategory":"Construction",
            "type":"Services"
        }
    ],
    "sg:phone":"+1 914 968 9245",
    "sg:postcode":"10701",
    "sg:province":"NY",
    "sg:tags":[
        "hanging",
        "contractor"
    ],
    "wof:name":"Paintng By Francisco",
    "wof:placetype":"venue"
},
  "geometry": {"coordinates":[-73.85547699999999,40.946633],"type":"Point"}
}