{
  "type": "Feature",
  "properties": {
    "iso:country":"US",
    "sg:address":"5 Saddle Ridge",
    "sg:city":"Old Westbury",
    "sg:classifiers":[
        {
            "category":"Banks & Credit Unions",
            "subcategory":"Investment Brokerage",
            "type":"Services"
        },
        {
            "category":"Professional",
            "subcategory":"Management & Consulting",
            "type":"Services"
        }
    ],
    "sg:phone":"+1 516 625 8848",
    "sg:postcode":"11568",
    "sg:province":"NY",
    "sg:tags":[
        "advisory",
        "financial"
    ],
    "wof:name":"Stone Harbor Capital LLC",
    "wof:placetype":"venue"
},
  "geometry": {"coordinates":[-73.61045300000001,40.799654],"type":"Point"}
}