{
  "type": "Feature",
  "properties": {
    "addr:full":"11 Belvedere Ct Manhasset NY 11030",
    "addr:housenumber":"11",
    "addr:postcode":"11030",
    "addr:street":"Belvedere Ct",
    "iso:country":"US",
    "sg:address":"11 Belvedere Ct",
    "sg:city":"Manhasset",
    "sg:classifiers":[
        {
            "category":"Building & Trades",
            "subcategory":"Construction",
            "type":"Services"
        }
    ],
    "sg:phone":"+1 516 365 2244",
    "sg:postcode":"11030",
    "sg:province":"NY",
    "sg:tags":[
        "contractor"
    ],
    "sg:website":"www.praxisgroup.com",
    "wof:name":"Praxis Group International Inc",
    "wof:placetype":"venue"
},
  "geometry": {"coordinates":[-73.683764,40.769328],"type":"Point"}
}