{
  "type": "Feature",
  "properties": {
    "iso:country":"US",
    "sg:address":"776 Pre Emption Rd",
    "sg:city":"Geneva",
    "sg:classifiers":[
        {
            "category":"Autos & Motor Vehicles",
            "subcategory":"Automobile Sales",
            "type":"Retail Goods"
        }
    ],
    "sg:phone":"+1 315 789 9813",
    "sg:postcode":"14456",
    "sg:province":"NY",
    "sg:tags":[
        "car",
        "dealer"
    ],
    "wof:name":"Geneva Coach Inc",
    "wof:placetype":"venue"
},
  "geometry": {"coordinates":[-77.01099499999999,42.864906],"type":"Point"}
}