{
  "type": "Feature",
  "properties": {
    "iso:country":"US",
    "sg:address":"10 Jefferson Boulevard",
    "sg:city":"Staten Island",
    "sg:classifiers":[
        {
            "category":"Professional",
            "subcategory":"Accounting & Tax Preparation",
            "type":"Services"
        }
    ],
    "sg:phone":"+1 718 227 0166",
    "sg:postcode":"10312",
    "sg:province":"NY",
    "sg:tags":[
        "accountant"
    ],
    "wof:name":"Media 2 the Max CPA",
    "wof:placetype":"venue"
},
  "geometry": {"coordinates":[-74.177694,40.548411],"type":"Point"}
}