{
  "type": "Feature",
  "properties": {
    "iso:country":"US",
    "sg:address":"33 Grandview Ave",
    "sg:city":"Rye",
    "sg:classifiers":[
        {
            "category":"Professional",
            "subcategory":"Management & Consulting",
            "type":"Services"
        }
    ],
    "sg:phone":"+1 914 925 9107",
    "sg:postcode":"10580",
    "sg:province":"NY",
    "wof:name":"Royal Alliance Associates",
    "wof:placetype":"venue"
},
  "geometry": {"coordinates":[-73.682495,40.987949],"type":"Point"}
}