{
  "type": "Feature",
  "properties": {
    "iso:country":"US",
    "sg:address":"19 E 80th Street",
    "sg:city":"New York",
    "sg:classifiers":[
        {
            "category":"Health Services",
            "subcategory":"Dentist",
            "type":"Services"
        }
    ],
    "sg:phone":"+1 212 772 7668",
    "sg:postcode":"10021",
    "sg:province":"NY",
    "wof:name":"Deblinger Jason DDS",
    "wof:placetype":"venue"
},
  "geometry": {"coordinates":[-73.962265,40.7774],"type":"Point"}
}