{
  "type": "Feature",
  "properties": {
    "iso:country":"US",
    "sg:address":"425 Jerusalem Ave",
    "sg:city":"Uniondale",
    "sg:classifiers":[
        {
            "category":"Personal",
            "subcategory":"Beauty Salon",
            "type":"Services"
        }
    ],
    "sg:phone":"+1 516 565 3326",
    "sg:postcode":"11553",
    "sg:province":"NY",
    "wof:name":"Sensation Beauty Salon",
    "wof:placetype":"venue"
},
  "geometry": {"coordinates":[-73.6011,40.701996],"type":"Point"}
}