{
  "type": "Feature",
  "properties": {
    "iso:country":"US",
    "sg:address":"3281 Fairway 6",
    "sg:city":"Macedon",
    "sg:classifiers":[
        {
            "category":"Building & Trades",
            "subcategory":"Construction",
            "type":"Services"
        }
    ],
    "sg:phone":"+1 315 986 2173",
    "sg:postcode":"14502",
    "sg:province":"NY",
    "sg:tags":[
        "house"
    ],
    "wof:name":"Dimcas Const",
    "wof:placetype":"venue"
},
  "geometry": {"coordinates":[-77.316343,43.123536],"type":"Point"}
}