{
  "type": "Feature",
  "properties": {
    "addr:full":"913 N Broadway Massapequa NY 11758",
    "addr:housenumber":"913",
    "addr:postcode":"11758",
    "addr:street":"N Broadway",
    "iso:country":"US",
    "sg:address":"913 N Broadway",
    "sg:city":"Massapequa",
    "sg:classifiers":[
        {
            "category":"Retail",
            "subcategory":"Auto Repair",
            "type":"Services"
        }
    ],
    "sg:phone":"+1 516 694 1950",
    "sg:postcode":"11758",
    "sg:province":"NY",
    "sg:tags":[
        "repairing",
        "automobile"
    ],
    "wof:name":"Greg's Auto Repair",
    "wof:placetype":"venue"
},
  "geometry": {"coordinates":[-73.46259499999999,40.7005],"type":"Point"}
}