{
  "type": "Feature",
  "properties": {
    "iso:country":"US",
    "sg:address":"264 E John St",
    "sg:city":"Lindenhurst",
    "sg:classifiers":[
        {
            "category":"Building & Trades",
            "subcategory":"Construction",
            "type":"Services"
        }
    ],
    "sg:phone":"+1 631 888 0621",
    "sg:postcode":"11757",
    "sg:province":"NY",
    "sg:tags":[
        "house"
    ],
    "wof:name":"European Home Improvement",
    "wof:placetype":"venue"
},
  "geometry": {"coordinates":[-73.363598,40.693816],"type":"Point"}
}