{
  "type": "Feature",
  "properties": {
    "addr:full":"50 Hauppauge Rd Commack NY 11725",
    "addr:housenumber":"50",
    "addr:postcode":"11725",
    "addr:street":"Hauppauge Rd",
    "iso:country":"US",
    "sg:address":"50 Hauppauge Rd",
    "sg:city":"Commack",
    "sg:classifiers":[
        {
            "category":"Health Services",
            "subcategory":"Nursing And Care Facility",
            "type":"Services"
        }
    ],
    "sg:phone":"+1 631 715 8500",
    "sg:postcode":"11725",
    "sg:province":"NY",
    "sg:tags":[
        "home",
        "convalescent"
    ],
    "wof:name":"Gurwin Jewish Fay Lindner",
    "wof:placetype":"venue"
},
  "geometry": {"coordinates":[-73.305994,40.827417],"type":"Point"}
}