{
  "type": "Feature",
  "properties": {
    "addr:full":"2622 Co Rte 7 Oswego NY 13126",
    "addr:housenumber":"2622",
    "addr:postcode":"13126",
    "addr:street":"Co Rte 7",
    "iso:country":"US",
    "sg:address":"2622 Co Rte 7",
    "sg:city":"Oswego",
    "sg:classifiers":[
        {
            "category":"Freight",
            "type":"Transportation"
        }
    ],
    "sg:phone":"+1 315 343 7099",
    "sg:postcode":"13126",
    "sg:province":"NY",
    "sg:tags":[
        "commercial",
        "storage"
    ],
    "wof:name":"Oswego Mini Storage Warehouse",
    "wof:placetype":"venue"
},
  "geometry": {"coordinates":[-76.534103,43.42066],"type":"Point"}
}