{
  "type": "Feature",
  "properties": {
    "addr:full":"8 Juliet Ln Northport NY 11768",
    "addr:housenumber":"8",
    "addr:postcode":"11768",
    "addr:street":"Juliet Ln",
    "iso:country":"US",
    "sg:address":"8 Juliet Ln",
    "sg:city":"Northport",
    "sg:classifiers":[
        {
            "category":"Building & Trades",
            "subcategory":"Construction",
            "type":"Services"
        }
    ],
    "sg:phone":"+1 631 754 5118",
    "sg:postcode":"11768",
    "sg:province":"NY",
    "sg:tags":[
        "masonry",
        "contractor"
    ],
    "wof:name":"Contemporary Stonescapes",
    "wof:placetype":"venue"
},
  "geometry": {"coordinates":[-73.298299,40.923483],"type":"Point"}
}