{
  "type": "Feature",
  "properties": {
    "addr:full":"72 Allen St Buffalo NY 14202",
    "addr:housenumber":"72",
    "addr:postcode":"14202",
    "addr:street":"Allen St",
    "iso:country":"US",
    "sg:address":"72 Allen St",
    "sg:city":"Buffalo",
    "sg:classifiers":[
        {
            "category":"Shopping",
            "subcategory":"Clothing, Apparel, & Fashions",
            "type":"Retail Goods"
        }
    ],
    "sg:phone":"+1 716 885 6963",
    "sg:postcode":"14202",
    "sg:province":"NY",
    "wof:name":"Juney Moon's Fantabulous Btq",
    "wof:placetype":"venue"
},
  "geometry": {"coordinates":[-78.872658,42.899341],"type":"Point"}
}