{
  "type": "Feature",
  "properties": {
    "iso:country":"US",
    "sg:address":"77 Bleecker St Ste C221",
    "sg:city":"New York",
    "sg:classifiers":[
        {
            "category":"Professional",
            "subcategory":"Computer Services",
            "type":"Services"
        }
    ],
    "sg:phone":"+1 212 777 2986",
    "sg:postcode":"10012",
    "sg:province":"NY",
    "sg:tags":[
        "repair"
    ],
    "sg:website":"www.joenyc.com",
    "wof:name":"JoeNYC, Inc",
    "wof:placetype":"venue"
},
  "geometry": {"coordinates":[-73.996235,40.726747],"type":"Point"}
}