{
  "type": "Feature",
  "properties": {
    "addr:full":"11 Delmar Ln Commack NY 11725",
    "addr:housenumber":"11",
    "addr:postcode":"11725",
    "addr:street":"Delmar Ln",
    "iso:country":"US",
    "sg:address":"11 Delmar Ln",
    "sg:city":"Commack",
    "sg:classifiers":[
        {
            "category":"Professional",
            "subcategory":"Business Services",
            "type":"Services"
        },
        {
            "category":"Shopping",
            "subcategory":"Clothing, Apparel, & Fashions",
            "type":"Retail Goods"
        }
    ],
    "sg:phone":"+1 631 232 2229",
    "sg:postcode":"11725",
    "sg:province":"NY",
    "sg:tags":[
        "baby",
        "accessory"
    ],
    "wof:name":"American Stork Company",
    "wof:placetype":"venue"
},
  "geometry": {"coordinates":[-73.286452,40.869301],"type":"Point"}
}