{
  "type": "Feature",
  "properties": {
    "addr:full":"132 Main St Salamanca NY 14779",
    "addr:housenumber":"132",
    "addr:postcode":"14779",
    "addr:street":"Main St",
    "iso:country":"US",
    "sg:address":"132 Main St",
    "sg:city":"Salamanca",
    "sg:classifiers":[
        {
            "category":"Restaurant",
            "type":"Food & Drink"
        }
    ],
    "sg:phone":"+1 716 945 2002",
    "sg:postcode":"14779",
    "sg:province":"NY",
    "sg:tags":[
        "caterer"
    ],
    "wof:name":"Dudley",
    "wof:placetype":"venue"
},
  "geometry": {"coordinates":[-78.714733,42.159144],"type":"Point"}
}