{
  "type": "Feature",
  "properties": {
    "addr:full":"6404 14th Ave Brooklyn NY 11219",
    "addr:housenumber":"6404",
    "addr:postcode":"11219",
    "addr:street":"14Th Ave",
    "iso:country":"US",
    "sg:address":"6404 14th Ave",
    "sg:city":"Brooklyn",
    "sg:classifiers":[
        {
            "category":"Building & Trades",
            "subcategory":"Construction",
            "type":"Services"
        }
    ],
    "sg:phone":"+1 718 232 8872",
    "sg:postcode":"11219",
    "sg:province":"NY",
    "sg:tags":[
        "windows"
    ],
    "wof:name":"Vincent Prestia Replacement",
    "wof:placetype":"venue"
},
  "geometry": {"coordinates":[-73.99936099999999,40.624727],"type":"Point"}
}