{
  "type": "Feature",
  "properties": {
    "iso:country":"US",
    "sg:address":"25 Fairview Sq",
    "sg:city":"Ithaca",
    "sg:classifiers":[
        {
            "category":"Building & Trades",
            "subcategory":"Electrical",
            "type":"Services"
        }
    ],
    "sg:phone":"+1 607 277 1965",
    "sg:postcode":"14850",
    "sg:province":"NY",
    "sg:tags":[
        "rod",
        "installation",
        "lightning"
    ],
    "wof:name":"Lightlink Internet Instltn",
    "wof:placetype":"venue"
},
  "geometry": {"coordinates":[-76.475994,42.440493],"type":"Point"}
}