{
  "type": "Feature",
  "properties": {
    "iso:country":"US",
    "sg:address":"1785 Dutch Broadway",
    "sg:city":"Elmont",
    "sg:classifiers":[
        {
            "category":"Shopping",
            "subcategory":"Pharmacy",
            "type":"Retail Goods"
        }
    ],
    "sg:phone":"+1 516 825 3177",
    "sg:postcode":"11003",
    "sg:province":"NY",
    "sg:tags":[
        "drugstore"
    ],
    "wof:name":"Dutch Bway Pharmcy",
    "wof:placetype":"venue"
},
  "geometry": {"coordinates":[-73.705299,40.688],"type":"Point"}
}