{
  "type": "Feature",
  "properties": {
    "addr:full":"52 Franck Rd Stony Point NY 10980",
    "addr:housenumber":"52",
    "addr:postcode":"10980",
    "addr:street":"Franck Rd",
    "iso:country":"US",
    "sg:address":"52 Franck Rd",
    "sg:city":"Stony Point",
    "sg:classifiers":[
        {
            "category":"Building & Trades",
            "subcategory":"Plumbing",
            "type":"Services"
        }
    ],
    "sg:phone":"+1 845 786 2288",
    "sg:postcode":"10980",
    "sg:province":"NY",
    "sg:tags":[
        "conditioning",
        "air",
        "system",
        "contractor"
    ],
    "wof:name":"Bates Heating & Cooling",
    "wof:placetype":"venue"
},
  "geometry": {"coordinates":[-74.010701,41.248314],"type":"Point"}
}