{
  "type": "Feature",
  "properties": {
    "iso:country":"US",
    "sg:address":"15 Westchester Sq",
    "sg:city":"Bronx",
    "sg:classifiers":[
        {
            "category":"Retail",
            "subcategory":"Repair Shop",
            "type":"Services"
        }
    ],
    "sg:phone":"+1 718 766 2545",
    "sg:postcode":"10461",
    "sg:province":"NY",
    "sg:tags":[
        "lock",
        "locksmith"
    ],
    "wof:name":"Emergency Locksmith",
    "wof:placetype":"venue"
},
  "geometry": {"coordinates":[-73.84323999999999,40.84135],"type":"Point"}
}