{
  "type": "Feature",
  "properties": {
    "addr:full":"2323 Broadway New York NY 10024",
    "addr:housenumber":"2323",
    "addr:postcode":"10024",
    "addr:street":"Broadway",
    "iso:country":"US",
    "sg:address":"2323 Broadway",
    "sg:city":"New York",
    "sg:classifiers":[
        {
            "category":"Ice Cream",
            "type":"Food & Drink"
        }
    ],
    "sg:phone":"+1 212 877 4556",
    "sg:postcode":"10024",
    "sg:province":"NY",
    "sg:tags":[
        "frozen",
        "yogurt"
    ],
    "wof:name":"Haagen Daz Ice Cream Shoppe",
    "wof:placetype":"venue"
},
  "geometry": {"coordinates":[-73.97768000000001,40.787298],"type":"Point"}
}