{
  "type": "Feature",
  "properties": {
    "addr:full":"1300 Ryan Rd Tully NY 13159",
    "addr:housenumber":"1300",
    "addr:postcode":"13159",
    "addr:street":"Ryan Rd",
    "iso:country":"US",
    "sg:address":"1300 Ryan Rd",
    "sg:city":"Tully",
    "sg:classifiers":[
        {
            "category":"Building & Trades",
            "subcategory":"Electrical",
            "type":"Services"
        }
    ],
    "sg:phone":"+1 315 696 8543",
    "sg:postcode":"13159",
    "sg:province":"NY",
    "sg:tags":[
        "electrical",
        "contractor"
    ],
    "wof:name":"Jae Bee Electric",
    "wof:placetype":"venue"
},
  "geometry": {"coordinates":[-76.219718,42.824614],"type":"Point"}
}