{
  "type": "Feature",
  "properties": {
    "iso:country":"US",
    "sg:address":"720 Rockaway Ave",
    "sg:city":"Brooklyn",
    "sg:classifiers":[
        {
            "category":"Health Services",
            "subcategory":"Doctor",
            "type":"Services"
        }
    ],
    "sg:phone":"+1 718 346 1914",
    "sg:postcode":"11212",
    "sg:province":"NY",
    "sg:tags":[
        "medical"
    ],
    "wof:name":"M Mehrfar",
    "wof:placetype":"venue"
},
  "geometry": {"coordinates":[-73.908649,40.661265],"type":"Point"}
}