{
  "type": "Feature",
  "properties": {
    "addr:full":"580 5th Ave New York NY 10036",
    "addr:housenumber":"580",
    "addr:postcode":"10036",
    "addr:street":"5Th Ave",
    "iso:country":"US",
    "sg:address":"580 5th Ave",
    "sg:city":"New York",
    "sg:classifiers":[
        {
            "category":"Wholesale",
            "subcategory":"Jewelry",
            "type":"Manufacturing & Wholesale Goods"
        }
    ],
    "sg:phone":"+1 212 575 0959",
    "sg:postcode":"10036",
    "sg:province":"NY",
    "sg:tags":[
        "import",
        "precious",
        "diamond",
        "stone"
    ],
    "wof:name":"Simantov Trading Company",
    "wof:placetype":"venue"
},
  "geometry": {"coordinates":[-73.978116,40.757284],"type":"Point"}
}