{
  "type": "Feature",
  "properties": {
    "iso:country":"US",
    "sg:address":"1165 Harbor Rd",
    "sg:city":"Hewlett",
    "sg:classifiers":[
        {
            "category":"Wholesale",
            "subcategory":"Non-durable Goods",
            "type":"Manufacturing & Wholesale Goods"
        }
    ],
    "sg:phone":"+1 516 295 0268",
    "sg:postcode":"11557",
    "sg:province":"NY",
    "wof:name":"164 01 Trading Inc",
    "wof:placetype":"venue"
},
  "geometry": {"coordinates":[-73.681411,40.626775],"type":"Point"}
}