{
  "type": "Feature",
  "properties": {
    "addr:full":"50 Harvest Dr Brewster NY 10509",
    "addr:housenumber":"50",
    "addr:postcode":"10509",
    "addr:street":"Harvest Dr",
    "iso:country":"US",
    "sg:address":"50 Harvest Dr",
    "sg:city":"Brewster",
    "sg:classifiers":[
        {
            "category":"Organizations",
            "subcategory":"Religious Organization",
            "type":"Services"
        }
    ],
    "sg:phone":"+1 845 279 7847",
    "sg:postcode":"10509",
    "sg:province":"NY",
    "sg:tags":[
        "clergy"
    ],
    "wof:name":"Raymond J Mellett",
    "wof:placetype":"venue"
},
  "geometry": {"coordinates":[-73.59404000000001,41.425976],"type":"Point"}
}