{
  "type": "Feature",
  "properties": {
    "iso:country":"US",
    "sg:address":"3822 Eagle Harbor Rd",
    "sg:city":"Albion",
    "sg:classifiers":[
        {
            "category":"Farming",
            "subcategory":"Orchard",
            "type":"Manufacturing & Wholesale Goods"
        }
    ],
    "sg:phone":"+1 585 589 4159",
    "sg:postcode":"14411",
    "sg:province":"NY",
    "sg:tags":[
        "fruit",
        "tree"
    ],
    "wof:name":"Eagle Harbor Orchard",
    "wof:placetype":"venue"
},
  "geometry": {"coordinates":[-78.25453899999999,43.215388],"type":"Point"}
}