{
  "type": "Feature",
  "properties": {
    "addr:full":"6323 Tulipwood Ln Jamesville NY 13078",
    "addr:postcode":"6323;13078",
    "addr:street":"Tulipwood Ln",
    "iso:country":"US",
    "sg:address":"6323 Tulipwood Ln",
    "sg:city":"Jamesville",
    "sg:classifiers":[
        {
            "category":"Professional",
            "subcategory":"Management & Consulting",
            "type":"Services"
        }
    ],
    "sg:phone":"+1 800 554 2832",
    "sg:postcode":"13078",
    "sg:province":"NY",
    "sg:tags":[
        "business"
    ],
    "wof:name":"Blistertech",
    "wof:placetype":"venue"
},
  "geometry": {"coordinates":[-76.07708599999999,43.017911],"type":"Point"}
}