{
  "type": "Feature",
  "properties": {
    "addr:full":"233 W 47 St New York NY 10036",
    "addr:housenumber":"233",
    "addr:postcode":"10036",
    "addr:street":"W 47 St",
    "iso:country":"US",
    "sg:address":"233 W 47 St",
    "sg:city":"New York",
    "sg:classifiers":[
        {
            "category":"Manufacturing",
            "subcategory":"Jewelry",
            "type":"Manufacturing & Wholesale Goods"
        }
    ],
    "sg:phone":"+1   ",
    "sg:postcode":"10036",
    "sg:province":"NY",
    "sg:tags":[
        "precious",
        "metal",
        "mfg"
    ],
    "wof:name":"NY Diamond Setter",
    "wof:placetype":"venue"
},
  "geometry": {"coordinates":[-73.986924,40.760184],"type":"Point"}
}