{
  "type": "Feature",
  "properties": {
    "iso:country":"US",
    "sg:address":"4 E Ridge Rd",
    "sg:city":"Hankins",
    "sg:classifiers":[
        {
            "category":"Professional",
            "subcategory":"Detective & Security Services",
            "type":"Services"
        }
    ],
    "sg:phone":"+1 845 887 5257",
    "sg:postcode":"12741",
    "sg:province":"NY",
    "sg:tags":[
        "information",
        "bureau"
    ],
    "wof:name":"Blackcherry Services Inc",
    "wof:placetype":"venue"
},
  "geometry": {"coordinates":[-75.09115,41.814347],"type":"Point"}
}