{
  "type": "Feature",
  "properties": {
    "iso:country":"US",
    "sg:address":"8 Apollo Dr",
    "sg:city":"Colonie",
    "sg:classifiers":[
        {
            "category":"Freight",
            "type":"Transportation"
        }
    ],
    "sg:phone":"+1 518 452 0959",
    "sg:postcode":"12205",
    "sg:province":"NY",
    "sg:tags":[
        "broker",
        "trucking"
    ],
    "wof:name":"Leo Lapierre Jr",
    "wof:placetype":"venue"
},
  "geometry": {"coordinates":[-73.86704899999999,42.722324],"type":"Point"}
}