{
  "type": "Feature",
  "properties": {
    "iso:country":"US",
    "sg:address":"885 E 149th St",
    "sg:city":"Bronx",
    "sg:classifiers":[
        {
            "category":"Professional",
            "type":"Services"
        }
    ],
    "sg:phone":"+1 718 665 1014",
    "sg:postcode":"10455",
    "sg:province":"NY",
    "sg:tags":[
        "establishment"
    ],
    "wof:name":"Fox Lines LTD",
    "wof:placetype":"venue"
},
  "geometry": {"coordinates":[-73.90307300000001,40.811426],"type":"Point"}
}