{
  "type": "Feature",
  "properties": {
    "addr:full":"15 Forbus St Poughkeepsie NY 12601",
    "addr:housenumber":"15",
    "addr:postcode":"12601",
    "addr:street":"Forbus St",
    "iso:country":"US",
    "sg:address":"15 Forbus St",
    "sg:city":"Poughkeepsie",
    "sg:classifiers":[
        {
            "category":"Professional",
            "subcategory":"Business Services",
            "type":"Services"
        }
    ],
    "sg:phone":"+1 845 337 4376",
    "sg:postcode":"12601",
    "sg:province":"NY",
    "sg:tags":[
        "organizing",
        "services-household"
    ],
    "wof:name":"Equity Property Management Cor",
    "wof:placetype":"venue"
},
  "geometry": {"coordinates":[-73.92135399999999,41.696021],"type":"Point"}
}