{
  "type": "Feature",
  "properties": {
    "addr:full":"108 W End Avenue Brooklyn NY 11235",
    "addr:housenumber":"108",
    "addr:postcode":"11235",
    "addr:street":"W End Avenue",
    "iso:country":"US",
    "sg:address":"108 W End Avenue",
    "sg:city":"Brooklyn",
    "sg:classifiers":[
        {
            "category":"Health Services",
            "subcategory":"Dentist",
            "type":"Services"
        }
    ],
    "sg:phone":"+1 718 648 3317",
    "sg:postcode":"11235",
    "sg:province":"NY",
    "wof:name":"Brenner Family Dental Center",
    "wof:placetype":"venue"
},
  "geometry": {"coordinates":[-73.95344299999999,40.578983],"type":"Point"}
}