{
  "type": "Feature",
  "properties": {
    "iso:country":"US",
    "sg:address":"102 W Post Rd",
    "sg:city":"White Plains",
    "sg:classifiers":[
        {
            "category":"Restaurant",
            "type":"Food & Drink"
        }
    ],
    "sg:phone":"+1 914 761 0800",
    "sg:postcode":"10606",
    "sg:province":"NY",
    "sg:tags":[
        "delicatessen",
        "eating"
    ],
    "wof:name":"Anthony's Triangle Deli",
    "wof:placetype":"venue"
},
  "geometry": {"coordinates":[-73.77496499999999,41.022515],"type":"Point"}
}