{
  "type": "Feature",
  "properties": {
    "addr:full":"3733 Rich's Corners Rd Albion NY 14411",
    "addr:housenumber":"3733",
    "addr:postcode":"14411",
    "addr:street":"Rich'S Corners Rd",
    "iso:country":"US",
    "sg:address":"3733 Rich's Corners Rd",
    "sg:city":"Albion",
    "sg:classifiers":[
        {
            "category":"Manufacturing",
            "subcategory":"Printing",
            "type":"Manufacturing & Wholesale Goods"
        }
    ],
    "sg:phone":"+1 585 589 9488",
    "sg:postcode":"14411",
    "sg:province":"NY",
    "sg:tags":[
        "lithographic",
        "printer",
        "commercial"
    ],
    "wof:name":"Printing Place The",
    "wof:placetype":"venue"
},
  "geometry": {"coordinates":[-78.149356,43.235747],"type":"Point"}
}