{
  "type": "Feature",
  "properties": {
    "addr:full":"9401 3rd Ave Brooklyn NY 11209",
    "addr:housenumber":"9401",
    "addr:postcode":"11209",
    "addr:street":"3Rd Ave",
    "iso:country":"US",
    "sg:address":"9401 3rd Ave",
    "sg:city":"Brooklyn",
    "sg:classifiers":[
        {
            "category":"Real Estate",
            "subcategory":"Real Estate Operator",
            "type":"Services"
        }
    ],
    "sg:phone":"+1 718 836 1014",
    "sg:postcode":"11209",
    "sg:province":"NY",
    "sg:tags":[
        "mall",
        "shopping",
        "center"
    ],
    "wof:name":"Hussain Zakir",
    "wof:placetype":"venue"
},
  "geometry": {"coordinates":[-74.03358799999999,40.617276],"type":"Point"}
}