{
  "type": "Feature",
  "properties": {
    "addr:full":"668 Bluebird Ct Central Valley NY 10917",
    "addr:housenumber":"668",
    "addr:postcode":"10917",
    "addr:street":"Bluebird Ct",
    "iso:country":"US",
    "sg:address":"668 Bluebird Ct",
    "sg:city":"Central Valley",
    "sg:classifiers":[
        {
            "category":"Shopping",
            "subcategory":"Discount & Variety Stores",
            "type":"Retail Goods"
        }
    ],
    "sg:phone":"+1 845 928 6100",
    "sg:postcode":"10917",
    "sg:province":"NY",
    "sg:tags":[
        "outlet"
    ],
    "wof:name":"Corning Revere Factory Store",
    "wof:placetype":"venue"
},
  "geometry": {"coordinates":[-74.125702,41.315201],"type":"Point"}
}