{
  "type": "Feature",
  "properties": {
    "iso:country":"US",
    "sg:address":"234 Holmes Rd",
    "sg:city":"Holmes",
    "sg:classifiers":[
        {
            "category":"Retail",
            "subcategory":"Repair Shop",
            "type":"Services"
        },
        {
            "category":"Wholesale",
            "subcategory":"Electrical",
            "type":"Manufacturing & Wholesale Goods"
        }
    ],
    "sg:phone":"+1 845 878 2547",
    "sg:postcode":"12531",
    "sg:province":"NY",
    "sg:tags":[
        "equipment",
        "facsimile",
        "communication"
    ],
    "wof:name":"Intone Office Products",
    "wof:placetype":"venue"
},
  "geometry": {"coordinates":[-73.65255399999999,41.527312],"type":"Point"}
}