{
  "type": "Feature",
  "properties": {
    "addr:full":"4731 White Plains Rd Bronx NY 10470",
    "addr:housenumber":"4731",
    "addr:postcode":"10470",
    "addr:street":"White Plains Rd",
    "iso:country":"US",
    "sg:address":"4731 White Plains Rd",
    "sg:city":"Bronx",
    "sg:classifiers":[
        {
            "category":"Insurance",
            "subcategory":"Insurance Agent",
            "type":"Services"
        },
        {
            "category":"Insurance",
            "subcategory":"Hazard Insurance",
            "type":"Services"
        },
        {
            "category":"Insurance",
            "subcategory":"Title Insurance",
            "type":"Services"
        },
        {
            "category":"Insurance",
            "subcategory":"Life Insurance",
            "type":"Services"
        }
    ],
    "sg:phone":"+1 718 994 5050",
    "sg:postcode":"10470",
    "sg:province":"NY",
    "sg:tags":[
        "business",
        "auto",
        "commercial",
        "homeowner",
        "motorcycle",
        "renter"
    ],
    "wof:name":"Allstate Insurance Company - Lesly Vixama",
    "wof:placetype":"venue"
},
  "geometry": {"coordinates":[-73.84984300000001,40.904124],"type":"Point"}
}