{
  "type": "Feature",
  "properties": {
    "iso:country":"US",
    "sg:address":"3954 McFarland Rd",
    "sg:city":"Taberg",
    "sg:classifiers":[
        {
            "category":"Autos & Motor Vehicles",
            "subcategory":"Automobile Sales",
            "type":"Retail Goods"
        }
    ],
    "sg:phone":"+1   ",
    "sg:postcode":"13471",
    "sg:province":"NY",
    "sg:tags":[
        "used"
    ],
    "wof:name":"T Auto Sales",
    "wof:placetype":"venue"
},
  "geometry": {"coordinates":[-75.626891,43.284985],"type":"Point"}
}