{
  "type": "Feature",
  "properties": {
    "addr:full":"3916 16th Ave Brooklyn NY 11218",
    "addr:housenumber":"3916",
    "addr:postcode":"11218",
    "addr:street":"16Th Ave",
    "iso:country":"US",
    "sg:address":"3916 16th Ave",
    "sg:city":"Brooklyn",
    "sg:classifiers":[
        {
            "category":"Professional",
            "type":"Services"
        }
    ],
    "sg:phone":"+1 718 435 2600",
    "sg:postcode":"11218",
    "sg:province":"NY",
    "sg:tags":[
        "establishment"
    ],
    "wof:name":"Classic Benches",
    "wof:placetype":"venue"
},
  "geometry": {"coordinates":[-73.98025199999999,40.636213],"type":"Point"}
}