{
  "type": "Feature",
  "properties": {
    "iso:country":"US",
    "sg:address":"900 West Shore Road",
    "sg:city":"Port Washington",
    "sg:classifiers":[
        {
            "category":"Professional",
            "subcategory":"Management & Consulting",
            "type":"Services"
        }
    ],
    "sg:postcode":"11050",
    "sg:province":"NY",
    "sg:website":"http://www.npd.com/corpServlet?nextpage=corp_welcome.html",
    "wof:name":"NPD Group",
    "wof:placetype":"venue"
},
  "geometry": {"coordinates":[-73.65745099999999,40.82479],"type":"Point"}
}