{
  "type": "Feature",
  "properties": {
    "iso:country":"US",
    "sg:address":"63 Cascade Rd",
    "sg:city":"Warwick",
    "sg:classifiers":[
        {
            "category":"Building & Trades",
            "subcategory":"Construction",
            "type":"Services"
        }
    ],
    "sg:phone":"+1 917 578 6183",
    "sg:postcode":"10990",
    "sg:province":"NY",
    "wof:name":"Vincent Deangelis",
    "wof:placetype":"venue"
},
  "geometry": {"coordinates":[-74.31734,41.235794],"type":"Point"}
}