{
  "type": "Feature",
  "properties": {
    "iso:country":"US",
    "sg:address":"1765 East Ave",
    "sg:city":"Rochester",
    "sg:classifiers":[
        {
            "category":"Retail",
            "subcategory":"Laundry & Dry Cleaning",
            "type":"Services"
        }
    ],
    "sg:phone":"+1 585 256 2795",
    "sg:postcode":"14610",
    "sg:province":"NY",
    "sg:tags":[
        "cleaners"
    ],
    "wof:name":"Speedy's Cleaners",
    "wof:placetype":"venue"
},
  "geometry": {"coordinates":[-77.559254,43.1464],"type":"Point"}
}