{
  "type": "Feature",
  "properties": {
    "addr:full":"390 Main St Bolivar NY 14715",
    "addr:housenumber":"390",
    "addr:postcode":"14715",
    "addr:street":"Main St Bolivar",
    "iso:country":"US",
    "sg:address":"390 Main St",
    "sg:city":"Bolivar",
    "sg:classifiers":[
        {
            "category":"Education",
            "subcategory":"Library",
            "type":"Public Place"
        }
    ],
    "sg:phone":"+1   ",
    "sg:postcode":"14715",
    "sg:province":"NY",
    "wof:name":"Bolivar Free Library",
    "wof:placetype":"venue"
},
  "geometry": {"coordinates":[-78.167984,42.065274],"type":"Point"}
}