{
  "type": "Feature",
  "properties": {
    "addr:full":"5310 Sheridan Dr Buffalo NY 14221",
    "addr:housenumber":"5310",
    "addr:postcode":"14221",
    "addr:street":"Sheridan Dr",
    "iso:country":"US",
    "sg:address":"5310 Sheridan Dr",
    "sg:city":"Buffalo",
    "sg:classifiers":[
        {
            "category":"Building & Trades",
            "subcategory":"Construction",
            "type":"Services"
        }
    ],
    "sg:phone":"+1 716 570 9711",
    "sg:postcode":"14221",
    "sg:province":"NY",
    "sg:tags":[
        "residential"
    ],
    "wof:name":"Inness Inc",
    "wof:placetype":"venue"
},
  "geometry": {"coordinates":[-78.73509799999999,42.978608],"type":"Point"}
}