{
  "type": "Feature",
  "properties": {
    "iso:country":"US",
    "sg:address":"1 Morse Ct",
    "sg:city":"New Canaan",
    "sg:classifiers":[
        {
            "category":"Health Services",
            "subcategory":"Doctor",
            "type":"Services"
        }
    ],
    "sg:phone":"+1   ",
    "sg:postcode":"06840",
    "sg:province":"NY",
    "sg:tags":[
        "medical"
    ],
    "wof:name":"Sharon J Littzi",
    "wof:placetype":"venue"
},
  "geometry": {"coordinates":[-73.492054,41.14665],"type":"Point"}
}