{
  "type": "Feature",
  "properties": {
    "iso:country":"US",
    "sg:address":"11208 Liberty Ave",
    "sg:city":"Jamaica",
    "sg:classifiers":[
        {
            "category":"Health Services",
            "subcategory":"Doctor",
            "type":"Services"
        }
    ],
    "sg:phone":"+1 718 848 2727",
    "sg:postcode":"11419",
    "sg:province":"NY",
    "wof:name":"Woodhaven Medical",
    "wof:placetype":"venue"
},
  "geometry": {"coordinates":[-73.830133,40.684971],"type":"Point"}
}