{
  "type": "Feature",
  "properties": {
    "iso:country":"US",
    "sg:address":"1112 Park Ave",
    "sg:city":"Mamaroneck",
    "sg:classifiers":[
        {
            "category":"Real Estate",
            "subcategory":"Real Estate Agent",
            "type":"Services"
        }
    ],
    "sg:phone":"+1 914 777 1115",
    "sg:postcode":"10543",
    "sg:province":"NY",
    "sg:tags":[
        "appraiser"
    ],
    "wof:name":"Key Consultant",
    "wof:placetype":"venue"
},
  "geometry": {"coordinates":[-73.725133,40.959161],"type":"Point"}
}