{
  "type": "Feature",
  "properties": {
    "iso:country":"US",
    "sg:address":"18 Main Ter",
    "sg:city":"Perry",
    "sg:classifiers":[
        {
            "category":"Personal",
            "subcategory":"Barber",
            "type":"Services"
        }
    ],
    "sg:phone":"+1 585 237 6260",
    "sg:postcode":"14530",
    "sg:province":"NY",
    "sg:tags":[
        "shop"
    ],
    "wof:name":"Jake's Barber Shop",
    "wof:placetype":"venue"
},
  "geometry": {"coordinates":[-77.99796000000001,42.721099],"type":"Point"}
}