{
  "type": "Feature",
  "properties": {
    "iso:country":"US",
    "sg:address":"680 Jericho Tpke",
    "sg:city":"Huntington Station",
    "sg:classifiers":[
        {
            "category":"Shopping",
            "subcategory":"Optician",
            "type":"Retail Goods"
        }
    ],
    "sg:phone":"+1 631 351 5711",
    "sg:postcode":"11746",
    "sg:province":"NY",
    "sg:tags":[
        "eyewear"
    ],
    "wof:name":"Opti-Grip Inc",
    "wof:placetype":"venue"
},
  "geometry": {"coordinates":[-73.38420600000001,40.833825],"type":"Point"}
}