{
  "type": "Feature",
  "properties": {
    "iso:country":"US",
    "sg:address":"1559 Islip Ave",
    "sg:city":"Central Islip",
    "sg:classifiers":[
        {
            "category":"Restaurant",
            "type":"Food & Drink"
        }
    ],
    "sg:menulink":"http://www.allmenus.com/ny/islip/254599-wah-nan-kitchen/menu/",
    "sg:phone":"+1 631 234 8787",
    "sg:postcode":"11722",
    "sg:province":"NY",
    "sg:tags":[
        "asian",
        "chinese"
    ],
    "wof:name":"Wah Nan Kitchen",
    "wof:placetype":"venue"
},
  "geometry": {"coordinates":[-73.21666999999999,40.780565],"type":"Point"}
}