{
  "type": "Feature",
  "properties": {
    "iso:country":"US",
    "sg:address":"172 E Main St",
    "sg:city":"Huntington",
    "sg:classifiers":[
        {
            "category":"Health Services",
            "subcategory":"Doctor",
            "type":"Services"
        }
    ],
    "sg:phone":"+1 631 385 0022",
    "sg:postcode":"11743",
    "sg:province":"NY",
    "sg:tags":[
        "medical"
    ],
    "wof:name":"Raj Patcha MD",
    "wof:placetype":"venue"
},
  "geometry": {"coordinates":[-73.395157,40.881315],"type":"Point"}
}