{
  "type": "Feature",
  "properties": {
    "iso:country":"US",
    "sg:address":"3426 31st Street",
    "sg:city":"Long Island City",
    "sg:classifiers":[
        {
            "category":"Building & Trades",
            "subcategory":"Construction",
            "type":"Services"
        }
    ],
    "sg:phone":"+1 718 392 0300",
    "sg:postcode":"11106",
    "sg:province":"NY",
    "sg:tags":[
        "contractor"
    ],
    "wof:name":"Build Source Corporation",
    "wof:placetype":"venue"
},
  "geometry": {"coordinates":[-73.927863,40.759125],"type":"Point"}
}