{
  "type": "Feature",
  "properties": {
    "addr:full":"10404 Liberty Ave Ozone Park NY 11417",
    "addr:housenumber":"10404",
    "addr:postcode":"11417",
    "addr:street":"Liberty Ave",
    "iso:country":"US",
    "sg:address":"10404 Liberty Ave",
    "sg:city":"Ozone Park",
    "sg:classifiers":[
        {
            "category":"Food & Beverages",
            "subcategory":"Groceries & Convenience Stores",
            "type":"Retail Goods"
        }
    ],
    "sg:phone":"+1 718 848 1616",
    "sg:postcode":"11417",
    "sg:province":"NY",
    "wof:name":"Sharmin West Indian Grocery",
    "wof:placetype":"venue"
},
  "geometry": {"coordinates":[-73.836854,40.681878],"type":"Point"}
}