{
  "type": "Feature",
  "properties": {
    "addr:full":"1444 86th St Brooklyn NY 11228",
    "addr:housenumber":"1444",
    "addr:postcode":"11228",
    "addr:street":"86Th St",
    "iso:country":"US",
    "sg:address":"1444 86th St",
    "sg:city":"Brooklyn",
    "sg:classifiers":[
        {
            "category":"Professional",
            "subcategory":"Accounting & Tax Preparation",
            "type":"Services"
        }
    ],
    "sg:phone":"+1 718 234 0190",
    "sg:postcode":"11228",
    "sg:province":"NY",
    "sg:tags":[
        "accountant"
    ],
    "sg:website":"www.colabella.com",
    "wof:name":"Colabella & Co CPA",
    "wof:placetype":"venue"
},
  "geometry": {"coordinates":[-74.010592,40.612029],"type":"Point"}
}