{
  "type": "Feature",
  "properties": {
    "iso:country":"US",
    "sg:address":"17 Delray Dr",
    "sg:city":"Buffalo",
    "sg:classifiers":[
        {
            "category":"Professional",
            "subcategory":"Accounting & Tax Preparation",
            "type":"Services"
        }
    ],
    "sg:phone":"+1   ",
    "sg:postcode":"14225",
    "sg:province":"NY",
    "wof:name":"Webpaycom",
    "wof:placetype":"venue"
},
  "geometry": {"coordinates":[-78.772592,42.940194],"type":"Point"}
}