{
  "type": "Feature",
  "properties": {
    "addr:full":"80 N Research Pl Central Islip NY 11722",
    "addr:housenumber":"80",
    "addr:postcode":"11722",
    "addr:street":"N Research Pl",
    "iso:country":"US",
    "sg:address":"80 N Research Pl",
    "sg:city":"Central Islip",
    "sg:classifiers":[
        {
            "category":"Professional",
            "type":"Services"
        }
    ],
    "sg:phone":"+1 631 851 9720",
    "sg:postcode":"11722",
    "sg:province":"NY",
    "sg:tags":[
        "establishment"
    ],
    "wof:name":"E W Howell Co Inc",
    "wof:placetype":"venue"
},
  "geometry": {"coordinates":[-73.19945,40.774086],"type":"Point"}
}