{
  "type": "Feature",
  "properties": {
    "addr:full":"200 E 58th St New York NY 10022",
    "addr:housenumber":"200",
    "addr:postcode":"10022",
    "addr:street":"E 58Th St",
    "iso:country":"US",
    "sg:address":"200 E 58th St",
    "sg:city":"New York",
    "sg:classifiers":[
        {
            "category":"Real Estate",
            "subcategory":"Real Estate Agent",
            "type":"Services"
        }
    ],
    "sg:phone":"+1 212 879 4393",
    "sg:postcode":"10022",
    "sg:province":"NY",
    "wof:name":"Izsak Realty",
    "wof:placetype":"venue"
},
  "geometry": {"coordinates":[-73.96480099999999,40.759982],"type":"Point"}
}