{
  "type": "Feature",
  "properties": {
    "addr:full":"2388 24th St Astoria NY 11105",
    "addr:housenumber":"2388",
    "addr:postcode":"11105",
    "addr:street":"24Th St",
    "iso:country":"US",
    "sg:address":"2388 24th St",
    "sg:city":"Astoria",
    "sg:classifiers":[
        {
            "category":"Building & Trades",
            "subcategory":"Electrical",
            "type":"Services"
        }
    ],
    "sg:phone":"+1 718 721 2624",
    "sg:postcode":"11105",
    "sg:province":"NY",
    "sg:tags":[
        "electrician"
    ],
    "wof:name":"City Lights Electric Inc",
    "wof:placetype":"venue"
},
  "geometry": {"coordinates":[-73.9198,40.7756],"type":"Point"}
}