{
  "type": "Feature",
  "properties": {
    "addr:full":"525 W Merrick Rd Valley Stream NY 11580",
    "addr:housenumber":"525",
    "addr:postcode":"11580",
    "addr:street":"W Merrick Rd",
    "iso:country":"US",
    "sg:address":"525 W Merrick Rd",
    "sg:city":"Valley Stream",
    "sg:classifiers":[
        {
            "category":"Shopping",
            "subcategory":"Discount & Variety Stores",
            "type":"Retail Goods"
        }
    ],
    "sg:phone":"+1   ",
    "sg:postcode":"11580",
    "sg:province":"NY",
    "sg:tags":[
        "department"
    ],
    "wof:name":"Ryans Family Discount Center",
    "wof:placetype":"venue"
},
  "geometry": {"coordinates":[-73.713933,40.66896],"type":"Point"}
}