{
  "type": "Feature",
  "properties": {
    "iso:country":"US",
    "sg:address":"626 RexCorp Plaza",
    "sg:city":"Uniondale",
    "sg:classifiers":[
        {
            "category":"Professional",
            "subcategory":"Research",
            "type":"Services"
        }
    ],
    "sg:phone":"+1 516 832 7000",
    "sg:postcode":"11556",
    "sg:province":"NY",
    "sg:website":"http://www.altgreentech.com/home.htm",
    "wof:name":"Alternative Green Technologies",
    "wof:placetype":"venue"
},
  "geometry": {"coordinates":[-73.58380699999999,40.719683],"type":"Point"}
}