{
  "type": "Feature",
  "properties": {
    "addr:full":"7616 Park Ave Lowville NY 13367",
    "addr:housenumber":"7616",
    "addr:postcode":"13367",
    "addr:street":"Park Ave",
    "iso:country":"US",
    "sg:address":"7616 Park Ave",
    "sg:city":"Lowville",
    "sg:classifiers":[
        {
            "category":"Organizations",
            "subcategory":"Religious Organization",
            "type":"Services"
        }
    ],
    "sg:phone":"+1 315 376 1996",
    "sg:postcode":"13367",
    "sg:province":"NY",
    "wof:name":"Mormon Missionaries",
    "wof:placetype":"venue"
},
  "geometry": {"coordinates":[-75.489441,43.789492],"type":"Point"}
}