{
  "type": "Feature",
  "properties": {
    "addr:full":"1345 Castle Hill Ave Bronx NY 10462",
    "addr:housenumber":"1345",
    "addr:postcode":"10462",
    "addr:street":"Castle Hill Ave",
    "iso:country":"US",
    "sg:address":"1345 Castle Hill Ave",
    "sg:city":"Bronx",
    "sg:classifiers":[
        {
            "category":"Food & Beverages",
            "subcategory":"Groceries & Convenience Stores",
            "type":"Retail Goods"
        }
    ],
    "sg:phone":"+1 718 597 2991",
    "sg:postcode":"10462",
    "sg:province":"NY",
    "sg:tags":[
        "grocer",
        "supermarket"
    ],
    "wof:name":"Pioneer Supermarket Inc",
    "wof:placetype":"venue"
},
  "geometry": {"coordinates":[-73.85194199999999,40.834631],"type":"Point"}
}