{
  "type": "Feature",
  "properties": {
    "addr:full":"296 Fortsville Rd Gansevoort NY 12831",
    "addr:housenumber":"296",
    "addr:postcode":"12831",
    "addr:street":"Fortsville Rd",
    "iso:country":"US",
    "sg:address":"296 Fortsville Rd",
    "sg:city":"Gansevoort",
    "sg:classifiers":[
        {
            "category":"Shopping",
            "subcategory":"Bicycles & Sporting Goods",
            "type":"Retail Goods"
        }
    ],
    "sg:phone":"+1   ",
    "sg:postcode":"12831",
    "sg:province":"NY",
    "wof:name":"Outback Sports",
    "wof:placetype":"venue"
},
  "geometry": {"coordinates":[-73.679903,43.243324],"type":"Point"}
}