{
  "type": "Feature",
  "properties": {
    "iso:country":"US",
    "sg:address":"31 Rio Dr",
    "sg:city":"Frewsburg",
    "sg:classifiers":[
        {
            "category":"Social Services",
            "type":"Services"
        }
    ],
    "sg:phone":"+1 716 569 3343",
    "sg:postcode":"14738",
    "sg:province":"NY",
    "sg:tags":[
        "organization",
        "welfare"
    ],
    "wof:name":"Resource Center",
    "wof:placetype":"venue"
},
  "geometry": {"coordinates":[-79.143153,42.06322],"type":"Point"}
}