{
  "type": "Feature",
  "properties": {
    "iso:country":"US",
    "sg:address":"18819 Tioga Dr",
    "sg:city":"Saint Albans",
    "sg:classifiers":[
        {
            "category":"Personal",
            "type":"Services"
        }
    ],
    "sg:phone":"+1 718 949 0566",
    "sg:postcode":"11412",
    "sg:province":"NY",
    "sg:tags":[
        "mover"
    ],
    "wof:name":"Albano Movers",
    "wof:placetype":"venue"
},
  "geometry": {"coordinates":[-73.764,40.694901],"type":"Point"}
}