{
  "type": "Feature",
  "properties": {
    "iso:country":"US",
    "sg:address":"575 Broadway",
    "sg:city":"Amityville",
    "sg:classifiers":[
        {
            "category":"Banks & Credit Unions",
            "subcategory":"Bank",
            "type":"Services"
        }
    ],
    "sg:phone":"+1 631 789 5433",
    "sg:postcode":"11701",
    "sg:province":"NY",
    "sg:tags":[
        "loan",
        "real estate"
    ],
    "wof:name":"Discount Funding",
    "wof:placetype":"venue"
},
  "geometry": {"coordinates":[-73.422426,40.692613],"type":"Point"}
}