{
  "type": "Feature",
  "properties": {
    "addr:full":"1383 Ridge Rd W Rochester NY 14615",
    "addr:housenumber":"1383",
    "addr:postcode":"14615",
    "addr:street":"Ridge Rd W",
    "iso:country":"US",
    "sg:address":"1383 Ridge Rd W",
    "sg:city":"Rochester",
    "sg:classifiers":[
        {
            "category":"Professional",
            "subcategory":"Engineering",
            "type":"Services"
        },
        {
            "category":"Home & Garden",
            "subcategory":"Building Materials",
            "type":"Retail Goods"
        },
        {
            "category":"Building & Trades",
            "subcategory":"Construction",
            "type":"Services"
        }
    ],
    "sg:phone":"+1 585 227 4512",
    "sg:postcode":"14615",
    "sg:province":"NY",
    "sg:tags":[
        "system",
        "specialty",
        "heating",
        "contractor",
        "equipment",
        "air conditioning"
    ],
    "sg:website":"http://find.trane.com/tcs-dealer-417086?utm_source=YP&utm_medium=banner&utm_campaign=TL",
    "wof:name":"Andrew Paris Heating & Cooling",
    "wof:placetype":"venue"
},
  "geometry": {"coordinates":[-77.66428399999999,43.204813],"type":"Point"}
}