{
  "type": "Feature",
  "properties": {
    "addr:full":"90 Sandy Rd Accord NY 12401",
    "addr:housenumber":"90",
    "addr:postcode":"12401",
    "addr:street":"Sandy Rd",
    "iso:country":"US",
    "sg:address":"90 Sandy Rd",
    "sg:city":"Accord",
    "sg:classifiers":[
        {
            "category":"Building & Trades",
            "subcategory":"Construction",
            "type":"Services"
        }
    ],
    "sg:phone":"+1 845 626 5537",
    "sg:postcode":"12401",
    "sg:province":"NY",
    "sg:tags":[
        "contractor"
    ],
    "wof:name":"Richard Weaver Contracting",
    "wof:placetype":"venue"
},
  "geometry": {"coordinates":[-74.02361500000001,41.940311],"type":"Point"}
}