{
  "type": "Feature",
  "properties": {
    "addr:full":"17 Tobey Village Rd Pittsford NY 14534",
    "addr:housenumber":"17",
    "addr:postcode":"14534",
    "addr:street":"Tobey Village Rd",
    "iso:country":"US",
    "sg:address":"17 Tobey Village Rd",
    "sg:city":"Pittsford",
    "sg:classifiers":[
        {
            "category":"Professional",
            "subcategory":"Business Services",
            "type":"Services"
        }
    ],
    "sg:phone":"+1 585 248 0770",
    "sg:postcode":"14534",
    "sg:province":"NY",
    "sg:tags":[
        "broker"
    ],
    "wof:name":"Vangellow & Co",
    "wof:placetype":"venue"
},
  "geometry": {"coordinates":[-77.543406,43.084978],"type":"Point"}
}