{
  "type": "Feature",
  "properties": {
    "iso:country":"US",
    "sg:address":"New York City College of Technology 300 Jay St",
    "sg:city":"Brooklyn",
    "sg:classifiers":[
        {
            "category":"Health Services",
            "subcategory":"Optometrist",
            "type":"Services"
        }
    ],
    "sg:postcode":"11201",
    "sg:province":"NY",
    "sg:website":"www.citytech.cuny.edu",
    "wof:name":"Ophthalmic Dispensing Service",
    "wof:placetype":"venue"
},
  "geometry": {"coordinates":[-73.987117,40.695564],"type":"Point"}
}