{
  "type": "Feature",
  "properties": {
    "iso:country":"US",
    "sg:address":"36 Main St",
    "sg:city":"Addison",
    "sg:classifiers":[
        {
            "category":"Personal",
            "subcategory":"Beauty Salon",
            "type":"Services"
        }
    ],
    "sg:phone":"+1   ",
    "sg:postcode":"14801",
    "sg:province":"NY",
    "sg:tags":[
        "shop"
    ],
    "wof:name":"Creative Images Too",
    "wof:placetype":"venue"
},
  "geometry": {"coordinates":[-77.23397799999999,42.106367],"type":"Point"}
}