{
  "type": "Feature",
  "properties": {
    "iso:country":"US",
    "sg:address":"121 W 27th St Ste 901",
    "sg:city":"New York",
    "sg:classifiers":[
        {
            "category":"Restaurant",
            "type":"Food & Drink"
        }
    ],
    "sg:phone":"+1 212 924 3000",
    "sg:postcode":"10001",
    "sg:province":"NY",
    "wof:name":"Bz Rights & Permissions Inc",
    "wof:placetype":"venue"
},
  "geometry": {"coordinates":[-73.991501,40.745701],"type":"Point"}
}