{
  "type": "Feature",
  "properties": {
    "iso:country":"US",
    "sg:address":"3186 Freshour Rd",
    "sg:city":"Canandaigua",
    "sg:classifiers":[
        {
            "category":"Shopping",
            "type":"Retail Goods"
        }
    ],
    "sg:phone":"+1   ",
    "sg:postcode":"14424",
    "sg:province":"NY",
    "sg:tags":[
        "farm",
        "repair",
        "machinery"
    ],
    "wof:name":"Coryn Farm Supplies Inc",
    "wof:placetype":"venue"
},
  "geometry": {"coordinates":[-77.208643,42.876047],"type":"Point"}
}