{
  "type": "Feature",
  "properties": {
    "addr:full":"480 Halstead Ave Harrison NY 10528",
    "addr:housenumber":"480",
    "addr:postcode":"10528",
    "addr:street":"Halstead Ave",
    "iso:country":"US",
    "sg:address":"480 Halstead Ave",
    "sg:city":"Harrison",
    "sg:classifiers":[
        {
            "category":"Banks & Credit Unions",
            "subcategory":"Bank",
            "type":"Services"
        }
    ],
    "sg:phone":"+1 914 835 3300",
    "sg:postcode":"10528",
    "sg:province":"NY",
    "wof:name":"Harrison Teachers Federal CU",
    "wof:placetype":"venue"
},
  "geometry": {"coordinates":[-73.707976,40.969882],"type":"Point"}
}