{
  "type": "Feature",
  "properties": {
    "iso:country":"US",
    "sg:address":"100 Voice Rd",
    "sg:city":"Carle Place",
    "sg:classifiers":[
        {
            "category":"Retail",
            "subcategory":"Repair Shop",
            "type":"Services"
        }
    ],
    "sg:phone":"+1 516 747 2347",
    "sg:postcode":"11514",
    "sg:province":"NY",
    "sg:tags":[
        "plumbing",
        "drain",
        "cleaning",
        "sewer"
    ],
    "wof:name":"Grease Masters",
    "wof:placetype":"venue"
},
  "geometry": {"coordinates":[-73.621022,40.746791],"type":"Point"}
}