{
  "type": "Feature",
  "properties": {
    "addr:full":"11 Wall Street Huntington NY 11743",
    "addr:housenumber":"11",
    "addr:postcode":"11743",
    "addr:street":"Wall Street",
    "iso:country":"US",
    "sg:address":"11 Wall Street",
    "sg:city":"Huntington",
    "sg:classifiers":[
        {
            "category":"Bakery",
            "type":"Food & Drink"
        }
    ],
    "sg:postcode":"11743",
    "sg:province":"NY",
    "sg:website":"www.crumbsbakeshop.com/",
    "wof:name":"Crumbs Bake Shop",
    "wof:placetype":"venue"
},
  "geometry": {"coordinates":[-73.42775899999999,40.871683],"type":"Point"}
}