{
  "type": "Feature",
  "properties": {
    "addr:full":"27 Jesse St Freeport NY 11520",
    "addr:housenumber":"27",
    "addr:postcode":"11520",
    "addr:street":"Jesse St",
    "iso:country":"US",
    "sg:address":"27 Jesse St",
    "sg:city":"Freeport",
    "sg:classifiers":[
        {
            "category":"Education",
            "subcategory":"Dance Studio",
            "type":"Public Place"
        }
    ],
    "sg:phone":"+1 516 223 7896",
    "sg:postcode":"11520",
    "sg:province":"NY",
    "sg:tags":[
        "instruction",
        "dancing"
    ],
    "wof:name":"De Vore C",
    "wof:placetype":"venue"
},
  "geometry": {"coordinates":[-73.57304999999999,40.663169],"type":"Point"}
}