{
  "type": "Feature",
  "properties": {
    "addr:full":"268 Clinton St Brooklyn NY 11201",
    "addr:housenumber":"268",
    "addr:postcode":"11201",
    "addr:street":"Clinton St",
    "iso:country":"US",
    "sg:address":"268 Clinton St",
    "sg:city":"Brooklyn",
    "sg:classifiers":[
        {
            "category":"Restaurant",
            "type":"Food & Drink"
        }
    ],
    "sg:phone":"+1 718 625 5908",
    "sg:postcode":"11201",
    "sg:province":"NY",
    "wof:name":"Cafe on Clinton",
    "wof:placetype":"venue"
},
  "geometry": {"coordinates":[-73.995593,40.687727],"type":"Point"}
}