{
  "type": "Feature",
  "properties": {
    "iso:country":"US",
    "sg:address":"59 Harrison Ave",
    "sg:city":"Delmar",
    "sg:classifiers":[
        {
            "category":"Professional",
            "subcategory":"Art Services",
            "type":"Services"
        }
    ],
    "sg:phone":"+1 518 439 9132",
    "sg:postcode":"12054",
    "sg:province":"NY",
    "sg:tags":[
        "antique",
        "repair",
        "restoration"
    ],
    "wof:name":"Unfinished Basement",
    "wof:placetype":"venue"
},
  "geometry": {"coordinates":[-73.81781700000001,42.618046],"type":"Point"}
}