{
  "type": "Feature",
  "properties": {
    "addr:full":"266 Prospect Place Brooklyn NY 11238",
    "addr:housenumber":"266",
    "addr:postcode":"11238",
    "addr:street":"Prospect Place",
    "iso:country":"US",
    "sg:address":"266 Prospect Place",
    "sg:city":"Brooklyn",
    "sg:classifiers":[
        {
            "category":"Retail",
            "subcategory":"Portrait Studio",
            "type":"Services"
        },
        {
            "category":"Professional",
            "subcategory":"Art Services",
            "type":"Services"
        }
    ],
    "sg:phone":"+1 212 473 8485",
    "sg:postcode":"11238",
    "sg:province":"NY",
    "sg:tags":[
        "photographer",
        "photography",
        "store"
    ],
    "wof:name":"Morris Leonard Photg",
    "wof:placetype":"venue"
},
  "geometry": {"coordinates":[-73.965611,40.676871],"type":"Point"}
}