{
  "type": "Feature",
  "properties": {
    "iso:country":"US",
    "sg:address":"505 Mitchell Ave",
    "sg:city":"Syracuse",
    "sg:classifiers":[
        {
            "category":"Building & Trades",
            "subcategory":"Construction",
            "type":"Services"
        }
    ],
    "sg:phone":"+1 315 455 3233",
    "sg:postcode":"13208",
    "sg:province":"NY",
    "sg:tags":[
        "siding",
        "contractor"
    ],
    "wof:name":"Brightview Remodeling Contrs",
    "wof:placetype":"venue"
},
  "geometry": {"coordinates":[-76.140978,43.090906],"type":"Point"}
}