{
  "type": "Feature",
  "properties": {
    "addr:full":"381 Broadway New York NY 10013",
    "addr:housenumber":"381",
    "addr:postcode":"10013",
    "addr:street":"Broadway",
    "iso:country":"US",
    "sg:address":"381 Broadway",
    "sg:city":"New York",
    "sg:classifiers":[
        {
            "category":"Restaurant",
            "type":"Food & Drink"
        }
    ],
    "sg:phone":"+1 212 226 3969",
    "sg:postcode":"10013",
    "sg:province":"NY",
    "wof:name":"WOW Cafe",
    "wof:placetype":"venue"
},
  "geometry": {"coordinates":[-74.00309799999999,40.718201],"type":"Point"}
}