{
  "type": "Feature",
  "properties": {
    "addr:full":"14218 38th Ave Flushing NY 11354",
    "addr:housenumber":"14218",
    "addr:postcode":"11354",
    "addr:street":"38Th Ave",
    "iso:country":"US",
    "sg:address":"14218 38th Ave",
    "sg:city":"Flushing",
    "sg:classifiers":[
        {
            "category":"Health Services",
            "subcategory":"Doctor",
            "type":"Services"
        },
        {
            "category":"Health Services",
            "subcategory":"Clinic",
            "type":"Services"
        },
        {
            "category":"Community Center",
            "type":"Public Place"
        }
    ],
    "sg:phone":"+1 718 661 0055",
    "sg:postcode":"11354",
    "sg:province":"NY",
    "sg:tags":[
        "medical"
    ],
    "wof:name":"Unitedmedical Diagnostic",
    "wof:placetype":"venue"
},
  "geometry": {"coordinates":[-73.825785,40.761804],"type":"Point"}
}