{
  "type": "Feature",
  "properties": {
    "addr:full":"241 W 37th St Rm 718 New York NY 10018",
    "addr:housenumber":"241;718",
    "addr:postcode":"10018",
    "addr:street":"W 37Th St Rm",
    "iso:country":"US",
    "sg:address":"241 W 37th St Rm 718",
    "sg:city":"New York",
    "sg:classifiers":[
        {
            "category":"Shopping",
            "subcategory":"Jewelry",
            "type":"Retail Goods"
        }
    ],
    "sg:phone":"+1 212 575 5015",
    "sg:postcode":"10018",
    "sg:province":"NY",
    "sg:website":"www.gemstoneking.net",
    "wof:name":"Gem Stone King",
    "wof:placetype":"venue"
},
  "geometry": {"coordinates":[-73.990314,40.753528],"type":"Point"}
}