{
  "type": "Feature",
  "properties": {
    "addr:full":"1 Schwab Rd Melville NY 11747",
    "addr:housenumber":"1",
    "addr:postcode":"11747",
    "addr:street":"Schwab Rd",
    "iso:country":"US",
    "sg:address":"1 Schwab Rd",
    "sg:city":"Melville",
    "sg:classifiers":[
        {
            "category":"Banks & Credit Unions",
            "subcategory":"Bank",
            "type":"Services"
        }
    ],
    "sg:phone":"+1 631 351 9700",
    "sg:postcode":"11747",
    "sg:province":"NY",
    "sg:tags":[
        "loan",
        "real estate"
    ],
    "wof:name":"Dupont Funding Co",
    "wof:placetype":"venue"
},
  "geometry": {"coordinates":[-73.41030000000001,40.814705],"type":"Point"}
}