{
  "type": "Feature",
  "properties": {
    "addr:full":"99 Clay Pitts Rd Greenlawn NY 11740",
    "addr:housenumber":"99",
    "addr:postcode":"11740",
    "addr:street":"Clay Pitts Rd",
    "iso:country":"US",
    "sg:address":"99 Clay Pitts Rd",
    "sg:city":"Greenlawn",
    "sg:classifiers":[
        {
            "category":"Professional",
            "type":"Services"
        }
    ],
    "sg:phone":"+1   ",
    "sg:postcode":"11740",
    "sg:province":"NY",
    "wof:name":"Tu-Lin Enterpries",
    "wof:placetype":"venue"
},
  "geometry": {"coordinates":[-73.34872799999999,40.863837],"type":"Point"}
}