{
  "type": "Feature",
  "properties": {
    "iso:country":"US",
    "sg:address":"150 French Rd",
    "sg:city":"Rochester",
    "sg:classifiers":[
        {
            "category":"Real Estate",
            "subcategory":"Real Estate Services",
            "type":"Services"
        },
        {
            "category":"Real Estate",
            "subcategory":"Real Estate Agent",
            "type":"Services"
        }
    ],
    "sg:phone":"+1 585 389 1910",
    "sg:postcode":"14618",
    "sg:province":"NY",
    "sg:tags":[
        "buyer",
        "broker"
    ],
    "wof:name":"Sheila Walsh Realty Inc",
    "wof:placetype":"venue"
},
  "geometry": {"coordinates":[-77.52923,43.102328],"type":"Point"}
}