{
  "type": "Feature",
  "properties": {
    "iso:country":"US",
    "sg:address":"250 W 57th St Ste 1500",
    "sg:city":"New York",
    "sg:classifiers":[
        {
            "category":"Sports & Exercise",
            "subcategory":"Gym",
            "type":"Entertainment"
        }
    ],
    "sg:phone":"+1 212 974 0555",
    "sg:postcode":"10107",
    "sg:province":"NY",
    "sg:tags":[
        "trainer"
    ],
    "wof:name":"Manhattan Health Svces",
    "wof:placetype":"venue"
},
  "geometry": {"coordinates":[-73.982212,40.766279],"type":"Point"}
}