{
  "type": "Feature",
  "properties": {
    "iso:country":"US",
    "sg:address":"200 Mamaroneck Ave",
    "sg:city":"White Plains",
    "sg:classifiers":[
        {
            "category":"Professional",
            "subcategory":"Detective & Security Services",
            "type":"Services"
        }
    ],
    "sg:phone":"+1 914 686 0770",
    "sg:postcode":"10601",
    "sg:province":"NY",
    "sg:tags":[
        "guard",
        "patrol"
    ],
    "wof:name":"Stellar Security Solutions",
    "wof:placetype":"venue"
},
  "geometry": {"coordinates":[-73.76500799999999,41.02834],"type":"Point"}
}