{
  "type": "Feature",
  "properties": {
    "addr:full":"330 Old Country Road Suite 207 Mineola NY 11501",
    "addr:housenumber":"330",
    "addr:postcode":"11501",
    "addr:street":"Old Country Road Suite 207",
    "iso:country":"US",
    "sg:address":"330 Old Country Road Suite 207",
    "sg:city":"Mineola",
    "sg:classifiers":[
        {
            "category":"Professional",
            "subcategory":"Computer Services",
            "type":"Services"
        }
    ],
    "sg:phone":"+1 516 328 9473",
    "sg:postcode":"11501",
    "sg:province":"NY",
    "sg:website":"http://www.fatwire.com/",
    "wof:name":"Fatwire",
    "wof:placetype":"venue"
},
  "geometry": {"coordinates":[-73.63571399999999,40.73959],"type":"Point"}
}