{
  "type": "Feature",
  "properties": {
    "addr:full":"1 Pondfield Rd Bronxville NY 10708",
    "addr:housenumber":"1",
    "addr:postcode":"10708",
    "addr:street":"Pondfield Rd",
    "iso:country":"US",
    "sg:address":"1 Pondfield Rd",
    "sg:city":"Bronxville",
    "sg:classifiers":[
        {
            "category":"Health Services",
            "subcategory":"Doctor",
            "type":"Services"
        }
    ],
    "sg:phone":"+1 914 337 0434",
    "sg:postcode":"10708",
    "sg:province":"NY",
    "sg:tags":[
        "physician",
        "surgeon"
    ],
    "wof:name":"Professional Anesthesiology",
    "wof:placetype":"venue"
},
  "geometry": {"coordinates":[-73.83471299999999,40.941615],"type":"Point"}
}