{
  "type": "Feature",
  "properties": {
    "addr:full":"503 Cary Ave Staten Island NY 10310",
    "addr:housenumber":"503",
    "addr:postcode":"10310",
    "addr:street":"Cary Ave",
    "iso:country":"US",
    "sg:address":"503 Cary Ave",
    "sg:city":"Staten Island",
    "sg:classifiers":[
        {
            "category":"Building & Trades",
            "subcategory":"Construction",
            "type":"Services"
        }
    ],
    "sg:phone":"+1 718 448 7000",
    "sg:postcode":"10310",
    "sg:province":"NY",
    "sg:tags":[
        "pole",
        "line",
        "contractor"
    ],
    "sg:website":"www.micsinc.net",
    "wof:name":"Mulvihill Electric Co",
    "wof:placetype":"venue"
},
  "geometry": {"coordinates":[-74.118694,40.632544],"type":"Point"}
}