{
  "type": "Feature",
  "properties": {
    "iso:country":"US",
    "sg:address":"88 Hunns Lake Rd",
    "sg:city":"Stanfordville",
    "sg:classifiers":[
        {
            "category":"Travel",
            "subcategory":"Hotels & Motels",
            "type":"Entertainment"
        }
    ],
    "sg:phone":"+1 845 868 1665",
    "sg:postcode":"12567",
    "sg:province":"NY",
    "sg:tags":[
        "breakfast",
        "accommodation",
        "bed"
    ],
    "wof:name":"Bullis Hall",
    "wof:placetype":"venue"
},
  "geometry": {"coordinates":[-73.62516599999999,41.906161],"type":"Point"}
}