{
  "type": "Feature",
  "properties": {
    "iso:country":"US",
    "sg:address":"2335 US Hwy 11",
    "sg:city":"Kirkwood",
    "sg:classifiers":[
        {
            "category":"Building & Trades",
            "subcategory":"Construction",
            "type":"Services"
        }
    ],
    "sg:phone":"+1 607 772 4866",
    "sg:postcode":"13795",
    "sg:province":"NY",
    "sg:tags":[
        "restoration",
        "cleaning",
        "patio",
        "deck"
    ],
    "wof:name":"All Bright Svc Restoration",
    "wof:placetype":"venue"
},
  "geometry": {"coordinates":[-75.766657,42.009203],"type":"Point"}
}