{
  "type": "Feature",
  "properties": {
    "addr:full":"99 Harvard St Hempstead NY 11550",
    "addr:housenumber":"99",
    "addr:postcode":"11550",
    "addr:street":"Harvard St",
    "iso:country":"US",
    "sg:address":"99 Harvard St",
    "sg:city":"Hempstead",
    "sg:classifiers":[
        {
            "category":"Shopping",
            "subcategory":"Crafts & Fabrics",
            "type":"Retail Goods"
        }
    ],
    "sg:phone":"+1 516 483 1702",
    "sg:postcode":"11550",
    "sg:province":"NY",
    "sg:tags":[
        "art",
        "supply"
    ],
    "wof:name":"Crafting Incorporated",
    "wof:placetype":"venue"
},
  "geometry": {"coordinates":[-73.61634100000001,40.714673],"type":"Point"}
}