{
  "type": "Feature",
  "properties": {
    "addr:full":"2200 Military Rd Niagara Falls NY 14304",
    "addr:housenumber":"2200",
    "addr:postcode":"14304",
    "addr:street":"Military Rd",
    "iso:country":"US",
    "sg:address":"2200 Military Rd",
    "sg:city":"Niagara Falls",
    "sg:classifiers":[
        {
            "category":"Utilities",
            "subcategory":"Mobile Phone",
            "type":"Services"
        }
    ],
    "sg:phone":"+1   ",
    "sg:postcode":"14304",
    "sg:province":"NY",
    "sg:tags":[
        "paging"
    ],
    "wof:name":"Global Paging",
    "wof:placetype":"venue"
},
  "geometry": {"coordinates":[-78.977491,43.099591],"type":"Point"}
}