{
  "type": "Feature",
  "properties": {
    "addr:full":"3 Galwood Dr Rochester NY 14622",
    "addr:housenumber":"3",
    "addr:postcode":"14622",
    "addr:street":"Galwood Dr",
    "iso:country":"US",
    "sg:address":"3 Galwood Dr",
    "sg:city":"Rochester",
    "sg:phone":"+1 585 288 0360",
    "sg:postcode":"14622",
    "sg:province":"NY",
    "sg:tags":[
        "purchase",
        "industrial",
        "supply",
        "point",
        "equipment",
        "electronics"
    ],
    "sg:website":"http://www.bluestaroh.com",
    "wof:name":"Bluestar",
    "wof:placetype":"venue"
},
  "geometry": {"coordinates":[-77.574825,43.20639],"type":"Point"}
}