{
  "type": "Feature",
  "properties": {
    "addr:full":"8622 5th Ave Brooklyn NY 11209",
    "addr:housenumber":"8622",
    "addr:postcode":"11209",
    "addr:street":"5Th Ave",
    "iso:country":"US",
    "sg:address":"8622 5th Ave",
    "sg:city":"Brooklyn",
    "sg:classifiers":[
        {
            "category":"Retail",
            "subcategory":"Portrait Studio",
            "type":"Services"
        }
    ],
    "sg:phone":"+1 718 680 7070",
    "sg:postcode":"11209",
    "sg:province":"NY",
    "sg:tags":[
        "photography",
        "store"
    ],
    "wof:name":"Eastman Wireless",
    "wof:placetype":"venue"
},
  "geometry": {"coordinates":[-74.026664,40.620994],"type":"Point"}
}