{
  "type": "Feature",
  "properties": {
    "addr:full":"142 Roslyn Rd Roslyn Heights NY 11577",
    "addr:housenumber":"142",
    "addr:postcode":"11577",
    "addr:street":"Roslyn Rd",
    "iso:country":"US",
    "sg:address":"142 Roslyn Rd",
    "sg:city":"Roslyn Heights",
    "sg:classifiers":[
        {
            "category":"Wholesale",
            "subcategory":"Non-durable Goods",
            "type":"Manufacturing & Wholesale Goods"
        }
    ],
    "sg:phone":"+1 516 484 4130",
    "sg:postcode":"11577",
    "sg:province":"NY",
    "wof:name":"Son Imports Ltd",
    "wof:placetype":"venue"
},
  "geometry": {"coordinates":[-73.639624,40.787577],"type":"Point"}
}