{
  "type": "Feature",
  "properties": {
    "iso:country":"US",
    "sg:address":"28 E 8th St",
    "sg:city":"New York",
    "sg:classifiers":[
        {
            "category":"Food & Beverages",
            "subcategory":"Bakery",
            "type":"Retail Goods"
        }
    ],
    "sg:phone":"+1 212 358 0286",
    "sg:postcode":"10003",
    "sg:province":"NY",
    "sg:tags":[
        "sandwich"
    ],
    "wof:name":"Subway Sandwiches",
    "wof:placetype":"venue"
},
  "geometry": {"coordinates":[-73.994941,40.73151],"type":"Point"}
}