{
  "type": "Feature",
  "properties": {
    "addr:full":"440 9th Ave Watervliet NY 12189",
    "addr:housenumber":"440",
    "addr:postcode":"12189",
    "addr:street":"9Th Ave",
    "iso:country":"US",
    "sg:address":"440 9th Ave",
    "sg:city":"Watervliet",
    "sg:classifiers":[
        {
            "category":"Professional",
            "subcategory":"Advertising",
            "type":"Services"
        }
    ],
    "sg:phone":"+1 518 404 1281",
    "sg:postcode":"12189",
    "sg:province":"NY",
    "sg:tags":[
        "medium",
        "buying"
    ],
    "wof:name":"Daily Candy",
    "wof:placetype":"venue"
},
  "geometry": {"coordinates":[-73.713302,42.712545],"type":"Point"}
}