{
  "type": "Feature",
  "properties": {
    "iso:country":"US",
    "sg:address":"1226 E 35th St",
    "sg:city":"Brooklyn",
    "sg:classifiers":[
        {
            "category":"Local Transit",
            "type":"Transportation"
        }
    ],
    "sg:phone":"+1 718 252 1618",
    "sg:postcode":"11210",
    "sg:province":"NY",
    "sg:tags":[
        "ambulance"
    ],
    "wof:name":"East Midwood Volunteer Amblnc",
    "wof:placetype":"venue"
},
  "geometry": {"coordinates":[-73.941394,40.62314],"type":"Point"}
}