{
  "type": "Feature",
  "properties": {
    "addr:full":"19 Bridle Ln Dryden NY 13053",
    "addr:housenumber":"19",
    "addr:postcode":"13053",
    "addr:street":"Bridle Ln",
    "iso:country":"US",
    "sg:address":"19 Bridle Ln",
    "sg:city":"Dryden",
    "sg:classifiers":[
        {
            "category":"Insurance",
            "subcategory":"Hazard Insurance",
            "type":"Services"
        }
    ],
    "sg:phone":"+1 607 844 8022",
    "sg:postcode":"13053",
    "sg:province":"NY",
    "wof:name":"Doug & Melissa Tesoriero",
    "wof:placetype":"venue"
},
  "geometry": {"coordinates":[-76.297849,42.478063],"type":"Point"}
}