{
  "type": "Feature",
  "properties": {
    "iso:country":"US",
    "sg:address":"110 Cuttermill Rd",
    "sg:city":"Great Neck",
    "sg:classifiers":[
        {
            "category":"Professional",
            "type":"Services"
        }
    ],
    "sg:phone":"+1 516 466 4964",
    "sg:postcode":"11021",
    "sg:province":"NY",
    "sg:tags":[
        "establishment"
    ],
    "wof:name":"Earth Tec Inc",
    "wof:placetype":"venue"
},
  "geometry": {"coordinates":[-73.733998,40.782539],"type":"Point"}
}