{
  "type": "Feature",
  "properties": {
    "addr:full":"14 Gansevoort Blvd Staten Island NY 10314",
    "addr:housenumber":"14",
    "addr:postcode":"10314",
    "addr:street":"Gansevoort Blvd",
    "iso:country":"US",
    "sg:address":"14 Gansevoort Blvd",
    "sg:city":"Staten Island",
    "sg:classifiers":[
        {
            "category":"Social Services",
            "type":"Services"
        }
    ],
    "sg:phone":"+1 718 761 4498",
    "sg:postcode":"10314",
    "sg:province":"NY",
    "sg:tags":[
        "worker"
    ],
    "wof:name":"Team Staten Island",
    "wof:placetype":"venue"
},
  "geometry": {"coordinates":[-74.127644,40.610978],"type":"Point"}
}