{
  "type": "Feature",
  "properties": {
    "addr:full":"576 Pacific St Brooklyn NY 11217",
    "addr:housenumber":"576",
    "addr:postcode":"11217",
    "addr:street":"Pacific St",
    "iso:country":"US",
    "sg:address":"576 Pacific St",
    "sg:city":"Brooklyn",
    "sg:classifiers":[
        {
            "category":"Professional",
            "subcategory":"Advertising",
            "type":"Services"
        }
    ],
    "sg:phone":"+1 718 638 9223",
    "sg:postcode":"11217",
    "sg:province":"NY",
    "sg:tags":[
        "counselor"
    ],
    "wof:name":"Unlimited Creative Enterprises",
    "wof:placetype":"venue"
},
  "geometry": {"coordinates":[-73.97712900000001,40.683121],"type":"Point"}
}