{
  "type": "Feature",
  "properties": {
    "addr:full":"24 S Bay Ave Amityville NY 11701",
    "addr:housenumber":"24",
    "addr:postcode":"11701",
    "addr:street":"S Bay Ave",
    "iso:country":"US",
    "sg:address":"24 S Bay Ave",
    "sg:city":"Amityville",
    "sg:classifiers":[
        {
            "category":"Building & Trades",
            "subcategory":"Construction",
            "type":"Services"
        }
    ],
    "sg:phone":"+1 631 589 2233",
    "sg:postcode":"11701",
    "sg:province":"NY",
    "sg:tags":[
        "designer",
        "dealer",
        "pool",
        "swimming"
    ],
    "wof:name":"Simply Pools",
    "wof:placetype":"venue"
},
  "geometry": {"coordinates":[-73.41807799999999,40.656527],"type":"Point"}
}