{
  "type": "Feature",
  "properties": {
    "addr:full":"77 Prospect St Binghamton NY 13905",
    "addr:housenumber":"77",
    "addr:postcode":"13905",
    "addr:street":"Prospect St",
    "iso:country":"US",
    "sg:address":"77 Prospect St",
    "sg:city":"Binghamton",
    "sg:classifiers":[
        {
            "category":"Manufacturing",
            "subcategory":"Printing",
            "type":"Manufacturing & Wholesale Goods"
        }
    ],
    "sg:phone":"+1 607 722 9522",
    "sg:postcode":"13905",
    "sg:province":"NY",
    "sg:tags":[
        "printer"
    ],
    "wof:name":"Towne & Country Press",
    "wof:placetype":"venue"
},
  "geometry": {"coordinates":[-75.91942299999999,42.112123],"type":"Point"}
}