{
  "type": "Feature",
  "properties": {
    "addr:full":"226 Franklin Pl Ste 107A Woodmere NY 11598",
    "addr:housenumber":"226;107a",
    "addr:postcode":"11598",
    "addr:street":"Franklin Pl Ste",
    "iso:country":"US",
    "sg:address":"226 Franklin Pl Ste 107A",
    "sg:city":"Woodmere",
    "sg:classifiers":[
        {
            "category":"Professional",
            "type":"Services"
        }
    ],
    "sg:phone":"+1 516 791 8000",
    "sg:postcode":"11598",
    "sg:province":"NY",
    "sg:tags":[
        "literary",
        "writer",
        "agent"
    ],
    "wof:name":"Writers & Company",
    "wof:placetype":"venue"
},
  "geometry": {"coordinates":[-73.710052,40.634934],"type":"Point"}
}