{
  "type": "Feature",
  "properties": {
    "addr:full":"40 Main St Port Washington NY 11050",
    "addr:housenumber":"40",
    "addr:postcode":"11050",
    "addr:street":"Main St",
    "iso:country":"US",
    "sg:address":"40 Main St",
    "sg:city":"Port Washington",
    "sg:classifiers":[
        {
            "category":"Personal",
            "type":"Services"
        }
    ],
    "sg:phone":"+1   ",
    "sg:postcode":"11050",
    "sg:province":"NY",
    "wof:name":"Party Favors & More",
    "wof:placetype":"venue"
},
  "geometry": {"coordinates":[-73.686393,40.830761],"type":"Point"}
}