{
  "type": "Feature",
  "properties": {
    "addr:full":"133 N Jensen Rd Vestal NY 13850",
    "addr:housenumber":"133",
    "addr:postcode":"13850",
    "addr:street":"N Jensen Rd",
    "iso:country":"US",
    "sg:address":"133 N Jensen Rd",
    "sg:city":"Vestal",
    "sg:classifiers":[
        {
            "category":"Shopping",
            "subcategory":"Clothing, Apparel, & Fashions",
            "type":"Retail Goods"
        }
    ],
    "sg:phone":"+1   ",
    "sg:postcode":"13850",
    "sg:province":"NY",
    "wof:name":"One Price Sportswear",
    "wof:placetype":"venue"
},
  "geometry": {"coordinates":[-75.995733,42.096675],"type":"Point"}
}