{
  "type": "Feature",
  "properties": {
    "addr:full":"376 Scottsville Mumford Rd Scottsville NY 14546",
    "addr:housenumber":"376",
    "addr:postcode":"14546",
    "addr:street":"Scottsville Mumford Rd",
    "iso:country":"US",
    "sg:address":"376 Scottsville Mumford Rd",
    "sg:city":"Scottsville",
    "sg:classifiers":[
        {
            "category":"Autos & Motor Vehicles",
            "subcategory":"Automobile Sales",
            "type":"Retail Goods"
        },
        {
            "category":"Retail",
            "subcategory":"Auto Repair",
            "type":"Services"
        }
    ],
    "sg:phone":"+1 585 889 8780",
    "sg:postcode":"14546",
    "sg:province":"NY",
    "sg:tags":[
        "car",
        "new"
    ],
    "wof:name":"Vintage Auto",
    "wof:placetype":"venue"
},
  "geometry": {"coordinates":[-77.76610700000001,43.01462],"type":"Point"}
}