{
  "type": "Feature",
  "properties": {
    "addr:full":"136 Ball Cir Syracuse NY 13210",
    "addr:housenumber":"136",
    "addr:postcode":"13210",
    "addr:street":"Ball Cir",
    "iso:country":"US",
    "sg:address":"136 Ball Cir",
    "sg:city":"Syracuse",
    "sg:classifiers":[
        {
            "category":"Autos & Motor Vehicles",
            "subcategory":"Automobile Sales",
            "type":"Retail Goods"
        }
    ],
    "sg:phone":"+1   ",
    "sg:postcode":"13210",
    "sg:province":"NY",
    "sg:tags":[
        "used"
    ],
    "wof:name":"Woodin Works",
    "wof:placetype":"venue"
},
  "geometry": {"coordinates":[-76.13257299999999,43.01219],"type":"Point"}
}