{
  "type": "Feature",
  "properties": {
    "addr:full":"2102 3 Ave New York NY 10029",
    "addr:housenumber":"2102",
    "addr:postcode":"10029",
    "addr:street":"3 Ave",
    "iso:country":"US",
    "sg:address":"2102 3 Ave",
    "sg:city":"New York",
    "sg:classifiers":[
        {
            "category":"Shopping",
            "subcategory":"Musical Instruments",
            "type":"Retail Goods"
        }
    ],
    "sg:phone":"+1 212 987 7323",
    "sg:postcode":"10029",
    "sg:province":"NY",
    "sg:tags":[
        "music",
        "dealer"
    ],
    "wof:name":"El Barrio Music Ctr",
    "wof:placetype":"venue"
},
  "geometry": {"coordinates":[-73.94882699999999,40.785881],"type":"Point"}
}