{
  "type": "Feature",
  "properties": {
    "iso:country":"US",
    "sg:address":"34 Audley End",
    "sg:city":"Buffalo",
    "sg:classifiers":[
        {
            "category":"Professional",
            "subcategory":"Business Services",
            "type":"Services"
        }
    ],
    "sg:phone":"+1   ",
    "sg:postcode":"14226",
    "sg:province":"NY",
    "sg:tags":[
        "interior",
        "decorating"
    ],
    "wof:name":"Audley End Interiors  LLC",
    "wof:placetype":"venue"
},
  "geometry": {"coordinates":[-78.80615299999999,42.960446],"type":"Point"}
}