{
  "type": "Feature",
  "properties": {
    "iso:country":"US",
    "sg:address":"755 Suffolk Ave",
    "sg:city":"Brentwood",
    "sg:classifiers":[
        {
            "category":"Retail",
            "subcategory":"Repair Shop",
            "type":"Services"
        }
    ],
    "sg:phone":"+1 631 231 0159",
    "sg:postcode":"11717",
    "sg:province":"NY",
    "sg:tags":[
        "jewelry"
    ],
    "wof:name":"Colombian Jewelry Repair Shop",
    "wof:placetype":"venue"
},
  "geometry": {"coordinates":[-73.24674400000001,40.781193],"type":"Point"}
}