{
  "type": "Feature",
  "properties": {
    "addr:full":"1097 Tulip Ave Franklin Square NY 11010",
    "addr:housenumber":"1097",
    "addr:postcode":"11010",
    "addr:street":"Tulip Ave",
    "iso:country":"US",
    "sg:address":"1097 Tulip Ave",
    "sg:city":"Franklin Square",
    "sg:classifiers":[
        {
            "category":"Communications",
            "type":"Services"
        }
    ],
    "sg:phone":"+1 516 437 8052",
    "sg:postcode":"11010",
    "sg:province":"NY",
    "sg:tags":[
        "recording",
        "rehearsal",
        "studio"
    ],
    "wof:name":"Adtime Media",
    "wof:placetype":"venue"
},
  "geometry": {"coordinates":[-73.679777,40.713313],"type":"Point"}
}