{
  "type": "Feature",
  "properties": {
    "addr:full":"8610 19 Ave New York NY 10001",
    "addr:housenumber":"8610",
    "addr:postcode":"10001",
    "addr:street":"19 Ave",
    "iso:country":"US",
    "sg:address":"8610 19 Ave",
    "sg:city":"New York",
    "sg:classifiers":[
        {
            "category":"Food & Beverages",
            "subcategory":"Bakery",
            "type":"Retail Goods"
        }
    ],
    "sg:phone":"+1 347 673 6789",
    "sg:postcode":"10001",
    "sg:province":"NY",
    "sg:tags":[
        "sandwich"
    ],
    "wof:name":"American Hero And Sandwich Shop",
    "wof:placetype":"venue"
},
  "geometry": {"coordinates":[-73.99777,40.751326],"type":"Point"}
}