{
  "type": "Feature",
  "properties": {
    "addr:full":"590 Ave of the Americas New York NY 10011",
    "addr:housenumber":"590",
    "addr:postcode":"10011",
    "addr:street":"Ave Of The Americas",
    "iso:country":"US",
    "sg:address":"590 Ave of the Americas",
    "sg:city":"New York",
    "sg:classifiers":[
        {
            "category":"Social Services",
            "subcategory":"Adult Care",
            "type":"Services"
        },
        {
            "category":"Health Services",
            "subcategory":"Hospital",
            "type":"Services"
        }
    ],
    "sg:phone":"+1 212 633 9300",
    "sg:postcode":"10011",
    "sg:province":"NY",
    "sg:tags":[
        "program",
        "preventive",
        "foster",
        "for",
        "child"
    ],
    "sg:website":"www.nyfoundling.org",
    "wof:name":"New York Foundling Hospital",
    "wof:placetype":"venue"
},
  "geometry": {"coordinates":[-73.995605,40.73883],"type":"Point"}
}