{
  "type": "Feature",
  "properties": {
    "iso:country":"US",
    "sg:address":"88 New Dorp Plz",
    "sg:city":"Staten Island",
    "sg:classifiers":[
        {
            "category":"Social Services",
            "type":"Services"
        }
    ],
    "sg:phone":"+1   ",
    "sg:postcode":"10306",
    "sg:province":"NY",
    "wof:name":"William Devery",
    "wof:placetype":"venue"
},
  "geometry": {"coordinates":[-74.11828800000001,40.572469],"type":"Point"}
}