{
  "type": "Feature",
  "properties": {
    "addr:full":"1028 Rte 25A Mt Sinai NY 11766",
    "addr:housenumber":"1028",
    "addr:postcode":"11766",
    "addr:street":"Rte 25A",
    "iso:country":"US",
    "sg:address":"1028 Rte 25A",
    "sg:city":"Mt Sinai",
    "sg:classifiers":[
        {
            "category":"Restaurant",
            "type":"Food & Drink"
        }
    ],
    "sg:phone":"+1 631 476 8226",
    "sg:postcode":"11766",
    "sg:province":"NY",
    "wof:name":"Senor Taco Express",
    "wof:placetype":"venue"
},
  "geometry": {"coordinates":[-72.999304,40.940582],"type":"Point"}
}