{
  "type": "Feature",
  "properties": {
    "addr:full":"37 Division St Holtsville NY 11742",
    "addr:housenumber":"37",
    "addr:postcode":"11742",
    "addr:street":"Division St",
    "iso:country":"US",
    "sg:address":"37 Division St",
    "sg:city":"Holtsville",
    "sg:classifiers":[
        {
            "category":"Building & Trades",
            "subcategory":"Construction",
            "type":"Services"
        }
    ],
    "sg:phone":"+1 631 736 5951",
    "sg:postcode":"11742",
    "sg:province":"NY",
    "sg:tags":[
        "concrete",
        "contractor"
    ],
    "wof:name":"Ralp Construction Co",
    "wof:placetype":"venue"
},
  "geometry": {"coordinates":[-73.05236499999999,40.826482],"type":"Point"}
}