{
  "type": "Feature",
  "properties": {
    "addr:full":"303 Canal St New York NY 10013",
    "addr:housenumber":"303",
    "addr:postcode":"10013",
    "addr:street":"Canal St",
    "iso:country":"US",
    "sg:address":"303 Canal St",
    "sg:city":"New York",
    "sg:classifiers":[
        {
            "category":"Professional",
            "type":"Services"
        }
    ],
    "sg:phone":"+1 212 226 1077",
    "sg:postcode":"10013",
    "sg:province":"NY",
    "sg:tags":[
        "establishment"
    ],
    "wof:name":"AHV Orient Enterprise NYC",
    "wof:placetype":"venue"
},
  "geometry": {"coordinates":[-74.002247,40.719677],"type":"Point"}
}