{
  "type": "Feature",
  "properties": {
    "iso:country":"US",
    "sg:address":"1548 Burden Lake Rd",
    "sg:city":"Averill Park",
    "sg:classifiers":[
        {
            "category":"Manufacturing",
            "subcategory":"Tools & Machinery",
            "type":"Manufacturing & Wholesale Goods"
        }
    ],
    "sg:phone":"+1 518 674 2939",
    "sg:postcode":"12018",
    "sg:province":"NY",
    "sg:tags":[
        "equipment",
        "material",
        "handling"
    ],
    "wof:name":"Worden Safety Products Inc",
    "wof:placetype":"venue"
},
  "geometry": {"coordinates":[-73.56123100000001,42.627475],"type":"Point"}
}