{
  "type": "Feature",
  "properties": {
    "addr:full":"19 Oak St Elmont NY 11003",
    "addr:housenumber":"19",
    "addr:postcode":"11003",
    "addr:street":"Oak St",
    "iso:country":"US",
    "sg:address":"19 Oak St",
    "sg:city":"Elmont",
    "sg:classifiers":[
        {
            "category":"Wholesale",
            "subcategory":"Machinery & Supplies",
            "type":"Manufacturing & Wholesale Goods"
        }
    ],
    "sg:phone":"+1 516 354 3462",
    "sg:postcode":"11003",
    "sg:province":"NY",
    "sg:tags":[
        "equipment",
        "industrial"
    ],
    "wof:name":"K T Industrial Lift Truck Svc",
    "wof:placetype":"venue"
},
  "geometry": {"coordinates":[-73.719753,40.705653],"type":"Point"}
}