{
  "type": "Feature",
  "properties": {
    "addr:full":"3160 Lake Rd Horseheads NY 14845",
    "addr:housenumber":"3160",
    "addr:postcode":"14845",
    "addr:street":"Lake Rd",
    "iso:country":"US",
    "sg:address":"3160 Lake Rd",
    "sg:city":"Horseheads",
    "sg:classifiers":[
        {
            "category":"Autos & Motor Vehicles",
            "subcategory":"Auto Supplies",
            "type":"Retail Goods"
        },
        {
            "category":"Retail",
            "subcategory":"Auto Repair",
            "type":"Services"
        }
    ],
    "sg:phone":"+1 607 733 7044",
    "sg:postcode":"14845",
    "sg:province":"NY",
    "sg:tags":[
        "recap",
        "retread",
        "tire"
    ],
    "wof:name":"Gcr Tire Centers 3220",
    "wof:placetype":"venue"
},
  "geometry": {"coordinates":[-76.81426999999999,42.14212],"type":"Point"}
}