{
  "type": "Feature",
  "properties": {
    "iso:country":"US",
    "sg:address":"10 Bank St",
    "sg:city":"White Plains",
    "sg:classifiers":[
        {
            "category":"Professional",
            "type":"Services"
        }
    ],
    "sg:phone":"+1 914 259 2220",
    "sg:postcode":"10606",
    "sg:province":"NY",
    "sg:tags":[
        "establishment"
    ],
    "wof:name":"Acciai Speciali Terni USA Inc",
    "wof:placetype":"venue"
},
  "geometry": {"coordinates":[-73.774585,41.028714],"type":"Point"}
}