{
  "type": "Feature",
  "properties": {
    "iso:country":"US",
    "sg:address":"3950 E Robinson Rd",
    "sg:city":"Amherst",
    "sg:classifiers":[
        {
            "category":"Health Services",
            "subcategory":"Doctor",
            "type":"Services"
        }
    ],
    "sg:phone":"+1 716 691 3500",
    "sg:postcode":"14228",
    "sg:province":"NY",
    "sg:tags":[
        "physician",
        "surgeon"
    ],
    "wof:name":"Amherst Ear Nose & Throat",
    "wof:placetype":"venue"
},
  "geometry": {"coordinates":[-78.81902599999999,43.036152],"type":"Point"}
}