{
  "type": "Feature",
  "properties": {
    "addr:full":"103 Berwyn Dr Camillus NY 13031",
    "addr:housenumber":"103",
    "addr:postcode":"13031",
    "addr:street":"Berwyn Dr",
    "iso:country":"US",
    "sg:address":"103 Berwyn Dr",
    "sg:city":"Camillus",
    "sg:classifiers":[
        {
            "category":"Organizations",
            "subcategory":"Religious Organization",
            "type":"Services"
        }
    ],
    "sg:phone":"+1 315 487 1355",
    "sg:postcode":"13031",
    "sg:province":"NY",
    "sg:tags":[
        "clergy"
    ],
    "wof:name":"Leonard B Whitney",
    "wof:placetype":"venue"
},
  "geometry": {"coordinates":[-76.278344,43.034322],"type":"Point"}
}