{
  "type": "Feature",
  "properties": {
    "addr:full":"3896 Richmond Ave Staten Island NY 10312",
    "addr:housenumber":"3896",
    "addr:postcode":"10312",
    "addr:street":"Richmond Ave",
    "iso:country":"US",
    "sg:address":"3896 Richmond Ave",
    "sg:city":"Staten Island",
    "sg:classifiers":[
        {
            "category":"Home & Garden",
            "subcategory":"Carpets & Floor Coverings",
            "type":"Retail Goods"
        }
    ],
    "sg:phone":"+1 718 227 8851",
    "sg:postcode":"10312",
    "sg:province":"NY",
    "sg:tags":[
        "mattress"
    ],
    "sg:website":"www.sleepys.com/",
    "wof:name":"Sleepy's, The Mattress Professionals",
    "wof:placetype":"venue"
},
  "geometry": {"coordinates":[-74.164095,40.542991],"type":"Point"}
}