{
  "type": "Feature",
  "properties": {
    "addr:full":"45 Covert Ave Floral Park NY 11001",
    "addr:housenumber":"45",
    "addr:postcode":"11001",
    "addr:street":"Covert Ave",
    "iso:country":"US",
    "sg:address":"45 Covert Ave",
    "sg:city":"Floral Park",
    "sg:classifiers":[
        {
            "category":"Arena",
            "subcategory":"Sports Club",
            "type":"Entertainment"
        }
    ],
    "sg:phone":"+1 516 354 4702",
    "sg:postcode":"11001",
    "sg:province":"NY",
    "sg:tags":[
        "martial art"
    ],
    "wof:name":"Shin's Tae Kwon DO Center",
    "wof:placetype":"venue"
},
  "geometry": {"coordinates":[-73.687698,40.7234],"type":"Point"}
}