{
  "type": "Feature",
  "properties": {
    "addr:full":"92 Ackerly Ln Ronkonkoma NY 11779",
    "addr:housenumber":"92",
    "addr:postcode":"11779",
    "addr:street":"Ackerly Ln",
    "iso:country":"US",
    "sg:address":"92 Ackerly Ln",
    "sg:city":"Ronkonkoma",
    "sg:classifiers":[
        {
            "category":"Real Estate",
            "subcategory":"Real Estate Agent",
            "type":"Services"
        }
    ],
    "sg:phone":"+1 631 585 5593",
    "sg:postcode":"11779",
    "sg:province":"NY",
    "wof:name":"Lojong International Realty Co",
    "wof:placetype":"venue"
},
  "geometry": {"coordinates":[-73.089904,40.820553],"type":"Point"}
}