{
  "type": "Feature",
  "properties": {
    "addr:full":"600 E Main St Rochester NY 14605",
    "addr:housenumber":"600",
    "addr:postcode":"14605",
    "addr:street":"E Main St",
    "iso:country":"US",
    "sg:address":"600 E Main St",
    "sg:city":"Rochester",
    "sg:classifiers":[
        {
            "category":"Restaurant",
            "type":"Food & Drink"
        }
    ],
    "sg:menulink":"http://www.allmenus.com/ny/rochester/210567-kfc---kentucky-fried-chicken/menu/",
    "sg:phone":"+1 585 546 6172",
    "sg:postcode":"14605",
    "sg:province":"NY",
    "sg:tags":[
        "american",
        "chicken"
    ],
    "wof:name":"KFC - Kentucky Fried Chicken",
    "wof:placetype":"venue"
},
  "geometry": {"coordinates":[-77.59532799999999,43.159605],"type":"Point"}
}