{
  "type": "Feature",
  "properties": {
    "iso:country":"US",
    "sg:address":"6324 14th Ave",
    "sg:city":"Brooklyn",
    "sg:classifiers":[
        {
            "category":"Food & Beverages",
            "subcategory":"Groceries & Convenience Stores",
            "type":"Retail Goods"
        }
    ],
    "sg:phone":"+1   ",
    "sg:postcode":"11219",
    "sg:province":"NY",
    "wof:name":"Cheong Kee Grocery",
    "wof:placetype":"venue"
},
  "geometry": {"coordinates":[-73.998648,40.62544],"type":"Point"}
}