{
  "type": "Feature",
  "properties": {
    "addr:full":"1449 Richmond Ter Staten Island NY 10310",
    "addr:housenumber":"1449",
    "addr:postcode":"10310",
    "addr:street":"Richmond Ter",
    "iso:country":"US",
    "sg:address":"1449 Richmond Ter",
    "sg:city":"Staten Island",
    "sg:classifiers":[
        {
            "category":"Professional",
            "subcategory":"Management & Consulting",
            "type":"Services"
        }
    ],
    "sg:phone":"+1 718 815 2749",
    "sg:postcode":"10310",
    "sg:province":"NY",
    "sg:tags":[
        "food"
    ],
    "wof:name":"Emily's Food Svc",
    "wof:placetype":"venue"
},
  "geometry": {"coordinates":[-74.116338,40.641128],"type":"Point"}
}