{
  "type": "Feature",
  "properties": {
    "addr:full":"190 Sackville Rd Garden City NY 11530",
    "addr:housenumber":"190",
    "addr:postcode":"11530",
    "addr:street":"Sackville Rd",
    "iso:country":"US",
    "sg:address":"190 Sackville Rd",
    "sg:city":"Garden City",
    "sg:classifiers":[
        {
            "category":"Shopping",
            "subcategory":"Stationery & Office Supplies",
            "type":"Retail Goods"
        },
        {
            "category":"Home & Garden",
            "subcategory":"Furniture",
            "type":"Retail Goods"
        }
    ],
    "sg:phone":"+1 516 248 4380",
    "sg:postcode":"11530",
    "sg:province":"NY",
    "sg:tags":[
        "equipment",
        "store"
    ],
    "wof:name":"Fuller Contract Accessories Corp",
    "wof:placetype":"venue"
},
  "geometry": {"coordinates":[-73.66669,40.731819],"type":"Point"}
}