{
  "type": "Feature",
  "properties": {
    "iso:country":"US",
    "sg:address":"123 Marcus Blvd",
    "sg:city":"Hauppauge",
    "sg:classifiers":[
        {
            "category":"Wholesale",
            "subcategory":"Apparel",
            "type":"Manufacturing & Wholesale Goods"
        }
    ],
    "sg:phone":"+1 631 300 1485",
    "sg:postcode":"11788",
    "sg:province":"NY",
    "sg:tags":[
        "hat"
    ],
    "wof:name":"Luna International Inc",
    "wof:placetype":"venue"
},
  "geometry": {"coordinates":[-73.246972,40.811378],"type":"Point"}
}