{
  "type": "Feature",
  "properties": {
    "iso:country":"US",
    "sg:address":"1330 Gotham St",
    "sg:city":"Watertown",
    "sg:classifiers":[
        {
            "category":"Organizations",
            "subcategory":"Religious Organization",
            "type":"Services"
        }
    ],
    "sg:phone":"+1 315 788 2742",
    "sg:postcode":"13601",
    "sg:province":"NY",
    "sg:tags":[
        "church"
    ],
    "wof:name":"All Souls Unitarian Univt Chur",
    "wof:placetype":"venue"
},
  "geometry": {"coordinates":[-75.89640799999999,43.956591],"type":"Point"}
}