{
  "type": "Feature",
  "properties": {
    "addr:full":"1999 Marcus Ave New Hyde Park NY 11042",
    "addr:housenumber":"1999",
    "addr:postcode":"11042",
    "addr:street":"Marcus Ave",
    "iso:country":"US",
    "sg:address":"1999 Marcus Ave",
    "sg:city":"New Hyde Park",
    "sg:classifiers":[
        {
            "category":"Banks & Credit Unions",
            "subcategory":"Investment Brokerage",
            "type":"Services"
        }
    ],
    "sg:phone":"+1 516 358 5700",
    "sg:postcode":"11042",
    "sg:province":"NY",
    "sg:tags":[
        "investing"
    ],
    "wof:name":"Sumitomo Corp Of America",
    "wof:placetype":"venue"
},
  "geometry": {"coordinates":[-73.69695,40.758157],"type":"Point"}
}