{
  "type": "Feature",
  "properties": {
    "iso:country":"US",
    "sg:address":"6 Cairn St",
    "sg:city":"Rochester",
    "sg:classifiers":[
        {
            "category":"Retail",
            "subcategory":"Repair Shop",
            "type":"Services"
        }
    ],
    "sg:phone":"+1 585 254 9353",
    "sg:postcode":"14611",
    "sg:province":"NY",
    "sg:tags":[
        "welding"
    ],
    "wof:name":"New York Manufacturing",
    "wof:placetype":"venue"
},
  "geometry": {"coordinates":[-77.659803,43.149659],"type":"Point"}
}