{
  "type": "Feature",
  "properties": {
    "iso:country":"US",
    "sg:address":"1515 Knox St",
    "sg:city":"Ogdensburg",
    "sg:classifiers":[
        {
            "category":"Education",
            "subcategory":"School",
            "type":"Public Place"
        }
    ],
    "sg:phone":"+1 315 393 7836",
    "sg:postcode":"13669",
    "sg:province":"NY",
    "sg:website":"www.ogdensburgk12.org/web",
    "wof:name":"Lincoln Elementary School",
    "wof:placetype":"venue"
},
  "geometry": {"coordinates":[-75.47559800000001,44.701987],"type":"Point"}
}