{
  "type": "Feature",
  "properties": {
    "addr:full":"32 Fargo Ave Buffalo NY 14201",
    "addr:housenumber":"32",
    "addr:postcode":"14201",
    "addr:street":"Fargo Ave",
    "iso:country":"US",
    "sg:address":"32 Fargo Ave",
    "sg:city":"Buffalo",
    "sg:classifiers":[
        {
            "category":"Wholesale",
            "subcategory":"Machinery & Supplies",
            "type":"Manufacturing & Wholesale Goods"
        }
    ],
    "sg:phone":"+1 716 882 3586",
    "sg:postcode":"14201",
    "sg:province":"NY",
    "sg:tags":[
        "equipment",
        "establishment"
    ],
    "wof:name":"Broadway Beauty Supply",
    "wof:placetype":"venue"
},
  "geometry": {"coordinates":[-78.886039,42.898403],"type":"Point"}
}