{
  "type": "Feature",
  "properties": {
    "iso:country":"US",
    "sg:address":"120 Black Rd",
    "sg:city":"Arkville",
    "sg:classifiers":[
        {
            "category":"Building & Trades",
            "subcategory":"Construction",
            "type":"Services"
        }
    ],
    "sg:phone":"+1 845 586 3523",
    "sg:postcode":"12481",
    "sg:province":"NY",
    "sg:tags":[
        "painter"
    ],
    "wof:name":"R & M Mc Vitty",
    "wof:placetype":"venue"
},
  "geometry": {"coordinates":[-74.222735,41.982275],"type":"Point"}
}