{
  "type": "Feature",
  "properties": {
    "iso:country":"US",
    "sg:address":"2545 State Hwy 9",
    "sg:city":"Ballston Spa",
    "sg:classifiers":[
        {
            "category":"Autos & Motor Vehicles",
            "subcategory":"Motorcycle Sales",
            "type":"Retail Goods"
        }
    ],
    "sg:phone":"+1   ",
    "sg:postcode":"12020",
    "sg:province":"NY",
    "wof:name":"T J Cycle Quad & Kart Shoppe",
    "wof:placetype":"venue"
},
  "geometry": {"coordinates":[-73.791854,42.973329],"type":"Point"}
}