{
  "type": "Feature",
  "properties": {
    "iso:country":"US",
    "sg:address":"24 Sherwood Dr",
    "sg:city":"Port Washington",
    "sg:classifiers":[
        {
            "category":"Professional",
            "subcategory":"Management & Consulting",
            "type":"Services"
        }
    ],
    "sg:phone":"+1 516 883 3314",
    "sg:postcode":"11050",
    "sg:province":"NY",
    "wof:name":"G M M Corporation",
    "wof:placetype":"venue"
},
  "geometry": {"coordinates":[-73.684697,40.857249],"type":"Point"}
}