{
  "type": "Feature",
  "properties": {
    "addr:full":"250 W 19th St New York NY 10011",
    "addr:housenumber":"250",
    "addr:postcode":"10011",
    "addr:street":"W 19Th St",
    "iso:country":"US",
    "sg:address":"250 W 19th St",
    "sg:city":"New York",
    "sg:classifiers":[
        {
            "category":"Personal",
            "subcategory":"Tanning Parlor",
            "type":"Services"
        }
    ],
    "sg:phone":"+1 212 620 0070",
    "sg:postcode":"10011",
    "sg:province":"NY",
    "wof:name":"S & G",
    "wof:placetype":"venue"
},
  "geometry": {"coordinates":[-73.999172,40.742357],"type":"Point"}
}