{
  "type": "Feature",
  "properties": {
    "iso:country":"US",
    "sg:address":"100 Thompson St",
    "sg:city":"Fayetteville",
    "sg:classifiers":[
        {
            "category":"Wholesale",
            "subcategory":"Electrical",
            "type":"Manufacturing & Wholesale Goods"
        }
    ],
    "sg:phone":"+1 315 637 0511",
    "sg:postcode":"13066",
    "sg:province":"NY",
    "sg:tags":[
        "equipment",
        "representative",
        "for"
    ],
    "wof:name":"Talbot Mills Company",
    "wof:placetype":"venue"
},
  "geometry": {"coordinates":[-76.014636,43.028276],"type":"Point"}
}