{
  "type": "Feature",
  "properties": {
    "addr:full":"3360 Big Tree Rd Hamburg NY 14075",
    "addr:housenumber":"3360",
    "addr:postcode":"14075",
    "addr:street":"Big Tree Rd",
    "iso:country":"US",
    "sg:address":"3360 Big Tree Rd",
    "sg:city":"Hamburg",
    "sg:classifiers":[
        {
            "category":"Restaurant",
            "type":"Food & Drink"
        }
    ],
    "sg:phone":"+1   ",
    "sg:postcode":"14075",
    "sg:province":"NY",
    "sg:tags":[
        "eating"
    ],
    "wof:name":"Red Top Hots",
    "wof:placetype":"venue"
},
  "geometry": {"coordinates":[-78.86240100000001,42.773276],"type":"Point"}
}