{
  "type": "Feature",
  "properties": {
    "addr:full":"239 E 53rd St New York NY 10022",
    "addr:housenumber":"239",
    "addr:postcode":"10022",
    "addr:street":"E 53Rd St",
    "iso:country":"US",
    "sg:address":"239 E 53rd St",
    "sg:city":"New York",
    "sg:classifiers":[
        {
            "category":"Personal",
            "subcategory":"Hair Removal",
            "type":"Services"
        }
    ],
    "sg:phone":"+1 212 826 5090",
    "sg:postcode":"10022",
    "sg:province":"NY",
    "sg:website":"www.arhairsalon.com",
    "wof:name":"AR Hair Salon",
    "wof:placetype":"venue"
},
  "geometry": {"coordinates":[-73.96772900000001,40.757256],"type":"Point"}
}