{
  "type": "Feature",
  "properties": {
    "iso:country":"US",
    "sg:address":"330 5th Ave",
    "sg:city":"New York",
    "sg:classifiers":[
        {
            "category":"Shopping",
            "subcategory":"Shoes",
            "type":"Retail Goods"
        }
    ],
    "sg:phone":"+1   ",
    "sg:postcode":"10001",
    "sg:province":"NY",
    "sg:tags":[
        "shoe",
        "store"
    ],
    "wof:name":"Kenneth Cole Productions Inc",
    "wof:placetype":"venue"
},
  "geometry": {"coordinates":[-73.985282,40.747498],"type":"Point"}
}