{
  "type": "Feature",
  "properties": {
    "iso:country":"US",
    "sg:address":"702 E 180th St",
    "sg:city":"Bronx",
    "sg:classifiers":[
        {
            "category":"Insurance",
            "subcategory":"Insurance Agent",
            "type":"Services"
        }
    ],
    "sg:phone":"+1 718 733 3101",
    "sg:postcode":"10457",
    "sg:province":"NY",
    "wof:name":"Marrero Insurance Agency",
    "wof:placetype":"venue"
},
  "geometry": {"coordinates":[-73.88788599999999,40.847592],"type":"Point"}
}