{
  "type": "Feature",
  "properties": {
    "addr:full":"313 E 53 St New York NY 10022",
    "addr:housenumber":"313;53",
    "addr:postcode":"10022",
    "addr:street":"E",
    "iso:country":"US",
    "sg:address":"313 E 53 St",
    "sg:city":"New York",
    "sg:classifiers":[
        {
            "category":"Building & Trades",
            "subcategory":"Construction",
            "type":"Services"
        }
    ],
    "sg:phone":"+1 212 754 2400",
    "sg:postcode":"10022",
    "sg:province":"NY",
    "sg:tags":[
        "general",
        "contractor"
    ],
    "wof:name":"Liberty Management & Constr",
    "wof:placetype":"venue"
},
  "geometry": {"coordinates":[-73.964969,40.755945],"type":"Point"}
}