{
  "type": "Feature",
  "properties": {
    "iso:country":"US",
    "sg:address":"9999 Main St",
    "sg:city":"Clarence",
    "sg:classifiers":[
        {
            "category":"Shopping",
            "subcategory":"Hobbies, Toys, & Games",
            "type":"Retail Goods"
        },
        {
            "category":"Shopping",
            "subcategory":"Crafts & Fabrics",
            "type":"Retail Goods"
        }
    ],
    "sg:phone":"+1 716 759 8899",
    "sg:postcode":"14031",
    "sg:province":"NY",
    "sg:tags":[
        "shop",
        "hobby",
        "model",
        "supply"
    ],
    "wof:name":"Seneca Jct Toy Train World",
    "wof:placetype":"venue"
},
  "geometry": {"coordinates":[-78.616753,42.976299],"type":"Point"}
}