{
  "type": "Feature",
  "properties": {
    "addr:full":"2 River Ter Manhattan NY 10282",
    "addr:housenumber":"2",
    "addr:postcode":"10282",
    "addr:street":"River Ter",
    "iso:country":"US",
    "sg:address":"2 River Ter",
    "sg:city":"Manhattan",
    "sg:classifiers":[
        {
            "category":"Restaurant",
            "type":"Food & Drink"
        },
        {
            "category":"Bakery",
            "type":"Food & Drink"
        }
    ],
    "sg:phone":"+1 212 227 2300",
    "sg:postcode":"10282",
    "sg:province":"NY",
    "sg:tags":[
        "belgian"
    ],
    "sg:website":"www.lepainquotidien.com",
    "wof:name":"Le Pain Quotidien",
    "wof:placetype":"venue"
},
  "geometry": {"coordinates":[-74.01606,40.715374],"type":"Point"}
}