{
  "type": "Feature",
  "properties": {
    "iso:country":"US",
    "sg:address":"167 Village Ln",
    "sg:city":"Rochester",
    "sg:classifiers":[
        {
            "category":"Professional",
            "type":"Services"
        }
    ],
    "sg:phone":"+1   ",
    "sg:postcode":"14610",
    "sg:province":"NY",
    "wof:name":"Never Out Corp",
    "wof:placetype":"venue"
},
  "geometry": {"coordinates":[-77.552136,43.132485],"type":"Point"}
}