{
  "type": "Feature",
  "properties": {
    "addr:full":"2909 Fulton St Brooklyn NY 11207",
    "addr:housenumber":"2909",
    "addr:postcode":"11207",
    "addr:street":"Fulton St",
    "iso:country":"US",
    "sg:address":"2909 Fulton St",
    "sg:city":"Brooklyn",
    "sg:classifiers":[
        {
            "category":"Deli",
            "type":"Food & Drink"
        },
        {
            "category":"Food & Beverages",
            "subcategory":"Bakery",
            "type":"Retail Goods"
        }
    ],
    "sg:phone":"+1 718 235 2430",
    "sg:postcode":"11207",
    "sg:province":"NY",
    "sg:tags":[
        "sandwich"
    ],
    "wof:name":"Hucatan Deli Corporation",
    "wof:placetype":"venue"
},
  "geometry": {"coordinates":[-73.88825,40.678915],"type":"Point"}
}