{
  "type": "Feature",
  "properties": {
    "iso:country":"US",
    "sg:address":"6 Wildwood Cir",
    "sg:city":"Larchmont",
    "sg:classifiers":[
        {
            "category":"Banks & Credit Unions",
            "subcategory":"Investment Brokerage",
            "type":"Services"
        }
    ],
    "sg:phone":"+1 914 576 2353",
    "sg:postcode":"10538",
    "sg:province":"NY",
    "sg:tags":[
        "advisory"
    ],
    "wof:name":"Winslow Capital Inc",
    "wof:placetype":"venue"
},
  "geometry": {"coordinates":[-73.757048,40.918188],"type":"Point"}
}