{
  "type": "Feature",
  "properties": {
    "addr:full":"1 Midway Ct Endicott NY 13760",
    "addr:housenumber":"1",
    "addr:postcode":"13760",
    "addr:street":"Midway Ct",
    "iso:country":"US",
    "sg:address":"1 Midway Ct",
    "sg:city":"Endicott",
    "sg:classifiers":[
        {
            "category":"Recreation",
            "type":"Entertainment"
        }
    ],
    "sg:phone":"+1   ",
    "sg:postcode":"13760",
    "sg:province":"NY",
    "wof:name":"Peaceful Yoga",
    "wof:placetype":"venue"
},
  "geometry": {"coordinates":[-76.05949099999999,42.109024],"type":"Point"}
}