{
  "type": "Feature",
  "properties": {
    "iso:country":"US",
    "sg:address":"277 E 3rd St",
    "sg:city":"Mount Vernon",
    "sg:classifiers":[
        {
            "category":"Building & Trades",
            "subcategory":"Construction",
            "type":"Services"
        }
    ],
    "sg:phone":"+1 914 665 4293",
    "sg:postcode":"10553",
    "sg:province":"NY",
    "sg:tags":[
        "general",
        "contractor"
    ],
    "wof:name":"Mpc Contrctng",
    "wof:placetype":"venue"
},
  "geometry": {"coordinates":[-73.82482,40.909283],"type":"Point"}
}