{
  "type": "Feature",
  "properties": {
    "addr:full":"150 55th Street Brooklyn NY 11220",
    "addr:housenumber":"150",
    "addr:postcode":"11220",
    "addr:street":"55Th Street",
    "iso:country":"US",
    "sg:address":"150 55th Street",
    "sg:city":"Brooklyn",
    "sg:classifiers":[
        {
            "category":"Health Services",
            "subcategory":"Health Practitioner",
            "type":"Services"
        }
    ],
    "sg:phone":"+1 718 921 2945",
    "sg:postcode":"11220",
    "sg:province":"NY",
    "sg:tags":[
        "therapy",
        "physical"
    ],
    "wof:name":"Family Health Center Network of Lutheran Medical Center",
    "wof:placetype":"venue"
},
  "geometry": {"coordinates":[-74.020239,40.646554],"type":"Point"}
}