{
  "type": "Feature",
  "properties": {
    "addr:full":"416 E 59th Street New York NY 10022",
    "addr:housenumber":"416",
    "addr:postcode":"10022",
    "addr:street":"E 59Th Street",
    "iso:country":"US",
    "sg:address":"416 E 59th Street",
    "sg:city":"New York",
    "sg:classifiers":[
        {
            "category":"Arts & Performance",
            "subcategory":"Art Gallery",
            "type":"Entertainment"
        }
    ],
    "sg:phone":"+1 212 753 4444",
    "sg:postcode":"10022",
    "sg:province":"NY",
    "sg:website":"www.ubugallery.com",
    "wof:name":"Ubu Gallery",
    "wof:placetype":"venue"
},
  "geometry": {"coordinates":[-73.96128899999999,40.759322],"type":"Point"}
}