{
  "type": "Feature",
  "properties": {
    "iso:country":"US",
    "sg:address":"210 E 46th St",
    "sg:city":"New York",
    "sg:classifiers":[
        {
            "category":"Restaurant",
            "type":"Food & Drink"
        }
    ],
    "sg:phone":"+1 212 687 4855",
    "sg:postcode":"10017",
    "sg:province":"NY",
    "sg:tags":[
        "steakhouse"
    ],
    "sg:website":"www.sparkssteakhouse.com",
    "wof:name":"Sparks Steak House",
    "wof:placetype":"venue"
},
  "geometry": {"coordinates":[-73.97229799999999,40.752998],"type":"Point"}
}