{
  "type": "Feature",
  "properties": {
    "addr:full":"5644 S Transit Rd Lockport NY 14094",
    "addr:housenumber":"5644",
    "addr:postcode":"14094",
    "addr:street":"S Transit Rd",
    "iso:country":"US",
    "sg:address":"5644 S Transit Rd",
    "sg:city":"Lockport",
    "sg:classifiers":[
        {
            "category":"Autos & Motor Vehicles",
            "subcategory":"Auto Supplies",
            "type":"Retail Goods"
        }
    ],
    "sg:phone":"+1 716 433 1110",
    "sg:postcode":"14094",
    "sg:province":"NY",
    "sg:tags":[
        "automobile",
        "stereo",
        "radio",
        "system"
    ],
    "wof:name":"Auto 1",
    "wof:placetype":"venue"
},
  "geometry": {"coordinates":[-78.69690199999999,43.150715],"type":"Point"}
}