{
  "type": "Feature",
  "properties": {
    "iso:country":"US",
    "sg:address":"762 Grand St",
    "sg:city":"Brooklyn",
    "sg:classifiers":[
        {
            "category":"Shopping",
            "subcategory":"Bicycles & Sporting Goods",
            "type":"Retail Goods"
        }
    ],
    "sg:phone":"+1 718 384 1280",
    "sg:postcode":"11211",
    "sg:province":"NY",
    "sg:tags":[
        "equipment",
        "diver",
        "supply"
    ],
    "sg:website":"www.stingraydivers.com",
    "wof:name":"Stingray Divers",
    "wof:placetype":"venue"
},
  "geometry": {"coordinates":[-73.943217,40.711601],"type":"Point"}
}