{
  "type": "Feature",
  "properties": {
    "addr:full":"31 State Hwy 303 Tappan NY 10983",
    "addr:housenumber":"31",
    "addr:postcode":"10983",
    "addr:street":"State Hwy 303",
    "iso:country":"US",
    "sg:address":"31 State Hwy 303",
    "sg:city":"Tappan",
    "sg:classifiers":[
        {
            "category":"Shopping",
            "subcategory":"Discount & Variety Stores",
            "type":"Retail Goods"
        }
    ],
    "sg:phone":"+1 845 359 8808",
    "sg:postcode":"10983",
    "sg:province":"NY",
    "wof:name":"V & S Variety Store",
    "wof:placetype":"venue"
},
  "geometry": {"coordinates":[-73.94390799999999,41.017243],"type":"Point"}
}