{
  "type": "Feature",
  "properties": {
    "addr:full":"626 Courtlandt Avenue Bronx NY 10451",
    "addr:housenumber":"626",
    "addr:postcode":"10451",
    "addr:street":"Courtlandt Avenue",
    "iso:country":"US",
    "sg:address":"626 Courtlandt Avenue",
    "sg:city":"Bronx",
    "sg:classifiers":[
        {
            "category":"Food & Beverages",
            "subcategory":"Liquor & Beverages",
            "type":"Retail Goods"
        }
    ],
    "sg:phone":"+1 718 292 9380",
    "sg:postcode":"10451",
    "sg:province":"NY",
    "sg:tags":[
        "beer",
        "spirit",
        "wine"
    ],
    "wof:name":"J & A Liquor & Wines",
    "wof:placetype":"venue"
},
  "geometry": {"coordinates":[-73.91851699999999,40.818454],"type":"Point"}
}