{
  "type": "Feature",
  "properties": {
    "addr:full":"2 E 2nd St Jamestown NY 14701",
    "addr:housenumber":"2",
    "addr:postcode":"14701",
    "addr:street":"E 2Nd St",
    "iso:country":"US",
    "sg:address":"2 E 2nd St",
    "sg:city":"Jamestown",
    "sg:classifiers":[
        {
            "category":"Professional",
            "subcategory":"Lawyer & Legal Services",
            "type":"Services"
        }
    ],
    "sg:phone":"+1 716 483 3233",
    "sg:postcode":"14701",
    "sg:province":"NY",
    "sg:tags":[
        "attorney"
    ],
    "wof:name":"Duncanson & Assoc",
    "wof:placetype":"venue"
},
  "geometry": {"coordinates":[-79.24050099999999,42.095574],"type":"Point"}
}