{
  "type": "Feature",
  "properties": {
    "addr:full":"5 Valewood Dr New Windsor NY 12553",
    "addr:housenumber":"5",
    "addr:postcode":"12553",
    "addr:street":"Valewood Dr",
    "iso:country":"US",
    "sg:address":"5 Valewood Dr",
    "sg:city":"New Windsor",
    "sg:classifiers":[
        {
            "category":"Building & Trades",
            "subcategory":"Construction",
            "type":"Services"
        }
    ],
    "sg:phone":"+1 845 565 2696",
    "sg:postcode":"12553",
    "sg:province":"NY",
    "sg:tags":[
        "general",
        "contractor"
    ],
    "wof:name":"Golden Touch Home Improvement",
    "wof:placetype":"venue"
},
  "geometry": {"coordinates":[-74.037431,41.470992],"type":"Point"}
}