{
  "type": "Feature",
  "properties": {
    "addr:full":"1720 Avenue M Brooklyn NY 11230",
    "addr:housenumber":"1720",
    "addr:postcode":"11230",
    "addr:street":"Avenue M",
    "iso:country":"US",
    "sg:address":"1720 Avenue M",
    "sg:city":"Brooklyn",
    "sg:classifiers":[
        {
            "category":"Home & Garden",
            "subcategory":"Home Furnishings",
            "type":"Retail Goods"
        }
    ],
    "sg:phone":"+1 718 336 0366",
    "sg:postcode":"11230",
    "sg:province":"NY",
    "sg:tags":[
        "decor"
    ],
    "sg:website":"www.judislampshades.com",
    "wof:name":"Judi's Custom Lampshades",
    "wof:placetype":"venue"
},
  "geometry": {"coordinates":[-73.957397,40.618198],"type":"Point"}
}