{
  "type": "Feature",
  "properties": {
    "iso:country":"US",
    "sg:address":"111 John St",
    "sg:city":"New York",
    "sg:classifiers":[
        {
            "category":"Banks & Credit Unions",
            "subcategory":"Bank",
            "type":"Services"
        }
    ],
    "sg:phone":"+1 212 528 1622",
    "sg:postcode":"10038",
    "sg:province":"NY",
    "sg:tags":[
        "loan",
        "real estate"
    ],
    "wof:name":"Metropolitan Mortgage Banking",
    "wof:placetype":"venue"
},
  "geometry": {"coordinates":[-74.005627,40.707692],"type":"Point"}
}