{
  "type": "Feature",
  "properties": {
    "iso:country":"US",
    "sg:address":"320 E 11th St",
    "sg:city":"New York",
    "sg:classifiers":[
        {
            "category":"Shopping",
            "subcategory":"Clothing, Apparel, & Fashions",
            "type":"Retail Goods"
        }
    ],
    "sg:phone":"+1 212 598 4327",
    "sg:postcode":"10003",
    "sg:province":"NY",
    "sg:tags":[
        "clothing",
        "women's"
    ],
    "sg:website":"www.omistressmine.com",
    "wof:name":"O Mistress Mine Vintage Boutique",
    "wof:placetype":"venue"
},
  "geometry": {"coordinates":[-73.985885,40.730166],"type":"Point"}
}