{
  "type": "Feature",
  "properties": {
    "iso:country":"US",
    "sg:address":"4451 W Fairmount Ave",
    "sg:city":"Lakewood",
    "sg:classifiers":[
        {
            "category":"Shopping",
            "subcategory":"Crafts & Fabrics",
            "type":"Retail Goods"
        }
    ],
    "sg:phone":"+1 716 763 8167",
    "sg:postcode":"14750",
    "sg:province":"NY",
    "sg:tags":[
        "shop"
    ],
    "wof:name":"Calico Cat",
    "wof:placetype":"venue"
},
  "geometry": {"coordinates":[-79.351116,42.09903],"type":"Point"}
}