{
  "type": "Feature",
  "properties": {
    "addr:full":"160-20 Willets Point Blvd Queens NY 11357",
    "addr:housenumber":"160-20",
    "addr:postcode":"11357",
    "addr:street":"Willets Point Blvd",
    "iso:country":"US",
    "sg:address":"160-20 Willets Point Blvd",
    "sg:city":"Queens",
    "sg:classifiers":[
        {
            "category":"Health Services",
            "subcategory":"Health Practitioner",
            "type":"Services"
        }
    ],
    "sg:phone":"+1 718 279 4300",
    "sg:postcode":"11357",
    "sg:province":"NY",
    "sg:tags":[
        "therapy",
        "physical"
    ],
    "sg:website":"protekpt.com",
    "wof:name":"PRO-TEK Physical Therapy",
    "wof:placetype":"venue"
},
  "geometry": {"coordinates":[-73.80158,40.780629],"type":"Point"}
}