{
  "type": "Feature",
  "properties": {
    "addr:full":"317 Madison Avenue Suite 1220 New York NY 10017",
    "addr:housenumber":"317",
    "addr:postcode":"10017",
    "addr:street":"Madison Avenue Suite 1220",
    "iso:country":"US",
    "sg:address":"317 Madison Avenue Suite 1220",
    "sg:city":"New York",
    "sg:classifiers":[
        {
            "category":"Professional",
            "subcategory":"Computer Services",
            "type":"Services"
        }
    ],
    "sg:phone":"+1 646 421 2830",
    "sg:postcode":"10017",
    "sg:province":"NY",
    "sg:tags":[
        "application-server",
        "data-grid",
        "in-memory-data-grid",
        "enterprise-middleware",
        "high-availability-server",
        "low-latency",
        "scalability",
        "dynamic-scalability",
        "elastic-middleware",
        "application-server-scalability",
        "saas-enablement",
        "multi-tenancy"
    ],
    "sg:website":"http://www.gigaspaces.com/",
    "wof:name":"GigaSpaces Technologies",
    "wof:placetype":"venue"
},
  "geometry": {"coordinates":[-73.97878300000001,40.753481],"type":"Point"}
}