{
  "type": "Feature",
  "properties": {
    "iso:country":"US",
    "sg:address":"473 W End Ave",
    "sg:city":"New York",
    "sg:classifiers":[
        {
            "category":"Professional",
            "subcategory":"Computer Services",
            "type":"Services"
        }
    ],
    "sg:phone":"+1 212 724 8799",
    "sg:postcode":"10024",
    "sg:province":"NY",
    "sg:tags":[
        "related"
    ],
    "wof:name":"Rory Butler Systems Inc",
    "wof:placetype":"venue"
},
  "geometry": {"coordinates":[-73.979623,40.786475],"type":"Point"}
}