{
  "type": "Feature",
  "properties": {
    "addr:full":"3804 Prince St Flushing NY 11354",
    "addr:housenumber":"3804",
    "addr:postcode":"11354",
    "addr:street":"Prince St",
    "iso:country":"US",
    "sg:address":"3804 Prince St",
    "sg:city":"Flushing",
    "sg:classifiers":[
        {
            "category":"Restaurant",
            "type":"Food & Drink"
        }
    ],
    "sg:phone":"+1 718 353 1888",
    "sg:postcode":"11354",
    "sg:province":"NY",
    "sg:tags":[
        "thai"
    ],
    "wof:name":"Green Papaya Thai Cuisine",
    "wof:placetype":"venue"
},
  "geometry": {"coordinates":[-73.832549,40.760052],"type":"Point"}
}