{
  "type": "Feature",
  "properties": {
    "addr:full":"808 Columbus Ave. Manhattan NY 10025",
    "addr:housenumber":"808",
    "addr:postcode":"10025",
    "addr:street":"Columbus Ave.",
    "iso:country":"US",
    "sg:address":"808 Columbus Ave.",
    "sg:city":"Manhattan",
    "sg:classifiers":[
        {
            "category":"Shopping",
            "subcategory":"Beauty & Cosmetics",
            "type":"Retail Goods"
        }
    ],
    "sg:postcode":"10025",
    "sg:province":"NY",
    "sg:tags":[
        "supply"
    ],
    "sg:website":"www.sephora.com/",
    "wof:name":"Sephora",
    "wof:placetype":"venue"
},
  "geometry": {"coordinates":[-73.96665400000001,40.79467],"type":"Point"}
}