{
  "type": "Feature",
  "properties": {
    "iso:country":"US",
    "sg:address":"295 Merrick Rd",
    "sg:city":"Amityville",
    "sg:classifiers":[
        {
            "category":"Home & Garden",
            "subcategory":"Building Materials",
            "type":"Retail Goods"
        },
        {
            "category":"Building & Trades",
            "subcategory":"Construction",
            "type":"Services"
        }
    ],
    "sg:phone":"+1 631 742 4733",
    "sg:postcode":"11701",
    "sg:province":"NY",
    "sg:tags":[
        "concrete",
        "staining",
        "contractor"
    ],
    "wof:name":"Five Star Concrete",
    "wof:placetype":"venue"
},
  "geometry": {"coordinates":[-73.41021000000001,40.669241],"type":"Point"}
}