{
  "type": "Feature",
  "properties": {
    "iso:country":"US",
    "sg:address":"777 Warren Rd",
    "sg:city":"Ithaca",
    "sg:classifiers":[
        {
            "category":"Professional",
            "type":"Services"
        }
    ],
    "sg:phone":"+1 607 257 9777",
    "sg:postcode":"14850",
    "sg:province":"NY",
    "sg:tags":[
        "establishment"
    ],
    "wof:name":"Ny's Agrability",
    "wof:placetype":"venue"
},
  "geometry": {"coordinates":[-76.47082,42.49783],"type":"Point"}
}