{
  "type": "Feature",
  "properties": {
    "iso:country":"US",
    "sg:address":"628 W 158th St",
    "sg:city":"New York",
    "sg:classifiers":[
        {
            "category":"Shopping",
            "subcategory":"Clothing, Apparel, & Fashions",
            "type":"Retail Goods"
        }
    ],
    "sg:phone":"+1   ",
    "sg:postcode":"10032",
    "sg:province":"NY",
    "wof:name":"Jarrell Vintage Menswear",
    "wof:placetype":"venue"
},
  "geometry": {"coordinates":[-73.948185,40.836083],"type":"Point"}
}