{
  "type": "Feature",
  "properties": {
    "addr:full":"527 Aviation Rd Queensbury NY 12804",
    "addr:housenumber":"527",
    "addr:postcode":"12804",
    "addr:street":"Aviation Rd",
    "iso:country":"US",
    "sg:address":"527 Aviation Rd",
    "sg:city":"Queensbury",
    "sg:classifiers":[
        {
            "category":"Deli",
            "type":"Food & Drink"
        }
    ],
    "sg:menulink":"http://www.allmenus.com/ny/queensbury/126462-blimpie-subs--sandwiches/menu/",
    "sg:phone":"+1 518 745 5469",
    "sg:postcode":"12804",
    "sg:province":"NY",
    "sg:tags":[
        "wrap",
        "american",
        "sandwich"
    ],
    "wof:name":"Blimpie Subs & Sandwiches",
    "wof:placetype":"venue"
},
  "geometry": {"coordinates":[-73.68134000000001,43.330203],"type":"Point"}
}