{
  "type": "Feature",
  "properties": {
    "addr:full":"2740 Bunker Hill Rd Randolph NY 14772",
    "addr:housenumber":"2740",
    "addr:postcode":"14772",
    "addr:street":"Bunker Hill Rd",
    "iso:country":"US",
    "sg:address":"2740 Bunker Hill Rd",
    "sg:city":"Randolph",
    "sg:classifiers":[
        {
            "category":"Farming",
            "subcategory":"Dairy Farm",
            "type":"Manufacturing & Wholesale Goods"
        }
    ],
    "sg:phone":"+1 716 354 4303",
    "sg:postcode":"14772",
    "sg:province":"NY",
    "wof:name":"Horton Dairy",
    "wof:placetype":"venue"
},
  "geometry": {"coordinates":[-78.88425100000001,42.118761],"type":"Point"}
}