{
  "type": "Feature",
  "properties": {
    "addr:full":"185 State Hwy 312 Brewster NY 10509",
    "addr:housenumber":"185",
    "addr:postcode":"10509",
    "addr:street":"State Hwy 312",
    "iso:country":"US",
    "sg:address":"185 State Hwy 312",
    "sg:city":"Brewster",
    "sg:classifiers":[
        {
            "category":"Insurance",
            "subcategory":"Hazard Insurance",
            "type":"Services"
        }
    ],
    "sg:phone":"+1 845 279 2742",
    "sg:postcode":"10509",
    "sg:province":"NY",
    "sg:tags":[
        "employee",
        "benefit",
        "compensation",
        "plan"
    ],
    "wof:name":"Cobeso",
    "wof:placetype":"venue"
},
  "geometry": {"coordinates":[-73.63304599999999,41.423998],"type":"Point"}
}