{
  "type": "Feature",
  "properties": {
    "iso:country":"US",
    "sg:address":"150 Main St",
    "sg:city":"Fishkill",
    "sg:classifiers":[
        {
            "category":"Banks & Credit Unions",
            "subcategory":"Bank",
            "type":"Services"
        }
    ],
    "sg:phone":"+1 845 896 9300",
    "sg:postcode":"12524",
    "sg:province":"NY",
    "sg:website":"www.riversidebankhv.com",
    "wof:name":"Riverside Bank",
    "wof:placetype":"venue"
},
  "geometry": {"coordinates":[-73.90479999999999,41.5317],"type":"Point"}
}