{
  "type": "Feature",
  "properties": {
    "addr:full":"316 W 88 St New York NY 10024",
    "addr:housenumber":"316",
    "addr:postcode":"10024",
    "addr:street":"W 88 St",
    "iso:country":"US",
    "sg:address":"316 W 88 St",
    "sg:city":"New York",
    "sg:classifiers":[
        {
            "category":"Museum",
            "type":"Entertainment"
        }
    ],
    "sg:phone":"+1   ",
    "sg:postcode":"10024",
    "sg:province":"NY",
    "sg:tags":[
        "gallery"
    ],
    "wof:name":"Glitter Moon",
    "wof:placetype":"venue"
},
  "geometry": {"coordinates":[-73.979124,40.791007],"type":"Point"}
}