{
  "type": "Feature",
  "properties": {
    "addr:full":"3220 Bainbridge Ave Bronx NY 10467",
    "addr:housenumber":"3220",
    "addr:postcode":"10467",
    "addr:street":"Bainbridge Ave",
    "iso:country":"US",
    "sg:address":"3220 Bainbridge Ave",
    "sg:city":"Bronx",
    "sg:classifiers":[
        {
            "category":"Home & Garden",
            "subcategory":"Hardware",
            "type":"Retail Goods"
        }
    ],
    "sg:phone":"+1 718 654 9951",
    "sg:postcode":"10467",
    "sg:province":"NY",
    "wof:name":"Bainbridge Hardware Inc",
    "wof:placetype":"venue"
},
  "geometry": {"coordinates":[-73.87962899999999,40.876641],"type":"Point"}
}