{
  "type": "Feature",
  "properties": {
    "iso:country":"US",
    "sg:address":"699 Blossom Rd",
    "sg:city":"Rochester",
    "sg:classifiers":[
        {
            "category":"Retail",
            "subcategory":"Laundry & Dry Cleaning",
            "type":"Services"
        }
    ],
    "sg:phone":"+1 585 482 0860",
    "sg:postcode":"14610",
    "sg:province":"NY",
    "sg:tags":[
        "cleaners",
        "plant",
        "coin",
        "drycleaning"
    ],
    "wof:name":"Julian's Dry Cleaners",
    "wof:placetype":"venue"
},
  "geometry": {"coordinates":[-77.55138100000001,43.149338],"type":"Point"}
}