{
  "type": "Feature",
  "properties": {
    "addr:full":"48 W 21st St 7th Fl New York NY 10010",
    "addr:housenumber":"48",
    "addr:postcode":"10010",
    "addr:street":"W 21St St",
    "iso:country":"US",
    "sg:address":"48 W 21st St 7th Fl",
    "sg:city":"New York",
    "sg:classifiers":[
        {
            "category":"Health Services",
            "subcategory":"Health Practitioner",
            "type":"Services"
        }
    ],
    "sg:phone":"+1 212 242 8701",
    "sg:postcode":"10010",
    "sg:province":"NY",
    "sg:tags":[
        "acupuncture",
        "naturopathic/holistic"
    ],
    "sg:website":"www.loveandcompassion.com",
    "wof:name":"Love & Compassion Integrative Health and Healing",
    "wof:placetype":"venue"
},
  "geometry": {"coordinates":[-73.992841,40.74107],"type":"Point"}
}