{
  "type": "Feature",
  "properties": {
    "addr:full":"460 Elmridge Center Dr Rochester NY 14626",
    "addr:housenumber":"460",
    "addr:postcode":"14626",
    "addr:street":"Elmridge Center Dr",
    "iso:country":"US",
    "sg:address":"460 Elmridge Center Dr",
    "sg:city":"Rochester",
    "sg:classifiers":[
        {
            "category":"Personal",
            "subcategory":"Beauty Salon",
            "type":"Services"
        },
        {
            "category":"Personal",
            "subcategory":"Barber",
            "type":"Services"
        }
    ],
    "sg:phone":"+1 585 225 0660",
    "sg:postcode":"14626",
    "sg:province":"NY",
    "sg:tags":[
        "hair",
        "stylist"
    ],
    "sg:website":"http://www.hairzoosalons.com",
    "wof:name":"Hair Zoo Family Hair Salons",
    "wof:placetype":"venue"
},
  "geometry": {"coordinates":[-77.72947000000001,43.215439],"type":"Point"}
}