{
  "type": "Feature",
  "properties": {
    "iso:country":"US",
    "sg:address":"3212 E Main St",
    "sg:city":"Dunkirk",
    "sg:classifiers":[
        {
            "category":"Farming",
            "subcategory":"Nursery",
            "type":"Manufacturing & Wholesale Goods"
        }
    ],
    "sg:phone":"+1 716 679 9138",
    "sg:postcode":"14048",
    "sg:province":"NY",
    "sg:tags":[
        "ornamental"
    ],
    "wof:name":"Loyal Oak Greenhouses",
    "wof:placetype":"venue"
},
  "geometry": {"coordinates":[-79.269673,42.471705],"type":"Point"}
}