{
  "type": "Feature",
  "properties": {
    "iso:country":"US",
    "sg:address":"1258 Central Ave",
    "sg:city":"Albany",
    "sg:classifiers":[
        {
            "category":"Autos & Motor Vehicles",
            "subcategory":"Automobile Sales",
            "type":"Retail Goods"
        }
    ],
    "sg:phone":"+1 518 489 2111",
    "sg:postcode":"12205",
    "sg:province":"NY",
    "sg:tags":[
        "car",
        "dealer"
    ],
    "wof:name":"Lia Group Headquarters",
    "wof:placetype":"venue"
},
  "geometry": {"coordinates":[-73.810761,42.69812],"type":"Point"}
}