{
  "type": "Feature",
  "properties": {
    "addr:full":"29 N Hamilton St Poughkeepsie NY 12601",
    "addr:housenumber":"29",
    "addr:postcode":"12601",
    "addr:street":"N Hamilton St",
    "iso:country":"US",
    "sg:address":"29 N Hamilton St",
    "sg:city":"Poughkeepsie",
    "sg:classifiers":[
        {
            "category":"Health Services",
            "subcategory":"Doctor",
            "type":"Services"
        }
    ],
    "sg:phone":"+1 845 454 8204",
    "sg:postcode":"12601",
    "sg:province":"NY",
    "sg:tags":[
        "physician",
        "family",
        "practice",
        "surgeons",
        "medicine",
        "surgeon"
    ],
    "wof:name":"Hudson River Healthcare",
    "wof:placetype":"venue"
},
  "geometry": {"coordinates":[-73.922404,41.704008],"type":"Point"}
}