{
  "type": "Feature",
  "properties": {
    "iso:country":"US",
    "sg:address":"343 Genesee St Ste 3",
    "sg:city":"Auburn",
    "sg:classifiers":[
        {
            "category":"Utilities",
            "subcategory":"Electric",
            "type":"Services"
        },
        {
            "category":"Manufacturing",
            "subcategory":"Electronics",
            "type":"Manufacturing & Wholesale Goods"
        }
    ],
    "sg:phone":"+1 315 253 9789",
    "sg:postcode":"13021",
    "sg:province":"NY",
    "sg:tags":[
        "equipment-testing"
    ],
    "sg:website":"http://www.ligcomputer.com",
    "wof:name":"Bergan Electric Co Inc",
    "wof:placetype":"venue"
},
  "geometry": {"coordinates":[-76.589653,42.92025],"type":"Point"}
}