{
  "type": "Feature",
  "properties": {
    "iso:country":"US",
    "sg:address":"100 River St ",
    "sg:city":"Hastings On Hudson",
    "sg:classifiers":[
        {
            "category":"Restaurant",
            "type":"Food & Drink"
        }
    ],
    "sg:menulink":"http://www.allmenus.com/ny/greenburgh/261551-blu/menu/",
    "sg:phone":"+1 914 478 4481",
    "sg:postcode":"10706",
    "sg:province":"NY",
    "sg:tags":[
        "seafood",
        "american"
    ],
    "wof:name":"Blu",
    "wof:placetype":"venue"
},
  "geometry": {"coordinates":[-73.88454299999999,40.996304],"type":"Point"}
}