{
  "type": "Feature",
  "properties": {
    "addr:full":"1473 Myrtle Ave Brooklyn NY 11237",
    "addr:housenumber":"1473",
    "addr:postcode":"11237",
    "addr:street":"Myrtle Ave",
    "iso:country":"US",
    "sg:address":"1473 Myrtle Ave",
    "sg:city":"Brooklyn",
    "sg:classifiers":[
        {
            "category":"Home & Garden",
            "subcategory":"Furniture",
            "type":"Retail Goods"
        }
    ],
    "sg:phone":"+1 718 381 7152",
    "sg:postcode":"11237",
    "sg:province":"NY",
    "sg:tags":[
        "store"
    ],
    "wof:name":"City Living Furniture Co",
    "wof:placetype":"venue"
},
  "geometry": {"coordinates":[-73.91709899999999,40.699001],"type":"Point"}
}