{
  "type": "Feature",
  "properties": {
    "addr:full":"58 Valley Rd Larchmont NY 10538",
    "addr:housenumber":"58",
    "addr:postcode":"10538",
    "addr:street":"Valley Rd",
    "iso:country":"US",
    "sg:address":"58 Valley Rd",
    "sg:city":"Larchmont",
    "sg:classifiers":[
        {
            "category":"Professional",
            "subcategory":"Employment Agencies",
            "type":"Services"
        }
    ],
    "sg:phone":"+1   ",
    "sg:postcode":"10538",
    "sg:province":"NY",
    "wof:name":"Noble Associates",
    "wof:placetype":"venue"
},
  "geometry": {"coordinates":[-73.766001,40.940885],"type":"Point"}
}