{
  "type": "Feature",
  "properties": {
    "iso:country":"US",
    "sg:address":"294 State Hwy 7",
    "sg:city":"Sidney",
    "sg:classifiers":[
        {
            "category":"Health Services",
            "subcategory":"Chiropractor",
            "type":"Services"
        }
    ],
    "sg:phone":"+1 607 563 7333",
    "sg:postcode":"13838",
    "sg:province":"NY",
    "wof:name":"Edwards Chiropractic",
    "wof:placetype":"venue"
},
  "geometry": {"coordinates":[-75.39265899999999,42.319648],"type":"Point"}
}