{
  "type": "Feature",
  "properties": {
    "iso:country":"US",
    "sg:address":"6 Jefferson St",
    "sg:city":"East Islip",
    "sg:classifiers":[
        {
            "category":"Communications",
            "type":"Services"
        }
    ],
    "sg:phone":"+1 631 650 3962",
    "sg:postcode":"11730",
    "sg:province":"NY",
    "sg:tags":[
        "web",
        "design"
    ],
    "wof:name":"Website Corperation",
    "wof:placetype":"venue"
},
  "geometry": {"coordinates":[-73.191451,40.738356],"type":"Point"}
}