{
  "type": "Feature",
  "properties": {
    "addr:full":"3 W 35th St New York NY 10001",
    "addr:housenumber":"3",
    "addr:postcode":"10001",
    "addr:street":"W 35Th St",
    "iso:country":"US",
    "sg:address":"3 W 35th St",
    "sg:city":"New York",
    "sg:classifiers":[
        {
            "category":"Professional",
            "subcategory":"Lawyer & Legal Services",
            "type":"Services"
        }
    ],
    "sg:phone":"+1 212 947 6555",
    "sg:postcode":"10001",
    "sg:province":"NY",
    "wof:name":"Cabrera Anna M Atty",
    "wof:placetype":"venue"
},
  "geometry": {"coordinates":[-73.9842,40.749001],"type":"Point"}
}