{
  "type": "Feature",
  "properties": {
    "iso:country":"US",
    "sg:address":"395 Gateway Dr",
    "sg:city":"Brooklyn",
    "sg:classifiers":[
        {
            "category":"Wholesale",
            "subcategory":"Apparel",
            "type":"Manufacturing & Wholesale Goods"
        }
    ],
    "sg:phone":"+1 718 277 5626",
    "sg:postcode":"11239",
    "sg:province":"NY",
    "sg:tags":[
        "clothing"
    ],
    "wof:name":"Babies R Us",
    "wof:placetype":"venue"
},
  "geometry": {"coordinates":[-73.87457000000001,40.650499],"type":"Point"}
}