{
  "type": "Feature",
  "properties": {
    "addr:full":"1178 Lexington Ave New York NY 10028",
    "addr:housenumber":"1178",
    "addr:postcode":"10028",
    "addr:street":"Lexington Ave",
    "iso:country":"US",
    "sg:address":"1178 Lexington Ave",
    "sg:city":"New York",
    "sg:classifiers":[
        {
            "category":"Shopping",
            "subcategory":"Used Merchandise",
            "type":"Retail Goods"
        }
    ],
    "sg:phone":"+1 212 988 4821",
    "sg:postcode":"10028",
    "sg:province":"NY",
    "sg:tags":[
        "antique"
    ],
    "wof:name":"Agostino",
    "wof:placetype":"venue"
},
  "geometry": {"coordinates":[-73.958206,40.775942],"type":"Point"}
}