{
  "type": "Feature",
  "properties": {
    "addr:full":"530 Lakeview Park Rochester NY 14613",
    "addr:housenumber":"530",
    "addr:postcode":"14613",
    "addr:street":"Lakeview Park",
    "iso:country":"US",
    "sg:address":"530 Lakeview Park",
    "sg:city":"Rochester",
    "sg:classifiers":[
        {
            "category":"Building & Trades",
            "subcategory":"Construction",
            "type":"Services"
        }
    ],
    "sg:phone":"+1 585 458 4359",
    "sg:postcode":"14613",
    "sg:province":"NY",
    "sg:tags":[
        "wallcoverings-installation",
        "wallpaper",
        "painting",
        "contractor"
    ],
    "wof:name":"Morris Painting",
    "wof:placetype":"venue"
},
  "geometry": {"coordinates":[-77.646559,43.182561],"type":"Point"}
}