{
  "type": "Feature",
  "properties": {
    "iso:country":"US",
    "sg:address":"771 Flatbush Ave",
    "sg:city":"Brooklyn",
    "sg:classifiers":[
        {
            "category":"Restaurant",
            "type":"Food & Drink"
        }
    ],
    "sg:phone":"+1   ",
    "sg:postcode":"11226",
    "sg:province":"NY",
    "sg:tags":[
        "eating"
    ],
    "wof:name":"Danny & Pepper Jerk Chicken Ex",
    "wof:placetype":"venue"
},
  "geometry": {"coordinates":[-73.95950999999999,40.654488],"type":"Point"}
}