{
  "type": "Feature",
  "properties": {
    "iso:country":"US",
    "sg:address":"147 E Oxford St",
    "sg:city":"Valley Stream",
    "sg:classifiers":[
        {
            "category":"Building & Trades",
            "subcategory":"Construction",
            "type":"Services"
        }
    ],
    "sg:phone":"+1 516 561 2886",
    "sg:postcode":"11580",
    "sg:province":"NY",
    "sg:tags":[
        "house"
    ],
    "wof:name":"Xtreem Construction Corp",
    "wof:placetype":"venue"
},
  "geometry": {"coordinates":[-73.691401,40.664639],"type":"Point"}
}