{
  "type": "Feature",
  "properties": {
    "addr:full":"121 Ellicott St Buffalo NY 14203",
    "addr:housenumber":"121",
    "addr:postcode":"14203",
    "addr:street":"Ellicott St",
    "iso:country":"US",
    "sg:address":"121 Ellicott St",
    "sg:city":"Buffalo",
    "sg:classifiers":[
        {
            "category":"Shopping",
            "subcategory":"Books",
            "type":"Retail Goods"
        }
    ],
    "sg:phone":"+1   ",
    "sg:postcode":"14203",
    "sg:province":"NY",
    "wof:name":"City Campus Book Stores",
    "wof:placetype":"venue"
},
  "geometry": {"coordinates":[-78.87326299999999,42.881871],"type":"Point"}
}