{
  "type": "Feature",
  "properties": {
    "iso:country":"US",
    "sg:address":"500 Piermont Ave",
    "sg:city":"Piermont",
    "sg:classifiers":[
        {
            "category":"Personal",
            "subcategory":"Massage",
            "type":"Services"
        }
    ],
    "sg:phone":"+1 845 359 0740",
    "sg:postcode":"10968",
    "sg:province":"NY",
    "sg:tags":[
        "therapist"
    ],
    "wof:name":"Elements Studio Incorporated",
    "wof:placetype":"venue"
},
  "geometry": {"coordinates":[-73.91617599999999,41.040304],"type":"Point"}
}