{
  "type": "Feature",
  "properties": {
    "iso:country":"US",
    "sg:address":"10 Louis Ave",
    "sg:city":"Monsey",
    "sg:classifiers":[
        {
            "category":"Health Services",
            "subcategory":"Health Practitioner",
            "type":"Services"
        }
    ],
    "sg:phone":"+1 845 352 0293",
    "sg:postcode":"10952",
    "sg:province":"NY",
    "sg:tags":[
        "psychotherapist"
    ],
    "wof:name":"Consultation Center",
    "wof:placetype":"venue"
},
  "geometry": {"coordinates":[-74.089026,41.121336],"type":"Point"}
}