{
  "type": "Feature",
  "properties": {
    "addr:full":"925 E Henrietta Rd Rochester NY 14623",
    "addr:housenumber":"925",
    "addr:postcode":"14623",
    "addr:street":"E Henrietta Rd",
    "iso:country":"US",
    "sg:address":"925 E Henrietta Rd",
    "sg:city":"Rochester",
    "sg:classifiers":[
        {
            "category":"Health Services",
            "subcategory":"Doctor",
            "type":"Services"
        }
    ],
    "sg:phone":"+1 585 424 6400",
    "sg:postcode":"14623",
    "sg:province":"NY",
    "sg:tags":[
        "dentist"
    ],
    "sg:website":"www.toothmover.com",
    "wof:name":"Bradley D Kaufman DDS",
    "wof:placetype":"venue"
},
  "geometry": {"coordinates":[-77.614717,43.101628],"type":"Point"}
}