{
  "type": "Feature",
  "properties": {
    "addr:full":"100 Merrick Rd Ste 112E Rockville Ctr NY 11570",
    "addr:housenumber":"100",
    "addr:postcode":"11570",
    "addr:street":"Merrick Rd Ste 112E",
    "iso:country":"US",
    "sg:address":"100 Merrick Rd Ste 112E",
    "sg:city":"Rockville Ctr",
    "sg:classifiers":[
        {
            "category":"Professional",
            "subcategory":"Accounting & Tax Preparation",
            "type":"Services"
        }
    ],
    "sg:phone":"+1 516 763 1212",
    "sg:postcode":"11570",
    "sg:province":"NY",
    "sg:tags":[
        "accountant"
    ],
    "wof:name":"Rosenblum & Cohen CPA",
    "wof:placetype":"venue"
},
  "geometry": {"coordinates":[-73.647301,40.656502],"type":"Point"}
}