{
  "type": "Feature",
  "properties": {
    "iso:country":"US",
    "sg:address":"48-05 45th St",
    "sg:city":"Woodside",
    "sg:classifiers":[
        {
            "category":"Personal",
            "subcategory":"Massage",
            "type":"Services"
        },
        {
            "category":"Personal",
            "subcategory":"Hair Removal",
            "type":"Services"
        },
        {
            "category":"Personal",
            "subcategory":"Nail Salon",
            "type":"Services"
        }
    ],
    "sg:phone":"+1 718 383 1818",
    "sg:postcode":"11377",
    "sg:province":"NY",
    "wof:name":"Beauty Town Nail & Spa",
    "wof:placetype":"venue"
},
  "geometry": {"coordinates":[-73.919909,40.741753],"type":"Point"}
}