{
  "type": "Feature",
  "properties": {
    "addr:full":"14 N Pearl St Pearl River NY 10965",
    "addr:housenumber":"14",
    "addr:postcode":"10965",
    "addr:street":"N Pearl St",
    "iso:country":"US",
    "sg:address":"14 N Pearl St",
    "sg:city":"Pearl River",
    "sg:classifiers":[
        {
            "category":"Banks & Credit Unions",
            "subcategory":"Bank",
            "type":"Services"
        }
    ],
    "sg:phone":"+1 845 620 3710",
    "sg:postcode":"10965",
    "sg:province":"NY",
    "sg:tags":[
        "loan",
        "real estate"
    ],
    "wof:name":"Cornerstone Home Loans",
    "wof:placetype":"venue"
},
  "geometry": {"coordinates":[-74.02413900000001,41.059529],"type":"Point"}
}