{
  "type": "Feature",
  "properties": {
    "iso:country":"US",
    "sg:address":"157 Glen Cove Rd",
    "sg:city":"Carle Place",
    "sg:classifiers":[
        {
            "category":"Shopping",
            "subcategory":"Crafts & Fabrics",
            "type":"Retail Goods"
        }
    ],
    "sg:phone":"+1 516 294 8401",
    "sg:postcode":"11514",
    "sg:province":"NY",
    "sg:tags":[
        "art",
        "supply"
    ],
    "wof:name":"A.C. Moore",
    "wof:placetype":"venue"
},
  "geometry": {"coordinates":[-73.61689699999999,40.745834],"type":"Point"}
}