{
  "type": "Feature",
  "properties": {
    "iso:country":"US",
    "sg:address":"1300 Jericho Tpke",
    "sg:city":"New Hyde Park",
    "sg:classifiers":[
        {
            "category":"Retail",
            "subcategory":"Portrait Studio",
            "type":"Services"
        }
    ],
    "sg:phone":"+1 516 352 3445",
    "sg:postcode":"11040",
    "sg:province":"NY",
    "sg:tags":[
        "photography"
    ],
    "sg:website":"www.millerphotos.com",
    "wof:name":"Miller Photography",
    "wof:placetype":"venue"
},
  "geometry": {"coordinates":[-73.68172800000001,40.733311],"type":"Point"}
}