{
  "type": "Feature",
  "properties": {
    "addr:full":"370 Esser Ave Buffalo NY 14207",
    "addr:housenumber":"370",
    "addr:postcode":"14207",
    "addr:street":"Esser Ave",
    "iso:country":"US",
    "sg:address":"370 Esser Ave",
    "sg:city":"Buffalo",
    "sg:phone":"+1 716 873 7696",
    "sg:postcode":"14207",
    "sg:province":"NY",
    "sg:tags":[
        "oil"
    ],
    "wof:name":"Francis W King Petroleum Prod",
    "wof:placetype":"venue"
},
  "geometry": {"coordinates":[-78.89741600000001,42.960358],"type":"Point"}
}