{
  "type": "Feature",
  "properties": {
    "iso:country":"US",
    "sg:address":"133A New York Ave",
    "sg:city":"Huntington",
    "sg:classifiers":[
        {
            "category":"Health Services",
            "subcategory":"Chiropractor",
            "type":"Services"
        }
    ],
    "sg:phone":"+1 631 549 1490",
    "sg:postcode":"11743",
    "sg:province":"NY",
    "wof:name":"Waterfront Chiropractor Center",
    "wof:placetype":"venue"
},
  "geometry": {"coordinates":[-73.421204,40.880001],"type":"Point"}
}