{
  "type": "Feature",
  "properties": {
    "iso:country":"US",
    "sg:address":"25 N Division St",
    "sg:city":"Auburn",
    "sg:classifiers":[
        {
            "category":"Retail",
            "subcategory":"Auto Repair",
            "type":"Services"
        }
    ],
    "sg:phone":"+1 315 258 8978",
    "sg:postcode":"13021",
    "sg:province":"NY",
    "sg:tags":[
        "repairing",
        "automobile"
    ],
    "wof:name":"Trombley's Automotive Svc",
    "wof:placetype":"venue"
},
  "geometry": {"coordinates":[-76.584563,42.932922],"type":"Point"}
}