{
  "type": "Feature",
  "properties": {
    "iso:country":"US",
    "sg:address":"11060 Flatlands Ave",
    "sg:city":"Brooklyn",
    "sg:classifiers":[
        {
            "category":"Food & Beverages",
            "subcategory":"Liquor & Beverages",
            "type":"Retail Goods"
        }
    ],
    "sg:phone":"+1 718 272 9342",
    "sg:postcode":"11207",
    "sg:province":"NY",
    "sg:tags":[
        "beer",
        "spirit",
        "wine"
    ],
    "wof:name":"Arnona Liquors Inc",
    "wof:placetype":"venue"
},
  "geometry": {"coordinates":[-73.89099899999999,40.650002],"type":"Point"}
}