{
  "type": "Feature",
  "properties": {
    "addr:full":"868 E 147th St Bronx NY 10455",
    "addr:housenumber":"868",
    "addr:postcode":"10455",
    "addr:street":"E 147Th St",
    "iso:country":"US",
    "sg:address":"868 E 147th St",
    "sg:city":"Bronx",
    "sg:classifiers":[
        {
            "category":"Building & Trades",
            "subcategory":"Construction",
            "type":"Services"
        }
    ],
    "sg:phone":"+1 718 402 3198",
    "sg:postcode":"10455",
    "sg:province":"NY",
    "sg:tags":[
        "house"
    ],
    "wof:name":"CS&s Mgmt",
    "wof:placetype":"venue"
},
  "geometry": {"coordinates":[-73.904256,40.81026],"type":"Point"}
}