{
  "type": "Feature",
  "properties": {
    "iso:country":"US",
    "sg:address":"3455 Gehan Rd",
    "sg:city":"Canandaigua",
    "sg:classifiers":[
        {
            "category":"Autos & Motor Vehicles",
            "subcategory":"Automobile Sales",
            "type":"Retail Goods"
        }
    ],
    "sg:phone":"+1 585 394 1230",
    "sg:postcode":"14424",
    "sg:province":"NY",
    "sg:tags":[
        "car",
        "dealer"
    ],
    "wof:name":"R & R Auto Sales",
    "wof:placetype":"venue"
},
  "geometry": {"coordinates":[-77.19535999999999,42.865067],"type":"Point"}
}