{
  "type": "Feature",
  "properties": {
    "iso:country":"US",
    "sg:address":"229 W Union St",
    "sg:city":"Newark",
    "sg:classifiers":[
        {
            "category":"Personal",
            "subcategory":"Beauty Salon",
            "type":"Services"
        }
    ],
    "sg:phone":"+1   ",
    "sg:postcode":"14513",
    "sg:province":"NY",
    "sg:tags":[
        "shop"
    ],
    "wof:name":"Kreative Kuts",
    "wof:placetype":"venue"
},
  "geometry": {"coordinates":[-77.098305,43.046545],"type":"Point"}
}