{
  "type": "Feature",
  "properties": {
    "addr:full":"2074 S Apalachin Rd Apalachin NY 13732",
    "addr:housenumber":"2074",
    "addr:postcode":"13732",
    "addr:street":"S Apalachin Rd",
    "iso:country":"US",
    "sg:address":"2074 S Apalachin Rd",
    "sg:city":"Apalachin",
    "sg:classifiers":[
        {
            "category":"Personal",
            "type":"Services"
        }
    ],
    "sg:phone":"+1 607 687 2490",
    "sg:postcode":"13732",
    "sg:province":"NY",
    "sg:tags":[
        "credit",
        "debt",
        "counseling"
    ],
    "wof:name":"Garden State Consumer Credit",
    "wof:placetype":"venue"
},
  "geometry": {"coordinates":[-76.195714,42.013639],"type":"Point"}
}