{
  "type": "Feature",
  "properties": {
    "iso:country":"US",
    "sg:address":"5634 Ottman Rd",
    "sg:city":"Vernon",
    "sg:classifiers":[
        {
            "category":"Professional",
            "subcategory":"Business Services",
            "type":"Services"
        }
    ],
    "sg:phone":"+1 315 829 3747",
    "sg:postcode":"13476",
    "sg:province":"NY",
    "sg:tags":[
        "painter",
        "sign"
    ],
    "wof:name":"Dave Cole Bldg & Repair",
    "wof:placetype":"venue"
},
  "geometry": {"coordinates":[-75.50507,43.106132],"type":"Point"}
}