{
  "type": "Feature",
  "properties": {
    "addr:full":"1912 Newbridge Rd North Bellmore NY 11710",
    "addr:housenumber":"1912",
    "addr:postcode":"11710",
    "addr:street":"Newbridge Rd",
    "iso:country":"US",
    "sg:address":"1912 Newbridge Rd",
    "sg:city":"North Bellmore",
    "sg:classifiers":[
        {
            "category":"Retail",
            "subcategory":"Auto Repair",
            "type":"Services"
        }
    ],
    "sg:phone":"+1 516 785 5227",
    "sg:postcode":"11710",
    "sg:province":"NY",
    "wof:name":"Nats Auto Repairs Inc",
    "wof:placetype":"venue"
},
  "geometry": {"coordinates":[-73.53919999999999,40.675201],"type":"Point"}
}