{
  "type": "Feature",
  "properties": {
    "addr:full":"4322 Junction Boulevard Flushing NY 11368",
    "addr:housenumber":"4322",
    "addr:postcode":"11368",
    "addr:street":"Junction Boulevard",
    "iso:country":"US",
    "sg:address":"4322 Junction Boulevard",
    "sg:city":"Flushing",
    "sg:classifiers":[
        {
            "category":"Health Services",
            "subcategory":"Dentist",
            "type":"Services"
        }
    ],
    "sg:phone":"+1 718 446 8800",
    "sg:postcode":"11368",
    "sg:province":"NY",
    "wof:name":"AAA Family Dental",
    "wof:placetype":"venue"
},
  "geometry": {"coordinates":[-73.868077,40.745026],"type":"Point"}
}