{
  "type": "Feature",
  "properties": {
    "iso:country":"US",
    "sg:address":"840 Chili Ave Exd",
    "sg:city":"Churchville",
    "sg:classifiers":[
        {
            "category":"Building & Trades",
            "subcategory":"Construction",
            "type":"Services"
        }
    ],
    "sg:phone":"+1 585 889 4289",
    "sg:postcode":"14428",
    "sg:province":"NY",
    "sg:tags":[
        "house"
    ],
    "wof:name":"Martin Construction",
    "wof:placetype":"venue"
},
  "geometry": {"coordinates":[-77.83123999999999,43.08854],"type":"Point"}
}