{
  "type": "Feature",
  "properties": {
    "iso:country":"US",
    "sg:address":"1 Roosevelt Ave",
    "sg:city":"Port Jefferson Station",
    "sg:classifiers":[
        {
            "category":"Banks & Credit Unions",
            "subcategory":"Investment Brokerage",
            "type":"Services"
        }
    ],
    "sg:phone":"+1 631 331 1400",
    "sg:postcode":"11776",
    "sg:province":"NY",
    "sg:tags":[
        "stockbroker",
        "stock",
        "bond"
    ],
    "wof:name":"Time Capital Securities Corp",
    "wof:placetype":"venue"
},
  "geometry": {"coordinates":[-73.04609499999999,40.922498],"type":"Point"}
}