{
  "type": "Feature",
  "properties": {
    "addr:full":"1080 Chenango St Binghamton NY 13901",
    "addr:housenumber":"1080",
    "addr:postcode":"13901",
    "addr:street":"Chenango St",
    "iso:country":"US",
    "sg:address":"1080 Chenango St",
    "sg:city":"Binghamton",
    "sg:classifiers":[
        {
            "category":"Wholesale",
            "subcategory":"Medical Equipment & Supplies",
            "type":"Manufacturing & Wholesale Goods"
        }
    ],
    "sg:phone":"+1 607 772 0979",
    "sg:postcode":"13901",
    "sg:province":"NY",
    "sg:tags":[
        "optical"
    ],
    "sg:website":"www.kandsoptics.com",
    "wof:name":"K & S Optics",
    "wof:placetype":"venue"
},
  "geometry": {"coordinates":[-75.88857899999999,42.147408],"type":"Point"}
}