{
  "type": "Feature",
  "properties": {
    "iso:country":"US",
    "sg:address":"4515 Ave N",
    "sg:city":"Brooklyn",
    "sg:classifiers":[
        {
            "category":"Real Estate",
            "subcategory":"Real Estate Agent",
            "type":"Services"
        }
    ],
    "sg:phone":"+1 718 377 6161",
    "sg:postcode":"11234",
    "sg:province":"NY",
    "wof:name":"Fillmore Real Estate",
    "wof:placetype":"venue"
},
  "geometry": {"coordinates":[-73.92657199999999,40.612862],"type":"Point"}
}