{
  "type": "Feature",
  "properties": {
    "addr:full":"12 Cedar Ln Bronxville NY 10708",
    "addr:housenumber":"12",
    "addr:postcode":"10708",
    "addr:street":"Cedar Ln",
    "iso:country":"US",
    "sg:address":"12 Cedar Ln",
    "sg:city":"Bronxville",
    "sg:classifiers":[
        {
            "category":"Food & Beverages",
            "subcategory":"Groceries & Convenience Stores",
            "type":"Retail Goods"
        }
    ],
    "sg:phone":"+1 914 961 9552",
    "sg:postcode":"10708",
    "sg:province":"NY",
    "sg:tags":[
        "grocer"
    ],
    "wof:name":"A & P Food Store",
    "wof:placetype":"venue"
},
  "geometry": {"coordinates":[-73.843986,40.946052],"type":"Point"}
}