{
  "type": "Feature",
  "properties": {
    "iso:country":"US",
    "sg:address":"13996 State Rte 31",
    "sg:city":"Albion",
    "sg:classifiers":[
        {
            "category":"Government",
            "subcategory":"Office",
            "type":"Public Place"
        }
    ],
    "sg:phone":"+1 585 589 3120",
    "sg:postcode":"14411",
    "sg:province":"NY",
    "wof:name":"Orleans Foster Parents Program",
    "wof:placetype":"venue"
},
  "geometry": {"coordinates":[-78.214782,43.240639],"type":"Point"}
}