{
  "type": "Feature",
  "properties": {
    "addr:full":"103 W Montauk Hwy Hampton Bays NY 11946",
    "addr:housenumber":"103",
    "addr:postcode":"11946",
    "addr:street":"W Montauk Hwy",
    "iso:country":"US",
    "sg:address":"103 W Montauk Hwy",
    "sg:city":"Hampton Bays",
    "sg:classifiers":[
        {
            "category":"Professional",
            "subcategory":"Research",
            "type":"Services"
        }
    ],
    "sg:phone":"+1 631 728 9100",
    "sg:postcode":"11946",
    "sg:province":"NY",
    "sg:tags":[
        "organization",
        "educational"
    ],
    "wof:name":"E P I E Institute",
    "wof:placetype":"venue"
},
  "geometry": {"coordinates":[-72.531735,40.876568],"type":"Point"}
}