{
  "type": "Feature",
  "properties": {
    "iso:country":"US",
    "sg:address":"261 E Merrick Rd",
    "sg:city":"Freeport",
    "sg:classifiers":[
        {
            "category":"Autos & Motor Vehicles",
            "subcategory":"Fuel & Gas Station",
            "type":"Retail Goods"
        }
    ],
    "sg:phone":"+1 516 623 1213",
    "sg:postcode":"11520",
    "sg:province":"NY",
    "sg:tags":[
        "oil"
    ],
    "wof:name":"Gulden Inc",
    "wof:placetype":"venue"
},
  "geometry": {"coordinates":[-73.57372599999999,40.654326],"type":"Point"}
}