{
  "type": "Feature",
  "properties": {
    "addr:full":"604 Calvert St Rome NY 13440",
    "addr:housenumber":"604",
    "addr:postcode":"13440",
    "addr:street":"Calvert St",
    "iso:country":"US",
    "sg:address":"604 Calvert St",
    "sg:city":"Rome",
    "sg:classifiers":[
        {
            "category":"Autos & Motor Vehicles",
            "subcategory":"Auto Supplies",
            "type":"Retail Goods"
        }
    ],
    "sg:phone":"+1 315 336 2487",
    "sg:postcode":"13440",
    "sg:province":"NY",
    "sg:tags":[
        "automobile",
        "parts"
    ],
    "wof:name":"Automobile Tech",
    "wof:placetype":"venue"
},
  "geometry": {"coordinates":[-75.468587,43.215102],"type":"Point"}
}