{
  "type": "Feature",
  "properties": {
    "addr:full":"55 W Railroad Ave Garnerville NY 10923",
    "addr:housenumber":"55",
    "addr:postcode":"10923",
    "addr:street":"W Railroad Ave",
    "iso:country":"US",
    "sg:address":"55 W Railroad Ave",
    "sg:city":"Garnerville",
    "sg:classifiers":[
        {
            "category":"Shopping",
            "subcategory":"Hobbies, Toys, & Games",
            "type":"Retail Goods"
        }
    ],
    "sg:phone":"+1 845 942 1920",
    "sg:postcode":"10923",
    "sg:province":"NY",
    "sg:tags":[
        "model",
        "supply"
    ],
    "wof:name":"Nitro Hobbies",
    "wof:placetype":"venue"
},
  "geometry": {"coordinates":[-73.99155500000001,41.208626],"type":"Point"}
}