{
  "type": "Feature",
  "properties": {
    "addr:full":"225 W 12th St New York NY 10011",
    "addr:housenumber":"225",
    "addr:postcode":"10011",
    "addr:street":"W 12Th St",
    "iso:country":"US",
    "sg:address":"225 W 12th St",
    "sg:city":"New York",
    "sg:classifiers":[
        {
            "category":"Restaurant",
            "type":"Food & Drink"
        }
    ],
    "sg:phone":"+1 212 691 0303",
    "sg:postcode":"10011",
    "sg:province":"NY",
    "sg:tags":[
        "traditional",
        "american",
        "brunch",
        "breakfast"
    ],
    "sg:website":"VillageDenNYC.com",
    "wof:name":"Village Den Restaurant",
    "wof:placetype":"venue"
},
  "geometry": {"coordinates":[-74.001653,40.737643],"type":"Point"}
}