{
  "type": "Feature",
  "properties": {
    "addr:full":"2645 Grand Ave Baldwin NY 11510",
    "addr:housenumber":"2645",
    "addr:postcode":"11510",
    "addr:street":"Grand Ave",
    "iso:country":"US",
    "sg:address":"2645 Grand Ave",
    "sg:city":"Baldwin",
    "sg:classifiers":[
        {
            "category":"Health Services",
            "subcategory":"Clinic",
            "type":"Services"
        }
    ],
    "sg:phone":"+1 516 867 6594",
    "sg:postcode":"11510",
    "sg:province":"NY",
    "sg:tags":[
        "welfare"
    ],
    "wof:name":"Epilepsy Foundation Of Long Island Inc",
    "wof:placetype":"venue"
},
  "geometry": {"coordinates":[-73.612799,40.645229],"type":"Point"}
}