{
  "type": "Feature",
  "properties": {
    "addr:full":"3200 Skillman Ave Long Island City NY 11101",
    "addr:housenumber":"3200",
    "addr:postcode":"11101",
    "addr:street":"Skillman Ave",
    "iso:country":"US",
    "sg:address":"3200 Skillman Ave",
    "sg:city":"Long Island City",
    "sg:classifiers":[
        {
            "category":"Shopping",
            "subcategory":"Stationery & Office Supplies",
            "type":"Retail Goods"
        }
    ],
    "sg:phone":"+1 718 433 3800",
    "sg:postcode":"11101",
    "sg:province":"NY",
    "sg:tags":[
        "equipment"
    ],
    "sg:website":"www.kruysman.com",
    "wof:name":"Kruysman Redweld",
    "wof:placetype":"venue"
},
  "geometry": {"coordinates":[-73.93319700000001,40.7463],"type":"Point"}
}