{
  "type": "Feature",
  "properties": {
    "iso:country":"US",
    "sg:address":"61 Quail St",
    "sg:city":"Albany",
    "sg:classifiers":[
        {
            "category":"Food & Beverages",
            "subcategory":"Groceries & Convenience Stores",
            "type":"Retail Goods"
        },
        {
            "category":"Wholesale",
            "subcategory":"Groceries",
            "type":"Manufacturing & Wholesale Goods"
        }
    ],
    "sg:phone":"+1 518 462 9570",
    "sg:postcode":"12206",
    "sg:province":"NY",
    "sg:tags":[
        "general"
    ],
    "wof:name":"Mr Sams Food Market",
    "wof:placetype":"venue"
},
  "geometry": {"coordinates":[-73.76970799999999,42.667831],"type":"Point"}
}