{
  "type": "Feature",
  "properties": {
    "addr:full":"89 Co Rte 41 Hudson Falls NY 12839",
    "addr:housenumber":"89",
    "addr:postcode":"12839",
    "addr:street":"Co Rte 41",
    "iso:country":"US",
    "sg:address":"89 Co Rte 41",
    "sg:city":"Hudson Falls",
    "sg:classifiers":[
        {
            "category":"Travel",
            "subcategory":"Hotels & Motels",
            "type":"Entertainment"
        }
    ],
    "sg:phone":"+1 518 747 2694",
    "sg:postcode":"12839",
    "sg:province":"NY",
    "sg:tags":[
        "breakfast",
        "accommodation",
        "bed"
    ],
    "wof:name":"A B & B On The Green",
    "wof:placetype":"venue"
},
  "geometry": {"coordinates":[-73.55021499999999,43.316369],"type":"Point"}
}