{
  "type": "Feature",
  "properties": {
    "addr:full":"212 Rte 25A East Setauket NY 11733",
    "addr:housenumber":"212",
    "addr:postcode":"11733",
    "addr:street":"Rte 25A East",
    "iso:country":"US",
    "sg:address":"212 Rte 25A",
    "sg:city":"East Setauket",
    "sg:classifiers":[
        {
            "category":"Restaurant",
            "type":"Food & Drink"
        }
    ],
    "sg:phone":"+1 631 751 8663",
    "sg:postcode":"11733",
    "sg:province":"NY",
    "sg:tags":[
        "bar",
        "italian"
    ],
    "wof:name":"Mario's Italian Kitchen Inc",
    "wof:placetype":"venue"
},
  "geometry": {"coordinates":[-73.10337199999999,40.942561],"type":"Point"}
}