{
  "type": "Feature",
  "properties": {
    "addr:full":"1355 Noel Ave Hewlett NY 11557",
    "addr:housenumber":"1355",
    "addr:postcode":"11557",
    "addr:street":"Noel Ave",
    "iso:country":"US",
    "sg:address":"1355 Noel Ave",
    "sg:city":"Hewlett",
    "sg:classifiers":[
        {
            "category":"Education",
            "subcategory":"School",
            "type":"Public Place"
        }
    ],
    "sg:phone":"+1 516 569 6080",
    "sg:postcode":"11557",
    "sg:province":"NY",
    "wof:name":"St Joseph's Religious Edu",
    "wof:placetype":"venue"
},
  "geometry": {"coordinates":[-73.699369,40.642796],"type":"Point"}
}