{
  "type": "Feature",
  "properties": {
    "iso:country":"US",
    "sg:address":"119 South St",
    "sg:city":"New York",
    "sg:classifiers":[
        {
            "category":"Restaurant",
            "type":"Food & Drink"
        }
    ],
    "sg:menulink":"http://www.allmenus.com/ny/new-york/2737-the-paris/menu/",
    "sg:phone":"+1 212 240 9797",
    "sg:postcode":"10038",
    "sg:province":"NY",
    "sg:tags":[
        "seafood",
        "american"
    ],
    "wof:name":"The Paris",
    "wof:placetype":"venue"
},
  "geometry": {"coordinates":[-74.00157900000001,40.707321],"type":"Point"}
}