{
  "type": "Feature",
  "properties": {
    "addr:full":"10 Nathan D Perlman Pl New York NY 10003",
    "addr:housenumber":"10",
    "addr:postcode":"10003",
    "addr:street":"Nathan D Perlman Pl",
    "iso:country":"US",
    "sg:address":"10 Nathan D Perlman Pl",
    "sg:city":"New York",
    "sg:classifiers":[
        {
            "category":"Health Services",
            "subcategory":"Hospital",
            "type":"Services"
        }
    ],
    "sg:phone":"+1 212 420 2000",
    "sg:postcode":"10003",
    "sg:province":"NY",
    "sg:website":"www.chpnyc.org",
    "wof:name":"Hospitals",
    "wof:placetype":"venue"
},
  "geometry": {"coordinates":[-73.983328,40.732895],"type":"Point"}
}