{
  "type": "Feature",
  "properties": {
    "addr:full":"36 Martin St Webster NY 14580",
    "addr:housenumber":"36",
    "addr:postcode":"14580",
    "addr:street":"Martin St",
    "iso:country":"US",
    "sg:address":"36 Martin St",
    "sg:city":"Webster",
    "sg:classifiers":[
        {
            "category":"Shopping",
            "subcategory":"Computers & Home Electronics",
            "type":"Retail Goods"
        }
    ],
    "sg:phone":"+1   ",
    "sg:postcode":"14580",
    "sg:province":"NY",
    "wof:name":"Carnival Supplies & Rentals",
    "wof:placetype":"venue"
},
  "geometry": {"coordinates":[-77.43464899999999,43.218542],"type":"Point"}
}