{
  "type": "Feature",
  "properties": {
    "addr:full":"650 Lee Blvd Yorktown Heights NY 10598",
    "addr:housenumber":"650",
    "addr:postcode":"10598",
    "addr:street":"Lee Blvd",
    "iso:country":"US",
    "sg:address":"650 Lee Blvd",
    "sg:city":"Yorktown Heights",
    "sg:classifiers":[
        {
            "category":"Banks & Credit Unions",
            "subcategory":"Bank",
            "type":"Services"
        }
    ],
    "sg:phone":"+1 914 962 7283",
    "sg:postcode":"10598",
    "sg:province":"NY",
    "sg:tags":[
        "state",
        "commercial"
    ],
    "wof:name":"Hsbc Bank USA National Assn",
    "wof:placetype":"venue"
},
  "geometry": {"coordinates":[-73.80998599999999,41.32777],"type":"Point"}
}