{
  "type": "Feature",
  "properties": {
    "iso:country":"US",
    "sg:address":"11 Westhaven Ln",
    "sg:city":"White Plains",
    "sg:classifiers":[
        {
            "category":"Real Estate",
            "subcategory":"Real Estate Operator",
            "type":"Services"
        }
    ],
    "sg:phone":"+1 914 948 2325",
    "sg:postcode":"10605",
    "sg:province":"NY",
    "sg:tags":[
        "building",
        "nonresidential"
    ],
    "wof:name":"Keslow Properties LLC",
    "wof:placetype":"venue"
},
  "geometry": {"coordinates":[-73.737038,40.991975],"type":"Point"}
}