{
  "type": "Feature",
  "properties": {
    "addr:full":"1404 2nd Avenue New York NY 10021",
    "addr:housenumber":"1404",
    "addr:postcode":"10021",
    "addr:street":"2Nd Avenue",
    "iso:country":"US",
    "sg:address":"1404 2nd Avenue",
    "sg:city":"New York",
    "sg:classifiers":[
        {
            "category":"Banks & Credit Unions",
            "subcategory":"Bank",
            "type":"Services"
        }
    ],
    "sg:phone":"+1 212 472 7939",
    "sg:postcode":"10021",
    "sg:province":"NY",
    "wof:name":"City & Suburban Federal Savings Bank",
    "wof:placetype":"venue"
},
  "geometry": {"coordinates":[-73.957556,40.769659],"type":"Point"}
}