{
  "type": "Feature",
  "properties": {
    "addr:full":"48 James Hawkins Rd Moriches NY 11955",
    "addr:housenumber":"48",
    "addr:postcode":"11955",
    "addr:street":"James Hawkins Rd",
    "iso:country":"US",
    "sg:address":"48 James Hawkins Rd",
    "sg:city":"Moriches",
    "sg:classifiers":[
        {
            "category":"Restaurant",
            "type":"Food & Drink"
        }
    ],
    "sg:phone":"+1 631 874 0777",
    "sg:postcode":"11955",
    "sg:province":"NY",
    "wof:name":"Abkr Enterprises",
    "wof:placetype":"venue"
},
  "geometry": {"coordinates":[-72.821117,40.800443],"type":"Point"}
}