{
  "type": "Feature",
  "properties": {
    "addr:full":"427 E 74th St New York NY 10021",
    "addr:housenumber":"427",
    "addr:postcode":"10021",
    "addr:street":"E 74Th St",
    "iso:country":"US",
    "sg:address":"427 E 74th St",
    "sg:city":"New York",
    "sg:classifiers":[
        {
            "category":"Retail",
            "subcategory":"Laundry & Dry Cleaning",
            "type":"Services"
        }
    ],
    "sg:phone":"+1 212 889 1372",
    "sg:postcode":"10021",
    "sg:province":"NY",
    "wof:name":"Madison Dry Cleaners",
    "wof:placetype":"venue"
},
  "geometry": {"coordinates":[-73.954399,40.768902],"type":"Point"}
}