{
  "type": "Feature",
  "properties": {
    "iso:country":"US",
    "sg:address":"63 E 7th St",
    "sg:city":"New York",
    "sg:classifiers":[
        {
            "category":"Shopping",
            "subcategory":"Jewelry",
            "type":"Retail Goods"
        }
    ],
    "sg:phone":"+1 212 420 8080",
    "sg:postcode":"10003",
    "sg:province":"NY",
    "wof:name":"Jitkanda",
    "wof:placetype":"venue"
},
  "geometry": {"coordinates":[-73.98683,40.727683],"type":"Point"}
}