{
  "type": "Feature",
  "properties": {
    "iso:country":"US",
    "sg:address":"246 W 106th St",
    "sg:city":"New York",
    "sg:classifiers":[
        {
            "category":"Social Services",
            "subcategory":"Child Care",
            "type":"Services"
        }
    ],
    "sg:phone":"+1 212 866 4095",
    "sg:postcode":"10025",
    "sg:province":"NY",
    "wof:name":"Children's House",
    "wof:placetype":"venue"
},
  "geometry": {"coordinates":[-73.96669799999999,40.800607],"type":"Point"}
}