{
  "type": "Feature",
  "properties": {
    "addr:full":"111 Fulton St New York NY 10038",
    "addr:housenumber":"111",
    "addr:postcode":"10038",
    "addr:street":"Fulton St",
    "iso:country":"US",
    "sg:address":"111 Fulton St",
    "sg:city":"New York",
    "sg:classifiers":[
        {
            "category":"Professional",
            "subcategory":"Lawyer & Legal Services",
            "type":"Services"
        }
    ],
    "sg:phone":"+1 212 349 0783",
    "sg:postcode":"10038",
    "sg:province":"NY",
    "wof:name":"Law Offices of Stephen J King",
    "wof:placetype":"venue"
},
  "geometry": {"coordinates":[-74.006908,40.70982],"type":"Point"}
}