{
  "type": "Feature",
  "properties": {
    "addr:full":"191 7th Ave New York NY 10011",
    "addr:housenumber":"191",
    "addr:postcode":"10011",
    "addr:street":"7Th Ave",
    "iso:country":"US",
    "sg:address":"191 7th Ave",
    "sg:city":"New York",
    "sg:classifiers":[
        {
            "category":"Restaurant",
            "type":"Food & Drink"
        }
    ],
    "sg:phone":"+1 212 675 5980",
    "sg:postcode":"10011",
    "sg:province":"NY",
    "sg:tags":[
        "steakhouse",
        "italian"
    ],
    "sg:website":"www.ilbastardonyc.com",
    "wof:name":"Il Bastardo Lounge",
    "wof:placetype":"venue"
},
  "geometry": {"coordinates":[-73.99650200000001,40.742899],"type":"Point"}
}