{
  "type": "Feature",
  "properties": {
    "iso:country":"US",
    "sg:address":"636 Middle Country Rd",
    "sg:city":"Selden",
    "sg:classifiers":[
        {
            "category":"Health Services",
            "subcategory":"Chiropractor",
            "type":"Services"
        }
    ],
    "sg:phone":"+1 631 736 4414",
    "sg:postcode":"11784",
    "sg:province":"NY",
    "sg:website":"www.drbenchiro.com",
    "wof:name":"Coram-Selden Chiropractic",
    "wof:placetype":"venue"
},
  "geometry": {"coordinates":[-73.038399,40.866199],"type":"Point"}
}