{
  "type": "Feature",
  "properties": {
    "iso:country":"US",
    "sg:address":"2627 Hylan Blvd",
    "sg:city":"Staten Island",
    "sg:classifiers":[
        {
            "category":"Health Services",
            "subcategory":"Doctor",
            "type":"Services"
        }
    ],
    "sg:phone":"+1 718 980 4800",
    "sg:postcode":"10306",
    "sg:province":"NY",
    "sg:tags":[
        "dentist"
    ],
    "wof:name":"Joseph A Toia DDS",
    "wof:placetype":"venue"
},
  "geometry": {"coordinates":[-74.112403,40.568042],"type":"Point"}
}