{
  "type": "Feature",
  "properties": {
    "addr:full":"70 Pine Hill Park Valatie NY 12184",
    "addr:housenumber":"70",
    "addr:postcode":"12184",
    "addr:street":"Pine Hill Park",
    "iso:country":"US",
    "sg:address":"70 Pine Hill Park",
    "sg:city":"Valatie",
    "sg:classifiers":[
        {
            "category":"Building & Trades",
            "subcategory":"Construction",
            "type":"Services"
        }
    ],
    "sg:phone":"+1 518 784 9189",
    "sg:postcode":"12184",
    "sg:province":"NY",
    "sg:tags":[
        "house",
        "contractor"
    ],
    "wof:name":"Wilson Builders",
    "wof:placetype":"venue"
},
  "geometry": {"coordinates":[-73.687906,42.452435],"type":"Point"}
}