{
  "type": "Feature",
  "properties": {
    "addr:full":"339 Hogan Rd Fairport NY 14450",
    "addr:housenumber":"339",
    "addr:postcode":"14450",
    "addr:street":"Hogan Rd",
    "iso:country":"US",
    "sg:address":"339 Hogan Rd",
    "sg:city":"Fairport",
    "sg:classifiers":[
        {
            "category":"Professional",
            "type":"Services"
        }
    ],
    "sg:phone":"+1 585 223 2561",
    "sg:postcode":"14450",
    "sg:province":"NY",
    "sg:tags":[
        "establishment"
    ],
    "wof:name":"Aristo Development Inc",
    "wof:placetype":"venue"
},
  "geometry": {"coordinates":[-77.419282,43.068768],"type":"Point"}
}