{
  "type": "Feature",
  "properties": {
    "addr:full":"116 E Genesee St Fayetteville NY 13066",
    "addr:housenumber":"116",
    "addr:postcode":"13066",
    "addr:street":"E Genesee St",
    "iso:country":"US",
    "sg:address":"116 E Genesee St",
    "sg:city":"Fayetteville",
    "sg:classifiers":[
        {
            "category":"Organizations",
            "subcategory":"Community Association",
            "type":"Services"
        }
    ],
    "sg:phone":"+1 315 637 6431",
    "sg:postcode":"13066",
    "sg:province":"NY",
    "sg:tags":[
        "club"
    ],
    "wof:name":"Fayetteville Masonic Club Inc",
    "wof:placetype":"venue"
},
  "geometry": {"coordinates":[-76.010199,43.029285],"type":"Point"}
}