{
  "type": "Feature",
  "properties": {
    "addr:full":"139-07 Hillside Ave Jamaica NY 11435",
    "addr:housenumber":"139-07",
    "addr:postcode":"11435",
    "addr:street":"Hillside Ave",
    "iso:country":"US",
    "sg:address":"139-07 Hillside Ave",
    "sg:city":"Jamaica",
    "sg:classifiers":[
        {
            "category":"Autos & Motor Vehicles",
            "subcategory":"Automobile Sales",
            "type":"Retail Goods"
        },
        {
            "category":"Retail",
            "subcategory":"Auto Rental",
            "type":"Services"
        },
        {
            "category":"Retail",
            "subcategory":"Auto Repair",
            "type":"Services"
        }
    ],
    "sg:phone":"+1 718 657 7810",
    "sg:postcode":"11435",
    "sg:province":"NY",
    "sg:tags":[
        "car"
    ],
    "sg:website":"www.HillsideHonda.com",
    "wof:name":"Hillside Honda",
    "wof:placetype":"venue"
},
  "geometry": {"coordinates":[-73.814052,40.704773],"type":"Point"}
}