{
  "type": "Feature",
  "properties": {
    "iso:country":"US",
    "sg:address":"98 Midwood Rd",
    "sg:city":"West Babylon",
    "sg:classifiers":[
        {
            "category":"Building & Trades",
            "subcategory":"Construction",
            "type":"Services"
        }
    ],
    "sg:phone":"+1 631 831 0468",
    "sg:postcode":"11704",
    "sg:province":"NY",
    "sg:tags":[
        "contractor"
    ],
    "wof:name":"J C Land Development",
    "wof:placetype":"venue"
},
  "geometry": {"coordinates":[-73.34757999999999,40.707871],"type":"Point"}
}