{
  "type": "Feature",
  "properties": {
    "addr:full":"2455 Hylan Blvd Staten Island NY 10306",
    "addr:housenumber":"2455",
    "addr:postcode":"10306",
    "addr:street":"Hylan Blvd",
    "iso:country":"US",
    "sg:address":"2455 Hylan Blvd",
    "sg:city":"Staten Island",
    "sg:classifiers":[
        {
            "category":"Home & Garden",
            "subcategory":"Furniture",
            "type":"Retail Goods"
        }
    ],
    "sg:phone":"+1   ",
    "sg:postcode":"10306",
    "sg:province":"NY",
    "wof:name":"Hi-Line Home Furnishings LLC",
    "wof:placetype":"venue"
},
  "geometry": {"coordinates":[-74.10906900000001,40.571315],"type":"Point"}
}