{
  "type": "Feature",
  "properties": {
    "addr:full":"7575 Van Buren Rd Baldwinsville NY 13027",
    "addr:housenumber":"7575",
    "addr:postcode":"13027",
    "addr:street":"Van Buren Rd",
    "iso:country":"US",
    "sg:address":"7575 Van Buren Rd",
    "sg:city":"Baldwinsville",
    "sg:classifiers":[
        {
            "category":"Utilities",
            "subcategory":"Water",
            "type":"Services"
        }
    ],
    "sg:phone":"+1 315 635 3011",
    "sg:postcode":"13027",
    "sg:province":"NY",
    "sg:tags":[
        "company",
        "sewage"
    ],
    "wof:name":"Van Buren Water & Sewer Dept",
    "wof:placetype":"venue"
},
  "geometry": {"coordinates":[-76.32075,43.132724],"type":"Point"}
}