{
  "type": "Feature",
  "properties": {
    "addr:full":"307 E 92nd St New York NY 10128",
    "addr:housenumber":"307",
    "addr:postcode":"10128",
    "addr:street":"E 92Nd St",
    "iso:country":"US",
    "sg:address":"307 E 92nd St",
    "sg:city":"New York",
    "sg:classifiers":[
        {
            "category":"Retail",
            "subcategory":"Auto Repair",
            "type":"Services"
        }
    ],
    "sg:phone":"+1 212 860 2277",
    "sg:postcode":"10128",
    "sg:province":"NY",
    "sg:tags":[
        "body",
        "shop"
    ],
    "wof:name":"A & A Imported Motors Inc",
    "wof:placetype":"venue"
},
  "geometry": {"coordinates":[-73.947304,40.781101],"type":"Point"}
}