{
  "type": "Feature",
  "properties": {
    "iso:country":"US",
    "sg:address":"37 Buena Vista Rd",
    "sg:city":"New City",
    "sg:classifiers":[
        {
            "category":"Health Services",
            "subcategory":"Doctor",
            "type":"Services"
        }
    ],
    "sg:phone":"+1 845 634 4772",
    "sg:postcode":"10956",
    "sg:province":"NY",
    "sg:tags":[
        "medical"
    ],
    "wof:name":"Lee Yosing C MD PC",
    "wof:placetype":"venue"
},
  "geometry": {"coordinates":[-74.02116700000001,41.1537],"type":"Point"}
}