{
  "type": "Feature",
  "properties": {
    "addr:full":"228 Southport St Ronkonkoma NY 11779",
    "addr:housenumber":"228",
    "addr:postcode":"11779",
    "addr:street":"Southport St",
    "iso:country":"US",
    "sg:address":"228 Southport St",
    "sg:city":"Ronkonkoma",
    "sg:classifiers":[
        {
            "category":"Manufacturing",
            "subcategory":"Apparel",
            "type":"Manufacturing & Wholesale Goods"
        }
    ],
    "sg:phone":"+1   ",
    "sg:postcode":"11779",
    "sg:province":"NY",
    "sg:tags":[
        "clothing",
        "outerwear",
        "mfg"
    ],
    "wof:name":"R R Athletic Apparel",
    "wof:placetype":"venue"
},
  "geometry": {"coordinates":[-73.153248,40.797371],"type":"Point"}
}