{
  "type": "Feature",
  "properties": {
    "iso:country":"US",
    "sg:address":"81 Botsford Pl",
    "sg:city":"Buffalo",
    "sg:phone":"+1 716 447 9924",
    "sg:postcode":"14216",
    "sg:province":"NY",
    "sg:tags":[
        "scale"
    ],
    "wof:name":"Central Food Processing Equip",
    "wof:placetype":"venue"
},
  "geometry": {"coordinates":[-78.87444600000001,42.950362],"type":"Point"}
}