{
  "type": "Feature",
  "properties": {
    "iso:country":"US",
    "sg:address":"138 Sullivan St",
    "sg:city":"New York",
    "sg:classifiers":[
        {
            "category":"Real Estate",
            "subcategory":"Real Estate Operator",
            "type":"Services"
        }
    ],
    "sg:phone":"+1 212 982 2350",
    "sg:postcode":"10012",
    "sg:province":"NY",
    "sg:tags":[
        "commercial"
    ],
    "wof:name":"Stock Blue Realty Corp",
    "wof:placetype":"venue"
},
  "geometry": {"coordinates":[-74.001668,40.727357],"type":"Point"}
}