{
  "type": "Feature",
  "properties": {
    "iso:country":"US",
    "sg:address":"62 W Main St",
    "sg:city":"Gowanda",
    "sg:classifiers":[
        {
            "category":"Professional",
            "subcategory":"Advertising",
            "type":"Services"
        },
        {
            "category":"Manufacturing",
            "subcategory":"Printing",
            "type":"Manufacturing & Wholesale Goods"
        }
    ],
    "sg:phone":"+1 716 532 2288",
    "sg:postcode":"14070",
    "sg:province":"NY",
    "sg:tags":[
        "newspaper",
        "counselor"
    ],
    "wof:name":"Gowanda Pennysaver & News",
    "wof:placetype":"venue"
},
  "geometry": {"coordinates":[-78.937192,42.462703],"type":"Point"}
}