{
  "type": "Feature",
  "properties": {
    "iso:country":"US",
    "sg:address":"36 Main St",
    "sg:city":"Attica",
    "sg:classifiers":[
        {
            "category":"Wholesale",
            "subcategory":"Electrical",
            "type":"Manufacturing & Wholesale Goods"
        }
    ],
    "sg:phone":"+1 585 591 2300",
    "sg:postcode":"14011",
    "sg:province":"NY",
    "sg:tags":[
        "new",
        "electronics",
        "car"
    ],
    "wof:name":"Electronics Warehouse & More",
    "wof:placetype":"venue"
},
  "geometry": {"coordinates":[-78.28265,42.864149],"type":"Point"}
}