{
  "type": "Feature",
  "properties": {
    "iso:country":"US",
    "sg:address":"130 Linden St",
    "sg:city":"Bellmore",
    "sg:classifiers":[
        {
            "category":"Professional",
            "subcategory":"Accounting & Tax Preparation",
            "type":"Services"
        }
    ],
    "sg:phone":"+1 516 242 6398",
    "sg:postcode":"11710",
    "sg:province":"NY",
    "sg:tags":[
        "bookkeeping",
        "general"
    ],
    "wof:name":"Ask Howe Office Svc",
    "wof:placetype":"venue"
},
  "geometry": {"coordinates":[-73.528887,40.672117],"type":"Point"}
}