{
  "type": "Feature",
  "properties": {
    "iso:country":"US",
    "sg:address":"418 Ditmas Ave",
    "sg:city":"Brooklyn",
    "sg:classifiers":[
        {
            "category":"Retail",
            "subcategory":"Laundry & Dry Cleaning",
            "type":"Services"
        }
    ],
    "sg:phone":"+1 718 633 0696",
    "sg:postcode":"11218",
    "sg:province":"NY",
    "sg:tags":[
        "drycleaning",
        "plant"
    ],
    "wof:name":"Kensington Dry Cleaners",
    "wof:placetype":"venue"
},
  "geometry": {"coordinates":[-73.974503,40.635799],"type":"Point"}
}