{
  "type": "Feature",
  "properties": {
    "iso:country":"US",
    "sg:address":"60 Gordon Pkwy",
    "sg:city":"Syracuse",
    "sg:classifiers":[
        {
            "category":"Communications",
            "subcategory":"Film & Video Production",
            "type":"Services"
        }
    ],
    "sg:phone":"+1 315 575 1355",
    "sg:postcode":"13219",
    "sg:province":"NY",
    "sg:tags":[
        "editing",
        "tape"
    ],
    "wof:name":"Uwamu",
    "wof:placetype":"venue"
},
  "geometry": {"coordinates":[-76.25556400000001,43.051633],"type":"Point"}
}