{
  "type": "Feature",
  "properties": {
    "iso:country":"US",
    "sg:address":"5263 Duguid Rd",
    "sg:city":"Fayetteville",
    "sg:classifiers":[
        {
            "category":"Shopping",
            "type":"Retail Goods"
        }
    ],
    "sg:phone":"+1   ",
    "sg:postcode":"13066",
    "sg:province":"NY",
    "sg:tags":[
        "equipment",
        "pool"
    ],
    "wof:name":"Calm Enterprises Inc",
    "wof:placetype":"venue"
},
  "geometry": {"coordinates":[-75.97684099999999,43.025666],"type":"Point"}
}