{
  "type": "Feature",
  "properties": {
    "addr:full":"26 North St Caledonia NY 14423",
    "addr:housenumber":"26",
    "addr:postcode":"14423",
    "addr:street":"North St",
    "iso:country":"US",
    "sg:address":"26 North St",
    "sg:city":"Caledonia",
    "sg:classifiers":[
        {
            "category":"Restaurant",
            "type":"Food & Drink"
        }
    ],
    "sg:phone":"+1   ",
    "sg:postcode":"14423",
    "sg:province":"NY",
    "sg:tags":[
        "eating"
    ],
    "wof:name":"Springbrook Inn",
    "wof:placetype":"venue"
},
  "geometry": {"coordinates":[-77.858136,42.986563],"type":"Point"}
}