{
  "type": "Feature",
  "properties": {
    "addr:full":"271 Central Park W New York NY 10024",
    "addr:housenumber":"271",
    "addr:postcode":"10024",
    "addr:street":"Central Park W",
    "iso:country":"US",
    "sg:address":"271 Central Park W",
    "sg:city":"New York",
    "sg:classifiers":[
        {
            "category":"Professional",
            "subcategory":"Management & Consulting",
            "type":"Services"
        }
    ],
    "sg:phone":"+1 917 441 6224",
    "sg:postcode":"10024",
    "sg:province":"NY",
    "sg:tags":[
        "construction"
    ],
    "wof:name":"Aviv Construction Inc",
    "wof:placetype":"venue"
},
  "geometry": {"coordinates":[-73.96862400000001,40.786317],"type":"Point"}
}