{
  "type": "Feature",
  "properties": {
    "iso:country":"US",
    "sg:address":"24 Lincoln Rd N",
    "sg:city":"Plainview",
    "sg:classifiers":[
        {
            "category":"Home & Garden",
            "subcategory":"Building Materials",
            "type":"Retail Goods"
        }
    ],
    "sg:phone":"+1 516 932 7295",
    "sg:postcode":"11803",
    "sg:province":"NY",
    "sg:tags":[
        "shutter"
    ],
    "wof:name":"Shutters By Q Corp",
    "wof:placetype":"venue"
},
  "geometry": {"coordinates":[-73.485992,40.77227],"type":"Point"}
}