{
  "type": "Feature",
  "properties": {
    "iso:country":"US",
    "sg:address":"139 Franklin St",
    "sg:city":"New York",
    "sg:classifiers":[
        {
            "category":"Professional",
            "type":"Services"
        }
    ],
    "sg:phone":"+1 212 501 7227",
    "sg:postcode":"10013",
    "sg:province":"NY",
    "sg:tags":[
        "establishment"
    ],
    "wof:name":"Gary Null Assoc",
    "wof:placetype":"venue"
},
  "geometry": {"coordinates":[-74.008357,40.719177],"type":"Point"}
}