{
  "type": "Feature",
  "properties": {
    "addr:full":"1765 Como Park Blvd Depew NY 14043",
    "addr:housenumber":"1765",
    "addr:postcode":"14043",
    "addr:street":"Como Park Blvd",
    "iso:country":"US",
    "sg:address":"1765 Como Park Blvd",
    "sg:city":"Depew",
    "sg:classifiers":[
        {
            "category":"Real Estate",
            "subcategory":"Real Estate Agent",
            "type":"Services"
        }
    ],
    "sg:phone":"+1 716 681 3850",
    "sg:postcode":"14043",
    "sg:province":"NY",
    "wof:name":"Hunt Real Estate ERA",
    "wof:placetype":"venue"
},
  "geometry": {"coordinates":[-78.687853,42.892512],"type":"Point"}
}