{
  "type": "Feature",
  "properties": {
    "addr:full":"1701 Sunrise Hwy Bay Shore NY 11706",
    "addr:housenumber":"1701",
    "addr:postcode":"11706",
    "addr:street":"Sunrise Hwy",
    "iso:country":"US",
    "sg:address":"1701 Sunrise Hwy",
    "sg:city":"Bay Shore",
    "sg:classifiers":[
        {
            "category":"Restaurant",
            "type":"Food & Drink"
        }
    ],
    "sg:menulink":"http://www.allmenus.com/ny/islip/61904-old-country-buffet/menu/",
    "sg:phone":"+1 631 969 3943",
    "sg:postcode":"11706",
    "sg:province":"NY",
    "sg:tags":[
        "american"
    ],
    "wof:name":"Old Country Buffet",
    "wof:placetype":"venue"
},
  "geometry": {"coordinates":[-73.25443,40.734658],"type":"Point"}
}