{
  "type": "Feature",
  "properties": {
    "addr:full":"241 Bay Ridge Ave Brooklyn NY 11220",
    "addr:housenumber":"241",
    "addr:postcode":"11220",
    "addr:street":"Bay Ridge Ave",
    "iso:country":"US",
    "sg:address":"241 Bay Ridge Ave",
    "sg:city":"Brooklyn",
    "sg:classifiers":[
        {
            "category":"Home & Garden",
            "subcategory":"Furniture",
            "type":"Retail Goods"
        }
    ],
    "sg:phone":"+1   ",
    "sg:postcode":"11220",
    "sg:province":"NY",
    "sg:tags":[
        "household"
    ],
    "wof:name":"Harrys For The Home",
    "wof:placetype":"venue"
},
  "geometry": {"coordinates":[-74.02628300000001,40.63592],"type":"Point"}
}