{
  "type": "Feature",
  "properties": {
    "iso:country":"US",
    "sg:address":"275 S Ridge St",
    "sg:city":"Rye Brook",
    "sg:classifiers":[
        {
            "category":"Restaurant",
            "type":"Food & Drink"
        }
    ],
    "sg:phone":"+1 914 937 5770",
    "sg:postcode":"10573",
    "sg:province":"NY",
    "wof:name":"Eclisse Northern Italian",
    "wof:placetype":"venue"
},
  "geometry": {"coordinates":[-73.681045,40.999431],"type":"Point"}
}