{
  "type": "Feature",
  "properties": {
    "addr:full":"630 Old Country Rd Unit 2084A Garden City NY 11530",
    "addr:housenumber":"630;2084a",
    "addr:postcode":"11530",
    "addr:street":"Old Country Rd Unit",
    "iso:country":"US",
    "sg:address":"630 Old Country Rd Unit 2084A",
    "sg:city":"Garden City",
    "sg:classifiers":[
        {
            "category":"Wholesale",
            "subcategory":"Computers",
            "type":"Manufacturing & Wholesale Goods"
        }
    ],
    "sg:phone":"+1 516 248 1219",
    "sg:postcode":"11530",
    "sg:province":"NY",
    "sg:website":"store.apple.com",
    "wof:name":"Apple Store",
    "wof:placetype":"venue"
},
  "geometry": {"coordinates":[-73.614296,40.742997],"type":"Point"}
}