{
  "type": "Feature",
  "properties": {
    "addr:full":"2035 River Rd Niagara Falls NY 14304",
    "addr:housenumber":"2035",
    "addr:postcode":"14304",
    "addr:street":"River Rd",
    "iso:country":"US",
    "sg:address":"2035 River Rd",
    "sg:city":"Niagara Falls",
    "sg:classifiers":[
        {
            "category":"Retail",
            "subcategory":"Auto Repair",
            "type":"Services"
        }
    ],
    "sg:phone":"+1 716 283 8388",
    "sg:postcode":"14304",
    "sg:province":"NY",
    "sg:tags":[
        "body",
        "automobile",
        "painting"
    ],
    "wof:name":"Larock's Restoration",
    "wof:placetype":"venue"
},
  "geometry": {"coordinates":[-78.94331099999999,43.072579],"type":"Point"}
}