{
  "type": "Feature",
  "properties": {
    "addr:full":"40 W Main St Chateaugay NY 12920",
    "addr:housenumber":"40",
    "addr:postcode":"12920",
    "addr:street":"W Main St",
    "iso:country":"US",
    "sg:address":"40 W Main St",
    "sg:city":"Chateaugay",
    "sg:classifiers":[
        {
            "category":"Restaurant",
            "type":"Food & Drink"
        }
    ],
    "sg:phone":"+1 518 497 0707",
    "sg:postcode":"12920",
    "sg:province":"NY",
    "wof:name":"Terriann's Restaurant",
    "wof:placetype":"venue"
},
  "geometry": {"coordinates":[-74.087692,44.925983],"type":"Point"}
}