{
  "type": "Feature",
  "properties": {
    "addr:full":"157 Elk St Buffalo NY 14210",
    "addr:housenumber":"157",
    "addr:postcode":"14210",
    "addr:street":"Elk St",
    "iso:country":"US",
    "sg:address":"157 Elk St",
    "sg:city":"Buffalo",
    "sg:classifiers":[
        {
            "category":"Education",
            "subcategory":"School",
            "type":"Public Place"
        }
    ],
    "sg:phone":"+1 716 816 4783",
    "sg:postcode":"14210",
    "sg:province":"NY",
    "wof:name":"Buffalo Public Schools",
    "wof:placetype":"venue"
},
  "geometry": {"coordinates":[-78.84804,42.868687],"type":"Point"}
}