{
  "type": "Feature",
  "properties": {
    "addr:full":"655 Riverside Dr New York NY 10031",
    "addr:housenumber":"655",
    "addr:postcode":"10031",
    "addr:street":"Riverside Dr",
    "iso:country":"US",
    "sg:address":"655 Riverside Dr",
    "sg:city":"New York",
    "sg:classifiers":[
        {
            "category":"Retail",
            "subcategory":"Auto Repair",
            "type":"Services"
        }
    ],
    "sg:phone":"+1 212 368 7637",
    "sg:postcode":"10031",
    "sg:province":"NY",
    "sg:tags":[
        "wrecker"
    ],
    "wof:name":"All Harlem Tire",
    "wof:placetype":"venue"
},
  "geometry": {"coordinates":[-73.953228,40.825505],"type":"Point"}
}