{
  "type": "Feature",
  "properties": {
    "iso:country":"US",
    "sg:address":"499 Ocean Pkwy",
    "sg:city":"Brooklyn",
    "sg:classifiers":[
        {
            "category":"Freight",
            "type":"Transportation"
        }
    ],
    "sg:phone":"+1   ",
    "sg:postcode":"11218",
    "sg:province":"NY",
    "sg:tags":[
        "operator",
        "local",
        "trucking"
    ],
    "wof:name":"E M & R Trucking Corporation",
    "wof:placetype":"venue"
},
  "geometry": {"coordinates":[-73.972458,40.636164],"type":"Point"}
}