{
  "type": "Feature",
  "properties": {
    "addr:full":"898 New Loudon Rd Latham NY 12110",
    "addr:housenumber":"898",
    "addr:postcode":"12110",
    "addr:street":"New Loudon Rd",
    "iso:country":"US",
    "sg:address":"898 New Loudon Rd",
    "sg:city":"Latham",
    "sg:classifiers":[
        {
            "category":"Restaurant",
            "type":"Food & Drink"
        }
    ],
    "sg:menulink":"http://www.allmenus.com/ny/colonie/62864-new-panda/menu/",
    "sg:phone":"+1 518 786 0700",
    "sg:postcode":"12110",
    "sg:province":"NY",
    "sg:tags":[
        "asian",
        "chinese"
    ],
    "wof:name":"New Panda",
    "wof:placetype":"venue"
},
  "geometry": {"coordinates":[-73.75785500000001,42.757375],"type":"Point"}
}