{
  "type": "Feature",
  "properties": {
    "iso:country":"US",
    "sg:address":"925 W Alaura Dr",
    "sg:city":"Alden",
    "sg:classifiers":[
        {
            "category":"Manufacturing",
            "subcategory":"Tools & Machinery",
            "type":"Manufacturing & Wholesale Goods"
        }
    ],
    "sg:phone":"+1   ",
    "sg:postcode":"14004",
    "sg:province":"NY",
    "sg:tags":[
        "industrial",
        "mfg"
    ],
    "wof:name":"5 Axis Unlimited",
    "wof:placetype":"venue"
},
  "geometry": {"coordinates":[-78.57311300000001,42.888724],"type":"Point"}
}