{
  "type": "Feature",
  "properties": {
    "iso:country":"US",
    "sg:address":"36 Zellweger Bch",
    "sg:city":"Hilton",
    "sg:classifiers":[
        {
            "category":"Manufacturing",
            "subcategory":"Buildings",
            "type":"Manufacturing & Wholesale Goods"
        },
        {
            "category":"Building & Trades",
            "subcategory":"Construction",
            "type":"Services"
        }
    ],
    "sg:phone":"+1 585 392 1306",
    "sg:postcode":"14468",
    "sg:province":"NY",
    "sg:tags":[
        "home",
        "builder",
        "contractor"
    ],
    "wof:name":"Kozlowsky Construction",
    "wof:placetype":"venue"
},
  "geometry": {"coordinates":[-77.774703,43.339462],"type":"Point"}
}