{
  "type": "Feature",
  "properties": {
    "iso:country":"US",
    "sg:address":"567 Dune Rd",
    "sg:city":"Westhampton Bch",
    "sg:classifiers":[
        {
            "category":"Real Estate",
            "subcategory":"Real Estate Operator",
            "type":"Services"
        }
    ],
    "sg:phone":"+1 631 288 6559",
    "sg:postcode":"11978",
    "sg:province":"NY",
    "sg:tags":[
        "condominium"
    ],
    "wof:name":"High Dune Condo Mntnc Ofc",
    "wof:placetype":"venue"
},
  "geometry": {"coordinates":[-72.681673,40.784649],"type":"Point"}
}