{
  "type": "Feature",
  "properties": {
    "addr:full":"201 W 131st St New York NY 10027",
    "addr:housenumber":"201",
    "addr:postcode":"10027",
    "addr:street":"W 131St St",
    "iso:country":"US",
    "sg:address":"201 W 131st St",
    "sg:city":"New York",
    "sg:classifiers":[
        {
            "category":"Food & Beverages",
            "subcategory":"Groceries & Convenience Stores",
            "type":"Retail Goods"
        }
    ],
    "sg:phone":"+1 212 368 3100",
    "sg:postcode":"10027",
    "sg:province":"NY",
    "wof:name":"Sarh Deli & Grocery",
    "wof:placetype":"venue"
},
  "geometry": {"coordinates":[-73.945581,40.812926],"type":"Point"}
}