{
  "type": "Feature",
  "properties": {
    "iso:country":"US",
    "sg:address":"26 Leighton Ave",
    "sg:city":"Rochester",
    "sg:classifiers":[
        {
            "category":"Home & Garden",
            "subcategory":"Building Materials",
            "type":"Retail Goods"
        }
    ],
    "sg:phone":"+1 585 482 4860",
    "sg:postcode":"14609",
    "sg:province":"NY",
    "sg:tags":[
        "glass",
        "window",
        "plate"
    ],
    "wof:name":"Atlantic Glass & Mirror",
    "wof:placetype":"venue"
},
  "geometry": {"coordinates":[-77.573201,43.158967],"type":"Point"}
}