{
  "type": "Feature",
  "properties": {
    "iso:country":"US",
    "sg:address":"291 Young St",
    "sg:city":"Wilson",
    "sg:classifiers":[
        {
            "category":"Home & Garden",
            "subcategory":"Hardware",
            "type":"Retail Goods"
        }
    ],
    "sg:phone":"+1   ",
    "sg:postcode":"14172",
    "sg:province":"NY",
    "wof:name":"Schefflers",
    "wof:placetype":"venue"
},
  "geometry": {"coordinates":[-78.826048,43.309606],"type":"Point"}
}