{
  "type": "Feature",
  "properties": {
    "iso:country":"US",
    "sg:address":"1624 Stillwell Avenue",
    "sg:city":"Bronx",
    "sg:classifiers":[
        {
            "category":"Wholesale",
            "subcategory":"Fruits & Vegetables",
            "type":"Manufacturing & Wholesale Goods"
        }
    ],
    "sg:phone":"+1 718 828 0800",
    "sg:postcode":"10461",
    "sg:province":"NY",
    "sg:tags":[
        "veggie"
    ],
    "wof:name":"Cz Whol Fruits & Vegetables",
    "wof:placetype":"venue"
},
  "geometry": {"coordinates":[-73.84025200000001,40.855603],"type":"Point"}
}