{
  "type": "Feature",
  "properties": {
    "iso:country":"US",
    "sg:address":"465 Paul Rd",
    "sg:city":"Rochester",
    "sg:classifiers":[
        {
            "category":"Professional",
            "subcategory":"Research",
            "type":"Services"
        }
    ],
    "sg:phone":"+1 585 429 1600",
    "sg:postcode":"14624",
    "sg:province":"NY",
    "sg:tags":[
        "development",
        "laboratory"
    ],
    "sg:website":"www.codaco.com",
    "wof:name":"Codaco",
    "wof:placetype":"venue"
},
  "geometry": {"coordinates":[-77.721074,43.106306],"type":"Point"}
}