{
  "type": "Feature",
  "properties": {
    "addr:full":"1400 Altamont Ave Schenectady NY 12303",
    "addr:housenumber":"1400",
    "addr:postcode":"12303",
    "addr:street":"Altamont Ave",
    "iso:country":"US",
    "sg:address":"1400 Altamont Ave",
    "sg:city":"Schenectady",
    "sg:classifiers":[
        {
            "category":"Banks & Credit Unions",
            "subcategory":"Bank",
            "type":"Services"
        }
    ],
    "sg:phone":"+1 518 356 1317",
    "sg:postcode":"12303",
    "sg:province":"NY",
    "sg:tags":[
        "saving",
        "commercial"
    ],
    "sg:website":"http://www.trustcobank.com",
    "wof:name":"Trustco Bank",
    "wof:placetype":"venue"
},
  "geometry": {"coordinates":[-73.944537,42.785301],"type":"Point"}
}