{
  "type": "Feature",
  "properties": {
    "addr:full":"75 Varick St New York NY 10013",
    "addr:housenumber":"75",
    "addr:postcode":"10013",
    "addr:street":"Varick St",
    "iso:country":"US",
    "sg:address":"75 Varick St",
    "sg:city":"New York",
    "sg:classifiers":[
        {
            "category":"Social Services",
            "subcategory":"Child Care",
            "type":"Services"
        }
    ],
    "sg:phone":"+1 212 925 0005",
    "sg:postcode":"10013",
    "sg:province":"NY",
    "sg:tags":[
        "day"
    ],
    "wof:name":"Day Care Council-Local 205 D C 1707 Welfare Fund",
    "wof:placetype":"venue"
},
  "geometry": {"coordinates":[-74.00630200000001,40.722599],"type":"Point"}
}