{
  "type": "Feature",
  "properties": {
    "iso:country":"US",
    "sg:address":"204 Elm Rd",
    "sg:city":"Mahopac",
    "sg:classifiers":[
        {
            "category":"Building & Trades",
            "subcategory":"Construction",
            "type":"Services"
        }
    ],
    "sg:phone":"+1 914 736 3431",
    "sg:postcode":"10541",
    "sg:province":"NY",
    "sg:tags":[
        "system",
        "specialty",
        "heating",
        "contractor",
        "air conditioning"
    ],
    "wof:name":"Fr Heating",
    "wof:placetype":"venue"
},
  "geometry": {"coordinates":[-73.79195799999999,41.379851],"type":"Point"}
}