{
  "type": "Feature",
  "properties": {
    "addr:full":"I U Willets Rd Roslyn NY 11576",
    "addr:postcode":"11576",
    "addr:street":"Willets Rd",
    "iso:country":"US",
    "sg:address":"I U Willets Rd",
    "sg:city":"Roslyn",
    "sg:classifiers":[
        {
            "category":"Education",
            "subcategory":"Preschool",
            "type":"Public Place"
        },
        {
            "category":"Education",
            "subcategory":"School",
            "type":"Public Place"
        }
    ],
    "sg:phone":"+1 516 627 1910",
    "sg:postcode":"11576",
    "sg:province":"NY",
    "sg:tags":[
        "elementary"
    ],
    "wof:name":"Buckley Country Day School",
    "wof:placetype":"venue"
},
  "geometry": {"coordinates":[-73.648399,40.797001],"type":"Point"}
}