{
  "type": "Feature",
  "properties": {
    "addr:full":"1741 Broad Hollow Rd Farmingdale NY 11735",
    "addr:housenumber":"1741",
    "addr:postcode":"11735",
    "addr:street":"Broad Hollow Rd",
    "iso:country":"US",
    "sg:address":"1741 Broad Hollow Rd",
    "sg:city":"Farmingdale",
    "sg:classifiers":[
        {
            "category":"Home & Garden",
            "subcategory":"Furniture",
            "type":"Retail Goods"
        }
    ],
    "sg:phone":"+1 631 777 1841",
    "sg:postcode":"11735",
    "sg:province":"NY",
    "wof:name":"All Island Furniture",
    "wof:placetype":"venue"
},
  "geometry": {"coordinates":[-73.42289700000001,40.740101],"type":"Point"}
}