{
  "type": "Feature",
  "properties": {
    "addr:full":"14 Latourette Ln Staten Island NY 10314",
    "addr:housenumber":"14",
    "addr:postcode":"10314",
    "addr:street":"Latourette Ln",
    "iso:country":"US",
    "sg:address":"14 Latourette Ln",
    "sg:city":"Staten Island",
    "sg:classifiers":[
        {
            "category":"Social Services",
            "subcategory":"Child Care",
            "type":"Services"
        }
    ],
    "sg:phone":"+1   ",
    "sg:postcode":"10314",
    "sg:province":"NY",
    "sg:tags":[
        "day"
    ],
    "wof:name":"Building Blocks Services Inc",
    "wof:placetype":"venue"
},
  "geometry": {"coordinates":[-74.146097,40.589897],"type":"Point"}
}