{
  "type": "Feature",
  "properties": {
    "iso:country":"US",
    "sg:address":"250 Crown St",
    "sg:city":"Brooklyn",
    "sg:classifiers":[
        {
            "category":"Community Center",
            "type":"Public Place"
        }
    ],
    "sg:phone":"+1 718 919 1962",
    "sg:postcode":"11225",
    "sg:province":"NY",
    "sg:tags":[
        "medical"
    ],
    "wof:name":"Interfaith Medical Center",
    "wof:placetype":"venue"
},
  "geometry": {"coordinates":[-73.95175999999999,40.666034],"type":"Point"}
}