{
  "type": "Feature",
  "properties": {
    "iso:country":"US",
    "sg:address":"2155 Broadway",
    "sg:city":"Schenectady",
    "sg:classifiers":[
        {
            "category":"Autos & Motor Vehicles",
            "subcategory":"Automobile Sales",
            "type":"Retail Goods"
        }
    ],
    "sg:phone":"+1 518 372 7555",
    "sg:postcode":"12306",
    "sg:province":"NY",
    "sg:tags":[
        "car",
        "dealer"
    ],
    "wof:name":"Bobar's Used Cars",
    "wof:placetype":"venue"
},
  "geometry": {"coordinates":[-73.967648,42.796946],"type":"Point"}
}