{
  "type": "Feature",
  "properties": {
    "iso:country":"US",
    "sg:address":"329 Church Ave",
    "sg:city":"Brooklyn",
    "sg:classifiers":[
        {
            "category":"Food & Beverages",
            "subcategory":"Fruits & Vegetables",
            "type":"Retail Goods"
        }
    ],
    "sg:phone":"+1 718 871 1009",
    "sg:postcode":"11218",
    "sg:province":"NY",
    "sg:tags":[
        "grocery",
        "produce"
    ],
    "wof:name":"Golden Farm",
    "wof:placetype":"venue"
},
  "geometry": {"coordinates":[-73.977197,40.643738],"type":"Point"}
}