{
  "type": "Feature",
  "properties": {
    "addr:full":"15 Kempster Rd Scarsdale NY 10583",
    "addr:housenumber":"15",
    "addr:postcode":"10583",
    "addr:street":"Kempster Rd",
    "iso:country":"US",
    "sg:address":"15 Kempster Rd",
    "sg:city":"Scarsdale",
    "sg:classifiers":[
        {
            "category":"Real Estate",
            "subcategory":"Real Estate Operator",
            "type":"Services"
        }
    ],
    "sg:phone":"+1 914 472 6040",
    "sg:postcode":"10583",
    "sg:province":"NY",
    "sg:tags":[
        "building",
        "apartment"
    ],
    "wof:name":"Farkas Realty Services Inc",
    "wof:placetype":"venue"
},
  "geometry": {"coordinates":[-73.816181,40.990585],"type":"Point"}
}