{
  "type": "Feature",
  "properties": {
    "iso:country":"US",
    "sg:address":"51 E 25th St",
    "sg:city":"New York",
    "sg:classifiers":[
        {
            "category":"Professional",
            "subcategory":"Employment Agencies",
            "type":"Services"
        }
    ],
    "sg:phone":"+1 212 545 0363",
    "sg:postcode":"10010",
    "sg:province":"NY",
    "wof:name":"Bonnie Lunt Management",
    "wof:placetype":"venue"
},
  "geometry": {"coordinates":[-73.98220999999999,40.740114],"type":"Point"}
}