{
  "type": "Feature",
  "properties": {
    "iso:country":"US",
    "sg:address":"203 Colonial Dr",
    "sg:city":"Horseheads",
    "sg:classifiers":[
        {
            "category":"Professional",
            "subcategory":"Computer Services",
            "type":"Services"
        }
    ],
    "sg:phone":"+1 607 739 4511",
    "sg:postcode":"14845",
    "sg:province":"NY",
    "sg:tags":[
        "design",
        "analysis",
        "software"
    ],
    "wof:name":"Salient Corp",
    "wof:placetype":"venue"
},
  "geometry": {"coordinates":[-76.86952599999999,42.162475],"type":"Point"}
}