{
  "type": "Feature",
  "properties": {
    "addr:full":"642 W 57th Street New York NY 10019",
    "addr:housenumber":"642",
    "addr:postcode":"10019",
    "addr:street":"W 57Th Street",
    "iso:country":"US",
    "sg:address":"642 W 57th Street",
    "sg:city":"New York",
    "sg:classifiers":[
        {
            "category":"Retail",
            "subcategory":"Auto Repair",
            "type":"Services"
        }
    ],
    "sg:phone":"+1 212 246 5530",
    "sg:postcode":"10019",
    "sg:province":"NY",
    "wof:name":"Jamie's Foreign Car Service",
    "wof:placetype":"venue"
},
  "geometry": {"coordinates":[-73.993312,40.771255],"type":"Point"}
}