{
  "type": "Feature",
  "properties": {
    "iso:country":"US",
    "sg:address":"498 W End Ave",
    "sg:city":"New York",
    "sg:classifiers":[
        {
            "category":"Real Estate",
            "subcategory":"Real Estate Services",
            "type":"Services"
        }
    ],
    "sg:phone":"+1 212 496 6042",
    "sg:postcode":"10024",
    "sg:province":"NY",
    "wof:name":"Weisbord Jeffrey Real Estate Broker",
    "wof:placetype":"venue"
},
  "geometry": {"coordinates":[-73.978798,40.787601],"type":"Point"}
}