{
  "type": "Feature",
  "properties": {
    "iso:country":"US",
    "sg:address":"250 W 19 St",
    "sg:city":"New York",
    "sg:classifiers":[
        {
            "category":"Professional",
            "subcategory":"Business Services",
            "type":"Services"
        }
    ],
    "sg:phone":"+1 212 924 9691",
    "sg:postcode":"10011",
    "sg:province":"NY",
    "sg:tags":[
        "interior",
        "consultant",
        "design",
        "decorator"
    ],
    "wof:name":"Jonathan Ringel Inc",
    "wof:placetype":"venue"
},
  "geometry": {"coordinates":[-73.99938400000001,40.742258],"type":"Point"}
}