{
  "type": "Feature",
  "properties": {
    "addr:full":"170 Canal St Ellenville NY 12428",
    "addr:housenumber":"170",
    "addr:postcode":"12428",
    "addr:street":"Canal St",
    "iso:country":"US",
    "sg:address":"170 Canal St",
    "sg:city":"Ellenville",
    "sg:classifiers":[
        {
            "category":"Sports & Exercise",
            "subcategory":"Gym",
            "type":"Entertainment"
        }
    ],
    "sg:phone":"+1 845 647 0035",
    "sg:postcode":"12428",
    "sg:province":"NY",
    "sg:tags":[
        "club",
        "health",
        "studio",
        "gymnasium"
    ],
    "wof:name":"Curves",
    "wof:placetype":"venue"
},
  "geometry": {"coordinates":[-74.392016,41.716025],"type":"Point"}
}