{
  "type": "Feature",
  "properties": {
    "addr:full":"4 Brewster Ave Northport NY 11768",
    "addr:housenumber":"4",
    "addr:postcode":"11768",
    "addr:street":"Brewster Ave",
    "iso:country":"US",
    "sg:address":"4 Brewster Ave",
    "sg:city":"Northport",
    "sg:classifiers":[
        {
            "category":"Professional",
            "subcategory":"Accounting & Tax Preparation",
            "type":"Services"
        }
    ],
    "sg:phone":"+1 631 261 2269",
    "sg:postcode":"11768",
    "sg:province":"NY",
    "sg:tags":[
        "accountant"
    ],
    "wof:name":"Naoum P Tsaousis CPA",
    "wof:placetype":"venue"
},
  "geometry": {"coordinates":[-73.28430899999999,40.892176],"type":"Point"}
}