{
  "type": "Feature",
  "properties": {
    "addr:full":"58 Pershing Ave Poughkeepsie NY 12601",
    "addr:housenumber":"58",
    "addr:postcode":"12601",
    "addr:street":"Pershing Ave",
    "iso:country":"US",
    "sg:address":"58 Pershing Ave",
    "sg:city":"Poughkeepsie",
    "sg:classifiers":[
        {
            "category":"Manufacturing",
            "subcategory":"Metals",
            "type":"Manufacturing & Wholesale Goods"
        }
    ],
    "sg:phone":"+1   ",
    "sg:postcode":"12601",
    "sg:province":"NY",
    "sg:tags":[
        "steel",
        "product",
        "mfg",
        "primary",
        "shape",
        "cold"
    ],
    "wof:name":"Rollo Advanced Design",
    "wof:placetype":"venue"
},
  "geometry": {"coordinates":[-73.913191,41.702307],"type":"Point"}
}