{
  "type": "Feature",
  "properties": {
    "addr:full":"50 W Lake St Skaneateles NY 13152",
    "addr:housenumber":"50",
    "addr:postcode":"13152",
    "addr:street":"W Lake St",
    "iso:country":"US",
    "sg:address":"50 W Lake St",
    "sg:city":"Skaneateles",
    "sg:classifiers":[
        {
            "category":"Professional",
            "type":"Services"
        }
    ],
    "sg:phone":"+1 315 685 0557",
    "sg:postcode":"13152",
    "sg:province":"NY",
    "sg:tags":[
        "establishment"
    ],
    "wof:name":"Fine Details",
    "wof:placetype":"venue"
},
  "geometry": {"coordinates":[-76.433869,42.941273],"type":"Point"}
}