{
  "type": "Feature",
  "properties": {
    "addr:full":"430 Route 25A Ste 4 Saint James NY 11780",
    "addr:housenumber":"430",
    "addr:postcode":"11780",
    "addr:street":"Route 25A Ste 4",
    "iso:country":"US",
    "sg:address":"430 Route 25A Ste 4",
    "sg:city":"Saint James",
    "sg:classifiers":[
        {
            "category":"Food & Beverages",
            "subcategory":"Liquor & Beverages",
            "type":"Retail Goods"
        }
    ],
    "sg:phone":"+1 631 862 7020",
    "sg:postcode":"11780",
    "sg:province":"NY",
    "sg:tags":[
        "beer",
        "spirit",
        "wine"
    ],
    "wof:name":"Liquorium Wine & Liquors",
    "wof:placetype":"venue"
},
  "geometry": {"coordinates":[-73.17040299999999,40.8759],"type":"Point"}
}