{
  "type": "Feature",
  "properties": {
    "iso:country":"US",
    "sg:address":"5829 Camp Rd",
    "sg:city":"Hamburg",
    "sg:classifiers":[
        {
            "category":"Autos & Motor Vehicles",
            "subcategory":"Auto Supplies",
            "type":"Retail Goods"
        }
    ],
    "sg:phone":"+1 716 649 0484",
    "sg:postcode":"14075",
    "sg:province":"NY",
    "sg:tags":[
        "automobile",
        "parts"
    ],
    "wof:name":"Autozone",
    "wof:placetype":"venue"
},
  "geometry": {"coordinates":[-78.83677299999999,42.728372],"type":"Point"}
}