{
  "type": "Feature",
  "properties": {
    "addr:full":"3840 E Tremont Ave Bronx NY 10465",
    "addr:housenumber":"3840",
    "addr:postcode":"10465",
    "addr:street":"E Tremont Ave",
    "iso:country":"US",
    "sg:address":"3840 E Tremont Ave",
    "sg:city":"Bronx",
    "sg:classifiers":[
        {
            "category":"Personal",
            "type":"Services"
        }
    ],
    "sg:phone":"+1   ",
    "sg:postcode":"10465",
    "sg:province":"NY",
    "wof:name":"Oracle",
    "wof:placetype":"venue"
},
  "geometry": {"coordinates":[-73.82017399999999,40.824272],"type":"Point"}
}