{
  "type": "Feature",
  "properties": {
    "addr:full":"18 Cooks Ln Walden NY 12586",
    "addr:housenumber":"18",
    "addr:postcode":"12586",
    "addr:street":"Cooks Ln",
    "iso:country":"US",
    "sg:address":"18 Cooks Ln",
    "sg:city":"Walden",
    "sg:classifiers":[
        {
            "category":"Building & Trades",
            "subcategory":"Plumbing",
            "type":"Services"
        }
    ],
    "sg:phone":"+1 845 895 2501",
    "sg:postcode":"12586",
    "sg:province":"NY",
    "sg:tags":[
        "tank",
        "septic"
    ],
    "wof:name":"American Septic & Excavating",
    "wof:placetype":"venue"
},
  "geometry": {"coordinates":[-74.122028,41.540928],"type":"Point"}
}