{
  "type": "Feature",
  "properties": {
    "iso:country":"US",
    "sg:address":"19 Fulton St",
    "sg:city":"New York",
    "sg:classifiers":[
        {
            "category":"Insurance",
            "subcategory":"Insurance Agent",
            "type":"Services"
        }
    ],
    "sg:phone":"+1 212 406 4499",
    "sg:postcode":"10038",
    "sg:province":"NY",
    "wof:name":"C & S Insurance",
    "wof:placetype":"venue"
},
  "geometry": {"coordinates":[-74.003941,40.707228],"type":"Point"}
}