{
  "type": "Feature",
  "properties": {
    "iso:country":"US",
    "sg:address":"3300 Franklin Ave",
    "sg:city":"Millbrook",
    "sg:classifiers":[
        {
            "category":"Shopping",
            "subcategory":"Used Merchandise",
            "type":"Retail Goods"
        }
    ],
    "sg:phone":"+1 845 677 9786",
    "sg:postcode":"12545",
    "sg:province":"NY",
    "sg:tags":[
        "antique"
    ],
    "wof:name":"Red School House Antiques",
    "wof:placetype":"venue"
},
  "geometry": {"coordinates":[-73.691703,41.785379],"type":"Point"}
}