{
  "type": "Feature",
  "properties": {
    "iso:country":"US",
    "sg:address":"8633 State Hwy 20A",
    "sg:city":"Honeoye",
    "sg:classifiers":[
        {
            "category":"Banks & Credit Unions",
            "subcategory":"Bank",
            "type":"Services"
        }
    ],
    "sg:phone":"+1 585 229 5146",
    "sg:postcode":"14471",
    "sg:province":"NY",
    "wof:name":"Canandaigua National Bank",
    "wof:placetype":"venue"
},
  "geometry": {"coordinates":[-77.50014299999999,42.789578],"type":"Point"}
}