{
  "type": "Feature",
  "properties": {
    "addr:full":"5528 S Abbott Rd Hamburg NY 14075",
    "addr:housenumber":"5528",
    "addr:postcode":"14075",
    "addr:street":"S Abbott Rd",
    "iso:country":"US",
    "sg:address":"5528 S Abbott Rd",
    "sg:city":"Hamburg",
    "sg:classifiers":[
        {
            "category":"Retail",
            "subcategory":"Animal Services",
            "type":"Services"
        }
    ],
    "sg:phone":"+1 716 649 0712",
    "sg:postcode":"14075",
    "sg:province":"NY",
    "wof:name":"Ton Dor Boarding Training Kenl",
    "wof:placetype":"venue"
},
  "geometry": {"coordinates":[-78.797803,42.7369],"type":"Point"}
}