{
  "type": "Feature",
  "properties": {
    "addr:full":"3525 E Henrietta Rd Henrietta NY 14467",
    "addr:housenumber":"3525",
    "addr:postcode":"14467",
    "addr:street":"E Henrietta Rd",
    "iso:country":"US",
    "sg:address":"3525 E Henrietta Rd",
    "sg:city":"Henrietta",
    "sg:classifiers":[
        {
            "category":"Organizations",
            "subcategory":"Community Association",
            "type":"Services"
        }
    ],
    "sg:phone":"+1 585 334 1900",
    "sg:postcode":"14467",
    "sg:province":"NY",
    "sg:tags":[
        "fraternal"
    ],
    "wof:name":"Elks Lodge",
    "wof:placetype":"venue"
},
  "geometry": {"coordinates":[-77.61629000000001,43.05259],"type":"Point"}
}