{
  "type": "Feature",
  "properties": {
    "iso:country":"US",
    "sg:address":"71 S Main St",
    "sg:city":"New Berlin",
    "sg:classifiers":[
        {
            "category":"Building & Trades",
            "subcategory":"Construction",
            "type":"Services"
        }
    ],
    "sg:phone":"+1 607 847 8811",
    "sg:postcode":"13411",
    "sg:province":"NY",
    "sg:tags":[
        "marking",
        "maintenance",
        "parking"
    ],
    "wof:name":"New Berlin Public Works Barn",
    "wof:placetype":"venue"
},
  "geometry": {"coordinates":[-75.33285100000001,42.618167],"type":"Point"}
}