{
  "type": "Feature",
  "properties": {
    "addr:full":"853 Second Ave. New York NY 10017",
    "addr:housenumber":"853",
    "addr:postcode":"10017",
    "addr:street":"Second Ave.",
    "iso:country":"US",
    "sg:address":"853 Second Ave.",
    "sg:city":"New York",
    "sg:classifiers":[
        {
            "category":"Personal",
            "subcategory":"Barber",
            "type":"Services"
        }
    ],
    "sg:phone":"+1 917 862 7642",
    "sg:postcode":"10017",
    "sg:province":"NY",
    "wof:name":"Golden Hair Salon & Barber Shop",
    "wof:placetype":"venue"
},
  "geometry": {"coordinates":[-73.970401,40.75229],"type":"Point"}
}