{
  "type": "Feature",
  "properties": {
    "iso:country":"US",
    "sg:address":"426 89th St",
    "sg:city":"Brooklyn",
    "sg:classifiers":[
        {
            "category":"Food & Beverages",
            "subcategory":"Liquor & Beverages",
            "type":"Retail Goods"
        }
    ],
    "sg:phone":"+1   ",
    "sg:postcode":"11209",
    "sg:province":"NY",
    "sg:tags":[
        "alcoholic"
    ],
    "wof:name":"Ridge Beverage Inc",
    "wof:placetype":"venue"
},
  "geometry": {"coordinates":[-74.028071,40.619875],"type":"Point"}
}