{
  "type": "Feature",
  "properties": {
    "iso:country":"US",
    "sg:address":"357 Merrick Rd",
    "sg:city":"Lynbrook",
    "sg:classifiers":[
        {
            "category":"Manufacturing",
            "subcategory":"Apparel",
            "type":"Manufacturing & Wholesale Goods"
        },
        {
            "category":"Shopping",
            "subcategory":"Clothing, Apparel, & Fashions",
            "type":"Retail Goods"
        }
    ],
    "sg:phone":"+1 516 593 8768",
    "sg:postcode":"11563",
    "sg:province":"NY",
    "sg:tags":[
        "shop",
        "bridal",
        "dress",
        "mfg"
    ],
    "wof:name":"Belle Vie Bridals",
    "wof:placetype":"venue"
},
  "geometry": {"coordinates":[-73.67163499999999,40.657151],"type":"Point"}
}