{
  "type": "Feature",
  "properties": {
    "iso:country":"US",
    "sg:address":"166 Ludlow St",
    "sg:city":"Yonkers",
    "sg:classifiers":[
        {
            "category":"Professional",
            "subcategory":"Business Services",
            "type":"Services"
        }
    ],
    "sg:phone":"+1   ",
    "sg:postcode":"10705",
    "sg:province":"NY",
    "wof:name":"Recreations Murals Ltd",
    "wof:placetype":"venue"
},
  "geometry": {"coordinates":[-73.90256599999999,40.924034],"type":"Point"}
}