{
  "type": "Feature",
  "properties": {
    "addr:full":"33 W 19th St, Fl 4 New York NY 10011",
    "addr:housenumber":"33;4",
    "addr:postcode":"10011",
    "addr:street":"W 19Th St",
    "iso:country":"US",
    "sg:address":"33 W 19th St, Fl 4",
    "sg:city":"New York",
    "sg:classifiers":[
        {
            "category":"Professional",
            "subcategory":"Computer Services",
            "type":"Services"
        }
    ],
    "sg:phone":"+1 646 770 1758",
    "sg:postcode":"10011",
    "sg:province":"NY",
    "sg:tags":[
        "deliveries",
        "local",
        "ecommerce",
        "merchant",
        "new-york-city",
        "personal-assistance",
        "errands"
    ],
    "sg:website":"http://zipgigs.com/",
    "wof:name":"ZipGigs",
    "wof:placetype":"venue"
},
  "geometry": {"coordinates":[-73.99375999999999,40.740065],"type":"Point"}
}