{
  "type": "Feature",
  "properties": {
    "iso:country":"US",
    "sg:address":"4702 State Hwy 31",
    "sg:city":"Vernon",
    "sg:classifiers":[
        {
            "category":"Retail",
            "subcategory":"Auto Repair",
            "type":"Services"
        }
    ],
    "sg:phone":"+1 315 829 2083",
    "sg:postcode":"13476",
    "sg:province":"NY",
    "sg:tags":[
        "repairing",
        "automobile"
    ],
    "wof:name":"Jim's Small Engine",
    "wof:placetype":"venue"
},
  "geometry": {"coordinates":[-75.555142,43.101848],"type":"Point"}
}