{
  "type": "Feature",
  "properties": {
    "iso:country":"US",
    "sg:address":"2208 State Route 208",
    "sg:city":"Montgomery",
    "sg:classifiers":[
        {
            "category":"Professional",
            "subcategory":"Lawyer & Legal Services",
            "type":"Services"
        }
    ],
    "sg:phone":"+1 845 457 9009",
    "sg:postcode":"12549",
    "sg:province":"NY",
    "wof:name":"McGillicuddy & Siegel PC",
    "wof:placetype":"venue"
},
  "geometry": {"coordinates":[-74.20120199999999,41.522999],"type":"Point"}
}