{
  "type": "Feature",
  "properties": {
    "iso:country":"US",
    "sg:address":"3782 3rd Avenue",
    "sg:city":"Bronx",
    "sg:classifiers":[
        {
            "category":"Bakery",
            "type":"Food & Drink"
        }
    ],
    "sg:phone":"+1 718 992 4332",
    "sg:postcode":"10456",
    "sg:province":"NY",
    "wof:name":"Uncle Willie's Bakery",
    "wof:placetype":"venue"
},
  "geometry": {"coordinates":[-73.902148,40.836922],"type":"Point"}
}