{
  "type": "Feature",
  "properties": {
    "iso:country":"US",
    "sg:address":"317 Stonytown Rd",
    "sg:city":"Manhasset",
    "sg:classifiers":[
        {
            "category":"Professional",
            "subcategory":"Employment Agencies",
            "type":"Services"
        }
    ],
    "sg:phone":"+1 516 869 3577",
    "sg:postcode":"11030",
    "sg:province":"NY",
    "sg:tags":[
        "consultant",
        "search",
        "executive"
    ],
    "wof:name":"E & F Search Assoc",
    "wof:placetype":"venue"
},
  "geometry": {"coordinates":[-73.69073,40.810161],"type":"Point"}
}