{
  "type": "Feature",
  "properties": {
    "addr:full":"764 9th Ave New York NY 10019",
    "addr:housenumber":"764",
    "addr:postcode":"10019",
    "addr:street":"9Th Ave",
    "iso:country":"US",
    "sg:address":"764 9th Ave",
    "sg:city":"New York",
    "sg:classifiers":[
        {
            "category":"Restaurant",
            "type":"Food & Drink"
        }
    ],
    "sg:phone":"+1 212 977 3098",
    "sg:postcode":"10019",
    "sg:province":"NY",
    "sg:tags":[
        "indian"
    ],
    "sg:website":"orderBombayExpress.com",
    "wof:name":"Bombay Express",
    "wof:placetype":"venue"
},
  "geometry": {"coordinates":[-73.988055,40.764143],"type":"Point"}
}