{
  "type": "Feature",
  "properties": {
    "iso:country":"US",
    "sg:address":"5097 Transit Rd",
    "sg:city":"Buffalo",
    "sg:classifiers":[
        {
            "category":"Shopping",
            "subcategory":"Gifts & Souvenirs",
            "type":"Retail Goods"
        }
    ],
    "sg:phone":"+1 716 626 3333",
    "sg:postcode":"14221",
    "sg:province":"NY",
    "sg:tags":[
        "party",
        "supply"
    ],
    "sg:website":"www.partycity.com",
    "wof:name":"Party City",
    "wof:placetype":"venue"
},
  "geometry": {"coordinates":[-78.69686900000001,42.983933],"type":"Point"}
}