{
  "type": "Feature",
  "properties": {
    "iso:country":"US",
    "sg:address":"261 W Main St",
    "sg:city":"Sayville",
    "sg:classifiers":[
        {
            "category":"Bars & Pubs",
            "type":"Food & Drink"
        }
    ],
    "sg:phone":"+1 631 567 9179",
    "sg:postcode":"11782",
    "sg:province":"NY",
    "wof:name":"Main Street Sports Bar",
    "wof:placetype":"venue"
},
  "geometry": {"coordinates":[-73.08838,40.733004],"type":"Point"}
}