{
  "type": "Feature",
  "properties": {
    "addr:full":"167 Glen St Glens Falls NY 12801",
    "addr:housenumber":"167",
    "addr:postcode":"12801",
    "addr:street":"Glen St",
    "iso:country":"US",
    "sg:address":"167 Glen St",
    "sg:city":"Glens Falls",
    "sg:classifiers":[
        {
            "category":"Shopping",
            "subcategory":"Jewelry",
            "type":"Retail Goods"
        }
    ],
    "sg:phone":"+1 518 793 1442",
    "sg:postcode":"12801",
    "sg:province":"NY",
    "sg:tags":[
        "jeweler"
    ],
    "sg:website":"www.scovillejewelers.com",
    "wof:name":"Scoville Jewelers",
    "wof:placetype":"venue"
},
  "geometry": {"coordinates":[-73.64400500000001,43.309512],"type":"Point"}
}