{
  "type": "Feature",
  "properties": {
    "addr:full":"302 Dellwood Rd Rochester NY 14616",
    "addr:housenumber":"302",
    "addr:postcode":"14616",
    "addr:street":"Dellwood Rd",
    "iso:country":"US",
    "sg:address":"302 Dellwood Rd",
    "sg:city":"Rochester",
    "sg:classifiers":[
        {
            "category":"Arts & Performance",
            "subcategory":"Theater",
            "type":"Entertainment"
        }
    ],
    "sg:phone":"+1 585 663 6180",
    "sg:postcode":"14616",
    "sg:province":"NY",
    "sg:tags":[
        "entertainer"
    ],
    "wof:name":"Peggy Dolan Guitarist & Vclst",
    "wof:placetype":"venue"
},
  "geometry": {"coordinates":[-77.644285,43.24737],"type":"Point"}
}