{
  "type": "Feature",
  "properties": {
    "addr:full":"72 Henry St Binghamton NY 13901",
    "addr:housenumber":"72",
    "addr:postcode":"13901",
    "addr:street":"Henry St",
    "iso:country":"US",
    "sg:address":"72 Henry St",
    "sg:city":"Binghamton",
    "sg:classifiers":[
        {
            "category":"Retail",
            "subcategory":"Auto Repair",
            "type":"Services"
        }
    ],
    "sg:phone":"+1 607 722 5331",
    "sg:postcode":"13901",
    "sg:province":"NY",
    "sg:tags":[
        "repairing",
        "automobile"
    ],
    "sg:website":"www.goodyear.com",
    "wof:name":"Goodyear Auto Svc Ctr",
    "wof:placetype":"venue"
},
  "geometry": {"coordinates":[-75.909075,42.100936],"type":"Point"}
}