{
  "type": "Feature",
  "properties": {
    "iso:country":"US",
    "sg:address":"54 Clinton St",
    "sg:city":"Center Moriches",
    "sg:classifiers":[
        {
            "category":"Building & Trades",
            "subcategory":"Landscaping Services",
            "type":"Services"
        }
    ],
    "sg:phone":"+1 631 878 2445",
    "sg:postcode":"11934",
    "sg:province":"NY",
    "sg:tags":[
        "designer",
        "landscape"
    ],
    "wof:name":"True Nature Landscaping Inc",
    "wof:placetype":"venue"
},
  "geometry": {"coordinates":[-72.790537,40.804208],"type":"Point"}
}