{
  "type": "Feature",
  "properties": {
    "addr:full":"95 N Main St Wellsville NY 14895",
    "addr:housenumber":"95",
    "addr:postcode":"14895",
    "addr:street":"N Main St",
    "iso:country":"US",
    "sg:address":"95 N Main St",
    "sg:city":"Wellsville",
    "sg:classifiers":[
        {
            "category":"Professional",
            "subcategory":"Lawyer & Legal Services",
            "type":"Services"
        }
    ],
    "sg:phone":"+1 585 593 3170",
    "sg:postcode":"14895",
    "sg:province":"NY",
    "sg:tags":[
        "attorney"
    ],
    "wof:name":"Harris & Synakowski",
    "wof:placetype":"venue"
},
  "geometry": {"coordinates":[-77.94649800000001,42.120757],"type":"Point"}
}