{
  "type": "Feature",
  "properties": {
    "addr:full":"240 9th Avenue New York NY 10001",
    "addr:housenumber":"240",
    "addr:postcode":"10001",
    "addr:street":"9Th Avenue",
    "iso:country":"US",
    "sg:address":"240 9th Avenue",
    "sg:city":"New York",
    "sg:classifiers":[
        {
            "category":"Food & Beverages",
            "subcategory":"Cheese",
            "type":"Retail Goods"
        }
    ],
    "sg:phone":"+1 212 691 1512",
    "sg:postcode":"10001",
    "sg:province":"NY",
    "sg:tags":[
        "shop"
    ],
    "wof:name":"Cheese Unlimited",
    "wof:placetype":"venue"
},
  "geometry": {"coordinates":[-74.000404,40.74751],"type":"Point"}
}