{
  "type": "Feature",
  "properties": {
    "addr:full":"465 E Main St Middletown NY 10940",
    "addr:housenumber":"465",
    "addr:postcode":"10940",
    "addr:street":"E Main St",
    "iso:country":"US",
    "sg:address":"465 E Main St",
    "sg:city":"Middletown",
    "sg:classifiers":[
        {
            "category":"Health Services",
            "subcategory":"Doctor",
            "type":"Services"
        }
    ],
    "sg:phone":"+1 845 343 8212",
    "sg:postcode":"10940",
    "sg:province":"NY",
    "sg:tags":[
        "dentist"
    ],
    "wof:name":"Family Orthodontics",
    "wof:placetype":"venue"
},
  "geometry": {"coordinates":[-74.389657,41.444171],"type":"Point"}
}