{
  "type": "Feature",
  "properties": {
    "iso:country":"US",
    "sg:address":"30 Cabot Rd W",
    "sg:city":"Massapequa",
    "sg:classifiers":[
        {
            "category":"Professional",
            "subcategory":"Detective & Security Services",
            "type":"Services"
        }
    ],
    "sg:phone":"+1   ",
    "sg:postcode":"11758",
    "sg:province":"NY",
    "sg:tags":[
        "car"
    ],
    "wof:name":"Brothers Protection Group",
    "wof:placetype":"venue"
},
  "geometry": {"coordinates":[-73.46572399999999,40.655113],"type":"Point"}
}