{
  "type": "Feature",
  "properties": {
    "addr:full":"55 Broadway Amityville NY 11701",
    "addr:housenumber":"55",
    "addr:postcode":"11701",
    "addr:street":"Broadway",
    "iso:country":"US",
    "sg:address":"55 Broadway",
    "sg:city":"Amityville",
    "sg:classifiers":[
        {
            "category":"Building & Trades",
            "subcategory":"Pest Control",
            "type":"Services"
        }
    ],
    "sg:phone":"+1 631 225 5667",
    "sg:postcode":"11701",
    "sg:province":"NY",
    "sg:tags":[
        "industrial",
        "services-commercial"
    ],
    "wof:name":"Top Quality Exterminating",
    "wof:placetype":"venue"
},
  "geometry": {"coordinates":[-73.41616,40.673091],"type":"Point"}
}