{
  "type": "Feature",
  "properties": {
    "addr:full":"53 Stratford Ave Garden City NY 11530",
    "addr:housenumber":"53",
    "addr:postcode":"11530",
    "addr:street":"Stratford Ave",
    "iso:country":"US",
    "sg:address":"53 Stratford Ave",
    "sg:city":"Garden City",
    "sg:classifiers":[
        {
            "category":"Professional",
            "subcategory":"Computer Services",
            "type":"Services"
        }
    ],
    "sg:phone":"+1 516 484 5151",
    "sg:postcode":"11530",
    "sg:province":"NY",
    "sg:tags":[
        "related"
    ],
    "wof:name":"Transitional Computing",
    "wof:placetype":"venue"
},
  "geometry": {"coordinates":[-73.67183900000001,40.727312],"type":"Point"}
}