{
  "type": "Feature",
  "properties": {
    "addr:full":"303 Avenue M Brooklyn NY 11230",
    "addr:housenumber":"303",
    "addr:postcode":"11230",
    "addr:street":"Avenue M",
    "iso:country":"US",
    "sg:address":"303 Avenue M",
    "sg:city":"Brooklyn",
    "sg:classifiers":[
        {
            "category":"Education",
            "subcategory":"Kindergarten",
            "type":"Public Place"
        }
    ],
    "sg:phone":"+1 718 382 0800",
    "sg:postcode":"11230",
    "sg:province":"NY",
    "sg:tags":[
        "school",
        "driving"
    ],
    "wof:name":"Global Modifications",
    "wof:placetype":"venue"
},
  "geometry": {"coordinates":[-73.972246,40.616879],"type":"Point"}
}