{
  "type": "Feature",
  "properties": {
    "iso:country":"US",
    "sg:address":"703 S Main St",
    "sg:city":"Horseheads",
    "sg:classifiers":[
        {
            "category":"Professional",
            "subcategory":"Computer Services",
            "type":"Services"
        }
    ],
    "sg:phone":"+1 607 795 1968",
    "sg:postcode":"14845",
    "sg:province":"NY",
    "sg:tags":[
        "related"
    ],
    "wof:name":"Bit Bucket Computers",
    "wof:placetype":"venue"
},
  "geometry": {"coordinates":[-76.820553,42.167532],"type":"Point"}
}