{
  "type": "Feature",
  "properties": {
    "iso:country":"US",
    "name:eng_x_preferred":[
        "Huguenot"
    ],
    "wof:name":"Huguenot",
    "wof:placetype":"venue"
},
  "geometry": {"coordinates":[-74.191794,40.533674],"type":"Point"}
}