{
  "type": "Feature",
  "properties": {
    "addr:full":"680 New Salem Rd Voorheesville NY 12186",
    "addr:housenumber":"680",
    "addr:postcode":"12186",
    "addr:street":"New Salem Rd",
    "iso:country":"US",
    "sg:address":"680 New Salem Rd",
    "sg:city":"Voorheesville",
    "sg:classifiers":[
        {
            "category":"Health Services",
            "subcategory":"Doctor",
            "type":"Services"
        }
    ],
    "sg:phone":"+1 518 765 2151",
    "sg:postcode":"12186",
    "sg:province":"NY",
    "sg:tags":[
        "physician",
        "surgeon"
    ],
    "wof:name":"Michael Kieserman MD",
    "wof:placetype":"venue"
},
  "geometry": {"coordinates":[-73.970703,42.629437],"type":"Point"}
}