{
  "type": "Feature",
  "properties": {
    "iso:country":"US",
    "sg:address":"21 W Prospect Ave",
    "sg:city":"Mt Vernon",
    "sg:classifiers":[
        {
            "category":"Shopping",
            "subcategory":"Department Store",
            "type":"Retail Goods"
        }
    ],
    "sg:phone":"+1 914 699 7600",
    "sg:postcode":"10550",
    "sg:province":"NY",
    "sg:tags":[
        "shop"
    ],
    "wof:name":"Dollar Dreams",
    "wof:placetype":"venue"
},
  "geometry": {"coordinates":[-73.837597,40.912794],"type":"Point"}
}