{
  "type": "Feature",
  "properties": {
    "iso:country":"US",
    "sg:address":"294 Main St",
    "sg:city":"Huntington",
    "sg:classifiers":[
        {
            "category":"Farming",
            "subcategory":"Vineyard",
            "type":"Manufacturing & Wholesale Goods"
        }
    ],
    "sg:phone":"+1 631 549 6600",
    "sg:postcode":"11743",
    "sg:province":"NY",
    "wof:name":"Galluccio Estate Vineyards LLC",
    "wof:placetype":"venue"
},
  "geometry": {"coordinates":[-73.428291,40.870897],"type":"Point"}
}