{
  "type": "Feature",
  "properties": {
    "addr:full":"2082 Crotona Pkwy Bronx NY 10460",
    "addr:housenumber":"2082",
    "addr:postcode":"10460",
    "addr:street":"Crotona Pkwy",
    "iso:country":"US",
    "sg:address":"2082 Crotona Pkwy",
    "sg:city":"Bronx",
    "sg:classifiers":[
        {
            "category":"Professional",
            "type":"Services"
        }
    ],
    "sg:phone":"+1 718 561 5567",
    "sg:postcode":"10460",
    "sg:province":"NY",
    "sg:tags":[
        "establishment"
    ],
    "wof:name":"Mohegan Crotona Assoc",
    "wof:placetype":"venue"
},
  "geometry": {"coordinates":[-73.884393,40.845081],"type":"Point"}
}