{
  "type": "Feature",
  "properties": {
    "addr:full":"851 Ave of the Americas New York NY 10001",
    "addr:housenumber":"851",
    "addr:postcode":"10001",
    "addr:street":"Ave Of The Americas",
    "iso:country":"US",
    "sg:address":"851 Ave of the Americas",
    "sg:city":"New York",
    "sg:classifiers":[
        {
            "category":"Wholesale",
            "subcategory":"Non-durable Goods",
            "type":"Manufacturing & Wholesale Goods"
        }
    ],
    "sg:phone":"+1 212 683 8402",
    "sg:postcode":"10001",
    "sg:province":"NY",
    "wof:name":"US New Wilson Trading Inc",
    "wof:placetype":"venue"
},
  "geometry": {"coordinates":[-73.990067,40.746659],"type":"Point"}
}