{
  "type": "Feature",
  "properties": {
    "addr:full":"9804 159th Avenue Howard Beach NY 11414",
    "addr:housenumber":"9804",
    "addr:postcode":"11414",
    "addr:street":"159Th Avenue",
    "iso:country":"US",
    "sg:address":"9804 159th Avenue",
    "sg:city":"Howard Beach",
    "sg:classifiers":[
        {
            "category":"Health Services",
            "subcategory":"Dentist",
            "type":"Services"
        }
    ],
    "sg:phone":"+1 718 835 5100",
    "sg:postcode":"11414",
    "sg:province":"NY",
    "wof:name":"Lipsky Franklin H DDS",
    "wof:placetype":"venue"
},
  "geometry": {"coordinates":[-73.83494899999999,40.659768],"type":"Point"}
}