{
  "type": "Feature",
  "properties": {
    "iso:country":"US",
    "sg:address":"521 Ridge Rd E",
    "sg:city":"Rochester",
    "sg:classifiers":[
        {
            "category":"Manufacturing",
            "subcategory":"Printing",
            "type":"Manufacturing & Wholesale Goods"
        }
    ],
    "sg:phone":"+1 585 467 8140",
    "sg:postcode":"14621",
    "sg:province":"NY",
    "sg:tags":[
        "printer"
    ],
    "wof:name":"Jamar Printers Inc",
    "wof:placetype":"venue"
},
  "geometry": {"coordinates":[-77.600307,43.196],"type":"Point"}
}