{
  "type": "Feature",
  "properties": {
    "addr:full":"5002 8th Ave Brooklyn NY 11220",
    "addr:housenumber":"5002",
    "addr:postcode":"11220",
    "addr:street":"8Th Ave",
    "iso:country":"US",
    "sg:address":"5002 8th Ave",
    "sg:city":"Brooklyn",
    "sg:classifiers":[
        {
            "category":"Professional",
            "subcategory":"Management & Consulting",
            "type":"Services"
        },
        {
            "category":"Social Services",
            "type":"Services"
        }
    ],
    "sg:phone":"+1 718 437 0596",
    "sg:postcode":"11220",
    "sg:province":"NY",
    "sg:tags":[
        "association",
        "community",
        "center"
    ],
    "wof:name":"Brooklyn Chinese-American Assn",
    "wof:placetype":"venue"
},
  "geometry": {"coordinates":[-74.004345,40.640615],"type":"Point"}
}