{
  "type": "Feature",
  "properties": {
    "iso:country":"US",
    "sg:address":"1484 1st Avenue",
    "sg:city":"New York",
    "sg:classifiers":[
        {
            "category":"Health Services",
            "subcategory":"Doctor",
            "type":"Services"
        }
    ],
    "sg:phone":"+1 212 746 7001",
    "sg:postcode":"10021",
    "sg:province":"NY",
    "wof:name":"Fishman Lisa C MD",
    "wof:placetype":"venue"
},
  "geometry": {"coordinates":[-73.953332,40.771206],"type":"Point"}
}