{
  "type": "Feature",
  "properties": {
    "addr:full":"24 Adams St Kingston NY 12401",
    "addr:housenumber":"24",
    "addr:postcode":"12401",
    "addr:street":"Adams St",
    "iso:country":"US",
    "sg:address":"24 Adams St",
    "sg:city":"Kingston",
    "sg:classifiers":[
        {
            "category":"Travel",
            "subcategory":"Travel Agent",
            "type":"Entertainment"
        }
    ],
    "sg:phone":"+1 845 334 8511",
    "sg:postcode":"12401",
    "sg:province":"NY",
    "sg:tags":[
        "agency",
        "bureau"
    ],
    "wof:name":"Candy Bouquet",
    "wof:placetype":"venue"
},
  "geometry": {"coordinates":[-73.987713,41.921247],"type":"Point"}
}