{
  "type": "Feature",
  "properties": {
    "addr:full":"964 E 227th St Bronx NY 10466",
    "addr:housenumber":"964",
    "addr:postcode":"10466",
    "addr:street":"E 227Th St",
    "iso:country":"US",
    "sg:address":"964 E 227th St",
    "sg:city":"Bronx",
    "sg:classifiers":[
        {
            "category":"Shopping",
            "type":"Retail Goods"
        }
    ],
    "sg:phone":"+1 718 881 6566",
    "sg:postcode":"10466",
    "sg:province":"NY",
    "sg:tags":[
        "picture"
    ],
    "wof:name":"Huntpoint Pictures",
    "wof:placetype":"venue"
},
  "geometry": {"coordinates":[-73.852508,40.886999],"type":"Point"}
}