{
  "type": "Feature",
  "properties": {
    "addr:full":"35 W 31st St Fl 2 New York NY 10001",
    "addr:housenumber":"35;2",
    "addr:postcode":"10001",
    "addr:street":"W 31St St",
    "iso:country":"US",
    "sg:address":"35 W 31st St Fl 2",
    "sg:city":"New York",
    "sg:classifiers":[
        {
            "category":"Health Services",
            "subcategory":"Dentist",
            "type":"Services"
        }
    ],
    "sg:phone":"+1 212 594 9197",
    "sg:postcode":"10001",
    "sg:province":"NY",
    "wof:name":"Budget Dental Holding Inc",
    "wof:placetype":"venue"
},
  "geometry": {"coordinates":[-73.987801,40.747398],"type":"Point"}
}