{
  "type": "Feature",
  "properties": {
    "iso:country":"US",
    "sg:address":"106 W 80 St",
    "sg:city":"New York",
    "sg:classifiers":[
        {
            "category":"Manufacturing",
            "subcategory":"Printing",
            "type":"Manufacturing & Wholesale Goods"
        }
    ],
    "sg:phone":"+1 212 579 3925",
    "sg:postcode":"10024",
    "sg:province":"NY",
    "sg:tags":[
        "publisher"
    ],
    "wof:name":"KARZ Publishers",
    "wof:placetype":"venue"
},
  "geometry": {"coordinates":[-73.97773100000001,40.783692],"type":"Point"}
}