{
  "type": "Feature",
  "properties": {
    "addr:full":"57 Shinnecock Rd Hampton Bays NY 11946",
    "addr:housenumber":"57",
    "addr:postcode":"11946",
    "addr:street":"Shinnecock Rd",
    "iso:country":"US",
    "sg:address":"57 Shinnecock Rd",
    "sg:city":"Hampton Bays",
    "sg:classifiers":[
        {
            "category":"Building & Trades",
            "subcategory":"Construction",
            "type":"Services"
        }
    ],
    "sg:phone":"+1 631 728 0747",
    "sg:postcode":"11946",
    "sg:province":"NY",
    "sg:tags":[
        "contractor"
    ],
    "wof:name":"Big Paw General Contracting",
    "wof:placetype":"venue"
},
  "geometry": {"coordinates":[-72.504481,40.856538],"type":"Point"}
}