{
  "type": "Feature",
  "properties": {
    "addr:full":"339 Lexington Ave New York NY 10016",
    "addr:housenumber":"339",
    "addr:postcode":"10016",
    "addr:street":"Lexington Ave",
    "iso:country":"US",
    "sg:address":"339 Lexington Ave",
    "sg:city":"New York",
    "sg:classifiers":[
        {
            "category":"Restaurant",
            "type":"Food & Drink"
        }
    ],
    "sg:menulink":"http://www.allmenus.com/ny/new-york/7489-top-one/menu/",
    "sg:phone":"+1 212 867 4880",
    "sg:postcode":"10016",
    "sg:province":"NY",
    "sg:tags":[
        "asian",
        "chinese"
    ],
    "wof:name":"Top One",
    "wof:placetype":"venue"
},
  "geometry": {"coordinates":[-73.97732999999999,40.749694],"type":"Point"}
}