{
  "type": "Feature",
  "properties": {
    "addr:full":"232 Calyer Street Brooklyn NY 11222",
    "addr:housenumber":"232",
    "addr:postcode":"11222",
    "addr:street":"Calyer Street",
    "iso:country":"US",
    "sg:address":"232 Calyer Street",
    "sg:city":"Brooklyn",
    "sg:classifiers":[
        {
            "category":"Building & Trades",
            "subcategory":"Construction",
            "type":"Services"
        }
    ],
    "sg:phone":"+1 718 349 0350",
    "sg:postcode":"11222",
    "sg:province":"NY",
    "sg:tags":[
        "contractor"
    ],
    "wof:name":"Best Interiors Management Company",
    "wof:placetype":"venue"
},
  "geometry": {"coordinates":[-73.95020599999999,40.72903],"type":"Point"}
}