{
  "type": "Feature",
  "properties": {
    "iso:country":"US",
    "sg:address":"235 Garth Rd",
    "sg:city":"Scarsdale",
    "sg:classifiers":[
        {
            "category":"Health Services",
            "subcategory":"Doctor",
            "type":"Services"
        }
    ],
    "sg:phone":"+1 914 723 3725",
    "sg:postcode":"10583",
    "sg:province":"NY",
    "sg:tags":[
        "clinic"
    ],
    "wof:name":"Medical Services Group",
    "wof:placetype":"venue"
},
  "geometry": {"coordinates":[-73.812099,40.98251],"type":"Point"}
}