{
  "type": "Feature",
  "properties": {
    "iso:country":"US",
    "sg:address":"219 Fairport Rd",
    "sg:city":"East Rochester",
    "sg:classifiers":[
        {
            "category":"Health Services",
            "subcategory":"Clinic",
            "type":"Services"
        }
    ],
    "sg:phone":"+1 585 385 6681",
    "sg:postcode":"14445",
    "sg:province":"NY",
    "sg:tags":[
        "holistic",
        "practitioner"
    ],
    "wof:name":"Loving Touch Ctr School",
    "wof:placetype":"venue"
},
  "geometry": {"coordinates":[-77.500012,43.108198],"type":"Point"}
}