{
  "type": "Feature",
  "properties": {
    "addr:full":"21 Florgate Rd Farmingdale NY 11735",
    "addr:housenumber":"21",
    "addr:postcode":"11735",
    "addr:street":"Florgate Rd",
    "iso:country":"US",
    "sg:address":"21 Florgate Rd",
    "sg:city":"Farmingdale",
    "sg:classifiers":[
        {
            "category":"Professional",
            "subcategory":"Business Services",
            "type":"Services"
        }
    ],
    "sg:phone":"+1   ",
    "sg:postcode":"11735",
    "sg:province":"NY",
    "wof:name":"J Muti Consultants Inc",
    "wof:placetype":"venue"
},
  "geometry": {"coordinates":[-73.47222600000001,40.730627],"type":"Point"}
}