{
  "type": "Feature",
  "properties": {
    "addr:full":"24 Rock Shelter Rd Waccabuc NY 10597",
    "addr:housenumber":"24",
    "addr:postcode":"10597",
    "addr:street":"Rock Shelter Rd",
    "iso:country":"US",
    "sg:address":"24 Rock Shelter Rd",
    "sg:city":"Waccabuc",
    "sg:classifiers":[
        {
            "category":"Professional",
            "type":"Services"
        }
    ],
    "sg:phone":"+1 914 763 0965",
    "sg:postcode":"10597",
    "sg:province":"NY",
    "sg:tags":[
        "establishment"
    ],
    "wof:name":"John Ciardullo Assoc",
    "wof:placetype":"venue"
},
  "geometry": {"coordinates":[-73.60269,41.298565],"type":"Point"}
}