{
  "type": "Feature",
  "properties": {
    "iso:country":"US",
    "sg:address":"6965 Chestnut Ridge Rd",
    "sg:city":"Lockport",
    "sg:classifiers":[
        {
            "category":"Organizations",
            "subcategory":"Religious Organization",
            "type":"Services"
        }
    ],
    "sg:phone":"+1   ",
    "sg:postcode":"14094",
    "sg:province":"NY",
    "sg:tags":[
        "church"
    ],
    "wof:name":"Mt Olive Lutheran Church",
    "wof:placetype":"venue"
},
  "geometry": {"coordinates":[-78.65106900000001,43.181871],"type":"Point"}
}