{
  "type": "Feature",
  "properties": {
    "addr:full":"210 State Hwy 59 Nanuet NY 10954",
    "addr:housenumber":"210",
    "addr:postcode":"10954",
    "addr:street":"State Hwy 59",
    "iso:country":"US",
    "sg:address":"210 State Hwy 59",
    "sg:city":"Nanuet",
    "sg:classifiers":[
        {
            "category":"Home & Garden",
            "subcategory":"Carpets & Floor Coverings",
            "type":"Retail Goods"
        }
    ],
    "sg:phone":"+1 845 623 7267",
    "sg:postcode":"10954",
    "sg:province":"NY",
    "wof:name":"Sam's Floor Covering",
    "wof:placetype":"venue"
},
  "geometry": {"coordinates":[-74.00239000000001,41.093796],"type":"Point"}
}