{
  "type": "Feature",
  "properties": {
    "addr:full":"186 American Blvd Brentwood NY 11717",
    "addr:housenumber":"186",
    "addr:postcode":"11717",
    "addr:street":"American Blvd",
    "iso:country":"US",
    "sg:address":"186 American Blvd",
    "sg:city":"Brentwood",
    "sg:classifiers":[
        {
            "category":"Freight",
            "type":"Transportation"
        }
    ],
    "sg:phone":"+1   ",
    "sg:postcode":"11717",
    "sg:province":"NY",
    "sg:tags":[
        "company",
        "moving"
    ],
    "wof:name":"A & S and Company",
    "wof:placetype":"venue"
},
  "geometry": {"coordinates":[-73.235328,40.769196],"type":"Point"}
}