{
  "type": "Feature",
  "properties": {
    "addr:full":"617 Route 9W Glenmont NY 12077",
    "addr:housenumber":"617",
    "addr:postcode":"12077",
    "addr:street":"Route 9W",
    "iso:country":"US",
    "sg:address":"617 Route 9W",
    "sg:city":"Glenmont",
    "sg:classifiers":[
        {
            "category":"Autos & Motor Vehicles",
            "subcategory":"Automobile Sales",
            "type":"Retail Goods"
        },
        {
            "category":"Retail",
            "subcategory":"Auto Repair",
            "type":"Services"
        }
    ],
    "sg:phone":"+1 518 463 3141",
    "sg:postcode":"12077",
    "sg:province":"NY",
    "sg:tags":[
        "body",
        "shop",
        "car"
    ],
    "sg:website":"capitalcitiesbmw.com",
    "wof:name":"Capital Cities Imported Cars",
    "wof:placetype":"venue"
},
  "geometry": {"coordinates":[-73.796997,42.5882],"type":"Point"}
}