{
  "type": "Feature",
  "properties": {
    "addr:full":"2322 Broad St Frankfort NY 13340",
    "addr:housenumber":"2322",
    "addr:postcode":"13340",
    "addr:street":"Broad St",
    "iso:country":"US",
    "sg:address":"2322 Broad St",
    "sg:city":"Frankfort",
    "sg:classifiers":[
        {
            "category":"Wholesale",
            "subcategory":"Machinery & Supplies",
            "type":"Manufacturing & Wholesale Goods"
        }
    ],
    "sg:phone":"+1 315 732 4138",
    "sg:postcode":"13340",
    "sg:province":"NY",
    "sg:tags":[
        "crane",
        "derrick"
    ],
    "wof:name":"Rig All Inc",
    "wof:placetype":"venue"
},
  "geometry": {"coordinates":[-75.167182,43.088368],"type":"Point"}
}