{
  "type": "Feature",
  "properties": {
    "addr:full":"48 Skillman Ave Sunnyside NY 11104",
    "addr:housenumber":"48",
    "addr:postcode":"11104",
    "addr:street":"Skillman Ave",
    "iso:country":"US",
    "sg:address":"48 Skillman Ave",
    "sg:city":"Sunnyside",
    "sg:classifiers":[
        {
            "category":"Shopping",
            "subcategory":"Pharmacy",
            "type":"Retail Goods"
        }
    ],
    "sg:phone":"+1   ",
    "sg:postcode":"11104",
    "sg:province":"NY",
    "wof:name":"Fmrg Pharmacy Inc",
    "wof:placetype":"venue"
},
  "geometry": {"coordinates":[-73.923793,40.74717],"type":"Point"}
}