{
  "type": "Feature",
  "properties": {
    "addr:full":"4306 E Genesee St De Witt NY 13214",
    "addr:housenumber":"4306",
    "addr:postcode":"13214",
    "addr:street":"E Genesee St",
    "iso:country":"US",
    "sg:address":"4306 E Genesee St",
    "sg:city":"De Witt",
    "sg:classifiers":[
        {
            "category":"Real Estate",
            "subcategory":"Real Estate Agent",
            "type":"Services"
        }
    ],
    "sg:phone":"+1 315 446 2444",
    "sg:postcode":"13214",
    "sg:province":"NY",
    "wof:name":"De WITT Real Estate Inc",
    "wof:placetype":"venue"
},
  "geometry": {"coordinates":[-76.068254,43.035283],"type":"Point"}
}