{
  "type": "Feature",
  "properties": {
    "addr:full":"27 Forest Ave Locust Valley NY 11560",
    "addr:housenumber":"27",
    "addr:postcode":"11560",
    "addr:street":"Forest Ave",
    "iso:country":"US",
    "sg:address":"27 Forest Ave",
    "sg:city":"Locust Valley",
    "sg:classifiers":[
        {
            "category":"Shopping",
            "subcategory":"Pharmacy",
            "type":"Retail Goods"
        }
    ],
    "sg:phone":"+1 516 676 3101",
    "sg:postcode":"11560",
    "sg:province":"NY",
    "wof:name":"Savon America Inc",
    "wof:placetype":"venue"
},
  "geometry": {"coordinates":[-73.597993,40.875651],"type":"Point"}
}