{
  "type": "Feature",
  "properties": {
    "iso:country":"US",
    "sg:address":"2 Erie Blvd",
    "sg:city":"Canajoharie",
    "sg:classifiers":[
        {
            "category":"Education",
            "subcategory":"Library",
            "type":"Public Place"
        }
    ],
    "sg:phone":"+1 518 673 2314",
    "sg:postcode":"13317",
    "sg:province":"NY",
    "sg:website":"www.clag.org",
    "wof:name":"Canajoharie Library & Art Glry",
    "wof:placetype":"venue"
},
  "geometry": {"coordinates":[-74.57167099999999,42.906854],"type":"Point"}
}