{
  "type": "Feature",
  "properties": {
    "addr:full":"1556 Flatbush Ave Brooklyn NY 11210",
    "addr:housenumber":"1556",
    "addr:postcode":"11210",
    "addr:street":"Flatbush Ave",
    "iso:country":"US",
    "sg:address":"1556 Flatbush Ave",
    "sg:city":"Brooklyn",
    "sg:classifiers":[
        {
            "category":"Personal",
            "subcategory":"Massage",
            "type":"Services"
        },
        {
            "category":"Health Services",
            "subcategory":"Clinic",
            "type":"Services"
        },
        {
            "category":"Health Services",
            "subcategory":"Health Practitioner",
            "type":"Services"
        }
    ],
    "sg:phone":"+1 718 421 1390",
    "sg:postcode":"11210",
    "sg:province":"NY",
    "sg:tags":[
        "therapist",
        "therapy",
        "physical"
    ],
    "wof:name":"Mt Massage Parlor Spa Wellness Center",
    "wof:placetype":"venue"
},
  "geometry": {"coordinates":[-73.947821,40.632957],"type":"Point"}
}