{
  "type": "Feature",
  "properties": {
    "addr:full":"2904 Stillwell Ave Brooklyn NY 11226",
    "addr:housenumber":"2904",
    "addr:postcode":"11226",
    "addr:street":"Stillwell Ave",
    "iso:country":"US",
    "sg:address":"2904 Stillwell Ave",
    "sg:city":"Brooklyn",
    "sg:classifiers":[
        {
            "category":"Fast Food",
            "type":"Food & Drink"
        }
    ],
    "sg:postcode":"11226",
    "sg:province":"NY",
    "sg:website":"www.kennedyfriedchicken.com/",
    "wof:name":"Kennedy Fried Chicken",
    "wof:placetype":"venue"
},
  "geometry": {"coordinates":[-73.981532,40.576899],"type":"Point"}
}