{
  "type": "Feature",
  "properties": {
    "addr:full":"518 Wyckoff Rd Ithaca NY 14850",
    "addr:housenumber":"518",
    "addr:postcode":"14850",
    "addr:street":"Wyckoff Rd",
    "iso:country":"US",
    "sg:address":"518 Wyckoff Rd",
    "sg:city":"Ithaca",
    "sg:classifiers":[
        {
            "category":"Health Services",
            "subcategory":"Health Practitioner",
            "type":"Services"
        }
    ],
    "sg:phone":"+1 607 257 5008",
    "sg:postcode":"14850",
    "sg:province":"NY",
    "sg:tags":[
        "psychologist"
    ],
    "wof:name":"Dorothy Shaffer",
    "wof:placetype":"venue"
},
  "geometry": {"coordinates":[-76.49046199999999,42.45849],"type":"Point"}
}