{
  "type": "Feature",
  "properties": {
    "addr:full":"7701 3rd Ave Brooklyn NY 11209",
    "addr:housenumber":"7701",
    "addr:postcode":"11209",
    "addr:street":"3Rd Ave",
    "iso:country":"US",
    "sg:address":"7701 3rd Ave",
    "sg:city":"Brooklyn",
    "sg:classifiers":[
        {
            "category":"Local Transit",
            "type":"Transportation"
        }
    ],
    "sg:phone":"+1 718 745 7444",
    "sg:postcode":"11209",
    "sg:province":"NY",
    "sg:tags":[
        "public"
    ],
    "wof:name":"Carnival Tours",
    "wof:placetype":"venue"
},
  "geometry": {"coordinates":[-74.028361,40.63001],"type":"Point"}
}