{
  "type": "Feature",
  "properties": {
    "addr:full":"146 W 29th St Ste 6RE2 Manhattan NY 10001",
    "addr:housenumber":"146",
    "addr:postcode":"10001",
    "addr:street":"W 29Th St Ste 6Re2",
    "iso:country":"US",
    "sg:address":"146 W 29th St Ste 6RE2",
    "sg:city":"Manhattan",
    "sg:classifiers":[
        {
            "category":"Communications",
            "subcategory":"Newspaper",
            "type":"Services"
        }
    ],
    "sg:phone":"+1 347 443 2724",
    "sg:postcode":"10001",
    "sg:province":"NY",
    "sg:tags":[
        "print",
        "medium"
    ],
    "sg:website":"www.vipercolorgraphics.com",
    "wof:name":"Viper Color",
    "wof:placetype":"venue"
},
  "geometry": {"coordinates":[-73.99216,40.747286],"type":"Point"}
}