{
  "type": "Feature",
  "properties": {
    "iso:country":"US",
    "sg:address":"138 Roundhouse Rd",
    "sg:city":"Oneonta",
    "sg:classifiers":[
        {
            "category":"Manufacturing",
            "subcategory":"Metals",
            "type":"Manufacturing & Wholesale Goods"
        }
    ],
    "sg:phone":"+1 607 432 4518",
    "sg:postcode":"13820",
    "sg:province":"NY",
    "sg:tags":[
        "casting"
    ],
    "wof:name":"G C Castings",
    "wof:placetype":"venue"
},
  "geometry": {"coordinates":[-75.081282,42.449917],"type":"Point"}
}