{
  "type": "Feature",
  "properties": {
    "addr:full":"4476 Broadway New York NY 10040",
    "addr:housenumber":"4476",
    "addr:postcode":"10040",
    "addr:street":"Broadway",
    "iso:country":"US",
    "sg:address":"4476 Broadway",
    "sg:city":"New York",
    "sg:classifiers":[
        {
            "category":"Food & Beverages",
            "subcategory":"Meat & Fish",
            "type":"Retail Goods"
        }
    ],
    "sg:phone":"+1 212 304 4500",
    "sg:postcode":"10040",
    "sg:province":"NY",
    "wof:name":"Broadway Hala Meats LLC",
    "wof:placetype":"venue"
},
  "geometry": {"coordinates":[-73.932196,40.857251],"type":"Point"}
}