{
  "type": "Feature",
  "properties": {
    "iso:country":"US",
    "sg:address":"720 State Hwy 17M",
    "sg:city":"Middletown",
    "sg:classifiers":[
        {
            "category":"Social Services",
            "type":"Services"
        }
    ],
    "sg:phone":"+1 845 343 8100",
    "sg:postcode":"10940",
    "sg:province":"NY",
    "sg:tags":[
        "organization",
        "welfare"
    ],
    "wof:name":"Family Empowerment Council",
    "wof:placetype":"venue"
},
  "geometry": {"coordinates":[-74.41635599999999,41.482339],"type":"Point"}
}