{
  "type": "Feature",
  "properties": {
    "addr:full":"165 Christopher St New York NY 10014",
    "addr:housenumber":"165",
    "addr:postcode":"10014",
    "addr:street":"Christopher St",
    "iso:country":"US",
    "sg:address":"165 Christopher St",
    "sg:city":"New York",
    "sg:classifiers":[
        {
            "category":"Professional",
            "subcategory":"Computer Services",
            "type":"Services"
        }
    ],
    "sg:phone":"+1 212 727 9502",
    "sg:postcode":"10014",
    "sg:province":"NY",
    "sg:tags":[
        "website",
        "design"
    ],
    "wof:name":"Hoon International Inc",
    "wof:placetype":"venue"
},
  "geometry": {"coordinates":[-74.00986899999999,40.73245],"type":"Point"}
}