{
  "type": "Feature",
  "properties": {
    "iso:country":"US",
    "sg:address":"1075 Carll Dr",
    "sg:city":"Bay Shore",
    "sg:classifiers":[
        {
            "category":"Building & Trades",
            "subcategory":"Construction",
            "type":"Services"
        }
    ],
    "sg:phone":"+1 631 665 4317",
    "sg:postcode":"11706",
    "sg:province":"NY",
    "sg:tags":[
        "contractor"
    ],
    "wof:name":"Suds Pressure Washing",
    "wof:placetype":"venue"
},
  "geometry": {"coordinates":[-73.281677,40.723022],"type":"Point"}
}