{
  "type": "Feature",
  "properties": {
    "iso:country":"US",
    "sg:address":"1650 Bath Ave",
    "sg:city":"Brooklyn",
    "sg:classifiers":[
        {
            "category":"Food & Beverages",
            "subcategory":"Groceries & Convenience Stores",
            "type":"Retail Goods"
        }
    ],
    "sg:phone":"+1 718 837 6137",
    "sg:postcode":"11214",
    "sg:province":"NY",
    "wof:name":"Friends Food Market Inc",
    "wof:placetype":"venue"
},
  "geometry": {"coordinates":[-74.00900300000001,40.605499],"type":"Point"}
}