{
  "type": "Feature",
  "properties": {
    "iso:country":"US",
    "sg:address":"11545 174th St",
    "sg:city":"Jamaica",
    "sg:classifiers":[
        {
            "category":"Science Facility",
            "type":"Public Place"
        }
    ],
    "sg:phone":"+1 718 739 1734",
    "sg:postcode":"11434",
    "sg:province":"NY",
    "sg:tags":[
        "development",
        "laboratories-research"
    ],
    "wof:name":"A D & Sons Research & Development",
    "wof:placetype":"venue"
},
  "geometry": {"coordinates":[-73.77529,40.69039],"type":"Point"}
}