{
  "type": "Feature",
  "properties": {
    "iso:country":"US",
    "sg:address":"2612 Genesee St",
    "sg:city":"Utica",
    "sg:classifiers":[
        {
            "category":"Personal",
            "subcategory":"Beauty Salon",
            "type":"Services"
        }
    ],
    "sg:phone":"+1   ",
    "sg:postcode":"13502",
    "sg:province":"NY",
    "sg:tags":[
        "shop"
    ],
    "wof:name":"Nails By Debbie",
    "wof:placetype":"venue"
},
  "geometry": {"coordinates":[-75.277292,43.078791],"type":"Point"}
}