{
  "type": "Feature",
  "properties": {
    "addr:full":"6318 Shimer Rd Lockport NY 14094",
    "addr:housenumber":"6318",
    "addr:postcode":"14094",
    "addr:street":"Shimer Rd",
    "iso:country":"US",
    "sg:address":"6318 Shimer Rd",
    "sg:city":"Lockport",
    "sg:classifiers":[
        {
            "category":"Building & Trades",
            "subcategory":"Construction",
            "type":"Services"
        }
    ],
    "sg:phone":"+1 716 433 3719",
    "sg:postcode":"14094",
    "sg:province":"NY",
    "sg:tags":[
        "contractor"
    ],
    "wof:name":"Kitchen Concepts",
    "wof:placetype":"venue"
},
  "geometry": {"coordinates":[-78.689818,43.145885],"type":"Point"}
}