{
  "type": "Feature",
  "properties": {
    "iso:country":"US",
    "sg:address":"12 S Lake Ave",
    "sg:city":"Bergen",
    "sg:classifiers":[
        {
            "category":"Organizations",
            "subcategory":"Community Association",
            "type":"Services"
        }
    ],
    "sg:phone":"+1 585 494 1408",
    "sg:postcode":"14416",
    "sg:province":"NY",
    "sg:tags":[
        "fraternal"
    ],
    "wof:name":"Masonic Lodge",
    "wof:placetype":"venue"
},
  "geometry": {"coordinates":[-77.943296,43.082809],"type":"Point"}
}