{
  "type": "Feature",
  "properties": {
    "iso:country":"US",
    "sg:address":"15 25th St",
    "sg:city":"Watervliet",
    "sg:classifiers":[
        {
            "category":"Insurance",
            "subcategory":"Insurance Agent",
            "type":"Services"
        }
    ],
    "sg:phone":"+1 518 273 9501",
    "sg:postcode":"12189",
    "sg:province":"NY",
    "sg:website":"www.themooreagency.com",
    "wof:name":"Moore Insurance Agency Inc",
    "wof:placetype":"venue"
},
  "geometry": {"coordinates":[-73.69887,42.735358],"type":"Point"}
}