{
  "type": "Feature",
  "properties": {
    "addr:full":"265 Canal St Ste 309 Chinatown NY 10013",
    "addr:housenumber":"265",
    "addr:postcode":"10013",
    "addr:street":"Canal St Ste 309",
    "iso:country":"US",
    "sg:address":"265 Canal St Ste 309",
    "sg:city":"Chinatown",
    "sg:classifiers":[
        {
            "category":"Building & Trades",
            "subcategory":"Construction",
            "type":"Services"
        }
    ],
    "sg:phone":"+1 212 431 1166",
    "sg:postcode":"10013",
    "sg:province":"NY",
    "sg:tags":[
        "contractor"
    ],
    "wof:name":"United Contractor Incorporated",
    "wof:placetype":"venue"
},
  "geometry": {"coordinates":[-74.01439999999999,40.718966],"type":"Point"}
}