{
  "type": "Feature",
  "properties": {
    "addr:full":"8396 State St Gasport NY 14067",
    "addr:housenumber":"8396",
    "addr:postcode":"14067",
    "addr:street":"State St",
    "iso:country":"US",
    "sg:address":"8396 State St",
    "sg:city":"Gasport",
    "sg:classifiers":[
        {
            "category":"Restaurant",
            "type":"Food & Drink"
        }
    ],
    "sg:phone":"+1   ",
    "sg:postcode":"14067",
    "sg:province":"NY",
    "sg:tags":[
        "eating"
    ],
    "wof:name":"Marias Pizzaria",
    "wof:placetype":"venue"
},
  "geometry": {"coordinates":[-78.574476,43.199289],"type":"Point"}
}