{
  "type": "Feature",
  "properties": {
    "addr:full":"6 Deering Ln East Rockaway NY 11518",
    "addr:housenumber":"6",
    "addr:postcode":"11518",
    "addr:street":"Deering Ln East",
    "iso:country":"US",
    "sg:address":"6 Deering Ln",
    "sg:city":"East Rockaway",
    "sg:classifiers":[
        {
            "category":"Professional",
            "subcategory":"Computer Services",
            "type":"Services"
        }
    ],
    "sg:phone":"+1 516 374 7952",
    "sg:postcode":"11518",
    "sg:province":"NY",
    "sg:tags":[
        "design",
        "system"
    ],
    "wof:name":"Advantage Technologies Inc",
    "wof:placetype":"venue"
},
  "geometry": {"coordinates":[-73.678284,40.638868],"type":"Point"}
}