{
  "type": "Feature",
  "properties": {
    "addr:full":"115 N Main St Minoa NY 13116",
    "addr:housenumber":"115",
    "addr:postcode":"13116",
    "addr:street":"N Main St",
    "iso:country":"US",
    "sg:address":"115 N Main St",
    "sg:city":"Minoa",
    "sg:classifiers":[
        {
            "category":"Government",
            "subcategory":"Post Office",
            "type":"Public Place"
        }
    ],
    "sg:phone":"+1 315 656 8845",
    "sg:postcode":"13116",
    "sg:province":"NY",
    "wof:name":"US Post Office",
    "wof:placetype":"venue"
},
  "geometry": {"coordinates":[-76.001165,43.075914],"type":"Point"}
}