{
  "type": "Feature",
  "properties": {
    "addr:full":"4701 Queens Blvd Sunnyside NY 11104",
    "addr:housenumber":"4701",
    "addr:postcode":"11104",
    "addr:street":"Queens Blvd",
    "iso:country":"US",
    "sg:address":"4701 Queens Blvd",
    "sg:city":"Sunnyside",
    "sg:classifiers":[
        {
            "category":"Health Services",
            "subcategory":"Dentist",
            "type":"Services"
        }
    ],
    "sg:phone":"+1 718 706 1717",
    "sg:postcode":"11104",
    "sg:province":"NY",
    "wof:name":"Sunnyside Dental",
    "wof:placetype":"venue"
},
  "geometry": {"coordinates":[-73.917395,40.743425],"type":"Point"}
}