{
  "type": "Feature",
  "properties": {
    "iso:country":"US",
    "sg:address":"116 E Main St",
    "sg:city":"Afton",
    "sg:classifiers":[
        {
            "category":"Organizations",
            "subcategory":"Professional Association",
            "type":"Services"
        }
    ],
    "sg:phone":"+1 607 639 1110",
    "sg:postcode":"13730",
    "sg:province":"NY",
    "wof:name":"Afton Historical Society",
    "wof:placetype":"venue"
},
  "geometry": {"coordinates":[-75.51779399999999,42.226529],"type":"Point"}
}