{
  "type": "Feature",
  "properties": {
    "addr:full":"146 Lombard St Buffalo NY 14212",
    "addr:housenumber":"146",
    "addr:postcode":"14212",
    "addr:street":"Lombard St",
    "iso:country":"US",
    "sg:address":"146 Lombard St",
    "sg:city":"Buffalo",
    "sg:classifiers":[
        {
            "category":"Social Services",
            "subcategory":"Child Care",
            "type":"Services"
        }
    ],
    "sg:phone":"+1 716 893 7100",
    "sg:postcode":"14212",
    "sg:province":"NY",
    "sg:tags":[
        "day"
    ],
    "wof:name":"Kiddy Cat Daycare",
    "wof:placetype":"venue"
},
  "geometry": {"coordinates":[-78.83726,42.890105],"type":"Point"}
}