{
  "type": "Feature",
  "properties": {
    "iso:country":"US",
    "sg:address":"1 Nassau Ave",
    "sg:city":"Brooklyn",
    "sg:classifiers":[
        {
            "category":"Manufacturing",
            "subcategory":"Retail Goods",
            "type":"Manufacturing & Wholesale Goods"
        }
    ],
    "sg:phone":"+1 718 387 4530",
    "sg:postcode":"11222",
    "sg:province":"NY",
    "sg:tags":[
        "assembly",
        "fabricating"
    ],
    "wof:name":"Associated Fabrication",
    "wof:placetype":"venue"
},
  "geometry": {"coordinates":[-73.954183,40.722636],"type":"Point"}
}