{
  "type": "Feature",
  "properties": {
    "iso:country":"US",
    "sg:address":"611 Jackson Ave",
    "sg:city":"Bronx",
    "sg:classifiers":[
        {
            "category":"Professional",
            "subcategory":"Detective & Security Services",
            "type":"Services"
        }
    ],
    "sg:phone":"+1   ",
    "sg:postcode":"10455",
    "sg:province":"NY",
    "sg:tags":[
        "guard",
        "investigation"
    ],
    "wof:name":"John C Mandel Security Bureau",
    "wof:placetype":"venue"
},
  "geometry": {"coordinates":[-73.908503,40.815024],"type":"Point"}
}