{
  "type": "Feature",
  "properties": {
    "addr:full":"391 Kern Rd Cowlesville NY 14037",
    "addr:housenumber":"391",
    "addr:postcode":"14037",
    "addr:street":"Kern Rd",
    "iso:country":"US",
    "sg:address":"391 Kern Rd",
    "sg:city":"Cowlesville",
    "sg:classifiers":[
        {
            "category":"Wholesale",
            "subcategory":"Farm Supplies",
            "type":"Manufacturing & Wholesale Goods"
        }
    ],
    "sg:phone":"+1 585 591 0970",
    "sg:postcode":"14037",
    "sg:province":"NY",
    "wof:name":"Western Counties Service & Supply",
    "wof:placetype":"venue"
},
  "geometry": {"coordinates":[-78.45919600000001,42.823766],"type":"Point"}
}