{
  "type": "Feature",
  "properties": {
    "iso:country":"US",
    "sg:address":"751 Franklin Ave",
    "sg:city":"Franklin Square",
    "sg:classifiers":[
        {
            "category":"Arts & Performance",
            "subcategory":"Arts Center",
            "type":"Entertainment"
        }
    ],
    "sg:phone":"+1 516 872 2552",
    "sg:postcode":"11010",
    "sg:province":"NY",
    "sg:tags":[
        "performing"
    ],
    "wof:name":"Miss Edie's Dancin Feet",
    "wof:placetype":"venue"
},
  "geometry": {"coordinates":[-73.685997,40.688],"type":"Point"}
}