{
  "type": "Feature",
  "properties": {
    "addr:full":"5614 New Utrecht Ave Brooklyn NY 11219",
    "addr:housenumber":"5614",
    "addr:postcode":"11219",
    "addr:street":"New Utrecht Ave",
    "iso:country":"US",
    "sg:address":"5614 New Utrecht Ave",
    "sg:city":"Brooklyn",
    "sg:classifiers":[
        {
            "category":"Shopping",
            "subcategory":"Computers & Home Electronics",
            "type":"Retail Goods"
        }
    ],
    "sg:phone":"+1 718 686 7445",
    "sg:postcode":"11219",
    "sg:province":"NY",
    "sg:tags":[
        "parts"
    ],
    "wof:name":"Comtech",
    "wof:placetype":"venue"
},
  "geometry": {"coordinates":[-73.995965,40.630049],"type":"Point"}
}