{
  "type": "Feature",
  "properties": {
    "addr:full":"73 Summit Rd Port Washington NY 11050",
    "addr:housenumber":"73",
    "addr:postcode":"11050",
    "addr:street":"Summit Rd",
    "iso:country":"US",
    "sg:address":"73 Summit Rd",
    "sg:city":"Port Washington",
    "sg:classifiers":[
        {
            "category":"Shopping",
            "subcategory":"Computers & Home Electronics",
            "type":"Retail Goods"
        }
    ],
    "sg:phone":"+1 516 767 1272",
    "sg:postcode":"11050",
    "sg:province":"NY",
    "sg:tags":[
        "equipment",
        "dealer"
    ],
    "wof:name":"JLP Computer Enterprises",
    "wof:placetype":"venue"
},
  "geometry": {"coordinates":[-73.673745,40.836863],"type":"Point"}
}