{
  "type": "Feature",
  "properties": {
    "addr:full":"1166 Zerega Avenue Bronx NY 10462",
    "addr:housenumber":"1166",
    "addr:postcode":"10462",
    "addr:street":"Zerega Avenue",
    "iso:country":"US",
    "sg:address":"1166 Zerega Avenue",
    "sg:city":"Bronx",
    "sg:classifiers":[
        {
            "category":"Sports & Exercise",
            "subcategory":"Sports Center",
            "type":"Entertainment"
        }
    ],
    "sg:phone":"+1 718 824 5555",
    "sg:postcode":"10462",
    "sg:province":"NY",
    "sg:tags":[
        "amateur",
        "team"
    ],
    "wof:name":"Castle Hill Little League",
    "wof:placetype":"venue"
},
  "geometry": {"coordinates":[-73.844752,40.832034],"type":"Point"}
}