{
  "type": "Feature",
  "properties": {
    "addr:full":"245 Echo Ave Sound Beach NY 11789",
    "addr:housenumber":"245",
    "addr:postcode":"11789",
    "addr:street":"Echo Ave",
    "iso:country":"US",
    "sg:address":"245 Echo Ave",
    "sg:city":"Sound Beach",
    "sg:classifiers":[
        {
            "category":"Wholesale",
            "subcategory":"Meat",
            "type":"Manufacturing & Wholesale Goods"
        }
    ],
    "sg:phone":"+1 631 821 3386",
    "sg:postcode":"11789",
    "sg:province":"NY",
    "sg:tags":[
        "butchering"
    ],
    "wof:name":"Antonio's Prime Butcher Inc",
    "wof:placetype":"venue"
},
  "geometry": {"coordinates":[-72.98402,40.951964],"type":"Point"}
}