{
  "type": "Feature",
  "properties": {
    "addr:full":"281 Dodge Rd Getzville NY 14068",
    "addr:housenumber":"281",
    "addr:postcode":"14068",
    "addr:street":"Dodge Rd",
    "iso:country":"US",
    "sg:address":"281 Dodge Rd",
    "sg:city":"Getzville",
    "sg:classifiers":[
        {
            "category":"Retail",
            "subcategory":"Funeral Services",
            "type":"Services"
        }
    ],
    "sg:phone":"+1 716 636 4174",
    "sg:postcode":"14068",
    "sg:province":"NY",
    "sg:tags":[
        "director"
    ],
    "wof:name":"Amherst Memorial Chapel Inc",
    "wof:placetype":"venue"
},
  "geometry": {"coordinates":[-78.783727,43.023926],"type":"Point"}
}