{
  "type": "Feature",
  "properties": {
    "addr:full":"1633 Sheepshead Bay Rd Brooklyn NY 11235",
    "addr:housenumber":"1633",
    "addr:postcode":"11235",
    "addr:street":"Sheepshead Bay Rd",
    "iso:country":"US",
    "sg:address":"1633 Sheepshead Bay Rd",
    "sg:city":"Brooklyn",
    "sg:classifiers":[
        {
            "category":"Banks & Credit Unions",
            "subcategory":"Bank",
            "type":"Services"
        }
    ],
    "sg:phone":"+1 718 743 1416",
    "sg:postcode":"11235",
    "sg:province":"NY",
    "wof:name":"Valley National Bank",
    "wof:placetype":"venue"
},
  "geometry": {"coordinates":[-73.952426,40.58692],"type":"Point"}
}