{
  "type": "Feature",
  "properties": {
    "iso:country":"US",
    "sg:address":"4305 Fassett Ln",
    "sg:city":"Wellsville",
    "sg:classifiers":[
        {
            "category":"Health Services",
            "subcategory":"Podiatrist",
            "type":"Services"
        }
    ],
    "sg:phone":"+1   ",
    "sg:postcode":"14895",
    "sg:province":"NY",
    "wof:name":"Robert L Gilfert",
    "wof:placetype":"venue"
},
  "geometry": {"coordinates":[-77.974003,42.124619],"type":"Point"}
}