{
  "type": "Feature",
  "properties": {
    "iso:country":"US",
    "sg:address":"120 Clinton Ave",
    "sg:city":"Mineola",
    "sg:classifiers":[
        {
            "category":"Real Estate",
            "subcategory":"Real Estate Operator",
            "type":"Services"
        }
    ],
    "sg:phone":"+1 516 741 9005",
    "sg:postcode":"11501",
    "sg:province":"NY",
    "sg:tags":[
        "building",
        "apartment"
    ],
    "wof:name":"Embassy Apts LLC",
    "wof:placetype":"venue"
},
  "geometry": {"coordinates":[-73.638188,40.745845],"type":"Point"}
}