{
  "type": "Feature",
  "properties": {
    "addr:full":"126 E Oneida St Oswego NY 13126",
    "addr:housenumber":"126",
    "addr:postcode":"13126",
    "addr:street":"E Oneida St",
    "iso:country":"US",
    "sg:address":"126 E Oneida St",
    "sg:city":"Oswego",
    "sg:classifiers":[
        {
            "category":"Food & Beverages",
            "subcategory":"Groceries & Convenience Stores",
            "type":"Retail Goods"
        }
    ],
    "sg:phone":"+1 315 343 1220",
    "sg:postcode":"13126",
    "sg:province":"NY",
    "wof:name":"Rise & Shine Oswego",
    "wof:placetype":"venue"
},
  "geometry": {"coordinates":[-76.495615,43.459622],"type":"Point"}
}