{
  "type": "Feature",
  "properties": {
    "addr:full":"1400 3rd Ave New York NY 10021",
    "addr:housenumber":"1400",
    "addr:postcode":"10021",
    "addr:street":"3Rd Ave",
    "iso:country":"US",
    "sg:address":"1400 3rd Ave",
    "sg:city":"New York",
    "sg:classifiers":[
        {
            "category":"Personal",
            "subcategory":"Day Spa",
            "type":"Services"
        },
        {
            "category":"Wholesale",
            "subcategory":"Home Furnishings",
            "type":"Manufacturing & Wholesale Goods"
        }
    ],
    "sg:phone":"+1 212 794 3300",
    "sg:postcode":"10021",
    "sg:province":"NY",
    "sg:tags":[
        "blind",
        "shade"
    ],
    "wof:name":"La Marqueza",
    "wof:placetype":"venue"
},
  "geometry": {"coordinates":[-73.95700100000001,40.774601],"type":"Point"}
}