{
  "type": "Feature",
  "properties": {
    "iso:country":"US",
    "sg:address":"22 Peck Slip",
    "sg:city":"New York",
    "sg:classifiers":[
        {
            "category":"Restaurant",
            "type":"Food & Drink"
        }
    ],
    "sg:phone":"+1 212 791 1818",
    "sg:postcode":"10038",
    "sg:province":"NY",
    "sg:tags":[
        "bar"
    ],
    "sg:website":"meadesbar.com/",
    "wof:name":"Meade's Restaurant",
    "wof:placetype":"venue"
},
  "geometry": {"coordinates":[-74.002189,40.7085],"type":"Point"}
}