{
  "type": "Feature",
  "properties": {
    "iso:country":"US",
    "sg:address":"10 Western Ave",
    "sg:city":"Marlboro",
    "sg:classifiers":[
        {
            "category":"Food & Beverages",
            "subcategory":"Liquor & Beverages",
            "type":"Retail Goods"
        }
    ],
    "sg:phone":"+1 845 236 3915",
    "sg:postcode":"12542",
    "sg:province":"NY",
    "sg:tags":[
        "beer",
        "spirit",
        "wine"
    ],
    "sg:website":"www.winestore.com",
    "wof:name":"The Wine Store",
    "wof:placetype":"venue"
},
  "geometry": {"coordinates":[-73.972013,41.605764],"type":"Point"}
}