{
  "type": "Feature",
  "properties": {
    "iso:country":"US",
    "sg:address":"520 Broadway",
    "sg:city":"New York",
    "sg:classifiers":[
        {
            "category":"Banks & Credit Unions",
            "subcategory":"Investment Brokerage",
            "type":"Services"
        }
    ],
    "sg:phone":"+1 212 431 0856",
    "sg:postcode":"10012",
    "sg:province":"NY",
    "sg:tags":[
        "investing"
    ],
    "wof:name":"Vectors Research Managment",
    "wof:placetype":"venue"
},
  "geometry": {"coordinates":[-73.998958,40.722811],"type":"Point"}
}