{
  "type": "Feature",
  "properties": {
    "iso:country":"US",
    "sg:address":"421 State Hwy 211",
    "sg:city":"Middletown",
    "sg:classifiers":[
        {
            "category":"Food & Beverages",
            "subcategory":"Bakery",
            "type":"Retail Goods"
        }
    ],
    "sg:phone":"+1 845 342 6098",
    "sg:postcode":"10940",
    "sg:province":"NY",
    "sg:tags":[
        "doughnut"
    ],
    "sg:website":"www.dunkindonuts.com",
    "wof:name":"Dunkin' Donuts",
    "wof:placetype":"venue"
},
  "geometry": {"coordinates":[-74.446409,41.46412],"type":"Point"}
}