{
  "type": "Feature",
  "properties": {
    "iso:country":"US",
    "sg:address":"875 Saw Mill River Rd",
    "sg:city":"Ardsley",
    "sg:classifiers":[
        {
            "category":"Retail",
            "subcategory":"Repair Shop",
            "type":"Services"
        }
    ],
    "sg:phone":"+1 914 233 5704",
    "sg:postcode":"10502",
    "sg:province":"NY",
    "sg:tags":[
        "lock",
        "locksmith"
    ],
    "wof:name":"USA Locksmith",
    "wof:placetype":"venue"
},
  "geometry": {"coordinates":[-73.844223,41.017758],"type":"Point"}
}