{
  "type": "Feature",
  "properties": {
    "addr:full":"207 W 14 St New York NY 10011",
    "addr:housenumber":"207",
    "addr:postcode":"10011",
    "addr:street":"W 14 St",
    "iso:country":"US",
    "sg:address":"207 W 14 St",
    "sg:city":"New York",
    "sg:classifiers":[
        {
            "category":"Shopping",
            "subcategory":"Books",
            "type":"Retail Goods"
        }
    ],
    "sg:phone":"+1   ",
    "sg:postcode":"10011",
    "sg:province":"NY",
    "wof:name":"Rodgers Time Machine",
    "wof:placetype":"venue"
},
  "geometry": {"coordinates":[-74.00235499999999,40.739745],"type":"Point"}
}