{
  "type": "Feature",
  "properties": {
    "addr:full":"156 Newcastle Rd Rochester NY 14610",
    "addr:housenumber":"156",
    "addr:postcode":"14610",
    "addr:street":"Newcastle Rd",
    "iso:country":"US",
    "sg:address":"156 Newcastle Rd",
    "sg:city":"Rochester",
    "sg:classifiers":[
        {
            "category":"Arts & Performance",
            "subcategory":"Art Gallery",
            "type":"Entertainment"
        }
    ],
    "sg:phone":"+1 585 482 9519",
    "sg:postcode":"14610",
    "sg:province":"NY",
    "sg:tags":[
        "consultant",
        "galleries"
    ],
    "wof:name":"Forest Sherwoods",
    "wof:placetype":"venue"
},
  "geometry": {"coordinates":[-77.542282,43.153304],"type":"Point"}
}