{
  "type": "Feature",
  "properties": {
    "iso:country":"US",
    "sg:address":"1 Solar Dr",
    "sg:city":"Clifton Park",
    "sg:classifiers":[
        {
            "category":"Manufacturing",
            "subcategory":"Tools & Machinery",
            "type":"Manufacturing & Wholesale Goods"
        }
    ],
    "sg:phone":"+1   ",
    "sg:postcode":"12065",
    "sg:province":"NY",
    "sg:tags":[
        "manufacture",
        "insulated",
        "panel"
    ],
    "sg:website":"www.advanceet.com",
    "wof:name":"Advance Energy Technologies",
    "wof:placetype":"venue"
},
  "geometry": {"coordinates":[-73.751076,42.866397],"type":"Point"}
}