{
  "type": "Feature",
  "properties": {
    "addr:full":"3891 State Hwy 89 Seneca Falls NY 13148",
    "addr:housenumber":"3891",
    "addr:postcode":"13148",
    "addr:street":"State Hwy 89",
    "iso:country":"US",
    "sg:address":"3891 State Hwy 89",
    "sg:city":"Seneca Falls",
    "sg:classifiers":[
        {
            "category":"Autos & Motor Vehicles",
            "subcategory":"Automobile Sales",
            "type":"Retail Goods"
        }
    ],
    "sg:phone":"+1 315 549 8257",
    "sg:postcode":"13148",
    "sg:province":"NY",
    "sg:tags":[
        "car",
        "dealer"
    ],
    "wof:name":"J B Collision & Auto Sales",
    "wof:placetype":"venue"
},
  "geometry": {"coordinates":[-76.743644,42.836528],"type":"Point"}
}