{
  "type": "Feature",
  "properties": {
    "addr:full":"886 Pelham Pkwy Pelham NY 10803",
    "addr:housenumber":"886",
    "addr:postcode":"10803",
    "addr:street":"Pelham Pkwy",
    "iso:country":"US",
    "sg:address":"886 Pelham Pkwy",
    "sg:city":"Pelham",
    "sg:classifiers":[
        {
            "category":"Home & Garden",
            "subcategory":"Furniture",
            "type":"Retail Goods"
        }
    ],
    "sg:phone":"+1 914 738 6404",
    "sg:postcode":"10803",
    "sg:province":"NY",
    "sg:tags":[
        "store"
    ],
    "wof:name":"Furniture City Inc",
    "wof:placetype":"venue"
},
  "geometry": {"coordinates":[-73.862021,40.856749],"type":"Point"}
}