{
  "type": "Feature",
  "properties": {
    "addr:full":"266 Red Apple Ct Central Valley NY 10917",
    "addr:housenumber":"266",
    "addr:postcode":"10917",
    "addr:street":"Red Apple Ct",
    "iso:country":"US",
    "sg:address":"266 Red Apple Ct",
    "sg:city":"Central Valley",
    "sg:classifiers":[
        {
            "category":"Shopping",
            "subcategory":"Clothing, Apparel, & Fashions",
            "type":"Retail Goods"
        },
        {
            "category":"Shopping",
            "subcategory":"Hobbies, Toys, & Games",
            "type":"Retail Goods"
        },
        {
            "category":"Sports & Exercise",
            "subcategory":"Bicycle Rental",
            "type":"Entertainment"
        },
        {
            "category":"Shopping",
            "subcategory":"Discount & Variety Stores",
            "type":"Retail Goods"
        }
    ],
    "sg:phone":"+1 845 928 9247",
    "sg:postcode":"10917",
    "sg:province":"NY",
    "sg:tags":[
        "children's",
        "toy",
        "clothing",
        "outlet",
        "wear"
    ],
    "wof:name":"Woodbury Common Premium Outlets",
    "wof:placetype":"venue"
},
  "geometry": {"coordinates":[-74.125809,41.316234],"type":"Point"}
}