{
  "type": "Feature",
  "properties": {
    "addr:full":"107 Spruce Ln Clinton Corners NY 12514",
    "addr:housenumber":"107",
    "addr:postcode":"12514",
    "addr:street":"Spruce Ln",
    "iso:country":"US",
    "sg:address":"107 Spruce Ln",
    "sg:city":"Clinton Corners",
    "sg:classifiers":[
        {
            "category":"Social Services",
            "subcategory":"Adult Care",
            "type":"Services"
        }
    ],
    "sg:phone":"+1 845 266 4535",
    "sg:postcode":"12514",
    "sg:province":"NY",
    "sg:tags":[
        "home",
        "group"
    ],
    "wof:name":"Evergreen Community Residence",
    "wof:placetype":"venue"
},
  "geometry": {"coordinates":[-73.76985999999999,41.874002],"type":"Point"}
}