{
  "type": "Feature",
  "properties": {
    "iso:country":"US",
    "sg:address":"8765 Brewerton Rd",
    "sg:city":"Brewerton",
    "sg:classifiers":[
        {
            "category":"Home & Garden",
            "subcategory":"Building Materials",
            "type":"Retail Goods"
        }
    ],
    "sg:phone":"+1 315 698 1600",
    "sg:postcode":"13029",
    "sg:province":"NY",
    "sg:tags":[
        "modular"
    ],
    "sg:website":"www.ahsyr.com",
    "wof:name":"American Homes Of Syracuse",
    "wof:placetype":"venue"
},
  "geometry": {"coordinates":[-76.12584,43.193104],"type":"Point"}
}