{
  "type": "Feature",
  "properties": {
    "iso:country":"US",
    "sg:address":"239 Dekalb Ave",
    "sg:city":"Brooklyn",
    "sg:classifiers":[
        {
            "category":"Building & Trades",
            "subcategory":"Locksmith",
            "type":"Services"
        }
    ],
    "sg:phone":"+1 347 844 6070",
    "sg:postcode":"11205",
    "sg:province":"NY",
    "sg:tags":[
        "key"
    ],
    "wof:name":"Anytime Anywhere Dekalb Ave Emergency Locksmit",
    "wof:placetype":"venue"
},
  "geometry": {"coordinates":[-73.96966500000001,40.689629],"type":"Point"}
}