{
  "type": "Feature",
  "properties": {
    "addr:full":"17 Wadg Riv Wading River NY 11792",
    "addr:housenumber":"17",
    "addr:postcode":"11792",
    "addr:street":"Wadg Riv",
    "iso:country":"US",
    "sg:address":"17 Wadg Riv",
    "sg:city":"Wading River",
    "sg:classifiers":[
        {
            "category":"Bakery",
            "type":"Food & Drink"
        }
    ],
    "sg:phone":"+1 631 929 4616",
    "sg:postcode":"11792",
    "sg:province":"NY",
    "wof:name":"Fontana's Bakery",
    "wof:placetype":"venue"
},
  "geometry": {"coordinates":[-72.835403,40.948002],"type":"Point"}
}