{
  "type": "Feature",
  "properties": {
    "addr:full":"919 Flushing Ave Brooklyn NY 11206",
    "addr:housenumber":"919",
    "addr:postcode":"11206",
    "addr:street":"Flushing Ave",
    "iso:country":"US",
    "sg:address":"919 Flushing Ave",
    "sg:city":"Brooklyn",
    "sg:classifiers":[
        {
            "category":"Food & Beverages",
            "subcategory":"Meat & Fish",
            "type":"Retail Goods"
        },
        {
            "category":"Wholesale",
            "subcategory":"Meat",
            "type":"Manufacturing & Wholesale Goods"
        }
    ],
    "sg:phone":"+1 718 386 3300",
    "sg:postcode":"11206",
    "sg:province":"NY",
    "wof:name":"Flushing Meat Provisions Corp",
    "wof:placetype":"venue"
},
  "geometry": {"coordinates":[-73.936166,40.702124],"type":"Point"}
}