{
  "type": "Feature",
  "properties": {
    "addr:full":"552 Port Richmond Ave Staten Island NY 10302",
    "addr:housenumber":"552",
    "addr:postcode":"10302",
    "addr:street":"Port Richmond Ave",
    "iso:country":"US",
    "sg:address":"552 Port Richmond Ave",
    "sg:city":"Staten Island",
    "sg:classifiers":[
        {
            "category":"Personal",
            "subcategory":"Barber",
            "type":"Services"
        }
    ],
    "sg:phone":"+1 718 420 3668",
    "sg:postcode":"10302",
    "sg:province":"NY",
    "wof:name":"Innovative Style Shop",
    "wof:placetype":"venue"
},
  "geometry": {"coordinates":[-74.1409,40.629601],"type":"Point"}
}