{
  "type": "Feature",
  "properties": {
    "iso:country":"US",
    "sg:address":"4731 Onondaga Blvd",
    "sg:city":"Syracuse",
    "sg:classifiers":[
        {
            "category":"Retail",
            "subcategory":"Auto Repair",
            "type":"Services"
        }
    ],
    "sg:phone":"+1 315 471 3338",
    "sg:postcode":"13219",
    "sg:province":"NY",
    "sg:tags":[
        "repairing",
        "automobile",
        "brake",
        "provides",
        "automotive"
    ],
    "sg:website":"http://www.monro.com",
    "wof:name":"Monro Muffler Brake & Service",
    "wof:placetype":"venue"
},
  "geometry": {"coordinates":[-76.19051399999999,43.033249],"type":"Point"}
}