{
  "type": "Feature",
  "properties": {
    "iso:country":"US",
    "sg:address":"646 Jericho Tpke",
    "sg:city":"St James",
    "sg:classifiers":[
        {
            "category":"Autos & Motor Vehicles",
            "subcategory":"Auto Supplies",
            "type":"Retail Goods"
        }
    ],
    "sg:phone":"+1 631 361 0001",
    "sg:postcode":"11780",
    "sg:province":"NY",
    "sg:tags":[
        "automobile",
        "stereo",
        "radio"
    ],
    "wof:name":"Beverly Hills Auto Toy Store",
    "wof:placetype":"venue"
},
  "geometry": {"coordinates":[-73.158188,40.860039],"type":"Point"}
}