{
  "type": "Feature",
  "properties": {
    "iso:country":"US",
    "sg:address":"8 Ulster Ave",
    "sg:city":"Saugerties",
    "sg:classifiers":[
        {
            "category":"Health Services",
            "subcategory":"Doctor",
            "type":"Services"
        }
    ],
    "sg:phone":"+1 845 246 3070",
    "sg:postcode":"12477",
    "sg:province":"NY",
    "wof:name":"Polaski Dental Group",
    "wof:placetype":"venue"
},
  "geometry": {"coordinates":[-73.95479,42.078458],"type":"Point"}
}