{
  "type": "Feature",
  "properties": {
    "addr:full":"24 Bolan Dr Huntington Sta NY 11746",
    "addr:housenumber":"24",
    "addr:postcode":"11746",
    "addr:street":"Bolan Dr",
    "iso:country":"US",
    "sg:address":"24 Bolan Dr",
    "sg:city":"Huntington Sta",
    "sg:classifiers":[
        {
            "category":"Building & Trades",
            "subcategory":"Construction",
            "type":"Services"
        }
    ],
    "sg:phone":"+1 631 423 3910",
    "sg:postcode":"11746",
    "sg:province":"NY",
    "sg:tags":[
        "resurfacing",
        "laying",
        "refinishing",
        "floor"
    ],
    "wof:name":"Profile Flooring Consultants",
    "wof:placetype":"venue"
},
  "geometry": {"coordinates":[-73.38192600000001,40.841601],"type":"Point"}
}