{
  "type": "Feature",
  "properties": {
    "addr:full":"45 Eagle Ridge Way Nanuet NY 10954",
    "addr:housenumber":"45",
    "addr:postcode":"10954",
    "addr:street":"Eagle Ridge Way",
    "iso:country":"US",
    "sg:address":"45 Eagle Ridge Way",
    "sg:city":"Nanuet",
    "sg:classifiers":[
        {
            "category":"Real Estate",
            "subcategory":"Real Estate Operator",
            "type":"Services"
        }
    ],
    "sg:phone":"+1 845 352 8068",
    "sg:postcode":"10954",
    "sg:province":"NY",
    "sg:tags":[
        "apartment"
    ],
    "wof:name":"Eagle Ridge Condominium Hoa",
    "wof:placetype":"venue"
},
  "geometry": {"coordinates":[-74.020053,41.112367],"type":"Point"}
}