{
  "type": "Feature",
  "properties": {
    "iso:country":"US",
    "sg:address":"3786 Eckhardt Rd",
    "sg:city":"Hamburg",
    "sg:classifiers":[
        {
            "category":"Retail",
            "subcategory":"Auto Repair",
            "type":"Services"
        }
    ],
    "sg:phone":"+1   ",
    "sg:postcode":"14075",
    "sg:province":"NY",
    "sg:tags":[
        "body"
    ],
    "wof:name":"Village Auto Body & Glass",
    "wof:placetype":"venue"
},
  "geometry": {"coordinates":[-78.853148,42.685429],"type":"Point"}
}