{
  "type": "Feature",
  "properties": {
    "addr:full":"120 Stuyvesant Pl Staten Island NY 10301",
    "addr:housenumber":"120",
    "addr:postcode":"10301",
    "addr:street":"Stuyvesant Pl",
    "iso:country":"US",
    "sg:address":"120 Stuyvesant Pl",
    "sg:city":"Staten Island",
    "sg:classifiers":[
        {
            "category":"Social Services",
            "subcategory":"Child Care",
            "type":"Services"
        }
    ],
    "sg:phone":"+1 718 815 7740",
    "sg:postcode":"10301",
    "sg:province":"NY",
    "sg:tags":[
        "day"
    ],
    "wof:name":"Children's Life Center St George",
    "wof:placetype":"venue"
},
  "geometry": {"coordinates":[-74.07710299999999,40.643101],"type":"Point"}
}