{
  "type": "Feature",
  "properties": {
    "addr:full":"1594 Westchester Avenue Bronx NY 10472",
    "addr:housenumber":"1594",
    "addr:postcode":"10472",
    "addr:street":"Westchester Avenue",
    "iso:country":"US",
    "sg:address":"1594 Westchester Avenue",
    "sg:city":"Bronx",
    "sg:classifiers":[
        {
            "category":"Shopping",
            "subcategory":"Optician",
            "type":"Retail Goods"
        }
    ],
    "sg:phone":"+1 718 861 6009",
    "sg:postcode":"10472",
    "sg:province":"NY",
    "sg:tags":[
        "eyewear"
    ],
    "wof:name":"Family Optical Shoppe Corporation",
    "wof:placetype":"venue"
},
  "geometry": {"coordinates":[-73.875626,40.82902],"type":"Point"}
}