{
  "type": "Feature",
  "properties": {
    "addr:full":"14 Wall St New York NY 10005",
    "addr:housenumber":"14",
    "addr:postcode":"10005",
    "addr:street":"Wall St",
    "iso:country":"US",
    "sg:address":"14 Wall St",
    "sg:city":"New York",
    "sg:classifiers":[
        {
            "category":"Professional",
            "subcategory":"Lawyer & Legal Services",
            "type":"Services"
        }
    ],
    "sg:phone":"+1 212 571 9596",
    "sg:postcode":"10005",
    "sg:province":"NY",
    "wof:name":"Burke Constance M",
    "wof:placetype":"venue"
},
  "geometry": {"coordinates":[-74.01129899999999,40.7075],"type":"Point"}
}