{
  "type": "Feature",
  "properties": {
    "iso:country":"US",
    "sg:address":"240 Commerce Blvd",
    "sg:city":"Liverpool",
    "sg:classifiers":[
        {
            "category":"Professional",
            "subcategory":"Credit Reporting & Collection",
            "type":"Services"
        }
    ],
    "sg:phone":"+1   ",
    "sg:postcode":"13088",
    "sg:province":"NY",
    "wof:name":"Mohawk Assistance Inc",
    "wof:placetype":"venue"
},
  "geometry": {"coordinates":[-76.199963,43.111756],"type":"Point"}
}