{
  "type": "Feature",
  "properties": {
    "addr:full":"183 E 98 St New York NY 10029",
    "addr:housenumber":"183;98",
    "addr:postcode":"10029",
    "addr:street":"E;St",
    "iso:country":"US",
    "sg:address":"183 E 98 St",
    "sg:city":"New York",
    "sg:classifiers":[
        {
            "category":"Government",
            "subcategory":"Office",
            "type":"Public Place"
        }
    ],
    "sg:phone":"+1 212 876 2659",
    "sg:postcode":"10029",
    "sg:province":"NY",
    "sg:tags":[
        "city",
        "planning",
        "dev"
    ],
    "wof:name":"East Harlem Renewal Agency Inc",
    "wof:placetype":"venue"
},
  "geometry": {"coordinates":[-73.949251,40.787069],"type":"Point"}
}