{
  "type": "Feature",
  "properties": {
    "addr:full":"1 Kalev Way Unit 102 Monroe NY 10950",
    "addr:housenumber":"1;102",
    "addr:postcode":"10950",
    "addr:street":"Kalev Way Unit",
    "iso:country":"US",
    "sg:address":"1 Kalev Way Unit 102",
    "sg:city":"Monroe",
    "sg:classifiers":[
        {
            "category":"Home & Garden",
            "subcategory":"Building Materials",
            "type":"Retail Goods"
        },
        {
            "category":"Building & Trades",
            "subcategory":"Construction",
            "type":"Services"
        }
    ],
    "sg:phone":"+1 845 782 0308",
    "sg:postcode":"10950",
    "sg:province":"NY",
    "sg:tags":[
        "insulation",
        "contractor"
    ],
    "wof:name":"R&R Well Done Insulation Corp",
    "wof:placetype":"venue"
},
  "geometry": {"coordinates":[-74.165627,41.339321],"type":"Point"}
}