{
  "type": "Feature",
  "properties": {
    "addr:full":"14 E 60 St New York NY 10022",
    "addr:housenumber":"14;60",
    "addr:postcode":"10022",
    "addr:street":"E",
    "iso:country":"US",
    "sg:address":"14 E 60 St",
    "sg:city":"New York",
    "sg:classifiers":[
        {
            "category":"Shopping",
            "subcategory":"Clothing, Apparel, & Fashions",
            "type":"Retail Goods"
        }
    ],
    "sg:phone":"+1 212 935 5379",
    "sg:postcode":"10022",
    "sg:province":"NY",
    "sg:tags":[
        "tailor"
    ],
    "wof:name":"Bhambi's Custom Tailors LTD",
    "wof:placetype":"venue"
},
  "geometry": {"coordinates":[-73.97202900000001,40.764734],"type":"Point"}
}