{
  "type": "Feature",
  "properties": {
    "iso:country":"US",
    "sg:address":"1123 Broadway Ste 716",
    "sg:city":"New York",
    "sg:classifiers":[
        {
            "category":"Arts & Performance",
            "subcategory":"Arts Center",
            "type":"Entertainment"
        }
    ],
    "sg:phone":"+1 212 675 4176",
    "sg:postcode":"10010",
    "sg:province":"NY",
    "sg:website":"www.altpick.com",
    "wof:name":"Alternative Pick",
    "wof:placetype":"venue"
},
  "geometry": {"coordinates":[-73.989294,40.743307],"type":"Point"}
}