{
  "type": "Feature",
  "properties": {
    "addr:full":"355 W 52nd Street New York NY 10019",
    "addr:housenumber":"355",
    "addr:postcode":"10019",
    "addr:street":"W 52Nd Street",
    "iso:country":"US",
    "sg:address":"355 W 52nd Street",
    "sg:city":"New York",
    "sg:classifiers":[
        {
            "category":"Health Services",
            "subcategory":"Doctor",
            "type":"Services"
        }
    ],
    "sg:phone":"+1 646 778 5550",
    "sg:postcode":"10019",
    "sg:province":"NY",
    "sg:website":"www.millerinstitute.org",
    "wof:name":"Miller Health Care Institue",
    "wof:placetype":"venue"
},
  "geometry": {"coordinates":[-73.98577899999999,40.765422],"type":"Point"}
}