{
  "type": "Feature",
  "properties": {
    "iso:country":"US",
    "sg:address":"118 Woodbury Rd",
    "sg:city":"Woodbury",
    "sg:classifiers":[
        {
            "category":"Retail",
            "subcategory":"Laundry & Dry Cleaning",
            "type":"Services"
        }
    ],
    "sg:phone":"+1 631 789 3607",
    "sg:postcode":"11797",
    "sg:province":"NY",
    "wof:name":"Steve's Valet Cleaners",
    "wof:placetype":"venue"
},
  "geometry": {"coordinates":[-73.458,40.8307],"type":"Point"}
}