{
  "type": "Feature",
  "properties": {
    "addr:full":"299 Amsterdam Ave Scotia NY 12302",
    "addr:housenumber":"299",
    "addr:postcode":"12302",
    "addr:street":"Amsterdam Ave",
    "iso:country":"US",
    "sg:address":"299 Amsterdam Ave",
    "sg:city":"Scotia",
    "sg:classifiers":[
        {
            "category":"Bars & Pubs",
            "type":"Food & Drink"
        }
    ],
    "sg:phone":"+1 518 372 9391",
    "sg:postcode":"12302",
    "sg:province":"NY",
    "wof:name":"Chart Room Tavern",
    "wof:placetype":"venue"
},
  "geometry": {"coordinates":[-73.983802,42.847688],"type":"Point"}
}