{
  "type": "Feature",
  "properties": {
    "addr:full":"981 Van Patten Rd Duanesburg NY 12056",
    "addr:housenumber":"981",
    "addr:postcode":"12056",
    "addr:street":"Van Patten Rd",
    "iso:country":"US",
    "sg:address":"981 Van Patten Rd",
    "sg:city":"Duanesburg",
    "sg:classifiers":[
        {
            "category":"Building & Trades",
            "subcategory":"Construction",
            "type":"Services"
        }
    ],
    "sg:phone":"+1 518 895 8268",
    "sg:postcode":"12056",
    "sg:province":"NY",
    "sg:tags":[
        "heavy"
    ],
    "wof:name":"Suhrada Construction",
    "wof:placetype":"venue"
},
  "geometry": {"coordinates":[-74.12398899999999,42.767757],"type":"Point"}
}