{
  "type": "Feature",
  "properties": {
    "addr:full":"148 Carleton Ave East Islip NY 11730",
    "addr:housenumber":"148",
    "addr:postcode":"11730",
    "addr:street":"Carleton Ave",
    "iso:country":"US",
    "sg:address":"148 Carleton Ave",
    "sg:city":"East Islip",
    "sg:classifiers":[
        {
            "category":"Restaurant",
            "type":"Food & Drink"
        }
    ],
    "sg:phone":"+1 631 581 3386",
    "sg:postcode":"11730",
    "sg:province":"NY",
    "wof:name":"Yellow Ledbetters Bar & Grill",
    "wof:placetype":"venue"
},
  "geometry": {"coordinates":[-73.192046,40.737448],"type":"Point"}
}