{
  "type": "Feature",
  "properties": {
    "addr:full":"2480 86th St Brooklyn NY 11214",
    "addr:housenumber":"2480",
    "addr:postcode":"11214",
    "addr:street":"86Th St",
    "iso:country":"US",
    "sg:address":"2480 86th St",
    "sg:city":"Brooklyn",
    "sg:classifiers":[
        {
            "category":"Autos & Motor Vehicles",
            "subcategory":"Automobile Sales",
            "type":"Retail Goods"
        }
    ],
    "sg:phone":"+1 718 265 5200",
    "sg:postcode":"11214",
    "sg:province":"NY",
    "sg:tags":[
        "limo"
    ],
    "wof:name":"Excelsior Two Way Radio Corp",
    "wof:placetype":"venue"
},
  "geometry": {"coordinates":[-73.987503,40.598],"type":"Point"}
}