{
  "type": "Feature",
  "properties": {
    "addr:full":"32 E Washington St Ellicottville NY 14731",
    "addr:housenumber":"32",
    "addr:postcode":"14731",
    "addr:street":"E Washington St",
    "iso:country":"US",
    "sg:address":"32 E Washington St",
    "sg:city":"Ellicottville",
    "sg:phone":"+1 716 699 2136",
    "sg:postcode":"14731",
    "sg:province":"NY",
    "wof:name":"Tip's-Up Cafe",
    "wof:placetype":"venue"
},
  "geometry": {"coordinates":[-78.667089,42.279068],"type":"Point"}
}