{
  "type": "Feature",
  "properties": {
    "addr:full":"6658 S Transit Rd Lockport NY 14094",
    "addr:housenumber":"6658",
    "addr:postcode":"14094",
    "addr:street":"S Transit Rd",
    "iso:country":"US",
    "sg:address":"6658 S Transit Rd",
    "sg:city":"Lockport",
    "sg:classifiers":[
        {
            "category":"Wholesale",
            "subcategory":"Machinery & Supplies",
            "type":"Manufacturing & Wholesale Goods"
        }
    ],
    "sg:phone":"+1 716 625 7981",
    "sg:postcode":"14094",
    "sg:province":"NY",
    "wof:name":"Eun Trailers Inc",
    "wof:placetype":"venue"
},
  "geometry": {"coordinates":[-78.69695400000001,43.109315],"type":"Point"}
}