{
  "type": "Feature",
  "properties": {
    "iso:country":"US",
    "sg:address":"201 Mill St",
    "sg:city":"Rome",
    "sg:classifiers":[
        {
            "category":"Real Estate",
            "subcategory":"Real Estate Agent",
            "type":"Services"
        }
    ],
    "sg:phone":"+1 315 336 6436",
    "sg:postcode":"13440",
    "sg:province":"NY",
    "wof:name":"A J Ryan Real Estate",
    "wof:placetype":"venue"
},
  "geometry": {"coordinates":[-75.44872100000001,43.203041],"type":"Point"}
}