{
  "type": "Feature",
  "properties": {
    "addr:full":"114 Chatsworth Ave Larchmont NY 10538",
    "addr:housenumber":"114",
    "addr:postcode":"10538",
    "addr:street":"Chatsworth Ave",
    "iso:country":"US",
    "sg:address":"114 Chatsworth Ave",
    "sg:city":"Larchmont",
    "sg:classifiers":[
        {
            "category":"Shopping",
            "subcategory":"Florist",
            "type":"Retail Goods"
        }
    ],
    "sg:phone":"+1 914 834 3036",
    "sg:postcode":"10538",
    "sg:province":"NY",
    "wof:name":"Larchmont Floral Designs",
    "wof:placetype":"venue"
},
  "geometry": {"coordinates":[-73.758792,40.932754],"type":"Point"}
}