{
  "type": "Feature",
  "properties": {
    "addr:full":"776 Nostrand Ave Brooklyn NY 11216",
    "addr:housenumber":"776",
    "addr:postcode":"11216",
    "addr:street":"Nostrand Ave",
    "iso:country":"US",
    "sg:address":"776 Nostrand Ave",
    "sg:city":"Brooklyn",
    "sg:classifiers":[
        {
            "category":"Health Services",
            "subcategory":"Clinic",
            "type":"Services"
        }
    ],
    "sg:phone":"+1 718 744 0084",
    "sg:postcode":"11216",
    "sg:province":"NY",
    "sg:tags":[
        "medical",
        "group",
        "doctor"
    ],
    "wof:name":"Sterling Medical Accounts",
    "wof:placetype":"venue"
},
  "geometry": {"coordinates":[-73.950401,40.6721],"type":"Point"}
}