{
  "type": "Feature",
  "properties": {
    "iso:country":"US",
    "sg:address":"107 7th Ave",
    "sg:city":"Brooklyn",
    "sg:classifiers":[
        {
            "category":"Health Services",
            "subcategory":"Optometrist",
            "type":"Services"
        }
    ],
    "sg:phone":"+1   ",
    "sg:postcode":"11215",
    "sg:province":"NY",
    "sg:tags":[
        "optical",
        "good"
    ],
    "wof:name":"Eyesop",
    "wof:placetype":"venue"
},
  "geometry": {"coordinates":[-73.975537,40.674362],"type":"Point"}
}