{
  "type": "Feature",
  "properties": {
    "iso:country":"US",
    "sg:address":"220 E 42nd St",
    "sg:city":"New York",
    "sg:classifiers":[
        {
            "category":"Professional",
            "subcategory":"Lawyer & Legal Services",
            "type":"Services"
        }
    ],
    "sg:phone":"+1 212 504 5630",
    "sg:postcode":"10017",
    "sg:province":"NY",
    "sg:tags":[
        "attorney"
    ],
    "wof:name":"Keck Mahin & Cate",
    "wof:placetype":"venue"
},
  "geometry": {"coordinates":[-73.972587,40.74995],"type":"Point"}
}