{
  "type": "Feature",
  "properties": {
    "iso:country":"US",
    "sg:address":"261 Goossen Regan Rd",
    "sg:city":"Buskirk",
    "sg:classifiers":[
        {
            "category":"Professional",
            "subcategory":"Management & Consulting",
            "type":"Services"
        }
    ],
    "sg:phone":"+1 518 753 7655",
    "sg:postcode":"12028",
    "sg:province":"NY",
    "sg:tags":[
        "consultant"
    ],
    "wof:name":"Think Biotechnology",
    "wof:placetype":"venue"
},
  "geometry": {"coordinates":[-73.4667,42.917546],"type":"Point"}
}