{
  "type": "Feature",
  "properties": {
    "addr:full":"6 Murray St New York NY 10007",
    "addr:housenumber":"6",
    "addr:postcode":"10007",
    "addr:street":"Murray St",
    "iso:country":"US",
    "sg:address":"6 Murray St",
    "sg:city":"New York",
    "sg:classifiers":[
        {
            "category":"Restaurant",
            "type":"Food & Drink"
        }
    ],
    "sg:phone":"+1   ",
    "sg:postcode":"10007",
    "sg:province":"NY",
    "sg:tags":[
        "eating",
        "bar"
    ],
    "wof:name":"Nathan Hales Bar & Grill",
    "wof:placetype":"venue"
},
  "geometry": {"coordinates":[-74.008708,40.713632],"type":"Point"}
}