{
  "type": "Feature",
  "properties": {
    "iso:country":"US",
    "sg:address":"544 W Old Country Rd",
    "sg:city":"Hicksville",
    "sg:classifiers":[
        {
            "category":"Autos & Motor Vehicles",
            "subcategory":"Motorcycle Sales",
            "type":"Retail Goods"
        }
    ],
    "sg:phone":"+1 516 433 0701",
    "sg:postcode":"11801",
    "sg:province":"NY",
    "wof:name":"Champion Honda",
    "wof:placetype":"venue"
},
  "geometry": {"coordinates":[-73.5485,40.757],"type":"Point"}
}