{
  "type": "Feature",
  "properties": {
    "iso:country":"US",
    "sg:address":"931 E Fayette St",
    "sg:city":"Syracuse",
    "sg:classifiers":[
        {
            "category":"Organizations",
            "subcategory":"Labor Organization",
            "type":"Services"
        }
    ],
    "sg:phone":"+1 315 474 4618",
    "sg:postcode":"13210",
    "sg:province":"NY",
    "wof:name":"Csea Local 615",
    "wof:placetype":"venue"
},
  "geometry": {"coordinates":[-76.136786,43.048555],"type":"Point"}
}