{
  "type": "Feature",
  "properties": {
    "addr:full":"63 W 38th St New York NY 10018",
    "addr:housenumber":"63",
    "addr:postcode":"10018",
    "addr:street":"W 38Th St",
    "iso:country":"US",
    "sg:address":"63 W 38th St",
    "sg:city":"New York",
    "sg:classifiers":[
        {
            "category":"Wholesale",
            "subcategory":"Apparel",
            "type":"Manufacturing & Wholesale Goods"
        }
    ],
    "sg:phone":"+1 212 719 2150",
    "sg:postcode":"10018",
    "sg:province":"NY",
    "sg:tags":[
        "synthetic",
        "woven",
        "converter",
        "fabric"
    ],
    "wof:name":"Hertz Fabrics",
    "wof:placetype":"venue"
},
  "geometry": {"coordinates":[-73.984365,40.751523],"type":"Point"}
}