{
  "type": "Feature",
  "properties": {
    "addr:full":"97 W Utica St Oswego NY 13126",
    "addr:housenumber":"97",
    "addr:postcode":"13126",
    "addr:street":"W Utica St",
    "iso:country":"US",
    "sg:address":"97 W Utica St",
    "sg:city":"Oswego",
    "sg:classifiers":[
        {
            "category":"Banks & Credit Unions",
            "subcategory":"Investment Brokerage",
            "type":"Services"
        }
    ],
    "sg:phone":"+1 315 342 1227",
    "sg:postcode":"13126",
    "sg:province":"NY",
    "sg:tags":[
        "consultant",
        "planning",
        "financial"
    ],
    "sg:website":"www.ameriprise.com",
    "wof:name":"Ameriprise Financial",
    "wof:placetype":"venue"
},
  "geometry": {"coordinates":[-76.516448,43.450589],"type":"Point"}
}