{
  "type": "Feature",
  "properties": {
    "addr:full":"780 Marconi Ave Ronkonkoma NY 11779",
    "addr:housenumber":"780",
    "addr:postcode":"11779",
    "addr:street":"Marconi Ave",
    "iso:country":"US",
    "sg:address":"780 Marconi Ave",
    "sg:city":"Ronkonkoma",
    "sg:classifiers":[
        {
            "category":"Professional",
            "type":"Services"
        }
    ],
    "sg:phone":"+1 631 204 9300",
    "sg:postcode":"11779",
    "sg:province":"NY",
    "sg:tags":[
        "establishment"
    ],
    "wof:name":"Select A Form Inc",
    "wof:placetype":"venue"
},
  "geometry": {"coordinates":[-73.12009,40.795617],"type":"Point"}
}