{
  "type": "Feature",
  "properties": {
    "addr:full":"109 Roxbury Rd Kirkville NY 13082",
    "addr:housenumber":"109",
    "addr:postcode":"13082",
    "addr:street":"Roxbury Rd",
    "iso:country":"US",
    "sg:address":"109 Roxbury Rd",
    "sg:city":"Kirkville",
    "sg:classifiers":[
        {
            "category":"Landmark",
            "subcategory":"Tourist Information",
            "type":"Public Place"
        }
    ],
    "sg:phone":"+1 315 727 5852",
    "sg:postcode":"13082",
    "sg:province":"NY",
    "sg:tags":[
        "promoter",
        "tours-operators"
    ],
    "wof:name":"Clarke Tours Co",
    "wof:placetype":"venue"
},
  "geometry": {"coordinates":[-75.938171,43.096925],"type":"Point"}
}