{
  "type": "Feature",
  "properties": {
    "iso:country":"US",
    "sg:address":"318 N Broadway",
    "sg:city":"Hicksville",
    "sg:classifiers":[
        {
            "category":"Home & Garden",
            "subcategory":"Furniture",
            "type":"Retail Goods"
        },
        {
            "category":"Wholesale",
            "subcategory":"Home Furnishings",
            "type":"Manufacturing & Wholesale Goods"
        }
    ],
    "sg:phone":"+1 516 433 4333",
    "sg:postcode":"11801",
    "sg:province":"NY",
    "sg:tags":[
        "equipment-wholesale",
        "kitchen",
        "equipment-household",
        "manufacturer",
        "cabinet"
    ],
    "wof:name":"Design Concepts Inc",
    "wof:placetype":"venue"
},
  "geometry": {"coordinates":[-73.516425,40.761538],"type":"Point"}
}