{
  "type": "Feature",
  "properties": {
    "addr:full":"110 Marcus Blvd Hauppauge NY 11788",
    "addr:housenumber":"110",
    "addr:postcode":"11788",
    "addr:street":"Marcus Blvd",
    "iso:country":"US",
    "sg:address":"110 Marcus Blvd",
    "sg:city":"Hauppauge",
    "sg:classifiers":[
        {
            "category":"Insurance",
            "subcategory":"Insurance Agent",
            "type":"Services"
        }
    ],
    "sg:phone":"+1 631 273 7700",
    "sg:postcode":"11788",
    "sg:province":"NY",
    "wof:name":"Tri-City Ins Brokers",
    "wof:placetype":"venue"
},
  "geometry": {"coordinates":[-73.24711000000001,40.811175],"type":"Point"}
}