{
  "type": "Feature",
  "properties": {
    "iso:country":"US",
    "sg:address":"44 Elm Ave",
    "sg:city":"Larchmont",
    "sg:classifiers":[
        {
            "category":"Freight",
            "type":"Transportation"
        }
    ],
    "sg:phone":"+1   ",
    "sg:postcode":"10538",
    "sg:province":"NY",
    "sg:tags":[
        "local",
        "without",
        "storage",
        "trucking"
    ],
    "wof:name":"Elm Ave Trucking Service Inc",
    "wof:placetype":"venue"
},
  "geometry": {"coordinates":[-73.754071,40.924328],"type":"Point"}
}