{
  "type": "Feature",
  "properties": {
    "addr:full":"25 Ave B New York NY 10009",
    "addr:postcode":"10009",
    "addr:street":"25 Ave B",
    "iso:country":"US",
    "sg:address":"25 Ave B",
    "sg:city":"New York",
    "sg:classifiers":[
        {
            "category":"Restaurant",
            "type":"Food & Drink"
        }
    ],
    "sg:phone":"+1 646 692 6216",
    "sg:postcode":"10009",
    "sg:province":"NY",
    "sg:tags":[
        "cajun/creole"
    ],
    "sg:website":"billyhurricanes.com",
    "wof:name":"Billy Hurricane's",
    "wof:placetype":"venue"
},
  "geometry": {"coordinates":[-73.983133,40.722275],"type":"Point"}
}