{
  "type": "Feature",
  "properties": {
    "iso:country":"US",
    "sg:address":"10 Kelly Ave",
    "sg:city":"Middleport",
    "sg:classifiers":[
        {
            "category":"Freight",
            "type":"Transportation"
        }
    ],
    "sg:phone":"+1 716 735 7724",
    "sg:postcode":"14105",
    "sg:province":"NY",
    "sg:tags":[
        "warehouse",
        "storage"
    ],
    "wof:name":"Middleport Cold Storage Co",
    "wof:placetype":"venue"
},
  "geometry": {"coordinates":[-78.48133,43.210057],"type":"Point"}
}