{
  "type": "Feature",
  "properties": {
    "addr:full":"5719 Meetinghouse Rd Tully NY 13159",
    "addr:housenumber":"5719",
    "addr:postcode":"13159",
    "addr:street":"Meetinghouse Rd",
    "iso:country":"US",
    "sg:address":"5719 Meetinghouse Rd",
    "sg:city":"Tully",
    "sg:classifiers":[
        {
            "category":"Personal",
            "type":"Services"
        },
        {
            "category":"Retail",
            "subcategory":"Auto Rental",
            "type":"Services"
        }
    ],
    "sg:phone":"+1 315 696 2536",
    "sg:postcode":"13159",
    "sg:province":"NY",
    "sg:tags":[
        "mover",
        "truck"
    ],
    "wof:name":"U-Haul Co.",
    "wof:placetype":"venue"
},
  "geometry": {"coordinates":[-76.122879,42.791228],"type":"Point"}
}