{
  "type": "Feature",
  "properties": {
    "addr:full":"162 Ditmars St Bronx NY 10464",
    "addr:housenumber":"162",
    "addr:postcode":"10464",
    "addr:street":"Ditmars St",
    "iso:country":"US",
    "sg:address":"162 Ditmars St",
    "sg:city":"Bronx",
    "sg:classifiers":[
        {
            "category":"Building & Trades",
            "subcategory":"Electrical",
            "type":"Services"
        }
    ],
    "sg:phone":"+1 718 885 3141",
    "sg:postcode":"10464",
    "sg:province":"NY",
    "sg:tags":[
        "electrical",
        "contractor"
    ],
    "wof:name":"Seaside Electrical Cnstr",
    "wof:placetype":"venue"
},
  "geometry": {"coordinates":[-73.787178,40.849626],"type":"Point"}
}