{
  "type": "Feature",
  "properties": {
    "addr:full":"7 Allan Ln Mount Kisco NY 10549",
    "addr:housenumber":"7",
    "addr:postcode":"10549",
    "addr:street":"Allan Ln",
    "iso:country":"US",
    "sg:address":"7 Allan Ln",
    "sg:city":"Mount Kisco",
    "sg:classifiers":[
        {
            "category":"Professional",
            "type":"Services"
        }
    ],
    "sg:phone":"+1   ",
    "sg:postcode":"10549",
    "sg:province":"NY",
    "wof:name":"Newgen Tech Inc",
    "wof:placetype":"venue"
},
  "geometry": {"coordinates":[-73.717277,41.213507],"type":"Point"}
}