{
  "type": "Feature",
  "properties": {
    "addr:full":"358 Saw Mill River Rd Millwood NY 10546",
    "addr:housenumber":"358",
    "addr:postcode":"10546",
    "addr:street":"Saw Mill River Rd",
    "iso:country":"US",
    "sg:address":"358 Saw Mill River Rd",
    "sg:city":"Millwood",
    "sg:classifiers":[
        {
            "category":"Shopping",
            "subcategory":"Mobile Phones",
            "type":"Retail Goods"
        }
    ],
    "sg:phone":"+1 914 762 1993",
    "sg:postcode":"10546",
    "sg:province":"NY",
    "sg:website":"www.vorec.com",
    "wof:name":"Vorec",
    "wof:placetype":"venue"
},
  "geometry": {"coordinates":[-73.796204,41.193901],"type":"Point"}
}