{
  "type": "Feature",
  "properties": {
    "addr:full":"2203 Avenue Z Brooklyn NY 11235",
    "addr:housenumber":"2203",
    "addr:postcode":"11235",
    "addr:street":"Avenue Z",
    "iso:country":"US",
    "sg:address":"2203 Avenue Z",
    "sg:city":"Brooklyn",
    "sg:classifiers":[
        {
            "category":"Retail",
            "subcategory":"Funeral Services",
            "type":"Services"
        }
    ],
    "sg:phone":"+1 718 648 3093",
    "sg:postcode":"11235",
    "sg:province":"NY",
    "sg:tags":[
        "cemetery"
    ],
    "wof:name":"William G Benson Funeral Director",
    "wof:placetype":"venue"
},
  "geometry": {"coordinates":[-73.947197,40.588902],"type":"Point"}
}