{
  "type": "Feature",
  "properties": {
    "iso:country":"US",
    "sg:address":"2345 Westervelt Ave",
    "sg:city":"Bronx",
    "sg:classifiers":[
        {
            "category":"Building & Trades",
            "subcategory":"Construction",
            "type":"Services"
        }
    ],
    "sg:phone":"+1 718 881 4224",
    "sg:postcode":"10469",
    "sg:province":"NY",
    "sg:tags":[
        "home",
        "improvement"
    ],
    "wof:name":"Prestige Builders",
    "wof:placetype":"venue"
},
  "geometry": {"coordinates":[-73.840035,40.860132],"type":"Point"}
}