{
  "type": "Feature",
  "properties": {
    "iso:country":"US",
    "sg:address":"557 E Fordham Rd",
    "sg:city":"Bronx",
    "sg:classifiers":[
        {
            "category":"Autos & Motor Vehicles",
            "subcategory":"Auto Supplies",
            "type":"Retail Goods"
        }
    ],
    "sg:phone":"+1 718 365 0495",
    "sg:postcode":"10458",
    "sg:province":"NY",
    "sg:tags":[
        "automobile",
        "stereo",
        "radio"
    ],
    "wof:name":"Extioc Auto Sounds",
    "wof:placetype":"venue"
},
  "geometry": {"coordinates":[-73.88673300000001,40.859255],"type":"Point"}
}