{
  "type": "Feature",
  "properties": {
    "iso:country":"US",
    "sg:address":"10 Northwood Rd",
    "sg:city":"Lake Placid",
    "sg:classifiers":[
        {
            "category":"Professional",
            "subcategory":"Management & Consulting",
            "type":"Services"
        }
    ],
    "sg:phone":"+1   ",
    "sg:postcode":"12946",
    "sg:province":"NY",
    "sg:tags":[
        "marketing",
        "communications"
    ],
    "wof:name":"Arrow Communications LLC",
    "wof:placetype":"venue"
},
  "geometry": {"coordinates":[-73.97212399999999,44.290639],"type":"Point"}
}