{
  "type": "Feature",
  "properties": {
    "addr:full":"47 Sunset Blvd Oneonta NY 13820",
    "addr:housenumber":"47",
    "addr:postcode":"13820",
    "addr:street":"Sunset Blvd",
    "iso:country":"US",
    "sg:address":"47 Sunset Blvd",
    "sg:city":"Oneonta",
    "sg:classifiers":[
        {
            "category":"Professional",
            "subcategory":"Lawyer & Legal Services",
            "type":"Services"
        }
    ],
    "sg:phone":"+1 607 433 1626",
    "sg:postcode":"13820",
    "sg:province":"NY",
    "sg:tags":[
        "attorney",
        "practice"
    ],
    "wof:name":"Kara Harmon Esq",
    "wof:placetype":"venue"
},
  "geometry": {"coordinates":[-75.018243,42.591892],"type":"Point"}
}