{
  "type": "Feature",
  "properties": {
    "addr:full":"81 Ashford Ave Dobbs Ferry NY 10522",
    "addr:housenumber":"81",
    "addr:postcode":"10522",
    "addr:street":"Ashford Ave",
    "iso:country":"US",
    "sg:address":"81 Ashford Ave",
    "sg:city":"Dobbs Ferry",
    "sg:classifiers":[
        {
            "category":"Local Transit",
            "type":"Transportation"
        }
    ],
    "sg:phone":"+1 914 693 3619",
    "sg:postcode":"10522",
    "sg:province":"NY",
    "sg:tags":[
        "ambulance"
    ],
    "wof:name":"Dobbs Ferry Ambulance Corp Inc",
    "wof:placetype":"venue"
},
  "geometry": {"coordinates":[-73.862737,41.014916],"type":"Point"}
}