{
  "type": "Feature",
  "properties": {
    "iso:country":"US",
    "sg:address":"1501 3rd Avenue",
    "sg:city":"New York",
    "sg:classifiers":[
        {
            "category":"Sports & Exercise",
            "subcategory":"Gym",
            "type":"Entertainment"
        }
    ],
    "sg:phone":"+1 212 696 0467",
    "sg:postcode":"10028",
    "sg:province":"NY",
    "sg:tags":[
        "trainer"
    ],
    "wof:name":"Lancercise",
    "wof:placetype":"venue"
},
  "geometry": {"coordinates":[-73.954904,40.777751],"type":"Point"}
}