{
  "type": "Feature",
  "properties": {
    "addr:full":"42 E 46th St New York NY 10017",
    "addr:housenumber":"42",
    "addr:postcode":"10017",
    "addr:street":"E 46Th St",
    "iso:country":"US",
    "sg:address":"42 E 46th St",
    "sg:city":"New York",
    "sg:classifiers":[
        {
            "category":"Shopping",
            "type":"Retail Goods"
        }
    ],
    "sg:phone":"+1   ",
    "sg:postcode":"10017",
    "sg:province":"NY",
    "sg:tags":[
        "phone",
        "cellular",
        "accessory"
    ],
    "wof:name":"Wireless Hub",
    "wof:placetype":"venue"
},
  "geometry": {"coordinates":[-73.976845,40.755071],"type":"Point"}
}