{
  "type": "Feature",
  "properties": {
    "addr:full":"2548B White Plains Rd Bronx NY 10467",
    "addr:housenumber":"2548b",
    "addr:postcode":"10467",
    "addr:street":"White Plains Rd",
    "iso:country":"US",
    "sg:address":"2548B White Plains Rd",
    "sg:city":"Bronx",
    "sg:classifiers":[
        {
            "category":"Shopping",
            "subcategory":"Pawn Shop",
            "type":"Retail Goods"
        }
    ],
    "sg:phone":"+1 718 324 2274",
    "sg:postcode":"10467",
    "sg:province":"NY",
    "wof:name":"Allerton Pawnbrokers & Jewelers",
    "wof:placetype":"venue"
},
  "geometry": {"coordinates":[-73.86726,40.863752],"type":"Point"}
}