{
  "type": "Feature",
  "properties": {
    "iso:country":"US",
    "sg:address":"16 Main St W",
    "sg:city":"Rochester",
    "sg:classifiers":[
        {
            "category":"Building & Trades",
            "subcategory":"Construction",
            "type":"Services"
        }
    ],
    "sg:phone":"+1 585 232 7305",
    "sg:postcode":"14614",
    "sg:province":"NY",
    "sg:tags":[
        "house"
    ],
    "wof:name":"Prestige General Contract",
    "wof:placetype":"venue"
},
  "geometry": {"coordinates":[-77.612945,43.155718],"type":"Point"}
}