{
  "type": "Feature",
  "properties": {
    "iso:country":"US",
    "sg:address":"34 Route 17K",
    "sg:city":"Newburgh",
    "sg:classifiers":[
        {
            "category":"Professional",
            "subcategory":"Lawyer & Legal Services",
            "type":"Services"
        }
    ],
    "sg:phone":"+1 845 562 3366",
    "sg:postcode":"12550",
    "sg:province":"NY",
    "sg:tags":[
        "personal",
        "injury"
    ],
    "wof:name":"Cooperstein Gordon E",
    "wof:placetype":"venue"
},
  "geometry": {"coordinates":[-74.05789900000001,41.503399],"type":"Point"}
}