{
  "type": "Feature",
  "properties": {
    "addr:full":"262 Smith St Brooklyn NY 11231",
    "addr:housenumber":"262",
    "addr:postcode":"11231",
    "addr:street":"Smith St",
    "iso:country":"US",
    "sg:address":"262 Smith St",
    "sg:city":"Brooklyn",
    "sg:classifiers":[
        {
            "category":"Real Estate",
            "subcategory":"Real Estate Agent",
            "type":"Services"
        }
    ],
    "sg:phone":"+1 718 625 9635",
    "sg:postcode":"11231",
    "sg:province":"NY",
    "wof:name":"Carroll Gardens Realty",
    "wof:placetype":"venue"
},
  "geometry": {"coordinates":[-73.99347899999999,40.682274],"type":"Point"}
}