{
  "type": "Feature",
  "properties": {
    "iso:country":"US",
    "sg:address":"145 Grove St",
    "sg:city":"Angola",
    "sg:classifiers":[
        {
            "category":"Building & Trades",
            "subcategory":"Construction",
            "type":"Services"
        }
    ],
    "sg:phone":"+1 716 549 0156",
    "sg:postcode":"14006",
    "sg:province":"NY",
    "sg:tags":[
        "contractor"
    ],
    "wof:name":"Strothmann Contracting",
    "wof:placetype":"venue"
},
  "geometry": {"coordinates":[-79.036682,42.635701],"type":"Point"}
}