{
  "type": "Feature",
  "properties": {
    "addr:full":"2324 Boston Rd Apt 15C Bronx NY 10467",
    "addr:housenumber":"2324",
    "addr:postcode":"10467",
    "addr:street":"Boston Rd Apt",
    "iso:country":"US",
    "sg:address":"2324 Boston Rd Apt 15C",
    "sg:city":"Bronx",
    "sg:classifiers":[
        {
            "category":"Building & Trades",
            "subcategory":"Construction",
            "type":"Services"
        }
    ],
    "sg:phone":"+1 347 964 6269",
    "sg:postcode":"10467",
    "sg:province":"NY",
    "sg:tags":[
        "contractor"
    ],
    "wof:name":"Feb General Contractors",
    "wof:placetype":"venue"
},
  "geometry": {"coordinates":[-73.867205,40.859933],"type":"Point"}
}