{
  "type": "Feature",
  "properties": {
    "addr:full":"28 Montcalm Ave Plattsburgh NY 12901",
    "addr:housenumber":"28",
    "addr:postcode":"12901",
    "addr:street":"Montcalm Ave",
    "iso:country":"US",
    "sg:address":"28 Montcalm Ave",
    "sg:city":"Plattsburgh",
    "sg:classifiers":[
        {
            "category":"Wholesale",
            "subcategory":"Medical Equipment & Supplies",
            "type":"Manufacturing & Wholesale Goods"
        }
    ],
    "sg:phone":"+1 518 563 1010",
    "sg:postcode":"12901",
    "sg:province":"NY",
    "sg:tags":[
        "hospital"
    ],
    "wof:name":"Condo Pharmacy",
    "wof:placetype":"venue"
},
  "geometry": {"coordinates":[-73.460505,44.700147],"type":"Point"}
}