{
  "type": "Feature",
  "properties": {
    "addr:full":"1250 Ocean Parkway Brooklyn NY 11230",
    "addr:housenumber":"1250",
    "addr:postcode":"11230",
    "addr:street":"Ocean Parkway",
    "iso:country":"US",
    "sg:address":"1250 Ocean Parkway",
    "sg:city":"Brooklyn",
    "sg:classifiers":[
        {
            "category":"Health Services",
            "subcategory":"Dentist",
            "type":"Services"
        }
    ],
    "sg:phone":"+1 718 648 5265",
    "sg:postcode":"11230",
    "sg:province":"NY",
    "sg:tags":[
        "orthodontist"
    ],
    "wof:name":"Shomer M Israelian D D S P C",
    "wof:placetype":"venue"
},
  "geometry": {"coordinates":[-73.969629,40.618165],"type":"Point"}
}