{
  "type": "Feature",
  "properties": {
    "addr:full":"33 Pioneer St Cooperstown NY 13326",
    "addr:housenumber":"33",
    "addr:postcode":"13326",
    "addr:street":"Pioneer St",
    "iso:country":"US",
    "sg:address":"33 Pioneer St",
    "sg:city":"Cooperstown",
    "sg:classifiers":[
        {
            "category":"Restaurant",
            "type":"Food & Drink"
        }
    ],
    "sg:phone":"+1 607 547 9609",
    "sg:postcode":"13326",
    "sg:province":"NY",
    "sg:tags":[
        "eating"
    ],
    "wof:name":"Short Stop Restaurant",
    "wof:placetype":"venue"
},
  "geometry": {"coordinates":[-74.924088,42.700851],"type":"Point"}
}