{
  "type": "Feature",
  "properties": {
    "addr:full":"475 Lexington Ave New York NY 10017",
    "addr:housenumber":"475",
    "addr:postcode":"10017",
    "addr:street":"Lexington Ave",
    "iso:country":"US",
    "sg:address":"475 Lexington Ave",
    "sg:city":"New York",
    "sg:classifiers":[
        {
            "category":"Communications",
            "subcategory":"Film & Video Production",
            "type":"Services"
        }
    ],
    "sg:phone":"+1 917 723 2627",
    "sg:postcode":"10017",
    "sg:province":"NY",
    "sg:tags":[
        "medium"
    ],
    "wof:name":"Urban City Media Inc",
    "wof:placetype":"venue"
},
  "geometry": {"coordinates":[-73.974648,40.753367],"type":"Point"}
}