{
  "type": "Feature",
  "properties": {
    "addr:full":"681 Brown St Rochester NY 14611",
    "addr:housenumber":"681",
    "addr:postcode":"14611",
    "addr:street":"Brown St",
    "iso:country":"US",
    "sg:address":"681 Brown St",
    "sg:city":"Rochester",
    "sg:classifiers":[
        {
            "category":"Real Estate",
            "subcategory":"Real Estate Operator",
            "type":"Services"
        }
    ],
    "sg:phone":"+1 585 436 3730",
    "sg:postcode":"14611",
    "sg:province":"NY",
    "sg:tags":[
        "building",
        "apartment"
    ],
    "wof:name":"Fairchild Place",
    "wof:placetype":"venue"
},
  "geometry": {"coordinates":[-77.633827,43.151852],"type":"Point"}
}