{
  "type": "Feature",
  "properties": {
    "addr:full":"2334 Route 6 Brewster NY 10509",
    "addr:housenumber":"2334",
    "addr:postcode":"10509",
    "addr:street":"Route 6",
    "iso:country":"US",
    "sg:address":"2334 Route 6",
    "sg:city":"Brewster",
    "sg:classifiers":[
        {
            "category":"Building & Trades",
            "subcategory":"Plumbing",
            "type":"Services"
        }
    ],
    "sg:phone":"+1 845 279 4414",
    "sg:postcode":"10509",
    "sg:province":"NY",
    "wof:name":"Dennis Palmer Plumbing & Heating Inc",
    "wof:placetype":"venue"
},
  "geometry": {"coordinates":[-73.638525,41.405645],"type":"Point"}
}