{
  "type": "Feature",
  "properties": {
    "iso:country":"US",
    "sg:address":"4619 30th Ave",
    "sg:city":"Astoria",
    "sg:classifiers":[
        {
            "category":"Restaurant",
            "type":"Food & Drink"
        }
    ],
    "sg:menulink":"http://www.allmenus.com/ny/queens/114326-dilliigers/menu/",
    "sg:phone":"+1 718 956 5601",
    "sg:postcode":"11103",
    "sg:province":"NY",
    "sg:tags":[
        "american"
    ],
    "wof:name":"Dilliigers",
    "wof:placetype":"venue"
},
  "geometry": {"coordinates":[-73.91004700000001,40.761568],"type":"Point"}
}