{
  "type": "Feature",
  "properties": {
    "iso:country":"US",
    "sg:address":"2148 Niagara Falls Blvd",
    "sg:city":"Tonawanda",
    "sg:classifiers":[
        {
            "category":"Professional",
            "subcategory":"Computer Services",
            "type":"Services"
        }
    ],
    "sg:phone":"+1 716 213 4444",
    "sg:postcode":"14150",
    "sg:province":"NY",
    "wof:name":"Quad B Systems LLC",
    "wof:placetype":"venue"
},
  "geometry": {"coordinates":[-78.822335,43.014016],"type":"Point"}
}