{
  "type": "Feature",
  "properties": {
    "iso:country":"US",
    "sg:address":"4242 11th Street",
    "sg:city":"Long Island City",
    "sg:classifiers":[
        {
            "category":"Restaurant",
            "type":"Food & Drink"
        }
    ],
    "sg:phone":"+1 718 361 1696",
    "sg:postcode":"11101",
    "sg:province":"NY",
    "wof:name":"Caviateria",
    "wof:placetype":"venue"
},
  "geometry": {"coordinates":[-73.94784,40.75225],"type":"Point"}
}