{
  "type": "Feature",
  "properties": {
    "iso:country":"US",
    "sg:address":"5001 Genesee Street",
    "sg:city":"Buffalo",
    "sg:classifiers":[
        {
            "category":"Professional",
            "subcategory":"Computer Services",
            "type":"Services"
        }
    ],
    "sg:phone":"+1 877 787 7666",
    "sg:postcode":"14225",
    "sg:province":"NY",
    "sg:tags":[
        "upstate-ny"
    ],
    "sg:website":"http://www.pureroom.com",
    "wof:name":"Pure Solutions",
    "wof:placetype":"venue"
},
  "geometry": {"coordinates":[-78.70246,42.936978],"type":"Point"}
}