{
  "type": "Feature",
  "properties": {
    "addr:full":"195 Granite Ave Staten Island NY 10303",
    "addr:housenumber":"195",
    "addr:postcode":"10303",
    "addr:street":"Granite Ave",
    "iso:country":"US",
    "sg:address":"195 Granite Ave",
    "sg:city":"Staten Island",
    "sg:classifiers":[
        {
            "category":"Building & Trades",
            "subcategory":"Landscaping Services",
            "type":"Services"
        }
    ],
    "sg:phone":"+1 718 448 7568",
    "sg:postcode":"10303",
    "sg:province":"NY",
    "sg:tags":[
        "landscape",
        "maintenance",
        "contractor"
    ],
    "wof:name":"Loffreno Landscaping & Lawn",
    "wof:placetype":"venue"
},
  "geometry": {"coordinates":[-74.148785,40.63171],"type":"Point"}
}