{
  "type": "Feature",
  "properties": {
    "iso:country":"US",
    "sg:address":"26 E Montauk Hwy",
    "sg:city":"Hampton Bays",
    "sg:classifiers":[
        {
            "category":"Restaurant",
            "type":"Food & Drink"
        }
    ],
    "sg:phone":"+1 631 723 2626",
    "sg:postcode":"11946",
    "sg:province":"NY",
    "wof:name":"J T's Place",
    "wof:placetype":"venue"
},
  "geometry": {"coordinates":[-72.521979,40.878524],"type":"Point"}
}