{
  "type": "Feature",
  "properties": {
    "addr:full":"100 Madison St Syracuse NY 13202",
    "addr:housenumber":"100",
    "addr:postcode":"13202",
    "addr:street":"Madison St",
    "iso:country":"US",
    "sg:address":"100 Madison St",
    "sg:city":"Syracuse",
    "sg:classifiers":[
        {
            "category":"Professional",
            "subcategory":"Lawyer & Legal Services",
            "type":"Services"
        }
    ],
    "sg:phone":"+1 315 474 6448",
    "sg:postcode":"13202",
    "sg:province":"NY",
    "sg:tags":[
        "litigation",
        "tort",
        "attorney"
    ],
    "wof:name":"Stewart , David M. - Byrne, Costello & P",
    "wof:placetype":"venue"
},
  "geometry": {"coordinates":[-76.150841,43.04549],"type":"Point"}
}