{
  "type": "Feature",
  "properties": {
    "iso:country":"US",
    "sg:address":"35 Burlington Ave",
    "sg:city":"Mechanicville",
    "sg:classifiers":[
        {
            "category":"Restaurant",
            "type":"Food & Drink"
        }
    ],
    "sg:phone":"+1 518 899 6000",
    "sg:postcode":"12151",
    "sg:province":"NY",
    "wof:name":"Lake Ridge Restaurant",
    "wof:placetype":"venue"
},
  "geometry": {"coordinates":[-73.795062,42.938319],"type":"Point"}
}