{
  "type": "Feature",
  "properties": {
    "addr:full":"3215 Broadway St Buffalo NY 14227",
    "addr:housenumber":"3215",
    "addr:postcode":"14227",
    "addr:street":"Broadway St",
    "iso:country":"US",
    "sg:address":"3215 Broadway St",
    "sg:city":"Buffalo",
    "sg:classifiers":[
        {
            "category":"Retail",
            "subcategory":"Laundry & Dry Cleaning",
            "type":"Services"
        }
    ],
    "sg:phone":"+1 716 683 5479",
    "sg:postcode":"14227",
    "sg:province":"NY",
    "sg:tags":[
        "uniform",
        "supply"
    ],
    "wof:name":"Aramark Uniform Svc Inc",
    "wof:placetype":"venue"
},
  "geometry": {"coordinates":[-78.761651,42.902766],"type":"Point"}
}