{
  "type": "Feature",
  "properties": {
    "addr:full":"957 Kings Hwy Saugerties NY 12477",
    "addr:housenumber":"957",
    "addr:postcode":"12477",
    "addr:street":"Kings Hwy",
    "iso:country":"US",
    "sg:address":"957 Kings Hwy",
    "sg:city":"Saugerties",
    "sg:classifiers":[
        {
            "category":"Retail",
            "subcategory":"Animal Services",
            "type":"Services"
        }
    ],
    "sg:phone":"+1 845 246 9540",
    "sg:postcode":"12477",
    "sg:province":"NY",
    "sg:tags":[
        "breeder",
        "horse"
    ],
    "wof:name":"J M Stables Inc",
    "wof:placetype":"venue"
},
  "geometry": {"coordinates":[-73.97956000000001,42.050647],"type":"Point"}
}