{
  "type": "Feature",
  "properties": {
    "addr:full":"3418 Northern Boulevard Long Island City NY 11101",
    "addr:housenumber":"3418",
    "addr:postcode":"11101",
    "addr:street":"Northern Boulevard",
    "iso:country":"US",
    "sg:address":"3418 Northern Boulevard",
    "sg:city":"Long Island City",
    "sg:classifiers":[
        {
            "category":"Retail",
            "subcategory":"Portrait Studio",
            "type":"Services"
        },
        {
            "category":"Professional",
            "subcategory":"Art Services",
            "type":"Services"
        }
    ],
    "sg:phone":"+1 718 472 2382",
    "sg:postcode":"11101",
    "sg:province":"NY",
    "sg:tags":[
        "photographer",
        "photography",
        "store"
    ],
    "wof:name":"Slotnick Jeff Studio",
    "wof:placetype":"venue"
},
  "geometry": {"coordinates":[-73.929884,40.751995],"type":"Point"}
}