{
  "type": "Feature",
  "properties": {
    "iso:country":"US",
    "sg:address":"70 Pondfield Rd",
    "sg:city":"Bronxville",
    "sg:classifiers":[
        {
            "category":"Shopping",
            "subcategory":"Clothing, Apparel, & Fashions",
            "type":"Retail Goods"
        }
    ],
    "sg:phone":"+1 914 793 0737",
    "sg:postcode":"10708",
    "sg:province":"NY",
    "sg:tags":[
        "boutique",
        "woman"
    ],
    "wof:name":"Toney Toni Bronxville Inc",
    "wof:placetype":"venue"
},
  "geometry": {"coordinates":[-73.833285,40.94004],"type":"Point"}
}