{
  "type": "Feature",
  "properties": {
    "addr:full":"91 Broadway Greenlawn NY 11740",
    "addr:housenumber":"91",
    "addr:postcode":"11740",
    "addr:street":"Broadway",
    "iso:country":"US",
    "sg:address":"91 Broadway",
    "sg:city":"Greenlawn",
    "sg:classifiers":[
        {
            "category":"Restaurant",
            "type":"Food & Drink"
        }
    ],
    "sg:phone":"+1 631 754 6263",
    "sg:postcode":"11740",
    "sg:province":"NY",
    "sg:tags":[
        "pizza"
    ],
    "wof:name":"Jimmy's Pizza",
    "wof:placetype":"venue"
},
  "geometry": {"coordinates":[-73.364403,40.866299],"type":"Point"}
}