{
  "type": "Feature",
  "properties": {
    "addr:full":"3337 Montrose Tpke Owego NY 13827",
    "addr:housenumber":"3337",
    "addr:postcode":"13827",
    "addr:street":"Montrose Tpke",
    "iso:country":"US",
    "sg:address":"3337 Montrose Tpke",
    "sg:city":"Owego",
    "sg:classifiers":[
        {
            "category":"Farming",
            "subcategory":"Dairy Farm",
            "type":"Manufacturing & Wholesale Goods"
        }
    ],
    "sg:phone":"+1 607 687 3318",
    "sg:postcode":"13827",
    "sg:province":"NY",
    "wof:name":"Klett Farm",
    "wof:placetype":"venue"
},
  "geometry": {"coordinates":[-76.25596400000001,42.0872],"type":"Point"}
}