{
  "type": "Feature",
  "properties": {
    "iso:country":"US",
    "sg:address":"17 E 45th St",
    "sg:city":"New York",
    "sg:classifiers":[
        {
            "category":"Shopping",
            "subcategory":"Discount & Variety Stores",
            "type":"Retail Goods"
        }
    ],
    "sg:phone":"+1 888 791 5600",
    "sg:postcode":"10017",
    "sg:province":"NY",
    "sg:tags":[
        "outlet"
    ],
    "wof:name":"World Outlet Inc",
    "wof:placetype":"venue"
},
  "geometry": {"coordinates":[-73.977808,40.754855],"type":"Point"}
}