{
  "type": "Feature",
  "properties": {
    "addr:full":"151 E 151st St Bronx NY 10451",
    "addr:housenumber":"151",
    "addr:postcode":"10451",
    "addr:street":"E 151St St",
    "iso:country":"US",
    "sg:address":"151 E 151st St",
    "sg:city":"Bronx",
    "sg:classifiers":[
        {
            "category":"Building & Trades",
            "subcategory":"Construction",
            "type":"Services"
        }
    ],
    "sg:phone":"+1 718 292 9079",
    "sg:postcode":"10451",
    "sg:province":"NY",
    "sg:tags":[
        "contractor"
    ],
    "wof:name":"Calcedo Construction",
    "wof:placetype":"venue"
},
  "geometry": {"coordinates":[-73.927333,40.82119],"type":"Point"}
}