{
  "type": "Feature",
  "properties": {
    "iso:country":"US",
    "sg:address":"349 N Greeley Ave",
    "sg:city":"Chappaqua",
    "sg:classifiers":[
        {
            "category":"Shopping",
            "subcategory":"Stationery & Office Supplies",
            "type":"Retail Goods"
        }
    ],
    "sg:phone":"+1 914 238 0373",
    "sg:postcode":"10514",
    "sg:province":"NY",
    "wof:name":"Chrysler Office Supplies",
    "wof:placetype":"venue"
},
  "geometry": {"coordinates":[-73.767759,41.165708],"type":"Point"}
}