{
  "type": "Feature",
  "properties": {
    "addr:full":"3135 Perry Ave Bronx NY 10467",
    "addr:housenumber":"3135",
    "addr:postcode":"10467",
    "addr:street":"Perry Ave",
    "iso:country":"US",
    "sg:address":"3135 Perry Ave",
    "sg:city":"Bronx",
    "sg:classifiers":[
        {
            "category":"Building & Trades",
            "subcategory":"Construction",
            "type":"Services"
        }
    ],
    "sg:phone":"+1 718 547 7578",
    "sg:postcode":"10467",
    "sg:province":"NY",
    "sg:tags":[
        "house"
    ],
    "wof:name":"Noeth East Construction C",
    "wof:placetype":"venue"
},
  "geometry": {"coordinates":[-73.877932,40.873726],"type":"Point"}
}