{
  "type": "Feature",
  "properties": {
    "addr:full":"138 Railroad Ave Pearl River NY 10965",
    "addr:housenumber":"138",
    "addr:postcode":"10965",
    "addr:street":"Railroad Ave",
    "iso:country":"US",
    "sg:address":"138 Railroad Ave",
    "sg:city":"Pearl River",
    "sg:classifiers":[
        {
            "category":"Building & Trades",
            "subcategory":"Construction",
            "type":"Services"
        }
    ],
    "sg:phone":"+1 845 733 1051",
    "sg:postcode":"10965",
    "sg:province":"NY",
    "sg:tags":[
        "contractor"
    ],
    "wof:name":"D B C Glass Mirror",
    "wof:placetype":"venue"
},
  "geometry": {"coordinates":[-74.022775,41.061424],"type":"Point"}
}