{
  "type": "Feature",
  "properties": {
    "addr:full":"88 10 Ave New York NY 10011",
    "addr:postcode":"10011",
    "addr:street":"10 Ave",
    "iso:country":"US",
    "sg:address":"88 10 Ave",
    "sg:city":"New York",
    "sg:classifiers":[
        {
            "category":"Real Estate",
            "subcategory":"Real Estate Agent",
            "type":"Services"
        }
    ],
    "sg:phone":"+1 212 243 6005",
    "sg:postcode":"10011",
    "sg:province":"NY",
    "sg:tags":[
        "manager"
    ],
    "wof:name":"Atc Management",
    "wof:placetype":"venue"
},
  "geometry": {"coordinates":[-74.007705,40.742833],"type":"Point"}
}