{
  "type": "Feature",
  "properties": {
    "addr:full":"274 Meserole St Brooklyn NY 11206",
    "addr:housenumber":"274",
    "addr:postcode":"11206",
    "addr:street":"Meserole St",
    "iso:country":"US",
    "sg:address":"274 Meserole St",
    "sg:city":"Brooklyn",
    "sg:classifiers":[
        {
            "category":"Wholesale",
            "subcategory":"Durable Goods & Equipment",
            "type":"Manufacturing & Wholesale Goods"
        }
    ],
    "sg:phone":"+1 718 386 8872",
    "sg:postcode":"11206",
    "sg:province":"NY",
    "sg:tags":[
        "importer"
    ],
    "wof:name":"Ying International Corp",
    "wof:placetype":"venue"
},
  "geometry": {"coordinates":[-73.938022,40.708469],"type":"Point"}
}