{
  "type": "Feature",
  "properties": {
    "iso:country":"US",
    "sg:address":"1955 Turnbull Ave",
    "sg:city":"Bronx",
    "sg:classifiers":[
        {
            "category":"Personal",
            "subcategory":"Barber",
            "type":"Services"
        }
    ],
    "sg:phone":"+1   ",
    "sg:postcode":"10473",
    "sg:province":"NY",
    "sg:tags":[
        "shop"
    ],
    "wof:name":"J & R Barber Shop Unisex",
    "wof:placetype":"venue"
},
  "geometry": {"coordinates":[-73.856358,40.823083],"type":"Point"}
}