{
  "type": "Feature",
  "properties": {
    "iso:country":"US",
    "sg:address":"4 Midland Ave",
    "sg:city":"Hicksville",
    "sg:classifiers":[
        {
            "category":"Professional",
            "subcategory":"Business Services",
            "type":"Services"
        }
    ],
    "sg:phone":"+1 516 942 0861",
    "sg:postcode":"11801",
    "sg:province":"NY",
    "sg:tags":[
        "delivery",
        "courier"
    ],
    "wof:name":"Jet Transport Inc",
    "wof:placetype":"venue"
},
  "geometry": {"coordinates":[-73.51840199999999,40.773701],"type":"Point"}
}