{
  "type": "Feature",
  "properties": {
    "addr:full":"22 Washington St Ellicottville NY 14731",
    "addr:housenumber":"22",
    "addr:postcode":"14731",
    "addr:street":"Washington St",
    "iso:country":"US",
    "sg:address":"22 Washington St",
    "sg:city":"Ellicottville",
    "sg:classifiers":[
        {
            "category":"Home & Garden",
            "subcategory":"Home Furnishings",
            "type":"Retail Goods"
        }
    ],
    "sg:phone":"+1   ",
    "sg:postcode":"14731",
    "sg:province":"NY",
    "wof:name":"One of A Kind",
    "wof:placetype":"venue"
},
  "geometry": {"coordinates":[-78.672276,42.275352],"type":"Point"}
}