{
  "type": "Feature",
  "properties": {
    "addr:full":"1501 Bellmore Rd North Bellmore NY 11710",
    "addr:housenumber":"1501",
    "addr:postcode":"11710",
    "addr:street":"Bellmore Rd",
    "iso:country":"US",
    "sg:address":"1501 Bellmore Rd",
    "sg:city":"North Bellmore",
    "sg:classifiers":[
        {
            "category":"Building & Trades",
            "subcategory":"Construction",
            "type":"Services"
        }
    ],
    "sg:phone":"+1 516 826 1908",
    "sg:postcode":"11710",
    "sg:province":"NY",
    "sg:tags":[
        "contractor"
    ],
    "wof:name":"Canbridge Construction",
    "wof:placetype":"venue"
},
  "geometry": {"coordinates":[-73.533621,40.684369],"type":"Point"}
}