{
  "type": "Feature",
  "properties": {
    "addr:full":"8822 3rd Ave Brooklyn NY 11209",
    "addr:housenumber":"8822",
    "addr:postcode":"11209",
    "addr:street":"3Rd Ave",
    "iso:country":"US",
    "sg:address":"8822 3rd Ave",
    "sg:city":"Brooklyn",
    "sg:classifiers":[
        {
            "category":"Professional",
            "type":"Services"
        },
        {
            "category":"Restaurant",
            "type":"Food & Drink"
        }
    ],
    "sg:phone":"+1 718 833 9855",
    "sg:postcode":"11209",
    "sg:province":"NY",
    "sg:tags":[
        "style",
        "family",
        "seafood",
        "traditional",
        "american",
        "caterer"
    ],
    "sg:website":"chadwicksny.com",
    "wof:name":"Chadwick's",
    "wof:placetype":"venue"
},
  "geometry": {"coordinates":[-74.03171500000001,40.621894],"type":"Point"}
}