{
  "type": "Feature",
  "properties": {
    "addr:full":"4037 Broadway New York NY 10032",
    "addr:housenumber":"4037",
    "addr:postcode":"10032",
    "addr:street":"Broadway",
    "iso:country":"US",
    "sg:address":"4037 Broadway",
    "sg:city":"New York",
    "sg:classifiers":[
        {
            "category":"Deli",
            "type":"Food & Drink"
        }
    ],
    "sg:menulink":"http://www.allmenus.com/ny/new-york/251928-gristedes/menu/",
    "sg:phone":"+1 212 923 2333",
    "sg:postcode":"10032",
    "sg:province":"NY",
    "sg:tags":[
        "american"
    ],
    "wof:name":"Gristedes",
    "wof:placetype":"venue"
},
  "geometry": {"coordinates":[-73.939258,40.842375],"type":"Point"}
}