{
  "type": "Feature",
  "properties": {
    "addr:full":"1850 Front St East Meadow NY 11554",
    "addr:housenumber":"1850",
    "addr:postcode":"11554",
    "addr:street":"Front St",
    "iso:country":"US",
    "sg:address":"1850 Front St",
    "sg:city":"East Meadow",
    "sg:classifiers":[
        {
            "category":"Shopping",
            "subcategory":"Pharmacy",
            "type":"Retail Goods"
        }
    ],
    "sg:phone":"+1 516 485 2972",
    "sg:postcode":"11554",
    "sg:province":"NY",
    "wof:name":"Prescription Hdq East Meadow",
    "wof:placetype":"venue"
},
  "geometry": {"coordinates":[-73.564441,40.71967],"type":"Point"}
}