{
  "type": "Feature",
  "properties": {
    "iso:country":"US",
    "sg:address":"828 S Broadway",
    "sg:city":"Tarrytown",
    "sg:classifiers":[
        {
            "category":"Wholesale",
            "subcategory":"Office Equipment",
            "type":"Manufacturing & Wholesale Goods"
        }
    ],
    "sg:phone":"+1 914 631 7900",
    "sg:postcode":"10591",
    "sg:province":"NY",
    "wof:name":"Facsimile Communications Inds",
    "wof:placetype":"venue"
},
  "geometry": {"coordinates":[-73.86112,41.048705],"type":"Point"}
}