{
  "type": "Feature",
  "properties": {
    "iso:country":"US",
    "sg:address":"2 Spear St",
    "sg:city":"Nyack",
    "sg:classifiers":[
        {
            "category":"Restaurant",
            "type":"Food & Drink"
        }
    ],
    "sg:phone":"+1 845 353 7733",
    "sg:postcode":"10960",
    "sg:province":"NY",
    "sg:website":"http://www.lenasrestaurant.com",
    "wof:name":"Lena's Restaurant",
    "wof:placetype":"venue"
},
  "geometry": {"coordinates":[-73.916359,41.08968],"type":"Point"}
}