{
  "type": "Feature",
  "properties": {
    "iso:country":"US",
    "sg:address":"284 Jerusalem Ave",
    "sg:city":"Hempstead",
    "sg:classifiers":[
        {
            "category":"Autos & Motor Vehicles",
            "subcategory":"Fuel & Gas Station",
            "type":"Retail Goods"
        }
    ],
    "sg:phone":"+1 516 279 4848",
    "sg:postcode":"11550",
    "sg:province":"NY",
    "wof:name":"Jorge Auto Service",
    "wof:placetype":"venue"
},
  "geometry": {"coordinates":[-73.607112,40.702241],"type":"Point"}
}