{
  "type": "Feature",
  "properties": {
    "addr:full":"349 Waverly Ave Brooklyn NY 11238",
    "addr:housenumber":"349",
    "addr:postcode":"11238",
    "addr:street":"Waverly Ave",
    "iso:country":"US",
    "sg:address":"349 Waverly Ave",
    "sg:city":"Brooklyn",
    "sg:classifiers":[
        {
            "category":"Retail",
            "subcategory":"Laundry & Dry Cleaning",
            "type":"Services"
        }
    ],
    "sg:phone":"+1 718 789 9737",
    "sg:postcode":"11238",
    "sg:province":"NY",
    "sg:tags":[
        "cleaner"
    ],
    "wof:name":"Brothers Cleaners",
    "wof:placetype":"venue"
},
  "geometry": {"coordinates":[-73.966499,40.6866],"type":"Point"}
}