{
  "type": "Feature",
  "properties": {
    "iso:country":"US",
    "sg:address":"185 Delaware St",
    "sg:city":"Tonawanda",
    "sg:classifiers":[
        {
            "category":"Wholesale",
            "subcategory":"Plants",
            "type":"Manufacturing & Wholesale Goods"
        }
    ],
    "sg:phone":"+1 716 693 5800",
    "sg:postcode":"14150",
    "sg:province":"NY",
    "sg:tags":[
        "florist"
    ],
    "sg:website":"www.dickmillerflorist.com",
    "wof:name":"Dick Miller Florist",
    "wof:placetype":"venue"
},
  "geometry": {"coordinates":[-78.873217,43.015041],"type":"Point"}
}