{
  "type": "Feature",
  "properties": {
    "addr:full":"45 Whittier Ave Medford NY 11763",
    "addr:housenumber":"45",
    "addr:postcode":"11763",
    "addr:street":"Whittier Ave",
    "iso:country":"US",
    "sg:address":"45 Whittier Ave",
    "sg:city":"Medford",
    "sg:classifiers":[
        {
            "category":"Home & Garden",
            "subcategory":"Carpets & Floor Coverings",
            "type":"Retail Goods"
        }
    ],
    "sg:phone":"+1 631 732 4904",
    "sg:postcode":"11763",
    "sg:province":"NY",
    "sg:tags":[
        "hardwood",
        "flooring",
        "contractor"
    ],
    "wof:name":"Mario Acquaviva Flooring",
    "wof:placetype":"venue"
},
  "geometry": {"coordinates":[-73.00305899999999,40.836231],"type":"Point"}
}