{
  "type": "Feature",
  "properties": {
    "addr:full":"175 Hooker Ave Poughkeepsie NY 12603",
    "addr:housenumber":"175",
    "addr:postcode":"12603",
    "addr:street":"Hooker Ave",
    "iso:country":"US",
    "sg:address":"175 Hooker Ave",
    "sg:city":"Poughkeepsie",
    "sg:classifiers":[
        {
            "category":"Wholesale",
            "subcategory":"Office Equipment",
            "type":"Manufacturing & Wholesale Goods"
        },
        {
            "category":"Shopping",
            "type":"Retail Goods"
        }
    ],
    "sg:phone":"+1 845 454 4171",
    "sg:postcode":"12603",
    "sg:province":"NY",
    "sg:tags":[
        "machine",
        "copying",
        "duplicating",
        "business",
        "supply"
    ],
    "sg:website":"www.allstatebusiness.com",
    "wof:name":"All State Business Systems Inc",
    "wof:placetype":"venue"
},
  "geometry": {"coordinates":[-73.916195,41.688821],"type":"Point"}
}