{
  "type": "Feature",
  "properties": {
    "addr:full":"1201 US Highway 9 #1207 Wappingers Falls NY 12590",
    "addr:housenumber":"1201",
    "addr:postcode":"12590",
    "addr:street":"Us Highway 9 # 1207",
    "iso:country":"US",
    "sg:address":"1201 US Highway 9 #1207",
    "sg:city":"Wappingers Falls",
    "sg:classifiers":[
        {
            "category":"Home & Garden",
            "subcategory":"Building Materials",
            "type":"Retail Goods"
        }
    ],
    "sg:phone":"+1 845 298 3400",
    "sg:postcode":"12590",
    "sg:province":"NY",
    "sg:tags":[
        "supply"
    ],
    "wof:name":"Home Depot the",
    "wof:placetype":"venue"
},
  "geometry": {"coordinates":[-73.912626,41.612006],"type":"Point"}
}