{
  "type": "Feature",
  "properties": {
    "addr:full":"125 W Milton Rd Ballston Spa NY 12020",
    "addr:housenumber":"125",
    "addr:postcode":"12020",
    "addr:street":"W Milton Rd",
    "iso:country":"US",
    "sg:address":"125 W Milton Rd",
    "sg:city":"Ballston Spa",
    "sg:classifiers":[
        {
            "category":"Building & Trades",
            "subcategory":"Landscaping Services",
            "type":"Services"
        }
    ],
    "sg:phone":"+1 518 885 0983",
    "sg:postcode":"12020",
    "sg:province":"NY",
    "wof:name":"Newmans Lawn Landscape",
    "wof:placetype":"venue"
},
  "geometry": {"coordinates":[-73.927746,43.03206],"type":"Point"}
}