{
  "type": "Feature",
  "properties": {
    "addr:full":"39 Saint James St Kingston NY 12401",
    "addr:housenumber":"39",
    "addr:postcode":"12401",
    "addr:street":"Saint James St",
    "iso:country":"US",
    "sg:address":"39 Saint James St",
    "sg:city":"Kingston",
    "sg:classifiers":[
        {
            "category":"Autos & Motor Vehicles",
            "subcategory":"Auto Supplies",
            "type":"Retail Goods"
        }
    ],
    "sg:phone":"+1 845 331 3800",
    "sg:postcode":"12401",
    "sg:province":"NY",
    "sg:tags":[
        "automobile",
        "part"
    ],
    "wof:name":"Usa Datanet Corp",
    "wof:placetype":"venue"
},
  "geometry": {"coordinates":[-74.013169,41.931336],"type":"Point"}
}