{
  "type": "Feature",
  "properties": {
    "iso:country":"US",
    "sg:address":"261 Gravesville Rd",
    "sg:city":"Poland",
    "sg:classifiers":[
        {
            "category":"Shopping",
            "subcategory":"Discount & Variety Stores",
            "type":"Retail Goods"
        }
    ],
    "sg:phone":"+1   ",
    "sg:postcode":"13431",
    "sg:province":"NY",
    "sg:tags":[
        "merchandise",
        "general"
    ],
    "wof:name":"Gravesville Store",
    "wof:placetype":"venue"
},
  "geometry": {"coordinates":[-75.134894,43.251101],"type":"Point"}
}