{
  "type": "Feature",
  "properties": {
    "addr:full":"141-19 Rockaway Blvd Jamaica NY 11436",
    "addr:housenumber":"141-19",
    "addr:postcode":"11436",
    "addr:street":"Rockaway Blvd",
    "iso:country":"US",
    "sg:address":"141-19 Rockaway Blvd",
    "sg:city":"Jamaica",
    "sg:classifiers":[
        {
            "category":"Personal",
            "subcategory":"Beauty Salon",
            "type":"Services"
        }
    ],
    "sg:phone":"+1 347 238 1602",
    "sg:postcode":"11436",
    "sg:province":"NY",
    "sg:tags":[
        "hair"
    ],
    "sg:website":"www.offdahooksalon.com",
    "wof:name":"Off Da Hook Salon",
    "wof:placetype":"venue"
},
  "geometry": {"coordinates":[-73.79907300000001,40.674356],"type":"Point"}
}