{
  "type": "Feature",
  "properties": {
    "iso:country":"US",
    "sg:address":"248 E 73rd Street",
    "sg:city":"New York",
    "sg:classifiers":[
        {
            "category":"Health Services",
            "subcategory":"Health Practitioner",
            "type":"Services"
        },
        {
            "category":"Personal",
            "subcategory":"Day Spa",
            "type":"Services"
        }
    ],
    "sg:phone":"+1 212 744 9949",
    "sg:postcode":"10021",
    "sg:province":"NY",
    "sg:tags":[
        "acupuncture"
    ],
    "wof:name":"Satori Holistic Center and Spa",
    "wof:placetype":"venue"
},
  "geometry": {"coordinates":[-73.959142,40.769885],"type":"Point"}
}