{
  "type": "Feature",
  "properties": {
    "addr:full":"76 W 225th St Bronx NY 10463",
    "addr:housenumber":"76",
    "addr:postcode":"10463",
    "addr:street":"W 225Th St",
    "iso:country":"US",
    "sg:address":"76 W 225th St",
    "sg:city":"Bronx",
    "sg:classifiers":[
        {
            "category":"Building & Trades",
            "subcategory":"Construction",
            "type":"Services"
        }
    ],
    "sg:phone":"+1 718 220 0051",
    "sg:postcode":"10463",
    "sg:province":"NY",
    "sg:tags":[
        "general",
        "contractor"
    ],
    "wof:name":"Control Construction",
    "wof:placetype":"venue"
},
  "geometry": {"coordinates":[-73.90696199999999,40.873368],"type":"Point"}
}