{
  "type": "Feature",
  "properties": {
    "addr:full":"347 E 105th St Frnt New York NY 10029",
    "addr:housenumber":"347",
    "addr:postcode":"10029",
    "addr:street":"E 105Th St",
    "iso:country":"US",
    "sg:address":"347 E 105th St Frnt",
    "sg:city":"New York",
    "sg:classifiers":[
        {
            "category":"Organizations",
            "subcategory":"Religious Organization",
            "type":"Services"
        }
    ],
    "sg:phone":"+1 212 427 7955",
    "sg:postcode":"10029",
    "sg:province":"NY",
    "wof:name":"The Glory of Lebanon",
    "wof:placetype":"venue"
},
  "geometry": {"coordinates":[-73.94180299999999,40.789501],"type":"Point"}
}