{
  "type": "Feature",
  "properties": {
    "addr:full":"10 Stanton St New York NY 10002",
    "addr:housenumber":"10",
    "addr:postcode":"10002",
    "addr:street":"Stanton St",
    "iso:country":"US",
    "sg:address":"10 Stanton St",
    "sg:city":"New York",
    "sg:classifiers":[
        {
            "category":"Real Estate",
            "subcategory":"Real Estate Agent",
            "type":"Services"
        }
    ],
    "sg:phone":"+1 212 420 1733",
    "sg:postcode":"10002",
    "sg:province":"NY",
    "wof:name":"Mereda Realty Corp",
    "wof:placetype":"venue"
},
  "geometry": {"coordinates":[-73.991986,40.72261],"type":"Point"}
}