{
  "type": "Feature",
  "properties": {
    "iso:country":"US",
    "sg:address":"42 Merrick Ave",
    "sg:city":"Merrick",
    "sg:classifiers":[
        {
            "category":"Shopping",
            "subcategory":"Clothing, Apparel, & Fashions",
            "type":"Retail Goods"
        }
    ],
    "sg:phone":"+1 516 771 9124",
    "sg:postcode":"11566",
    "sg:province":"NY",
    "sg:tags":[
        "swimwear",
        "accessory"
    ],
    "wof:name":"Hobieswim Shop",
    "wof:placetype":"venue"
},
  "geometry": {"coordinates":[-73.552542,40.664625],"type":"Point"}
}