{
  "type": "Feature",
  "properties": {
    "addr:full":"24 S Main St Churchville NY 14428",
    "addr:housenumber":"24",
    "addr:postcode":"14428",
    "addr:street":"S Main St",
    "iso:country":"US",
    "sg:address":"24 S Main St",
    "sg:city":"Churchville",
    "sg:classifiers":[
        {
            "category":"Shopping",
            "subcategory":"Florist",
            "type":"Retail Goods"
        }
    ],
    "sg:phone":"+1   ",
    "sg:postcode":"14428",
    "sg:province":"NY",
    "wof:name":"A Touch of Country Class",
    "wof:placetype":"venue"
},
  "geometry": {"coordinates":[-77.88459,43.103851],"type":"Point"}
}