{
  "type": "Feature",
  "properties": {
    "addr:full":"16 Brunson Way Penfield NY 14526",
    "addr:housenumber":"16",
    "addr:postcode":"14526",
    "addr:street":"Brunson Way",
    "iso:country":"US",
    "sg:address":"16 Brunson Way",
    "sg:city":"Penfield",
    "sg:classifiers":[
        {
            "category":"Insurance",
            "subcategory":"Hazard Insurance",
            "type":"Services"
        }
    ],
    "sg:phone":"+1 585 598 3056",
    "sg:postcode":"14526",
    "sg:province":"NY",
    "wof:name":"State Farm Insurance",
    "wof:placetype":"venue"
},
  "geometry": {"coordinates":[-77.449806,43.120071],"type":"Point"}
}