{
  "type": "Feature",
  "properties": {
    "iso:country":"US",
    "sg:address":"642 Abeel St",
    "sg:city":"Kingston",
    "sg:classifiers":[
        {
            "category":"Wholesale",
            "subcategory":"Scrap",
            "type":"Manufacturing & Wholesale Goods"
        }
    ],
    "sg:phone":"+1 845 331 3312",
    "sg:postcode":"12401",
    "sg:province":"NY",
    "sg:tags":[
        "material"
    ],
    "wof:name":"Kingston Recycling Inc",
    "wof:placetype":"venue"
},
  "geometry": {"coordinates":[-74.004802,41.907117],"type":"Point"}
}