{
  "type": "Feature",
  "properties": {
    "addr:full":"3443 Clifton Blvd Wantagh NY 11793",
    "addr:housenumber":"3443",
    "addr:postcode":"11793",
    "addr:street":"Clifton Blvd",
    "iso:country":"US",
    "sg:address":"3443 Clifton Blvd",
    "sg:city":"Wantagh",
    "sg:classifiers":[
        {
            "category":"Restaurant",
            "type":"Food & Drink"
        }
    ],
    "sg:phone":"+1 516 292 7200",
    "sg:postcode":"11793",
    "sg:province":"NY",
    "sg:tags":[
        "delicatessen"
    ],
    "wof:name":"Masone's Family Market Place",
    "wof:placetype":"venue"
},
  "geometry": {"coordinates":[-73.50700999999999,40.676944],"type":"Point"}
}