{
  "type": "Feature",
  "properties": {
    "addr:full":"1663 Central Ave Albany NY 12205",
    "addr:housenumber":"1663",
    "addr:postcode":"12205",
    "addr:street":"Central Ave",
    "iso:country":"US",
    "sg:address":"1663 Central Ave",
    "sg:city":"Albany",
    "sg:classifiers":[
        {
            "category":"Personal",
            "subcategory":"Beauty Salon",
            "type":"Services"
        }
    ],
    "sg:phone":"+1 518 869 7912",
    "sg:postcode":"12205",
    "sg:province":"NY",
    "sg:tags":[
        "shop"
    ],
    "wof:name":"Marianne's Beauty Shop",
    "wof:placetype":"venue"
},
  "geometry": {"coordinates":[-73.836528,42.720691],"type":"Point"}
}