{
  "type": "Feature",
  "properties": {
    "iso:country":"US",
    "sg:address":"257 Mineola Blvd",
    "sg:city":"Mineola",
    "sg:classifiers":[
        {
            "category":"Real Estate",
            "subcategory":"Real Estate Operator",
            "type":"Services"
        }
    ],
    "sg:phone":"+1 516 742 4614",
    "sg:postcode":"11501",
    "sg:province":"NY",
    "wof:name":"Metro Commercial & Bus Brks In",
    "wof:placetype":"venue"
},
  "geometry": {"coordinates":[-73.643367,40.747102],"type":"Point"}
}