{
  "type": "Feature",
  "properties": {
    "iso:country":"US",
    "sg:address":"334 S Salina St",
    "sg:city":"Syracuse",
    "sg:classifiers":[
        {
            "category":"Shopping",
            "subcategory":"Shoes",
            "type":"Retail Goods"
        }
    ],
    "sg:phone":"+1 315 472 3276",
    "sg:postcode":"13202",
    "sg:province":"NY",
    "wof:name":"Payless Shoe Source",
    "wof:placetype":"venue"
},
  "geometry": {"coordinates":[-76.15230200000001,43.047608],"type":"Point"}
}