{
  "type": "Feature",
  "properties": {
    "addr:full":"912 Roanoke Ave Riverhead NY 11901",
    "addr:housenumber":"912",
    "addr:postcode":"11901",
    "addr:street":"Roanoke Ave",
    "iso:country":"US",
    "sg:address":"912 Roanoke Ave",
    "sg:city":"Riverhead",
    "sg:classifiers":[
        {
            "category":"Health Services",
            "subcategory":"Doctor",
            "type":"Services"
        }
    ],
    "sg:phone":"+1 631 326 9800",
    "sg:postcode":"11901",
    "sg:province":"NY",
    "wof:name":"Butt Afzal M MD",
    "wof:placetype":"venue"
},
  "geometry": {"coordinates":[-72.669601,40.927799],"type":"Point"}
}