{
  "type": "Feature",
  "properties": {
    "iso:country":"US",
    "sg:address":"130 Maple Blvd",
    "sg:city":"Long Beach",
    "sg:classifiers":[
        {
            "category":"Education",
            "subcategory":"School",
            "type":"Public Place"
        }
    ],
    "sg:phone":"+1 516 897 2120",
    "sg:postcode":"11561",
    "sg:province":"NY",
    "wof:name":"Maint Dept",
    "wof:placetype":"venue"
},
  "geometry": {"coordinates":[-73.638119,40.585436],"type":"Point"}
}