{
  "type": "Feature",
  "properties": {
    "iso:country":"US",
    "sg:address":"12 Villa Rd",
    "sg:city":"Albany",
    "sg:classifiers":[
        {
            "category":"Organizations",
            "subcategory":"Religious Organization",
            "type":"Services"
        }
    ],
    "sg:phone":"+1   ",
    "sg:postcode":"12204",
    "sg:province":"NY",
    "wof:name":"Rock Of Restoration",
    "wof:placetype":"venue"
},
  "geometry": {"coordinates":[-73.72657100000001,42.695372],"type":"Point"}
}