{
  "type": "Feature",
  "properties": {
    "addr:full":"42 Lakeshore Dr Eastchester NY 10709",
    "addr:housenumber":"42",
    "addr:postcode":"10709",
    "addr:street":"Lakeshore Dr",
    "iso:country":"US",
    "sg:address":"42 Lakeshore Dr",
    "sg:city":"Eastchester",
    "sg:classifiers":[
        {
            "category":"Real Estate",
            "subcategory":"Real Estate Agent",
            "type":"Services"
        }
    ],
    "sg:phone":"+1 914 793 1050",
    "sg:postcode":"10709",
    "sg:province":"NY",
    "sg:tags":[
        "broker"
    ],
    "wof:name":"Eugene Rooney Real Estate",
    "wof:placetype":"venue"
},
  "geometry": {"coordinates":[-73.80222500000001,40.960297],"type":"Point"}
}