{
  "type": "Feature",
  "properties": {
    "iso:country":"US",
    "sg:address":"1059 Mallis Ct",
    "sg:city":"Valley Stream",
    "sg:classifiers":[
        {
            "category":"Health Services",
            "subcategory":"Doctor",
            "type":"Services"
        }
    ],
    "sg:phone":"+1 516 568 1482",
    "sg:postcode":"11580",
    "sg:province":"NY",
    "sg:tags":[
        "physician",
        "surgeon"
    ],
    "wof:name":"Salti B Zeidan MD",
    "wof:placetype":"venue"
},
  "geometry": {"coordinates":[-73.682734,40.679939],"type":"Point"}
}