{
  "type": "Feature",
  "properties": {
    "addr:full":"127 Burrs Ln Dix Hills NY 11746",
    "addr:housenumber":"127",
    "addr:postcode":"11746",
    "addr:street":"Burrs Ln",
    "iso:country":"US",
    "sg:address":"127 Burrs Ln",
    "sg:city":"Dix Hills",
    "sg:classifiers":[
        {
            "category":"Professional",
            "type":"Services"
        }
    ],
    "sg:phone":"+1 631 643 3045",
    "sg:postcode":"11746",
    "sg:province":"NY",
    "sg:tags":[
        "establishment"
    ],
    "wof:name":"Mobex Inc",
    "wof:placetype":"venue"
},
  "geometry": {"coordinates":[-73.36563,40.783797],"type":"Point"}
}