{
  "type": "Feature",
  "properties": {
    "addr:full":"2502 Barnes Ave Bronx NY 10467",
    "addr:housenumber":"2502",
    "addr:postcode":"10467",
    "addr:street":"Barnes Ave",
    "iso:country":"US",
    "sg:address":"2502 Barnes Ave",
    "sg:city":"Bronx",
    "sg:classifiers":[
        {
            "category":"Building & Trades",
            "subcategory":"Construction",
            "type":"Services"
        }
    ],
    "sg:phone":"+1 718 798 4687",
    "sg:postcode":"10467",
    "sg:province":"NY",
    "sg:tags":[
        "house"
    ],
    "wof:name":"Atlantis Renovations",
    "wof:placetype":"venue"
},
  "geometry": {"coordinates":[-73.86347600000001,40.864601],"type":"Point"}
}