{
  "type": "Feature",
  "properties": {
    "addr:full":"505 8 Ave New York NY 10018",
    "addr:housenumber":"505",
    "addr:postcode":"10018",
    "addr:street":"8 Ave",
    "iso:country":"US",
    "sg:address":"505 8 Ave",
    "sg:city":"New York",
    "sg:classifiers":[
        {
            "category":"Professional",
            "subcategory":"Management & Consulting",
            "type":"Services"
        }
    ],
    "sg:phone":"+1 212 239 1004",
    "sg:postcode":"10018",
    "sg:province":"NY",
    "sg:tags":[
        "consultant"
    ],
    "wof:name":"Caruso Dominick Consultant",
    "wof:placetype":"venue"
},
  "geometry": {"coordinates":[-73.99252799999999,40.753474],"type":"Point"}
}