{
  "type": "Feature",
  "properties": {
    "iso:country":"US",
    "sg:address":"234 Hudson Ave",
    "sg:city":"Albany",
    "sg:classifiers":[
        {
            "category":"Building & Trades",
            "subcategory":"Construction",
            "type":"Services"
        }
    ],
    "sg:phone":"+1 518 272 1723",
    "sg:postcode":"12210",
    "sg:province":"NY",
    "sg:tags":[
        "siding",
        "contractor"
    ],
    "wof:name":"Siding Distributors Of Ny",
    "wof:placetype":"venue"
},
  "geometry": {"coordinates":[-73.762479,42.651458],"type":"Point"}
}