{
  "type": "Feature",
  "properties": {
    "iso:country":"US",
    "sg:address":"1185 Dekalb Ave",
    "sg:city":"Brooklyn",
    "sg:classifiers":[
        {
            "category":"Food & Beverages",
            "subcategory":"Groceries & Convenience Stores",
            "type":"Retail Goods"
        }
    ],
    "sg:phone":"+1   ",
    "sg:postcode":"11221",
    "sg:province":"NY",
    "wof:name":"Cesar Jose Almanzar",
    "wof:placetype":"venue"
},
  "geometry": {"coordinates":[-73.929423,40.693952],"type":"Point"}
}