{
  "type": "Feature",
  "properties": {
    "iso:country":"US",
    "sg:address":"12 Roosevelt Ave",
    "sg:city":"Malverne",
    "sg:classifiers":[
        {
            "category":"Building & Trades",
            "subcategory":"Construction",
            "type":"Services"
        }
    ],
    "sg:phone":"+1 516 887 5452",
    "sg:postcode":"11565",
    "sg:province":"NY",
    "wof:name":"Kerley Construction",
    "wof:placetype":"venue"
},
  "geometry": {"coordinates":[-73.675383,40.673603],"type":"Point"}
}