{
  "type": "Feature",
  "properties": {
    "addr:full":"1103 Old Country Rd Riverhead NY 11901",
    "addr:housenumber":"1103",
    "addr:postcode":"11901",
    "addr:street":"Old Country Rd",
    "iso:country":"US",
    "sg:address":"1103 Old Country Rd",
    "sg:city":"Riverhead",
    "sg:classifiers":[
        {
            "category":"Home & Garden",
            "subcategory":"Furniture",
            "type":"Retail Goods"
        }
    ],
    "sg:phone":"+1 631 208 0200",
    "sg:postcode":"11901",
    "sg:province":"NY",
    "sg:tags":[
        "store"
    ],
    "wof:name":"B & B Furniture",
    "wof:placetype":"venue"
},
  "geometry": {"coordinates":[-72.677712,40.931371],"type":"Point"}
}