{
  "type": "Feature",
  "properties": {
    "addr:full":"168 Heyward St Brooklyn NY 11206",
    "addr:housenumber":"168",
    "addr:postcode":"11206",
    "addr:street":"Heyward St",
    "iso:country":"US",
    "sg:address":"168 Heyward St",
    "sg:city":"Brooklyn",
    "sg:classifiers":[
        {
            "category":"Organizations",
            "subcategory":"Religious Organization",
            "type":"Services"
        }
    ],
    "sg:phone":"+1   ",
    "sg:postcode":"11206",
    "sg:province":"NY",
    "sg:tags":[
        "printing",
        "commercial"
    ],
    "wof:name":"Joseph Kohn",
    "wof:placetype":"venue"
},
  "geometry": {"coordinates":[-73.954971,40.702095],"type":"Point"}
}