{
  "type": "Feature",
  "properties": {
    "iso:country":"US",
    "name:eng_x_preferred":[
        "170 St"
    ],
    "wof:name":"170 St Station",
    "wof:placetype":"venue"
},
  "geometry": {"coordinates":[-73.9134,40.839306],"type":"Point"}
}