{
  "type": "Feature",
  "properties": {
    "addr:full":"727 Manhattan Ave Brooklyn NY 11211",
    "addr:housenumber":"727",
    "addr:postcode":"11211",
    "addr:street":"Manhattan Ave",
    "iso:country":"US",
    "sg:address":"727 Manhattan Ave",
    "sg:city":"Brooklyn",
    "sg:classifiers":[
        {
            "category":"Bakery",
            "type":"Food & Drink"
        },
        {
            "category":"Donuts",
            "subcategory":"None",
            "type":"Food & Drink"
        }
    ],
    "sg:phone":"+1 718 389 3676",
    "sg:postcode":"11211",
    "sg:province":"NY",
    "wof:name":"Peter Pan Bakery",
    "wof:placetype":"venue"
},
  "geometry": {"coordinates":[-73.95230100000001,40.726002],"type":"Point"}
}