{
  "type": "Feature",
  "properties": {
    "iso:country":"US",
    "sg:address":"6646 Hessenthaler Rd",
    "sg:city":"Byron",
    "sg:classifiers":[
        {
            "category":"Organizations",
            "subcategory":"Community Association",
            "type":"Services"
        }
    ],
    "sg:phone":"+1 585 548 7304",
    "sg:postcode":"14422",
    "sg:province":"NY",
    "sg:tags":[
        "environmental",
        "org"
    ],
    "wof:name":"Bergen Swamp Preservation Soc",
    "wof:placetype":"venue"
},
  "geometry": {"coordinates":[-78.026614,43.091575],"type":"Point"}
}