{
  "type": "Feature",
  "properties": {
    "addr:full":"310 E 72 St New York NY 10021",
    "addr:housenumber":"310;72",
    "addr:postcode":"10021",
    "addr:street":"E;St",
    "iso:country":"US",
    "sg:address":"310 E 72 St",
    "sg:city":"New York",
    "sg:classifiers":[
        {
            "category":"Health Services",
            "subcategory":"Doctor",
            "type":"Services"
        }
    ],
    "sg:phone":"+1 212 472 3333",
    "sg:postcode":"10021",
    "sg:province":"NY",
    "sg:tags":[
        "medical"
    ],
    "wof:name":"Michael C Cantor",
    "wof:placetype":"venue"
},
  "geometry": {"coordinates":[-73.956217,40.76784],"type":"Point"}
}