{
  "type": "Feature",
  "properties": {
    "iso:country":"US",
    "sg:address":"48 Prospect Ave",
    "sg:city":"Ardsley",
    "sg:classifiers":[
        {
            "category":"Professional",
            "subcategory":"Management & Consulting",
            "type":"Services"
        }
    ],
    "sg:phone":"+1 914 693 6193",
    "sg:postcode":"10502",
    "sg:province":"NY",
    "sg:tags":[
        "consultant"
    ],
    "wof:name":"Piluso Consulting Svc",
    "wof:placetype":"venue"
},
  "geometry": {"coordinates":[-73.840039,41.005353],"type":"Point"}
}