{
  "type": "Feature",
  "properties": {
    "addr:full":"48 Windmill Ct Huntington Sta NY 11746",
    "addr:housenumber":"48",
    "addr:postcode":"11746",
    "addr:street":"Windmill Ct",
    "iso:country":"US",
    "sg:address":"48 Windmill Ct",
    "sg:city":"Huntington Sta",
    "sg:classifiers":[
        {
            "category":"Professional",
            "type":"Services"
        }
    ],
    "sg:phone":"+1 631 427 5371",
    "sg:postcode":"11746",
    "sg:province":"NY",
    "sg:tags":[
        "establishment"
    ],
    "wof:name":"H H Enterprises",
    "wof:placetype":"venue"
},
  "geometry": {"coordinates":[-73.394836,40.85441],"type":"Point"}
}