{
  "type": "Feature",
  "properties": {
    "iso:country":"US",
    "sg:address":"357 S Plank Rd",
    "sg:city":"Newburgh",
    "sg:classifiers":[
        {
            "category":"Health Services",
            "subcategory":"Chiropractor",
            "type":"Services"
        }
    ],
    "sg:phone":"+1 845 566 3603",
    "sg:postcode":"12550",
    "sg:province":"NY",
    "wof:name":"Angelone Chiropractic",
    "wof:placetype":"venue"
},
  "geometry": {"coordinates":[-74.08547,41.534911],"type":"Point"}
}