{
  "type": "Feature",
  "properties": {
    "addr:full":"4110 Monticello Ave Bronx NY 10466",
    "addr:housenumber":"4110",
    "addr:postcode":"10466",
    "addr:street":"Monticello Ave",
    "iso:country":"US",
    "sg:address":"4110 Monticello Ave",
    "sg:city":"Bronx",
    "sg:classifiers":[
        {
            "category":"Travel",
            "subcategory":"Travel Agent",
            "type":"Entertainment"
        }
    ],
    "sg:phone":"+1 718 515 6385",
    "sg:postcode":"10466",
    "sg:province":"NY",
    "sg:tags":[
        "agency",
        "bureau"
    ],
    "wof:name":"Global Travel Intl",
    "wof:placetype":"venue"
},
  "geometry": {"coordinates":[-73.839938,40.895733],"type":"Point"}
}