{
  "type": "Feature",
  "properties": {
    "iso:country":"US",
    "sg:address":"403 Park Ave",
    "sg:city":"Herkimer",
    "sg:classifiers":[
        {
            "category":"Social Services",
            "subcategory":"Adult Care",
            "type":"Services"
        }
    ],
    "sg:phone":"+1 315 866 0041",
    "sg:postcode":"13350",
    "sg:province":"NY",
    "sg:tags":[
        "home",
        "group"
    ],
    "wof:name":"Central NEW York Dso",
    "wof:placetype":"venue"
},
  "geometry": {"coordinates":[-74.99166200000001,43.024472],"type":"Point"}
}