{
  "type": "Feature",
  "properties": {
    "addr:full":"7500 Commons Blvd Victor NY 14564",
    "addr:housenumber":"7500",
    "addr:postcode":"14564",
    "addr:street":"Commons Blvd",
    "iso:country":"US",
    "sg:address":"7500 Commons Blvd",
    "sg:city":"Victor",
    "sg:classifiers":[
        {
            "category":"Shopping",
            "subcategory":"Department Store",
            "type":"Retail Goods"
        },
        {
            "category":"Shopping",
            "subcategory":"Clothing, Apparel, & Fashions",
            "type":"Retail Goods"
        },
        {
            "category":"Shopping",
            "type":"Retail Goods"
        },
        {
            "category":"Shopping",
            "subcategory":"Discount & Variety Stores",
            "type":"Retail Goods"
        }
    ],
    "sg:phone":"+1 585 425 0800",
    "sg:postcode":"14564",
    "sg:province":"NY",
    "sg:tags":[
        "clothing",
        "merchandise"
    ],
    "sg:website":"http://www.target.com",
    "wof:name":"Target",
    "wof:placetype":"venue"
},
  "geometry": {"coordinates":[-77.44651,43.0317],"type":"Point"}
}