{
  "type": "Feature",
  "properties": {
    "addr:full":"6711 79th St Middle Village NY 11379",
    "addr:housenumber":"6711",
    "addr:postcode":"11379",
    "addr:street":"79Th St",
    "iso:country":"US",
    "sg:address":"6711 79th St",
    "sg:city":"Middle Village",
    "sg:classifiers":[
        {
            "category":"Building & Trades",
            "subcategory":"Electrical",
            "type":"Services"
        }
    ],
    "sg:phone":"+1 718 326 1666",
    "sg:postcode":"11379",
    "sg:province":"NY",
    "sg:tags":[
        "electrician"
    ],
    "wof:name":"J R D Electric Co Inc",
    "wof:placetype":"venue"
},
  "geometry": {"coordinates":[-73.87339799999999,40.7131],"type":"Point"}
}