{
  "type": "Feature",
  "properties": {
    "addr:full":"53 Sylvan Dr Wading River NY 11792",
    "addr:housenumber":"53",
    "addr:postcode":"11792",
    "addr:street":"Sylvan Dr Wading",
    "iso:country":"US",
    "sg:address":"53 Sylvan Dr",
    "sg:city":"Wading River",
    "sg:classifiers":[
        {
            "category":"Banks & Credit Unions",
            "subcategory":"Investment Brokerage",
            "type":"Services"
        }
    ],
    "sg:phone":"+1 631 929 0721",
    "sg:postcode":"11792",
    "sg:province":"NY",
    "sg:tags":[
        "advisory"
    ],
    "wof:name":"Upward Financial Systems",
    "wof:placetype":"venue"
},
  "geometry": {"coordinates":[-72.816895,40.96071],"type":"Point"}
}