{
  "type": "Feature",
  "properties": {
    "iso:country":"US",
    "sg:address":"19 Kimberly Dr",
    "sg:city":"Jamestown",
    "sg:classifiers":[
        {
            "category":"Health Services",
            "subcategory":"Doctor",
            "type":"Services"
        }
    ],
    "sg:phone":"+1 716 488 1677",
    "sg:postcode":"14701",
    "sg:province":"NY",
    "sg:tags":[
        "dentist"
    ],
    "wof:name":"S Jack Peppy DDS",
    "wof:placetype":"venue"
},
  "geometry": {"coordinates":[-79.216396,42.088777],"type":"Point"}
}