{
  "type": "Feature",
  "properties": {
    "iso:country":"US",
    "sg:address":"340 Illington Rd",
    "sg:city":"Ossining",
    "sg:classifiers":[
        {
            "category":"Organizations",
            "subcategory":"Religious Organization",
            "type":"Services"
        }
    ],
    "sg:phone":"+1 914 941 3642",
    "sg:postcode":"10562",
    "sg:province":"NY",
    "wof:name":"Jacob Grunwald",
    "wof:placetype":"venue"
},
  "geometry": {"coordinates":[-73.812309,41.221352],"type":"Point"}
}