{
  "type": "Feature",
  "properties": {
    "addr:full":"23 Lexington Ave New York NY 10010",
    "addr:housenumber":"23",
    "addr:postcode":"10010",
    "addr:street":"Lexington Ave",
    "iso:country":"US",
    "sg:address":"23 Lexington Ave",
    "sg:city":"New York",
    "sg:classifiers":[
        {
            "category":"Travel",
            "subcategory":"Bed & Breakfast",
            "type":"Entertainment"
        }
    ],
    "sg:phone":"+1 212 475 1924",
    "sg:postcode":"10010",
    "sg:province":"NY",
    "sg:tags":[
        "house"
    ],
    "wof:name":"Devon Management Co",
    "wof:placetype":"venue"
},
  "geometry": {"coordinates":[-73.984269,40.740002],"type":"Point"}
}