{
  "type": "Feature",
  "properties": {
    "addr:full":"2044 South Rd Poughkeepsie NY 12601",
    "addr:housenumber":"2044",
    "addr:postcode":"12601",
    "addr:street":"South Rd",
    "iso:country":"US",
    "sg:address":"2044 South Rd",
    "sg:city":"Poughkeepsie",
    "sg:classifiers":[
        {
            "category":"Fast Food",
            "type":"Food & Drink"
        },
        {
            "category":"Restaurant",
            "type":"Food & Drink"
        }
    ],
    "sg:phone":"+1 845 297 1787",
    "sg:postcode":"12601",
    "sg:province":"NY",
    "sg:tags":[
        "style",
        "family",
        "american",
        "take",
        "pasta",
        "italian"
    ],
    "sg:website":"http://www.olivegarden.com",
    "wof:name":"Olive Garden",
    "wof:placetype":"venue"
},
  "geometry": {"coordinates":[-73.916225,41.628557],"type":"Point"}
}