{
  "type": "Feature",
  "properties": {
    "addr:full":"2488 N Jerusalem Rd Bellmore NY 11710",
    "addr:housenumber":"2488",
    "addr:postcode":"11710",
    "addr:street":"N Jerusalem Rd",
    "iso:country":"US",
    "sg:address":"2488 N Jerusalem Rd",
    "sg:city":"Bellmore",
    "sg:classifiers":[
        {
            "category":"Building & Trades",
            "subcategory":"Construction",
            "type":"Services"
        }
    ],
    "sg:phone":"+1 516 679 8991",
    "sg:postcode":"11710",
    "sg:province":"NY",
    "sg:tags":[
        "home",
        "improvement"
    ],
    "wof:name":"Kreku Murlan",
    "wof:placetype":"venue"
},
  "geometry": {"coordinates":[-73.54247599999999,40.705855],"type":"Point"}
}