{
  "type": "Feature",
  "properties": {
    "iso:country":"US",
    "sg:address":"191 Wilson St",
    "sg:city":"Brooklyn",
    "sg:phone":"+1   ",
    "sg:postcode":"11211",
    "sg:province":"NY",
    "sg:tags":[
        "communications",
        "other",
        "telegraph"
    ],
    "wof:name":"Bloumberg Group Inc",
    "wof:placetype":"venue"
},
  "geometry": {"coordinates":[-73.959872,40.707043],"type":"Point"}
}