{
  "type": "Feature",
  "properties": {
    "addr:full":"7 Fawn Ln East Islip NY 11730",
    "addr:housenumber":"7",
    "addr:postcode":"11730",
    "addr:street":"Fawn Ln",
    "iso:country":"US",
    "sg:address":"7 Fawn Ln",
    "sg:city":"East Islip",
    "sg:classifiers":[
        {
            "category":"Home & Garden",
            "subcategory":"Home Furnishings",
            "type":"Retail Goods"
        },
        {
            "category":"Building & Trades",
            "subcategory":"Plumbing",
            "type":"Services"
        }
    ],
    "sg:phone":"+1 631 581 2595",
    "sg:postcode":"11730",
    "sg:province":"NY",
    "sg:tags":[
        "bathroom",
        "contractor",
        "fixture",
        "accessory"
    ],
    "wof:name":"Trade Winds Plumbing & Heating",
    "wof:placetype":"venue"
},
  "geometry": {"coordinates":[-73.188638,40.71778],"type":"Point"}
}