{
  "type": "Feature",
  "properties": {
    "iso:country":"US",
    "sg:address":"26 Elm Pl",
    "sg:city":"Amityville",
    "sg:classifiers":[
        {
            "category":"Retail",
            "subcategory":"Auto Repair",
            "type":"Services"
        }
    ],
    "sg:phone":"+1   ",
    "sg:postcode":"11701",
    "sg:province":"NY",
    "sg:tags":[
        "general"
    ],
    "wof:name":"Corvette Doctors",
    "wof:placetype":"venue"
},
  "geometry": {"coordinates":[-73.413973,40.682954],"type":"Point"}
}