{
  "type": "Feature",
  "properties": {
    "iso:country":"US",
    "sg:address":"189 Portion Rd",
    "sg:city":"Ronkonkoma",
    "sg:classifiers":[
        {
            "category":"Restaurant",
            "type":"Food & Drink"
        }
    ],
    "sg:phone":"+1   ",
    "sg:postcode":"11779",
    "sg:province":"NY",
    "sg:tags":[
        "eating"
    ],
    "wof:name":"Pizza Hut",
    "wof:placetype":"venue"
},
  "geometry": {"coordinates":[-73.10610699999999,40.826663],"type":"Point"}
}