{
  "type": "Feature",
  "properties": {
    "addr:full":"696 Willowbrook Rd Staten Island NY 10314",
    "addr:housenumber":"696",
    "addr:postcode":"10314",
    "addr:street":"Willowbrook Rd",
    "iso:country":"US",
    "sg:address":"696 Willowbrook Rd",
    "sg:city":"Staten Island",
    "sg:classifiers":[
        {
            "category":"Retail",
            "subcategory":"Auto Rental",
            "type":"Services"
        }
    ],
    "sg:phone":"+1 718 494 4997",
    "sg:postcode":"10314",
    "sg:province":"NY",
    "sg:tags":[
        "car"
    ],
    "wof:name":"Eldan Rent A Car Inc",
    "wof:placetype":"venue"
},
  "geometry": {"coordinates":[-74.14752900000001,40.607323],"type":"Point"}
}