{
  "type": "Feature",
  "properties": {
    "iso:country":"US",
    "sg:address":"359 Church Ave",
    "sg:city":"Woodmere",
    "sg:classifiers":[
        {
            "category":"Real Estate",
            "subcategory":"Real Estate Agent",
            "type":"Services"
        }
    ],
    "sg:phone":"+1 516 295 4444",
    "sg:postcode":"11598",
    "sg:province":"NY",
    "wof:name":"Smolinsky Properties Inc",
    "wof:placetype":"venue"
},
  "geometry": {"coordinates":[-73.724524,40.62995],"type":"Point"}
}