{
  "type": "Feature",
  "properties": {
    "iso:country":"US",
    "sg:address":"2815 Covered Bridge Rd",
    "sg:city":"Merrick",
    "sg:classifiers":[
        {
            "category":"Wholesale",
            "subcategory":"Non-durable Goods",
            "type":"Manufacturing & Wholesale Goods"
        }
    ],
    "sg:phone":"+1   ",
    "sg:postcode":"11566",
    "sg:province":"NY",
    "sg:tags":[
        "product",
        "commercial",
        "mfg"
    ],
    "wof:name":"Premier Printing & Novlt Co",
    "wof:placetype":"venue"
},
  "geometry": {"coordinates":[-73.55562500000001,40.646572],"type":"Point"}
}