{
  "type": "Feature",
  "properties": {
    "addr:full":"420 Kent Ave Brooklyn NY 11211",
    "addr:housenumber":"420",
    "addr:postcode":"11211",
    "addr:street":"Kent Ave",
    "iso:country":"US",
    "sg:address":"420 Kent Ave",
    "sg:city":"Brooklyn",
    "sg:classifiers":[
        {
            "category":"Professional",
            "subcategory":"Employment Agencies",
            "type":"Services"
        }
    ],
    "sg:phone":"+1 718 782 3533",
    "sg:postcode":"11211",
    "sg:province":"NY",
    "sg:tags":[
        "help",
        "supply"
    ],
    "wof:name":"Dial",
    "wof:placetype":"venue"
},
  "geometry": {"coordinates":[-73.968524,40.710046],"type":"Point"}
}