{
  "type": "Feature",
  "properties": {
    "addr:full":"64 Nathan Hale Dr Stormville NY 12582",
    "addr:housenumber":"64",
    "addr:postcode":"12582",
    "addr:street":"Nathan Hale Dr",
    "iso:country":"US",
    "sg:address":"64 Nathan Hale Dr",
    "sg:city":"Stormville",
    "sg:classifiers":[
        {
            "category":"Shopping",
            "subcategory":"Stationery & Office Supplies",
            "type":"Retail Goods"
        }
    ],
    "sg:phone":"+1   ",
    "sg:postcode":"12582",
    "sg:province":"NY",
    "sg:tags":[
        "a",
        "educational",
        "for",
        "company",
        "retailer",
        "holding"
    ],
    "wof:name":"Educatnal Rfrral Ntwrk The Inc",
    "wof:placetype":"venue"
},
  "geometry": {"coordinates":[-73.739209,41.522209],"type":"Point"}
}