{
  "type": "Feature",
  "properties": {
    "iso:country":"US",
    "sg:address":"232 Ave U",
    "sg:city":"Brooklyn",
    "sg:classifiers":[
        {
            "category":"Professional",
            "subcategory":"Management & Consulting",
            "type":"Services"
        }
    ],
    "sg:phone":"+1 718 266 6000",
    "sg:postcode":"11223",
    "sg:province":"NY",
    "wof:name":"Ultimate Management Inc",
    "wof:placetype":"venue"
},
  "geometry": {"coordinates":[-73.97650899999999,40.596616],"type":"Point"}
}