{
  "type": "Feature",
  "properties": {
    "addr:full":"199 Community Dr Great Neck NY 11021",
    "addr:housenumber":"199",
    "addr:postcode":"11021",
    "addr:street":"Community Dr",
    "iso:country":"US",
    "sg:address":"199 Community Dr",
    "sg:city":"Great Neck",
    "sg:classifiers":[
        {
            "category":"Health Services",
            "subcategory":"Nursing And Care Facility",
            "type":"Services"
        }
    ],
    "sg:phone":"+1 516 365 9229",
    "sg:postcode":"11021",
    "sg:province":"NY",
    "sg:tags":[
        "home",
        "skilled"
    ],
    "wof:name":"Wedgewood Care Center Inc",
    "wof:placetype":"venue"
},
  "geometry": {"coordinates":[-73.703529,40.78102],"type":"Point"}
}