{
  "type": "Feature",
  "properties": {
    "addr:full":"4910 7th Ave Brooklyn NY 11220",
    "addr:housenumber":"4910",
    "addr:postcode":"11220",
    "addr:street":"7Th Ave",
    "iso:country":"US",
    "sg:address":"4910 7th Ave",
    "sg:city":"Brooklyn",
    "sg:classifiers":[
        {
            "category":"Real Estate",
            "subcategory":"Real Estate Agent",
            "type":"Services"
        }
    ],
    "sg:phone":"+1 718 633 4999",
    "sg:postcode":"11220",
    "sg:province":"NY",
    "wof:name":"Hamdan Group",
    "wof:placetype":"venue"
},
  "geometry": {"coordinates":[-74.005926,40.642548],"type":"Point"}
}