{
  "type": "Feature",
  "properties": {
    "iso:country":"US",
    "sg:address":"341 Main St Apt 2",
    "sg:city":"Islip",
    "sg:classifiers":[
        {
            "category":"Shopping",
            "subcategory":"Florist",
            "type":"Retail Goods"
        }
    ],
    "sg:phone":"+1 631 581 3464",
    "sg:postcode":"11751",
    "sg:province":"NY",
    "sg:website":"www.carolinesflowershoppe.com",
    "wof:name":"Caroline's Flower Shoppe",
    "wof:placetype":"venue"
},
  "geometry": {"coordinates":[-73.217474,40.728694],"type":"Point"}
}