{
  "type": "Feature",
  "properties": {
    "addr:full":"55 Bethune St New York NY 10014",
    "addr:housenumber":"55",
    "addr:postcode":"10014",
    "addr:street":"Bethune St",
    "iso:country":"US",
    "sg:address":"55 Bethune St",
    "sg:city":"New York",
    "sg:classifiers":[
        {
            "category":"Banks & Credit Unions",
            "subcategory":"Investment Brokerage",
            "type":"Services"
        }
    ],
    "sg:phone":"+1 212 741 7088",
    "sg:postcode":"10014",
    "sg:province":"NY",
    "sg:tags":[
        "advisory"
    ],
    "wof:name":"Krefetz Management and Res",
    "wof:placetype":"venue"
},
  "geometry": {"coordinates":[-74.00953699999999,40.736892],"type":"Point"}
}