{
  "type": "Feature",
  "properties": {
    "addr:full":"281 Schoenfield Blvd Patchogue NY 11772",
    "addr:housenumber":"281",
    "addr:postcode":"11772",
    "addr:street":"Schoenfield Blvd",
    "iso:country":"US",
    "sg:address":"281 Schoenfield Blvd",
    "sg:city":"Patchogue",
    "sg:classifiers":[
        {
            "category":"Professional",
            "subcategory":"Management & Consulting",
            "type":"Services"
        }
    ],
    "sg:phone":"+1 631 475 9463",
    "sg:postcode":"11772",
    "sg:province":"NY",
    "sg:tags":[
        "house",
        "con"
    ],
    "wof:name":"Reyling Consulting Inc",
    "wof:placetype":"venue"
},
  "geometry": {"coordinates":[-72.99603999999999,40.776417],"type":"Point"}
}