{
  "type": "Feature",
  "properties": {
    "iso:country":"US",
    "sg:address":"5074 N Main St",
    "sg:city":"North Rose",
    "sg:classifiers":[
        {
            "category":"Government",
            "subcategory":"Office",
            "type":"Public Place"
        }
    ],
    "sg:phone":"+1 315 587 2419",
    "sg:postcode":"14516",
    "sg:province":"NY",
    "sg:tags":[
        "city",
        "taxation"
    ],
    "wof:name":"Town Assessor",
    "wof:placetype":"venue"
},
  "geometry": {"coordinates":[-76.892662,43.185447],"type":"Point"}
}