{
  "type": "Feature",
  "properties": {
    "addr:full":"1011 1 Ave New York NY 10022",
    "addr:housenumber":"1011",
    "addr:postcode":"10022",
    "addr:street":"1 Ave",
    "iso:country":"US",
    "sg:address":"1011 1 Ave",
    "sg:city":"New York",
    "sg:classifiers":[
        {
            "category":"Health Services",
            "subcategory":"Clinic",
            "type":"Services"
        }
    ],
    "sg:phone":"+1 212 486 7180",
    "sg:postcode":"10022",
    "sg:province":"NY",
    "wof:name":"Catholic Healthcare System",
    "wof:placetype":"venue"
},
  "geometry": {"coordinates":[-73.966157,40.753878],"type":"Point"}
}