{
  "type": "Feature",
  "properties": {
    "iso:country":"US",
    "sg:address":"1045 Park Ave",
    "sg:city":"New York",
    "sg:classifiers":[
        {
            "category":"Health Services",
            "subcategory":"Doctor",
            "type":"Services"
        }
    ],
    "sg:phone":"+1 212 534 5570",
    "sg:postcode":"10028",
    "sg:province":"NY",
    "sg:tags":[
        "physician",
        "medical",
        "surgeon"
    ],
    "wof:name":"Joseph Ament, MD",
    "wof:placetype":"venue"
},
  "geometry": {"coordinates":[-73.95672399999999,40.780289],"type":"Point"}
}