{
  "type": "Feature",
  "properties": {
    "addr:full":"2 Medical Plz Glen Cove NY 11542",
    "addr:housenumber":"2",
    "addr:postcode":"11542",
    "addr:street":"Medical Plz",
    "iso:country":"US",
    "sg:address":"2 Medical Plz",
    "sg:city":"Glen Cove",
    "sg:classifiers":[
        {
            "category":"Health Services",
            "subcategory":"Nursing And Care Facility",
            "type":"Services"
        }
    ],
    "sg:phone":"+1 516 671 0858",
    "sg:postcode":"11542",
    "sg:province":"NY",
    "sg:tags":[
        "intermediate",
        "skilled",
        "convalescent",
        "home"
    ],
    "sg:website":"www.marquiscarecenter.com",
    "wof:name":"Marquis Care Center",
    "wof:placetype":"venue"
},
  "geometry": {"coordinates":[-73.622647,40.874122],"type":"Point"}
}