{
  "type": "Feature",
  "properties": {
    "iso:country":"US",
    "sg:address":"90 Depew Ave",
    "sg:city":"Buffalo",
    "sg:classifiers":[
        {
            "category":"Real Estate",
            "subcategory":"Real Estate Operator",
            "type":"Services"
        }
    ],
    "sg:phone":"+1 716 838 5563",
    "sg:postcode":"14214",
    "sg:province":"NY",
    "sg:tags":[
        "building",
        "apartment"
    ],
    "wof:name":"Ridge Lea Apts",
    "wof:placetype":"venue"
},
  "geometry": {"coordinates":[-78.844544,42.943962],"type":"Point"}
}