{
  "type": "Feature",
  "properties": {
    "iso:country":"US",
    "sg:address":"52 Spruce St",
    "sg:city":"Oneonta",
    "sg:classifiers":[
        {
            "category":"Building & Trades",
            "subcategory":"Construction",
            "type":"Services"
        }
    ],
    "sg:phone":"+1 607 287 0293",
    "sg:postcode":"13820",
    "sg:province":"NY",
    "sg:tags":[
        "house"
    ],
    "wof:name":"Trotti Construction",
    "wof:placetype":"venue"
},
  "geometry": {"coordinates":[-75.063649,42.460647],"type":"Point"}
}