{
  "type": "Feature",
  "properties": {
    "addr:full":"144 Exchange Blvd Rochester NY 14614",
    "addr:housenumber":"144",
    "addr:postcode":"14614",
    "addr:street":"Exchange Blvd",
    "iso:country":"US",
    "sg:address":"144 Exchange Blvd",
    "sg:city":"Rochester",
    "sg:classifiers":[
        {
            "category":"Real Estate",
            "subcategory":"Real Estate Operator",
            "type":"Services"
        }
    ],
    "sg:phone":"+1 585 232 3758",
    "sg:postcode":"14614",
    "sg:province":"NY",
    "sg:tags":[
        "building",
        "parks"
    ],
    "wof:name":"Court Exchange Office Bldg",
    "wof:placetype":"venue"
},
  "geometry": {"coordinates":[-77.610933,43.151399],"type":"Point"}
}