{
  "type": "Feature",
  "properties": {
    "addr:full":"900 W 190th St New York NY 10040",
    "addr:housenumber":"900",
    "addr:postcode":"10040",
    "addr:street":"W 190Th St",
    "iso:country":"US",
    "sg:address":"900 W 190th St",
    "sg:city":"New York",
    "sg:classifiers":[
        {
            "category":"Professional",
            "subcategory":"Management & Consulting",
            "type":"Services"
        }
    ],
    "sg:phone":"+1   ",
    "sg:postcode":"10040",
    "sg:province":"NY",
    "wof:name":"A Development Stage Company",
    "wof:placetype":"venue"
},
  "geometry": {"coordinates":[-73.936576,40.857351],"type":"Point"}
}