{
  "type": "Feature",
  "properties": {
    "addr:full":"80 Pine St New York NY 10005",
    "addr:housenumber":"80",
    "addr:postcode":"10005",
    "addr:street":"Pine St",
    "iso:country":"US",
    "sg:address":"80 Pine St",
    "sg:city":"New York",
    "sg:classifiers":[
        {
            "category":"Professional",
            "subcategory":"Lawyer & Legal Services",
            "type":"Services"
        }
    ],
    "sg:phone":"+1 212 701 3812",
    "sg:postcode":"10005",
    "sg:province":"NY",
    "wof:name":"Gamboni Ciro A Atty",
    "wof:placetype":"venue"
},
  "geometry": {"coordinates":[-74.006897,40.705799],"type":"Point"}
}