{
  "type": "Feature",
  "properties": {
    "addr:full":"10 Milton Ave Highland NY 12528",
    "addr:housenumber":"10",
    "addr:postcode":"12528",
    "addr:street":"Milton Ave",
    "iso:country":"US",
    "sg:address":"10 Milton Ave",
    "sg:city":"Highland",
    "sg:classifiers":[
        {
            "category":"Banks & Credit Unions",
            "subcategory":"Bank",
            "type":"Services"
        }
    ],
    "sg:phone":"+1 845 691 6900",
    "sg:postcode":"12528",
    "sg:province":"NY",
    "wof:name":"M & T Bank",
    "wof:placetype":"venue"
},
  "geometry": {"coordinates":[-73.964037,41.717971],"type":"Point"}
}