{
  "type": "Feature",
  "properties": {
    "addr:full":"2381 Hylan Blvd Staten Island NY 10306",
    "addr:housenumber":"2381",
    "addr:postcode":"10306",
    "addr:street":"Hylan Blvd",
    "iso:country":"US",
    "sg:address":"2381 Hylan Blvd",
    "sg:city":"Staten Island",
    "sg:classifiers":[
        {
            "category":"Health Services",
            "subcategory":"Clinic",
            "type":"Services"
        }
    ],
    "sg:phone":"+1 718 668 1015",
    "sg:postcode":"10306",
    "sg:province":"NY",
    "sg:tags":[
        "medical",
        "examiner"
    ],
    "wof:name":"Pryamid Claims Svc",
    "wof:placetype":"venue"
},
  "geometry": {"coordinates":[-74.106694,40.573733],"type":"Point"}
}