{
  "type": "Feature",
  "properties": {
    "addr:full":"694 9th Avenue New York NY 10036",
    "addr:housenumber":"694",
    "addr:postcode":"10036",
    "addr:street":"9Th Avenue",
    "iso:country":"US",
    "sg:address":"694 9th Avenue",
    "sg:city":"New York",
    "sg:classifiers":[
        {
            "category":"Food & Beverages",
            "subcategory":"Groceries & Convenience Stores",
            "type":"Retail Goods"
        }
    ],
    "sg:phone":"+1 212 586 1448",
    "sg:postcode":"10036",
    "sg:province":"NY",
    "wof:name":"Mazzella's Market",
    "wof:placetype":"venue"
},
  "geometry": {"coordinates":[-73.99014099999999,40.762081],"type":"Point"}
}