{
  "type": "Feature",
  "properties": {
    "addr:full":"220 E 54th Street Lowr New York NY 10022",
    "addr:housenumber":"220",
    "addr:postcode":"10022",
    "addr:street":"E 54Th Street",
    "iso:country":"US",
    "sg:address":"220 E 54th Street Lowr",
    "sg:city":"New York",
    "sg:classifiers":[
        {
            "category":"Health Services",
            "subcategory":"Doctor",
            "type":"Services"
        }
    ],
    "sg:phone":"+1 212 486 3191",
    "sg:postcode":"10022",
    "sg:province":"NY",
    "wof:name":"Breitkopf Muriel",
    "wof:placetype":"venue"
},
  "geometry": {"coordinates":[-73.96848799999999,40.758114],"type":"Point"}
}