{
  "type": "Feature",
  "properties": {
    "addr:full":"10402 Mill Rd Medina NY 14103",
    "addr:housenumber":"10402",
    "addr:postcode":"14103",
    "addr:street":"Mill Rd",
    "iso:country":"US",
    "sg:address":"10402 Mill Rd",
    "sg:city":"Medina",
    "sg:classifiers":[
        {
            "category":"Building & Trades",
            "subcategory":"Construction",
            "type":"Services"
        }
    ],
    "sg:phone":"+1 585 798 4635",
    "sg:postcode":"14103",
    "sg:province":"NY",
    "sg:tags":[
        "carpenter"
    ],
    "wof:name":"David M Carpenter",
    "wof:placetype":"venue"
},
  "geometry": {"coordinates":[-78.45084199999999,43.294152],"type":"Point"}
}