{
  "type": "Feature",
  "properties": {
    "addr:full":"146 Bellport Ave Medford NY 11763",
    "addr:housenumber":"146",
    "addr:postcode":"11763",
    "addr:street":"Bellport Ave",
    "iso:country":"US",
    "sg:address":"146 Bellport Ave",
    "sg:city":"Medford",
    "sg:classifiers":[
        {
            "category":"Shopping",
            "subcategory":"Hobbies, Toys, & Games",
            "type":"Retail Goods"
        }
    ],
    "sg:phone":"+1 631 924 8540",
    "sg:postcode":"11763",
    "sg:province":"NY",
    "sg:tags":[
        "gun",
        "gunsmith"
    ],
    "wof:name":"L&L Equipment",
    "wof:placetype":"venue"
},
  "geometry": {"coordinates":[-72.957973,40.828539],"type":"Point"}
}