{
  "type": "Feature",
  "properties": {
    "iso:country":"US",
    "sg:address":"16 Church St",
    "sg:city":"Saranac Lake",
    "sg:classifiers":[
        {
            "category":"Shopping",
            "subcategory":"Bicycles & Sporting Goods",
            "type":"Retail Goods"
        }
    ],
    "sg:phone":"+1 518 359 2897",
    "sg:postcode":"12983",
    "sg:province":"NY",
    "wof:name":"Adirondack Action Sports",
    "wof:placetype":"venue"
},
  "geometry": {"coordinates":[-74.128918,44.326514],"type":"Point"}
}