{
  "type": "Feature",
  "properties": {
    "addr:full":"857 E 149th St Bronx NY 10455",
    "addr:housenumber":"857",
    "addr:postcode":"10455",
    "addr:street":"E 149Th St",
    "iso:country":"US",
    "sg:address":"857 E 149th St",
    "sg:city":"Bronx",
    "sg:classifiers":[
        {
            "category":"Wholesale",
            "subcategory":"Sporting Goods",
            "type":"Manufacturing & Wholesale Goods"
        }
    ],
    "sg:phone":"+1 718 742 5660",
    "sg:postcode":"10455",
    "sg:province":"NY",
    "sg:tags":[
        "equipment",
        "billiard",
        "supply"
    ],
    "wof:name":"Alberto Planco",
    "wof:placetype":"venue"
},
  "geometry": {"coordinates":[-73.903554,40.811764],"type":"Point"}
}