{
  "type": "Feature",
  "properties": {
    "addr:full":"174 Pike St Port Jervis NY 12771",
    "addr:housenumber":"174",
    "addr:postcode":"12771",
    "addr:street":"Pike St",
    "iso:country":"US",
    "sg:address":"174 Pike St",
    "sg:city":"Port Jervis",
    "sg:classifiers":[
        {
            "category":"Food & Beverages",
            "subcategory":"Groceries & Convenience Stores",
            "type":"Retail Goods"
        }
    ],
    "sg:phone":"+1 845 858 1142",
    "sg:postcode":"12771",
    "sg:province":"NY",
    "wof:name":"J J Delicatessen",
    "wof:placetype":"venue"
},
  "geometry": {"coordinates":[-74.68922000000001,41.377818],"type":"Point"}
}