{
  "type": "Feature",
  "properties": {
    "addr:full":"65 St. Marks Pl New York NY 10003",
    "addr:housenumber":"65",
    "addr:postcode":"10003",
    "addr:street":"St. Marks Pl",
    "iso:country":"US",
    "sg:address":"65 St. Marks Pl",
    "sg:city":"New York",
    "sg:classifiers":[
        {
            "category":"Restaurant",
            "type":"Food & Drink"
        }
    ],
    "sg:phone":"+1 212 477 5560",
    "sg:postcode":"10003",
    "sg:province":"NY",
    "sg:tags":[
        "french"
    ],
    "sg:website":"www.julesbistro.com/",
    "wof:name":"Jules Bistro",
    "wof:placetype":"venue"
},
  "geometry": {"coordinates":[-73.98606100000001,40.728176],"type":"Point"}
}