{
  "type": "Feature",
  "properties": {
    "addr:full":"2257 Jericho Tpke New Hyde Park NY 11040",
    "addr:housenumber":"2257",
    "addr:postcode":"11040",
    "addr:street":"Jericho Tpke;Hyde Park",
    "iso:country":"US",
    "sg:address":"2257 Jericho Tpke",
    "sg:city":"New Hyde Park",
    "sg:classifiers":[
        {
            "category":"Autos & Motor Vehicles",
            "subcategory":"Automobile Sales",
            "type":"Retail Goods"
        },
        {
            "category":"Retail",
            "subcategory":"Auto Rental",
            "type":"Services"
        },
        {
            "category":"Retail",
            "subcategory":"Auto Repair",
            "type":"Services"
        }
    ],
    "sg:phone":"+1 516 877 9550",
    "sg:postcode":"11040",
    "sg:province":"NY",
    "sg:tags":[
        "car"
    ],
    "wof:name":"GMC Truck Dealer",
    "wof:placetype":"venue"
},
  "geometry": {"coordinates":[-73.6716,40.737],"type":"Point"}
}