{
  "type": "Feature",
  "properties": {
    "addr:full":"8 Raymond Dr Rochester NY 14624",
    "addr:housenumber":"8",
    "addr:postcode":"14624",
    "addr:street":"Raymond Dr",
    "iso:country":"US",
    "sg:address":"8 Raymond Dr",
    "sg:city":"Rochester",
    "sg:classifiers":[
        {
            "category":"Building & Trades",
            "subcategory":"Pest Control",
            "type":"Services"
        }
    ],
    "sg:phone":"+1 585 436 8359",
    "sg:postcode":"14624",
    "sg:province":"NY",
    "wof:name":"X X-Terminator",
    "wof:placetype":"venue"
},
  "geometry": {"coordinates":[-77.672929,43.136471],"type":"Point"}
}