{
  "type": "Feature",
  "properties": {
    "addr:full":"99 Washington Ave Albany NY 12210",
    "addr:housenumber":"99",
    "addr:postcode":"12210",
    "addr:street":"Washington Ave",
    "iso:country":"US",
    "sg:address":"99 Washington Ave",
    "sg:city":"Albany",
    "sg:classifiers":[
        {
            "category":"Professional",
            "type":"Services"
        }
    ],
    "sg:phone":"+1 518 432 5205",
    "sg:postcode":"12210",
    "sg:province":"NY",
    "sg:tags":[
        "establishment"
    ],
    "wof:name":"Manhattan Institute-Policy",
    "wof:placetype":"venue"
},
  "geometry": {"coordinates":[-73.760971,42.655443],"type":"Point"}
}