{
  "type": "Feature",
  "properties": {
    "addr:full":"2441 Wallace Ave Bronx NY 10467",
    "addr:housenumber":"2441",
    "addr:postcode":"10467",
    "addr:street":"Wallace Ave",
    "iso:country":"US",
    "sg:address":"2441 Wallace Ave",
    "sg:city":"Bronx",
    "sg:classifiers":[
        {
            "category":"Education",
            "subcategory":"School",
            "type":"Public Place"
        }
    ],
    "sg:phone":"+1 718 653 1237",
    "sg:postcode":"10467",
    "sg:province":"NY",
    "wof:name":"F D Whalen Junior High School",
    "wof:placetype":"venue"
},
  "geometry": {"coordinates":[-73.864627,40.862401],"type":"Point"}
}