{
  "type": "Feature",
  "properties": {
    "iso:country":"US",
    "sg:address":"2 Woodcrest Cir",
    "sg:city":"Fairport",
    "sg:classifiers":[
        {
            "category":"Social Services",
            "subcategory":"Child Care",
            "type":"Services"
        }
    ],
    "sg:phone":"+1 585 388 5909",
    "sg:postcode":"14450",
    "sg:province":"NY",
    "wof:name":"Child Care Connections",
    "wof:placetype":"venue"
},
  "geometry": {"coordinates":[-77.462186,43.085629],"type":"Point"}
}