{
  "type": "Feature",
  "properties": {
    "iso:country":"US",
    "sg:address":"955 Montauk Hwy",
    "sg:city":"Oakdale",
    "sg:classifiers":[
        {
            "category":"Autos & Motor Vehicles",
            "subcategory":"Fuel & Gas Station",
            "type":"Retail Goods"
        },
        {
            "category":"Retail",
            "subcategory":"Auto Repair",
            "type":"Services"
        }
    ],
    "sg:phone":"+1 631 567 4440",
    "sg:postcode":"11769",
    "sg:province":"NY",
    "sg:tags":[
        "repairing",
        "automobile",
        "gasoline"
    ],
    "wof:name":"Doug's Automotive",
    "wof:placetype":"venue"
},
  "geometry": {"coordinates":[-73.12130000000001,40.7384],"type":"Point"}
}