{
  "type": "Feature",
  "properties": {
    "iso:country":"US",
    "sg:address":"1117 Central Ave",
    "sg:city":"Albany",
    "sg:classifiers":[
        {
            "category":"Retail",
            "subcategory":"Auto Repair",
            "type":"Services"
        }
    ],
    "sg:phone":"+1 518 437 1771",
    "sg:postcode":"12205",
    "sg:province":"NY",
    "sg:tags":[
        "repairing",
        "automobile"
    ],
    "wof:name":"LA Barge's Tire & Auto",
    "wof:placetype":"venue"
},
  "geometry": {"coordinates":[-73.800173,42.688779],"type":"Point"}
}