{
  "type": "Feature",
  "properties": {
    "addr:full":"838 Broadway New York NY 10003",
    "addr:housenumber":"838",
    "addr:postcode":"10003",
    "addr:street":"Broadway",
    "iso:country":"US",
    "sg:address":"838 Broadway",
    "sg:city":"New York",
    "sg:classifiers":[
        {
            "category":"Professional",
            "subcategory":"Art Services",
            "type":"Services"
        }
    ],
    "sg:phone":"+1   ",
    "sg:postcode":"10003",
    "sg:province":"NY",
    "sg:tags":[
        "commercial",
        "design"
    ],
    "wof:name":"Studioworks",
    "wof:placetype":"venue"
},
  "geometry": {"coordinates":[-73.990981,40.733311],"type":"Point"}
}