{
  "type": "Feature",
  "properties": {
    "iso:country":"US",
    "sg:address":"111 Neptune Ave",
    "sg:city":"Brooklyn",
    "sg:classifiers":[
        {
            "category":"Building & Trades",
            "subcategory":"Construction",
            "type":"Services"
        }
    ],
    "sg:phone":"+1 718 646 0400",
    "sg:postcode":"11235",
    "sg:province":"NY",
    "sg:tags":[
        "house"
    ],
    "wof:name":"Singh Pinder and Swaran",
    "wof:placetype":"venue"
},
  "geometry": {"coordinates":[-73.95861600000001,40.582321],"type":"Point"}
}