{
  "type": "Feature",
  "properties": {
    "addr:full":"1091 Yonkers Ave Yonkers NY 10704",
    "addr:housenumber":"1091",
    "addr:postcode":"10704",
    "addr:street":"Yonkers Ave",
    "iso:country":"US",
    "sg:address":"1091 Yonkers Ave",
    "sg:city":"Yonkers",
    "sg:classifiers":[
        {
            "category":"Communications",
            "type":"Services"
        }
    ],
    "sg:phone":"+1 914 237 5189",
    "sg:postcode":"10704",
    "sg:province":"NY",
    "wof:name":"Smart Tel Communications",
    "wof:placetype":"venue"
},
  "geometry": {"coordinates":[-73.85548,40.913526],"type":"Point"}
}