{
  "type": "Feature",
  "properties": {
    "addr:full":"10430 Rockaway Boulevard Ozone Park NY 11417",
    "addr:housenumber":"10430",
    "addr:postcode":"11417",
    "addr:street":"Rockaway Boulevard",
    "iso:country":"US",
    "sg:address":"10430 Rockaway Boulevard",
    "sg:city":"Ozone Park",
    "sg:classifiers":[
        {
            "category":"Organizations",
            "subcategory":"Religious Organization",
            "type":"Services"
        }
    ],
    "sg:phone":"+1 718 845 7325",
    "sg:postcode":"11417",
    "sg:province":"NY",
    "sg:website":"www.watchtower.org",
    "wof:name":"Kingdom Hall of Jehovah's Witnesses Ozone Park",
    "wof:placetype":"venue"
},
  "geometry": {"coordinates":[-73.834497,40.67883],"type":"Point"}
}