{
  "type": "Feature",
  "properties": {
    "addr:full":"4604 Nixon Park Dr Syracuse NY 13215",
    "addr:housenumber":"4604",
    "addr:postcode":"13215",
    "addr:street":"Nixon Park Dr",
    "iso:country":"US",
    "sg:address":"4604 Nixon Park Dr",
    "sg:city":"Syracuse",
    "sg:classifiers":[
        {
            "category":"Building & Trades",
            "subcategory":"Construction",
            "type":"Services"
        }
    ],
    "sg:phone":"+1 315 469 7788",
    "sg:postcode":"13215",
    "sg:province":"NY",
    "sg:tags":[
        "general",
        "contractor"
    ],
    "wof:name":"Ken Whiting & Son Contracting",
    "wof:placetype":"venue"
},
  "geometry": {"coordinates":[-76.200898,42.987122],"type":"Point"}
}