{
  "type": "Feature",
  "properties": {
    "iso:country":"US",
    "sg:address":"765 Fdr Dr",
    "sg:city":"New York",
    "sg:classifiers":[
        {
            "category":"Banks & Credit Unions",
            "subcategory":"Financial Services",
            "type":"Services"
        }
    ],
    "sg:phone":"+1 973 332 8846",
    "sg:postcode":"10009",
    "sg:province":"NY",
    "sg:tags":[
        "trust",
        "investment",
        "real estate"
    ],
    "wof:name":"Torres Osiris",
    "wof:placetype":"venue"
},
  "geometry": {"coordinates":[-73.97416,40.722966],"type":"Point"}
}