{
  "type": "Feature",
  "properties": {
    "addr:full":"37 E 64th St New York NY 10065",
    "addr:housenumber":"37",
    "addr:postcode":"10065",
    "addr:street":"E 64Th St",
    "iso:country":"US",
    "sg:address":"37 E 64th St",
    "sg:city":"New York",
    "sg:classifiers":[
        {
            "category":"Travel",
            "subcategory":"Hotels & Motels",
            "type":"Entertainment"
        }
    ],
    "sg:phone":"+1 212 734 9100",
    "sg:postcode":"10065",
    "sg:province":"NY",
    "wof:name":"Plaza Athenee",
    "wof:placetype":"venue"
},
  "geometry": {"coordinates":[-73.968294,40.766615],"type":"Point"}
}