{
  "type": "Feature",
  "properties": {
    "addr:full":"575 8th Ave New York NY 10018",
    "addr:housenumber":"575",
    "addr:postcode":"10018",
    "addr:street":"8Th Ave",
    "iso:country":"US",
    "sg:address":"575 8th Ave",
    "sg:city":"New York",
    "sg:classifiers":[
        {
            "category":"Shopping",
            "subcategory":"Mobile Phones",
            "type":"Retail Goods"
        }
    ],
    "sg:phone":"+1 877 423 5366",
    "sg:postcode":"10018",
    "sg:province":"NY",
    "wof:name":"3 Pt Wireless",
    "wof:placetype":"venue"
},
  "geometry": {"coordinates":[-73.991711,40.754888],"type":"Point"}
}