{
  "type": "Feature",
  "properties": {
    "iso:country":"US",
    "sg:address":"5 Cypress Ct",
    "sg:city":"Selden",
    "sg:classifiers":[
        {
            "category":"Local Transit",
            "type":"Transportation"
        }
    ],
    "sg:phone":"+1   ",
    "sg:postcode":"11784",
    "sg:province":"NY",
    "sg:tags":[
        "passenger"
    ],
    "wof:name":"F G Services",
    "wof:placetype":"venue"
},
  "geometry": {"coordinates":[-73.007047,40.860276],"type":"Point"}
}