{
  "type": "Feature",
  "properties": {
    "addr:full":"1067 Union Ave Newburgh NY 12550",
    "addr:housenumber":"1067",
    "addr:postcode":"12550",
    "addr:street":"Union Ave",
    "iso:country":"US",
    "sg:address":"1067 Union Ave",
    "sg:city":"Newburgh",
    "sg:classifiers":[
        {
            "category":"Shopping",
            "subcategory":"Jewelry",
            "type":"Retail Goods"
        }
    ],
    "sg:phone":"+1 845 566 9983",
    "sg:postcode":"12550",
    "sg:province":"NY",
    "wof:name":"Silver & Gold Connection",
    "wof:placetype":"venue"
},
  "geometry": {"coordinates":[-74.0299,41.5131],"type":"Point"}
}