{
  "type": "Feature",
  "properties": {
    "addr:full":"15 W 10th St New York NY 10011",
    "addr:housenumber":"15",
    "addr:postcode":"10011",
    "addr:street":"W 10Th St",
    "iso:country":"US",
    "sg:address":"15 W 10th St",
    "sg:city":"New York",
    "sg:classifiers":[
        {
            "category":"Shopping",
            "subcategory":"Clothing, Apparel, & Fashions",
            "type":"Retail Goods"
        }
    ],
    "sg:phone":"+1   ",
    "sg:postcode":"10011",
    "sg:province":"NY",
    "wof:name":"Ruben Zurch Inc",
    "wof:placetype":"venue"
},
  "geometry": {"coordinates":[-73.998329,40.734657],"type":"Point"}
}