{
  "type": "Feature",
  "properties": {
    "addr:full":"350 Broadway Ste 407 New York NY 10013",
    "addr:housenumber":"350;407",
    "addr:postcode":"10013",
    "addr:street":"Broadway Ste",
    "iso:country":"US",
    "sg:address":"350 Broadway Ste 407",
    "sg:city":"New York",
    "sg:classifiers":[
        {
            "category":"Professional",
            "subcategory":"Lawyer & Legal Services",
            "type":"Services"
        }
    ],
    "sg:phone":"+1 646 770 0989",
    "sg:postcode":"10013",
    "sg:province":"NY",
    "sg:tags":[
        "litigation"
    ],
    "wof:name":"Perez & Cede?o",
    "wof:placetype":"venue"
},
  "geometry": {"coordinates":[-74.00397700000001,40.716904],"type":"Point"}
}