{
  "type": "Feature",
  "properties": {
    "iso:country":"US",
    "sg:address":"12 Hillswood Rd",
    "sg:city":"Rochester",
    "sg:classifiers":[
        {
            "category":"Health Services",
            "subcategory":"Doctor",
            "type":"Services"
        }
    ],
    "sg:phone":"+1 585 258 4999",
    "sg:postcode":"14624",
    "sg:province":"NY",
    "sg:tags":[
        "medical"
    ],
    "wof:name":"Joseph M Marino MD",
    "wof:placetype":"venue"
},
  "geometry": {"coordinates":[-77.704892,43.128903],"type":"Point"}
}