{
  "type": "Feature",
  "properties": {
    "iso:country":"US",
    "sg:address":"2 Church St",
    "sg:city":"Hoosick Falls",
    "sg:classifiers":[
        {
            "category":"Food & Beverages",
            "subcategory":"Groceries & Convenience Stores",
            "type":"Retail Goods"
        }
    ],
    "sg:phone":"+1 518 686 9944",
    "sg:postcode":"12090",
    "sg:province":"NY",
    "sg:website":"www.stewartsicecream.com",
    "wof:name":"Stewart's Shop",
    "wof:placetype":"venue"
},
  "geometry": {"coordinates":[-73.35167199999999,42.902026],"type":"Point"}
}