{
  "type": "Feature",
  "properties": {
    "iso:country":"US",
    "sg:address":"52 Kellogg Rd",
    "sg:city":"New Hartford",
    "sg:classifiers":[
        {
            "category":"Personal",
            "type":"Services"
        }
    ],
    "sg:phone":"+1 315 732 3496",
    "sg:postcode":"13413",
    "sg:province":"NY",
    "sg:tags":[
        "control",
        "weight"
    ],
    "wof:name":"L A Weight Loss Ctr Inc",
    "wof:placetype":"venue"
},
  "geometry": {"coordinates":[-75.275975,43.054193],"type":"Point"}
}