{
  "type": "Feature",
  "properties": {
    "iso:country":"US",
    "sg:address":"24 W Main St",
    "sg:city":"Marcellus",
    "sg:classifiers":[
        {
            "category":"Building & Trades",
            "subcategory":"Construction",
            "type":"Services"
        }
    ],
    "sg:phone":"+1 315 673 3940",
    "sg:postcode":"13108",
    "sg:province":"NY",
    "sg:tags":[
        "house",
        "contractor",
        "roofing"
    ],
    "wof:name":"Jerry Beaulieu Construction",
    "wof:placetype":"venue"
},
  "geometry": {"coordinates":[-76.34091600000001,42.982358],"type":"Point"}
}