{
  "type": "Feature",
  "properties": {
    "addr:full":"40 Leversee Rd Troy NY 12182",
    "addr:housenumber":"40",
    "addr:postcode":"12182",
    "addr:street":"Leversee Rd",
    "iso:country":"US",
    "sg:address":"40 Leversee Rd",
    "sg:city":"Troy",
    "sg:classifiers":[
        {
            "category":"Banks & Credit Unions",
            "subcategory":"Bank",
            "type":"Services"
        }
    ],
    "sg:phone":"+1 518 235 0417",
    "sg:postcode":"12182",
    "sg:province":"NY",
    "sg:tags":[
        "state",
        "commercial"
    ],
    "wof:name":"Hsbc Bank USA National Assn",
    "wof:placetype":"venue"
},
  "geometry": {"coordinates":[-73.651194,42.790673],"type":"Point"}
}