{
  "type": "Feature",
  "properties": {
    "addr:full":"1385 Metropolitan Ave Bronx NY 10462",
    "addr:housenumber":"1385",
    "addr:postcode":"10462",
    "addr:street":"Metropolitan Ave",
    "iso:country":"US",
    "sg:address":"1385 Metropolitan Ave",
    "sg:city":"Bronx",
    "sg:classifiers":[
        {
            "category":"Coffee & Tea",
            "type":"Food & Drink"
        }
    ],
    "sg:menulink":"http://www.allmenus.com/ny/bronx/113229-starbucks-coffee/menu/",
    "sg:phone":"+1 718 319 1702",
    "sg:postcode":"10462",
    "sg:province":"NY",
    "sg:tags":[
        "american"
    ],
    "wof:name":"Starbucks Coffee",
    "wof:placetype":"venue"
},
  "geometry": {"coordinates":[-73.861192,40.835241],"type":"Point"}
}