{
  "type": "Feature",
  "properties": {
    "addr:full":"12 Benjamin St Albany NY 12202",
    "addr:housenumber":"12",
    "addr:postcode":"12202",
    "addr:street":"Benjamin St",
    "iso:country":"US",
    "sg:address":"12 Benjamin St",
    "sg:city":"Albany",
    "sg:classifiers":[
        {
            "category":"Organizations",
            "subcategory":"Religious Organization",
            "type":"Services"
        }
    ],
    "sg:phone":"+1 518 462 6759",
    "sg:postcode":"12202",
    "sg:province":"NY",
    "sg:tags":[
        "church"
    ],
    "wof:name":"Elijah Full Gospel Baptist Chr",
    "wof:placetype":"venue"
},
  "geometry": {"coordinates":[-73.762956,42.636854],"type":"Point"}
}