{
  "type": "Feature",
  "properties": {
    "iso:country":"US",
    "sg:address":"1791 Grand Island Blvd",
    "sg:city":"Grand Island",
    "sg:classifiers":[
        {
            "category":"Personal",
            "subcategory":"Beauty Salon",
            "type":"Services"
        }
    ],
    "sg:phone":"+1 716 773 5888",
    "sg:postcode":"14072",
    "sg:province":"NY",
    "wof:name":"Carlo's Hair Fashions",
    "wof:placetype":"venue"
},
  "geometry": {"coordinates":[-78.952684,43.011075],"type":"Point"}
}