{
  "type": "Feature",
  "properties": {
    "iso:country":"US",
    "sg:address":"816 Wyckoff Avenue",
    "sg:city":"Brooklyn",
    "sg:classifiers":[
        {
            "category":"Food & Beverages",
            "subcategory":"Groceries & Convenience Stores",
            "type":"Retail Goods"
        }
    ],
    "sg:phone":"+1 718 417 0594",
    "sg:postcode":"11237",
    "sg:province":"NY",
    "wof:name":"Latino Grocery Food",
    "wof:placetype":"venue"
},
  "geometry": {"coordinates":[-73.908162,40.697757],"type":"Point"}
}