{
  "type": "Feature",
  "properties": {
    "iso:country":"US",
    "sg:address":"106 Pearl St",
    "sg:city":"Buffalo",
    "sg:classifiers":[
        {
            "category":"Building & Trades",
            "subcategory":"Cleaning & Sanitation",
            "type":"Services"
        }
    ],
    "sg:phone":"+1 716 656 9482",
    "sg:postcode":"14224",
    "sg:province":"NY",
    "sg:tags":[
        "maintenance"
    ],
    "wof:name":"Pure Perfection",
    "wof:placetype":"venue"
},
  "geometry": {"coordinates":[-78.721048,42.859429],"type":"Point"}
}