{
  "type": "Feature",
  "properties": {
    "iso:country":"US",
    "sg:address":"407 Gidney Ave",
    "sg:city":"Newburgh",
    "sg:classifiers":[
        {
            "category":"Health Services",
            "subcategory":"Doctor",
            "type":"Services"
        }
    ],
    "sg:phone":"+1   ",
    "sg:postcode":"12550",
    "sg:province":"NY",
    "sg:tags":[
        "medical"
    ],
    "wof:name":"Goldman Gregory I",
    "wof:placetype":"venue"
},
  "geometry": {"coordinates":[-74.026027,41.513046],"type":"Point"}
}