{
  "type": "Feature",
  "properties": {
    "iso:country":"US",
    "sg:address":"213 E 188th St",
    "sg:city":"Bronx",
    "sg:classifiers":[
        {
            "category":"Home & Garden",
            "subcategory":"Furniture",
            "type":"Retail Goods"
        }
    ],
    "sg:phone":"+1   ",
    "sg:postcode":"10458",
    "sg:province":"NY",
    "sg:tags":[
        "household",
        "dealer"
    ],
    "wof:name":"Furniture Express",
    "wof:placetype":"venue"
},
  "geometry": {"coordinates":[-73.896646,40.861156],"type":"Point"}
}