{
  "type": "Feature",
  "properties": {
    "iso:country":"US",
    "sg:address":"4400 S Salina St",
    "sg:city":"Syracuse",
    "sg:classifiers":[
        {
            "category":"Home & Garden",
            "subcategory":"Building Materials",
            "type":"Retail Goods"
        }
    ],
    "sg:phone":"+1 315 492 9511",
    "sg:postcode":"13205",
    "sg:province":"NY",
    "sg:tags":[
        "paint"
    ],
    "wof:name":"Purcell's Wallpaper & Paint",
    "wof:placetype":"venue"
},
  "geometry": {"coordinates":[-76.14301399999999,43.004221],"type":"Point"}
}