{
  "type": "Feature",
  "properties": {
    "addr:full":"75 Benjamin St Albany NY 12202",
    "addr:housenumber":"75",
    "addr:postcode":"12202",
    "addr:street":"Benjamin St",
    "iso:country":"US",
    "sg:address":"75 Benjamin St",
    "sg:city":"Albany",
    "sg:classifiers":[
        {
            "category":"Manufacturing",
            "subcategory":"Printing",
            "type":"Manufacturing & Wholesale Goods"
        }
    ],
    "sg:phone":"+1   ",
    "sg:postcode":"12202",
    "sg:province":"NY",
    "sg:tags":[
        "digital"
    ],
    "sg:website":"www.digital-page.com",
    "wof:name":"Digital Page LLC",
    "wof:placetype":"venue"
},
  "geometry": {"coordinates":[-73.763627,42.636353],"type":"Point"}
}