{
  "type": "Feature",
  "properties": {
    "addr:full":"37 E 1 St New York NY 10003",
    "addr:housenumber":"37;1",
    "addr:postcode":"10003",
    "addr:street":"E;St",
    "iso:country":"US",
    "sg:address":"37 E 1 St",
    "sg:city":"New York",
    "sg:classifiers":[
        {
            "category":"Shopping",
            "subcategory":"Gifts & Souvenirs",
            "type":"Retail Goods"
        }
    ],
    "sg:phone":"+1 212 674 2125",
    "sg:postcode":"10003",
    "sg:province":"NY",
    "sg:tags":[
        "shop"
    ],
    "wof:name":"Nix Wares",
    "wof:placetype":"venue"
},
  "geometry": {"coordinates":[-73.988878,40.723428],"type":"Point"}
}