{
  "type": "Feature",
  "properties": {
    "iso:country":"US",
    "sg:address":"51 Bedford Rd",
    "sg:city":"Katonah",
    "sg:classifiers":[
        {
            "category":"Professional",
            "subcategory":"Lawyer & Legal Services",
            "type":"Services"
        }
    ],
    "sg:phone":"+1 914 232 3185",
    "sg:postcode":"10536",
    "sg:province":"NY",
    "sg:tags":[
        "attorney"
    ],
    "wof:name":"Thomas T Antonecchia",
    "wof:placetype":"venue"
},
  "geometry": {"coordinates":[-73.68459199999999,41.255182],"type":"Point"}
}