{
  "type": "Feature",
  "properties": {
    "iso:country":"US",
    "sg:address":"2070 Grand Concourse",
    "sg:city":"Bronx",
    "sg:classifiers":[
        {
            "category":"Health Services",
            "subcategory":"Doctor",
            "type":"Services"
        }
    ],
    "sg:phone":"+1 718 716 8400",
    "sg:postcode":"10457",
    "sg:province":"NY",
    "sg:tags":[
        "dentist"
    ],
    "wof:name":"Same Day Oral Surgery",
    "wof:placetype":"venue"
},
  "geometry": {"coordinates":[-73.903175,40.852671],"type":"Point"}
}