{
  "type": "Feature",
  "properties": {
    "iso:country":"US",
    "sg:address":"1600 Church Ave",
    "sg:city":"Brooklyn",
    "sg:classifiers":[
        {
            "category":"Professional",
            "subcategory":"Employment Agencies",
            "type":"Services"
        }
    ],
    "sg:phone":"+1 718 693 2600",
    "sg:postcode":"11226",
    "sg:province":"NY",
    "wof:name":"Miracles Can Happen Employment Agency",
    "wof:placetype":"venue"
},
  "geometry": {"coordinates":[-73.964699,40.648701],"type":"Point"}
}