{
  "type": "Feature",
  "properties": {
    "iso:country":"US",
    "sg:address":"601 E 79th St",
    "sg:city":"Brooklyn",
    "sg:classifiers":[
        {
            "category":"Banks & Credit Unions",
            "subcategory":"Bank",
            "type":"Services"
        }
    ],
    "sg:phone":"+1 718 444 3311",
    "sg:postcode":"11236",
    "sg:province":"NY",
    "sg:tags":[
        "broker",
        "mortgage"
    ],
    "wof:name":"Greenbae Mortgage LLC",
    "wof:placetype":"venue"
},
  "geometry": {"coordinates":[-73.91571399999999,40.636506],"type":"Point"}
}