{
  "type": "Feature",
  "properties": {
    "addr:full":"130 Gramatan Ave Mt Vernon NY 10550",
    "addr:housenumber":"130",
    "addr:postcode":"10550",
    "addr:street":"Gramatan Ave",
    "iso:country":"US",
    "sg:address":"130 Gramatan Ave",
    "sg:city":"Mt Vernon",
    "sg:classifiers":[
        {
            "category":"Retail",
            "subcategory":"Self-service Laundry",
            "type":"Services"
        }
    ],
    "sg:phone":"+1 914 664 5317",
    "sg:postcode":"10550",
    "sg:province":"NY",
    "wof:name":"Laundry Basket",
    "wof:placetype":"venue"
},
  "geometry": {"coordinates":[-73.83753,40.915928],"type":"Point"}
}