{
  "type": "Feature",
  "properties": {
    "iso:country":"US",
    "sg:address":"6705 Heise Rd",
    "sg:city":"Clarence Center",
    "sg:classifiers":[
        {
            "category":"Recreation",
            "type":"Entertainment"
        }
    ],
    "sg:phone":"+1 716 741 4223",
    "sg:postcode":"14032",
    "sg:province":"NY",
    "sg:tags":[
        "stable"
    ],
    "wof:name":"Volante Farm",
    "wof:placetype":"venue"
},
  "geometry": {"coordinates":[-78.65246999999999,43.022128],"type":"Point"}
}