{
  "type": "Feature",
  "properties": {
    "addr:full":"405 N State St Syracuse NY 13203",
    "addr:housenumber":"405",
    "addr:postcode":"13203",
    "addr:street":"N State St",
    "iso:country":"US",
    "sg:address":"405 N State St",
    "sg:city":"Syracuse",
    "sg:classifiers":[
        {
            "category":"Personal",
            "subcategory":"Beauty Salon",
            "type":"Services"
        }
    ],
    "sg:phone":"+1 315 426 1903",
    "sg:postcode":"13203",
    "sg:province":"NY",
    "wof:name":"Aissa Professional African",
    "wof:placetype":"venue"
},
  "geometry": {"coordinates":[-76.15057299999999,43.055035],"type":"Point"}
}