{
  "type": "Feature",
  "properties": {
    "iso:country":"US",
    "sg:address":"25 Little Plains Rd",
    "sg:city":"Huntington",
    "sg:classifiers":[
        {
            "category":"Education",
            "subcategory":"School",
            "type":"Public Place"
        }
    ],
    "sg:phone":"+1 631 266 4400",
    "sg:postcode":"11743",
    "sg:province":"NY",
    "wof:name":"Developmental Disabilities Institute Inc",
    "wof:placetype":"venue"
},
  "geometry": {"coordinates":[-73.375603,40.851898],"type":"Point"}
}