{
  "type": "Feature",
  "properties": {
    "iso:country":"US",
    "sg:address":"175 W Merrick Rd",
    "sg:city":"Freeport",
    "sg:classifiers":[
        {
            "category":"Health Services",
            "subcategory":"Doctor",
            "type":"Services"
        }
    ],
    "sg:phone":"+1 516 379 7550",
    "sg:postcode":"11520",
    "sg:province":"NY",
    "sg:tags":[
        "physician",
        "surgeon"
    ],
    "sg:website":"www.rehabphysician.com",
    "wof:name":"South Shore Medical & Rehab",
    "wof:placetype":"venue"
},
  "geometry": {"coordinates":[-73.58617700000001,40.653155],"type":"Point"}
}