{
  "type": "Feature",
  "properties": {
    "iso:country":"US",
    "sg:address":"49 Lafayette Ave",
    "sg:city":"Suffern",
    "sg:classifiers":[
        {
            "category":"Home & Garden",
            "subcategory":"Carpets & Floor Coverings",
            "type":"Retail Goods"
        }
    ],
    "sg:phone":"+1 845 357 3381",
    "sg:postcode":"10901",
    "sg:province":"NY",
    "sg:tags":[
        "dealer",
        "rug"
    ],
    "wof:name":"Bill's Linoleum Shop",
    "wof:placetype":"venue"
},
  "geometry": {"coordinates":[-74.151698,41.115472],"type":"Point"}
}