{
  "type": "Feature",
  "properties": {
    "iso:country":"US",
    "sg:address":"666 State Hwy 211",
    "sg:city":"Middletown",
    "sg:classifiers":[
        {
            "category":"Personal",
            "subcategory":"Beauty Salon",
            "type":"Services"
        }
    ],
    "sg:phone":"+1 845 695 0616",
    "sg:postcode":"10941",
    "sg:province":"NY",
    "sg:tags":[
        "manicuring"
    ],
    "wof:name":"Top Citi Nails",
    "wof:placetype":"venue"
},
  "geometry": {"coordinates":[-74.36197,41.465295],"type":"Point"}
}