{
  "type": "Feature",
  "properties": {
    "iso:country":"US",
    "sg:address":"19 Eaton Ave",
    "sg:city":"Norwich",
    "sg:classifiers":[
        {
            "category":"Banks & Credit Unions",
            "subcategory":"Investment Brokerage",
            "type":"Services"
        }
    ],
    "sg:phone":"+1 607 336 2434",
    "sg:postcode":"13815",
    "sg:province":"NY",
    "sg:tags":[
        "security"
    ],
    "wof:name":"Joseph A Gunther Cfp",
    "wof:placetype":"venue"
},
  "geometry": {"coordinates":[-75.525409,42.527875],"type":"Point"}
}