{
  "type": "Feature",
  "properties": {
    "iso:country":"US",
    "sg:address":"848 Franklin Ave",
    "sg:city":"Bohemia",
    "sg:classifiers":[
        {
            "category":"Professional",
            "subcategory":"Computer Services",
            "type":"Services"
        }
    ],
    "sg:phone":"+1 631 567 3455",
    "sg:postcode":"11716",
    "sg:province":"NY",
    "sg:tags":[
        "related"
    ],
    "wof:name":"CJ & J Inc",
    "wof:placetype":"venue"
},
  "geometry": {"coordinates":[-73.101693,40.763435],"type":"Point"}
}