{
  "type": "Feature",
  "properties": {
    "iso:country":"US",
    "sg:address":"1451 Broadway",
    "sg:city":"New York",
    "sg:classifiers":[
        {
            "category":"Real Estate",
            "subcategory":"Real Estate Agent",
            "type":"Services"
        }
    ],
    "sg:phone":"+1 212 790 1400",
    "sg:postcode":"10036",
    "sg:province":"NY",
    "wof:name":"C/O Rosenthal & Rosenthal",
    "wof:placetype":"venue"
},
  "geometry": {"coordinates":[-73.98639799999999,40.755804],"type":"Point"}
}