{
  "type": "Feature",
  "properties": {
    "addr:full":"1679 E 3rd St Brooklyn NY 11230",
    "addr:housenumber":"1679",
    "addr:postcode":"11230",
    "addr:street":"E 3Rd St",
    "iso:country":"US",
    "sg:address":"1679 E 3rd St",
    "sg:city":"Brooklyn",
    "sg:classifiers":[
        {
            "category":"Health Services",
            "subcategory":"Doctor",
            "type":"Services"
        }
    ],
    "sg:phone":"+1 718 998 1337",
    "sg:postcode":"11230",
    "sg:province":"NY",
    "sg:tags":[
        "medical"
    ],
    "wof:name":"Israel Ben-David",
    "wof:placetype":"venue"
},
  "geometry": {"coordinates":[-73.97113299999999,40.611224],"type":"Point"}
}