{
  "type": "Feature",
  "properties": {
    "iso:country":"US",
    "sg:address":"23 S Church St",
    "sg:city":"Honeoye Falls",
    "sg:classifiers":[
        {
            "category":"Real Estate",
            "subcategory":"Surveying",
            "type":"Services"
        }
    ],
    "sg:phone":"+1 585 624 4740",
    "sg:postcode":"14472",
    "sg:province":"NY",
    "sg:tags":[
        "surveyor"
    ],
    "wof:name":"Arthur M English Land Surveyor",
    "wof:placetype":"venue"
},
  "geometry": {"coordinates":[-77.590431,42.94935],"type":"Point"}
}