{
  "type": "Feature",
  "properties": {
    "addr:full":"53 Radcliffe Ave Farmingdale NY 11735",
    "addr:housenumber":"53",
    "addr:postcode":"11735",
    "addr:street":"Radcliffe Ave",
    "iso:country":"US",
    "sg:address":"53 Radcliffe Ave",
    "sg:city":"Farmingdale",
    "sg:classifiers":[
        {
            "category":"Manufacturing",
            "subcategory":"Toys & Sporting Goods",
            "type":"Manufacturing & Wholesale Goods"
        }
    ],
    "sg:phone":"+1 516 249 8019",
    "sg:postcode":"11735",
    "sg:province":"NY",
    "sg:tags":[
        "tackle",
        "fishing",
        "mfg"
    ],
    "sg:website":"www.superstrikelures.com",
    "wof:name":"Super Strike Lures Inc",
    "wof:placetype":"venue"
},
  "geometry": {"coordinates":[-73.44699799999999,40.71856],"type":"Point"}
}