{
  "type": "Feature",
  "properties": {
    "iso:country":"US",
    "sg:address":"1947 Bath Ave",
    "sg:city":"Brooklyn",
    "sg:classifiers":[
        {
            "category":"Retail",
            "subcategory":"Photofinishing",
            "type":"Services"
        }
    ],
    "sg:phone":"+1   ",
    "sg:postcode":"11214",
    "sg:province":"NY",
    "sg:tags":[
        "laboratory"
    ],
    "wof:name":"Photo Photo",
    "wof:placetype":"venue"
},
  "geometry": {"coordinates":[-74.003067,40.60226],"type":"Point"}
}