{
  "type": "Feature",
  "properties": {
    "addr:full":"1156 Abbott Rd Buffalo NY 14220",
    "addr:housenumber":"1156",
    "addr:postcode":"14220",
    "addr:street":"Abbott Rd",
    "iso:country":"US",
    "sg:address":"1156 Abbott Rd",
    "sg:city":"Buffalo",
    "sg:classifiers":[
        {
            "category":"Building & Trades",
            "subcategory":"Plumbing",
            "type":"Services"
        }
    ],
    "sg:phone":"+1 716 823 0361",
    "sg:postcode":"14220",
    "sg:province":"NY",
    "wof:name":"Domes Heating",
    "wof:placetype":"venue"
},
  "geometry": {"coordinates":[-78.80619799999999,42.833199],"type":"Point"}
}