{
  "type": "Feature",
  "properties": {
    "addr:full":"81 Warren St New York NY 10007",
    "addr:housenumber":"81",
    "addr:postcode":"10007",
    "addr:street":"Warren St",
    "iso:country":"US",
    "sg:address":"81 Warren St",
    "sg:city":"New York",
    "sg:classifiers":[
        {
            "category":"Restaurant",
            "type":"Food & Drink"
        }
    ],
    "sg:menulink":"http://www.allmenus.com/ny/new-york/247028-il-giglio/menu/",
    "sg:phone":"+1 212 571 5555",
    "sg:postcode":"10007",
    "sg:province":"NY",
    "sg:tags":[
        "italian"
    ],
    "wof:name":"Il Giglio",
    "wof:placetype":"venue"
},
  "geometry": {"coordinates":[-74.01051200000001,40.715083],"type":"Point"}
}