{
  "type": "Feature",
  "properties": {
    "addr:full":"1166 Liberty Ave Brooklyn NY 11208",
    "addr:housenumber":"1166",
    "addr:postcode":"11208",
    "addr:street":"Liberty Ave",
    "iso:country":"US",
    "sg:address":"1166 Liberty Ave",
    "sg:city":"Brooklyn",
    "sg:classifiers":[
        {
            "category":"Shopping",
            "subcategory":"Clothing, Apparel, & Fashions",
            "type":"Retail Goods"
        }
    ],
    "sg:phone":"+1 718 348 9018",
    "sg:postcode":"11208",
    "sg:province":"NY",
    "sg:tags":[
        "ready"
    ],
    "wof:name":"Blue Angel Boutique No 2",
    "wof:placetype":"venue"
},
  "geometry": {"coordinates":[-73.86700399999999,40.678712],"type":"Point"}
}