{
  "type": "Feature",
  "properties": {
    "iso:country":"US",
    "sg:address":"137 State Hwy 284",
    "sg:city":"Unionville",
    "sg:classifiers":[
        {
            "category":"Shopping",
            "subcategory":"Used Merchandise",
            "type":"Retail Goods"
        }
    ],
    "sg:phone":"+1 845 726 3355",
    "sg:postcode":"10988",
    "sg:province":"NY",
    "sg:tags":[
        "antique"
    ],
    "sg:website":"www.booksold.com",
    "wof:name":"Old Books",
    "wof:placetype":"venue"
},
  "geometry": {"coordinates":[-74.56158499999999,41.302644],"type":"Point"}
}