{
  "type": "Feature",
  "properties": {
    "addr:full":"185 E 123rd Street New York NY 10035",
    "addr:housenumber":"185",
    "addr:postcode":"10035",
    "addr:street":"E 123Rd Street",
    "iso:country":"US",
    "sg:address":"185 E 123rd Street",
    "sg:city":"New York",
    "sg:classifiers":[
        {
            "category":"Building & Trades",
            "subcategory":"Construction",
            "type":"Services"
        }
    ],
    "sg:phone":"+1 212 876 8807",
    "sg:postcode":"10035",
    "sg:province":"NY",
    "sg:tags":[
        "contractor"
    ],
    "wof:name":"Insider Sam",
    "wof:placetype":"venue"
},
  "geometry": {"coordinates":[-73.93717100000001,40.802687],"type":"Point"}
}