{
  "type": "Feature",
  "properties": {
    "iso:country":"US",
    "sg:address":"20006 Linden Blvd",
    "sg:city":"Jamaica",
    "sg:classifiers":[
        {
            "category":"Education",
            "subcategory":"Kindergarten",
            "type":"Public Place"
        }
    ],
    "sg:phone":"+1 718 276 5566",
    "sg:postcode":"11412",
    "sg:province":"NY",
    "sg:tags":[
        "school",
        "driving"
    ],
    "sg:website":"www.access2drive.info",
    "wof:name":"ACCESS DRIVING SCHOOL",
    "wof:placetype":"venue"
},
  "geometry": {"coordinates":[-73.752387,40.694256],"type":"Point"}
}