{
  "type": "Feature",
  "properties": {
    "addr:full":"5 Lupi Ct Mahopac NY 10541",
    "addr:housenumber":"5",
    "addr:postcode":"10541",
    "addr:street":"Lupi Ct",
    "iso:country":"US",
    "sg:address":"5 Lupi Ct",
    "sg:city":"Mahopac",
    "sg:classifiers":[
        {
            "category":"Freight",
            "type":"Transportation"
        }
    ],
    "sg:phone":"+1   ",
    "sg:postcode":"10541",
    "sg:province":"NY",
    "sg:tags":[
        "storage",
        "facility"
    ],
    "wof:name":"Storage USA",
    "wof:placetype":"venue"
},
  "geometry": {"coordinates":[-73.74830799999999,41.355451],"type":"Point"}
}