{
  "type": "Feature",
  "properties": {
    "iso:country":"US",
    "sg:address":"255 Kings Hwy",
    "sg:city":"Brooklyn",
    "sg:classifiers":[
        {
            "category":"Wholesale",
            "subcategory":"Groceries",
            "type":"Manufacturing & Wholesale Goods"
        }
    ],
    "sg:phone":"+1 718 714 5456",
    "sg:postcode":"11223",
    "sg:province":"NY",
    "sg:tags":[
        "grocer"
    ],
    "wof:name":"Prima Provision",
    "wof:placetype":"venue"
},
  "geometry": {"coordinates":[-73.98139999999999,40.6054],"type":"Point"}
}