{
  "type": "Feature",
  "properties": {
    "iso:country":"US",
    "sg:address":"145 Fulton St",
    "sg:city":"New York",
    "sg:classifiers":[
        {
            "category":"Restaurant",
            "type":"Food & Drink"
        }
    ],
    "sg:phone":"+1 212 732 5078",
    "sg:postcode":"10038",
    "sg:province":"NY",
    "sg:tags":[
        "pizza"
    ],
    "wof:name":"Solace Pizza & Pasta",
    "wof:placetype":"venue"
},
  "geometry": {"coordinates":[-74.008698,40.710602],"type":"Point"}
}