{
  "type": "Feature",
  "properties": {
    "addr:full":"240 Center Dr Riverhead NY 11901",
    "addr:housenumber":"240",
    "addr:postcode":"11901",
    "addr:street":"Center Dr",
    "iso:country":"US",
    "sg:address":"240 Center Dr",
    "sg:city":"Riverhead",
    "sg:classifiers":[
        {
            "category":"Restaurant",
            "type":"Food & Drink"
        }
    ],
    "sg:phone":"+1 631 727 5170",
    "sg:postcode":"11901",
    "sg:province":"NY",
    "wof:name":"Criminal Court Coffee Shop",
    "wof:placetype":"venue"
},
  "geometry": {"coordinates":[-72.664597,40.915001],"type":"Point"}
}