{
  "type": "Feature",
  "properties": {
    "iso:country":"US",
    "sg:address":"23 Quaker Ridge",
    "sg:city":"New Rochelle",
    "sg:classifiers":[
        {
            "category":"Restaurant",
            "type":"Food & Drink"
        }
    ],
    "sg:menulink":"http://www.allmenus.com/ny/new-rochelle/107182-soup-man/menu/",
    "sg:phone":"+1 914 636 1368",
    "sg:postcode":"10804",
    "sg:province":"NY",
    "sg:tags":[
        "soup",
        "american",
        "salad"
    ],
    "wof:name":"Soup Man",
    "wof:placetype":"venue"
},
  "geometry": {"coordinates":[-73.795517,40.94767],"type":"Point"}
}