{
  "type": "Feature",
  "properties": {
    "addr:full":"90 Dongan Ave Albany NY 12202",
    "addr:housenumber":"90",
    "addr:postcode":"12202",
    "addr:street":"Dongan Ave",
    "iso:country":"US",
    "sg:address":"90 Dongan Ave",
    "sg:city":"Albany",
    "sg:classifiers":[
        {
            "category":"Wholesale",
            "subcategory":"Fruits & Vegetables",
            "type":"Manufacturing & Wholesale Goods"
        }
    ],
    "sg:phone":"+1 518 472 9188",
    "sg:postcode":"12202",
    "sg:province":"NY",
    "wof:name":"Joseph Aiello & Sons Inc",
    "wof:placetype":"venue"
},
  "geometry": {"coordinates":[-73.753317,42.641823],"type":"Point"}
}