{
  "type": "Feature",
  "properties": {
    "addr:full":"1360 State Hwy 5 Silver Creek NY 14136",
    "addr:housenumber":"1360",
    "addr:postcode":"14136",
    "addr:street":"State Hwy 5",
    "iso:country":"US",
    "sg:address":"1360 State Hwy 5",
    "sg:city":"Silver Creek",
    "sg:classifiers":[
        {
            "category":"Shopping",
            "subcategory":"Discount & Variety Stores",
            "type":"Retail Goods"
        }
    ],
    "sg:phone":"+1 716 934 4131",
    "sg:postcode":"14136",
    "sg:province":"NY",
    "wof:name":"Dollar General",
    "wof:placetype":"venue"
},
  "geometry": {"coordinates":[-79.145999,42.550784],"type":"Point"}
}