{
  "type": "Feature",
  "properties": {
    "addr:full":"2000 Corporate Dr Orangeburg NY 10962",
    "addr:housenumber":"2000",
    "addr:postcode":"10962",
    "addr:street":"Corporate Dr",
    "iso:country":"US",
    "sg:address":"2000 Corporate Dr",
    "sg:city":"Orangeburg",
    "sg:classifiers":[
        {
            "category":"Utilities",
            "subcategory":"Mobile Phone",
            "type":"Services"
        }
    ],
    "sg:phone":"+1   ",
    "sg:postcode":"10962",
    "sg:province":"NY",
    "sg:tags":[
        "communication",
        "radio"
    ],
    "wof:name":"Nmcc Subsidiary Company",
    "wof:placetype":"venue"
},
  "geometry": {"coordinates":[-73.983661,41.035312],"type":"Point"}
}