{
  "type": "Feature",
  "properties": {
    "iso:country":"US",
    "sg:address":"44-02 23rd st",
    "sg:city":"Long Island City",
    "sg:classifiers":[
        {
            "category":"Arts & Performance",
            "subcategory":"Art Gallery",
            "type":"Entertainment"
        }
    ],
    "sg:phone":"+1 718 249 9359",
    "sg:postcode":"11101",
    "sg:province":"NY",
    "sg:website":"www.galleryaes.com",
    "wof:name":"AES Gallery",
    "wof:placetype":"venue"
},
  "geometry": {"coordinates":[-73.94434099999999,40.748952],"type":"Point"}
}