{
  "type": "Feature",
  "properties": {
    "iso:country":"US",
    "sg:address":"51 Hawkins Rd",
    "sg:city":"Nineveh",
    "sg:classifiers":[
        {
            "category":"Travel",
            "subcategory":"Campground",
            "type":"Entertainment"
        }
    ],
    "sg:phone":"+1   ",
    "sg:postcode":"13813",
    "sg:province":"NY",
    "sg:tags":[
        "trailer"
    ],
    "wof:name":"Mellkel Enterprise",
    "wof:placetype":"venue"
},
  "geometry": {"coordinates":[-75.527463,42.164627],"type":"Point"}
}