{
  "type": "Feature",
  "properties": {
    "addr:full":"935 Schenck Ave Brooklyn NY 11207",
    "addr:housenumber":"935",
    "addr:postcode":"11207",
    "addr:street":"Schenck Ave",
    "iso:country":"US",
    "sg:address":"935 Schenck Ave",
    "sg:city":"Brooklyn",
    "sg:classifiers":[
        {
            "category":"Manufacturing",
            "subcategory":"Printing",
            "type":"Manufacturing & Wholesale Goods"
        }
    ],
    "sg:phone":"+1   ",
    "sg:postcode":"11207",
    "sg:province":"NY",
    "sg:tags":[
        "commercial"
    ],
    "wof:name":"Wedding Plan Plus Inc",
    "wof:placetype":"venue"
},
  "geometry": {"coordinates":[-73.881198,40.657781],"type":"Point"}
}