{
  "type": "Feature",
  "properties": {
    "iso:country":"US",
    "sg:address":"5254 State Hwy 9n",
    "sg:city":"Corinth",
    "sg:classifiers":[
        {
            "category":"Travel",
            "subcategory":"Campground",
            "type":"Entertainment"
        }
    ],
    "sg:phone":"+1 518 654 9995",
    "sg:postcode":"12822",
    "sg:province":"NY",
    "wof:name":"River Road Campgrounds",
    "wof:placetype":"venue"
},
  "geometry": {"coordinates":[-73.844007,43.235957],"type":"Point"}
}