{
  "type": "Feature",
  "properties": {
    "iso:country":"US",
    "sg:address":"1 Constitution Ct",
    "sg:city":"Ballston Spa",
    "sg:classifiers":[
        {
            "category":"Building & Trades",
            "subcategory":"Construction",
            "type":"Services"
        }
    ],
    "sg:phone":"+1 518 885 4232",
    "sg:postcode":"12020",
    "sg:province":"NY",
    "sg:tags":[
        "house",
        "builder",
        "operative"
    ],
    "wof:name":"Frank Rossi Builders",
    "wof:placetype":"venue"
},
  "geometry": {"coordinates":[-73.871115,43.006253],"type":"Point"}
}