{
  "type": "Feature",
  "properties": {
    "iso:country":"US",
    "sg:address":"341 Knickerbocker Ave",
    "sg:city":"Brooklyn",
    "sg:classifiers":[
        {
            "category":"Health Services",
            "subcategory":"Doctor",
            "type":"Services"
        }
    ],
    "sg:phone":"+1 718 386 1100",
    "sg:postcode":"11237",
    "sg:province":"NY",
    "wof:name":"Phoenix Medical Center Inc",
    "wof:placetype":"venue"
},
  "geometry": {"coordinates":[-73.922096,40.701099],"type":"Point"}
}