{
  "type": "Feature",
  "properties": {
    "addr:full":"5019 Skillman Ave  Woodside NY 11377",
    "addr:housenumber":"5019",
    "addr:postcode":"11377",
    "addr:street":"Skillman Ave",
    "iso:country":"US",
    "sg:address":"5019 Skillman Ave ",
    "sg:city":"Woodside",
    "sg:classifiers":[
        {
            "category":"Restaurant",
            "type":"Food & Drink"
        }
    ],
    "sg:menulink":"http://www.allmenus.com/ny/queens/293287-tj-asian-bistro/menu/",
    "sg:phone":"+1 718 205 2088",
    "sg:postcode":"11377",
    "sg:province":"NY",
    "sg:tags":[
        "noodle",
        "bar",
        "salad",
        "sushi",
        "japanese",
        "asian"
    ],
    "wof:name":"T.J Asian Bistro",
    "wof:placetype":"venue"
},
  "geometry": {"coordinates":[-73.91404199999999,40.746245],"type":"Point"}
}