{
  "type": "Feature",
  "properties": {
    "addr:full":"11 Penn Plz New York NY 10001",
    "addr:housenumber":"11",
    "addr:postcode":"10001",
    "addr:street":"Penn Plz",
    "iso:country":"US",
    "sg:address":"11 Penn Plz",
    "sg:city":"New York",
    "sg:classifiers":[
        {
            "category":"Professional",
            "type":"Services"
        }
    ],
    "sg:phone":"+1 212 946 2898",
    "sg:postcode":"10001",
    "sg:province":"NY",
    "sg:tags":[
        "establishment"
    ],
    "wof:name":"Customer Strategies Worldwide",
    "wof:placetype":"venue"
},
  "geometry": {"coordinates":[-73.991563,40.749705],"type":"Point"}
}