{
  "type": "Feature",
  "properties": {
    "iso:country":"US",
    "sg:address":"295 Putnam Ave",
    "sg:city":"Brooklyn",
    "sg:classifiers":[
        {
            "category":"Retail",
            "subcategory":"Portrait Studio",
            "type":"Services"
        }
    ],
    "sg:phone":"+1 718 623 6737",
    "sg:postcode":"11216",
    "sg:province":"NY",
    "sg:tags":[
        "photography"
    ],
    "wof:name":"Jose Vaz",
    "wof:placetype":"venue"
},
  "geometry": {"coordinates":[-73.947017,40.68438],"type":"Point"}
}