{
  "type": "Feature",
  "properties": {
    "addr:full":"139 Remsen Rd Yonkers NY 10710",
    "addr:housenumber":"139",
    "addr:postcode":"10710",
    "addr:street":"Remsen Rd",
    "iso:country":"US",
    "sg:address":"139 Remsen Rd",
    "sg:city":"Yonkers",
    "sg:classifiers":[
        {
            "category":"Building & Trades",
            "subcategory":"Construction",
            "type":"Services"
        }
    ],
    "sg:phone":"+1 914 771 7600",
    "sg:postcode":"10710",
    "sg:province":"NY",
    "sg:tags":[
        "contractor"
    ],
    "wof:name":"Splash Pools & Decks",
    "wof:placetype":"venue"
},
  "geometry": {"coordinates":[-73.83731299999999,40.978201],"type":"Point"}
}