{
  "type": "Feature",
  "properties": {
    "addr:full":"29 Horseshoe Hill Rd Pound Ridge NY 10576",
    "addr:housenumber":"29",
    "addr:postcode":"10576",
    "addr:street":"Horseshoe Hill Rd",
    "iso:country":"US",
    "sg:address":"29 Horseshoe Hill Rd",
    "sg:city":"Pound Ridge",
    "sg:classifiers":[
        {
            "category":"Wholesale",
            "subcategory":"Apparel",
            "type":"Manufacturing & Wholesale Goods"
        }
    ],
    "sg:phone":"+1 914 764 1757",
    "sg:postcode":"10576",
    "sg:province":"NY",
    "sg:tags":[
        "clothing",
        "italian"
    ],
    "wof:name":"Five Tuna Ltd Inc",
    "wof:placetype":"venue"
},
  "geometry": {"coordinates":[-73.571164,41.195165],"type":"Point"}
}