{
  "type": "Feature",
  "properties": {
    "addr:full":"11 Ford Ave Oneonta NY 13820",
    "addr:housenumber":"11",
    "addr:postcode":"13820",
    "addr:street":"Ford Ave",
    "iso:country":"US",
    "sg:address":"11 Ford Ave",
    "sg:city":"Oneonta",
    "sg:classifiers":[
        {
            "category":"Museum",
            "type":"Entertainment"
        }
    ],
    "sg:phone":"+1   ",
    "sg:postcode":"13820",
    "sg:province":"NY",
    "sg:tags":[
        "gallery"
    ],
    "sg:website":"www.upstatehistory.org",
    "wof:name":"Upstate History Alliance",
    "wof:placetype":"venue"
},
  "geometry": {"coordinates":[-75.061792,42.457339],"type":"Point"}
}