{
  "type": "Feature",
  "properties": {
    "addr:full":"648 Broadway New York NY 10012",
    "addr:housenumber":"648",
    "addr:postcode":"10012",
    "addr:street":"Broadway",
    "iso:country":"US",
    "sg:address":"648 Broadway",
    "sg:city":"New York",
    "sg:classifiers":[
        {
            "category":"Arts & Performance",
            "subcategory":"Theater",
            "type":"Entertainment"
        }
    ],
    "sg:phone":"+1 212 475 0415",
    "sg:postcode":"10012",
    "sg:province":"NY",
    "sg:tags":[
        "bureau"
    ],
    "wof:name":"Jazz Tree",
    "wof:placetype":"venue"
},
  "geometry": {"coordinates":[-73.995293,40.727034],"type":"Point"}
}