{
  "type": "Feature",
  "properties": {
    "addr:full":"109 Ingraham St #309 Brooklyn NY 11237",
    "addr:housenumber":"109",
    "addr:postcode":"11237",
    "addr:street":"Ingraham St # 309",
    "iso:country":"US",
    "sg:address":"109 Ingraham St #309",
    "sg:city":"Brooklyn",
    "sg:classifiers":[
        {
            "category":"Shopping",
            "subcategory":"Clothing, Apparel, & Fashions",
            "type":"Retail Goods"
        }
    ],
    "sg:phone":"+1 858 952 1032",
    "sg:postcode":"11237",
    "sg:province":"NY",
    "sg:tags":[
        "accessory"
    ],
    "sg:website":"baggubag.com",
    "wof:name":"BAGGU",
    "wof:placetype":"venue"
},
  "geometry": {"coordinates":[-73.929295,40.707501],"type":"Point"}
}