{
  "type": "Feature",
  "properties": {
    "addr:full":"6907 50th Ave Woodside NY 11377",
    "addr:housenumber":"6907",
    "addr:postcode":"11377",
    "addr:street":"50Th Ave",
    "iso:country":"US",
    "sg:address":"6907 50th Ave",
    "sg:city":"Woodside",
    "sg:classifiers":[
        {
            "category":"Shopping",
            "subcategory":"Beauty & Cosmetics",
            "type":"Retail Goods"
        }
    ],
    "sg:phone":"+1 718 478 7184",
    "sg:postcode":"11377",
    "sg:province":"NY",
    "sg:tags":[
        "supply"
    ],
    "wof:name":"Umi Beauty Supply",
    "wof:placetype":"venue"
},
  "geometry": {"coordinates":[-73.89569899999999,40.737],"type":"Point"}
}