{
  "type": "Feature",
  "properties": {
    "iso:country":"US",
    "sg:address":"520 Elmwood Ave Ste 7",
    "sg:city":"Buffalo",
    "sg:classifiers":[
        {
            "category":"Professional",
            "subcategory":"Advertising",
            "type":"Services"
        }
    ],
    "sg:phone":"+1 716 507 4474",
    "sg:postcode":"14222",
    "sg:province":"NY",
    "sg:tags":[
        "marketing"
    ],
    "sg:website":"www.blockclubcreative.com",
    "wof:name":"Block Club, Inc.",
    "wof:placetype":"venue"
},
  "geometry": {"coordinates":[-78.877467,42.911154],"type":"Point"}
}