{
  "type": "Feature",
  "properties": {
    "iso:country":"US",
    "sg:address":"730 Columbus Ave",
    "sg:city":"New York",
    "sg:classifiers":[
        {
            "category":"Parking",
            "type":"Transportation"
        }
    ],
    "sg:phone":"+1 212 280 6849",
    "sg:postcode":"10025",
    "sg:province":"NY",
    "sg:tags":[
        "garage"
    ],
    "wof:name":"Imperial Parking Systems",
    "wof:placetype":"venue"
},
  "geometry": {"coordinates":[-73.967855,40.792413],"type":"Point"}
}