{
  "type": "Feature",
  "properties": {
    "addr:full":"1585 Broadway New York NY 10036",
    "addr:housenumber":"1585",
    "addr:postcode":"10036",
    "addr:street":"Broadway",
    "iso:country":"US",
    "sg:address":"1585 Broadway",
    "sg:city":"New York",
    "sg:classifiers":[
        {
            "category":"Professional",
            "subcategory":"Lawyer & Legal Services",
            "type":"Services"
        }
    ],
    "sg:phone":"+1 212 969 5670",
    "sg:postcode":"10036",
    "sg:province":"NY",
    "sg:tags":[
        "attorney"
    ],
    "wof:name":"Gerald L Shargel Law Office",
    "wof:placetype":"venue"
},
  "geometry": {"coordinates":[-73.98503599999999,40.75957],"type":"Point"}
}