{
  "type": "Feature",
  "properties": {
    "iso:country":"US",
    "sg:address":"233 Federal Hill Rd",
    "sg:city":"Brewster",
    "sg:classifiers":[
        {
            "category":"Recreation",
            "type":"Entertainment"
        }
    ],
    "sg:phone":"+1 845 279 7179",
    "sg:postcode":"10509",
    "sg:province":"NY",
    "sg:tags":[
        "course",
        "golf"
    ],
    "wof:name":"Morefar Golf Course",
    "wof:placetype":"venue"
},
  "geometry": {"coordinates":[-73.54612299999999,41.406015],"type":"Point"}
}