{
  "type": "Feature",
  "properties": {
    "iso:country":"US",
    "sg:address":"107 W 25th St",
    "sg:city":"New York",
    "sg:classifiers":[
        {
            "category":"Manufacturing",
            "subcategory":"Furniture",
            "type":"Manufacturing & Wholesale Goods"
        }
    ],
    "sg:phone":"+1   ",
    "sg:postcode":"10001",
    "sg:province":"NY",
    "sg:tags":[
        "mfg",
        "foam",
        "mattress"
    ],
    "wof:name":"Dixiefoam Beds",
    "wof:placetype":"venue"
},
  "geometry": {"coordinates":[-73.994541,40.745375],"type":"Point"}
}