{
  "type": "Feature",
  "properties": {
    "iso:country":"US",
    "sg:address":"26 Genesee Park Blvd",
    "sg:city":"Rochester",
    "sg:classifiers":[
        {
            "category":"Building & Trades",
            "subcategory":"Landscaping Services",
            "type":"Services"
        }
    ],
    "sg:phone":"+1 585 370 8583",
    "sg:postcode":"14611",
    "sg:province":"NY",
    "sg:tags":[
        "lawn",
        "maintenance"
    ],
    "wof:name":"Cassara Lawn Landscape",
    "wof:placetype":"venue"
},
  "geometry": {"coordinates":[-77.63932800000001,43.126411],"type":"Point"}
}