{
  "type": "Feature",
  "properties": {
    "addr:full":"261 Ave U Brooklyn NY 11223",
    "addr:housenumber":"261",
    "addr:postcode":"11223",
    "addr:street":"Ave U",
    "iso:country":"US",
    "sg:address":"261 Ave U",
    "sg:city":"Brooklyn",
    "sg:classifiers":[
        {
            "category":"Food & Beverages",
            "subcategory":"Bakery",
            "type":"Retail Goods"
        }
    ],
    "sg:phone":"+1   ",
    "sg:postcode":"11223",
    "sg:province":"NY",
    "wof:name":"Nuccios Bakery",
    "wof:placetype":"venue"
},
  "geometry": {"coordinates":[-73.97444299999999,40.596908],"type":"Point"}
}