{
  "type": "Feature",
  "properties": {
    "addr:full":"325 Park Ave Huntington NY 11743",
    "addr:housenumber":"325",
    "addr:postcode":"11743",
    "addr:street":"Park Ave",
    "iso:country":"US",
    "sg:address":"325 Park Ave",
    "sg:city":"Huntington",
    "sg:classifiers":[
        {
            "category":"Health Services",
            "subcategory":"Doctor",
            "type":"Services"
        }
    ],
    "sg:phone":"+1 631 351 3802",
    "sg:postcode":"11743",
    "sg:province":"NY",
    "sg:tags":[
        "physician",
        "surgeon"
    ],
    "wof:name":"Grace E Reina MD",
    "wof:placetype":"venue"
},
  "geometry": {"coordinates":[-73.417608,40.877804],"type":"Point"}
}