{
  "type": "Feature",
  "properties": {
    "iso:country":"US",
    "sg:address":"367 Windsor Hwy",
    "sg:city":"New Windsor",
    "sg:classifiers":[
        {
            "category":"Retail",
            "subcategory":"Laundry & Dry Cleaning",
            "type":"Services"
        }
    ],
    "sg:phone":"+1 845 565 5960",
    "sg:postcode":"12553",
    "sg:province":"NY",
    "sg:tags":[
        "cleaners"
    ],
    "wof:name":"Tops Cleaners",
    "wof:placetype":"venue"
},
  "geometry": {"coordinates":[-74.055708,41.45697],"type":"Point"}
}