{
  "type": "Feature",
  "properties": {
    "addr:full":"908 Ten Eyck Ave Schenectady NY 12303",
    "addr:housenumber":"908",
    "addr:postcode":"12303",
    "addr:street":"Ten Eyck Ave",
    "iso:country":"US",
    "sg:address":"908 Ten Eyck Ave",
    "sg:city":"Schenectady",
    "sg:classifiers":[
        {
            "category":"Travel",
            "subcategory":"Travel Agent",
            "type":"Entertainment"
        }
    ],
    "sg:phone":"+1   ",
    "sg:postcode":"12303",
    "sg:province":"NY",
    "sg:tags":[
        "agency"
    ],
    "wof:name":"Cruises & Tours Galore",
    "wof:placetype":"venue"
},
  "geometry": {"coordinates":[-73.937433,42.791447],"type":"Point"}
}