{
  "type": "Feature",
  "properties": {
    "iso:country":"US",
    "sg:address":"1002 Morris Park Avenue",
    "sg:city":"Bronx",
    "sg:classifiers":[
        {
            "category":"Food & Beverages",
            "subcategory":"Liquor & Beverages",
            "type":"Retail Goods"
        }
    ],
    "sg:phone":"+1 718 239 8816",
    "sg:postcode":"10462",
    "sg:province":"NY",
    "sg:tags":[
        "beer",
        "spirit",
        "wine"
    ],
    "wof:name":"Mor Park Fine Wines & Liquors",
    "wof:placetype":"venue"
},
  "geometry": {"coordinates":[-73.856047,40.848056],"type":"Point"}
}