{
  "type": "Feature",
  "properties": {
    "iso:country":"US",
    "sg:address":"5801 Palisade Ave",
    "sg:city":"Bronx",
    "sg:classifiers":[
        {
            "category":"Professional",
            "type":"Services"
        },
        {
            "category":"Organizations",
            "subcategory":"Religious Organization",
            "type":"Services"
        }
    ],
    "sg:phone":"+1 718 796 7038",
    "sg:postcode":"10471",
    "sg:province":"NY",
    "sg:tags":[
        "establishment"
    ],
    "wof:name":"Passionate Residence",
    "wof:placetype":"venue"
},
  "geometry": {"coordinates":[-73.907411,40.910233],"type":"Point"}
}