{
  "type": "Feature",
  "properties": {
    "addr:full":"115 State Hwy 30 Schoharie NY 12157",
    "addr:housenumber":"115",
    "addr:postcode":"12157",
    "addr:street":"State Hwy 30",
    "iso:country":"US",
    "sg:address":"115 State Hwy 30",
    "sg:city":"Schoharie",
    "sg:classifiers":[
        {
            "category":"Real Estate",
            "subcategory":"Architect",
            "type":"Services"
        }
    ],
    "sg:phone":"+1 518 295 6440",
    "sg:postcode":"12157",
    "sg:province":"NY",
    "sg:tags":[
        "building",
        "designer"
    ],
    "wof:name":"Robert M Loden LTD",
    "wof:placetype":"venue"
},
  "geometry": {"coordinates":[-74.30444300000001,42.674232],"type":"Point"}
}