{
  "type": "Feature",
  "properties": {
    "iso:country":"US",
    "sg:address":"3 Meserole St",
    "sg:city":"Brooklyn",
    "sg:classifiers":[
        {
            "category":"Shopping",
            "subcategory":"Gifts & Souvenirs",
            "type":"Retail Goods"
        }
    ],
    "sg:phone":"+1 718 302 4690",
    "sg:postcode":"11206",
    "sg:province":"NY",
    "sg:tags":[
        "party",
        "supply"
    ],
    "wof:name":"Vanessa Party Supplies",
    "wof:placetype":"venue"
},
  "geometry": {"coordinates":[-73.948385,40.707662],"type":"Point"}
}