{
  "type": "Feature",
  "properties": {
    "addr:full":"50 Broad St Fl 6 New York NY 10004",
    "addr:housenumber":"50;6",
    "addr:postcode":"10004",
    "addr:street":"Broad St",
    "iso:country":"US",
    "sg:address":"50 Broad St Fl 6",
    "sg:city":"New York",
    "sg:classifiers":[
        {
            "category":"Building & Trades",
            "subcategory":"Construction",
            "type":"Services"
        }
    ],
    "sg:phone":"+1 212 635 0760",
    "sg:postcode":"10004",
    "sg:province":"NY",
    "sg:tags":[
        "contractor"
    ],
    "wof:name":"Builders Group",
    "wof:placetype":"venue"
},
  "geometry": {"coordinates":[-74.01161,40.705864],"type":"Point"}
}