{
  "type": "Feature",
  "properties": {
    "iso:country":"US",
    "sg:address":"1160 E Jericho Tpke",
    "sg:city":"Huntington",
    "sg:classifiers":[
        {
            "category":"Real Estate",
            "subcategory":"Real Estate Services",
            "type":"Services"
        }
    ],
    "sg:phone":"+1 631 385 7894",
    "sg:postcode":"11743",
    "sg:province":"NY",
    "sg:tags":[
        "abstract",
        "title"
    ],
    "wof:name":"Land Bound",
    "wof:placetype":"venue"
},
  "geometry": {"coordinates":[-73.36998699999999,40.835261],"type":"Point"}
}