{
  "type": "Feature",
  "properties": {
    "addr:full":"215 W 125th St New York NY 10027",
    "addr:housenumber":"215",
    "addr:postcode":"10027",
    "addr:street":"W 125Th St",
    "iso:country":"US",
    "sg:address":"215 W 125th St",
    "sg:city":"New York",
    "sg:classifiers":[
        {
            "category":"Restaurant",
            "type":"Food & Drink"
        }
    ],
    "sg:menulink":"http://www.allmenus.com/ny/new-york/188967-mcdonalds/menu/",
    "sg:postcode":"10027",
    "sg:province":"NY",
    "sg:tags":[
        "burger",
        "american"
    ],
    "wof:name":"McDonald's",
    "wof:placetype":"venue"
},
  "geometry": {"coordinates":[-73.948932,40.809706],"type":"Point"}
}