{
  "type": "Feature",
  "properties": {
    "addr:full":"6936 Sybilla Street Forest Hills NY 11375",
    "addr:housenumber":"6936",
    "addr:postcode":"11375",
    "addr:street":"Sybilla Street",
    "iso:country":"US",
    "sg:address":"6936 Sybilla Street",
    "sg:city":"Forest Hills",
    "sg:classifiers":[
        {
            "category":"Building & Trades",
            "subcategory":"Construction",
            "type":"Services"
        }
    ],
    "sg:phone":"+1 718 261 1139",
    "sg:postcode":"11375",
    "sg:province":"NY",
    "sg:tags":[
        "contractor"
    ],
    "wof:name":"Ram Rock Contrctng Company",
    "wof:placetype":"venue"
},
  "geometry": {"coordinates":[-73.85501600000001,40.709094],"type":"Point"}
}