{
  "type": "Feature",
  "properties": {
    "iso:country":"US",
    "sg:address":"18 Willow Ave",
    "sg:city":"Larchmont",
    "sg:classifiers":[
        {
            "category":"Professional",
            "subcategory":"Management & Consulting",
            "type":"Services"
        }
    ],
    "sg:phone":"+1 914 833 7827",
    "sg:postcode":"10538",
    "sg:province":"NY",
    "sg:tags":[
        "consultant"
    ],
    "wof:name":"D F Group Consulting",
    "wof:placetype":"venue"
},
  "geometry": {"coordinates":[-73.749358,40.924288],"type":"Point"}
}