{
  "type": "Feature",
  "properties": {
    "iso:country":"US",
    "sg:address":"71 Lafayette Ave",
    "sg:city":"Suffern",
    "sg:classifiers":[
        {
            "category":"Banks & Credit Unions",
            "subcategory":"Bank",
            "type":"Services"
        }
    ],
    "sg:phone":"+1 845 369 8350",
    "sg:postcode":"10901",
    "sg:province":"NY",
    "wof:name":"Provident Bank",
    "wof:placetype":"venue"
},
  "geometry": {"coordinates":[-74.15060200000001,41.115086],"type":"Point"}
}