{
  "type": "Feature",
  "properties": {
    "iso:country":"US",
    "sg:address":"4055 Main St",
    "sg:city":"Warrensburg",
    "sg:classifiers":[
        {
            "category":"Building & Trades",
            "subcategory":"Construction",
            "type":"Services"
        }
    ],
    "sg:phone":"+1 518 623 4142",
    "sg:postcode":"12885",
    "sg:province":"NY",
    "sg:tags":[
        "carpentry",
        "contractor"
    ],
    "wof:name":"Warren County Storehouse",
    "wof:placetype":"venue"
},
  "geometry": {"coordinates":[-73.77843,43.498358],"type":"Point"}
}