{
  "type": "Feature",
  "properties": {
    "iso:country":"US",
    "sg:address":"945 Albany St",
    "sg:city":"Schenectady",
    "sg:classifiers":[
        {
            "category":"Wholesale",
            "subcategory":"Construction Materials",
            "type":"Manufacturing & Wholesale Goods"
        }
    ],
    "sg:phone":"+1 518 381 4222",
    "sg:postcode":"12307",
    "sg:province":"NY",
    "sg:tags":[
        "fence"
    ],
    "wof:name":"Affordable Fence Co",
    "wof:placetype":"venue"
},
  "geometry": {"coordinates":[-73.93225099999999,42.803925],"type":"Point"}
}