{
  "type": "Feature",
  "properties": {
    "addr:full":"263 Floral Ave Johnson City NY 13790",
    "addr:housenumber":"263",
    "addr:postcode":"13790",
    "addr:street":"Floral Ave",
    "iso:country":"US",
    "sg:address":"263 Floral Ave",
    "sg:city":"Johnson City",
    "sg:classifiers":[
        {
            "category":"Restaurant",
            "type":"Food & Drink"
        }
    ],
    "sg:menulink":"http://www.allmenus.com/ny/union/271783-american-calzone/menu/",
    "sg:phone":"+1 607 729 2111",
    "sg:postcode":"13790",
    "sg:province":"NY",
    "sg:tags":[
        "calzones",
        "american",
        "italian",
        "pizza"
    ],
    "wof:name":"American Calzone",
    "wof:placetype":"venue"
},
  "geometry": {"coordinates":[-75.959844,42.10762],"type":"Point"}
}