{
  "type": "Feature",
  "properties": {
    "iso:country":"US",
    "sg:address":"94 Park Rd Exn",
    "sg:city":"Goldens Bridge",
    "sg:classifiers":[
        {
            "category":"Professional",
            "subcategory":"Business Services",
            "type":"Services"
        }
    ],
    "sg:phone":"+1 914 767 3909",
    "sg:postcode":"10526",
    "sg:province":"NY",
    "sg:tags":[
        "interior",
        "consultant",
        "design",
        "decorator"
    ],
    "wof:name":"Dianne Wells Interiors",
    "wof:placetype":"venue"
},
  "geometry": {"coordinates":[-73.670007,41.29676],"type":"Point"}
}