{
  "type": "Feature",
  "properties": {
    "iso:country":"US",
    "sg:address":"18 Corporate Woods Blvd",
    "sg:city":"Albany",
    "sg:classifiers":[
        {
            "category":"Shopping",
            "subcategory":"Stationery & Office Supplies",
            "type":"Retail Goods"
        }
    ],
    "sg:phone":"+1 518 432 7820",
    "sg:postcode":"12211",
    "sg:province":"NY",
    "sg:tags":[
        "educational",
        "material"
    ],
    "wof:name":"Institute For Humanist Studies",
    "wof:placetype":"venue"
},
  "geometry": {"coordinates":[-73.761989,42.680638],"type":"Point"}
}