{
  "type": "Feature",
  "properties": {
    "addr:full":"846 Flushing Avenue Brooklyn NY 11206",
    "addr:housenumber":"846",
    "addr:postcode":"11206",
    "addr:street":"Flushing Avenue",
    "iso:country":"US",
    "sg:address":"846 Flushing Avenue",
    "sg:city":"Brooklyn",
    "sg:classifiers":[
        {
            "category":"Retail",
            "subcategory":"Auto Repair",
            "type":"Services"
        }
    ],
    "sg:phone":"+1 718 453 0621",
    "sg:postcode":"11206",
    "sg:province":"NY",
    "wof:name":"Auto Repair",
    "wof:placetype":"venue"
},
  "geometry": {"coordinates":[-73.937901,40.70155],"type":"Point"}
}