{
  "type": "Feature",
  "properties": {
    "addr:full":"40 W 57 St New York NY 10019",
    "addr:housenumber":"40",
    "addr:postcode":"10019",
    "addr:street":"W 57 St",
    "iso:country":"US",
    "sg:address":"40 W 57 St",
    "sg:city":"New York",
    "sg:classifiers":[
        {
            "category":"Banks & Credit Unions",
            "subcategory":"Investment Brokerage",
            "type":"Services"
        }
    ],
    "sg:phone":"+1 212 261 0275",
    "sg:postcode":"10019",
    "sg:province":"NY",
    "sg:tags":[
        "consultant",
        "planning",
        "financial"
    ],
    "wof:name":"Blank Financial Group",
    "wof:placetype":"venue"
},
  "geometry": {"coordinates":[-73.97563,40.763368],"type":"Point"}
}