{
  "type": "Feature",
  "properties": {
    "addr:full":"7 Haines Ct Carmel NY 10512",
    "addr:housenumber":"7",
    "addr:postcode":"10512",
    "addr:street":"Haines Ct",
    "iso:country":"US",
    "sg:address":"7 Haines Ct",
    "sg:city":"Carmel",
    "sg:classifiers":[
        {
            "category":"Building & Trades",
            "subcategory":"Pest Control",
            "type":"Services"
        }
    ],
    "sg:phone":"+1 845 225 1941",
    "sg:postcode":"10512",
    "sg:province":"NY",
    "wof:name":"Rid-A-Pest",
    "wof:placetype":"venue"
},
  "geometry": {"coordinates":[-73.66145899999999,41.446137],"type":"Point"}
}