{
  "type": "Feature",
  "properties": {
    "iso:country":"US",
    "sg:address":"2530 Boston Rd",
    "sg:city":"Bronx",
    "sg:classifiers":[
        {
            "category":"Wholesale",
            "subcategory":"Fruits & Vegetables",
            "type":"Manufacturing & Wholesale Goods"
        }
    ],
    "sg:phone":"+1 347 945 1540",
    "sg:postcode":"10467",
    "sg:province":"NY",
    "sg:tags":[
        "veggie"
    ],
    "wof:name":"Simply Food & Vegetable",
    "wof:placetype":"venue"
},
  "geometry": {"coordinates":[-73.86439300000001,40.863779],"type":"Point"}
}