{
  "type": "Feature",
  "properties": {
    "iso:country":"US",
    "sg:address":"107 Jersey Ave",
    "sg:city":"Port Jervis",
    "sg:classifiers":[
        {
            "category":"Food & Beverages",
            "subcategory":"Groceries & Convenience Stores",
            "type":"Retail Goods"
        }
    ],
    "sg:phone":"+1   ",
    "sg:postcode":"12771",
    "sg:province":"NY",
    "wof:name":"Save A Lot",
    "wof:placetype":"venue"
},
  "geometry": {"coordinates":[-74.68906800000001,41.369726],"type":"Point"}
}