{
  "type": "Feature",
  "properties": {
    "iso:country":"US",
    "sg:address":"3 Park Ave",
    "sg:city":"Binghamton",
    "sg:classifiers":[
        {
            "category":"Banks & Credit Unions",
            "subcategory":"Investment Brokerage",
            "type":"Services"
        }
    ],
    "sg:phone":"+1 607 771 4146",
    "sg:postcode":"13903",
    "sg:province":"NY",
    "sg:tags":[
        "security"
    ],
    "sg:website":"www.edwardjones.com",
    "wof:name":"Edward Jones",
    "wof:placetype":"venue"
},
  "geometry": {"coordinates":[-75.915464,42.083427],"type":"Point"}
}