{
  "type": "Feature",
  "properties": {
    "addr:full":"1539 Franklin Ave Mineola NY 11501",
    "addr:housenumber":"1539",
    "addr:postcode":"11501",
    "addr:street":"Franklin Ave",
    "iso:country":"US",
    "sg:address":"1539 Franklin Ave",
    "sg:city":"Mineola",
    "sg:classifiers":[
        {
            "category":"Professional",
            "subcategory":"Lawyer & Legal Services",
            "type":"Services"
        }
    ],
    "sg:phone":"+1 516 741 6010",
    "sg:postcode":"11501",
    "sg:province":"NY",
    "wof:name":"Tate Robert E Atty",
    "wof:placetype":"venue"
},
  "geometry": {"coordinates":[-73.638901,40.737999],"type":"Point"}
}