{
  "type": "Feature",
  "properties": {
    "iso:country":"US",
    "sg:address":"282 Timberpoint Rd",
    "sg:city":"East Islip",
    "sg:classifiers":[
        {
            "category":"Professional",
            "subcategory":"Computer Services",
            "type":"Services"
        }
    ],
    "sg:phone":"+1 631 277 4725",
    "sg:postcode":"11730",
    "sg:province":"NY",
    "sg:tags":[
        "design",
        "system"
    ],
    "wof:name":"Soft-Tech Solutions Inc",
    "wof:placetype":"venue"
},
  "geometry": {"coordinates":[-73.170901,40.722186],"type":"Point"}
}