{
  "type": "Feature",
  "properties": {
    "addr:full":"32 Weber Rd Central Square NY 13036",
    "addr:housenumber":"32",
    "addr:postcode":"13036",
    "addr:street":"Weber Rd",
    "iso:country":"US",
    "sg:address":"32 Weber Rd",
    "sg:city":"Central Square",
    "sg:classifiers":[
        {
            "category":"Autos & Motor Vehicles",
            "subcategory":"Boat Sales",
            "type":"Retail Goods"
        }
    ],
    "sg:phone":"+1 315 676 2171",
    "sg:postcode":"13036",
    "sg:province":"NY",
    "sg:tags":[
        "dealer",
        "sales"
    ],
    "sg:website":"www.tradeayacht.com",
    "wof:name":"Trade-A-Yacht",
    "wof:placetype":"venue"
},
  "geometry": {"coordinates":[-76.12854400000001,43.241412],"type":"Point"}
}