{
  "type": "Feature",
  "properties": {
    "addr:full":"421 W 125th St New York NY 10027",
    "addr:housenumber":"421",
    "addr:postcode":"10027",
    "addr:street":"W 125Th St",
    "iso:country":"US",
    "sg:address":"421 W 125th St",
    "sg:city":"New York",
    "sg:classifiers":[
        {
            "category":"Building & Trades",
            "subcategory":"Plumbing",
            "type":"Services"
        }
    ],
    "sg:phone":"+1 212 222 7500",
    "sg:postcode":"10027",
    "sg:province":"NY",
    "sg:tags":[
        "plumbing",
        "contractor"
    ],
    "wof:name":"J & M Plumbing Corp",
    "wof:placetype":"venue"
},
  "geometry": {"coordinates":[-73.954835,40.811724],"type":"Point"}
}