{
  "type": "Feature",
  "properties": {
    "addr:full":"2678 Kingsbridge Ter Bronx NY 10463",
    "addr:housenumber":"2678",
    "addr:postcode":"10463",
    "addr:street":"Kingsbridge Ter",
    "iso:country":"US",
    "sg:address":"2678 Kingsbridge Ter",
    "sg:city":"Bronx",
    "sg:classifiers":[
        {
            "category":"Retail",
            "subcategory":"Laundry & Dry Cleaning",
            "type":"Services"
        }
    ],
    "sg:phone":"+1 718 796 5800",
    "sg:postcode":"10463",
    "sg:province":"NY",
    "sg:tags":[
        "laundromat",
        "coin"
    ],
    "wof:name":"Debdon Laundry Corp Inc",
    "wof:placetype":"venue"
},
  "geometry": {"coordinates":[-73.902569,40.874134],"type":"Point"}
}