{
  "type": "Feature",
  "properties": {
    "addr:full":"5507 Nesconset Hwy Mount Sinai NY 11766",
    "addr:postcode":"5507;11766",
    "addr:street":"Nesconset Hwy",
    "iso:country":"US",
    "sg:address":"5507 Nesconset Hwy",
    "sg:city":"Mount Sinai",
    "sg:classifiers":[
        {
            "category":"Ice Cream",
            "type":"Food & Drink"
        }
    ],
    "sg:menulink":"http://www.allmenus.com/ny/brookhaven/209170-tcby/menu/",
    "sg:phone":"+1 631 474 3345",
    "sg:postcode":"11766",
    "sg:province":"NY",
    "sg:tags":[
        "smoothy",
        "juice",
        "american"
    ],
    "wof:name":"TCBY",
    "wof:placetype":"venue"
},
  "geometry": {"coordinates":[-73.033085,40.931974],"type":"Point"}
}