{
  "type": "Feature",
  "properties": {
    "iso:country":"US",
    "sg:address":"23 Chase Ave",
    "sg:city":"White Plains",
    "sg:classifiers":[
        {
            "category":"Manufacturing",
            "subcategory":"Printing",
            "type":"Manufacturing & Wholesale Goods"
        }
    ],
    "sg:phone":"+1   ",
    "sg:postcode":"10606",
    "sg:province":"NY",
    "sg:tags":[
        "periodical"
    ],
    "wof:name":"Fino Graphic Conslts",
    "wof:placetype":"venue"
},
  "geometry": {"coordinates":[-73.785729,41.024319],"type":"Point"}
}