{
  "type": "Feature",
  "properties": {
    "addr:full":"30 2nd St Athens NY 12015",
    "addr:housenumber":"30",
    "addr:postcode":"12015",
    "addr:street":"2Nd St",
    "iso:country":"US",
    "sg:address":"30 2nd St",
    "sg:city":"Athens",
    "sg:classifiers":[
        {
            "category":"Social Services",
            "subcategory":"Child Care",
            "type":"Services"
        }
    ],
    "sg:phone":"+1 518 945 2142",
    "sg:postcode":"12015",
    "sg:province":"NY",
    "sg:tags":[
        "kindergarten",
        "academic",
        "school",
        "day"
    ],
    "wof:name":"Animal Crackers Preschool",
    "wof:placetype":"venue"
},
  "geometry": {"coordinates":[-73.80940200000001,42.260502],"type":"Point"}
}