{
  "type": "Feature",
  "properties": {
    "addr:full":"1556A White Plains Rd Bronx NY 10462",
    "addr:housenumber":"1556a",
    "addr:postcode":"10462",
    "addr:street":"White Plains Rd",
    "iso:country":"US",
    "sg:address":"1556A White Plains Rd",
    "sg:city":"Bronx",
    "sg:classifiers":[
        {
            "category":"Personal",
            "subcategory":"Beauty Salon",
            "type":"Services"
        }
    ],
    "sg:phone":"+1 718 824 0084",
    "sg:postcode":"10462",
    "sg:province":"NY",
    "sg:tags":[
        "hair"
    ],
    "wof:name":"Energy Barber Shop Unisex",
    "wof:placetype":"venue"
},
  "geometry": {"coordinates":[-73.86366099999999,40.839634],"type":"Point"}
}