{
  "type": "Feature",
  "properties": {
    "iso:country":"US",
    "sg:address":"2533 James St",
    "sg:city":"Syracuse",
    "sg:classifiers":[
        {
            "category":"Restaurant",
            "type":"Food & Drink"
        }
    ],
    "sg:phone":"+1 315 463 9422",
    "sg:postcode":"13206",
    "sg:province":"NY",
    "wof:name":"Taste Of Philadelphia",
    "wof:placetype":"venue"
},
  "geometry": {"coordinates":[-76.11059299999999,43.068712],"type":"Point"}
}