{
  "type": "Feature",
  "properties": {
    "iso:country":"US",
    "sg:address":"301 Park Ave",
    "sg:city":"New York",
    "sg:classifiers":[
        {
            "category":"Restaurant",
            "type":"Food & Drink"
        },
        {
            "category":"Food & Beverages",
            "subcategory":"Liquor & Beverages",
            "type":"Retail Goods"
        }
    ],
    "sg:phone":"+1 212 872 4900",
    "sg:postcode":"10022",
    "sg:province":"NY",
    "sg:tags":[
        "beer",
        "steakhouse",
        "spirit",
        "wine"
    ],
    "sg:website":"www.bullandbearsteakhouse.com/in...",
    "wof:name":"Bull and Bear Steakhouse",
    "wof:placetype":"venue"
},
  "geometry": {"coordinates":[-73.97427399999999,40.756641],"type":"Point"}
}