{
  "type": "Feature",
  "properties": {
    "iso:country":"US",
    "sg:address":"110 8th St",
    "sg:city":"Troy",
    "sg:classifiers":[
        {
            "category":"Professional",
            "subcategory":"Research",
            "type":"Services"
        }
    ],
    "sg:phone":"+1 518 276 6021",
    "sg:postcode":"12180",
    "sg:province":"NY",
    "sg:tags":[
        "center"
    ],
    "wof:name":"Design & Manufacturing Instit",
    "wof:placetype":"venue"
},
  "geometry": {"coordinates":[-73.68392900000001,42.731107],"type":"Point"}
}