{
  "type": "Feature",
  "properties": {
    "iso:country":"US",
    "sg:address":"407 S Park Ave",
    "sg:city":"Buffalo",
    "sg:classifiers":[
        {
            "category":"Retail",
            "subcategory":"Auto Repair",
            "type":"Services"
        }
    ],
    "sg:phone":"+1 716 856 0930",
    "sg:postcode":"14204",
    "sg:province":"NY",
    "wof:name":"Fredo's Kar Klinic",
    "wof:placetype":"venue"
},
  "geometry": {"coordinates":[-78.86460099999999,42.871601],"type":"Point"}
}