{
  "type": "Feature",
  "properties": {
    "addr:full":"119 McCormack Dr Lake George NY 12845",
    "addr:housenumber":"119",
    "addr:postcode":"12845",
    "addr:street":"Mccormack Dr",
    "iso:country":"US",
    "sg:address":"119 McCormack Dr",
    "sg:city":"Lake George",
    "sg:classifiers":[
        {
            "category":"Building & Trades",
            "subcategory":"Plumbing",
            "type":"Services"
        }
    ],
    "sg:phone":"+1 518 798 6560",
    "sg:postcode":"12845",
    "sg:province":"NY",
    "sg:tags":[
        "plumbing",
        "contractor"
    ],
    "wof:name":"Anthony Cerrone Plumbing & Htg",
    "wof:placetype":"venue"
},
  "geometry": {"coordinates":[-73.696269,43.362607],"type":"Point"}
}