{
  "type": "Feature",
  "properties": {
    "addr:full":"663 Macelroy Rd Ballston Lake NY 12019",
    "addr:housenumber":"663",
    "addr:postcode":"12019",
    "addr:street":"Macelroy Rd",
    "iso:country":"US",
    "sg:address":"663 Macelroy Rd",
    "sg:city":"Ballston Lake",
    "sg:classifiers":[
        {
            "category":"Building & Trades",
            "subcategory":"Plumbing",
            "type":"Services"
        }
    ],
    "sg:phone":"+1 518 877 0283",
    "sg:postcode":"12019",
    "sg:province":"NY",
    "sg:tags":[
        "contractor"
    ],
    "wof:name":"R T Kramer Energy Systems",
    "wof:placetype":"venue"
},
  "geometry": {"coordinates":[-73.84088800000001,42.904275],"type":"Point"}
}