{
  "type": "Feature",
  "properties": {
    "addr:full":"1545 Four Mile Rd Allegany NY 14706",
    "addr:housenumber":"1545",
    "addr:postcode":"14706",
    "addr:street":"Four Mile Rd",
    "iso:country":"US",
    "sg:address":"1545 Four Mile Rd",
    "sg:city":"Allegany",
    "sg:classifiers":[
        {
            "category":"Place Of Worship",
            "type":"Public Place"
        }
    ],
    "sg:phone":"+1 716 372 9220",
    "sg:postcode":"14706",
    "sg:province":"NY",
    "sg:tags":[
        "church"
    ],
    "wof:name":"Gerard Lefeber",
    "wof:placetype":"venue"
},
  "geometry": {"coordinates":[-78.49301,42.06955],"type":"Point"}
}