{
  "type": "Feature",
  "properties": {
    "iso:country":"US",
    "sg:address":"4 Thistle Way",
    "sg:city":"Binghamton",
    "sg:classifiers":[
        {
            "category":"Building & Trades",
            "subcategory":"Plumbing",
            "type":"Services"
        }
    ],
    "sg:phone":"+1 607 648 6117",
    "sg:postcode":"13901",
    "sg:province":"NY",
    "sg:tags":[
        "contractor"
    ],
    "wof:name":"John Burczak Plumbing & Htg",
    "wof:placetype":"venue"
},
  "geometry": {"coordinates":[-75.852761,42.167297],"type":"Point"}
}