{
  "type": "Feature",
  "properties": {
    "addr:full":"4 E 89 St New York NY 10128",
    "addr:housenumber":"4;89",
    "addr:postcode":"10128",
    "addr:street":"E",
    "iso:country":"US",
    "sg:address":"4 E 89 St",
    "sg:city":"New York",
    "sg:classifiers":[
        {
            "category":"Health Services",
            "subcategory":"Chiropractor",
            "type":"Services"
        }
    ],
    "sg:phone":"+1 212 360 6611",
    "sg:postcode":"10128",
    "sg:province":"NY",
    "wof:name":"Lanfranchi Ronald G",
    "wof:placetype":"venue"
},
  "geometry": {"coordinates":[-73.957509,40.782762],"type":"Point"}
}