{
  "type": "Feature",
  "properties": {
    "addr:full":"31 Beachfern Rd Center Moriches NY 11934",
    "addr:housenumber":"31",
    "addr:postcode":"11934",
    "addr:street":"Beachfern Rd",
    "iso:country":"US",
    "sg:address":"31 Beachfern Rd",
    "sg:city":"Center Moriches",
    "sg:classifiers":[
        {
            "category":"Building & Trades",
            "subcategory":"Construction",
            "type":"Services"
        }
    ],
    "sg:phone":"+1 631 878 0173",
    "sg:postcode":"11934",
    "sg:province":"NY",
    "sg:tags":[
        "nonresidential"
    ],
    "wof:name":"F Gargiulo Construction",
    "wof:placetype":"venue"
},
  "geometry": {"coordinates":[-72.79010100000001,40.799386],"type":"Point"}
}