{
  "type": "Feature",
  "properties": {
    "addr:full":"660 Lakeland Ave Bohemia NY 11716",
    "addr:housenumber":"660",
    "addr:postcode":"11716",
    "addr:street":"Lakeland Ave",
    "iso:country":"US",
    "sg:address":"660 Lakeland Ave",
    "sg:city":"Bohemia",
    "sg:classifiers":[
        {
            "category":"Food & Beverages",
            "subcategory":"Groceries & Convenience Stores",
            "type":"Retail Goods"
        }
    ],
    "sg:phone":"+1 631 563 2605",
    "sg:postcode":"11716",
    "sg:province":"NY",
    "sg:website":"www.7-eleven.com",
    "wof:name":"7-Eleven",
    "wof:placetype":"venue"
},
  "geometry": {"coordinates":[-73.099541,40.763058],"type":"Point"}
}