{
  "type": "Feature",
  "properties": {
    "addr:full":"73 Provost St Brooklyn NY 11222",
    "addr:housenumber":"73",
    "addr:postcode":"11222",
    "addr:street":"Provost St",
    "iso:country":"US",
    "sg:address":"73 Provost St",
    "sg:city":"Brooklyn",
    "sg:classifiers":[
        {
            "category":"Professional",
            "subcategory":"Management & Consulting",
            "type":"Services"
        }
    ],
    "sg:phone":"+1 718 383 8514",
    "sg:postcode":"11222",
    "sg:province":"NY",
    "wof:name":"Kiska Construction Corp USA",
    "wof:placetype":"venue"
},
  "geometry": {"coordinates":[-73.949803,40.734224],"type":"Point"}
}