{
  "type": "Feature",
  "properties": {
    "addr:full":"378 Marcus Garvey Blvd Brooklyn NY 11221",
    "addr:housenumber":"378",
    "addr:postcode":"11221",
    "addr:street":"Marcus Garvey Blvd",
    "iso:country":"US",
    "sg:address":"378 Marcus Garvey Blvd",
    "sg:city":"Brooklyn",
    "sg:classifiers":[
        {
            "category":"Personal",
            "subcategory":"Barber",
            "type":"Services"
        }
    ],
    "sg:phone":"+1 718 484 0929",
    "sg:postcode":"11221",
    "sg:province":"NY",
    "wof:name":"R & B Barber Shop",
    "wof:placetype":"venue"
},
  "geometry": {"coordinates":[-73.93841999999999,40.684034],"type":"Point"}
}