{
  "type": "Feature",
  "properties": {
    "addr:full":"124 E 84th St New York NY 10028",
    "addr:housenumber":"124",
    "addr:postcode":"10028",
    "addr:street":"E 84Th St",
    "iso:country":"US",
    "sg:address":"124 E 84th St",
    "sg:city":"New York",
    "sg:classifiers":[
        {
            "category":"Professional",
            "subcategory":"Lawyer & Legal Services",
            "type":"Services"
        }
    ],
    "sg:phone":"+1 212 879 3451",
    "sg:postcode":"10028",
    "sg:province":"NY",
    "wof:name":"Sukenick Edward",
    "wof:placetype":"venue"
},
  "geometry": {"coordinates":[-73.957067,40.778325],"type":"Point"}
}