{
  "type": "Feature",
  "properties": {
    "addr:full":"1276 Upper Front St Binghamton NY 13901",
    "addr:housenumber":"1276",
    "addr:postcode":"13901",
    "addr:street":"Upper Front St",
    "iso:country":"US",
    "sg:address":"1276 Upper Front St",
    "sg:city":"Binghamton",
    "sg:classifiers":[
        {
            "category":"Shopping",
            "subcategory":"Pharmacy",
            "type":"Retail Goods"
        }
    ],
    "sg:phone":"+1 607 722 4324",
    "sg:postcode":"13901",
    "sg:province":"NY",
    "sg:tags":[
        "drugstore"
    ],
    "sg:website":"www.cvs.com",
    "wof:name":"CVS pharmacy",
    "wof:placetype":"venue"
},
  "geometry": {"coordinates":[-75.89565,42.158112],"type":"Point"}
}