{
  "type": "Feature",
  "properties": {
    "addr:full":"158 Gramatan Ave Mount Vernon NY 10550",
    "addr:housenumber":"158",
    "addr:postcode":"10550",
    "addr:street":"Gramatan Ave",
    "iso:country":"US",
    "sg:address":"158 Gramatan Ave",
    "sg:city":"Mount Vernon",
    "sg:classifiers":[
        {
            "category":"Social Services",
            "subcategory":"Child Care",
            "type":"Services"
        },
        {
            "category":"Education",
            "subcategory":"Vocational School",
            "type":"Public Place"
        }
    ],
    "sg:phone":"+1 914 667 9255",
    "sg:postcode":"10550",
    "sg:province":"NY",
    "sg:tags":[
        "training",
        "processing",
        "datum",
        "day",
        "computer"
    ],
    "wof:name":"American Learning Center",
    "wof:placetype":"venue"
},
  "geometry": {"coordinates":[-73.837513,40.915399],"type":"Point"}
}