{
  "type": "Feature",
  "properties": {
    "iso:country":"US",
    "sg:address":"550 Northern Blvd",
    "sg:city":"Great Neck",
    "sg:classifiers":[
        {
            "category":"Shopping",
            "subcategory":"Clothing, Apparel, & Fashions",
            "type":"Retail Goods"
        }
    ],
    "sg:phone":"+1   ",
    "sg:postcode":"11021",
    "sg:province":"NY",
    "sg:tags":[
        "ready"
    ],
    "wof:name":"En Toto Couture",
    "wof:placetype":"venue"
},
  "geometry": {"coordinates":[-73.71841499999999,40.781284],"type":"Point"}
}