{
  "type": "Feature",
  "properties": {
    "addr:full":"3207 Broadway Astoria NY 11106",
    "addr:housenumber":"3207",
    "addr:postcode":"11106",
    "addr:street":"Broadway",
    "iso:country":"US",
    "sg:address":"3207 Broadway",
    "sg:city":"Astoria",
    "sg:classifiers":[
        {
            "category":"Shopping",
            "subcategory":"Florist",
            "type":"Retail Goods"
        }
    ],
    "sg:phone":"+1 718 274 8463",
    "sg:postcode":"11106",
    "sg:province":"NY",
    "wof:name":"Charles Florals & the Edible Gift",
    "wof:placetype":"venue"
},
  "geometry": {"coordinates":[-73.924536,40.761606],"type":"Point"}
}