{
  "type": "Feature",
  "properties": {
    "iso:country":"US",
    "sg:address":"11 Waverly Place",
    "sg:city":"Manhattan",
    "sg:classifiers":[
        {
            "category":"Real Estate",
            "subcategory":"Real Estate Services",
            "type":"Services"
        }
    ],
    "sg:phone":"+1 212 533 1300",
    "sg:postcode":"10003",
    "sg:province":"NY",
    "sg:tags":[
        "management",
        "property"
    ],
    "sg:website":"www.nofeerentals.com",
    "wof:name":"Jakobson Properties",
    "wof:placetype":"venue"
},
  "geometry": {"coordinates":[-73.994151,40.72986],"type":"Point"}
}