{
  "type": "Feature",
  "properties": {
    "addr:full":"142 Linden Boulevard Brooklyn NY 11226",
    "addr:housenumber":"142",
    "addr:postcode":"11226",
    "addr:street":"Linden Boulevard",
    "iso:country":"US",
    "sg:address":"142 Linden Boulevard",
    "sg:city":"Brooklyn",
    "sg:classifiers":[
        {
            "category":"Health Services",
            "subcategory":"Dentist",
            "type":"Services"
        }
    ],
    "sg:phone":"+1 718 282 9292",
    "sg:postcode":"11226",
    "sg:province":"NY",
    "wof:name":"Popescu Paraschiva DDS",
    "wof:placetype":"venue"
},
  "geometry": {"coordinates":[-73.953467,40.652331],"type":"Point"}
}