{
  "type": "Feature",
  "properties": {
    "iso:country":"US",
    "sg:address":"964 Middle Country Rd",
    "sg:city":"Saint James",
    "sg:classifiers":[
        {
            "category":"Restaurant",
            "type":"Food & Drink"
        }
    ],
    "sg:phone":"+1 631 265 1212",
    "sg:postcode":"11780",
    "sg:province":"NY",
    "wof:name":"Intermezzo Americana Bar & Grill",
    "wof:placetype":"venue"
},
  "geometry": {"coordinates":[-73.1409,40.861401],"type":"Point"}
}