{
  "type": "Feature",
  "properties": {
    "addr:full":"64-43 108th St Forest Hills NY 11375",
    "addr:housenumber":"64-43",
    "addr:postcode":"11375",
    "addr:street":"108Th St",
    "iso:country":"US",
    "sg:address":"64-43 108th St",
    "sg:city":"Forest Hills",
    "sg:classifiers":[
        {
            "category":"Restaurant",
            "type":"Food & Drink"
        }
    ],
    "sg:phone":"+1 718 275 1300",
    "sg:postcode":"11375",
    "sg:province":"NY",
    "sg:tags":[
        "kosher",
        "chinese"
    ],
    "sg:website":"www.chosengarden.com/Garden.html",
    "wof:name":"Cho-Sen Garden",
    "wof:placetype":"venue"
},
  "geometry": {"coordinates":[-73.849054,40.731921],"type":"Point"}
}