{
  "type": "Feature",
  "properties": {
    "iso:country":"US",
    "sg:address":"1450 Metropolitan Ave",
    "sg:city":"Bronx",
    "sg:classifiers":[
        {
            "category":"Shopping",
            "subcategory":"Clothing, Apparel, & Fashions",
            "type":"Retail Goods"
        },
        {
            "category":"Home & Garden",
            "subcategory":"Home Furnishings",
            "type":"Retail Goods"
        },
        {
            "category":"Home & Garden",
            "subcategory":"Furniture",
            "type":"Retail Goods"
        }
    ],
    "sg:phone":"+1 718 430 6751",
    "sg:postcode":"10462",
    "sg:province":"NY",
    "sg:tags":[
        "furniture-children's",
        "clothing",
        "store"
    ],
    "sg:website":"http://www.kidsplaceofmarin.com",
    "wof:name":"Baby Place Of Parkchester",
    "wof:placetype":"venue"
},
  "geometry": {"coordinates":[-73.86084700000001,40.836472],"type":"Point"}
}