{
  "type": "Feature",
  "properties": {
    "addr:full":"30 Newton St Staten Island NY 10312",
    "addr:housenumber":"30",
    "addr:postcode":"10312",
    "addr:street":"Newton St",
    "iso:country":"US",
    "sg:address":"30 Newton St",
    "sg:city":"Staten Island",
    "sg:classifiers":[
        {
            "category":"Building & Trades",
            "subcategory":"Construction",
            "type":"Services"
        }
    ],
    "sg:phone":"+1 718 227 8024",
    "sg:postcode":"10312",
    "sg:province":"NY",
    "sg:tags":[
        "residential"
    ],
    "wof:name":"Peter Hardt Inc",
    "wof:placetype":"venue"
},
  "geometry": {"coordinates":[-74.174357,40.527297],"type":"Point"}
}