{
  "type": "Feature",
  "properties": {
    "addr:full":"11 12th St Astoria NY 11106",
    "addr:housenumber":"11",
    "addr:postcode":"11106",
    "addr:street":"12Th St",
    "iso:country":"US",
    "sg:address":"11 12th St",
    "sg:city":"Astoria",
    "sg:classifiers":[
        {
            "category":"Organizations",
            "subcategory":"Membership Organization",
            "type":"Services"
        }
    ],
    "sg:phone":"+1   ",
    "sg:postcode":"11106",
    "sg:province":"NY",
    "wof:name":"Hour Children Thrift Shop",
    "wof:placetype":"venue"
},
  "geometry": {"coordinates":[-73.93986099999999,40.759572],"type":"Point"}
}