{
  "type": "Feature",
  "properties": {
    "addr:full":"4120 Maple Rd Buffalo NY 14226",
    "addr:housenumber":"4120",
    "addr:postcode":"14226",
    "addr:street":"Maple Rd",
    "iso:country":"US",
    "sg:address":"4120 Maple Rd",
    "sg:city":"Buffalo",
    "sg:classifiers":[
        {
            "category":"Restaurant",
            "type":"Food & Drink"
        }
    ],
    "sg:menulink":"http://www.allmenus.com/ny/amherst/101125-smokey-bones/menu/",
    "sg:phone":"+1 716 834 0148",
    "sg:postcode":"14226",
    "sg:province":"NY",
    "sg:tags":[
        "barbecue",
        "american"
    ],
    "wof:name":"Smokey Bones",
    "wof:placetype":"venue"
},
  "geometry": {"coordinates":[-78.811071,42.990826],"type":"Point"}
}