{
  "type": "Feature",
  "properties": {
    "addr:full":"345 Rockaway Tpke Lawrence NY 11559",
    "addr:housenumber":"345",
    "addr:postcode":"11559",
    "addr:street":"Rockaway Tpke",
    "iso:country":"US",
    "sg:address":"345 Rockaway Tpke",
    "sg:city":"Lawrence",
    "sg:classifiers":[
        {
            "category":"Building & Trades",
            "subcategory":"Locksmith",
            "type":"Services"
        }
    ],
    "sg:phone":"+1 516 612 0576",
    "sg:postcode":"11559",
    "sg:province":"NY",
    "sg:tags":[
        "key"
    ],
    "wof:name":"1 A 1 A 1 Hour A Emergency 1 Locks",
    "wof:placetype":"venue"
},
  "geometry": {"coordinates":[-73.73665200000001,40.626511],"type":"Point"}
}