{
  "type": "Feature",
  "properties": {
    "addr:full":"9 Sommers Ln Staten Island NY 10314",
    "addr:housenumber":"9",
    "addr:postcode":"10314",
    "addr:street":"Sommers Ln",
    "iso:country":"US",
    "sg:address":"9 Sommers Ln",
    "sg:city":"Staten Island",
    "sg:classifiers":[
        {
            "category":"Professional",
            "subcategory":"Management & Consulting",
            "type":"Services"
        }
    ],
    "sg:phone":"+1   ",
    "sg:postcode":"10314",
    "sg:province":"NY",
    "sg:tags":[
        "retail",
        "direct",
        "sales"
    ],
    "wof:name":"Browns Fuel Service",
    "wof:placetype":"venue"
},
  "geometry": {"coordinates":[-74.120491,40.612084],"type":"Point"}
}