{
  "type": "Feature",
  "properties": {
    "addr:full":"325 N Main St Canandaigua NY 14424",
    "addr:housenumber":"325",
    "addr:postcode":"14424",
    "addr:street":"N Main St",
    "iso:country":"US",
    "sg:address":"325 N Main St",
    "sg:city":"Canandaigua",
    "sg:classifiers":[
        {
            "category":"Restaurant",
            "type":"Food & Drink"
        }
    ],
    "sg:phone":"+1 585 394 3050",
    "sg:postcode":"14424",
    "sg:province":"NY",
    "sg:tags":[
        "shop",
        "coffee"
    ],
    "wof:name":"Phoenix Coffee",
    "wof:placetype":"venue"
},
  "geometry": {"coordinates":[-77.28834000000001,42.897387],"type":"Point"}
}