{
  "type": "Feature",
  "properties": {
    "addr:full":"87 Bellwood Dr New Hyde Park NY 11040",
    "addr:housenumber":"87",
    "addr:postcode":"11040",
    "addr:street":"Bellwood Dr New",
    "iso:country":"US",
    "sg:address":"87 Bellwood Dr",
    "sg:city":"New Hyde Park",
    "sg:classifiers":[
        {
            "category":"Wholesale",
            "subcategory":"Jewelry",
            "type":"Manufacturing & Wholesale Goods"
        }
    ],
    "sg:phone":"+1 718 205 7174",
    "sg:postcode":"11040",
    "sg:province":"NY",
    "wof:name":"Jewels De Paragon Inc",
    "wof:placetype":"venue"
},
  "geometry": {"coordinates":[-73.660179,40.744212],"type":"Point"}
}