{
  "type": "Feature",
  "properties": {
    "addr:full":"107 Heath St Lockport NY 14094",
    "addr:housenumber":"107",
    "addr:postcode":"14094",
    "addr:street":"Heath St",
    "iso:country":"US",
    "sg:address":"107 Heath St",
    "sg:city":"Lockport",
    "sg:classifiers":[
        {
            "category":"Social Services",
            "type":"Services"
        }
    ],
    "sg:phone":"+1 716 434 4050",
    "sg:postcode":"14094",
    "sg:province":"NY",
    "sg:tags":[
        "handicapped",
        "human",
        "for"
    ],
    "wof:name":"Opportnties Unlmted of Niagara",
    "wof:placetype":"venue"
},
  "geometry": {"coordinates":[-78.718851,43.167889],"type":"Point"}
}