{
  "type": "Feature",
  "properties": {
    "addr:full":"375 Downing Dr Yorktown Heights NY 10598",
    "addr:housenumber":"375",
    "addr:postcode":"10598",
    "addr:street":"Downing Dr",
    "iso:country":"US",
    "sg:address":"375 Downing Dr",
    "sg:city":"Yorktown Heights",
    "sg:classifiers":[
        {
            "category":"Shopping",
            "type":"Retail Goods"
        }
    ],
    "sg:phone":"+1   ",
    "sg:postcode":"10598",
    "sg:province":"NY",
    "sg:tags":[
        "merchandise"
    ],
    "wof:name":"Wireless Solutions",
    "wof:placetype":"venue"
},
  "geometry": {"coordinates":[-73.79636499999999,41.275594],"type":"Point"}
}