{
  "type": "Feature",
  "properties": {
    "addr:full":"1066 N Broadway North Massapequa NY 11758",
    "addr:housenumber":"1066",
    "addr:postcode":"11758",
    "addr:street":"N Broadway",
    "iso:country":"US",
    "sg:address":"1066 N Broadway",
    "sg:city":"North Massapequa",
    "sg:classifiers":[
        {
            "category":"Wholesale",
            "subcategory":"Electrical",
            "type":"Manufacturing & Wholesale Goods"
        }
    ],
    "sg:phone":"+1 516 293 5939",
    "sg:postcode":"11758",
    "sg:province":"NY",
    "sg:tags":[
        "alarm",
        "burglar",
        "system"
    ],
    "wof:name":"Safe Guard Alarm Inc",
    "wof:placetype":"venue"
},
  "geometry": {"coordinates":[-73.46103599999999,40.711279],"type":"Point"}
}