{
  "type": "Feature",
  "properties": {
    "iso:country":"US",
    "sg:address":"376 W Old Country Rd",
    "sg:city":"Hicksville",
    "sg:classifiers":[
        {
            "category":"Shopping",
            "subcategory":"Discount & Variety Stores",
            "type":"Retail Goods"
        }
    ],
    "sg:phone":"+1 516 942 1951",
    "sg:postcode":"11801",
    "sg:province":"NY",
    "wof:name":"Mega 99 Cent Store",
    "wof:placetype":"venue"
},
  "geometry": {"coordinates":[-73.538428,40.759233],"type":"Point"}
}