{
  "type": "Feature",
  "properties": {
    "iso:country":"US",
    "sg:address":"83 Amherst Rd",
    "sg:city":"Valley Stream",
    "sg:classifiers":[
        {
            "category":"Wholesale",
            "subcategory":"Computers",
            "type":"Manufacturing & Wholesale Goods"
        },
        {
            "category":"Professional",
            "subcategory":"Computer Services",
            "type":"Services"
        }
    ],
    "sg:phone":"+1 516 791 6744",
    "sg:postcode":"11581",
    "sg:province":"NY",
    "sg:tags":[
        "repair"
    ],
    "sg:website":"www.a1systems.net",
    "wof:name":"A-1 Systems Service Inc",
    "wof:placetype":"venue"
},
  "geometry": {"coordinates":[-73.700203,40.6479],"type":"Point"}
}