{
  "type": "Feature",
  "properties": {
    "iso:country":"US",
    "sg:address":"1784 Utica Ave",
    "sg:city":"Brooklyn",
    "sg:classifiers":[
        {
            "category":"Personal",
            "subcategory":"Beauty Salon",
            "type":"Services"
        }
    ],
    "sg:phone":"+1   ",
    "sg:postcode":"11234",
    "sg:province":"NY",
    "sg:tags":[
        "shop"
    ],
    "wof:name":"Tiers Trvl & Unisex Hair Salon",
    "wof:placetype":"venue"
},
  "geometry": {"coordinates":[-73.928079,40.62989],"type":"Point"}
}