{
  "type": "Feature",
  "properties": {
    "addr:full":"20112 Linden Boulevard Saint Albans NY 11412",
    "addr:housenumber":"20112",
    "addr:postcode":"11412",
    "addr:street":"Linden Boulevard",
    "iso:country":"US",
    "sg:address":"20112 Linden Boulevard",
    "sg:city":"Saint Albans",
    "sg:classifiers":[
        {
            "category":"Retail",
            "subcategory":"Laundry & Dry Cleaning",
            "type":"Services"
        }
    ],
    "sg:phone":"+1 718 978 7908",
    "sg:postcode":"11412",
    "sg:province":"NY",
    "wof:name":"DC Dry Cleaning",
    "wof:placetype":"venue"
},
  "geometry": {"coordinates":[-73.751076,40.694646],"type":"Point"}
}