{
  "type": "Feature",
  "properties": {
    "addr:full":"3303 Palmer Ave Bronx NY 10475",
    "addr:housenumber":"3303",
    "addr:postcode":"10475",
    "addr:street":"Palmer Ave",
    "iso:country":"US",
    "sg:address":"3303 Palmer Ave",
    "sg:city":"Bronx",
    "sg:classifiers":[
        {
            "category":"Food & Beverages",
            "subcategory":"Specialty",
            "type":"Retail Goods"
        }
    ],
    "sg:phone":"+1   ",
    "sg:postcode":"10475",
    "sg:province":"NY",
    "wof:name":"Healthy Requests Inc",
    "wof:placetype":"venue"
},
  "geometry": {"coordinates":[-73.835797,40.879638],"type":"Point"}
}