{
  "type": "Feature",
  "properties": {
    "iso:country":"US",
    "sg:address":"5709 Cemetery Hill Rd",
    "sg:city":"Belmont",
    "sg:classifiers":[
        {
            "category":"Building & Trades",
            "subcategory":"Construction",
            "type":"Services"
        }
    ],
    "sg:phone":"+1 585 268 7144",
    "sg:postcode":"14813",
    "sg:province":"NY",
    "sg:tags":[
        "demolition",
        "contractor"
    ],
    "wof:name":"Sequoyah Equipment",
    "wof:placetype":"venue"
},
  "geometry": {"coordinates":[-78.07267,42.210979],"type":"Point"}
}