{
  "type": "Feature",
  "properties": {
    "iso:country":"US",
    "sg:address":"888 Grand Concourse",
    "sg:city":"Bronx",
    "sg:classifiers":[
        {
            "category":"Professional",
            "subcategory":"Lawyer & Legal Services",
            "type":"Services"
        }
    ],
    "sg:phone":"+1 718 588 2000",
    "sg:postcode":"10451",
    "sg:province":"NY",
    "wof:name":"Diamond Ivan M Atty",
    "wof:placetype":"venue"
},
  "geometry": {"coordinates":[-73.922668,40.82665],"type":"Point"}
}