{
  "type": "Feature",
  "properties": {
    "addr:full":"364 Holmes St Levittown NY 11756",
    "addr:housenumber":"364",
    "addr:postcode":"11756",
    "addr:street":"Holmes St",
    "iso:country":"US",
    "sg:address":"364 Holmes St",
    "sg:city":"Levittown",
    "sg:classifiers":[
        {
            "category":"Shopping",
            "subcategory":"Bicycles & Sporting Goods",
            "type":"Retail Goods"
        }
    ],
    "sg:phone":"+1 516 796 8789",
    "sg:postcode":"11756",
    "sg:province":"NY",
    "wof:name":"Sports Central",
    "wof:placetype":"venue"
},
  "geometry": {"coordinates":[-73.492383,40.715667],"type":"Point"}
}