{
  "type": "Feature",
  "properties": {
    "addr:full":"9676 State Highway 56 Massena NY 13662",
    "addr:housenumber":"9676",
    "addr:postcode":"13662",
    "addr:street":"State Highway 56",
    "iso:country":"US",
    "sg:address":"9676 State Highway 56",
    "sg:city":"Massena",
    "sg:classifiers":[
        {
            "category":"Manufacturing",
            "subcategory":"Motor Vehicles & Parts",
            "type":"Manufacturing & Wholesale Goods"
        },
        {
            "category":"Wholesale",
            "subcategory":"Auto Parts",
            "type":"Manufacturing & Wholesale Goods"
        },
        {
            "category":"Retail",
            "subcategory":"Auto Repair",
            "type":"Services"
        }
    ],
    "sg:phone":"+1 315 705 4307",
    "sg:postcode":"13662",
    "sg:province":"NY",
    "sg:tags":[
        "body",
        "repairing",
        "shop",
        "supply",
        "automobile",
        "supply-wholesale",
        "equipment",
        "service-equipment",
        "painting",
        "manufacturer"
    ],
    "wof:name":"Legacy Collision",
    "wof:placetype":"venue"
},
  "geometry": {"coordinates":[-74.940606,44.889524],"type":"Point"}
}