{
  "type": "Feature",
  "properties": {
    "addr:full":"56 E 12th St New York NY 10003",
    "addr:housenumber":"56",
    "addr:postcode":"10003",
    "addr:street":"E 12Th St",
    "iso:country":"US",
    "sg:address":"56 E 12th St",
    "sg:city":"New York",
    "sg:classifiers":[
        {
            "category":"Personal",
            "subcategory":"Hair Removal",
            "type":"Services"
        }
    ],
    "sg:phone":"+1 917 817 4562",
    "sg:postcode":"10003",
    "sg:province":"NY",
    "sg:tags":[
        "laser"
    ],
    "sg:website":"www.strictlylasernyc.com",
    "wof:name":"Strictly Laser",
    "wof:placetype":"venue"
},
  "geometry": {"coordinates":[-73.991254,40.733259],"type":"Point"}
}