{
  "type": "Feature",
  "properties": {
    "iso:country":"US",
    "sg:address":"1808 Ave M",
    "sg:city":"Brooklyn",
    "sg:classifiers":[
        {
            "category":"Shopping",
            "subcategory":"Gifts & Souvenirs",
            "type":"Retail Goods"
        }
    ],
    "sg:phone":"+1 718 376 3083",
    "sg:postcode":"11230",
    "sg:province":"NY",
    "wof:name":"Elizabeth Gifts",
    "wof:placetype":"venue"
},
  "geometry": {"coordinates":[-73.956936,40.61827],"type":"Point"}
}