{
  "type": "Feature",
  "properties": {
    "addr:full":"1 Peter Dr Albany NY 12205",
    "addr:housenumber":"1",
    "addr:postcode":"12205",
    "addr:street":"Peter Dr",
    "iso:country":"US",
    "sg:address":"1 Peter Dr",
    "sg:city":"Albany",
    "sg:classifiers":[
        {
            "category":"Professional",
            "type":"Services"
        }
    ],
    "sg:phone":"+1 518 956 1007",
    "sg:postcode":"12205",
    "sg:province":"NY",
    "sg:tags":[
        "establishment"
    ],
    "wof:name":"Fleet Technology",
    "wof:placetype":"venue"
},
  "geometry": {"coordinates":[-73.827612,42.723231],"type":"Point"}
}