{
  "type": "Feature",
  "properties": {
    "addr:full":"1807 Hemmer Rd Wayland NY 14572",
    "addr:housenumber":"1807",
    "addr:postcode":"14572",
    "addr:street":"Hemmer Rd",
    "iso:country":"US",
    "sg:address":"1807 Hemmer Rd",
    "sg:city":"Wayland",
    "sg:classifiers":[
        {
            "category":"Retail",
            "subcategory":"Veterinary Services",
            "type":"Services"
        }
    ],
    "sg:phone":"+1 585 728 5562",
    "sg:postcode":"14572",
    "sg:province":"NY",
    "sg:tags":[
        "veterinarian"
    ],
    "wof:name":"Equi Power",
    "wof:placetype":"venue"
},
  "geometry": {"coordinates":[-77.625253,42.571498],"type":"Point"}
}