{
  "type": "Feature",
  "properties": {
    "addr:full":"1848 Flatbush Ave Brooklyn NY 11210",
    "addr:housenumber":"1848",
    "addr:postcode":"11210",
    "addr:street":"Flatbush Ave",
    "iso:country":"US",
    "sg:address":"1848 Flatbush Ave",
    "sg:city":"Brooklyn",
    "sg:classifiers":[
        {
            "category":"Real Estate",
            "subcategory":"Real Estate Agent",
            "type":"Services"
        }
    ],
    "sg:phone":"+1 718 253 2323",
    "sg:postcode":"11210",
    "sg:province":"NY",
    "wof:name":"Maria Lucielma Held RE",
    "wof:placetype":"venue"
},
  "geometry": {"coordinates":[-73.93898900000001,40.624621],"type":"Point"}
}