{
  "type": "Feature",
  "properties": {
    "addr:full":"2631 Schurz Ave Bronx NY 10465",
    "addr:housenumber":"2631",
    "addr:postcode":"10465",
    "addr:street":"Schurz Ave",
    "iso:country":"US",
    "sg:address":"2631 Schurz Ave",
    "sg:city":"Bronx",
    "sg:classifiers":[
        {
            "category":"Arts & Performance",
            "subcategory":"Theater",
            "type":"Entertainment"
        }
    ],
    "sg:phone":"+1 718 792 9716",
    "sg:postcode":"10465",
    "sg:province":"NY",
    "sg:tags":[
        "live",
        "music"
    ],
    "wof:name":"Mixednuts Interactive DJ Svc",
    "wof:placetype":"venue"
},
  "geometry": {"coordinates":[-73.82433,40.812801],"type":"Point"}
}