{
  "type": "Feature",
  "properties": {
    "addr:full":"2556 Arthur Kill Rd Staten Island NY 10309",
    "addr:housenumber":"2556",
    "addr:postcode":"10309",
    "addr:street":"Arthur Kill Rd",
    "iso:country":"US",
    "sg:address":"2556 Arthur Kill Rd",
    "sg:city":"Staten Island",
    "sg:classifiers":[
        {
            "category":"Health Services",
            "subcategory":"Clinic",
            "type":"Services"
        }
    ],
    "sg:phone":"+1 718 966 8200",
    "sg:postcode":"10309",
    "sg:province":"NY",
    "wof:name":"Crossroads Healthcare Mgmt LLC",
    "wof:placetype":"venue"
},
  "geometry": {"coordinates":[-74.22131400000001,40.550253],"type":"Point"}
}