{
  "type": "Feature",
  "properties": {
    "iso:country":"US",
    "sg:address":"6608 Main Rd",
    "sg:city":"Stafford",
    "sg:classifiers":[
        {
            "category":"Freight",
            "type":"Transportation"
        }
    ],
    "sg:phone":"+1 585 815 0215",
    "sg:postcode":"14143",
    "sg:province":"NY",
    "sg:tags":[
        "trucking"
    ],
    "wof:name":"Douglas Trans Of W Ny Inc",
    "wof:placetype":"venue"
},
  "geometry": {"coordinates":[-78.048946,42.979746],"type":"Point"}
}