{
  "type": "Feature",
  "properties": {
    "addr:full":"179 Cherry Ln Monsey NY 10952",
    "addr:housenumber":"179",
    "addr:postcode":"10952",
    "addr:street":"Cherry Ln",
    "iso:country":"US",
    "sg:address":"179 Cherry Ln",
    "sg:city":"Monsey",
    "sg:classifiers":[
        {
            "category":"Manufacturing",
            "subcategory":"Metals",
            "type":"Manufacturing & Wholesale Goods"
        }
    ],
    "sg:phone":"+1   ",
    "sg:postcode":"10952",
    "sg:province":"NY",
    "sg:tags":[
        "blast",
        "furnace",
        "works"
    ],
    "wof:name":"Conklin Iron Works",
    "wof:placetype":"venue"
},
  "geometry": {"coordinates":[-74.094706,41.097719],"type":"Point"}
}