{
  "type": "Feature",
  "properties": {
    "iso:country":"US",
    "sg:address":"270 Ferndale Ct",
    "sg:city":"Copiague",
    "sg:classifiers":[
        {
            "category":"Building & Trades",
            "subcategory":"Construction",
            "type":"Services"
        }
    ],
    "sg:phone":"+1 631 225 5138",
    "sg:postcode":"11726",
    "sg:province":"NY",
    "sg:tags":[
        "contractor",
        "carpenter",
        "carpentry"
    ],
    "wof:name":"Werkmeister Carpentry",
    "wof:placetype":"venue"
},
  "geometry": {"coordinates":[-73.390546,40.675956],"type":"Point"}
}