{
  "type": "Feature",
  "properties": {
    "addr:full":"1140 Flatbush Ave Brooklyn NY 11226",
    "addr:housenumber":"1140",
    "addr:postcode":"11226",
    "addr:street":"Flatbush Ave",
    "iso:country":"US",
    "sg:address":"1140 Flatbush Ave",
    "sg:city":"Brooklyn",
    "sg:classifiers":[
        {
            "category":"Wholesale",
            "subcategory":"Hardware",
            "type":"Manufacturing & Wholesale Goods"
        }
    ],
    "sg:phone":"+1 718 462 1189",
    "sg:postcode":"11226",
    "sg:province":"NY",
    "sg:tags":[
        "plumbing",
        "retail",
        "heating",
        "supply"
    ],
    "wof:name":"Michaels Plumbing Supply Co",
    "wof:placetype":"venue"
},
  "geometry": {"coordinates":[-73.957584,40.642469],"type":"Point"}
}