{
  "type": "Feature",
  "properties": {
    "iso:country":"US",
    "sg:address":"244 E Route 59",
    "sg:city":"Nanuet",
    "sg:classifiers":[
        {
            "category":"Wholesale",
            "subcategory":"Non-durable Goods",
            "type":"Manufacturing & Wholesale Goods"
        },
        {
            "category":"Personal",
            "subcategory":"Beauty Salon",
            "type":"Services"
        },
        {
            "category":"Personal",
            "subcategory":"Barber",
            "type":"Services"
        },
        {
            "category":"Shopping",
            "subcategory":"Beauty & Cosmetics",
            "type":"Retail Goods"
        }
    ],
    "sg:phone":"+1 845 624 1122",
    "sg:postcode":"10954",
    "sg:province":"NY",
    "sg:tags":[
        "supply",
        "accessory",
        "hair",
        "equipment",
        "salons-equipment",
        "perfume",
        "supplies-wholesale",
        "manufacturer"
    ],
    "sg:website":"http://www.sallybeauty.com",
    "wof:name":"Sally Beauty Supply",
    "wof:placetype":"venue"
},
  "geometry": {"coordinates":[-74.003136,41.093964],"type":"Point"}
}