{
  "type": "Feature",
  "properties": {
    "addr:full":"30 Aero Rd Bohemia NY 11716",
    "addr:housenumber":"30",
    "addr:postcode":"11716",
    "addr:street":"Aero Rd",
    "iso:country":"US",
    "sg:address":"30 Aero Rd",
    "sg:city":"Bohemia",
    "sg:classifiers":[
        {
            "category":"Manufacturing",
            "subcategory":"Tools & Machinery",
            "type":"Manufacturing & Wholesale Goods"
        }
    ],
    "sg:phone":"+1   ",
    "sg:postcode":"11716",
    "sg:province":"NY",
    "sg:tags":[
        "equipment",
        "peripheral",
        "computer",
        "mfg"
    ],
    "wof:name":"Lsc Peripherals Inc",
    "wof:placetype":"venue"
},
  "geometry": {"coordinates":[-73.092129,40.780011],"type":"Point"}
}