{
  "type": "Feature",
  "properties": {
    "iso:country":"US",
    "sg:address":"1143 River Rd",
    "sg:city":"Binghamton",
    "sg:classifiers":[
        {
            "category":"Building & Trades",
            "subcategory":"Construction",
            "type":"Services"
        }
    ],
    "sg:phone":"+1 607 648 6719",
    "sg:postcode":"13901",
    "sg:province":"NY",
    "sg:tags":[
        "painting",
        "contractor"
    ],
    "wof:name":"Perry L Hitchcock",
    "wof:placetype":"venue"
},
  "geometry": {"coordinates":[-75.835279,42.1713],"type":"Point"}
}