{
  "type": "Feature",
  "properties": {
    "addr:full":"77 Front St 2nd Floor Brooklyn NY 11201",
    "addr:housenumber":"77;2nd floor",
    "addr:postcode":"11201",
    "addr:street":"Front St",
    "iso:country":"US",
    "sg:address":"77 Front St 2nd Floor",
    "sg:city":"Brooklyn",
    "sg:classifiers":[
        {
            "category":"Sports & Exercise",
            "subcategory":"Gym",
            "type":"Entertainment"
        },
        {
            "category":"Health Services",
            "subcategory":"Health Practitioner",
            "type":"Services"
        }
    ],
    "sg:phone":"+1 718 237 0207",
    "sg:postcode":"11201",
    "sg:province":"NY",
    "sg:tags":[
        "nutritionist"
    ],
    "sg:website":"fitnessgurunyc.com/",
    "wof:name":"The Fitness Guru",
    "wof:placetype":"venue"
},
  "geometry": {"coordinates":[-73.99300599999999,40.702497],"type":"Point"}
}