{
  "type": "Feature",
  "properties": {
    "addr:full":"26 Oriskany Blvd Whitesboro NY 13492",
    "addr:housenumber":"26",
    "addr:postcode":"13492",
    "addr:street":"Oriskany Blvd",
    "iso:country":"US",
    "sg:address":"26 Oriskany Blvd",
    "sg:city":"Whitesboro",
    "sg:classifiers":[
        {
            "category":"Restaurant",
            "type":"Food & Drink"
        }
    ],
    "sg:menulink":"http://www.allmenus.com/ny/whitestown/170110-burger-king/menu/",
    "sg:phone":"+1 315 736 7998",
    "sg:postcode":"13492",
    "sg:province":"NY",
    "sg:tags":[
        "burger",
        "american"
    ],
    "wof:name":"Burger King",
    "wof:placetype":"venue"
},
  "geometry": {"coordinates":[-75.28947100000001,43.116532],"type":"Point"}
}