{
  "type": "Feature",
  "properties": {
    "iso:country":"US",
    "sg:address":"104 W 40th St Fl 9",
    "sg:city":"New York",
    "sg:classifiers":[
        {
            "category":"Professional",
            "subcategory":"Lawyer & Legal Services",
            "type":"Services"
        }
    ],
    "sg:phone":"+1 212 594 8870",
    "sg:postcode":"10018",
    "sg:province":"NY",
    "wof:name":"Young Carl S Lwyr",
    "wof:placetype":"venue"
},
  "geometry": {"coordinates":[-73.98586,40.753475],"type":"Point"}
}