{
  "type": "Feature",
  "properties": {
    "iso:country":"US",
    "sg:address":"19 W Main St",
    "sg:city":"Webster",
    "sg:classifiers":[
        {
            "category":"Bars & Pubs",
            "type":"Food & Drink"
        },
        {
            "category":"Restaurant",
            "type":"Food & Drink"
        }
    ],
    "sg:phone":"+1 585 872 2910",
    "sg:postcode":"14580",
    "sg:province":"NY",
    "sg:tags":[
        "brew",
        "tavern"
    ],
    "wof:name":"Coach Sports Bar",
    "wof:placetype":"venue"
},
  "geometry": {"coordinates":[-77.431027,43.212123],"type":"Point"}
}