{
  "type": "Feature",
  "properties": {
    "iso:country":"US",
    "sg:address":"170 63rd St",
    "sg:city":"Niagara Falls",
    "sg:classifiers":[
        {
            "category":"Building & Trades",
            "subcategory":"Construction",
            "type":"Services"
        }
    ],
    "sg:phone":"+1 716 283 7734",
    "sg:postcode":"14304",
    "sg:province":"NY",
    "sg:tags":[
        "installation",
        "carpet"
    ],
    "wof:name":"Precision Carpet Installation",
    "wof:placetype":"venue"
},
  "geometry": {"coordinates":[-78.99189200000001,43.078562],"type":"Point"}
}