{
  "type": "Feature",
  "properties": {
    "addr:full":"23 E 2 St New York NY 10003",
    "addr:housenumber":"23;2",
    "addr:postcode":"10003",
    "addr:street":"E",
    "iso:country":"US",
    "sg:address":"23 E 2 St",
    "sg:city":"New York",
    "sg:classifiers":[
        {
            "category":"Wholesale",
            "subcategory":"Apparel",
            "type":"Manufacturing & Wholesale Goods"
        }
    ],
    "sg:phone":"+1 212 477 0758",
    "sg:postcode":"10003",
    "sg:province":"NY",
    "sg:tags":[
        "clothing"
    ],
    "wof:name":"Sugar Man",
    "wof:placetype":"venue"
},
  "geometry": {"coordinates":[-73.99034399999999,40.724928],"type":"Point"}
}