{
  "type": "Feature",
  "properties": {
    "addr:full":"135 Zandhoek Rd Hurley NY 12443",
    "addr:housenumber":"135",
    "addr:postcode":"12443",
    "addr:street":"Zandhoek Rd",
    "iso:country":"US",
    "sg:address":"135 Zandhoek Rd",
    "sg:city":"Hurley",
    "sg:classifiers":[
        {
            "category":"Manufacturing",
            "subcategory":"Food",
            "type":"Manufacturing & Wholesale Goods"
        }
    ],
    "sg:phone":"+1   ",
    "sg:postcode":"12443",
    "sg:province":"NY",
    "sg:tags":[
        "product",
        "confectionery",
        "mfg"
    ],
    "wof:name":"Ko Enterprises",
    "wof:placetype":"venue"
},
  "geometry": {"coordinates":[-74.057942,41.917327],"type":"Point"}
}