{
  "type": "Feature",
  "properties": {
    "iso:country":"US",
    "sg:address":"237 W 15 St",
    "sg:city":"New York",
    "sg:classifiers":[
        {
            "category":"Food & Beverages",
            "subcategory":"Specialty",
            "type":"Retail Goods"
        }
    ],
    "sg:phone":"+1 212 675 0565",
    "sg:postcode":"10011",
    "sg:province":"NY",
    "sg:tags":[
        "vitamin"
    ],
    "wof:name":"Nutri Sport",
    "wof:placetype":"venue"
},
  "geometry": {"coordinates":[-74.001193,40.740068],"type":"Point"}
}