{
  "type": "Feature",
  "properties": {
    "iso:country":"US",
    "sg:address":"212 Avenue B",
    "sg:city":"New York",
    "sg:classifiers":[
        {
            "category":"Cafe",
            "type":"Food & Drink"
        }
    ],
    "sg:menulink":"http://www.allmenus.com/ny/new-york/4738-name-your-cafe/menu/",
    "sg:phone":"+1 212 228 4808",
    "sg:postcode":"10009",
    "sg:province":"NY",
    "sg:tags":[
        "american"
    ],
    "wof:name":"Name Your Cafe",
    "wof:placetype":"venue"
},
  "geometry": {"coordinates":[-73.97885100000001,40.728693],"type":"Point"}
}