{
  "type": "Feature",
  "properties": {
    "iso:country":"US",
    "sg:address":"5391 Ridge Rd W",
    "sg:city":"Spencerport",
    "sg:classifiers":[
        {
            "category":"Autos & Motor Vehicles",
            "subcategory":"Automobile Sales",
            "type":"Retail Goods"
        }
    ],
    "sg:phone":"+1 585 352 5557",
    "sg:postcode":"14559",
    "sg:province":"NY",
    "sg:tags":[
        "car",
        "dealer"
    ],
    "wof:name":"Garland Auto Sales",
    "wof:placetype":"venue"
},
  "geometry": {"coordinates":[-77.847031,43.223442],"type":"Point"}
}