{
  "type": "Feature",
  "properties": {
    "addr:full":"1 Notre Dame Ln Utica NY 13502",
    "addr:housenumber":"1",
    "addr:postcode":"13502",
    "addr:street":"Notre Dame Ln",
    "iso:country":"US",
    "sg:address":"1 Notre Dame Ln",
    "sg:city":"Utica",
    "sg:classifiers":[
        {
            "category":"Education",
            "subcategory":"Special Training",
            "type":"Public Place"
        }
    ],
    "sg:phone":"+1 315 732 1652",
    "sg:postcode":"13502",
    "sg:province":"NY",
    "sg:tags":[
        "tutoring"
    ],
    "wof:name":"Sylvan Learning Ctr",
    "wof:placetype":"venue"
},
  "geometry": {"coordinates":[-75.281268,43.094513],"type":"Point"}
}