{
  "type": "Feature",
  "properties": {
    "addr:full":"2723 Broadway New York NY 10025",
    "addr:housenumber":"2723",
    "addr:postcode":"10025",
    "addr:street":"Broadway",
    "iso:country":"US",
    "sg:address":"2723 Broadway",
    "sg:city":"New York",
    "sg:classifiers":[
        {
            "category":"Restaurant",
            "type":"Food & Drink"
        }
    ],
    "sg:phone":"+1 212 316 5000",
    "sg:postcode":"10025",
    "sg:province":"NY",
    "sg:tags":[
        "french"
    ],
    "sg:website":"www.cafedusoleilnyc.com",
    "wof:name":"Cafe Du Soleil",
    "wof:placetype":"venue"
},
  "geometry": {"coordinates":[-73.96839900000001,40.799999],"type":"Point"}
}