{
  "type": "Feature",
  "properties": {
    "addr:full":"300 Hooker Ave Poughkeepsie NY 12603",
    "addr:housenumber":"300",
    "addr:postcode":"12603",
    "addr:street":"Hooker Ave",
    "iso:country":"US",
    "sg:address":"300 Hooker Ave",
    "sg:city":"Poughkeepsie",
    "sg:classifiers":[
        {
            "category":"Restaurant",
            "type":"Food & Drink"
        }
    ],
    "sg:phone":"+1 845 452 1754",
    "sg:postcode":"12603",
    "sg:province":"NY",
    "sg:tags":[
        "pizza"
    ],
    "wof:name":"D D's Pizza",
    "wof:placetype":"venue"
},
  "geometry": {"coordinates":[-73.907042,41.684988],"type":"Point"}
}