{
  "type": "Feature",
  "properties": {
    "iso:country":"US",
    "sg:address":"16 Bedford Rd",
    "sg:city":"Chappaqua",
    "sg:classifiers":[
        {
            "category":"Professional",
            "subcategory":"Lawyer & Legal Services",
            "type":"Services"
        }
    ],
    "sg:phone":"+1 914 238 1377",
    "sg:postcode":"10514",
    "sg:province":"NY",
    "wof:name":"Grimes & Zimet",
    "wof:placetype":"venue"
},
  "geometry": {"coordinates":[-73.774173,41.150455],"type":"Point"}
}