{
  "type": "Feature",
  "properties": {
    "addr:full":"6913 11th Ave Brooklyn NY 11228",
    "addr:housenumber":"6913",
    "addr:postcode":"11228",
    "addr:street":"11Th Ave",
    "iso:country":"US",
    "sg:address":"6913 11th Ave",
    "sg:city":"Brooklyn",
    "sg:classifiers":[
        {
            "category":"Freight",
            "type":"Transportation"
        }
    ],
    "sg:phone":"+1 718 627 2458",
    "sg:postcode":"11228",
    "sg:province":"NY",
    "sg:tags":[
        "trucking"
    ],
    "wof:name":"Truckitusa.Com Inc",
    "wof:placetype":"venue"
},
  "geometry": {"coordinates":[-74.00876599999999,40.625824],"type":"Point"}
}