{
  "type": "Feature",
  "properties": {
    "iso:country":"US",
    "sg:address":"2478 86th St",
    "sg:city":"Brooklyn",
    "sg:classifiers":[
        {
            "category":"Personal",
            "subcategory":"Beauty Salon",
            "type":"Services"
        }
    ],
    "sg:phone":"+1   ",
    "sg:postcode":"11214",
    "sg:province":"NY",
    "sg:tags":[
        "shop"
    ],
    "wof:name":"Lauras Nail Salon",
    "wof:placetype":"venue"
},
  "geometry": {"coordinates":[-73.987472,40.598051],"type":"Point"}
}