{
  "type": "Feature",
  "properties": {
    "iso:country":"US",
    "sg:address":"2550 Centre Ave",
    "sg:city":"Bellmore",
    "sg:classifiers":[
        {
            "category":"Place Of Worship",
            "subcategory":"Synagogue",
            "type":"Public Place"
        },
        {
            "category":"Place Of Worship",
            "type":"Public Place"
        },
        {
            "category":"Organizations",
            "subcategory":"Religious Organization",
            "type":"Services"
        }
    ],
    "sg:phone":"+1 516 781 3072",
    "sg:postcode":"11710",
    "sg:province":"NY",
    "sg:tags":[
        "synagogues-reform",
        "church"
    ],
    "wof:name":"Bellmore Jewish Ctr Congregatn",
    "wof:placetype":"venue"
},
  "geometry": {"coordinates":[-73.527902,40.659608],"type":"Point"}
}