{
  "type": "Feature",
  "properties": {
    "iso:country":"US",
    "sg:address":"2412 65th St",
    "sg:city":"Brooklyn",
    "sg:classifiers":[
        {
            "category":"Retail",
            "subcategory":"Repair Shop",
            "type":"Services"
        }
    ],
    "sg:phone":"+1 718 339 8341",
    "sg:postcode":"11204",
    "sg:province":"NY",
    "sg:tags":[
        "television",
        "radio"
    ],
    "wof:name":"Amcor Electronic Svc Corp",
    "wof:placetype":"venue"
},
  "geometry": {"coordinates":[-73.976527,40.61082],"type":"Point"}
}