{
  "type": "Feature",
  "properties": {
    "addr:full":"651 Old Country Rd Plainview NY 11803",
    "addr:housenumber":"651",
    "addr:postcode":"11803",
    "addr:street":"Old Country Rd",
    "iso:country":"US",
    "sg:address":"651 Old Country Rd",
    "sg:city":"Plainview",
    "sg:classifiers":[
        {
            "category":"Health Services",
            "subcategory":"Doctor",
            "type":"Services"
        }
    ],
    "sg:phone":"+1 516 681 8822",
    "sg:postcode":"11803",
    "sg:province":"NY",
    "sg:tags":[
        "physician",
        "surgeon",
        "orthopedics",
        "surgeons"
    ],
    "wof:name":"Central Orthopedic Group",
    "wof:placetype":"venue"
},
  "geometry": {"coordinates":[-73.490144,40.771951],"type":"Point"}
}