{
  "type": "Feature",
  "properties": {
    "addr:full":"71 Clinton Rd Garden City NY 11530",
    "addr:housenumber":"71",
    "addr:postcode":"11530",
    "addr:street":"Clinton Rd",
    "iso:country":"US",
    "sg:address":"71 Clinton Rd",
    "sg:city":"Garden City",
    "sg:classifiers":[
        {
            "category":"Professional",
            "type":"Services"
        }
    ],
    "sg:phone":"+1 516 248 9191",
    "sg:postcode":"11530",
    "sg:province":"NY",
    "sg:tags":[
        "establishment"
    ],
    "wof:name":"Sutton & Edwards Management",
    "wof:placetype":"venue"
},
  "geometry": {"coordinates":[-73.620454,40.727141],"type":"Point"}
}