{
  "type": "Feature",
  "properties": {
    "addr:full":"13042 90th Ave Richmond Hill NY 11418",
    "addr:housenumber":"13042",
    "addr:postcode":"11418",
    "addr:street":"90Th Ave",
    "iso:country":"US",
    "sg:address":"13042 90th Ave",
    "sg:city":"Richmond Hill",
    "sg:classifiers":[
        {
            "category":"Building & Trades",
            "subcategory":"Construction",
            "type":"Services"
        }
    ],
    "sg:phone":"+1 718 441 0766",
    "sg:postcode":"11418",
    "sg:province":"NY",
    "sg:tags":[
        "contractor"
    ],
    "sg:website":"www.gavrielcontracting.com",
    "wof:name":"Gavriel Contracting Corp",
    "wof:placetype":"venue"
},
  "geometry": {"coordinates":[-73.82011799999999,40.698886],"type":"Point"}
}