{
  "type": "Feature",
  "properties": {
    "addr:full":"2 Charter Ln Smithtown NY 11787",
    "addr:housenumber":"2",
    "addr:postcode":"11787",
    "addr:street":"Charter Ln",
    "iso:country":"US",
    "sg:address":"2 Charter Ln",
    "sg:city":"Smithtown",
    "sg:classifiers":[
        {
            "category":"Shopping",
            "subcategory":"Computers & Home Electronics",
            "type":"Retail Goods"
        }
    ],
    "sg:phone":"+1 631 265 2621",
    "sg:postcode":"11787",
    "sg:province":"NY",
    "sg:tags":[
        "hardware",
        "supply"
    ],
    "wof:name":"Labella Products",
    "wof:placetype":"venue"
},
  "geometry": {"coordinates":[-73.249908,40.853771],"type":"Point"}
}