{
  "type": "Feature",
  "properties": {
    "addr:full":"1232 Yonkers Ave Yonkers NY 10704",
    "addr:housenumber":"1232",
    "addr:postcode":"10704",
    "addr:street":"Yonkers Ave",
    "iso:country":"US",
    "sg:address":"1232 Yonkers Ave",
    "sg:city":"Yonkers",
    "sg:classifiers":[
        {
            "category":"Restaurant",
            "type":"Food & Drink"
        }
    ],
    "sg:phone":"+1   ",
    "sg:postcode":"10704",
    "sg:province":"NY",
    "sg:tags":[
        "eating"
    ],
    "wof:name":"Golden Fountain Chinese Rest",
    "wof:placetype":"venue"
},
  "geometry": {"coordinates":[-73.85101400000001,40.914657],"type":"Point"}
}