{
  "type": "Feature",
  "properties": {
    "iso:country":"US",
    "sg:address":"132 Woodward Ave",
    "sg:city":"Springville",
    "sg:classifiers":[
        {
            "category":"Building & Trades",
            "subcategory":"Landscaping Services",
            "type":"Services"
        }
    ],
    "sg:phone":"+1 716 592 8018",
    "sg:postcode":"14141",
    "sg:province":"NY",
    "wof:name":"Smooth Cuts Lawncare",
    "wof:placetype":"venue"
},
  "geometry": {"coordinates":[-78.672028,42.507395],"type":"Point"}
}