{
  "type": "Feature",
  "properties": {
    "iso:country":"US",
    "sg:address":"702 Allerton Avenue",
    "sg:city":"Bronx",
    "sg:classifiers":[
        {
            "category":"Health Services",
            "subcategory":"Optometrist",
            "type":"Services"
        },
        {
            "category":"Shopping",
            "subcategory":"Optician",
            "type":"Retail Goods"
        }
    ],
    "sg:phone":"+1 718 654 2020",
    "sg:postcode":"10467",
    "sg:province":"NY",
    "sg:tags":[
        "eyewear"
    ],
    "sg:website":"www.envisageoptical.com",
    "wof:name":"Envisage Optical",
    "wof:placetype":"venue"
},
  "geometry": {"coordinates":[-73.86716800000001,40.865416],"type":"Point"}
}