{
  "type": "Feature",
  "properties": {
    "iso:country":"US",
    "sg:address":"3322 Walden Ave",
    "sg:city":"Depew",
    "sg:classifiers":[
        {
            "category":"Professional",
            "subcategory":"Research",
            "type":"Services"
        }
    ],
    "sg:phone":"+1 716 681 7938",
    "sg:postcode":"14043",
    "sg:province":"NY",
    "sg:tags":[
        "environmental",
        "ecological"
    ],
    "wof:name":"Enviro Sense Corp",
    "wof:placetype":"venue"
},
  "geometry": {"coordinates":[-78.69087500000001,42.912943],"type":"Point"}
}