{
  "type": "Feature",
  "properties": {
    "iso:country":"US",
    "sg:address":"120 Glenwood Rd",
    "sg:city":"Glenwood Landing",
    "sg:classifiers":[
        {
            "category":"Home & Garden",
            "subcategory":"Household Appliances",
            "type":"Retail Goods"
        }
    ],
    "sg:phone":"+1   ",
    "sg:postcode":"11547",
    "sg:province":"NY",
    "wof:name":"Davis Appliance Repair",
    "wof:placetype":"venue"
},
  "geometry": {"coordinates":[-73.641981,40.830298],"type":"Point"}
}