{
  "type": "Feature",
  "properties": {
    "addr:full":"844 Salt Springs Rd Syracuse NY 13224",
    "addr:housenumber":"844",
    "addr:postcode":"13224",
    "addr:street":"Salt Springs Rd",
    "iso:country":"US",
    "sg:address":"844 Salt Springs Rd",
    "sg:city":"Syracuse",
    "sg:classifiers":[
        {
            "category":"Organizations",
            "subcategory":"Religious Organization",
            "type":"Services"
        }
    ],
    "sg:phone":"+1 315 446 6644",
    "sg:postcode":"13224",
    "sg:province":"NY",
    "sg:tags":[
        "clergy"
    ],
    "wof:name":"Sherman Dunmore",
    "wof:placetype":"venue"
},
  "geometry": {"coordinates":[-76.10346199999999,43.046257],"type":"Point"}
}