{
  "type": "Feature",
  "properties": {
    "addr:full":"373 Smithtown Byp #116 Hauppauge NY 11788",
    "addr:housenumber":"373;# 116",
    "addr:postcode":"11788",
    "addr:street":"Byp",
    "iso:country":"US",
    "sg:address":"373 Smithtown Byp #116",
    "sg:city":"Hauppauge",
    "sg:classifiers":[
        {
            "category":"Banks & Credit Unions",
            "subcategory":"Financial Services",
            "type":"Services"
        }
    ],
    "sg:phone":"+1 631 615 0024",
    "sg:postcode":"11788",
    "sg:province":"NY",
    "sg:tags":[
        "franchising"
    ],
    "sg:website":"http://www.becomeaticketbroker.com",
    "wof:name":"Become A Ticket Broker",
    "wof:placetype":"venue"
},
  "geometry": {"coordinates":[-73.201846,40.828668],"type":"Point"}
}