{
  "type": "Feature",
  "properties": {
    "addr:full":"13 Dickinson Ave Nyack NY 10960",
    "addr:housenumber":"13",
    "addr:postcode":"10960",
    "addr:street":"Dickinson Ave",
    "iso:country":"US",
    "sg:address":"13 Dickinson Ave",
    "sg:city":"Nyack",
    "sg:classifiers":[
        {
            "category":"Education",
            "subcategory":"School",
            "type":"Public Place"
        }
    ],
    "sg:phone":"+1 845 353 7000",
    "sg:postcode":"10960",
    "sg:province":"NY",
    "wof:name":"Nyack Union Free School Supt",
    "wof:placetype":"venue"
},
  "geometry": {"coordinates":[-73.935813,41.09142],"type":"Point"}
}