{
  "type": "Feature",
  "properties": {
    "addr:full":"3508 E Tremont Ave Bronx NY 10465",
    "addr:housenumber":"3508",
    "addr:postcode":"10465",
    "addr:street":"E Tremont Ave",
    "iso:country":"US",
    "sg:address":"3508 E Tremont Ave",
    "sg:city":"Bronx",
    "sg:classifiers":[
        {
            "category":"Cinema",
            "subcategory":"Movie Rental",
            "type":"Entertainment"
        }
    ],
    "sg:phone":"+1 718 409 4634",
    "sg:postcode":"10465",
    "sg:province":"NY",
    "sg:tags":[
        "leasing",
        "video",
        "disc",
        "tape"
    ],
    "wof:name":"ABC D's",
    "wof:placetype":"venue"
},
  "geometry": {"coordinates":[-73.82612899999999,40.830497],"type":"Point"}
}