{
  "type": "Feature",
  "properties": {
    "iso:country":"US",
    "sg:address":"170 Golf Ave",
    "sg:city":"Pittsford",
    "sg:classifiers":[
        {
            "category":"Building & Trades",
            "subcategory":"Construction",
            "type":"Services"
        }
    ],
    "sg:phone":"+1 585 586 5397",
    "sg:postcode":"14534",
    "sg:province":"NY",
    "sg:tags":[
        "residential"
    ],
    "wof:name":"Marshall D Gates III",
    "wof:placetype":"venue"
},
  "geometry": {"coordinates":[-77.487043,43.096684],"type":"Point"}
}