{
  "type": "Feature",
  "properties": {
    "addr:full":"1724 86th St Brooklyn NY 11214",
    "addr:housenumber":"1724",
    "addr:postcode":"11214",
    "addr:street":"86Th St",
    "iso:country":"US",
    "sg:address":"1724 86th St",
    "sg:city":"Brooklyn",
    "sg:classifiers":[
        {
            "category":"Professional",
            "subcategory":"Management & Consulting",
            "type":"Services"
        }
    ],
    "sg:phone":"+1 718 259 6377",
    "sg:postcode":"11214",
    "sg:province":"NY",
    "wof:name":"Dennis Ferrier",
    "wof:placetype":"venue"
},
  "geometry": {"coordinates":[-74.00485399999999,40.608594],"type":"Point"}
}