{
  "type": "Feature",
  "properties": {
    "addr:full":"802 Foxwood Dr Clifton Park NY 12065",
    "addr:housenumber":"802",
    "addr:postcode":"12065",
    "addr:street":"Foxwood Dr",
    "iso:country":"US",
    "sg:address":"802 Foxwood Dr",
    "sg:city":"Clifton Park",
    "sg:classifiers":[
        {
            "category":"Wholesale",
            "subcategory":"Sporting Goods",
            "type":"Manufacturing & Wholesale Goods"
        }
    ],
    "sg:phone":"+1 518 348 6358",
    "sg:postcode":"12065",
    "sg:province":"NY",
    "wof:name":"Penguin Specialty Inc",
    "wof:placetype":"venue"
},
  "geometry": {"coordinates":[-73.795891,42.811208],"type":"Point"}
}