{
  "type": "Feature",
  "properties": {
    "iso:country":"US",
    "sg:address":"33 Corporate Dr",
    "sg:city":"Orangeburg",
    "sg:classifiers":[
        {
            "category":"Manufacturing",
            "subcategory":"Printing",
            "type":"Manufacturing & Wholesale Goods"
        }
    ],
    "sg:phone":"+1 845 398 9500",
    "sg:postcode":"10962",
    "sg:province":"NY",
    "sg:tags":[
        "apparel",
        "custom"
    ],
    "wof:name":"Zag Wear",
    "wof:placetype":"venue"
},
  "geometry": {"coordinates":[-73.983661,41.035312],"type":"Point"}
}