{
  "type": "Feature",
  "properties": {
    "iso:country":"US",
    "sg:address":"1055 Stewart Ave",
    "sg:city":"Bethpage",
    "sg:classifiers":[
        {
            "category":"Restaurant",
            "type":"Food & Drink"
        }
    ],
    "sg:phone":"+1   ",
    "sg:postcode":"11714",
    "sg:province":"NY",
    "sg:tags":[
        "eating"
    ],
    "wof:name":"Skjc Corp",
    "wof:placetype":"venue"
},
  "geometry": {"coordinates":[-73.489081,40.759505],"type":"Point"}
}