{
  "type": "Feature",
  "properties": {
    "addr:full":"5891 State Hwy 29 Saint Johnsville NY 13452",
    "addr:housenumber":"5891",
    "addr:postcode":"13452",
    "addr:street":"State Hwy 29 Saint",
    "iso:country":"US",
    "sg:address":"5891 State Hwy 29",
    "sg:city":"Saint Johnsville",
    "sg:classifiers":[
        {
            "category":"Manufacturing",
            "subcategory":"Tools & Machinery",
            "type":"Manufacturing & Wholesale Goods"
        }
    ],
    "sg:phone":"+1   ",
    "sg:postcode":"13452",
    "sg:province":"NY",
    "sg:tags":[
        "power",
        "mfg"
    ],
    "wof:name":"De Pietro Bros",
    "wof:placetype":"venue"
},
  "geometry": {"coordinates":[-74.59873899999999,43.048308],"type":"Point"}
}