{
  "type": "Feature",
  "properties": {
    "iso:country":"US",
    "sg:address":"120 N Miller St",
    "sg:city":"Newburgh",
    "sg:classifiers":[
        {
            "category":"Organizations",
            "subcategory":"Religious Organization",
            "type":"Services"
        }
    ],
    "sg:phone":"+1   ",
    "sg:postcode":"12550",
    "sg:province":"NY",
    "sg:website":"www.soulsavingstation.org",
    "wof:name":"Soul Saving Station",
    "wof:placetype":"venue"
},
  "geometry": {"coordinates":[-74.0142,41.506491],"type":"Point"}
}