{
  "type": "Feature",
  "properties": {
    "addr:full":"111 Kelly Dr Cheektowaga NY 14227",
    "addr:housenumber":"111",
    "addr:postcode":"14227",
    "addr:street":"Kelly Dr",
    "iso:country":"US",
    "sg:address":"111 Kelly Dr",
    "sg:city":"Cheektowaga",
    "sg:classifiers":[
        {
            "category":"Social Services",
            "subcategory":"Child Care",
            "type":"Services"
        }
    ],
    "sg:phone":"+1 716 677 4063",
    "sg:postcode":"14227",
    "sg:province":"NY",
    "sg:tags":[
        "kindergarten",
        "academic",
        "school"
    ],
    "sg:website":"www.childrenkastle.com",
    "wof:name":"Childrens' Kastle",
    "wof:placetype":"venue"
},
  "geometry": {"coordinates":[-78.736807,42.867203],"type":"Point"}
}