{
  "type": "Feature",
  "properties": {
    "addr:full":"579 5th Ave Brooklyn NY 11215",
    "addr:housenumber":"579",
    "addr:postcode":"11215",
    "addr:street":"5Th Ave",
    "iso:country":"US",
    "sg:address":"579 5th Ave",
    "sg:city":"Brooklyn",
    "sg:classifiers":[
        {
            "category":"Shopping",
            "type":"Retail Goods"
        }
    ],
    "sg:phone":"+1 718 788 2950",
    "sg:postcode":"11215",
    "sg:province":"NY",
    "wof:name":"Monk Vintage Thrift Shop",
    "wof:placetype":"venue"
},
  "geometry": {"coordinates":[-73.98987700000001,40.664892],"type":"Point"}
}