{
  "type": "Feature",
  "properties": {
    "iso:country":"US",
    "sg:address":"2599 Saw Mill Rd",
    "sg:city":"North Bellmore",
    "sg:classifiers":[
        {
            "category":"Shopping",
            "subcategory":"Musical Instruments",
            "type":"Retail Goods"
        }
    ],
    "sg:phone":"+1 516 781 6466",
    "sg:postcode":"11710",
    "sg:province":"NY",
    "wof:name":"Ash Instruments Inc",
    "wof:placetype":"venue"
},
  "geometry": {"coordinates":[-73.533708,40.698301],"type":"Point"}
}