{
  "type": "Feature",
  "properties": {
    "iso:country":"US",
    "sg:address":"96 Lefferts Pl",
    "sg:city":"Brooklyn",
    "sg:classifiers":[
        {
            "category":"Communications",
            "subcategory":"Film & Video Production",
            "type":"Services"
        }
    ],
    "sg:phone":"+1 718 636 4038",
    "sg:postcode":"11238",
    "sg:province":"NY",
    "sg:tags":[
        "taping"
    ],
    "wof:name":"Brooklyn Funk Productions",
    "wof:placetype":"venue"
},
  "geometry": {"coordinates":[-73.959536,40.681035],"type":"Point"}
}