{
  "type": "Feature",
  "properties": {
    "iso:country":"US",
    "sg:address":"313 43rd St",
    "sg:city":"Brooklyn",
    "sg:classifiers":[
        {
            "category":"Health Services",
            "subcategory":"Doctor",
            "type":"Services"
        }
    ],
    "sg:phone":"+1 718 788 1919",
    "sg:postcode":"11232",
    "sg:province":"NY",
    "wof:name":"Pavilion At the Ambulator Surgery Ctr of Brooklyn",
    "wof:placetype":"venue"
},
  "geometry": {"coordinates":[-74.010002,40.651501],"type":"Point"}
}