{
  "type": "Feature",
  "properties": {
    "iso:country":"US",
    "sg:address":"109 MacDougal St",
    "sg:city":"New York",
    "sg:classifiers":[
        {
            "category":"Bars & Pubs",
            "type":"Food & Drink"
        }
    ],
    "sg:phone":"+1 212 533 4487",
    "sg:postcode":"10012",
    "sg:province":"NY",
    "wof:name":"Off The Wagon",
    "wof:placetype":"venue"
},
  "geometry": {"coordinates":[-74.00082399999999,40.729929],"type":"Point"}
}