{
  "type": "Feature",
  "properties": {
    "addr:full":"27 Masten Ave Buffalo NY 14204",
    "addr:housenumber":"27",
    "addr:postcode":"14204",
    "addr:street":"Masten Ave",
    "iso:country":"US",
    "sg:address":"27 Masten Ave",
    "sg:city":"Buffalo",
    "sg:classifiers":[
        {
            "category":"Government",
            "subcategory":"Office",
            "type":"Public Place"
        }
    ],
    "sg:phone":"+1 716 888 5652",
    "sg:postcode":"14204",
    "sg:province":"NY",
    "sg:tags":[
        "force",
        "national",
        "armed",
        "security",
        "recruiting"
    ],
    "wof:name":"Oms 1",
    "wof:placetype":"venue"
},
  "geometry": {"coordinates":[-78.859781,42.903099],"type":"Point"}
}