{
  "type": "Feature",
  "properties": {
    "addr:full":"437 Mill Rd Rochester NY 14626",
    "addr:housenumber":"437",
    "addr:postcode":"14626",
    "addr:street":"Mill Rd",
    "iso:country":"US",
    "sg:address":"437 Mill Rd",
    "sg:city":"Rochester",
    "sg:classifiers":[
        {
            "category":"Real Estate",
            "subcategory":"Real Estate Agent",
            "type":"Services"
        }
    ],
    "sg:phone":"+1 585 227 9090",
    "sg:postcode":"14626",
    "sg:province":"NY",
    "wof:name":"Tra-Mac Realty Corp",
    "wof:placetype":"venue"
},
  "geometry": {"coordinates":[-77.735511,43.231592],"type":"Point"}
}