{
  "type": "Feature",
  "properties": {
    "addr:full":"577 3rd Ave Brooklyn NY 11215",
    "addr:housenumber":"577",
    "addr:postcode":"11215",
    "addr:street":"3Rd Ave",
    "iso:country":"US",
    "sg:address":"577 3rd Ave",
    "sg:city":"Brooklyn",
    "sg:classifiers":[
        {
            "category":"Food & Beverages",
            "subcategory":"Meat & Fish",
            "type":"Retail Goods"
        }
    ],
    "sg:phone":"+1 718 499 0304",
    "sg:postcode":"11215",
    "sg:province":"NY",
    "sg:tags":[
        "shop"
    ],
    "wof:name":"Tye Ping Supply Inc",
    "wof:placetype":"venue"
},
  "geometry": {"coordinates":[-73.994044,40.667565],"type":"Point"}
}