{
  "type": "Feature",
  "properties": {
    "addr:full":"1126 Kings Hwy Brooklyn NY 11229",
    "addr:housenumber":"1126",
    "addr:postcode":"11229",
    "addr:street":"Kings Hwy",
    "iso:country":"US",
    "sg:address":"1126 Kings Hwy",
    "sg:city":"Brooklyn",
    "sg:classifiers":[
        {
            "category":"Building & Trades",
            "subcategory":"Equipment Rental",
            "type":"Services"
        }
    ],
    "sg:phone":"+1 718 339 5867",
    "sg:postcode":"11229",
    "sg:province":"NY",
    "sg:tags":[
        "leasing"
    ],
    "wof:name":"Safe Harbor Leasing",
    "wof:placetype":"venue"
},
  "geometry": {"coordinates":[-73.961073,40.607531],"type":"Point"}
}