{
  "type": "Feature",
  "properties": {
    "addr:full":"67 Thompson St New York NY 10012",
    "addr:housenumber":"67",
    "addr:postcode":"10012",
    "addr:street":"Thompson St",
    "iso:country":"US",
    "sg:address":"67 Thompson St",
    "sg:city":"New York",
    "sg:classifiers":[
        {
            "category":"Communications",
            "type":"Services"
        }
    ],
    "sg:phone":"+1 917 640 5217",
    "sg:postcode":"10012",
    "sg:province":"NY",
    "sg:tags":[
        "medium",
        "mass"
    ],
    "sg:website":"www.stevebrickles.com",
    "wof:name":"Steve Brickles",
    "wof:placetype":"venue"
},
  "geometry": {"coordinates":[-74.003316,40.724433],"type":"Point"}
}