{
  "type": "Feature",
  "properties": {
    "iso:country":"US",
    "sg:address":"399 Knickerbocker Ave",
    "sg:city":"Brooklyn",
    "sg:classifiers":[
        {
            "category":"Shopping",
            "subcategory":"Clothing, Apparel, & Fashions",
            "type":"Retail Goods"
        }
    ],
    "sg:phone":"+1 718 574 0115",
    "sg:postcode":"11237",
    "sg:province":"NY",
    "wof:name":"S & D Children's Ctr",
    "wof:placetype":"venue"
},
  "geometry": {"coordinates":[-73.920445,40.700151],"type":"Point"}
}