{
  "type": "Feature",
  "properties": {
    "iso:country":"US",
    "sg:address":"99 Division Ave",
    "sg:city":"East Islip",
    "sg:classifiers":[
        {
            "category":"Building & Trades",
            "subcategory":"Construction",
            "type":"Services"
        }
    ],
    "sg:phone":"+1 631 277 7400",
    "sg:postcode":"11730",
    "sg:province":"NY",
    "sg:tags":[
        "contractor"
    ],
    "wof:name":"Regional Renovation Corp",
    "wof:placetype":"venue"
},
  "geometry": {"coordinates":[-73.189634,40.738753],"type":"Point"}
}