{
  "type": "Feature",
  "properties": {
    "iso:country":"US",
    "sg:address":"4105 Hylan Blvd",
    "sg:city":"Staten Island",
    "sg:classifiers":[
        {
            "category":"Restaurant",
            "type":"Food & Drink"
        }
    ],
    "sg:postcode":"10314",
    "sg:province":"NY",
    "sg:tags":[
        "italian"
    ],
    "wof:name":"Giuliana's",
    "wof:placetype":"venue"
},
  "geometry": {"coordinates":[-74.14819900000001,40.539784],"type":"Point"}
}