{
  "type": "Feature",
  "properties": {
    "addr:full":"6 Winters Ct Plainview NY 11803",
    "addr:housenumber":"6",
    "addr:postcode":"11803",
    "addr:street":"Winters Ct",
    "iso:country":"US",
    "sg:address":"6 Winters Ct",
    "sg:city":"Plainview",
    "sg:classifiers":[
        {
            "category":"Building & Trades",
            "subcategory":"Plumbing",
            "type":"Services"
        }
    ],
    "sg:phone":"+1 516 349 5561",
    "sg:postcode":"11803",
    "sg:province":"NY",
    "sg:tags":[
        "contractor"
    ],
    "wof:name":"Fairway Properties Corp",
    "wof:placetype":"venue"
},
  "geometry": {"coordinates":[-73.478177,40.791531],"type":"Point"}
}