{
  "type": "Feature",
  "properties": {
    "iso:country":"US",
    "sg:address":"201 W Broadway",
    "sg:city":"Port Jefferson",
    "sg:classifiers":[
        {
            "category":"Travel",
            "subcategory":"Hotels & Motels",
            "type":"Entertainment"
        }
    ],
    "sg:phone":"+1 631 928 2400",
    "sg:postcode":"11777",
    "sg:province":"NY",
    "sg:website":"www.portjeffheritageinn.com",
    "wof:name":"Heritage Inn",
    "wof:placetype":"venue"
},
  "geometry": {"coordinates":[-73.073638,40.944663],"type":"Point"}
}