{
  "type": "Feature",
  "properties": {
    "addr:full":"31-13 21 Long Island City NY 11101",
    "addr:housenumber":"31-13",
    "addr:postcode":"11101",
    "addr:street":"21",
    "iso:country":"US",
    "sg:address":"31-13 21",
    "sg:city":"Long Island City",
    "sg:classifiers":[
        {
            "category":"Food & Beverages",
            "subcategory":"Groceries & Convenience Stores",
            "type":"Retail Goods"
        }
    ],
    "sg:phone":"+1 718 728 7022",
    "sg:postcode":"11101",
    "sg:province":"NY",
    "wof:name":"Ana Deli & Grocery",
    "wof:placetype":"venue"
},
  "geometry": {"coordinates":[-73.938869,40.759639],"type":"Point"}
}