{
  "type": "Feature",
  "properties": {
    "addr:full":"194 Olmstead Ave Depew NY 14043",
    "addr:housenumber":"194",
    "addr:postcode":"14043",
    "addr:street":"Olmstead Ave",
    "iso:country":"US",
    "sg:address":"194 Olmstead Ave",
    "sg:city":"Depew",
    "sg:classifiers":[
        {
            "category":"Manufacturing",
            "subcategory":"Printing",
            "type":"Manufacturing & Wholesale Goods"
        }
    ],
    "sg:phone":"+1   ",
    "sg:postcode":"14043",
    "sg:province":"NY",
    "sg:tags":[
        "commercial"
    ],
    "wof:name":"Independent Press",
    "wof:placetype":"venue"
},
  "geometry": {"coordinates":[-78.68850399999999,42.916896],"type":"Point"}
}