{
  "type": "Feature",
  "properties": {
    "addr:full":"65 Cedar Ave Hewlett NY 11557",
    "addr:housenumber":"65",
    "addr:postcode":"11557",
    "addr:street":"Cedar Ave",
    "iso:country":"US",
    "sg:address":"65 Cedar Ave",
    "sg:city":"Hewlett",
    "sg:classifiers":[
        {
            "category":"Health Services",
            "subcategory":"Doctor",
            "type":"Services"
        }
    ],
    "sg:phone":"+1 516 295 0505",
    "sg:postcode":"11557",
    "sg:province":"NY",
    "sg:tags":[
        "physician",
        "surgeon"
    ],
    "wof:name":"Irwin L Harris PC",
    "wof:placetype":"venue"
},
  "geometry": {"coordinates":[-73.699123,40.637572],"type":"Point"}
}