{
  "type": "Feature",
  "properties": {
    "iso:country":"US",
    "sg:address":"28 Dogwood Dr",
    "sg:city":"Smithtown",
    "sg:classifiers":[
        {
            "category":"Building & Trades",
            "subcategory":"Construction",
            "type":"Services"
        }
    ],
    "sg:phone":"+1 631 360 7764",
    "sg:postcode":"11787",
    "sg:province":"NY",
    "sg:tags":[
        "house",
        "business"
    ],
    "wof:name":"All Island Termite & Hm Imprv",
    "wof:placetype":"venue"
},
  "geometry": {"coordinates":[-73.176604,40.860587],"type":"Point"}
}