{
  "type": "Feature",
  "properties": {
    "addr:full":"2361 Morris Ave Bronx NY 10468",
    "addr:housenumber":"2361",
    "addr:postcode":"10468",
    "addr:street":"Morris Ave",
    "iso:country":"US",
    "sg:address":"2361 Morris Ave",
    "sg:city":"Bronx",
    "sg:classifiers":[
        {
            "category":"Retail",
            "subcategory":"Photofinishing",
            "type":"Services"
        }
    ],
    "sg:phone":"+1 718 561 7934",
    "sg:postcode":"10468",
    "sg:province":"NY",
    "sg:tags":[
        "photo",
        "finishing"
    ],
    "wof:name":"One Step Film & Polaroi",
    "wof:placetype":"venue"
},
  "geometry": {"coordinates":[-73.90106400000001,40.859544],"type":"Point"}
}