{
  "type": "Feature",
  "properties": {
    "addr:full":"975 Clinton Ave S Rochester NY 14620",
    "addr:housenumber":"975",
    "addr:postcode":"14620",
    "addr:street":"Clinton Ave S",
    "iso:country":"US",
    "sg:address":"975 Clinton Ave S",
    "sg:city":"Rochester",
    "sg:classifiers":[
        {
            "category":"Shopping",
            "subcategory":"Hobbies, Toys, & Games",
            "type":"Retail Goods"
        }
    ],
    "sg:phone":"+1   ",
    "sg:postcode":"14620",
    "sg:province":"NY",
    "wof:name":"Animas Traders",
    "wof:placetype":"venue"
},
  "geometry": {"coordinates":[-77.595444,43.13888],"type":"Point"}
}