{
  "type": "Feature",
  "properties": {
    "iso:country":"US",
    "sg:address":"850 3rd Ave Ste 1101",
    "sg:city":"New York",
    "sg:classifiers":[
        {
            "category":"Professional",
            "subcategory":"Employment Agencies",
            "type":"Services"
        }
    ],
    "sg:phone":"+1 212 792 2265",
    "sg:postcode":"10022",
    "sg:province":"NY",
    "wof:name":"Whitney Group LLC",
    "wof:placetype":"venue"
},
  "geometry": {"coordinates":[-73.969847,40.756865],"type":"Point"}
}