{
  "type": "Feature",
  "properties": {
    "iso:country":"US",
    "sg:address":"23 Romca Rd",
    "sg:city":"Poughkeepsie",
    "sg:classifiers":[
        {
            "category":"Professional",
            "subcategory":"Management & Consulting",
            "type":"Services"
        },
        {
            "category":"Professional",
            "subcategory":"Business Services",
            "type":"Services"
        },
        {
            "category":"Professional",
            "subcategory":"Engineering",
            "type":"Services"
        }
    ],
    "sg:phone":"+1 845 462 0022",
    "sg:postcode":"12603",
    "sg:province":"NY",
    "sg:tags":[
        "consultant",
        "engineer"
    ],
    "wof:name":"Stormwater Management Consultants Inc",
    "wof:placetype":"venue"
},
  "geometry": {"coordinates":[-73.870687,41.655046],"type":"Point"}
}