{
  "type": "Feature",
  "properties": {
    "iso:country":"US",
    "sg:address":"421 Hawkins Ave",
    "sg:city":"Ronkonkoma",
    "sg:classifiers":[
        {
            "category":"Organizations",
            "subcategory":"Community Association",
            "type":"Services"
        }
    ],
    "sg:phone":"+1 631 737 1077",
    "sg:postcode":"11779",
    "sg:province":"NY",
    "sg:tags":[
        "club"
    ],
    "wof:name":"BBC Social",
    "wof:placetype":"venue"
},
  "geometry": {"coordinates":[-73.10737899999999,40.825929],"type":"Point"}
}