{
  "type": "Feature",
  "properties": {
    "iso:country":"US",
    "sg:address":"112 Winfield St",
    "sg:city":"Staten Island",
    "sg:classifiers":[
        {
            "category":"Building & Trades",
            "subcategory":"Construction",
            "type":"Services"
        }
    ],
    "sg:phone":"+1 718 980 6332",
    "sg:postcode":"10305",
    "sg:province":"NY",
    "sg:tags":[
        "general",
        "contractor"
    ],
    "wof:name":"Shaw Contracting",
    "wof:placetype":"venue"
},
  "geometry": {"coordinates":[-74.077085,40.589336],"type":"Point"}
}