{
  "type": "Feature",
  "properties": {
    "iso:country":"US",
    "sg:address":"60 Dott Ave",
    "sg:city":"Albany",
    "sg:classifiers":[
        {
            "category":"Freight",
            "type":"Transportation"
        }
    ],
    "sg:phone":"+1 518 689 0467",
    "sg:postcode":"12205",
    "sg:province":"NY",
    "sg:tags":[
        "delivery"
    ],
    "wof:name":"Airline Luggage Delivery Svc",
    "wof:placetype":"venue"
},
  "geometry": {"coordinates":[-73.813495,42.693139],"type":"Point"}
}