{
  "type": "Feature",
  "properties": {
    "addr:full":"37 Morgan Rd Binghamton NY 13903",
    "addr:housenumber":"37",
    "addr:postcode":"13903",
    "addr:street":"Morgan Rd",
    "iso:country":"US",
    "sg:address":"37 Morgan Rd",
    "sg:city":"Binghamton",
    "sg:classifiers":[
        {
            "category":"Building & Trades",
            "subcategory":"Landscaping Services",
            "type":"Services"
        }
    ],
    "sg:phone":"+1 607 772 1228",
    "sg:postcode":"13903",
    "sg:province":"NY",
    "wof:name":"Skuban Tree Specialists",
    "wof:placetype":"venue"
},
  "geometry": {"coordinates":[-75.909498,42.07664],"type":"Point"}
}