{
  "type": "Feature",
  "properties": {
    "iso:country":"US",
    "sg:address":"701 Bedford Rd",
    "sg:city":"Bedford Hills",
    "sg:classifiers":[
        {
            "category":"Building & Trades",
            "subcategory":"Construction",
            "type":"Services"
        }
    ],
    "sg:phone":"+1 914 244 8815",
    "sg:postcode":"10507",
    "sg:province":"NY",
    "sg:tags":[
        "carpenter"
    ],
    "wof:name":"Larry Perlman Carpentry & Elec",
    "wof:placetype":"venue"
},
  "geometry": {"coordinates":[-73.71334899999999,41.226348],"type":"Point"}
}