{
  "type": "Feature",
  "properties": {
    "iso:country":"US",
    "sg:address":"1916 7th Ave",
    "sg:city":"New York",
    "sg:classifiers":[
        {
            "category":"Food & Beverages",
            "subcategory":"Groceries & Convenience Stores",
            "type":"Retail Goods"
        }
    ],
    "sg:phone":"+1   ",
    "sg:postcode":"10026",
    "sg:province":"NY",
    "sg:tags":[
        "product",
        "tobacco"
    ],
    "wof:name":"Harlem Grocery & Tobacco",
    "wof:placetype":"venue"
},
  "geometry": {"coordinates":[-73.952975,40.802624],"type":"Point"}
}