{
  "type": "Feature",
  "properties": {
    "iso:country":"US",
    "sg:address":"203 W 12th St",
    "sg:city":"New York",
    "sg:classifiers":[
        {
            "category":"Health Services",
            "subcategory":"Doctor",
            "type":"Services"
        },
        {
            "category":"Health Services",
            "subcategory":"Dentist",
            "type":"Services"
        }
    ],
    "sg:phone":"+1 212 243 2023",
    "sg:postcode":"10011",
    "sg:province":"NY",
    "sg:tags":[
        "surgeon",
        "oral"
    ],
    "wof:name":"Engelhard Gwen M DDS",
    "wof:placetype":"venue"
},
  "geometry": {"coordinates":[-73.998802,40.741501],"type":"Point"}
}