{
  "type": "Feature",
  "properties": {
    "addr:full":"39 Downing St New York NY 10014",
    "addr:housenumber":"39",
    "addr:postcode":"10014",
    "addr:street":"Downing St",
    "iso:country":"US",
    "sg:address":"39 Downing St",
    "sg:city":"New York",
    "sg:classifiers":[
        {
            "category":"Restaurant",
            "type":"Food & Drink"
        }
    ],
    "sg:phone":"+1 212 255 1790",
    "sg:postcode":"10014",
    "sg:province":"NY",
    "sg:tags":[
        "new",
        "american",
        "french"
    ],
    "sg:website":"www.masfarmhouse.com",
    "wof:name":"Mas Farmhouse",
    "wof:placetype":"venue"
},
  "geometry": {"coordinates":[-74.003608,40.729345],"type":"Point"}
}