{
  "type": "Feature",
  "properties": {
    "addr:full":"45 Spring St New York NY 10012",
    "addr:housenumber":"45",
    "addr:postcode":"10012",
    "addr:street":"Spring St",
    "iso:country":"US",
    "sg:address":"45 Spring St",
    "sg:city":"New York",
    "sg:classifiers":[
        {
            "category":"Professional",
            "subcategory":"Management & Consulting",
            "type":"Services"
        }
    ],
    "sg:phone":"+1   ",
    "sg:postcode":"10012",
    "sg:province":"NY",
    "sg:tags":[
        "retail",
        "direct",
        "sales"
    ],
    "wof:name":"Nyc Case Co",
    "wof:placetype":"venue"
},
  "geometry": {"coordinates":[-73.99569,40.721722],"type":"Point"}
}