{
  "type": "Feature",
  "properties": {
    "addr:full":"123 Fiddlers Hollow Penfield NY 14526",
    "addr:housenumber":"123",
    "addr:postcode":"14526",
    "addr:street":"Fiddlers Hollow",
    "iso:country":"US",
    "sg:address":"123 Fiddlers Hollow",
    "sg:city":"Penfield",
    "sg:classifiers":[
        {
            "category":"Organizations",
            "subcategory":"Community Association",
            "type":"Services"
        }
    ],
    "sg:phone":"+1 585 377 6384",
    "sg:postcode":"14526",
    "sg:province":"NY",
    "wof:name":"Gamma Beta",
    "wof:placetype":"venue"
},
  "geometry": {"coordinates":[-77.452991,43.157333],"type":"Point"}
}