{
  "type": "Feature",
  "properties": {
    "iso:country":"US",
    "sg:address":"8 Lent Ct",
    "sg:city":"Schenectady",
    "sg:classifiers":[
        {
            "category":"Freight",
            "type":"Transportation"
        }
    ],
    "sg:phone":"+1   ",
    "sg:postcode":"12306",
    "sg:province":"NY",
    "sg:tags":[
        "operator",
        "local",
        "trucking"
    ],
    "wof:name":"J Cruz Trucking",
    "wof:placetype":"venue"
},
  "geometry": {"coordinates":[-74.001942,42.795969],"type":"Point"}
}