{
  "type": "Feature",
  "properties": {
    "iso:country":"US",
    "sg:address":"100 Route 303",
    "sg:city":"Tappan",
    "sg:classifiers":[
        {
            "category":"Professional",
            "subcategory":"Lawyer & Legal Services",
            "type":"Services"
        }
    ],
    "sg:phone":"+1 845 359 0093",
    "sg:postcode":"10983",
    "sg:province":"NY",
    "sg:tags":[
        "attorney",
        "practice"
    ],
    "wof:name":"Ciganek Thomas A",
    "wof:placetype":"venue"
},
  "geometry": {"coordinates":[-73.943916,41.029129],"type":"Point"}
}