{
  "type": "Feature",
  "properties": {
    "iso:country":"US",
    "sg:address":"559 Lexington Ave",
    "sg:city":"Brooklyn",
    "sg:classifiers":[
        {
            "category":"Organizations",
            "subcategory":"Religious Organization",
            "type":"Services"
        }
    ],
    "sg:phone":"+1 718 573 0208",
    "sg:postcode":"11221",
    "sg:province":"NY",
    "sg:tags":[
        "clergy"
    ],
    "wof:name":"V Robinson",
    "wof:placetype":"venue"
},
  "geometry": {"coordinates":[-73.93640000000001,40.689418],"type":"Point"}
}