{
  "type": "Feature",
  "properties": {
    "iso:country":"US",
    "sg:address":"2075 Grand Ave",
    "sg:city":"North Baldwin",
    "sg:classifiers":[
        {
            "category":"Insurance",
            "subcategory":"Insurance Agent",
            "type":"Services"
        }
    ],
    "sg:phone":"+1 516 223 3144",
    "sg:postcode":"11510",
    "sg:province":"NY",
    "sg:website":"www.abilityservice.com",
    "wof:name":"Ability Service Agency Inc",
    "wof:placetype":"venue"
},
  "geometry": {"coordinates":[-73.608289,40.658887],"type":"Point"}
}