{
  "type": "Feature",
  "properties": {
    "iso:country":"US",
    "sg:address":"420 S Broadway",
    "sg:city":"Hicksville",
    "sg:classifiers":[
        {
            "category":"Building & Trades",
            "subcategory":"Electrical",
            "type":"Services"
        }
    ],
    "sg:phone":"+1 516 681 5656",
    "sg:postcode":"11801",
    "sg:province":"NY",
    "sg:tags":[
        "electric",
        "contractor"
    ],
    "wof:name":"Nassau Electric League Inc",
    "wof:placetype":"venue"
},
  "geometry": {"coordinates":[-73.51260600000001,40.758347],"type":"Point"}
}