{
  "type": "Feature",
  "properties": {
    "addr:full":"51 S Alder St West Babylon NY 11704",
    "addr:housenumber":"51",
    "addr:postcode":"11704",
    "addr:street":"S Alder St",
    "iso:country":"US",
    "sg:address":"51 S Alder St",
    "sg:city":"West Babylon",
    "sg:classifiers":[
        {
            "category":"Building & Trades",
            "subcategory":"Plumbing",
            "type":"Services"
        },
        {
            "category":"Retail",
            "subcategory":"Auto Repair",
            "type":"Services"
        }
    ],
    "sg:phone":"+1 631 293 0045",
    "sg:postcode":"11704",
    "sg:province":"NY",
    "sg:tags":[
        "mechanical",
        "general",
        "contractor"
    ],
    "wof:name":"TNT Mechanical N Interiors",
    "wof:placetype":"venue"
},
  "geometry": {"coordinates":[-73.394774,40.729887],"type":"Point"}
}