{
  "type": "Feature",
  "properties": {
    "iso:country":"US",
    "sg:address":"5 Helen Pl",
    "sg:city":"Glen Cove",
    "sg:classifiers":[
        {
            "category":"Organizations",
            "subcategory":"Religious Organization",
            "type":"Services"
        }
    ],
    "sg:phone":"+1 516 671 8238",
    "sg:postcode":"11542",
    "sg:province":"NY",
    "sg:tags":[
        "science",
        "christian",
        "practitioner"
    ],
    "wof:name":"Natalie S Dodge",
    "wof:placetype":"venue"
},
  "geometry": {"coordinates":[-73.605362,40.864521],"type":"Point"}
}