{
  "type": "Feature",
  "properties": {
    "addr:full":"90 Broad St Plattsburgh NY 12901",
    "addr:housenumber":"90",
    "addr:postcode":"12901",
    "addr:street":"Broad St",
    "iso:country":"US",
    "sg:address":"90 Broad St",
    "sg:city":"Plattsburgh",
    "sg:classifiers":[
        {
            "category":"Organizations",
            "subcategory":"Religious Organization",
            "type":"Services"
        }
    ],
    "sg:phone":"+1 518 561 7545",
    "sg:postcode":"12901",
    "sg:province":"NY",
    "sg:tags":[
        "church"
    ],
    "wof:name":"Newman Ctr",
    "wof:placetype":"venue"
},
  "geometry": {"coordinates":[-73.464285,44.694825],"type":"Point"}
}