{
  "type": "Feature",
  "properties": {
    "addr:full":"1580 Jerome Avenue Bronx NY 10452",
    "addr:housenumber":"1580",
    "addr:postcode":"10452",
    "addr:street":"Jerome Avenue",
    "iso:country":"US",
    "sg:address":"1580 Jerome Avenue",
    "sg:city":"Bronx",
    "sg:classifiers":[
        {
            "category":"Restaurant",
            "type":"Food & Drink"
        }
    ],
    "sg:phone":"+1 718 583 0327",
    "sg:postcode":"10452",
    "sg:province":"NY",
    "sg:tags":[
        "chinese"
    ],
    "wof:name":"China Wok",
    "wof:placetype":"venue"
},
  "geometry": {"coordinates":[-73.914507,40.844344],"type":"Point"}
}