{
  "type": "Feature",
  "properties": {
    "iso:country":"US",
    "sg:address":"121 US Hwy 4",
    "sg:city":"Schuylerville",
    "sg:classifiers":[
        {
            "category":"Government",
            "subcategory":"Office",
            "type":"Public Place"
        }
    ],
    "sg:phone":"+1 518 695 4995",
    "sg:postcode":"12871",
    "sg:province":"NY",
    "sg:tags":[
        "state",
        "program"
    ],
    "wof:name":"Environmental Dept",
    "wof:placetype":"venue"
},
  "geometry": {"coordinates":[-73.59710800000001,43.018063],"type":"Point"}
}