{
  "type": "Feature",
  "properties": {
    "addr:full":"740 Saint Nicholas Avenue New York NY 10031",
    "addr:housenumber":"740",
    "addr:postcode":"10031",
    "addr:street":"Saint Nicholas Avenue",
    "iso:country":"US",
    "sg:address":"740 Saint Nicholas Avenue",
    "sg:city":"New York",
    "sg:classifiers":[
        {
            "category":"Professional",
            "subcategory":"Lawyer & Legal Services",
            "type":"Services"
        }
    ],
    "sg:phone":"+1 212 926 7200",
    "sg:postcode":"10031",
    "sg:province":"NY",
    "wof:name":"Seraile Janette Lwyr",
    "wof:placetype":"venue"
},
  "geometry": {"coordinates":[-73.943741,40.825179],"type":"Point"}
}