{
  "type": "Feature",
  "properties": {
    "iso:country":"US",
    "sg:address":"2433 86th Street",
    "sg:city":"Brooklyn",
    "sg:classifiers":[
        {
            "category":"Health Services",
            "subcategory":"Doctor",
            "type":"Services"
        }
    ],
    "sg:phone":"+1 718 265 2424",
    "sg:postcode":"11214",
    "sg:province":"NY",
    "wof:name":"Health & Beauty Medical Ofc",
    "wof:placetype":"venue"
},
  "geometry": {"coordinates":[-73.988122,40.598618],"type":"Point"}
}