{
  "type": "Feature",
  "properties": {
    "addr:full":"152 Ludlow St New York NY 10002",
    "addr:housenumber":"152",
    "addr:postcode":"10002",
    "addr:street":"Ludlow St",
    "iso:country":"US",
    "sg:address":"152 Ludlow St",
    "sg:city":"New York",
    "sg:classifiers":[
        {
            "category":"Manufacturing",
            "subcategory":"Apparel",
            "type":"Manufacturing & Wholesale Goods"
        }
    ],
    "sg:phone":"+1   ",
    "sg:postcode":"10002",
    "sg:province":"NY",
    "sg:tags":[
        "mfg"
    ],
    "wof:name":"Donkey LLC",
    "wof:placetype":"venue"
},
  "geometry": {"coordinates":[-73.98804,40.720317],"type":"Point"}
}