{
  "type": "Feature",
  "properties": {
    "addr:full":"10876 Anstee Rd Clyde NY 14433",
    "addr:housenumber":"10876",
    "addr:postcode":"14433",
    "addr:street":"Anstee Rd",
    "iso:country":"US",
    "sg:address":"10876 Anstee Rd",
    "sg:city":"Clyde",
    "sg:classifiers":[
        {
            "category":"Building & Trades",
            "subcategory":"Construction",
            "type":"Services"
        }
    ],
    "sg:phone":"+1 315 923 4351",
    "sg:postcode":"14433",
    "sg:province":"NY",
    "sg:tags":[
        "house",
        "business",
        "mfg"
    ],
    "wof:name":"Signs & Designs",
    "wof:placetype":"venue"
},
  "geometry": {"coordinates":[-76.88154900000001,43.043773],"type":"Point"}
}