{
  "type": "Feature",
  "properties": {
    "addr:full":"12802 7th Ave College Point NY 11356",
    "addr:housenumber":"12802",
    "addr:postcode":"11356",
    "addr:street":"7Th Ave",
    "iso:country":"US",
    "sg:address":"12802 7th Ave",
    "sg:city":"College Point",
    "sg:classifiers":[
        {
            "category":"Education",
            "subcategory":"School",
            "type":"Public Place"
        }
    ],
    "sg:phone":"+1 718 353 3150",
    "sg:postcode":"11356",
    "sg:province":"NY",
    "sg:tags":[
        "high",
        "middle",
        "elementary"
    ],
    "wof:name":"N Y City of",
    "wof:placetype":"venue"
},
  "geometry": {"coordinates":[-73.8396,40.790501],"type":"Point"}
}