{
  "type": "Feature",
  "properties": {
    "addr:full":"857 Little Britain Rd New Windsor NY 12553",
    "addr:housenumber":"857",
    "addr:postcode":"12553",
    "addr:street":"Little Britain Rd",
    "iso:country":"US",
    "sg:address":"857 Little Britain Rd",
    "sg:city":"New Windsor",
    "sg:classifiers":[
        {
            "category":"Building & Trades",
            "subcategory":"Construction",
            "type":"Services"
        }
    ],
    "sg:phone":"+1 845 565 0528",
    "sg:postcode":"12553",
    "sg:province":"NY",
    "sg:tags":[
        "contractor"
    ],
    "wof:name":"Victor Perez Drywall",
    "wof:placetype":"venue"
},
  "geometry": {"coordinates":[-74.07828499999999,41.485697],"type":"Point"}
}