{
  "type": "Feature",
  "properties": {
    "iso:country":"US",
    "sg:address":"12 Saratoga Ave",
    "sg:city":"Brooklyn",
    "sg:classifiers":[
        {
            "category":"Professional",
            "type":"Services"
        }
    ],
    "sg:phone":"+1 718 574 7900",
    "sg:postcode":"11233",
    "sg:province":"NY",
    "sg:tags":[
        "establishment"
    ],
    "wof:name":"Fremia Castillo",
    "wof:placetype":"venue"
},
  "geometry": {"coordinates":[-73.918032,40.686868],"type":"Point"}
}