{
  "type": "Feature",
  "properties": {
    "addr:full":"421 73rd St Brooklyn NY 11209",
    "addr:housenumber":"421",
    "addr:postcode":"11209",
    "addr:street":"73Rd St",
    "iso:country":"US",
    "sg:address":"421 73rd St",
    "sg:city":"Brooklyn",
    "sg:classifiers":[
        {
            "category":"Health Services",
            "subcategory":"Health Practitioner",
            "type":"Services"
        }
    ],
    "sg:phone":"+1 718 748 0202",
    "sg:postcode":"11209",
    "sg:province":"NY",
    "sg:tags":[
        "therapy",
        "physical"
    ],
    "wof:name":"Bay Ridge Sports Medicine & Physical Therapy",
    "wof:placetype":"venue"
},
  "geometry": {"coordinates":[-74.02374500000001,40.632053],"type":"Point"}
}