{
  "type": "Feature",
  "properties": {
    "addr:full":"220 Main St Saugerties NY 12477",
    "addr:housenumber":"220",
    "addr:postcode":"12477",
    "addr:street":"Main St",
    "iso:country":"US",
    "sg:address":"220 Main St",
    "sg:city":"Saugerties",
    "sg:classifiers":[
        {
            "category":"Shopping",
            "subcategory":"Used Merchandise",
            "type":"Retail Goods"
        }
    ],
    "sg:phone":"+1   ",
    "sg:postcode":"12477",
    "sg:province":"NY",
    "wof:name":"Saugertis Antique Center",
    "wof:placetype":"venue"
},
  "geometry": {"coordinates":[-73.952738,42.077591],"type":"Point"}
}