{
  "type": "Feature",
  "properties": {
    "iso:country":"US",
    "sg:address":"1346 Saltvale Rd",
    "sg:city":"Wyoming",
    "sg:classifiers":[
        {
            "category":"Mining & Drilling",
            "type":"Manufacturing & Wholesale Goods"
        }
    ],
    "sg:phone":"+1 585 495 6228",
    "sg:postcode":"14591",
    "sg:province":"NY",
    "sg:tags":[
        "company"
    ],
    "wof:name":"Texas Brine Corp",
    "wof:placetype":"venue"
},
  "geometry": {"coordinates":[-78.078506,42.816642],"type":"Point"}
}