{
  "type": "Feature",
  "properties": {
    "iso:country":"US",
    "sg:address":"2906 E Main St",
    "sg:city":"Endicott",
    "sg:classifiers":[
        {
            "category":"Bars & Pubs",
            "type":"Food & Drink"
        }
    ],
    "sg:phone":"+1   ",
    "sg:postcode":"13760",
    "sg:province":"NY",
    "sg:tags":[
        "tavern"
    ],
    "wof:name":"OS Take Out",
    "wof:placetype":"venue"
},
  "geometry": {"coordinates":[-76.028025,42.106126],"type":"Point"}
}