{
  "type": "Feature",
  "properties": {
    "addr:full":"1250 Union Rd Buffalo NY 14224",
    "addr:housenumber":"1250",
    "addr:postcode":"14224",
    "addr:street":"Union Rd",
    "iso:country":"US",
    "sg:address":"1250 Union Rd",
    "sg:city":"Buffalo",
    "sg:classifiers":[
        {
            "category":"Government",
            "subcategory":"Police Station",
            "type":"Public Place"
        }
    ],
    "sg:phone":"+1 716 674 3154",
    "sg:postcode":"14224",
    "sg:province":"NY",
    "sg:tags":[
        "protection"
    ],
    "wof:name":"Detectives Bureau",
    "wof:placetype":"venue"
},
  "geometry": {"coordinates":[-78.753916,42.834988],"type":"Point"}
}