{
  "type": "Feature",
  "properties": {
    "iso:country":"US",
    "sg:address":"15 Scotty Ln",
    "sg:city":"Bethpage",
    "sg:classifiers":[
        {
            "category":"Real Estate",
            "subcategory":"Real Estate Agent",
            "type":"Services"
        }
    ],
    "sg:phone":"+1 516 629 9338",
    "sg:postcode":"11720",
    "sg:province":"NY",
    "sg:tags":[
        "consultant"
    ],
    "wof:name":"Brengelman Realty Advisors LLC",
    "wof:placetype":"venue"
},
  "geometry": {"coordinates":[-73.07121100000001,40.872724],"type":"Point"}
}