{
  "type": "Feature",
  "properties": {
    "addr:full":"2012 Merrick Rd Merrick NY 11566",
    "addr:housenumber":"2012",
    "addr:postcode":"11566",
    "addr:street":"Merrick Rd",
    "iso:country":"US",
    "sg:address":"2012 Merrick Rd",
    "sg:city":"Merrick",
    "sg:classifiers":[
        {
            "category":"Wholesale",
            "subcategory":"Groceries",
            "type":"Manufacturing & Wholesale Goods"
        }
    ],
    "sg:phone":"+1 516 546 1220",
    "sg:postcode":"11566",
    "sg:province":"NY",
    "sg:tags":[
        "general"
    ],
    "wof:name":"Plaza Market Place",
    "wof:placetype":"venue"
},
  "geometry": {"coordinates":[-73.549645,40.656036],"type":"Point"}
}