{
  "type": "Feature",
  "properties": {
    "iso:country":"US",
    "sg:address":"2604 Coney Island Ave",
    "sg:city":"Brooklyn",
    "sg:classifiers":[
        {
            "category":"Wholesale",
            "subcategory":"Construction Materials",
            "type":"Manufacturing & Wholesale Goods"
        }
    ],
    "sg:phone":"+1 718 646 4600",
    "sg:postcode":"11223",
    "sg:province":"NY",
    "sg:tags":[
        "lumber"
    ],
    "wof:name":"Flotteron",
    "wof:placetype":"venue"
},
  "geometry": {"coordinates":[-73.96089000000001,40.593478],"type":"Point"}
}