{
  "type": "Feature",
  "properties": {
    "addr:full":"766 Macon Pl Uniondale NY 11553",
    "addr:housenumber":"766",
    "addr:postcode":"11553",
    "addr:street":"Macon Pl",
    "iso:country":"US",
    "sg:address":"766 Macon Pl",
    "sg:city":"Uniondale",
    "sg:classifiers":[
        {
            "category":"Manufacturing",
            "subcategory":"Printing",
            "type":"Manufacturing & Wholesale Goods"
        }
    ],
    "sg:phone":"+1 516 481 7079",
    "sg:postcode":"11553",
    "sg:province":"NY",
    "sg:tags":[
        "printer"
    ],
    "wof:name":"Jam Enterprises",
    "wof:placetype":"venue"
},
  "geometry": {"coordinates":[-73.58940699999999,40.697341],"type":"Point"}
}