{
  "type": "Feature",
  "properties": {
    "iso:country":"US",
    "sg:address":"1296 Broadway",
    "sg:city":"Albany",
    "sg:classifiers":[
        {
            "category":"Personal",
            "subcategory":"Barber",
            "type":"Services"
        }
    ],
    "sg:phone":"+1 518 463 7765",
    "sg:postcode":"12204",
    "sg:province":"NY",
    "wof:name":"Gamello's Barber Shop",
    "wof:placetype":"venue"
},
  "geometry": {"coordinates":[-73.736164,42.675272],"type":"Point"}
}