{
  "type": "Feature",
  "properties": {
    "addr:full":"107 Java Street Brooklyn NY 11222",
    "addr:housenumber":"107",
    "addr:postcode":"11222",
    "addr:street":"Java Street",
    "iso:country":"US",
    "sg:address":"107 Java Street",
    "sg:city":"Brooklyn",
    "sg:classifiers":[
        {
            "category":"Health Services",
            "subcategory":"Health Practitioner",
            "type":"Services"
        }
    ],
    "sg:phone":"+1 718 383 3209",
    "sg:postcode":"11222",
    "sg:province":"NY",
    "sg:tags":[
        "therapy",
        "physical"
    ],
    "wof:name":"Domkowski Donald E Physthrpst",
    "wof:placetype":"venue"
},
  "geometry": {"coordinates":[-73.956655,40.731434],"type":"Point"}
}