{
  "type": "Feature",
  "properties": {
    "addr:full":"101 N Clinton St Syracuse NY 13202",
    "addr:housenumber":"101",
    "addr:postcode":"13202",
    "addr:street":"N Clinton St",
    "iso:country":"US",
    "sg:address":"101 N Clinton St",
    "sg:city":"Syracuse",
    "sg:classifiers":[
        {
            "category":"Real Estate",
            "subcategory":"Real Estate Operator",
            "type":"Services"
        }
    ],
    "sg:phone":"+1 315 422 8780",
    "sg:postcode":"13202",
    "sg:province":"NY",
    "sg:tags":[
        "apartment"
    ],
    "wof:name":"Pine Tree Apartments",
    "wof:placetype":"venue"
},
  "geometry": {"coordinates":[-76.15352,43.051296],"type":"Point"}
}