{
  "type": "Feature",
  "properties": {
    "iso:country":"US",
    "sg:address":"850 Hudson Ave",
    "sg:city":"Rochester",
    "sg:classifiers":[
        {
            "category":"Manufacturing",
            "subcategory":"Tools & Machinery",
            "type":"Manufacturing & Wholesale Goods"
        }
    ],
    "sg:phone":"+1   ",
    "sg:postcode":"14621",
    "sg:province":"NY",
    "sg:tags":[
        "photo",
        "optical",
        "mfg"
    ],
    "sg:website":"www.agslides.com",
    "wof:name":"Optical Gaging Products Inc",
    "wof:placetype":"venue"
},
  "geometry": {"coordinates":[-77.59905000000001,43.179841],"type":"Point"}
}