{
  "type": "Feature",
  "properties": {
    "iso:country":"US",
    "sg:address":"208 E Main St",
    "sg:city":"Patchogue",
    "sg:classifiers":[
        {
            "category":"Personal",
            "subcategory":"Beauty Salon",
            "type":"Services"
        }
    ],
    "sg:phone":"+1 631 730 7670",
    "sg:postcode":"11772",
    "sg:province":"NY",
    "wof:name":"Spa Balance",
    "wof:placetype":"venue"
},
  "geometry": {"coordinates":[-73.00908699999999,40.765875],"type":"Point"}
}