{
  "type": "Feature",
  "properties": {
    "addr:full":"635 Elk St Buffalo NY 14210",
    "addr:housenumber":"635",
    "addr:postcode":"14210",
    "addr:street":"Elk St",
    "iso:country":"US",
    "sg:address":"635 Elk St",
    "sg:city":"Buffalo",
    "sg:classifiers":[
        {
            "category":"Government",
            "subcategory":"Police Station",
            "type":"Public Place"
        }
    ],
    "sg:phone":"+1 716 851 4585",
    "sg:postcode":"14210",
    "sg:province":"NY",
    "sg:tags":[
        "protection"
    ],
    "wof:name":"Buffalo Police Dept",
    "wof:placetype":"venue"
},
  "geometry": {"coordinates":[-78.829748,42.865468],"type":"Point"}
}