{
  "type": "Feature",
  "properties": {
    "iso:country":"US",
    "sg:address":"136-23 Latimer Pl",
    "sg:city":"Flushing",
    "sg:classifiers":[
        {
            "category":"Home & Garden",
            "subcategory":"Building Materials",
            "type":"Retail Goods"
        },
        {
            "category":"Building & Trades",
            "subcategory":"Construction",
            "type":"Services"
        },
        {
            "category":"Home & Garden",
            "subcategory":"Kitchen Supply",
            "type":"Retail Goods"
        }
    ],
    "sg:phone":"+1 718 353 0706",
    "sg:postcode":"11354",
    "sg:province":"NY",
    "sg:tags":[
        "bathroom",
        "marble-natural",
        "accessory",
        "planning",
        "granite",
        "fixtures",
        "cabinet",
        "remodeling"
    ],
    "sg:website":"http://dreamviewmarble.com",
    "wof:name":"Dream View Marble and Granite",
    "wof:placetype":"venue"
},
  "geometry": {"coordinates":[-73.830733,40.766739],"type":"Point"}
}