{
  "type": "Feature",
  "properties": {
    "addr:full":"31 Plainfield Ave Bedford Hills NY 10507",
    "addr:housenumber":"31",
    "addr:postcode":"10507",
    "addr:street":"Plainfield Ave",
    "iso:country":"US",
    "sg:address":"31 Plainfield Ave",
    "sg:city":"Bedford Hills",
    "sg:classifiers":[
        {
            "category":"Utilities",
            "subcategory":"Mobile Phone",
            "type":"Services"
        }
    ],
    "sg:phone":"+1   ",
    "sg:postcode":"10507",
    "sg:province":"NY",
    "sg:tags":[
        "communications"
    ],
    "wof:name":"Kenwood Land Mobile Radio",
    "wof:placetype":"venue"
},
  "geometry": {"coordinates":[-73.71359200000001,41.228205],"type":"Point"}
}