{
  "type": "Feature",
  "properties": {
    "iso:country":"US",
    "sg:address":"105 Kingston Avenue",
    "sg:city":"Brooklyn",
    "sg:classifiers":[
        {
            "category":"Retail",
            "subcategory":"Laundry & Dry Cleaning",
            "type":"Services"
        }
    ],
    "sg:phone":"+1 718 771 7600",
    "sg:postcode":"11213",
    "sg:province":"NY",
    "wof:name":"Universal Dry Cleaners & Business",
    "wof:placetype":"venue"
},
  "geometry": {"coordinates":[-73.94140400000001,40.676256],"type":"Point"}
}