{
  "type": "Feature",
  "properties": {
    "addr:full":"500 Grand St Brooklyn NY 11211",
    "addr:housenumber":"500",
    "addr:postcode":"11211",
    "addr:street":"Grand St",
    "iso:country":"US",
    "sg:address":"500 Grand St",
    "sg:city":"Brooklyn",
    "sg:classifiers":[
        {
            "category":"Food & Beverages",
            "subcategory":"Groceries & Convenience Stores",
            "type":"Retail Goods"
        }
    ],
    "sg:phone":"+1 718 963 0438",
    "sg:postcode":"11211",
    "sg:province":"NY",
    "wof:name":"Mojali Deli Grocery",
    "wof:placetype":"venue"
},
  "geometry": {"coordinates":[-73.95210299999999,40.711102],"type":"Point"}
}