{
  "type": "Feature",
  "properties": {
    "addr:full":"715 Broadway New York NY 10003",
    "addr:housenumber":"715",
    "addr:postcode":"10003",
    "addr:street":"Broadway",
    "iso:country":"US",
    "sg:address":"715 Broadway",
    "sg:city":"New York",
    "sg:classifiers":[
        {
            "category":"Education",
            "subcategory":"College",
            "type":"Public Place"
        }
    ],
    "sg:phone":"+1 212 998 3390",
    "sg:postcode":"10003",
    "sg:province":"NY",
    "sg:tags":[
        "university"
    ],
    "wof:name":"Center For Advanced Technology",
    "wof:placetype":"venue"
},
  "geometry": {"coordinates":[-73.993262,40.72958],"type":"Point"}
}