{
  "type": "Feature",
  "properties": {
    "addr:full":"250 N Henry St Brooklyn NY 11222",
    "addr:housenumber":"250",
    "addr:postcode":"11222",
    "addr:street":"N Henry St",
    "iso:country":"US",
    "sg:address":"250 N Henry St",
    "sg:city":"Brooklyn",
    "sg:classifiers":[
        {
            "category":"Building & Trades",
            "subcategory":"Construction",
            "type":"Services"
        }
    ],
    "sg:phone":"+1 718 383 9995",
    "sg:postcode":"11222",
    "sg:province":"NY",
    "sg:tags":[
        "contractor"
    ],
    "wof:name":"Marble Lite",
    "wof:placetype":"venue"
},
  "geometry": {"coordinates":[-73.94409,40.729281],"type":"Point"}
}