{
  "type": "Feature",
  "properties": {
    "addr:full":"20 Skyline Dr Huntington NY 11743",
    "addr:housenumber":"20",
    "addr:postcode":"11743",
    "addr:street":"Skyline Dr",
    "iso:country":"US",
    "sg:address":"20 Skyline Dr",
    "sg:city":"Huntington",
    "sg:classifiers":[
        {
            "category":"Building & Trades",
            "subcategory":"Construction",
            "type":"Services"
        }
    ],
    "sg:phone":"+1 631 424 7272",
    "sg:postcode":"11743",
    "sg:province":"NY",
    "sg:tags":[
        "contractor"
    ],
    "sg:website":"www.andersoncontractingco.com",
    "wof:name":"Anderson Contracting Company of Long Island",
    "wof:placetype":"venue"
},
  "geometry": {"coordinates":[-73.431297,40.856499],"type":"Point"}
}