{
  "type": "Feature",
  "properties": {
    "addr:full":"4014 Greenpoint Avenue Sunnyside NY 11104",
    "addr:housenumber":"4014",
    "addr:postcode":"11104",
    "addr:street":"Greenpoint Avenue",
    "iso:country":"US",
    "sg:address":"4014 Greenpoint Avenue",
    "sg:city":"Sunnyside",
    "sg:classifiers":[
        {
            "category":"Health Services",
            "subcategory":"Dentist",
            "type":"Services"
        }
    ],
    "sg:phone":"+1 718 392 2858",
    "sg:postcode":"11104",
    "sg:province":"NY",
    "wof:name":"Greenpoint Dental",
    "wof:placetype":"venue"
},
  "geometry": {"coordinates":[-73.924699,40.739578],"type":"Point"}
}