{
  "type": "Feature",
  "properties": {
    "iso:country":"US",
    "sg:address":"257 E Main St",
    "sg:city":"Middletown",
    "sg:classifiers":[
        {
            "category":"Restaurant",
            "type":"Food & Drink"
        }
    ],
    "sg:phone":"+1 845 343 7499",
    "sg:postcode":"10940",
    "sg:province":"NY",
    "wof:name":"Nonna Lucia's Ristorante",
    "wof:placetype":"venue"
},
  "geometry": {"coordinates":[-74.408142,41.44577],"type":"Point"}
}