{
  "type": "Feature",
  "properties": {
    "addr:full":"241 Carleton Dr E Yaphank NY 11967",
    "addr:housenumber":"241",
    "addr:postcode":"11967",
    "addr:street":"Carleton Dr E Yaphank",
    "iso:country":"US",
    "sg:address":"241 Carleton Dr E",
    "sg:city":"Yaphank",
    "sg:classifiers":[
        {
            "category":"Marine",
            "type":"Transportation"
        }
    ],
    "sg:phone":"+1 631 924 4362",
    "sg:postcode":"11967",
    "sg:province":"NY",
    "sg:tags":[
        "surveyor"
    ],
    "wof:name":"Ocean Bay Marine Svc Inc",
    "wof:placetype":"venue"
},
  "geometry": {"coordinates":[-72.87212100000001,40.844767],"type":"Point"}
}