{
  "type": "Feature",
  "properties": {
    "iso:country":"US",
    "sg:address":"59 Western Ave",
    "sg:city":"Ravena",
    "sg:classifiers":[
        {
            "category":"Building & Trades",
            "subcategory":"Landscaping Services",
            "type":"Services"
        }
    ],
    "sg:phone":"+1 518 756 2296",
    "sg:postcode":"12143",
    "sg:province":"NY",
    "wof:name":"Perfection Ldscpg & Lawn Care",
    "wof:placetype":"venue"
},
  "geometry": {"coordinates":[-73.81631299999999,42.475392],"type":"Point"}
}