{
  "type": "Feature",
  "properties": {
    "iso:country":"US",
    "sg:address":"230 W 17 St",
    "sg:city":"New York",
    "sg:classifiers":[
        {
            "category":"Building & Trades",
            "subcategory":"Plumbing",
            "type":"Services"
        }
    ],
    "sg:phone":"+1 212 924 1010",
    "sg:postcode":"10011",
    "sg:province":"NY",
    "sg:tags":[
        "duct",
        "work",
        "heating",
        "air",
        "ventilation",
        "conditioning",
        "contractor"
    ],
    "wof:name":"Harbour Mechanical Corporation",
    "wof:placetype":"venue"
},
  "geometry": {"coordinates":[-74.000505,40.741235],"type":"Point"}
}