{
  "type": "Feature",
  "properties": {
    "addr:full":"301 Reeves Ave Riverhead NY 11901",
    "addr:housenumber":"301",
    "addr:postcode":"11901",
    "addr:street":"Reeves Ave",
    "iso:country":"US",
    "sg:address":"301 Reeves Ave",
    "sg:city":"Riverhead",
    "sg:classifiers":[
        {
            "category":"Farming",
            "subcategory":"Nursery",
            "type":"Manufacturing & Wholesale Goods"
        },
        {
            "category":"Shopping",
            "subcategory":"Crafts & Fabrics",
            "type":"Retail Goods"
        },
        {
            "category":"Manufacturing",
            "subcategory":"Paper Products",
            "type":"Manufacturing & Wholesale Goods"
        }
    ],
    "sg:phone":"+1 631 727 8887",
    "sg:postcode":"11901",
    "sg:province":"NY",
    "sg:tags":[
        "florists'",
        "supply",
        "nursery-wholesale",
        "florist",
        "bamboo",
        "supplies-wholesale",
        "grower",
        "manufacturer"
    ],
    "sg:website":"http://www.eastcoastnurseries.com",
    "wof:name":"East Coast Nurseries, Inc.",
    "wof:placetype":"venue"
},
  "geometry": {"coordinates":[-72.704328,40.949413],"type":"Point"}
}