{
  "type": "Feature",
  "properties": {
    "addr:full":"820 Canandaigua Rd Geneva NY 14456",
    "addr:housenumber":"820",
    "addr:postcode":"14456",
    "addr:street":"Canandaigua Rd",
    "iso:country":"US",
    "sg:address":"820 Canandaigua Rd",
    "sg:city":"Geneva",
    "sg:classifiers":[
        {
            "category":"Food & Beverages",
            "subcategory":"Liquor & Beverages",
            "type":"Retail Goods"
        }
    ],
    "sg:phone":"+1 315 789 1858",
    "sg:postcode":"14456",
    "sg:province":"NY",
    "sg:tags":[
        "alcoholic"
    ],
    "wof:name":"Headley's Discount Liquor Barn",
    "wof:placetype":"venue"
},
  "geometry": {"coordinates":[-77.01599899999999,42.857103],"type":"Point"}
}