{
  "type": "Feature",
  "properties": {
    "addr:full":"90 Earhart Dr Buffalo NY 14221",
    "addr:housenumber":"90",
    "addr:postcode":"14221",
    "addr:street":"Earhart Dr",
    "iso:country":"US",
    "sg:address":"90 Earhart Dr",
    "sg:city":"Buffalo",
    "sg:classifiers":[
        {
            "category":"Wholesale",
            "subcategory":"Machinery & Supplies",
            "type":"Manufacturing & Wholesale Goods"
        }
    ],
    "sg:phone":"+1 716 634 0234",
    "sg:postcode":"14221",
    "sg:province":"NY",
    "sg:tags":[
        "machine",
        "floor"
    ],
    "wof:name":"American Custodial",
    "wof:placetype":"venue"
},
  "geometry": {"coordinates":[-78.71462099999999,42.954724],"type":"Point"}
}