{
  "type": "Feature",
  "properties": {
    "iso:country":"US",
    "sg:address":"6017 Tarbell Rd",
    "sg:city":"Syracuse",
    "sg:classifiers":[
        {
            "category":"Wholesale",
            "subcategory":"Furniture",
            "type":"Manufacturing & Wholesale Goods"
        }
    ],
    "sg:phone":"+1 315 474 6801",
    "sg:postcode":"13206",
    "sg:province":"NY",
    "sg:website":"www.hurbson.com",
    "wof:name":"Hurbson Office Furnishings",
    "wof:placetype":"venue"
},
  "geometry": {"coordinates":[-76.101805,43.090241],"type":"Point"}
}