{
  "type": "Feature",
  "properties": {
    "addr:full":"5033 Transit Rd Buffalo NY 14221",
    "addr:housenumber":"5033",
    "addr:postcode":"14221",
    "addr:street":"Transit Rd",
    "iso:country":"US",
    "sg:address":"5033 Transit Rd",
    "sg:city":"Buffalo",
    "sg:classifiers":[
        {
            "category":"Shopping",
            "type":"Retail Goods"
        }
    ],
    "sg:phone":"+1 716 626 3323",
    "sg:postcode":"14221",
    "sg:province":"NY",
    "sg:tags":[
        "hearing",
        "equipment",
        "supply",
        "impaired"
    ],
    "wof:name":"National Hearing Ctr",
    "wof:placetype":"venue"
},
  "geometry": {"coordinates":[-78.696878,42.986322],"type":"Point"}
}