{
  "type": "Feature",
  "properties": {
    "addr:full":"8 Parkway Dr Carle Place NY 11514",
    "addr:housenumber":"8",
    "addr:postcode":"11514",
    "addr:street":"Parkway Dr Carle Place",
    "iso:country":"US",
    "sg:address":"8 Parkway Dr",
    "sg:city":"Carle Place",
    "sg:classifiers":[
        {
            "category":"Building & Trades",
            "subcategory":"Landscaping Services",
            "type":"Services"
        }
    ],
    "sg:phone":"+1 516 294 9346",
    "sg:postcode":"11514",
    "sg:province":"NY",
    "sg:tags":[
        "landscape"
    ],
    "wof:name":"Almeida Landscaping & Cemetery",
    "wof:placetype":"venue"
},
  "geometry": {"coordinates":[-73.620154,40.754839],"type":"Point"}
}