{
  "type": "Feature",
  "properties": {
    "iso:country":"US",
    "sg:address":"999 Co Rd 107",
    "sg:city":"Fort Johnson",
    "sg:classifiers":[
        {
            "category":"Building & Trades",
            "subcategory":"Construction",
            "type":"Services"
        }
    ],
    "sg:phone":"+1 518 762 1380",
    "sg:postcode":"12070",
    "sg:province":"NY",
    "sg:tags":[
        "drywall",
        "contractor"
    ],
    "wof:name":"Brown Chester Drywall LLC",
    "wof:placetype":"venue"
},
  "geometry": {"coordinates":[-74.269672,43.012657],"type":"Point"}
}