{
  "type": "Feature",
  "properties": {
    "iso:country":"US",
    "sg:address":"100 Oliver St",
    "sg:city":"North Tonawanda",
    "sg:classifiers":[
        {
            "category":"Real Estate",
            "subcategory":"Real Estate Operator",
            "type":"Services"
        }
    ],
    "sg:phone":"+1 716 693 5536",
    "sg:postcode":"14120",
    "sg:province":"NY",
    "sg:tags":[
        "apartment",
        "management",
        "rental"
    ],
    "wof:name":"Carousel Park Assoc",
    "wof:placetype":"venue"
},
  "geometry": {"coordinates":[-78.874045,43.026166],"type":"Point"}
}