{
  "type": "Feature",
  "properties": {
    "addr:full":"99 3rd Ave New York NY 11222",
    "addr:housenumber":"99",
    "addr:postcode":"11222",
    "addr:street":"3Rd Ave",
    "iso:country":"US",
    "sg:address":"99 3rd Ave",
    "sg:city":"New York",
    "sg:classifiers":[
        {
            "category":"Building & Trades",
            "subcategory":"Cleaning & Sanitation",
            "type":"Services"
        }
    ],
    "sg:phone":"+1 646 224 5972",
    "sg:postcode":"11222",
    "sg:province":"NY",
    "sg:tags":[
        "carpet"
    ],
    "sg:website":"www.nycorientalrugcleaning.com",
    "wof:name":"Oriental Rug Cleaning NYC",
    "wof:placetype":"venue"
},
  "geometry": {"coordinates":[-73.982135,40.683169],"type":"Point"}
}