{
  "type": "Feature",
  "properties": {
    "addr:full":"44 Charlton St New York NY 10014",
    "addr:housenumber":"44",
    "addr:postcode":"10014",
    "addr:street":"Charlton St",
    "iso:country":"US",
    "sg:address":"44 Charlton St",
    "sg:city":"New York",
    "sg:classifiers":[
        {
            "category":"Arts & Performance",
            "subcategory":"Arts Center",
            "type":"Entertainment"
        }
    ],
    "sg:postcode":"10014",
    "sg:province":"NY",
    "sg:website":"www.thegreenespace.org",
    "wof:name":"The Greene Space at WNYC",
    "wof:placetype":"venue"
},
  "geometry": {"coordinates":[-74.005584,40.727151],"type":"Point"}
}