{
  "type": "Feature",
  "properties": {
    "addr:full":"29 Phyllis Ter Monsey NY 10952",
    "addr:housenumber":"29",
    "addr:postcode":"10952",
    "addr:street":"Phyllis Ter Monsey",
    "iso:country":"US",
    "sg:address":"29 Phyllis Ter",
    "sg:city":"Monsey",
    "sg:classifiers":[
        {
            "category":"Organizations",
            "subcategory":"Religious Organization",
            "type":"Services"
        }
    ],
    "sg:phone":"+1 845 425 3866",
    "sg:postcode":"10952",
    "sg:province":"NY",
    "sg:tags":[
        "clergy"
    ],
    "wof:name":"David Rubinstein",
    "wof:placetype":"venue"
},
  "geometry": {"coordinates":[-74.06622400000001,41.118699],"type":"Point"}
}