{
  "type": "Feature",
  "properties": {
    "iso:country":"US",
    "sg:address":"1334 Central Ave",
    "sg:city":"Albany",
    "sg:classifiers":[
        {
            "category":"Retail",
            "subcategory":"Auto Repair",
            "type":"Services"
        }
    ],
    "sg:phone":"+1 518 459 2555",
    "sg:postcode":"12205",
    "sg:province":"NY",
    "sg:tags":[
        "body",
        "shop",
        "automobile",
        "dealers-used",
        "automotive",
        "cars-wholesale"
    ],
    "wof:name":"Colonie Garage Inc",
    "wof:placetype":"venue"
},
  "geometry": {"coordinates":[-73.815483,42.70237],"type":"Point"}
}