{
  "type": "Feature",
  "properties": {
    "addr:full":"3527 Harlem Rd Buffalo NY 14225",
    "addr:housenumber":"3527",
    "addr:postcode":"14225",
    "addr:street":"Harlem Rd",
    "iso:country":"US",
    "sg:address":"3527 Harlem Rd",
    "sg:city":"Buffalo",
    "sg:classifiers":[
        {
            "category":"Organizations",
            "subcategory":"Labor Organization",
            "type":"Services"
        }
    ],
    "sg:phone":"+1 716 874 4494",
    "sg:postcode":"14225",
    "sg:province":"NY",
    "sg:tags":[
        "union"
    ],
    "wof:name":"Local Union 14",
    "wof:placetype":"venue"
},
  "geometry": {"coordinates":[-78.784015,42.940473],"type":"Point"}
}