{
  "type": "Feature",
  "properties": {
    "addr:full":"189 N Main St Liberty NY 12754",
    "addr:housenumber":"189",
    "addr:postcode":"12754",
    "addr:street":"N Main St",
    "iso:country":"US",
    "sg:address":"189 N Main St",
    "sg:city":"Liberty",
    "sg:classifiers":[
        {
            "category":"Education",
            "subcategory":"Library",
            "type":"Public Place"
        }
    ],
    "sg:phone":"+1 845 292 6070",
    "sg:postcode":"12754",
    "sg:province":"NY",
    "wof:name":"Liberty Public Library",
    "wof:placetype":"venue"
},
  "geometry": {"coordinates":[-74.747372,41.804729],"type":"Point"}
}