{
  "type": "Feature",
  "properties": {
    "iso:country":"US",
    "sg:address":"877 Seneca St",
    "sg:city":"Buffalo",
    "sg:classifiers":[
        {
            "category":"Retail",
            "subcategory":"Auto Rental",
            "type":"Services"
        }
    ],
    "sg:phone":"+1 716 854 4919",
    "sg:postcode":"14210",
    "sg:province":"NY",
    "sg:tags":[
        "renting",
        "truck",
        "leasing"
    ],
    "wof:name":"Budget Truck Rental",
    "wof:placetype":"venue"
},
  "geometry": {"coordinates":[-78.845564,42.87489],"type":"Point"}
}