{
  "type": "Feature",
  "properties": {
    "addr:full":"365 Co Rd 39A Southampton NY 11968",
    "addr:housenumber":"365;39a",
    "addr:postcode":"11968",
    "addr:street":"Co Rd",
    "iso:country":"US",
    "sg:address":"365 Co Rd 39A",
    "sg:city":"Southampton",
    "sg:classifiers":[
        {
            "category":"Shopping",
            "subcategory":"Department Store",
            "type":"Retail Goods"
        }
    ],
    "sg:phone":"+1 631 287 9300",
    "sg:postcode":"11968",
    "sg:province":"NY",
    "sg:tags":[
        "shop"
    ],
    "wof:name":"National Discount Health Plan",
    "wof:placetype":"venue"
},
  "geometry": {"coordinates":[-72.377872,40.900195],"type":"Point"}
}