{
  "type": "Feature",
  "properties": {
    "addr:full":"499 Park Ave New York NY 10022",
    "addr:housenumber":"499",
    "addr:postcode":"10022",
    "addr:street":"Park Ave",
    "iso:country":"US",
    "sg:address":"499 Park Ave",
    "sg:city":"New York",
    "sg:classifiers":[
        {
            "category":"Communications",
            "subcategory":"News Services",
            "type":"Services"
        }
    ],
    "sg:phone":"+1   ",
    "sg:postcode":"10022",
    "sg:province":"NY",
    "sg:tags":[
        "reporting"
    ],
    "wof:name":"Bloomberg Inc",
    "wof:placetype":"venue"
},
  "geometry": {"coordinates":[-73.969337,40.763546],"type":"Point"}
}