{
  "type": "Feature",
  "properties": {
    "addr:full":"242 Meacham Ave Elmont NY 11003",
    "addr:housenumber":"242",
    "addr:postcode":"11003",
    "addr:street":"Meacham Ave",
    "iso:country":"US",
    "sg:address":"242 Meacham Ave",
    "sg:city":"Elmont",
    "sg:classifiers":[
        {
            "category":"Shopping",
            "subcategory":"Clothing, Apparel, & Fashions",
            "type":"Retail Goods"
        }
    ],
    "sg:phone":"+1 516 437 7040",
    "sg:postcode":"11003",
    "sg:province":"NY",
    "sg:tags":[
        "wig",
        "toupee",
        "hairpiece"
    ],
    "wof:name":"New Pro Group Corp",
    "wof:placetype":"venue"
},
  "geometry": {"coordinates":[-73.69062700000001,40.701842],"type":"Point"}
}