{
  "type": "Feature",
  "properties": {
    "addr:full":"2359 Flatbush Ave Brooklyn NY 11234",
    "addr:housenumber":"2359",
    "addr:postcode":"11234",
    "addr:street":"Flatbush Ave",
    "iso:country":"US",
    "sg:address":"2359 Flatbush Ave",
    "sg:city":"Brooklyn",
    "sg:classifiers":[
        {
            "category":"Banks & Credit Unions",
            "subcategory":"Financial Services",
            "type":"Services"
        }
    ],
    "sg:phone":"+1 718 258 1333",
    "sg:postcode":"11234",
    "sg:province":"NY",
    "sg:tags":[
        "broker",
        "mortgage"
    ],
    "wof:name":"Melaleuca Marketing Executive",
    "wof:placetype":"venue"
},
  "geometry": {"coordinates":[-73.925499,40.612801],"type":"Point"}
}