{
  "type": "Feature",
  "properties": {
    "addr:full":"20 Center St Buffalo NY 14218",
    "addr:housenumber":"20",
    "addr:postcode":"14218",
    "addr:street":"Center St",
    "iso:country":"US",
    "sg:address":"20 Center St",
    "sg:city":"Buffalo",
    "sg:classifiers":[
        {
            "category":"Restaurant",
            "type":"Food & Drink"
        }
    ],
    "sg:menulink":"http://www.allmenus.com/ny/lackawanna/245711-center-street-smoke-house/menu/",
    "sg:phone":"+1 585 343 7470",
    "sg:postcode":"14218",
    "sg:province":"NY",
    "sg:tags":[
        "barbecue",
        "american"
    ],
    "wof:name":"Center Street Smoke House",
    "wof:placetype":"venue"
},
  "geometry": {"coordinates":[-78.832165,42.825149],"type":"Point"}
}