{
  "type": "Feature",
  "properties": {
    "iso:country":"US",
    "sg:address":"529 Highland Ave",
    "sg:city":"Peekskill",
    "sg:classifiers":[
        {
            "category":"Autos & Motor Vehicles",
            "subcategory":"Fuel & Gas Station",
            "type":"Retail Goods"
        }
    ],
    "sg:phone":"+1 914 788 1095",
    "sg:postcode":"10566",
    "sg:province":"NY",
    "sg:tags":[
        "oil"
    ],
    "wof:name":"Treasure Service Station",
    "wof:placetype":"venue"
},
  "geometry": {"coordinates":[-73.920215,41.296931],"type":"Point"}
}