{
  "type": "Feature",
  "properties": {
    "addr:full":"350 Broadway Canal Street NY 10013",
    "addr:housenumber":"350",
    "addr:postcode":"10013",
    "addr:street":"Broadway Canal Street",
    "iso:country":"US",
    "sg:address":"350 Broadway",
    "sg:city":"Canal Street",
    "sg:classifiers":[
        {
            "category":"Professional",
            "subcategory":"Lawyer & Legal Services",
            "type":"Services"
        }
    ],
    "sg:phone":"+1 212 226 8858",
    "sg:postcode":"10013",
    "sg:province":"NY",
    "wof:name":"Leifer Max & Assocs",
    "wof:placetype":"venue"
},
  "geometry": {"coordinates":[-74.003918,40.716916],"type":"Point"}
}