{
  "type": "Feature",
  "properties": {
    "iso:country":"US",
    "sg:address":"100 Old Maryvale Dr",
    "sg:city":"Buffalo",
    "sg:classifiers":[
        {
            "category":"Social Services",
            "subcategory":"Child Care",
            "type":"Services"
        }
    ],
    "sg:phone":"+1 716 831 0550",
    "sg:postcode":"14225",
    "sg:province":"NY",
    "sg:tags":[
        "day"
    ],
    "wof:name":"Kids Klub Pre Schl & Day Care",
    "wof:placetype":"venue"
},
  "geometry": {"coordinates":[-78.76941600000001,42.934695],"type":"Point"}
}