{
  "type": "Feature",
  "properties": {
    "iso:country":"US",
    "sg:address":"35 Clark Rd",
    "sg:city":"Port Jefferson Station",
    "sg:classifiers":[
        {
            "category":"Farming",
            "subcategory":"Livestock Farm",
            "type":"Manufacturing & Wholesale Goods"
        }
    ],
    "sg:phone":"+1 631 331 0892",
    "sg:postcode":"11776",
    "sg:province":"NY",
    "sg:tags":[
        "animal",
        "general"
    ],
    "wof:name":"Second Chance Ranch",
    "wof:placetype":"venue"
},
  "geometry": {"coordinates":[-73.012413,40.912472],"type":"Point"}
}