{
  "type": "Feature",
  "properties": {
    "iso:country":"US",
    "sg:address":"9 Harwood Ct",
    "sg:city":"Scarsdale",
    "sg:classifiers":[
        {
            "category":"Restaurant",
            "type":"Food & Drink"
        }
    ],
    "sg:phone":"+1 914 472 0702",
    "sg:postcode":"10583",
    "sg:province":"NY",
    "sg:tags":[
        "caterer"
    ],
    "wof:name":"LA-Renaissance French Pastry",
    "wof:placetype":"venue"
},
  "geometry": {"coordinates":[-73.807479,40.989183],"type":"Point"}
}