{
  "type": "Feature",
  "properties": {
    "addr:full":"46 Canterbury Dr Hauppauge NY 11788",
    "addr:housenumber":"46",
    "addr:postcode":"11788",
    "addr:street":"Canterbury Dr",
    "iso:country":"US",
    "sg:address":"46 Canterbury Dr",
    "sg:city":"Hauppauge",
    "sg:classifiers":[
        {
            "category":"Professional",
            "type":"Services"
        }
    ],
    "sg:phone":"+1 631 360 2033",
    "sg:postcode":"11788",
    "sg:province":"NY",
    "sg:tags":[
        "establishment"
    ],
    "wof:name":"Spartan Brands Inc",
    "wof:placetype":"venue"
},
  "geometry": {"coordinates":[-73.17160199999999,40.825148],"type":"Point"}
}