{
  "type": "Feature",
  "properties": {
    "addr:full":"440 Lawrence Bell Dr Buffalo NY 14221",
    "addr:housenumber":"440",
    "addr:postcode":"14221",
    "addr:street":"Lawrence Bell Dr",
    "iso:country":"US",
    "sg:address":"440 Lawrence Bell Dr",
    "sg:city":"Buffalo",
    "sg:classifiers":[
        {
            "category":"Professional",
            "subcategory":"Advertising",
            "type":"Services"
        }
    ],
    "sg:phone":"+1 716 633 5335",
    "sg:postcode":"14221",
    "sg:province":"NY",
    "sg:tags":[
        "distribution"
    ],
    "wof:name":"KML Distribution Inc",
    "wof:placetype":"venue"
},
  "geometry": {"coordinates":[-78.715548,42.952662],"type":"Point"}
}