{
  "type": "Feature",
  "properties": {
    "addr:full":"930 Glenridge Ave Valley Stream NY 11581",
    "addr:housenumber":"930",
    "addr:postcode":"11581",
    "addr:street":"Glenridge Ave",
    "iso:country":"US",
    "sg:address":"930 Glenridge Ave",
    "sg:city":"Valley Stream",
    "sg:classifiers":[
        {
            "category":"Building & Trades",
            "subcategory":"Plumbing",
            "type":"Services"
        }
    ],
    "sg:phone":"+1 516 374 7900",
    "sg:postcode":"11581",
    "sg:province":"NY",
    "wof:name":"Sarabella Service Inc",
    "wof:placetype":"venue"
},
  "geometry": {"coordinates":[-73.73211999999999,40.648289],"type":"Point"}
}