{
  "type": "Feature",
  "properties": {
    "iso:country":"US",
    "sg:address":"122 Remington Blvd",
    "sg:city":"Ronkonkoma",
    "sg:classifiers":[
        {
            "category":"Banks & Credit Unions",
            "subcategory":"Financial Services",
            "type":"Services"
        }
    ],
    "sg:phone":"+1 631 676 7888",
    "sg:postcode":"11779",
    "sg:province":"NY",
    "sg:tags":[
        "broker",
        "mortgage"
    ],
    "wof:name":"ABM Mortgage Company",
    "wof:placetype":"venue"
},
  "geometry": {"coordinates":[-73.132245,40.791572],"type":"Point"}
}