{
  "type": "Feature",
  "properties": {
    "addr:full":"214 E 167th St Bronx NY 10456",
    "addr:housenumber":"214",
    "addr:postcode":"10456",
    "addr:street":"E 167Th St",
    "iso:country":"US",
    "sg:address":"214 E 167th St",
    "sg:city":"Bronx",
    "sg:classifiers":[
        {
            "category":"Food & Beverages",
            "subcategory":"Meat & Fish",
            "type":"Retail Goods"
        }
    ],
    "sg:phone":"+1 718 681 9756",
    "sg:postcode":"10456",
    "sg:province":"NY",
    "sg:tags":[
        "seafood"
    ],
    "wof:name":"Grand Seafood",
    "wof:placetype":"venue"
},
  "geometry": {"coordinates":[-73.91627699999999,40.833954],"type":"Point"}
}