{
  "type": "Feature",
  "properties": {
    "iso:country":"US",
    "sg:address":"276 Freedom Rd",
    "sg:city":"Freedom",
    "sg:classifiers":[
        {
            "category":"Home & Garden",
            "subcategory":"Building Materials",
            "type":"Retail Goods"
        }
    ],
    "sg:phone":"+1 716 496 5133",
    "sg:postcode":"14065",
    "sg:province":"NY",
    "sg:tags":[
        "lumber"
    ],
    "wof:name":"Glen Phillippi Lumber Co Inc",
    "wof:placetype":"venue"
},
  "geometry": {"coordinates":[-78.324594,42.485191],"type":"Point"}
}