{
  "type": "Feature",
  "properties": {
    "addr:full":"146 Cordial Rd Yorktown Heights NY 10598",
    "addr:housenumber":"146",
    "addr:postcode":"10598",
    "addr:street":"Cordial Rd",
    "iso:country":"US",
    "sg:address":"146 Cordial Rd",
    "sg:city":"Yorktown Heights",
    "sg:classifiers":[
        {
            "category":"Retail",
            "subcategory":"Repair Shop",
            "type":"Services"
        }
    ],
    "sg:phone":"+1   ",
    "sg:postcode":"10598",
    "sg:province":"NY",
    "sg:tags":[
        "electrical"
    ],
    "wof:name":"Bja & Sons Electric",
    "wof:placetype":"venue"
},
  "geometry": {"coordinates":[-73.782805,41.318496],"type":"Point"}
}