{
  "type": "Feature",
  "properties": {
    "addr:full":"1248 Ruie Rd North Tonawanda NY 14120",
    "addr:housenumber":"1248",
    "addr:postcode":"14120",
    "addr:street":"Ruie Rd",
    "iso:country":"US",
    "sg:address":"1248 Ruie Rd",
    "sg:city":"North Tonawanda",
    "sg:classifiers":[
        {
            "category":"Restaurant",
            "type":"Food & Drink"
        }
    ],
    "sg:phone":"+1 716 695 1592",
    "sg:postcode":"14120",
    "sg:province":"NY",
    "sg:tags":[
        "out"
    ],
    "wof:name":"Good Guys Pizza",
    "wof:placetype":"venue"
},
  "geometry": {"coordinates":[-78.866765,43.063927],"type":"Point"}
}