{
  "type": "Feature",
  "properties": {
    "addr:full":"30 Mountain Rd Pomona NY 10970",
    "addr:housenumber":"30",
    "addr:postcode":"10970",
    "addr:street":"Mountain Rd",
    "iso:country":"US",
    "sg:address":"30 Mountain Rd",
    "sg:city":"Pomona",
    "sg:classifiers":[
        {
            "category":"Recreation",
            "type":"Entertainment"
        }
    ],
    "sg:phone":"+1 845 354 1600",
    "sg:postcode":"10970",
    "sg:province":"NY",
    "wof:name":"Campgroup LLC",
    "wof:placetype":"venue"
},
  "geometry": {"coordinates":[-74.06975799999999,41.186796],"type":"Point"}
}