{
  "type": "Feature",
  "properties": {
    "iso:country":"US",
    "sg:address":"146 W 170th St",
    "sg:city":"Bronx",
    "sg:classifiers":[
        {
            "category":"Freight",
            "type":"Transportation"
        }
    ],
    "sg:phone":"+1   ",
    "sg:postcode":"10452",
    "sg:province":"NY",
    "sg:tags":[
        "shipping"
    ],
    "wof:name":"Ocean Sealine Inc",
    "wof:placetype":"venue"
},
  "geometry": {"coordinates":[-73.924723,40.841338],"type":"Point"}
}