{
  "type": "Feature",
  "properties": {
    "addr:full":"12 Morris Ave Buffalo NY 14214",
    "addr:housenumber":"12",
    "addr:postcode":"14214",
    "addr:street":"Morris Ave",
    "iso:country":"US",
    "sg:address":"12 Morris Ave",
    "sg:city":"Buffalo",
    "sg:classifiers":[
        {
            "category":"Professional",
            "subcategory":"Management & Consulting",
            "type":"Services"
        }
    ],
    "sg:phone":"+1 716 836 3160",
    "sg:postcode":"14214",
    "sg:province":"NY",
    "sg:tags":[
        "food",
        "retail",
        "direct",
        "sales"
    ],
    "wof:name":"Tjd Food Service Enterprises",
    "wof:placetype":"venue"
},
  "geometry": {"coordinates":[-78.844404,42.94272],"type":"Point"}
}