{
  "type": "Feature",
  "properties": {
    "addr:full":"1490 Saratoga Rd Ballston Spa NY 12020",
    "addr:housenumber":"1490",
    "addr:postcode":"12020",
    "addr:street":"Saratoga Rd",
    "iso:country":"US",
    "sg:address":"1490 Saratoga Rd",
    "sg:city":"Ballston Spa",
    "sg:classifiers":[
        {
            "category":"Autos & Motor Vehicles",
            "subcategory":"Motorcycle Sales",
            "type":"Retail Goods"
        }
    ],
    "sg:phone":"+1 518 884 0100",
    "sg:postcode":"12020",
    "sg:province":"NY",
    "sg:website":"www.marshallsmotorsports.com",
    "wof:name":"MARSHALL'S MOTORSPORTS INC",
    "wof:placetype":"venue"
},
  "geometry": {"coordinates":[-73.855603,42.983907],"type":"Point"}
}