{
  "type": "Feature",
  "properties": {
    "iso:country":"US",
    "sg:address":"229 W 28 St",
    "sg:city":"New York",
    "sg:classifiers":[
        {
            "category":"Communications",
            "subcategory":"Television Station",
            "type":"Services"
        }
    ],
    "sg:phone":"+1   ",
    "sg:postcode":"10001",
    "sg:province":"NY",
    "sg:tags":[
        "chinese",
        "language"
    ],
    "wof:name":"New Tang Dynasty TV",
    "wof:placetype":"venue"
},
  "geometry": {"coordinates":[-73.99554500000001,40.74816],"type":"Point"}
}