{
  "type": "Feature",
  "properties": {
    "addr:full":"1694 Penfield Rd Rochester NY 14526",
    "addr:housenumber":"1694",
    "addr:postcode":"14526",
    "addr:street":"Penfield Rd",
    "iso:country":"US",
    "sg:address":"1694 Penfield Rd",
    "sg:city":"Rochester",
    "sg:classifiers":[
        {
            "category":"Restaurant",
            "type":"Food & Drink"
        }
    ],
    "sg:phone":"+1 585 249 9320",
    "sg:postcode":"14526",
    "sg:province":"NY",
    "wof:name":"Haung San Chinese Restaurant",
    "wof:placetype":"venue"
},
  "geometry": {"coordinates":[-77.489662,43.131647],"type":"Point"}
}