{
  "type": "Feature",
  "properties": {
    "addr:full":"86 Bush St Buffalo NY 14207",
    "addr:housenumber":"86",
    "addr:postcode":"14207",
    "addr:street":"Bush St",
    "iso:country":"US",
    "sg:address":"86 Bush St",
    "sg:city":"Buffalo",
    "sg:classifiers":[
        {
            "category":"Organizations",
            "subcategory":"Political Organization",
            "type":"Services"
        }
    ],
    "sg:phone":"+1   ",
    "sg:postcode":"14207",
    "sg:province":"NY",
    "sg:tags":[
        "child",
        "care"
    ],
    "wof:name":"Gems Childcare",
    "wof:placetype":"venue"
},
  "geometry": {"coordinates":[-78.88713300000001,42.94174],"type":"Point"}
}