{
  "type": "Feature",
  "properties": {
    "addr:full":"583 State Hwy 414 Beaver Dams NY 14812",
    "addr:housenumber":"583",
    "addr:postcode":"14812",
    "addr:street":"State Hwy 414",
    "iso:country":"US",
    "sg:address":"583 State Hwy 414",
    "sg:city":"Beaver Dams",
    "sg:classifiers":[
        {
            "category":"Sports & Exercise",
            "subcategory":"Golf",
            "type":"Entertainment"
        }
    ],
    "sg:phone":"+1   ",
    "sg:postcode":"14812",
    "sg:province":"NY",
    "sg:tags":[
        "shop",
        "par",
        "snack",
        "bar",
        "beauty",
        "three",
        "course",
        "go",
        "retail"
    ],
    "wof:name":"Circle R",
    "wof:placetype":"venue"
},
  "geometry": {"coordinates":[-76.957277,42.271708],"type":"Point"}
}