{
  "type": "Feature",
  "properties": {
    "addr:full":"2552 Pitkin Avenue Brooklyn NY 11208",
    "addr:housenumber":"2552",
    "addr:postcode":"11208",
    "addr:street":"Pitkin Avenue",
    "iso:country":"US",
    "sg:address":"2552 Pitkin Avenue",
    "sg:city":"Brooklyn",
    "sg:classifiers":[
        {
            "category":"Food & Beverages",
            "subcategory":"Candy",
            "type":"Retail Goods"
        }
    ],
    "sg:phone":"+1 718 235 6655",
    "sg:postcode":"11208",
    "sg:province":"NY",
    "sg:tags":[
        "store"
    ],
    "wof:name":"J F Wholesale Corporation",
    "wof:placetype":"venue"
},
  "geometry": {"coordinates":[-73.878022,40.674526],"type":"Point"}
}