{
  "type": "Feature",
  "properties": {
    "iso:country":"US",
    "sg:address":"16 Manetto Hill Mall",
    "sg:city":"Plainview",
    "sg:classifiers":[
        {
            "category":"Restaurant",
            "type":"Food & Drink"
        },
        {
            "category":"Bakery",
            "type":"Food & Drink"
        }
    ],
    "sg:phone":"+1 516 935 5225",
    "sg:postcode":"11803",
    "sg:province":"NY",
    "wof:name":"Pearl's Kosher Bake Shop",
    "wof:placetype":"venue"
},
  "geometry": {"coordinates":[-73.467073,40.776891],"type":"Point"}
}