{
  "type": "Feature",
  "properties": {
    "addr:full":"5825 S Salina St Syracuse NY 13205",
    "addr:housenumber":"5825",
    "addr:postcode":"13205",
    "addr:street":"S Salina St",
    "iso:country":"US",
    "sg:address":"5825 S Salina St",
    "sg:city":"Syracuse",
    "sg:classifiers":[
        {
            "category":"Health Services",
            "subcategory":"Doctor",
            "type":"Services"
        }
    ],
    "sg:phone":"+1 315 492 1213",
    "sg:postcode":"13205",
    "sg:province":"NY",
    "sg:tags":[
        "dentist"
    ],
    "wof:name":"Jerome E Mc Carthy DDS",
    "wof:placetype":"venue"
},
  "geometry": {"coordinates":[-76.143823,42.987011],"type":"Point"}
}