{
  "type": "Feature",
  "properties": {
    "addr:full":"515 Madison Ave New York NY 10022",
    "addr:housenumber":"515",
    "addr:postcode":"10022",
    "addr:street":"Madison Ave",
    "iso:country":"US",
    "sg:address":"515 Madison Ave",
    "sg:city":"New York",
    "sg:classifiers":[
        {
            "category":"Banks & Credit Unions",
            "subcategory":"Financial Services",
            "type":"Services"
        }
    ],
    "sg:phone":"+1 212 223 0882",
    "sg:postcode":"10022",
    "sg:province":"NY",
    "sg:tags":[
        "investor"
    ],
    "wof:name":"Broadway Bushwick Builders",
    "wof:placetype":"venue"
},
  "geometry": {"coordinates":[-73.97373899999999,40.760257],"type":"Point"}
}