{
  "type": "Feature",
  "properties": {
    "addr:full":"1067 Pacific Street, Brooklyn, New York, NY, USA",
    "addr:housenumber":1067,
    "addr:postcode":"11238",
    "addr:street":"Pacific Street",
    "addr:website":"http://www.environmentalperformanceagency.com/",
    "iso:country":"US",
    "name:eng_x_preferred":[
        "Environmental Performance Agency"
    ],
    "wof:name":"Environmental Performance Agency",
    "wof:placetype":"venue"
},
  "geometry": {"coordinates":[-73.958009,40.679047],"type":"Point"}
}