{
  "type": "Feature",
  "properties": {
    "iso:country":"US",
    "sg:address":"101 Excelsior Ave",
    "sg:city":"Middletown",
    "sg:classifiers":[
        {
            "category":"Wholesale",
            "subcategory":"Construction Materials",
            "type":"Manufacturing & Wholesale Goods"
        }
    ],
    "sg:phone":"+1 845 343 6457",
    "sg:postcode":"10940",
    "sg:province":"NY",
    "sg:tags":[
        "fence"
    ],
    "wof:name":"Excelsior Fence Co",
    "wof:placetype":"venue"
},
  "geometry": {"coordinates":[-74.402057,41.441107],"type":"Point"}
}