{
  "type": "Feature",
  "properties": {
    "addr:full":"2890 Ridge Rd W Rochester NY 14626",
    "addr:housenumber":"2890",
    "addr:postcode":"14626",
    "addr:street":"Ridge Rd W",
    "iso:country":"US",
    "sg:address":"2890 Ridge Rd W",
    "sg:city":"Rochester",
    "sg:classifiers":[
        {
            "category":"Restaurant",
            "type":"Food & Drink"
        }
    ],
    "sg:menulink":"http://www.allmenus.com/ny/greece/11442-dennys/menu/",
    "sg:phone":"+1 585 225 8350",
    "sg:postcode":"14626",
    "sg:province":"NY",
    "sg:tags":[
        "american",
        "diner"
    ],
    "wof:name":"Denny's",
    "wof:placetype":"venue"
},
  "geometry": {"coordinates":[-77.705493,43.210411],"type":"Point"}
}