{
  "type": "Feature",
  "properties": {
    "addr:full":"505 E 165th St Bronx NY 10456",
    "addr:housenumber":"505",
    "addr:postcode":"10456",
    "addr:street":"E 165Th St",
    "iso:country":"US",
    "sg:address":"505 E 165th St",
    "sg:city":"Bronx",
    "sg:classifiers":[
        {
            "category":"Professional",
            "type":"Services"
        }
    ],
    "sg:phone":"+1 718 402 0610",
    "sg:postcode":"10456",
    "sg:province":"NY",
    "sg:tags":[
        "establishment"
    ],
    "wof:name":"Bowlah Goolcharan",
    "wof:placetype":"venue"
},
  "geometry": {"coordinates":[-73.90856100000001,40.826922],"type":"Point"}
}