{
  "type": "Feature",
  "properties": {
    "addr:full":"16116 Crossbay Boulevard Howard Beach NY 11414",
    "addr:postcode":"16116;11414",
    "addr:street":"Crossbay Boulevard",
    "iso:country":"US",
    "sg:address":"16116 Crossbay Boulevard",
    "sg:city":"Howard Beach",
    "sg:classifiers":[
        {
            "category":"Restaurant",
            "type":"Food & Drink"
        }
    ],
    "sg:phone":"+1 718 843 7263",
    "sg:postcode":"11414",
    "sg:province":"NY",
    "sg:website":"www.brothersravioli.com",
    "wof:name":"Brothers Ravioli",
    "wof:placetype":"venue"
},
  "geometry": {"coordinates":[-73.83896799999999,40.654945],"type":"Point"}
}