{
  "type": "Feature",
  "properties": {
    "iso:country":"US",
    "sg:address":"235 E 53rd Street",
    "sg:city":"New York",
    "sg:classifiers":[
        {
            "category":"Restaurant",
            "type":"Food & Drink"
        }
    ],
    "sg:phone":"+1 212 752 2221",
    "sg:postcode":"10022",
    "sg:province":"NY",
    "wof:name":"Marrakesh",
    "wof:placetype":"venue"
},
  "geometry": {"coordinates":[-73.968525,40.757474],"type":"Point"}
}