{
  "type": "Feature",
  "properties": {
    "addr:full":"251 W 30th St Ste 9FW New York NY 10001",
    "addr:housenumber":"251",
    "addr:postcode":"10001",
    "addr:street":"W 30Th St Ste 9Fw",
    "iso:country":"US",
    "sg:address":"251 W 30th St Ste 9FW",
    "sg:city":"New York",
    "sg:classifiers":[
        {
            "category":"Personal",
            "subcategory":"Massage",
            "type":"Services"
        }
    ],
    "sg:phone":"+1 917 474 9394",
    "sg:postcode":"10001",
    "sg:province":"NY",
    "sg:website":"www.bodyplusmindnyc.com",
    "wof:name":"Body + Mind",
    "wof:placetype":"venue"
},
  "geometry": {"coordinates":[-73.994247,40.749482],"type":"Point"}
}