{
  "type": "Feature",
  "properties": {
    "addr:full":"180 Madison Ave New York NY 10016",
    "addr:housenumber":"180",
    "addr:postcode":"10016",
    "addr:street":"Madison Ave",
    "iso:country":"US",
    "sg:address":"180 Madison Ave",
    "sg:city":"New York",
    "sg:classifiers":[
        {
            "category":"Shopping",
            "subcategory":"Discount & Variety Stores",
            "type":"Retail Goods"
        }
    ],
    "sg:phone":"+1 212 686 1090",
    "sg:postcode":"10016",
    "sg:province":"NY",
    "sg:tags":[
        "merchandise",
        "general"
    ],
    "wof:name":"Majestic Sales",
    "wof:placetype":"venue"
},
  "geometry": {"coordinates":[-73.983268,40.747357],"type":"Point"}
}