{
  "type": "Feature",
  "properties": {
    "iso:country":"US",
    "sg:address":"11517 Genesee St",
    "sg:city":"Alden",
    "sg:classifiers":[
        {
            "category":"Organizations",
            "subcategory":"Religious Organization",
            "type":"Services"
        }
    ],
    "sg:phone":"+1 716 937 7926",
    "sg:postcode":"14004",
    "sg:province":"NY",
    "wof:name":"Millgrove Bible Church",
    "wof:placetype":"venue"
},
  "geometry": {"coordinates":[-78.558707,42.943823],"type":"Point"}
}