{
  "type": "Feature",
  "properties": {
    "addr:full":"411 State Hwy 211 Middletown NY 10940",
    "addr:housenumber":"411",
    "addr:postcode":"10940",
    "addr:street":"State Hwy 211",
    "iso:country":"US",
    "sg:address":"411 State Hwy 211",
    "sg:city":"Middletown",
    "sg:classifiers":[
        {
            "category":"Restaurant",
            "type":"Food & Drink"
        }
    ],
    "sg:phone":"+1 845 343 4841",
    "sg:postcode":"10940",
    "sg:province":"NY",
    "wof:name":"Denny's",
    "wof:placetype":"venue"
},
  "geometry": {"coordinates":[-74.446949,41.464484],"type":"Point"}
}