{
  "type": "Feature",
  "properties": {
    "addr:full":"304 E 134th St Bronx NY 10454",
    "addr:housenumber":"304",
    "addr:postcode":"10454",
    "addr:street":"E 134Th St",
    "iso:country":"US",
    "sg:address":"304 E 134th St",
    "sg:city":"Bronx",
    "sg:classifiers":[
        {
            "category":"Bus Station",
            "type":"Transportation"
        }
    ],
    "sg:phone":"+1   ",
    "sg:postcode":"10454",
    "sg:province":"NY",
    "sg:tags":[
        "facility"
    ],
    "wof:name":"Bravo Bus Service Inc",
    "wof:placetype":"venue"
},
  "geometry": {"coordinates":[-73.92813200000001,40.808055],"type":"Point"}
}