{
  "type": "Feature",
  "properties": {
    "iso:country":"US",
    "sg:address":"9887 Burns Rd",
    "sg:city":"Arkport",
    "sg:classifiers":[
        {
            "category":"Organizations",
            "subcategory":"Religious Organization",
            "type":"Services"
        }
    ],
    "sg:phone":"+1 607 295 8782",
    "sg:postcode":"14807",
    "sg:province":"NY",
    "sg:tags":[
        "church"
    ],
    "wof:name":"Burns Community Church",
    "wof:placetype":"venue"
},
  "geometry": {"coordinates":[-77.72523099999999,42.429857],"type":"Point"}
}