{
  "type": "Feature",
  "properties": {
    "addr:full":"991 Route 6 Mahopac NY 10541",
    "addr:housenumber":"991",
    "addr:postcode":"10541",
    "addr:street":"Route 6",
    "iso:country":"US",
    "sg:address":"991 Route 6",
    "sg:city":"Mahopac",
    "sg:classifiers":[
        {
            "category":"Personal",
            "subcategory":"Nail Salon",
            "type":"Services"
        }
    ],
    "sg:phone":"+1 845 621 4016",
    "sg:postcode":"10541",
    "sg:province":"NY",
    "wof:name":"Lake Nail Spa",
    "wof:placetype":"venue"
},
  "geometry": {"coordinates":[-73.72303700000001,41.392498],"type":"Point"}
}