{
  "type": "Feature",
  "properties": {
    "addr:full":"1 Battiato Ln Chester NY 10918",
    "addr:housenumber":"1",
    "addr:postcode":"10918",
    "addr:street":"Battiato Ln",
    "iso:country":"US",
    "sg:address":"1 Battiato Ln",
    "sg:city":"Chester",
    "sg:classifiers":[
        {
            "category":"Building & Trades",
            "subcategory":"Construction",
            "type":"Services"
        }
    ],
    "sg:phone":"+1 845 469 6775",
    "sg:postcode":"10918",
    "sg:province":"NY",
    "sg:tags":[
        "floor",
        "laying",
        "contractor"
    ],
    "wof:name":"Mountain Top Tile",
    "wof:placetype":"venue"
},
  "geometry": {"coordinates":[-74.270273,41.361985],"type":"Point"}
}