{
  "type": "Feature",
  "properties": {
    "addr:full":"838 W German St Herkimer NY 13350",
    "addr:housenumber":"838",
    "addr:postcode":"13350",
    "addr:street":"W German St",
    "iso:country":"US",
    "sg:address":"838 W German St",
    "sg:city":"Herkimer",
    "sg:classifiers":[
        {
            "category":"Organizations",
            "subcategory":"Religious Organization",
            "type":"Services"
        }
    ],
    "sg:phone":"+1 315 866 0575",
    "sg:postcode":"13350",
    "sg:province":"NY",
    "wof:name":"Oakridge Free Methodist Church",
    "wof:placetype":"venue"
},
  "geometry": {"coordinates":[-75.00275000000001,43.023095],"type":"Point"}
}