{
  "type": "Feature",
  "properties": {
    "iso:country":"US",
    "sg:address":"40 Hook Ln",
    "sg:city":"Levittown",
    "sg:classifiers":[
        {
            "category":"Insurance",
            "subcategory":"Life Insurance",
            "type":"Services"
        }
    ],
    "sg:phone":"+1 516 731 8442",
    "sg:postcode":"11756",
    "sg:province":"NY",
    "sg:tags":[
        "carrier"
    ],
    "wof:name":"Woodbury Financial Services",
    "wof:placetype":"venue"
},
  "geometry": {"coordinates":[-73.504825,40.714458],"type":"Point"}
}