{
  "type": "Feature",
  "properties": {
    "iso:country":"US",
    "sg:address":"260 Hilltop Dr",
    "sg:city":"Elma",
    "sg:classifiers":[
        {
            "category":"Building & Trades",
            "subcategory":"Construction",
            "type":"Services"
        }
    ],
    "sg:phone":"+1 716 687 1264",
    "sg:postcode":"14059",
    "sg:province":"NY",
    "sg:tags":[
        "home",
        "family"
    ],
    "wof:name":"Jeffrey Brodowski",
    "wof:placetype":"venue"
},
  "geometry": {"coordinates":[-78.628877,42.827174],"type":"Point"}
}