{
  "type": "Feature",
  "properties": {
    "iso:country":"US",
    "sg:address":"100 Union Ave",
    "sg:city":"New Rochelle",
    "sg:classifiers":[
        {
            "category":"Food & Beverages",
            "subcategory":"Groceries & Convenience Stores",
            "type":"Retail Goods"
        }
    ],
    "sg:phone":"+1   ",
    "sg:postcode":"10801",
    "sg:province":"NY",
    "wof:name":"Mexican Supermarket",
    "wof:placetype":"venue"
},
  "geometry": {"coordinates":[-73.788759,40.91004],"type":"Point"}
}