{
  "type": "Feature",
  "properties": {
    "iso:country":"US",
    "sg:address":"3501 Boston Rd",
    "sg:city":"Bronx",
    "sg:classifiers":[
        {
            "category":"Food & Beverages",
            "subcategory":"Groceries & Convenience Stores",
            "type":"Retail Goods"
        }
    ],
    "sg:phone":"+1 718 653 3064",
    "sg:postcode":"10469",
    "sg:province":"NY",
    "sg:website":"www.7-eleven.com",
    "wof:name":"7-Eleven",
    "wof:placetype":"venue"
},
  "geometry": {"coordinates":[-73.845461,40.877347],"type":"Point"}
}