{
  "type": "Feature",
  "properties": {
    "iso:country":"US",
    "sg:address":"111 W Nicholai St",
    "sg:city":"Hicksville",
    "sg:classifiers":[
        {
            "category":"Banks & Credit Unions",
            "subcategory":"Investment Brokerage",
            "type":"Services"
        }
    ],
    "sg:phone":"+1 516 681 6175",
    "sg:postcode":"11801",
    "sg:province":"NY",
    "sg:tags":[
        "consultant",
        "planning",
        "financial"
    ],
    "wof:name":"Delphi Insurance Brokerage",
    "wof:placetype":"venue"
},
  "geometry": {"coordinates":[-73.52649099999999,40.764454],"type":"Point"}
}