{
  "type": "Feature",
  "properties": {
    "addr:full":"5 Limestone Dr Buffalo NY 14221",
    "addr:housenumber":"5",
    "addr:postcode":"14221",
    "addr:street":"Limestone Dr",
    "iso:country":"US",
    "sg:address":"5 Limestone Dr",
    "sg:city":"Buffalo",
    "sg:classifiers":[
        {
            "category":"Banks & Credit Unions",
            "subcategory":"Investment Brokerage",
            "type":"Services"
        }
    ],
    "sg:phone":"+1 716 632 4500",
    "sg:postcode":"14221",
    "sg:province":"NY",
    "sg:tags":[
        "advisory",
        "security",
        "financial",
        "dealer"
    ],
    "wof:name":"Bryan E Tenney Financial Serv",
    "wof:placetype":"venue"
},
  "geometry": {"coordinates":[-78.71275799999999,42.96313],"type":"Point"}
}