{
  "type": "Feature",
  "properties": {
    "iso:country":"US",
    "sg:address":"414 New York Ave",
    "sg:city":"Huntington",
    "sg:classifiers":[
        {
            "category":"Building & Trades",
            "subcategory":"Construction",
            "type":"Services"
        }
    ],
    "sg:phone":"+1 631 351 8900",
    "sg:postcode":"11743",
    "sg:province":"NY",
    "sg:tags":[
        "interior",
        "design"
    ],
    "wof:name":"Huntington Village Design Center",
    "wof:placetype":"venue"
},
  "geometry": {"coordinates":[-73.425797,40.868099],"type":"Point"}
}