{
  "type": "Feature",
  "properties": {
    "addr:full":"2640 3rd Ave Bronx NY 10454",
    "addr:housenumber":"2640",
    "addr:postcode":"10454",
    "addr:street":"3Rd Ave",
    "iso:country":"US",
    "sg:address":"2640 3rd Ave",
    "sg:city":"Bronx",
    "sg:classifiers":[
        {
            "category":"Organizations",
            "subcategory":"Non-profit Organization",
            "type":"Services"
        }
    ],
    "sg:phone":"+1 718 993 0001",
    "sg:postcode":"10454",
    "sg:province":"NY",
    "sg:tags":[
        "info",
        "addiction",
        "abuse",
        "treatment",
        "drug"
    ],
    "wof:name":"Narco Freedom Inc",
    "wof:placetype":"venue"
},
  "geometry": {"coordinates":[-73.92411,40.812542],"type":"Point"}
}