{
  "type": "Feature",
  "properties": {
    "addr:full":"706 Morris Park Avenue Bronx NY 10462",
    "addr:housenumber":"706",
    "addr:postcode":"10462",
    "addr:street":"Morris Park Avenue",
    "iso:country":"US",
    "sg:address":"706 Morris Park Avenue",
    "sg:city":"Bronx",
    "sg:classifiers":[
        {
            "category":"Building & Trades",
            "subcategory":"Plumbing",
            "type":"Services"
        }
    ],
    "sg:phone":"+1 718 822 6050",
    "sg:postcode":"10462",
    "sg:province":"NY",
    "wof:name":"Expert Plumbing Svces",
    "wof:placetype":"venue"
},
  "geometry": {"coordinates":[-73.865601,40.845216],"type":"Point"}
}