{
  "type": "Feature",
  "properties": {
    "addr:full":"4423 8th Ave Brooklyn NY 11220",
    "addr:housenumber":"4423",
    "addr:postcode":"11220",
    "addr:street":"8Th Ave",
    "iso:country":"US",
    "sg:address":"4423 8th Ave",
    "sg:city":"Brooklyn",
    "sg:classifiers":[
        {
            "category":"Food & Beverages",
            "subcategory":"Groceries & Convenience Stores",
            "type":"Retail Goods"
        }
    ],
    "sg:phone":"+1 718 871 0928",
    "sg:postcode":"11220",
    "sg:province":"NY",
    "sg:tags":[
        "market"
    ],
    "wof:name":"Fei Long Market",
    "wof:placetype":"venue"
},
  "geometry": {"coordinates":[-74.00064,40.643997],"type":"Point"}
}