{
  "type": "Feature",
  "properties": {
    "iso:country":"US",
    "sg:address":"4610 13th Ave",
    "sg:city":"Brooklyn",
    "sg:classifiers":[
        {
            "category":"Shopping",
            "subcategory":"Clothing, Apparel, & Fashions",
            "type":"Retail Goods"
        }
    ],
    "sg:phone":"+1 718 853 3420",
    "sg:postcode":"11219",
    "sg:province":"NY",
    "wof:name":"Benetton",
    "wof:placetype":"venue"
},
  "geometry": {"coordinates":[-73.99097,40.636249],"type":"Point"}
}