{
  "type": "Feature",
  "properties": {
    "addr:full":"4400 Covington Rd Leicester NY 14481",
    "addr:housenumber":"4400",
    "addr:postcode":"14481",
    "addr:street":"Covington Rd",
    "iso:country":"US",
    "sg:address":"4400 Covington Rd",
    "sg:city":"Leicester",
    "sg:classifiers":[
        {
            "category":"Building & Trades",
            "subcategory":"Construction",
            "type":"Services"
        }
    ],
    "sg:phone":"+1 585 382 9503",
    "sg:postcode":"14481",
    "sg:province":"NY",
    "sg:tags":[
        "roofing",
        "industrial",
        "contractors-commercial",
        "contractor"
    ],
    "wof:name":"All American Roofing",
    "wof:placetype":"venue"
},
  "geometry": {"coordinates":[-77.943878,42.803848],"type":"Point"}
}