{
  "type": "Feature",
  "properties": {
    "addr:full":"10 Stewart Pl White Plains NY 10603",
    "addr:housenumber":"10",
    "addr:postcode":"10603",
    "addr:street":"Stewart Pl",
    "iso:country":"US",
    "sg:address":"10 Stewart Pl",
    "sg:city":"White Plains",
    "sg:classifiers":[
        {
            "category":"Organizations",
            "subcategory":"Religious Organization",
            "type":"Services"
        }
    ],
    "sg:phone":"+1 914 946 5748",
    "sg:postcode":"10603",
    "sg:province":"NY",
    "sg:tags":[
        "clergy"
    ],
    "wof:name":"Richard E Stout",
    "wof:placetype":"venue"
},
  "geometry": {"coordinates":[-73.762579,41.036815],"type":"Point"}
}