{
  "type": "Feature",
  "properties": {
    "iso:country":"US",
    "sg:address":"7 Weir St",
    "sg:city":"Locust Valley",
    "sg:classifiers":[
        {
            "category":"Wholesale",
            "subcategory":"Medical Equipment & Supplies",
            "type":"Manufacturing & Wholesale Goods"
        }
    ],
    "sg:phone":"+1 516 676 8700",
    "sg:postcode":"11550",
    "sg:province":"NY",
    "sg:tags":[
        "export"
    ],
    "wof:name":"Rosot Enterprises Inc",
    "wof:placetype":"venue"
},
  "geometry": {"coordinates":[-73.620878,40.689023],"type":"Point"}
}