{
  "type": "Feature",
  "properties": {
    "addr:full":"1009 Glen Cove Ave Glen Head NY 11545",
    "addr:housenumber":"1009",
    "addr:postcode":"11545",
    "addr:street":"Glen Cove Ave Glen",
    "iso:country":"US",
    "sg:address":"1009 Glen Cove Ave",
    "sg:city":"Glen Head",
    "sg:classifiers":[
        {
            "category":"Insurance",
            "subcategory":"Insurance Agent",
            "type":"Services"
        }
    ],
    "sg:phone":"+1 516 671 5030",
    "sg:postcode":"11545",
    "sg:province":"NY",
    "wof:name":"Multi Risk Lines Insurance",
    "wof:placetype":"venue"
},
  "geometry": {"coordinates":[-73.626623,40.823597],"type":"Point"}
}