{
  "type": "Feature",
  "properties": {
    "addr:full":"606 Johnson Ave Bohemia NY 11716",
    "addr:housenumber":"606",
    "addr:postcode":"11716",
    "addr:street":"Johnson Ave",
    "iso:country":"US",
    "sg:address":"606 Johnson Ave",
    "sg:city":"Bohemia",
    "sg:classifiers":[
        {
            "category":"Shopping",
            "subcategory":"Jewelry",
            "type":"Retail Goods"
        }
    ],
    "sg:phone":"+1 631 244 4546",
    "sg:postcode":"11716",
    "sg:province":"NY",
    "sg:tags":[
        "platinum",
        "silver",
        "gold"
    ],
    "wof:name":"First National Gold & Silver",
    "wof:placetype":"venue"
},
  "geometry": {"coordinates":[-73.097041,40.780468],"type":"Point"}
}