{
  "type": "Feature",
  "properties": {
    "iso:country":"US",
    "sg:address":"579 Heritage Dr",
    "sg:city":"Rochester",
    "sg:classifiers":[
        {
            "category":"Real Estate",
            "subcategory":"Real Estate Agent",
            "type":"Services"
        }
    ],
    "sg:phone":"+1 585 663 3609",
    "sg:postcode":"14615",
    "sg:province":"NY",
    "wof:name":"Maysie Goodreau",
    "wof:placetype":"venue"
},
  "geometry": {"coordinates":[-77.665798,43.234968],"type":"Point"}
}