{
  "type": "Feature",
  "properties": {
    "iso:country":"US",
    "sg:address":"24830 S Conduit Avenue",
    "sg:city":"Rosedale",
    "sg:classifiers":[
        {
            "category":"Autos & Motor Vehicles",
            "subcategory":"Fuel & Gas Station",
            "type":"Retail Goods"
        }
    ],
    "sg:phone":"+1 718 978 8623",
    "sg:postcode":"11422",
    "sg:province":"NY",
    "wof:name":"Citylineservice Station",
    "wof:placetype":"venue"
},
  "geometry": {"coordinates":[-73.729242,40.66524],"type":"Point"}
}