{
  "type": "Feature",
  "properties": {
    "iso:country":"US",
    "sg:address":"937 Sacandaga Rd",
    "sg:city":"Schenectady",
    "sg:classifiers":[
        {
            "category":"Manufacturing",
            "subcategory":"Tools & Machinery",
            "type":"Manufacturing & Wholesale Goods"
        }
    ],
    "sg:phone":"+1   ",
    "sg:postcode":"12302",
    "sg:province":"NY",
    "sg:tags":[
        "devices",
        "mfg"
    ],
    "wof:name":"AZ Radiation Mesrmnt",
    "wof:placetype":"venue"
},
  "geometry": {"coordinates":[-73.995966,42.918284],"type":"Point"}
}