{
  "type": "Feature",
  "properties": {
    "iso:country":"US",
    "sg:address":"3448 Junction Blvd",
    "sg:city":"Jackson Heights",
    "sg:classifiers":[
        {
            "category":"Bakery",
            "type":"Food & Drink"
        }
    ],
    "sg:phone":"+1 718 478 1888",
    "sg:postcode":"11372",
    "sg:province":"NY",
    "wof:name":"Barranquilla Bakery",
    "wof:placetype":"venue"
},
  "geometry": {"coordinates":[-73.87220000000001,40.7537],"type":"Point"}
}