{
  "type": "Feature",
  "properties": {
    "iso:country":"US",
    "sg:address":"50 Lisburne Ln",
    "sg:city":"Garrison",
    "sg:classifiers":[
        {
            "category":"Professional",
            "subcategory":"Art Services",
            "type":"Services"
        }
    ],
    "sg:phone":"+1 845 424 3518",
    "sg:postcode":"10524",
    "sg:province":"NY",
    "sg:tags":[
        "designer",
        "display",
        "producer"
    ],
    "wof:name":"Lacko Strong Studios",
    "wof:placetype":"venue"
},
  "geometry": {"coordinates":[-73.939178,41.378391],"type":"Point"}
}