{
  "type": "Feature",
  "properties": {
    "iso:country":"US",
    "sg:address":"6505 E Quaker St",
    "sg:city":"Orchard Park",
    "sg:classifiers":[
        {
            "category":"Real Estate",
            "subcategory":"Real Estate Agent",
            "type":"Services"
        }
    ],
    "sg:phone":"+1 716 662 2000",
    "sg:postcode":"14127",
    "sg:province":"NY",
    "sg:tags":[
        "manager"
    ],
    "wof:name":"Stovorff & Potter",
    "wof:placetype":"venue"
},
  "geometry": {"coordinates":[-78.741241,42.767839],"type":"Point"}
}