{
  "type": "Feature",
  "properties": {
    "addr:full":"8386 N Main St Eden NY 14057",
    "addr:housenumber":"8386",
    "addr:postcode":"14057",
    "addr:street":"N Main St",
    "iso:country":"US",
    "sg:address":"8386 N Main St",
    "sg:city":"Eden",
    "sg:classifiers":[
        {
            "category":"Shopping",
            "subcategory":"Crafts & Fabrics",
            "type":"Retail Goods"
        }
    ],
    "sg:phone":"+1   ",
    "sg:postcode":"14057",
    "sg:province":"NY",
    "sg:tags":[
        "sewing"
    ],
    "sg:website":"www.edensewingcenter.com",
    "wof:name":"Best Impressions By Carolynn",
    "wof:placetype":"venue"
},
  "geometry": {"coordinates":[-78.89395500000001,42.658486],"type":"Point"}
}