{
  "type": "Feature",
  "properties": {
    "iso:country":"US",
    "sg:address":"3958 Demont Rd",
    "sg:city":"Seaford",
    "sg:classifiers":[
        {
            "category":"Organizations",
            "subcategory":"Community Association",
            "type":"Services"
        }
    ],
    "sg:phone":"+1 516 616 3366",
    "sg:postcode":"11783",
    "sg:province":"NY",
    "sg:tags":[
        "club"
    ],
    "wof:name":"Mothers Of Twins Club Nassau",
    "wof:placetype":"venue"
},
  "geometry": {"coordinates":[-73.48509199999999,40.699769],"type":"Point"}
}