{
  "type": "Feature",
  "properties": {
    "addr:full":"12 E 79th St New York NY 10021",
    "addr:housenumber":"12",
    "addr:postcode":"10021",
    "addr:street":"E 79Th St",
    "iso:country":"US",
    "sg:address":"12 E 79th St",
    "sg:city":"New York",
    "sg:classifiers":[
        {
            "category":"Social Services",
            "subcategory":"Child Care",
            "type":"Services"
        }
    ],
    "sg:phone":"+1 212 744 0811",
    "sg:postcode":"10021",
    "sg:province":"NY",
    "sg:tags":[
        "day"
    ],
    "wof:name":"Ark Nursery School",
    "wof:placetype":"venue"
},
  "geometry": {"coordinates":[-73.963402,40.776699],"type":"Point"}
}