{
  "type": "Feature",
  "properties": {
    "addr:full":"573 Linda Ave Thornwood NY 10594",
    "addr:housenumber":"573",
    "addr:postcode":"10594",
    "addr:street":"Linda Ave",
    "iso:country":"US",
    "sg:address":"573 Linda Ave",
    "sg:city":"Thornwood",
    "sg:classifiers":[
        {
            "category":"Wholesale",
            "subcategory":"Groceries",
            "type":"Manufacturing & Wholesale Goods"
        }
    ],
    "sg:phone":"+1 914 769 5721",
    "sg:postcode":"10594",
    "sg:province":"NY",
    "sg:tags":[
        "frozen",
        "food"
    ],
    "wof:name":"Seaberghs Freezer Owners Depot",
    "wof:placetype":"venue"
},
  "geometry": {"coordinates":[-73.785724,41.113496],"type":"Point"}
}