{
  "type": "Feature",
  "properties": {
    "addr:full":"395 Autumn Ave Brooklyn NY 11208",
    "addr:housenumber":"395",
    "addr:postcode":"11208",
    "addr:street":"Autumn Ave",
    "iso:country":"US",
    "sg:address":"395 Autumn Ave",
    "sg:city":"Brooklyn",
    "sg:classifiers":[
        {
            "category":"Personal",
            "subcategory":"Barber",
            "type":"Services"
        }
    ],
    "sg:phone":"+1 718 942 3332",
    "sg:postcode":"11208",
    "sg:province":"NY",
    "wof:name":"Def Cutz Inc",
    "wof:placetype":"venue"
},
  "geometry": {"coordinates":[-73.869202,40.680302],"type":"Point"}
}