{
  "type": "Feature",
  "properties": {
    "iso:country":"US",
    "sg:address":"6165 Pennell Rd",
    "sg:city":"Canandaigua",
    "sg:classifiers":[
        {
            "category":"Wholesale",
            "subcategory":"Scrap",
            "type":"Manufacturing & Wholesale Goods"
        }
    ],
    "sg:phone":"+1 315 986 2259",
    "sg:postcode":"14425",
    "sg:province":"NY",
    "sg:tags":[
        "metal",
        "iron"
    ],
    "wof:name":"Allen Recycling",
    "wof:placetype":"venue"
},
  "geometry": {"coordinates":[-77.360631,43.033776],"type":"Point"}
}