{
  "type": "Feature",
  "properties": {
    "addr:full":"6544 4th Section Rd Brockport NY 14420",
    "addr:housenumber":"6544",
    "addr:postcode":"14420",
    "addr:street":"4Th Section Rd",
    "iso:country":"US",
    "sg:address":"6544 4th Section Rd",
    "sg:city":"Brockport",
    "sg:classifiers":[
        {
            "category":"Shopping",
            "subcategory":"Clothing, Apparel, & Fashions",
            "type":"Retail Goods"
        },
        {
            "category":"Shopping",
            "subcategory":"Shoes",
            "type":"Retail Goods"
        }
    ],
    "sg:phone":"+1 585 637 2240",
    "sg:postcode":"14420",
    "sg:province":"NY",
    "sg:tags":[
        "accessory",
        "store",
        "women's"
    ],
    "sg:website":"http://www.paylessshoesource.com",
    "wof:name":"Payless ShoeSource",
    "wof:placetype":"venue"
},
  "geometry": {"coordinates":[-77.94525400000001,43.198362],"type":"Point"}
}