{
  "type": "Feature",
  "properties": {
    "addr:full":"95 Searing Ave Mineola NY 11501",
    "addr:housenumber":"95",
    "addr:postcode":"11501",
    "addr:street":"Searing Ave",
    "iso:country":"US",
    "sg:address":"95 Searing Ave",
    "sg:city":"Mineola",
    "sg:classifiers":[
        {
            "category":"Wholesale",
            "subcategory":"Plants",
            "type":"Manufacturing & Wholesale Goods"
        }
    ],
    "sg:phone":"+1 516 741 6450",
    "sg:postcode":"11501",
    "sg:province":"NY",
    "sg:tags":[
        "flower"
    ],
    "wof:name":"National Flowers Inc",
    "wof:placetype":"venue"
},
  "geometry": {"coordinates":[-73.635682,40.744804],"type":"Point"}
}