{
  "type": "Feature",
  "properties": {
    "addr:full":"18 Fletcher Pl Melville NY 11747",
    "addr:housenumber":"18",
    "addr:postcode":"11747",
    "addr:street":"Fletcher Pl",
    "iso:country":"US",
    "sg:address":"18 Fletcher Pl",
    "sg:city":"Melville",
    "sg:classifiers":[
        {
            "category":"Organizations",
            "subcategory":"Religious Organization",
            "type":"Services"
        }
    ],
    "sg:phone":"+1 631 673 0919",
    "sg:postcode":"11747",
    "sg:province":"NY",
    "sg:tags":[
        "clergy"
    ],
    "wof:name":"Yoon W Kim",
    "wof:placetype":"venue"
},
  "geometry": {"coordinates":[-73.413916,40.800789],"type":"Point"}
}