{
  "type": "Feature",
  "properties": {
    "addr:full":"325 Broadway Lawrence NY 11559",
    "addr:housenumber":"325",
    "addr:postcode":"11559",
    "addr:street":"Broadway",
    "iso:country":"US",
    "sg:address":"325 Broadway",
    "sg:city":"Lawrence",
    "sg:phone":"+1 516 239 6449",
    "sg:postcode":"11559",
    "sg:province":"NY",
    "sg:tags":[
        "equipment",
        "commercial"
    ],
    "wof:name":"Kooltech LLC",
    "wof:placetype":"venue"
},
  "geometry": {"coordinates":[-73.729403,40.615609],"type":"Point"}
}