{
  "type": "Feature",
  "properties": {
    "iso:country":"US",
    "sg:address":"99 Gardiners Ave",
    "sg:city":"Levittown",
    "sg:classifiers":[
        {
            "category":"Home & Garden",
            "subcategory":"Household Appliances",
            "type":"Retail Goods"
        },
        {
            "category":"Retail",
            "subcategory":"Repair Shop",
            "type":"Services"
        },
        {
            "category":"Building & Trades",
            "subcategory":"Construction",
            "type":"Services"
        }
    ],
    "sg:phone":"+1 516 731 6022",
    "sg:postcode":"11756",
    "sg:province":"NY",
    "sg:tags":[
        "major",
        "refinishing",
        "system",
        "appliances-small",
        "specialty",
        "heating",
        "small",
        "contractor",
        "air conditioning"
    ],
    "wof:name":"Celtic Appliance & Air Conditioning Inc",
    "wof:placetype":"venue"
},
  "geometry": {"coordinates":[-73.51505899999999,40.723439],"type":"Point"}
}