{
  "type": "Feature",
  "properties": {
    "iso:country":"US",
    "sg:address":"424 E 52 St",
    "sg:city":"New York",
    "sg:phone":"+1 212 888 6393",
    "sg:postcode":"10022",
    "sg:province":"NY",
    "sg:tags":[
        "industrial",
        "shelving"
    ],
    "wof:name":"Metro Wire Shelving",
    "wof:placetype":"venue"
},
  "geometry": {"coordinates":[-73.964218,40.754686],"type":"Point"}
}