{
  "type": "Feature",
  "properties": {
    "iso:country":"US",
    "sg:address":"8266 Warbler Way Apt C3",
    "sg:city":"Liverpool",
    "sg:classifiers":[
        {
            "category":"Shopping",
            "subcategory":"Gifts & Souvenirs",
            "type":"Retail Goods"
        }
    ],
    "sg:phone":"+1 315 698 7897",
    "sg:postcode":"13090",
    "sg:province":"NY",
    "sg:tags":[
        "basket"
    ],
    "wof:name":"Quality Gift Baskets",
    "wof:placetype":"venue"
},
  "geometry": {"coordinates":[-76.24136799999999,43.170873],"type":"Point"}
}