{
  "type": "Feature",
  "properties": {
    "addr:full":"145 Metro Park Rochester NY 14623",
    "addr:housenumber":"145",
    "addr:postcode":"14623",
    "addr:street":"Metro Park",
    "iso:country":"US",
    "sg:address":"145 Metro Park",
    "sg:city":"Rochester",
    "sg:classifiers":[
        {
            "category":"Wholesale",
            "subcategory":"Metals & Minerals",
            "type":"Manufacturing & Wholesale Goods"
        }
    ],
    "sg:phone":"+1 585 475 1050",
    "sg:postcode":"14623",
    "sg:province":"NY",
    "sg:tags":[
        "warehouse",
        "steel",
        "product",
        "aluminum"
    ],
    "sg:website":"www.emjmetals.com",
    "wof:name":"Earle M Jorgensen Company",
    "wof:placetype":"venue"
},
  "geometry": {"coordinates":[-77.617113,43.097497],"type":"Point"}
}