{
  "type": "Feature",
  "properties": {
    "addr:full":"126 Main St Whitehall NY 12887",
    "addr:housenumber":"126",
    "addr:postcode":"12887",
    "addr:street":"Main St",
    "iso:country":"US",
    "sg:address":"126 Main St",
    "sg:city":"Whitehall",
    "sg:classifiers":[
        {
            "category":"Manufacturing",
            "subcategory":"Printing",
            "type":"Manufacturing & Wholesale Goods"
        }
    ],
    "sg:phone":"+1 518 499 1500",
    "sg:postcode":"12887",
    "sg:province":"NY",
    "sg:tags":[
        "newspaper"
    ],
    "wof:name":"Whitehall Times",
    "wof:placetype":"venue"
},
  "geometry": {"coordinates":[-73.402522,43.555229],"type":"Point"}
}