{
  "type": "Feature",
  "properties": {
    "addr:full":"3 Treeline Ter Nyack NY 10960",
    "addr:housenumber":"3",
    "addr:postcode":"10960",
    "addr:street":"Treeline Ter Nyack",
    "iso:country":"US",
    "sg:address":"3 Treeline Ter",
    "sg:city":"Nyack",
    "sg:classifiers":[
        {
            "category":"Communications",
            "type":"Services"
        }
    ],
    "sg:phone":"+1 845 727 4020",
    "sg:postcode":"10960",
    "sg:province":"NY",
    "wof:name":"Six Thirteen Communications",
    "wof:placetype":"venue"
},
  "geometry": {"coordinates":[-73.924083,41.065002],"type":"Point"}
}