{
  "type": "Feature",
  "properties": {
    "addr:full":"8 Access Rd Albany NY 12205",
    "addr:housenumber":"8",
    "addr:postcode":"12205",
    "addr:street":"Access Rd",
    "iso:country":"US",
    "sg:address":"8 Access Rd",
    "sg:city":"Albany",
    "sg:classifiers":[
        {
            "category":"Wholesale",
            "subcategory":"Wine & Distilled Alcoholic Beverages",
            "type":"Manufacturing & Wholesale Goods"
        }
    ],
    "sg:phone":"+1 518 464 1571",
    "sg:postcode":"12205",
    "sg:province":"NY",
    "wof:name":"Seagram Americas",
    "wof:placetype":"venue"
},
  "geometry": {"coordinates":[-73.858853,42.724494],"type":"Point"}
}