{
  "type": "Feature",
  "properties": {
    "iso:country":"US",
    "sg:address":"526 E 187th St",
    "sg:city":"Bronx",
    "sg:classifiers":[
        {
            "category":"Banks & Credit Unions",
            "subcategory":"Bank",
            "type":"Services"
        }
    ],
    "sg:phone":"+1 718 733 2054",
    "sg:postcode":"10458",
    "sg:province":"NY",
    "sg:tags":[
        "machine",
        "teller",
        "automated"
    ],
    "wof:name":"Nam's Atm Bankcard Svc",
    "wof:placetype":"venue"
},
  "geometry": {"coordinates":[-73.890817,40.857336],"type":"Point"}
}