{
  "type": "Feature",
  "properties": {
    "addr:full":"22 Fran Ln Selden NY 11784",
    "addr:housenumber":"22",
    "addr:postcode":"11784",
    "addr:street":"Fran Ln",
    "iso:country":"US",
    "sg:address":"22 Fran Ln",
    "sg:city":"Selden",
    "sg:classifiers":[
        {
            "category":"Professional",
            "subcategory":"Accounting & Tax Preparation",
            "type":"Services"
        }
    ],
    "sg:phone":"+1 631 561 7247",
    "sg:postcode":"11784",
    "sg:province":"NY",
    "sg:tags":[
        "bookkeeping"
    ],
    "wof:name":"D & B Consulting",
    "wof:placetype":"venue"
},
  "geometry": {"coordinates":[-73.05559,40.852573],"type":"Point"}
}