{
  "type": "Feature",
  "properties": {
    "iso:country":"US",
    "sg:address":"147 Utica Ave",
    "sg:city":"Brooklyn",
    "sg:classifiers":[
        {
            "category":"Travel",
            "subcategory":"Travel Agent",
            "type":"Entertainment"
        }
    ],
    "sg:phone":"+1   ",
    "sg:postcode":"11213",
    "sg:province":"NY",
    "sg:tags":[
        "agency"
    ],
    "wof:name":"Acw Travel Enterprises Inc",
    "wof:placetype":"venue"
},
  "geometry": {"coordinates":[-73.9306,40.67357],"type":"Point"}
}