{
  "type": "Feature",
  "properties": {
    "addr:full":"102 E 238th St Bronx NY 10470",
    "addr:housenumber":"102",
    "addr:postcode":"10470",
    "addr:street":"E 238Th St",
    "iso:country":"US",
    "sg:address":"102 E 238th St",
    "sg:city":"Bronx",
    "sg:classifiers":[
        {
            "category":"Building & Trades",
            "subcategory":"Construction",
            "type":"Services"
        }
    ],
    "sg:phone":"+1 718 325 2545",
    "sg:postcode":"10470",
    "sg:province":"NY",
    "sg:tags":[
        "floor",
        "laying",
        "contractor"
    ],
    "wof:name":"Edge Hardwood Flooring",
    "wof:placetype":"venue"
},
  "geometry": {"coordinates":[-73.870997,40.899186],"type":"Point"}
}