{
  "type": "Feature",
  "properties": {
    "addr:full":"75 Broad St New York NY 10004",
    "addr:housenumber":"75",
    "addr:postcode":"10004",
    "addr:street":"Broad St",
    "iso:country":"US",
    "sg:address":"75 Broad St",
    "sg:city":"New York",
    "sg:classifiers":[
        {
            "category":"Utilities",
            "subcategory":"Telephone",
            "type":"Services"
        }
    ],
    "sg:phone":"+1 212 785 9848",
    "sg:postcode":"10004",
    "sg:province":"NY",
    "sg:tags":[
        "telecommunication"
    ],
    "wof:name":"Fusion Telecom",
    "wof:placetype":"venue"
},
  "geometry": {"coordinates":[-74.01164199999999,40.704323],"type":"Point"}
}