{
  "type": "Feature",
  "properties": {
    "addr:full":"254 5th Ave New York NY 10001",
    "addr:housenumber":"254",
    "addr:postcode":"10001",
    "addr:street":"5Th Ave",
    "iso:country":"US",
    "sg:address":"254 5th Ave",
    "sg:city":"New York",
    "sg:classifiers":[
        {
            "category":"Banks & Credit Unions",
            "subcategory":"Financial Services",
            "type":"Services"
        }
    ],
    "sg:phone":"+1 212 684 1006",
    "sg:postcode":"10001",
    "sg:province":"NY",
    "sg:tags":[
        "company",
        "holding"
    ],
    "wof:name":"Karsten America Corp",
    "wof:placetype":"venue"
},
  "geometry": {"coordinates":[-73.987005,40.745168],"type":"Point"}
}