{
  "type": "Feature",
  "properties": {
    "addr:full":"836 Tilden St Bronx NY 10467",
    "addr:housenumber":"836",
    "addr:postcode":"10467",
    "addr:street":"Tilden St",
    "iso:country":"US",
    "sg:address":"836 Tilden St",
    "sg:city":"Bronx",
    "sg:classifiers":[
        {
            "category":"Real Estate",
            "subcategory":"Real Estate Operator",
            "type":"Services"
        },
        {
            "category":"Real Estate",
            "subcategory":"Real Estate Agent",
            "type":"Services"
        }
    ],
    "sg:phone":"+1 718 652 3023",
    "sg:postcode":"10467",
    "sg:province":"NY",
    "sg:tags":[
        "building",
        "apartment"
    ],
    "sg:website":"http://www.surreycoop.com",
    "wof:name":"Surrey Cooperative Apartments Inc",
    "wof:placetype":"venue"
},
  "geometry": {"coordinates":[-73.86094,40.876862],"type":"Point"}
}