{
  "type": "Feature",
  "properties": {
    "addr:full":"787 Rte 35 Cross River NY 10518",
    "addr:housenumber":"787",
    "addr:postcode":"10518",
    "addr:street":"Rte 35",
    "iso:country":"US",
    "sg:address":"787 Rte 35",
    "sg:city":"Cross River",
    "sg:classifiers":[
        {
            "category":"Professional",
            "subcategory":"Lawyer & Legal Services",
            "type":"Services"
        }
    ],
    "sg:phone":"+1 914 763 8831",
    "sg:postcode":"10518",
    "sg:province":"NY",
    "sg:tags":[
        "attorney"
    ],
    "wof:name":"Simon & Simon",
    "wof:placetype":"venue"
},
  "geometry": {"coordinates":[-73.611644,41.263511],"type":"Point"}
}