{
  "type": "Feature",
  "properties": {
    "iso:country":"US",
    "sg:address":"4823 State Hwy 23",
    "sg:city":"Norwich",
    "sg:classifiers":[
        {
            "category":"Food & Beverages",
            "subcategory":"Groceries & Convenience Stores",
            "type":"Retail Goods"
        }
    ],
    "sg:phone":"+1 607 334 8432",
    "sg:postcode":"13815",
    "sg:province":"NY",
    "wof:name":"Nice N Easy",
    "wof:placetype":"venue"
},
  "geometry": {"coordinates":[-75.506676,42.540628],"type":"Point"}
}