{
  "type": "Feature",
  "properties": {
    "addr:full":"562 Commerce St Thornwood NY 10594",
    "addr:housenumber":"562",
    "addr:postcode":"10594",
    "addr:street":"Commerce St",
    "iso:country":"US",
    "sg:address":"562 Commerce St",
    "sg:city":"Thornwood",
    "sg:classifiers":[
        {
            "category":"Professional",
            "subcategory":"Accounting & Tax Preparation",
            "type":"Services"
        }
    ],
    "sg:phone":"+1 914 769 8419",
    "sg:postcode":"10594",
    "sg:province":"NY",
    "sg:tags":[
        "accountant"
    ],
    "wof:name":"Hummel & Butler Cpa's PC",
    "wof:placetype":"venue"
},
  "geometry": {"coordinates":[-73.790199,41.114799],"type":"Point"}
}