{
  "type": "Feature",
  "properties": {
    "addr:full":"7620 Woodside Ave Elmhurst NY 11373",
    "addr:housenumber":"7620",
    "addr:postcode":"11373",
    "addr:street":"Woodside Ave",
    "iso:country":"US",
    "sg:address":"7620 Woodside Ave",
    "sg:city":"Elmhurst",
    "sg:classifiers":[
        {
            "category":"Insurance",
            "subcategory":"Health Insurance",
            "type":"Services"
        }
    ],
    "sg:phone":"+1 718 672 6389",
    "sg:postcode":"11373",
    "sg:province":"NY",
    "sg:tags":[
        "market"
    ],
    "wof:name":"E I Products Corp",
    "wof:placetype":"venue"
},
  "geometry": {"coordinates":[-73.88809999999999,40.743401],"type":"Point"}
}