{
  "type": "Feature",
  "properties": {
    "iso:country":"US",
    "sg:address":"5662 Main St",
    "sg:city":"Williamsville",
    "sg:classifiers":[
        {
            "category":"Professional",
            "subcategory":"Lawyer & Legal Services",
            "type":"Services"
        }
    ],
    "sg:phone":"+1 716 631 0004",
    "sg:postcode":"14221",
    "sg:province":"NY",
    "sg:tags":[
        "attorney"
    ],
    "wof:name":"Sunil Bakshi Attorney At Law",
    "wof:placetype":"venue"
},
  "geometry": {"coordinates":[-78.74212300000001,42.963311],"type":"Point"}
}