{
  "type": "Feature",
  "properties": {
    "addr:full":"175 Main Ave Wynantskill NY 12198",
    "addr:housenumber":"175",
    "addr:postcode":"12198",
    "addr:street":"Main Ave",
    "iso:country":"US",
    "sg:address":"175 Main Ave",
    "sg:city":"Wynantskill",
    "sg:classifiers":[
        {
            "category":"Restaurant",
            "type":"Food & Drink"
        }
    ],
    "sg:phone":"+1 518 283 2138",
    "sg:postcode":"12198",
    "sg:province":"NY",
    "sg:tags":[
        "eating"
    ],
    "wof:name":"Gregory's Restaurant",
    "wof:placetype":"venue"
},
  "geometry": {"coordinates":[-73.638533,42.695359],"type":"Point"}
}