{
  "type": "Feature",
  "properties": {
    "addr:full":"231 W 142nd Street New York NY 10030",
    "addr:housenumber":"231",
    "addr:postcode":"10030",
    "addr:street":"W 142Nd Street",
    "iso:country":"US",
    "sg:address":"231 W 142nd Street",
    "sg:city":"New York",
    "sg:classifiers":[
        {
            "category":"Museum",
            "type":"Entertainment"
        }
    ],
    "sg:phone":"+1 212 234 4926",
    "sg:postcode":"10030",
    "sg:province":"NY",
    "wof:name":"Freedom Journey Foundation",
    "wof:placetype":"venue"
},
  "geometry": {"coordinates":[-73.941908,40.820199],"type":"Point"}
}