{
  "type": "Feature",
  "properties": {
    "addr:full":"1001 Mace Ave Bronx NY 10469",
    "addr:housenumber":"1001",
    "addr:postcode":"10469",
    "addr:street":"Mace Ave",
    "iso:country":"US",
    "sg:address":"1001 Mace Ave",
    "sg:city":"Bronx",
    "sg:classifiers":[
        {
            "category":"Food & Beverages",
            "subcategory":"Groceries & Convenience Stores",
            "type":"Retail Goods"
        }
    ],
    "sg:phone":"+1   ",
    "sg:postcode":"10469",
    "sg:province":"NY",
    "wof:name":"Bocio Superette",
    "wof:placetype":"venue"
},
  "geometry": {"coordinates":[-73.85805999999999,40.863042],"type":"Point"}
}