{
  "type": "Feature",
  "properties": {
    "addr:full":"4704 13th Ave Brooklyn NY 11219",
    "addr:housenumber":"4704",
    "addr:postcode":"11219",
    "addr:street":"13Th Ave",
    "iso:country":"US",
    "sg:address":"4704 13th Ave",
    "sg:city":"Brooklyn",
    "sg:classifiers":[
        {
            "category":"Shopping",
            "subcategory":"Jewelry",
            "type":"Retail Goods"
        }
    ],
    "sg:phone":"+1 718 438 3075",
    "sg:postcode":"11219",
    "sg:province":"NY",
    "sg:tags":[
        "retailer"
    ],
    "sg:website":"www.paradise-jewelry.com",
    "wof:name":"Paradise Jewelry",
    "wof:placetype":"venue"
},
  "geometry": {"coordinates":[-73.991203,40.636101],"type":"Point"}
}