{
  "type": "Feature",
  "properties": {
    "addr:full":"7970 Brewerton Rd Cicero NY 13039",
    "addr:housenumber":"7970",
    "addr:postcode":"13039",
    "addr:street":"Brewerton Rd",
    "iso:country":"US",
    "sg:address":"7970 Brewerton Rd",
    "sg:city":"Cicero",
    "sg:classifiers":[
        {
            "category":"Retail",
            "subcategory":"Auto Repair",
            "type":"Services"
        }
    ],
    "sg:phone":"+1 315 699 6281",
    "sg:postcode":"13039",
    "sg:province":"NY",
    "sg:tags":[
        "automotive"
    ],
    "wof:name":"Valvoline Instant Oil Change",
    "wof:placetype":"venue"
},
  "geometry": {"coordinates":[-76.122821,43.155109],"type":"Point"}
}