{
  "type": "Feature",
  "properties": {
    "iso:country":"US",
    "sg:address":"48 E 3rd St",
    "sg:city":"Mount Vernon",
    "sg:classifiers":[
        {
            "category":"Personal",
            "subcategory":"Beauty Salon",
            "type":"Services"
        }
    ],
    "sg:phone":"+1 914 667 2670",
    "sg:postcode":"10550",
    "sg:province":"NY",
    "sg:tags":[
        "shop"
    ],
    "wof:name":"Star Lite Beauty Shop",
    "wof:placetype":"venue"
},
  "geometry": {"coordinates":[-73.83280499999999,40.907257],"type":"Point"}
}