{
  "type": "Feature",
  "properties": {
    "addr:full":"104 E 31st St New York NY 10016",
    "addr:housenumber":"104",
    "addr:postcode":"10016",
    "addr:street":"E 31St St",
    "iso:country":"US",
    "sg:address":"104 E 31st St",
    "sg:city":"New York",
    "sg:classifiers":[
        {
            "category":"Real Estate",
            "subcategory":"Real Estate Agent",
            "type":"Services"
        }
    ],
    "sg:phone":"+1 212 683 5396",
    "sg:postcode":"10016",
    "sg:province":"NY",
    "wof:name":"Boxer Labs",
    "wof:placetype":"venue"
},
  "geometry": {"coordinates":[-73.98129900000001,40.744518],"type":"Point"}
}