{
  "type": "Feature",
  "properties": {
    "iso:country":"US",
    "sg:address":"14 Walden Glen",
    "sg:city":"Ballston Lake",
    "sg:classifiers":[
        {
            "category":"Building & Trades",
            "subcategory":"Construction",
            "type":"Services"
        }
    ],
    "sg:phone":"+1 518 899 7445",
    "sg:postcode":"12019",
    "sg:province":"NY",
    "sg:tags":[
        "carpentry",
        "contractor"
    ],
    "wof:name":"Fine Woodworking",
    "wof:placetype":"venue"
},
  "geometry": {"coordinates":[-73.81306600000001,42.928155],"type":"Point"}
}