{
  "type": "Feature",
  "properties": {
    "iso:country":"US",
    "sg:address":"70 Boniface Dr",
    "sg:city":"Pine Bush",
    "sg:classifiers":[
        {
            "category":"Personal",
            "subcategory":"Beauty Salon",
            "type":"Services"
        }
    ],
    "sg:phone":"+1 845 744 6899",
    "sg:postcode":"12566",
    "sg:province":"NY",
    "wof:name":"Hair We Are!",
    "wof:placetype":"venue"
},
  "geometry": {"coordinates":[-74.301455,41.602051],"type":"Point"}
}