{
  "type": "Feature",
  "properties": {
    "addr:full":"25 S Main St Cassadaga NY 14718",
    "addr:housenumber":"25",
    "addr:postcode":"14718",
    "addr:street":"S Main St",
    "iso:country":"US",
    "sg:address":"25 S Main St",
    "sg:city":"Cassadaga",
    "sg:classifiers":[
        {
            "category":"Insurance",
            "subcategory":"Insurance Agent",
            "type":"Services"
        }
    ],
    "sg:phone":"+1 716 595 3718",
    "sg:postcode":"14718",
    "sg:province":"NY",
    "wof:name":"Scott Danahy Naylon Co Inc",
    "wof:placetype":"venue"
},
  "geometry": {"coordinates":[-79.309517,42.343468],"type":"Point"}
}