{
  "type": "Feature",
  "properties": {
    "addr:full":"651 Broadway New York NY 10012",
    "addr:housenumber":"651",
    "addr:postcode":"10012",
    "addr:street":"Broadway",
    "iso:country":"US",
    "sg:address":"651 Broadway",
    "sg:city":"New York",
    "sg:classifiers":[
        {
            "category":"Shopping",
            "subcategory":"Optical Goods",
            "type":"Retail Goods"
        }
    ],
    "sg:phone":"+1 212 614 0069",
    "sg:postcode":"10012",
    "sg:province":"NY",
    "sg:tags":[
        "contact",
        "lense",
        "optician",
        "eyewear"
    ],
    "sg:website":"eyesonny.com/",
    "wof:name":"Eyes On Broadway Inc",
    "wof:placetype":"venue"
},
  "geometry": {"coordinates":[-73.995468,40.726973],"type":"Point"}
}