{
  "type": "Feature",
  "properties": {
    "iso:country":"US",
    "sg:address":"633 Jericho Tpke",
    "sg:city":"Syosset",
    "sg:classifiers":[
        {
            "category":"Restaurant",
            "type":"Food & Drink"
        }
    ],
    "sg:menulink":"http://www.allmenus.com/ny/syosset/162662-nathans-famous/menu/",
    "sg:phone":"+1 561 496 0682",
    "sg:postcode":"11791",
    "sg:province":"NY",
    "sg:tags":[
        "american",
        "hot",
        "dog"
    ],
    "wof:name":"Nathan's Famous",
    "wof:placetype":"venue"
},
  "geometry": {"coordinates":[-73.494342,40.811356],"type":"Point"}
}