{
  "type": "Feature",
  "properties": {
    "addr:full":"8247 Saint James Ave Elmhurst NY 11373",
    "addr:housenumber":"8247",
    "addr:postcode":"11373",
    "addr:street":"Saint James Ave",
    "iso:country":"US",
    "sg:address":"8247 Saint James Ave",
    "sg:city":"Elmhurst",
    "sg:classifiers":[
        {
            "category":"Real Estate",
            "subcategory":"Real Estate Operator",
            "type":"Services"
        }
    ],
    "sg:phone":"+1 718 898 3057",
    "sg:postcode":"11373",
    "sg:province":"NY",
    "sg:tags":[
        "apartment"
    ],
    "wof:name":"Eastern Sunshine Inc",
    "wof:placetype":"venue"
},
  "geometry": {"coordinates":[-73.881147,40.738095],"type":"Point"}
}