{
  "type": "Feature",
  "properties": {
    "addr:full":"414 Andrews St Rochester NY 14604",
    "addr:housenumber":"414",
    "addr:postcode":"14604",
    "addr:street":"Andrews St",
    "iso:country":"US",
    "sg:address":"414 Andrews St",
    "sg:city":"Rochester",
    "sg:classifiers":[
        {
            "category":"Government",
            "subcategory":"Office",
            "type":"Public Place"
        }
    ],
    "sg:phone":"+1 585 428 7100",
    "sg:postcode":"14604",
    "sg:province":"NY",
    "sg:tags":[
        "village"
    ],
    "sg:website":"www.cityofrochester.gov",
    "wof:name":"Building Services",
    "wof:placetype":"venue"
},
  "geometry": {"coordinates":[-77.604286,43.160809],"type":"Point"}
}