{
  "type": "Feature",
  "properties": {
    "addr:full":"300 Vanderbilt Avenue Brooklyn NY 11205",
    "addr:housenumber":"300",
    "addr:postcode":"11205",
    "addr:street":"Vanderbilt Avenue",
    "iso:country":"US",
    "sg:address":"300 Vanderbilt Avenue",
    "sg:city":"Brooklyn",
    "sg:classifiers":[
        {
            "category":"Organizations",
            "subcategory":"Religious Organization",
            "type":"Services"
        }
    ],
    "sg:phone":"+1 718 638 7625",
    "sg:postcode":"11205",
    "sg:province":"NY",
    "wof:name":"Queen of All Saints Church",
    "wof:placetype":"venue"
},
  "geometry": {"coordinates":[-73.969168,40.689077],"type":"Point"}
}