{
  "type": "Feature",
  "properties": {
    "addr:full":"60 Virginia Ln Thornwood NY 10594",
    "addr:housenumber":"60",
    "addr:postcode":"10594",
    "addr:street":"Virginia Ln",
    "iso:country":"US",
    "sg:address":"60 Virginia Ln",
    "sg:city":"Thornwood",
    "sg:classifiers":[
        {
            "category":"Wholesale",
            "subcategory":"Durable Goods & Equipment",
            "type":"Manufacturing & Wholesale Goods"
        }
    ],
    "sg:phone":"+1 914 747 3838",
    "sg:postcode":"10594",
    "sg:province":"NY",
    "sg:tags":[
        "importer"
    ],
    "wof:name":"Finds From The Far East",
    "wof:placetype":"venue"
},
  "geometry": {"coordinates":[-73.764399,41.123882],"type":"Point"}
}