{
  "type": "Feature",
  "properties": {
    "addr:full":"5 Chestnut Rd New Hartford NY 13413",
    "addr:housenumber":"5",
    "addr:postcode":"13413",
    "addr:street":"Chestnut Rd",
    "iso:country":"US",
    "sg:address":"5 Chestnut Rd",
    "sg:city":"New Hartford",
    "sg:classifiers":[
        {
            "category":"Insurance",
            "subcategory":"Insurance Agent",
            "type":"Services"
        }
    ],
    "sg:phone":"+1 315 732 0431",
    "sg:postcode":"13413",
    "sg:province":"NY",
    "wof:name":"Paul Shaffer Agency",
    "wof:placetype":"venue"
},
  "geometry": {"coordinates":[-75.271334,43.061742],"type":"Point"}
}