{
  "type": "Feature",
  "properties": {
    "addr:full":"24 Kenmore St Dix Hills NY 11746",
    "addr:housenumber":"24",
    "addr:postcode":"11746",
    "addr:street":"Kenmore St",
    "iso:country":"US",
    "sg:address":"24 Kenmore St",
    "sg:city":"Dix Hills",
    "sg:classifiers":[
        {
            "category":"Professional",
            "subcategory":"Business Services",
            "type":"Services"
        }
    ],
    "sg:phone":"+1 631 667 9169",
    "sg:postcode":"11746",
    "sg:province":"NY",
    "sg:tags":[
        "interior",
        "consultant",
        "design",
        "decorator"
    ],
    "wof:name":"Decorators Choice",
    "wof:placetype":"venue"
},
  "geometry": {"coordinates":[-73.334789,40.775785],"type":"Point"}
}