{
  "type": "Feature",
  "properties": {
    "iso:country":"US",
    "sg:address":"1909 3 Ave",
    "sg:city":"New York",
    "sg:classifiers":[
        {
            "category":"Shopping",
            "subcategory":"Clothing, Apparel, & Fashions",
            "type":"Retail Goods"
        }
    ],
    "sg:phone":"+1 646 672 1477",
    "sg:postcode":"10029",
    "sg:province":"NY",
    "sg:website":"www.rainbowshops.com",
    "wof:name":"5-7-9 Shops",
    "wof:placetype":"venue"
},
  "geometry": {"coordinates":[-73.94882699999999,40.785881],"type":"Point"}
}