{
  "type": "Feature",
  "properties": {
    "iso:country":"US",
    "sg:address":"419 Stevers Mills Rd",
    "sg:city":"Broadalbin",
    "sg:classifiers":[
        {
            "category":"Retail",
            "subcategory":"Repair Shop",
            "type":"Services"
        }
    ],
    "sg:phone":"+1 518 883 8622",
    "sg:postcode":"12025",
    "sg:province":"NY",
    "sg:tags":[
        "machine"
    ],
    "wof:name":"Mach Laurie",
    "wof:placetype":"venue"
},
  "geometry": {"coordinates":[-74.145375,43.065831],"type":"Point"}
}