{
  "type": "Feature",
  "properties": {
    "addr:full":"31 Morton St New York NY 10014",
    "addr:housenumber":"31",
    "addr:postcode":"10014",
    "addr:street":"Morton St",
    "iso:country":"US",
    "sg:address":"31 Morton St",
    "sg:city":"New York",
    "sg:classifiers":[
        {
            "category":"Professional",
            "subcategory":"Lawyer & Legal Services",
            "type":"Services"
        }
    ],
    "sg:phone":"+1 212 929 3124",
    "sg:postcode":"10014",
    "sg:province":"NY",
    "wof:name":"Hyde George W Atty",
    "wof:placetype":"venue"
},
  "geometry": {"coordinates":[-74.854781,40.73107],"type":"Point"}
}