{
  "type": "Feature",
  "properties": {
    "iso:country":"US",
    "sg:address":"70 Gillette Ave",
    "sg:city":"Buffalo",
    "sg:classifiers":[
        {
            "category":"Wholesale",
            "subcategory":"Machinery & Supplies",
            "type":"Manufacturing & Wholesale Goods"
        }
    ],
    "sg:phone":"+1 716 871 1396",
    "sg:postcode":"14214",
    "sg:province":"NY",
    "sg:tags":[
        "equipment",
        "safety",
        "clothing"
    ],
    "wof:name":"National Safety Supply Co",
    "wof:placetype":"venue"
},
  "geometry": {"coordinates":[-78.844031,42.924683],"type":"Point"}
}