{
  "type": "Feature",
  "properties": {
    "iso:country":"US",
    "sg:address":"8709 Turin Rd",
    "sg:city":"Rome",
    "sg:classifiers":[
        {
            "category":"Building & Trades",
            "subcategory":"Construction",
            "type":"Services"
        }
    ],
    "sg:phone":"+1 315 334 4500",
    "sg:postcode":"13440",
    "sg:province":"NY",
    "sg:tags":[
        "contractor"
    ],
    "wof:name":"Glass Doctor of Rome",
    "wof:placetype":"venue"
},
  "geometry": {"coordinates":[-75.470905,43.283926],"type":"Point"}
}