{
  "type": "Feature",
  "properties": {
    "addr:full":"30 Sutton Pl New York NY 10022",
    "addr:housenumber":"30",
    "addr:postcode":"10022",
    "addr:street":"Sutton Pl",
    "iso:country":"US",
    "sg:address":"30 Sutton Pl",
    "sg:city":"New York",
    "sg:classifiers":[
        {
            "category":"Professional",
            "subcategory":"Business Services",
            "type":"Services"
        }
    ],
    "sg:phone":"+1   ",
    "sg:postcode":"10022",
    "sg:province":"NY",
    "wof:name":"David Tracy Associates Inc",
    "wof:placetype":"venue"
},
  "geometry": {"coordinates":[-73.959829,40.758626],"type":"Point"}
}