{
  "type": "Feature",
  "properties": {
    "addr:full":"1764 Empire Blvd Webster NY 14580",
    "addr:housenumber":"1764",
    "addr:postcode":"14580",
    "addr:street":"Empire Blvd",
    "iso:country":"US",
    "sg:address":"1764 Empire Blvd",
    "sg:city":"Webster",
    "sg:classifiers":[
        {
            "category":"Shopping",
            "subcategory":"Computers & Home Electronics",
            "type":"Retail Goods"
        }
    ],
    "sg:phone":"+1 585 671 9710",
    "sg:postcode":"14580",
    "sg:province":"NY",
    "sg:tags":[
        "equipment",
        "dealer"
    ],
    "wof:name":"Blue G Computers",
    "wof:placetype":"venue"
},
  "geometry": {"coordinates":[-77.50620000000001,43.185067],"type":"Point"}
}