{
  "type": "Feature",
  "properties": {
    "iso:country":"US",
    "sg:address":"2156 Tilden Ave",
    "sg:city":"Brooklyn",
    "sg:classifiers":[
        {
            "category":"Organizations",
            "subcategory":"Religious Organization",
            "type":"Services"
        }
    ],
    "sg:phone":"+1 718 284 6201",
    "sg:postcode":"11226",
    "sg:province":"NY",
    "wof:name":"Jesus The True Way",
    "wof:placetype":"venue"
},
  "geometry": {"coordinates":[-73.95728,40.646469],"type":"Point"}
}