{
  "type": "Feature",
  "properties": {
    "addr:full":"162 Alwin Ct Woodmere NY 11598",
    "addr:housenumber":"162",
    "addr:postcode":"11598",
    "addr:street":"Alwin Ct",
    "iso:country":"US",
    "sg:address":"162 Alwin Ct",
    "sg:city":"Woodmere",
    "sg:classifiers":[
        {
            "category":"Insurance",
            "subcategory":"Insurance Agent",
            "type":"Services"
        }
    ],
    "sg:phone":"+1 516 374 8514",
    "sg:postcode":"11598",
    "sg:province":"NY",
    "wof:name":"Serafino Maiorano",
    "wof:placetype":"venue"
},
  "geometry": {"coordinates":[-73.699001,40.628288],"type":"Point"}
}