{
  "type": "Feature",
  "properties": {
    "addr:full":"795 Rogers Ave Brooklyn NY 11226",
    "addr:housenumber":"795",
    "addr:postcode":"11226",
    "addr:street":"Rogers Ave",
    "iso:country":"US",
    "sg:address":"795 Rogers Ave",
    "sg:city":"Brooklyn",
    "sg:classifiers":[
        {
            "category":"Retail",
            "subcategory":"Repair Shop",
            "type":"Services"
        }
    ],
    "sg:phone":"+1   ",
    "sg:postcode":"11226",
    "sg:province":"NY",
    "sg:tags":[
        "hardware",
        "store"
    ],
    "wof:name":"Trevs Locksmith Service",
    "wof:placetype":"venue"
},
  "geometry": {"coordinates":[-73.952404,40.650801],"type":"Point"}
}