{
  "type": "Feature",
  "properties": {
    "iso:country":"US",
    "sg:address":"245 Delaware Ave",
    "sg:city":"Buffalo",
    "sg:classifiers":[
        {
            "category":"Home & Garden",
            "subcategory":"Hardware",
            "type":"Retail Goods"
        }
    ],
    "sg:phone":"+1 716 875 3328",
    "sg:postcode":"14202",
    "sg:province":"NY",
    "wof:name":"Drew's True Value",
    "wof:placetype":"venue"
},
  "geometry": {"coordinates":[-78.87636999999999,42.891593],"type":"Point"}
}