{
  "type": "Feature",
  "properties": {
    "iso:country":"US",
    "sg:address":"180 State St",
    "sg:city":"Brooklyn",
    "sg:classifiers":[
        {
            "category":"Autos & Motor Vehicles",
            "subcategory":"Auto Supplies",
            "type":"Retail Goods"
        },
        {
            "category":"Wholesale",
            "subcategory":"Auto Parts",
            "type":"Manufacturing & Wholesale Goods"
        }
    ],
    "sg:phone":"+1 718 665 1500",
    "sg:postcode":"11201",
    "sg:province":"NY",
    "sg:tags":[
        "wheel",
        "vehicles-supplies",
        "drive",
        "four",
        "equipment",
        "truck"
    ],
    "wof:name":"Atlantic Detroit Diesel Alliso",
    "wof:placetype":"venue"
},
  "geometry": {"coordinates":[-73.992912,40.690567],"type":"Point"}
}