{
  "type": "Feature",
  "properties": {
    "iso:country":"US",
    "sg:address":"62 Garden Dr",
    "sg:city":"Rye",
    "sg:classifiers":[
        {
            "category":"Communications",
            "type":"Services"
        }
    ],
    "sg:phone":"+1   ",
    "sg:postcode":"10580",
    "sg:province":"NY",
    "sg:tags":[
        "communication"
    ],
    "wof:name":"Peter Vandijk Communications L",
    "wof:placetype":"venue"
},
  "geometry": {"coordinates":[-73.687973,40.960048],"type":"Point"}
}