{
  "type": "Feature",
  "properties": {
    "addr:full":"14429 Northern Blvd Flushing NY 11354",
    "addr:housenumber":"14429",
    "addr:postcode":"11354",
    "addr:street":"Northern Blvd",
    "iso:country":"US",
    "sg:address":"14429 Northern Blvd",
    "sg:city":"Flushing",
    "sg:classifiers":[
        {
            "category":"Retail",
            "subcategory":"Portrait Studio",
            "type":"Services"
        },
        {
            "category":"Shopping",
            "subcategory":"Pharmacy",
            "type":"Retail Goods"
        }
    ],
    "sg:phone":"+1 718 886 1515",
    "sg:postcode":"11354",
    "sg:province":"NY",
    "sg:tags":[
        "photography",
        "drugstore",
        "store"
    ],
    "wof:name":"Rite Aid",
    "wof:placetype":"venue"
},
  "geometry": {"coordinates":[-73.82236399999999,40.764956],"type":"Point"}
}