{
  "type": "Feature",
  "properties": {
    "addr:full":"114 E 118th St New York NY 10035",
    "addr:housenumber":"114",
    "addr:postcode":"10035",
    "addr:street":"E 118Th St",
    "iso:country":"US",
    "sg:address":"114 E 118th St",
    "sg:city":"New York",
    "sg:classifiers":[
        {
            "category":"Education",
            "subcategory":"School",
            "type":"Public Place"
        }
    ],
    "sg:phone":"+1 212 369 9708",
    "sg:postcode":"10035",
    "sg:province":"NY",
    "sg:tags":[
        "high",
        "middle",
        "elementary"
    ],
    "wof:name":"St Paul's Schl",
    "wof:placetype":"venue"
},
  "geometry": {"coordinates":[-73.94180299999999,40.800301],"type":"Point"}
}