{
  "type": "Feature",
  "properties": {
    "addr:full":"415 Colonie Ctr Albany NY 12205",
    "addr:housenumber":"415",
    "addr:postcode":"12205",
    "addr:street":"Colonie Ctr",
    "iso:country":"US",
    "sg:address":"415 Colonie Ctr",
    "sg:city":"Albany",
    "sg:classifiers":[
        {
            "category":"Shopping",
            "subcategory":"Hobbies, Toys, & Games",
            "type":"Retail Goods"
        }
    ],
    "sg:phone":"+1 518 489 8535",
    "sg:postcode":"12205",
    "sg:province":"NY",
    "sg:tags":[
        "video",
        "supply"
    ],
    "sg:website":"http://www.gamestop.com/",
    "wof:name":"Gamestop",
    "wof:placetype":"venue"
},
  "geometry": {"coordinates":[-73.81594699999999,42.708577],"type":"Point"}
}