{
  "type": "Feature",
  "properties": {
    "addr:full":"103 Knollwood Rd White Plains NY 10607",
    "addr:housenumber":"103",
    "addr:postcode":"10607",
    "addr:street":"Knollwood Rd",
    "iso:country":"US",
    "sg:address":"103 Knollwood Rd",
    "sg:city":"White Plains",
    "sg:classifiers":[
        {
            "category":"Professional",
            "type":"Services"
        }
    ],
    "sg:phone":"+1 914 684 9154",
    "sg:postcode":"10607",
    "sg:province":"NY",
    "sg:tags":[
        "establishment"
    ],
    "wof:name":"Shopwell Inc",
    "wof:placetype":"venue"
},
  "geometry": {"coordinates":[-73.807073,41.040299],"type":"Point"}
}