{
  "type": "Feature",
  "properties": {
    "addr:full":"293 Wyckoff Ave Brooklyn NY 11237",
    "addr:housenumber":"293",
    "addr:postcode":"11237",
    "addr:street":"Wyckoff Ave",
    "iso:country":"US",
    "sg:address":"293 Wyckoff Ave",
    "sg:city":"Brooklyn",
    "sg:classifiers":[
        {
            "category":"Personal",
            "subcategory":"Beauty Salon",
            "type":"Services"
        }
    ],
    "sg:phone":"+1 718 418 5084",
    "sg:postcode":"11237",
    "sg:province":"NY",
    "wof:name":"Gladys Unisex Beauty Salon",
    "wof:placetype":"venue"
},
  "geometry": {"coordinates":[-73.912908,40.700697],"type":"Point"}
}