{
  "type": "Feature",
  "properties": {
    "addr:full":"203 W Hills Rd Huntington Sta NY 11746",
    "addr:housenumber":"203",
    "addr:postcode":"11746",
    "addr:street":"W Hills Rd",
    "iso:country":"US",
    "sg:address":"203 W Hills Rd",
    "sg:city":"Huntington Sta",
    "sg:classifiers":[
        {
            "category":"Professional",
            "subcategory":"Business Services",
            "type":"Services"
        }
    ],
    "sg:phone":"+1 631 421 4780",
    "sg:postcode":"11746",
    "sg:province":"NY",
    "sg:tags":[
        "interior",
        "consultant",
        "design",
        "decorator"
    ],
    "wof:name":"Interior Dynamics",
    "wof:placetype":"venue"
},
  "geometry": {"coordinates":[-73.42120799999999,40.829905],"type":"Point"}
}