{
  "type": "Feature",
  "properties": {
    "addr:full":"25 W Jefryn Blvd Deer Park NY 11729",
    "addr:housenumber":"25",
    "addr:postcode":"11729",
    "addr:street":"W Jefryn Blvd",
    "iso:country":"US",
    "sg:address":"25 W Jefryn Blvd",
    "sg:city":"Deer Park",
    "sg:classifiers":[
        {
            "category":"Professional",
            "type":"Services"
        }
    ],
    "sg:phone":"+1 631 254 2013",
    "sg:postcode":"11729",
    "sg:province":"NY",
    "sg:tags":[
        "establishment"
    ],
    "wof:name":"Department Of Clean Outs",
    "wof:placetype":"venue"
},
  "geometry": {"coordinates":[-73.301608,40.760518],"type":"Point"}
}