{
  "type": "Feature",
  "properties": {
    "iso:country":"US",
    "sg:address":"5552 E Valley Rd",
    "sg:city":"Alfred Station",
    "sg:classifiers":[
        {
            "category":"Building & Trades",
            "subcategory":"Construction",
            "type":"Services"
        }
    ],
    "sg:phone":"+1 607 587 9508",
    "sg:postcode":"14803",
    "sg:province":"NY",
    "sg:tags":[
        "tile",
        "dealer"
    ],
    "sg:website":"www.mooremerkowitz.com",
    "wof:name":"Moore-Merkowitz Tile LTD",
    "wof:placetype":"venue"
},
  "geometry": {"coordinates":[-77.759489,42.226765],"type":"Point"}
}