{
  "type": "Feature",
  "properties": {
    "addr:full":"572 Dick Rd Depew NY 14043",
    "addr:housenumber":"572",
    "addr:postcode":"14043",
    "addr:street":"Dick Rd",
    "iso:country":"US",
    "sg:address":"572 Dick Rd",
    "sg:city":"Depew",
    "sg:classifiers":[
        {
            "category":"Fast Food",
            "type":"Food & Drink"
        },
        {
            "category":"Restaurant",
            "type":"Food & Drink"
        },
        {
            "category":"Food & Beverages",
            "subcategory":"Groceries & Convenience Stores",
            "type":"Retail Goods"
        }
    ],
    "sg:phone":"+1 716 601 7595",
    "sg:postcode":"14043",
    "sg:province":"NY",
    "sg:tags":[
        "shop",
        "american",
        "sandwich"
    ],
    "sg:website":"http://www.arbys.com",
    "wof:name":"Arby's",
    "wof:placetype":"venue"
},
  "geometry": {"coordinates":[-78.737602,42.918789],"type":"Point"}
}