{
  "type": "Feature",
  "properties": {
    "iso:country":"US",
    "sg:address":"26 Rustic Bridge Rd",
    "sg:city":"Rexford",
    "sg:classifiers":[
        {
            "category":"Building & Trades",
            "subcategory":"Construction",
            "type":"Services"
        }
    ],
    "sg:phone":"+1 518 384 7249",
    "sg:postcode":"12148",
    "sg:province":"NY",
    "sg:tags":[
        "contractor",
        "enclosure",
        "pool",
        "swimming"
    ],
    "wof:name":"De Lano Fence",
    "wof:placetype":"venue"
},
  "geometry": {"coordinates":[-73.892636,42.888379],"type":"Point"}
}