{
  "type": "Feature",
  "properties": {
    "addr:full":"2852 Harlem Rd Cheektowaga NY 14225",
    "addr:housenumber":"2852",
    "addr:postcode":"14225",
    "addr:street":"Harlem Rd",
    "iso:country":"US",
    "sg:address":"2852 Harlem Rd",
    "sg:city":"Cheektowaga",
    "sg:classifiers":[
        {
            "category":"Manufacturing",
            "subcategory":"Signs",
            "type":"Manufacturing & Wholesale Goods"
        }
    ],
    "sg:phone":"+1 716 892 8666",
    "sg:postcode":"14225",
    "sg:province":"NY",
    "sg:website":"www.castlebannersigns.com",
    "wof:name":"Castle Banner & Sign Co",
    "wof:placetype":"venue"
},
  "geometry": {"coordinates":[-78.78434300000001,42.921135],"type":"Point"}
}