{
  "type": "Feature",
  "properties": {
    "addr:full":"1645 Grand Concourse Bronx NY 10452",
    "addr:housenumber":"1645",
    "addr:postcode":"10452",
    "addr:street":"Grand Concourse",
    "iso:country":"US",
    "sg:address":"1645 Grand Concourse",
    "sg:city":"Bronx",
    "sg:classifiers":[
        {
            "category":"Real Estate",
            "subcategory":"Real Estate Operator",
            "type":"Services"
        }
    ],
    "sg:phone":"+1 718 901 1562",
    "sg:postcode":"10452",
    "sg:province":"NY",
    "sg:tags":[
        "building",
        "nonresidential"
    ],
    "wof:name":"Vsh Properties",
    "wof:placetype":"venue"
},
  "geometry": {"coordinates":[-73.91179700000001,40.843837],"type":"Point"}
}