{
  "type": "Feature",
  "properties": {
    "iso:country":"US",
    "sg:address":"610 Salt Rd",
    "sg:city":"Webster",
    "sg:classifiers":[
        {
            "category":"Mining & Drilling",
            "type":"Manufacturing & Wholesale Goods"
        }
    ],
    "sg:phone":"+1 585 265 3260",
    "sg:postcode":"14580",
    "sg:province":"NY",
    "sg:tags":[
        "rigger"
    ],
    "wof:name":"Boulter Rigging Corp",
    "wof:placetype":"venue"
},
  "geometry": {"coordinates":[-77.400409,43.240246],"type":"Point"}
}