{
  "type": "Feature",
  "properties": {
    "addr:full":"4641 S Gravel Rd Medina NY 14103",
    "addr:housenumber":"4641",
    "addr:postcode":"14103",
    "addr:street":"S Gravel Rd",
    "iso:country":"US",
    "sg:address":"4641 S Gravel Rd",
    "sg:city":"Medina",
    "sg:classifiers":[
        {
            "category":"Retail",
            "subcategory":"Auto Repair",
            "type":"Services"
        }
    ],
    "sg:phone":"+1 585 798 3771",
    "sg:postcode":"14103",
    "sg:province":"NY",
    "sg:tags":[
        "repairing",
        "automobile"
    ],
    "wof:name":"Radiators Plus",
    "wof:placetype":"venue"
},
  "geometry": {"coordinates":[-78.392492,43.187754],"type":"Point"}
}