{
  "type": "Feature",
  "properties": {
    "addr:full":"292 5th Ave Frnt New York NY 10001",
    "addr:housenumber":"292",
    "addr:postcode":"10001",
    "addr:street":"5Th Ave",
    "iso:country":"US",
    "sg:address":"292 5th Ave Frnt",
    "sg:city":"New York",
    "sg:classifiers":[
        {
            "category":"Professional",
            "subcategory":"Lawyer & Legal Services",
            "type":"Services"
        }
    ],
    "sg:phone":"+1 212 714 3540",
    "sg:postcode":"10001",
    "sg:province":"NY",
    "sg:website":"www.robertsongroup.com",
    "wof:name":"Robertson Group the",
    "wof:placetype":"venue"
},
  "geometry": {"coordinates":[-73.986099,40.7463],"type":"Point"}
}