{
  "type": "Feature",
  "properties": {
    "addr:full":"2648 Ransomville Rd Ransomville NY 14131",
    "addr:housenumber":"2648",
    "addr:postcode":"14131",
    "addr:street":"Ransomville Rd",
    "iso:country":"US",
    "sg:address":"2648 Ransomville Rd",
    "sg:city":"Ransomville",
    "sg:classifiers":[
        {
            "category":"Industrial Area",
            "type":"Public Place"
        }
    ],
    "sg:phone":"+1 716 791 3559",
    "sg:postcode":"14131",
    "sg:province":"NY",
    "sg:tags":[
        "development"
    ],
    "sg:website":"http://www.sycore.com",
    "wof:name":"Sycore Inc",
    "wof:placetype":"venue"
},
  "geometry": {"coordinates":[-78.909813,43.289767],"type":"Point"}
}