{
  "type": "Feature",
  "properties": {
    "addr:full":"79 Havermill Rd New City NY 10956",
    "addr:housenumber":"79",
    "addr:postcode":"10956",
    "addr:street":"Havermill Rd",
    "iso:country":"US",
    "sg:address":"79 Havermill Rd",
    "sg:city":"New City",
    "sg:classifiers":[
        {
            "category":"Professional",
            "subcategory":"Business Services",
            "type":"Services"
        }
    ],
    "sg:phone":"+1 845 634 2670",
    "sg:postcode":"10956",
    "sg:province":"NY",
    "sg:tags":[
        "broker"
    ],
    "wof:name":"Paragon Group Inc",
    "wof:placetype":"venue"
},
  "geometry": {"coordinates":[-74.00197199999999,41.139966],"type":"Point"}
}