{
  "type": "Feature",
  "properties": {
    "iso:country":"US",
    "sg:address":"3240 3rd Ave",
    "sg:city":"Bronx",
    "sg:classifiers":[
        {
            "category":"Restaurant",
            "type":"Food & Drink"
        }
    ],
    "sg:menulink":"http://www.allmenus.com/ny/bronx/59332-cestras-pizza/menu/",
    "sg:phone":"+1 718 292 3100",
    "sg:postcode":"10451",
    "sg:province":"NY",
    "sg:tags":[
        "italian"
    ],
    "wof:name":"Cestra's Pizza",
    "wof:placetype":"venue"
},
  "geometry": {"coordinates":[-73.908796,40.823904],"type":"Point"}
}