{
  "type": "Feature",
  "properties": {
    "addr:full":"3662 Nostrand Ave Brooklyn NY 11229",
    "addr:housenumber":"3662",
    "addr:postcode":"11229",
    "addr:street":"Nostrand Ave",
    "iso:country":"US",
    "sg:address":"3662 Nostrand Ave",
    "sg:city":"Brooklyn",
    "sg:classifiers":[
        {
            "category":"Food & Beverages",
            "subcategory":"Candy",
            "type":"Retail Goods"
        }
    ],
    "sg:phone":"+1 718 769 8425",
    "sg:postcode":"11229",
    "sg:province":"NY",
    "sg:tags":[
        "confectionery",
        "store"
    ],
    "wof:name":"Candy Plus Inc",
    "wof:placetype":"venue"
},
  "geometry": {"coordinates":[-73.941002,40.5952],"type":"Point"}
}