{
  "type": "Feature",
  "properties": {
    "iso:country":"US",
    "sg:address":"2616 Rte 112",
    "sg:city":"Medford",
    "sg:classifiers":[
        {
            "category":"Home & Garden",
            "subcategory":"Furniture",
            "type":"Retail Goods"
        }
    ],
    "sg:phone":"+1 631 475 0511",
    "sg:postcode":"11763",
    "sg:province":"NY",
    "sg:tags":[
        "equipment",
        "kitchen",
        "cabinet"
    ],
    "wof:name":"Kitchen Mart Inc",
    "wof:placetype":"venue"
},
  "geometry": {"coordinates":[-72.997811,40.821751],"type":"Point"}
}