{
  "type": "Feature",
  "properties": {
    "addr:full":"228 Roosevelt Dr Utica NY 13502",
    "addr:housenumber":"228",
    "addr:postcode":"13502",
    "addr:street":"Roosevelt Dr",
    "iso:country":"US",
    "sg:address":"228 Roosevelt Dr",
    "sg:city":"Utica",
    "sg:classifiers":[
        {
            "category":"Manufacturing",
            "subcategory":"Food",
            "type":"Manufacturing & Wholesale Goods"
        },
        {
            "category":"Wholesale",
            "subcategory":"Groceries",
            "type":"Manufacturing & Wholesale Goods"
        }
    ],
    "sg:phone":"+1 315 797 6835",
    "sg:postcode":"13502",
    "sg:province":"NY",
    "sg:tags":[
        "pasta",
        "eating",
        "mfg"
    ],
    "wof:name":"Maria's Pasta Shop",
    "wof:placetype":"venue"
},
  "geometry": {"coordinates":[-75.277557,43.083129],"type":"Point"}
}