{
  "type": "Feature",
  "properties": {
    "addr:full":"29 Mortimer Pl Eastport NY 11941",
    "addr:housenumber":"29",
    "addr:postcode":"11941",
    "addr:street":"Mortimer Pl",
    "iso:country":"US",
    "sg:address":"29 Mortimer Pl",
    "sg:city":"Eastport",
    "sg:classifiers":[
        {
            "category":"Building & Trades",
            "subcategory":"Construction",
            "type":"Services"
        }
    ],
    "sg:phone":"+1 631 325 9062",
    "sg:postcode":"11941",
    "sg:province":"NY",
    "sg:tags":[
        "contractor"
    ],
    "wof:name":"Minho Constr Inc",
    "wof:placetype":"venue"
},
  "geometry": {"coordinates":[-72.737999,40.823898],"type":"Point"}
}