{
  "type": "Feature",
  "properties": {
    "addr:full":"7563 3rd Avenue Brooklyn NY 11209",
    "addr:housenumber":"7563",
    "addr:postcode":"11209",
    "addr:street":"3Rd Avenue",
    "iso:country":"US",
    "sg:address":"7563 3rd Avenue",
    "sg:city":"Brooklyn",
    "sg:classifiers":[
        {
            "category":"Shopping",
            "subcategory":"Pets & Pet Supplies",
            "type":"Retail Goods"
        }
    ],
    "sg:phone":"+1 718 788 7970",
    "sg:postcode":"11209",
    "sg:province":"NY",
    "sg:tags":[
        "store"
    ],
    "wof:name":"Dog Delight",
    "wof:placetype":"venue"
},
  "geometry": {"coordinates":[-74.02790899999999,40.630806],"type":"Point"}
}