{
  "type": "Feature",
  "properties": {
    "addr:full":"4223 Bell Blvd Bayside NY 11361",
    "addr:housenumber":"4223",
    "addr:postcode":"11361",
    "addr:street":"Bell Blvd",
    "iso:country":"US",
    "sg:address":"4223 Bell Blvd",
    "sg:city":"Bayside",
    "sg:classifiers":[
        {
            "category":"Restaurant",
            "type":"Food & Drink"
        }
    ],
    "sg:menulink":"http://www.allmenus.com/ny/queens/107849-bellissima-pizza--restaurant/menu/",
    "sg:phone":"+1 718 229 2418",
    "sg:postcode":"11361",
    "sg:province":"NY",
    "sg:tags":[
        "italian"
    ],
    "wof:name":"Bellissima Pizza & Restaurant",
    "wof:placetype":"venue"
},
  "geometry": {"coordinates":[-73.770398,40.762413],"type":"Point"}
}