{
  "type": "Feature",
  "properties": {
    "addr:full":"15 N Mabbettsville Rd Millbrook NY 12545",
    "addr:housenumber":"15",
    "addr:postcode":"12545",
    "addr:street":"N Mabbettsville Rd",
    "iso:country":"US",
    "sg:address":"15 N Mabbettsville Rd",
    "sg:city":"Millbrook",
    "sg:classifiers":[
        {
            "category":"Farming",
            "subcategory":"Farm",
            "type":"Manufacturing & Wholesale Goods"
        }
    ],
    "sg:phone":"+1 845 677 6065",
    "sg:postcode":"12545",
    "sg:province":"NY",
    "wof:name":"Yellowframe Farm Guest House",
    "wof:placetype":"venue"
},
  "geometry": {"coordinates":[-73.661683,41.8004],"type":"Point"}
}