{
  "type": "Feature",
  "properties": {
    "iso:country":"US",
    "sg:address":"52 Maple St",
    "sg:city":"Yonkers",
    "sg:classifiers":[
        {
            "category":"Professional",
            "type":"Services"
        }
    ],
    "sg:phone":"+1   ",
    "sg:postcode":"10701",
    "sg:province":"NY",
    "wof:name":"Salem Maqattash",
    "wof:placetype":"venue"
},
  "geometry": {"coordinates":[-73.891741,40.932267],"type":"Point"}
}