{
  "type": "Feature",
  "properties": {
    "addr:full":"2056 Cook Rd Ballston Lake NY 12019",
    "addr:housenumber":"2056",
    "addr:postcode":"12019",
    "addr:street":"Cook Rd",
    "iso:country":"US",
    "sg:address":"2056 Cook Rd",
    "sg:city":"Ballston Lake",
    "sg:classifiers":[
        {
            "category":"Shopping",
            "subcategory":"Used Merchandise",
            "type":"Retail Goods"
        }
    ],
    "sg:phone":"+1   ",
    "sg:postcode":"12019",
    "sg:province":"NY",
    "wof:name":"Kevin Oaks",
    "wof:placetype":"venue"
},
  "geometry": {"coordinates":[-73.988394,42.958746],"type":"Point"}
}