{
  "type": "Feature",
  "properties": {
    "addr:full":"631 Montauk Hwy Bay Shore NY 11706",
    "addr:housenumber":"631",
    "addr:postcode":"11706",
    "addr:street":"Montauk Hwy",
    "iso:country":"US",
    "sg:address":"631 Montauk Hwy",
    "sg:city":"Bay Shore",
    "sg:classifiers":[
        {
            "category":"Personal",
            "subcategory":"Beauty Salon",
            "type":"Services"
        }
    ],
    "sg:phone":"+1 631 665 7750",
    "sg:postcode":"11706",
    "sg:province":"NY",
    "sg:tags":[
        "shop"
    ],
    "wof:name":"Design Masters",
    "wof:placetype":"venue"
},
  "geometry": {"coordinates":[-73.26207700000001,40.708898],"type":"Point"}
}