{
  "type": "Feature",
  "properties": {
    "addr:full":"20 N Broadway Ave Nyack NY 10960",
    "addr:housenumber":"20",
    "addr:postcode":"10960",
    "addr:street":"N Broadway Ave",
    "iso:country":"US",
    "sg:address":"20 N Broadway Ave",
    "sg:city":"Nyack",
    "sg:classifiers":[
        {
            "category":"Health Services",
            "subcategory":"Health Practitioner",
            "type":"Services"
        }
    ],
    "sg:phone":"+1 845 353 6497",
    "sg:postcode":"10960",
    "sg:province":"NY",
    "sg:tags":[
        "psychologist"
    ],
    "wof:name":"Rita Lieberman PHD",
    "wof:placetype":"venue"
},
  "geometry": {"coordinates":[-73.91814100000001,41.091648],"type":"Point"}
}