{
  "type": "Feature",
  "properties": {
    "iso:country":"US",
    "sg:address":"96 Main St",
    "sg:city":"Stamford",
    "sg:classifiers":[
        {
            "category":"Organizations",
            "subcategory":"Religious Organization",
            "type":"Services"
        }
    ],
    "sg:phone":"+1 607 652 7242",
    "sg:postcode":"12167",
    "sg:province":"NY",
    "sg:tags":[
        "church"
    ],
    "wof:name":"First Presbyterian Church",
    "wof:placetype":"venue"
},
  "geometry": {"coordinates":[-74.619738,42.410205],"type":"Point"}
}