{
  "type": "Feature",
  "properties": {
    "addr:full":"1091 Fulton St Brooklyn NY 11238",
    "addr:housenumber":"1091",
    "addr:postcode":"11238",
    "addr:street":"Fulton St",
    "iso:country":"US",
    "sg:address":"1091 Fulton St",
    "sg:city":"Brooklyn",
    "sg:classifiers":[
        {
            "category":"Organizations",
            "subcategory":"Religious Organization",
            "type":"Services"
        }
    ],
    "sg:phone":"+1 718 928 7352",
    "sg:postcode":"11238",
    "sg:province":"NY",
    "wof:name":"Universal Church",
    "wof:placetype":"venue"
},
  "geometry": {"coordinates":[-73.95805900000001,40.681784],"type":"Point"}
}