{
  "type": "Feature",
  "properties": {
    "addr:full":"23 Bay Dr W Huntington NY 11743",
    "addr:housenumber":"23",
    "addr:postcode":"11743",
    "addr:street":"Bay Dr W",
    "iso:country":"US",
    "sg:address":"23 Bay Dr W",
    "sg:city":"Huntington",
    "sg:classifiers":[
        {
            "category":"Professional",
            "subcategory":"Research",
            "type":"Services"
        }
    ],
    "sg:phone":"+1   ",
    "sg:postcode":"11743",
    "sg:province":"NY",
    "sg:tags":[
        "nonphysical",
        "consulting",
        "management",
        "commercial",
        "s"
    ],
    "wof:name":"Bison Business Consultants",
    "wof:placetype":"venue"
},
  "geometry": {"coordinates":[-73.40506600000001,40.902606],"type":"Point"}
}