{
  "type": "Feature",
  "properties": {
    "iso:country":"US",
    "sg:address":"7118 Fort Hamilton Pkwy",
    "sg:city":"Brooklyn",
    "sg:classifiers":[
        {
            "category":"Professional",
            "subcategory":"Computer Services",
            "type":"Services"
        }
    ],
    "sg:phone":"+1   ",
    "sg:postcode":"11228",
    "sg:province":"NY",
    "sg:tags":[
        "related"
    ],
    "wof:name":"Technobabble Inc",
    "wof:placetype":"venue"
},
  "geometry": {"coordinates":[-74.014235,40.627391],"type":"Point"}
}