{
  "type": "Feature",
  "properties": {
    "addr:full":"176 7 Ave S New York NY 10014",
    "addr:housenumber":"176",
    "addr:postcode":"10014",
    "addr:street":"7 Ave S",
    "iso:country":"US",
    "sg:address":"176 7 Ave S",
    "sg:city":"New York",
    "sg:classifiers":[
        {
            "category":"Restaurant",
            "type":"Food & Drink"
        }
    ],
    "sg:phone":"+1   ",
    "sg:postcode":"10014",
    "sg:province":"NY",
    "sg:tags":[
        "shop",
        "pizza"
    ],
    "wof:name":"Rivoli Pizza Inc",
    "wof:placetype":"venue"
},
  "geometry": {"coordinates":[-74.005095,40.738088],"type":"Point"}
}