{
  "type": "Feature",
  "properties": {
    "addr:full":"55 Main St Brewster NY 10509",
    "addr:housenumber":"55",
    "addr:postcode":"10509",
    "addr:street":"Main St",
    "iso:country":"US",
    "sg:address":"55 Main St",
    "sg:city":"Brewster",
    "sg:classifiers":[
        {
            "category":"Recreation",
            "type":"Entertainment"
        }
    ],
    "sg:phone":"+1 845 279 9878",
    "sg:postcode":"10509",
    "sg:province":"NY",
    "sg:tags":[
        "parlor",
        "billiard",
        "hall",
        "pool"
    ],
    "wof:name":"Jack & Jill Q Lounge",
    "wof:placetype":"venue"
},
  "geometry": {"coordinates":[-73.617699,41.394501],"type":"Point"}
}