{
  "type": "Feature",
  "properties": {
    "addr:full":"2914 Kinloch Rd Wantagh NY 11793",
    "addr:housenumber":"2914",
    "addr:postcode":"11793",
    "addr:street":"Kinloch Rd",
    "iso:country":"US",
    "sg:address":"2914 Kinloch Rd",
    "sg:city":"Wantagh",
    "sg:classifiers":[
        {
            "category":"Retail",
            "subcategory":"Car Wash",
            "type":"Services"
        }
    ],
    "sg:phone":"+1 516 409 2037",
    "sg:postcode":"11793",
    "sg:province":"NY",
    "wof:name":"Hjn Steel Detailing Inc",
    "wof:placetype":"venue"
},
  "geometry": {"coordinates":[-73.527664,40.69836],"type":"Point"}
}