{
  "type": "Feature",
  "properties": {
    "addr:full":"519 Broadway New York NY 10012",
    "addr:housenumber":"519",
    "addr:postcode":"10012",
    "addr:street":"Broadway",
    "iso:country":"US",
    "sg:address":"519 Broadway",
    "sg:city":"New York",
    "sg:classifiers":[
        {
            "category":"Wholesale",
            "subcategory":"Apparel",
            "type":"Manufacturing & Wholesale Goods"
        }
    ],
    "sg:phone":"+1 718 388 5518",
    "sg:postcode":"10012",
    "sg:province":"NY",
    "sg:tags":[
        "button"
    ],
    "wof:name":"K Button Co",
    "wof:placetype":"venue"
},
  "geometry": {"coordinates":[-73.999498,40.722091],"type":"Point"}
}