{
  "type": "Feature",
  "properties": {
    "iso:country":"US",
    "sg:address":"283 Flatbush Ave",
    "sg:city":"Brooklyn",
    "sg:classifiers":[
        {
            "category":"Personal",
            "subcategory":"Beauty Salon",
            "type":"Services"
        }
    ],
    "sg:phone":"+1 718 636 7357",
    "sg:postcode":"11217",
    "sg:province":"NY",
    "wof:name":"Komara",
    "wof:placetype":"venue"
},
  "geometry": {"coordinates":[-73.973626,40.679004],"type":"Point"}
}