{
  "type": "Feature",
  "properties": {
    "iso:country":"US",
    "sg:address":"126 S Emerson Ave",
    "sg:city":"Montauk",
    "sg:classifiers":[
        {
            "category":"Cafe",
            "type":"Food & Drink"
        },
        {
            "category":"Restaurant",
            "type":"Food & Drink"
        }
    ],
    "sg:menulink":"http://www.allmenus.com/ny/east-hampton/272082-john-papas-cafe/menu/",
    "sg:phone":"+1 631 668 1511",
    "sg:postcode":"11954",
    "sg:province":"NY",
    "sg:tags":[
        "american"
    ],
    "wof:name":"John Papas Cafe",
    "wof:placetype":"venue"
},
  "geometry": {"coordinates":[-71.94296799999999,41.032878],"type":"Point"}
}