{
  "type": "Feature",
  "properties": {
    "iso:country":"US",
    "sg:address":"1435A Webster Ave",
    "sg:city":"Bronx",
    "sg:classifiers":[
        {
            "category":"Restaurant",
            "type":"Food & Drink"
        },
        {
            "category":"Food & Beverages",
            "subcategory":"Ethnic Foods",
            "type":"Retail Goods"
        }
    ],
    "sg:phone":"+1 718 588 0495",
    "sg:postcode":"10456",
    "sg:province":"NY",
    "sg:tags":[
        "caribbean",
        "soul"
    ],
    "wof:name":"Tree Of Life Caribbean Soul Food Restaurant",
    "wof:placetype":"venue"
},
  "geometry": {"coordinates":[-73.90713700000001,40.837125],"type":"Point"}
}