{
  "type": "Feature",
  "properties": {
    "addr:full":"17 Eastern Parkway Brooklyn NY 11238",
    "addr:housenumber":"17",
    "addr:postcode":"11238",
    "addr:street":"Eastern Parkway",
    "iso:country":"US",
    "sg:address":"17 Eastern Parkway",
    "sg:city":"Brooklyn",
    "sg:classifiers":[
        {
            "category":"Place Of Worship",
            "subcategory":"Synagogue",
            "type":"Public Place"
        }
    ],
    "sg:phone":"+1 718 638 7600",
    "sg:postcode":"11238",
    "sg:province":"NY",
    "wof:name":"Union Temple",
    "wof:placetype":"venue"
},
  "geometry": {"coordinates":[-73.96787500000001,40.67319],"type":"Point"}
}