{
  "type": "Feature",
  "properties": {
    "iso:country":"US",
    "sg:address":"333 W 57 St",
    "sg:city":"New York",
    "sg:classifiers":[
        {
            "category":"Professional",
            "subcategory":"Advertising",
            "type":"Services"
        }
    ],
    "sg:phone":"+1 212 586 0418",
    "sg:postcode":"10019",
    "sg:province":"NY",
    "sg:tags":[
        "counselor"
    ],
    "wof:name":"Lee Brandywyne",
    "wof:placetype":"venue"
},
  "geometry": {"coordinates":[-73.98559,40.767933],"type":"Point"}
}