{
  "type": "Feature",
  "properties": {
    "iso:country":"US",
    "sg:address":"1401 5th Ave",
    "sg:city":"Troy",
    "sg:classifiers":[
        {
            "category":"Wholesale",
            "subcategory":"Machinery & Supplies",
            "type":"Manufacturing & Wholesale Goods"
        },
        {
            "category":"Manufacturing",
            "subcategory":"Paper Products",
            "type":"Manufacturing & Wholesale Goods"
        }
    ],
    "sg:phone":"+1 518 274 4061",
    "sg:postcode":"12180",
    "sg:province":"NY",
    "sg:tags":[
        "industrial",
        "container",
        "cup",
        "personal",
        "plastic",
        "janitorial"
    ],
    "wof:name":"Lusco Paper Co Inc",
    "wof:placetype":"venue"
},
  "geometry": {"coordinates":[-73.688568,42.727388],"type":"Point"}
}