{
  "type": "Feature",
  "properties": {
    "iso:country":"US",
    "sg:address":"684 Utica Ave",
    "sg:city":"Brooklyn",
    "sg:classifiers":[
        {
            "category":"Professional",
            "type":"Services"
        }
    ],
    "sg:phone":"+1 718 773 8540",
    "sg:postcode":"11203",
    "sg:province":"NY",
    "wof:name":"Trotta Service Ctr",
    "wof:placetype":"venue"
},
  "geometry": {"coordinates":[-73.931106,40.658185],"type":"Point"}
}