{
  "type": "Feature",
  "properties": {
    "iso:country":"US",
    "sg:address":"3301 Pearl St",
    "sg:city":"Endicott",
    "sg:classifiers":[
        {
            "category":"Building & Trades",
            "subcategory":"Construction",
            "type":"Services"
        }
    ],
    "sg:phone":"+1 607 785 6205",
    "sg:postcode":"13760",
    "sg:province":"NY",
    "sg:tags":[
        "hanging",
        "contractor"
    ],
    "wof:name":"HI Low Painting",
    "wof:placetype":"venue"
},
  "geometry": {"coordinates":[-76.02001199999999,42.1076],"type":"Point"}
}