{
  "type": "Feature",
  "properties": {
    "iso:country":"US",
    "sg:address":"1 Germaine St",
    "sg:city":"Glen Cove",
    "sg:classifiers":[
        {
            "category":"Health Services",
            "subcategory":"Nursing And Care Facility",
            "type":"Services"
        }
    ],
    "sg:phone":"+1   ",
    "sg:postcode":"11542",
    "sg:province":"NY",
    "wof:name":"Total Care LLC",
    "wof:placetype":"venue"
},
  "geometry": {"coordinates":[-73.65101199999999,40.863268],"type":"Point"}
}