{
  "type": "Feature",
  "properties": {
    "addr:full":"7208 Transit Rd Buffalo NY 14221",
    "addr:housenumber":"7208",
    "addr:postcode":"14221",
    "addr:street":"Transit Rd",
    "iso:country":"US",
    "sg:address":"7208 Transit Rd",
    "sg:city":"Buffalo",
    "sg:phone":"+1 716 634 8000",
    "sg:postcode":"14221",
    "sg:province":"NY",
    "sg:website":"http://www.transitownedodge.com",
    "wof:name":"Transitowne Dodge Of Williamsville",
    "wof:placetype":"venue"
},
  "geometry": {"coordinates":[-78.69688499999999,42.963028],"type":"Point"}
}