{
  "type": "Feature",
  "properties": {
    "iso:country":"US",
    "sg:address":"28 Campion Rd",
    "sg:city":"New Hartford",
    "sg:classifiers":[
        {
            "category":"Health Services",
            "subcategory":"Medical Lab",
            "type":"Services"
        }
    ],
    "sg:phone":"+1 315 797 0791",
    "sg:postcode":"13413",
    "sg:province":"NY",
    "sg:tags":[
        "laboratory",
        "clinical"
    ],
    "sg:website":"www.centrexlabs.com",
    "wof:name":"Centrex Clinical Laboratories",
    "wof:placetype":"venue"
},
  "geometry": {"coordinates":[-75.288673,43.075001],"type":"Point"}
}