{
  "type": "Feature",
  "properties": {
    "iso:country":"US",
    "sg:address":"500 Bloomfield Ave",
    "sg:city":"Verona",
    "sg:classifiers":[
        {
            "category":"Professional",
            "subcategory":"Computer Services",
            "type":"Services"
        }
    ],
    "sg:phone":"+1 718 344 5371",
    "sg:postcode":"07044",
    "sg:province":"NY",
    "sg:tags":[
        "edyech",
        "online-learning",
        "virtual-labs",
        "elearning",
        "distance-learning",
        "hybrid-learning"
    ],
    "sg:website":"http://www.latenitelabs.com",
    "wof:name":"Late Nite Labs",
    "wof:placetype":"venue"
},
  "geometry": {"coordinates":[-74.246776,40.832222],"type":"Point"}
}