{
  "type": "Feature",
  "properties": {
    "iso:country":"US",
    "sg:address":"140 W 23rd St",
    "sg:city":"New York",
    "sg:classifiers":[
        {
            "category":"Manufacturing",
            "subcategory":"Apparel",
            "type":"Manufacturing & Wholesale Goods"
        }
    ],
    "sg:phone":"+1   ",
    "sg:postcode":"10011",
    "sg:province":"NY",
    "sg:tags":[
        "sportswear"
    ],
    "wof:name":"Aoyama Itchome",
    "wof:placetype":"venue"
},
  "geometry": {"coordinates":[-73.994803,40.743544],"type":"Point"}
}