{
  "type": "Feature",
  "properties": {
    "iso:country":"US",
    "sg:address":"5214 13th Ave",
    "sg:city":"Brooklyn",
    "sg:classifiers":[
        {
            "category":"Food & Beverages",
            "subcategory":"Dairy",
            "type":"Retail Goods"
        }
    ],
    "sg:phone":"+1 718 633 1600",
    "sg:postcode":"11219",
    "sg:province":"NY",
    "sg:tags":[
        "cheese"
    ],
    "wof:name":"Its Cheese",
    "wof:placetype":"venue"
},
  "geometry": {"coordinates":[-73.994446,40.632912],"type":"Point"}
}