{
  "type": "Feature",
  "properties": {
    "iso:country":"US",
    "sg:address":"47 Shore Rd",
    "sg:city":"Port Washington",
    "sg:classifiers":[
        {
            "category":"Restaurant",
            "type":"Food & Drink"
        }
    ],
    "sg:phone":"+1   ",
    "sg:postcode":"11050",
    "sg:province":"NY",
    "sg:tags":[
        "eating"
    ],
    "wof:name":"LA Piccola Liguria Restaurant",
    "wof:placetype":"venue"
},
  "geometry": {"coordinates":[-73.70336399999999,40.838137],"type":"Point"}
}