{
  "type": "Feature",
  "properties": {
    "addr:full":"111 Craigville Rd Goshen NY 10924",
    "addr:housenumber":"111",
    "addr:postcode":"10924",
    "addr:street":"Craigville Rd",
    "iso:country":"US",
    "sg:address":"111 Craigville Rd",
    "sg:city":"Goshen",
    "sg:classifiers":[
        {
            "category":"Organizations",
            "subcategory":"Membership Organization",
            "type":"Services"
        }
    ],
    "sg:phone":"+1 845 291 3150",
    "sg:postcode":"10924",
    "sg:province":"NY",
    "sg:tags":[
        "military",
        "veteran"
    ],
    "wof:name":"Orange County Veterans Service Agency",
    "wof:placetype":"venue"
},
  "geometry": {"coordinates":[-74.298129,41.398954],"type":"Point"}
}