{
  "type": "Feature",
  "properties": {
    "addr:full":"203 Lee Ave Brooklyn NY 11206",
    "addr:housenumber":"203",
    "addr:postcode":"11206",
    "addr:street":"Lee Ave",
    "iso:country":"US",
    "sg:address":"203 Lee Ave",
    "sg:city":"Brooklyn",
    "sg:classifiers":[
        {
            "category":"Professional",
            "subcategory":"Testing Lab",
            "type":"Services"
        }
    ],
    "sg:phone":"+1   ",
    "sg:postcode":"11206",
    "sg:province":"NY",
    "sg:tags":[
        "laboratory"
    ],
    "wof:name":"Shatnes Lab Of Mizvoth Inc",
    "wof:placetype":"venue"
},
  "geometry": {"coordinates":[-73.95508700000001,40.701492],"type":"Point"}
}