{
  "type": "Feature",
  "properties": {
    "addr:full":"13619 37th Ave Flushing NY 11354",
    "addr:housenumber":"13619",
    "addr:postcode":"11354",
    "addr:street":"37Th Ave",
    "iso:country":"US",
    "sg:address":"13619 37th Ave",
    "sg:city":"Flushing",
    "sg:classifiers":[
        {
            "category":"Personal",
            "subcategory":"Beauty Salon",
            "type":"Services"
        }
    ],
    "sg:phone":"+1 718 353 3893",
    "sg:postcode":"11354",
    "sg:province":"NY",
    "sg:tags":[
        "hair"
    ],
    "wof:name":"Ny Beauty Salon Incorporated",
    "wof:placetype":"venue"
},
  "geometry": {"coordinates":[-73.8306,40.7618],"type":"Point"}
}