{
  "type": "Feature",
  "properties": {
    "addr:full":"11651 128th Street South Ozone Park NY 11420",
    "addr:housenumber":"11651",
    "addr:postcode":"11420",
    "addr:street":"128Th Street",
    "iso:country":"US",
    "sg:address":"11651 128th Street",
    "sg:city":"South Ozone Park",
    "sg:classifiers":[
        {
            "category":"Retail",
            "subcategory":"Auto Repair",
            "type":"Services"
        }
    ],
    "sg:phone":"+1 718 925 2168",
    "sg:postcode":"11420",
    "sg:province":"NY",
    "wof:name":"Dr Auto Repair & Body Shop",
    "wof:placetype":"venue"
},
  "geometry": {"coordinates":[-73.809928,40.675941],"type":"Point"}
}