{
  "type": "Feature",
  "properties": {
    "iso:country":"US",
    "sg:address":"791 Stewart Ave",
    "sg:city":"Garden City",
    "sg:classifiers":[
        {
            "category":"Autos & Motor Vehicles",
            "subcategory":"Fuel & Gas Station",
            "type":"Retail Goods"
        }
    ],
    "sg:phone":"+1 516 794 0300",
    "sg:postcode":"11530",
    "sg:province":"NY",
    "wof:name":"Garden City Super Pumper",
    "wof:placetype":"venue"
},
  "geometry": {"coordinates":[-73.602898,40.733799],"type":"Point"}
}