{
  "type": "Feature",
  "properties": {
    "iso:country":"US",
    "sg:address":"85 Columbia St",
    "sg:city":"New York",
    "sg:classifiers":[
        {
            "category":"Organizations",
            "subcategory":"Religious Organization",
            "type":"Services"
        }
    ],
    "sg:phone":"+1 212 228 3848",
    "sg:postcode":"10002",
    "sg:province":"NY",
    "sg:tags":[
        "clergy"
    ],
    "wof:name":"Leo Lawrence",
    "wof:placetype":"venue"
},
  "geometry": {"coordinates":[-73.979798,40.71793],"type":"Point"}
}