{
  "type": "Feature",
  "properties": {
    "addr:full":"449 Route 25A Mount Sinai NY 11766",
    "addr:housenumber":"449",
    "addr:postcode":"11766",
    "addr:street":"Route 25A",
    "iso:country":"US",
    "sg:address":"449 Route 25A",
    "sg:city":"Mount Sinai",
    "sg:classifiers":[
        {
            "category":"Personal",
            "subcategory":"Barber",
            "type":"Services"
        }
    ],
    "sg:phone":"+1 631 474 0646",
    "sg:postcode":"11766",
    "sg:province":"NY",
    "wof:name":"Frankie's Barber Shop",
    "wof:placetype":"venue"
},
  "geometry": {"coordinates":[-73.02469600000001,40.934299],"type":"Point"}
}