{
  "type": "Feature",
  "properties": {
    "addr:full":"2010 James St Syracuse NY 13206",
    "addr:housenumber":"2010",
    "addr:postcode":"13206",
    "addr:street":"James St",
    "iso:country":"US",
    "sg:address":"2010 James St",
    "sg:city":"Syracuse",
    "sg:classifiers":[
        {
            "category":"Banks & Credit Unions",
            "subcategory":"Investment Brokerage",
            "type":"Services"
        }
    ],
    "sg:phone":"+1 315 431 0524",
    "sg:postcode":"13206",
    "sg:province":"NY",
    "sg:tags":[
        "consultant",
        "planning",
        "financial"
    ],
    "wof:name":"En Passant Financial Planning",
    "wof:placetype":"venue"
},
  "geometry": {"coordinates":[-76.11797300000001,43.067216],"type":"Point"}
}