{
  "type": "Feature",
  "properties": {
    "iso:country":"US",
    "sg:address":"1295 Portland Ave",
    "sg:city":"Rochester",
    "sg:classifiers":[
        {
            "category":"Health Services",
            "subcategory":"Doctor",
            "type":"Services"
        }
    ],
    "sg:phone":"+1 585 342 8050",
    "sg:postcode":"14621",
    "sg:province":"NY",
    "sg:tags":[
        "dentist"
    ],
    "wof:name":"Ronald Daymon DDS",
    "wof:placetype":"venue"
},
  "geometry": {"coordinates":[-77.584327,43.189517],"type":"Point"}
}