{
  "type": "Feature",
  "properties": {
    "iso:country":"US",
    "sg:address":"206 Marcellus St",
    "sg:city":"Syracuse",
    "sg:classifiers":[
        {
            "category":"Home & Garden",
            "subcategory":"Building Materials",
            "type":"Retail Goods"
        }
    ],
    "sg:phone":"+1   ",
    "sg:postcode":"13204",
    "sg:province":"NY",
    "sg:tags":[
        "repair"
    ],
    "wof:name":"Just Glass Studio",
    "wof:placetype":"venue"
},
  "geometry": {"coordinates":[-76.16188099999999,43.047042],"type":"Point"}
}