{
  "type": "Feature",
  "properties": {
    "iso:country":"US",
    "sg:address":"1873 W Kendall Rd",
    "sg:city":"Kendall",
    "sg:classifiers":[
        {
            "category":"Government",
            "subcategory":"Court House",
            "type":"Public Place"
        }
    ],
    "sg:phone":"+1 585 659 8546",
    "sg:postcode":"14476",
    "sg:province":"NY",
    "sg:tags":[
        "city"
    ],
    "wof:name":"Justice Court",
    "wof:placetype":"venue"
},
  "geometry": {"coordinates":[-78.075794,43.320326],"type":"Point"}
}