{
  "type": "Feature",
  "properties": {
    "addr:full":"6916 4th Ave Brooklyn NY 11209",
    "addr:housenumber":"6916",
    "addr:postcode":"11209",
    "addr:street":"4Th Ave",
    "iso:country":"US",
    "sg:address":"6916 4th Ave",
    "sg:city":"Brooklyn",
    "sg:classifiers":[
        {
            "category":"Restaurant",
            "type":"Food & Drink"
        }
    ],
    "sg:menulink":"http://www.allmenus.com/ny/brooklyn/52484-hot-hamburger/menu/",
    "sg:phone":"+1 718 238 8349",
    "sg:postcode":"11209",
    "sg:province":"NY",
    "sg:tags":[
        "american",
        "diner"
    ],
    "wof:name":"Hot Hamburger",
    "wof:placetype":"venue"
},
  "geometry": {"coordinates":[-74.023584,40.634396],"type":"Point"}
}