{
  "type": "Feature",
  "properties": {
    "iso:country":"US",
    "sg:address":"4201 Oakdale Ct",
    "sg:city":"Schenectady",
    "sg:classifiers":[
        {
            "category":"Building & Trades",
            "subcategory":"Construction",
            "type":"Services"
        }
    ],
    "sg:phone":"+1 518 355 5290",
    "sg:postcode":"12303",
    "sg:province":"NY",
    "sg:tags":[
        "painter"
    ],
    "wof:name":"Robert J Nuttall",
    "wof:placetype":"venue"
},
  "geometry": {"coordinates":[-73.935807,42.748329],"type":"Point"}
}