{
  "type": "Feature",
  "properties": {
    "addr:full":"103 Morningside Dr Ossining NY 10562",
    "addr:housenumber":"103",
    "addr:postcode":"10562",
    "addr:street":"Morningside Dr",
    "iso:country":"US",
    "sg:address":"103 Morningside Dr",
    "sg:city":"Ossining",
    "sg:classifiers":[
        {
            "category":"Building & Trades",
            "subcategory":"Construction",
            "type":"Services"
        }
    ],
    "sg:phone":"+1 914 941 7181",
    "sg:postcode":"10562",
    "sg:province":"NY",
    "sg:tags":[
        "excavation",
        "grading"
    ],
    "wof:name":"Scott Contracting",
    "wof:placetype":"venue"
},
  "geometry": {"coordinates":[-73.816537,41.173031],"type":"Point"}
}