{
  "type": "Feature",
  "properties": {
    "iso:country":"US",
    "sg:address":"41 Crescent Ave",
    "sg:city":"Hamburg",
    "sg:classifiers":[
        {
            "category":"Professional",
            "subcategory":"Business Services",
            "type":"Services"
        },
        {
            "category":"Wholesale",
            "subcategory":"Durable Goods & Equipment",
            "type":"Manufacturing & Wholesale Goods"
        }
    ],
    "sg:phone":"+1 716 646 0144",
    "sg:postcode":"14075",
    "sg:province":"NY",
    "sg:tags":[
        "hanger",
        "sign"
    ],
    "wof:name":"Graffiti Grafix & Signs Inc",
    "wof:placetype":"venue"
},
  "geometry": {"coordinates":[-78.827037,42.712797],"type":"Point"}
}