{
  "type": "Feature",
  "properties": {
    "iso:country":"US",
    "sg:address":"689 Horseblock Rd",
    "sg:city":"Farmingville",
    "sg:classifiers":[
        {
            "category":"Retail",
            "subcategory":"Laundry & Dry Cleaning",
            "type":"Services"
        }
    ],
    "sg:phone":"+1 631 451 0194",
    "sg:postcode":"11738",
    "sg:province":"NY",
    "wof:name":"Horseblock Road Laundromat",
    "wof:placetype":"venue"
},
  "geometry": {"coordinates":[-73.035442,40.832226],"type":"Point"}
}