{
  "type": "Feature",
  "properties": {
    "addr:full":"717 Front St Hempstead NY 11550",
    "addr:housenumber":"717",
    "addr:postcode":"11550",
    "addr:street":"Front St",
    "iso:country":"US",
    "sg:address":"717 Front St",
    "sg:city":"Hempstead",
    "sg:classifiers":[
        {
            "category":"Professional",
            "subcategory":"Management & Consulting",
            "type":"Services"
        }
    ],
    "sg:phone":"+1 516 565 2745",
    "sg:postcode":"11550",
    "sg:province":"NY",
    "sg:tags":[
        "fuel"
    ],
    "wof:name":"RUL Management Inc",
    "wof:placetype":"venue"
},
  "geometry": {"coordinates":[-73.605964,40.709482],"type":"Point"}
}