{
  "type": "Feature",
  "properties": {
    "addr:full":"600 Broadway Lynbrook NY 11563",
    "addr:housenumber":"600",
    "addr:postcode":"11563",
    "addr:street":"Broadway",
    "iso:country":"US",
    "sg:address":"600 Broadway",
    "sg:city":"Lynbrook",
    "sg:classifiers":[
        {
            "category":"Building & Trades",
            "subcategory":"Construction",
            "type":"Services"
        }
    ],
    "sg:phone":"+1 516 561 5628",
    "sg:postcode":"11563",
    "sg:province":"NY",
    "sg:tags":[
        "home",
        "improvement"
    ],
    "wof:name":"Super Pro Contracting",
    "wof:placetype":"venue"
},
  "geometry": {"coordinates":[-73.68608399999999,40.64889],"type":"Point"}
}