{
  "type": "Feature",
  "properties": {
    "addr:full":"5570 Main St Buffalo NY 14221",
    "addr:housenumber":"5570",
    "addr:postcode":"14221",
    "addr:street":"Main St",
    "iso:country":"US",
    "sg:address":"5570 Main St",
    "sg:city":"Buffalo",
    "sg:classifiers":[
        {
            "category":"Building & Trades",
            "subcategory":"Construction",
            "type":"Services"
        }
    ],
    "sg:phone":"+1 716 634 7786",
    "sg:postcode":"14221",
    "sg:province":"NY",
    "sg:tags":[
        "new",
        "home"
    ],
    "wof:name":"Fisher Homes LLC",
    "wof:placetype":"venue"
},
  "geometry": {"coordinates":[-78.745008,42.962861],"type":"Point"}
}