{
  "type": "Feature",
  "properties": {
    "addr:full":"66 66th Rd Martville NY 13111",
    "addr:housenumber":"66",
    "addr:postcode":"13111",
    "addr:street":"66Th Rd",
    "iso:country":"US",
    "sg:address":"66 66th Rd",
    "sg:city":"Martville",
    "sg:classifiers":[
        {
            "category":"Building & Trades",
            "subcategory":"Construction",
            "type":"Services"
        }
    ],
    "sg:phone":"+1 315 564 5710",
    "sg:postcode":"13111",
    "sg:province":"NY",
    "sg:tags":[
        "excavating",
        "contractor"
    ],
    "wof:name":"R F Stanton Trucking & Excavtg",
    "wof:placetype":"venue"
},
  "geometry": {"coordinates":[-76.60045,43.262632],"type":"Point"}
}