{
  "type": "Feature",
  "properties": {
    "addr:full":"2330 Graham Ave Yorkville NY 13495",
    "addr:housenumber":"2330",
    "addr:postcode":"13495",
    "addr:street":"Graham Ave",
    "iso:country":"US",
    "sg:address":"2330 Graham Ave",
    "sg:city":"Yorkville",
    "sg:classifiers":[
        {
            "category":"Building & Trades",
            "subcategory":"Construction",
            "type":"Services"
        }
    ],
    "sg:phone":"+1 315 736 7275",
    "sg:postcode":"13495",
    "sg:province":"NY",
    "sg:tags":[
        "house"
    ],
    "wof:name":"Breen Brothers Home Imprv",
    "wof:placetype":"venue"
},
  "geometry": {"coordinates":[-75.271413,43.107551],"type":"Point"}
}