{
  "type": "Feature",
  "properties": {
    "iso:country":"US",
    "sg:address":"702 Badger Ave",
    "sg:city":"Endicott",
    "sg:classifiers":[
        {
            "category":"Retail",
            "subcategory":"Repair Shop",
            "type":"Services"
        }
    ],
    "sg:phone":"+1 607 754 4086",
    "sg:postcode":"13760",
    "sg:province":"NY",
    "sg:tags":[
        "equipment",
        "locksmith",
        "commercial",
        "lock"
    ],
    "wof:name":"Carlson's Key Shop",
    "wof:placetype":"venue"
},
  "geometry": {"coordinates":[-76.06707400000001,42.091953],"type":"Point"}
}