{
  "type": "Feature",
  "properties": {
    "iso:country":"US",
    "sg:address":"2516 Bailey Ave",
    "sg:city":"Buffalo",
    "sg:classifiers":[
        {
            "category":"Building & Trades",
            "subcategory":"Electrical",
            "type":"Services"
        }
    ],
    "sg:phone":"+1 716 897 2544",
    "sg:postcode":"14215",
    "sg:province":"NY",
    "sg:tags":[
        "telephone"
    ],
    "wof:name":"Jack Man",
    "wof:placetype":"venue"
},
  "geometry": {"coordinates":[-78.813751,42.923141],"type":"Point"}
}