{
  "type": "Feature",
  "properties": {
    "addr:full":"214 W 29th St 3rd Fl New York NY 10001",
    "addr:housenumber":"214;3rd fl",
    "addr:postcode":"10001",
    "addr:street":"W 29Th St",
    "iso:country":"US",
    "sg:address":"214 W 29th St 3rd Fl",
    "sg:city":"New York",
    "sg:classifiers":[
        {
            "category":"Arena",
            "subcategory":"Sports Club",
            "type":"Entertainment"
        }
    ],
    "sg:phone":"+1 212 260 0927",
    "sg:postcode":"10001",
    "sg:province":"NY",
    "sg:tags":[
        "martial art"
    ],
    "sg:website":"www.EizanRyuJuJitsu.org",
    "wof:name":"Eizan Ryu Ju Jitsu",
    "wof:placetype":"venue"
},
  "geometry": {"coordinates":[-73.99354200000001,40.747956],"type":"Point"}
}