{
  "type": "Feature",
  "properties": {
    "addr:full":"28 Bank St Valley Stream NY 11580",
    "addr:housenumber":"28",
    "addr:postcode":"11580",
    "addr:street":"Bank St",
    "iso:country":"US",
    "sg:address":"28 Bank St",
    "sg:city":"Valley Stream",
    "sg:classifiers":[
        {
            "category":"Professional",
            "subcategory":"Lawyer & Legal Services",
            "type":"Services"
        }
    ],
    "sg:phone":"+1 516 285 1400",
    "sg:postcode":"11580",
    "sg:province":"NY",
    "sg:tags":[
        "research"
    ],
    "sg:website":"www.heirsusa.com",
    "wof:name":"Diliberto Probate Research",
    "wof:placetype":"venue"
},
  "geometry": {"coordinates":[-73.71859000000001,40.683575],"type":"Point"}
}