{
  "type": "Feature",
  "properties": {
    "addr:full":"130 N Long Beach Rd Rockville Centre NY 11570",
    "addr:housenumber":"130",
    "addr:postcode":"11570",
    "addr:street":"N Long Beach Rd",
    "iso:country":"US",
    "sg:address":"130 N Long Beach Rd",
    "sg:city":"Rockville Centre",
    "sg:classifiers":[
        {
            "category":"Professional",
            "subcategory":"Lawyer & Legal Services",
            "type":"Services"
        }
    ],
    "sg:phone":"+1 516 872 8880",
    "sg:postcode":"11570",
    "sg:province":"NY",
    "sg:tags":[
        "attorney"
    ],
    "wof:name":"Pat R Mercurio",
    "wof:placetype":"venue"
},
  "geometry": {"coordinates":[-73.630498,40.658979],"type":"Point"}
}