{
  "type": "Feature",
  "properties": {
    "addr:full":"29 Suzanne Dr Monsey NY 10952",
    "addr:housenumber":"29",
    "addr:postcode":"10952",
    "addr:street":"Suzanne Dr",
    "iso:country":"US",
    "sg:address":"29 Suzanne Dr",
    "sg:city":"Monsey",
    "sg:classifiers":[
        {
            "category":"Shopping",
            "subcategory":"Clothing, Apparel, & Fashions",
            "type":"Retail Goods"
        }
    ],
    "sg:phone":"+1 845 352 4825",
    "sg:postcode":"10952",
    "sg:province":"NY",
    "wof:name":"SCC Creations Wholesale",
    "wof:placetype":"venue"
},
  "geometry": {"coordinates":[-74.063985,41.117765],"type":"Point"}
}