{
  "type": "Feature",
  "properties": {
    "addr:full":"1350 First Avenue & 72nd Street New York NY 10021",
    "addr:housenumber":"1350",
    "addr:postcode":"10021",
    "addr:street":"First Avenue & 72Nd Street",
    "iso:country":"US",
    "sg:address":"1350 First Avenue & 72nd Street",
    "sg:city":"New York",
    "sg:classifiers":[
        {
            "category":"Restaurant",
            "type":"Food & Drink"
        }
    ],
    "sg:menulink":"http://www.allmenus.com/ny/new-york/107211-soup-man/menu/",
    "sg:phone":"+1 212 535 1381",
    "sg:postcode":"10021",
    "sg:province":"NY",
    "sg:tags":[
        "soup",
        "american",
        "salad"
    ],
    "wof:name":"Soup Man",
    "wof:placetype":"venue"
},
  "geometry": {"coordinates":[-73.955733,40.768175],"type":"Point"}
}