{
  "type": "Feature",
  "properties": {
    "iso:country":"US",
    "sg:address":"45 Birdie Ln",
    "sg:city":"Southampton",
    "sg:classifiers":[
        {
            "category":"Real Estate",
            "subcategory":"Developer",
            "type":"Services"
        },
        {
            "category":"Real Estate",
            "subcategory":"Real Estate Operator",
            "type":"Services"
        }
    ],
    "sg:phone":"+1 631 287 0555",
    "sg:postcode":"11937",
    "sg:province":"NY",
    "sg:tags":[
        "building",
        "nonresidential"
    ],
    "wof:name":"Boom Development Corp",
    "wof:placetype":"venue"
},
  "geometry": {"coordinates":[-72.16898399999999,40.99452],"type":"Point"}
}