{
  "type": "Feature",
  "properties": {
    "iso:country":"US",
    "sg:address":"39 W Main St",
    "sg:city":"Fredonia",
    "sg:classifiers":[
        {
            "category":"Shopping",
            "subcategory":"Florist",
            "type":"Retail Goods"
        }
    ],
    "sg:phone":"+1 716 679 1569",
    "sg:postcode":"14063",
    "sg:province":"NY",
    "wof:name":"Neil's Flower Shop",
    "wof:placetype":"venue"
},
  "geometry": {"coordinates":[-79.33263700000001,42.439143],"type":"Point"}
}