{
  "type": "Feature",
  "properties": {
    "iso:country":"US",
    "sg:address":"753 Emerson St",
    "sg:city":"Rochester",
    "sg:classifiers":[
        {
            "category":"Freight",
            "type":"Transportation"
        }
    ],
    "sg:phone":"+1 585 254 5619",
    "sg:postcode":"14613",
    "sg:province":"NY",
    "sg:tags":[
        "delivery"
    ],
    "wof:name":"Louis Povio Deliveries",
    "wof:placetype":"venue"
},
  "geometry": {"coordinates":[-77.65068599999999,43.173781],"type":"Point"}
}