{
  "type": "Feature",
  "properties": {
    "addr:full":"20 Bridge St Seneca Falls NY 13148",
    "addr:housenumber":"20",
    "addr:postcode":"13148",
    "addr:street":"Bridge St",
    "iso:country":"US",
    "sg:address":"20 Bridge St",
    "sg:city":"Seneca Falls",
    "sg:classifiers":[
        {
            "category":"Food & Beverages",
            "subcategory":"Liquor & Beverages",
            "type":"Retail Goods"
        }
    ],
    "sg:phone":"+1   ",
    "sg:postcode":"13148",
    "sg:province":"NY",
    "sg:tags":[
        "alcoholic"
    ],
    "wof:name":"Pedullas Liquors",
    "wof:placetype":"venue"
},
  "geometry": {"coordinates":[-76.800709,42.908502],"type":"Point"}
}