{
  "type": "Feature",
  "properties": {
    "iso:country":"US",
    "sg:address":"752 Nostrand Ave",
    "sg:city":"Brooklyn",
    "sg:classifiers":[
        {
            "category":"Personal",
            "subcategory":"Nail Salon",
            "type":"Services"
        }
    ],
    "sg:phone":"+1 718 778 1800",
    "sg:postcode":"11216",
    "sg:province":"NY",
    "sg:website":"www.alertmedicalsupply.com",
    "wof:name":"Alert Medical Supply Inc",
    "wof:placetype":"venue"
},
  "geometry": {"coordinates":[-73.95038099999999,40.672911],"type":"Point"}
}