{
  "type": "Feature",
  "properties": {
    "iso:country":"US",
    "sg:address":"172 Gifford Rd",
    "sg:city":"Greenville",
    "sg:phone":"+1 518 966 4271",
    "sg:postcode":"12083",
    "sg:province":"NY",
    "sg:website":"http://www.redsunbuilders.com",
    "wof:name":"Red Sun Builders",
    "wof:placetype":"venue"
},
  "geometry": {"coordinates":[-74.08251199999999,42.455231],"type":"Point"}
}