{
  "type": "Feature",
  "properties": {
    "addr:full":"68 W Maple Ave Monsey NY 10952",
    "addr:housenumber":"68",
    "addr:postcode":"10952",
    "addr:street":"W Maple Ave",
    "iso:country":"US",
    "sg:address":"68 W Maple Ave",
    "sg:city":"Monsey",
    "sg:classifiers":[
        {
            "category":"Professional",
            "type":"Services"
        }
    ],
    "sg:phone":"+1 845 573 0022",
    "sg:postcode":"10952",
    "sg:province":"NY",
    "sg:tags":[
        "establishment"
    ],
    "wof:name":"Hamaor",
    "wof:placetype":"venue"
},
  "geometry": {"coordinates":[-74.07719,41.119191],"type":"Point"}
}