{
  "type": "Feature",
  "properties": {
    "addr:full":"2901 Ocean Ave Brooklyn NY 11235",
    "addr:housenumber":"2901",
    "addr:postcode":"11235",
    "addr:street":"Ocean Ave",
    "iso:country":"US",
    "sg:address":"2901 Ocean Ave",
    "sg:city":"Brooklyn",
    "sg:classifiers":[
        {
            "category":"Restaurant",
            "type":"Food & Drink"
        }
    ],
    "sg:phone":"+1 718 368 3668",
    "sg:postcode":"11235",
    "sg:province":"NY",
    "sg:tags":[
        "sushi",
        "bar",
        "japanese"
    ],
    "sg:website":"hayashisushibrooklyn.com",
    "wof:name":"Hayashi",
    "wof:placetype":"venue"
},
  "geometry": {"coordinates":[-73.94938,40.590465],"type":"Point"}
}