{
  "type": "Feature",
  "properties": {
    "addr:full":"6712 Brooklawn Pkwy Mattydale NY 13211",
    "addr:housenumber":"6712",
    "addr:postcode":"13211",
    "addr:street":"Brooklawn Pkwy",
    "iso:country":"US",
    "sg:address":"6712 Brooklawn Pkwy",
    "sg:city":"Mattydale",
    "sg:classifiers":[
        {
            "category":"Professional",
            "subcategory":"Lawyer & Legal Services",
            "type":"Services"
        }
    ],
    "sg:phone":"+1 315 437 6655",
    "sg:postcode":"13211",
    "sg:province":"NY",
    "sg:tags":[
        "attorney"
    ],
    "wof:name":"UAW-Gm Legal Svc Plan",
    "wof:placetype":"venue"
},
  "geometry": {"coordinates":[-76.096521,43.09443],"type":"Point"}
}