{
  "type": "Feature",
  "properties": {
    "addr:full":"191 Rockaway Ave Valley Stream NY 11580",
    "addr:housenumber":"191",
    "addr:postcode":"11580",
    "addr:street":"Rockaway Ave",
    "iso:country":"US",
    "sg:address":"191 Rockaway Ave",
    "sg:city":"Valley Stream",
    "sg:classifiers":[
        {
            "category":"Restaurant",
            "type":"Food & Drink"
        }
    ],
    "sg:phone":"+1   ",
    "sg:postcode":"11580",
    "sg:province":"NY",
    "sg:tags":[
        "luncheonette"
    ],
    "wof:name":"Mitchells Diner",
    "wof:placetype":"venue"
},
  "geometry": {"coordinates":[-73.699252,40.662113],"type":"Point"}
}