{
  "type": "Feature",
  "properties": {
    "addr:full":"867 Cypress Ave Ridgewood NY 11385",
    "addr:housenumber":"867",
    "addr:postcode":"11385",
    "addr:street":"Cypress Ave",
    "iso:country":"US",
    "sg:address":"867 Cypress Ave",
    "sg:city":"Ridgewood",
    "sg:classifiers":[
        {
            "category":"Insurance",
            "subcategory":"Insurance Agent",
            "type":"Services"
        },
        {
            "category":"Insurance",
            "subcategory":"Hazard Insurance",
            "type":"Services"
        },
        {
            "category":"Insurance",
            "subcategory":"Title Insurance",
            "type":"Services"
        },
        {
            "category":"Insurance",
            "subcategory":"Life Insurance",
            "type":"Services"
        }
    ],
    "sg:phone":"+1 718 418 7000",
    "sg:postcode":"11385",
    "sg:province":"NY",
    "sg:tags":[
        "business",
        "auto",
        "commercial",
        "homeowner",
        "motorcycle",
        "renter"
    ],
    "wof:name":"Allstate Insurance Company - Nanci Coronado",
    "wof:placetype":"venue"
},
  "geometry": {"coordinates":[-73.89463000000001,40.6926],"type":"Point"}
}