{
  "type": "Feature",
  "properties": {
    "addr:full":"558 Broome St New York NY 10013",
    "addr:housenumber":"558",
    "addr:postcode":"10013",
    "addr:street":"Broome St",
    "iso:country":"US",
    "sg:address":"558 Broome St",
    "sg:city":"New York",
    "sg:classifiers":[
        {
            "category":"Professional",
            "type":"Services"
        }
    ],
    "sg:phone":"+1 646 442 2816",
    "sg:postcode":"10013",
    "sg:province":"NY",
    "sg:tags":[
        "establishment"
    ],
    "wof:name":"New York Chart & Diagram",
    "wof:placetype":"venue"
},
  "geometry": {"coordinates":[-74.005241,40.724368],"type":"Point"}
}