{
  "type": "Feature",
  "properties": {
    "addr:full":"30 Harriman Dr Goshen NY 10924",
    "addr:housenumber":"30",
    "addr:postcode":"10924",
    "addr:street":"Harriman Dr",
    "iso:country":"US",
    "sg:address":"30 Harriman Dr",
    "sg:city":"Goshen",
    "sg:classifiers":[
        {
            "category":"Social Services",
            "type":"Services"
        }
    ],
    "sg:phone":"+1 845 565 1234",
    "sg:postcode":"10924",
    "sg:province":"NY",
    "sg:tags":[
        "organization",
        "welfare"
    ],
    "wof:name":"Domestic Violence Classes Men",
    "wof:placetype":"venue"
},
  "geometry": {"coordinates":[-74.317915,41.3887],"type":"Point"}
}