{
  "type": "Feature",
  "properties": {
    "addr:full":"97 Washburn St Lake Grove NY 11755",
    "addr:housenumber":"97",
    "addr:postcode":"11755",
    "addr:street":"Washburn St",
    "iso:country":"US",
    "sg:address":"97 Washburn St",
    "sg:city":"Lake Grove",
    "sg:classifiers":[
        {
            "category":"Shopping",
            "type":"Retail Goods"
        }
    ],
    "sg:phone":"+1   ",
    "sg:postcode":"11755",
    "sg:province":"NY",
    "sg:tags":[
        "merchandise"
    ],
    "wof:name":"Simbonics Tech",
    "wof:placetype":"venue"
},
  "geometry": {"coordinates":[-73.114914,40.853146],"type":"Point"}
}