{
  "type": "Feature",
  "properties": {
    "addr:full":"482 Court St Brooklyn NY 11231",
    "addr:housenumber":"482",
    "addr:postcode":"11231",
    "addr:street":"Court St",
    "iso:country":"US",
    "sg:address":"482 Court St",
    "sg:city":"Brooklyn",
    "sg:classifiers":[
        {
            "category":"Local Transit",
            "type":"Transportation"
        }
    ],
    "sg:phone":"+1   ",
    "sg:postcode":"11231",
    "sg:province":"NY",
    "sg:tags":[
        "passenger",
        "transport"
    ],
    "wof:name":"New Yorks Battery Car Service",
    "wof:placetype":"venue"
},
  "geometry": {"coordinates":[-73.998323,40.677616],"type":"Point"}
}