{
  "type": "Feature",
  "properties": {
    "addr:full":"75 Orange Ave Walden NY 12586",
    "addr:housenumber":"75",
    "addr:postcode":"12586",
    "addr:street":"Orange Ave",
    "iso:country":"US",
    "sg:address":"75 Orange Ave",
    "sg:city":"Walden",
    "sg:classifiers":[
        {
            "category":"Shopping",
            "subcategory":"Florist",
            "type":"Retail Goods"
        }
    ],
    "sg:phone":"+1 845 778 1218",
    "sg:postcode":"12586",
    "sg:province":"NY",
    "wof:name":"Happy Flower Shop",
    "wof:placetype":"venue"
},
  "geometry": {"coordinates":[-74.186615,41.557238],"type":"Point"}
}