{
  "type": "Feature",
  "properties": {
    "addr:full":"393 Smith Rd Shirley NY 11967",
    "addr:housenumber":"393",
    "addr:postcode":"11967",
    "addr:street":"Smith Rd",
    "iso:country":"US",
    "sg:address":"393 Smith Rd",
    "sg:city":"Shirley",
    "sg:classifiers":[
        {
            "category":"Freight",
            "type":"Transportation"
        }
    ],
    "sg:phone":"+1 631 395 7014",
    "sg:postcode":"11967",
    "sg:province":"NY",
    "sg:tags":[
        "commercial",
        "storage"
    ],
    "wof:name":"Storage Depot",
    "wof:placetype":"venue"
},
  "geometry": {"coordinates":[-72.88121,40.801706],"type":"Point"}
}