{
  "type": "Feature",
  "properties": {
    "addr:full":"2050 Webster Ave Bronx NY 10457",
    "addr:housenumber":"2050",
    "addr:postcode":"10457",
    "addr:street":"Webster Ave",
    "iso:country":"US",
    "sg:address":"2050 Webster Ave",
    "sg:city":"Bronx",
    "sg:classifiers":[
        {
            "category":"Restaurant",
            "type":"Food & Drink"
        }
    ],
    "sg:phone":"+1 718 364 4400",
    "sg:postcode":"10457",
    "sg:province":"NY",
    "sg:tags":[
        "beverage"
    ],
    "wof:name":"Pepsi-Cola Bottling Co",
    "wof:placetype":"venue"
},
  "geometry": {"coordinates":[-73.89868199999999,40.851092],"type":"Point"}
}