{
  "type": "Feature",
  "properties": {
    "addr:full":"22 Sullivan Ave Liberty NY 12754",
    "addr:housenumber":"22",
    "addr:postcode":"12754",
    "addr:street":"Sullivan Ave",
    "iso:country":"US",
    "sg:address":"22 Sullivan Ave",
    "sg:city":"Liberty",
    "sg:classifiers":[
        {
            "category":"Restaurant",
            "type":"Food & Drink"
        }
    ],
    "sg:phone":"+1 845 292 6644",
    "sg:postcode":"12754",
    "sg:province":"NY",
    "sg:website":"www.pizzahut.com",
    "wof:name":"Pizza Hut",
    "wof:placetype":"venue"
},
  "geometry": {"coordinates":[-74.728723,41.786168],"type":"Point"}
}