{
  "type": "Feature",
  "properties": {
    "iso:country":"US",
    "sg:address":"290 Drake Ave",
    "sg:city":"New Rochelle",
    "sg:classifiers":[
        {
            "category":"Building & Trades",
            "subcategory":"Electrical",
            "type":"Services"
        }
    ],
    "sg:phone":"+1 914 740 2062",
    "sg:postcode":"10805",
    "sg:province":"NY",
    "sg:tags":[
        "electric",
        "contractor"
    ],
    "wof:name":"Westchester Electrical Co",
    "wof:placetype":"venue"
},
  "geometry": {"coordinates":[-73.78225500000001,40.893732],"type":"Point"}
}