{
  "type": "Feature",
  "properties": {
    "addr:full":"8122 5th Ave Brooklyn NY 11209",
    "addr:housenumber":"8122",
    "addr:postcode":"11209",
    "addr:street":"5Th Ave",
    "iso:country":"US",
    "sg:address":"8122 5th Ave",
    "sg:city":"Brooklyn",
    "sg:classifiers":[
        {
            "category":"Organizations",
            "subcategory":"Community Association",
            "type":"Services"
        }
    ],
    "sg:phone":"+1 718 745 9175",
    "sg:postcode":"11209",
    "sg:province":"NY",
    "sg:tags":[
        "fraternal"
    ],
    "wof:name":"Knights Of Columbus",
    "wof:placetype":"venue"
},
  "geometry": {"coordinates":[-74.02477,40.624506],"type":"Point"}
}