{
  "type": "Feature",
  "properties": {
    "iso:country":"US",
    "sg:address":"59 Boss St",
    "sg:city":"Bolivar",
    "sg:classifiers":[
        {
            "category":"Professional",
            "subcategory":"Accounting & Tax Preparation",
            "type":"Services"
        }
    ],
    "sg:phone":"+1 585 928 1230",
    "sg:postcode":"14715",
    "sg:province":"NY",
    "sg:tags":[
        "return",
        "filing"
    ],
    "wof:name":"Thomas J Dunn Pa",
    "wof:placetype":"venue"
},
  "geometry": {"coordinates":[-78.168744,42.066779],"type":"Point"}
}