{
  "type": "Feature",
  "properties": {
    "addr:full":"1067 Union Ave Newburgh NY 12550",
    "addr:housenumber":"1067",
    "addr:postcode":"12550",
    "addr:street":"Union Ave",
    "iso:country":"US",
    "sg:address":"1067 Union Ave",
    "sg:city":"Newburgh",
    "sg:classifiers":[
        {
            "category":"Retail",
            "subcategory":"Portrait Studio",
            "type":"Services"
        },
        {
            "category":"Shopping",
            "subcategory":"Pharmacy",
            "type":"Retail Goods"
        }
    ],
    "sg:phone":"+1 845 564 5747",
    "sg:postcode":"12550",
    "sg:province":"NY",
    "sg:tags":[
        "photography",
        "drugstore",
        "store"
    ],
    "wof:name":"CVS pharmacy",
    "wof:placetype":"venue"
},
  "geometry": {"coordinates":[-74.217128,41.497272],"type":"Point"}
}