{
  "type": "Feature",
  "properties": {
    "addr:full":"2616 Sanitarium Rd Clifton Springs NY 14432",
    "addr:postcode":"2616;14432",
    "addr:street":"Sanitarium Rd",
    "iso:country":"US",
    "sg:address":"2616 Sanitarium Rd",
    "sg:city":"Clifton Springs",
    "sg:phone":"+1 315 462 3217",
    "sg:postcode":"14432",
    "sg:province":"NY",
    "sg:tags":[
        "farm",
        "corn"
    ],
    "wof:name":"Driscoll Farm",
    "wof:placetype":"venue"
},
  "geometry": {"coordinates":[-77.134587,42.975386],"type":"Point"}
}