{
  "type": "Feature",
  "properties": {
    "addr:full":"251 N Main St Gloversville NY 12078",
    "addr:housenumber":"251",
    "addr:postcode":"12078",
    "addr:street":"N Main St",
    "iso:country":"US",
    "sg:address":"251 N Main St",
    "sg:city":"Gloversville",
    "sg:classifiers":[
        {
            "category":"Food & Beverages",
            "subcategory":"Groceries & Convenience Stores",
            "type":"Retail Goods"
        }
    ],
    "sg:phone":"+1 518 725 8122",
    "sg:postcode":"12078",
    "sg:province":"NY",
    "sg:tags":[
        "grocer"
    ],
    "wof:name":"Abraham's Grocery",
    "wof:placetype":"venue"
},
  "geometry": {"coordinates":[-74.341335,43.057246],"type":"Point"}
}