{
  "type": "Feature",
  "properties": {
    "addr:full":"1215 Avenue N Brooklyn NY 11230",
    "addr:housenumber":"1215",
    "addr:postcode":"11230",
    "addr:street":"Avenue N",
    "iso:country":"US",
    "sg:address":"1215 Avenue N",
    "sg:city":"Brooklyn",
    "sg:classifiers":[
        {
            "category":"Communications",
            "subcategory":"Film & Video Production",
            "type":"Services"
        }
    ],
    "sg:phone":"+1   ",
    "sg:postcode":"11230",
    "sg:province":"NY",
    "sg:tags":[
        "motion"
    ],
    "wof:name":"At Once Media Corp",
    "wof:placetype":"venue"
},
  "geometry": {"coordinates":[-73.961546,40.615474],"type":"Point"}
}