{
  "type": "Feature",
  "properties": {
    "addr:full":"75 Brookline Rd Ballston Spa NY 12020",
    "addr:housenumber":"75",
    "addr:postcode":"12020",
    "addr:street":"Brookline Rd",
    "iso:country":"US",
    "sg:address":"75 Brookline Rd",
    "sg:city":"Ballston Spa",
    "sg:classifiers":[
        {
            "category":"Retail",
            "subcategory":"Storage",
            "type":"Services"
        }
    ],
    "sg:phone":"+1 518 885 4800",
    "sg:postcode":"12020",
    "sg:province":"NY",
    "sg:tags":[
        "self"
    ],
    "sg:website":"www.extraspace.com",
    "wof:name":"Extra Space Storage",
    "wof:placetype":"venue"
},
  "geometry": {"coordinates":[-73.860439,42.974587],"type":"Point"}
}