{
  "type": "Feature",
  "properties": {
    "addr:full":"1542 Pitkin Ave Brooklyn NY 11212",
    "addr:housenumber":"1542",
    "addr:postcode":"11212",
    "addr:street":"Pitkin Ave",
    "iso:country":"US",
    "sg:address":"1542 Pitkin Ave",
    "sg:city":"Brooklyn",
    "sg:classifiers":[
        {
            "category":"Home & Garden",
            "subcategory":"Furniture",
            "type":"Retail Goods"
        }
    ],
    "sg:phone":"+1 718 498 7108",
    "sg:postcode":"11212",
    "sg:province":"NY",
    "sg:tags":[
        "store"
    ],
    "wof:name":"Kai Furniture Center Inc",
    "wof:placetype":"venue"
},
  "geometry": {"coordinates":[-73.91658200000001,40.668676],"type":"Point"}
}