{
  "type": "Feature",
  "properties": {
    "addr:full":"252 E 89 St New York NY 10128",
    "addr:housenumber":"252;89",
    "addr:postcode":"10128",
    "addr:street":"E",
    "iso:country":"US",
    "sg:address":"252 E 89 St",
    "sg:city":"New York",
    "sg:classifiers":[
        {
            "category":"Professional",
            "type":"Services"
        }
    ],
    "sg:phone":"+1 212 534 0493",
    "sg:postcode":"10128",
    "sg:province":"NY",
    "sg:tags":[
        "establishment"
    ],
    "wof:name":"Gross S",
    "wof:placetype":"venue"
},
  "geometry": {"coordinates":[-73.951272,40.780245],"type":"Point"}
}