{
  "type": "Feature",
  "properties": {
    "iso:country":"US",
    "sg:address":"665 Main St",
    "sg:city":"Niagara Falls",
    "sg:classifiers":[
        {
            "category":"Professional",
            "subcategory":"Lawyer & Legal Services",
            "type":"Services"
        }
    ],
    "sg:phone":"+1 716 285 0626",
    "sg:postcode":"14301",
    "sg:province":"NY",
    "sg:tags":[
        "attorney"
    ],
    "wof:name":"Levine & Levine",
    "wof:placetype":"venue"
},
  "geometry": {"coordinates":[-79.05655400000001,43.094064],"type":"Point"}
}