{
  "type": "Feature",
  "properties": {
    "iso:country":"US",
    "sg:address":"2 Lancaster Pkwy",
    "sg:city":"Lancaster",
    "sg:classifiers":[
        {
            "category":"Personal",
            "subcategory":"Sauna",
            "type":"Services"
        },
        {
            "category":"Sports & Exercise",
            "subcategory":"Swimming Pool",
            "type":"Entertainment"
        },
        {
            "category":"Professional",
            "type":"Services"
        },
        {
            "category":"Shopping",
            "subcategory":"Bicycles & Sporting Goods",
            "type":"Retail Goods"
        },
        {
            "category":"Home & Garden",
            "subcategory":"Building Materials",
            "type":"Retail Goods"
        },
        {
            "category":"Building & Trades",
            "subcategory":"Construction",
            "type":"Services"
        }
    ],
    "sg:phone":"+1 716 684 3100",
    "sg:postcode":"14086",
    "sg:province":"NY",
    "sg:tags":[
        "plastering",
        "supply",
        "tubs-repair",
        "specialty",
        "contractor",
        "equipment",
        "hot",
        "concrete",
        "spa",
        "staining",
        "repair"
    ],
    "sg:website":"http://www.leisurecraftpools.com",
    "wof:name":"Leisure Craft Pools",
    "wof:placetype":"venue"
},
  "geometry": {"coordinates":[-78.622665,42.926353],"type":"Point"}
}