{
  "type": "Feature",
  "properties": {
    "addr:full":"5 Everglades Ln Coram NY 11727",
    "addr:housenumber":"5",
    "addr:postcode":"11727",
    "addr:street":"Everglades Ln",
    "iso:country":"US",
    "sg:address":"5 Everglades Ln",
    "sg:city":"Coram",
    "sg:classifiers":[
        {
            "category":"Professional",
            "subcategory":"Computer Services",
            "type":"Services"
        }
    ],
    "sg:phone":"+1   ",
    "sg:postcode":"11727",
    "sg:province":"NY",
    "sg:tags":[
        "hardware",
        "consulting",
        "software"
    ],
    "wof:name":"Imaginative Systems Inc",
    "wof:placetype":"venue"
},
  "geometry": {"coordinates":[-73.000075,40.897325],"type":"Point"}
}