{
  "type": "Feature",
  "properties": {
    "iso:country":"US",
    "sg:address":"3913 Gates Rd",
    "sg:city":"Vestal",
    "sg:classifiers":[
        {
            "category":"Wholesale",
            "subcategory":"Machinery & Supplies",
            "type":"Manufacturing & Wholesale Goods"
        }
    ],
    "sg:phone":"+1 607 729 9254",
    "sg:postcode":"13850",
    "sg:province":"NY",
    "sg:tags":[
        "equipment",
        "establishment"
    ],
    "wof:name":"Vasco Brands Inc",
    "wof:placetype":"venue"
},
  "geometry": {"coordinates":[-75.985079,42.104706],"type":"Point"}
}