{
  "type": "Feature",
  "properties": {
    "iso:country":"US",
    "sg:address":"1664 Old Country Rd",
    "sg:city":"Plainview",
    "sg:classifiers":[
        {
            "category":"Building & Trades",
            "subcategory":"Construction",
            "type":"Services"
        },
        {
            "category":"Professional",
            "subcategory":"Management & Consulting",
            "type":"Services"
        }
    ],
    "sg:phone":"+1 516 752 1199",
    "sg:postcode":"11803",
    "sg:province":"NY",
    "sg:tags":[
        "contractor"
    ],
    "wof:name":"Rosner Construction LLC",
    "wof:placetype":"venue"
},
  "geometry": {"coordinates":[-73.44488,40.78451],"type":"Point"}
}