{
  "type": "Feature",
  "properties": {
    "addr:full":"6077 Myrtle Ave Ridgewood NY 11385",
    "addr:housenumber":"6077",
    "addr:postcode":"11385",
    "addr:street":"Myrtle Ave",
    "iso:country":"US",
    "sg:address":"6077 Myrtle Ave",
    "sg:city":"Ridgewood",
    "sg:classifiers":[
        {
            "category":"Shopping",
            "subcategory":"Shoes",
            "type":"Retail Goods"
        }
    ],
    "sg:phone":"+1 718 366 7330",
    "sg:postcode":"11385",
    "sg:province":"NY",
    "sg:tags":[
        "store"
    ],
    "wof:name":"Marco Polo Shoes",
    "wof:placetype":"venue"
},
  "geometry": {"coordinates":[-73.895461,40.700851],"type":"Point"}
}