{
  "type": "Feature",
  "properties": {
    "iso:country":"US",
    "sg:address":"1079 Broadway",
    "sg:city":"Brooklyn",
    "sg:classifiers":[
        {
            "category":"Shopping",
            "subcategory":"Shoes",
            "type":"Retail Goods"
        }
    ],
    "sg:phone":"+1 718 684 6006",
    "sg:postcode":"11221",
    "sg:province":"NY",
    "sg:tags":[
        "store"
    ],
    "wof:name":"Easy Step Shoes",
    "wof:placetype":"venue"
},
  "geometry": {"coordinates":[-73.93081100000001,40.694648],"type":"Point"}
}