{
  "type": "Feature",
  "properties": {
    "iso:country":"US",
    "sg:address":"44 S Main St",
    "sg:city":"Bloomfield",
    "sg:classifiers":[
        {
            "category":"Government",
            "subcategory":"Fire Station",
            "type":"Public Place"
        }
    ],
    "sg:phone":"+1 585 657 7422",
    "sg:postcode":"14469",
    "sg:province":"NY",
    "sg:tags":[
        "department"
    ],
    "wof:name":"East Bloomfield-Holcomb Fire",
    "wof:placetype":"venue"
},
  "geometry": {"coordinates":[-77.41113,42.90548],"type":"Point"}
}