{
  "type": "Feature",
  "properties": {
    "iso:country":"US",
    "sg:address":"12 Village Green",
    "sg:city":"Port Chester",
    "sg:classifiers":[
        {
            "category":"Organizations",
            "subcategory":"Religious Organization",
            "type":"Services"
        }
    ],
    "sg:phone":"+1 914 939 3653",
    "sg:postcode":"10573",
    "sg:province":"NY",
    "sg:tags":[
        "clergy"
    ],
    "wof:name":"Bernard Dienstag",
    "wof:placetype":"venue"
},
  "geometry": {"coordinates":[-73.66760600000001,41.01143],"type":"Point"}
}