{
  "type": "Feature",
  "properties": {
    "iso:country":"US",
    "sg:address":"3475 Hempstead Tpke",
    "sg:city":"Levittown",
    "sg:classifiers":[
        {
            "category":"Professional",
            "subcategory":"Management & Consulting",
            "type":"Services"
        }
    ],
    "sg:phone":"+1 516 796 5660",
    "sg:postcode":"11756",
    "sg:province":"NY",
    "sg:tags":[
        "consultant",
        "relation",
        "service/non-profit",
        "community",
        "labor"
    ],
    "wof:name":"Levittown Teachers Local 1383",
    "wof:placetype":"venue"
},
  "geometry": {"coordinates":[-73.508202,40.7258],"type":"Point"}
}