{
  "type": "Feature",
  "properties": {
    "addr:full":"322 Co Rd 101 Gloversville NY 12078",
    "addr:housenumber":"322;101",
    "addr:postcode":"12078",
    "addr:street":"Co Rd",
    "iso:country":"US",
    "sg:address":"322 Co Rd 101",
    "sg:city":"Gloversville",
    "sg:classifiers":[
        {
            "category":"Restaurant",
            "type":"Food & Drink"
        }
    ],
    "sg:phone":"+1 518 725 2737",
    "sg:postcode":"12078",
    "sg:province":"NY",
    "sg:tags":[
        "personal",
        "eating"
    ],
    "wof:name":"Vincenza's Banquet House",
    "wof:placetype":"venue"
},
  "geometry": {"coordinates":[-74.40430000000001,43.053983],"type":"Point"}
}