{
  "type": "Feature",
  "properties": {
    "iso:country":"US",
    "sg:address":"1213 E 233rd St",
    "sg:city":"Bronx",
    "sg:classifiers":[
        {
            "category":"Shopping",
            "subcategory":"Computers & Home Electronics",
            "type":"Retail Goods"
        }
    ],
    "sg:phone":"+1   ",
    "sg:postcode":"10466",
    "sg:province":"NY",
    "wof:name":"Radio Shack",
    "wof:placetype":"venue"
},
  "geometry": {"coordinates":[-73.84373100000001,40.889192],"type":"Point"}
}