{
  "type": "Feature",
  "properties": {
    "addr:full":"110 McClean Ave Staten Island NY 10305",
    "addr:housenumber":"110",
    "addr:postcode":"10305",
    "addr:street":"Mcclean Ave",
    "iso:country":"US",
    "sg:address":"110 McClean Ave",
    "sg:city":"Staten Island",
    "sg:classifiers":[
        {
            "category":"Manufacturing",
            "subcategory":"Printing",
            "type":"Manufacturing & Wholesale Goods"
        }
    ],
    "sg:phone":"+1 718 556 5300",
    "sg:postcode":"10305",
    "sg:province":"NY",
    "sg:tags":[
        "newspaper"
    ],
    "sg:website":"www.starcpg.com",
    "wof:name":"Newsday's Marketeer",
    "wof:placetype":"venue"
},
  "geometry": {"coordinates":[-74.06549800000001,40.598315],"type":"Point"}
}