{
  "type": "Feature",
  "properties": {
    "iso:country":"US",
    "sg:address":"299 Mountain Rest Rd",
    "sg:city":"New Paltz",
    "sg:classifiers":[
        {
            "category":"Organizations",
            "subcategory":"Community Association",
            "type":"Services"
        }
    ],
    "sg:phone":"+1   ",
    "sg:postcode":"12561",
    "sg:province":"NY",
    "wof:name":"Student Conservation Assoc",
    "wof:placetype":"venue"
},
  "geometry": {"coordinates":[-74.123938,41.775166],"type":"Point"}
}