{
  "type": "Feature",
  "properties": {
    "addr:full":"88 Old Farm Rd Chappaqua NY 10583",
    "addr:housenumber":"88",
    "addr:postcode":"10583",
    "addr:street":"Old Farm Rd",
    "iso:country":"US",
    "sg:address":"88 Old Farm Rd",
    "sg:city":"Chappaqua",
    "sg:classifiers":[
        {
            "category":"Professional",
            "subcategory":"Computer Services",
            "type":"Services"
        }
    ],
    "sg:phone":"+1 212 432 2844",
    "sg:postcode":"10583",
    "sg:province":"NY",
    "sg:tags":[
        "development",
        "software"
    ],
    "wof:name":"Professional Access LLC",
    "wof:placetype":"venue"
},
  "geometry": {"coordinates":[-73.790723,40.972799],"type":"Point"}
}