{
  "type": "Feature",
  "properties": {
    "addr:full":"211 Edgecombe Ave New York NY 10030",
    "addr:housenumber":"211",
    "addr:postcode":"10030",
    "addr:street":"Edgecombe Ave",
    "iso:country":"US",
    "sg:address":"211 Edgecombe Ave",
    "sg:city":"New York",
    "sg:classifiers":[
        {
            "category":"Professional",
            "subcategory":"Management & Consulting",
            "type":"Services"
        }
    ],
    "sg:phone":"+1 212 862 8855",
    "sg:postcode":"10030",
    "sg:province":"NY",
    "sg:website":"www.phasepiggyback.org",
    "wof:name":"Nia Management Corp",
    "wof:placetype":"venue"
},
  "geometry": {"coordinates":[-73.944394,40.822342],"type":"Point"}
}