{
  "type": "Feature",
  "properties": {
    "iso:country":"US",
    "sg:address":"5126 Commercial Dr",
    "sg:city":"Yorkville",
    "sg:classifiers":[
        {
            "category":"Home & Garden",
            "subcategory":"Furniture",
            "type":"Retail Goods"
        }
    ],
    "sg:phone":"+1 315 736 0125",
    "sg:postcode":"13495",
    "sg:province":"NY",
    "sg:tags":[
        "equipment",
        "kitchen",
        "cabinet"
    ],
    "wof:name":"Vetere Designs",
    "wof:placetype":"venue"
},
  "geometry": {"coordinates":[-75.290474,43.114267],"type":"Point"}
}