{
  "type": "Feature",
  "properties": {
    "iso:country":"US",
    "sg:address":"35 S Main St",
    "sg:city":"Norfolk",
    "sg:classifiers":[
        {
            "category":"Food & Beverages",
            "subcategory":"Liquor & Beverages",
            "type":"Retail Goods"
        }
    ],
    "sg:phone":"+1 315 384 4532",
    "sg:postcode":"13667",
    "sg:province":"NY",
    "sg:tags":[
        "wine"
    ],
    "wof:name":"Norfolk Liquor Store",
    "wof:placetype":"venue"
},
  "geometry": {"coordinates":[-74.98654999999999,44.787878],"type":"Point"}
}