{
  "type": "Feature",
  "properties": {
    "iso:country":"US",
    "sg:address":"2290 South Rd",
    "sg:city":"Poughkeepsie",
    "sg:classifiers":[
        {
            "category":"Restaurant",
            "type":"Food & Drink"
        }
    ],
    "sg:menulink":"http://www.allmenus.com/ny/poughkeepsie/32304-crew/menu/",
    "sg:phone":"+1 845 462 5900",
    "sg:postcode":"12601",
    "sg:province":"NY",
    "sg:tags":[
        "american"
    ],
    "wof:name":"Crew",
    "wof:placetype":"venue"
},
  "geometry": {"coordinates":[-73.922736,41.646045],"type":"Point"}
}