{
  "type": "Feature",
  "properties": {
    "iso:country":"US",
    "sg:address":"212 Cornelia St",
    "sg:city":"Plattsburgh",
    "sg:classifiers":[
        {
            "category":"Health Services",
            "subcategory":"Doctor",
            "type":"Services"
        },
        {
            "category":"Community Center",
            "type":"Public Place"
        }
    ],
    "sg:phone":"+1 518 562 7100",
    "sg:postcode":"12901",
    "sg:province":"NY",
    "sg:tags":[
        "physician",
        "oncology",
        "surgeons",
        "medical",
        "gynecologic"
    ],
    "wof:name":"Cvph Medical Center",
    "wof:placetype":"venue"
},
  "geometry": {"coordinates":[-73.46923099999999,44.69817],"type":"Point"}
}