{
  "type": "Feature",
  "properties": {
    "addr:full":"34 Willoughby Street Brooklyn NY 11201",
    "addr:housenumber":"34",
    "addr:postcode":"11201",
    "addr:street":"Willoughby Street",
    "iso:country":"US",
    "sg:address":"34 Willoughby Street",
    "sg:city":"Brooklyn",
    "sg:classifiers":[
        {
            "category":"Shopping",
            "subcategory":"Mobile Phones",
            "type":"Retail Goods"
        },
        {
            "category":"Shopping",
            "subcategory":"Computers & Home Electronics",
            "type":"Retail Goods"
        }
    ],
    "sg:phone":"+1 718 858 8777",
    "sg:postcode":"11201",
    "sg:province":"NY",
    "sg:website":"www.radioshack.com",
    "wof:name":"Radioshack",
    "wof:placetype":"venue"
},
  "geometry": {"coordinates":[-73.98782199999999,40.69215],"type":"Point"}
}