{
  "type": "Feature",
  "properties": {
    "iso:country":"US",
    "sg:address":"64 E Main St",
    "sg:city":"Bay Shore",
    "sg:classifiers":[
        {
            "category":"Building & Trades",
            "subcategory":"Construction",
            "type":"Services"
        }
    ],
    "sg:phone":"+1 631 969 1300",
    "sg:postcode":"11706",
    "sg:province":"NY",
    "sg:tags":[
        "contractor"
    ],
    "wof:name":"Hyacinth",
    "wof:placetype":"venue"
},
  "geometry": {"coordinates":[-73.24630000000001,40.722599],"type":"Point"}
}