{
  "type": "Feature",
  "properties": {
    "addr:full":"1859 Tomlinson Avenue Bronx NY 10461",
    "addr:housenumber":"1859",
    "addr:postcode":"10461",
    "addr:street":"Tomlinson Avenue",
    "iso:country":"US",
    "sg:address":"1859 Tomlinson Avenue",
    "sg:city":"Bronx",
    "sg:classifiers":[
        {
            "category":"Building & Trades",
            "subcategory":"Construction",
            "type":"Services"
        }
    ],
    "sg:phone":"+1 718 892 3736",
    "sg:postcode":"10461",
    "sg:province":"NY",
    "sg:tags":[
        "contractor"
    ],
    "wof:name":"Iodice Genl Contractors",
    "wof:placetype":"venue"
},
  "geometry": {"coordinates":[-73.853824,40.85173],"type":"Point"}
}