{
  "type": "Feature",
  "properties": {
    "iso:country":"US",
    "sg:address":"248 Richfield Ave",
    "sg:city":"Syracuse",
    "sg:classifiers":[
        {
            "category":"Professional",
            "subcategory":"Management & Consulting",
            "type":"Services"
        }
    ],
    "sg:phone":"+1   ",
    "sg:postcode":"13205",
    "sg:province":"NY",
    "sg:tags":[
        "business"
    ],
    "wof:name":"Mc Millian Enterprises",
    "wof:placetype":"venue"
},
  "geometry": {"coordinates":[-76.14301399999999,42.988931],"type":"Point"}
}