{
  "type": "Feature",
  "properties": {
    "iso:country":"US",
    "sg:address":"319 Cairo Junction Rd",
    "sg:city":"Catskill",
    "sg:classifiers":[
        {
            "category":"Retail",
            "subcategory":"Animal Services",
            "type":"Services"
        }
    ],
    "sg:phone":"+1 518 943 4003",
    "sg:postcode":"12414",
    "sg:province":"NY",
    "sg:tags":[
        "horse",
        "training"
    ],
    "wof:name":"Mountain View Farm",
    "wof:placetype":"venue"
},
  "geometry": {"coordinates":[-73.949789,42.2499],"type":"Point"}
}