{
  "type": "Feature",
  "properties": {
    "iso:country":"US",
    "sg:address":"1491 2nd Avenue",
    "sg:city":"New York",
    "sg:classifiers":[
        {
            "category":"Personal",
            "subcategory":"Nail Salon",
            "type":"Services"
        }
    ],
    "sg:phone":"+1 212 327 1005",
    "sg:postcode":"10021",
    "sg:province":"NY",
    "wof:name":"Swiss Nails",
    "wof:placetype":"venue"
},
  "geometry": {"coordinates":[-73.95578500000001,40.772536],"type":"Point"}
}