{
  "type": "Feature",
  "properties": {
    "addr:full":"2530 21st Avenue Suite 234 New York NY 11105",
    "addr:housenumber":"2530;234",
    "addr:postcode":"11105",
    "addr:street":"21St Avenue Suite",
    "iso:country":"US",
    "sg:address":"2530 21st Avenue Suite 234",
    "sg:city":"New York",
    "sg:classifiers":[
        {
            "category":"Shopping",
            "subcategory":"Crafts & Fabrics",
            "type":"Retail Goods"
        }
    ],
    "sg:phone":"+1 718 204 0909",
    "sg:postcode":"11105",
    "sg:province":"NY",
    "sg:tags":[
        "art"
    ],
    "sg:website":"www.handcraftingjustice.org",
    "wof:name":"HandCrafting Justice",
    "wof:placetype":"venue"
},
  "geometry": {"coordinates":[-73.912024,40.780468],"type":"Point"}
}