{
  "type": "Feature",
  "properties": {
    "addr:full":"505 8th Ave New York NY 10018",
    "addr:housenumber":"505",
    "addr:postcode":"10018",
    "addr:street":"8Th Ave",
    "iso:country":"US",
    "sg:address":"505 8th Ave",
    "sg:city":"New York",
    "sg:classifiers":[
        {
            "category":"Sports & Exercise",
            "subcategory":"Sports Center",
            "type":"Entertainment"
        },
        {
            "category":"Arena",
            "subcategory":"Sports Club",
            "type":"Entertainment"
        }
    ],
    "sg:phone":"+1 718 932 1400",
    "sg:postcode":"10018",
    "sg:province":"NY",
    "sg:tags":[
        "professional",
        "amateur",
        "team"
    ],
    "wof:name":"New York Sports Club Astoria",
    "wof:placetype":"venue"
},
  "geometry": {"coordinates":[-73.992897,40.752998],"type":"Point"}
}