{
  "type": "Feature",
  "properties": {
    "iso:country":"US",
    "sg:address":"15 Fennell St",
    "sg:city":"Skaneateles",
    "sg:classifiers":[
        {
            "category":"Shopping",
            "subcategory":"Used Merchandise",
            "type":"Retail Goods"
        }
    ],
    "sg:phone":"+1   ",
    "sg:postcode":"13152",
    "sg:province":"NY",
    "wof:name":"Kids Exchange",
    "wof:placetype":"venue"
},
  "geometry": {"coordinates":[-76.43158,42.947193],"type":"Point"}
}