{
  "type": "Feature",
  "properties": {
    "addr:full":"3136 Winton Rd S Ste 203 Rochester NY 14623",
    "addr:housenumber":"3136",
    "addr:postcode":"14623",
    "addr:street":"Winton Rd S Ste 203",
    "iso:country":"US",
    "sg:address":"3136 Winton Rd S Ste 203",
    "sg:city":"Rochester",
    "sg:classifiers":[
        {
            "category":"Professional",
            "subcategory":"Advertising",
            "type":"Services"
        },
        {
            "category":"Professional",
            "subcategory":"Research",
            "type":"Services"
        }
    ],
    "sg:phone":"+1 585 272 9944",
    "sg:postcode":"14623",
    "sg:province":"NY",
    "sg:tags":[
        "marketing",
        "program",
        "market",
        "analysis"
    ],
    "sg:website":"http://www.geneseesurvey.com",
    "wof:name":"Genesee Survey Services, Inc",
    "wof:placetype":"venue"
},
  "geometry": {"coordinates":[-77.581976,43.091016],"type":"Point"}
}