{
  "type": "Feature",
  "properties": {
    "iso:country":"US",
    "sg:address":"23 Dartmouth Dr",
    "sg:city":"Plainview",
    "sg:classifiers":[
        {
            "category":"Building & Trades",
            "subcategory":"Construction",
            "type":"Services"
        }
    ],
    "sg:phone":"+1 516 349 7109",
    "sg:postcode":"11803",
    "sg:province":"NY",
    "sg:tags":[
        "installs",
        "clean",
        "carpet"
    ],
    "wof:name":"Michael Marder",
    "wof:placetype":"venue"
},
  "geometry": {"coordinates":[-73.482737,40.793355],"type":"Point"}
}