{
  "type": "Feature",
  "properties": {
    "addr:full":"760 Jericho Tpke Westbury NY 11590",
    "addr:housenumber":"760",
    "addr:postcode":"11590",
    "addr:street":"Jericho Tpke",
    "iso:country":"US",
    "sg:address":"760 Jericho Tpke",
    "sg:city":"Westbury",
    "sg:classifiers":[
        {
            "category":"Professional",
            "subcategory":"Accounting & Tax Preparation",
            "type":"Services"
        }
    ],
    "sg:phone":"+1   ",
    "sg:postcode":"11590",
    "sg:province":"NY",
    "wof:name":"Lipton Bernard",
    "wof:placetype":"venue"
},
  "geometry": {"coordinates":[-73.60551100000001,40.7626],"type":"Point"}
}