{
  "type": "Feature",
  "properties": {
    "iso:country":"US",
    "sg:address":"150 S 5th Ave",
    "sg:city":"Mount Vernon",
    "sg:classifiers":[
        {
            "category":"Real Estate",
            "subcategory":"Real Estate Agent",
            "type":"Services"
        }
    ],
    "sg:phone":"+1 914 664 1018",
    "sg:postcode":"10550",
    "sg:province":"NY",
    "sg:tags":[
        "operator",
        "manager",
        "apartment",
        "broker"
    ],
    "wof:name":"Macedonia Towers",
    "wof:placetype":"venue"
},
  "geometry": {"coordinates":[-73.836606,40.907763],"type":"Point"}
}