{
  "type": "Feature",
  "properties": {
    "iso:country":"US",
    "sg:address":"720 4th St",
    "sg:city":"Watervliet",
    "sg:classifiers":[
        {
            "category":"Wholesale",
            "subcategory":"Vending Machines",
            "type":"Manufacturing & Wholesale Goods"
        },
        {
            "category":"Food & Beverages",
            "subcategory":"Specialty",
            "type":"Retail Goods"
        }
    ],
    "sg:phone":"+1 518 273 1972",
    "sg:postcode":"12189",
    "sg:province":"NY",
    "sg:tags":[
        "bulk",
        "water",
        "company",
        "operator"
    ],
    "sg:website":"www.aramatic.com",
    "wof:name":"Aramatic Refreshment Services",
    "wof:placetype":"venue"
},
  "geometry": {"coordinates":[-73.71311799999999,42.710946],"type":"Point"}
}