{
  "type": "Feature",
  "properties": {
    "iso:country":"US",
    "sg:address":"11 Cayutaville Rd",
    "sg:city":"Newfield",
    "sg:classifiers":[
        {
            "category":"Organizations",
            "subcategory":"Religious Organization",
            "type":"Services"
        }
    ],
    "sg:phone":"+1 607 564 9994",
    "sg:postcode":"14867",
    "sg:province":"NY",
    "sg:tags":[
        "church"
    ],
    "wof:name":"Trumbulls Corners Community Ch",
    "wof:placetype":"venue"
},
  "geometry": {"coordinates":[-76.633574,42.383743],"type":"Point"}
}