{
  "type": "Feature",
  "properties": {
    "iso:country":"US",
    "sg:address":"360 Summit Hill Rd",
    "sg:city":"Jordanville",
    "sg:phone":"+1 315 858 0189",
    "sg:postcode":"13361",
    "sg:province":"NY",
    "sg:tags":[
        "farm",
        "corn"
    ],
    "wof:name":"Michael Barnhart",
    "wof:placetype":"venue"
},
  "geometry": {"coordinates":[-74.813261,42.868829],"type":"Point"}
}