{
  "type": "Feature",
  "properties": {
    "iso:country":"US",
    "sg:address":"48 Inverness Rd",
    "sg:city":"Scarsdale",
    "sg:phone":"+1 914 472 8779",
    "sg:postcode":"10583",
    "sg:province":"NY",
    "sg:tags":[
        "oil"
    ],
    "wof:name":"Almeida Oil Co",
    "wof:placetype":"venue"
},
  "geometry": {"coordinates":[-73.81786200000001,40.986526],"type":"Point"}
}