{
  "type": "Feature",
  "properties": {
    "iso:country":"US",
    "sg:address":"26 Main St",
    "sg:city":"Mt Kisco",
    "sg:classifiers":[
        {
            "category":"Travel",
            "subcategory":"Travel Agent",
            "type":"Entertainment"
        }
    ],
    "sg:phone":"+1 914 666 6681",
    "sg:postcode":"10549",
    "sg:province":"NY",
    "sg:tags":[
        "agency",
        "bureau"
    ],
    "sg:website":"www.geminitravelinc.com",
    "wof:name":"Gemini Travel Inc",
    "wof:placetype":"venue"
},
  "geometry": {"coordinates":[-73.72669399999999,41.206929],"type":"Point"}
}