{
  "type": "Feature",
  "properties": {
    "iso:country":"US",
    "sg:address":"1503 Canandaigua Rd",
    "sg:city":"Macedon",
    "sg:classifiers":[
        {
            "category":"Shopping",
            "subcategory":"Pharmacy",
            "type":"Retail Goods"
        }
    ],
    "sg:phone":"+1   ",
    "sg:postcode":"14502",
    "sg:province":"NY",
    "wof:name":"CVS",
    "wof:placetype":"venue"
},
  "geometry": {"coordinates":[-77.31993199999999,43.064049],"type":"Point"}
}