{
  "type": "Feature",
  "properties": {
    "iso:country":"US",
    "sg:address":"2446 Corning Rd Ste A",
    "sg:city":"Elmira",
    "sg:phone":"+1 607 734 0321",
    "sg:postcode":"14903",
    "sg:province":"NY",
    "wof:name":"Paramount Bowling Lanes",
    "wof:placetype":"venue"
},
  "geometry": {"coordinates":[-76.831991,42.146851],"type":"Point"}
}