{
  "type": "Feature",
  "properties": {
    "addr:full":"4966 Merrick Rd Massapequa Park NY 11762",
    "addr:housenumber":"4966",
    "addr:postcode":"11762",
    "addr:street":"Merrick Rd",
    "iso:country":"US",
    "sg:address":"4966 Merrick Rd",
    "sg:city":"Massapequa Park",
    "sg:classifiers":[
        {
            "category":"Banks & Credit Unions",
            "subcategory":"Bank",
            "type":"Services"
        }
    ],
    "sg:phone":"+1 516 935 9919",
    "sg:postcode":"11762",
    "sg:province":"NY",
    "wof:name":"North Fork Bank",
    "wof:placetype":"venue"
},
  "geometry": {"coordinates":[-73.452314,40.666396],"type":"Point"}
}