{
  "type": "Feature",
  "properties": {
    "addr:full":"2338 Slaterville Rd Ithaca NY 14850",
    "addr:housenumber":"2338",
    "addr:postcode":"14850",
    "addr:street":"Slaterville Rd",
    "iso:country":"US",
    "sg:address":"2338 Slaterville Rd",
    "sg:city":"Ithaca",
    "sg:classifiers":[
        {
            "category":"Freight",
            "type":"Transportation"
        }
    ],
    "sg:phone":"+1   ",
    "sg:postcode":"14850",
    "sg:province":"NY",
    "sg:tags":[
        "operator",
        "trucking"
    ],
    "wof:name":"Edward C Lott Inc",
    "wof:placetype":"venue"
},
  "geometry": {"coordinates":[-76.380167,42.395267],"type":"Point"}
}