{
  "type": "Feature",
  "properties": {
    "iso:country":"US",
    "sg:address":"35 Woodcrest Dr",
    "sg:city":"Hauppauge",
    "sg:classifiers":[
        {
            "category":"Building & Trades",
            "subcategory":"Construction",
            "type":"Services"
        }
    ],
    "sg:phone":"+1 631 348 0624",
    "sg:postcode":"11788",
    "sg:province":"NY",
    "sg:tags":[
        "carpentry",
        "contractor"
    ],
    "wof:name":"Custom Cut Carpentry Inc",
    "wof:placetype":"venue"
},
  "geometry": {"coordinates":[-73.21278700000001,40.820494],"type":"Point"}
}