{
  "type": "Feature",
  "properties": {
    "addr:full":"1745 Broadway New York NY 10019",
    "addr:housenumber":"1745",
    "addr:postcode":"10019",
    "addr:street":"Broadway",
    "iso:country":"US",
    "sg:address":"1745 Broadway",
    "sg:city":"New York",
    "sg:classifiers":[
        {
            "category":"Professional",
            "subcategory":"Computer Services",
            "type":"Services"
        }
    ],
    "sg:postcode":"10019",
    "sg:province":"NY",
    "sg:tags":[
        "virtual-game",
        "online-game",
        "games-online"
    ],
    "sg:website":"http://www.vroengardacademy.com/",
    "wof:name":"Vroengard Academy",
    "wof:placetype":"venue"
},
  "geometry": {"coordinates":[-73.982214,40.764832],"type":"Point"}
}