{
  "type": "Feature",
  "properties": {
    "addr:full":"637 Tifft St Buffalo NY 14220",
    "addr:housenumber":"637",
    "addr:postcode":"14220",
    "addr:street":"Tifft St",
    "iso:country":"US",
    "sg:address":"637 Tifft St",
    "sg:city":"Buffalo",
    "sg:classifiers":[
        {
            "category":"Autos & Motor Vehicles",
            "subcategory":"Automobile Sales",
            "type":"Retail Goods"
        },
        {
            "category":"Autos & Motor Vehicles",
            "subcategory":"Auto Supplies",
            "type":"Retail Goods"
        },
        {
            "category":"Retail",
            "subcategory":"Auto Repair",
            "type":"Services"
        }
    ],
    "sg:phone":"+1 716 824 4348",
    "sg:postcode":"14220",
    "sg:province":"NY",
    "sg:tags":[
        "shop",
        "accessory",
        "machine",
        "part",
        "supplies-used",
        "rebuilt",
        "salvage"
    ],
    "sg:website":"http://www.skywayauto.org",
    "wof:name":"Skyway Auto Parts Inc",
    "wof:placetype":"venue"
},
  "geometry": {"coordinates":[-78.837165,42.846988],"type":"Point"}
}