{
  "type": "Feature",
  "properties": {
    "addr:full":"950 Ridge Rd Webster NY 14580",
    "addr:housenumber":"950",
    "addr:postcode":"14580",
    "addr:street":"Ridge Rd",
    "iso:country":"US",
    "sg:address":"950 Ridge Rd",
    "sg:city":"Webster",
    "sg:classifiers":[
        {
            "category":"Shopping",
            "subcategory":"Hobbies, Toys, & Games",
            "type":"Retail Goods"
        }
    ],
    "sg:phone":"+1 585 671 6090",
    "sg:postcode":"14580",
    "sg:province":"NY",
    "sg:tags":[
        "supply"
    ],
    "wof:name":"EB Games",
    "wof:placetype":"venue"
},
  "geometry": {"coordinates":[-77.465975,43.207565],"type":"Point"}
}