{
  "type": "Feature",
  "properties": {
    "iso:country":"US",
    "sg:address":"106 W 32nd St",
    "sg:city":"New York",
    "sg:classifiers":[
        {
            "category":"Restaurant",
            "type":"Food & Drink"
        }
    ],
    "sg:menulink":"http://www.allmenus.com/ny/new-york/7680-blarney-stone/menu/",
    "sg:phone":"+1 212 695 6328",
    "sg:postcode":"10001",
    "sg:province":"NY",
    "sg:tags":[
        "american"
    ],
    "wof:name":"Blarney Stone",
    "wof:placetype":"venue"
},
  "geometry": {"coordinates":[-73.989357,40.748552],"type":"Point"}
}