{
  "type": "Feature",
  "properties": {
    "addr:full":"15 Red Roof Dr Port Chester NY 10573",
    "addr:housenumber":"15",
    "addr:postcode":"10573",
    "addr:street":"Red Roof Dr",
    "iso:country":"US",
    "sg:address":"15 Red Roof Dr",
    "sg:city":"Port Chester",
    "sg:classifiers":[
        {
            "category":"Professional",
            "subcategory":"Accounting & Tax Preparation",
            "type":"Services"
        }
    ],
    "sg:phone":"+1   ",
    "sg:postcode":"10573",
    "sg:province":"NY",
    "wof:name":"Peter M Gottlieb CPA",
    "wof:placetype":"venue"
},
  "geometry": {"coordinates":[-73.685382,41.019207],"type":"Point"}
}