{
  "type": "Feature",
  "properties": {
    "addr:full":"11241 175th Pl Jamaica NY 11433",
    "addr:housenumber":"11241",
    "addr:postcode":"11433",
    "addr:street":"175Th Pl",
    "iso:country":"US",
    "sg:address":"11241 175th Pl",
    "sg:city":"Jamaica",
    "sg:classifiers":[
        {
            "category":"Professional",
            "type":"Services"
        }
    ],
    "sg:phone":"+1 718 297 6796",
    "sg:postcode":"11433",
    "sg:province":"NY",
    "sg:tags":[
        "caterer"
    ],
    "wof:name":"International Caterers",
    "wof:placetype":"venue"
},
  "geometry": {"coordinates":[-73.781136,40.700294],"type":"Point"}
}