{
  "type": "Feature",
  "properties": {
    "addr:full":"264 W 35 St New York NY 10001",
    "addr:housenumber":"264",
    "addr:postcode":"10001",
    "addr:street":"W 35 St",
    "iso:country":"US",
    "sg:address":"264 W 35 St",
    "sg:city":"New York",
    "sg:classifiers":[
        {
            "category":"Wholesale",
            "subcategory":"Apparel",
            "type":"Manufacturing & Wholesale Goods"
        }
    ],
    "sg:phone":"+1 212 967 3320",
    "sg:postcode":"10001",
    "sg:province":"NY",
    "sg:tags":[
        "clothing"
    ],
    "wof:name":"Count Giuseppe Fashions Ltd",
    "wof:placetype":"venue"
},
  "geometry": {"coordinates":[-73.991607,40.752008],"type":"Point"}
}