{
  "type": "Feature",
  "properties": {
    "addr:full":"135 E 55 St New York NY 10022",
    "addr:housenumber":"135;55",
    "addr:postcode":"10022",
    "addr:street":"E;St",
    "iso:country":"US",
    "sg:address":"135 E 55 St",
    "sg:city":"New York",
    "sg:classifiers":[
        {
            "category":"Building & Trades",
            "subcategory":"Plumbing",
            "type":"Services"
        }
    ],
    "sg:phone":"+1 917 709 6463",
    "sg:postcode":"10022",
    "sg:province":"NY",
    "sg:tags":[
        "air"
    ],
    "wof:name":"Its A Breeze",
    "wof:placetype":"venue"
},
  "geometry": {"coordinates":[-73.96848,40.75895],"type":"Point"}
}