{
  "type": "Feature",
  "properties": {
    "addr:full":"155 E Route 59 Nanuet NY 10954",
    "addr:housenumber":"155",
    "addr:postcode":"10954",
    "addr:street":"E Route 59",
    "iso:country":"US",
    "sg:address":"155 E Route 59",
    "sg:city":"Nanuet",
    "sg:classifiers":[
        {
            "category":"Retail",
            "subcategory":"Veterinary Services",
            "type":"Services"
        }
    ],
    "sg:phone":"+1 845 624 2147",
    "sg:postcode":"10954",
    "sg:province":"NY",
    "sg:tags":[
        "clinic",
        "hospital",
        "veterinarian",
        "specialty"
    ],
    "sg:website":"http://www.banfield.net/ypoffer/?source=yp",
    "wof:name":"Banfield the Pet Hospital",
    "wof:placetype":"venue"
},
  "geometry": {"coordinates":[-74.00491599999999,41.094444],"type":"Point"}
}