{
  "type": "Feature",
  "properties": {
    "iso:country":"US",
    "sg:address":"6 Ridge Dr W",
    "sg:city":"Roslyn",
    "sg:classifiers":[
        {
            "category":"Restaurant",
            "type":"Food & Drink"
        }
    ],
    "sg:phone":"+1   ",
    "sg:postcode":"11576",
    "sg:province":"NY",
    "sg:tags":[
        "ice",
        "cream"
    ],
    "wof:name":"Three Beers Corp",
    "wof:placetype":"venue"
},
  "geometry": {"coordinates":[-73.66011399999999,40.800848],"type":"Point"}
}