{
  "type": "Feature",
  "properties": {
    "addr:full":"90 Washington Dr Centerport NY 11721",
    "addr:housenumber":"90",
    "addr:postcode":"11721",
    "addr:street":"Washington Dr",
    "iso:country":"US",
    "sg:address":"90 Washington Dr",
    "sg:city":"Centerport",
    "sg:classifiers":[
        {
            "category":"Shopping",
            "type":"Retail Goods"
        }
    ],
    "sg:phone":"+1 631 427 5757",
    "sg:postcode":"11721",
    "sg:province":"NY",
    "sg:tags":[
        "pet",
        "food",
        "supply"
    ],
    "wof:name":"Barkingham Palace",
    "wof:placetype":"venue"
},
  "geometry": {"coordinates":[-73.38514499999999,40.889531],"type":"Point"}
}