{
  "type": "Feature",
  "properties": {
    "iso:country":"US",
    "sg:address":"25 Surrey Dr",
    "sg:city":"Merrick",
    "sg:classifiers":[
        {
            "category":"Building & Trades",
            "subcategory":"Plumbing",
            "type":"Services"
        }
    ],
    "sg:phone":"+1 516 868 7126",
    "sg:postcode":"11566",
    "sg:province":"NY",
    "sg:tags":[
        "plumbing",
        "contractor"
    ],
    "wof:name":"Elite Plumbing & Heating",
    "wof:placetype":"venue"
},
  "geometry": {"coordinates":[-73.560177,40.679813],"type":"Point"}
}