{
  "type": "Feature",
  "properties": {
    "addr:full":"961 Washington Avenue Bronx NY 10456",
    "addr:housenumber":"961",
    "addr:postcode":"10456",
    "addr:street":"Washington Avenue",
    "iso:country":"US",
    "sg:address":"961 Washington Avenue",
    "sg:city":"Bronx",
    "sg:classifiers":[
        {
            "category":"Autos & Motor Vehicles",
            "subcategory":"Automobile Sales",
            "type":"Retail Goods"
        }
    ],
    "sg:phone":"+1 718 993 2800",
    "sg:postcode":"10456",
    "sg:province":"NY",
    "sg:tags":[
        "limo"
    ],
    "wof:name":"Original Uptown Car Svce",
    "wof:placetype":"venue"
},
  "geometry": {"coordinates":[-73.910481,40.825139],"type":"Point"}
}