{
  "type": "Feature",
  "properties": {
    "iso:country":"US",
    "sg:address":"9915 Seaview Ave",
    "sg:city":"Brooklyn",
    "sg:classifiers":[
        {
            "category":"Health Services",
            "subcategory":"Dentist",
            "type":"Services"
        }
    ],
    "sg:phone":"+1 718 763 7799",
    "sg:postcode":"11236",
    "sg:province":"NY",
    "wof:name":"Katz Alvin Dr",
    "wof:placetype":"venue"
},
  "geometry": {"coordinates":[-73.88800000000001,40.634998],"type":"Point"}
}