{
  "type": "Feature",
  "properties": {
    "addr:full":"4516 11th Ave Brooklyn NY 11219",
    "addr:housenumber":"4516",
    "addr:postcode":"11219",
    "addr:street":"11Th Ave",
    "iso:country":"US",
    "sg:address":"4516 11th Ave",
    "sg:city":"Brooklyn",
    "sg:classifiers":[
        {
            "category":"Home & Garden",
            "subcategory":"Home Furnishings",
            "type":"Retail Goods"
        }
    ],
    "sg:phone":"+1 718 436 4490",
    "sg:postcode":"11219",
    "sg:province":"NY",
    "sg:tags":[
        "blind",
        "window",
        "treatment",
        "shade"
    ],
    "wof:name":"Perfect Window Shade & Blind Co",
    "wof:placetype":"venue"
},
  "geometry": {"coordinates":[-73.9944,40.639999],"type":"Point"}
}