{
  "type": "Feature",
  "properties": {
    "addr:full":"249 W 17 St New York NY 10011",
    "addr:housenumber":"249",
    "addr:postcode":"10011",
    "addr:street":"W 17 St",
    "iso:country":"US",
    "sg:address":"249 W 17 St",
    "sg:city":"New York",
    "sg:classifiers":[
        {
            "category":"Communications",
            "type":"Services"
        }
    ],
    "sg:phone":"+1 212 463 6411",
    "sg:postcode":"10011",
    "sg:province":"NY",
    "wof:name":"Communications In Medicine",
    "wof:placetype":"venue"
},
  "geometry": {"coordinates":[-74.00003700000001,40.741146],"type":"Point"}
}