{
  "type": "Feature",
  "properties": {
    "addr:full":"314 Leggett Rd Champlain NY 12919",
    "addr:housenumber":"314",
    "addr:postcode":"12919",
    "addr:street":"Leggett Rd",
    "iso:country":"US",
    "sg:address":"314 Leggett Rd",
    "sg:city":"Champlain",
    "sg:classifiers":[
        {
            "category":"Building & Trades",
            "subcategory":"Construction",
            "type":"Services"
        }
    ],
    "sg:phone":"+1 518 298 5396",
    "sg:postcode":"12919",
    "sg:province":"NY",
    "sg:tags":[
        "wallcoverings-installation",
        "wallpaper",
        "painting",
        "contractor"
    ],
    "wof:name":"D D Painting",
    "wof:placetype":"venue"
},
  "geometry": {"coordinates":[-73.399638,44.961971],"type":"Point"}
}