{
  "type": "Feature",
  "properties": {
    "addr:full":"1050 Broad Hollow Rd Farmingdale NY 11735",
    "addr:housenumber":"1050",
    "addr:postcode":"11735",
    "addr:street":"Broad Hollow Rd",
    "iso:country":"US",
    "sg:address":"1050 Broad Hollow Rd",
    "sg:city":"Farmingdale",
    "sg:classifiers":[
        {
            "category":"Retail",
            "subcategory":"Auto Repair",
            "type":"Services"
        }
    ],
    "sg:phone":"+1   ",
    "sg:postcode":"11735",
    "sg:province":"NY",
    "sg:tags":[
        "general"
    ],
    "wof:name":"T L C Mobile Service Center",
    "wof:placetype":"venue"
},
  "geometry": {"coordinates":[-73.423496,40.734748],"type":"Point"}
}