{
  "type": "Feature",
  "properties": {
    "addr:full":"10022 Avenue L Brooklyn NY 11236",
    "addr:housenumber":"10022",
    "addr:postcode":"11236",
    "addr:street":"Avenue L",
    "iso:country":"US",
    "sg:address":"10022 Avenue L",
    "sg:city":"Brooklyn",
    "sg:classifiers":[
        {
            "category":"Professional",
            "subcategory":"Lawyer & Legal Services",
            "type":"Services"
        }
    ],
    "sg:phone":"+1 718 444 4088",
    "sg:postcode":"11236",
    "sg:province":"NY",
    "wof:name":"Oliver Ishelli",
    "wof:placetype":"venue"
},
  "geometry": {"coordinates":[-73.892589,40.64024],"type":"Point"}
}