{
  "type": "Feature",
  "properties": {
    "iso:country":"US",
    "sg:address":"245 Main St",
    "sg:city":"New Rochelle",
    "sg:classifiers":[
        {
            "category":"Shopping",
            "subcategory":"Stationery & Office Supplies",
            "type":"Retail Goods"
        }
    ],
    "sg:phone":"+1 914 632 2558",
    "sg:postcode":"10801",
    "sg:province":"NY",
    "sg:tags":[
        "stationer"
    ],
    "wof:name":"M & M Stationery",
    "wof:placetype":"venue"
},
  "geometry": {"coordinates":[-73.77184,40.914981],"type":"Point"}
}