{
  "type": "Feature",
  "properties": {
    "iso:country":"US",
    "sg:address":"120 White Plains Rd Ste 1",
    "sg:city":"Tarrytown",
    "sg:classifiers":[
        {
            "category":"Health Services",
            "subcategory":"Medical Lab",
            "type":"Services"
        },
        {
            "category":"Professional",
            "subcategory":"Employment Agencies",
            "type":"Services"
        }
    ],
    "sg:phone":"+1 914 220 5040",
    "sg:postcode":"10591",
    "sg:province":"NY",
    "sg:tags":[
        "employer"
    ],
    "wof:name":"National Alliance For Thrombosis And Thrombophilia",
    "wof:placetype":"venue"
},
  "geometry": {"coordinates":[-73.857597,41.063869],"type":"Point"}
}