{
  "type": "Feature",
  "properties": {
    "iso:country":"US",
    "sg:address":"1703 Monroe Ave",
    "sg:city":"Rochester",
    "sg:classifiers":[
        {
            "category":"Building & Trades",
            "subcategory":"Cleaning & Sanitation",
            "type":"Services"
        }
    ],
    "sg:phone":"+1 585 442 7090",
    "sg:postcode":"14618",
    "sg:province":"NY",
    "sg:tags":[
        "maid"
    ],
    "wof:name":"Maids Of Southeast Rochester",
    "wof:placetype":"venue"
},
  "geometry": {"coordinates":[-77.570809,43.132037],"type":"Point"}
}