{
  "type": "Feature",
  "properties": {
    "addr:full":"486 Troy Schenectady Rd Latham NY 12110",
    "addr:housenumber":"486",
    "addr:postcode":"12110",
    "addr:street":"Troy Schenectady Rd",
    "iso:country":"US",
    "sg:address":"486 Troy Schenectady Rd",
    "sg:city":"Latham",
    "sg:classifiers":[
        {
            "category":"Bars & Pubs",
            "type":"Food & Drink"
        }
    ],
    "sg:phone":"+1 518 783 6585",
    "sg:postcode":"12110",
    "sg:province":"NY",
    "wof:name":"First Step",
    "wof:placetype":"venue"
},
  "geometry": {"coordinates":[-73.760244,42.74756],"type":"Point"}
}