{
  "type": "Feature",
  "properties": {
    "addr:full":"2483 Jerome Ave Bronx NY 10468",
    "addr:housenumber":"2483",
    "addr:postcode":"10468",
    "addr:street":"Jerome Ave",
    "iso:country":"US",
    "sg:address":"2483 Jerome Ave",
    "sg:city":"Bronx",
    "sg:classifiers":[
        {
            "category":"Restaurant",
            "type":"Food & Drink"
        }
    ],
    "sg:menulink":"http://www.allmenus.com/ny/bronx/62492-choi-sun-express/menu/",
    "sg:phone":"+1 718 220 8588",
    "sg:postcode":"10468",
    "sg:province":"NY",
    "sg:tags":[
        "asian",
        "chinese"
    ],
    "wof:name":"Choi Sun Express",
    "wof:placetype":"venue"
},
  "geometry": {"coordinates":[-73.900593,40.863456],"type":"Point"}
}