{
  "type": "Feature",
  "properties": {
    "addr:full":"93 W Campbell Rd Schenectady NY 12306",
    "addr:housenumber":"93",
    "addr:postcode":"12306",
    "addr:street":"W Campbell Rd",
    "iso:country":"US",
    "sg:address":"93 W Campbell Rd",
    "sg:city":"Schenectady",
    "sg:classifiers":[
        {
            "category":"Shopping",
            "subcategory":"Department Store",
            "type":"Retail Goods"
        }
    ],
    "sg:phone":"+1 518 386 5222",
    "sg:postcode":"12306",
    "sg:province":"NY",
    "sg:website":"www.sears.com",
    "wof:name":"Sears Roebuck & Co",
    "wof:placetype":"venue"
},
  "geometry": {"coordinates":[-73.99139599999999,42.806142],"type":"Point"}
}