{
  "type": "Feature",
  "properties": {
    "addr:full":"407 Gidney Ave Newburgh NY 12550",
    "addr:housenumber":"407",
    "addr:postcode":"12550",
    "addr:street":"Gidney Ave",
    "iso:country":"US",
    "sg:address":"407 Gidney Ave",
    "sg:city":"Newburgh",
    "sg:classifiers":[
        {
            "category":"Health Services",
            "subcategory":"Doctor",
            "type":"Services"
        }
    ],
    "sg:phone":"+1 845 565 5550",
    "sg:postcode":"12550",
    "sg:province":"NY",
    "sg:tags":[
        "physician",
        "surgeon"
    ],
    "wof:name":"Neurological Associates",
    "wof:placetype":"venue"
},
  "geometry": {"coordinates":[-74.026027,41.513046],"type":"Point"}
}