{
  "type": "Feature",
  "properties": {
    "iso:country":"US",
    "sg:address":"926 State Hwy 6n",
    "sg:city":"Mahopac",
    "sg:classifiers":[
        {
            "category":"Recreation",
            "type":"Entertainment"
        }
    ],
    "sg:phone":"+1 845 621 4922",
    "sg:postcode":"10541",
    "sg:province":"NY",
    "wof:name":"Jumpin Jeepers",
    "wof:placetype":"venue"
},
  "geometry": {"coordinates":[-73.736751,41.372037],"type":"Point"}
}