{
  "type": "Feature",
  "properties": {
    "addr:full":"42 Celeste Ave Holbrook NY 11741",
    "addr:housenumber":"42",
    "addr:postcode":"11741",
    "addr:street":"Celeste Ave",
    "iso:country":"US",
    "sg:address":"42 Celeste Ave",
    "sg:city":"Holbrook",
    "sg:classifiers":[
        {
            "category":"Freight",
            "type":"Transportation"
        }
    ],
    "sg:phone":"+1   ",
    "sg:postcode":"11741",
    "sg:province":"NY",
    "sg:tags":[
        "operator",
        "local",
        "trucking"
    ],
    "wof:name":"Rbbm Trucking Co Inc",
    "wof:placetype":"venue"
},
  "geometry": {"coordinates":[-73.079646,40.791858],"type":"Point"}
}