{
  "type": "Feature",
  "properties": {
    "iso:country":"US",
    "sg:address":"34 State Hwy 17K",
    "sg:city":"Newburgh",
    "sg:classifiers":[
        {
            "category":"Professional",
            "subcategory":"Lawyer & Legal Services",
            "type":"Services"
        }
    ],
    "sg:phone":"+1 845 562 3366",
    "sg:postcode":"12550",
    "sg:province":"NY",
    "sg:tags":[
        "attorney"
    ],
    "wof:name":"Larkin Axelrod & Trachte",
    "wof:placetype":"venue"
},
  "geometry": {"coordinates":[-74.057863,41.503515],"type":"Point"}
}