{
  "type": "Feature",
  "properties": {
    "addr:full":"868 E Main St Riverhead NY 11901",
    "addr:housenumber":"868",
    "addr:postcode":"11901",
    "addr:street":"E Main St",
    "iso:country":"US",
    "sg:address":"868 E Main St",
    "sg:city":"Riverhead",
    "sg:classifiers":[
        {
            "category":"Banks & Credit Unions",
            "subcategory":"Financial Services",
            "type":"Services"
        }
    ],
    "sg:phone":"+1 631 208 3386",
    "sg:postcode":"11901",
    "sg:province":"NY",
    "sg:tags":[
        "trust",
        "management"
    ],
    "wof:name":"Alice Macdonald Estate ADM",
    "wof:placetype":"venue"
},
  "geometry": {"coordinates":[-72.65160299999999,40.923679],"type":"Point"}
}