{
  "type": "Feature",
  "properties": {
    "addr:full":"1166 Co Rd 114 Cochecton NY 12726",
    "addr:housenumber":"1166",
    "addr:postcode":"12726",
    "addr:street":"Co Rd 114",
    "iso:country":"US",
    "sg:address":"1166 Co Rd 114",
    "sg:city":"Cochecton",
    "sg:classifiers":[
        {
            "category":"Travel",
            "subcategory":"Hotels & Motels",
            "type":"Entertainment"
        }
    ],
    "sg:phone":"+1 845 932 8538",
    "sg:postcode":"12726",
    "sg:province":"NY",
    "sg:tags":[
        "breakfast",
        "accommodation",
        "bed"
    ],
    "sg:website":"www.fmlodge.com",
    "wof:name":"Fosterdale Motor Lodge",
    "wof:placetype":"venue"
},
  "geometry": {"coordinates":[-74.972184,41.707603],"type":"Point"}
}