{
  "type": "Feature",
  "properties": {
    "addr:full":"70 Broadway Hicksville NY 11801",
    "addr:housenumber":"70",
    "addr:postcode":"11801",
    "addr:street":"Broadway",
    "iso:country":"US",
    "sg:address":"70 Broadway",
    "sg:city":"Hicksville",
    "sg:classifiers":[
        {
            "category":"Personal",
            "subcategory":"Nail Salon",
            "type":"Services"
        }
    ],
    "sg:phone":"+1 516 822 3055",
    "sg:postcode":"11801",
    "sg:province":"NY",
    "wof:name":"Nail Art",
    "wof:placetype":"venue"
},
  "geometry": {"coordinates":[-73.524101,40.767399],"type":"Point"}
}