{
  "type": "Feature",
  "properties": {
    "addr:full":"1320 Grand Ave North Baldwin NY 11510",
    "addr:housenumber":"1320",
    "addr:postcode":"11510",
    "addr:street":"Grand Ave North",
    "iso:country":"US",
    "sg:address":"1320 Grand Ave",
    "sg:city":"North Baldwin",
    "sg:classifiers":[
        {
            "category":"Autos & Motor Vehicles",
            "subcategory":"Auto Supplies",
            "type":"Retail Goods"
        },
        {
            "category":"Retail",
            "subcategory":"Auto Repair",
            "type":"Services"
        }
    ],
    "sg:phone":"+1 516 223 2700",
    "sg:postcode":"11510",
    "sg:province":"NY",
    "sg:tags":[
        "tire"
    ],
    "wof:name":"Baldwin Tire Center Inc",
    "wof:placetype":"venue"
},
  "geometry": {"coordinates":[-73.614502,40.678101],"type":"Point"}
}