{
  "type": "Feature",
  "properties": {
    "addr:full":"302 Everingham Rd Syracuse NY 13205",
    "addr:housenumber":"302",
    "addr:postcode":"13205",
    "addr:street":"Everingham Rd",
    "iso:country":"US",
    "sg:address":"302 Everingham Rd",
    "sg:city":"Syracuse",
    "sg:classifiers":[
        {
            "category":"Retail",
            "subcategory":"Laundry & Dry Cleaning",
            "type":"Services"
        }
    ],
    "sg:phone":"+1 315 487 0526",
    "sg:postcode":"13205",
    "sg:province":"NY",
    "sg:tags":[
        "cleaners",
        "rug",
        "carpet"
    ],
    "wof:name":"ABC Chem Dry",
    "wof:placetype":"venue"
},
  "geometry": {"coordinates":[-76.150929,42.981705],"type":"Point"}
}