{
  "type": "Feature",
  "properties": {
    "iso:country":"US",
    "sg:address":"316 W 1st St S",
    "sg:city":"Fulton",
    "sg:classifiers":[
        {
            "category":"Shopping",
            "subcategory":"Bicycles & Sporting Goods",
            "type":"Retail Goods"
        }
    ],
    "sg:phone":"+1 315 592 4537",
    "sg:postcode":"13069",
    "sg:province":"NY",
    "sg:tags":[
        "security",
        "system",
        "rack"
    ],
    "wof:name":"Doyle's Bike Sales",
    "wof:placetype":"venue"
},
  "geometry": {"coordinates":[-76.41784199999999,43.315417],"type":"Point"}
}