{
  "type": "Feature",
  "properties": {
    "addr:full":"410 Fishkill Ave Beacon NY 12508",
    "addr:housenumber":"410",
    "addr:postcode":"12508",
    "addr:street":"Fishkill Ave",
    "iso:country":"US",
    "sg:address":"410 Fishkill Ave",
    "sg:city":"Beacon",
    "sg:classifiers":[
        {
            "category":"Autos & Motor Vehicles",
            "subcategory":"Automobile Sales",
            "type":"Retail Goods"
        }
    ],
    "sg:phone":"+1 845 831 1975",
    "sg:postcode":"12508",
    "sg:province":"NY",
    "sg:tags":[
        "car",
        "dealer"
    ],
    "sg:website":"www.healeybrothers.com",
    "wof:name":"Healey Chevrolet",
    "wof:placetype":"venue"
},
  "geometry": {"coordinates":[-73.948044,41.514861],"type":"Point"}
}