{
  "type": "Feature",
  "properties": {
    "iso:country":"US",
    "sg:address":"988 Tilbury Hill Rd",
    "sg:city":"Endicott",
    "sg:classifiers":[
        {
            "category":"Shopping",
            "subcategory":"Books",
            "type":"Retail Goods"
        }
    ],
    "sg:phone":"+1   ",
    "sg:postcode":"13760",
    "sg:province":"NY",
    "wof:name":"Cindys Cape Covers",
    "wof:placetype":"venue"
},
  "geometry": {"coordinates":[-76.14742099999999,42.09693],"type":"Point"}
}