{
  "type": "Feature",
  "properties": {
    "iso:country":"US",
    "sg:address":"179 MacDougal Street",
    "sg:city":"New York",
    "sg:classifiers":[
        {
            "category":"Personal",
            "subcategory":"Barber",
            "type":"Services"
        }
    ],
    "sg:phone":"+1 212 598 1001",
    "sg:postcode":"10011",
    "sg:province":"NY",
    "wof:name":"Alex & Son Barber Shop",
    "wof:placetype":"venue"
},
  "geometry": {"coordinates":[-73.998203,40.732889],"type":"Point"}
}