{
  "type": "Feature",
  "properties": {
    "iso:country":"US",
    "sg:address":"55 Bay St",
    "sg:city":"Glens Falls",
    "sg:classifiers":[
        {
            "category":"Retail",
            "subcategory":"Animal Services",
            "type":"Services"
        }
    ],
    "sg:phone":"+1 518 793 4048",
    "sg:postcode":"12801",
    "sg:province":"NY",
    "sg:tags":[
        "pet"
    ],
    "wof:name":"Warren County SPCA",
    "wof:placetype":"venue"
},
  "geometry": {"coordinates":[-73.64724099999999,43.313435],"type":"Point"}
}