{
  "type": "Feature",
  "properties": {
    "addr:full":"15 Gardenia Ave Hampton Bays NY 11946",
    "addr:housenumber":"15",
    "addr:postcode":"11946",
    "addr:street":"Gardenia Ave",
    "iso:country":"US",
    "sg:address":"15 Gardenia Ave",
    "sg:city":"Hampton Bays",
    "sg:classifiers":[
        {
            "category":"Building & Trades",
            "subcategory":"Landscaping Services",
            "type":"Services"
        }
    ],
    "sg:phone":"+1 631 723 2835",
    "sg:postcode":"11946",
    "sg:province":"NY",
    "wof:name":"Knatz Lawn Bob Maintenance",
    "wof:placetype":"venue"
},
  "geometry": {"coordinates":[-72.50676199999999,40.864813],"type":"Point"}
}