{
  "type": "Feature",
  "properties": {
    "addr:full":"2602 State Rte 5 and 20 Stanley NY 14561",
    "addr:housenumber":"2602",
    "addr:postcode":"14561",
    "addr:street":"State Rte 5 And 20",
    "iso:country":"US",
    "sg:address":"2602 State Rte 5 and 20",
    "sg:city":"Stanley",
    "sg:classifiers":[
        {
            "category":"Building & Trades",
            "subcategory":"Construction",
            "type":"Services"
        }
    ],
    "sg:phone":"+1 585 329 8669",
    "sg:postcode":"14561",
    "sg:province":"NY",
    "sg:tags":[
        "house"
    ],
    "wof:name":"B K H Construction",
    "wof:placetype":"venue"
},
  "geometry": {"coordinates":[-77.125407,42.861083],"type":"Point"}
}