{
  "type": "Feature",
  "properties": {
    "addr:full":"79 Guernsey St Brooklyn NY 11222",
    "addr:housenumber":"79",
    "addr:postcode":"11222",
    "addr:street":"Guernsey St",
    "iso:country":"US",
    "sg:address":"79 Guernsey St",
    "sg:city":"Brooklyn",
    "sg:classifiers":[
        {
            "category":"Manufacturing",
            "subcategory":"Paper Products",
            "type":"Manufacturing & Wholesale Goods"
        }
    ],
    "sg:phone":"+1 718 599 7857",
    "sg:postcode":"11222",
    "sg:province":"NY",
    "sg:tags":[
        "making",
        "material",
        "fine",
        "mfg"
    ],
    "sg:website":"www.carriagehousepaper.com",
    "wof:name":"Carriage House Paper Company",
    "wof:placetype":"venue"
},
  "geometry": {"coordinates":[-73.953214,40.724153],"type":"Point"}
}