{
  "type": "Feature",
  "properties": {
    "iso:country":"US",
    "sg:address":"230 Duffy Ave",
    "sg:city":"Hicksville",
    "sg:classifiers":[
        {
            "category":"Wholesale",
            "subcategory":"Fruits & Vegetables",
            "type":"Manufacturing & Wholesale Goods"
        }
    ],
    "sg:phone":"+1 516 932 7282",
    "sg:postcode":"11801",
    "sg:province":"NY",
    "sg:tags":[
        "veggie"
    ],
    "wof:name":"Atlantic Banana",
    "wof:placetype":"venue"
},
  "geometry": {"coordinates":[-73.53479799999999,40.7644],"type":"Point"}
}