{
  "type": "Feature",
  "properties": {
    "iso:country":"US",
    "sg:address":"696 Colby St",
    "sg:city":"Spencerport",
    "sg:classifiers":[
        {
            "category":"Farming",
            "subcategory":"Farm",
            "type":"Manufacturing & Wholesale Goods"
        },
        {
            "category":"Social Services",
            "type":"Services"
        }
    ],
    "sg:phone":"+1 585 352 5320",
    "sg:postcode":"14559",
    "sg:province":"NY",
    "sg:tags":[
        "business",
        "association"
    ],
    "wof:name":"Springdale Farms",
    "wof:placetype":"venue"
},
  "geometry": {"coordinates":[-77.87188500000001,43.179608],"type":"Point"}
}