{
  "type": "Feature",
  "properties": {
    "addr:full":"1616 Summerfield St Ridgewood NY 11385",
    "addr:housenumber":"1616",
    "addr:postcode":"11385",
    "addr:street":"Summerfield St",
    "iso:country":"US",
    "sg:address":"1616 Summerfield St",
    "sg:city":"Ridgewood",
    "sg:classifiers":[
        {
            "category":"Manufacturing",
            "subcategory":"Textiles",
            "type":"Manufacturing & Wholesale Goods"
        }
    ],
    "sg:phone":"+1 718 381 7300",
    "sg:postcode":"11385",
    "sg:province":"NY",
    "sg:tags":[
        "goods-wholesale",
        "knit",
        "manufacturer"
    ],
    "wof:name":"Sarug Inc.",
    "wof:placetype":"venue"
},
  "geometry": {"coordinates":[-73.902182,40.695025],"type":"Point"}
}