{
  "type": "Feature",
  "properties": {
    "iso:country":"US",
    "sg:address":"19 Central Ave",
    "sg:city":"Chatham",
    "sg:classifiers":[
        {
            "category":"Real Estate",
            "subcategory":"Architect",
            "type":"Services"
        }
    ],
    "sg:phone":"+1 518 392 2979",
    "sg:postcode":"12047",
    "sg:province":"NY",
    "wof:name":"Stoller Architecture",
    "wof:placetype":"venue"
},
  "geometry": {"coordinates":[-73.704449,42.767998],"type":"Point"}
}