{
  "type": "Feature",
  "properties": {
    "iso:country":"US",
    "sg:address":"3993 Jordanville Rd",
    "sg:city":"Jordanville",
    "sg:classifiers":[
        {
            "category":"Farming",
            "subcategory":"Farm",
            "type":"Manufacturing & Wholesale Goods"
        }
    ],
    "sg:phone":"+1 315 858 0311",
    "sg:postcode":"13361",
    "sg:province":"NY",
    "sg:tags":[
        "crop",
        "general"
    ],
    "wof:name":"Spring Lawn Farm",
    "wof:placetype":"venue"
},
  "geometry": {"coordinates":[-74.841346,42.908522],"type":"Point"}
}