{
  "type": "Feature",
  "properties": {
    "iso:country":"US",
    "sg:address":"4027 Main St",
    "sg:city":"Flushing",
    "sg:classifiers":[
        {
            "category":"Bars & Pubs",
            "type":"Food & Drink"
        }
    ],
    "sg:menulink":"http://www.allmenus.com/ny/queens/51964-barone-pizza/menu/",
    "sg:phone":"+1 718 463 2218",
    "sg:postcode":"11354",
    "sg:province":"NY",
    "sg:tags":[
        "italian"
    ],
    "wof:name":"Barone Pizza",
    "wof:placetype":"venue"
},
  "geometry": {"coordinates":[-73.82969199999999,40.758752],"type":"Point"}
}