{
  "type": "Feature",
  "properties": {
    "addr:full":"7 Bond St Frnt New York NY 10012",
    "addr:housenumber":"7",
    "addr:postcode":"10012",
    "addr:street":"Bond St",
    "iso:country":"US",
    "sg:address":"7 Bond St Frnt",
    "sg:city":"New York",
    "sg:classifiers":[
        {
            "category":"Shopping",
            "subcategory":"Optician",
            "type":"Retail Goods"
        },
        {
            "category":"Shopping",
            "subcategory":"Clothing, Apparel, & Fashions",
            "type":"Retail Goods"
        }
    ],
    "sg:phone":"+1 212 677 7690",
    "sg:postcode":"10012",
    "sg:province":"NY",
    "sg:tags":[
        "eyewear",
        "accessory"
    ],
    "wof:name":"Bond 07",
    "wof:placetype":"venue"
},
  "geometry": {"coordinates":[-73.99430099999999,40.726898],"type":"Point"}
}