{
  "type": "Feature",
  "properties": {
    "iso:country":"US",
    "sg:address":"3481 Randall Rd",
    "sg:city":"Ransomville",
    "sg:classifiers":[
        {
            "category":"Building & Trades",
            "subcategory":"Landscaping Services",
            "type":"Services"
        }
    ],
    "sg:phone":"+1 716 791 8116",
    "sg:postcode":"14131",
    "sg:province":"NY",
    "wof:name":"Russell Williams",
    "wof:placetype":"venue"
},
  "geometry": {"coordinates":[-78.870307,43.249133],"type":"Point"}
}