{
  "type": "Feature",
  "properties": {
    "addr:full":"7153 Fish House Rd Galway NY 12074",
    "addr:housenumber":"7153",
    "addr:postcode":"12074",
    "addr:street":"Fish House Rd",
    "iso:country":"US",
    "sg:address":"7153 Fish House Rd",
    "sg:city":"Galway",
    "sg:classifiers":[
        {
            "category":"Place Of Worship",
            "subcategory":"Church",
            "type":"Public Place"
        },
        {
            "category":"Place Of Worship",
            "type":"Public Place"
        }
    ],
    "sg:phone":"+1 518 883 5221",
    "sg:postcode":"12074",
    "sg:province":"NY",
    "sg:tags":[
        "churches-baptist-general",
        "churches-baptist"
    ],
    "wof:name":"Providence Baptist Church",
    "wof:placetype":"venue"
},
  "geometry": {"coordinates":[-74.100121,43.076839],"type":"Point"}
}