{
  "type": "Feature",
  "properties": {
    "iso:country":"US",
    "sg:address":"6168 Monitor Way",
    "sg:city":"Cicero",
    "sg:classifiers":[
        {
            "category":"Professional",
            "subcategory":"Computer Services",
            "type":"Services"
        }
    ],
    "sg:phone":"+1 315 698 2547",
    "sg:postcode":"13039",
    "sg:province":"NY",
    "sg:tags":[
        "internet"
    ],
    "wof:name":"Pete's Web Sites",
    "wof:placetype":"venue"
},
  "geometry": {"coordinates":[-76.096447,43.179411],"type":"Point"}
}