{
  "type": "Feature",
  "properties": {
    "iso:country":"US",
    "sg:address":"56 E 170th St",
    "sg:city":"Bronx",
    "sg:classifiers":[
        {
            "category":"Professional",
            "subcategory":"Accounting & Tax Preparation",
            "type":"Services"
        }
    ],
    "sg:phone":"+1 718 410 9100",
    "sg:postcode":"10452",
    "sg:province":"NY",
    "sg:tags":[
        "return",
        "filing"
    ],
    "wof:name":"Jackson Hewitt Tax Svc",
    "wof:placetype":"venue"
},
  "geometry": {"coordinates":[-73.917276,40.840046],"type":"Point"}
}