{
  "type": "Feature",
  "properties": {
    "addr:full":"280 Lafayette Ave Brooklyn NY 11238",
    "addr:housenumber":"280",
    "addr:postcode":"11238",
    "addr:street":"Lafayette Ave",
    "iso:country":"US",
    "sg:address":"280 Lafayette Ave",
    "sg:city":"Brooklyn",
    "sg:classifiers":[
        {
            "category":"Professional",
            "subcategory":"Computer Services",
            "type":"Services"
        }
    ],
    "sg:phone":"+1 718 789 2313",
    "sg:postcode":"11238",
    "sg:province":"NY",
    "sg:tags":[
        "consultant",
        "designer"
    ],
    "wof:name":"Nsoroma",
    "wof:placetype":"venue"
},
  "geometry": {"coordinates":[-73.965822,40.688209],"type":"Point"}
}