{
  "type": "Feature",
  "properties": {
    "iso:country":"US",
    "sg:address":"95 Cliff St",
    "sg:city":"Canajoharie",
    "sg:classifiers":[
        {
            "category":"Health Services",
            "subcategory":"Health Practitioner",
            "type":"Services"
        }
    ],
    "sg:phone":"+1 518 438 0484",
    "sg:postcode":"13317",
    "sg:province":"NY",
    "wof:name":"Walter J Finnegan",
    "wof:placetype":"venue"
},
  "geometry": {"coordinates":[-74.57683900000001,42.904607],"type":"Point"}
}