{
  "type": "Feature",
  "properties": {
    "addr:full":"27 Farragut Ave Hastings On Hdsn NY 10706",
    "addr:housenumber":"27",
    "addr:postcode":"10706",
    "addr:street":"Farragut Ave",
    "iso:country":"US",
    "sg:address":"27 Farragut Ave",
    "sg:city":"Hastings On Hdsn",
    "sg:classifiers":[
        {
            "category":"Education",
            "subcategory":"School",
            "type":"Public Place"
        }
    ],
    "sg:phone":"+1 914 478 2900",
    "sg:postcode":"10706",
    "sg:province":"NY",
    "wof:name":"Hastings Board Of Education",
    "wof:placetype":"venue"
},
  "geometry": {"coordinates":[-73.877516,40.994408],"type":"Point"}
}