{
  "type": "Feature",
  "properties": {
    "addr:full":"47 Salisbury Rd Delmar NY 12054",
    "addr:housenumber":"47",
    "addr:postcode":"12054",
    "addr:street":"Salisbury Rd",
    "iso:country":"US",
    "sg:address":"47 Salisbury Rd",
    "sg:city":"Delmar",
    "sg:classifiers":[
        {
            "category":"Shopping",
            "subcategory":"Used Merchandise",
            "type":"Retail Goods"
        }
    ],
    "sg:phone":"+1 518 439 2507",
    "sg:postcode":"12054",
    "sg:province":"NY",
    "sg:tags":[
        "antique"
    ],
    "wof:name":"Bill N' Lou's Antiques",
    "wof:placetype":"venue"
},
  "geometry": {"coordinates":[-73.81850300000001,42.632568],"type":"Point"}
}