{
  "type": "Feature",
  "properties": {
    "iso:country":"US",
    "sg:address":"5162 Woodlawn Dr",
    "sg:city":"Schenectady",
    "sg:classifiers":[
        {
            "category":"Organizations",
            "subcategory":"Religious Organization",
            "type":"Services"
        }
    ],
    "sg:phone":"+1 518 356 7108",
    "sg:postcode":"12303",
    "sg:province":"NY",
    "sg:tags":[
        "clergy"
    ],
    "wof:name":"Susan M Morrison",
    "wof:placetype":"venue"
},
  "geometry": {"coordinates":[-73.938332,42.722437],"type":"Point"}
}