{
  "type": "Feature",
  "properties": {
    "addr:full":"380 Lexington Ave New York NY 10017",
    "addr:housenumber":"380",
    "addr:postcode":"10017",
    "addr:street":"Lexington Ave",
    "iso:country":"US",
    "sg:address":"380 Lexington Ave",
    "sg:city":"New York",
    "sg:classifiers":[
        {
            "category":"Professional",
            "subcategory":"Advertising",
            "type":"Services"
        }
    ],
    "sg:phone":"+1 212 551 1048",
    "sg:postcode":"10017",
    "sg:province":"NY",
    "wof:name":"Enterprise Cable Network",
    "wof:placetype":"venue"
},
  "geometry": {"coordinates":[-73.976236,40.751255],"type":"Point"}
}