{
  "type": "Feature",
  "properties": {
    "addr:full":"116 N Central Ave Hartsdale NY 10530",
    "addr:housenumber":"116",
    "addr:postcode":"10530",
    "addr:street":"N Central Ave",
    "iso:country":"US",
    "sg:address":"116 N Central Ave",
    "sg:city":"Hartsdale",
    "sg:classifiers":[
        {
            "category":"Health Services",
            "subcategory":"Chiropractor",
            "type":"Services"
        }
    ],
    "sg:phone":"+1 914 686 8899",
    "sg:postcode":"10530",
    "sg:province":"NY",
    "wof:name":"Kenneth M Trotta DC",
    "wof:placetype":"venue"
},
  "geometry": {"coordinates":[-73.79759199999999,41.019875],"type":"Point"}
}