{
  "type": "Feature",
  "properties": {
    "addr:full":"512 55th St Brooklyn NY 11220",
    "addr:housenumber":"512",
    "addr:postcode":"11220",
    "addr:street":"55Th St",
    "iso:country":"US",
    "sg:address":"512 55th St",
    "sg:city":"Brooklyn",
    "sg:classifiers":[
        {
            "category":"Real Estate",
            "subcategory":"Real Estate Agent",
            "type":"Services"
        }
    ],
    "sg:phone":"+1 718 492 7882",
    "sg:postcode":"11220",
    "sg:province":"NY",
    "wof:name":"Monte's Real Estate",
    "wof:placetype":"venue"
},
  "geometry": {"coordinates":[-74.01128,40.641079],"type":"Point"}
}