{
  "type": "Feature",
  "properties": {
    "iso:country":"US",
    "sg:address":"107 Saybrook Ln",
    "sg:city":"De Witt",
    "sg:classifiers":[
        {
            "category":"Building & Trades",
            "subcategory":"Landscaping Services",
            "type":"Services"
        }
    ],
    "sg:phone":"+1 315 446 0102",
    "sg:postcode":"13214",
    "sg:province":"NY",
    "sg:tags":[
        "designer",
        "landscape"
    ],
    "wof:name":"Landscape & Prospect",
    "wof:placetype":"venue"
},
  "geometry": {"coordinates":[-76.075148,43.030264],"type":"Point"}
}