{
  "type": "Feature",
  "properties": {
    "addr:full":"1329 E 65th St Brooklyn NY 11234",
    "addr:housenumber":"1329",
    "addr:postcode":"11234",
    "addr:street":"E 65Th St",
    "iso:country":"US",
    "sg:address":"1329 E 65th St",
    "sg:city":"Brooklyn",
    "sg:classifiers":[
        {
            "category":"Bus Charters",
            "type":"Transportation"
        }
    ],
    "sg:phone":"+1   ",
    "sg:postcode":"11234",
    "sg:province":"NY",
    "sg:tags":[
        "local"
    ],
    "wof:name":"La Express Limousines Ltd",
    "wof:placetype":"venue"
},
  "geometry": {"coordinates":[-73.915521,40.620723],"type":"Point"}
}