{
  "type": "Feature",
  "properties": {
    "iso:country":"US",
    "sg:address":"306 E State St",
    "sg:city":"Ithaca",
    "sg:classifiers":[
        {
            "category":"Social Services",
            "type":"Services"
        }
    ],
    "sg:phone":"+1 607 272 0034",
    "sg:postcode":"14850",
    "sg:province":"NY",
    "sg:tags":[
        "organization",
        "welfare"
    ],
    "sg:website":"www.nysccc.org",
    "wof:name":"New York State Citizens Coal",
    "wof:placetype":"venue"
},
  "geometry": {"coordinates":[-76.495419,42.439693],"type":"Point"}
}