{
  "type": "Feature",
  "properties": {
    "addr:full":"38 Downhill Ln Wantagh NY 11793",
    "addr:housenumber":"38",
    "addr:postcode":"11793",
    "addr:street":"Downhill Ln",
    "iso:country":"US",
    "sg:address":"38 Downhill Ln",
    "sg:city":"Wantagh",
    "sg:classifiers":[
        {
            "category":"Recreation",
            "type":"Entertainment"
        }
    ],
    "sg:phone":"+1 516 221 9811",
    "sg:postcode":"11793",
    "sg:province":"NY",
    "sg:tags":[
        "skating",
        "rink"
    ],
    "wof:name":"Top Shelf Roller Hockey",
    "wof:placetype":"venue"
},
  "geometry": {"coordinates":[-73.51134399999999,40.697694],"type":"Point"}
}