{
  "type": "Feature",
  "properties": {
    "iso:country":"US",
    "sg:address":"2 Newark St",
    "sg:city":"Phelps",
    "sg:classifiers":[
        {
            "category":"Food & Beverages",
            "subcategory":"Bakery",
            "type":"Retail Goods"
        }
    ],
    "sg:phone":"+1 315 548 9467",
    "sg:postcode":"14532",
    "sg:province":"NY",
    "sg:tags":[
        "baker"
    ],
    "wof:name":"Dollars To Donuts",
    "wof:placetype":"venue"
},
  "geometry": {"coordinates":[-77.07561099999999,42.963815],"type":"Point"}
}