{
  "type": "Feature",
  "properties": {
    "iso:country":"US",
    "sg:address":"43 Santino Ct",
    "sg:city":"Mahopac",
    "sg:classifiers":[
        {
            "category":"Manufacturing",
            "subcategory":"Tools & Machinery",
            "type":"Manufacturing & Wholesale Goods"
        }
    ],
    "sg:phone":"+1   ",
    "sg:postcode":"10541",
    "sg:province":"NY",
    "sg:tags":[
        "x",
        "mfg"
    ],
    "wof:name":"Xr Concepts",
    "wof:placetype":"venue"
},
  "geometry": {"coordinates":[-73.779859,41.387186],"type":"Point"}
}