{
  "type": "Feature",
  "properties": {
    "iso:country":"US",
    "sg:address":"608 Ford St Ste 1",
    "sg:city":"Ogdensburg",
    "sg:classifiers":[
        {
            "category":"Restaurant",
            "type":"Food & Drink"
        }
    ],
    "sg:phone":"+1 315 393 3474",
    "sg:postcode":"13669",
    "sg:province":"NY",
    "wof:name":"Fish'er Chips",
    "wof:placetype":"venue"
},
  "geometry": {"coordinates":[-75.488822,44.699326],"type":"Point"}
}