{
  "type": "Feature",
  "properties": {
    "addr:full":"53 Montrose Ave Brooklyn NY 11206",
    "addr:housenumber":"53",
    "addr:postcode":"11206",
    "addr:street":"Montrose Ave",
    "iso:country":"US",
    "sg:address":"53 Montrose Ave",
    "sg:city":"Brooklyn",
    "sg:classifiers":[
        {
            "category":"Food & Beverages",
            "subcategory":"Groceries & Convenience Stores",
            "type":"Retail Goods"
        }
    ],
    "sg:phone":"+1   ",
    "sg:postcode":"11206",
    "sg:province":"NY",
    "wof:name":"Elly Deli Grocery",
    "wof:placetype":"venue"
},
  "geometry": {"coordinates":[-73.946691,40.707066],"type":"Point"}
}