{
  "type": "Feature",
  "properties": {
    "addr:full":"199 Loines Ave Merrick NY 11566",
    "addr:housenumber":"199",
    "addr:postcode":"11566",
    "addr:street":"Loines Ave",
    "iso:country":"US",
    "sg:address":"199 Loines Ave",
    "sg:city":"Merrick",
    "sg:classifiers":[
        {
            "category":"Health Services",
            "subcategory":"Chiropractor",
            "type":"Services"
        }
    ],
    "sg:phone":"+1 516 771 0632",
    "sg:postcode":"11566",
    "sg:province":"NY",
    "sg:tags":[
        "chiropractic"
    ],
    "wof:name":"Lagueras, Peter",
    "wof:placetype":"venue"
},
  "geometry": {"coordinates":[-73.544617,40.671497],"type":"Point"}
}