{
  "type": "Feature",
  "properties": {
    "addr:full":"121 McKinley Ave Brooklyn NY 11208",
    "addr:housenumber":"121",
    "addr:postcode":"11208",
    "addr:street":"Mckinley Ave",
    "iso:country":"US",
    "sg:address":"121 McKinley Ave",
    "sg:city":"Brooklyn",
    "sg:classifiers":[
        {
            "category":"Professional",
            "type":"Services"
        }
    ],
    "sg:phone":"+1 718 647 5454",
    "sg:postcode":"11208",
    "sg:province":"NY",
    "sg:tags":[
        "establishment"
    ],
    "wof:name":"Symex Inc",
    "wof:placetype":"venue"
},
  "geometry": {"coordinates":[-73.872523,40.679338],"type":"Point"}
}