{
  "type": "Feature",
  "properties": {
    "addr:full":"20 Central Park Plz Buffalo NY 14214",
    "addr:housenumber":"20",
    "addr:postcode":"14214",
    "addr:street":"Central Park Plz",
    "iso:country":"US",
    "sg:address":"20 Central Park Plz",
    "sg:city":"Buffalo",
    "sg:classifiers":[
        {
            "category":"Organizations",
            "subcategory":"Religious Organization",
            "type":"Services"
        }
    ],
    "sg:phone":"+1 716 834 5951",
    "sg:postcode":"14214",
    "sg:province":"NY",
    "sg:tags":[
        "church"
    ],
    "wof:name":"Elim Christian Fellowship",
    "wof:placetype":"venue"
},
  "geometry": {"coordinates":[-78.833039,42.938413],"type":"Point"}
}