{
  "type": "Feature",
  "properties": {
    "addr:full":"2196 Nesconset Hwy Stony Brook NY 11790",
    "addr:housenumber":"2196",
    "addr:postcode":"11790",
    "addr:street":"Nesconset Hwy",
    "iso:country":"US",
    "sg:address":"2196 Nesconset Hwy",
    "sg:city":"Stony Brook",
    "sg:classifiers":[
        {
            "category":"Cinema",
            "subcategory":"Movie Theater",
            "type":"Entertainment"
        }
    ],
    "sg:phone":"+1 631 941 0124",
    "sg:postcode":"11790",
    "sg:province":"NY",
    "wof:name":"Loews Stonybrook Theatre",
    "wof:placetype":"venue"
},
  "geometry": {"coordinates":[-73.106762,40.883123],"type":"Point"}
}