{
  "type": "Feature",
  "properties": {
    "iso:country":"US",
    "sg:address":"115 Central Park W",
    "sg:city":"New York",
    "sg:classifiers":[
        {
            "category":"Health Services",
            "subcategory":"Doctor",
            "type":"Services"
        }
    ],
    "sg:phone":"+1 212 877 2100",
    "sg:postcode":"10023",
    "sg:province":"NY",
    "sg:tags":[
        "medical",
        "practice",
        "family"
    ],
    "wof:name":"Neufeld Richard R MD",
    "wof:placetype":"venue"
},
  "geometry": {"coordinates":[-73.976658,40.776035],"type":"Point"}
}