{
  "type": "Feature",
  "properties": {
    "iso:country":"US",
    "sg:address":"8260 Main St",
    "sg:city":"Hammondsport",
    "sg:classifiers":[
        {
            "category":"Travel",
            "subcategory":"Hotels & Motels",
            "type":"Entertainment"
        }
    ],
    "sg:phone":"+1 607 569 2984",
    "sg:postcode":"14840",
    "sg:province":"NY",
    "sg:tags":[
        "breakfast",
        "accommodation",
        "bed"
    ],
    "wof:name":"Berry Basket Bed & Breakfast",
    "wof:placetype":"venue"
},
  "geometry": {"coordinates":[-77.22209599999999,42.40187],"type":"Point"}
}