{
  "type": "Feature",
  "properties": {
    "addr:full":"369 3 Ave New York NY 10016",
    "addr:housenumber":"369",
    "addr:postcode":"10016",
    "addr:street":"3 Ave",
    "iso:country":"US",
    "sg:address":"369 3 Ave",
    "sg:city":"New York",
    "sg:classifiers":[
        {
            "category":"Shopping",
            "subcategory":"Computers & Home Electronics",
            "type":"Retail Goods"
        }
    ],
    "sg:phone":"+1   ",
    "sg:postcode":"10016",
    "sg:province":"NY",
    "sg:tags":[
        "consumer"
    ],
    "wof:name":"Radio Shack",
    "wof:placetype":"venue"
},
  "geometry": {"coordinates":[-73.981312,40.741351],"type":"Point"}
}