{
  "type": "Feature",
  "properties": {
    "iso:country":"US",
    "sg:address":"353 Cornelia St",
    "sg:city":"Plattsburgh",
    "sg:classifiers":[
        {
            "category":"Autos & Motor Vehicles",
            "subcategory":"Automobile Sales",
            "type":"Retail Goods"
        }
    ],
    "sg:phone":"+1   ",
    "sg:postcode":"12901",
    "sg:province":"NY",
    "sg:tags":[
        "used"
    ],
    "wof:name":"Affordable Auto",
    "wof:placetype":"venue"
},
  "geometry": {"coordinates":[-73.48058899999999,44.697132],"type":"Point"}
}