{
  "type": "Feature",
  "properties": {
    "iso:country":"US",
    "sg:address":"3722 Main St",
    "sg:city":"Hinsdale",
    "sg:classifiers":[
        {
            "category":"Government",
            "subcategory":"Post Office",
            "type":"Public Place"
        }
    ],
    "sg:phone":"+1   ",
    "sg:postcode":"14743",
    "sg:province":"NY",
    "sg:tags":[
        "postal",
        "us"
    ],
    "wof:name":"US Post Office",
    "wof:placetype":"venue"
},
  "geometry": {"coordinates":[-78.39438199999999,42.160669],"type":"Point"}
}