{
  "type": "Feature",
  "properties": {
    "iso:country":"US",
    "sg:address":"2178 Brooklyn Ave",
    "sg:city":"Brooklyn",
    "sg:classifiers":[
        {
            "category":"Utilities",
            "subcategory":"Recycling",
            "type":"Services"
        },
        {
            "category":"Building & Trades",
            "subcategory":"Construction",
            "type":"Services"
        }
    ],
    "sg:phone":"+1 888 883 6161",
    "sg:postcode":"11210",
    "sg:province":"NY",
    "sg:tags":[
        "garbage",
        "contractor",
        "equipment",
        "rubbish",
        "removal",
        "demolition",
        "contractors'"
    ],
    "wof:name":"B&G Rubbish and Demolition",
    "wof:placetype":"venue"
},
  "geometry": {"coordinates":[-73.943794,40.637609],"type":"Point"}
}