{
  "type": "Feature",
  "properties": {
    "addr:full":"17 Bank St Peekskill NY 10566",
    "addr:housenumber":"17",
    "addr:postcode":"10566",
    "addr:street":"Bank St",
    "iso:country":"US",
    "sg:address":"17 Bank St",
    "sg:city":"Peekskill",
    "sg:classifiers":[
        {
            "category":"Food & Beverages",
            "subcategory":"Meat & Fish",
            "type":"Retail Goods"
        }
    ],
    "sg:phone":"+1 914 737 1505",
    "sg:postcode":"10566",
    "sg:province":"NY",
    "sg:tags":[
        "seafood"
    ],
    "wof:name":"Peekskill Fish Market",
    "wof:placetype":"venue"
},
  "geometry": {"coordinates":[-73.919014,41.29165],"type":"Point"}
}