{
  "type": "Feature",
  "properties": {
    "iso:country":"US",
    "sg:address":"56 Tanners Ln",
    "sg:city":"Levittown",
    "sg:classifiers":[
        {
            "category":"Sports & Exercise",
            "subcategory":"Bowling",
            "type":"Entertainment"
        }
    ],
    "sg:phone":"+1   ",
    "sg:postcode":"11756",
    "sg:province":"NY",
    "sg:tags":[
        "drinking",
        "eating",
        "center"
    ],
    "wof:name":"Levittown Lanes Bowling",
    "wof:placetype":"venue"
},
  "geometry": {"coordinates":[-73.50516399999999,40.719941],"type":"Point"}
}