{
  "type": "Feature",
  "properties": {
    "iso:country":"US",
    "sg:address":"1313 Jericho Turnpike",
    "sg:city":"New Hyde Park",
    "sg:classifiers":[
        {
            "category":"Personal",
            "subcategory":"Beauty Salon",
            "type":"Services"
        },
        {
            "category":"Personal",
            "subcategory":"Barber",
            "type":"Services"
        },
        {
            "category":"Personal",
            "subcategory":"Nail Salon",
            "type":"Services"
        }
    ],
    "sg:phone":"+1 516 488 6900",
    "sg:postcode":"11040",
    "sg:province":"NY",
    "sg:tags":[
        "hair"
    ],
    "sg:website":"www.lilypond.com",
    "wof:name":"Lily Pond",
    "wof:placetype":"venue"
},
  "geometry": {"coordinates":[-73.68276899999999,40.733374],"type":"Point"}
}