{
  "type": "Feature",
  "properties": {
    "addr:full":"841 Barretto St Bronx NY 10474",
    "addr:housenumber":"841",
    "addr:postcode":"10474",
    "addr:street":"Barretto St",
    "iso:country":"US",
    "sg:address":"841 Barretto St",
    "sg:city":"Bronx",
    "sg:classifiers":[
        {
            "category":"Shopping",
            "type":"Retail Goods"
        }
    ],
    "sg:phone":"+1 718 378 6168",
    "sg:postcode":"10474",
    "sg:province":"NY",
    "sg:tags":[
        "trophy",
        "medal",
        "award"
    ],
    "wof:name":"North American Trophies",
    "wof:placetype":"venue"
},
  "geometry": {"coordinates":[-73.890473,40.816978],"type":"Point"}
}