{
  "type": "Feature",
  "properties": {
    "addr:full":"33 Frog Pond Road Huntington Station NY 11746",
    "addr:housenumber":"33",
    "addr:postcode":"11746",
    "addr:street":"Frog Pond Road Huntington",
    "iso:country":"US",
    "sg:address":"33 Frog Pond Road",
    "sg:city":"Huntington Station",
    "sg:classifiers":[
        {
            "category":"Building & Trades",
            "subcategory":"Construction",
            "type":"Services"
        },
        {
            "category":"Building & Trades",
            "subcategory":"Electrical",
            "type":"Services"
        }
    ],
    "sg:phone":"+1 631 425 1474",
    "sg:postcode":"11746",
    "sg:province":"NY",
    "sg:tags":[
        "electrician",
        "contractor"
    ],
    "sg:website":"www.frogpnd.com",
    "wof:name":"Frog Pond Consulting",
    "wof:placetype":"venue"
},
  "geometry": {"coordinates":[-73.39591299999999,40.833863],"type":"Point"}
}