{
  "type": "Feature",
  "properties": {
    "addr:full":"90 Greenwich Ave New York NY 10011",
    "addr:housenumber":"90",
    "addr:postcode":"10011",
    "addr:street":"Greenwich Ave",
    "iso:country":"US",
    "sg:address":"90 Greenwich Ave",
    "sg:city":"New York",
    "sg:classifiers":[
        {
            "category":"Bars & Pubs",
            "type":"Food & Drink"
        }
    ],
    "sg:phone":"+1 212 741 5279",
    "sg:postcode":"10011",
    "sg:province":"NY",
    "wof:name":"Johnny's Bar",
    "wof:placetype":"venue"
},
  "geometry": {"coordinates":[-74.00173542100001,40.7379262184],"type":"Point"}
}