{
  "type": "Feature",
  "properties": {
    "addr:full":"150 E 58th St Fl 33 New York NY 10155",
    "addr:housenumber":"150;33",
    "addr:postcode":"10155",
    "addr:street":"E 58Th St Fl",
    "iso:country":"US",
    "sg:address":"150 E 58th St Fl 33",
    "sg:city":"New York",
    "sg:classifiers":[
        {
            "category":"Real Estate",
            "subcategory":"Real Estate Services",
            "type":"Services"
        }
    ],
    "sg:phone":"+1 212 832 9100",
    "sg:postcode":"10155",
    "sg:province":"NY",
    "sg:tags":[
        "management",
        "property"
    ],
    "wof:name":"Scott Center Corp",
    "wof:placetype":"venue"
},
  "geometry": {"coordinates":[-73.96843800000001,40.761363],"type":"Point"}
}