{
  "type": "Feature",
  "properties": {
    "addr:full":"371 Marcy Ave Brooklyn NY 11206",
    "addr:housenumber":"371",
    "addr:postcode":"11206",
    "addr:street":"Marcy Ave",
    "iso:country":"US",
    "sg:address":"371 Marcy Ave",
    "sg:city":"Brooklyn",
    "sg:classifiers":[
        {
            "category":"Organizations",
            "subcategory":"Religious Organization",
            "type":"Services"
        }
    ],
    "sg:phone":"+1 718 387 6698",
    "sg:postcode":"11206",
    "sg:province":"NY",
    "sg:tags":[
        "clergy"
    ],
    "wof:name":"Solomon Weinberger",
    "wof:placetype":"venue"
},
  "geometry": {"coordinates":[-73.952685,40.702326],"type":"Point"}
}