{
  "type": "Feature",
  "properties": {
    "addr:full":"207 Flanders Rd Riverhead NY 11901",
    "addr:housenumber":"207",
    "addr:postcode":"11901",
    "addr:street":"Flanders Rd",
    "iso:country":"US",
    "sg:address":"207 Flanders Rd",
    "sg:city":"Riverhead",
    "sg:classifiers":[
        {
            "category":"Organizations",
            "subcategory":"Religious Organization",
            "type":"Services"
        }
    ],
    "sg:phone":"+1 631 369 8588",
    "sg:postcode":"11901",
    "sg:province":"NY",
    "sg:tags":[
        "church"
    ],
    "wof:name":"Marcos",
    "wof:placetype":"venue"
},
  "geometry": {"coordinates":[-72.657043,40.914204],"type":"Point"}
}