{
  "type": "Feature",
  "properties": {
    "addr:full":"520 Milton Rd Rye NY 10580",
    "addr:housenumber":"520",
    "addr:postcode":"10580",
    "addr:street":"Milton Rd",
    "iso:country":"US",
    "sg:address":"520 Milton Rd",
    "sg:city":"Rye",
    "sg:classifiers":[
        {
            "category":"Restaurant",
            "type":"Food & Drink"
        }
    ],
    "sg:phone":"+1   ",
    "sg:postcode":"10580",
    "sg:province":"NY",
    "sg:tags":[
        "eating",
        "product",
        "dairy"
    ],
    "wof:name":"Piazza Pizzeria & Ice Cream",
    "wof:placetype":"venue"
},
  "geometry": {"coordinates":[-73.687895,40.962784],"type":"Point"}
}