{
  "type": "Feature",
  "properties": {
    "iso:country":"US",
    "sg:address":"17 Noviski Ln",
    "sg:city":"Pine Island",
    "sg:classifiers":[
        {
            "category":"Building & Trades",
            "subcategory":"Landscaping Services",
            "type":"Services"
        }
    ],
    "sg:phone":"+1 845 258 4107",
    "sg:postcode":"10969",
    "sg:province":"NY",
    "sg:tags":[
        "landscape",
        "contractor"
    ],
    "wof:name":"Dave's Landscaping",
    "wof:placetype":"venue"
},
  "geometry": {"coordinates":[-74.50064500000001,41.289666],"type":"Point"}
}