{
  "type": "Feature",
  "properties": {
    "addr:full":"2115 Crompond Rd Cortlandt Manor NY 10567",
    "addr:housenumber":"2115",
    "addr:postcode":"10567",
    "addr:street":"Crompond Rd",
    "iso:country":"US",
    "sg:address":"2115 Crompond Rd",
    "sg:city":"Cortlandt Manor",
    "sg:classifiers":[
        {
            "category":"Local Transit",
            "type":"Transportation"
        }
    ],
    "sg:phone":"+1 914 739 1053",
    "sg:postcode":"10567",
    "sg:province":"NY",
    "sg:tags":[
        "airport"
    ],
    "wof:name":"L L Cab Corp",
    "wof:placetype":"venue"
},
  "geometry": {"coordinates":[-73.881618,41.2925],"type":"Point"}
}