{
  "type": "Feature",
  "properties": {
    "iso:country":"US",
    "sg:address":"29 7th Ave",
    "sg:city":"New Hyde Park",
    "sg:classifiers":[
        {
            "category":"Banks & Credit Unions",
            "subcategory":"Bank",
            "type":"Services"
        }
    ],
    "sg:phone":"+1 516 877 1804",
    "sg:postcode":"11040",
    "sg:province":"NY",
    "sg:tags":[
        "broker",
        "mortgage"
    ],
    "wof:name":"Residential & Coml Mrtg Co",
    "wof:placetype":"venue"
},
  "geometry": {"coordinates":[-73.66532100000001,40.737892],"type":"Point"}
}