{
  "type": "Feature",
  "properties": {
    "addr:full":"123 Grove Ave Cedarhurst NY 11516",
    "addr:housenumber":"123",
    "addr:postcode":"11516",
    "addr:street":"Grove Ave",
    "iso:country":"US",
    "sg:address":"123 Grove Ave",
    "sg:city":"Cedarhurst",
    "sg:classifiers":[
        {
            "category":"Health Services",
            "subcategory":"Clinic",
            "type":"Services"
        }
    ],
    "sg:phone":"+1 516 295 5591",
    "sg:postcode":"11516",
    "sg:province":"NY",
    "sg:tags":[
        "counseling",
        "mental"
    ],
    "wof:name":"Brill Chaim",
    "wof:placetype":"venue"
},
  "geometry": {"coordinates":[-73.720901,40.625801],"type":"Point"}
}