{
  "type": "Feature",
  "properties": {
    "iso:country":"US",
    "sg:address":"61 River Heights Dr",
    "sg:city":"Smithtown",
    "sg:classifiers":[
        {
            "category":"Real Estate",
            "subcategory":"Real Estate Operator",
            "type":"Services"
        }
    ],
    "sg:phone":"+1 631 467 5672",
    "sg:postcode":"11787",
    "sg:province":"NY",
    "sg:tags":[
        "building",
        "apartment"
    ],
    "wof:name":"Blaintze Inc",
    "wof:placetype":"venue"
},
  "geometry": {"coordinates":[-73.212439,40.868395],"type":"Point"}
}