{
  "type": "Feature",
  "properties": {
    "addr:full":"629 N Barry Ave Mamaroneck NY 10543",
    "addr:housenumber":"629",
    "addr:postcode":"10543",
    "addr:street":"N Barry Ave",
    "iso:country":"US",
    "sg:address":"629 N Barry Ave",
    "sg:city":"Mamaroneck",
    "sg:classifiers":[
        {
            "category":"Building & Trades",
            "subcategory":"Plumbing",
            "type":"Services"
        }
    ],
    "sg:phone":"+1 914 698 2228",
    "sg:postcode":"10543",
    "sg:province":"NY",
    "sg:tags":[
        "plumbing",
        "contractor"
    ],
    "wof:name":"W S Mc Guire Plumbing & Htg",
    "wof:placetype":"venue"
},
  "geometry": {"coordinates":[-73.731791,40.959947],"type":"Point"}
}