{
  "type": "Feature",
  "properties": {
    "iso:country":"US",
    "sg:address":"335 Driving Park Ave",
    "sg:city":"Rochester",
    "sg:classifiers":[
        {
            "category":"Food & Beverages",
            "subcategory":"Meat & Fish",
            "type":"Retail Goods"
        }
    ],
    "sg:phone":"+1 585 719 9160",
    "sg:postcode":"14613",
    "sg:province":"NY",
    "sg:tags":[
        "seafood"
    ],
    "wof:name":"Rochester Seafood Plus",
    "wof:placetype":"venue"
},
  "geometry": {"coordinates":[-77.639397,43.180857],"type":"Point"}
}