{
  "type": "Feature",
  "properties": {
    "addr:full":"10411 99th Street Ozone Park NY 11417",
    "addr:housenumber":"10411",
    "addr:postcode":"11417",
    "addr:street":"99Th Street",
    "iso:country":"US",
    "sg:address":"10411 99th Street",
    "sg:city":"Ozone Park",
    "sg:classifiers":[
        {
            "category":"Home & Garden",
            "subcategory":"Hardware",
            "type":"Retail Goods"
        }
    ],
    "sg:phone":"+1 718 529 5161",
    "sg:postcode":"11417",
    "sg:province":"NY",
    "sg:tags":[
        "store"
    ],
    "wof:name":"Ali Safdar",
    "wof:placetype":"venue"
},
  "geometry": {"coordinates":[-73.84026299999999,40.680963],"type":"Point"}
}