{
  "type": "Feature",
  "properties": {
    "addr:full":"122 Orchard St New York NY 10002",
    "addr:housenumber":"122",
    "addr:postcode":"10002",
    "addr:street":"Orchard St",
    "iso:country":"US",
    "sg:address":"122 Orchard St",
    "sg:city":"New York",
    "sg:classifiers":[
        {
            "category":"Shopping",
            "subcategory":"Clothing, Apparel, & Fashions",
            "type":"Retail Goods"
        }
    ],
    "sg:phone":"+1 212 228 0682",
    "sg:postcode":"10002",
    "sg:province":"NY",
    "sg:tags":[
        "fur"
    ],
    "wof:name":"New York Leather & Fur",
    "wof:placetype":"venue"
},
  "geometry": {"coordinates":[-73.98923000000001,40.7198],"type":"Point"}
}