{
  "type": "Feature",
  "properties": {
    "iso:country":"US",
    "sg:address":"7 Hyatt St",
    "sg:city":"Staten Island",
    "sg:classifiers":[
        {
            "category":"Shopping",
            "subcategory":"Gifts & Souvenirs",
            "type":"Retail Goods"
        }
    ],
    "sg:phone":"+1 718 981 0428",
    "sg:postcode":"10301",
    "sg:province":"NY",
    "sg:tags":[
        "shop"
    ],
    "wof:name":"Hyatt Card & Gift Inc",
    "wof:placetype":"venue"
},
  "geometry": {"coordinates":[-74.077021,40.642065],"type":"Point"}
}