{
  "type": "Feature",
  "properties": {
    "iso:country":"US",
    "sg:address":"1791 Webster Ave",
    "sg:city":"Bronx",
    "sg:classifiers":[
        {
            "category":"Real Estate",
            "subcategory":"Real Estate Agent",
            "type":"Services"
        }
    ],
    "sg:phone":"+1 718 601 1629",
    "sg:postcode":"10457",
    "sg:province":"NY",
    "wof:name":"Atlas Autotronics Center Inc",
    "wof:placetype":"venue"
},
  "geometry": {"coordinates":[-73.902466,40.845039],"type":"Point"}
}