{
  "type": "Feature",
  "properties": {
    "iso:country":"US",
    "sg:address":"585 Bicycle Path",
    "sg:city":"Port Jefferson Station",
    "sg:classifiers":[
        {
            "category":"Wholesale",
            "subcategory":"Groceries",
            "type":"Manufacturing & Wholesale Goods"
        }
    ],
    "sg:phone":"+1 631 473 4747",
    "sg:postcode":"11776",
    "sg:province":"NY",
    "sg:tags":[
        "coffee"
    ],
    "wof:name":"Colonial Coffee Co LLC",
    "wof:placetype":"venue"
},
  "geometry": {"coordinates":[-73.03745000000001,40.906733],"type":"Point"}
}