{
  "type": "Feature",
  "properties": {
    "addr:full":"6193 Baker Rd Ashville NY 14710",
    "addr:housenumber":"6193",
    "addr:postcode":"14710",
    "addr:street":"Baker Rd",
    "iso:country":"US",
    "sg:address":"6193 Baker Rd",
    "sg:city":"Ashville",
    "sg:classifiers":[
        {
            "category":"Building & Trades",
            "subcategory":"Construction",
            "type":"Services"
        }
    ],
    "sg:phone":"+1 716 782 4969",
    "sg:postcode":"14710",
    "sg:province":"NY",
    "sg:tags":[
        "general",
        "contractor"
    ],
    "wof:name":"Lakeshore Builders",
    "wof:placetype":"venue"
},
  "geometry": {"coordinates":[-79.46411000000001,42.106556],"type":"Point"}
}