{
  "type": "Feature",
  "properties": {
    "iso:country":"US",
    "sg:address":"120 41st St",
    "sg:city":"Brooklyn",
    "sg:classifiers":[
        {
            "category":"Wholesale",
            "subcategory":"Apparel",
            "type":"Manufacturing & Wholesale Goods"
        }
    ],
    "sg:phone":"+1 718 369 6407",
    "sg:postcode":"11232",
    "sg:province":"NY",
    "wof:name":"Shabiller Inc",
    "wof:placetype":"venue"
},
  "geometry": {"coordinates":[-74.012073,40.654348],"type":"Point"}
}