{
  "type": "Feature",
  "properties": {
    "iso:country":"US",
    "sg:address":"220 E 60th St",
    "sg:city":"New York",
    "sg:classifiers":[
        {
            "category":"Home & Garden",
            "subcategory":"Building Materials",
            "type":"Retail Goods"
        }
    ],
    "sg:phone":"+1 212 888 5707",
    "sg:postcode":"10022",
    "sg:province":"NY",
    "sg:tags":[
        "equipment",
        "fixture",
        "lighting"
    ],
    "sg:website":"www.justbulbsnyc.com",
    "wof:name":"Just Bulbs",
    "wof:placetype":"venue"
},
  "geometry": {"coordinates":[-73.965309,40.761825],"type":"Point"}
}