{
  "type": "Feature",
  "properties": {
    "iso:country":"US",
    "sg:address":"984 Gates Ave",
    "sg:city":"Brooklyn",
    "sg:classifiers":[
        {
            "category":"Personal",
            "subcategory":"Beauty Salon",
            "type":"Services"
        }
    ],
    "sg:phone":"+1 718 452 0033",
    "sg:postcode":"11221",
    "sg:province":"NY",
    "wof:name":"A Square Unisex Hair Salon",
    "wof:placetype":"venue"
},
  "geometry": {"coordinates":[-73.926238,40.688859],"type":"Point"}
}