{
  "type": "Feature",
  "properties": {
    "addr:full":"436 River Rd Shirley NY 11967",
    "addr:housenumber":"436",
    "addr:postcode":"11967",
    "addr:street":"River Rd",
    "iso:country":"US",
    "sg:address":"436 River Rd",
    "sg:city":"Shirley",
    "sg:classifiers":[
        {
            "category":"Social Services",
            "subcategory":"Job Training",
            "type":"Services"
        }
    ],
    "sg:phone":"+1 631 345 3736",
    "sg:postcode":"11967",
    "sg:province":"NY",
    "sg:tags":[
        "rehabilitation"
    ],
    "wof:name":"Mediplex Rehab Ctr",
    "wof:placetype":"venue"
},
  "geometry": {"coordinates":[-72.897567,40.830427],"type":"Point"}
}