{
  "type": "Feature",
  "properties": {
    "addr:full":"641 Grand Ave Brooklyn NY 11238",
    "addr:housenumber":"641",
    "addr:postcode":"11238",
    "addr:street":"Grand Ave",
    "iso:country":"US",
    "sg:address":"641 Grand Ave",
    "sg:city":"Brooklyn",
    "sg:classifiers":[
        {
            "category":"Shopping",
            "subcategory":"Beauty & Cosmetics",
            "type":"Retail Goods"
        }
    ],
    "sg:phone":"+1   ",
    "sg:postcode":"11238",
    "sg:province":"NY",
    "sg:tags":[
        "merchandise"
    ],
    "wof:name":"McClain Keisha",
    "wof:placetype":"venue"
},
  "geometry": {"coordinates":[-73.96299,40.675948],"type":"Point"}
}