{
  "type": "Feature",
  "properties": {
    "addr:full":"2085 Richmond Rd Staten Island NY 10306",
    "addr:housenumber":"2085",
    "addr:postcode":"10306",
    "addr:street":"Richmond Rd",
    "iso:country":"US",
    "sg:address":"2085 Richmond Rd",
    "sg:city":"Staten Island",
    "sg:classifiers":[
        {
            "category":"Shopping",
            "type":"Retail Goods"
        }
    ],
    "sg:phone":"+1 718 351 1616",
    "sg:postcode":"10306",
    "sg:province":"NY",
    "sg:tags":[
        "funeral",
        "cemetery",
        "monument"
    ],
    "sg:website":"www.simonuments.com",
    "wof:name":"Moravian Monuments",
    "wof:placetype":"venue"
},
  "geometry": {"coordinates":[-74.11170799999999,40.581849],"type":"Point"}
}