{
  "type": "Feature",
  "properties": {
    "addr:full":"30 5th Ave New Rochelle NY 10801",
    "addr:housenumber":"30",
    "addr:postcode":"10801",
    "addr:street":"5Th Ave",
    "iso:country":"US",
    "sg:address":"30 5th Ave",
    "sg:city":"New Rochelle",
    "sg:classifiers":[
        {
            "category":"Building & Trades",
            "subcategory":"Construction",
            "type":"Services"
        }
    ],
    "sg:phone":"+1 914 632 6201",
    "sg:postcode":"10801",
    "sg:province":"NY",
    "sg:tags":[
        "masonry",
        "contractor"
    ],
    "wof:name":"Reyes Construction Inc",
    "wof:placetype":"venue"
},
  "geometry": {"coordinates":[-73.78717,40.921389],"type":"Point"}
}