{
  "type": "Feature",
  "properties": {
    "addr:full":"49 Crown St Brooklyn NY 11225",
    "addr:housenumber":"49",
    "addr:postcode":"11225",
    "addr:street":"Crown St",
    "iso:country":"US",
    "sg:address":"49 Crown St",
    "sg:city":"Brooklyn",
    "sg:classifiers":[
        {
            "category":"Professional",
            "subcategory":"Lawyer & Legal Services",
            "type":"Services"
        }
    ],
    "sg:phone":"+1 718 826 1589",
    "sg:postcode":"11225",
    "sg:province":"NY",
    "sg:tags":[
        "plan"
    ],
    "sg:website":"www.prepaidlegal.com",
    "wof:name":"Pre-Paid Legal Svc Inc",
    "wof:placetype":"venue"
},
  "geometry": {"coordinates":[-73.961146,40.667673],"type":"Point"}
}