{
  "type": "Feature",
  "properties": {
    "addr:full":"509 5th Avenue New York NY 10017",
    "addr:housenumber":"509",
    "addr:postcode":"10017",
    "addr:street":"5Th Avenue",
    "iso:country":"US",
    "sg:address":"509 5th Avenue",
    "sg:city":"New York",
    "sg:classifiers":[
        {
            "category":"Place Of Worship",
            "subcategory":"Synagogue",
            "type":"Public Place"
        },
        {
            "category":"Building & Trades",
            "subcategory":"Construction",
            "type":"Services"
        }
    ],
    "sg:phone":"+1 212 972 0770",
    "sg:postcode":"10017",
    "sg:province":"NY",
    "sg:tags":[
        "contractor"
    ],
    "sg:website":"www.chabadmidtown.com",
    "wof:name":"Chabad Lubavitch of Midtown",
    "wof:placetype":"venue"
},
  "geometry": {"coordinates":[-73.980555,40.75385],"type":"Point"}
}