{
  "type": "Feature",
  "properties": {
    "addr:full":"903 Dekalb Ave Brooklyn NY 11221",
    "addr:housenumber":"903",
    "addr:postcode":"11221",
    "addr:street":"Dekalb Ave",
    "iso:country":"US",
    "sg:address":"903 Dekalb Ave",
    "sg:city":"Brooklyn",
    "sg:classifiers":[
        {
            "category":"Wholesale",
            "subcategory":"Machinery & Supplies",
            "type":"Manufacturing & Wholesale Goods"
        }
    ],
    "sg:phone":"+1 718 453 6553",
    "sg:postcode":"11221",
    "sg:province":"NY",
    "sg:tags":[
        "salon",
        "beauty"
    ],
    "wof:name":"Variety Beauty Supply",
    "wof:placetype":"venue"
},
  "geometry": {"coordinates":[-73.94184199999999,40.692476],"type":"Point"}
}