{
  "type": "Feature",
  "properties": {
    "addr:full":"8802 4th Ave Brooklyn NY 11209",
    "addr:housenumber":"8802",
    "addr:postcode":"11209",
    "addr:street":"4Th Ave",
    "iso:country":"US",
    "sg:address":"8802 4th Ave",
    "sg:city":"Brooklyn",
    "sg:classifiers":[
        {
            "category":"Banks & Credit Unions",
            "subcategory":"Bank",
            "type":"Services"
        }
    ],
    "sg:phone":"+1 718 491 7630",
    "sg:postcode":"11209",
    "sg:province":"NY",
    "sg:tags":[
        "loan",
        "real estate"
    ],
    "wof:name":"Chase Home Finance",
    "wof:placetype":"venue"
},
  "geometry": {"coordinates":[-74.029059,40.621285],"type":"Point"}
}