{
  "type": "Feature",
  "properties": {
    "iso:country":"US",
    "sg:address":"50 Wolf Rd",
    "sg:city":"Albany",
    "sg:classifiers":[
        {
            "category":"Freight",
            "type":"Transportation"
        }
    ],
    "sg:phone":"+1 518 489 8634",
    "sg:postcode":"12205",
    "sg:province":"NY",
    "sg:tags":[
        "truck"
    ],
    "sg:website":"www.xerofax.com",
    "wof:name":"Xero-Fax Inc",
    "wof:placetype":"venue"
},
  "geometry": {"coordinates":[-73.811673,42.715403],"type":"Point"}
}