{
  "type": "Feature",
  "properties": {
    "addr:full":"2140 Dieter Rd Wayland NY 14572",
    "addr:housenumber":"2140",
    "addr:postcode":"14572",
    "addr:street":"Dieter Rd",
    "iso:country":"US",
    "sg:address":"2140 Dieter Rd",
    "sg:city":"Wayland",
    "sg:classifiers":[
        {
            "category":"Personal",
            "subcategory":"Barber",
            "type":"Services"
        }
    ],
    "sg:phone":"+1 585 728 3861",
    "sg:postcode":"14572",
    "sg:province":"NY",
    "wof:name":"Family Barber Shop",
    "wof:placetype":"venue"
},
  "geometry": {"coordinates":[-77.60809999999999,42.556537],"type":"Point"}
}