{
  "type": "Feature",
  "properties": {
    "iso:country":"US",
    "sg:address":"1337 Valley Rd",
    "sg:city":"Owego",
    "sg:classifiers":[
        {
            "category":"Retail",
            "subcategory":"Animal Services",
            "type":"Services"
        }
    ],
    "sg:phone":"+1 607 687 5271",
    "sg:postcode":"13827",
    "sg:province":"NY",
    "sg:tags":[
        "merchandise"
    ],
    "wof:name":"Fawn Acre Pet Care",
    "wof:placetype":"venue"
},
  "geometry": {"coordinates":[-76.232759,42.057328],"type":"Point"}
}