{
  "type": "Feature",
  "properties": {
    "iso:country":"US",
    "sg:address":"729 Mont Vista Ln",
    "sg:city":"Webster",
    "sg:classifiers":[
        {
            "category":"Shopping",
            "subcategory":"Computers & Home Electronics",
            "type":"Retail Goods"
        }
    ],
    "sg:phone":"+1 585 787 9290",
    "sg:postcode":"14580",
    "sg:province":"NY",
    "sg:tags":[
        "equipment",
        "satellite",
        "system"
    ],
    "wof:name":"Custom Cable Co",
    "wof:placetype":"venue"
},
  "geometry": {"coordinates":[-77.479995,43.197219],"type":"Point"}
}