{
  "type": "Feature",
  "properties": {
    "addr:full":"6352 Woodhaven Boulevard Rego Park NY 11374",
    "addr:housenumber":"6352",
    "addr:postcode":"11374",
    "addr:street":"Woodhaven Boulevard",
    "iso:country":"US",
    "sg:address":"6352 Woodhaven Boulevard",
    "sg:city":"Rego Park",
    "sg:classifiers":[
        {
            "category":"Health Services",
            "subcategory":"Doctor",
            "type":"Services"
        }
    ],
    "sg:phone":"+1 718 458 6012",
    "sg:postcode":"11374",
    "sg:province":"NY",
    "wof:name":"Nathan Sami MD",
    "wof:placetype":"venue"
},
  "geometry": {"coordinates":[-73.868337,40.72302],"type":"Point"}
}