{
  "type": "Feature",
  "properties": {
    "iso:country":"US",
    "sg:address":"90 W Merrick Rd",
    "sg:city":"Freeport",
    "sg:classifiers":[
        {
            "category":"Shopping",
            "type":"Retail Goods"
        }
    ],
    "sg:phone":"+1 516 377 0077",
    "sg:postcode":"11520",
    "sg:province":"NY",
    "sg:tags":[
        "cosmetic",
        "perfume"
    ],
    "wof:name":"Latino Beauty Supply",
    "wof:placetype":"venue"
},
  "geometry": {"coordinates":[-73.582075,40.654094],"type":"Point"}
}