{
  "type": "Feature",
  "properties": {
    "iso:country":"US",
    "sg:address":"268 W Fordham Rd",
    "sg:city":"Bronx",
    "sg:classifiers":[
        {
            "category":"Local Transit",
            "type":"Transportation"
        }
    ],
    "sg:phone":"+1 718 933 1111",
    "sg:postcode":"10468",
    "sg:province":"NY",
    "sg:tags":[
        "car"
    ],
    "wof:name":"High Class Limo Bx",
    "wof:placetype":"venue"
},
  "geometry": {"coordinates":[-73.911554,40.861698],"type":"Point"}
}