{
  "type": "Feature",
  "properties": {
    "addr:full":"130 James Ave Solvay NY 13209",
    "addr:housenumber":"130",
    "addr:postcode":"13209",
    "addr:street":"James Ave",
    "iso:country":"US",
    "sg:address":"130 James Ave",
    "sg:city":"Solvay",
    "sg:classifiers":[
        {
            "category":"Manufacturing",
            "subcategory":"Printing",
            "type":"Manufacturing & Wholesale Goods"
        }
    ],
    "sg:phone":"+1 315 487 5326",
    "sg:postcode":"13209",
    "sg:province":"NY",
    "sg:tags":[
        "commercial"
    ],
    "wof:name":"Don's Lithography",
    "wof:placetype":"venue"
},
  "geometry": {"coordinates":[-76.23796900000001,43.066308],"type":"Point"}
}