{
  "type": "Feature",
  "properties": {
    "addr:full":"8581 Klondyke Rd Sherman NY 14781",
    "addr:housenumber":"8581",
    "addr:postcode":"14781",
    "addr:street":"Klondyke Rd",
    "iso:country":"US",
    "sg:address":"8581 Klondyke Rd",
    "sg:city":"Sherman",
    "sg:classifiers":[
        {
            "category":"Farming",
            "subcategory":"Farm & Veterinary Services",
            "type":"Manufacturing & Wholesale Goods"
        }
    ],
    "sg:phone":"+1 716 761 6768",
    "sg:postcode":"14781",
    "sg:province":"NY",
    "sg:tags":[
        "crop",
        "harvesting"
    ],
    "wof:name":"West End Custom Harvesting",
    "wof:placetype":"venue"
},
  "geometry": {"coordinates":[-79.635443,42.168328],"type":"Point"}
}