{
  "type": "Feature",
  "properties": {
    "addr:full":"122 W Albany St Herkimer NY 13350",
    "addr:housenumber":"122",
    "addr:postcode":"13350",
    "addr:street":"W Albany St",
    "iso:country":"US",
    "sg:address":"122 W Albany St",
    "sg:city":"Herkimer",
    "sg:classifiers":[
        {
            "category":"Restaurant",
            "type":"Food & Drink"
        }
    ],
    "sg:phone":"+1   ",
    "sg:postcode":"13350",
    "sg:province":"NY",
    "sg:tags":[
        "eating"
    ],
    "wof:name":"Albany Street Cafe",
    "wof:placetype":"venue"
},
  "geometry": {"coordinates":[-74.986953,43.025206],"type":"Point"}
}