{
  "type": "Feature",
  "properties": {
    "addr:full":"20 E 1st St Mt Vernon NY 10550",
    "addr:housenumber":"20",
    "addr:postcode":"10550",
    "addr:street":"E 1St St",
    "iso:country":"US",
    "sg:address":"20 E 1st St",
    "sg:city":"Mt Vernon",
    "sg:classifiers":[
        {
            "category":"Organizations",
            "subcategory":"Non-profit Organization",
            "type":"Services"
        }
    ],
    "sg:phone":"+1 914 668 1450",
    "sg:postcode":"10550",
    "sg:province":"NY",
    "sg:tags":[
        "information",
        "alcoholism",
        "treatment"
    ],
    "wof:name":"Archway Alcoholism Program",
    "wof:placetype":"venue"
},
  "geometry": {"coordinates":[-73.83710499999999,40.911729],"type":"Point"}
}