{
  "type": "Feature",
  "properties": {
    "addr:full":"5 E 62nd St New York NY 10021",
    "addr:housenumber":"5",
    "addr:postcode":"10021",
    "addr:street":"E 62Nd St",
    "iso:country":"US",
    "sg:address":"5 E 62nd St",
    "sg:city":"New York",
    "sg:classifiers":[
        {
            "category":"Place Of Worship",
            "subcategory":"Synagogue",
            "type":"Public Place"
        }
    ],
    "sg:phone":"+1 212 838 2122",
    "sg:postcode":"10021",
    "sg:province":"NY",
    "wof:name":"Fifth Ave Synagogue Preschool",
    "wof:placetype":"venue"
},
  "geometry": {"coordinates":[-73.971001,40.765999],"type":"Point"}
}