{
  "type": "Feature",
  "properties": {
    "addr:full":"2408 Grand Concourse Bronx NY 10458",
    "addr:housenumber":"2408",
    "addr:postcode":"10458",
    "addr:street":"Grand Concourse",
    "iso:country":"US",
    "sg:address":"2408 Grand Concourse",
    "sg:city":"Bronx",
    "sg:classifiers":[
        {
            "category":"Personal",
            "subcategory":"Beauty Salon",
            "type":"Services"
        }
    ],
    "sg:phone":"+1   ",
    "sg:postcode":"10458",
    "sg:province":"NY",
    "sg:tags":[
        "shop"
    ],
    "wof:name":"Felipes International Unisex",
    "wof:placetype":"venue"
},
  "geometry": {"coordinates":[-73.898532,40.85951],"type":"Point"}
}