{
  "type": "Feature",
  "properties": {
    "addr:full":"601 Veterans Memorial Hwy Hauppauge NY 11787",
    "addr:housenumber":"601",
    "addr:postcode":"11787",
    "addr:street":"Veterans Memorial Hwy",
    "iso:country":"US",
    "sg:address":"601 Veterans Memorial Hwy",
    "sg:city":"Hauppauge",
    "sg:classifiers":[
        {
            "category":"Banks & Credit Unions",
            "subcategory":"Bank",
            "type":"Services"
        }
    ],
    "sg:phone":"+1 631 979 8070",
    "sg:postcode":"11787",
    "sg:province":"NY",
    "wof:name":"Chase Manhattan",
    "wof:placetype":"venue"
},
  "geometry": {"coordinates":[-73.24253899999999,40.826867],"type":"Point"}
}