{
  "type": "Feature",
  "properties": {
    "addr:full":"30 River Road New York NY 10044",
    "addr:housenumber":"30",
    "addr:postcode":"10044",
    "addr:street":"River Road",
    "iso:country":"US",
    "sg:address":"30 River Road",
    "sg:city":"New York",
    "sg:classifiers":[
        {
            "category":"Real Estate",
            "subcategory":"Real Estate Services",
            "type":"Services"
        },
        {
            "category":"Real Estate",
            "subcategory":"Real Estate Operator",
            "type":"Services"
        }
    ],
    "sg:phone":"+1 212 308 4040",
    "sg:postcode":"10044",
    "sg:province":"NY",
    "sg:tags":[
        "apartment",
        "property",
        "management"
    ],
    "sg:website":"www.manhattanpark.com",
    "wof:name":"Manhattan Park Rental Center",
    "wof:placetype":"venue"
},
  "geometry": {"coordinates":[-73.94659900000001,40.766115],"type":"Point"}
}