{
  "type": "Feature",
  "properties": {
    "addr:full":"25 Lafayette Ave Suffern NY 10901",
    "addr:housenumber":"25",
    "addr:postcode":"10901",
    "addr:street":"Lafayette Ave",
    "iso:country":"US",
    "sg:address":"25 Lafayette Ave",
    "sg:city":"Suffern",
    "sg:classifiers":[
        {
            "category":"Restaurant",
            "type":"Food & Drink"
        }
    ],
    "sg:phone":"+1 845 368 0011",
    "sg:postcode":"10901",
    "sg:province":"NY",
    "sg:tags":[
        "eating"
    ],
    "wof:name":"Oriental Garden",
    "wof:placetype":"venue"
},
  "geometry": {"coordinates":[-74.153693,41.116174],"type":"Point"}
}