{
  "type": "Feature",
  "properties": {
    "iso:country":"US",
    "sg:address":"378 Great Neck Rd",
    "sg:city":"Great Neck",
    "sg:classifiers":[
        {
            "category":"Manufacturing",
            "subcategory":"Chemicals & Compounds",
            "type":"Manufacturing & Wholesale Goods"
        }
    ],
    "sg:phone":"+1   ",
    "sg:postcode":"11021",
    "sg:province":"NY",
    "sg:tags":[
        "preparation",
        "pharmaceutical",
        "mfg",
        "eating",
        "f"
    ],
    "wof:name":"Nutritional Designs",
    "wof:placetype":"venue"
},
  "geometry": {"coordinates":[-73.732805,40.780423],"type":"Point"}
}