{
  "type": "Feature",
  "properties": {
    "addr:full":"138 W Fairmount Ave Lakewood NY 14750",
    "addr:housenumber":"138",
    "addr:postcode":"14750",
    "addr:street":"W Fairmount Ave",
    "iso:country":"US",
    "sg:address":"138 W Fairmount Ave",
    "sg:city":"Lakewood",
    "sg:classifiers":[
        {
            "category":"Travel",
            "subcategory":"Hotels & Motels",
            "type":"Entertainment"
        }
    ],
    "sg:phone":"+1 716 763 9550",
    "sg:postcode":"14750",
    "sg:province":"NY",
    "wof:name":"Fairmount Motel",
    "wof:placetype":"venue"
},
  "geometry": {"coordinates":[-79.341419,42.098556],"type":"Point"}
}