{
  "type": "Feature",
  "properties": {
    "iso:country":"US",
    "sg:address":"5783 Camp Rd",
    "sg:city":"Hamburg",
    "sg:classifiers":[
        {
            "category":"Manufacturing",
            "subcategory":"Printing",
            "type":"Manufacturing & Wholesale Goods"
        }
    ],
    "sg:phone":"+1 716 648 7400",
    "sg:postcode":"14075",
    "sg:province":"NY",
    "sg:tags":[
        "printer"
    ],
    "wof:name":"Glass Printer Inc",
    "wof:placetype":"venue"
},
  "geometry": {"coordinates":[-78.835837,42.729597],"type":"Point"}
}