{
  "type": "Feature",
  "properties": {
    "addr:full":"740 Manida St Bronx NY 10474",
    "addr:housenumber":"740",
    "addr:postcode":"10474",
    "addr:street":"Manida St",
    "iso:country":"US",
    "sg:address":"740 Manida St",
    "sg:city":"Bronx",
    "sg:classifiers":[
        {
            "category":"Education",
            "subcategory":"School",
            "type":"Public Place"
        }
    ],
    "sg:phone":"+1 718 861 9084",
    "sg:postcode":"10474",
    "sg:province":"NY",
    "wof:name":"St Ignatius School",
    "wof:placetype":"venue"
},
  "geometry": {"coordinates":[-73.888732,40.815635],"type":"Point"}
}