{
  "type": "Feature",
  "properties": {
    "addr:full":"2345 Broadway Lbby New York NY 10024",
    "addr:housenumber":"2345",
    "addr:postcode":"10024",
    "addr:street":"Broadway",
    "iso:country":"US",
    "sg:address":"2345 Broadway Lbby",
    "sg:city":"New York",
    "sg:classifiers":[
        {
            "category":"Retail",
            "subcategory":"Laundry & Dry Cleaning",
            "type":"Services"
        }
    ],
    "sg:phone":"+1 212 787 7617",
    "sg:postcode":"10024",
    "sg:province":"NY",
    "wof:name":"Landmark Cleaners Inc",
    "wof:placetype":"venue"
},
  "geometry": {"coordinates":[-73.976601,40.7883],"type":"Point"}
}