{
  "type": "Feature",
  "properties": {
    "addr:full":"24 W Main St Port Jervis NY 12771",
    "addr:housenumber":"24",
    "addr:postcode":"12771",
    "addr:street":"W Main St",
    "iso:country":"US",
    "sg:address":"24 W Main St",
    "sg:city":"Port Jervis",
    "sg:classifiers":[
        {
            "category":"Home & Garden",
            "subcategory":"Building Materials",
            "type":"Retail Goods"
        }
    ],
    "sg:phone":"+1 845 856 7705",
    "sg:postcode":"12771",
    "sg:province":"NY",
    "sg:tags":[
        "paint"
    ],
    "wof:name":"Paint & Wallpaper Stores",
    "wof:placetype":"venue"
},
  "geometry": {"coordinates":[-74.690438,41.378392],"type":"Point"}
}