{
  "type": "Feature",
  "properties": {
    "addr:full":"505 Bedford Ave Brooklyn NY 11211",
    "addr:housenumber":"505",
    "addr:postcode":"11211",
    "addr:street":"Bedford Ave",
    "iso:country":"US",
    "sg:address":"505 Bedford Ave",
    "sg:city":"Brooklyn",
    "sg:classifiers":[
        {
            "category":"Social Services",
            "subcategory":"Child Care",
            "type":"Services"
        }
    ],
    "sg:phone":"+1   ",
    "sg:postcode":"11211",
    "sg:province":"NY",
    "sg:tags":[
        "day"
    ],
    "wof:name":"Viener Day Care Center",
    "wof:placetype":"venue"
},
  "geometry": {"coordinates":[-73.96347,40.706455],"type":"Point"}
}