{
  "type": "Feature",
  "properties": {
    "addr:full":"522 W 136th St New York NY 10031",
    "addr:housenumber":"522",
    "addr:postcode":"10031",
    "addr:street":"W 136Th St",
    "iso:country":"US",
    "sg:address":"522 W 136th St",
    "sg:city":"New York",
    "sg:classifiers":[
        {
            "category":"Arena",
            "subcategory":"Sports Club",
            "type":"Entertainment"
        }
    ],
    "sg:phone":"+1 212 694 9952",
    "sg:postcode":"10031",
    "sg:province":"NY",
    "sg:tags":[
        "martial art"
    ],
    "wof:name":"Moisesdelacruz",
    "wof:placetype":"venue"
},
  "geometry": {"coordinates":[-73.9524,40.819801],"type":"Point"}
}