{
  "type": "Feature",
  "properties": {
    "addr:full":"7917 Flatlands Ave Brooklyn NY 11236",
    "addr:housenumber":"7917",
    "addr:postcode":"11236",
    "addr:street":"Flatlands Ave",
    "iso:country":"US",
    "sg:address":"7917 Flatlands Ave",
    "sg:city":"Brooklyn",
    "sg:classifiers":[
        {
            "category":"Shopping",
            "subcategory":"Florist",
            "type":"Retail Goods"
        }
    ],
    "sg:phone":"+1 718 251 3159",
    "sg:postcode":"11236",
    "sg:province":"NY",
    "wof:name":"Helena's Flowers Inc",
    "wof:placetype":"venue"
},
  "geometry": {"coordinates":[-73.913421,40.635484],"type":"Point"}
}