{
  "type": "Feature",
  "properties": {
    "addr:full":"1 E 182nd St Bronx NY 10453",
    "addr:housenumber":"1",
    "addr:postcode":"10453",
    "addr:street":"E 182Nd St",
    "iso:country":"US",
    "sg:address":"1 E 182nd St",
    "sg:city":"Bronx",
    "sg:classifiers":[
        {
            "category":"Wholesale",
            "subcategory":"Auto Parts",
            "type":"Manufacturing & Wholesale Goods"
        }
    ],
    "sg:phone":"+1 718 295 6768",
    "sg:postcode":"10453",
    "sg:province":"NY",
    "sg:tags":[
        "automobile",
        "supply"
    ],
    "wof:name":"Kay-Vee Auto Parts Co Inc",
    "wof:placetype":"venue"
},
  "geometry": {"coordinates":[-73.903615,40.85702],"type":"Point"}
}