{
  "type": "Feature",
  "properties": {
    "addr:full":"134 Co Rte 57 Phoenix NY 13135",
    "addr:housenumber":"134",
    "addr:postcode":"13135",
    "addr:street":"Co Rte 57",
    "iso:country":"US",
    "sg:address":"134 Co Rte 57",
    "sg:city":"Phoenix",
    "sg:classifiers":[
        {
            "category":"Real Estate",
            "subcategory":"Real Estate Operator",
            "type":"Services"
        }
    ],
    "sg:phone":"+1 315 598 3256",
    "sg:postcode":"13135",
    "sg:province":"NY",
    "sg:tags":[
        "mobile",
        "home",
        "site"
    ],
    "wof:name":"Crosby Hill Mobile Home Park",
    "wof:placetype":"venue"
},
  "geometry": {"coordinates":[-76.28083100000001,43.209028],"type":"Point"}
}