{
  "type": "Feature",
  "properties": {
    "addr:full":"34 Clinton St Batavia NY 14020",
    "addr:housenumber":"34",
    "addr:postcode":"14020",
    "addr:street":"Clinton St",
    "iso:country":"US",
    "sg:address":"34 Clinton St",
    "sg:city":"Batavia",
    "sg:classifiers":[
        {
            "category":"Professional",
            "subcategory":"Business Services",
            "type":"Services"
        }
    ],
    "sg:phone":"+1 585 344 4346",
    "sg:postcode":"14020",
    "sg:province":"NY",
    "wof:name":"Aramark",
    "wof:placetype":"venue"
},
  "geometry": {"coordinates":[-78.15971999999999,42.996897],"type":"Point"}
}