{
  "type": "Feature",
  "properties": {
    "addr:full":"78 W 120th St Ground Fl New York NY 10026",
    "addr:housenumber":"78",
    "addr:postcode":"10026",
    "addr:street":"W 120Th St",
    "iso:country":"US",
    "sg:address":"78 W 120th St Ground Fl",
    "sg:city":"New York",
    "sg:classifiers":[
        {
            "category":"Retail",
            "subcategory":"Pet Boarding",
            "type":"Services"
        }
    ],
    "sg:phone":"+1 212 920 7492",
    "sg:postcode":"10026",
    "sg:province":"NY",
    "sg:tags":[
        "boarding/pet",
        "sitting"
    ],
    "wof:name":"Pets Home in NYC",
    "wof:placetype":"venue"
},
  "geometry": {"coordinates":[-73.94729100000001,40.804114],"type":"Point"}
}