{
  "type": "Feature",
  "properties": {
    "addr:full":"4546 Clark St Hamburg NY 14075",
    "addr:housenumber":"4546",
    "addr:postcode":"14075",
    "addr:street":"Clark St",
    "iso:country":"US",
    "sg:address":"4546 Clark St",
    "sg:city":"Hamburg",
    "sg:classifiers":[
        {
            "category":"Professional",
            "type":"Services"
        }
    ],
    "sg:phone":"+1 716 648 8802",
    "sg:postcode":"14075",
    "sg:province":"NY",
    "sg:tags":[
        "establishment"
    ],
    "wof:name":"Danny Dole Inc",
    "wof:placetype":"venue"
},
  "geometry": {"coordinates":[-78.820398,42.728078],"type":"Point"}
}