{
  "type": "Feature",
  "properties": {
    "addr:full":"639 11th Ave New York NY 10036",
    "addr:housenumber":"639",
    "addr:postcode":"10036",
    "addr:street":"11Th Ave",
    "iso:country":"US",
    "sg:address":"639 11th Ave",
    "sg:city":"New York",
    "sg:classifiers":[
        {
            "category":"Autos & Motor Vehicles",
            "subcategory":"Fuel & Gas Station",
            "type":"Retail Goods"
        }
    ],
    "sg:phone":"+1 212 246 3453",
    "sg:postcode":"10036",
    "sg:province":"NY",
    "sg:website":"www.sunocoinc.com",
    "wof:name":"Sunoco Gas Station",
    "wof:placetype":"venue"
},
  "geometry": {"coordinates":[-73.99630000000001,40.763901],"type":"Point"}
}