{
  "type": "Feature",
  "properties": {
    "addr:full":"44 Rosman Rd Thiells NY 10984",
    "addr:housenumber":"44",
    "addr:postcode":"10984",
    "addr:street":"Rosman Rd",
    "iso:country":"US",
    "sg:address":"44 Rosman Rd",
    "sg:city":"Thiells",
    "sg:classifiers":[
        {
            "category":"Health Services",
            "subcategory":"Doctor",
            "type":"Services"
        }
    ],
    "sg:phone":"+1 845 354 8718",
    "sg:postcode":"10984",
    "sg:province":"NY",
    "sg:tags":[
        "physician",
        "surgeon"
    ],
    "wof:name":"Dr Howard Farewell",
    "wof:placetype":"venue"
},
  "geometry": {"coordinates":[-74.014837,41.202305],"type":"Point"}
}