{
  "type": "Feature",
  "properties": {
    "addr:full":"402 S Albany St Ithaca NY 14850",
    "addr:housenumber":"402",
    "addr:postcode":"14850",
    "addr:street":"S Albany St",
    "iso:country":"US",
    "sg:address":"402 S Albany St",
    "sg:city":"Ithaca",
    "sg:classifiers":[
        {
            "category":"Shopping",
            "subcategory":"Discount & Variety Stores",
            "type":"Retail Goods"
        }
    ],
    "sg:phone":"+1   ",
    "sg:postcode":"14850",
    "sg:province":"NY",
    "wof:name":"Reynolds Hallmark",
    "wof:placetype":"venue"
},
  "geometry": {"coordinates":[-76.501599,42.435566],"type":"Point"}
}