{
  "type": "Feature",
  "properties": {
    "iso:country":"US",
    "sg:address":"2128 Caton Ave Ste 2",
    "sg:city":"Brooklyn",
    "sg:classifiers":[
        {
            "category":"Professional",
            "subcategory":"Computer Services",
            "type":"Services"
        }
    ],
    "sg:phone":"+1 718 484 9493",
    "sg:postcode":"11226",
    "sg:province":"NY",
    "sg:tags":[
        "repair"
    ],
    "wof:name":"Black Inc",
    "wof:placetype":"venue"
},
  "geometry": {"coordinates":[-73.959452,40.652779],"type":"Point"}
}