{
  "type": "Feature",
  "properties": {
    "iso:country":"US",
    "sg:address":"37 James St",
    "sg:city":"New York",
    "sg:classifiers":[
        {
            "category":"Restaurant",
            "type":"Food & Drink"
        }
    ],
    "sg:phone":"+1 212 619 2820",
    "sg:postcode":"10038",
    "sg:province":"NY",
    "sg:tags":[
        "delicatessen"
    ],
    "wof:name":"Madison Finest Deli Inc",
    "wof:placetype":"venue"
},
  "geometry": {"coordinates":[-73.99878699999999,40.712024],"type":"Point"}
}