{
  "type": "Feature",
  "properties": {
    "addr:full":"5 Harbor Hill Dr Huntington NY 11743",
    "addr:housenumber":"5",
    "addr:postcode":"11743",
    "addr:street":"Harbor Hill Dr",
    "iso:country":"US",
    "sg:address":"5 Harbor Hill Dr",
    "sg:city":"Huntington",
    "sg:classifiers":[
        {
            "category":"Building & Trades",
            "subcategory":"Construction",
            "type":"Services"
        }
    ],
    "sg:phone":"+1 631 424 2845",
    "sg:postcode":"11743",
    "sg:province":"NY",
    "sg:tags":[
        "contractor"
    ],
    "wof:name":"European Development Builders Corp",
    "wof:placetype":"venue"
},
  "geometry": {"coordinates":[-73.45487300000001,40.896195],"type":"Point"}
}