{
  "type": "Feature",
  "properties": {
    "addr:full":"412 Soundview Ave Bronx NY 10473",
    "addr:housenumber":"412",
    "addr:postcode":"10473",
    "addr:street":"Soundview Ave",
    "iso:country":"US",
    "sg:address":"412 Soundview Ave",
    "sg:city":"Bronx",
    "sg:classifiers":[
        {
            "category":"Banks & Credit Unions",
            "subcategory":"Bank",
            "type":"Services"
        }
    ],
    "sg:phone":"+1 718 617 8070",
    "sg:postcode":"10473",
    "sg:province":"NY",
    "sg:tags":[
        "cashing",
        "check"
    ],
    "wof:name":"All American Check Cashing",
    "wof:placetype":"venue"
},
  "geometry": {"coordinates":[-73.858018,40.813716],"type":"Point"}
}