{
  "type": "Feature",
  "properties": {
    "iso:country":"US",
    "sg:address":"451 Albany Shaker Rd",
    "sg:city":"Albany",
    "sg:classifiers":[
        {
            "category":"Personal",
            "type":"Services"
        }
    ],
    "sg:phone":"+1   ",
    "sg:postcode":"12211",
    "sg:province":"NY",
    "wof:name":"Training Dynamics",
    "wof:placetype":"venue"
},
  "geometry": {"coordinates":[-73.77582700000001,42.704368],"type":"Point"}
}