{
  "type": "Feature",
  "properties": {
    "iso:country":"US",
    "sg:address":"97 Old Mill Rd",
    "sg:city":"Farmington",
    "sg:classifiers":[
        {
            "category":"Professional",
            "subcategory":"Research",
            "type":"Services"
        }
    ],
    "sg:phone":"+1 315 986 9438",
    "sg:postcode":"14425",
    "sg:province":"NY",
    "sg:tags":[
        "environmental",
        "ecological"
    ],
    "wof:name":"New York State Environ",
    "wof:placetype":"venue"
},
  "geometry": {"coordinates":[-77.359557,43.03259],"type":"Point"}
}