{
  "type": "Feature",
  "properties": {
    "iso:country":"US",
    "sg:address":"112 Soundview Ter",
    "sg:city":"Northport",
    "sg:classifiers":[
        {
            "category":"Professional",
            "subcategory":"Advertising",
            "type":"Services"
        }
    ],
    "sg:phone":"+1 631 262 9800",
    "sg:postcode":"11768",
    "sg:province":"NY",
    "sg:tags":[
        "counselor"
    ],
    "wof:name":"Healthcare Communications",
    "wof:placetype":"venue"
},
  "geometry": {"coordinates":[-73.329803,40.928454],"type":"Point"}
}