{
  "type": "Feature",
  "properties": {
    "iso:country":"US",
    "sg:address":"1 Simmons Dr",
    "sg:city":"Saugerties",
    "sg:classifiers":[
        {
            "category":"Professional",
            "type":"Services"
        }
    ],
    "sg:phone":"+1 845 246 1658",
    "sg:postcode":"12477",
    "sg:province":"NY",
    "wof:name":"Select Services Group",
    "wof:placetype":"venue"
},
  "geometry": {"coordinates":[-73.95381399999999,42.060367],"type":"Point"}
}