{
  "type": "Feature",
  "properties": {
    "iso:country":"US",
    "sg:address":"1361 Kew Ave",
    "sg:city":"Hewlett",
    "sg:classifiers":[
        {
            "category":"Taxi",
            "type":"Transportation"
        }
    ],
    "sg:phone":"+1   ",
    "sg:postcode":"11557",
    "sg:province":"NY",
    "sg:tags":[
        "taxicab"
    ],
    "wof:name":"Orlee Cab Corp",
    "wof:placetype":"venue"
},
  "geometry": {"coordinates":[-73.700247,40.643019],"type":"Point"}
}