{
  "type": "Feature",
  "properties": {
    "addr:full":"1497 Westchester Avenue Bronx NY 10472",
    "addr:housenumber":"1497",
    "addr:postcode":"10472",
    "addr:street":"Westchester Avenue",
    "iso:country":"US",
    "sg:address":"1497 Westchester Avenue",
    "sg:city":"Bronx",
    "sg:classifiers":[
        {
            "category":"Health Services",
            "subcategory":"Dentist",
            "type":"Services"
        }
    ],
    "sg:phone":"+1 718 378 2262",
    "sg:postcode":"10472",
    "sg:province":"NY",
    "wof:name":"Dental Saver",
    "wof:placetype":"venue"
},
  "geometry": {"coordinates":[-73.880301,40.828557],"type":"Point"}
}