{
  "type": "Feature",
  "properties": {
    "iso:country":"US",
    "sg:address":"27 Merlin Ave",
    "sg:city":"Tarrytown",
    "sg:classifiers":[
        {
            "category":"Banks & Credit Unions",
            "subcategory":"Investment Brokerage",
            "type":"Services"
        }
    ],
    "sg:phone":"+1 914 631 3231",
    "sg:postcode":"10591",
    "sg:province":"NY",
    "sg:tags":[
        "advisory"
    ],
    "wof:name":"Global Financial Services Inc",
    "wof:placetype":"venue"
},
  "geometry": {"coordinates":[-73.86291199999999,41.091712],"type":"Point"}
}