{
  "type": "Feature",
  "properties": {
    "iso:country":"US",
    "sg:address":"1163 47th St",
    "sg:city":"Brooklyn",
    "sg:classifiers":[
        {
            "category":"Professional",
            "subcategory":"Computer Services",
            "type":"Services"
        }
    ],
    "sg:phone":"+1 718 972 6423",
    "sg:postcode":"11219",
    "sg:province":"NY",
    "sg:tags":[
        "internet"
    ],
    "wof:name":"Dial A Toy",
    "wof:placetype":"venue"
},
  "geometry": {"coordinates":[-73.993583,40.637913],"type":"Point"}
}