{
  "type": "Feature",
  "properties": {
    "iso:country":"US",
    "sg:address":"2 Entrance Way",
    "sg:city":"Valhalla",
    "sg:classifiers":[
        {
            "category":"Building & Trades",
            "subcategory":"Plumbing",
            "type":"Services"
        }
    ],
    "sg:phone":"+1 914 592 1818",
    "sg:postcode":"10595",
    "sg:province":"NY",
    "sg:tags":[
        "plumbing",
        "heating",
        "contractor"
    ],
    "wof:name":"Mount Pleasant Plumbing & Htg",
    "wof:placetype":"venue"
},
  "geometry": {"coordinates":[-73.777236,41.072148],"type":"Point"}
}