{
  "type": "Feature",
  "properties": {
    "iso:country":"US",
    "sg:address":"197 Huguenot St",
    "sg:city":"New Paltz",
    "sg:classifiers":[
        {
            "category":"Health Services",
            "subcategory":"Health Practitioner",
            "type":"Services"
        }
    ],
    "sg:phone":"+1 845 255 6733",
    "sg:postcode":"12561",
    "sg:province":"NY",
    "sg:tags":[
        "psychologist"
    ],
    "wof:name":"Arnold J Weiner PHD",
    "wof:placetype":"venue"
},
  "geometry": {"coordinates":[-74.083912,41.763325],"type":"Point"}
}