{
  "type": "Feature",
  "properties": {
    "addr:full":"24 Washington St Trumansburg NY 14886",
    "addr:housenumber":"24",
    "addr:postcode":"14886",
    "addr:street":"Washington St",
    "iso:country":"US",
    "sg:address":"24 Washington St",
    "sg:city":"Trumansburg",
    "sg:classifiers":[
        {
            "category":"Professional",
            "subcategory":"Computer Services",
            "type":"Services"
        }
    ],
    "sg:phone":"+1 607 330 5711",
    "sg:postcode":"14886",
    "sg:province":"NY",
    "wof:name":"Network Abuse Clearinghouse",
    "wof:placetype":"venue"
},
  "geometry": {"coordinates":[-76.66401399999999,42.546114],"type":"Point"}
}