{
  "type": "Feature",
  "properties": {
    "iso:country":"US",
    "sg:address":"615 Middle Neck Rd",
    "sg:city":"Great Neck",
    "sg:classifiers":[
        {
            "category":"Professional",
            "subcategory":"Computer Services",
            "type":"Services"
        }
    ],
    "sg:phone":"+1 877 427 9992",
    "sg:postcode":"11023",
    "sg:province":"NY",
    "sg:tags":[
        "detail-renovations"
    ],
    "sg:website":"http://www.detailrenovations.com",
    "wof:name":"Detail Renovations",
    "wof:placetype":"venue"
},
  "geometry": {"coordinates":[-73.735675,40.803562],"type":"Point"}
}