{
  "type": "Feature",
  "properties": {
    "iso:country":"US",
    "sg:address":"25-40 27th St 3rd Fl",
    "sg:city":"Astoria",
    "sg:classifiers":[
        {
            "category":"Shopping",
            "subcategory":"Pets & Pet Supplies",
            "type":"Retail Goods"
        }
    ],
    "sg:phone":"+1 718 728 3200",
    "sg:postcode":"11102",
    "sg:province":"NY",
    "sg:tags":[
        "store"
    ],
    "sg:website":"www.twowaypet.com",
    "wof:name":"Two Way Pet",
    "wof:placetype":"venue"
},
  "geometry": {"coordinates":[-73.920886,40.771399],"type":"Point"}
}