{
  "type": "Feature",
  "properties": {
    "iso:country":"US",
    "sg:address":"1066 Englewood Ave",
    "sg:city":"Buffalo",
    "sg:classifiers":[
        {
            "category":"Professional",
            "subcategory":"Lawyer & Legal Services",
            "type":"Services"
        }
    ],
    "sg:phone":"+1 716 856 7784",
    "sg:postcode":"14223",
    "sg:province":"NY",
    "sg:tags":[
        "attorney"
    ],
    "wof:name":"William B Reilly",
    "wof:placetype":"venue"
},
  "geometry": {"coordinates":[-78.85579199999999,42.974087],"type":"Point"}
}