{
  "type": "Feature",
  "properties": {
    "iso:country":"US",
    "sg:address":"85 Bramhill Ct",
    "sg:city":"East Amherst",
    "sg:classifiers":[
        {
            "category":"Building & Trades",
            "subcategory":"Cleaning & Sanitation",
            "type":"Services"
        }
    ],
    "sg:phone":"+1 716 689 2624",
    "sg:postcode":"14051",
    "sg:province":"NY",
    "sg:tags":[
        "window"
    ],
    "wof:name":"Terry's Window Cleaning",
    "wof:placetype":"venue"
},
  "geometry": {"coordinates":[-78.722618,43.046874],"type":"Point"}
}