{
  "type": "Feature",
  "properties": {
    "addr:full":"RR 25 Box A Wading River NY 11792",
    "addr:housenumber":"25",
    "addr:postcode":"11792",
    "addr:street":"Rr;A Wading",
    "iso:country":"US",
    "sg:address":"RR 25 Box A",
    "sg:city":"Wading River",
    "sg:classifiers":[
        {
            "category":"Health Services",
            "subcategory":"Doctor",
            "type":"Services"
        }
    ],
    "sg:phone":"+1 631 929 4808",
    "sg:postcode":"11792",
    "sg:province":"NY",
    "sg:tags":[
        "cardiologist"
    ],
    "wof:name":"Eastern Suffolk Cardiology PC",
    "wof:placetype":"venue"
},
  "geometry": {"coordinates":[-72.835403,40.948002],"type":"Point"}
}