{
  "type": "Feature",
  "properties": {
    "iso:country":"US",
    "sg:address":"128 2nd Ave",
    "sg:city":"Albany",
    "sg:classifiers":[
        {
            "category":"Organizations",
            "subcategory":"Religious Organization",
            "type":"Services"
        }
    ],
    "sg:phone":"+1 518 465 1616",
    "sg:postcode":"12202",
    "sg:province":"NY",
    "sg:tags":[
        "church"
    ],
    "wof:name":"Church Of Jesus Christ Light",
    "wof:placetype":"venue"
},
  "geometry": {"coordinates":[-73.766212,42.638803],"type":"Point"}
}