{
  "type": "Feature",
  "properties": {
    "addr:full":"9011 35th Avenue Jackson Heights NY 11372",
    "addr:housenumber":"9011",
    "addr:postcode":"11372",
    "addr:street":"35Th Avenue",
    "iso:country":"US",
    "sg:address":"9011 35th Avenue",
    "sg:city":"Jackson Heights",
    "sg:classifiers":[
        {
            "category":"Real Estate",
            "subcategory":"Real Estate Services",
            "type":"Services"
        }
    ],
    "sg:phone":"+1 718 565 9039",
    "sg:postcode":"11372",
    "sg:province":"NY",
    "sg:tags":[
        "management",
        "property"
    ],
    "wof:name":"South View Owner Corporation",
    "wof:placetype":"venue"
},
  "geometry": {"coordinates":[-73.877005,40.752586],"type":"Point"}
}