{
  "type": "Feature",
  "properties": {
    "addr:full":"900 Jerusalem Ave Uniondale NY 11553",
    "addr:housenumber":"900",
    "addr:postcode":"11553",
    "addr:street":"Jerusalem Ave",
    "iso:country":"US",
    "sg:address":"900 Jerusalem Ave",
    "sg:city":"Uniondale",
    "sg:classifiers":[
        {
            "category":"Education",
            "subcategory":"Library",
            "type":"Public Place"
        }
    ],
    "sg:phone":"+1 516 292 8920",
    "sg:postcode":"11553",
    "sg:province":"NY",
    "sg:tags":[
        "information",
        "center"
    ],
    "sg:website":"www.nassaulibrary.org",
    "wof:name":"Nassau Library System",
    "wof:placetype":"venue"
},
  "geometry": {"coordinates":[-73.584577,40.6968],"type":"Point"}
}