{
  "type": "Feature",
  "properties": {
    "addr:full":"335 Delaware Ave Albany NY 12209",
    "addr:housenumber":"335",
    "addr:postcode":"12209",
    "addr:street":"Delaware Ave",
    "iso:country":"US",
    "sg:address":"335 Delaware Ave",
    "sg:city":"Albany",
    "sg:classifiers":[
        {
            "category":"Professional",
            "subcategory":"Lawyer & Legal Services",
            "type":"Services"
        }
    ],
    "sg:phone":"+1 518 478 0245",
    "sg:postcode":"12209",
    "sg:province":"NY",
    "sg:tags":[
        "attorney"
    ],
    "wof:name":"Melissa A Carpinello",
    "wof:placetype":"venue"
},
  "geometry": {"coordinates":[-73.778165,42.642469],"type":"Point"}
}