{
  "type": "Feature",
  "properties": {
    "iso:country":"US",
    "sg:address":"729 Main St",
    "sg:city":"East Aurora",
    "sg:classifiers":[
        {
            "category":"Manufacturing",
            "subcategory":"Tools & Machinery",
            "type":"Manufacturing & Wholesale Goods"
        }
    ],
    "sg:phone":"+1 716 652 1507",
    "sg:postcode":"14052",
    "sg:province":"NY",
    "sg:tags":[
        "machine",
        "shop"
    ],
    "wof:name":"Logan & Youngers Napa AUTO",
    "wof:placetype":"venue"
},
  "geometry": {"coordinates":[-78.60638299999999,42.767723],"type":"Point"}
}