{
  "type": "Feature",
  "properties": {
    "addr:full":"45 Austin Blvd Commack NY 11725",
    "addr:housenumber":"45",
    "addr:postcode":"11725",
    "addr:street":"Austin Blvd",
    "iso:country":"US",
    "sg:address":"45 Austin Blvd",
    "sg:city":"Commack",
    "sg:classifiers":[
        {
            "category":"Home & Garden",
            "subcategory":"Carpets & Floor Coverings",
            "type":"Retail Goods"
        }
    ],
    "sg:phone":"+1 631 864 9169",
    "sg:postcode":"11725",
    "sg:province":"NY",
    "sg:tags":[
        "carpeting"
    ],
    "wof:name":"Excel Carpets",
    "wof:placetype":"venue"
},
  "geometry": {"coordinates":[-73.273804,40.807999],"type":"Point"}
}