{
  "type": "Feature",
  "properties": {
    "addr:full":"1140 Bay St Ste G Staten Island NY 10305",
    "addr:housenumber":"1140",
    "addr:postcode":"10305",
    "addr:street":"Bay St Ste G",
    "iso:country":"US",
    "sg:address":"1140 Bay St Ste G",
    "sg:city":"Staten Island",
    "sg:classifiers":[
        {
            "category":"Food & Beverages",
            "subcategory":"Groceries & Convenience Stores",
            "type":"Retail Goods"
        }
    ],
    "sg:phone":"+1 718 448 8077",
    "sg:postcode":"10305",
    "sg:province":"NY",
    "wof:name":"Montalbanos Salumeria",
    "wof:placetype":"venue"
},
  "geometry": {"coordinates":[-74.067001,40.6152],"type":"Point"}
}