{
  "type": "Feature",
  "properties": {
    "addr:full":"5904 N Burdick St East Syracuse NY 13057",
    "addr:housenumber":"5904",
    "addr:postcode":"13057",
    "addr:street":"N Burdick St",
    "iso:country":"US",
    "sg:address":"5904 N Burdick St",
    "sg:city":"East Syracuse",
    "sg:classifiers":[
        {
            "category":"Sports & Exercise",
            "subcategory":"Golf",
            "type":"Entertainment"
        }
    ],
    "sg:phone":"+1 315 656 4653",
    "sg:postcode":"13057",
    "sg:province":"NY",
    "sg:tags":[
        "course"
    ],
    "wof:name":"Links At Erie Village",
    "wof:placetype":"venue"
},
  "geometry": {"coordinates":[-76.021743,43.059918],"type":"Point"}
}