{
  "type": "Feature",
  "properties": {
    "addr:full":"65 W 90 St New York NY 10024",
    "addr:housenumber":"65",
    "addr:postcode":"10024",
    "addr:street":"W 90 St",
    "iso:country":"US",
    "sg:address":"65 W 90 St",
    "sg:city":"New York",
    "sg:classifiers":[
        {
            "category":"Shopping",
            "subcategory":"Computers & Home Electronics",
            "type":"Retail Goods"
        }
    ],
    "sg:phone":"+1 212 877 8893",
    "sg:postcode":"10024",
    "sg:province":"NY",
    "sg:tags":[
        "equipment",
        "dealer"
    ],
    "wof:name":"North River Corp",
    "wof:placetype":"venue"
},
  "geometry": {"coordinates":[-73.969263,40.788566],"type":"Point"}
}