{
  "type": "Feature",
  "properties": {
    "iso:country":"US",
    "sg:address":"9 Market St",
    "sg:city":"Potsdam",
    "sg:classifiers":[
        {
            "category":"Food & Beverages",
            "subcategory":"Bakery",
            "type":"Retail Goods"
        }
    ],
    "sg:phone":"+1 315 265 9378",
    "sg:postcode":"13676",
    "sg:province":"NY",
    "sg:tags":[
        "bagel"
    ],
    "wof:name":"Bagelry",
    "wof:placetype":"venue"
},
  "geometry": {"coordinates":[-74.986845,44.668921],"type":"Point"}
}