{
  "type": "Feature",
  "properties": {
    "addr:full":"875 Old Country Rd Plainview NY 11803",
    "addr:housenumber":"875",
    "addr:postcode":"11803",
    "addr:street":"Old Country Rd",
    "iso:country":"US",
    "sg:address":"875 Old Country Rd",
    "sg:city":"Plainview",
    "sg:classifiers":[
        {
            "category":"Restaurant",
            "type":"Food & Drink"
        }
    ],
    "sg:phone":"+1 516 681 0941",
    "sg:postcode":"11803",
    "sg:province":"NY",
    "wof:name":"Old Country Professional Ofc",
    "wof:placetype":"venue"
},
  "geometry": {"coordinates":[-73.478696,40.774169],"type":"Point"}
}