{
  "type": "Feature",
  "properties": {
    "iso:country":"US",
    "sg:address":"6726 Town Line Rd",
    "sg:city":"Syracuse",
    "sg:classifiers":[
        {
            "category":"Wholesale",
            "subcategory":"Office Equipment",
            "type":"Manufacturing & Wholesale Goods"
        }
    ],
    "sg:phone":"+1 315 455 5005",
    "sg:postcode":"13211",
    "sg:province":"NY",
    "sg:tags":[
        "machine",
        "supply"
    ],
    "wof:name":"A S A Imaging Systems",
    "wof:placetype":"venue"
},
  "geometry": {"coordinates":[-76.117171,43.096529],"type":"Point"}
}