{
  "type": "Feature",
  "properties": {
    "addr:full":"3200 Jerome Ave Bronx NY 10468",
    "addr:housenumber":"3200",
    "addr:postcode":"10468",
    "addr:street":"Jerome Ave",
    "iso:country":"US",
    "sg:address":"3200 Jerome Ave",
    "sg:city":"Bronx",
    "sg:classifiers":[
        {
            "category":"Education",
            "subcategory":"School",
            "type":"Public Place"
        }
    ],
    "sg:phone":"+1 718 584 8772",
    "sg:postcode":"10468",
    "sg:province":"NY",
    "sg:website":"http://www.autohs.com",
    "wof:name":"Ps 51",
    "wof:placetype":"venue"
},
  "geometry": {"coordinates":[-73.887749,40.877022],"type":"Point"}
}