{
  "type": "Feature",
  "properties": {
    "addr:full":"1 Babbitt Rd Bedford Hills NY 10507",
    "addr:housenumber":"1",
    "addr:postcode":"10507",
    "addr:street":"Babbitt Rd",
    "iso:country":"US",
    "sg:address":"1 Babbitt Rd",
    "sg:city":"Bedford Hills",
    "sg:classifiers":[
        {
            "category":"Shopping",
            "subcategory":"Clothing, Apparel, & Fashions",
            "type":"Retail Goods"
        }
    ],
    "sg:phone":"+1   ",
    "sg:postcode":"10507",
    "sg:province":"NY",
    "sg:tags":[
        "dry",
        "cleaners",
        "tailor",
        "custom"
    ],
    "wof:name":"Curro Custom Tailors & Clrs",
    "wof:placetype":"venue"
},
  "geometry": {"coordinates":[-73.699218,41.236633],"type":"Point"}
}