{
  "type": "Feature",
  "properties": {
    "iso:country":"US",
    "sg:address":"233 W 99 St",
    "sg:city":"New York",
    "sg:classifiers":[
        {
            "category":"Personal",
            "subcategory":"Beauty Salon",
            "type":"Services"
        }
    ],
    "sg:phone":"+1   ",
    "sg:postcode":"10025",
    "sg:province":"NY",
    "sg:tags":[
        "shop"
    ],
    "wof:name":"Jl Haircutters Prendergast",
    "wof:placetype":"venue"
},
  "geometry": {"coordinates":[-73.96943400000001,40.79615],"type":"Point"}
}