{
  "type": "Feature",
  "properties": {
    "addr:full":"121 Old Niskayuna Rd Loudonville NY 12211",
    "addr:housenumber":"121",
    "addr:postcode":"12211",
    "addr:street":"Old Niskayuna Rd",
    "iso:country":"US",
    "sg:address":"121 Old Niskayuna Rd",
    "sg:city":"Loudonville",
    "sg:classifiers":[
        {
            "category":"Education",
            "subcategory":"School",
            "type":"Public Place"
        }
    ],
    "sg:phone":"+1 518 785 6621",
    "sg:postcode":"12211",
    "sg:province":"NY",
    "sg:tags":[
        "religious"
    ],
    "sg:website":"www.stgregoryschool.org",
    "wof:name":"St Gregory's School For Boys",
    "wof:placetype":"venue"
},
  "geometry": {"coordinates":[-73.771196,42.721358],"type":"Point"}
}