{
  "type": "Feature",
  "properties": {
    "addr:full":"855 Madison Avenue New York NY 10021",
    "addr:housenumber":"855",
    "addr:postcode":"10021",
    "addr:street":"Madison Avenue",
    "iso:country":"US",
    "sg:address":"855 Madison Avenue",
    "sg:city":"New York",
    "sg:classifiers":[
        {
            "category":"Shopping",
            "subcategory":"Clothing, Apparel, & Fashions",
            "type":"Retail Goods"
        },
        {
            "category":"Manufacturing",
            "subcategory":"Leather Goods",
            "type":"Manufacturing & Wholesale Goods"
        },
        {
            "category":"Shopping",
            "subcategory":"Shoes",
            "type":"Retail Goods"
        }
    ],
    "sg:phone":"+1 212 988 3821",
    "sg:postcode":"10021",
    "sg:province":"NY",
    "sg:tags":[
        "women's",
        "men's",
        "clothing",
        "store",
        "accessory"
    ],
    "sg:website":"www.ysl.com",
    "wof:name":"Yves Saint Laurent Boutique",
    "wof:placetype":"venue"
},
  "geometry": {"coordinates":[-73.966204,40.770936],"type":"Point"}
}