{
  "type": "Feature",
  "properties": {
    "addr:full":"265 Hempstead Tpke Elmont NY 11003",
    "addr:housenumber":"265",
    "addr:postcode":"11003",
    "addr:street":"Hempstead Tpke",
    "iso:country":"US",
    "sg:address":"265 Hempstead Tpke",
    "sg:city":"Elmont",
    "sg:classifiers":[
        {
            "category":"Travel",
            "subcategory":"Travel Agent",
            "type":"Entertainment"
        }
    ],
    "sg:phone":"+1   ",
    "sg:postcode":"11003",
    "sg:province":"NY",
    "sg:tags":[
        "agency"
    ],
    "wof:name":"Belmont Travel",
    "wof:placetype":"venue"
},
  "geometry": {"coordinates":[-73.71681599999999,40.707989],"type":"Point"}
}