{
  "type": "Feature",
  "properties": {
    "iso:country":"US",
    "sg:address":"4640 Broadway",
    "sg:city":"Depew",
    "sg:classifiers":[
        {
            "category":"Home & Garden",
            "subcategory":"Household Appliances",
            "type":"Retail Goods"
        }
    ],
    "sg:phone":"+1 716 684 8383",
    "sg:postcode":"14043",
    "sg:province":"NY",
    "sg:tags":[
        "cleaners",
        "vacuum"
    ],
    "wof:name":"Kirby Co",
    "wof:placetype":"venue"
},
  "geometry": {"coordinates":[-78.703174,42.901777],"type":"Point"}
}