{
  "type": "Feature",
  "properties": {
    "addr:full":"51 Beechdale Rd Dobbs Ferry NY 10522",
    "addr:housenumber":"51",
    "addr:postcode":"10522",
    "addr:street":"Beechdale Rd",
    "iso:country":"US",
    "sg:address":"51 Beechdale Rd",
    "sg:city":"Dobbs Ferry",
    "sg:classifiers":[
        {
            "category":"Arts & Performance",
            "subcategory":"Theater",
            "type":"Entertainment"
        }
    ],
    "sg:phone":"+1   ",
    "sg:postcode":"10522",
    "sg:province":"NY",
    "sg:tags":[
        "theatrical"
    ],
    "wof:name":"Gallega Productions",
    "wof:placetype":"venue"
},
  "geometry": {"coordinates":[-73.870344,41.002922],"type":"Point"}
}