{
  "type": "Feature",
  "properties": {
    "iso:country":"US",
    "sg:address":"88 Bowery",
    "sg:city":"New York",
    "sg:classifiers":[
        {
            "category":"Wholesale",
            "subcategory":"Jewelry",
            "type":"Manufacturing & Wholesale Goods"
        }
    ],
    "sg:phone":"+1 212 966 7445",
    "sg:postcode":"10013",
    "sg:province":"NY",
    "wof:name":"L & L Jewelry Distributors",
    "wof:placetype":"venue"
},
  "geometry": {"coordinates":[-73.996078,40.716196],"type":"Point"}
}