{
  "type": "Feature",
  "properties": {
    "addr:full":"432 E 14th St New York NY 10009",
    "addr:housenumber":"432",
    "addr:postcode":"10009",
    "addr:street":"E 14Th St",
    "iso:country":"US",
    "sg:address":"432 E 14th St",
    "sg:city":"New York",
    "sg:classifiers":[
        {
            "category":"Government",
            "subcategory":"Post Office",
            "type":"Public Place"
        }
    ],
    "sg:phone":"+1 212 677 2112",
    "sg:postcode":"10009",
    "sg:province":"NY",
    "wof:name":"United States Government",
    "wof:placetype":"venue"
},
  "geometry": {"coordinates":[-73.981022,40.730641],"type":"Point"}
}