{
  "type": "Feature",
  "properties": {
    "iso:country":"US",
    "sg:address":"4833 State Hwy 365",
    "sg:city":"Oneida",
    "sg:classifiers":[
        {
            "category":"Shopping",
            "type":"Retail Goods"
        }
    ],
    "sg:phone":"+1   ",
    "sg:postcode":"13421",
    "sg:province":"NY",
    "sg:tags":[
        "laboratory",
        "testing",
        "merchandise"
    ],
    "wof:name":"Water Solutions",
    "wof:placetype":"venue"
},
  "geometry": {"coordinates":[-75.621094,43.096964],"type":"Point"}
}