{
  "type": "Feature",
  "properties": {
    "iso:country":"US",
    "sg:address":"219 Hillside Ave",
    "sg:city":"Orchard Park",
    "sg:classifiers":[
        {
            "category":"Personal",
            "subcategory":"Beauty Salon",
            "type":"Services"
        }
    ],
    "sg:phone":"+1   ",
    "sg:postcode":"14127",
    "sg:province":"NY",
    "sg:tags":[
        "shop"
    ],
    "wof:name":"Hair Shed",
    "wof:placetype":"venue"
},
  "geometry": {"coordinates":[-78.78882,42.799794],"type":"Point"}
}