{
  "type": "Feature",
  "properties": {
    "iso:country":"US",
    "sg:address":"4480 Old Post Rd",
    "sg:city":"Bedford",
    "sg:classifiers":[
        {
            "category":"Home & Garden",
            "subcategory":"Building Materials",
            "type":"Retail Goods"
        },
        {
            "category":"Building & Trades",
            "subcategory":"Construction",
            "type":"Services"
        }
    ],
    "sg:phone":"+1 914 205 3304",
    "sg:postcode":"10506",
    "sg:province":"NY",
    "sg:tags":[
        "altering",
        "improvement",
        "remodeling",
        "contractor"
    ],
    "wof:name":"Maintenance Made Simple",
    "wof:placetype":"venue"
},
  "geometry": {"coordinates":[-73.647087,41.20023],"type":"Point"}
}