{
  "type": "Feature",
  "properties": {
    "addr:full":"120 Bevy Ct Brooklyn NY 11229",
    "addr:housenumber":"120",
    "addr:postcode":"11229",
    "addr:street":"Bevy Ct",
    "iso:country":"US",
    "sg:address":"120 Bevy Ct",
    "sg:city":"Brooklyn",
    "sg:classifiers":[
        {
            "category":"Home & Garden",
            "subcategory":"Building Materials",
            "type":"Retail Goods"
        },
        {
            "category":"Building & Trades",
            "subcategory":"Construction",
            "type":"Services"
        }
    ],
    "sg:phone":"+1 718 648 1309",
    "sg:postcode":"11229",
    "sg:province":"NY",
    "sg:tags":[
        "windows",
        "window",
        "installation",
        "siding",
        "contractor"
    ],
    "wof:name":"Witkowski Brothers Inc",
    "wof:placetype":"venue"
},
  "geometry": {"coordinates":[-73.929772,40.595609],"type":"Point"}
}