{
  "type": "Feature",
  "properties": {
    "iso:country":"US",
    "sg:address":"16 Crawford St",
    "sg:city":"Cortland",
    "sg:classifiers":[
        {
            "category":"Social Services",
            "type":"Services"
        }
    ],
    "sg:phone":"+1 607 756 2015",
    "sg:postcode":"13045",
    "sg:province":"NY",
    "wof:name":"Madisn-Cortlnd Cty Chptr Nysar",
    "wof:placetype":"venue"
},
  "geometry": {"coordinates":[-76.181653,42.590981],"type":"Point"}
}