{
  "type": "Feature",
  "properties": {
    "addr:full":"454 Chester St Brooklyn NY 11212",
    "addr:housenumber":"454",
    "addr:postcode":"11212",
    "addr:street":"Chester St",
    "iso:country":"US",
    "sg:address":"454 Chester St",
    "sg:city":"Brooklyn",
    "sg:classifiers":[
        {
            "category":"Organizations",
            "subcategory":"Non-profit Organization",
            "type":"Services"
        }
    ],
    "sg:phone":"+1 718 485 1200",
    "sg:postcode":"11212",
    "sg:province":"NY",
    "sg:tags":[
        "social"
    ],
    "wof:name":"Fpro",
    "wof:placetype":"venue"
},
  "geometry": {"coordinates":[-73.909222,40.659748],"type":"Point"}
}