{
  "type": "Feature",
  "properties": {
    "iso:country":"US",
    "sg:address":"624 Central Ave",
    "sg:city":"Albany",
    "sg:classifiers":[
        {
            "category":"Retail",
            "subcategory":"Repair Shop",
            "type":"Services"
        }
    ],
    "sg:phone":"+1 518 489 2268",
    "sg:postcode":"12206",
    "sg:province":"NY",
    "sg:tags":[
        "upholsterer"
    ],
    "wof:name":"Johnston Upholstery",
    "wof:placetype":"venue"
},
  "geometry": {"coordinates":[-73.78251899999999,42.673426],"type":"Point"}
}