{
  "type": "Feature",
  "properties": {
    "addr:full":"2115 Caroline St Utica NY 13502",
    "addr:housenumber":"2115",
    "addr:postcode":"13502",
    "addr:street":"Caroline St",
    "iso:country":"US",
    "sg:address":"2115 Caroline St",
    "sg:city":"Utica",
    "sg:classifiers":[
        {
            "category":"Organizations",
            "subcategory":"Religious Organization",
            "type":"Services"
        }
    ],
    "sg:phone":"+1 315 735 6105",
    "sg:postcode":"13502",
    "sg:province":"NY",
    "wof:name":"Sacred Heart Church",
    "wof:placetype":"venue"
},
  "geometry": {"coordinates":[-75.26582999999999,43.107906],"type":"Point"}
}