{
  "type": "Feature",
  "properties": {
    "addr:full":"4 Knox Pl Huntington Station NY 11746",
    "addr:housenumber":"4",
    "addr:postcode":"11746",
    "addr:street":"Knox Pl Huntington",
    "iso:country":"US",
    "sg:address":"4 Knox Pl",
    "sg:city":"Huntington Station",
    "sg:classifiers":[
        {
            "category":"Building & Trades",
            "subcategory":"Cleaning & Sanitation",
            "type":"Services"
        }
    ],
    "sg:phone":"+1   ",
    "sg:postcode":"11746",
    "sg:province":"NY",
    "sg:tags":[
        "maintenance"
    ],
    "wof:name":"Caumsett Leasing Inc",
    "wof:placetype":"venue"
},
  "geometry": {"coordinates":[-73.302655,40.81291],"type":"Point"}
}