{
  "type": "Feature",
  "properties": {
    "iso:country":"US",
    "sg:address":"1 Family Practice Dr",
    "sg:city":"Kingston",
    "sg:classifiers":[
        {
            "category":"Health Services",
            "subcategory":"Doctor",
            "type":"Services"
        }
    ],
    "sg:phone":"+1 845 339 9055",
    "sg:postcode":"12401",
    "sg:province":"NY",
    "sg:tags":[
        "physician",
        "surgeon"
    ],
    "wof:name":"Pediatric Care Ctr",
    "wof:placetype":"venue"
},
  "geometry": {"coordinates":[-74.015399,41.916658],"type":"Point"}
}