{
  "type": "Feature",
  "properties": {
    "iso:country":"US",
    "sg:address":"38 E 4th St",
    "sg:city":"Manhattan",
    "sg:classifiers":[
        {
            "category":"Travel",
            "subcategory":"Hotels & Motels",
            "type":"Entertainment"
        }
    ],
    "sg:phone":"+1 212 505 8100",
    "sg:postcode":"10003",
    "sg:province":"NY",
    "sg:website":"www.lafayettehouse.com",
    "wof:name":"The Lafayette House",
    "wof:placetype":"venue"
},
  "geometry": {"coordinates":[-73.992209,40.727161],"type":"Point"}
}