{
  "type": "Feature",
  "properties": {
    "addr:full":"307 S Bicycle Path Farmingville NY 11738",
    "addr:housenumber":"307",
    "addr:postcode":"11738",
    "addr:street":"S Bicycle Path",
    "iso:country":"US",
    "sg:address":"307 S Bicycle Path",
    "sg:city":"Farmingville",
    "sg:classifiers":[
        {
            "category":"Building & Trades",
            "subcategory":"Construction",
            "type":"Services"
        }
    ],
    "sg:phone":"+1 631 696 8012",
    "sg:postcode":"11738",
    "sg:province":"NY",
    "sg:tags":[
        "concrete",
        "contractor"
    ],
    "wof:name":"Vista Contractors Corp",
    "wof:placetype":"venue"
},
  "geometry": {"coordinates":[-73.014816,40.839275],"type":"Point"}
}