{
  "type": "Feature",
  "properties": {
    "addr:full":"468 Mamaroneck Ave White Plains NY 10605",
    "addr:housenumber":"468",
    "addr:postcode":"10605",
    "addr:street":"Mamaroneck Ave",
    "iso:country":"US",
    "sg:address":"468 Mamaroneck Ave",
    "sg:city":"White Plains",
    "sg:classifiers":[
        {
            "category":"Restaurant",
            "type":"Food & Drink"
        }
    ],
    "sg:phone":"+1 914 946 5670",
    "sg:postcode":"10605",
    "sg:province":"NY",
    "wof:name":"Church St Cafe",
    "wof:placetype":"venue"
},
  "geometry": {"coordinates":[-73.759647,41.022604],"type":"Point"}
}