{
  "type": "Feature",
  "properties": {
    "iso:country":"US",
    "sg:address":"454 Manhattan Ave.",
    "sg:city":"Manhattan",
    "sg:classifiers":[
        {
            "category":"Professional",
            "type":"Services"
        },
        {
            "category":"Personal",
            "type":"Services"
        }
    ],
    "sg:phone":"+1 917 301 1981",
    "sg:postcode":"10026",
    "sg:province":"NY",
    "sg:tags":[
        "local"
    ],
    "sg:website":"www.organizingwiz.com",
    "wof:name":"The Organizing Wiz",
    "wof:placetype":"venue"
},
  "geometry": {"coordinates":[-73.954911,40.807167],"type":"Point"}
}