{
  "type": "Feature",
  "properties": {
    "iso:country":"US",
    "sg:address":"1814 E 19th St",
    "sg:city":"Brooklyn",
    "sg:classifiers":[
        {
            "category":"Building & Trades",
            "subcategory":"Construction",
            "type":"Services"
        }
    ],
    "sg:phone":"+1 718 339 2466",
    "sg:postcode":"11229",
    "sg:province":"NY",
    "sg:tags":[
        "hanging",
        "painter",
        "contractor"
    ],
    "wof:name":"Abe's Painting & Decorating",
    "wof:placetype":"venue"
},
  "geometry": {"coordinates":[-73.95360700000001,40.604213],"type":"Point"}
}