{
  "type": "Feature",
  "properties": {
    "addr:full":"1154 Nostrand Ave Brooklyn NY 11225",
    "addr:housenumber":"1154",
    "addr:postcode":"11225",
    "addr:street":"Nostrand Ave",
    "iso:country":"US",
    "sg:address":"1154 Nostrand Ave",
    "sg:city":"Brooklyn",
    "sg:classifiers":[
        {
            "category":"Building & Trades",
            "subcategory":"Construction",
            "type":"Services"
        }
    ],
    "sg:phone":"+1 347 425 8496",
    "sg:postcode":"11225",
    "sg:province":"NY",
    "sg:tags":[
        "contractor"
    ],
    "wof:name":"Clover Communication Services",
    "wof:placetype":"venue"
},
  "geometry": {"coordinates":[-73.95067299999999,40.659334],"type":"Point"}
}