{
  "type": "Feature",
  "properties": {
    "iso:country":"US",
    "sg:address":"4 Delavan Ter",
    "sg:city":"Yonkers",
    "sg:classifiers":[
        {
            "category":"Professional",
            "subcategory":"Lawyer & Legal Services",
            "type":"Services"
        }
    ],
    "sg:phone":"+1 914 423 7075",
    "sg:postcode":"10703",
    "sg:province":"NY",
    "sg:tags":[
        "attorney"
    ],
    "wof:name":"Lawrence Sykes Attorney",
    "wof:placetype":"venue"
},
  "geometry": {"coordinates":[-73.890773,40.944934],"type":"Point"}
}