{
  "type": "Feature",
  "properties": {
    "addr:full":"11 Clinton Ave Rockville Centre NY 11570",
    "addr:housenumber":"11",
    "addr:postcode":"11570",
    "addr:street":"Clinton Ave",
    "iso:country":"US",
    "sg:address":"11 Clinton Ave",
    "sg:city":"Rockville Centre",
    "sg:classifiers":[
        {
            "category":"Professional",
            "subcategory":"Lawyer & Legal Services",
            "type":"Services"
        }
    ],
    "sg:phone":"+1 516 255 2070",
    "sg:postcode":"11570",
    "sg:province":"NY",
    "sg:tags":[
        "attorney"
    ],
    "wof:name":"Kevin T Kearon",
    "wof:placetype":"venue"
},
  "geometry": {"coordinates":[-73.64593600000001,40.658768],"type":"Point"}
}