{
  "type": "Feature",
  "properties": {
    "addr:full":"47 Montcalm St Lake George NY 12845",
    "addr:housenumber":"47",
    "addr:postcode":"12845",
    "addr:street":"Montcalm St",
    "iso:country":"US",
    "sg:address":"47 Montcalm St",
    "sg:city":"Lake George",
    "sg:classifiers":[
        {
            "category":"Travel",
            "subcategory":"Hotels & Motels",
            "type":"Entertainment"
        }
    ],
    "sg:phone":"+1 518 668 5477",
    "sg:postcode":"12845",
    "sg:province":"NY",
    "sg:website":"www.lakegeorgebb.com",
    "wof:name":"Lake George Bed & Breakfast",
    "wof:placetype":"venue"
},
  "geometry": {"coordinates":[-73.714297,43.42486],"type":"Point"}
}