{
  "type": "Feature",
  "properties": {
    "iso:country":"US",
    "sg:address":"7607 Oswego Rd",
    "sg:city":"Liverpool",
    "sg:classifiers":[
        {
            "category":"Local Transit",
            "type":"Transportation"
        }
    ],
    "sg:phone":"+1 315 622 5700",
    "sg:postcode":"13090",
    "sg:province":"NY",
    "sg:tags":[
        "limousine"
    ],
    "wof:name":"Allknight Limousine",
    "wof:placetype":"venue"
},
  "geometry": {"coordinates":[-76.226361,43.137921],"type":"Point"}
}