{
  "type": "Feature",
  "properties": {
    "iso:country":"US",
    "sg:address":"23707 Linden Blvd",
    "sg:city":"Elmont",
    "sg:classifiers":[
        {
            "category":"Personal",
            "subcategory":"Nail Salon",
            "type":"Services"
        }
    ],
    "sg:phone":"+1 516 285 5184",
    "sg:postcode":"11003",
    "sg:province":"NY",
    "wof:name":"Ninique Nail Salon",
    "wof:placetype":"venue"
},
  "geometry": {"coordinates":[-73.72530399999999,40.690601],"type":"Point"}
}