{
  "type": "Feature",
  "properties": {
    "addr:full":"4775 Wetzel Rd Liverpool NY 13090",
    "addr:housenumber":"4775",
    "addr:postcode":"13090",
    "addr:street":"Wetzel Rd",
    "iso:country":"US",
    "sg:address":"4775 Wetzel Rd",
    "sg:city":"Liverpool",
    "sg:classifiers":[
        {
            "category":"Social Services",
            "subcategory":"Child Care",
            "type":"Services"
        }
    ],
    "sg:phone":"+1 315 451 2562",
    "sg:postcode":"13090",
    "sg:province":"NY",
    "sg:website":"www.northareafamilyymca.org",
    "wof:name":"YMCA",
    "wof:placetype":"venue"
},
  "geometry": {"coordinates":[-76.183311,43.149374],"type":"Point"}
}