{
  "type": "Feature",
  "properties": {
    "iso:country":"US",
    "sg:address":"140 Fairmont Ave",
    "sg:city":"Hastings On Hudson",
    "sg:classifiers":[
        {
            "category":"Building & Trades",
            "subcategory":"Electrical",
            "type":"Services"
        }
    ],
    "sg:phone":"+1 914 478 3192",
    "sg:postcode":"10706",
    "sg:province":"NY",
    "sg:tags":[
        "electrical",
        "contractor"
    ],
    "wof:name":"Wire Masters",
    "wof:placetype":"venue"
},
  "geometry": {"coordinates":[-73.86510699999999,40.989101],"type":"Point"}
}