{
  "type": "Feature",
  "properties": {
    "iso:country":"US",
    "sg:address":"13520 39th Ave",
    "sg:city":"Flushing",
    "sg:classifiers":[
        {
            "category":"Banks & Credit Unions",
            "subcategory":"Bank",
            "type":"Services"
        }
    ],
    "sg:phone":"+1 718 886 9765",
    "sg:postcode":"11354",
    "sg:province":"NY",
    "wof:name":"Bank of East Asia",
    "wof:placetype":"venue"
},
  "geometry": {"coordinates":[-73.83200100000001,40.7598],"type":"Point"}
}