{
  "type": "Feature",
  "properties": {
    "iso:country":"US",
    "sg:address":"531 Meade St",
    "sg:city":"Watertown",
    "sg:classifiers":[
        {
            "category":"Government",
            "subcategory":"Office",
            "type":"Public Place"
        }
    ],
    "sg:phone":"+1 315 785 3062",
    "sg:postcode":"13601",
    "sg:province":"NY",
    "sg:tags":[
        "county",
        "resource"
    ],
    "wof:name":"Jefferson County Handicapped",
    "wof:placetype":"venue"
},
  "geometry": {"coordinates":[-75.91829199999999,43.986021],"type":"Point"}
}