{
  "type": "Feature",
  "properties": {
    "addr:full":"1117 Madison Ave New York NY 10028",
    "addr:housenumber":"1117",
    "addr:postcode":"10028",
    "addr:street":"Madison Ave",
    "iso:country":"US",
    "sg:address":"1117 Madison Ave",
    "sg:city":"New York",
    "sg:classifiers":[
        {
            "category":"Restaurant",
            "type":"Food & Drink"
        }
    ],
    "sg:phone":"+1   ",
    "sg:postcode":"10028",
    "sg:province":"NY",
    "sg:tags":[
        "eating"
    ],
    "wof:name":"La Tete De Paris",
    "wof:placetype":"venue"
},
  "geometry": {"coordinates":[-73.959959,40.77905],"type":"Point"}
}