{
  "type": "Feature",
  "properties": {
    "iso:country":"US",
    "sg:address":"6 Simmons Ln",
    "sg:city":"Albany",
    "sg:classifiers":[
        {
            "category":"Professional",
            "subcategory":"Business Services",
            "type":"Services"
        }
    ],
    "sg:phone":"+1 518 459 2855",
    "sg:postcode":"12204",
    "sg:province":"NY",
    "sg:tags":[
        "embroidery"
    ],
    "wof:name":"Wicked Smart Apparel",
    "wof:placetype":"venue"
},
  "geometry": {"coordinates":[-73.730699,42.680563],"type":"Point"}
}