{
  "type": "Feature",
  "properties": {
    "iso:country":"US",
    "sg:address":"1231 Beech St",
    "sg:city":"Atlantic Beach",
    "sg:classifiers":[
        {
            "category":"Health Services",
            "subcategory":"Doctor",
            "type":"Services"
        }
    ],
    "sg:phone":"+1 718 831 0205",
    "sg:postcode":"11509",
    "sg:province":"NY",
    "sg:tags":[
        "medical"
    ],
    "wof:name":"A Lawrence Rubine",
    "wof:placetype":"venue"
},
  "geometry": {"coordinates":[-73.70778799999999,40.586774],"type":"Point"}
}