{
  "type": "Feature",
  "properties": {
    "addr:full":"1069 Flatbush Ave Brooklyn NY 11226",
    "addr:housenumber":"1069",
    "addr:postcode":"11226",
    "addr:street":"Flatbush Ave",
    "iso:country":"US",
    "sg:address":"1069 Flatbush Ave",
    "sg:city":"Brooklyn",
    "sg:classifiers":[
        {
            "category":"Shopping",
            "subcategory":"Clothing, Apparel, & Fashions",
            "type":"Retail Goods"
        }
    ],
    "sg:phone":"+1 718 284 5801",
    "sg:postcode":"11226",
    "sg:province":"NY",
    "sg:tags":[
        "furnishing"
    ],
    "wof:name":"Song's Clothing",
    "wof:placetype":"venue"
},
  "geometry": {"coordinates":[-73.958022,40.64507],"type":"Point"}
}