{
  "type": "Feature",
  "properties": {
    "addr:full":"100 W 94 St New York NY 10025",
    "addr:housenumber":"100",
    "addr:postcode":"10025",
    "addr:street":"W 94 St",
    "iso:country":"US",
    "sg:address":"100 W 94 St",
    "sg:city":"New York",
    "sg:classifiers":[
        {
            "category":"Shopping",
            "subcategory":"Gifts & Souvenirs",
            "type":"Retail Goods"
        }
    ],
    "sg:phone":"+1   ",
    "sg:postcode":"10025",
    "sg:province":"NY",
    "wof:name":"Belle Epoque",
    "wof:placetype":"venue"
},
  "geometry": {"coordinates":[-73.96879199999999,40.791699],"type":"Point"}
}