{
  "type": "Feature",
  "properties": {
    "iso:country":"US",
    "sg:address":"1671 Route 112 Ste 3",
    "sg:city":"Coram",
    "sg:classifiers":[
        {
            "category":"Deli",
            "type":"Food & Drink"
        },
        {
            "category":"Food & Beverages",
            "subcategory":"Bakery",
            "type":"Retail Goods"
        }
    ],
    "sg:phone":"+1 631 476 5857",
    "sg:postcode":"11727",
    "sg:province":"NY",
    "sg:tags":[
        "sandwich"
    ],
    "wof:name":"Earlys Market",
    "wof:placetype":"venue"
},
  "geometry": {"coordinates":[-73.31771999999999,40.901584],"type":"Point"}
}