{
  "type": "Feature",
  "properties": {
    "iso:country":"US",
    "sg:address":"525 Fashion Ave Rm 314",
    "sg:city":"New York",
    "sg:classifiers":[
        {
            "category":"Shopping",
            "subcategory":"Shoes",
            "type":"Retail Goods"
        }
    ],
    "sg:phone":"+1 212 382 1116",
    "sg:postcode":"10018",
    "sg:province":"NY",
    "sg:tags":[
        "store"
    ],
    "wof:name":"Inter Trading LLC",
    "wof:placetype":"venue"
},
  "geometry": {"coordinates":[-73.98842999999999,40.753684],"type":"Point"}
}