{
  "type": "Feature",
  "properties": {
    "iso:country":"US",
    "sg:address":"1311 Sheridan Dr",
    "sg:city":"Kenmore",
    "sg:classifiers":[
        {
            "category":"Autos & Motor Vehicles",
            "subcategory":"Fuel & Gas Station",
            "type":"Retail Goods"
        }
    ],
    "sg:phone":"+1 716 875 5508",
    "sg:postcode":"14217",
    "sg:province":"NY",
    "sg:tags":[
        "oil"
    ],
    "wof:name":"Sunoco Plus",
    "wof:placetype":"venue"
},
  "geometry": {"coordinates":[-78.87889300000001,42.980827],"type":"Point"}
}