{
  "type": "Feature",
  "properties": {
    "addr:full":"608 Jericho Tpke New Hyde Park NY 11040",
    "addr:housenumber":"608",
    "addr:postcode":"11040",
    "addr:street":"Jericho Tpke;Hyde Park",
    "iso:country":"US",
    "sg:address":"608 Jericho Tpke",
    "sg:city":"New Hyde Park",
    "sg:classifiers":[
        {
            "category":"Wholesale",
            "subcategory":"Home Furnishings",
            "type":"Manufacturing & Wholesale Goods"
        }
    ],
    "sg:phone":"+1 516 488 8705",
    "sg:postcode":"11040",
    "sg:province":"NY",
    "sg:tags":[
        "bedspread"
    ],
    "wof:name":"Satin Mill Corp",
    "wof:placetype":"venue"
},
  "geometry": {"coordinates":[-73.688761,40.73171],"type":"Point"}
}