{
  "type": "Feature",
  "properties": {
    "addr:full":"7422 Bloomer Rd Mayville NY 14757",
    "addr:housenumber":"7422",
    "addr:postcode":"14757",
    "addr:street":"Bloomer Rd",
    "iso:country":"US",
    "sg:address":"7422 Bloomer Rd",
    "sg:city":"Mayville",
    "sg:classifiers":[
        {
            "category":"Professional",
            "type":"Services"
        }
    ],
    "sg:phone":"+1   ",
    "sg:postcode":"14757",
    "sg:province":"NY",
    "wof:name":"R R Joseph Inc",
    "wof:placetype":"venue"
},
  "geometry": {"coordinates":[-79.543166,42.250533],"type":"Point"}
}