{
  "type": "Feature",
  "properties": {
    "addr:full":"1416 Ferris Pl Bronx NY 10461",
    "addr:housenumber":"1416",
    "addr:postcode":"10461",
    "addr:street":"Ferris Pl",
    "iso:country":"US",
    "sg:address":"1416 Ferris Pl",
    "sg:city":"Bronx",
    "sg:classifiers":[
        {
            "category":"Building & Trades",
            "subcategory":"Plumbing",
            "type":"Services"
        }
    ],
    "sg:phone":"+1 718 824 0503",
    "sg:postcode":"10461",
    "sg:province":"NY",
    "wof:name":"John Cuccia Plumbing Hvac",
    "wof:placetype":"venue"
},
  "geometry": {"coordinates":[-73.841266,40.839363],"type":"Point"}
}