{
  "type": "Feature",
  "properties": {
    "iso:country":"US",
    "sg:address":"11141 Ayles Rd",
    "sg:city":"Adams",
    "sg:classifiers":[
        {
            "category":"Retail",
            "subcategory":"Repair Shop",
            "type":"Services"
        },
        {
            "category":"Wholesale",
            "subcategory":"Machinery & Supplies",
            "type":"Manufacturing & Wholesale Goods"
        },
        {
            "category":"Building & Trades",
            "subcategory":"Construction",
            "type":"Services"
        },
        {
            "category":"Building & Trades",
            "subcategory":"Electrical",
            "type":"Services"
        }
    ],
    "sg:phone":"+1 315 938 5539",
    "sg:postcode":"13605",
    "sg:province":"NY",
    "sg:tags":[
        "major",
        "equipment-commercial",
        "electrician",
        "specialty",
        "industrial-servicing",
        "appliance",
        "system",
        "heating",
        "part",
        "contractor",
        "air conditioning",
        "refrigerating"
    ],
    "wof:name":"A & A Refrigeration & Electric",
    "wof:placetype":"venue"
},
  "geometry": {"coordinates":[-76.167033,43.828664],"type":"Point"}
}