{
  "type": "Feature",
  "properties": {
    "iso:country":"US",
    "sg:address":"205 E 76th St",
    "sg:city":"New York",
    "sg:classifiers":[
        {
            "category":"Health Services",
            "subcategory":"Doctor",
            "type":"Services"
        }
    ],
    "sg:phone":"+1 212 988 5990",
    "sg:postcode":"10021",
    "sg:province":"NY",
    "wof:name":"Rosensweig Norton MD",
    "wof:placetype":"venue"
},
  "geometry": {"coordinates":[-73.95826700000001,40.772207],"type":"Point"}
}