{
  "type": "Feature",
  "properties": {
    "iso:country":"US",
    "sg:address":"300 Linden Oaks",
    "sg:city":"Rochester",
    "sg:classifiers":[
        {
            "category":"Banks & Credit Unions",
            "subcategory":"Investment Brokerage",
            "type":"Services"
        }
    ],
    "sg:phone":"+1 585 385 5110",
    "sg:postcode":"14625",
    "sg:province":"NY",
    "wof:name":"George W Andrews",
    "wof:placetype":"venue"
},
  "geometry": {"coordinates":[-77.50877800000001,43.120085],"type":"Point"}
}