{
  "type": "Feature",
  "properties": {
    "addr:full":"5225 Southwestern Blvd Hamburg NY 14075",
    "addr:housenumber":"5225",
    "addr:postcode":"14075",
    "addr:street":"Southwestern Blvd",
    "iso:country":"US",
    "sg:address":"5225 Southwestern Blvd",
    "sg:city":"Hamburg",
    "sg:classifiers":[
        {
            "category":"Wholesale",
            "subcategory":"Machinery & Supplies",
            "type":"Manufacturing & Wholesale Goods"
        }
    ],
    "sg:phone":"+1 716 646 5467",
    "sg:postcode":"14075",
    "sg:province":"NY",
    "sg:tags":[
        "equipment",
        "establishment"
    ],
    "wof:name":"Wilber Services",
    "wof:placetype":"venue"
},
  "geometry": {"coordinates":[-78.863119,42.745024],"type":"Point"}
}