{
  "type": "Feature",
  "properties": {
    "iso:country":"US",
    "sg:address":"40 Wildwood Dr",
    "sg:city":"Wappingers Falls",
    "sg:classifiers":[
        {
            "category":"Professional",
            "type":"Services"
        }
    ],
    "sg:phone":"+1   ",
    "sg:postcode":"12590",
    "sg:province":"NY",
    "wof:name":"Citizens For Goldberg",
    "wof:placetype":"venue"
},
  "geometry": {"coordinates":[-73.896654,41.610462],"type":"Point"}
}