{
  "type": "Feature",
  "properties": {
    "addr:full":"1914 Kings Hwy Brooklyn NY 11229",
    "addr:housenumber":"1914",
    "addr:postcode":"11229",
    "addr:street":"Kings Hwy",
    "iso:country":"US",
    "sg:address":"1914 Kings Hwy",
    "sg:city":"Brooklyn",
    "sg:classifiers":[
        {
            "category":"Food & Beverages",
            "subcategory":"Meat & Fish",
            "type":"Retail Goods"
        }
    ],
    "sg:phone":"+1 718 336 8100",
    "sg:postcode":"11229",
    "sg:province":"NY",
    "sg:tags":[
        "shop"
    ],
    "wof:name":"Kings Food Market",
    "wof:placetype":"venue"
},
  "geometry": {"coordinates":[-73.954464,40.610196],"type":"Point"}
}