{
  "type": "Feature",
  "properties": {
    "iso:country":"US",
    "sg:address":"7744 Debusse Rd",
    "sg:city":"Lyons",
    "sg:classifiers":[
        {
            "category":"Building & Trades",
            "subcategory":"Landscaping Services",
            "type":"Services"
        }
    ],
    "sg:phone":"+1 315 946 4606",
    "sg:postcode":"14489",
    "sg:province":"NY",
    "sg:tags":[
        "landscape"
    ],
    "wof:name":"C McIntyre Landscaping",
    "wof:placetype":"venue"
},
  "geometry": {"coordinates":[-77.013651,43.093226],"type":"Point"}
}