{
  "type": "Feature",
  "properties": {
    "iso:country":"US",
    "sg:address":"1641 Deer Park Ave",
    "sg:city":"Deer Park",
    "sg:classifiers":[
        {
            "category":"Professional",
            "subcategory":"Lawyer & Legal Services",
            "type":"Services"
        }
    ],
    "sg:phone":"+1 631 667 7100",
    "sg:postcode":"11729",
    "sg:province":"NY",
    "sg:tags":[
        "attorney"
    ],
    "wof:name":"Powers & Caramagno",
    "wof:placetype":"venue"
},
  "geometry": {"coordinates":[-73.32534200000001,40.751541],"type":"Point"}
}