{
  "type": "Feature",
  "properties": {
    "iso:country":"US",
    "sg:address":"102 Marle Pl",
    "sg:city":"Bellmore",
    "sg:classifiers":[
        {
            "category":"Building & Trades",
            "subcategory":"Landscaping Services",
            "type":"Services"
        }
    ],
    "sg:phone":"+1 516 489 6181",
    "sg:postcode":"11710",
    "sg:province":"NY",
    "sg:tags":[
        "landscape"
    ],
    "wof:name":"Peter De Santis Landscaping",
    "wof:placetype":"venue"
},
  "geometry": {"coordinates":[-73.525375,40.666679],"type":"Point"}
}