{
  "type": "Feature",
  "properties": {
    "addr:full":"811 Trinity Ave Bronx NY 10456",
    "addr:housenumber":"811",
    "addr:postcode":"10456",
    "addr:street":"Trinity Ave",
    "iso:country":"US",
    "sg:address":"811 Trinity Ave",
    "sg:city":"Bronx",
    "sg:classifiers":[
        {
            "category":"Home & Garden",
            "subcategory":"Building Materials",
            "type":"Retail Goods"
        }
    ],
    "sg:phone":"+1 718 402 8674",
    "sg:postcode":"10456",
    "sg:province":"NY",
    "sg:tags":[
        "plate",
        "glass-auto",
        "window",
        "glass"
    ],
    "wof:name":"Ricks Store Front & Glass Work",
    "wof:placetype":"venue"
},
  "geometry": {"coordinates":[-73.90710199999999,40.820243],"type":"Point"}
}