{
  "type": "Feature",
  "properties": {
    "iso:country":"US",
    "sg:address":"1156 County Route 7",
    "sg:city":"Hannibal",
    "sg:classifiers":[
        {
            "category":"Professional",
            "subcategory":"Management & Consulting",
            "type":"Services"
        },
        {
            "category":"Professional",
            "subcategory":"Business Services",
            "type":"Services"
        }
    ],
    "sg:phone":"+1 315 564 8054",
    "sg:postcode":"13074",
    "sg:province":"NY",
    "sg:tags":[
        "consultant",
        "coach",
        "agricultural"
    ],
    "sg:website":"http://www.NorthernForestryProducts.com",
    "wof:name":"Northern Forestry Products Inc",
    "wof:placetype":"venue"
},
  "geometry": {"coordinates":[-76.53932399999999,43.337931],"type":"Point"}
}