{
  "type": "Feature",
  "properties": {
    "iso:country":"US",
    "sg:address":"51 Wellsboro Rd",
    "sg:city":"Valley Stream",
    "sg:classifiers":[
        {
            "category":"Shopping",
            "subcategory":"Stationery & Office Supplies",
            "type":"Retail Goods"
        }
    ],
    "sg:phone":"+1 516 256 3238",
    "sg:postcode":"11580",
    "sg:province":"NY",
    "sg:tags":[
        "equipment"
    ],
    "wof:name":"RK Office And Computer Supls",
    "wof:placetype":"venue"
},
  "geometry": {"coordinates":[-73.707339,40.680032],"type":"Point"}
}