{
  "type": "Feature",
  "properties": {
    "iso:country":"US",
    "sg:address":"170 Garden St",
    "sg:city":"Garden City",
    "sg:classifiers":[
        {
            "category":"Professional",
            "type":"Services"
        }
    ],
    "sg:phone":"+1   ",
    "sg:postcode":"11530",
    "sg:province":"NY",
    "wof:name":"Eurpartner Inc",
    "wof:placetype":"venue"
},
  "geometry": {"coordinates":[-73.612307,40.724065],"type":"Point"}
}