{
  "type": "Feature",
  "properties": {
    "addr:full":"1167 Castle Hill Ave Bronx NY 10462",
    "addr:housenumber":"1167",
    "addr:postcode":"10462",
    "addr:street":"Castle Hill Ave",
    "iso:country":"US",
    "sg:address":"1167 Castle Hill Ave",
    "sg:city":"Bronx",
    "sg:classifiers":[
        {
            "category":"Retail",
            "subcategory":"Repair Shop",
            "type":"Services"
        }
    ],
    "sg:phone":"+1 718 535 9267",
    "sg:postcode":"10462",
    "sg:province":"NY",
    "sg:tags":[
        "lock",
        "locksmith"
    ],
    "wof:name":"24 Hour 7 Day Emerg Locksmith",
    "wof:placetype":"venue"
},
  "geometry": {"coordinates":[-73.851094,40.831801],"type":"Point"}
}