{
  "type": "Feature",
  "properties": {
    "iso:country":"US",
    "sg:address":"1043 McDonald Ave",
    "sg:city":"Brooklyn",
    "sg:classifiers":[
        {
            "category":"Manufacturing",
            "subcategory":"Metals",
            "type":"Manufacturing & Wholesale Goods"
        }
    ],
    "sg:phone":"+1   ",
    "sg:postcode":"11230",
    "sg:province":"NY",
    "sg:tags":[
        "sheet",
        "mfg"
    ],
    "wof:name":"M & R Skylight Inc",
    "wof:placetype":"venue"
},
  "geometry": {"coordinates":[-73.976533,40.627842],"type":"Point"}
}