{
  "type": "Feature",
  "properties": {
    "iso:country":"US",
    "sg:address":"112 Chauncey Ave",
    "sg:city":"New Rochelle",
    "sg:classifiers":[
        {
            "category":"Education",
            "subcategory":"Special Training",
            "type":"Public Place"
        }
    ],
    "sg:phone":"+1 914 576 5666",
    "sg:postcode":"10801",
    "sg:province":"NY",
    "sg:tags":[
        "self",
        "motivational",
        "improvement"
    ],
    "wof:name":"Self Help Foundation Inc",
    "wof:placetype":"venue"
},
  "geometry": {"coordinates":[-73.794082,40.922088],"type":"Point"}
}