{
  "type": "Feature",
  "properties": {
    "addr:full":"11 Birch Hill Rd Locust Valley NY 11560",
    "addr:housenumber":"11",
    "addr:postcode":"11560",
    "addr:street":"Birch Hill Rd",
    "iso:country":"US",
    "sg:address":"11 Birch Hill Rd",
    "sg:city":"Locust Valley",
    "sg:classifiers":[
        {
            "category":"Sports & Exercise",
            "subcategory":"Gym",
            "type":"Entertainment"
        }
    ],
    "sg:phone":"+1   ",
    "sg:postcode":"11560",
    "sg:province":"NY",
    "sg:tags":[
        "fitness",
        "physical",
        "facility"
    ],
    "wof:name":"Fitness Studio At Marathon",
    "wof:placetype":"venue"
},
  "geometry": {"coordinates":[-73.597138,40.875513],"type":"Point"}
}