{
  "type": "Feature",
  "properties": {
    "iso:country":"US",
    "sg:address":"100 Holiday Drive",
    "sg:city":"Staten Island",
    "sg:classifiers":[
        {
            "category":"Sports & Exercise",
            "subcategory":"Sports Center",
            "type":"Entertainment"
        }
    ],
    "sg:phone":"+1 718 982 7925",
    "sg:postcode":"10314",
    "sg:province":"NY",
    "sg:tags":[
        "amateur",
        "team"
    ],
    "wof:name":"Holiday Villas Home Owners Assoc",
    "wof:placetype":"venue"
},
  "geometry": {"coordinates":[-74.147436,40.607001],"type":"Point"}
}