{
  "type": "Feature",
  "properties": {
    "addr:full":"49 Rte 25A Mt Sinai NY 11766",
    "addr:housenumber":"49",
    "addr:postcode":"11766",
    "addr:street":"Rte 25A",
    "iso:country":"US",
    "sg:address":"49 Rte 25A",
    "sg:city":"Mt Sinai",
    "sg:classifiers":[
        {
            "category":"Banks & Credit Unions",
            "subcategory":"Bank",
            "type":"Services"
        }
    ],
    "sg:phone":"+1 631 474 5970",
    "sg:postcode":"11766",
    "sg:province":"NY",
    "sg:tags":[
        "loan",
        "real estate"
    ],
    "wof:name":"Jericho Mortgage 2",
    "wof:placetype":"venue"
},
  "geometry": {"coordinates":[-73.031161,40.932778],"type":"Point"}
}