{
  "type": "Feature",
  "properties": {
    "iso:country":"US",
    "sg:address":"165 E Union St",
    "sg:city":"Newark",
    "sg:classifiers":[
        {
            "category":"Travel",
            "subcategory":"Hotels & Motels",
            "type":"Entertainment"
        }
    ],
    "sg:phone":"+1 315 331 5680",
    "sg:postcode":"14513",
    "sg:province":"NY",
    "wof:name":"Marriott Don",
    "wof:placetype":"venue"
},
  "geometry": {"coordinates":[-77.09399500000001,43.046598],"type":"Point"}
}