{
  "type": "Feature",
  "properties": {
    "addr:full":"297 Livingston St Brooklyn NY 11217",
    "addr:housenumber":"297",
    "addr:postcode":"11217",
    "addr:street":"Livingston St",
    "iso:country":"US",
    "sg:address":"297 Livingston St",
    "sg:city":"Brooklyn",
    "sg:classifiers":[
        {
            "category":"Food & Beverages",
            "subcategory":"Meat & Fish",
            "type":"Retail Goods"
        }
    ],
    "sg:phone":"+1 718 596 3578",
    "sg:postcode":"11217",
    "sg:province":"NY",
    "sg:tags":[
        "seafood",
        "market"
    ],
    "wof:name":"Jung's Fish Mkt",
    "wof:placetype":"venue"
},
  "geometry": {"coordinates":[-73.9813,40.681499],"type":"Point"}
}