{
  "type": "Feature",
  "properties": {
    "iso:country":"US",
    "sg:address":"7413 State St Rd",
    "sg:city":"Auburn",
    "sg:classifiers":[
        {
            "category":"Retail",
            "subcategory":"Laundry & Dry Cleaning",
            "type":"Services"
        }
    ],
    "sg:phone":"+1   ",
    "sg:postcode":"13021",
    "sg:province":"NY",
    "sg:tags":[
        "dyeing",
        "upholstery",
        "carpet"
    ],
    "wof:name":"Rainbow International",
    "wof:placetype":"venue"
},
  "geometry": {"coordinates":[-76.588663,42.973613],"type":"Point"}
}