{
  "type": "Feature",
  "properties": {
    "iso:country":"US",
    "sg:address":"308 W 39 St",
    "sg:city":"New York",
    "sg:classifiers":[
        {
            "category":"Shopping",
            "subcategory":"Crafts & Fabrics",
            "type":"Retail Goods"
        }
    ],
    "sg:phone":"+1 212 244 4777",
    "sg:postcode":"10018",
    "sg:province":"NY",
    "sg:tags":[
        "shop"
    ],
    "wof:name":"Millennium Fabric Of Ny",
    "wof:placetype":"venue"
},
  "geometry": {"coordinates":[-73.99388,40.756364],"type":"Point"}
}