{
  "type": "Feature",
  "properties": {
    "iso:country":"US",
    "sg:address":"168 W Boston Post Rd",
    "sg:city":"Mamaroneck",
    "sg:classifiers":[
        {
            "category":"Social Services",
            "subcategory":"Child Care",
            "type":"Services"
        }
    ],
    "sg:phone":"+1 914 777 1860",
    "sg:postcode":"10543",
    "sg:province":"NY",
    "sg:tags":[
        "kindergarten",
        "academic",
        "school",
        "day"
    ],
    "wof:name":"Mamaroneck Community Nursery",
    "wof:placetype":"venue"
},
  "geometry": {"coordinates":[-73.733823,40.948003],"type":"Point"}
}