{
  "type": "Feature",
  "properties": {
    "addr:full":"46 W Fairmount Ave Lakewood NY 14750",
    "addr:housenumber":"46",
    "addr:postcode":"14750",
    "addr:street":"W Fairmount Ave",
    "iso:country":"US",
    "sg:address":"46 W Fairmount Ave",
    "sg:city":"Lakewood",
    "sg:classifiers":[
        {
            "category":"Personal",
            "type":"Services"
        }
    ],
    "sg:phone":"+1 716 763 0403",
    "sg:postcode":"14750",
    "sg:province":"NY",
    "sg:tags":[
        "therapist",
        "massage"
    ],
    "wof:name":"Professional Massage Therapy",
    "wof:placetype":"venue"
},
  "geometry": {"coordinates":[-79.330027,42.09785],"type":"Point"}
}