{
  "type": "Feature",
  "properties": {
    "addr:full":"1000 Coney Island Ave Brooklyn NY 11230",
    "addr:housenumber":"1000",
    "addr:postcode":"11230",
    "addr:street":"Coney Island Ave",
    "iso:country":"US",
    "sg:address":"1000 Coney Island Ave",
    "sg:city":"Brooklyn",
    "sg:classifiers":[
        {
            "category":"Home & Garden",
            "subcategory":"Hardware",
            "type":"Retail Goods"
        }
    ],
    "sg:phone":"+1 718 434 8000",
    "sg:postcode":"11230",
    "sg:province":"NY",
    "sg:tags":[
        "store"
    ],
    "sg:website":"www.benjaminmoore.com",
    "wof:name":"Brooklyn Paint & Home Center",
    "wof:placetype":"venue"
},
  "geometry": {"coordinates":[-73.967361,40.63312],"type":"Point"}
}