{
  "type": "Feature",
  "properties": {
    "addr:full":"4020 10 Ave New York NY 10034",
    "addr:housenumber":"4020",
    "addr:postcode":"10034",
    "addr:street":"10 Ave",
    "iso:country":"US",
    "sg:address":"4020 10 Ave",
    "sg:city":"New York",
    "sg:classifiers":[
        {
            "category":"Building & Trades",
            "subcategory":"Plumbing",
            "type":"Services"
        }
    ],
    "sg:phone":"+1 212 567 3300",
    "sg:postcode":"10034",
    "sg:province":"NY",
    "sg:tags":[
        "plumbing",
        "contractor"
    ],
    "wof:name":"P J Foley",
    "wof:placetype":"venue"
},
  "geometry": {"coordinates":[-73.922369,40.859723],"type":"Point"}
}