{
  "type": "Feature",
  "properties": {
    "addr:full":"2 E 37th St New York NY 10016",
    "addr:housenumber":"2",
    "addr:postcode":"10016",
    "addr:street":"E 37Th St",
    "iso:country":"US",
    "sg:address":"2 E 37th St",
    "sg:city":"New York",
    "sg:classifiers":[
        {
            "category":"Personal",
            "type":"Services"
        }
    ],
    "sg:phone":"+1 212 547 6455",
    "sg:postcode":"10016",
    "sg:province":"NY",
    "sg:tags":[
        "towing"
    ],
    "wof:name":"Tow Truck Co",
    "wof:placetype":"venue"
},
  "geometry": {"coordinates":[-73.9832,40.750301],"type":"Point"}
}