{
  "type": "Feature",
  "properties": {
    "iso:country":"US",
    "sg:address":"1817 South Rd",
    "sg:city":"Wappingers Falls",
    "sg:classifiers":[
        {
            "category":"Restaurant",
            "type":"Food & Drink"
        }
    ],
    "sg:menulink":"http://www.allmenus.com/ny/wappinger/32280-neko-sushi--hibachi/menu/",
    "sg:phone":"+1 845 298 9869",
    "sg:postcode":"12590",
    "sg:province":"NY",
    "sg:tags":[
        "japanese",
        "asian"
    ],
    "wof:name":"Neko Sushi & Hibachi",
    "wof:placetype":"venue"
},
  "geometry": {"coordinates":[-73.92035799999999,41.591054],"type":"Point"}
}