{
  "type": "Feature",
  "properties": {
    "iso:country":"US",
    "sg:address":"100 Perinton Pkwy",
    "sg:city":"Fairport",
    "sg:classifiers":[
        {
            "category":"Shopping",
            "subcategory":"Computers & Home Electronics",
            "type":"Retail Goods"
        }
    ],
    "sg:phone":"+1 585 223 4330",
    "sg:postcode":"14450",
    "sg:province":"NY",
    "sg:tags":[
        "software"
    ],
    "wof:name":"Axis Technologies Inc",
    "wof:placetype":"venue"
},
  "geometry": {"coordinates":[-77.39241699999999,43.090039],"type":"Point"}
}