{
  "type": "Feature",
  "properties": {
    "addr:full":"15 Beach 105th St Far Rockaway NY 11694",
    "addr:housenumber":"15",
    "addr:postcode":"11694",
    "addr:street":"Beach 105Th St",
    "iso:country":"US",
    "sg:address":"15 Beach 105th St",
    "sg:city":"Far Rockaway",
    "sg:classifiers":[
        {
            "category":"Health Services",
            "subcategory":"Doctor",
            "type":"Services"
        }
    ],
    "sg:phone":"+1 718 474 0023",
    "sg:postcode":"11694",
    "sg:province":"NY",
    "wof:name":"Yakutilov Rafael",
    "wof:placetype":"venue"
},
  "geometry": {"coordinates":[-73.825385,40.581385],"type":"Point"}
}