{
  "type": "Feature",
  "properties": {
    "iso:country":"US",
    "sg:address":"100 Arden St",
    "sg:city":"New York",
    "sg:classifiers":[
        {
            "category":"Professional",
            "subcategory":"Advertising",
            "type":"Services"
        }
    ],
    "sg:phone":"+1 212 942 0596",
    "sg:postcode":"10040",
    "sg:province":"NY",
    "sg:tags":[
        "agency"
    ],
    "wof:name":"U S One Advertisement Inc",
    "wof:placetype":"venue"
},
  "geometry": {"coordinates":[-73.9285,40.863694],"type":"Point"}
}