{
  "type": "Feature",
  "properties": {
    "iso:country":"US",
    "sg:address":"1522 Northern Blvd",
    "sg:city":"Manhasset",
    "sg:classifiers":[
        {
            "category":"Travel",
            "subcategory":"Travel Agent",
            "type":"Entertainment"
        }
    ],
    "sg:phone":"+1 718 358 7900",
    "sg:postcode":"11030",
    "sg:province":"NY",
    "sg:tags":[
        "agency",
        "bureau"
    ],
    "wof:name":"Coronado Travel",
    "wof:placetype":"venue"
},
  "geometry": {"coordinates":[-73.68998499999999,40.79374],"type":"Point"}
}