{
  "type": "Feature",
  "properties": {
    "addr:full":"153 New Dorp Ln Staten Island NY 10306",
    "addr:housenumber":"153",
    "addr:postcode":"10306",
    "addr:street":"New Dorp Ln",
    "iso:country":"US",
    "sg:address":"153 New Dorp Ln",
    "sg:city":"Staten Island",
    "sg:classifiers":[
        {
            "category":"Communications",
            "subcategory":"Film & Video Production",
            "type":"Services"
        }
    ],
    "sg:phone":"+1 718 351 2400",
    "sg:postcode":"10306",
    "sg:province":"NY",
    "sg:tags":[
        "editing",
        "tape"
    ],
    "sg:website":"www.foxvideoinc.com",
    "wof:name":"Fox Video Productions Inc",
    "wof:placetype":"venue"
},
  "geometry": {"coordinates":[-74.115635,40.573709],"type":"Point"}
}