{
  "type": "Feature",
  "properties": {
    "iso:country":"US",
    "sg:address":"2426 Ocean Pkwy",
    "sg:city":"Brooklyn",
    "sg:classifiers":[
        {
            "category":"Health Services",
            "subcategory":"Doctor",
            "type":"Services"
        }
    ],
    "sg:phone":"+1 718 645 8300",
    "sg:postcode":"11235",
    "sg:province":"NY",
    "sg:tags":[
        "surgeon",
        "oral"
    ],
    "wof:name":"Mosery Rafael DDS",
    "wof:placetype":"venue"
},
  "geometry": {"coordinates":[-73.965698,40.590401],"type":"Point"}
}