{
  "type": "Feature",
  "properties": {
    "addr:full":"1050 State Route 36 Hornell NY 14843",
    "addr:housenumber":"1050",
    "addr:postcode":"14843",
    "addr:street":"State Route 36",
    "iso:country":"US",
    "sg:address":"1050 State Route 36",
    "sg:city":"Hornell",
    "sg:classifiers":[
        {
            "category":"Bakery",
            "type":"Food & Drink"
        },
        {
            "category":"Coffee & Tea",
            "type":"Food & Drink"
        },
        {
            "category":"Bagels",
            "type":"Food & Drink"
        },
        {
            "category":"Donuts",
            "type":"Food & Drink"
        }
    ],
    "sg:menulink":"http://www.allmenus.com/ny/hornellsville/138428-dunkin-donuts/menu/",
    "sg:phone":"+1 631 544 0031",
    "sg:postcode":"14843",
    "sg:province":"NY",
    "sg:tags":[
        "american",
        "pastry"
    ],
    "wof:name":"Dunkin' Donuts",
    "wof:placetype":"venue"
},
  "geometry": {"coordinates":[-77.69012600000001,42.379576],"type":"Point"}
}