{
  "type": "Feature",
  "properties": {
    "iso:country":"US",
    "sg:address":"41 Elizabeth Street",
    "sg:city":"New York",
    "sg:classifiers":[
        {
            "category":"Health Services",
            "subcategory":"Doctor",
            "type":"Services"
        }
    ],
    "sg:phone":"+1 212 334 3507",
    "sg:postcode":"10013",
    "sg:province":"NY",
    "sg:tags":[
        "cardiologist"
    ],
    "wof:name":"Dr. Michael Liou, MD",
    "wof:placetype":"venue"
},
  "geometry": {"coordinates":[-73.996948,40.717037],"type":"Point"}
}