{
  "type": "Feature",
  "properties": {
    "iso:country":"US",
    "sg:address":"23 E 3rd St",
    "sg:city":"Mount Vernon",
    "sg:classifiers":[
        {
            "category":"Restaurant",
            "type":"Food & Drink"
        }
    ],
    "sg:phone":"+1 914 665 5607",
    "sg:postcode":"10550",
    "sg:province":"NY",
    "sg:tags":[
        "eating"
    ],
    "wof:name":"Crown Fried Chicken",
    "wof:placetype":"venue"
},
  "geometry": {"coordinates":[-73.83355299999999,40.907262],"type":"Point"}
}