{
  "type": "Feature",
  "properties": {
    "addr:full":"4111 Broadway New York NY 10033",
    "addr:housenumber":"4111",
    "addr:postcode":"10033",
    "addr:street":"Broadway",
    "iso:country":"US",
    "sg:address":"4111 Broadway",
    "sg:city":"New York",
    "sg:classifiers":[
        {
            "category":"Social Services",
            "subcategory":"Child Care",
            "type":"Services"
        },
        {
            "category":"Education",
            "subcategory":"Preschool",
            "type":"Public Place"
        },
        {
            "category":"Education",
            "subcategory":"School",
            "type":"Public Place"
        }
    ],
    "sg:phone":"+1 212 568 6554",
    "sg:postcode":"10033",
    "sg:province":"NY",
    "sg:tags":[
        "elementary",
        "day"
    ],
    "wof:name":"Quo Jadis Montessori Day Care Center",
    "wof:placetype":"venue"
},
  "geometry": {"coordinates":[-73.938838,40.845247],"type":"Point"}
}