{
  "type": "Feature",
  "properties": {
    "addr:full":"158 State Hwy 96 Owego NY 13827",
    "addr:housenumber":"158",
    "addr:postcode":"13827",
    "addr:street":"State Hwy 96",
    "iso:country":"US",
    "sg:address":"158 State Hwy 96",
    "sg:city":"Owego",
    "sg:classifiers":[
        {
            "category":"Farming",
            "subcategory":"Livestock Farm",
            "type":"Manufacturing & Wholesale Goods"
        }
    ],
    "sg:phone":"+1 607 687 3028",
    "sg:postcode":"13827",
    "sg:province":"NY",
    "sg:tags":[
        "hog",
        "beef",
        "field",
        "cattle",
        "cr",
        "or",
        "feedlot"
    ],
    "wof:name":"William Eichhorn",
    "wof:placetype":"venue"
},
  "geometry": {"coordinates":[-76.276707,42.130524],"type":"Point"}
}