{
  "type": "Feature",
  "properties": {
    "iso:country":"US",
    "sg:address":"445 S Mountain Rd",
    "sg:city":"New City",
    "sg:classifiers":[
        {
            "category":"Organizations",
            "subcategory":"Membership Organization",
            "type":"Services"
        }
    ],
    "sg:phone":"+1   ",
    "sg:postcode":"10956",
    "sg:province":"NY",
    "wof:name":"Wenig  Arthur & Hilda Charitab",
    "wof:placetype":"venue"
},
  "geometry": {"coordinates":[-73.98991700000001,41.187141],"type":"Point"}
}