{
  "type": "Feature",
  "properties": {
    "addr:full":"708 Bloomingburg Rd Bloomingburg NY 12721",
    "addr:housenumber":"708",
    "addr:postcode":"12721",
    "addr:street":"Bloomingburg Rd",
    "iso:country":"US",
    "sg:address":"708 Bloomingburg Rd",
    "sg:city":"Bloomingburg",
    "sg:classifiers":[
        {
            "category":"Building & Trades",
            "subcategory":"Construction",
            "type":"Services"
        }
    ],
    "sg:phone":"+1 845 733 1754",
    "sg:postcode":"12721",
    "sg:province":"NY",
    "sg:tags":[
        "specializing",
        "remodeling",
        "general",
        "painting",
        "contractor"
    ],
    "wof:name":"Cornerstone Construction",
    "wof:placetype":"venue"
},
  "geometry": {"coordinates":[-74.425618,41.536502],"type":"Point"}
}