{
  "type": "Feature",
  "properties": {
    "iso:country":"US",
    "sg:address":"5013 13th Ave",
    "sg:city":"Brooklyn",
    "sg:classifiers":[
        {
            "category":"Food & Beverages",
            "subcategory":"Groceries & Convenience Stores",
            "type":"Retail Goods"
        }
    ],
    "sg:phone":"+1 718 438 9038",
    "sg:postcode":"11219",
    "sg:province":"NY",
    "sg:tags":[
        "grocer"
    ],
    "wof:name":"Semel's Food Inc",
    "wof:placetype":"venue"
},
  "geometry": {"coordinates":[-73.993171,40.633927],"type":"Point"}
}