{
  "type": "Feature",
  "properties": {
    "iso:country":"US",
    "sg:address":"1001 Sheridan Ave",
    "sg:city":"Bronx",
    "sg:classifiers":[
        {
            "category":"Food & Beverages",
            "subcategory":"Groceries & Convenience Stores",
            "type":"Retail Goods"
        }
    ],
    "sg:phone":"+1   ",
    "sg:postcode":"10456",
    "sg:province":"NY",
    "wof:name":"J & A Grocery Store",
    "wof:placetype":"venue"
},
  "geometry": {"coordinates":[-73.92019999999999,40.8281],"type":"Point"}
}