{
  "type": "Feature",
  "properties": {
    "addr:full":"874 Pacific St Brooklyn NY 11238",
    "addr:housenumber":"874",
    "addr:postcode":"11238",
    "addr:street":"Pacific St",
    "iso:country":"US",
    "sg:address":"874 Pacific St",
    "sg:city":"Brooklyn",
    "sg:classifiers":[
        {
            "category":"Professional",
            "type":"Services"
        }
    ],
    "sg:phone":"+1 718 857 2202",
    "sg:postcode":"11238",
    "sg:province":"NY",
    "sg:tags":[
        "sculptor"
    ],
    "wof:name":"Cadet Branly",
    "wof:placetype":"venue"
},
  "geometry": {"coordinates":[-73.966717,40.680805],"type":"Point"}
}