{
  "type": "Feature",
  "properties": {
    "addr:full":"14 Borrell Ct Saint James NY 11780",
    "addr:housenumber":"14",
    "addr:postcode":"11780",
    "addr:street":"Borrell Ct",
    "iso:country":"US",
    "sg:address":"14 Borrell Ct",
    "sg:city":"Saint James",
    "sg:classifiers":[
        {
            "category":"Autos & Motor Vehicles",
            "subcategory":"Automobile Sales",
            "type":"Retail Goods"
        }
    ],
    "sg:phone":"+1   ",
    "sg:postcode":"11780",
    "sg:province":"NY",
    "sg:tags":[
        "new",
        "used",
        "leasing",
        "sales"
    ],
    "wof:name":"Lane Leasing Ltd",
    "wof:placetype":"venue"
},
  "geometry": {"coordinates":[-73.18222900000001,40.867674],"type":"Point"}
}