{
  "type": "Feature",
  "properties": {
    "addr:full":"315 Sheridan Ave Albany NY 12206",
    "addr:housenumber":"315",
    "addr:postcode":"12206",
    "addr:street":"Sheridan Ave",
    "iso:country":"US",
    "sg:address":"315 Sheridan Ave",
    "sg:city":"Albany",
    "sg:classifiers":[
        {
            "category":"Organizations",
            "subcategory":"Membership Organization",
            "type":"Services"
        }
    ],
    "sg:phone":"+1   ",
    "sg:postcode":"12206",
    "sg:province":"NY",
    "wof:name":"Center City PSM",
    "wof:placetype":"venue"
},
  "geometry": {"coordinates":[-73.76461399999999,42.660844],"type":"Point"}
}