{
  "type": "Feature",
  "properties": {
    "iso:country":"US",
    "sg:address":"194 Jericho Tpke Unit A",
    "sg:city":"Mineola",
    "sg:phone":"+1 516 746 8567",
    "sg:postcode":"11501",
    "sg:province":"NY",
    "wof:name":"Tres Belle Stylist Corp",
    "wof:placetype":"venue"
},
  "geometry": {"coordinates":[-73.64364399999999,40.748317],"type":"Point"}
}