{
  "type": "Feature",
  "properties": {
    "iso:country":"US",
    "sg:address":"777 McLean Ave",
    "sg:city":"Yonkers",
    "sg:classifiers":[
        {
            "category":"Recreation",
            "type":"Entertainment"
        }
    ],
    "sg:phone":"+1 914 377 6472",
    "sg:postcode":"10704",
    "sg:province":"NY",
    "sg:tags":[
        "hall",
        "auditorium"
    ],
    "wof:name":"Coyne Park Community Ctr",
    "wof:placetype":"venue"
},
  "geometry": {"coordinates":[-73.871579,40.906706],"type":"Point"}
}