{
  "type": "Feature",
  "properties": {
    "addr:full":"551 Grand St New York NY 10002",
    "addr:housenumber":"551",
    "addr:postcode":"10002",
    "addr:street":"Grand St",
    "iso:country":"US",
    "sg:address":"551 Grand St",
    "sg:city":"New York",
    "sg:classifiers":[
        {
            "category":"Shopping",
            "subcategory":"Jewelry",
            "type":"Retail Goods"
        }
    ],
    "sg:phone":"+1 212 696 1902",
    "sg:postcode":"10002",
    "sg:province":"NY",
    "wof:name":"Friends of Silver",
    "wof:placetype":"venue"
},
  "geometry": {"coordinates":[-73.980161,40.713929],"type":"Point"}
}