{
  "type": "Feature",
  "properties": {
    "addr:full":"6025 State Hwy 5 Palatine Bridge NY 13428",
    "addr:housenumber":"6025",
    "addr:postcode":"13428",
    "addr:street":"State Hwy 5 Palatine Bridge",
    "iso:country":"US",
    "sg:address":"6025 State Hwy 5",
    "sg:city":"Palatine Bridge",
    "sg:classifiers":[
        {
            "category":"Food & Beverages",
            "subcategory":"Groceries & Convenience Stores",
            "type":"Retail Goods"
        }
    ],
    "sg:phone":"+1 518 673 2333",
    "sg:postcode":"13428",
    "sg:province":"NY",
    "sg:tags":[
        "grocer"
    ],
    "sg:website":"www.pricechopper.com",
    "wof:name":"Price Chopper-Palantine",
    "wof:placetype":"venue"
},
  "geometry": {"coordinates":[-74.589789,42.915594],"type":"Point"}
}