{
  "type": "Feature",
  "properties": {
    "iso:country":"US",
    "sg:address":"134 North Ave",
    "sg:city":"New Rochelle",
    "sg:classifiers":[
        {
            "category":"Building & Trades",
            "subcategory":"Cleaning & Sanitation",
            "type":"Services"
        }
    ],
    "sg:phone":"+1 914 632 0766",
    "sg:postcode":"10801",
    "sg:province":"NY",
    "sg:tags":[
        "maintenance"
    ],
    "wof:name":"Express Chimney Svc",
    "wof:placetype":"venue"
},
  "geometry": {"coordinates":[-73.778632,40.906886],"type":"Point"}
}