{
  "type": "Feature",
  "properties": {
    "iso:country":"US",
    "sg:address":"6 Rinne Rd",
    "sg:city":"Wallkill",
    "sg:classifiers":[
        {
            "category":"Professional",
            "subcategory":"Management & Consulting",
            "type":"Services"
        }
    ],
    "sg:phone":"+1   ",
    "sg:postcode":"12589",
    "sg:province":"NY",
    "sg:tags":[
        "business"
    ],
    "wof:name":"Warren Masiero Inc",
    "wof:placetype":"venue"
},
  "geometry": {"coordinates":[-74.11512399999999,41.589787],"type":"Point"}
}