{
  "type": "Feature",
  "properties": {
    "iso:country":"US",
    "sg:address":"1207 Almond St",
    "sg:city":"Syracuse",
    "sg:classifiers":[
        {
            "category":"Professional",
            "type":"Services"
        }
    ],
    "sg:phone":"+1 315 424 0057",
    "sg:postcode":"13210",
    "sg:province":"NY",
    "sg:tags":[
        "establishment"
    ],
    "wof:name":"Win",
    "wof:placetype":"venue"
},
  "geometry": {"coordinates":[-76.14205200000001,43.039],"type":"Point"}
}