{
  "type": "Feature",
  "properties": {
    "addr:full":"366 E 94th St Brooklyn NY 11212",
    "addr:housenumber":"366",
    "addr:postcode":"11212",
    "addr:street":"E 94Th St",
    "iso:country":"US",
    "sg:address":"366 E 94th St",
    "sg:city":"Brooklyn",
    "sg:classifiers":[
        {
            "category":"Retail",
            "subcategory":"Repair Shop",
            "type":"Services"
        }
    ],
    "sg:phone":"+1 718 257 4897",
    "sg:postcode":"11212",
    "sg:province":"NY",
    "sg:tags":[
        "upholsterer"
    ],
    "wof:name":"Super Steve Upholstery",
    "wof:placetype":"venue"
},
  "geometry": {"coordinates":[-73.919234,40.656626],"type":"Point"}
}