{
  "type": "Feature",
  "properties": {
    "addr:full":"24 E 33rd St New York NY 10016",
    "addr:housenumber":"24",
    "addr:postcode":"10016",
    "addr:street":"E 33Rd St",
    "iso:country":"US",
    "sg:address":"24 E 33rd St",
    "sg:city":"New York",
    "sg:classifiers":[
        {
            "category":"Building & Trades",
            "subcategory":"Locksmith",
            "type":"Services"
        }
    ],
    "sg:phone":"+1 646 758 7036",
    "sg:postcode":"10016",
    "sg:province":"NY",
    "sg:tags":[
        "key"
    ],
    "wof:name":"0 007 Lockl Service",
    "wof:placetype":"venue"
},
  "geometry": {"coordinates":[-73.983737,40.747081],"type":"Point"}
}