{
  "type": "Feature",
  "properties": {
    "addr:full":"10 Aerial Way Syosset NY 11791",
    "addr:housenumber":"10",
    "addr:postcode":"11791",
    "addr:street":"Aerial Way",
    "iso:country":"US",
    "sg:address":"10 Aerial Way",
    "sg:city":"Syosset",
    "sg:classifiers":[
        {
            "category":"Wholesale",
            "subcategory":"Metals & Minerals",
            "type":"Manufacturing & Wholesale Goods"
        }
    ],
    "sg:phone":"+1 516 681 2400",
    "sg:postcode":"11791",
    "sg:province":"NY",
    "sg:tags":[
        "steel",
        "distributor",
        "aircraft",
        "parts"
    ],
    "sg:website":"www.bsaa.com",
    "wof:name":"B & S Aircraft Alloys Inc",
    "wof:placetype":"venue"
},
  "geometry": {"coordinates":[-73.51582500000001,40.798192],"type":"Point"}
}