{
  "type": "Feature",
  "properties": {
    "iso:country":"US",
    "sg:address":"18 Beverly Dr",
    "sg:city":"Warwick",
    "sg:classifiers":[
        {
            "category":"Shopping",
            "subcategory":"Used Merchandise",
            "type":"Retail Goods"
        }
    ],
    "sg:phone":"+1 845 986 1996",
    "sg:postcode":"10990",
    "sg:province":"NY",
    "sg:tags":[
        "antique"
    ],
    "wof:name":"Bearly Antiques",
    "wof:placetype":"venue"
},
  "geometry": {"coordinates":[-74.369163,41.28385],"type":"Point"}
}