{
  "type": "Feature",
  "properties": {
    "iso:country":"US",
    "sg:address":"1577 E 8th St",
    "sg:city":"Brooklyn",
    "sg:classifiers":[
        {
            "category":"Organizations",
            "subcategory":"Religious Organization",
            "type":"Services"
        }
    ],
    "sg:phone":"+1 718 339 8173",
    "sg:postcode":"11230",
    "sg:province":"NY",
    "sg:tags":[
        "clergy"
    ],
    "wof:name":"Shmuel Milstein",
    "wof:placetype":"venue"
},
  "geometry": {"coordinates":[-73.965434,40.611665],"type":"Point"}
}