{
  "type": "Feature",
  "properties": {
    "addr:full":"205 Jericho Tpke New Hyde Park NY 11040",
    "addr:housenumber":"205",
    "addr:postcode":"11040",
    "addr:street":"Jericho Tpke;Hyde Park",
    "iso:country":"US",
    "sg:address":"205 Jericho Tpke",
    "sg:city":"New Hyde Park",
    "sg:classifiers":[
        {
            "category":"Retail",
            "subcategory":"Auto Repair",
            "type":"Services"
        }
    ],
    "sg:phone":"+1 516 327 3980",
    "sg:postcode":"11040",
    "sg:province":"NY",
    "sg:tags":[
        "repairing",
        "automobile"
    ],
    "wof:name":"Continental Auto Svc Corp",
    "wof:placetype":"venue"
},
  "geometry": {"coordinates":[-73.691794,40.731245],"type":"Point"}
}