{
  "type": "Feature",
  "properties": {
    "iso:country":"US",
    "sg:address":"8 Serrell Ave",
    "sg:city":"Binghamton",
    "sg:classifiers":[
        {
            "category":"Building & Trades",
            "subcategory":"Cleaning & Sanitation",
            "type":"Services"
        }
    ],
    "sg:phone":"+1 607 797 9225",
    "sg:postcode":"13905",
    "sg:province":"NY",
    "sg:tags":[
        "window",
        "maintenance",
        "contractor"
    ],
    "wof:name":"Kerk's Window Cleaning",
    "wof:placetype":"venue"
},
  "geometry": {"coordinates":[-75.948526,42.107096],"type":"Point"}
}