{
  "type": "Feature",
  "properties": {
    "addr:full":"19 Anna Ln Ballston Lake NY 12019",
    "addr:housenumber":"19",
    "addr:postcode":"12019",
    "addr:street":"Anna Ln",
    "iso:country":"US",
    "sg:address":"19 Anna Ln",
    "sg:city":"Ballston Lake",
    "sg:classifiers":[
        {
            "category":"Wholesale",
            "subcategory":"Vending Machines",
            "type":"Manufacturing & Wholesale Goods"
        }
    ],
    "sg:phone":"+1   ",
    "sg:postcode":"12019",
    "sg:province":"NY",
    "sg:tags":[
        "operator"
    ],
    "wof:name":"Action Vending Inc A Corp",
    "wof:placetype":"venue"
},
  "geometry": {"coordinates":[-73.805179,42.931052],"type":"Point"}
}