{
  "type": "Feature",
  "properties": {
    "iso:country":"US",
    "sg:address":"80 Catherine St",
    "sg:city":"New York",
    "sg:classifiers":[
        {
            "category":"Banks & Credit Unions",
            "subcategory":"Financial Services",
            "type":"Services"
        }
    ],
    "sg:phone":"+1 347 857 9487",
    "sg:postcode":"10302",
    "sg:province":"NY",
    "sg:tags":[
        "advising"
    ],
    "wof:name":"Collection Agency B&A",
    "wof:placetype":"venue"
},
  "geometry": {"coordinates":[-74.135357,40.627707],"type":"Point"}
}