{
  "type": "Feature",
  "properties": {
    "iso:country":"US",
    "sg:address":"220 Young St",
    "sg:city":"Tonawanda",
    "sg:classifiers":[
        {
            "category":"Retail",
            "subcategory":"Animal Services",
            "type":"Services"
        }
    ],
    "sg:phone":"+1 716 695 8047",
    "sg:postcode":"14150",
    "sg:province":"NY",
    "sg:tags":[
        "pet",
        "grooming",
        "washing"
    ],
    "wof:name":"Waggin' Tail",
    "wof:placetype":"venue"
},
  "geometry": {"coordinates":[-78.871045,43.016368],"type":"Point"}
}