{
  "type": "Feature",
  "properties": {
    "addr:full":"8 Knobb Hill Dr Pittsford NY 14534",
    "addr:housenumber":"8",
    "addr:postcode":"14534",
    "addr:street":"Knobb Hill Dr",
    "iso:country":"US",
    "sg:address":"8 Knobb Hill Dr",
    "sg:city":"Pittsford",
    "sg:classifiers":[
        {
            "category":"Building & Trades",
            "subcategory":"Construction",
            "type":"Services"
        }
    ],
    "sg:phone":"+1 585 381 8611",
    "sg:postcode":"14534",
    "sg:province":"NY",
    "sg:tags":[
        "residential",
        "contractor"
    ],
    "wof:name":"Chappell Contracting",
    "wof:placetype":"venue"
},
  "geometry": {"coordinates":[-77.517197,43.079488],"type":"Point"}
}