{
  "type": "Feature",
  "properties": {
    "iso:country":"US",
    "sg:address":"123 Gros Blvd",
    "sg:city":"Herkimer",
    "sg:classifiers":[
        {
            "category":"Retail",
            "subcategory":"Auto Repair",
            "type":"Services"
        }
    ],
    "sg:phone":"+1 315 866 1803",
    "sg:postcode":"13350",
    "sg:province":"NY",
    "sg:tags":[
        "general"
    ],
    "wof:name":"Town Garage",
    "wof:placetype":"venue"
},
  "geometry": {"coordinates":[-74.95528299999999,43.028425],"type":"Point"}
}