{
  "type": "Feature",
  "properties": {
    "iso:country":"US",
    "sg:address":"92 Crum Creek Rd",
    "sg:city":"New City",
    "sg:classifiers":[
        {
            "category":"Banks & Credit Unions",
            "subcategory":"Financial Services",
            "type":"Services"
        }
    ],
    "sg:phone":"+1 845 638 3357",
    "sg:postcode":"10956",
    "sg:province":"NY",
    "sg:tags":[
        "company",
        "holding"
    ],
    "wof:name":"AMG Realty Holdings LLC",
    "wof:placetype":"venue"
},
  "geometry": {"coordinates":[-73.991709,41.167433],"type":"Point"}
}