{
  "type": "Feature",
  "properties": {
    "addr:full":"652 Merrick Rd Baldwin NY 11510",
    "addr:housenumber":"652",
    "addr:postcode":"11510",
    "addr:street":"Merrick Rd",
    "iso:country":"US",
    "sg:address":"652 Merrick Rd",
    "sg:city":"Baldwin",
    "sg:classifiers":[
        {
            "category":"Local Transit",
            "type":"Transportation"
        }
    ],
    "sg:phone":"+1   ",
    "sg:postcode":"11510",
    "sg:province":"NY",
    "sg:tags":[
        "passenger"
    ],
    "wof:name":"Ajomar Transportation Inc",
    "wof:placetype":"venue"
},
  "geometry": {"coordinates":[-73.61703300000001,40.653038],"type":"Point"}
}