{
  "type": "Feature",
  "properties": {
    "addr:full":"9107 Ave L Brooklyn NY 11236",
    "addr:postcode":"11236",
    "addr:street":"9107 Ave L",
    "iso:country":"US",
    "sg:address":"9107 Ave L",
    "sg:city":"Brooklyn",
    "sg:classifiers":[
        {
            "category":"Home & Garden",
            "subcategory":"Carpets & Floor Coverings",
            "type":"Retail Goods"
        }
    ],
    "sg:phone":"+1 718 209 3440",
    "sg:postcode":"11236",
    "sg:province":"NY",
    "sg:tags":[
        "dealer",
        "rug"
    ],
    "wof:name":"All Corners",
    "wof:placetype":"venue"
},
  "geometry": {"coordinates":[-73.89901500000001,40.636353],"type":"Point"}
}