{
  "type": "Feature",
  "properties": {
    "iso:country":"US",
    "sg:address":"717 Manhattan Ave",
    "sg:city":"Brooklyn",
    "sg:classifiers":[
        {
            "category":"Home & Garden",
            "subcategory":"Furniture",
            "type":"Retail Goods"
        }
    ],
    "sg:phone":"+1   ",
    "sg:postcode":"11222",
    "sg:province":"NY",
    "wof:name":"RG Furniture Design",
    "wof:placetype":"venue"
},
  "geometry": {"coordinates":[-73.952569,40.726641],"type":"Point"}
}