{
  "type": "Feature",
  "properties": {
    "addr:full":"11635 190th St Saint Albans NY 11412",
    "addr:housenumber":"11635",
    "addr:postcode":"11412",
    "addr:street":"190Th St",
    "iso:country":"US",
    "sg:address":"11635 190th St",
    "sg:city":"Saint Albans",
    "sg:classifiers":[
        {
            "category":"Building & Trades",
            "subcategory":"Plumbing",
            "type":"Services"
        }
    ],
    "sg:phone":"+1 800 291 0446",
    "sg:postcode":"11412",
    "sg:province":"NY",
    "wof:name":"NY-PCO Mechanical Plumbing & Heating Corp",
    "wof:placetype":"venue"
},
  "geometry": {"coordinates":[-73.76127099999999,40.69275],"type":"Point"}
}