{
  "type": "Feature",
  "properties": {
    "addr:full":"113 Kent St Brooklyn NY 11222",
    "addr:housenumber":"113",
    "addr:postcode":"11222",
    "addr:street":"Kent St",
    "iso:country":"US",
    "sg:address":"113 Kent St",
    "sg:city":"Brooklyn",
    "sg:classifiers":[
        {
            "category":"Building & Trades",
            "subcategory":"Construction",
            "type":"Services"
        }
    ],
    "sg:phone":"+1 718 389 9522",
    "sg:postcode":"11222",
    "sg:province":"NY",
    "sg:tags":[
        "hanging",
        "contractor"
    ],
    "wof:name":"American Wallpaper Removal Co",
    "wof:placetype":"venue"
},
  "geometry": {"coordinates":[-73.955344,40.73086],"type":"Point"}
}