{
  "type": "Feature",
  "properties": {
    "addr:full":"1230 Lyell Ave Rochester NY 14606",
    "addr:housenumber":"1230",
    "addr:postcode":"14606",
    "addr:street":"Lyell Ave",
    "iso:country":"US",
    "sg:address":"1230 Lyell Ave",
    "sg:city":"Rochester",
    "sg:classifiers":[
        {
            "category":"Local Transit",
            "type":"Transportation"
        }
    ],
    "sg:phone":"+1 585 247 3831",
    "sg:postcode":"14606",
    "sg:province":"NY",
    "sg:tags":[
        "limousine"
    ],
    "sg:website":"www.eclimo.com",
    "wof:name":"East Coast Limousine",
    "wof:placetype":"venue"
},
  "geometry": {"coordinates":[-77.657855,43.164732],"type":"Point"}
}