{
  "type": "Feature",
  "properties": {
    "addr:full":"218 Pleasant Valley Rd South Fallsburg NY 12779",
    "addr:housenumber":"218",
    "addr:postcode":"12779",
    "addr:street":"Pleasant Valley Rd",
    "iso:country":"US",
    "sg:address":"218 Pleasant Valley Rd",
    "sg:city":"South Fallsburg",
    "sg:classifiers":[
        {
            "category":"Retail",
            "subcategory":"Repair Shop",
            "type":"Services"
        }
    ],
    "sg:phone":"+1 845 434 7140",
    "sg:postcode":"12779",
    "sg:province":"NY",
    "sg:tags":[
        "upholsterer"
    ],
    "wof:name":"Sal's Upholstery",
    "wof:placetype":"venue"
},
  "geometry": {"coordinates":[-74.637716,41.717628],"type":"Point"}
}