{
  "type": "Feature",
  "properties": {
    "iso:country":"US",
    "sg:address":"2 Water St",
    "sg:city":"Dundee",
    "sg:classifiers":[
        {
            "category":"Food & Beverages",
            "subcategory":"Groceries & Convenience Stores",
            "type":"Retail Goods"
        }
    ],
    "sg:phone":"+1 607 243 8551",
    "sg:postcode":"14837",
    "sg:province":"NY",
    "wof:name":"Wilson Farms",
    "wof:placetype":"venue"
},
  "geometry": {"coordinates":[-76.976889,42.524817],"type":"Point"}
}