{
  "type": "Feature",
  "properties": {
    "iso:country":"US",
    "sg:address":"200 University Ave",
    "sg:city":"Rochester",
    "sg:classifiers":[
        {
            "category":"Education",
            "subcategory":"School",
            "type":"Public Place"
        }
    ],
    "sg:phone":"+1 585 425 3553",
    "sg:postcode":"14605",
    "sg:province":"NY",
    "sg:website":"http://www.easthighschool.net",
    "wof:name":"Ps 58 World Of Inquiry",
    "wof:placetype":"venue"
},
  "geometry": {"coordinates":[-77.59774,43.15976],"type":"Point"}
}