{
  "type": "Feature",
  "properties": {
    "iso:country":"US",
    "sg:address":"110 Jefferson Rd",
    "sg:city":"Montgomery",
    "sg:classifiers":[
        {
            "category":"Education",
            "subcategory":"Special Training",
            "type":"Public Place"
        }
    ],
    "sg:phone":"+1 845 457 2421",
    "sg:postcode":"12549",
    "sg:province":"NY",
    "sg:tags":[
        "educational"
    ],
    "sg:website":"http://www.safe-ir.com",
    "wof:name":"Safe-Ir Inc",
    "wof:placetype":"venue"
},
  "geometry": {"coordinates":[-74.229276,41.516073],"type":"Point"}
}