{
  "type": "Feature",
  "properties": {
    "addr:full":"3161 Amboy Rd Staten Island NY 10306",
    "addr:housenumber":"3161",
    "addr:postcode":"10306",
    "addr:street":"Amboy Rd",
    "iso:country":"US",
    "sg:address":"3161 Amboy Rd",
    "sg:city":"Staten Island",
    "sg:classifiers":[
        {
            "category":"Restaurant",
            "type":"Food & Drink"
        }
    ],
    "sg:phone":"+1 718 987 8801",
    "sg:postcode":"10306",
    "sg:province":"NY",
    "sg:tags":[
        "eating",
        "pizza"
    ],
    "wof:name":"Ambrosino's",
    "wof:placetype":"venue"
},
  "geometry": {"coordinates":[-74.132103,40.564201],"type":"Point"}
}