{
  "type": "Feature",
  "properties": {
    "iso:country":"US",
    "sg:address":"215 Hallock Rd",
    "sg:city":"Stony Brook",
    "sg:classifiers":[
        {
            "category":"Manufacturing",
            "subcategory":"Tools & Machinery",
            "type":"Manufacturing & Wholesale Goods"
        }
    ],
    "sg:phone":"+1 631 689 1970",
    "sg:postcode":"11790",
    "sg:province":"NY",
    "sg:tags":[
        "filter"
    ],
    "wof:name":"Camfil Farr Inc",
    "wof:placetype":"venue"
},
  "geometry": {"coordinates":[-73.124094,40.876076],"type":"Point"}
}