{
  "type": "Feature",
  "properties": {
    "addr:full":"566 Main Street New York NY 10044",
    "addr:housenumber":"566",
    "addr:postcode":"10044",
    "addr:street":"Main Street",
    "iso:country":"US",
    "sg:address":"566 Main Street",
    "sg:city":"New York",
    "sg:classifiers":[
        {
            "category":"Education",
            "subcategory":"School",
            "type":"Public Place"
        }
    ],
    "sg:phone":"+1 212 223 6340",
    "sg:postcode":"10044",
    "sg:province":"NY",
    "wof:name":"The Child School",
    "wof:placetype":"venue"
},
  "geometry": {"coordinates":[-73.948853,40.762916],"type":"Point"}
}