{
  "type": "Feature",
  "properties": {
    "addr:full":"175 E 7th St Oswego NY 13126",
    "addr:housenumber":"175",
    "addr:postcode":"13126",
    "addr:street":"E 7Th St",
    "iso:country":"US",
    "sg:address":"175 E 7th St",
    "sg:city":"Oswego",
    "sg:classifiers":[
        {
            "category":"Banks & Credit Unions",
            "subcategory":"Bank",
            "type":"Services"
        }
    ],
    "sg:phone":"+1 315 343 7822",
    "sg:postcode":"13126",
    "sg:province":"NY",
    "sg:website":"www.oswegocountyfcu.org",
    "wof:name":"Oswego County Public Empl CU",
    "wof:placetype":"venue"
},
  "geometry": {"coordinates":[-76.498508,43.454349],"type":"Point"}
}