{
  "type": "Feature",
  "properties": {
    "iso:country":"US",
    "sg:address":"106 Crescent Pl",
    "sg:city":"Yonkers",
    "sg:classifiers":[
        {
            "category":"Health Services",
            "subcategory":"Medical Lab",
            "type":"Services"
        }
    ],
    "sg:phone":"+1 914 237 2143",
    "sg:postcode":"10704",
    "sg:province":"NY",
    "sg:tags":[
        "laboratory",
        "dental"
    ],
    "wof:name":"Lloyds Lab",
    "wof:placetype":"venue"
},
  "geometry": {"coordinates":[-73.849071,40.918927],"type":"Point"}
}