{
  "type": "Feature",
  "properties": {
    "addr:full":"38 State Hwy 59 Spring Valley NY 10977",
    "addr:housenumber":"38",
    "addr:postcode":"10977",
    "addr:street":"State Hwy 59",
    "iso:country":"US",
    "sg:address":"38 State Hwy 59",
    "sg:city":"Spring Valley",
    "sg:classifiers":[
        {
            "category":"Restaurant",
            "type":"Food & Drink"
        }
    ],
    "sg:phone":"+1 845 352 1275",
    "sg:postcode":"10977",
    "sg:province":"NY",
    "sg:tags":[
        "eating"
    ],
    "wof:name":"Mickey's Deli & Pizza",
    "wof:placetype":"venue"
},
  "geometry": {"coordinates":[-74.04440099999999,41.109052],"type":"Point"}
}