{
  "type": "Feature",
  "properties": {
    "addr:full":"5724 2nd Ave Brooklyn NY 11220",
    "addr:housenumber":"5724",
    "addr:postcode":"11220",
    "addr:street":"2Nd Ave",
    "iso:country":"US",
    "sg:address":"5724 2nd Ave",
    "sg:city":"Brooklyn",
    "sg:classifiers":[
        {
            "category":"Organizations",
            "subcategory":"Labor Organization",
            "type":"Services"
        }
    ],
    "sg:phone":"+1 718 745 7597",
    "sg:postcode":"11220",
    "sg:province":"NY",
    "wof:name":"Transport Workers Union",
    "wof:placetype":"venue"
},
  "geometry": {"coordinates":[-74.021546,40.644784],"type":"Point"}
}