{
  "type": "Feature",
  "properties": {
    "addr:full":"43 Albany Ave Dunkirk NY 14048",
    "addr:housenumber":"43",
    "addr:postcode":"14048",
    "addr:street":"Albany Ave",
    "iso:country":"US",
    "sg:address":"43 Albany Ave",
    "sg:city":"Dunkirk",
    "sg:classifiers":[
        {
            "category":"Insurance",
            "subcategory":"Insurance Agent",
            "type":"Services"
        }
    ],
    "sg:phone":"+1   ",
    "sg:postcode":"14048",
    "sg:province":"NY",
    "sg:tags":[
        "travel",
        "agency"
    ],
    "wof:name":"Dean Insurance",
    "wof:placetype":"venue"
},
  "geometry": {"coordinates":[-79.333377,42.468329],"type":"Point"}
}