{
  "type": "Feature",
  "properties": {
    "addr:full":"841 McDonald Ave Brooklyn NY 11218",
    "addr:housenumber":"841",
    "addr:postcode":"11218",
    "addr:street":"Mcdonald Ave",
    "iso:country":"US",
    "sg:address":"841 McDonald Ave",
    "sg:city":"Brooklyn",
    "sg:classifiers":[
        {
            "category":"Manufacturing",
            "subcategory":"Apparel",
            "type":"Manufacturing & Wholesale Goods"
        },
        {
            "category":"Shopping",
            "subcategory":"Clothing, Apparel, & Fashions",
            "type":"Retail Goods"
        }
    ],
    "sg:phone":"+1 718 972 0001",
    "sg:postcode":"11218",
    "sg:province":"NY",
    "sg:tags":[
        "dress",
        "mfg"
    ],
    "wof:name":"Dodi Fashions Inc",
    "wof:placetype":"venue"
},
  "geometry": {"coordinates":[-73.97780400000001,40.635205],"type":"Point"}
}