{
  "type": "Feature",
  "properties": {
    "addr:full":"227 4th Ave Brooklyn NY 11215",
    "addr:housenumber":"227",
    "addr:postcode":"11215",
    "addr:street":"4Th Ave",
    "iso:country":"US",
    "sg:address":"227 4th Ave",
    "sg:city":"Brooklyn",
    "sg:classifiers":[
        {
            "category":"Restaurant",
            "type":"Food & Drink"
        }
    ],
    "sg:phone":"+1 718 596 8855",
    "sg:postcode":"11215",
    "sg:province":"NY",
    "sg:tags":[
        "pizza"
    ],
    "wof:name":"Tomato N Basil",
    "wof:placetype":"venue"
},
  "geometry": {"coordinates":[-73.98305000000001,40.676767],"type":"Point"}
}