{
  "type": "Feature",
  "properties": {
    "addr:full":"2912 Vestal Pkwy W Vestal NY 13850",
    "addr:housenumber":"2912",
    "addr:postcode":"13850",
    "addr:street":"Vestal Pkwy W",
    "iso:country":"US",
    "sg:address":"2912 Vestal Pkwy W",
    "sg:city":"Vestal",
    "sg:classifiers":[
        {
            "category":"Autos & Motor Vehicles",
            "subcategory":"Automobile Sales",
            "type":"Retail Goods"
        }
    ],
    "sg:phone":"+1   ",
    "sg:postcode":"13850",
    "sg:province":"NY",
    "sg:tags":[
        "used"
    ],
    "wof:name":"Vestal Auto Mart",
    "wof:placetype":"venue"
},
  "geometry": {"coordinates":[-76.105073,42.067912],"type":"Point"}
}