{
  "type": "Feature",
  "properties": {
    "addr:full":"110 Farrell Rd Syracuse NY 13209",
    "addr:housenumber":"110",
    "addr:postcode":"13209",
    "addr:street":"Farrell Rd",
    "iso:country":"US",
    "sg:address":"110 Farrell Rd",
    "sg:city":"Syracuse",
    "sg:classifiers":[
        {
            "category":"Manufacturing",
            "subcategory":"Food",
            "type":"Manufacturing & Wholesale Goods"
        }
    ],
    "sg:phone":"+1 315 457 2230",
    "sg:postcode":"13209",
    "sg:province":"NY",
    "sg:tags":[
        "product",
        "manufacturer"
    ],
    "wof:name":"Con Agra Foods",
    "wof:placetype":"venue"
},
  "geometry": {"coordinates":[-76.269882,43.117333],"type":"Point"}
}