{
  "type": "Feature",
  "properties": {
    "addr:full":"462 First Avenue Building A, 9th Floor New York NY 10016-9196",
    "addr:housenumber":"462;9th floor",
    "addr:postcode":"10016-9196",
    "addr:street":"First",
    "iso:country":"US",
    "sg:address":"462 First Avenue Building A, 9th Floor",
    "sg:city":"New York",
    "sg:classifiers":[
        {
            "category":"Professional",
            "subcategory":"Research",
            "type":"Services"
        }
    ],
    "sg:phone":"+1 646 381 6680",
    "sg:postcode":"10016-9196",
    "sg:province":"NY",
    "sg:website":"http://www.vivaldibiosciences.com/",
    "wof:name":"Vivaldi Biosciences",
    "wof:placetype":"venue"
},
  "geometry": {"coordinates":[-73.97624999999999,40.740026],"type":"Point"}
}