{
  "type": "Feature",
  "properties": {
    "addr:full":"745 West Ave Rochester NY 14611",
    "addr:housenumber":"745",
    "addr:postcode":"14611",
    "addr:street":"West Ave",
    "iso:country":"US",
    "sg:address":"745 West Ave",
    "sg:city":"Rochester",
    "sg:classifiers":[
        {
            "category":"Health Services",
            "subcategory":"Doctor",
            "type":"Services"
        }
    ],
    "sg:phone":"+1 585 442 7960",
    "sg:postcode":"14611",
    "sg:province":"NY",
    "sg:tags":[
        "physician",
        "surgeon"
    ],
    "wof:name":"Jerome Paul Woodward MD",
    "wof:placetype":"venue"
},
  "geometry": {"coordinates":[-77.657977,43.149891],"type":"Point"}
}