{
  "type": "Feature",
  "properties": {
    "addr:full":"135 Sherman Avenue New York NY 10034",
    "addr:housenumber":"135",
    "addr:postcode":"10034",
    "addr:street":"Sherman Avenue",
    "iso:country":"US",
    "sg:address":"135 Sherman Avenue",
    "sg:city":"New York",
    "sg:classifiers":[
        {
            "category":"Food & Beverages",
            "subcategory":"Groceries & Convenience Stores",
            "type":"Retail Goods"
        }
    ],
    "sg:phone":"+1 212 569 5335",
    "sg:postcode":"10034",
    "sg:province":"NY",
    "wof:name":"135Sherman Av Food Corporation",
    "wof:placetype":"venue"
},
  "geometry": {"coordinates":[-73.92399399999999,40.864435],"type":"Point"}
}