{
  "type": "Feature",
  "properties": {
    "addr:full":"2939 Lockport Rd Niagara Falls NY 14305",
    "addr:housenumber":"2939",
    "addr:postcode":"14305",
    "addr:street":"Lockport Rd",
    "iso:country":"US",
    "sg:address":"2939 Lockport Rd",
    "sg:city":"Niagara Falls",
    "sg:classifiers":[
        {
            "category":"Building & Trades",
            "subcategory":"Construction",
            "type":"Services"
        }
    ],
    "sg:phone":"+1 716 285 9280",
    "sg:postcode":"14305",
    "sg:province":"NY",
    "sg:tags":[
        "asbestos",
        "abatement",
        "demolition"
    ],
    "wof:name":"Metro Enviromental",
    "wof:placetype":"venue"
},
  "geometry": {"coordinates":[-79.03302499999999,43.114679],"type":"Point"}
}