{
  "type": "Feature",
  "properties": {
    "addr:full":"3152 Albany Cres Bronx NY 10463",
    "addr:housenumber":"3152",
    "addr:postcode":"10463",
    "addr:street":"Albany Cres",
    "iso:country":"US",
    "sg:address":"3152 Albany Cres",
    "sg:city":"Bronx",
    "sg:classifiers":[
        {
            "category":"Professional",
            "subcategory":"Lawyer & Legal Services",
            "type":"Services"
        }
    ],
    "sg:phone":"+1 718 796 2210",
    "sg:postcode":"10463",
    "sg:province":"NY",
    "sg:tags":[
        "attorney"
    ],
    "wof:name":"Doyle & Brounand",
    "wof:placetype":"venue"
},
  "geometry": {"coordinates":[-73.90198599999999,40.879212],"type":"Point"}
}