{
  "type": "Feature",
  "properties": {
    "addr:full":"23 Seely Rd Chester NY 10918",
    "addr:housenumber":"23",
    "addr:postcode":"10918",
    "addr:street":"Seely Rd",
    "iso:country":"US",
    "sg:address":"23 Seely Rd",
    "sg:city":"Chester",
    "sg:classifiers":[
        {
            "category":"Building & Trades",
            "subcategory":"Electrical",
            "type":"Services"
        }
    ],
    "sg:phone":"+1 845 774 2974",
    "sg:postcode":"10918",
    "sg:province":"NY",
    "sg:tags":[
        "electric",
        "contractor"
    ],
    "wof:name":"Scotto Electric",
    "wof:placetype":"venue"
},
  "geometry": {"coordinates":[-74.236175,41.361395],"type":"Point"}
}