{
  "type": "Feature",
  "properties": {
    "iso:country":"US",
    "sg:address":"268 Eldert St",
    "sg:city":"Brooklyn",
    "sg:classifiers":[
        {
            "category":"Building & Trades",
            "subcategory":"Electrical",
            "type":"Services"
        }
    ],
    "sg:phone":"+1 718 919 6623",
    "sg:postcode":"11207",
    "sg:province":"NY",
    "sg:tags":[
        "electrical",
        "contractor"
    ],
    "wof:name":"Inside Wiring",
    "wof:placetype":"venue"
},
  "geometry": {"coordinates":[-73.907915,40.691662],"type":"Point"}
}