{
  "type": "Feature",
  "properties": {
    "addr:full":"694 W 48 St New York NY 10036",
    "addr:housenumber":"694",
    "addr:postcode":"10036",
    "addr:street":"W 48 St",
    "iso:country":"US",
    "sg:address":"694 W 48 St",
    "sg:city":"New York",
    "sg:classifiers":[
        {
            "category":"Wholesale",
            "subcategory":"Jewelry",
            "type":"Manufacturing & Wholesale Goods"
        }
    ],
    "sg:phone":"+1 212 869 6902",
    "sg:postcode":"10036",
    "sg:province":"NY",
    "sg:tags":[
        "stone"
    ],
    "wof:name":"Mazur Roman",
    "wof:placetype":"venue"
},
  "geometry": {"coordinates":[-73.99618100000001,40.764599],"type":"Point"}
}