{
  "type": "Feature",
  "properties": {
    "iso:country":"US",
    "sg:address":"50 Railroad Ave",
    "sg:city":"Glen Head",
    "sg:classifiers":[
        {
            "category":"Manufacturing",
            "subcategory":"Printing",
            "type":"Manufacturing & Wholesale Goods"
        }
    ],
    "sg:phone":"+1 516 676 9167",
    "sg:postcode":"11545",
    "sg:province":"NY",
    "sg:tags":[
        "printer"
    ],
    "sg:website":"www.printstars.com",
    "wof:name":"New York Blueprint Corp",
    "wof:placetype":"venue"
},
  "geometry": {"coordinates":[-73.62581400000001,40.831967],"type":"Point"}
}