{
  "type": "Feature",
  "properties": {
    "addr:full":"2949 Long Beach Rd Oceanside NY 11572",
    "addr:housenumber":"2949",
    "addr:postcode":"11572",
    "addr:street":"Long Beach Rd",
    "iso:country":"US",
    "sg:address":"2949 Long Beach Rd",
    "sg:city":"Oceanside",
    "sg:classifiers":[
        {
            "category":"Professional",
            "subcategory":"Lawyer & Legal Services",
            "type":"Services"
        }
    ],
    "sg:phone":"+1 516 536 7444",
    "sg:postcode":"11572",
    "sg:province":"NY",
    "wof:name":"Ackerman Raphan & Sultzer",
    "wof:placetype":"venue"
},
  "geometry": {"coordinates":[-73.6399,40.638699],"type":"Point"}
}