{
  "type": "Feature",
  "properties": {
    "iso:country":"US",
    "sg:address":"202 Mansion Ave",
    "sg:city":"Staten Island",
    "sg:classifiers":[
        {
            "category":"Recreation",
            "type":"Entertainment"
        }
    ],
    "sg:phone":"+1 718 984 3346",
    "sg:postcode":"10308",
    "sg:province":"NY",
    "sg:tags":[
        "party",
        "fishing"
    ],
    "wof:name":"Captains Marine Mercury",
    "wof:placetype":"venue"
},
  "geometry": {"coordinates":[-74.14231599999999,40.542467],"type":"Point"}
}