{
  "type": "Feature",
  "properties": {
    "iso:country":"US",
    "sg:address":"305 E 63 St",
    "sg:city":"New York",
    "sg:classifiers":[
        {
            "category":"Professional",
            "type":"Services"
        }
    ],
    "sg:phone":"+1 212 421 6248",
    "sg:postcode":"10065",
    "sg:province":"NY",
    "sg:tags":[
        "establishment"
    ],
    "wof:name":"Compuserve Inc",
    "wof:placetype":"venue"
},
  "geometry": {"coordinates":[-73.961578,40.762807],"type":"Point"}
}