{
  "type": "Feature",
  "properties": {
    "iso:country":"US",
    "sg:address":"314 Seneca St",
    "sg:city":"Fulton",
    "sg:classifiers":[
        {
            "category":"Building & Trades",
            "subcategory":"Construction",
            "type":"Services"
        }
    ],
    "sg:phone":"+1 315 698 1126",
    "sg:postcode":"13069",
    "sg:province":"NY",
    "sg:tags":[
        "roofing",
        "contractor"
    ],
    "wof:name":"RJS Roofing & Painting",
    "wof:placetype":"venue"
},
  "geometry": {"coordinates":[-76.413307,43.32655],"type":"Point"}
}