{
  "type": "Feature",
  "properties": {
    "iso:country":"US",
    "sg:address":"690 North Ave",
    "sg:city":"New Rochelle",
    "sg:classifiers":[
        {
            "category":"Restaurant",
            "type":"Food & Drink"
        }
    ],
    "sg:phone":"+1   ",
    "sg:postcode":"10801",
    "sg:province":"NY",
    "sg:tags":[
        "eating"
    ],
    "wof:name":"Mirage Diner",
    "wof:placetype":"venue"
},
  "geometry": {"coordinates":[-73.788967,40.926213],"type":"Point"}
}