{
  "type": "Feature",
  "properties": {
    "addr:full":"511 N Center St East Syracuse NY 13057",
    "addr:housenumber":"511",
    "addr:postcode":"13057",
    "addr:street":"N Center St",
    "iso:country":"US",
    "sg:address":"511 N Center St",
    "sg:city":"East Syracuse",
    "sg:classifiers":[
        {
            "category":"Building & Trades",
            "subcategory":"Construction",
            "type":"Services"
        }
    ],
    "sg:phone":"+1 315 437 9472",
    "sg:postcode":"13057",
    "sg:province":"NY",
    "sg:tags":[
        "general",
        "contractor"
    ],
    "wof:name":"De Feo & Sons Remodeling",
    "wof:placetype":"venue"
},
  "geometry": {"coordinates":[-76.070902,43.068129],"type":"Point"}
}