{
  "type": "Feature",
  "properties": {
    "addr:full":"111 S Highland Ave Ossining NY 10562",
    "addr:housenumber":"111",
    "addr:postcode":"10562",
    "addr:street":"S Highland Ave",
    "iso:country":"US",
    "sg:address":"111 S Highland Ave",
    "sg:city":"Ossining",
    "sg:classifiers":[
        {
            "category":"Real Estate",
            "subcategory":"Real Estate Operator",
            "type":"Services"
        }
    ],
    "sg:phone":"+1 914 941 0077",
    "sg:postcode":"10562",
    "sg:province":"NY",
    "sg:tags":[
        "apartment"
    ],
    "sg:website":"www.morgancommunities.com",
    "wof:name":"Sparta Green Apartment",
    "wof:placetype":"venue"
},
  "geometry": {"coordinates":[-73.85969799999999,41.152913],"type":"Point"}
}