{
  "type": "Feature",
  "properties": {
    "addr:full":"7716 Black Willow Liverpool NY 13090",
    "addr:housenumber":"7716",
    "addr:postcode":"13090",
    "addr:street":"Black Willow",
    "iso:country":"US",
    "sg:address":"7716 Black Willow",
    "sg:city":"Liverpool",
    "sg:classifiers":[
        {
            "category":"Professional",
            "subcategory":"Management & Consulting",
            "type":"Services"
        }
    ],
    "sg:phone":"+1 315 451 0503",
    "sg:postcode":"13090",
    "sg:province":"NY",
    "wof:name":"Marketing Management Center",
    "wof:placetype":"venue"
},
  "geometry": {"coordinates":[-76.170952,43.144518],"type":"Point"}
}