{
  "type": "Feature",
  "properties": {
    "iso:country":"US",
    "sg:address":"20 Green St",
    "sg:city":"Valley Stream",
    "sg:classifiers":[
        {
            "category":"Building & Trades",
            "subcategory":"Construction",
            "type":"Services"
        }
    ],
    "sg:phone":"+1 516 285 4953",
    "sg:postcode":"11580",
    "sg:province":"NY",
    "sg:tags":[
        "contractor"
    ],
    "wof:name":"Sheetrock and Taping Inc",
    "wof:placetype":"venue"
},
  "geometry": {"coordinates":[-73.722701,40.670961],"type":"Point"}
}