{
  "type": "Feature",
  "properties": {
    "iso:country":"US",
    "sg:address":"4 S Evarts Ave",
    "sg:city":"Elmsford",
    "sg:classifiers":[
        {
            "category":"Real Estate",
            "subcategory":"Real Estate Agent",
            "type":"Services"
        }
    ],
    "sg:phone":"+1 914 345 9351",
    "sg:postcode":"10523",
    "sg:province":"NY",
    "wof:name":"Chappaqua Realty & Managmnt Co",
    "wof:placetype":"venue"
},
  "geometry": {"coordinates":[-73.816042,41.051925],"type":"Point"}
}