{
  "type": "Feature",
  "properties": {
    "addr:full":"1405 Old Country Rd Riverhead NY 11901",
    "addr:housenumber":"1405",
    "addr:postcode":"11901",
    "addr:street":"Old Country Rd",
    "iso:country":"US",
    "sg:address":"1405 Old Country Rd",
    "sg:city":"Riverhead",
    "sg:classifiers":[
        {
            "category":"Government",
            "subcategory":"Office",
            "type":"Public Place"
        }
    ],
    "sg:phone":"+1 631 727 1213",
    "sg:postcode":"11901",
    "sg:province":"NY",
    "sg:tags":[
        "national",
        "security"
    ],
    "wof:name":"Nys Armory",
    "wof:placetype":"venue"
},
  "geometry": {"coordinates":[-72.687579,40.927116],"type":"Point"}
}