{
  "type": "Feature",
  "properties": {
    "iso:country":"US",
    "sg:address":"309 Mount Pleasant Ave",
    "sg:city":"Mamaroneck",
    "sg:classifiers":[
        {
            "category":"Government",
            "subcategory":"Post Office",
            "type":"Public Place"
        }
    ],
    "sg:phone":"+1   ",
    "sg:postcode":"10543",
    "sg:province":"NY",
    "sg:tags":[
        "postal",
        "us"
    ],
    "wof:name":"Mamaroneck Main Office",
    "wof:placetype":"venue"
},
  "geometry": {"coordinates":[-73.73641000000001,40.950681],"type":"Point"}
}