{
  "type": "Feature",
  "properties": {
    "iso:country":"US",
    "sg:address":"107 Broadway",
    "sg:city":"Newburgh",
    "sg:classifiers":[
        {
            "category":"Arts & Performance",
            "subcategory":"Arts Center",
            "type":"Entertainment"
        }
    ],
    "sg:phone":"+1 845 784 1199",
    "sg:postcode":"12550",
    "sg:province":"NY",
    "wof:name":"Ritz Theater",
    "wof:placetype":"venue"
},
  "geometry": {"coordinates":[-74.011571,41.499478],"type":"Point"}
}