{
  "type": "Feature",
  "properties": {
    "addr:full":"265 Roxford Rd N Syracuse NY 13208",
    "addr:housenumber":"265",
    "addr:postcode":"13208",
    "addr:street":"Roxford Rd N",
    "iso:country":"US",
    "sg:address":"265 Roxford Rd N",
    "sg:city":"Syracuse",
    "sg:classifiers":[
        {
            "category":"Shopping",
            "subcategory":"Gifts & Souvenirs",
            "type":"Retail Goods"
        }
    ],
    "sg:phone":"+1   ",
    "sg:postcode":"13208",
    "sg:province":"NY",
    "wof:name":"Johnnies Rec & Collectibles",
    "wof:placetype":"venue"
},
  "geometry": {"coordinates":[-76.136762,43.085672],"type":"Point"}
}