{
  "type": "Feature",
  "properties": {
    "addr:full":"146 Spring St New York NY 10012",
    "addr:housenumber":"146",
    "addr:postcode":"10012",
    "addr:street":"Spring St",
    "iso:country":"US",
    "sg:address":"146 Spring St",
    "sg:city":"New York",
    "sg:classifiers":[
        {
            "category":"Shopping",
            "subcategory":"Beauty & Cosmetics",
            "type":"Retail Goods"
        }
    ],
    "sg:phone":"+1 212 334 0830",
    "sg:postcode":"10012",
    "sg:province":"NY",
    "sg:tags":[
        "supply"
    ],
    "sg:website":"www.loccitane.com/",
    "wof:name":"L'Occitane",
    "wof:placetype":"venue"
},
  "geometry": {"coordinates":[-74.00134300000001,40.72429],"type":"Point"}
}