{
  "type": "Feature",
  "properties": {
    "iso:country":"US",
    "sg:address":"498 Avenue of the Americas",
    "sg:city":"New York",
    "sg:classifiers":[
        {
            "category":"Personal",
            "subcategory":"Massage",
            "type":"Services"
        }
    ],
    "sg:phone":"+1 212 675 0728",
    "sg:postcode":"10011",
    "sg:province":"NY",
    "wof:name":"498 Tui-Na Center",
    "wof:placetype":"venue"
},
  "geometry": {"coordinates":[-73.99709199999999,40.736272],"type":"Point"}
}