{
  "type": "Feature",
  "properties": {
    "iso:country":"US",
    "sg:address":"712 Manhattan Ave",
    "sg:city":"Brooklyn",
    "sg:classifiers":[
        {
            "category":"Banks & Credit Unions",
            "subcategory":"Bank",
            "type":"Services"
        }
    ],
    "sg:phone":"+1 718 383 0807",
    "sg:postcode":"11222",
    "sg:province":"NY",
    "sg:tags":[
        "machine",
        "teller",
        "automated"
    ],
    "wof:name":"ATM World",
    "wof:placetype":"venue"
},
  "geometry": {"coordinates":[-73.952493,40.726843],"type":"Point"}
}