{
  "type": "Feature",
  "properties": {
    "addr:full":"200 Gold Street Brooklyn NY 11201",
    "addr:housenumber":"200",
    "addr:postcode":"11201",
    "addr:street":"Gold Street",
    "iso:country":"US",
    "sg:address":"200 Gold Street",
    "sg:city":"Brooklyn",
    "sg:classifiers":[
        {
            "category":"Retail",
            "subcategory":"Event Space",
            "type":"Services"
        }
    ],
    "sg:phone":"+1 718 875 8801",
    "sg:postcode":"11201",
    "sg:province":"NY",
    "sg:tags":[
        "venue"
    ],
    "wof:name":"Catholic Settlement Assn",
    "wof:placetype":"venue"
},
  "geometry": {"coordinates":[-73.982912,40.698288],"type":"Point"}
}