{
  "type": "Feature",
  "properties": {
    "addr:full":"337 Main St Highland Falls NY 10928",
    "addr:housenumber":"337",
    "addr:postcode":"10928",
    "addr:street":"Main St",
    "iso:country":"US",
    "sg:address":"337 Main St",
    "sg:city":"Highland Falls",
    "sg:classifiers":[
        {
            "category":"Restaurant",
            "type":"Food & Drink"
        }
    ],
    "sg:phone":"+1   ",
    "sg:postcode":"10928",
    "sg:province":"NY",
    "sg:tags":[
        "eating"
    ],
    "wof:name":"Kings Garden Chin Rest",
    "wof:placetype":"venue"
},
  "geometry": {"coordinates":[-73.964878,41.370978],"type":"Point"}
}