{
  "type": "Feature",
  "properties": {
    "addr:full":"261 W 36th Street New York NY 10018",
    "addr:housenumber":"261",
    "addr:postcode":"10018",
    "addr:street":"W 36Th Street",
    "iso:country":"US",
    "sg:address":"261 W 36th Street",
    "sg:city":"New York",
    "sg:classifiers":[
        {
            "category":"Shopping",
            "subcategory":"Clothing, Apparel, & Fashions",
            "type":"Retail Goods"
        }
    ],
    "sg:phone":"+1 212 947 4559",
    "sg:postcode":"10018",
    "sg:province":"NY",
    "sg:tags":[
        "accessory",
        "clothing",
        "women's"
    ],
    "wof:name":"Add Fashion",
    "wof:placetype":"venue"
},
  "geometry": {"coordinates":[-73.991585,40.753091],"type":"Point"}
}