{
  "type": "Feature",
  "properties": {
    "addr:full":"38 Maple St Southampton NY 11968",
    "addr:housenumber":"38",
    "addr:postcode":"11968",
    "addr:street":"Maple St",
    "iso:country":"US",
    "sg:address":"38 Maple St",
    "sg:city":"Southampton",
    "sg:classifiers":[
        {
            "category":"Place Of Worship",
            "subcategory":"Monastery",
            "type":"Public Place"
        },
        {
            "category":"Organizations",
            "subcategory":"Religious Organization",
            "type":"Services"
        }
    ],
    "sg:phone":"+1 631 283 9110",
    "sg:postcode":"11968",
    "sg:province":"NY",
    "sg:tags":[
        "convent"
    ],
    "wof:name":"Our Lady of Poland R C Church",
    "wof:placetype":"venue"
},
  "geometry": {"coordinates":[-72.38967100000001,40.893509],"type":"Point"}
}