{
  "type": "Feature",
  "properties": {
    "iso:country":"US",
    "sg:address":"1602 Newkirk Ave",
    "sg:city":"Brooklyn",
    "sg:classifiers":[
        {
            "category":"Retail",
            "subcategory":"Laundry & Dry Cleaning",
            "type":"Services"
        }
    ],
    "sg:phone":"+1 718 434 5940",
    "sg:postcode":"11226",
    "sg:province":"NY",
    "sg:tags":[
        "cleaners"
    ],
    "wof:name":"World French Cleaners Corp",
    "wof:placetype":"venue"
},
  "geometry": {"coordinates":[-73.961556,40.636296],"type":"Point"}
}