{
  "type": "Feature",
  "properties": {
    "addr:full":"9215 Guy R Brewer Blvd Jamaica NY 11433",
    "addr:housenumber":"9215",
    "addr:postcode":"11433",
    "addr:street":"Guy R Brewer Blvd",
    "iso:country":"US",
    "sg:address":"9215 Guy R Brewer Blvd",
    "sg:city":"Jamaica",
    "sg:classifiers":[
        {
            "category":"Home & Garden",
            "subcategory":"Home Furnishings",
            "type":"Retail Goods"
        }
    ],
    "sg:phone":"+1 718 206 4260",
    "sg:postcode":"11433",
    "sg:province":"NY",
    "sg:tags":[
        "linen"
    ],
    "wof:name":"I Cha Linen",
    "wof:placetype":"venue"
},
  "geometry": {"coordinates":[-73.787052,40.690819],"type":"Point"}
}