{
  "type": "Feature",
  "properties": {
    "addr:full":"4126 54th Street Woodside NY 11377",
    "addr:housenumber":"4126",
    "addr:postcode":"11377",
    "addr:street":"54Th Street",
    "iso:country":"US",
    "sg:address":"4126 54th Street",
    "sg:city":"Woodside",
    "sg:classifiers":[
        {
            "category":"Food & Beverages",
            "subcategory":"Groceries & Convenience Stores",
            "type":"Retail Goods"
        }
    ],
    "sg:phone":"+1 718 899 7466",
    "sg:postcode":"11377",
    "sg:province":"NY",
    "wof:name":"Mexicano Ltd Deli Grocery",
    "wof:placetype":"venue"
},
  "geometry": {"coordinates":[-73.91053599999999,40.744859],"type":"Point"}
}