{
  "type": "Feature",
  "properties": {
    "iso:country":"US",
    "sg:address":"109 Highland Ave",
    "sg:city":"Brocton",
    "sg:classifiers":[
        {
            "category":"Building & Trades",
            "subcategory":"Construction",
            "type":"Services"
        }
    ],
    "sg:phone":"+1 716 792 6818",
    "sg:postcode":"14716",
    "sg:province":"NY",
    "sg:tags":[
        "excavation",
        "contractor"
    ],
    "wof:name":"Great Lakes Enterprises",
    "wof:placetype":"venue"
},
  "geometry": {"coordinates":[-79.441057,42.380632],"type":"Point"}
}