{
  "type": "Feature",
  "properties": {
    "iso:country":"US",
    "sg:address":"141 India St",
    "sg:city":"Brooklyn",
    "sg:classifiers":[
        {
            "category":"Personal",
            "subcategory":"Beauty Salon",
            "type":"Services"
        }
    ],
    "sg:phone":"+1   ",
    "sg:postcode":"11222",
    "sg:province":"NY",
    "sg:tags":[
        "shop"
    ],
    "wof:name":"H & E Unisex Salon",
    "wof:placetype":"venue"
},
  "geometry": {"coordinates":[-73.952157,40.732629],"type":"Point"}
}