{
  "type": "Feature",
  "properties": {
    "iso:country":"US",
    "sg:address":"1840 Abbott Rd",
    "sg:city":"Buffalo",
    "sg:classifiers":[
        {
            "category":"Wholesale",
            "subcategory":"Sporting Goods",
            "type":"Manufacturing & Wholesale Goods"
        }
    ],
    "sg:phone":"+1 716 828 0540",
    "sg:postcode":"14218",
    "sg:province":"NY",
    "wof:name":"Perfect Choice Pro Shop",
    "wof:placetype":"venue"
},
  "geometry": {"coordinates":[-78.800031,42.813828],"type":"Point"}
}