{
  "type": "Feature",
  "properties": {
    "iso:country":"US",
    "sg:address":"55 Chamberlain St",
    "sg:city":"Wellsville",
    "sg:classifiers":[
        {
            "category":"Professional",
            "subcategory":"Employment Agencies",
            "type":"Services"
        },
        {
            "category":"Social Services",
            "type":"Services"
        }
    ],
    "sg:phone":"+1 585 593 6390",
    "sg:postcode":"14895",
    "sg:province":"NY",
    "sg:tags":[
        "employee",
        "assistance",
        "program",
        "help",
        "supply"
    ],
    "sg:website":"www.theeap.com",
    "wof:name":"Employee Services Inc",
    "wof:placetype":"venue"
},
  "geometry": {"coordinates":[-77.954137,42.121261],"type":"Point"}
}