{
  "type": "Feature",
  "properties": {
    "iso:country":"US",
    "sg:address":"98 Linden St",
    "sg:city":"Roslyn Heights",
    "sg:classifiers":[
        {
            "category":"Building & Trades",
            "subcategory":"Construction",
            "type":"Services"
        }
    ],
    "sg:phone":"+1 516 967 5666",
    "sg:postcode":"11577",
    "sg:province":"NY",
    "sg:tags":[
        "interior"
    ],
    "wof:name":"Safa Construction Corp",
    "wof:placetype":"venue"
},
  "geometry": {"coordinates":[-73.64124,40.78794],"type":"Point"}
}