{
  "type": "Feature",
  "properties": {
    "addr:full":"406 Manchester Rd Poughkeepsie NY 12603",
    "addr:housenumber":"406",
    "addr:postcode":"12603",
    "addr:street":"Manchester Rd",
    "iso:country":"US",
    "sg:address":"406 Manchester Rd",
    "sg:city":"Poughkeepsie",
    "sg:classifiers":[
        {
            "category":"Professional",
            "subcategory":"Business Services",
            "type":"Services"
        }
    ],
    "sg:phone":"+1 845 856 5886",
    "sg:postcode":"12603",
    "sg:province":"NY",
    "sg:tags":[
        "water",
        "treatment"
    ],
    "wof:name":"Aquascience",
    "wof:placetype":"venue"
},
  "geometry": {"coordinates":[-73.86307499999999,41.68364],"type":"Point"}
}