{
  "type": "Feature",
  "properties": {
    "addr:full":"6807 5th Avenue Brooklyn NY 11220",
    "addr:housenumber":"6807",
    "addr:postcode":"11220",
    "addr:street":"5Th Avenue",
    "iso:country":"US",
    "sg:address":"6807 5th Avenue",
    "sg:city":"Brooklyn",
    "sg:classifiers":[
        {
            "category":"Place Of Worship",
            "subcategory":"Mosque",
            "type":"Public Place"
        }
    ],
    "sg:phone":"+1 718 680 0121",
    "sg:postcode":"11220",
    "sg:province":"NY",
    "wof:name":"Islamic Society of Bay Ridge",
    "wof:placetype":"venue"
},
  "geometry": {"coordinates":[-74.020719,40.634119],"type":"Point"}
}