{
  "type": "Feature",
  "properties": {
    "iso:country":"US",
    "sg:address":"114 Millertown Rd",
    "sg:city":"Bedford",
    "sg:classifiers":[
        {
            "category":"Retail",
            "subcategory":"Portrait Studio",
            "type":"Services"
        }
    ],
    "sg:phone":"+1   ",
    "sg:postcode":"10506",
    "sg:province":"NY",
    "sg:tags":[
        "photo"
    ],
    "wof:name":"Phillip H Ennis Photography",
    "wof:placetype":"venue"
},
  "geometry": {"coordinates":[-73.601652,41.210741],"type":"Point"}
}