{
  "type": "Feature",
  "properties": {
    "iso:country":"US",
    "sg:address":"340 Dundee-Glenora Rd",
    "sg:city":"Dundee",
    "sg:classifiers":[
        {
            "category":"Manufacturing",
            "subcategory":"Food",
            "type":"Manufacturing & Wholesale Goods"
        }
    ],
    "sg:phone":"+1 607 243 8383",
    "sg:postcode":"14837",
    "sg:province":"NY",
    "sg:tags":[
        "winery"
    ],
    "wof:name":"Glenora Farms",
    "wof:placetype":"venue"
},
  "geometry": {"coordinates":[-76.93055,42.500349],"type":"Point"}
}