{
  "type": "Feature",
  "properties": {
    "addr:full":"853 Manhattan Avenue Brooklyn NY 11222",
    "addr:housenumber":"853",
    "addr:postcode":"11222",
    "addr:street":"Manhattan Avenue",
    "iso:country":"US",
    "sg:address":"853 Manhattan Avenue",
    "sg:city":"Brooklyn",
    "sg:classifiers":[
        {
            "category":"Building & Trades",
            "subcategory":"Locksmith",
            "type":"Services"
        }
    ],
    "sg:phone":"+1 718 535 9492",
    "sg:postcode":"11222",
    "sg:province":"NY",
    "sg:tags":[
        "key"
    ],
    "wof:name":"Emergency All Day Locksmith",
    "wof:placetype":"venue"
},
  "geometry": {"coordinates":[-73.953805,40.729158],"type":"Point"}
}