{
  "type": "Feature",
  "properties": {
    "addr:full":"626 Co Rd 22 Middletown NY 10940",
    "addr:housenumber":"626;22",
    "addr:postcode":"10940",
    "addr:street":"Co Rd",
    "iso:country":"US",
    "sg:address":"626 Co Rd 22",
    "sg:city":"Middletown",
    "sg:classifiers":[
        {
            "category":"Organizations",
            "subcategory":"Religious Organization",
            "type":"Services"
        }
    ],
    "sg:phone":"+1 845 355 4439",
    "sg:postcode":"10940",
    "sg:province":"NY",
    "sg:tags":[
        "church"
    ],
    "wof:name":"Holy Cross Catholic Church",
    "wof:placetype":"venue"
},
  "geometry": {"coordinates":[-74.523245,41.383998],"type":"Point"}
}