{
  "type": "Feature",
  "properties": {
    "iso:country":"US",
    "sg:address":"3661 Horseblock Rd N",
    "sg:city":"Medford",
    "sg:classifiers":[
        {
            "category":"Building & Trades",
            "subcategory":"Construction",
            "type":"Services"
        }
    ],
    "sg:phone":"+1 631 924 3432",
    "sg:postcode":"11763",
    "sg:province":"NY",
    "sg:tags":[
        "specializing",
        "swimming",
        "pool",
        "contractor"
    ],
    "wof:name":"Specht Tacular Pools Inc",
    "wof:placetype":"venue"
},
  "geometry": {"coordinates":[-72.954903,40.813274],"type":"Point"}
}