{
  "type": "Feature",
  "properties": {
    "addr:full":"508 Highland Ave Peekskill NY 10566",
    "addr:housenumber":"508",
    "addr:postcode":"10566",
    "addr:street":"Highland Ave",
    "iso:country":"US",
    "sg:address":"508 Highland Ave",
    "sg:city":"Peekskill",
    "sg:phone":"+1 914 668 4328",
    "sg:postcode":"10566",
    "sg:province":"NY",
    "sg:tags":[
        "oil"
    ],
    "wof:name":"Heat USA",
    "wof:placetype":"venue"
},
  "geometry": {"coordinates":[-73.920418,41.297123],"type":"Point"}
}