{
  "type": "Feature",
  "properties": {
    "addr:full":"1405 Bodle Hill Rd Owego NY 13827",
    "addr:housenumber":"1405",
    "addr:postcode":"13827",
    "addr:street":"Bodle Hill Rd",
    "iso:country":"US",
    "sg:address":"1405 Bodle Hill Rd",
    "sg:city":"Owego",
    "sg:classifiers":[
        {
            "category":"Organizations",
            "subcategory":"Religious Organization",
            "type":"Services"
        }
    ],
    "sg:phone":"+1 607 687 3030",
    "sg:postcode":"13827",
    "sg:province":"NY",
    "sg:tags":[
        "church"
    ],
    "wof:name":"Living Water Baptist Church",
    "wof:placetype":"venue"
},
  "geometry": {"coordinates":[-76.220557,42.106205],"type":"Point"}
}