{
  "type": "Feature",
  "properties": {
    "addr:full":"542 Jersey St Staten Island NY 10301",
    "addr:housenumber":"542",
    "addr:postcode":"10301",
    "addr:street":"Jersey St",
    "iso:country":"US",
    "sg:address":"542 Jersey St",
    "sg:city":"Staten Island",
    "sg:classifiers":[
        {
            "category":"Building & Trades",
            "subcategory":"Plumbing",
            "type":"Services"
        }
    ],
    "sg:phone":"+1 718 876 7441",
    "sg:postcode":"10301",
    "sg:province":"NY",
    "sg:tags":[
        "plumbing",
        "residential",
        "heating",
        "contractor"
    ],
    "wof:name":"New York Plumbing Company Inc",
    "wof:placetype":"venue"
},
  "geometry": {"coordinates":[-74.084147,40.635892],"type":"Point"}
}