{
  "type": "Feature",
  "properties": {
    "addr:full":"247 Jericho Tpke Floral Park NY 11001",
    "addr:housenumber":"247",
    "addr:postcode":"11001",
    "addr:street":"Jericho Tpke",
    "iso:country":"US",
    "sg:address":"247 Jericho Tpke",
    "sg:city":"Floral Park",
    "sg:classifiers":[
        {
            "category":"Utilities",
            "subcategory":"Mobile Phone",
            "type":"Services"
        }
    ],
    "sg:phone":"+1   ",
    "sg:postcode":"11001",
    "sg:province":"NY",
    "sg:tags":[
        "communication",
        "radiotelephone",
        "business"
    ],
    "wof:name":"Map Mobile Communications Inc",
    "wof:placetype":"venue"
},
  "geometry": {"coordinates":[-73.70368999999999,40.728739],"type":"Point"}
}