{
  "type": "Feature",
  "properties": {
    "iso:country":"US",
    "name:eng_x_preferred":[
        "New Utrecht Av"
    ],
    "wof:name":"New Utrecht Av Station",
    "wof:placetype":"venue"
},
  "geometry": {"coordinates":[-73.996353,40.624842],"type":"Point"}
}