{
  "type": "Feature",
  "properties": {
    "addr:full":"13 Standish Pl Nesconset NY 11787",
    "addr:housenumber":"13",
    "addr:postcode":"11787",
    "addr:street":"Standish Pl",
    "iso:country":"US",
    "sg:address":"13 Standish Pl",
    "sg:city":"Nesconset",
    "sg:classifiers":[
        {
            "category":"Building & Trades",
            "subcategory":"Construction",
            "type":"Services"
        }
    ],
    "sg:phone":"+1 631 724 7579",
    "sg:postcode":"11787",
    "sg:province":"NY",
    "sg:tags":[
        "general",
        "contractor"
    ],
    "wof:name":"Arroyo Contracting Inc",
    "wof:placetype":"venue"
},
  "geometry": {"coordinates":[-73.16457,40.848728],"type":"Point"}
}