{
  "type": "Feature",
  "properties": {
    "addr:full":"4220 Hempstead Tpke Bethpage NY 11714",
    "addr:housenumber":"4220",
    "addr:postcode":"11714",
    "addr:street":"Hempstead Tpke",
    "iso:country":"US",
    "sg:address":"4220 Hempstead Tpke",
    "sg:city":"Bethpage",
    "sg:classifiers":[
        {
            "category":"Food & Beverages",
            "subcategory":"Groceries & Convenience Stores",
            "type":"Retail Goods"
        }
    ],
    "sg:phone":"+1 516 731 6393",
    "sg:postcode":"11714",
    "sg:province":"NY",
    "sg:website":"www.7-eleven.com",
    "wof:name":"7-Eleven",
    "wof:placetype":"venue"
},
  "geometry": {"coordinates":[-73.478883,40.725705],"type":"Point"}
}