{
  "type": "Feature",
  "properties": {
    "addr:full":"817 Union Rd Peru NY 12972",
    "addr:housenumber":"817",
    "addr:postcode":"12972",
    "addr:street":"Union Rd",
    "iso:country":"US",
    "sg:address":"817 Union Rd",
    "sg:city":"Peru",
    "sg:classifiers":[
        {
            "category":"Food & Beverages",
            "subcategory":"Bakery",
            "type":"Retail Goods"
        }
    ],
    "sg:phone":"+1 518 643 2605",
    "sg:postcode":"12972",
    "sg:province":"NY",
    "sg:tags":[
        "baker"
    ],
    "wof:name":"George Weston Foods Inc",
    "wof:placetype":"venue"
},
  "geometry": {"coordinates":[-73.525769,44.575784],"type":"Point"}
}