{
  "type": "Feature",
  "properties": {
    "addr:full":"51 Damski Rd Hudson NY 12534",
    "addr:housenumber":"51",
    "addr:postcode":"12534",
    "addr:street":"Damski Rd",
    "iso:country":"US",
    "sg:address":"51 Damski Rd",
    "sg:city":"Hudson",
    "sg:classifiers":[
        {
            "category":"Autos & Motor Vehicles",
            "subcategory":"Auto Supplies",
            "type":"Retail Goods"
        },
        {
            "category":"Retail",
            "subcategory":"Auto Repair",
            "type":"Services"
        }
    ],
    "sg:phone":"+1 518 851 5454",
    "sg:postcode":"12534",
    "sg:province":"NY",
    "sg:tags":[
        "tire"
    ],
    "wof:name":"Jimmy's Auto Repr",
    "wof:placetype":"venue"
},
  "geometry": {"coordinates":[-73.794403,42.164299],"type":"Point"}
}