{
  "type": "Feature",
  "properties": {
    "addr:full":"706 92nd St Niagara Falls NY 14304",
    "addr:housenumber":"706",
    "addr:postcode":"14304",
    "addr:street":"92Nd St",
    "iso:country":"US",
    "sg:address":"706 92nd St",
    "sg:city":"Niagara Falls",
    "sg:classifiers":[
        {
            "category":"Insurance",
            "subcategory":"Insurance Agent",
            "type":"Services"
        }
    ],
    "sg:phone":"+1 716 283 3335",
    "sg:postcode":"14304",
    "sg:province":"NY",
    "wof:name":"Harry F Hazel",
    "wof:placetype":"venue"
},
  "geometry": {"coordinates":[-78.956841,43.083848],"type":"Point"}
}