{
  "type": "Feature",
  "properties": {
    "addr:full":"1174 Commerce Ave Bronx NY 10462",
    "addr:housenumber":"1174",
    "addr:postcode":"10462",
    "addr:street":"Commerce Ave",
    "iso:country":"US",
    "sg:address":"1174 Commerce Ave",
    "sg:city":"Bronx",
    "sg:classifiers":[
        {
            "category":"Building & Trades",
            "subcategory":"Construction",
            "type":"Services"
        }
    ],
    "sg:phone":"+1 718 822 5719",
    "sg:postcode":"10462",
    "sg:province":"NY",
    "sg:tags":[
        "contractor"
    ],
    "wof:name":"National Construction Services",
    "wof:placetype":"venue"
},
  "geometry": {"coordinates":[-73.84134299999999,40.833501],"type":"Point"}
}