{
  "type": "Feature",
  "properties": {
    "addr:full":"222 W 10 St New York NY 10014",
    "addr:housenumber":"222",
    "addr:postcode":"10014",
    "addr:street":"W 10 St",
    "iso:country":"US",
    "sg:address":"222 W 10 St",
    "sg:city":"New York",
    "sg:classifiers":[
        {
            "category":"Personal",
            "subcategory":"Beauty Salon",
            "type":"Services"
        }
    ],
    "sg:phone":"+1 212 627 8665",
    "sg:postcode":"10014",
    "sg:province":"NY",
    "wof:name":"Koo Hair",
    "wof:placetype":"venue"
},
  "geometry": {"coordinates":[-74.006125,40.7337],"type":"Point"}
}