{
  "type": "Feature",
  "properties": {
    "addr:full":"31 E 31 St New York NY 10016",
    "addr:housenumber":"31;31",
    "addr:postcode":"10016",
    "addr:street":"E",
    "iso:country":"US",
    "sg:address":"31 E 31 St",
    "sg:city":"New York",
    "sg:classifiers":[
        {
            "category":"Wholesale",
            "subcategory":"Home Furnishings",
            "type":"Manufacturing & Wholesale Goods"
        }
    ],
    "sg:phone":"+1 212 889 2090",
    "sg:postcode":"10016",
    "sg:province":"NY",
    "sg:website":"www.farshinternational.com",
    "wof:name":"Farsh International",
    "wof:placetype":"venue"
},
  "geometry": {"coordinates":[-73.98282,40.745317],"type":"Point"}
}