{
  "type": "Feature",
  "properties": {
    "iso:country":"US",
    "sg:address":"902 Broadway Fl 13",
    "sg:city":"New York",
    "sg:classifiers":[
        {
            "category":"Real Estate",
            "subcategory":"Real Estate Services",
            "type":"Services"
        }
    ],
    "sg:phone":"+1 212 243 9090",
    "sg:postcode":"10010",
    "sg:province":"NY",
    "sg:tags":[
        "management",
        "property"
    ],
    "sg:website":"www.phippsny.org",
    "wof:name":"Phipps Houses",
    "wof:placetype":"venue"
},
  "geometry": {"coordinates":[-73.989363,40.739292],"type":"Point"}
}