{
  "type": "Feature",
  "properties": {
    "addr:full":"1826 Nostrand Ave Brooklyn NY 11226",
    "addr:housenumber":"1826",
    "addr:postcode":"11226",
    "addr:street":"Nostrand Ave",
    "iso:country":"US",
    "sg:address":"1826 Nostrand Ave",
    "sg:city":"Brooklyn",
    "sg:classifiers":[
        {
            "category":"Banks & Credit Unions",
            "subcategory":"Bank",
            "type":"Services"
        }
    ],
    "sg:phone":"+1 718 469 7547",
    "sg:postcode":"11226",
    "sg:province":"NY",
    "sg:tags":[
        "cashing",
        "check"
    ],
    "wof:name":"Bandco Check Cashing Svc",
    "wof:placetype":"venue"
},
  "geometry": {"coordinates":[-73.94875,40.642925],"type":"Point"}
}