{
  "type": "Feature",
  "properties": {
    "iso:country":"US",
    "sg:address":"6 Gladwyne Ct",
    "sg:city":"Spring Valley",
    "sg:classifiers":[
        {
            "category":"Professional",
            "subcategory":"Management & Consulting",
            "type":"Services"
        }
    ],
    "sg:phone":"+1 845 354 7720",
    "sg:postcode":"10977",
    "sg:province":"NY",
    "wof:name":"Innovators Inc",
    "wof:placetype":"venue"
},
  "geometry": {"coordinates":[-74.06686999999999,41.146349],"type":"Point"}
}