{
  "type": "Feature",
  "properties": {
    "addr:full":"1808 E Fayette St Syracuse NY 13210",
    "addr:housenumber":"1808",
    "addr:postcode":"13210",
    "addr:street":"E Fayette St",
    "iso:country":"US",
    "sg:address":"1808 E Fayette St",
    "sg:city":"Syracuse",
    "sg:classifiers":[
        {
            "category":"Organizations",
            "subcategory":"Religious Organization",
            "type":"Services"
        }
    ],
    "sg:phone":"+1 315 424 7777",
    "sg:postcode":"13210",
    "sg:province":"NY",
    "sg:tags":[
        "church"
    ],
    "wof:name":"Metro Harvest Assembly Of God",
    "wof:placetype":"venue"
},
  "geometry": {"coordinates":[-76.11728100000001,43.048169],"type":"Point"}
}