{
  "type": "Feature",
  "properties": {
    "addr:full":"110 State St Westbury NY 11590",
    "addr:housenumber":"110",
    "addr:postcode":"11590",
    "addr:street":"State St",
    "iso:country":"US",
    "sg:address":"110 State St",
    "sg:city":"Westbury",
    "sg:classifiers":[
        {
            "category":"Autos & Motor Vehicles",
            "subcategory":"Automobile Sales",
            "type":"Retail Goods"
        },
        {
            "category":"Retail",
            "subcategory":"Auto Rental",
            "type":"Services"
        },
        {
            "category":"Retail",
            "subcategory":"Auto Repair",
            "type":"Services"
        }
    ],
    "sg:phone":"+1 516 333 2666",
    "sg:postcode":"11590",
    "sg:province":"NY",
    "sg:tags":[
        "car"
    ],
    "wof:name":"Westbury Jeep Eagle Chrysler Plymouth Inc",
    "wof:placetype":"venue"
},
  "geometry": {"coordinates":[-73.558601,40.7575],"type":"Point"}
}