{
  "type": "Feature",
  "properties": {
    "iso:country":"US",
    "sg:address":"4390 Nesconset Hwy",
    "sg:city":"Port Jefferson Station",
    "sg:classifiers":[
        {
            "category":"Shopping",
            "type":"Retail Goods"
        }
    ],
    "sg:phone":"+1   ",
    "sg:postcode":"11776",
    "sg:province":"NY",
    "sg:tags":[
        "merchandise"
    ],
    "wof:name":"Ortholab Patient Care",
    "wof:placetype":"venue"
},
  "geometry": {"coordinates":[-73.062394,40.911048],"type":"Point"}
}