{
  "type": "Feature",
  "properties": {
    "addr:full":"643 Broadway New York NY 10012",
    "addr:housenumber":"643",
    "addr:postcode":"10012",
    "addr:street":"Broadway",
    "iso:country":"US",
    "sg:address":"643 Broadway",
    "sg:city":"New York",
    "sg:classifiers":[
        {
            "category":"Professional",
            "type":"Services"
        },
        {
            "category":"Restaurant",
            "type":"Food & Drink"
        }
    ],
    "sg:phone":"+1 212 253 7467",
    "sg:postcode":"10012",
    "sg:province":"NY",
    "sg:tags":[
        "new",
        "american",
        "caterer"
    ],
    "sg:website":"www.cornershopcafe.com/",
    "wof:name":"Corner Shop Cafe",
    "wof:placetype":"venue"
},
  "geometry": {"coordinates":[-73.995987,40.726753],"type":"Point"}
}