{
  "type": "Feature",
  "properties": {
    "addr:full":"21 Lincoln St Auburn NY 13021",
    "addr:housenumber":"21",
    "addr:postcode":"13021",
    "addr:street":"Lincoln St",
    "iso:country":"US",
    "sg:address":"21 Lincoln St",
    "sg:city":"Auburn",
    "sg:classifiers":[
        {
            "category":"Professional",
            "subcategory":"Lawyer & Legal Services",
            "type":"Services"
        }
    ],
    "sg:phone":"+1 315 252 5840",
    "sg:postcode":"13021",
    "sg:province":"NY",
    "sg:tags":[
        "attorney"
    ],
    "wof:name":"Earle Thurston Jr",
    "wof:placetype":"venue"
},
  "geometry": {"coordinates":[-76.564735,42.930842],"type":"Point"}
}