{
  "type": "Feature",
  "properties": {
    "addr:full":"15 Little Brook Ln Newburgh NY 12550",
    "addr:housenumber":"15",
    "addr:postcode":"12550",
    "addr:street":"Little Brook Ln",
    "iso:country":"US",
    "sg:address":"15 Little Brook Ln",
    "sg:city":"Newburgh",
    "sg:classifiers":[
        {
            "category":"Wholesale",
            "subcategory":"Machinery & Supplies",
            "type":"Manufacturing & Wholesale Goods"
        }
    ],
    "sg:phone":"+1 845 566 5071",
    "sg:postcode":"12550",
    "sg:province":"NY",
    "sg:website":"www.cleanharbors.com",
    "wof:name":"Clean Harbors Environmental",
    "wof:placetype":"venue"
},
  "geometry": {"coordinates":[-74.065122,41.544362],"type":"Point"}
}