{
  "type": "Feature",
  "properties": {
    "addr:full":"3882 Sunrise Hwy Seaford NY 11783",
    "addr:housenumber":"3882",
    "addr:postcode":"11783",
    "addr:street":"Sunrise Hwy",
    "iso:country":"US",
    "sg:address":"3882 Sunrise Hwy",
    "sg:city":"Seaford",
    "sg:classifiers":[
        {
            "category":"Restaurant",
            "type":"Food & Drink"
        }
    ],
    "sg:menulink":"http://www.allmenus.com/ny/seaford/182025-wendys/menu/",
    "sg:phone":"+1 516 409 4870",
    "sg:postcode":"11783",
    "sg:province":"NY",
    "sg:tags":[
        "burger",
        "american",
        "soup"
    ],
    "wof:name":"Wendy's",
    "wof:placetype":"venue"
},
  "geometry": {"coordinates":[-73.489632,40.674517],"type":"Point"}
}