{
  "type": "Feature",
  "properties": {
    "iso:country":"US",
    "sg:address":"123 Champlain Ave",
    "sg:city":"Ticonderoga",
    "sg:classifiers":[
        {
            "category":"Social Services",
            "type":"Services"
        }
    ],
    "sg:phone":"+1 518 585 6050",
    "sg:postcode":"12883",
    "sg:province":"NY",
    "sg:tags":[
        "senior",
        "citizen"
    ],
    "wof:name":"Ticonderoga Senior Ctr",
    "wof:placetype":"venue"
},
  "geometry": {"coordinates":[-73.42325700000001,43.848722],"type":"Point"}
}