{
  "type": "Feature",
  "properties": {
    "iso:country":"US",
    "sg:address":"95 Colebrook Rd",
    "sg:city":"Gansevoort",
    "sg:classifiers":[
        {
            "category":"Restaurant",
            "type":"Food & Drink"
        }
    ],
    "sg:phone":"+1 518 743 0874",
    "sg:postcode":"12831",
    "sg:province":"NY",
    "wof:name":"Wade Restaurants Inc",
    "wof:placetype":"venue"
},
  "geometry": {"coordinates":[-73.652181,43.13752],"type":"Point"}
}