{
  "type": "Feature",
  "properties": {
    "addr:full":"1676 54th St Brooklyn NY 11204",
    "addr:housenumber":"1676",
    "addr:postcode":"11204",
    "addr:street":"54Th St",
    "iso:country":"US",
    "sg:address":"1676 54th St",
    "sg:city":"Brooklyn",
    "sg:classifiers":[
        {
            "category":"Organizations",
            "subcategory":"Religious Organization",
            "type":"Services"
        }
    ],
    "sg:phone":"+1 718 871 1500",
    "sg:postcode":"11204",
    "sg:province":"NY",
    "sg:tags":[
        "clergy"
    ],
    "wof:name":"Mordecai Zimmerman",
    "wof:placetype":"venue"
},
  "geometry": {"coordinates":[-73.987461,40.627841],"type":"Point"}
}