{
  "type": "Feature",
  "properties": {
    "addr:full":"814 Butternut St Syracuse NY 13208",
    "addr:housenumber":"814",
    "addr:postcode":"13208",
    "addr:street":"Butternut St",
    "iso:country":"US",
    "sg:address":"814 Butternut St",
    "sg:city":"Syracuse",
    "sg:classifiers":[
        {
            "category":"Food & Beverages",
            "subcategory":"Groceries & Convenience Stores",
            "type":"Retail Goods"
        }
    ],
    "sg:phone":"+1 315 474 0721",
    "sg:postcode":"13208",
    "sg:province":"NY",
    "sg:tags":[
        "grocer"
    ],
    "wof:name":"Family Food Market",
    "wof:placetype":"venue"
},
  "geometry": {"coordinates":[-76.144625,43.06178],"type":"Point"}
}