{
  "type": "Feature",
  "properties": {
    "addr:full":"4526 Sunrise Hwy Oakdale NY 11769",
    "addr:housenumber":"4526",
    "addr:postcode":"11769",
    "addr:street":"Sunrise Hwy",
    "iso:country":"US",
    "sg:address":"4526 Sunrise Hwy",
    "sg:city":"Oakdale",
    "sg:classifiers":[
        {
            "category":"Food & Beverages",
            "subcategory":"Liquor & Beverages",
            "type":"Retail Goods"
        }
    ],
    "sg:phone":"+1   ",
    "sg:postcode":"11769",
    "sg:province":"NY",
    "sg:tags":[
        "alcoholic"
    ],
    "wof:name":"Slim & Harrys",
    "wof:placetype":"venue"
},
  "geometry": {"coordinates":[-73.117925,40.75363],"type":"Point"}
}