{
  "type": "Feature",
  "properties": {
    "iso:country":"US",
    "sg:address":"220 Grandview Ave",
    "sg:city":"Ithaca",
    "sg:classifiers":[
        {
            "category":"Organizations",
            "subcategory":"Religious Organization",
            "type":"Services"
        }
    ],
    "sg:phone":"+1 607 273 8953",
    "sg:postcode":"14850",
    "sg:province":"NY",
    "sg:tags":[
        "church"
    ],
    "sg:website":"www.southhillchurch.org",
    "wof:name":"South Hill Church-The Nazarene",
    "wof:placetype":"venue"
},
  "geometry": {"coordinates":[-76.493437,42.431196],"type":"Point"}
}