{
  "type": "Feature",
  "properties": {
    "addr:full":"3620 Abbott Rd Orchard Park NY 14127",
    "addr:housenumber":"3620",
    "addr:postcode":"14127",
    "addr:street":"Abbott Rd",
    "iso:country":"US",
    "sg:address":"3620 Abbott Rd",
    "sg:city":"Orchard Park",
    "sg:classifiers":[
        {
            "category":"Personal",
            "subcategory":"Beauty Salon",
            "type":"Services"
        }
    ],
    "sg:phone":"+1 716 826 6207",
    "sg:postcode":"14127",
    "sg:province":"NY",
    "wof:name":"Tip Top Beauty Shop",
    "wof:placetype":"venue"
},
  "geometry": {"coordinates":[-78.791549,42.78801],"type":"Point"}
}