{
  "type": "Feature",
  "properties": {
    "addr:full":"211 Hamilton Rd Fairport NY 14450",
    "addr:housenumber":"211",
    "addr:postcode":"14450",
    "addr:street":"Hamilton Rd",
    "iso:country":"US",
    "sg:address":"211 Hamilton Rd",
    "sg:city":"Fairport",
    "sg:classifiers":[
        {
            "category":"Education",
            "subcategory":"School",
            "type":"Public Place"
        }
    ],
    "sg:phone":"+1 585 421 2155",
    "sg:postcode":"14450",
    "sg:province":"NY",
    "sg:website":"www.fairport.org",
    "wof:name":"Dudley School",
    "wof:placetype":"venue"
},
  "geometry": {"coordinates":[-77.40727699999999,43.100559],"type":"Point"}
}