{
  "type": "Feature",
  "properties": {
    "iso:country":"US",
    "sg:address":"320 Herkimer Rd",
    "sg:city":"Utica",
    "sg:classifiers":[
        {
            "category":"Health Services",
            "subcategory":"Doctor",
            "type":"Services"
        }
    ],
    "sg:phone":"+1 315 724 0066",
    "sg:postcode":"13502",
    "sg:province":"NY",
    "sg:tags":[
        "medical"
    ],
    "wof:name":"Venkata R Mannava",
    "wof:placetype":"venue"
},
  "geometry": {"coordinates":[-75.204735,43.114437],"type":"Point"}
}