{
  "type": "Feature",
  "properties": {
    "addr:full":"75 Saxon Ave Bay Shore NY 11706",
    "addr:housenumber":"75",
    "addr:postcode":"11706",
    "addr:street":"Saxon Ave",
    "iso:country":"US",
    "sg:address":"75 Saxon Ave",
    "sg:city":"Bay Shore",
    "sg:classifiers":[
        {
            "category":"Retail",
            "subcategory":"Laundry & Dry Cleaning",
            "type":"Services"
        }
    ],
    "sg:phone":"+1 631 666 0141",
    "sg:postcode":"11706",
    "sg:province":"NY",
    "sg:tags":[
        "linen",
        "supply"
    ],
    "wof:name":"All American Linen Supply",
    "wof:placetype":"venue"
},
  "geometry": {"coordinates":[-73.228588,40.737303],"type":"Point"}
}