{
  "type": "Feature",
  "properties": {
    "iso:country":"US",
    "sg:address":"22 Main St",
    "sg:city":"Narrowsburg",
    "sg:classifiers":[
        {
            "category":"Home & Garden",
            "subcategory":"Furniture",
            "type":"Retail Goods"
        }
    ],
    "sg:phone":"+1 845 252 3253",
    "sg:postcode":"12764",
    "sg:province":"NY",
    "wof:name":"Tom's Treasures & Furniture",
    "wof:placetype":"venue"
},
  "geometry": {"coordinates":[-75.061266,41.608694],"type":"Point"}
}