{
  "type": "Feature",
  "properties": {
    "addr:full":"83 Rome St Farmingdale NY 11735",
    "addr:housenumber":"83",
    "addr:postcode":"11735",
    "addr:street":"Rome St",
    "iso:country":"US",
    "sg:address":"83 Rome St",
    "sg:city":"Farmingdale",
    "sg:classifiers":[
        {
            "category":"Manufacturing",
            "subcategory":"Paper Products",
            "type":"Manufacturing & Wholesale Goods"
        }
    ],
    "sg:phone":"+1 631 694 3325",
    "sg:postcode":"11735",
    "sg:province":"NY",
    "sg:tags":[
        "bag",
        "mfg",
        "coated",
        "plastic"
    ],
    "wof:name":"Mini Bag Corp",
    "wof:placetype":"venue"
},
  "geometry": {"coordinates":[-73.421441,40.712436],"type":"Point"}
}