{
  "type": "Feature",
  "properties": {
    "iso:country":"US",
    "sg:address":"201 S Main St",
    "sg:city":"Naples",
    "sg:classifiers":[
        {
            "category":"Food & Beverages",
            "subcategory":"Fruits & Vegetables",
            "type":"Retail Goods"
        }
    ],
    "sg:phone":"+1 585 374 5180",
    "sg:postcode":"14512",
    "sg:province":"NY",
    "sg:tags":[
        "produce"
    ],
    "wof:name":"Joseph's Wayside Market",
    "wof:placetype":"venue"
},
  "geometry": {"coordinates":[-77.408631,42.607458],"type":"Point"}
}