{
  "type": "Feature",
  "properties": {
    "addr:full":"4615 14th Ave Brooklyn NY 11219",
    "addr:housenumber":"4615",
    "addr:postcode":"11219",
    "addr:street":"14Th Ave",
    "iso:country":"US",
    "sg:address":"4615 14th Ave",
    "sg:city":"Brooklyn",
    "sg:classifiers":[
        {
            "category":"Professional",
            "type":"Services"
        }
    ],
    "sg:phone":"+1 718 972 7348",
    "sg:postcode":"11219",
    "sg:province":"NY",
    "sg:tags":[
        "establishment"
    ],
    "wof:name":"Yoshiva Ohr Torah",
    "wof:placetype":"venue"
},
  "geometry": {"coordinates":[-73.988629,40.634849],"type":"Point"}
}