{
  "type": "Feature",
  "properties": {
    "addr:full":"640 Old Country Rd Riverhead NY 11901",
    "addr:housenumber":"640",
    "addr:postcode":"11901",
    "addr:street":"Old Country Rd",
    "iso:country":"US",
    "sg:address":"640 Old Country Rd",
    "sg:city":"Riverhead",
    "sg:classifiers":[
        {
            "category":"Autos & Motor Vehicles",
            "subcategory":"Fuel & Gas Station",
            "type":"Retail Goods"
        }
    ],
    "sg:phone":"+1 631 369 9240",
    "sg:postcode":"11901",
    "sg:province":"NY",
    "wof:name":"Empire Service Station",
    "wof:placetype":"venue"
},
  "geometry": {"coordinates":[-72.66950199999999,40.934299],"type":"Point"}
}