{
  "type": "Feature",
  "properties": {
    "iso:country":"US",
    "sg:address":"202 Ford St B",
    "sg:city":"Boonville",
    "sg:classifiers":[
        {
            "category":"Retail",
            "subcategory":"Auto Repair",
            "type":"Services"
        }
    ],
    "sg:phone":"+1 315 942 3381",
    "sg:postcode":"13309",
    "sg:province":"NY",
    "sg:tags":[
        "body",
        "automobile",
        "painting",
        "repairing"
    ],
    "wof:name":"Zeigler Collision",
    "wof:placetype":"venue"
},
  "geometry": {"coordinates":[-75.342134,43.481681],"type":"Point"}
}