{
  "type": "Feature",
  "properties": {
    "addr:full":"1643 Lexington Avenue New York NY 10029",
    "addr:housenumber":"1643",
    "addr:postcode":"10029",
    "addr:street":"Lexington Avenue",
    "iso:country":"US",
    "sg:address":"1643 Lexington Avenue",
    "sg:city":"New York",
    "sg:classifiers":[
        {
            "category":"Restaurant",
            "type":"Food & Drink"
        }
    ],
    "sg:phone":"+1 212 860 4904",
    "sg:postcode":"10029",
    "sg:province":"NY",
    "wof:name":"Pablo Mexico Restaurant",
    "wof:placetype":"venue"
},
  "geometry": {"coordinates":[-73.947519,40.790781],"type":"Point"}
}