{
  "type": "Feature",
  "properties": {
    "addr:full":"5-53 48th ave Long Island City NY 11101",
    "addr:housenumber":"5-53",
    "addr:postcode":"11101",
    "addr:street":"48Th Ave",
    "iso:country":"US",
    "sg:address":"5-53 48th ave",
    "sg:city":"Long Island City",
    "sg:classifiers":[
        {
            "category":"Real Estate",
            "subcategory":"Real Estate Services",
            "type":"Services"
        }
    ],
    "sg:phone":"+1 347 560 4005",
    "sg:postcode":"11101",
    "sg:province":"NY",
    "wof:name":"Royalton Realty LIC",
    "wof:placetype":"venue"
},
  "geometry": {"coordinates":[-73.954139,40.744231],"type":"Point"}
}