{
  "type": "Feature",
  "properties": {
    "addr:full":"360 E 65 St New York NY 10065",
    "addr:housenumber":"360;65",
    "addr:postcode":"10065",
    "addr:street":"E;St",
    "iso:country":"US",
    "sg:address":"360 E 65 St",
    "sg:city":"New York",
    "sg:classifiers":[
        {
            "category":"Professional",
            "type":"Services"
        }
    ],
    "sg:phone":"+1 212 628 3901",
    "sg:postcode":"10065",
    "sg:province":"NY",
    "sg:tags":[
        "establishment"
    ],
    "wof:name":"CYBERXPO.COM",
    "wof:placetype":"venue"
},
  "geometry": {"coordinates":[-73.960374,40.763913],"type":"Point"}
}