{
  "type": "Feature",
  "properties": {
    "iso:country":"US",
    "sg:address":"3616 Merrick Rd",
    "sg:city":"Seaford",
    "sg:classifiers":[
        {
            "category":"Shopping",
            "type":"Retail Goods"
        },
        {
            "category":"Shopping",
            "subcategory":"Optical Goods",
            "type":"Retail Goods"
        }
    ],
    "sg:phone":"+1 516 679 0768",
    "sg:postcode":"11783",
    "sg:province":"NY",
    "sg:tags":[
        "optician",
        "merchandise"
    ],
    "wof:name":"South Shore Lens & Frames Ltd",
    "wof:placetype":"venue"
},
  "geometry": {"coordinates":[-73.498609,40.665055],"type":"Point"}
}