{
  "type": "Feature",
  "properties": {
    "addr:full":"181 Franklin St Brooklyn NY 11222",
    "addr:housenumber":"181",
    "addr:postcode":"11222",
    "addr:street":"Franklin St",
    "iso:country":"US",
    "sg:address":"181 Franklin St",
    "sg:city":"Brooklyn",
    "sg:classifiers":[
        {
            "category":"Shopping",
            "subcategory":"Music",
            "type":"Retail Goods"
        },
        {
            "category":"Recreation",
            "subcategory":"Dance Hall",
            "type":"Entertainment"
        }
    ],
    "sg:phone":"+1 718 383 4083",
    "sg:postcode":"11222",
    "sg:province":"NY",
    "sg:tags":[
        "club",
        "dvd's"
    ],
    "sg:website":"www.permanentrecords.info",
    "wof:name":"Permanent Records",
    "wof:placetype":"venue"
},
  "geometry": {"coordinates":[-73.95807600000001,40.732849],"type":"Point"}
}