{
  "type": "Feature",
  "properties": {
    "addr:full":"34 E Cortwood Rd Orangeburg NY 10962",
    "addr:housenumber":"34",
    "addr:postcode":"10962",
    "addr:street":"E Cortwood Rd",
    "iso:country":"US",
    "sg:address":"34 E Cortwood Rd",
    "sg:city":"Orangeburg",
    "sg:classifiers":[
        {
            "category":"Real Estate",
            "subcategory":"Real Estate Agent",
            "type":"Services"
        }
    ],
    "sg:phone":"+1 845 359 2690",
    "sg:postcode":"10962",
    "sg:province":"NY",
    "sg:tags":[
        "authorities",
        "housing"
    ],
    "wof:name":"Orangetown Housing Authority",
    "wof:placetype":"venue"
},
  "geometry": {"coordinates":[-73.95251500000001,41.041626],"type":"Point"}
}