{
  "type": "Feature",
  "properties": {
    "addr:full":"503 Village Blvd S Baldwinsville NY 13027",
    "addr:housenumber":"503",
    "addr:postcode":"13027",
    "addr:street":"Village Blvd S Baldwinsville",
    "iso:country":"US",
    "sg:address":"503 Village Blvd S",
    "sg:city":"Baldwinsville",
    "sg:classifiers":[
        {
            "category":"Banks & Credit Unions",
            "subcategory":"Bank",
            "type":"Services"
        }
    ],
    "sg:phone":"+1 315 638 7746",
    "sg:postcode":"13027",
    "sg:province":"NY",
    "sg:tags":[
        "financing"
    ],
    "wof:name":"Niccoli Funding Inc",
    "wof:placetype":"venue"
},
  "geometry": {"coordinates":[-76.313018,43.13108],"type":"Point"}
}