{
  "type": "Feature",
  "properties": {
    "addr:full":"5 Nassau Blvd S Garden City NY 11530",
    "addr:housenumber":"5",
    "addr:postcode":"11530",
    "addr:street":"Nassau Blvd S",
    "iso:country":"US",
    "sg:address":"5 Nassau Blvd S",
    "sg:city":"Garden City",
    "sg:classifiers":[
        {
            "category":"Health Services",
            "subcategory":"Health Practitioner",
            "type":"Services"
        }
    ],
    "sg:phone":"+1   ",
    "sg:postcode":"11530",
    "sg:province":"NY",
    "wof:name":"Andrea Acupuncture Gurciullo",
    "wof:placetype":"venue"
},
  "geometry": {"coordinates":[-73.66096400000001,40.712554],"type":"Point"}
}