{
  "type": "Feature",
  "properties": {
    "iso:country":"US",
    "sg:address":"14 Ramsey Rd",
    "sg:city":"Shirley",
    "sg:classifiers":[
        {
            "category":"Communications",
            "subcategory":"Newspaper",
            "type":"Services"
        }
    ],
    "sg:phone":"+1 631 345 3218",
    "sg:postcode":"11967",
    "sg:province":"NY",
    "sg:tags":[
        "print",
        "medium"
    ],
    "wof:name":"Fisherman the",
    "wof:placetype":"venue"
},
  "geometry": {"coordinates":[-72.887199,40.8405],"type":"Point"}
}