{
  "type": "Feature",
  "properties": {
    "addr:full":"1305 Nott St Schenectady NY 12308",
    "addr:housenumber":"1305",
    "addr:postcode":"12308",
    "addr:street":"Nott St",
    "iso:country":"US",
    "sg:address":"1305 Nott St",
    "sg:city":"Schenectady",
    "sg:classifiers":[
        {
            "category":"Wholesale",
            "subcategory":"Medical Equipment & Supplies",
            "type":"Manufacturing & Wholesale Goods"
        }
    ],
    "sg:phone":"+1 518 631 0024",
    "sg:postcode":"12308",
    "sg:province":"NY",
    "sg:tags":[
        "hospital"
    ],
    "wof:name":"Ortho Medical Products Inc",
    "wof:placetype":"venue"
},
  "geometry": {"coordinates":[-73.913239,42.818528],"type":"Point"}
}