{
  "type": "Feature",
  "properties": {
    "iso:country":"US",
    "sg:address":"11449 Sutphin Blvd",
    "sg:city":"Jamaica",
    "sg:classifiers":[
        {
            "category":"Shopping",
            "subcategory":"Pharmacy",
            "type":"Retail Goods"
        }
    ],
    "sg:phone":"+1 718 848 4900",
    "sg:postcode":"11434",
    "sg:province":"NY",
    "sg:tags":[
        "drugstore"
    ],
    "wof:name":"Apex Pharmacy",
    "wof:placetype":"venue"
},
  "geometry": {"coordinates":[-73.792967,40.685365],"type":"Point"}
}