{
  "type": "Feature",
  "properties": {
    "iso:country":"US",
    "sg:address":"163 Malcolm X Blvd",
    "sg:city":"New York",
    "sg:classifiers":[
        {
            "category":"Personal",
            "subcategory":"Barber",
            "type":"Services"
        }
    ],
    "sg:phone":"+1 212 222 2063",
    "sg:postcode":"10026",
    "sg:province":"NY",
    "wof:name":"Olga Barber Shop",
    "wof:placetype":"venue"
},
  "geometry": {"coordinates":[-73.948898,40.803398],"type":"Point"}
}