{
  "type": "Feature",
  "properties": {
    "addr:full":"90 Hoover St Blauvelt NY 10913",
    "addr:housenumber":"90",
    "addr:postcode":"10913",
    "addr:street":"Hoover St",
    "iso:country":"US",
    "sg:address":"90 Hoover St",
    "sg:city":"Blauvelt",
    "sg:classifiers":[
        {
            "category":"Real Estate",
            "subcategory":"Real Estate Agent",
            "type":"Services"
        }
    ],
    "sg:phone":"+1 845 359 5950",
    "sg:postcode":"10913",
    "sg:province":"NY",
    "wof:name":"Fornario Realty",
    "wof:placetype":"venue"
},
  "geometry": {"coordinates":[-73.977458,41.062017],"type":"Point"}
}