{
  "type": "Feature",
  "properties": {
    "addr:full":"784 Columbus Ave New York NY 10025",
    "addr:housenumber":"784",
    "addr:postcode":"10025",
    "addr:street":"Columbus Ave",
    "iso:country":"US",
    "sg:address":"784 Columbus Ave",
    "sg:city":"New York",
    "sg:classifiers":[
        {
            "category":"Building & Trades",
            "subcategory":"Construction",
            "type":"Services"
        }
    ],
    "sg:phone":"+1 212 280 2095",
    "sg:postcode":"10025",
    "sg:province":"NY",
    "sg:tags":[
        "contractor"
    ],
    "wof:name":"P W V Gc Inc",
    "wof:placetype":"venue"
},
  "geometry": {"coordinates":[-73.966527,40.794485],"type":"Point"}
}