{
  "type": "Feature",
  "properties": {
    "addr:full":"253 Ouaquaga Rd Binghamton NY 13904",
    "addr:housenumber":"253",
    "addr:postcode":"13904",
    "addr:street":"Ouaquaga Rd",
    "iso:country":"US",
    "sg:address":"253 Ouaquaga Rd",
    "sg:city":"Binghamton",
    "sg:classifiers":[
        {
            "category":"Building & Trades",
            "subcategory":"Plumbing",
            "type":"Services"
        }
    ],
    "sg:phone":"+1 607 693 2581",
    "sg:postcode":"13904",
    "sg:province":"NY",
    "sg:tags":[
        "contractor"
    ],
    "wof:name":"Grosvenor Construction",
    "wof:placetype":"venue"
},
  "geometry": {"coordinates":[-75.700523,42.134321],"type":"Point"}
}