{
  "type": "Feature",
  "properties": {
    "addr:full":"8 Peregrine Way Webster NY 14580",
    "addr:housenumber":"8",
    "addr:postcode":"14580",
    "addr:street":"Peregrine Way",
    "iso:country":"US",
    "sg:address":"8 Peregrine Way",
    "sg:city":"Webster",
    "sg:classifiers":[
        {
            "category":"Shopping",
            "subcategory":"Gifts & Souvenirs",
            "type":"Retail Goods"
        }
    ],
    "sg:phone":"+1 585 872 4375",
    "sg:postcode":"14580",
    "sg:province":"NY",
    "sg:tags":[
        "shop"
    ],
    "wof:name":"Fitzy's Custom Gifts",
    "wof:placetype":"venue"
},
  "geometry": {"coordinates":[-77.44518600000001,43.191088],"type":"Point"}
}