{
  "type": "Feature",
  "properties": {
    "iso:country":"US",
    "sg:address":"8 Stockbridge Rd",
    "sg:city":"Mount Kisco",
    "sg:classifiers":[
        {
            "category":"Shopping",
            "subcategory":"Pharmacy",
            "type":"Retail Goods"
        }
    ],
    "sg:phone":"+1   ",
    "sg:postcode":"10549",
    "sg:province":"NY",
    "wof:name":"Hull 2",
    "wof:placetype":"venue"
},
  "geometry": {"coordinates":[-73.748425,41.188295],"type":"Point"}
}