{
  "type": "Feature",
  "properties": {
    "addr:full":"6 Sussex Rd Elmont NY 11003",
    "addr:housenumber":"6",
    "addr:postcode":"11003",
    "addr:street":"Sussex Rd",
    "iso:country":"US",
    "sg:address":"6 Sussex Rd",
    "sg:city":"Elmont",
    "sg:classifiers":[
        {
            "category":"Wholesale",
            "subcategory":"Motor Vehicles",
            "type":"Manufacturing & Wholesale Goods"
        }
    ],
    "sg:phone":"+1 212 657 0307",
    "sg:postcode":"11003",
    "sg:province":"NY",
    "sg:tags":[
        "recreational",
        "campers-wholesale",
        "manufacturer"
    ],
    "wof:name":"Nashel Enterprises",
    "wof:placetype":"venue"
},
  "geometry": {"coordinates":[-73.72065000000001,40.708688],"type":"Point"}
}