{
  "type": "Feature",
  "properties": {
    "addr:full":"2334 Hughes Ave Bronx NY 10458",
    "addr:housenumber":"2334",
    "addr:postcode":"10458",
    "addr:street":"Hughes Ave",
    "iso:country":"US",
    "sg:address":"2334 Hughes Ave",
    "sg:city":"Bronx",
    "sg:classifiers":[
        {
            "category":"Retail",
            "subcategory":"Auto Repair",
            "type":"Services"
        }
    ],
    "sg:phone":"+1 718 563 3370",
    "sg:postcode":"10458",
    "sg:province":"NY",
    "sg:tags":[
        "truck"
    ],
    "wof:name":"Super Dave's Road Svc",
    "wof:placetype":"venue"
},
  "geometry": {"coordinates":[-73.88757699999999,40.854204],"type":"Point"}
}