{
  "type": "Feature",
  "properties": {
    "iso:country":"US",
    "sg:address":"17 Sage Ct",
    "sg:city":"Huntington Station",
    "sg:classifiers":[
        {
            "category":"Real Estate",
            "subcategory":"Developer",
            "type":"Services"
        },
        {
            "category":"Professional",
            "type":"Services"
        }
    ],
    "sg:phone":"+1 631 673 3649",
    "sg:postcode":"11746",
    "sg:province":"NY",
    "sg:tags":[
        "development",
        "establishment"
    ],
    "wof:name":"Tribeca Broadway Assoc LLC",
    "wof:placetype":"venue"
},
  "geometry": {"coordinates":[-73.420451,40.851428],"type":"Point"}
}