{
  "type": "Feature",
  "properties": {
    "addr:full":"246 Long Beach Rd Island Park NY 11558",
    "addr:housenumber":"246",
    "addr:postcode":"11558",
    "addr:street":"Long Beach Rd",
    "iso:country":"US",
    "sg:address":"246 Long Beach Rd",
    "sg:city":"Island Park",
    "sg:classifiers":[
        {
            "category":"Health Services",
            "subcategory":"Doctor",
            "type":"Services"
        }
    ],
    "sg:phone":"+1 516 431 3814",
    "sg:postcode":"11558",
    "sg:province":"NY",
    "sg:tags":[
        "clinic"
    ],
    "wof:name":"Ambulatory Medical Svc",
    "wof:placetype":"venue"
},
  "geometry": {"coordinates":[-73.655568,40.605287],"type":"Point"}
}