{
  "type": "Feature",
  "properties": {
    "addr:full":"80 Niagara St Tonawanda NY 14150",
    "addr:housenumber":"80",
    "addr:postcode":"14150",
    "addr:street":"Niagara St",
    "iso:country":"US",
    "sg:address":"80 Niagara St",
    "sg:city":"Tonawanda",
    "sg:classifiers":[
        {
            "category":"Personal",
            "subcategory":"Beauty Salon",
            "type":"Services"
        }
    ],
    "sg:phone":"+1 716 743 0362",
    "sg:postcode":"14150",
    "sg:province":"NY",
    "sg:tags":[
        "shop"
    ],
    "wof:name":"Supercuts",
    "wof:placetype":"venue"
},
  "geometry": {"coordinates":[-78.881473,43.020223],"type":"Point"}
}