{
  "type": "Feature",
  "properties": {
    "iso:country":"US",
    "sg:address":"132 Country Club Ln",
    "sg:city":"Pomona",
    "sg:classifiers":[
        {
            "category":"Retail",
            "subcategory":"Laundry & Dry Cleaning",
            "type":"Services"
        }
    ],
    "sg:phone":"+1 845 354 3668",
    "sg:postcode":"10970",
    "sg:province":"NY",
    "sg:tags":[
        "cleaner",
        "rug",
        "carpet"
    ],
    "wof:name":"Paul R Carroll Electro-Clean",
    "wof:placetype":"venue"
},
  "geometry": {"coordinates":[-74.030877,41.19199],"type":"Point"}
}