{
  "type": "Feature",
  "properties": {
    "addr:full":"31 30th Ave Astoria NY 11102",
    "addr:housenumber":"31",
    "addr:postcode":"11102",
    "addr:street":"30Th Ave",
    "iso:country":"US",
    "sg:address":"31 30th Ave",
    "sg:city":"Astoria",
    "sg:classifiers":[
        {
            "category":"Shopping",
            "subcategory":"Discount & Variety Stores",
            "type":"Retail Goods"
        }
    ],
    "sg:phone":"+1   ",
    "sg:postcode":"11102",
    "sg:province":"NY",
    "wof:name":"Exclusive Discount Variety",
    "wof:placetype":"venue"
},
  "geometry": {"coordinates":[-73.921391,40.766894],"type":"Point"}
}