{
  "type": "Feature",
  "properties": {
    "iso:country":"US",
    "sg:address":"3173 Richmond Road",
    "sg:city":"Staten Island",
    "sg:classifiers":[
        {
            "category":"Health Services",
            "subcategory":"Health Practitioner",
            "type":"Services"
        },
        {
            "category":"Insurance",
            "subcategory":"Health Insurance",
            "type":"Services"
        }
    ],
    "sg:phone":"+1 718 351 4443",
    "sg:postcode":"10306",
    "sg:province":"NY",
    "sg:tags":[
        "nutritionist",
        "market"
    ],
    "wof:name":"A Changes",
    "wof:placetype":"venue"
},
  "geometry": {"coordinates":[-74.127072,40.576395],"type":"Point"}
}