{
  "type": "Feature",
  "properties": {
    "addr:full":"2417 Pine Ave Niagara Falls NY 14301",
    "addr:housenumber":"2417",
    "addr:postcode":"14301",
    "addr:street":"Pine Ave",
    "iso:country":"US",
    "sg:address":"2417 Pine Ave",
    "sg:city":"Niagara Falls",
    "sg:classifiers":[
        {
            "category":"Autos & Motor Vehicles",
            "subcategory":"Fuel & Gas Station",
            "type":"Retail Goods"
        }
    ],
    "sg:phone":"+1 716 282 1832",
    "sg:postcode":"14301",
    "sg:province":"NY",
    "sg:tags":[
        "oil"
    ],
    "wof:name":"Nick's Sunoco",
    "wof:placetype":"venue"
},
  "geometry": {"coordinates":[-79.032709,43.09504],"type":"Point"}
}