{
  "type": "Feature",
  "properties": {
    "addr:full":"1407 2nd Ave New York NY 10021",
    "addr:housenumber":"1407",
    "addr:postcode":"10021",
    "addr:street":"2Nd Ave",
    "iso:country":"US",
    "sg:address":"1407 2nd Ave",
    "sg:city":"New York",
    "sg:classifiers":[
        {
            "category":"Restaurant",
            "type":"Food & Drink"
        }
    ],
    "sg:phone":"+1 212 535 1100",
    "sg:postcode":"10021",
    "sg:province":"NY",
    "sg:tags":[
        "middle",
        "persian/iranian",
        "eastern"
    ],
    "sg:website":"www.persepolisnyc.com",
    "wof:name":"Persepolis",
    "wof:placetype":"venue"
},
  "geometry": {"coordinates":[-73.957679,40.769715],"type":"Point"}
}