{
  "type": "Feature",
  "properties": {
    "addr:full":"110 E 87 St New York NY 10128",
    "addr:housenumber":"110;87",
    "addr:postcode":"10128",
    "addr:street":"E;St",
    "iso:country":"US",
    "sg:address":"110 E 87 St",
    "sg:city":"New York",
    "sg:classifiers":[
        {
            "category":"Health Services",
            "subcategory":"Doctor",
            "type":"Services"
        }
    ],
    "sg:phone":"+1 212 369 2213",
    "sg:postcode":"10128",
    "sg:province":"NY",
    "sg:tags":[
        "dentist"
    ],
    "wof:name":"Margot Jaffe DDS",
    "wof:placetype":"venue"
},
  "geometry": {"coordinates":[-73.95540699999999,40.780262],"type":"Point"}
}