{
  "type": "Feature",
  "properties": {
    "addr:full":"71 Creek Run Rd Newburgh NY 12550",
    "addr:housenumber":"71",
    "addr:postcode":"12550",
    "addr:street":"Creek Run Rd",
    "iso:country":"US",
    "sg:address":"71 Creek Run Rd",
    "sg:city":"Newburgh",
    "sg:classifiers":[
        {
            "category":"Restaurant",
            "type":"Food & Drink"
        }
    ],
    "sg:phone":"+1   ",
    "sg:postcode":"12550",
    "sg:province":"NY",
    "sg:tags":[
        "eating"
    ],
    "wof:name":"Giuseppes Pizzeria Inc",
    "wof:placetype":"venue"
},
  "geometry": {"coordinates":[-74.036733,41.52188],"type":"Point"}
}