{
  "type": "Feature",
  "properties": {
    "addr:full":"2215 S Geddes St Syracuse NY 13207",
    "addr:housenumber":"2215",
    "addr:postcode":"13207",
    "addr:street":"S Geddes St",
    "iso:country":"US",
    "sg:address":"2215 S Geddes St",
    "sg:city":"Syracuse",
    "sg:classifiers":[
        {
            "category":"Organizations",
            "subcategory":"Community Association",
            "type":"Services"
        }
    ],
    "sg:phone":"+1   ",
    "sg:postcode":"13207",
    "sg:province":"NY",
    "sg:tags":[
        "membership"
    ],
    "wof:name":"Greater Strathmore Neighbor",
    "wof:placetype":"venue"
},
  "geometry": {"coordinates":[-76.173929,43.019857],"type":"Point"}
}