{
  "type": "Feature",
  "properties": {
    "addr:full":"67 W Main St Honeoye Falls NY 14472",
    "addr:housenumber":"67",
    "addr:postcode":"14472",
    "addr:street":"W Main St",
    "iso:country":"US",
    "sg:address":"67 W Main St",
    "sg:city":"Honeoye Falls",
    "sg:classifiers":[
        {
            "category":"Health Services",
            "subcategory":"Doctor",
            "type":"Services"
        }
    ],
    "sg:phone":"+1 585 624 2910",
    "sg:postcode":"14472",
    "sg:province":"NY",
    "sg:tags":[
        "dentist"
    ],
    "wof:name":"Honeoye Falls Dental",
    "wof:placetype":"venue"
},
  "geometry": {"coordinates":[-77.593676,42.951699],"type":"Point"}
}