{
  "type": "Feature",
  "properties": {
    "iso:country":"US",
    "sg:address":"8003 Barnum Rd",
    "sg:city":"Cassadaga",
    "sg:phone":"+1 716 595 3905",
    "sg:postcode":"14718",
    "sg:province":"NY",
    "sg:tags":[
        "farm",
        "field",
        "crop"
    ],
    "wof:name":"Kotar John",
    "wof:placetype":"venue"
},
  "geometry": {"coordinates":[-79.295733,42.349311],"type":"Point"}
}