{
  "type": "Feature",
  "properties": {
    "iso:country":"US",
    "sg:address":"24 Swan St",
    "sg:city":"Amsterdam",
    "sg:classifiers":[
        {
            "category":"Retail",
            "subcategory":"Auto Repair",
            "type":"Services"
        }
    ],
    "sg:phone":"+1 518 842 3206",
    "sg:postcode":"12010",
    "sg:province":"NY",
    "sg:tags":[
        "automotive",
        "wrecker"
    ],
    "wof:name":"Angel's Towing & Recovery",
    "wof:placetype":"venue"
},
  "geometry": {"coordinates":[-74.183545,42.930401],"type":"Point"}
}