{
  "type": "Feature",
  "properties": {
    "iso:country":"US",
    "sg:address":"29 Jones Ave",
    "sg:city":"Chatham",
    "sg:classifiers":[
        {
            "category":"Health Services",
            "subcategory":"Doctor",
            "type":"Services"
        }
    ],
    "sg:phone":"+1 518 392 7816",
    "sg:postcode":"12037",
    "sg:province":"NY",
    "sg:tags":[
        "psychiatry",
        "physician",
        "surgeon",
        "surgeons"
    ],
    "wof:name":"Theodore J Sabot Md",
    "wof:placetype":"venue"
},
  "geometry": {"coordinates":[-73.589703,42.362779],"type":"Point"}
}