{
  "type": "Feature",
  "properties": {
    "iso:country":"US",
    "sg:address":"6 Jodi Ct",
    "sg:city":"Glen Cove",
    "sg:classifiers":[
        {
            "category":"Health Services",
            "subcategory":"Health Practitioner",
            "type":"Services"
        }
    ],
    "sg:phone":"+1 516 674 8361",
    "sg:postcode":"11542",
    "sg:province":"NY",
    "sg:tags":[
        "dietitian"
    ],
    "wof:name":"Susan Phillips",
    "wof:placetype":"venue"
},
  "geometry": {"coordinates":[-73.64048699999999,40.876738],"type":"Point"}
}