{
  "type": "Feature",
  "properties": {
    "iso:country":"US",
    "sg:address":"26 Wooster Street",
    "sg:city":"New York",
    "sg:classifiers":[
        {
            "category":"Arts & Performance",
            "subcategory":"Art Gallery",
            "type":"Entertainment"
        }
    ],
    "sg:phone":"+1 212 431 2609",
    "sg:postcode":"10013",
    "sg:province":"NY",
    "sg:website":"www.leslielohman.com",
    "wof:name":"The Leslie Lohman Gay Art Foundation",
    "wof:placetype":"venue"
},
  "geometry": {"coordinates":[-74.00322,40.721464],"type":"Point"}
}