{
  "type": "Feature",
  "properties": {
    "addr:full":"1100 Jefferson Rd Rochester NY 14623",
    "addr:housenumber":"1100",
    "addr:postcode":"14623",
    "addr:street":"Jefferson Rd",
    "iso:country":"US",
    "sg:address":"1100 Jefferson Rd",
    "sg:city":"Rochester",
    "sg:classifiers":[
        {
            "category":"Restaurant",
            "type":"Food & Drink"
        }
    ],
    "sg:menulink":"http://www.allmenus.com/ny/henrietta/169915-burger-king/menu/",
    "sg:phone":"+1 585 424 5552",
    "sg:postcode":"14623",
    "sg:province":"NY",
    "sg:tags":[
        "burger",
        "american"
    ],
    "wof:name":"Burger King",
    "wof:placetype":"venue"
},
  "geometry": {"coordinates":[-77.608098,43.088653],"type":"Point"}
}