{
  "type": "Feature",
  "properties": {
    "addr:full":"8 Marbledale Rd Tuckahoe NY 10707",
    "addr:housenumber":"8",
    "addr:postcode":"10707",
    "addr:street":"Marbledale Rd",
    "iso:country":"US",
    "sg:address":"8 Marbledale Rd",
    "sg:city":"Tuckahoe",
    "sg:classifiers":[
        {
            "category":"Autos & Motor Vehicles",
            "subcategory":"Fuel & Gas Station",
            "type":"Retail Goods"
        }
    ],
    "sg:phone":"+1   ",
    "sg:postcode":"10707",
    "sg:province":"NY",
    "sg:tags":[
        "car",
        "gasoline",
        "wash"
    ],
    "wof:name":"Tuckahoe Car Wash",
    "wof:placetype":"venue"
},
  "geometry": {"coordinates":[-73.82162,40.949869],"type":"Point"}
}