{
  "type": "Feature",
  "properties": {
    "addr:full":"427 New Karner Rd Albany NY 12205",
    "addr:housenumber":"427",
    "addr:postcode":"12205",
    "addr:street":"New Karner Rd",
    "iso:country":"US",
    "sg:address":"427 New Karner Rd",
    "sg:city":"Albany",
    "sg:classifiers":[
        {
            "category":"Banks & Credit Unions",
            "subcategory":"Financial Services",
            "type":"Services"
        }
    ],
    "sg:phone":"+1 518 218 0361",
    "sg:postcode":"12205",
    "sg:province":"NY",
    "sg:tags":[
        "investment",
        "closed"
    ],
    "wof:name":"ARC Investment Planning &",
    "wof:placetype":"venue"
},
  "geometry": {"coordinates":[-73.84559299999999,42.736651],"type":"Point"}
}