{
  "type": "Feature",
  "properties": {
    "iso:country":"US",
    "sg:address":"2313 7th Ave",
    "sg:city":"New York",
    "sg:classifiers":[
        {
            "category":"Organizations",
            "subcategory":"Labor Organization",
            "type":"Services"
        }
    ],
    "sg:phone":"+1   ",
    "sg:postcode":"10030",
    "sg:province":"NY",
    "wof:name":"Brotherhood of Security",
    "wof:placetype":"venue"
},
  "geometry": {"coordinates":[-73.94339100000001,40.815493],"type":"Point"}
}