{
  "type": "Feature",
  "properties": {
    "addr:full":"40 Oneida St Oneonta NY 13820",
    "addr:housenumber":"40",
    "addr:postcode":"13820",
    "addr:street":"Oneida St",
    "iso:country":"US",
    "sg:address":"40 Oneida St",
    "sg:city":"Oneonta",
    "sg:classifiers":[
        {
            "category":"Retail",
            "subcategory":"Auto Repair",
            "type":"Services"
        }
    ],
    "sg:phone":"+1 607 432 2695",
    "sg:postcode":"13820",
    "sg:province":"NY",
    "sg:tags":[
        "repairing",
        "automobile"
    ],
    "wof:name":"Morris Garage",
    "wof:placetype":"venue"
},
  "geometry": {"coordinates":[-75.09898099999999,42.45314],"type":"Point"}
}