{
  "type": "Feature",
  "properties": {
    "iso:country":"US",
    "sg:address":"901 Carmans Rd",
    "sg:city":"Massapequa",
    "sg:classifiers":[
        {
            "category":"Shopping",
            "subcategory":"Pharmacy",
            "type":"Retail Goods"
        }
    ],
    "sg:phone":"+1 516 795 4700",
    "sg:postcode":"11758",
    "sg:province":"NY",
    "wof:name":"Duane Reade",
    "wof:placetype":"venue"
},
  "geometry": {"coordinates":[-73.43289799999999,40.697427],"type":"Point"}
}