{
  "type": "Feature",
  "properties": {
    "addr:full":"575 5th Ave New York NY 10017",
    "addr:housenumber":"575",
    "addr:postcode":"10017",
    "addr:street":"5Th Ave",
    "iso:country":"US",
    "sg:address":"575 5th Ave",
    "sg:city":"New York",
    "sg:classifiers":[
        {
            "category":"Shopping",
            "subcategory":"Gifts & Souvenirs",
            "type":"Retail Goods"
        }
    ],
    "sg:phone":"+1   ",
    "sg:postcode":"10017",
    "sg:province":"NY",
    "sg:tags":[
        "ready",
        "b",
        "clothing"
    ],
    "wof:name":"Barneys",
    "wof:placetype":"venue"
},
  "geometry": {"coordinates":[-73.978543,40.75654],"type":"Point"}
}