{
  "type": "Feature",
  "properties": {
    "iso:country":"US",
    "sg:address":"3165 Richmond Ter",
    "sg:city":"Staten Island",
    "sg:classifiers":[
        {
            "category":"Manufacturing",
            "subcategory":"Watercraft",
            "type":"Manufacturing & Wholesale Goods"
        }
    ],
    "sg:phone":"+1 718 273 6300",
    "sg:postcode":"10303",
    "sg:province":"NY",
    "sg:tags":[
        "builder",
        "ship",
        "repairer"
    ],
    "wof:name":"Mc Allister Towing & Transport",
    "wof:placetype":"venue"
},
  "geometry": {"coordinates":[-74.16524099999999,40.639979],"type":"Point"}
}