{
  "type": "Feature",
  "properties": {
    "addr:full":"2570 E 17th St Brooklyn NY 11235",
    "addr:housenumber":"2570",
    "addr:postcode":"11235",
    "addr:street":"E 17Th St",
    "iso:country":"US",
    "sg:address":"2570 E 17th St",
    "sg:city":"Brooklyn",
    "sg:classifiers":[
        {
            "category":"Professional",
            "subcategory":"Management & Consulting",
            "type":"Services"
        },
        {
            "category":"Education",
            "subcategory":"Special Training",
            "type":"Public Place"
        },
        {
            "category":"Education",
            "subcategory":"Library",
            "type":"Public Place"
        }
    ],
    "sg:phone":"+1 718 368 3613",
    "sg:postcode":"11235",
    "sg:province":"NY",
    "sg:tags":[
        "educational",
        "consultant",
        "instruction",
        "system",
        "improvement",
        "preparation",
        "equipment",
        "adult",
        "test",
        "reading",
        "tutoring"
    ],
    "sg:website":"http://www.sylvanlearningcenter.com",
    "wof:name":"Sylvan Learning Center",
    "wof:placetype":"venue"
},
  "geometry": {"coordinates":[-73.952575,40.588775],"type":"Point"}
}