{
  "type": "Feature",
  "properties": {
    "addr:full":"260 N Little Tor Rd New City NY 10956",
    "addr:housenumber":"260",
    "addr:postcode":"10956",
    "addr:street":"N Little Tor Rd",
    "iso:country":"US",
    "sg:address":"260 N Little Tor Rd",
    "sg:city":"New City",
    "sg:classifiers":[
        {
            "category":"Health Services",
            "subcategory":"Clinic",
            "type":"Services"
        }
    ],
    "sg:phone":"+1 845 634 4648",
    "sg:postcode":"10956",
    "sg:province":"NY",
    "sg:tags":[
        "job",
        "camp",
        "specialty",
        "outpatient",
        "t"
    ],
    "wof:name":"Jawonio Inc",
    "wof:placetype":"venue"
},
  "geometry": {"coordinates":[-74.004469,41.167662],"type":"Point"}
}