{
  "type": "Feature",
  "properties": {
    "addr:full":"9944 Charles White Rd Fillmore NY 14735",
    "addr:housenumber":"9944",
    "addr:postcode":"14735",
    "addr:street":"Charles White Rd",
    "iso:country":"US",
    "sg:address":"9944 Charles White Rd",
    "sg:city":"Fillmore",
    "sg:classifiers":[
        {
            "category":"Shopping",
            "subcategory":"Computers & Home Electronics",
            "type":"Retail Goods"
        }
    ],
    "sg:phone":"+1   ",
    "sg:postcode":"14735",
    "sg:province":"NY",
    "sg:tags":[
        "dish",
        "satellite",
        "antenna"
    ],
    "wof:name":"Compact Satellite Systems",
    "wof:placetype":"venue"
},
  "geometry": {"coordinates":[-77.995565,42.435209],"type":"Point"}
}