{
  "type": "Feature",
  "properties": {
    "iso:country":"US",
    "sg:address":"750 Maiden Ln",
    "sg:city":"Rochester",
    "sg:classifiers":[
        {
            "category":"Education",
            "subcategory":"School",
            "type":"Public Place"
        }
    ],
    "sg:phone":"+1 585 966 5200",
    "sg:postcode":"14615",
    "sg:province":"NY",
    "sg:tags":[
        "middle"
    ],
    "sg:website":"http://www.greece.k12.ny.us",
    "wof:name":"Apollo Middle School",
    "wof:placetype":"venue"
},
  "geometry": {"coordinates":[-77.66295,43.223733],"type":"Point"}
}