{
  "type": "Feature",
  "properties": {
    "iso:country":"US",
    "sg:address":"2444 Niagara Rd",
    "sg:city":"Niagara Falls",
    "sg:classifiers":[
        {
            "category":"Retail",
            "subcategory":"Auto Repair",
            "type":"Services"
        }
    ],
    "sg:phone":"+1 716 731 8018",
    "sg:postcode":"14304",
    "sg:province":"NY",
    "sg:tags":[
        "repairing",
        "automobile"
    ],
    "wof:name":"G & S Automotive",
    "wof:placetype":"venue"
},
  "geometry": {"coordinates":[-78.91130699999999,43.102942],"type":"Point"}
}