{
  "type": "Feature",
  "properties": {
    "addr:full":"344 E 49th Street New York NY 10017",
    "addr:housenumber":"344",
    "addr:postcode":"10017",
    "addr:street":"E 49Th Street",
    "iso:country":"US",
    "sg:address":"344 E 49th Street",
    "sg:city":"New York",
    "sg:classifiers":[
        {
            "category":"Autos & Motor Vehicles",
            "subcategory":"Automobile Sales",
            "type":"Retail Goods"
        }
    ],
    "sg:phone":"+1 212 888 7577",
    "sg:postcode":"10017",
    "sg:province":"NY",
    "sg:tags":[
        "limo"
    ],
    "wof:name":"Goodland Chauffeurs",
    "wof:placetype":"venue"
},
  "geometry": {"coordinates":[-73.971509,40.752843],"type":"Point"}
}