{
  "type": "Feature",
  "properties": {
    "iso:country":"US",
    "sg:address":"80 Wall St Ste 1115",
    "sg:city":"New York",
    "sg:classifiers":[
        {
            "category":"Professional",
            "subcategory":"Lawyer & Legal Services",
            "type":"Services"
        }
    ],
    "sg:phone":"+1 212 509 4825",
    "sg:postcode":"10005",
    "sg:province":"NY",
    "wof:name":"Jonathan Ginsburg ESQ",
    "wof:placetype":"venue"
},
  "geometry": {"coordinates":[-74.007698,40.705502],"type":"Point"}
}