{
  "type": "Feature",
  "properties": {
    "addr:full":"8574 Sheridan Dr Buffalo NY 14221",
    "addr:housenumber":"8574",
    "addr:postcode":"14221",
    "addr:street":"Sheridan Dr",
    "iso:country":"US",
    "sg:address":"8574 Sheridan Dr",
    "sg:city":"Buffalo",
    "sg:phone":"+1 716 630 0012",
    "sg:postcode":"14221",
    "sg:province":"NY",
    "sg:website":"http://www.mussoplumbing.net",
    "wof:name":"Musso Plumbing & Heating",
    "wof:placetype":"venue"
},
  "geometry": {"coordinates":[-78.672127,42.978119],"type":"Point"}
}