{
  "type": "Feature",
  "properties": {
    "addr:full":"315 W 39th St Rm 809 New York NY 10018",
    "addr:housenumber":"315;809",
    "addr:postcode":"10018",
    "addr:street":"W 39Th St Rm",
    "iso:country":"US",
    "sg:address":"315 W 39th St Rm 809",
    "sg:city":"New York",
    "sg:classifiers":[
        {
            "category":"Real Estate",
            "subcategory":"Architect",
            "type":"Services"
        }
    ],
    "sg:phone":"+1 212 675 7265",
    "sg:postcode":"10018",
    "sg:province":"NY",
    "wof:name":"Baranowski Ann Marie",
    "wof:placetype":"venue"
},
  "geometry": {"coordinates":[-73.991511,40.755626],"type":"Point"}
}