{
  "type": "Feature",
  "properties": {
    "iso:country":"US",
    "sg:address":"49 Pioneer St",
    "sg:city":"Cooperstown",
    "sg:classifiers":[
        {
            "category":"Bars & Pubs",
            "type":"Food & Drink"
        },
        {
            "category":"Bars & Pubs",
            "subcategory":"Lounge",
            "type":"Food & Drink"
        }
    ],
    "sg:phone":"+1 607 547 9800",
    "sg:postcode":"13326",
    "sg:province":"NY",
    "sg:tags":[
        "cocktail"
    ],
    "wof:name":"Bold Dragon Corp",
    "wof:placetype":"venue"
},
  "geometry": {"coordinates":[-74.924476,42.699861],"type":"Point"}
}