{
  "type": "Feature",
  "properties": {
    "addr:full":"70 Randall Ave Rockville Centre NY 11570",
    "addr:housenumber":"70",
    "addr:postcode":"11570",
    "addr:street":"Randall Ave",
    "iso:country":"US",
    "sg:address":"70 Randall Ave",
    "sg:city":"Rockville Centre",
    "sg:classifiers":[
        {
            "category":"Manufacturing",
            "subcategory":"Jewelry",
            "type":"Manufacturing & Wholesale Goods"
        }
    ],
    "sg:phone":"+1 516 887 6363",
    "sg:postcode":"11570",
    "sg:province":"NY",
    "wof:name":"Klein & Co",
    "wof:placetype":"venue"
},
  "geometry": {"coordinates":[-73.649227,40.660935],"type":"Point"}
}