{
  "type": "Feature",
  "properties": {
    "addr:full":"2130 Delaware Ave Buffalo NY 14216",
    "addr:housenumber":"2130",
    "addr:postcode":"14216",
    "addr:street":"Delaware Ave",
    "iso:country":"US",
    "sg:address":"2130 Delaware Ave",
    "sg:city":"Buffalo",
    "sg:classifiers":[
        {
            "category":"Real Estate",
            "subcategory":"Developer",
            "type":"Services"
        }
    ],
    "sg:phone":"+1 716 832 1111",
    "sg:postcode":"14216",
    "sg:province":"NY",
    "wof:name":"A & Z Development",
    "wof:placetype":"venue"
},
  "geometry": {"coordinates":[-78.86783800000001,42.942094],"type":"Point"}
}