{
  "type": "Feature",
  "properties": {
    "addr:full":"131 Norfred Dr Buffalo NY 14218",
    "addr:housenumber":"131",
    "addr:postcode":"14218",
    "addr:street":"Norfred Dr",
    "iso:country":"US",
    "sg:address":"131 Norfred Dr",
    "sg:city":"Buffalo",
    "sg:classifiers":[
        {
            "category":"Insurance",
            "subcategory":"Insurance Agent",
            "type":"Services"
        }
    ],
    "sg:phone":"+1 716 822 0955",
    "sg:postcode":"14218",
    "sg:province":"NY",
    "wof:name":"Joseph Damian Inc",
    "wof:placetype":"venue"
},
  "geometry": {"coordinates":[-78.805521,42.824021],"type":"Point"}
}