{
  "type": "Feature",
  "properties": {
    "iso:country":"US",
    "sg:address":"300 E 3rd St",
    "sg:city":"Jamestown",
    "sg:classifiers":[
        {
            "category":"Banks & Credit Unions",
            "subcategory":"Bank",
            "type":"Services"
        }
    ],
    "sg:phone":"+1 716 487 9785",
    "sg:postcode":"14701",
    "sg:province":"NY",
    "wof:name":"Jamestown Post Ofc Emplys CU",
    "wof:placetype":"venue"
},
  "geometry": {"coordinates":[-79.236187,42.097069],"type":"Point"}
}