{
  "type": "Feature",
  "properties": {
    "addr:full":"224 W Merrick Rd Valley Stream NY 11580",
    "addr:housenumber":"224",
    "addr:postcode":"11580",
    "addr:street":"W Merrick Rd",
    "iso:country":"US",
    "sg:address":"224 W Merrick Rd",
    "sg:city":"Valley Stream",
    "sg:classifiers":[
        {
            "category":"Organizations",
            "subcategory":"Professional Association",
            "type":"Services"
        }
    ],
    "sg:phone":"+1 516 825 1741",
    "sg:postcode":"11580",
    "sg:province":"NY",
    "sg:tags":[
        "chambers",
        "commerce"
    ],
    "wof:name":"Chamber Of Commerce",
    "wof:placetype":"venue"
},
  "geometry": {"coordinates":[-73.70513699999999,40.666739],"type":"Point"}
}