{
  "type": "Feature",
  "properties": {
    "addr:full":"23 Colony Dr West Sayville NY 11796",
    "addr:housenumber":"23",
    "addr:postcode":"11796",
    "addr:street":"Colony Dr West",
    "iso:country":"US",
    "sg:address":"23 Colony Dr",
    "sg:city":"West Sayville",
    "sg:classifiers":[
        {
            "category":"Building & Trades",
            "subcategory":"Electrical",
            "type":"Services"
        }
    ],
    "sg:phone":"+1 631 567 4671",
    "sg:postcode":"11796",
    "sg:province":"NY",
    "sg:tags":[
        "electrical",
        "contractor"
    ],
    "wof:name":"Steven A Ferreira Electric",
    "wof:placetype":"venue"
},
  "geometry": {"coordinates":[-73.101681,40.731026],"type":"Point"}
}