{
  "type": "Feature",
  "properties": {
    "addr:full":"Met Life Building 200 Park Ave New York NY 10017",
    "addr:housenumber":"200",
    "addr:postcode":"10017",
    "addr:street":"Park Ave",
    "iso:country":"US",
    "sg:address":"Met Life Building 200 Park Ave",
    "sg:city":"New York",
    "sg:classifiers":[
        {
            "category":"Food & Beverages",
            "subcategory":"Chocolate",
            "type":"Retail Goods"
        }
    ],
    "sg:phone":"+1 212 697 9150",
    "sg:postcode":"10017",
    "sg:province":"NY",
    "sg:tags":[
        "shop",
        "chocolatiers"
    ],
    "sg:website":"www.godiva.com",
    "wof:name":"Godiva",
    "wof:placetype":"venue"
},
  "geometry": {"coordinates":[-73.97703,40.753986],"type":"Point"}
}