{
  "type": "Feature",
  "properties": {
    "iso:country":"US",
    "sg:address":"420 12th St",
    "sg:city":"Brooklyn",
    "sg:classifiers":[
        {
            "category":"Manufacturing",
            "subcategory":"Apparel",
            "type":"Manufacturing & Wholesale Goods"
        }
    ],
    "sg:phone":"+1   ",
    "sg:postcode":"11215",
    "sg:province":"NY",
    "sg:tags":[
        "manufacture",
        "design",
        "woman",
        "clothing"
    ],
    "wof:name":"Company of Unorganized People",
    "wof:placetype":"venue"
},
  "geometry": {"coordinates":[-73.981182,40.664153],"type":"Point"}
}