{
  "type": "Feature",
  "properties": {
    "addr:full":"75 Washington Pl New York NY 10011",
    "addr:housenumber":"75",
    "addr:postcode":"10011",
    "addr:street":"Washington Pl",
    "iso:country":"US",
    "sg:address":"75 Washington Pl",
    "sg:city":"New York",
    "sg:classifiers":[
        {
            "category":"Restaurant",
            "type":"Food & Drink"
        }
    ],
    "sg:phone":"+1 212 539 1776",
    "sg:postcode":"10011",
    "sg:province":"NY",
    "sg:tags":[
        "new",
        "american"
    ],
    "sg:website":"www.bluehillfarm.com",
    "wof:name":"Blue Hill",
    "wof:placetype":"venue"
},
  "geometry": {"coordinates":[-73.999701,40.731987],"type":"Point"}
}