{
  "type": "Feature",
  "properties": {
    "iso:country":"US",
    "sg:address":"510 Hempstead Tpke Rm 204",
    "sg:city":"West Hempstead",
    "sg:classifiers":[
        {
            "category":"Banks & Credit Unions",
            "subcategory":"Financial Services",
            "type":"Services"
        }
    ],
    "sg:phone":"+1 516 505 5809",
    "sg:postcode":"11552",
    "sg:province":"NY",
    "sg:tags":[
        "broker",
        "mortgage"
    ],
    "wof:name":"New York Capital Exchange Corp",
    "wof:placetype":"venue"
},
  "geometry": {"coordinates":[-73.656502,40.705502],"type":"Point"}
}