{
  "type": "Feature",
  "properties": {
    "iso:country":"US",
    "sg:address":"205 W River Rd",
    "sg:city":"Caledonia",
    "sg:classifiers":[
        {
            "category":"Manufacturing",
            "subcategory":"Glass & Minerals",
            "type":"Manufacturing & Wholesale Goods"
        }
    ],
    "sg:phone":"+1   ",
    "sg:postcode":"14423",
    "sg:province":"NY",
    "sg:tags":[
        "hydraulic",
        "cement",
        "mfg"
    ],
    "wof:name":"Hanson Aggregates",
    "wof:placetype":"venue"
},
  "geometry": {"coordinates":[-77.74356400000001,42.981436],"type":"Point"}
}