{
  "type": "Feature",
  "properties": {
    "iso:country":"US",
    "sg:address":"265 Indian Head Rd",
    "sg:city":"Kings Park",
    "sg:classifiers":[
        {
            "category":"Retail",
            "subcategory":"Auto Repair",
            "type":"Services"
        }
    ],
    "sg:phone":"+1 631 544 0092",
    "sg:postcode":"11754",
    "sg:province":"NY",
    "sg:tags":[
        "automobile",
        "co",
        "drive",
        "transporter"
    ],
    "wof:name":"Zytel Industries Inc",
    "wof:placetype":"venue"
},
  "geometry": {"coordinates":[-73.258106,40.869889],"type":"Point"}
}