{
  "type": "Feature",
  "properties": {
    "iso:country":"US",
    "sg:address":"5 W 91st St",
    "sg:city":"New York",
    "sg:classifiers":[
        {
            "category":"Arts & Performance",
            "subcategory":"Theater",
            "type":"Entertainment"
        }
    ],
    "sg:phone":"+1 212 591 0887",
    "sg:postcode":"10024",
    "sg:province":"NY",
    "sg:tags":[
        "group"
    ],
    "wof:name":"Creative Edge Entertainment",
    "wof:placetype":"venue"
},
  "geometry": {"coordinates":[-73.96751399999999,40.788756],"type":"Point"}
}