{
  "type": "Feature",
  "properties": {
    "addr:full":"8516 Roosevelt Ave Jackson Heights NY 11372",
    "addr:housenumber":"8516",
    "addr:postcode":"11372",
    "addr:street":"Roosevelt Ave",
    "iso:country":"US",
    "sg:address":"8516 Roosevelt Ave",
    "sg:city":"Jackson Heights",
    "sg:classifiers":[
        {
            "category":"Building & Trades",
            "subcategory":"Locksmith",
            "type":"Services"
        }
    ],
    "sg:phone":"+1 718 269 1325",
    "sg:postcode":"11372",
    "sg:province":"NY",
    "sg:tags":[
        "key"
    ],
    "wof:name":"Available Hour Jackson Heights Emergency Lock",
    "wof:placetype":"venue"
},
  "geometry": {"coordinates":[-73.88095,40.747809],"type":"Point"}
}