{
  "type": "Feature",
  "properties": {
    "addr:full":"1447 56th St Brooklyn NY 11219",
    "addr:housenumber":"1447",
    "addr:postcode":"11219",
    "addr:street":"56Th St",
    "iso:country":"US",
    "sg:address":"1447 56th St",
    "sg:city":"Brooklyn",
    "sg:classifiers":[
        {
            "category":"Wholesale",
            "subcategory":"Office Equipment",
            "type":"Manufacturing & Wholesale Goods"
        },
        {
            "category":"Wholesale",
            "subcategory":"Electrical",
            "type":"Manufacturing & Wholesale Goods"
        }
    ],
    "sg:phone":"+1 718 972 4600",
    "sg:postcode":"11219",
    "sg:province":"NY",
    "sg:tags":[
        "furniture",
        "electronic",
        "supply"
    ],
    "sg:website":"www.emazeltov.com",
    "wof:name":"Joseph Distributors Inc",
    "wof:placetype":"venue"
},
  "geometry": {"coordinates":[-73.992531,40.629129],"type":"Point"}
}