{
  "type": "Feature",
  "properties": {
    "iso:country":"US",
    "sg:address":"40 Walker St",
    "sg:city":"New York",
    "sg:classifiers":[
        {
            "category":"Building & Trades",
            "subcategory":"Construction",
            "type":"Services"
        }
    ],
    "sg:phone":"+1 212 274 9494",
    "sg:postcode":"10013",
    "sg:province":"NY",
    "sg:tags":[
        "residential",
        "commercial",
        "contractor"
    ],
    "wof:name":"Signature Construction Group",
    "wof:placetype":"venue"
},
  "geometry": {"coordinates":[-74.002886,40.718925],"type":"Point"}
}