{
  "type": "Feature",
  "properties": {
    "iso:country":"US",
    "sg:address":"458 Parkside Ave",
    "sg:city":"Buffalo",
    "sg:classifiers":[
        {
            "category":"Building & Trades",
            "subcategory":"Construction",
            "type":"Services"
        }
    ],
    "sg:phone":"+1 716 833 1887",
    "sg:postcode":"14216",
    "sg:province":"NY",
    "sg:tags":[
        "house"
    ],
    "wof:name":"University Contracting",
    "wof:placetype":"venue"
},
  "geometry": {"coordinates":[-78.850655,42.941961],"type":"Point"}
}