{
  "type": "Feature",
  "properties": {
    "addr:full":"1779 Camp Ave Merrick NY 11566",
    "addr:housenumber":"1779",
    "addr:postcode":"11566",
    "addr:street":"Camp Ave",
    "iso:country":"US",
    "sg:address":"1779 Camp Ave",
    "sg:city":"Merrick",
    "sg:classifiers":[
        {
            "category":"Building & Trades",
            "subcategory":"Plumbing",
            "type":"Services"
        }
    ],
    "sg:phone":"+1 516 429 0588",
    "sg:postcode":"11566",
    "sg:province":"NY",
    "sg:website":"www.keithsplumbing.com",
    "wof:name":"Keith's Plumbing, Heating & Drain Cleaning",
    "wof:placetype":"venue"
},
  "geometry": {"coordinates":[-73.55999,40.676742],"type":"Point"}
}