{
  "type": "Feature",
  "properties": {
    "iso:country":"US",
    "sg:address":"218 Spring St",
    "sg:city":"Catskill",
    "sg:classifiers":[
        {
            "category":"Landmark",
            "subcategory":"Historic",
            "type":"Public Place"
        }
    ],
    "sg:phone":"+1 518 943 7465",
    "sg:postcode":"12414",
    "sg:province":"NY",
    "sg:tags":[
        "building",
        "historical"
    ],
    "wof:name":"Thomas Cole Cedar Grove",
    "wof:placetype":"venue"
},
  "geometry": {"coordinates":[-73.86190000000001,42.225899],"type":"Point"}
}