{
  "type": "Feature",
  "properties": {
    "addr:full":"428 Lorimer St Brooklyn NY 11206",
    "addr:housenumber":"428",
    "addr:postcode":"11206",
    "addr:street":"Lorimer St",
    "iso:country":"US",
    "sg:address":"428 Lorimer St",
    "sg:city":"Brooklyn",
    "sg:classifiers":[
        {
            "category":"Wholesale",
            "subcategory":"Groceries",
            "type":"Manufacturing & Wholesale Goods"
        }
    ],
    "sg:phone":"+1 718 599 5819",
    "sg:postcode":"11206",
    "sg:province":"NY",
    "sg:tags":[
        "general"
    ],
    "wof:name":"Burgos Grocery Store",
    "wof:placetype":"venue"
},
  "geometry": {"coordinates":[-73.948539,40.709015],"type":"Point"}
}