{
  "type": "Feature",
  "properties": {
    "addr:full":"27005 76th Ave New Hyde Park NY 11040",
    "addr:housenumber":"27005",
    "addr:postcode":"11040",
    "addr:street":"76Th Ave",
    "iso:country":"US",
    "sg:address":"27005 76th Ave",
    "sg:city":"New Hyde Park",
    "sg:classifiers":[
        {
            "category":"Health Services",
            "subcategory":"Doctor",
            "type":"Services"
        }
    ],
    "sg:phone":"+1 718 470 8934",
    "sg:postcode":"11040",
    "sg:province":"NY",
    "wof:name":"Mehrota Bhoomi MD",
    "wof:placetype":"venue"
},
  "geometry": {"coordinates":[-73.70909899999999,40.751499],"type":"Point"}
}