{
  "type": "Feature",
  "properties": {
    "addr:full":"4936 Main St Bemus Point NY 14712",
    "addr:housenumber":"4936",
    "addr:postcode":"14712",
    "addr:street":"Main St",
    "iso:country":"US",
    "sg:address":"4936 Main St",
    "sg:city":"Bemus Point",
    "sg:classifiers":[
        {
            "category":"Health Services",
            "subcategory":"Doctor",
            "type":"Services"
        }
    ],
    "sg:phone":"+1 716 386 2414",
    "sg:postcode":"14712",
    "sg:province":"NY",
    "sg:tags":[
        "physician",
        "surgeon"
    ],
    "wof:name":"Bemus Point Family Practice",
    "wof:placetype":"venue"
},
  "geometry": {"coordinates":[-79.384941,42.155176],"type":"Point"}
}