{
  "type": "Feature",
  "properties": {
    "addr:full":"31 Matilda Ct Bayport NY 11705",
    "addr:housenumber":"31",
    "addr:postcode":"11705",
    "addr:street":"Matilda Ct",
    "iso:country":"US",
    "sg:address":"31 Matilda Ct",
    "sg:city":"Bayport",
    "sg:classifiers":[
        {
            "category":"Wholesale",
            "subcategory":"Apparel",
            "type":"Manufacturing & Wholesale Goods"
        }
    ],
    "sg:phone":"+1 631 472 2944",
    "sg:postcode":"11705",
    "sg:province":"NY",
    "sg:tags":[
        "rep",
        "sale",
        "clothing-men's-wholesale",
        "manufacturer"
    ],
    "wof:name":"Men's Fashion Resources Ltd",
    "wof:placetype":"venue"
},
  "geometry": {"coordinates":[-73.055863,40.729404],"type":"Point"}
}