{
  "type": "Feature",
  "properties": {
    "addr:full":"948 Eastern Pkwy Brooklyn NY 11213",
    "addr:housenumber":"948",
    "addr:postcode":"11213",
    "addr:street":"Eastern Pkwy",
    "iso:country":"US",
    "sg:address":"948 Eastern Pkwy",
    "sg:city":"Brooklyn",
    "sg:classifiers":[
        {
            "category":"Health Services",
            "subcategory":"Hospital",
            "type":"Services"
        }
    ],
    "sg:phone":"+1 718 778 0685",
    "sg:postcode":"11213",
    "sg:province":"NY",
    "sg:tags":[
        "mental"
    ],
    "wof:name":"Insitute For Community Living",
    "wof:placetype":"venue"
},
  "geometry": {"coordinates":[-73.938568,40.669163],"type":"Point"}
}