{
  "type": "Feature",
  "properties": {
    "iso:country":"US",
    "sg:address":"948 Eastern Pkwy",
    "sg:city":"Brooklyn",
    "sg:classifiers":[
        {
            "category":"Health Services",
            "subcategory":"Hospital",
            "type":"Services"
        }
    ],
    "sg:phone":"+1 718 778 0685",
    "sg:postcode":"11213",
    "sg:province":"NY",
    "sg:tags":[
        "mental"
    ],
    "wof:name":"Insitute For Community Living",
    "wof:placetype":"venue"
},
  "geometry": {"coordinates":[-73.938568,40.669163],"type":"Point"}
}