{
  "type": "Feature",
  "properties": {
    "iso:country":"US",
    "sg:address":"29 Canal St",
    "sg:city":"Middletown",
    "sg:classifiers":[
        {
            "category":"Professional",
            "subcategory":"Business Services",
            "type":"Services"
        }
    ],
    "sg:phone":"+1   ",
    "sg:postcode":"10940",
    "sg:province":"NY",
    "wof:name":"Ecstatica Recording Studios",
    "wof:placetype":"venue"
},
  "geometry": {"coordinates":[-74.421915,41.44457],"type":"Point"}
}