{
  "type": "Feature",
  "properties": {
    "addr:full":"75 Lewis Rd Merrick NY 11566",
    "addr:housenumber":"75",
    "addr:postcode":"11566",
    "addr:street":"Lewis Rd",
    "iso:country":"US",
    "sg:address":"75 Lewis Rd",
    "sg:city":"Merrick",
    "sg:classifiers":[
        {
            "category":"Banks & Credit Unions",
            "subcategory":"Bank",
            "type":"Services"
        }
    ],
    "sg:phone":"+1 516 546 4799",
    "sg:postcode":"11566",
    "sg:province":"NY",
    "sg:tags":[
        "federal",
        "agency"
    ],
    "wof:name":"George Luxner & Sons",
    "wof:placetype":"venue"
},
  "geometry": {"coordinates":[-73.56218200000001,40.679153],"type":"Point"}
}