{
  "type": "Feature",
  "properties": {
    "iso:country":"US",
    "sg:address":"4 N State St",
    "sg:city":"Nunda",
    "sg:classifiers":[
        {
            "category":"Government",
            "subcategory":"Fire Station",
            "type":"Public Place"
        }
    ],
    "sg:phone":"+1 585 468 2323",
    "sg:postcode":"14517",
    "sg:province":"NY",
    "sg:tags":[
        "department"
    ],
    "wof:name":"Fire Hall",
    "wof:placetype":"venue"
},
  "geometry": {"coordinates":[-77.942644,42.579827],"type":"Point"}
}