{
  "type": "Feature",
  "properties": {
    "iso:country":"US",
    "sg:address":"1721 Front St",
    "sg:city":"Keeseville",
    "sg:classifiers":[
        {
            "category":"Education",
            "subcategory":"Library",
            "type":"Public Place"
        }
    ],
    "sg:phone":"+1 518 834 9054",
    "sg:postcode":"12944",
    "sg:province":"NY",
    "wof:name":"Keeseville Free Library",
    "wof:placetype":"venue"
},
  "geometry": {"coordinates":[-73.480085,44.504799],"type":"Point"}
}