{
  "type": "Feature",
  "properties": {
    "iso:country":"US",
    "sg:address":"200 River Rd",
    "sg:city":"North Tonawanda",
    "sg:classifiers":[
        {
            "category":"Wholesale",
            "subcategory":"Machinery & Supplies",
            "type":"Manufacturing & Wholesale Goods"
        }
    ],
    "sg:phone":"+1 716 692 3788",
    "sg:postcode":"14120",
    "sg:province":"NY",
    "sg:tags":[
        "equipment",
        "industrial"
    ],
    "wof:name":"Igt",
    "wof:placetype":"venue"
},
  "geometry": {"coordinates":[-78.87985999999999,43.027777],"type":"Point"}
}