{
  "type": "Feature",
  "properties": {
    "iso:country":"US",
    "sg:address":"76 Titusville Rd",
    "sg:city":"Poughkeepsie",
    "sg:classifiers":[
        {
            "category":"Food & Beverages",
            "subcategory":"Groceries & Convenience Stores",
            "type":"Retail Goods"
        }
    ],
    "sg:phone":"+1   ",
    "sg:postcode":"12603",
    "sg:province":"NY",
    "wof:name":"Db Companies Inc",
    "wof:placetype":"venue"
},
  "geometry": {"coordinates":[-73.869347,41.676514],"type":"Point"}
}