{
  "type": "Feature",
  "properties": {
    "addr:full":"5428 S Abbott Rd Hamburg NY 14075",
    "addr:housenumber":"5428",
    "addr:postcode":"14075",
    "addr:street":"S Abbott Rd",
    "iso:country":"US",
    "sg:address":"5428 S Abbott Rd",
    "sg:city":"Hamburg",
    "sg:classifiers":[
        {
            "category":"Personal",
            "subcategory":"Shoe Repair & Shine",
            "type":"Services"
        }
    ],
    "sg:phone":"+1 716 649 5097",
    "sg:postcode":"14075",
    "sg:province":"NY",
    "sg:tags":[
        "repairing",
        "boot"
    ],
    "wof:name":"Shoemaker's Bench",
    "wof:placetype":"venue"
},
  "geometry": {"coordinates":[-78.79775100000001,42.738874],"type":"Point"}
}