{
  "type": "Feature",
  "properties": {
    "addr:full":"4846 Candy Ln Manlius NY 13104",
    "addr:housenumber":"4846",
    "addr:postcode":"13104",
    "addr:street":"Candy Ln",
    "iso:country":"US",
    "sg:address":"4846 Candy Ln",
    "sg:city":"Manlius",
    "sg:classifiers":[
        {
            "category":"Organizations",
            "subcategory":"Religious Organization",
            "type":"Services"
        }
    ],
    "sg:phone":"+1 315 682 5767",
    "sg:postcode":"13104",
    "sg:province":"NY",
    "sg:tags":[
        "clergy"
    ],
    "wof:name":"Landrum H Wooten",
    "wof:placetype":"venue"
},
  "geometry": {"coordinates":[-75.990914,43.005707],"type":"Point"}
}