{
  "type": "Feature",
  "properties": {
    "addr:full":"125 Lake Avenue Staten Island NY 10303",
    "addr:housenumber":"125",
    "addr:postcode":"10303",
    "addr:street":"Lake Avenue",
    "iso:country":"US",
    "sg:address":"125 Lake Avenue",
    "sg:city":"Staten Island",
    "sg:classifiers":[
        {
            "category":"Home & Garden",
            "subcategory":"Furniture",
            "type":"Retail Goods"
        }
    ],
    "sg:phone":"+1 718 789 6000",
    "sg:postcode":"10303",
    "sg:province":"NY",
    "sg:tags":[
        "store"
    ],
    "wof:name":"Nova Metal",
    "wof:placetype":"venue"
},
  "geometry": {"coordinates":[-74.150907,40.63371],"type":"Point"}
}