{
  "type": "Feature",
  "properties": {
    "addr:full":"129 Plainfield Ave Bedford Hills NY 10507",
    "addr:housenumber":"129",
    "addr:postcode":"10507",
    "addr:street":"Plainfield Ave",
    "iso:country":"US",
    "sg:address":"129 Plainfield Ave",
    "sg:city":"Bedford Hills",
    "sg:classifiers":[
        {
            "category":"Shopping",
            "subcategory":"Computers & Home Electronics",
            "type":"Retail Goods"
        }
    ],
    "sg:phone":"+1 914 666 0550",
    "sg:postcode":"10507",
    "sg:province":"NY",
    "wof:name":"Refrence Cinema",
    "wof:placetype":"venue"
},
  "geometry": {"coordinates":[-73.713527,41.2283],"type":"Point"}
}