{
  "type": "Feature",
  "properties": {
    "iso:country":"US",
    "sg:address":"888 Old Country Rd",
    "sg:city":"Riverhead",
    "sg:classifiers":[
        {
            "category":"Retail",
            "subcategory":"Auto Repair",
            "type":"Services"
        }
    ],
    "sg:phone":"+1 631 369 4054",
    "sg:postcode":"11901",
    "sg:province":"NY",
    "sg:tags":[
        "muffler",
        "exhaust",
        "system"
    ],
    "wof:name":"Turnpike Muffler East End Corp",
    "wof:placetype":"venue"
},
  "geometry": {"coordinates":[-72.672747,40.933754],"type":"Point"}
}