{
  "type": "Feature",
  "properties": {
    "addr:full":"54 Mendon St Rochester NY 14615",
    "addr:housenumber":"54",
    "addr:postcode":"14615",
    "addr:street":"Mendon St",
    "iso:country":"US",
    "sg:address":"54 Mendon St",
    "sg:city":"Rochester",
    "sg:classifiers":[
        {
            "category":"Manufacturing",
            "subcategory":"Petroleum Products",
            "type":"Manufacturing & Wholesale Goods"
        }
    ],
    "sg:phone":"+1 585 458 1582",
    "sg:postcode":"14615",
    "sg:province":"NY",
    "sg:tags":[
        "contract"
    ],
    "wof:name":"Ds Manufacturing",
    "wof:placetype":"venue"
},
  "geometry": {"coordinates":[-77.657662,43.197159],"type":"Point"}
}