{
  "type": "Feature",
  "properties": {
    "iso:country":"US",
    "sg:address":"18 Laura Dr",
    "sg:city":"Centereach",
    "sg:classifiers":[
        {
            "category":"Real Estate",
            "subcategory":"Real Estate Operator",
            "type":"Services"
        }
    ],
    "sg:phone":"+1 631 451 0220",
    "sg:postcode":"11720",
    "sg:province":"NY",
    "sg:tags":[
        "building",
        "nonresidential"
    ],
    "wof:name":"Bellandra Properties",
    "wof:placetype":"venue"
},
  "geometry": {"coordinates":[-73.068956,40.864824],"type":"Point"}
}