{
  "type": "Feature",
  "properties": {
    "addr:full":"340 Bolivar Rd Wellsville NY 14895",
    "addr:housenumber":"340",
    "addr:postcode":"14895",
    "addr:street":"Bolivar Rd",
    "iso:country":"US",
    "sg:address":"340 Bolivar Rd",
    "sg:city":"Wellsville",
    "sg:classifiers":[
        {
            "category":"Restaurant",
            "type":"Food & Drink"
        }
    ],
    "sg:phone":"+1   ",
    "sg:postcode":"14895",
    "sg:province":"NY",
    "sg:tags":[
        "eating"
    ],
    "sg:website":"www.ponderosasteakhouses.com",
    "wof:name":"Ponderosa Steakhouse",
    "wof:placetype":"venue"
},
  "geometry": {"coordinates":[-77.96526,42.127115],"type":"Point"}
}