{
  "type": "Feature",
  "properties": {
    "addr:full":"930 Willowbrook Rd Staten Island NY 10314",
    "addr:housenumber":"930",
    "addr:postcode":"10314",
    "addr:street":"Willowbrook Rd",
    "iso:country":"US",
    "sg:address":"930 Willowbrook Rd",
    "sg:city":"Staten Island",
    "sg:classifiers":[
        {
            "category":"Education",
            "subcategory":"Vocational School",
            "type":"Public Place"
        }
    ],
    "sg:phone":"+1 718 494 6457",
    "sg:postcode":"10314",
    "sg:province":"NY",
    "sg:tags":[
        "training",
        "computer"
    ],
    "wof:name":"New York State Institute",
    "wof:placetype":"venue"
},
  "geometry": {"coordinates":[-74.14112900000001,40.603162],"type":"Point"}
}