{
  "type": "Feature",
  "properties": {
    "addr:full":"1600 Sheepshead Bay Rd Brooklyn NY 11235",
    "addr:housenumber":"1600",
    "addr:postcode":"11235",
    "addr:street":"Sheepshead Bay Rd",
    "iso:country":"US",
    "sg:address":"1600 Sheepshead Bay Rd",
    "sg:city":"Brooklyn",
    "sg:classifiers":[
        {
            "category":"Social Services",
            "type":"Services"
        }
    ],
    "sg:phone":"+1 718 332 0137",
    "sg:postcode":"11235",
    "sg:province":"NY",
    "sg:tags":[
        "counselor",
        "marriage",
        "family"
    ],
    "wof:name":"Ronald Rodgriguez",
    "wof:placetype":"venue"
},
  "geometry": {"coordinates":[-73.954004,40.587219],"type":"Point"}
}