{
  "type": "Feature",
  "properties": {
    "addr:full":"470 Main St Armonk NY 10504",
    "addr:housenumber":"470",
    "addr:postcode":"10504",
    "addr:street":"Main St",
    "iso:country":"US",
    "sg:address":"470 Main St",
    "sg:city":"Armonk",
    "sg:classifiers":[
        {
            "category":"Shopping",
            "subcategory":"Gifts & Souvenirs",
            "type":"Retail Goods"
        }
    ],
    "sg:phone":"+1 914 273 9751",
    "sg:postcode":"10504",
    "sg:province":"NY",
    "sg:tags":[
        "shop"
    ],
    "sg:website":"www.wisteria-gifts.com",
    "wof:name":"Wisteria Gifts",
    "wof:placetype":"venue"
},
  "geometry": {"coordinates":[-73.713117,41.129051],"type":"Point"}
}