{
  "type": "Feature",
  "properties": {
    "iso:country":"US",
    "sg:address":"337 Hamilton St",
    "sg:city":"Geneva",
    "sg:classifiers":[
        {
            "category":"Personal",
            "subcategory":"Tanning Parlor",
            "type":"Services"
        }
    ],
    "sg:phone":"+1 315 789 1838",
    "sg:postcode":"14456",
    "sg:province":"NY",
    "sg:tags":[
        "salon"
    ],
    "wof:name":"Dark Tan",
    "wof:placetype":"venue"
},
  "geometry": {"coordinates":[-76.994426,42.858791],"type":"Point"}
}