{
  "type": "Feature",
  "properties": {
    "iso:country":"US",
    "sg:address":"9 Oakwood Blvd",
    "sg:city":"Bay Shore",
    "sg:classifiers":[
        {
            "category":"Building & Trades",
            "subcategory":"Construction",
            "type":"Services"
        }
    ],
    "sg:phone":"+1 631 968 4623",
    "sg:postcode":"11706",
    "sg:province":"NY",
    "sg:tags":[
        "general",
        "contractor"
    ],
    "wof:name":"Scott Soucy Construction",
    "wof:placetype":"venue"
},
  "geometry": {"coordinates":[-73.238559,40.741161],"type":"Point"}
}