{
  "type": "Feature",
  "properties": {
    "addr:full":"555 Central Park Ave Scarsdale NY 10583",
    "addr:housenumber":"555",
    "addr:postcode":"10583",
    "addr:street":"Central Park Ave",
    "iso:country":"US",
    "sg:address":"555 Central Park Ave",
    "sg:city":"Scarsdale",
    "sg:classifiers":[
        {
            "category":"Professional",
            "type":"Services"
        }
    ],
    "sg:phone":"+1 914 725 0493",
    "sg:postcode":"10583",
    "sg:province":"NY",
    "sg:tags":[
        "establishment"
    ],
    "wof:name":"Westchester Arc",
    "wof:placetype":"venue"
},
  "geometry": {"coordinates":[-73.81373499999999,41.002978],"type":"Point"}
}