{
  "type": "Feature",
  "properties": {
    "addr:full":"1532 Amsterdam Ave New York NY 10031",
    "addr:housenumber":"1532",
    "addr:postcode":"10031",
    "addr:street":"Amsterdam Ave",
    "iso:country":"US",
    "sg:address":"1532 Amsterdam Ave",
    "sg:city":"New York",
    "sg:classifiers":[
        {
            "category":"Wholesale",
            "subcategory":"Groceries",
            "type":"Manufacturing & Wholesale Goods"
        }
    ],
    "sg:phone":"+1 212 281 6168",
    "sg:postcode":"10031",
    "sg:province":"NY",
    "sg:tags":[
        "general"
    ],
    "wof:name":"Nicholas Rodriguez",
    "wof:placetype":"venue"
},
  "geometry": {"coordinates":[-73.95204099999999,40.819194],"type":"Point"}
}