{
  "type": "Feature",
  "properties": {
    "addr:full":"39 E Main St Fort Johnson NY 12070",
    "addr:housenumber":"39",
    "addr:postcode":"12070",
    "addr:street":"E Main St",
    "iso:country":"US",
    "sg:address":"39 E Main St",
    "sg:city":"Fort Johnson",
    "sg:classifiers":[
        {
            "category":"Organizations",
            "subcategory":"Religious Organization",
            "type":"Services"
        }
    ],
    "sg:phone":"+1 518 843 6630",
    "sg:postcode":"12070",
    "sg:province":"NY",
    "sg:tags":[
        "monastery",
        "convent"
    ],
    "wof:name":"Sisters Of St Joseph",
    "wof:placetype":"venue"
},
  "geometry": {"coordinates":[-74.22564,42.95636],"type":"Point"}
}