{
  "type": "Feature",
  "properties": {
    "iso:country":"US",
    "sg:address":"565 Conklin Rd",
    "sg:city":"Binghamton",
    "sg:classifiers":[
        {
            "category":"Retail",
            "subcategory":"Auto Repair",
            "type":"Services"
        }
    ],
    "sg:phone":"+1   ",
    "sg:postcode":"13903",
    "sg:province":"NY",
    "sg:tags":[
        "automotive",
        "general"
    ],
    "wof:name":"City Line Service",
    "wof:placetype":"venue"
},
  "geometry": {"coordinates":[-75.864131,42.100443],"type":"Point"}
}