{
  "type": "Feature",
  "properties": {
    "addr:full":"59 Pulaski St Auburn NY 13021",
    "addr:housenumber":"59",
    "addr:postcode":"13021",
    "addr:street":"Pulaski St",
    "iso:country":"US",
    "sg:address":"59 Pulaski St",
    "sg:city":"Auburn",
    "sg:classifiers":[
        {
            "category":"Education",
            "subcategory":"School",
            "type":"Public Place"
        }
    ],
    "sg:phone":"+1 315 252 9547",
    "sg:postcode":"13021",
    "sg:province":"NY",
    "wof:name":"St Hyacinth School",
    "wof:placetype":"venue"
},
  "geometry": {"coordinates":[-76.576103,42.941038],"type":"Point"}
}