{
  "type": "Feature",
  "properties": {
    "addr:full":"333 E 102nd Street Apt 335 New York NY 10029",
    "addr:housenumber":"333;335",
    "addr:postcode":"10029",
    "addr:street":"E 102Nd Street Apt",
    "iso:country":"US",
    "sg:address":"333 E 102nd Street Apt 335",
    "sg:city":"New York",
    "sg:classifiers":[
        {
            "category":"Shopping",
            "subcategory":"Pharmacy",
            "type":"Retail Goods"
        }
    ],
    "sg:phone":"+1 212 423 2042",
    "sg:postcode":"10029",
    "sg:province":"NY",
    "sg:tags":[
        "drugstore"
    ],
    "wof:name":"Duane Reade",
    "wof:placetype":"venue"
},
  "geometry": {"coordinates":[-73.943544,40.787731],"type":"Point"}
}