{
  "type": "Feature",
  "properties": {
    "addr:full":"10221 Larue Ave Corona NY 11368",
    "addr:housenumber":"10221",
    "addr:postcode":"11368",
    "addr:street":"Larue Ave",
    "iso:country":"US",
    "sg:address":"10221 Larue Ave",
    "sg:city":"Corona",
    "sg:classifiers":[
        {
            "category":"Building & Trades",
            "subcategory":"Construction",
            "type":"Services"
        }
    ],
    "sg:phone":"+1 888 613 5667",
    "sg:postcode":"11368",
    "sg:province":"NY",
    "sg:tags":[
        "contractor"
    ],
    "wof:name":"A USA Contractors Inc",
    "wof:placetype":"venue"
},
  "geometry": {"coordinates":[-73.857546,40.740659],"type":"Point"}
}