{
  "type": "Feature",
  "properties": {
    "addr:full":"140 E 3rd St Mt Vernon NY 10550",
    "addr:housenumber":"140",
    "addr:postcode":"10550",
    "addr:street":"E 3Rd St",
    "iso:country":"US",
    "sg:address":"140 E 3rd St",
    "sg:city":"Mt Vernon",
    "sg:classifiers":[
        {
            "category":"Organizations",
            "subcategory":"Religious Organization",
            "type":"Services"
        }
    ],
    "sg:phone":"+1 914 664 6280",
    "sg:postcode":"10550",
    "sg:province":"NY",
    "sg:tags":[
        "church"
    ],
    "wof:name":"Church Of God Of Prophecy",
    "wof:placetype":"venue"
},
  "geometry": {"coordinates":[-73.82828000000001,40.90834],"type":"Point"}
}