{
  "type": "Feature",
  "properties": {
    "addr:full":"131 Foster Ave Valley Stream NY 11580",
    "addr:housenumber":"131",
    "addr:postcode":"11580",
    "addr:street":"Foster Ave",
    "iso:country":"US",
    "sg:address":"131 Foster Ave",
    "sg:city":"Valley Stream",
    "sg:classifiers":[
        {
            "category":"Professional",
            "subcategory":"Management & Consulting",
            "type":"Services"
        }
    ],
    "sg:phone":"+1   ",
    "sg:postcode":"11580",
    "sg:province":"NY",
    "sg:tags":[
        "educational"
    ],
    "wof:name":"JP Associates Inc",
    "wof:placetype":"venue"
},
  "geometry": {"coordinates":[-73.68711,40.665347],"type":"Point"}
}