{
  "type": "Feature",
  "properties": {
    "iso:country":"US",
    "sg:address":"2488 Montauk Hwy",
    "sg:city":"Bridgehampton",
    "sg:classifiers":[
        {
            "category":"Real Estate",
            "subcategory":"Real Estate Agent",
            "type":"Services"
        }
    ],
    "sg:phone":"+1 631 537 6581",
    "sg:postcode":"11932",
    "sg:province":"NY",
    "wof:name":"Prudential Long Island Realty",
    "wof:placetype":"venue"
},
  "geometry": {"coordinates":[-72.30462900000001,40.936066],"type":"Point"}
}