{
  "type": "Feature",
  "properties": {
    "addr:full":"285 Southside Pkwy Buffalo NY 14220",
    "addr:housenumber":"285",
    "addr:postcode":"14220",
    "addr:street":"Southside Pkwy",
    "iso:country":"US",
    "sg:address":"285 Southside Pkwy",
    "sg:city":"Buffalo",
    "sg:classifiers":[
        {
            "category":"Social Services",
            "subcategory":"Child Care",
            "type":"Services"
        }
    ],
    "sg:phone":"+1 716 825 7400",
    "sg:postcode":"14220",
    "sg:province":"NY",
    "sg:tags":[
        "day"
    ],
    "wof:name":"Storytime Day Care & Learning Center",
    "wof:placetype":"venue"
},
  "geometry": {"coordinates":[-78.82379899999999,42.856098],"type":"Point"}
}