{
  "type": "Feature",
  "properties": {
    "addr:full":"45 Columbia St Poughkeepsie NY 12601",
    "addr:housenumber":"45",
    "addr:postcode":"12601",
    "addr:street":"Columbia",
    "iso:country":"US",
    "sg:address":"45 Columbia St",
    "sg:city":"Poughkeepsie",
    "sg:classifiers":[
        {
            "category":"Shopping",
            "type":"Retail Goods"
        }
    ],
    "sg:phone":"+1 845 454 1999",
    "sg:postcode":"12601",
    "sg:province":"NY",
    "sg:tags":[
        "equipment",
        "telephone",
        "supply"
    ],
    "wof:name":"Allied Telcom",
    "wof:placetype":"venue"
},
  "geometry": {"coordinates":[-73.93456,41.696064],"type":"Point"}
}