{
  "type": "Feature",
  "properties": {
    "iso:country":"US",
    "sg:address":"136 Radio Cir Dr",
    "sg:city":"Mount Kisco",
    "sg:classifiers":[
        {
            "category":"Manufacturing",
            "subcategory":"Motor Vehicles & Parts",
            "type":"Manufacturing & Wholesale Goods"
        }
    ],
    "sg:phone":"+1   ",
    "sg:postcode":"10549",
    "sg:province":"NY",
    "sg:tags":[
        "manufacture",
        "transmission",
        "rebuilt",
        "new",
        "bus"
    ],
    "wof:name":"De Feo Transit Mfg Sup",
    "wof:placetype":"venue"
},
  "geometry": {"coordinates":[-73.736407,41.191865],"type":"Point"}
}