{
  "type": "Feature",
  "properties": {
    "addr:full":"4202 Acme Rd Frankfort NY 13340",
    "addr:housenumber":"4202",
    "addr:postcode":"13340",
    "addr:street":"Acme Rd",
    "iso:country":"US",
    "sg:address":"4202 Acme Rd",
    "sg:city":"Frankfort",
    "sg:classifiers":[
        {
            "category":"Autos & Motor Vehicles",
            "subcategory":"Automobile Sales",
            "type":"Retail Goods"
        }
    ],
    "sg:phone":"+1 315 894 2019",
    "sg:postcode":"13340",
    "sg:province":"NY",
    "sg:tags":[
        "car",
        "dealer"
    ],
    "wof:name":"Crimmins Automotive Sales",
    "wof:placetype":"venue"
},
  "geometry": {"coordinates":[-75.06160300000001,43.030611],"type":"Point"}
}