{
  "type": "Feature",
  "properties": {
    "addr:full":"70 Roslyn Rd Roslyn Heights NY 11577",
    "addr:housenumber":"70",
    "addr:postcode":"11577",
    "addr:street":"Roslyn Rd",
    "iso:country":"US",
    "sg:address":"70 Roslyn Rd",
    "sg:city":"Roslyn Heights",
    "sg:classifiers":[
        {
            "category":"Health Services",
            "subcategory":"Health Practitioner",
            "type":"Services"
        }
    ],
    "sg:phone":"+1 516 484 2914",
    "sg:postcode":"11577",
    "sg:province":"NY",
    "sg:tags":[
        "psychologist"
    ],
    "wof:name":"Absolute Counseling",
    "wof:placetype":"venue"
},
  "geometry": {"coordinates":[-73.640697,40.791452],"type":"Point"}
}