{
  "type": "Feature",
  "properties": {
    "addr:full":"1375 Ridge Rd Lewiston NY 14092",
    "addr:housenumber":"1375",
    "addr:postcode":"14092",
    "addr:street":"Ridge Rd",
    "iso:country":"US",
    "sg:address":"1375 Ridge Rd",
    "sg:city":"Lewiston",
    "sg:classifiers":[
        {
            "category":"Government",
            "subcategory":"Office",
            "type":"Public Place"
        }
    ],
    "sg:phone":"+1 716 754 8213",
    "sg:postcode":"14092",
    "sg:province":"NY",
    "sg:tags":[
        "township",
        "government-city",
        "village"
    ],
    "wof:name":"Department Of Public Work",
    "wof:placetype":"venue"
},
  "geometry": {"coordinates":[-78.983543,43.178841],"type":"Point"}
}