{
  "type": "Feature",
  "properties": {
    "addr:full":"600 Northern Blvd Great Neck NY 11021",
    "addr:housenumber":"600",
    "addr:postcode":"11021",
    "addr:street":"Northern Blvd",
    "iso:country":"US",
    "sg:address":"600 Northern Blvd",
    "sg:city":"Great Neck",
    "sg:classifiers":[
        {
            "category":"Health Services",
            "subcategory":"Doctor",
            "type":"Services"
        }
    ],
    "sg:phone":"+1 516 487 0004",
    "sg:postcode":"11021",
    "sg:province":"NY",
    "sg:tags":[
        "medical",
        "imaging"
    ],
    "wof:name":"Geat Neck Stand Up MRI",
    "wof:placetype":"venue"
},
  "geometry": {"coordinates":[-73.715942,40.782286],"type":"Point"}
}