{
  "type": "Feature",
  "properties": {
    "addr:full":"170-172 Cannal St #3FL New York NY 10013",
    "addr:housenumber":"170-172",
    "addr:postcode":"10013",
    "addr:street":"Cannal St # 3Fl",
    "iso:country":"US",
    "sg:address":"170-172 Cannal St #3FL",
    "sg:city":"New York",
    "sg:classifiers":[
        {
            "category":"Personal",
            "subcategory":"Skin Care",
            "type":"Services"
        }
    ],
    "sg:phone":"+1 212 925 5114",
    "sg:postcode":"10013",
    "sg:province":"NY",
    "sg:website":"www.myfacialspa.com",
    "wof:name":"Facial Spa",
    "wof:placetype":"venue"
},
  "geometry": {"coordinates":[-73.99746399999999,40.716484],"type":"Point"}
}