{
  "type": "Feature",
  "properties": {
    "iso:country":"US",
    "sg:address":"109 W 42nd St",
    "sg:city":"New York",
    "sg:classifiers":[
        {
            "category":"Shopping",
            "subcategory":"Mobile Phones",
            "type":"Retail Goods"
        }
    ],
    "sg:phone":"+1 212 944 5686",
    "sg:postcode":"10036",
    "sg:province":"NY",
    "sg:website":"www.sprint.com",
    "wof:name":"Sprint",
    "wof:placetype":"venue"
},
  "geometry": {"coordinates":[-73.984398,40.754799],"type":"Point"}
}