{
  "type": "Feature",
  "properties": {
    "addr:full":"1188 Salt Rd Webster NY 14580",
    "addr:housenumber":"1188",
    "addr:postcode":"14580",
    "addr:street":"Salt Rd",
    "iso:country":"US",
    "sg:address":"1188 Salt Rd",
    "sg:city":"Webster",
    "sg:classifiers":[
        {
            "category":"Recreation",
            "type":"Entertainment"
        }
    ],
    "sg:phone":"+1 585 872 9924",
    "sg:postcode":"14580",
    "sg:province":"NY",
    "sg:tags":[
        "boarding",
        "horse",
        "lesson",
        "show"
    ],
    "wof:name":"Huntington Meadow Stables",
    "wof:placetype":"venue"
},
  "geometry": {"coordinates":[-77.400302,43.186938],"type":"Point"}
}