{
  "type": "Feature",
  "properties": {
    "iso:country":"US",
    "sg:address":"130 Centerport Rd",
    "sg:city":"Centerport",
    "sg:classifiers":[
        {
            "category":"Professional",
            "subcategory":"Lawyer & Legal Services",
            "type":"Services"
        }
    ],
    "sg:phone":"+1 800 734 1272",
    "sg:postcode":"11721",
    "sg:province":"NY",
    "wof:name":"Maddalone Joseph R",
    "wof:placetype":"venue"
},
  "geometry": {"coordinates":[-73.369895,40.884639],"type":"Point"}
}