{
  "type": "Feature",
  "properties": {
    "addr:full":"152 Watchogue Rd Staten Island NY 10314",
    "addr:housenumber":"152",
    "addr:postcode":"10314",
    "addr:street":"Watchogue Rd",
    "iso:country":"US",
    "sg:address":"152 Watchogue Rd",
    "sg:city":"Staten Island",
    "sg:classifiers":[
        {
            "category":"Home & Garden",
            "subcategory":"Building Materials",
            "type":"Retail Goods"
        }
    ],
    "sg:phone":"+1 718 650 0200",
    "sg:postcode":"10314",
    "sg:province":"NY",
    "sg:tags":[
        "shower",
        "door",
        "enclosure"
    ],
    "wof:name":"Primaseal",
    "wof:placetype":"venue"
},
  "geometry": {"coordinates":[-74.13431,40.615351],"type":"Point"}
}