{
  "type": "Feature",
  "properties": {
    "iso:country":"US",
    "sg:address":"23 Main St",
    "sg:city":"Mt Kisco",
    "sg:classifiers":[
        {
            "category":"Shopping",
            "type":"Retail Goods"
        }
    ],
    "sg:phone":"+1 914 666 2938",
    "sg:postcode":"10549",
    "sg:province":"NY",
    "sg:tags":[
        "art",
        "gallery",
        "dealer"
    ],
    "wof:name":"Art & Frame Gallery",
    "wof:placetype":"venue"
},
  "geometry": {"coordinates":[-73.726615,41.206952],"type":"Point"}
}