{
  "type": "Feature",
  "properties": {
    "iso:country":"US",
    "sg:address":"215 Co Rd 128",
    "sg:city":"Gloversville",
    "sg:classifiers":[
        {
            "category":"Health Services",
            "subcategory":"Doctor",
            "type":"Services"
        }
    ],
    "sg:phone":"+1 518 773 7306",
    "sg:postcode":"12095",
    "sg:province":"NY",
    "sg:tags":[
        "physician",
        "surgeon",
        "orthopedic"
    ],
    "wof:name":"Orthopedic & Wellness Center",
    "wof:placetype":"venue"
},
  "geometry": {"coordinates":[-74.34465400000001,43.031984],"type":"Point"}
}