{
  "type": "Feature",
  "properties": {
    "addr:full":"5115 Spring St Ashville NY 14710",
    "addr:housenumber":"5115",
    "addr:postcode":"14710",
    "addr:street":"Spring St",
    "iso:country":"US",
    "sg:address":"5115 Spring St",
    "sg:city":"Ashville",
    "sg:classifiers":[
        {
            "category":"Manufacturing",
            "subcategory":"Wood Products",
            "type":"Manufacturing & Wholesale Goods"
        }
    ],
    "sg:phone":"+1   ",
    "sg:postcode":"14710",
    "sg:province":"NY",
    "sg:tags":[
        "metalwork",
        "architectural",
        "mfg"
    ],
    "wof:name":"Freedom Outdoors",
    "wof:placetype":"venue"
},
  "geometry": {"coordinates":[-79.393213,42.130273],"type":"Point"}
}