{
  "type": "Feature",
  "properties": {
    "addr:full":"1180 Rockland Avenue Staten Island NY 10314",
    "addr:housenumber":"1180",
    "addr:postcode":"10314",
    "addr:street":"Rockland Avenue",
    "iso:country":"US",
    "sg:address":"1180 Rockland Avenue",
    "sg:city":"Staten Island",
    "sg:classifiers":[
        {
            "category":"Place Of Worship",
            "subcategory":"Synagogue",
            "type":"Public Place"
        }
    ],
    "sg:phone":"+1 718 494 8935",
    "sg:postcode":"10314",
    "sg:province":"NY",
    "wof:name":"Aur Torah Sephardic Minyan",
    "wof:placetype":"venue"
},
  "geometry": {"coordinates":[-74.155922,40.593076],"type":"Point"}
}