{
  "type": "Feature",
  "properties": {
    "addr:full":"760 Columbus Ave New York NY 10025",
    "addr:housenumber":"760",
    "addr:postcode":"10025",
    "addr:street":"Columbus Ave",
    "iso:country":"US",
    "sg:address":"760 Columbus Ave",
    "sg:city":"New York",
    "sg:classifiers":[
        {
            "category":"Restaurant",
            "type":"Food & Drink"
        }
    ],
    "sg:phone":"+1 212 866 3000",
    "sg:postcode":"10025",
    "sg:province":"NY",
    "sg:tags":[
        "eating"
    ],
    "wof:name":"Central Park Cafe",
    "wof:placetype":"venue"
},
  "geometry": {"coordinates":[-73.96669799999999,40.7938],"type":"Point"}
}