{
  "type": "Feature",
  "properties": {
    "iso:country":"US",
    "sg:address":"5322 Church Ave",
    "sg:city":"Brooklyn",
    "sg:classifiers":[
        {
            "category":"Government",
            "subcategory":"Office",
            "type":"Public Place"
        }
    ],
    "sg:phone":"+1 718 485 7462",
    "sg:postcode":"11203",
    "sg:province":"NY",
    "sg:tags":[
        "armed",
        "force",
        "recruiting"
    ],
    "wof:name":"US Army Recruiting",
    "wof:placetype":"venue"
},
  "geometry": {"coordinates":[-73.926704,40.652301],"type":"Point"}
}