{
  "type": "Feature",
  "properties": {
    "addr:full":"845 United Nations Plz New York NY 10017",
    "addr:housenumber":"845",
    "addr:postcode":"10017",
    "addr:street":"United Nations Plz",
    "iso:country":"US",
    "sg:address":"845 United Nations Plz",
    "sg:city":"New York",
    "sg:classifiers":[
        {
            "category":"Real Estate",
            "subcategory":"Real Estate Agent",
            "type":"Services"
        }
    ],
    "sg:phone":"+1 212 758 9381",
    "sg:postcode":"10017",
    "sg:province":"NY",
    "wof:name":"Shusterman  Fima",
    "wof:placetype":"venue"
},
  "geometry": {"coordinates":[-73.967012,40.752597],"type":"Point"}
}