{
  "type": "Feature",
  "properties": {
    "addr:full":"1072 Courtland Dr Bay Shore NY 11706",
    "addr:housenumber":"1072",
    "addr:postcode":"11706",
    "addr:street":"Courtland Dr",
    "iso:country":"US",
    "sg:address":"1072 Courtland Dr",
    "sg:city":"Bay Shore",
    "sg:classifiers":[
        {
            "category":"Building & Trades",
            "subcategory":"Electrical",
            "type":"Services"
        }
    ],
    "sg:phone":"+1 631 665 8832",
    "sg:postcode":"11706",
    "sg:province":"NY",
    "sg:tags":[
        "electrical",
        "contractor"
    ],
    "wof:name":"Mega Watt Electric",
    "wof:placetype":"venue"
},
  "geometry": {"coordinates":[-73.27809600000001,40.72275],"type":"Point"}
}