{
  "type": "Feature",
  "properties": {
    "iso:country":"US",
    "sg:address":"4 Oxford Xing",
    "sg:city":"New Hartford",
    "sg:classifiers":[
        {
            "category":"Health Services",
            "subcategory":"Doctor",
            "type":"Services"
        }
    ],
    "sg:phone":"+1 315 797 1623",
    "sg:postcode":"13413",
    "sg:province":"NY",
    "sg:tags":[
        "physician",
        "surgeon",
        "medical"
    ],
    "wof:name":"Gordon Fung MD",
    "wof:placetype":"venue"
},
  "geometry": {"coordinates":[-75.278854,43.054199],"type":"Point"}
}