{
  "type": "Feature",
  "properties": {
    "addr:full":"1144 Flatbush Ave Brooklyn NY 11226",
    "addr:housenumber":"1144",
    "addr:postcode":"11226",
    "addr:street":"Flatbush Ave",
    "iso:country":"US",
    "sg:address":"1144 Flatbush Ave",
    "sg:city":"Brooklyn",
    "sg:classifiers":[
        {
            "category":"Organizations",
            "subcategory":"Religious Organization",
            "type":"Services"
        }
    ],
    "sg:phone":"+1 718 287 2121",
    "sg:postcode":"11226",
    "sg:province":"NY",
    "sg:tags":[
        "church"
    ],
    "wof:name":"Emmaus Seventh Day Adventist",
    "wof:placetype":"venue"
},
  "geometry": {"coordinates":[-73.95763700000001,40.642597],"type":"Point"}
}