{
  "type": "Feature",
  "properties": {
    "addr:full":"1040 University Ave Ste 1 Rochester NY 14607",
    "addr:housenumber":"1040",
    "addr:postcode":"14607",
    "addr:street":"University Ave Ste 1",
    "iso:country":"US",
    "sg:address":"1040 University Ave Ste 1",
    "sg:city":"Rochester",
    "sg:classifiers":[
        {
            "category":"Banks & Credit Unions",
            "subcategory":"Investment Brokerage",
            "type":"Services"
        },
        {
            "category":"Insurance",
            "subcategory":"Hazard Insurance",
            "type":"Services"
        },
        {
            "category":"Banks & Credit Unions",
            "subcategory":"Financial Services",
            "type":"Services"
        }
    ],
    "sg:phone":"+1 585 461 6483",
    "sg:postcode":"14607",
    "sg:province":"NY",
    "sg:tags":[
        "advisory",
        "commercial",
        "business"
    ],
    "wof:name":"American Portfolio",
    "wof:placetype":"venue"
},
  "geometry": {"coordinates":[-77.574105,43.15263],"type":"Point"}
}