{
  "type": "Feature",
  "properties": {
    "iso:country":"US",
    "sg:address":"211 S Park Ave",
    "sg:city":"Buffalo",
    "sg:classifiers":[
        {
            "category":"Bars & Pubs",
            "type":"Food & Drink"
        }
    ],
    "sg:phone":"+1   ",
    "sg:postcode":"14204",
    "sg:province":"NY",
    "sg:tags":[
        "drinking",
        "eating"
    ],
    "wof:name":"Malamute Tavern",
    "wof:placetype":"venue"
},
  "geometry": {"coordinates":[-78.870975,42.872808],"type":"Point"}
}