{
  "type": "Feature",
  "properties": {
    "iso:country":"US",
    "sg:address":"435 Flower Ave W",
    "sg:city":"Watertown",
    "sg:classifiers":[
        {
            "category":"Sports & Exercise",
            "subcategory":"Golf",
            "type":"Entertainment"
        }
    ],
    "sg:phone":"+1 315 788 1410",
    "sg:postcode":"13601",
    "sg:province":"NY",
    "sg:tags":[
        "course"
    ],
    "wof:name":"Ives Hill Country Club Inc",
    "wof:placetype":"venue"
},
  "geometry": {"coordinates":[-75.922228,43.96741],"type":"Point"}
}