{
  "type": "Feature",
  "properties": {
    "addr:full":"183 Cathedral Ave Hempstead NY 11550",
    "addr:housenumber":"183",
    "addr:postcode":"11550",
    "addr:street":"Cathedral Ave",
    "iso:country":"US",
    "sg:address":"183 Cathedral Ave",
    "sg:city":"Hempstead",
    "sg:classifiers":[
        {
            "category":"Shopping",
            "subcategory":"Discount & Variety Stores",
            "type":"Retail Goods"
        }
    ],
    "sg:phone":"+1   ",
    "sg:postcode":"11550",
    "sg:province":"NY",
    "sg:tags":[
        "merchandise",
        "general"
    ],
    "wof:name":"Quickstar",
    "wof:placetype":"venue"
},
  "geometry": {"coordinates":[-73.63694700000001,40.712681],"type":"Point"}
}