{
  "type": "Feature",
  "properties": {
    "iso:country":"US",
    "sg:address":"105 Development Ct",
    "sg:city":"Kingston",
    "sg:classifiers":[
        {
            "category":"Social Services",
            "subcategory":"Adult Care",
            "type":"Services"
        }
    ],
    "sg:phone":"+1 845 331 9360",
    "sg:postcode":"12401",
    "sg:province":"NY",
    "sg:tags":[
        "organization",
        "senior",
        "citizen"
    ],
    "wof:name":"Kingston Senior Net Learning",
    "wof:placetype":"venue"
},
  "geometry": {"coordinates":[-73.99687900000001,41.946418],"type":"Point"}
}