{
  "type": "Feature",
  "properties": {
    "iso:country":"US",
    "sg:address":"1603 Myrtle Ave",
    "sg:city":"Brooklyn",
    "sg:classifiers":[
        {
            "category":"Shopping",
            "subcategory":"Hobbies, Toys, & Games",
            "type":"Retail Goods"
        }
    ],
    "sg:postcode":"11237",
    "sg:province":"NY",
    "sg:tags":[
        "shop",
        "hobby"
    ],
    "wof:name":"J & B Watch Repair and Computer Hospital",
    "wof:placetype":"venue"
},
  "geometry": {"coordinates":[-73.912032,40.699459],"type":"Point"}
}