{
  "type": "Feature",
  "properties": {
    "iso:country":"US",
    "sg:address":"400 Philo St",
    "sg:city":"New Windsor",
    "sg:classifiers":[
        {
            "category":"Real Estate",
            "subcategory":"Real Estate Agent",
            "type":"Services"
        }
    ],
    "sg:phone":"+1 845 569 7224",
    "sg:postcode":"12553",
    "sg:province":"NY",
    "wof:name":"Jjs Realty Inc",
    "wof:placetype":"venue"
},
  "geometry": {"coordinates":[-74.05824,41.484322],"type":"Point"}
}