{
  "type": "Feature",
  "properties": {
    "iso:country":"US",
    "sg:address":"3870 W Walworth Rd",
    "sg:city":"Macedon",
    "sg:classifiers":[
        {
            "category":"Government",
            "subcategory":"Fire Station",
            "type":"Public Place"
        }
    ],
    "sg:phone":"+1 315 986 2241",
    "sg:postcode":"14502",
    "sg:province":"NY",
    "sg:tags":[
        "department",
        "protection"
    ],
    "wof:name":"West Walworth Fire Department",
    "wof:placetype":"venue"
},
  "geometry": {"coordinates":[-77.346717,43.143542],"type":"Point"}
}