{
  "type": "Feature",
  "properties": {
    "addr:full":"75 Cheltenham Rd Rochester NY 14612",
    "addr:housenumber":"75",
    "addr:postcode":"14612",
    "addr:street":"Cheltenham Rd",
    "iso:country":"US",
    "sg:address":"75 Cheltenham Rd",
    "sg:city":"Rochester",
    "sg:classifiers":[
        {
            "category":"Shopping",
            "subcategory":"Clothing, Apparel, & Fashions",
            "type":"Retail Goods"
        }
    ],
    "sg:phone":"+1 585 663 0740",
    "sg:postcode":"14612",
    "sg:province":"NY",
    "sg:tags":[
        "lingerie"
    ],
    "wof:name":"Cupid's Place",
    "wof:placetype":"venue"
},
  "geometry": {"coordinates":[-77.624304,43.221384],"type":"Point"}
}