{
  "type": "Feature",
  "properties": {
    "iso:country":"US",
    "sg:address":"1 Croley St",
    "sg:city":"Huntington",
    "sg:classifiers":[
        {
            "category":"Travel",
            "subcategory":"Travel Agent",
            "type":"Entertainment"
        }
    ],
    "sg:phone":"+1   ",
    "sg:postcode":"11743",
    "sg:province":"NY",
    "sg:tags":[
        "operator",
        "tour"
    ],
    "wof:name":"M & V Transportation Inc",
    "wof:placetype":"venue"
},
  "geometry": {"coordinates":[-73.36993099999999,40.844802],"type":"Point"}
}