{
  "type": "Feature",
  "properties": {
    "iso:country":"US",
    "sg:address":"63112 Woodhaven Blvd",
    "sg:city":"Rego Park",
    "sg:classifiers":[
        {
            "category":"Banks & Credit Unions",
            "subcategory":"Financial Services",
            "type":"Services"
        }
    ],
    "sg:phone":"+1 718 416 4100",
    "sg:postcode":"11374",
    "sg:province":"NY",
    "sg:tags":[
        "broker",
        "mortgage"
    ],
    "wof:name":"Expert Mortgage Grp Inc",
    "wof:placetype":"venue"
},
  "geometry": {"coordinates":[-73.866876,40.721651],"type":"Point"}
}