{
  "type": "Feature",
  "properties": {
    "addr:full":"2604 Elmwood Ave Rochester NY 14618",
    "addr:housenumber":"2604",
    "addr:postcode":"14618",
    "addr:street":"Elmwood Ave",
    "iso:country":"US",
    "sg:address":"2604 Elmwood Ave",
    "sg:city":"Rochester",
    "sg:classifiers":[
        {
            "category":"Personal",
            "type":"Services"
        }
    ],
    "sg:phone":"+1 585 256 2866",
    "sg:postcode":"14618",
    "sg:province":"NY",
    "sg:tags":[
        "credit",
        "debt",
        "counseling"
    ],
    "wof:name":"City Management Co",
    "wof:placetype":"venue"
},
  "geometry": {"coordinates":[-77.56673600000001,43.126418],"type":"Point"}
}