{
  "type": "Feature",
  "properties": {
    "addr:full":"812 State St Watertown NY 13601",
    "addr:housenumber":"812",
    "addr:postcode":"13601",
    "addr:street":"State St",
    "iso:country":"US",
    "sg:address":"812 State St",
    "sg:city":"Watertown",
    "sg:classifiers":[
        {
            "category":"Organizations",
            "subcategory":"Professional Association",
            "type":"Services"
        }
    ],
    "sg:phone":"+1 315 785 9440",
    "sg:postcode":"13601",
    "sg:province":"NY",
    "sg:tags":[
        "social"
    ],
    "wof:name":"Mohawk Valy Lerng Disably Asoc",
    "wof:placetype":"venue"
},
  "geometry": {"coordinates":[-75.898133,43.971603],"type":"Point"}
}