{
  "type": "Feature",
  "properties": {
    "iso:country":"US",
    "sg:address":"28 E 35th St Fl 2",
    "sg:city":"New York",
    "sg:classifiers":[
        {
            "category":"Place Of Worship",
            "subcategory":"Synagogue",
            "type":"Public Place"
        }
    ],
    "sg:phone":"+1 212 679 8580",
    "sg:postcode":"10016",
    "sg:province":"NY",
    "wof:name":"Metropolitan Synagogue of Ny",
    "wof:placetype":"venue"
},
  "geometry": {"coordinates":[-73.98189000000001,40.747936],"type":"Point"}
}