{
  "type": "Feature",
  "properties": {
    "iso:country":"US",
    "sg:address":"2990 Webster Ave",
    "sg:city":"Bronx",
    "sg:classifiers":[
        {
            "category":"Building & Trades",
            "subcategory":"Construction",
            "type":"Services"
        }
    ],
    "sg:phone":"+1 718 364 5524",
    "sg:postcode":"10458",
    "sg:province":"NY",
    "sg:tags":[
        "general",
        "contractor"
    ],
    "wof:name":"Anytime Construction",
    "wof:placetype":"venue"
},
  "geometry": {"coordinates":[-73.88551200000001,40.866032],"type":"Point"}
}