{
  "type": "Feature",
  "properties": {
    "addr:full":"22 Beaver St New York NY 10004",
    "addr:housenumber":"22",
    "addr:postcode":"10004",
    "addr:street":"Beaver St",
    "iso:country":"US",
    "sg:address":"22 Beaver St",
    "sg:city":"New York",
    "sg:classifiers":[
        {
            "category":"Food & Beverages",
            "subcategory":"Bakery",
            "type":"Retail Goods"
        }
    ],
    "sg:phone":"+1 212 482 0619",
    "sg:postcode":"10004",
    "sg:province":"NY",
    "sg:tags":[
        "deli"
    ],
    "wof:name":"Traders Cafe",
    "wof:placetype":"venue"
},
  "geometry": {"coordinates":[-74.01190200000001,40.704899],"type":"Point"}
}