{
  "type": "Feature",
  "properties": {
    "addr:full":"14 Sycamore Ct Fishkill NY 12524",
    "addr:housenumber":"14",
    "addr:postcode":"12524",
    "addr:street":"Sycamore Ct",
    "iso:country":"US",
    "sg:address":"14 Sycamore Ct",
    "sg:city":"Fishkill",
    "sg:classifiers":[
        {
            "category":"Professional",
            "type":"Services"
        }
    ],
    "sg:phone":"+1 845 897 2080",
    "sg:postcode":"12524",
    "sg:province":"NY",
    "sg:tags":[
        "establishment"
    ],
    "wof:name":"Roundhill Assocs Inc",
    "wof:placetype":"venue"
},
  "geometry": {"coordinates":[-73.924352,41.538414],"type":"Point"}
}