{
  "type": "Feature",
  "properties": {
    "iso:country":"US",
    "sg:address":"63 Mountbatten St",
    "sg:city":"Rochester",
    "sg:classifiers":[
        {
            "category":"Home & Garden",
            "subcategory":"Building Materials",
            "type":"Retail Goods"
        }
    ],
    "sg:phone":"+1 585 319 3437",
    "sg:postcode":"14623",
    "sg:province":"NY",
    "sg:tags":[
        "sand",
        "gravel"
    ],
    "wof:name":"Christine M Syracusa",
    "wof:placetype":"venue"
},
  "geometry": {"coordinates":[-77.611065,43.07644],"type":"Point"}
}