{
  "type": "Feature",
  "properties": {
    "addr:full":"928 Clinton Ave S Rochester NY 14620",
    "addr:housenumber":"928",
    "addr:postcode":"14620",
    "addr:street":"Clinton Ave S",
    "iso:country":"US",
    "sg:address":"928 Clinton Ave S",
    "sg:city":"Rochester",
    "sg:classifiers":[
        {
            "category":"Personal",
            "subcategory":"Beauty Salon",
            "type":"Services"
        }
    ],
    "sg:phone":"+1 585 473 8340",
    "sg:postcode":"14620",
    "sg:province":"NY",
    "sg:website":"http://www.thestylestudiosalon.com",
    "wof:name":"Style Studio Salon",
    "wof:placetype":"venue"
},
  "geometry": {"coordinates":[-77.59626900000001,43.139995],"type":"Point"}
}