{
  "type": "Feature",
  "properties": {
    "iso:country":"US",
    "sg:address":"5 Cottonwood Dr",
    "sg:city":"Dix Hills",
    "sg:classifiers":[
        {
            "category":"Health Services",
            "subcategory":"Health Practitioner",
            "type":"Services"
        }
    ],
    "sg:phone":"+1 631 421 2907",
    "sg:postcode":"11746",
    "sg:province":"NY",
    "sg:tags":[
        "psychologist"
    ],
    "wof:name":"Thomas J Raab",
    "wof:placetype":"venue"
},
  "geometry": {"coordinates":[-73.348828,40.816573],"type":"Point"}
}