{
  "type": "Feature",
  "properties": {
    "addr:full":"10 Washington Ave Hastings On Hdsn NY 10706",
    "addr:housenumber":"10",
    "addr:postcode":"10706",
    "addr:street":"Washington Ave",
    "iso:country":"US",
    "sg:address":"10 Washington Ave",
    "sg:city":"Hastings On Hdsn",
    "sg:classifiers":[
        {
            "category":"Education",
            "subcategory":"Dance Studio",
            "type":"Public Place"
        }
    ],
    "sg:phone":"+1 914 478 5825",
    "sg:postcode":"10706",
    "sg:province":"NY",
    "sg:tags":[
        "instruction",
        "dancing"
    ],
    "wof:name":"Broadway Training Ctr",
    "wof:placetype":"venue"
},
  "geometry": {"coordinates":[-73.88388500000001,40.992655],"type":"Point"}
}