{
  "type": "Feature",
  "properties": {
    "addr:full":"744 S Meadow St Ithaca NY 14850",
    "addr:housenumber":"744",
    "addr:postcode":"14850",
    "addr:street":"S Meadow St",
    "iso:country":"US",
    "sg:address":"744 S Meadow St",
    "sg:city":"Ithaca",
    "sg:classifiers":[
        {
            "category":"Shopping",
            "subcategory":"Shoes",
            "type":"Retail Goods"
        }
    ],
    "sg:phone":"+1 607 272 1430",
    "sg:postcode":"14850",
    "sg:province":"NY",
    "sg:tags":[
        "store"
    ],
    "wof:name":"Meldisco K-M Ithaca Ny Inc",
    "wof:placetype":"venue"
},
  "geometry": {"coordinates":[-76.507946,42.430649],"type":"Point"}
}