{
  "type": "Feature",
  "properties": {
    "iso:country":"US",
    "sg:address":"134 Pike St",
    "sg:city":"Port Jervis",
    "sg:classifiers":[
        {
            "category":"Government",
            "subcategory":"Office",
            "type":"Public Place"
        }
    ],
    "sg:phone":"+1 845 858 4045",
    "sg:postcode":"12771",
    "sg:province":"NY",
    "sg:tags":[
        "village"
    ],
    "wof:name":"Port Jervis Youth Community Ct",
    "wof:placetype":"venue"
},
  "geometry": {"coordinates":[-74.69198400000001,41.375706],"type":"Point"}
}