{
  "type": "Feature",
  "properties": {
    "iso:country":"US",
    "sg:address":"54 Greene Rd",
    "sg:city":"Greenfield Center",
    "sg:classifiers":[
        {
            "category":"Shopping",
            "type":"Retail Goods"
        },
        {
            "category":"Professional",
            "subcategory":"Business Services",
            "type":"Services"
        }
    ],
    "sg:phone":"+1 518 893 2651",
    "sg:postcode":"12833",
    "sg:province":"NY",
    "sg:tags":[
        "merchandise",
        "auctioneer"
    ],
    "wof:name":"Northeast Auction Associates",
    "wof:placetype":"venue"
},
  "geometry": {"coordinates":[-73.84904899999999,43.157384],"type":"Point"}
}