{
  "type": "Feature",
  "properties": {
    "addr:full":"1626 Bruckner Blvd Bronx NY 10473",
    "addr:housenumber":"1626",
    "addr:postcode":"10473",
    "addr:street":"Bruckner Blvd",
    "iso:country":"US",
    "sg:address":"1626 Bruckner Blvd",
    "sg:city":"Bronx",
    "sg:classifiers":[
        {
            "category":"Banks & Credit Unions",
            "subcategory":"Bank",
            "type":"Services"
        }
    ],
    "sg:phone":"+1 718 589 1323",
    "sg:postcode":"10473",
    "sg:province":"NY",
    "sg:website":"www.ridgewoodbank.com",
    "wof:name":"Ridgewood Savings Bank",
    "wof:placetype":"venue"
},
  "geometry": {"coordinates":[-73.874178,40.823841],"type":"Point"}
}