{
  "type": "Feature",
  "properties": {
    "iso:country":"US",
    "sg:address":"80 Douglas Rd",
    "sg:city":"Rochester",
    "sg:classifiers":[
        {
            "category":"Real Estate",
            "subcategory":"Real Estate Operator",
            "type":"Services"
        }
    ],
    "sg:phone":"+1 585 271 2404",
    "sg:postcode":"14610",
    "sg:province":"NY",
    "sg:tags":[
        "building",
        "nonresidential"
    ],
    "wof:name":"Ajax Road Realty",
    "wof:placetype":"venue"
},
  "geometry": {"coordinates":[-77.57086700000001,43.147554],"type":"Point"}
}