{
  "type": "Feature",
  "properties": {
    "iso:country":"US",
    "sg:address":"136 N Allen St",
    "sg:city":"Albany",
    "sg:classifiers":[
        {
            "category":"Shopping",
            "subcategory":"News",
            "type":"Retail Goods"
        }
    ],
    "sg:phone":"+1 518 438 5955",
    "sg:postcode":"12206",
    "sg:province":"NY",
    "sg:tags":[
        "dealer"
    ],
    "wof:name":"Happy Days Deli Grocery",
    "wof:placetype":"venue"
},
  "geometry": {"coordinates":[-73.78697,42.671253],"type":"Point"}
}