{
  "type": "Feature",
  "properties": {
    "iso:country":"US",
    "sg:address":"1755 US Hwy 9",
    "sg:city":"Germantown",
    "sg:classifiers":[
        {
            "category":"Manufacturing",
            "subcategory":"Tools & Machinery",
            "type":"Manufacturing & Wholesale Goods"
        }
    ],
    "sg:phone":"+1   ",
    "sg:postcode":"12526",
    "sg:province":"NY",
    "sg:tags":[
        "electrical",
        "mfg"
    ],
    "wof:name":"B & H Cables Inc",
    "wof:placetype":"venue"
},
  "geometry": {"coordinates":[-73.833641,42.077551],"type":"Point"}
}