{
  "type": "Feature",
  "properties": {
    "addr:full":"135 E 22 St New York NY 10010",
    "addr:housenumber":"135;22",
    "addr:postcode":"10010",
    "addr:street":"E",
    "iso:country":"US",
    "sg:address":"135 E 22 St",
    "sg:city":"New York",
    "sg:classifiers":[
        {
            "category":"Education",
            "subcategory":"College",
            "type":"Public Place"
        }
    ],
    "sg:phone":"+1 212 387 1130",
    "sg:postcode":"10010",
    "sg:province":"NY",
    "sg:tags":[
        "academic",
        "school"
    ],
    "wof:name":"Baruch College Fund",
    "wof:placetype":"venue"
},
  "geometry": {"coordinates":[-73.983667,40.738269],"type":"Point"}
}