{
  "type": "Feature",
  "properties": {
    "addr:full":"1679 Popham Ave Bronx NY 10453",
    "addr:housenumber":"1679",
    "addr:postcode":"10453",
    "addr:street":"Popham Ave",
    "iso:country":"US",
    "sg:address":"1679 Popham Ave",
    "sg:city":"Bronx",
    "sg:classifiers":[
        {
            "category":"Social Services",
            "type":"Services"
        }
    ],
    "sg:phone":"+1   ",
    "sg:postcode":"10453",
    "sg:province":"NY",
    "wof:name":"Hallely Cnsling Spiritus Svces",
    "wof:placetype":"venue"
},
  "geometry": {"coordinates":[-73.920959,40.848924],"type":"Point"}
}