{
  "type": "Feature",
  "properties": {
    "addr:full":"8 Tiller Ln Levittown NY 11756",
    "addr:housenumber":"8",
    "addr:postcode":"11756",
    "addr:street":"Tiller Ln",
    "iso:country":"US",
    "sg:address":"8 Tiller Ln",
    "sg:city":"Levittown",
    "sg:classifiers":[
        {
            "category":"Manufacturing",
            "subcategory":"Buildings",
            "type":"Manufacturing & Wholesale Goods"
        },
        {
            "category":"Building & Trades",
            "subcategory":"Construction",
            "type":"Services"
        }
    ],
    "sg:phone":"+1 516 840 2699",
    "sg:postcode":"11756",
    "sg:province":"NY",
    "sg:tags":[
        "home",
        "builder",
        "contractor"
    ],
    "wof:name":"Pugliese Custom Builders I",
    "wof:placetype":"venue"
},
  "geometry": {"coordinates":[-73.50670599999999,40.736705],"type":"Point"}
}