{
  "type": "Feature",
  "properties": {
    "addr:full":"2890 Clinton St Buffalo NY 14224",
    "addr:housenumber":"2890",
    "addr:postcode":"14224",
    "addr:street":"Clinton St",
    "iso:country":"US",
    "sg:address":"2890 Clinton St",
    "sg:city":"Buffalo",
    "sg:classifiers":[
        {
            "category":"Retail",
            "subcategory":"Auto Repair",
            "type":"Services"
        }
    ],
    "sg:phone":"+1 716 822 8481",
    "sg:postcode":"14224",
    "sg:province":"NY",
    "wof:name":"Clinton Auto & Truck Svce",
    "wof:placetype":"venue"
},
  "geometry": {"coordinates":[-78.775497,42.867901],"type":"Point"}
}