{
  "type": "Feature",
  "properties": {
    "addr:full":"61 Van de Bogart Rd Woodstock NY 12498",
    "addr:housenumber":"61",
    "addr:postcode":"12498",
    "addr:street":"Van De Bogart Rd",
    "iso:country":"US",
    "sg:address":"61 Van de Bogart Rd",
    "sg:city":"Woodstock",
    "sg:classifiers":[
        {
            "category":"Manufacturing",
            "subcategory":"Tools & Machinery",
            "type":"Manufacturing & Wholesale Goods"
        }
    ],
    "sg:phone":"+1   ",
    "sg:postcode":"12498",
    "sg:province":"NY",
    "sg:tags":[
        "photographic",
        "mfg"
    ],
    "wof:name":"Riggin Design Inc",
    "wof:placetype":"venue"
},
  "geometry": {"coordinates":[-74.083893,42.0179],"type":"Point"}
}