{
  "type": "Feature",
  "properties": {
    "addr:full":"585 W 235th St Bronx NY 10463",
    "addr:housenumber":"585",
    "addr:postcode":"10463",
    "addr:street":"W 235Th St",
    "iso:country":"US",
    "sg:address":"585 W 235th St",
    "sg:city":"Bronx",
    "sg:classifiers":[
        {
            "category":"Arts & Performance",
            "subcategory":"Art Gallery",
            "type":"Entertainment"
        },
        {
            "category":"Farming",
            "subcategory":"Fish & Marine Products",
            "type":"Manufacturing & Wholesale Goods"
        },
        {
            "category":"Professional",
            "subcategory":"Art Services",
            "type":"Services"
        },
        {
            "category":"Shopping",
            "subcategory":"Crafts & Fabrics",
            "type":"Retail Goods"
        }
    ],
    "sg:phone":"+1 718 432 0632",
    "sg:postcode":"10463",
    "sg:province":"NY",
    "sg:tags":[
        "picture",
        "instruction",
        "consultant",
        "frame",
        "galleries",
        "framing"
    ],
    "wof:name":"Metro Framart",
    "wof:placetype":"venue"
},
  "geometry": {"coordinates":[-73.91113199999999,40.885868],"type":"Point"}
}