{
  "type": "Feature",
  "properties": {
    "addr:full":"40 Garden St Poughkeepsie NY 12601",
    "addr:housenumber":"40",
    "addr:postcode":"12601",
    "addr:street":"Garden St",
    "iso:country":"US",
    "sg:address":"40 Garden St",
    "sg:city":"Poughkeepsie",
    "sg:classifiers":[
        {
            "category":"Professional",
            "subcategory":"Engineering",
            "type":"Services"
        }
    ],
    "sg:phone":"+1 845 452 7515",
    "sg:postcode":"12601",
    "sg:province":"NY",
    "sg:tags":[
        "engineer"
    ],
    "wof:name":"Rohde Soyka & Andrews",
    "wof:placetype":"venue"
},
  "geometry": {"coordinates":[-73.925828,41.706579],"type":"Point"}
}