{
  "type": "Feature",
  "properties": {
    "addr:full":"800 E 38th St Brooklyn NY 11210",
    "addr:housenumber":"800",
    "addr:postcode":"11210",
    "addr:street":"E 38Th St",
    "iso:country":"US",
    "sg:address":"800 E 38th St",
    "sg:city":"Brooklyn",
    "sg:classifiers":[
        {
            "category":"Real Estate",
            "subcategory":"Real Estate Agent",
            "type":"Services"
        }
    ],
    "sg:phone":"+1 718 421 2385",
    "sg:postcode":"11210",
    "sg:province":"NY",
    "wof:name":"Annie's Home Sales",
    "wof:placetype":"venue"
},
  "geometry": {"coordinates":[-73.94028299999999,40.635706],"type":"Point"}
}