{
  "type": "Feature",
  "properties": {
    "addr:full":"6021 Day Hollow Rd Endicott NY 13760",
    "addr:housenumber":"6021",
    "addr:postcode":"13760",
    "addr:street":"Day Hollow Rd",
    "iso:country":"US",
    "sg:address":"6021 Day Hollow Rd",
    "sg:city":"Endicott",
    "sg:classifiers":[
        {
            "category":"Building & Trades",
            "subcategory":"Plumbing",
            "type":"Services"
        }
    ],
    "sg:phone":"+1 607 785 3876",
    "sg:postcode":"13760",
    "sg:province":"NY",
    "sg:tags":[
        "system",
        "contractor",
        "air conditioning"
    ],
    "wof:name":"Gary's Plumbing & Heating",
    "wof:placetype":"venue"
},
  "geometry": {"coordinates":[-76.113294,42.112897],"type":"Point"}
}