{
  "type": "Feature",
  "properties": {
    "addr:full":"2787 Monroe Ave Rochester NY 14618",
    "addr:housenumber":"2787",
    "addr:postcode":"14618",
    "addr:street":"Monroe Ave",
    "iso:country":"US",
    "sg:address":"2787 Monroe Ave",
    "sg:city":"Rochester",
    "sg:classifiers":[
        {
            "category":"Home & Garden",
            "subcategory":"Building Materials",
            "type":"Retail Goods"
        }
    ],
    "sg:phone":"+1 585 244 2563",
    "sg:postcode":"14618",
    "sg:province":"NY",
    "sg:tags":[
        "installs",
        "garage",
        "door"
    ],
    "wof:name":"Green Over Head Doors",
    "wof:placetype":"venue"
},
  "geometry": {"coordinates":[-77.548582,43.111556],"type":"Point"}
}