{
  "type": "Feature",
  "properties": {
    "iso:country":"US",
    "sg:address":"2638 Parkview Dr",
    "sg:city":"Niagara Falls",
    "sg:classifiers":[
        {
            "category":"Shopping",
            "subcategory":"Clothing, Apparel, & Fashions",
            "type":"Retail Goods"
        }
    ],
    "sg:phone":"+1 716 284 1369",
    "sg:postcode":"14305",
    "sg:province":"NY",
    "wof:name":"Fashions By Karen",
    "wof:placetype":"venue"
},
  "geometry": {"coordinates":[-79.016893,43.113198],"type":"Point"}
}