{
  "type": "Feature",
  "properties": {
    "addr:full":"80 Columbia St New York NY 10002",
    "addr:housenumber":"80",
    "addr:postcode":"10002",
    "addr:street":"Columbia",
    "iso:country":"US",
    "sg:address":"80 Columbia St",
    "sg:city":"New York",
    "sg:classifiers":[
        {
            "category":"Shopping",
            "subcategory":"Clothing, Apparel, & Fashions",
            "type":"Retail Goods"
        }
    ],
    "sg:phone":"+1   ",
    "sg:postcode":"10002",
    "sg:province":"NY",
    "wof:name":"My Tee Enterprises",
    "wof:placetype":"venue"
},
  "geometry": {"coordinates":[-73.97948599999999,40.718528],"type":"Point"}
}