{
  "type": "Feature",
  "properties": {
    "iso:country":"US",
    "sg:address":"4295 Albany Post Rd",
    "sg:city":"Hyde Park",
    "sg:classifiers":[
        {
            "category":"Professional",
            "subcategory":"Accounting & Tax Preparation",
            "type":"Services"
        }
    ],
    "sg:phone":"+1   ",
    "sg:postcode":"12538",
    "sg:province":"NY",
    "wof:name":"Vangor Cornell S PC",
    "wof:placetype":"venue"
},
  "geometry": {"coordinates":[-73.93473400000001,41.788358],"type":"Point"}
}