{
  "type": "Feature",
  "properties": {
    "addr:full":"68 Westchester Sq Bronx NY 10461",
    "addr:housenumber":"68",
    "addr:postcode":"10461",
    "addr:street":"Westchester Sq",
    "iso:country":"US",
    "sg:address":"68 Westchester Sq",
    "sg:city":"Bronx",
    "sg:classifiers":[
        {
            "category":"Banks & Credit Unions",
            "subcategory":"Bank",
            "type":"Services"
        }
    ],
    "sg:phone":"+1 718 597 1300",
    "sg:postcode":"10461",
    "sg:province":"NY",
    "sg:tags":[
        "financing"
    ],
    "sg:website":"www.hfc.com",
    "wof:name":"Household Finance",
    "wof:placetype":"venue"
},
  "geometry": {"coordinates":[-73.84204099999999,40.840646],"type":"Point"}
}