{
  "type": "Feature",
  "properties": {
    "iso:country":"US",
    "sg:address":"1934 Bath Ave",
    "sg:city":"Brooklyn",
    "sg:classifiers":[
        {
            "category":"Retail",
            "subcategory":"Animal Services",
            "type":"Services"
        }
    ],
    "sg:phone":"+1 718 333 1200",
    "sg:postcode":"11214",
    "sg:province":"NY",
    "sg:tags":[
        "pet",
        "grooming",
        "washing",
        "boarding/pet",
        "sitting"
    ],
    "wof:name":"Pets N Style Grooming Salon",
    "wof:placetype":"venue"
},
  "geometry": {"coordinates":[-74.00279999999999,40.602001],"type":"Point"}
}