{
  "type": "Feature",
  "properties": {
    "addr:full":"797 E 142nd St Bronx NY 10454",
    "addr:housenumber":"797",
    "addr:postcode":"10454",
    "addr:street":"E 142Nd St",
    "iso:country":"US",
    "sg:address":"797 E 142nd St",
    "sg:city":"Bronx",
    "sg:classifiers":[
        {
            "category":"Building & Trades",
            "subcategory":"Construction",
            "type":"Services"
        }
    ],
    "sg:phone":"+1 718 665 5680",
    "sg:postcode":"10454",
    "sg:province":"NY",
    "sg:tags":[
        "house",
        "residential"
    ],
    "wof:name":"AAa All Ways Cnstr Corp",
    "wof:placetype":"venue"
},
  "geometry": {"coordinates":[-73.908843,40.807491],"type":"Point"}
}