{
  "type": "Feature",
  "properties": {
    "iso:country":"US",
    "sg:address":"7 Meadow Wood Cir",
    "sg:city":"Pittsford",
    "sg:classifiers":[
        {
            "category":"Real Estate",
            "subcategory":"Real Estate Services",
            "type":"Services"
        },
        {
            "category":"Real Estate",
            "subcategory":"Real Estate Agent",
            "type":"Services"
        }
    ],
    "sg:phone":"+1 585 381 2848",
    "sg:postcode":"14534",
    "sg:province":"NY",
    "sg:tags":[
        "buyer",
        "broker"
    ],
    "wof:name":"Matthe Kells Real Estate Company",
    "wof:placetype":"venue"
},
  "geometry": {"coordinates":[-77.52969,43.078362],"type":"Point"}
}