{
  "type": "Feature",
  "properties": {
    "addr:full":"1805 Church Ave Brooklyn NY 11226",
    "addr:housenumber":"1805",
    "addr:postcode":"11226",
    "addr:street":"Church Ave",
    "iso:country":"US",
    "sg:address":"1805 Church Ave",
    "sg:city":"Brooklyn",
    "sg:classifiers":[
        {
            "category":"Shopping",
            "subcategory":"Mobile Phones",
            "type":"Retail Goods"
        }
    ],
    "sg:phone":"+1 718 282 0549",
    "sg:postcode":"11226",
    "sg:province":"NY",
    "sg:website":"www.t-mobile.com",
    "wof:name":"T-Mobile",
    "wof:placetype":"venue"
},
  "geometry": {"coordinates":[-73.96308399999999,40.64959],"type":"Point"}
}