{
  "type": "Feature",
  "properties": {
    "addr:full":"42 Eldridge St Manhattan NY 10002",
    "addr:housenumber":"42",
    "addr:postcode":"10002",
    "addr:street":"Eldridge St",
    "iso:country":"US",
    "sg:address":"42 Eldridge St",
    "sg:city":"Manhattan",
    "sg:classifiers":[
        {
            "category":"Food & Beverages",
            "subcategory":"Candy",
            "type":"Retail Goods"
        }
    ],
    "sg:phone":"+1 212 219 7789",
    "sg:postcode":"10002",
    "sg:province":"NY",
    "sg:tags":[
        "dessert"
    ],
    "wof:name":"Gude Gude Bubble Tea",
    "wof:placetype":"venue"
},
  "geometry": {"coordinates":[-73.99313100000001,40.71578],"type":"Point"}
}