{
  "type": "Feature",
  "properties": {
    "addr:full":"566 Horsehaven Rd Averill Park NY 12062",
    "addr:housenumber":"566",
    "addr:postcode":"12062",
    "addr:street":"Horsehaven Rd",
    "iso:country":"US",
    "sg:address":"566 Horsehaven Rd",
    "sg:city":"Averill Park",
    "sg:classifiers":[
        {
            "category":"Building & Trades",
            "subcategory":"Construction",
            "type":"Services"
        }
    ],
    "sg:phone":"+1 518 794 8619",
    "sg:postcode":"12062",
    "sg:province":"NY",
    "sg:tags":[
        "house"
    ],
    "wof:name":"Old Time Timber Framing",
    "wof:placetype":"venue"
},
  "geometry": {"coordinates":[-73.472306,42.557204],"type":"Point"}
}