{
  "type": "Feature",
  "properties": {
    "addr:full":"3481 W River Rd Grand Island NY 14072",
    "addr:housenumber":"3481",
    "addr:postcode":"14072",
    "addr:street":"W River Rd",
    "iso:country":"US",
    "sg:address":"3481 W River Rd",
    "sg:city":"Grand Island",
    "sg:classifiers":[
        {
            "category":"Retail",
            "subcategory":"Auto Repair",
            "type":"Services"
        }
    ],
    "sg:phone":"+1 716 773 4978",
    "sg:postcode":"14072",
    "sg:province":"NY",
    "sg:tags":[
        "transmission"
    ],
    "wof:name":"Kilmer's C4 Transmissions",
    "wof:placetype":"venue"
},
  "geometry": {"coordinates":[-79.007913,43.031957],"type":"Point"}
}