{
  "type": "Feature",
  "properties": {
    "addr:full":"302 A W 12th St Manhattan NY 10014",
    "addr:housenumber":"302",
    "addr:postcode":"10014",
    "addr:street":"A W 12Th St",
    "iso:country":"US",
    "sg:address":"302 A W 12th St",
    "sg:city":"Manhattan",
    "sg:classifiers":[
        {
            "category":"Shopping",
            "subcategory":"Pets & Pet Supplies",
            "type":"Retail Goods"
        },
        {
            "category":"Retail",
            "subcategory":"Pet Boarding",
            "type":"Services"
        }
    ],
    "sg:phone":"+1 212 929 4828",
    "sg:postcode":"10014",
    "sg:province":"NY",
    "sg:tags":[
        "walker",
        "training",
        "dog",
        "boarding/pet",
        "sitting"
    ],
    "sg:website":"www.furcoatandpants.com",
    "wof:name":"Fur Coat and Pants",
    "wof:placetype":"venue"
},
  "geometry": {"coordinates":[-74.00469099999999,40.737326],"type":"Point"}
}