{
  "type": "Feature",
  "properties": {
    "iso:country":"US",
    "sg:address":"162 Hornell St",
    "sg:city":"Hornell",
    "sg:classifiers":[
        {
            "category":"Building & Trades",
            "subcategory":"Landscaping Services",
            "type":"Services"
        }
    ],
    "sg:phone":"+1 607 324 9762",
    "sg:postcode":"14843",
    "sg:province":"NY",
    "sg:tags":[
        "landscape"
    ],
    "wof:name":"Dans Landscaping",
    "wof:placetype":"venue"
},
  "geometry": {"coordinates":[-77.666281,42.333924],"type":"Point"}
}