{
  "type": "Feature",
  "properties": {
    "addr:full":"3840 Broadway New York NY 10032",
    "addr:housenumber":"3840",
    "addr:postcode":"10032",
    "addr:street":"Broadway",
    "iso:country":"US",
    "sg:address":"3840 Broadway",
    "sg:city":"New York",
    "sg:classifiers":[
        {
            "category":"Shopping",
            "subcategory":"Clothing, Apparel, & Fashions",
            "type":"Retail Goods"
        }
    ],
    "sg:phone":"+1   ",
    "sg:postcode":"10032",
    "sg:province":"NY",
    "wof:name":"Centro Moda Inc",
    "wof:placetype":"venue"
},
  "geometry": {"coordinates":[-73.943022,40.836458],"type":"Point"}
}