{
  "type": "Feature",
  "properties": {
    "addr:full":"2040 5th Ave New York NY 10035",
    "addr:housenumber":"2040",
    "addr:postcode":"10035",
    "addr:street":"5Th Ave",
    "iso:country":"US",
    "sg:address":"2040 5th Ave",
    "sg:city":"New York",
    "sg:classifiers":[
        {
            "category":"Deli",
            "type":"Food & Drink"
        }
    ],
    "sg:phone":"+1 212 987 0051",
    "sg:postcode":"10035",
    "sg:province":"NY",
    "wof:name":"5162 Deli",
    "wof:placetype":"venue"
},
  "geometry": {"coordinates":[-73.94180299999999,40.8069],"type":"Point"}
}