{
  "type": "Feature",
  "properties": {
    "iso:country":"US",
    "sg:address":"257 Conklin Ave",
    "sg:city":"Binghamton",
    "sg:classifiers":[
        {
            "category":"Autos & Motor Vehicles",
            "subcategory":"Automobile Sales",
            "type":"Retail Goods"
        }
    ],
    "sg:phone":"+1   ",
    "sg:postcode":"13903",
    "sg:province":"NY",
    "sg:tags":[
        "car",
        "used",
        "dealer"
    ],
    "wof:name":"Preferred Used Cars",
    "wof:placetype":"venue"
},
  "geometry": {"coordinates":[-75.893811,42.095137],"type":"Point"}
}