{
  "type": "Feature",
  "properties": {
    "addr:full":"1987 Palmer Ave Larchmont NY 10538",
    "addr:housenumber":"1987",
    "addr:postcode":"10538",
    "addr:street":"Palmer Ave",
    "iso:country":"US",
    "sg:address":"1987 Palmer Ave",
    "sg:city":"Larchmont",
    "sg:classifiers":[
        {
            "category":"Home & Garden",
            "subcategory":"Home Furnishings",
            "type":"Retail Goods"
        }
    ],
    "sg:phone":"+1 914 834 6373",
    "sg:postcode":"10538",
    "sg:province":"NY",
    "sg:tags":[
        "curtain",
        "made",
        "drapery"
    ],
    "wof:name":"Curtain Exchange",
    "wof:placetype":"venue"
},
  "geometry": {"coordinates":[-73.761302,40.931],"type":"Point"}
}