{
  "type": "Feature",
  "properties": {
    "iso:country":"US",
    "sg:address":"4618 Avenue N",
    "sg:city":"Brooklyn",
    "sg:classifiers":[
        {
            "category":"Organizations",
            "subcategory":"Community Association",
            "type":"Services"
        }
    ],
    "sg:phone":"+1 718 258 6135",
    "sg:postcode":"11234",
    "sg:province":"NY",
    "sg:tags":[
        "club"
    ],
    "wof:name":"Societa Maria SS Di Casaluca",
    "wof:placetype":"venue"
},
  "geometry": {"coordinates":[-73.929919,40.618684],"type":"Point"}
}