{
  "type": "Feature",
  "properties": {
    "iso:country":"US",
    "sg:address":"136 Twist Run Rd",
    "sg:city":"Endicott",
    "sg:classifiers":[
        {
            "category":"Building & Trades",
            "subcategory":"Construction",
            "type":"Services"
        }
    ],
    "sg:phone":"+1 607 785 3405",
    "sg:postcode":"13760",
    "sg:province":"NY",
    "sg:tags":[
        "plastering",
        "contractor"
    ],
    "wof:name":"Bob Tanzini Plaster",
    "wof:placetype":"venue"
},
  "geometry": {"coordinates":[-76.05628900000001,42.145012],"type":"Point"}
}