{
  "type": "Feature",
  "properties": {
    "addr:full":"219 Westchester Ave Port Chester NY 10573",
    "addr:housenumber":"219",
    "addr:postcode":"10573",
    "addr:street":"Westchester Ave",
    "iso:country":"US",
    "sg:address":"219 Westchester Ave",
    "sg:city":"Port Chester",
    "sg:classifiers":[
        {
            "category":"Building & Trades",
            "subcategory":"Landscaping Services",
            "type":"Services"
        }
    ],
    "sg:phone":"+1 914 937 6521",
    "sg:postcode":"10573",
    "sg:province":"NY",
    "sg:tags":[
        "landscape",
        "contractor"
    ],
    "sg:website":"www.barchella.com",
    "wof:name":"Barchella Contracting Co Inc",
    "wof:placetype":"venue"
},
  "geometry": {"coordinates":[-73.66677799999999,41.002368],"type":"Point"}
}