{
  "type": "Feature",
  "properties": {
    "addr:full":"809 Castleton Avenue S I New York NY 10001",
    "addr:housenumber":"809",
    "addr:postcode":"10001",
    "addr:street":"Castleton Avenue S I",
    "iso:country":"US",
    "sg:address":"809 Castleton Avenue S I",
    "sg:city":"New York",
    "sg:classifiers":[
        {
            "category":"Building & Trades",
            "subcategory":"Cleaning & Sanitation",
            "type":"Services"
        }
    ],
    "sg:phone":"+1 212 619 2002",
    "sg:postcode":"10001",
    "sg:province":"NY",
    "sg:tags":[
        "carpet"
    ],
    "wof:name":"Magic Clean Carpet",
    "wof:placetype":"venue"
},
  "geometry": {"coordinates":[-73.996213,40.750051],"type":"Point"}
}