{
  "type": "Feature",
  "properties": {
    "iso:country":"US",
    "sg:address":"155 Crary Ave",
    "sg:city":"Mount Vernon",
    "sg:classifiers":[
        {
            "category":"Shopping",
            "type":"Retail Goods"
        }
    ],
    "sg:phone":"+1   ",
    "sg:postcode":"10550",
    "sg:province":"NY",
    "sg:tags":[
        "merchandise"
    ],
    "wof:name":"Frameable Petcards",
    "wof:placetype":"venue"
},
  "geometry": {"coordinates":[-73.835515,40.917651],"type":"Point"}
}