{
  "type": "Feature",
  "properties": {
    "addr:full":"2318 Delaware Ave Buffalo NY 14216",
    "addr:housenumber":"2318",
    "addr:postcode":"14216",
    "addr:street":"Delaware Ave",
    "iso:country":"US",
    "sg:address":"2318 Delaware Ave",
    "sg:city":"Buffalo",
    "sg:classifiers":[
        {
            "category":"Banks & Credit Unions",
            "subcategory":"Bank",
            "type":"Services"
        }
    ],
    "sg:phone":"+1 716 877 1752",
    "sg:postcode":"14216",
    "sg:province":"NY",
    "sg:website":"www.key.com",
    "wof:name":"Keybank",
    "wof:placetype":"venue"
},
  "geometry": {"coordinates":[-78.86840100000001,42.947701],"type":"Point"}
}