{
  "type": "Feature",
  "properties": {
    "addr:full":"10 Conselyea St Brooklyn NY 11211",
    "addr:housenumber":"10",
    "addr:postcode":"11211",
    "addr:street":"Conselyea St",
    "iso:country":"US",
    "sg:address":"10 Conselyea St",
    "sg:city":"Brooklyn",
    "sg:classifiers":[
        {
            "category":"Utilities",
            "subcategory":"Electric",
            "type":"Services"
        },
        {
            "category":"Shopping",
            "subcategory":"Computers & Home Electronics",
            "type":"Retail Goods"
        },
        {
            "category":"Manufacturing",
            "subcategory":"Retail Goods",
            "type":"Manufacturing & Wholesale Goods"
        },
        {
            "category":"Manufacturing",
            "subcategory":"Tools & Machinery",
            "type":"Manufacturing & Wholesale Goods"
        },
        {
            "category":"Manufacturing",
            "subcategory":"Electronics",
            "type":"Manufacturing & Wholesale Goods"
        },
        {
            "category":"Wholesale",
            "subcategory":"Home Furnishings",
            "type":"Manufacturing & Wholesale Goods"
        },
        {
            "category":"Wholesale",
            "subcategory":"Electrical",
            "type":"Manufacturing & Wholesale Goods"
        }
    ],
    "sg:phone":"+1 718 388 8668",
    "sg:postcode":"11211",
    "sg:province":"NY",
    "sg:tags":[
        "audio-visual",
        "stereo",
        "supply",
        "equipment-wholesale",
        "household",
        "transformer",
        "appliances-small-wholesale",
        "equipment",
        "video",
        "equipment-dealers",
        "fan",
        "audio",
        "supplies-wholesale",
        "manufacturer"
    ],
    "wof:name":"Batteries Now",
    "wof:placetype":"venue"
},
  "geometry": {"coordinates":[-73.95134400000001,40.714575],"type":"Point"}
}