{
  "type": "Feature",
  "properties": {
    "addr:full":"535 Broad Hollow Rd Melville NY 11747",
    "addr:housenumber":"535",
    "addr:postcode":"11747",
    "addr:street":"Broad Hollow Rd",
    "iso:country":"US",
    "sg:address":"535 Broad Hollow Rd",
    "sg:city":"Melville",
    "sg:classifiers":[
        {
            "category":"Wholesale",
            "subcategory":"Photographic Equipment",
            "type":"Manufacturing & Wholesale Goods"
        },
        {
            "category":"Professional",
            "subcategory":"Business Services",
            "type":"Services"
        }
    ],
    "sg:phone":"+1 631 761 7830",
    "sg:postcode":"11747",
    "sg:province":"NY",
    "sg:tags":[
        "credit",
        "identification",
        "card"
    ],
    "wof:name":"Metropolitan Data Solutions",
    "wof:placetype":"venue"
},
  "geometry": {"coordinates":[-73.42344,40.764941],"type":"Point"}
}