{
  "type": "Feature",
  "properties": {
    "addr:full":"4006 Queens Boulevard Sunnyside NY 11104",
    "addr:housenumber":"4006",
    "addr:postcode":"11104",
    "addr:street":"Queens Boulevard",
    "iso:country":"US",
    "sg:address":"4006 Queens Boulevard",
    "sg:city":"Sunnyside",
    "sg:classifiers":[
        {
            "category":"Restaurant",
            "type":"Food & Drink"
        }
    ],
    "sg:phone":"+1 718 706 0899",
    "sg:postcode":"11104",
    "sg:province":"NY",
    "wof:name":"Won Robert",
    "wof:placetype":"venue"
},
  "geometry": {"coordinates":[-73.92411199999999,40.743516],"type":"Point"}
}