{
  "type": "Feature",
  "properties": {
    "addr:full":"5821 Grant Hill Rd Voorheesville NY 12186",
    "addr:housenumber":"5821",
    "addr:postcode":"12186",
    "addr:street":"Grant Hill Rd",
    "iso:country":"US",
    "sg:address":"5821 Grant Hill Rd",
    "sg:city":"Voorheesville",
    "sg:classifiers":[
        {
            "category":"Shopping",
            "subcategory":"Catalog Store",
            "type":"Retail Goods"
        }
    ],
    "sg:phone":"+1   ",
    "sg:postcode":"12186",
    "sg:province":"NY",
    "sg:tags":[
        "house",
        "mail"
    ],
    "wof:name":"Connies Collectibles",
    "wof:placetype":"venue"
},
  "geometry": {"coordinates":[-73.93380399999999,42.684732],"type":"Point"}
}