{
  "type": "Feature",
  "properties": {
    "iso:country":"US",
    "sg:address":"93 Pennsylvania Ave",
    "sg:city":"Binghamton",
    "sg:classifiers":[
        {
            "category":"Health Services",
            "subcategory":"Doctor",
            "type":"Services"
        }
    ],
    "sg:phone":"+1 607 762 2048",
    "sg:postcode":"13903",
    "sg:province":"NY",
    "sg:tags":[
        "physician",
        "surgeon"
    ],
    "wof:name":"Uhs Sleep Disorders Ctr",
    "wof:placetype":"venue"
},
  "geometry": {"coordinates":[-75.91655299999999,42.085177],"type":"Point"}
}