{
  "type": "Feature",
  "properties": {
    "iso:country":"US",
    "sg:address":"141 E 103rd St",
    "sg:city":"New York",
    "sg:classifiers":[
        {
            "category":"Retail",
            "subcategory":"Funeral Services",
            "type":"Services"
        }
    ],
    "sg:phone":"+1 212 876 1913",
    "sg:postcode":"10029",
    "sg:province":"NY",
    "sg:tags":[
        "cemetery"
    ],
    "wof:name":"Ortiz R G Funeral Home",
    "wof:placetype":"venue"
},
  "geometry": {"coordinates":[-73.948303,40.790501],"type":"Point"}
}