{
  "type": "Feature",
  "properties": {
    "iso:country":"US",
    "sg:address":"146 Novak Rd",
    "sg:city":"Valatie",
    "sg:classifiers":[
        {
            "category":"Professional",
            "subcategory":"Lawyer & Legal Services",
            "type":"Services"
        }
    ],
    "sg:phone":"+1 518 758 7768",
    "sg:postcode":"12184",
    "sg:province":"NY",
    "sg:tags":[
        "plan"
    ],
    "wof:name":"Law Offices Of F Charles Dayter",
    "wof:placetype":"venue"
},
  "geometry": {"coordinates":[-73.68042800000001,42.398159],"type":"Point"}
}