{
  "type": "Feature",
  "properties": {
    "addr:full":"325 Webster Ave New Rochelle NY 10801",
    "addr:housenumber":"325",
    "addr:postcode":"10801",
    "addr:street":"Webster Ave",
    "iso:country":"US",
    "sg:address":"325 Webster Ave",
    "sg:city":"New Rochelle",
    "sg:classifiers":[
        {
            "category":"Restaurant",
            "type":"Food & Drink"
        }
    ],
    "sg:phone":"+1 914 632 5147",
    "sg:postcode":"10801",
    "sg:province":"NY",
    "sg:tags":[
        "caterer"
    ],
    "wof:name":"J & E Webster Deli",
    "wof:placetype":"venue"
},
  "geometry": {"coordinates":[-73.794392,40.914726],"type":"Point"}
}