{
  "type": "Feature",
  "properties": {
    "iso:country":"US",
    "sg:address":"43 W Main St",
    "sg:city":"Macedon",
    "sg:classifiers":[
        {
            "category":"Health Services",
            "subcategory":"Chiropractor",
            "type":"Services"
        }
    ],
    "sg:phone":"+1 315 986 5581",
    "sg:postcode":"14502",
    "sg:province":"NY",
    "wof:name":"Dennis Trovato DC",
    "wof:placetype":"venue"
},
  "geometry": {"coordinates":[-77.30558600000001,43.06678],"type":"Point"}
}