{
  "type": "Feature",
  "properties": {
    "addr:full":"945 Madison Avenue, Manhattan, New York, NY, USA",
    "addr:housenumber":945,
    "addr:postcode":10021,
    "addr:street":"Madison Avenue",
    "addr:website":"http://metmuseum.org/visit/met-breuer",
    "wof:name":"The Met Breuer",
    "wof:placetype":"venue"
},
  "geometry": {"coordinates":[-73.96384,40.773326],"type":"Point"}
}