{
  "type": "Feature",
  "properties": {
    "addr:full":"200 Salina St Liverpool NY 13088",
    "addr:housenumber":"200",
    "addr:postcode":"13088",
    "addr:street":"Salina St",
    "iso:country":"US",
    "sg:address":"200 Salina St",
    "sg:city":"Liverpool",
    "sg:classifiers":[
        {
            "category":"Professional",
            "type":"Services"
        }
    ],
    "sg:phone":"+1 315 461 8161",
    "sg:postcode":"13088",
    "sg:province":"NY",
    "sg:tags":[
        "establishment"
    ],
    "wof:name":"Remarcable Co",
    "wof:placetype":"venue"
},
  "geometry": {"coordinates":[-76.201649,43.102185],"type":"Point"}
}