{
  "type": "Feature",
  "properties": {
    "iso:country":"US",
    "sg:address":"366 Commack Rd",
    "sg:city":"Commack",
    "sg:classifiers":[
        {
            "category":"Health Services",
            "subcategory":"Medical Lab",
            "type":"Services"
        }
    ],
    "sg:phone":"+1 631 462 2939",
    "sg:postcode":"11725",
    "sg:province":"NY",
    "sg:tags":[
        "laboratory"
    ],
    "wof:name":"K-Art Dental Lab",
    "wof:placetype":"venue"
},
  "geometry": {"coordinates":[-73.293738,40.831476],"type":"Point"}
}