{
  "type": "Feature",
  "properties": {
    "addr:full":"804 Bronx River Rd Bronxville NY 10708",
    "addr:housenumber":"804",
    "addr:postcode":"10708",
    "addr:street":"Bronx River Rd",
    "iso:country":"US",
    "sg:address":"804 Bronx River Rd",
    "sg:city":"Bronxville",
    "sg:classifiers":[
        {
            "category":"Real Estate",
            "subcategory":"Real Estate Agent",
            "type":"Services"
        }
    ],
    "sg:phone":"+1 914 237 3101",
    "sg:postcode":"10708",
    "sg:province":"NY",
    "wof:name":"Fleetwood Superintendent",
    "wof:placetype":"venue"
},
  "geometry": {"coordinates":[-73.842359,40.928197],"type":"Point"}
}