{
  "type": "Feature",
  "properties": {
    "addr:full":"4 Sutton Pl New York NY 10022",
    "addr:housenumber":"4",
    "addr:postcode":"10022",
    "addr:street":"Sutton Pl",
    "iso:country":"US",
    "sg:address":"4 Sutton Pl",
    "sg:city":"New York",
    "sg:classifiers":[
        {
            "category":"Banks & Credit Unions",
            "subcategory":"Bank",
            "type":"Services"
        }
    ],
    "sg:phone":"+1 212 759 8640",
    "sg:postcode":"10022",
    "sg:province":"NY",
    "sg:tags":[
        "commercial"
    ],
    "wof:name":"Leila Hadley Luce",
    "wof:placetype":"venue"
},
  "geometry": {"coordinates":[-73.96028099999999,40.758012],"type":"Point"}
}