{
  "type": "Feature",
  "properties": {
    "iso:country":"US",
    "sg:address":"305 Waverly Ave",
    "sg:city":"Patchogue",
    "sg:classifiers":[
        {
            "category":"Deli",
            "type":"Food & Drink"
        },
        {
            "category":"Food & Beverages",
            "subcategory":"Bakery",
            "type":"Retail Goods"
        },
        {
            "category":"Food & Beverages",
            "subcategory":"Groceries & Convenience Stores",
            "type":"Retail Goods"
        }
    ],
    "sg:phone":"+1 631 569 2836",
    "sg:postcode":"11772",
    "sg:province":"NY",
    "sg:tags":[
        "sandwich"
    ],
    "wof:name":"Super Deli Food Mart Inc",
    "wof:placetype":"venue"
},
  "geometry": {"coordinates":[-73.838588,40.775057],"type":"Point"}
}