{
  "type": "Feature",
  "properties": {
    "iso:country":"US",
    "sg:address":"3120 Brighton 5th St",
    "sg:city":"Brooklyn",
    "sg:classifiers":[
        {
            "category":"Health Services",
            "subcategory":"Doctor",
            "type":"Services"
        }
    ],
    "sg:phone":"+1   ",
    "sg:postcode":"11235",
    "sg:province":"NY",
    "sg:tags":[
        "medical"
    ],
    "wof:name":"Igor Ostrovsky MD",
    "wof:placetype":"venue"
},
  "geometry": {"coordinates":[-73.962228,40.576329],"type":"Point"}
}