{
  "type": "Feature",
  "properties": {
    "iso:country":"US",
    "sg:address":"80 E Main St",
    "sg:city":"Canton",
    "sg:classifiers":[
        {
            "category":"Health Services",
            "subcategory":"Podiatrist",
            "type":"Services"
        }
    ],
    "sg:phone":"+1 315 386 8121",
    "sg:postcode":"13617",
    "sg:province":"NY",
    "wof:name":"Thomas R Nystrom DPM",
    "wof:placetype":"venue"
},
  "geometry": {"coordinates":[-75.15596499999999,44.596383],"type":"Point"}
}