{
  "type": "Feature",
  "properties": {
    "addr:full":"660 Louisiana Ave Brooklyn NY 11239",
    "addr:housenumber":"660",
    "addr:postcode":"11239",
    "addr:street":"Louisiana Ave",
    "iso:country":"US",
    "sg:address":"660 Louisiana Ave",
    "sg:city":"Brooklyn",
    "sg:classifiers":[
        {
            "category":"Building & Trades",
            "subcategory":"Construction",
            "type":"Services"
        }
    ],
    "sg:phone":"+1 718 642 1404",
    "sg:postcode":"11239",
    "sg:province":"NY",
    "sg:tags":[
        "contractor"
    ],
    "wof:name":"Atria Builders LLC",
    "wof:placetype":"venue"
},
  "geometry": {"coordinates":[-73.881311,40.641831],"type":"Point"}
}