{
  "type": "Feature",
  "properties": {
    "addr:full":"11 Summer St Flushing NY 11375",
    "addr:housenumber":"11",
    "addr:postcode":"11375",
    "addr:street":"Summer St",
    "iso:country":"US",
    "sg:address":"11 Summer St",
    "sg:city":"Flushing",
    "sg:classifiers":[
        {
            "category":"Real Estate",
            "subcategory":"Real Estate Agent",
            "type":"Services"
        }
    ],
    "sg:phone":"+1 718 544 4163",
    "sg:postcode":"11375",
    "sg:province":"NY",
    "wof:name":"910 Manhattan Avenue Realty",
    "wof:placetype":"venue"
},
  "geometry": {"coordinates":[-73.841444,40.713921],"type":"Point"}
}