{
  "type": "Feature",
  "properties": {
    "iso:country":"US",
    "sg:address":"854 State Hwy 6n",
    "sg:city":"Mahopac",
    "sg:classifiers":[
        {
            "category":"Museum",
            "type":"Entertainment"
        }
    ],
    "sg:phone":"+1 845 621 1260",
    "sg:postcode":"10541",
    "sg:province":"NY",
    "wof:name":"Putnam Children's Discovery",
    "wof:placetype":"venue"
},
  "geometry": {"coordinates":[-73.742963,41.372441],"type":"Point"}
}