{
  "type": "Feature",
  "properties": {
    "iso:country":"US",
    "sg:address":"900 Allerton Ave",
    "sg:city":"Bronx",
    "sg:classifiers":[
        {
            "category":"Personal",
            "subcategory":"Barber",
            "type":"Services"
        }
    ],
    "sg:phone":"+1 718 652 2319",
    "sg:postcode":"10469",
    "sg:province":"NY",
    "wof:name":"Victoriano S Barber Shop Unisex",
    "wof:placetype":"venue"
},
  "geometry": {"coordinates":[-73.86157,40.865413],"type":"Point"}
}