{
  "type": "Feature",
  "properties": {
    "addr:full":"1450 Ridge Rd W Rochester NY 14615",
    "addr:housenumber":"1450",
    "addr:postcode":"14615",
    "addr:street":"Ridge Rd W",
    "iso:country":"US",
    "sg:address":"1450 Ridge Rd W",
    "sg:city":"Rochester",
    "sg:classifiers":[
        {
            "category":"Restaurant",
            "type":"Food & Drink"
        }
    ],
    "sg:phone":"+1 585 663 0050",
    "sg:postcode":"14615",
    "sg:province":"NY",
    "wof:name":"Carmine's Family Restaurant Inc",
    "wof:placetype":"venue"
},
  "geometry": {"coordinates":[-77.66629,43.205139],"type":"Point"}
}