{
  "type": "Feature",
  "properties": {
    "iso:country":"US",
    "sg:address":"1311 Prospect Ave",
    "sg:city":"Bronx",
    "sg:classifiers":[
        {
            "category":"Personal",
            "subcategory":"Beauty Salon",
            "type":"Services"
        }
    ],
    "sg:phone":"+1 718 860 2860",
    "sg:postcode":"10459",
    "sg:province":"NY",
    "wof:name":"Ramona Unisex",
    "wof:placetype":"venue"
},
  "geometry": {"coordinates":[-73.898126,40.828193],"type":"Point"}
}