{
  "type": "Feature",
  "properties": {
    "addr:full":"117 Elliott Ave Yonkers NY 10705",
    "addr:housenumber":"117",
    "addr:postcode":"10705",
    "addr:street":"Elliott Ave",
    "iso:country":"US",
    "sg:address":"117 Elliott Ave",
    "sg:city":"Yonkers",
    "sg:classifiers":[
        {
            "category":"Organizations",
            "subcategory":"Religious Organization",
            "type":"Services"
        }
    ],
    "sg:phone":"+1 914 963 1762",
    "sg:postcode":"10705",
    "sg:province":"NY",
    "sg:tags":[
        "church"
    ],
    "wof:name":"Seventh Day Adventist Church",
    "wof:placetype":"venue"
},
  "geometry": {"coordinates":[-73.89764,40.918014],"type":"Point"}
}