{
  "type": "Feature",
  "properties": {
    "addr:full":"2310 E 13th St Brooklyn NY 11229",
    "addr:housenumber":"2310",
    "addr:postcode":"11229",
    "addr:street":"E 13Th St",
    "iso:country":"US",
    "sg:address":"2310 E 13th St",
    "sg:city":"Brooklyn",
    "sg:classifiers":[
        {
            "category":"Freight",
            "type":"Transportation"
        }
    ],
    "sg:phone":"+1 718 332 3828",
    "sg:postcode":"11229",
    "sg:province":"NY",
    "sg:tags":[
        "delivery"
    ],
    "wof:name":"Kinny Way Delivery",
    "wof:placetype":"venue"
},
  "geometry": {"coordinates":[-73.95714700000001,40.592479],"type":"Point"}
}