{
  "type": "Feature",
  "properties": {
    "addr:full":"36 Church St Canajoharie NY 13317",
    "addr:housenumber":"36",
    "addr:postcode":"13317",
    "addr:street":"Church St",
    "iso:country":"US",
    "sg:address":"36 Church St",
    "sg:city":"Canajoharie",
    "sg:classifiers":[
        {
            "category":"Restaurant",
            "type":"Food & Drink"
        }
    ],
    "sg:phone":"+1 518 673 8000",
    "sg:postcode":"13317",
    "sg:province":"NY",
    "wof:name":"Coppy C's Pizzeria Bar & Grill",
    "wof:placetype":"venue"
},
  "geometry": {"coordinates":[-74.572012,42.905586],"type":"Point"}
}