{
  "type": "Feature",
  "properties": {
    "addr:full":"555 Broadway Hastings On Hdsn NY 10706",
    "addr:housenumber":"555",
    "addr:postcode":"10706",
    "addr:street":"Broadway",
    "iso:country":"US",
    "sg:address":"555 Broadway",
    "sg:city":"Hastings On Hdsn",
    "sg:classifiers":[
        {
            "category":"Home & Garden",
            "subcategory":"Household Appliances",
            "type":"Retail Goods"
        }
    ],
    "sg:phone":"+1 914 674 6050",
    "sg:postcode":"10706",
    "sg:province":"NY",
    "wof:name":"A & M Appliance Svc Co",
    "wof:placetype":"venue"
},
  "geometry": {"coordinates":[-73.88016399999999,40.996866],"type":"Point"}
}