{
  "type": "Feature",
  "properties": {
    "addr:full":"7613 N State St Lowville NY 13367",
    "addr:housenumber":"7613",
    "addr:postcode":"13367",
    "addr:street":"N State St",
    "iso:country":"US",
    "sg:address":"7613 N State St",
    "sg:city":"Lowville",
    "sg:classifiers":[
        {
            "category":"Real Estate",
            "subcategory":"Real Estate Agent",
            "type":"Services"
        }
    ],
    "sg:phone":"+1 315 376 9921",
    "sg:postcode":"13367",
    "sg:province":"NY",
    "sg:tags":[
        "leasing",
        "agency",
        "rental"
    ],
    "wof:name":"North Country Rentals",
    "wof:placetype":"venue"
},
  "geometry": {"coordinates":[-75.492518,43.78703],"type":"Point"}
}