{
  "type": "Feature",
  "properties": {
    "addr:full":"1386 Randall Ave Bronx NY 10474",
    "addr:housenumber":"1386",
    "addr:postcode":"10474",
    "addr:street":"Randall Ave",
    "iso:country":"US",
    "sg:address":"1386 Randall Ave",
    "sg:city":"Bronx",
    "sg:classifiers":[
        {
            "category":"Home & Garden",
            "subcategory":"Hardware",
            "type":"Retail Goods"
        }
    ],
    "sg:phone":"+1 718 860 0012",
    "sg:postcode":"10474",
    "sg:province":"NY",
    "wof:name":"Hunts Point Hardware Inc",
    "wof:placetype":"venue"
},
  "geometry": {"coordinates":[-73.881444,40.812795],"type":"Point"}
}