{
  "type": "Feature",
  "properties": {
    "addr:full":"76 E Main St Huntington NY 11743",
    "addr:housenumber":"76",
    "addr:postcode":"11743",
    "addr:street":"E Main St",
    "iso:country":"US",
    "sg:address":"76 E Main St",
    "sg:city":"Huntington",
    "sg:classifiers":[
        {
            "category":"Wholesale",
            "subcategory":"Chemicals & Plastics",
            "type":"Manufacturing & Wholesale Goods"
        }
    ],
    "sg:phone":"+1 631 673 8484",
    "sg:postcode":"11743",
    "sg:province":"NY",
    "sg:tags":[
        "information",
        "retrieval",
        "n"
    ],
    "wof:name":"Industrial Options",
    "wof:placetype":"venue"
},
  "geometry": {"coordinates":[-73.410899,40.877712],"type":"Point"}
}