{
  "type": "Feature",
  "properties": {
    "addr:full":"250 Mill Rd Rochester NY 14626",
    "addr:housenumber":"250",
    "addr:postcode":"14626",
    "addr:street":"Mill Rd",
    "iso:country":"US",
    "sg:address":"250 Mill Rd",
    "sg:city":"Rochester",
    "sg:classifiers":[
        {
            "category":"Professional",
            "type":"Services"
        }
    ],
    "sg:phone":"+1 585 777 4099",
    "sg:postcode":"14626",
    "sg:province":"NY",
    "wof:name":"GE Capital Fleet Svc",
    "wof:placetype":"venue"
},
  "geometry": {"coordinates":[-77.720878,43.231535],"type":"Point"}
}