{
  "type": "Feature",
  "properties": {
    "addr:full":"353 Grand St New York NY 10002",
    "addr:housenumber":"353",
    "addr:postcode":"10002",
    "addr:street":"Grand St",
    "iso:country":"US",
    "sg:address":"353 Grand St",
    "sg:city":"New York",
    "sg:classifiers":[
        {
            "category":"Personal",
            "subcategory":"Shoe Repair & Shine",
            "type":"Services"
        }
    ],
    "sg:phone":"+1 212 673 0507",
    "sg:postcode":"10002",
    "sg:province":"NY",
    "sg:tags":[
        "repairing",
        "boot"
    ],
    "wof:name":"Erik Shoe Repair",
    "wof:placetype":"venue"
},
  "geometry": {"coordinates":[-73.989637,40.716837],"type":"Point"}
}