{
  "type": "Feature",
  "properties": {
    "iso:country":"US",
    "sg:address":"60 Gordon Dr",
    "sg:city":"Syosset",
    "sg:classifiers":[
        {
            "category":"Education",
            "subcategory":"Special Training",
            "type":"Public Place"
        },
        {
            "category":"Education",
            "subcategory":"School",
            "type":"Public Place"
        }
    ],
    "sg:phone":"+1 516 921 2987",
    "sg:postcode":"11791",
    "sg:province":"NY",
    "sg:tags":[
        "high",
        "middle",
        "specialty",
        "elementary"
    ],
    "wof:name":"Phoenix Academy",
    "wof:placetype":"venue"
},
  "geometry": {"coordinates":[-73.511999,40.80758],"type":"Point"}
}