{
  "type": "Feature",
  "properties": {
    "addr:full":"69 Beach Rd Stony Point NY 10980",
    "addr:housenumber":"69",
    "addr:postcode":"10980",
    "addr:street":"Beach Rd",
    "iso:country":"US",
    "sg:address":"69 Beach Rd",
    "sg:city":"Stony Point",
    "sg:classifiers":[
        {
            "category":"Building & Trades",
            "subcategory":"Electrical",
            "type":"Services"
        }
    ],
    "sg:phone":"+1 845 786 2475",
    "sg:postcode":"10980",
    "sg:province":"NY",
    "sg:tags":[
        "electrical",
        "electric",
        "contractor"
    ],
    "wof:name":"Casscles Electric Inc",
    "wof:placetype":"venue"
},
  "geometry": {"coordinates":[-73.974655,41.227809],"type":"Point"}
}