{
  "type": "Feature",
  "properties": {
    "addr:full":"53 McKinley Ave Endicott NY 13760",
    "addr:housenumber":"53",
    "addr:postcode":"13760",
    "addr:street":"Mckinley Ave",
    "iso:country":"US",
    "sg:address":"53 McKinley Ave",
    "sg:city":"Endicott",
    "sg:classifiers":[
        {
            "category":"Organizations",
            "subcategory":"Religious Organization",
            "type":"Services"
        }
    ],
    "sg:phone":"+1 607 748 0662",
    "sg:postcode":"13760",
    "sg:province":"NY",
    "sg:tags":[
        "church"
    ],
    "wof:name":"Binghamton District Office",
    "wof:placetype":"venue"
},
  "geometry": {"coordinates":[-76.044472,42.103214],"type":"Point"}
}