{
  "type": "Feature",
  "properties": {
    "addr:full":"154 Susquehanna St Binghamton NY 13901",
    "addr:housenumber":"154",
    "addr:postcode":"13901",
    "addr:street":"Susquehanna St",
    "iso:country":"US",
    "sg:address":"154 Susquehanna St",
    "sg:city":"Binghamton",
    "sg:classifiers":[
        {
            "category":"Home & Garden",
            "subcategory":"Carpets & Floor Coverings",
            "type":"Retail Goods"
        }
    ],
    "sg:phone":"+1 607 772 9000",
    "sg:postcode":"13901",
    "sg:province":"NY",
    "sg:tags":[
        "material",
        "rug",
        "dealer"
    ],
    "wof:name":"Floor Store The",
    "wof:placetype":"venue"
},
  "geometry": {"coordinates":[-75.90338,42.097198],"type":"Point"}
}