{
  "type": "Feature",
  "properties": {
    "iso:country":"US",
    "sg:address":"10 Woods Dr",
    "sg:city":"Roslyn",
    "sg:classifiers":[
        {
            "category":"Health Services",
            "subcategory":"Doctor",
            "type":"Services"
        }
    ],
    "sg:phone":"+1 516 621 7353",
    "sg:postcode":"11576",
    "sg:province":"NY",
    "wof:name":"UEP",
    "wof:placetype":"venue"
},
  "geometry": {"coordinates":[-73.62286,40.81082],"type":"Point"}
}