{
  "type": "Feature",
  "properties": {
    "iso:country":"US",
    "sg:address":"1455 Nepperhan Ave",
    "sg:city":"Yonkers",
    "sg:classifiers":[
        {
            "category":"Education",
            "subcategory":"Dance Studio",
            "type":"Public Place"
        }
    ],
    "sg:phone":"+1 914 968 2698",
    "sg:postcode":"10703",
    "sg:province":"NY",
    "sg:tags":[
        "instruction",
        "dancing"
    ],
    "wof:name":"Margaret Pike Studio Of Dance",
    "wof:placetype":"venue"
},
  "geometry": {"coordinates":[-73.871335,40.972607],"type":"Point"}
}