{
  "type": "Feature",
  "properties": {
    "addr:full":"28 Jefferson Ave Kingston NY 12401",
    "addr:housenumber":"28",
    "addr:postcode":"12401",
    "addr:street":"Jefferson Ave",
    "iso:country":"US",
    "sg:address":"28 Jefferson Ave",
    "sg:city":"Kingston",
    "sg:classifiers":[
        {
            "category":"Professional",
            "subcategory":"Advertising",
            "type":"Services"
        }
    ],
    "sg:phone":"+1 845 339 7849",
    "sg:postcode":"12401",
    "sg:province":"NY",
    "sg:website":"www.weddingjournal.com",
    "wof:name":"Rovereto Gallery Photography",
    "wof:placetype":"venue"
},
  "geometry": {"coordinates":[-74.00433700000001,41.942223],"type":"Point"}
}