{
  "type": "Feature",
  "properties": {
    "addr:full":"1 Lowell Rd Purchase NY 10577",
    "addr:housenumber":"1",
    "addr:postcode":"10577",
    "addr:street":"Lowell Rd",
    "iso:country":"US",
    "sg:address":"1 Lowell Rd",
    "sg:city":"Purchase",
    "sg:classifiers":[
        {
            "category":"Food & Beverages",
            "subcategory":"Specialty",
            "type":"Retail Goods"
        }
    ],
    "sg:phone":"+1 330 505 1111",
    "sg:postcode":"10577",
    "sg:province":"NY",
    "sg:tags":[
        "product",
        "health",
        "diet"
    ],
    "sg:website":"http://www.bodyworks.net",
    "wof:name":"Vitamin Shop at Bodyworks",
    "wof:placetype":"venue"
},
  "geometry": {"coordinates":[-73.74099,41.033981],"type":"Point"}
}