{
  "type": "Feature",
  "properties": {
    "iso:country":"US",
    "sg:address":"62 Bayview Ave",
    "sg:city":"New Rochelle",
    "sg:classifiers":[
        {
            "category":"Building & Trades",
            "subcategory":"Landscaping Services",
            "type":"Services"
        }
    ],
    "sg:phone":"+1 914 235 9239",
    "sg:postcode":"10805",
    "sg:province":"NY",
    "sg:tags":[
        "landscape"
    ],
    "wof:name":"Cianciulli",
    "wof:placetype":"venue"
},
  "geometry": {"coordinates":[-73.775188,40.910161],"type":"Point"}
}