{
  "type": "Feature",
  "properties": {
    "addr:full":"440 Ontario St Buffalo NY 14207",
    "addr:housenumber":"440",
    "addr:postcode":"14207",
    "addr:street":"Ontario St",
    "iso:country":"US",
    "sg:address":"440 Ontario St",
    "sg:city":"Buffalo",
    "sg:classifiers":[
        {
            "category":"Airline",
            "type":"Transportation"
        }
    ],
    "sg:phone":"+1 716 688 2222",
    "sg:postcode":"14207",
    "sg:province":"NY",
    "sg:tags":[
        "shuttle",
        "airport"
    ],
    "wof:name":"Suburban Cab",
    "wof:placetype":"venue"
},
  "geometry": {"coordinates":[-78.898201,42.955502],"type":"Point"}
}