{
  "type": "Feature",
  "properties": {
    "iso:country":"US",
    "sg:address":"850 Elbe Ave",
    "sg:city":"Staten Island",
    "sg:classifiers":[
        {
            "category":"Communications",
            "subcategory":"Film & Video Production",
            "type":"Services"
        }
    ],
    "sg:phone":"+1   ",
    "sg:postcode":"10304",
    "sg:province":"NY",
    "sg:tags":[
        "motion"
    ],
    "wof:name":"Fanelli Video Prodctns",
    "wof:placetype":"venue"
},
  "geometry": {"coordinates":[-74.085885,40.604626],"type":"Point"}
}