{
  "type": "Feature",
  "properties": {
    "iso:country":"US",
    "sg:address":"28 Bedford Park Blvd W",
    "sg:city":"Bronx",
    "sg:classifiers":[
        {
            "category":"Personal",
            "subcategory":"Beauty Salon",
            "type":"Services"
        }
    ],
    "sg:phone":"+1 718 733 5507",
    "sg:postcode":"10468",
    "sg:province":"NY",
    "wof:name":"T & M Beauty",
    "wof:placetype":"venue"
},
  "geometry": {"coordinates":[-73.892968,40.875193],"type":"Point"}
}