{
  "type": "Feature",
  "properties": {
    "addr:full":"19 Stowell Ave Candor NY 13743",
    "addr:housenumber":"19",
    "addr:postcode":"13743",
    "addr:street":"Stowell Ave",
    "iso:country":"US",
    "sg:address":"19 Stowell Ave",
    "sg:city":"Candor",
    "sg:classifiers":[
        {
            "category":"Building & Trades",
            "subcategory":"Construction",
            "type":"Services"
        }
    ],
    "sg:phone":"+1 607 659 3728",
    "sg:postcode":"13743",
    "sg:province":"NY",
    "sg:tags":[
        "contractor"
    ],
    "wof:name":"Ciappa Construction",
    "wof:placetype":"venue"
},
  "geometry": {"coordinates":[-76.340687,42.229297],"type":"Point"}
}