{
  "type": "Feature",
  "properties": {
    "iso:country":"US",
    "sg:address":"876 Manor Rd",
    "sg:city":"Staten Island",
    "sg:classifiers":[
        {
            "category":"Retail",
            "subcategory":"Self-service Laundry",
            "type":"Services"
        }
    ],
    "sg:phone":"+1 718 982 5454",
    "sg:postcode":"10314",
    "sg:province":"NY",
    "wof:name":"Charming Cleaners",
    "wof:placetype":"venue"
},
  "geometry": {"coordinates":[-74.120971,40.606295],"type":"Point"}
}