{
  "type": "Feature",
  "properties": {
    "addr:full":"47 4th Ave Brooklyn NY 11217",
    "addr:housenumber":"47",
    "addr:postcode":"11217",
    "addr:street":"4Th Ave",
    "iso:country":"US",
    "sg:address":"47 4th Ave",
    "sg:city":"Brooklyn",
    "sg:classifiers":[
        {
            "category":"Organizations",
            "subcategory":"Religious Organization",
            "type":"Services"
        }
    ],
    "sg:phone":"+1 718 789 4759",
    "sg:postcode":"11217",
    "sg:province":"NY",
    "sg:tags":[
        "church"
    ],
    "wof:name":"Universal Church",
    "wof:placetype":"venue"
},
  "geometry": {"coordinates":[-73.97941299999999,40.682693],"type":"Point"}
}