{
  "type": "Feature",
  "properties": {
    "addr:full":"107 Co Rd 39A Southampton NY 11968",
    "addr:housenumber":"107;39a",
    "addr:postcode":"11968",
    "addr:street":"Co Rd",
    "iso:country":"US",
    "sg:address":"107 Co Rd 39A",
    "sg:city":"Southampton",
    "sg:classifiers":[
        {
            "category":"Retail",
            "subcategory":"Repair Shop",
            "type":"Services"
        }
    ],
    "sg:phone":"+1   ",
    "sg:postcode":"11968",
    "sg:province":"NY",
    "wof:name":"Grodski Mower Service",
    "wof:placetype":"venue"
},
  "geometry": {"coordinates":[-72.37846399999999,40.90037],"type":"Point"}
}