{
  "type": "Feature",
  "properties": {
    "iso:country":"US",
    "sg:address":"3901 Main Street Suite 310",
    "sg:city":"Flushing",
    "sg:classifiers":[
        {
            "category":"Health Services",
            "subcategory":"Dentist",
            "type":"Services"
        }
    ],
    "sg:phone":"+1 718 461 5470",
    "sg:postcode":"11354",
    "sg:province":"NY",
    "sg:tags":[
        "orthodontist"
    ],
    "wof:name":"Dr Michael B Marouni",
    "wof:placetype":"venue"
},
  "geometry": {"coordinates":[-73.83047000000001,40.760222],"type":"Point"}
}