{
  "type": "Feature",
  "properties": {
    "iso:country":"US",
    "sg:address":"3946 Nevada Ave",
    "sg:city":"Island Park",
    "sg:classifiers":[
        {
            "category":"Building & Trades",
            "subcategory":"Landscaping Services",
            "type":"Services"
        }
    ],
    "sg:phone":"+1 516 897 8811",
    "sg:postcode":"11558",
    "sg:province":"NY",
    "sg:tags":[
        "consultant",
        "tree"
    ],
    "wof:name":"Mr Tree Tree Svc",
    "wof:placetype":"venue"
},
  "geometry": {"coordinates":[-73.643214,40.61213],"type":"Point"}
}