{
  "type": "Feature",
  "properties": {
    "iso:country":"US",
    "sg:address":"76 South St",
    "sg:city":"Warwick",
    "sg:classifiers":[
        {
            "category":"Building & Trades",
            "subcategory":"Construction",
            "type":"Services"
        }
    ],
    "sg:phone":"+1 845 987 1645",
    "sg:postcode":"10990",
    "sg:province":"NY",
    "sg:tags":[
        "contractor"
    ],
    "wof:name":"Miller Stone Contracting",
    "wof:placetype":"venue"
},
  "geometry": {"coordinates":[-74.357483,41.25317],"type":"Point"}
}