{
  "type": "Feature",
  "properties": {
    "addr:full":"1272 Hoe Avenue Bronx NY 10459",
    "addr:housenumber":"1272",
    "addr:postcode":"10459",
    "addr:street":"Hoe Avenue",
    "iso:country":"US",
    "sg:address":"1272 Hoe Avenue",
    "sg:city":"Bronx",
    "sg:classifiers":[
        {
            "category":"Organizations",
            "subcategory":"Religious Organization",
            "type":"Services"
        }
    ],
    "sg:phone":"+1 718 991 5654",
    "sg:postcode":"10459",
    "sg:province":"NY",
    "wof:name":"Beulah Christian Church",
    "wof:placetype":"venue"
},
  "geometry": {"coordinates":[-73.890727,40.830185],"type":"Point"}
}