{
  "type": "Feature",
  "properties": {
    "addr:full":"290 Baychester Ave Bronx NY 10475",
    "addr:housenumber":"290",
    "addr:postcode":"10475",
    "addr:street":"Baychester Ave",
    "iso:country":"US",
    "sg:address":"290 Baychester Ave",
    "sg:city":"Bronx",
    "sg:classifiers":[
        {
            "category":"Communications",
            "subcategory":"Newspaper",
            "type":"Services"
        }
    ],
    "sg:phone":"+1 718 862 3945",
    "sg:postcode":"10475",
    "sg:province":"NY",
    "sg:tags":[
        "magazine"
    ],
    "wof:name":"Barnes & Noble",
    "wof:placetype":"venue"
},
  "geometry": {"coordinates":[-73.82975500000001,40.865383],"type":"Point"}
}