{
  "type": "Feature",
  "properties": {
    "addr:full":"707 Chester St Brooklyn NY 11236",
    "addr:housenumber":"707",
    "addr:postcode":"11236",
    "addr:street":"Chester St",
    "iso:country":"US",
    "sg:address":"707 Chester St",
    "sg:city":"Brooklyn",
    "sg:classifiers":[
        {
            "category":"Retail",
            "subcategory":"Auto Repair",
            "type":"Services"
        }
    ],
    "sg:phone":"+1   ",
    "sg:postcode":"11236",
    "sg:province":"NY",
    "sg:tags":[
        "body",
        "general"
    ],
    "wof:name":"Orrie Auto Repair Inc",
    "wof:placetype":"venue"
},
  "geometry": {"coordinates":[-73.90744599999999,40.653462],"type":"Point"}
}