{
  "type": "Feature",
  "properties": {
    "iso:country":"US",
    "sg:address":"300 Sunrise Hwy",
    "sg:city":"Rockville Centre",
    "sg:classifiers":[
        {
            "category":"Bars & Pubs",
            "type":"Food & Drink"
        }
    ],
    "sg:phone":"+1 516 763 0737",
    "sg:postcode":"11570",
    "sg:province":"NY",
    "sg:website":"www.stingersirishpub.com",
    "wof:name":"Stingers Irish Pub",
    "wof:placetype":"venue"
},
  "geometry": {"coordinates":[-73.643084,40.657169],"type":"Point"}
}