{
  "type": "Feature",
  "properties": {
    "addr:full":"11 E Main St Pawling NY 12564",
    "addr:housenumber":"11",
    "addr:postcode":"12564",
    "addr:street":"E Main St",
    "iso:country":"US",
    "sg:address":"11 E Main St",
    "sg:city":"Pawling",
    "sg:classifiers":[
        {
            "category":"Shopping",
            "subcategory":"Bicycles & Sporting Goods",
            "type":"Retail Goods"
        }
    ],
    "sg:phone":"+1   ",
    "sg:postcode":"12564",
    "sg:province":"NY",
    "wof:name":"Anglers Den",
    "wof:placetype":"venue"
},
  "geometry": {"coordinates":[-73.60141,41.561892],"type":"Point"}
}