{
  "type": "Feature",
  "properties": {
    "iso:country":"US",
    "sg:address":"10 Bon Miller Rd",
    "sg:city":"Mahopac",
    "sg:classifiers":[
        {
            "category":"Social Services",
            "subcategory":"Child Care",
            "type":"Services"
        }
    ],
    "sg:phone":"+1 845 628 0775",
    "sg:postcode":"10541",
    "sg:province":"NY",
    "sg:website":"www.lpccc.com",
    "wof:name":"Little People Of Mahopac Inc",
    "wof:placetype":"venue"
},
  "geometry": {"coordinates":[-73.751136,41.351077],"type":"Point"}
}