{
  "type": "Feature",
  "properties": {
    "iso:country":"US",
    "sg:address":"1927 Kings Hwy",
    "sg:city":"Brooklyn",
    "sg:classifiers":[
        {
            "category":"Building & Trades",
            "subcategory":"Construction",
            "type":"Services"
        }
    ],
    "sg:phone":"+1 347 702 9300",
    "sg:postcode":"11229",
    "sg:province":"NY",
    "sg:tags":[
        "contractor"
    ],
    "wof:name":"Prestige Home Const",
    "wof:placetype":"venue"
},
  "geometry": {"coordinates":[-73.954453,40.610501],"type":"Point"}
}