{
  "type": "Feature",
  "properties": {
    "addr:full":"15652 Northern Blvd Flushing NY 11354",
    "addr:housenumber":"15652",
    "addr:postcode":"11354",
    "addr:street":"Northern Blvd",
    "iso:country":"US",
    "sg:address":"15652 Northern Blvd",
    "sg:city":"Flushing",
    "sg:classifiers":[
        {
            "category":"Restaurant",
            "type":"Food & Drink"
        }
    ],
    "sg:phone":"+1 718 939 9292",
    "sg:postcode":"11354",
    "sg:province":"NY",
    "sg:tags":[
        "house",
        "steak"
    ],
    "wof:name":"Chickenholic Of Northern",
    "wof:placetype":"venue"
},
  "geometry": {"coordinates":[-73.829247,40.763563],"type":"Point"}
}