{
  "type": "Feature",
  "properties": {
    "iso:country":"US",
    "sg:address":"3005 Kingsbridge Ter",
    "sg:city":"Bronx",
    "sg:classifiers":[
        {
            "category":"Wholesale",
            "subcategory":"Machinery & Supplies",
            "type":"Manufacturing & Wholesale Goods"
        }
    ],
    "sg:phone":"+1 718 432 6837",
    "sg:postcode":"10463",
    "sg:province":"NY",
    "sg:tags":[
        "salon",
        "beauty"
    ],
    "wof:name":"Vitala Unisex",
    "wof:placetype":"venue"
},
  "geometry": {"coordinates":[-73.90185099999999,40.87613],"type":"Point"}
}