{
  "type": "Feature",
  "properties": {
    "iso:country":"US",
    "sg:address":"17 Broadway Mall",
    "sg:city":"Hornell",
    "sg:classifiers":[
        {
            "category":"Shopping",
            "subcategory":"Discount & Variety Stores",
            "type":"Retail Goods"
        }
    ],
    "sg:phone":"+1   ",
    "sg:postcode":"14843",
    "sg:province":"NY",
    "wof:name":"Plaza Dollar Bazaar",
    "wof:placetype":"venue"
},
  "geometry": {"coordinates":[-77.660634,42.325899],"type":"Point"}
}