{
  "type": "Feature",
  "properties": {
    "addr:full":"644 58th St Brooklyn NY 11220",
    "addr:housenumber":"644",
    "addr:postcode":"11220",
    "addr:street":"58Th St",
    "iso:country":"US",
    "sg:address":"644 58th St",
    "sg:city":"Brooklyn",
    "sg:classifiers":[
        {
            "category":"Wholesale",
            "subcategory":"Apparel",
            "type":"Manufacturing & Wholesale Goods"
        }
    ],
    "sg:phone":"+1 212 802 7259",
    "sg:postcode":"11220",
    "sg:province":"NY",
    "sg:tags":[
        "import"
    ],
    "wof:name":"Cyntex Apparel",
    "wof:placetype":"venue"
},
  "geometry": {"coordinates":[-74.01137,40.638503],"type":"Point"}
}