{
  "type": "Feature",
  "properties": {
    "addr:full":"29 Washington Sq W New York NY 10011",
    "addr:housenumber":"29",
    "addr:postcode":"10011",
    "addr:street":"Washington Sq W",
    "iso:country":"US",
    "sg:address":"29 Washington Sq W",
    "sg:city":"New York",
    "sg:classifiers":[
        {
            "category":"Health Services",
            "subcategory":"Doctor",
            "type":"Services"
        }
    ],
    "sg:phone":"+1 212 673 2721",
    "sg:postcode":"10011",
    "sg:province":"NY",
    "sg:tags":[
        "physician",
        "surgeon"
    ],
    "wof:name":"Grenwich Village Gastro",
    "wof:placetype":"venue"
},
  "geometry": {"coordinates":[-73.998957,40.731814],"type":"Point"}
}