{
  "type": "Feature",
  "properties": {
    "addr:full":"23 Candee Ave Sayville NY 11782",
    "addr:housenumber":"23",
    "addr:postcode":"11782",
    "addr:street":"Candee Ave",
    "iso:country":"US",
    "sg:address":"23 Candee Ave",
    "sg:city":"Sayville",
    "sg:classifiers":[
        {
            "category":"Building & Trades",
            "subcategory":"Equipment Rental",
            "type":"Services"
        }
    ],
    "sg:phone":"+1 631 567 2626",
    "sg:postcode":"11782",
    "sg:province":"NY",
    "sg:tags":[
        "audio",
        "leasing"
    ],
    "sg:website":"www.communicationcorner.com",
    "wof:name":"Communication Corner Inc",
    "wof:placetype":"venue"
},
  "geometry": {"coordinates":[-73.08141500000001,40.731352],"type":"Point"}
}