{
  "type": "Feature",
  "properties": {
    "addr:full":"453 Co Rd 11 Bolton Landing NY 12814",
    "addr:housenumber":"453;11",
    "addr:postcode":"12814",
    "addr:street":"Co Rd",
    "iso:country":"US",
    "sg:address":"453 Co Rd 11",
    "sg:city":"Bolton Landing",
    "sg:classifiers":[
        {
            "category":"Building & Trades",
            "subcategory":"Construction",
            "type":"Services"
        }
    ],
    "sg:phone":"+1 518 644 3600",
    "sg:postcode":"12814",
    "sg:province":"NY",
    "sg:tags":[
        "house"
    ],
    "wof:name":"Adirondack Builders",
    "wof:placetype":"venue"
},
  "geometry": {"coordinates":[-73.670214,43.581468],"type":"Point"}
}