{
  "type": "Feature",
  "properties": {
    "addr:full":"285 W Broadway Storefront New York NY 10013",
    "addr:housenumber":"285",
    "addr:postcode":"10013",
    "addr:street":"W Broadway",
    "iso:country":"US",
    "sg:address":"285 W Broadway Storefront",
    "sg:city":"New York",
    "sg:classifiers":[
        {
            "category":"Professional",
            "subcategory":"Printing & Photocopies",
            "type":"Services"
        }
    ],
    "sg:phone":"+1 212 966 6886",
    "sg:postcode":"10013",
    "sg:province":"NY",
    "sg:website":"www.bestype.net",
    "wof:name":"Bestype Imaging",
    "wof:placetype":"venue"
},
  "geometry": {"coordinates":[-74.00469200000001,40.720997],"type":"Point"}
}