{
  "type": "Feature",
  "properties": {
    "iso:country":"US",
    "sg:address":"640 10 Ave",
    "sg:city":"New York",
    "sg:classifiers":[
        {
            "category":"Bars & Pubs",
            "type":"Food & Drink"
        }
    ],
    "sg:phone":"+1   ",
    "sg:postcode":"10036",
    "sg:province":"NY",
    "sg:tags":[
        "tavern"
    ],
    "wof:name":"Rufus",
    "wof:placetype":"venue"
},
  "geometry": {"coordinates":[-73.995474,40.759626],"type":"Point"}
}