{
  "type": "Feature",
  "properties": {
    "addr:full":"27 Richmond Pl Cortlandt Manor NY 10567",
    "addr:housenumber":"27",
    "addr:postcode":"10567",
    "addr:street":"Richmond Pl Cortlandt",
    "iso:country":"US",
    "sg:address":"27 Richmond Pl",
    "sg:city":"Cortlandt Manor",
    "sg:classifiers":[
        {
            "category":"Wholesale",
            "subcategory":"Electrical",
            "type":"Manufacturing & Wholesale Goods"
        }
    ],
    "sg:phone":"+1 914 736 0988",
    "sg:postcode":"10567",
    "sg:province":"NY",
    "sg:tags":[
        "alarm",
        "burglar",
        "system"
    ],
    "wof:name":"Godfather Security Systems Inc",
    "wof:placetype":"venue"
},
  "geometry": {"coordinates":[-73.885041,41.31196],"type":"Point"}
}