{
  "type": "Feature",
  "properties": {
    "addr:full":"1502 Forest Hill Rd Staten Island NY 10314",
    "addr:housenumber":"1502",
    "addr:postcode":"10314",
    "addr:street":"Forest Hill Rd",
    "iso:country":"US",
    "sg:address":"1502 Forest Hill Rd",
    "sg:city":"Staten Island",
    "sg:classifiers":[
        {
            "category":"Real Estate",
            "subcategory":"Real Estate Agent",
            "type":"Services"
        }
    ],
    "sg:phone":"+1 718 494 8830",
    "sg:postcode":"10314",
    "sg:province":"NY",
    "wof:name":"Hudson Bay Realty Corp",
    "wof:placetype":"venue"
},
  "geometry": {"coordinates":[-74.152338,40.580974],"type":"Point"}
}