{
  "type": "Feature",
  "properties": {
    "iso:country":"US",
    "sg:address":"10 Burchell Blvd",
    "sg:city":"Bay Shore",
    "sg:classifiers":[
        {
            "category":"Shopping",
            "type":"Retail Goods"
        }
    ],
    "sg:phone":"+1   ",
    "sg:postcode":"11706",
    "sg:province":"NY",
    "sg:tags":[
        "merchandise"
    ],
    "wof:name":"Lettis Be Inc",
    "wof:placetype":"venue"
},
  "geometry": {"coordinates":[-73.253563,40.725911],"type":"Point"}
}