{
  "type": "Feature",
  "properties": {
    "addr:full":"297 Main St Ste 1 Schoharie NY 12157",
    "addr:housenumber":"297",
    "addr:postcode":"12157",
    "addr:street":"Main St Ste 1",
    "iso:country":"US",
    "sg:address":"297 Main St Ste 1",
    "sg:city":"Schoharie",
    "sg:classifiers":[
        {
            "category":"Insurance",
            "subcategory":"Hazard Insurance",
            "type":"Services"
        }
    ],
    "sg:phone":"+1 518 295 7190",
    "sg:postcode":"12157",
    "sg:province":"NY",
    "sg:tags":[
        "commercial",
        "business"
    ],
    "wof:name":"Fake Agcy",
    "wof:placetype":"venue"
},
  "geometry": {"coordinates":[-74.311396,42.66447],"type":"Point"}
}