{
  "type": "Feature",
  "properties": {
    "iso:country":"US",
    "sg:address":"1100 Oak St",
    "sg:city":"Syracuse",
    "sg:classifiers":[
        {
            "category":"Museum",
            "type":"Entertainment"
        }
    ],
    "sg:phone":"+1   ",
    "sg:postcode":"13203",
    "sg:province":"NY",
    "sg:tags":[
        "gallery"
    ],
    "wof:name":"Business Art & Framing Inc",
    "wof:placetype":"venue"
},
  "geometry": {"coordinates":[-76.136421,43.068452],"type":"Point"}
}