{
  "type": "Feature",
  "properties": {
    "addr:full":"117 Holiday Dr Horseheads NY 14845",
    "addr:housenumber":"117",
    "addr:postcode":"14845",
    "addr:street":"Holiday Dr",
    "iso:country":"US",
    "sg:address":"117 Holiday Dr",
    "sg:city":"Horseheads",
    "sg:classifiers":[
        {
            "category":"Professional",
            "subcategory":"Computer Services",
            "type":"Services"
        }
    ],
    "sg:phone":"+1 607 795 1683",
    "sg:postcode":"14845",
    "sg:province":"NY",
    "sg:tags":[
        "consultant",
        "designer"
    ],
    "wof:name":"High Peak Solutions",
    "wof:placetype":"venue"
},
  "geometry": {"coordinates":[-76.80932,42.193199],"type":"Point"}
}