{
  "type": "Feature",
  "properties": {
    "iso:country":"US",
    "sg:address":"166 8th Ave",
    "sg:city":"New York",
    "sg:classifiers":[
        {
            "category":"Restaurant",
            "type":"Food & Drink"
        }
    ],
    "sg:phone":"+1 212 691 0299",
    "sg:postcode":"10011",
    "sg:province":"NY",
    "sg:tags":[
        "thai"
    ],
    "sg:website":"www.roomservicerestaurant.com",
    "wof:name":"Room Service",
    "wof:placetype":"venue"
},
  "geometry": {"coordinates":[-74.00056499999999,40.742431],"type":"Point"}
}