{
  "type": "Feature",
  "properties": {
    "addr:full":"669 Jericho Tpke Huntington Sta NY 11746",
    "addr:housenumber":"669",
    "addr:postcode":"11746",
    "addr:street":"Jericho Tpke",
    "iso:country":"US",
    "sg:address":"669 Jericho Tpke",
    "sg:city":"Huntington Sta",
    "sg:classifiers":[
        {
            "category":"Restaurant",
            "type":"Food & Drink"
        }
    ],
    "sg:phone":"+1 631 424 7676",
    "sg:postcode":"11746",
    "sg:province":"NY",
    "sg:tags":[
        "delicatessen"
    ],
    "wof:name":"Roy's Deli",
    "wof:placetype":"venue"
},
  "geometry": {"coordinates":[-73.386916,40.834002],"type":"Point"}
}