{
  "type": "Feature",
  "properties": {
    "addr:full":"31 Hugh J Grant Cir Bronx NY 10462",
    "addr:housenumber":"31",
    "addr:postcode":"10462",
    "addr:street":"Hugh J Grant Cir",
    "iso:country":"US",
    "sg:address":"31 Hugh J Grant Cir",
    "sg:city":"Bronx",
    "sg:classifiers":[
        {
            "category":"Shopping",
            "subcategory":"Gifts & Souvenirs",
            "type":"Retail Goods"
        }
    ],
    "sg:phone":"+1   ",
    "sg:postcode":"10462",
    "sg:province":"NY",
    "wof:name":"J&J Gift Shop",
    "wof:placetype":"venue"
},
  "geometry": {"coordinates":[-73.860851,40.833614],"type":"Point"}
}