{
  "type": "Feature",
  "properties": {
    "addr:full":"240 Church St Saratoga Springs NY 12866",
    "addr:housenumber":"240",
    "addr:postcode":"12866",
    "addr:street":"Church St",
    "iso:country":"US",
    "sg:address":"240 Church St",
    "sg:city":"Saratoga Springs",
    "sg:classifiers":[
        {
            "category":"Building & Trades",
            "subcategory":"Construction",
            "type":"Services"
        }
    ],
    "sg:phone":"+1 518 581 8159",
    "sg:postcode":"12866",
    "sg:province":"NY",
    "sg:tags":[
        "general",
        "contractor"
    ],
    "wof:name":"George Choate Construction",
    "wof:placetype":"venue"
},
  "geometry": {"coordinates":[-73.79671,43.084688],"type":"Point"}
}