{
  "type": "Feature",
  "properties": {
    "iso:country":"US",
    "sg:address":"2539 Vestal Pkwy E",
    "sg:city":"Vestal",
    "sg:classifiers":[
        {
            "category":"Personal",
            "subcategory":"Tanning Parlor",
            "type":"Services"
        }
    ],
    "sg:phone":"+1 607 729 7734",
    "sg:postcode":"13850",
    "sg:province":"NY",
    "sg:tags":[
        "salon"
    ],
    "wof:name":"California Sun-Daze LTD",
    "wof:placetype":"venue"
},
  "geometry": {"coordinates":[-76.009772,42.094744],"type":"Point"}
}