{
  "type": "Feature",
  "properties": {
    "addr:full":"326 Spring St New York NY 10013",
    "addr:housenumber":"326",
    "addr:postcode":"10013",
    "addr:street":"Spring St",
    "iso:country":"US",
    "sg:address":"326 Spring St",
    "sg:city":"New York",
    "sg:classifiers":[
        {
            "category":"Bars & Pubs",
            "type":"Food & Drink"
        },
        {
            "category":"Restaurant",
            "type":"Food & Drink"
        }
    ],
    "sg:phone":"+1 212 226 9060",
    "sg:postcode":"10013",
    "sg:province":"NY",
    "sg:website":"www.earinn.com",
    "wof:name":"Ear Inn",
    "wof:placetype":"venue"
},
  "geometry": {"coordinates":[-74.00948699999999,40.725842],"type":"Point"}
}