{
  "type": "Feature",
  "properties": {
    "addr:full":"2100 Bartow Ave Bronx NY 10475",
    "addr:housenumber":"2100",
    "addr:postcode":"10475",
    "addr:street":"Bartow Ave",
    "iso:country":"US",
    "sg:address":"2100 Bartow Ave",
    "sg:city":"Bronx",
    "sg:classifiers":[
        {
            "category":"Banks & Credit Unions",
            "subcategory":"Bank",
            "type":"Services"
        }
    ],
    "sg:phone":"+1 718 320 3202",
    "sg:postcode":"10475",
    "sg:province":"NY",
    "sg:tags":[
        "national",
        "commercial"
    ],
    "wof:name":"Chase Manhattan",
    "wof:placetype":"venue"
},
  "geometry": {"coordinates":[-73.821574,40.868477],"type":"Point"}
}