{
  "type": "Feature",
  "properties": {
    "addr:full":"225 W 37th St New York NY 10018",
    "addr:housenumber":"225",
    "addr:postcode":"10018",
    "addr:street":"W 37Th St",
    "iso:country":"US",
    "sg:address":"225 W 37th St",
    "sg:city":"New York",
    "sg:classifiers":[
        {
            "category":"Shopping",
            "subcategory":"Clothing, Apparel, & Fashions",
            "type":"Retail Goods"
        }
    ],
    "sg:phone":"+1 212 509 0468",
    "sg:postcode":"10018",
    "sg:province":"NY",
    "sg:tags":[
        "designer"
    ],
    "wof:name":"Jkem K'Vasi Designs",
    "wof:placetype":"venue"
},
  "geometry": {"coordinates":[-73.991516,40.753863],"type":"Point"}
}