{
  "type": "Feature",
  "properties": {
    "iso:country":"US",
    "sg:address":"112 Cedar Ave",
    "sg:city":"Islip",
    "sg:classifiers":[
        {
            "category":"Building & Trades",
            "subcategory":"Construction",
            "type":"Services"
        }
    ],
    "sg:phone":"+1 631 277 5852",
    "sg:postcode":"11751",
    "sg:province":"NY",
    "sg:tags":[
        "contractor"
    ],
    "wof:name":"Friendly Constr Co",
    "wof:placetype":"venue"
},
  "geometry": {"coordinates":[-73.217697,40.725201],"type":"Point"}
}