{
  "type": "Feature",
  "properties": {
    "addr:full":"91 Christopher St New York NY 10014",
    "addr:housenumber":"91",
    "addr:postcode":"10014",
    "addr:street":"Christopher St",
    "iso:country":"US",
    "sg:address":"91 Christopher St",
    "sg:city":"New York",
    "sg:classifiers":[
        {
            "category":"Restaurant",
            "type":"Food & Drink"
        }
    ],
    "sg:phone":"+1 212 647 8315",
    "sg:postcode":"10014",
    "sg:province":"NY",
    "wof:name":"Goodfellas Kitchen",
    "wof:placetype":"venue"
},
  "geometry": {"coordinates":[-74.00332400000001,40.733659],"type":"Point"}
}