{
  "type": "Feature",
  "properties": {
    "iso:country":"US",
    "sg:address":"19 W 3rd St",
    "sg:city":"Jamestown",
    "sg:classifiers":[
        {
            "category":"Real Estate",
            "subcategory":"Developer",
            "type":"Services"
        }
    ],
    "sg:phone":"+1 716 664 2477",
    "sg:postcode":"14701",
    "sg:province":"NY",
    "wof:name":"Downtown Jamestown Dev",
    "wof:placetype":"venue"
},
  "geometry": {"coordinates":[-79.242457,42.096111],"type":"Point"}
}