{
  "type": "Feature",
  "properties": {
    "addr:full":"2398 State Hwy 32 New Windsor NY 12553",
    "addr:housenumber":"2398",
    "addr:postcode":"12553",
    "addr:street":"State Hwy 32",
    "iso:country":"US",
    "sg:address":"2398 State Hwy 32",
    "sg:city":"New Windsor",
    "sg:classifiers":[
        {
            "category":"Health Services",
            "subcategory":"Doctor",
            "type":"Services"
        }
    ],
    "sg:phone":"+1 845 534 9200",
    "sg:postcode":"12553",
    "sg:province":"NY",
    "sg:tags":[
        "medical"
    ],
    "wof:name":"Dana L Gage",
    "wof:placetype":"venue"
},
  "geometry": {"coordinates":[-74.056628,41.446733],"type":"Point"}
}