{
  "type": "Feature",
  "properties": {
    "iso:country":"US",
    "sg:address":"110 Brookside Ave",
    "sg:city":"Amsterdam",
    "sg:classifiers":[
        {
            "category":"Retail",
            "subcategory":"Laundry & Dry Cleaning",
            "type":"Services"
        }
    ],
    "sg:phone":"+1   ",
    "sg:postcode":"12010",
    "sg:province":"NY",
    "wof:name":"Pakenas Cleaners",
    "wof:placetype":"venue"
},
  "geometry": {"coordinates":[-74.185418,42.943861],"type":"Point"}
}