{
  "type": "Feature",
  "properties": {
    "addr:full":"66 Main St Brockport NY 14420",
    "addr:housenumber":"66",
    "addr:postcode":"14420",
    "addr:street":"Main St",
    "iso:country":"US",
    "sg:address":"66 Main St",
    "sg:city":"Brockport",
    "sg:classifiers":[
        {
            "category":"Banks & Credit Unions",
            "subcategory":"Bank",
            "type":"Services"
        }
    ],
    "sg:phone":"+1 585 637 3946",
    "sg:postcode":"14420",
    "sg:province":"NY",
    "sg:tags":[
        "national",
        "commercial"
    ],
    "wof:name":"Chase Manhattan",
    "wof:placetype":"venue"
},
  "geometry": {"coordinates":[-77.938823,43.214473],"type":"Point"}
}