{
  "type": "Feature",
  "properties": {
    "iso:country":"US",
    "sg:address":"1019 Arsenal St",
    "sg:city":"Watertown",
    "sg:classifiers":[
        {
            "category":"Personal",
            "subcategory":"Barber",
            "type":"Services"
        }
    ],
    "sg:phone":"+1 315 782 2910",
    "sg:postcode":"13601",
    "sg:province":"NY",
    "wof:name":"Clippers Barber Shop",
    "wof:placetype":"venue"
},
  "geometry": {"coordinates":[-75.934999,43.976689],"type":"Point"}
}