{
  "type": "Feature",
  "properties": {
    "addr:full":"400 W Main St Ste 302 Riverhead NY 11901",
    "addr:housenumber":"400",
    "addr:postcode":"11901",
    "addr:street":"W Main St Ste 302",
    "iso:country":"US",
    "sg:address":"400 W Main St Ste 302",
    "sg:city":"Riverhead",
    "sg:classifiers":[
        {
            "category":"Insurance",
            "subcategory":"Hazard Insurance",
            "type":"Services"
        }
    ],
    "sg:phone":"+1 631 846 9198",
    "sg:postcode":"11901",
    "sg:province":"NY",
    "sg:tags":[
        "commercial",
        "business"
    ],
    "sg:website":"http://www.risc.com",
    "wof:name":"R I S C Inc",
    "wof:placetype":"venue"
},
  "geometry": {"coordinates":[-72.669746,40.918179],"type":"Point"}
}