{
  "type": "Feature",
  "properties": {
    "iso:country":"US",
    "sg:address":"1430 Sullivan St",
    "sg:city":"Elmira",
    "sg:classifiers":[
        {
            "category":"Manufacturing",
            "subcategory":"Signs",
            "type":"Manufacturing & Wholesale Goods"
        }
    ],
    "sg:phone":"+1 607 734 2295",
    "sg:postcode":"14901",
    "sg:province":"NY",
    "sg:website":"www.usa-sign.com",
    "wof:name":"Eastern Metal/USA Sign",
    "wof:placetype":"venue"
},
  "geometry": {"coordinates":[-76.804467,42.113382],"type":"Point"}
}