{
  "type": "Feature",
  "properties": {
    "iso:country":"US",
    "sg:address":"11 W 34th St",
    "sg:city":"New York",
    "sg:classifiers":[
        {
            "category":"Shopping",
            "subcategory":"Shoes",
            "type":"Retail Goods"
        }
    ],
    "sg:phone":"+1   ",
    "sg:postcode":"10001",
    "sg:province":"NY",
    "wof:name":"Shoe Mania Ix Inc",
    "wof:placetype":"venue"
},
  "geometry": {"coordinates":[-73.987495,40.749702],"type":"Point"}
}