{
  "type": "Feature",
  "properties": {
    "addr:full":"2740 Nostrand Avenue Brooklyn NY 11210",
    "addr:housenumber":"2740",
    "addr:postcode":"11210",
    "addr:street":"Nostrand Avenue",
    "iso:country":"US",
    "sg:address":"2740 Nostrand Avenue",
    "sg:city":"Brooklyn",
    "sg:classifiers":[
        {
            "category":"Retail",
            "subcategory":"Auto Rental",
            "type":"Services"
        }
    ],
    "sg:phone":"+1 718 258 5700",
    "sg:postcode":"11210",
    "sg:province":"NY",
    "sg:tags":[
        "car"
    ],
    "wof:name":"Plaza Fleet Systems",
    "wof:placetype":"venue"
},
  "geometry": {"coordinates":[-73.945599,40.619129],"type":"Point"}
}