{
  "type": "Feature",
  "properties": {
    "addr:full":"88 University Pl New York NY 10003",
    "addr:housenumber":"88",
    "addr:postcode":"10003",
    "addr:street":"University Pl",
    "iso:country":"US",
    "sg:address":"88 University Pl",
    "sg:city":"New York",
    "sg:classifiers":[
        {
            "category":"Real Estate",
            "subcategory":"Real Estate Agent",
            "type":"Services"
        }
    ],
    "sg:phone":"+1 212 242 6464",
    "sg:postcode":"10003",
    "sg:province":"NY",
    "sg:tags":[
        "manager"
    ],
    "wof:name":"12th Street Associates",
    "wof:placetype":"venue"
},
  "geometry": {"coordinates":[-73.993055,40.733654],"type":"Point"}
}