{
  "type": "Feature",
  "properties": {
    "addr:full":"100 Cabot St West Babylon NY 11704",
    "addr:housenumber":"100",
    "addr:postcode":"11704",
    "addr:street":"Cabot St",
    "iso:country":"US",
    "sg:address":"100 Cabot St",
    "sg:city":"West Babylon",
    "sg:classifiers":[
        {
            "category":"Manufacturing",
            "subcategory":"Printing",
            "type":"Manufacturing & Wholesale Goods"
        }
    ],
    "sg:phone":"+1 631 420 4949",
    "sg:postcode":"11704",
    "sg:province":"NY",
    "sg:tags":[
        "printer"
    ],
    "wof:name":"Northport Printing",
    "wof:placetype":"venue"
},
  "geometry": {"coordinates":[-73.391648,40.729984],"type":"Point"}
}