{
  "type": "Feature",
  "properties": {
    "addr:full":"800 Zerega Ave Bronx NY 10473",
    "addr:housenumber":"800",
    "addr:postcode":"10473",
    "addr:street":"Zerega Ave",
    "iso:country":"US",
    "sg:address":"800 Zerega Ave",
    "sg:city":"Bronx",
    "sg:classifiers":[
        {
            "category":"Real Estate",
            "subcategory":"Real Estate Agent",
            "type":"Services"
        }
    ],
    "sg:phone":"+1 718 792 0535",
    "sg:postcode":"10473",
    "sg:province":"NY",
    "wof:name":"GBPC Realty Corp",
    "wof:placetype":"venue"
},
  "geometry": {"coordinates":[-73.843082,40.824871],"type":"Point"}
}