{
  "type": "Feature",
  "properties": {
    "iso:country":"US",
    "sg:address":"1018 College Ave",
    "sg:city":"Niagara Falls",
    "sg:classifiers":[
        {
            "category":"Organizations",
            "subcategory":"Religious Organization",
            "type":"Services"
        }
    ],
    "sg:phone":"+1 716 282 0795",
    "sg:postcode":"14305",
    "sg:province":"NY",
    "sg:tags":[
        "church"
    ],
    "wof:name":"St Theresas School",
    "wof:placetype":"venue"
},
  "geometry": {"coordinates":[-79.050479,43.122422],"type":"Point"}
}