{
  "type": "Feature",
  "properties": {
    "addr:full":"7 N 5th St Holbrook NY 11741",
    "addr:housenumber":"7",
    "addr:postcode":"11741",
    "addr:street":"N 5Th St",
    "iso:country":"US",
    "sg:address":"7 N 5th St",
    "sg:city":"Holbrook",
    "sg:classifiers":[
        {
            "category":"Wholesale",
            "subcategory":"Toys & Hobbies",
            "type":"Manufacturing & Wholesale Goods"
        }
    ],
    "sg:phone":"+1 631 588 7567",
    "sg:postcode":"11741",
    "sg:province":"NY",
    "wof:name":"Robert Biazzo",
    "wof:placetype":"venue"
},
  "geometry": {"coordinates":[-73.085072,40.828719],"type":"Point"}
}