{
  "type": "Feature",
  "properties": {
    "addr:full":"243 Main St New Paltz NY 12561",
    "addr:housenumber":"243",
    "addr:postcode":"12561",
    "addr:street":"Main St",
    "iso:country":"US",
    "sg:address":"243 Main St",
    "sg:city":"New Paltz",
    "sg:classifiers":[
        {
            "category":"Banks & Credit Unions",
            "subcategory":"Investment Brokerage",
            "type":"Services"
        }
    ],
    "sg:phone":"+1 845 255 2955",
    "sg:postcode":"12561",
    "sg:province":"NY",
    "sg:tags":[
        "security"
    ],
    "sg:website":"www.edwardjones.com",
    "wof:name":"Edward Jones",
    "wof:placetype":"venue"
},
  "geometry": {"coordinates":[-74.07333199999999,41.744065],"type":"Point"}
}