{
  "type": "Feature",
  "properties": {
    "iso:country":"US",
    "sg:address":"205 Columbia St",
    "sg:city":"Brooklyn",
    "sg:classifiers":[
        {
            "category":"Real Estate",
            "subcategory":"Architect",
            "type":"Services"
        }
    ],
    "sg:phone":"+1 718 222 5071",
    "sg:postcode":"11231",
    "sg:province":"NY",
    "wof:name":"Robert Schultz Architect",
    "wof:placetype":"venue"
},
  "geometry": {"coordinates":[-74.002364,40.685736],"type":"Point"}
}