{
  "type": "Feature",
  "properties": {
    "iso:country":"US",
    "sg:address":"13 W 47 St",
    "sg:city":"New York",
    "sg:classifiers":[
        {
            "category":"Shopping",
            "subcategory":"Jewelry",
            "type":"Retail Goods"
        }
    ],
    "sg:phone":"+1 646 366 8998",
    "sg:postcode":"10036",
    "sg:province":"NY",
    "sg:tags":[
        "jeweler"
    ],
    "wof:name":"Diamond Scene",
    "wof:placetype":"venue"
},
  "geometry": {"coordinates":[-73.981458,40.757919],"type":"Point"}
}