{
  "type": "Feature",
  "properties": {
    "iso:country":"US",
    "sg:address":"3713 85th St",
    "sg:city":"Jackson Heights",
    "sg:classifiers":[
        {
            "category":"Health Services",
            "subcategory":"Doctor",
            "type":"Services"
        }
    ],
    "sg:phone":"+1 718 672 4844",
    "sg:postcode":"11372",
    "sg:province":"NY",
    "wof:name":"Abortion Womens Medical of Jackson Heights",
    "wof:placetype":"venue"
},
  "geometry": {"coordinates":[-73.881411,40.749548],"type":"Point"}
}