{
  "type": "Feature",
  "properties": {
    "addr:full":"164 Halgren Cres Haverstraw NY 10927",
    "addr:housenumber":"164",
    "addr:postcode":"10927",
    "addr:street":"Halgren Cres",
    "iso:country":"US",
    "sg:address":"164 Halgren Cres",
    "sg:city":"Haverstraw",
    "sg:classifiers":[
        {
            "category":"Travel",
            "subcategory":"Travel Agent",
            "type":"Entertainment"
        }
    ],
    "sg:phone":"+1 845 942 2835",
    "sg:postcode":"10927",
    "sg:province":"NY",
    "sg:tags":[
        "agency",
        "services-commercial"
    ],
    "sg:website":"http://www.cktours.net",
    "wof:name":"Cruise One, Inc.",
    "wof:placetype":"venue"
},
  "geometry": {"coordinates":[-73.980707,41.202137],"type":"Point"}
}