{
  "type": "Feature",
  "properties": {
    "iso:country":"US",
    "sg:address":"153 Near Rd",
    "sg:city":"Red Hook",
    "sg:classifiers":[
        {
            "category":"Professional",
            "subcategory":"Computer Services",
            "type":"Services"
        }
    ],
    "sg:phone":"+1 518 398 9280",
    "sg:postcode":"12571",
    "sg:province":"NY",
    "sg:tags":[
        "repair"
    ],
    "wof:name":"P C Doc",
    "wof:placetype":"venue"
},
  "geometry": {"coordinates":[-73.73007800000001,42.024806],"type":"Point"}
}