{
  "type": "Feature",
  "properties": {
    "iso:country":"US",
    "sg:address":"112 Vanderbilt Ave",
    "sg:city":"Central Islip",
    "sg:classifiers":[
        {
            "category":"Building & Trades",
            "subcategory":"Construction",
            "type":"Services"
        }
    ],
    "sg:phone":"+1 631 882 7241",
    "sg:postcode":"11722",
    "sg:province":"NY",
    "sg:tags":[
        "general",
        "contractor"
    ],
    "wof:name":"Mil Contractors",
    "wof:placetype":"venue"
},
  "geometry": {"coordinates":[-73.21883699999999,40.796154],"type":"Point"}
}