{
  "type": "Feature",
  "properties": {
    "addr:full":"2526 Wallace Avenue Bronx NY 10467",
    "addr:housenumber":"2526",
    "addr:postcode":"10467",
    "addr:street":"Wallace Avenue",
    "iso:country":"US",
    "sg:address":"2526 Wallace Avenue",
    "sg:city":"Bronx",
    "sg:classifiers":[
        {
            "category":"Arena",
            "subcategory":"Sports Club",
            "type":"Entertainment"
        }
    ],
    "sg:phone":"+1 718 881 9727",
    "sg:postcode":"10467",
    "sg:province":"NY",
    "sg:tags":[
        "martial art"
    ],
    "wof:name":"Troopers Touch",
    "wof:placetype":"venue"
},
  "geometry": {"coordinates":[-73.86457799999999,40.863819],"type":"Point"}
}