{
  "type": "Feature",
  "properties": {
    "addr:full":"1880 Prospect Pl Brooklyn NY 11233",
    "addr:housenumber":"1880",
    "addr:postcode":"11233",
    "addr:street":"Prospect Pl",
    "iso:country":"US",
    "sg:address":"1880 Prospect Pl",
    "sg:city":"Brooklyn",
    "sg:classifiers":[
        {
            "category":"Food & Beverages",
            "subcategory":"Groceries & Convenience Stores",
            "type":"Retail Goods"
        }
    ],
    "sg:phone":"+1 718 498 7072",
    "sg:postcode":"11233",
    "sg:province":"NY",
    "wof:name":"Hop Variety Corp",
    "wof:placetype":"venue"
},
  "geometry": {"coordinates":[-73.914299,40.672199],"type":"Point"}
}