{
  "type": "Feature",
  "properties": {
    "addr:full":"228 Magnolia Dr Mastic Beach NY 11951",
    "addr:housenumber":"228",
    "addr:postcode":"11951",
    "addr:street":"Magnolia Dr",
    "iso:country":"US",
    "sg:address":"228 Magnolia Dr",
    "sg:city":"Mastic Beach",
    "sg:classifiers":[
        {
            "category":"Building & Trades",
            "subcategory":"Construction",
            "type":"Services"
        }
    ],
    "sg:phone":"+1 631 281 4002",
    "sg:postcode":"11951",
    "sg:province":"NY",
    "sg:tags":[
        "house"
    ],
    "wof:name":"JV Construction",
    "wof:placetype":"venue"
},
  "geometry": {"coordinates":[-72.850114,40.77068],"type":"Point"}
}