{
  "type": "Feature",
  "properties": {
    "addr:full":"22 Tobey Woods Pittsford NY 14534",
    "addr:housenumber":"22",
    "addr:postcode":"14534",
    "addr:street":"Tobey Woods",
    "iso:country":"US",
    "sg:address":"22 Tobey Woods",
    "sg:city":"Pittsford",
    "sg:classifiers":[
        {
            "category":"Professional",
            "subcategory":"Art Services",
            "type":"Services"
        }
    ],
    "sg:phone":"+1 585 586 0861",
    "sg:postcode":"14534",
    "sg:province":"NY",
    "sg:tags":[
        "graphic",
        "commercial",
        "designer",
        "artist"
    ],
    "wof:name":"Design Matters",
    "wof:placetype":"venue"
},
  "geometry": {"coordinates":[-77.536934,43.081902],"type":"Point"}
}