{
  "type": "Feature",
  "properties": {
    "iso:country":"US",
    "sg:address":"1837 Columbia Tpke",
    "sg:city":"Castletn On Hdsn",
    "sg:classifiers":[
        {
            "category":"Shopping",
            "subcategory":"Computers & Home Electronics",
            "type":"Retail Goods"
        }
    ],
    "sg:phone":"+1 518 477 5849",
    "sg:postcode":"12033",
    "sg:province":"NY",
    "sg:tags":[
        "equipment",
        "dealer"
    ],
    "wof:name":"Computer Command Ctr",
    "wof:placetype":"venue"
},
  "geometry": {"coordinates":[-73.67233400000001,42.549996],"type":"Point"}
}