{
  "type": "Feature",
  "properties": {
    "iso:country":"US",
    "sg:address":"131 Woodworth Ave",
    "sg:city":"Yonkers",
    "sg:classifiers":[
        {
            "category":"Building & Trades",
            "subcategory":"Construction",
            "type":"Services"
        }
    ],
    "sg:phone":"+1 914 968 0757",
    "sg:postcode":"10701",
    "sg:province":"NY",
    "sg:tags":[
        "woodworker"
    ],
    "wof:name":"Woodcrafters Inc",
    "wof:placetype":"venue"
},
  "geometry": {"coordinates":[-73.898483,40.942927],"type":"Point"}
}