{
  "type": "Feature",
  "properties": {
    "iso:country":"US",
    "sg:address":"382 Plank Rd",
    "sg:city":"Macedon",
    "sg:classifiers":[
        {
            "category":"Home & Garden",
            "subcategory":"Hardware",
            "type":"Retail Goods"
        }
    ],
    "sg:phone":"+1   ",
    "sg:postcode":"14502",
    "sg:province":"NY",
    "wof:name":"Bodak John M Western Snow Plow",
    "wof:placetype":"venue"
},
  "geometry": {"coordinates":[-77.364405,43.18287],"type":"Point"}
}