{
  "type": "Feature",
  "properties": {
    "iso:country":"US",
    "sg:address":"232 N Main St",
    "sg:city":"Massena",
    "sg:classifiers":[
        {
            "category":"Shopping",
            "subcategory":"Discount & Variety Stores",
            "type":"Retail Goods"
        }
    ],
    "sg:phone":"+1 315 769 1701",
    "sg:postcode":"13662",
    "sg:province":"NY",
    "wof:name":"Dollar General",
    "wof:placetype":"venue"
},
  "geometry": {"coordinates":[-74.900177,44.944015],"type":"Point"}
}