{
  "type": "Feature",
  "properties": {
    "iso:country":"US",
    "sg:address":"154 River Rd",
    "sg:city":"Mechanicville",
    "sg:classifiers":[
        {
            "category":"Retail",
            "subcategory":"Repair Shop",
            "type":"Services"
        }
    ],
    "sg:phone":"+1   ",
    "sg:postcode":"12118",
    "sg:province":"NY",
    "sg:tags":[
        "equipment",
        "hydraulic"
    ],
    "wof:name":"Mewton Hydraulics",
    "wof:placetype":"venue"
},
  "geometry": {"coordinates":[-73.66717800000001,42.930178],"type":"Point"}
}