{
  "type": "Feature",
  "properties": {
    "iso:country":"US",
    "sg:address":"120 E 167th St",
    "sg:city":"Bronx",
    "sg:classifiers":[
        {
            "category":"Banks & Credit Unions",
            "subcategory":"Bank",
            "type":"Services"
        }
    ],
    "sg:phone":"+1 718 293 2664",
    "sg:postcode":"10452",
    "sg:province":"NY",
    "sg:tags":[
        "depository",
        "banking"
    ],
    "wof:name":"Karbill Check Cashing Inc",
    "wof:placetype":"venue"
},
  "geometry": {"coordinates":[-73.918519,40.834739],"type":"Point"}
}