{
  "type": "Feature",
  "properties": {
    "iso:country":"US",
    "sg:address":"118 Coach Ln",
    "sg:city":"Levittown",
    "sg:classifiers":[
        {
            "category":"Building & Trades",
            "subcategory":"Landscaping Services",
            "type":"Services"
        }
    ],
    "sg:phone":"+1 516 520 1239",
    "sg:postcode":"11756",
    "sg:province":"NY",
    "wof:name":"Aries Lawn Maintenance Corp",
    "wof:placetype":"venue"
},
  "geometry": {"coordinates":[-73.520251,40.719307],"type":"Point"}
}