{
  "type": "Feature",
  "properties": {
    "iso:country":"US",
    "sg:address":"2403 E 22nd St",
    "sg:city":"Brooklyn",
    "sg:classifiers":[
        {
            "category":"Wholesale",
            "subcategory":"Home Furnishings",
            "type":"Manufacturing & Wholesale Goods"
        }
    ],
    "sg:phone":"+1 718 615 1800",
    "sg:postcode":"11235",
    "sg:province":"NY",
    "sg:tags":[
        "blind",
        "shade"
    ],
    "wof:name":"Blinds Boutique Inc",
    "wof:placetype":"venue"
},
  "geometry": {"coordinates":[-73.948154,40.592881],"type":"Point"}
}