{
  "type": "Feature",
  "properties": {
    "iso:country":"US",
    "sg:address":"6359 S Stockton-Cassadaga Rd",
    "sg:city":"Sinclairville",
    "sg:classifiers":[
        {
            "category":"Shopping",
            "subcategory":"Gifts & Souvenirs",
            "type":"Retail Goods"
        }
    ],
    "sg:phone":"+1   ",
    "sg:postcode":"14782",
    "sg:province":"NY",
    "sg:tags":[
        "shop"
    ],
    "wof:name":"Kabob Bear Country",
    "wof:placetype":"venue"
},
  "geometry": {"coordinates":[-79.315681,42.274768],"type":"Point"}
}