{
  "type": "Feature",
  "properties": {
    "iso:country":"US",
    "sg:address":"108 Franklin St",
    "sg:city":"Brooklyn",
    "sg:classifiers":[
        {
            "category":"Coffee & Tea",
            "type":"Food & Drink"
        },
        {
            "category":"Restaurant",
            "type":"Food & Drink"
        }
    ],
    "sg:phone":"+1 718 770 7918",
    "sg:postcode":"11222",
    "sg:province":"NY",
    "sg:tags":[
        "french"
    ],
    "sg:website":"www.legamin.com",
    "wof:name":"Le Gamin",
    "wof:placetype":"venue"
},
  "geometry": {"coordinates":[-73.957071,40.728294],"type":"Point"}
}