{
  "type": "Feature",
  "properties": {
    "iso:country":"US",
    "sg:address":"1504 Old Country Rd",
    "sg:city":"Westbury",
    "sg:classifiers":[
        {
            "category":"Shopping",
            "subcategory":"Jewelry",
            "type":"Retail Goods"
        }
    ],
    "sg:phone":"+1 516 794 4361",
    "sg:postcode":"11590",
    "sg:province":"NY",
    "wof:name":"Zales Jewelers",
    "wof:placetype":"venue"
},
  "geometry": {"coordinates":[-73.59485100000001,40.746646],"type":"Point"}
}