{
  "type": "Feature",
  "properties": {
    "addr:full":"197 Riverdale Ave Yonkers NY 10705",
    "addr:housenumber":"197",
    "addr:postcode":"10705",
    "addr:street":"Riverdale Ave",
    "iso:country":"US",
    "sg:address":"197 Riverdale Ave",
    "sg:city":"Yonkers",
    "sg:classifiers":[
        {
            "category":"Retail",
            "subcategory":"Auto Repair",
            "type":"Services"
        }
    ],
    "sg:phone":"+1 914 963 5339",
    "sg:postcode":"10705",
    "sg:province":"NY",
    "sg:tags":[
        "body",
        "automobile",
        "painting"
    ],
    "wof:name":"Westchester Auto Body & Spring",
    "wof:placetype":"venue"
},
  "geometry": {"coordinates":[-73.901042,40.926713],"type":"Point"}
}