{
  "type": "Feature",
  "properties": {
    "addr:full":"223 Rogers Ave Brooklyn NY 11225",
    "addr:housenumber":"223",
    "addr:postcode":"11225",
    "addr:street":"Rogers Ave",
    "iso:country":"US",
    "sg:address":"223 Rogers Ave",
    "sg:city":"Brooklyn",
    "sg:classifiers":[
        {
            "category":"Social Services",
            "subcategory":"Child Care",
            "type":"Services"
        }
    ],
    "sg:phone":"+1 718 773 2397",
    "sg:postcode":"11225",
    "sg:province":"NY",
    "sg:tags":[
        "day"
    ],
    "wof:name":"Small Tots",
    "wof:placetype":"venue"
},
  "geometry": {"coordinates":[-73.9533,40.668701],"type":"Point"}
}