{
  "type": "Feature",
  "properties": {
    "addr:full":"160 Columbus Ave New York NY 10023",
    "addr:housenumber":"160",
    "addr:postcode":"10023",
    "addr:street":"Columbus Ave",
    "iso:country":"US",
    "sg:address":"160 Columbus Ave",
    "sg:city":"New York",
    "sg:classifiers":[
        {
            "category":"Retail",
            "subcategory":"Laundry & Dry Cleaning",
            "type":"Services"
        }
    ],
    "sg:phone":"+1 212 595 0932",
    "sg:postcode":"10023",
    "sg:province":"NY",
    "sg:tags":[
        "cleaners"
    ],
    "wof:name":"East 51 Dry Cleaners Inc",
    "wof:placetype":"venue"
},
  "geometry": {"coordinates":[-73.98076,40.774825],"type":"Point"}
}