{
  "type": "Feature",
  "properties": {
    "addr:full":"121 W 27th St Ste 305 Manhattan NY 10001",
    "addr:housenumber":"121",
    "addr:postcode":"10001",
    "addr:street":"W 27Th St Ste 305",
    "iso:country":"US",
    "sg:address":"121 W 27th St Ste 305",
    "sg:city":"Manhattan",
    "sg:classifiers":[
        {
            "category":"Health Services",
            "subcategory":"Health Practitioner",
            "type":"Services"
        }
    ],
    "sg:phone":"+1 646 484 9335",
    "sg:postcode":"10001",
    "sg:province":"NY",
    "sg:tags":[
        "acupuncture"
    ],
    "sg:website":"www.akoya-acupuncture.com",
    "wof:name":"Akoya Acupuncture",
    "wof:placetype":"venue"
},
  "geometry": {"coordinates":[-73.99194,40.746071],"type":"Point"}
}