{
  "type": "Feature",
  "properties": {
    "addr:full":"147 W Montauk Hwy Hampton Bays NY 11946",
    "addr:housenumber":"147",
    "addr:postcode":"11946",
    "addr:street":"W Montauk Hwy",
    "iso:country":"US",
    "sg:address":"147 W Montauk Hwy",
    "sg:city":"Hampton Bays",
    "sg:classifiers":[
        {
            "category":"Health Services",
            "subcategory":"Chiropractor",
            "type":"Services"
        }
    ],
    "sg:phone":"+1 631 728 8545",
    "sg:postcode":"11946",
    "sg:province":"NY",
    "wof:name":"Hampton Bays Chiropractic",
    "wof:placetype":"venue"
},
  "geometry": {"coordinates":[-72.53289599999999,40.876337],"type":"Point"}
}