{
  "type": "Feature",
  "properties": {
    "addr:full":"431 W Broadway New York NY 10012",
    "addr:housenumber":"431",
    "addr:postcode":"10012",
    "addr:street":"W Broadway",
    "iso:country":"US",
    "sg:address":"431 W Broadway",
    "sg:city":"New York",
    "sg:classifiers":[
        {
            "category":"Banks & Credit Unions",
            "subcategory":"Financial Services",
            "type":"Services"
        }
    ],
    "sg:phone":"+1 212 226 5891",
    "sg:postcode":"10012",
    "sg:province":"NY",
    "sg:tags":[
        "building",
        "owner",
        "cooperative"
    ],
    "wof:name":"431 Broad West Corp",
    "wof:placetype":"venue"
},
  "geometry": {"coordinates":[-74.001357,40.724918],"type":"Point"}
}