{
  "type": "Feature",
  "properties": {
    "addr:full":"5 May Hill Ln Dix Hills NY 11746",
    "addr:housenumber":"5",
    "addr:postcode":"11746",
    "addr:street":"May Hill Ln",
    "iso:country":"US",
    "sg:address":"5 May Hill Ln",
    "sg:city":"Dix Hills",
    "sg:classifiers":[
        {
            "category":"Real Estate",
            "subcategory":"Real Estate Agent",
            "type":"Services"
        }
    ],
    "sg:phone":"+1 631 253 9175",
    "sg:postcode":"11746",
    "sg:province":"NY",
    "wof:name":"National Properties Corp",
    "wof:placetype":"venue"
},
  "geometry": {"coordinates":[-73.361913,40.785742],"type":"Point"}
}