{
  "type": "Feature",
  "properties": {
    "addr:full":"166 Grand St Exd Brooklyn NY 11211",
    "addr:housenumber":"166",
    "addr:postcode":"11211",
    "addr:street":"Grand St Exd",
    "iso:country":"US",
    "sg:address":"166 Grand St Exd",
    "sg:city":"Brooklyn",
    "sg:classifiers":[
        {
            "category":"Retail",
            "subcategory":"Auto Repair",
            "type":"Services"
        }
    ],
    "sg:phone":"+1 718 384 7054",
    "sg:postcode":"11211",
    "sg:province":"NY",
    "sg:tags":[
        "repairing",
        "tire"
    ],
    "wof:name":"Choi's Tire & Svc",
    "wof:placetype":"venue"
},
  "geometry": {"coordinates":[-73.953132,40.71076],"type":"Point"}
}