{
  "type": "Feature",
  "properties": {
    "iso:country":"US",
    "sg:address":"149 33rd St",
    "sg:city":"Brooklyn",
    "sg:classifiers":[
        {
            "category":"Wholesale",
            "subcategory":"Apparel",
            "type":"Manufacturing & Wholesale Goods"
        }
    ],
    "sg:phone":"+1 718 788 2831",
    "sg:postcode":"11232",
    "sg:province":"NY",
    "wof:name":"Sincere Sportwear Corp",
    "wof:placetype":"venue"
},
  "geometry": {"coordinates":[-74.00355,40.656783],"type":"Point"}
}