{
  "type": "Feature",
  "properties": {
    "iso:country":"US",
    "sg:address":"110 Hopper St",
    "sg:city":"Westbury",
    "sg:classifiers":[
        {
            "category":"Professional",
            "subcategory":"Business Services",
            "type":"Services"
        }
    ],
    "sg:phone":"+1 800 381 9763",
    "sg:postcode":"11590",
    "sg:province":"NY",
    "wof:name":"Express Crane Service Inc",
    "wof:placetype":"venue"
},
  "geometry": {"coordinates":[-73.566093,40.758063],"type":"Point"}
}