{
  "type": "Feature",
  "properties": {
    "addr:full":"625 Merrick Ave East Meadow NY 11554",
    "addr:housenumber":"625",
    "addr:postcode":"11554",
    "addr:street":"Merrick Ave",
    "iso:country":"US",
    "sg:address":"625 Merrick Ave",
    "sg:city":"East Meadow",
    "sg:classifiers":[
        {
            "category":"Sports & Exercise",
            "subcategory":"Gym",
            "type":"Entertainment"
        }
    ],
    "sg:phone":"+1 516 564 9000",
    "sg:postcode":"11554",
    "sg:province":"NY",
    "sg:tags":[
        "trainer"
    ],
    "sg:website":"www.islandsportspt.com",
    "wof:name":"Island Sports Physical Therapy",
    "wof:placetype":"venue"
},
  "geometry": {"coordinates":[-73.570099,40.706799],"type":"Point"}
}