{
  "type": "Feature",
  "properties": {
    "addr:full":"381 Lido Blvd Long Beach NY 11561",
    "addr:housenumber":"381",
    "addr:postcode":"11561",
    "addr:street":"Lido Blvd",
    "iso:country":"US",
    "sg:address":"381 Lido Blvd",
    "sg:city":"Long Beach",
    "sg:classifiers":[
        {
            "category":"Professional",
            "subcategory":"Lawyer & Legal Services",
            "type":"Services"
        }
    ],
    "sg:phone":"+1 516 889 1660",
    "sg:postcode":"11561",
    "sg:province":"NY",
    "wof:name":"Wolkenberg Alfred Atty",
    "wof:placetype":"venue"
},
  "geometry": {"coordinates":[-73.62772699999999,40.588052],"type":"Point"}
}