{
  "type": "Feature",
  "properties": {
    "addr:full":"150 Express St Plainview NY 11803",
    "addr:postcode":"11803",
    "addr:street":"St",
    "iso:country":"US",
    "sg:address":"150 Express St",
    "sg:city":"Plainview",
    "sg:classifiers":[
        {
            "category":"Professional",
            "subcategory":"Management & Consulting",
            "type":"Services"
        }
    ],
    "sg:phone":"+1 516 349 7774",
    "sg:postcode":"11803",
    "sg:province":"NY",
    "sg:tags":[
        "fuel"
    ],
    "wof:name":"Able Management Group Inc",
    "wof:placetype":"venue"
},
  "geometry": {"coordinates":[-73.460956,40.789787],"type":"Point"}
}