{
  "type": "Feature",
  "properties": {
    "addr:full":"4519 Military Rd Niagara Falls NY 14305",
    "addr:housenumber":"4519",
    "addr:postcode":"14305",
    "addr:street":"Military Rd",
    "iso:country":"US",
    "sg:address":"4519 Military Rd",
    "sg:city":"Niagara Falls",
    "sg:classifiers":[
        {
            "category":"Shopping",
            "subcategory":"Discount & Variety Stores",
            "type":"Retail Goods"
        }
    ],
    "sg:phone":"+1 716 297 3158",
    "sg:postcode":"14305",
    "sg:province":"NY",
    "wof:name":"Dollar General",
    "wof:placetype":"venue"
},
  "geometry": {"coordinates":[-79.00401100000001,43.127087],"type":"Point"}
}