{
  "type": "Feature",
  "properties": {
    "iso:country":"US",
    "sg:address":"216 Lafayette St",
    "sg:city":"Schenectady",
    "sg:classifiers":[
        {
            "category":"Professional",
            "type":"Services"
        }
    ],
    "sg:phone":"+1 518 386 3360",
    "sg:postcode":"12305",
    "sg:province":"NY",
    "sg:tags":[
        "establishment"
    ],
    "wof:name":"Continuint Treatment",
    "wof:placetype":"venue"
},
  "geometry": {"coordinates":[-73.939781,42.811572],"type":"Point"}
}