{
  "type": "Feature",
  "properties": {
    "iso:country":"US",
    "sg:address":"230 Jersey Ave",
    "sg:city":"Port Jervis",
    "sg:classifiers":[
        {
            "category":"Real Estate",
            "subcategory":"Real Estate Operator",
            "type":"Services"
        }
    ],
    "sg:phone":"+1 845 856 7677",
    "sg:postcode":"12771",
    "sg:province":"NY",
    "sg:tags":[
        "building",
        "apartment"
    ],
    "wof:name":"Machackemach Village",
    "wof:placetype":"venue"
},
  "geometry": {"coordinates":[-74.68427699999999,41.364862],"type":"Point"}
}