{
  "type": "Feature",
  "properties": {
    "addr:full":"2705 Schley Ave Bronx NY 10465",
    "addr:housenumber":"2705",
    "addr:postcode":"10465",
    "addr:street":"Schley Ave",
    "iso:country":"US",
    "sg:address":"2705 Schley Ave",
    "sg:city":"Bronx",
    "sg:classifiers":[
        {
            "category":"Social Services",
            "type":"Services"
        }
    ],
    "sg:phone":"+1 718 863 8833",
    "sg:postcode":"10465",
    "sg:province":"NY",
    "sg:tags":[
        "organization",
        "welfare"
    ],
    "wof:name":"Jasa-Friendship House",
    "wof:placetype":"venue"
},
  "geometry": {"coordinates":[-73.82808300000001,40.82129],"type":"Point"}
}