{
  "type": "Feature",
  "properties": {
    "addr:full":"40 W 25th Street New York NY 10010",
    "addr:housenumber":"40",
    "addr:postcode":"10010",
    "addr:street":"W 25Th Street",
    "iso:country":"US",
    "sg:address":"40 W 25th Street",
    "sg:city":"New York",
    "sg:classifiers":[
        {
            "category":"Retail",
            "subcategory":"Portrait Studio",
            "type":"Services"
        },
        {
            "category":"Professional",
            "subcategory":"Art Services",
            "type":"Services"
        }
    ],
    "sg:phone":"+1 212 691 3923",
    "sg:postcode":"10010",
    "sg:province":"NY",
    "sg:tags":[
        "photographer",
        "photography",
        "store"
    ],
    "wof:name":"Marlene Wetherell Vintage Fashion and Photography",
    "wof:placetype":"venue"
},
  "geometry": {"coordinates":[-73.989997,40.743369],"type":"Point"}
}