{
  "type": "Feature",
  "properties": {
    "addr:full":"1747 Mahan Ave Bronx NY 10461",
    "addr:housenumber":"1747",
    "addr:postcode":"10461",
    "addr:street":"Mahan Ave",
    "iso:country":"US",
    "sg:address":"1747 Mahan Ave",
    "sg:city":"Bronx",
    "sg:classifiers":[
        {
            "category":"Restaurant",
            "type":"Food & Drink"
        }
    ],
    "sg:phone":"+1   ",
    "sg:postcode":"10461",
    "sg:province":"NY",
    "sg:tags":[
        "eating"
    ],
    "wof:name":"Family Affair Pizza & Dining",
    "wof:placetype":"venue"
},
  "geometry": {"coordinates":[-73.829357,40.847143],"type":"Point"}
}