{
  "type": "Feature",
  "properties": {
    "addr:full":"320 Ford St Ogdensburg NY 13669",
    "addr:housenumber":"320",
    "addr:postcode":"13669",
    "addr:street":"Ford St",
    "iso:country":"US",
    "sg:address":"320 Ford St",
    "sg:city":"Ogdensburg",
    "sg:classifiers":[
        {
            "category":"Banks & Credit Unions",
            "subcategory":"Bank",
            "type":"Services"
        }
    ],
    "sg:phone":"+1 315 393 7000",
    "sg:postcode":"13669",
    "sg:province":"NY",
    "wof:name":"Community Bank",
    "wof:placetype":"venue"
},
  "geometry": {"coordinates":[-75.49229200000001,44.697863],"type":"Point"}
}