{
  "type": "Feature",
  "properties": {
    "addr:full":"1552 Ralph Ave Brooklyn NY 11236",
    "addr:housenumber":"1552",
    "addr:postcode":"11236",
    "addr:street":"Ralph Ave",
    "iso:country":"US",
    "sg:address":"1552 Ralph Ave",
    "sg:city":"Brooklyn",
    "sg:classifiers":[
        {
            "category":"Health Services",
            "subcategory":"Health Practitioner",
            "type":"Services"
        }
    ],
    "sg:phone":"+1 718 444 0600",
    "sg:postcode":"11236",
    "sg:province":"NY",
    "sg:tags":[
        "therapist",
        "physical"
    ],
    "wof:name":"Canarsie Medical & Rehab PC",
    "wof:placetype":"venue"
},
  "geometry": {"coordinates":[-73.919416,40.639229],"type":"Point"}
}