{
  "type": "Feature",
  "properties": {
    "iso:country":"US",
    "sg:address":"930 Flatbush Ave",
    "sg:city":"Brooklyn",
    "sg:classifiers":[
        {
            "category":"Wholesale",
            "subcategory":"Sporting Goods",
            "type":"Manufacturing & Wholesale Goods"
        },
        {
            "category":"Shopping",
            "subcategory":"Bicycles & Sporting Goods",
            "type":"Retail Goods"
        }
    ],
    "sg:phone":"+1 718 462 7140",
    "sg:postcode":"11226",
    "sg:province":"NY",
    "sg:tags":[
        "sportswear"
    ],
    "wof:name":"Friedmans Sporting Goods Inc",
    "wof:placetype":"venue"
},
  "geometry": {"coordinates":[-73.958674,40.650141],"type":"Point"}
}