{
  "type": "Feature",
  "properties": {
    "addr:full":"387 E Fordham Rd Bronx NY 10458",
    "addr:housenumber":"387",
    "addr:postcode":"10458",
    "addr:street":"E Fordham Rd",
    "iso:country":"US",
    "sg:address":"387 E Fordham Rd",
    "sg:city":"Bronx",
    "sg:classifiers":[
        {
            "category":"Recreation",
            "type":"Entertainment"
        }
    ],
    "sg:phone":"+1 718 584 2394",
    "sg:postcode":"10458",
    "sg:province":"NY",
    "sg:tags":[
        "hall",
        "auditorium"
    ],
    "wof:name":"Kingsbridge Heights Comm Ctr",
    "wof:placetype":"venue"
},
  "geometry": {"coordinates":[-73.89138,40.861701],"type":"Point"}
}