{
  "type": "Feature",
  "properties": {
    "iso:country":"US",
    "sg:address":"20 Hewlett Rd",
    "sg:city":"Poughkeepsie",
    "sg:classifiers":[
        {
            "category":"Building & Trades",
            "subcategory":"Construction",
            "type":"Services"
        }
    ],
    "sg:phone":"+1 845 473 8843",
    "sg:postcode":"12603",
    "sg:province":"NY",
    "sg:tags":[
        "general",
        "contractor"
    ],
    "wof:name":"Woodside & Young Inc",
    "wof:placetype":"venue"
},
  "geometry": {"coordinates":[-73.907014,41.674643],"type":"Point"}
}