{
  "type": "Feature",
  "properties": {
    "iso:country":"US",
    "sg:address":"33 Muriel Ave",
    "sg:city":"Lawrence",
    "sg:classifiers":[
        {
            "category":"Real Estate",
            "subcategory":"Real Estate Agent",
            "type":"Services"
        }
    ],
    "sg:phone":"+1 516 239 6906",
    "sg:postcode":"11559",
    "sg:province":"NY",
    "wof:name":"Oxford Realty Co",
    "wof:placetype":"venue"
},
  "geometry": {"coordinates":[-73.726471,40.615799],"type":"Point"}
}