{
  "type": "Feature",
  "properties": {
    "addr:full":"2858 W Henrietta Rd Rochester NY 14623",
    "addr:housenumber":"2858",
    "addr:postcode":"14623",
    "addr:street":"W Henrietta Rd",
    "iso:country":"US",
    "sg:address":"2858 W Henrietta Rd",
    "sg:city":"Rochester",
    "sg:classifiers":[
        {
            "category":"Shopping",
            "subcategory":"Clothing, Apparel, & Fashions",
            "type":"Retail Goods"
        }
    ],
    "sg:phone":"+1 585 427 8446",
    "sg:postcode":"14623",
    "sg:province":"NY",
    "sg:tags":[
        "alteration"
    ],
    "wof:name":"Speedy's Cleaners",
    "wof:placetype":"venue"
},
  "geometry": {"coordinates":[-77.632886,43.094313],"type":"Point"}
}