{
  "type": "Feature",
  "properties": {
    "addr:full":"220 Clifton Country Mall Clifton Park NY 12065",
    "addr:housenumber":"220",
    "addr:postcode":"12065",
    "addr:street":"Clifton Country Mall",
    "iso:country":"US",
    "sg:address":"220 Clifton Country Mall",
    "sg:city":"Clifton Park",
    "sg:classifiers":[
        {
            "category":"Shopping",
            "subcategory":"Gifts & Souvenirs",
            "type":"Retail Goods"
        }
    ],
    "sg:phone":"+1   ",
    "sg:postcode":"12065",
    "sg:province":"NY",
    "wof:name":"Matthews Hallmark 144",
    "wof:placetype":"venue"
},
  "geometry": {"coordinates":[-73.777372,42.859324],"type":"Point"}
}