{
  "type": "Feature",
  "properties": {
    "addr:full":"180 W End Avenue New York NY 10023",
    "addr:housenumber":"180",
    "addr:postcode":"10023",
    "addr:street":"W End Avenue",
    "iso:country":"US",
    "sg:address":"180 W End Avenue",
    "sg:city":"New York",
    "sg:classifiers":[
        {
            "category":"Health Services",
            "subcategory":"Dentist",
            "type":"Services"
        }
    ],
    "sg:phone":"+1 212 595 1500",
    "sg:postcode":"10023",
    "sg:province":"NY",
    "sg:tags":[
        "orthodontist"
    ],
    "wof:name":"Ganjain Benjamin DDS",
    "wof:placetype":"venue"
},
  "geometry": {"coordinates":[-73.986014,40.777711],"type":"Point"}
}