{
  "type": "Feature",
  "properties": {
    "iso:country":"US",
    "sg:address":"3926 Broadway St",
    "sg:city":"Cheektowaga",
    "sg:classifiers":[
        {
            "category":"Wholesale",
            "subcategory":"Electrical",
            "type":"Manufacturing & Wholesale Goods"
        }
    ],
    "sg:phone":"+1 716 681 4277",
    "sg:postcode":"14227",
    "sg:province":"NY",
    "sg:tags":[
        "alarm",
        "burglar",
        "system"
    ],
    "sg:website":"www.alarmparts.com",
    "wof:name":"Alarm Parts & Supply Co Inc",
    "wof:placetype":"venue"
},
  "geometry": {"coordinates":[-78.730603,42.904423],"type":"Point"}
}