{
  "type": "Feature",
  "properties": {
    "addr:full":"3285 Veterans Memorial Hwy Ronkonkoma NY 11779",
    "addr:housenumber":"3285",
    "addr:postcode":"11779",
    "addr:street":"Veterans Memorial Hwy",
    "iso:country":"US",
    "sg:address":"3285 Veterans Memorial Hwy",
    "sg:city":"Ronkonkoma",
    "sg:classifiers":[
        {
            "category":"Insurance",
            "subcategory":"Insurance Agent",
            "type":"Services"
        }
    ],
    "sg:phone":"+1 631 297 0601",
    "sg:postcode":"11779",
    "sg:province":"NY",
    "sg:tags":[
        "property",
        "agency",
        "casualty"
    ],
    "wof:name":"New York Pacific Associates",
    "wof:placetype":"venue"
},
  "geometry": {"coordinates":[-73.132363,40.787718],"type":"Point"}
}