{
  "type": "Feature",
  "properties": {
    "addr:full":"5450 Camp Rd Hamburg NY 14075",
    "addr:housenumber":"5450",
    "addr:postcode":"14075",
    "addr:street":"Camp Rd",
    "iso:country":"US",
    "sg:address":"5450 Camp Rd",
    "sg:city":"Hamburg",
    "sg:classifiers":[
        {
            "category":"Health Services",
            "subcategory":"Medical Lab",
            "type":"Services"
        }
    ],
    "sg:phone":"+1 716 649 7404",
    "sg:postcode":"14075",
    "sg:province":"NY",
    "sg:tags":[
        "laboratory"
    ],
    "sg:website":"www.healthtrac.com",
    "wof:name":"Healthtrac Inc",
    "wof:placetype":"venue"
},
  "geometry": {"coordinates":[-78.844509,42.738365],"type":"Point"}
}