{
  "type": "Feature",
  "properties": {
    "addr:full":"317 E Delavan Ave Buffalo NY 14208",
    "addr:housenumber":"317",
    "addr:postcode":"14208",
    "addr:street":"E Delavan Ave",
    "iso:country":"US",
    "sg:address":"317 E Delavan Ave",
    "sg:city":"Buffalo",
    "sg:classifiers":[
        {
            "category":"Personal",
            "subcategory":"Barber",
            "type":"Services"
        }
    ],
    "sg:phone":"+1 716 995 6423",
    "sg:postcode":"14208",
    "sg:province":"NY",
    "wof:name":"Hair Drob Inc",
    "wof:placetype":"venue"
},
  "geometry": {"coordinates":[-78.845365,42.921832],"type":"Point"}
}