{
  "type": "Feature",
  "properties": {
    "iso:country":"US",
    "sg:address":"50 Monroe Pl",
    "sg:city":"Brooklyn",
    "sg:classifiers":[
        {
            "category":"Education",
            "subcategory":"Special Training",
            "type":"Public Place"
        }
    ],
    "sg:phone":"+1 718 253 9001",
    "sg:postcode":"11201",
    "sg:province":"NY",
    "sg:tags":[
        "health",
        "mental"
    ],
    "wof:name":"Blanton Peal Comm Couns Cnts",
    "wof:placetype":"venue"
},
  "geometry": {"coordinates":[-73.99238699999999,40.696912],"type":"Point"}
}