{
  "type": "Feature",
  "properties": {
    "addr:full":"6611 State Rte 5 and 20 Bloomfield NY 14469",
    "addr:housenumber":"6611",
    "addr:postcode":"14469",
    "addr:street":"State Rte 5 And 20",
    "iso:country":"US",
    "sg:address":"6611 State Rte 5 and 20",
    "sg:city":"Bloomfield",
    "sg:classifiers":[
        {
            "category":"Home & Garden",
            "subcategory":"Garden Supply",
            "type":"Retail Goods"
        },
        {
            "category":"Building & Trades",
            "subcategory":"Landscaping Services",
            "type":"Services"
        }
    ],
    "sg:phone":"+1 585 657 7165",
    "sg:postcode":"14469",
    "sg:province":"NY",
    "sg:tags":[
        "store",
        "landscape",
        "contractor"
    ],
    "wof:name":"Country Corners Nursery Inc",
    "wof:placetype":"venue"
},
  "geometry": {"coordinates":[-77.383206,42.883084],"type":"Point"}
}