{
  "type": "Feature",
  "properties": {
    "addr:full":"3902 S Salina St Syracuse NY 13205",
    "addr:housenumber":"3902",
    "addr:postcode":"13205",
    "addr:street":"S Salina St",
    "iso:country":"US",
    "sg:address":"3902 S Salina St",
    "sg:city":"Syracuse",
    "sg:classifiers":[
        {
            "category":"Retail",
            "subcategory":"Auto Rental",
            "type":"Services"
        }
    ],
    "sg:phone":"+1 315 492 0852",
    "sg:postcode":"13205",
    "sg:province":"NY",
    "sg:tags":[
        "renting",
        "truck",
        "leasing"
    ],
    "wof:name":"Budget Truck Rental",
    "wof:placetype":"venue"
},
  "geometry": {"coordinates":[-76.142431,43.009773],"type":"Point"}
}