{
  "type": "Feature",
  "properties": {
    "addr:full":"12 Cobeck Ct Brooklyn NY 11223",
    "addr:housenumber":"12",
    "addr:postcode":"11223",
    "addr:street":"Cobeck Ct",
    "iso:country":"US",
    "sg:address":"12 Cobeck Ct",
    "sg:city":"Brooklyn",
    "sg:classifiers":[
        {
            "category":"Retail",
            "subcategory":"Auto Repair",
            "type":"Services"
        }
    ],
    "sg:phone":"+1 718 382 1200",
    "sg:postcode":"11223",
    "sg:province":"NY",
    "sg:tags":[
        "body",
        "shop"
    ],
    "wof:name":"Meyer's Custom Collision",
    "wof:placetype":"venue"
},
  "geometry": {"coordinates":[-73.973602,40.5872],"type":"Point"}
}