{
  "type": "Feature",
  "properties": {
    "iso:country":"US",
    "sg:address":"1270 67th St",
    "sg:city":"Brooklyn",
    "sg:classifiers":[
        {
            "category":"Health Services",
            "subcategory":"Nursing And Care Facility",
            "type":"Services"
        }
    ],
    "sg:phone":"+1 718 232 2322",
    "sg:postcode":"11219",
    "sg:province":"NY",
    "sg:tags":[
        "skilled"
    ],
    "wof:name":"Norwegian Christn HM For Aged",
    "wof:placetype":"venue"
},
  "geometry": {"coordinates":[-74.00397,40.625712],"type":"Point"}
}