{
  "type": "Feature",
  "properties": {
    "iso:country":"US",
    "sg:address":"1019 Kinderhook St",
    "sg:city":"Valatie",
    "sg:classifiers":[
        {
            "category":"Professional",
            "subcategory":"Lawyer & Legal Services",
            "type":"Services"
        }
    ],
    "sg:phone":"+1   ",
    "sg:postcode":"12184",
    "sg:province":"NY",
    "wof:name":"Barford Burns F Jr Attny",
    "wof:placetype":"venue"
},
  "geometry": {"coordinates":[-73.689161,42.409624],"type":"Point"}
}