{
  "type": "Feature",
  "properties": {
    "addr:full":"82 S Long Beach Rd Rockville Centre NY 11570",
    "addr:housenumber":"82",
    "addr:postcode":"11570",
    "addr:street":"S Long Beach Rd",
    "iso:country":"US",
    "sg:address":"82 S Long Beach Rd",
    "sg:city":"Rockville Centre",
    "sg:classifiers":[
        {
            "category":"Manufacturing",
            "subcategory":"Furniture",
            "type":"Manufacturing & Wholesale Goods"
        },
        {
            "category":"Home & Garden",
            "subcategory":"Furniture",
            "type":"Retail Goods"
        }
    ],
    "sg:phone":"+1 516 536 7505",
    "sg:postcode":"11570",
    "sg:province":"NY",
    "sg:tags":[
        "cabinet",
        "manufacturer",
        "custom"
    ],
    "wof:name":"Diamond Cabinet Company Inc",
    "wof:placetype":"venue"
},
  "geometry": {"coordinates":[-73.63551200000001,40.652498],"type":"Point"}
}