{
  "type": "Feature",
  "properties": {
    "iso:country":"US",
    "sg:address":"1140 Broadway",
    "sg:city":"New York",
    "sg:classifiers":[
        {
            "category":"Shopping",
            "type":"Retail Goods"
        }
    ],
    "sg:phone":"+1 212 780 9680",
    "sg:postcode":"10001",
    "sg:province":"NY",
    "sg:tags":[
        "equipment",
        "telephone",
        "supply"
    ],
    "sg:website":"www.nccomm.com",
    "wof:name":"Newcastle Communications",
    "wof:placetype":"venue"
},
  "geometry": {"coordinates":[-73.98886899999999,40.744533],"type":"Point"}
}