{
  "type": "Feature",
  "properties": {
    "addr:full":"22 E 65th Street New York NY 10021",
    "addr:housenumber":"22",
    "addr:postcode":"10021",
    "addr:street":"E 65Th Street",
    "iso:country":"US",
    "sg:address":"22 E 65th Street",
    "sg:city":"New York",
    "sg:classifiers":[
        {
            "category":"Retail",
            "subcategory":"Portrait Studio",
            "type":"Services"
        }
    ],
    "sg:phone":"+1 212 535 2800",
    "sg:postcode":"10021",
    "sg:province":"NY",
    "sg:tags":[
        "photography",
        "store"
    ],
    "wof:name":"Carltle Photo Corporation",
    "wof:placetype":"venue"
},
  "geometry": {"coordinates":[-73.968977,40.767573],"type":"Point"}
}