{
  "type": "Feature",
  "properties": {
    "iso:country":"US",
    "sg:address":"1 Mustang Dr",
    "sg:city":"Cohoes",
    "sg:classifiers":[
        {
            "category":"Professional",
            "subcategory":"Computer Services",
            "type":"Services"
        }
    ],
    "sg:phone":"+1 518 782 4100",
    "sg:postcode":"12047",
    "sg:province":"NY",
    "sg:tags":[
        "processing",
        "datum"
    ],
    "wof:name":"CSC Business Solution Ctr",
    "wof:placetype":"venue"
},
  "geometry": {"coordinates":[-73.73266,42.79815],"type":"Point"}
}