{
  "type": "Feature",
  "properties": {
    "addr:full":"1290 Grand Ave Baldwin NY 11510",
    "addr:housenumber":"1290",
    "addr:postcode":"11510",
    "addr:street":"Grand Ave",
    "iso:country":"US",
    "sg:address":"1290 Grand Ave",
    "sg:city":"Baldwin",
    "sg:classifiers":[
        {
            "category":"Restaurant",
            "type":"Food & Drink"
        }
    ],
    "sg:menulink":"http://www.allmenus.com/ny/baldwin/89993-golden-krust/menu/",
    "sg:phone":"+1 516 377 3884",
    "sg:postcode":"11510",
    "sg:province":"NY",
    "sg:tags":[
        "caribbean"
    ],
    "wof:name":"Golden Krust",
    "wof:placetype":"venue"
},
  "geometry": {"coordinates":[-73.614588,40.678799],"type":"Point"}
}