{
  "type": "Feature",
  "properties": {
    "addr:full":"312 Lake St Elmira NY 14901",
    "addr:housenumber":"312",
    "addr:postcode":"14901",
    "addr:street":"Lake St",
    "iso:country":"US",
    "sg:address":"312 Lake St",
    "sg:city":"Elmira",
    "sg:classifiers":[
        {
            "category":"Professional",
            "subcategory":"Lawyer & Legal Services",
            "type":"Services"
        }
    ],
    "sg:phone":"+1 607 734 5004",
    "sg:postcode":"14901",
    "sg:province":"NY",
    "sg:tags":[
        "attorney"
    ],
    "wof:name":"Roe & Hamm",
    "wof:placetype":"venue"
},
  "geometry": {"coordinates":[-76.80322,42.09281],"type":"Point"}
}