{
  "type": "Feature",
  "properties": {
    "addr:full":"1212 5th Ave New York NY 10029",
    "addr:housenumber":"1212",
    "addr:postcode":"10029",
    "addr:street":"5Th Ave",
    "iso:country":"US",
    "sg:address":"1212 5th Ave",
    "sg:city":"New York",
    "sg:classifiers":[
        {
            "category":"Manufacturing",
            "subcategory":"Printing",
            "type":"Manufacturing & Wholesale Goods"
        }
    ],
    "sg:phone":"+1 212 427 7346",
    "sg:postcode":"10029",
    "sg:province":"NY",
    "sg:tags":[
        "publisher"
    ],
    "wof:name":"Boxwood Press",
    "wof:placetype":"venue"
},
  "geometry": {"coordinates":[-73.95343699999999,40.791084],"type":"Point"}
}