{
  "type": "Feature",
  "properties": {
    "addr:full":"25 E Bank St Albion NY 14411",
    "addr:housenumber":"25",
    "addr:postcode":"14411",
    "addr:street":"E Bank St",
    "iso:country":"US",
    "sg:address":"25 E Bank St",
    "sg:city":"Albion",
    "sg:classifiers":[
        {
            "category":"Real Estate",
            "subcategory":"Real Estate Agent",
            "type":"Services"
        }
    ],
    "sg:phone":"+1 585 589 6777",
    "sg:postcode":"14411",
    "sg:province":"NY",
    "wof:name":"E Z Sell Real Estate",
    "wof:placetype":"venue"
},
  "geometry": {"coordinates":[-78.19337400000001,43.247954],"type":"Point"}
}