{
  "type": "Feature",
  "properties": {
    "addr:full":"91 Rapp Rd Monticello NY 12701",
    "addr:housenumber":"91",
    "addr:postcode":"12701",
    "addr:street":"Rapp Rd",
    "iso:country":"US",
    "sg:address":"91 Rapp Rd",
    "sg:city":"Monticello",
    "sg:classifiers":[
        {
            "category":"Building & Trades",
            "subcategory":"Construction",
            "type":"Services"
        }
    ],
    "sg:phone":"+1 845 794 7645",
    "sg:postcode":"12701",
    "sg:province":"NY",
    "sg:tags":[
        "excavation",
        "contractor"
    ],
    "wof:name":"Douglas J Muller",
    "wof:placetype":"venue"
},
  "geometry": {"coordinates":[-74.74568600000001,41.682044],"type":"Point"}
}