{
  "type": "Feature",
  "properties": {
    "addr:full":"5090 State Hwy 12 Norwich NY 13815",
    "addr:housenumber":"5090",
    "addr:postcode":"13815",
    "addr:street":"State Hwy 12",
    "iso:country":"US",
    "sg:address":"5090 State Hwy 12",
    "sg:city":"Norwich",
    "sg:classifiers":[
        {
            "category":"Freight",
            "type":"Transportation"
        }
    ],
    "sg:phone":"+1   ",
    "sg:postcode":"13815",
    "sg:province":"NY",
    "sg:tags":[
        "local",
        "trucking"
    ],
    "wof:name":"U-Haul",
    "wof:placetype":"venue"
},
  "geometry": {"coordinates":[-75.528154,42.557282],"type":"Point"}
}