{
  "type": "Feature",
  "properties": {
    "iso:country":"US",
    "sg:address":"70 Pine St",
    "sg:city":"New York",
    "sg:classifiers":[
        {
            "category":"Insurance",
            "subcategory":"Insurance Agent",
            "type":"Services"
        }
    ],
    "sg:phone":"+1 212 770 3333",
    "sg:postcode":"10270",
    "sg:province":"NY",
    "wof:name":"A Freudmann/Aig",
    "wof:placetype":"venue"
},
  "geometry": {"coordinates":[-74.008996,40.706953],"type":"Point"}
}