{
  "type": "Feature",
  "properties": {
    "addr:full":"1525 Route 22 Brewster NY 10509",
    "addr:housenumber":"1525",
    "addr:postcode":"10509",
    "addr:street":"Route 22",
    "iso:country":"US",
    "sg:address":"1525 Route 22",
    "sg:city":"Brewster",
    "sg:classifiers":[
        {
            "category":"Banks & Credit Unions",
            "subcategory":"Bank",
            "type":"Services"
        }
    ],
    "sg:phone":"+1 845 279 8018",
    "sg:postcode":"10509",
    "sg:province":"NY",
    "wof:name":"M&T Bank",
    "wof:placetype":"venue"
},
  "geometry": {"coordinates":[-73.577192,41.421664],"type":"Point"}
}