{
  "type": "Feature",
  "properties": {
    "iso:country":"US",
    "sg:address":"343 E Meadow Ave",
    "sg:city":"East Meadow",
    "sg:classifiers":[
        {
            "category":"Bars & Pubs",
            "type":"Food & Drink"
        }
    ],
    "sg:phone":"+1 516 538 9116",
    "sg:postcode":"11554",
    "sg:province":"NY",
    "sg:tags":[
        "drinking"
    ],
    "wof:name":"Carroll's Bar & Grill",
    "wof:placetype":"venue"
},
  "geometry": {"coordinates":[-73.559725,40.714647],"type":"Point"}
}