{
  "type": "Feature",
  "properties": {
    "iso:country":"US",
    "sg:address":"5309 I D A Park Dr",
    "sg:city":"Lockport",
    "sg:classifiers":[
        {
            "category":"Manufacturing",
            "subcategory":"Tools & Machinery",
            "type":"Manufacturing & Wholesale Goods"
        },
        {
            "category":"Retail",
            "subcategory":"Repair Shop",
            "type":"Services"
        },
        {
            "category":"Retail",
            "subcategory":"Auto Repair",
            "type":"Services"
        }
    ],
    "sg:phone":"+1 716 433 7330",
    "sg:postcode":"14094",
    "sg:province":"NY",
    "sg:tags":[
        "machine",
        "automobile",
        "machinery-rebuild"
    ],
    "sg:website":"http://www.contractsunlimited.com",
    "wof:name":"Contracts Unlimited, Inc.",
    "wof:placetype":"venue"
},
  "geometry": {"coordinates":[-78.745064,43.173975],"type":"Point"}
}