{
  "type": "Feature",
  "properties": {
    "addr:full":"2115 Central Ave Unit 62 Schenectady NY 12304",
    "addr:housenumber":"2115;62",
    "addr:postcode":"12304",
    "addr:street":"Central Ave Unit",
    "iso:country":"US",
    "sg:address":"2115 Central Ave Unit 62",
    "sg:city":"Schenectady",
    "sg:classifiers":[
        {
            "category":"Deli",
            "type":"Food & Drink"
        },
        {
            "category":"Restaurant",
            "type":"Food & Drink"
        }
    ],
    "sg:phone":"+1 518 372 9282",
    "sg:postcode":"12304",
    "sg:province":"NY",
    "sg:tags":[
        "delicatessen"
    ],
    "wof:name":"Cook S Deli",
    "wof:placetype":"venue"
},
  "geometry": {"coordinates":[-73.874588,42.754238],"type":"Point"}
}