{
  "type": "Feature",
  "properties": {
    "addr:full":"11 Broadway New York NY 10004",
    "addr:housenumber":"11",
    "addr:postcode":"10004",
    "addr:street":"Broadway",
    "iso:country":"US",
    "sg:address":"11 Broadway",
    "sg:city":"New York",
    "sg:classifiers":[
        {
            "category":"Restaurant",
            "type":"Food & Drink"
        }
    ],
    "sg:phone":"+1 212 809 4101",
    "sg:postcode":"10004",
    "sg:province":"NY",
    "sg:tags":[
        "deli",
        "cafe"
    ],
    "wof:name":"Cafe Plaza Deli",
    "wof:placetype":"venue"
},
  "geometry": {"coordinates":[-74.013616,40.705453],"type":"Point"}
}