{
  "type": "Feature",
  "properties": {
    "iso:country":"US",
    "sg:address":"3398 Bailey Ave",
    "sg:city":"Buffalo",
    "sg:classifiers":[
        {
            "category":"Restaurant",
            "type":"Food & Drink"
        }
    ],
    "sg:phone":"+1 716 836 6058",
    "sg:postcode":"14215",
    "sg:province":"NY",
    "sg:tags":[
        "vietnamese"
    ],
    "wof:name":"Pho 99 Fast Food",
    "wof:placetype":"venue"
},
  "geometry": {"coordinates":[-78.81367400000001,42.947361],"type":"Point"}
}