{
  "type": "Feature",
  "properties": {
    "addr:full":"115 Parkwood Dr Buffalo NY 14226",
    "addr:housenumber":"115",
    "addr:postcode":"14226",
    "addr:street":"Parkwood Dr",
    "iso:country":"US",
    "sg:address":"115 Parkwood Dr",
    "sg:city":"Buffalo",
    "sg:classifiers":[
        {
            "category":"Shopping",
            "subcategory":"Optical Goods",
            "type":"Retail Goods"
        }
    ],
    "sg:phone":"+1   ",
    "sg:postcode":"14226",
    "sg:province":"NY",
    "wof:name":"Fox & Staniland Inc",
    "wof:placetype":"venue"
},
  "geometry": {"coordinates":[-78.771137,42.964614],"type":"Point"}
}