{
  "type": "Feature",
  "properties": {
    "addr:full":"52 N 11th St Brooklyn NY 11211",
    "addr:housenumber":"52",
    "addr:postcode":"11211",
    "addr:street":"N 11Th St",
    "iso:country":"US",
    "sg:address":"52 N 11th St",
    "sg:city":"Brooklyn",
    "sg:phone":"+1 347 497 6174",
    "sg:postcode":"11211",
    "sg:province":"NY",
    "sg:website":"http://brooklyn.citysearch.com/profile/external/41914278/brooklyn_ny/eva_s_play_pups.html?publisher=yellowpages&reference_id=1&placement=ypwebsitemip",
    "wof:name":"Eva's Play Pups",
    "wof:placetype":"venue"
},
  "geometry": {"coordinates":[-73.959045,40.722326],"type":"Point"}
}