{
  "type": "Feature",
  "properties": {
    "iso:country":"US",
    "sg:address":"41 Ferris St",
    "sg:city":"Rochester",
    "sg:classifiers":[
        {
            "category":"Communications",
            "subcategory":"Film & Video Production",
            "type":"Services"
        }
    ],
    "sg:phone":"+1   ",
    "sg:postcode":"14609",
    "sg:province":"NY",
    "sg:tags":[
        "motion"
    ],
    "wof:name":"Pigeoned Toed Productions",
    "wof:placetype":"venue"
},
  "geometry": {"coordinates":[-77.56113499999999,43.169916],"type":"Point"}
}