{
  "type": "Feature",
  "properties": {
    "addr:full":"441 Lexington Ave Fl 18 New York NY 10017",
    "addr:housenumber":"441;18",
    "addr:postcode":"10017",
    "addr:street":"Lexington Ave Fl",
    "iso:country":"US",
    "sg:address":"441 Lexington Ave Fl 18",
    "sg:city":"New York",
    "sg:classifiers":[
        {
            "category":"Professional",
            "subcategory":"Employment Agencies",
            "type":"Services"
        }
    ],
    "sg:phone":"+1 212 249 8888",
    "sg:postcode":"10017",
    "sg:province":"NY",
    "sg:website":"www.kirklandwest.com",
    "wof:name":"Kirkland West LLC",
    "wof:placetype":"venue"
},
  "geometry": {"coordinates":[-73.974874,40.75279],"type":"Point"}
}