{
  "type": "Feature",
  "properties": {
    "iso:country":"US",
    "sg:address":"251 Dorwin Ave",
    "sg:city":"Syracuse",
    "sg:classifiers":[
        {
            "category":"Recreation",
            "type":"Entertainment"
        }
    ],
    "sg:phone":"+1 315 492 9423",
    "sg:postcode":"13205",
    "sg:province":"NY",
    "sg:tags":[
        "parks"
    ],
    "wof:name":"Kelley Memorial Park",
    "wof:placetype":"venue"
},
  "geometry": {"coordinates":[-76.14856899999999,42.985118],"type":"Point"}
}