{
  "type": "Feature",
  "properties": {
    "iso:country":"US",
    "sg:address":"372 Bloomingdale Rd",
    "sg:city":"Akron",
    "sg:classifiers":[
        {
            "category":"Social Services",
            "type":"Services"
        }
    ],
    "sg:phone":"+1 585 542 5230",
    "sg:postcode":"14001",
    "sg:province":"NY",
    "sg:tags":[
        "organization",
        "welfare"
    ],
    "wof:name":"Tonawanda Indian Community Hse",
    "wof:placetype":"venue"
},
  "geometry": {"coordinates":[-78.49091199999999,43.024631],"type":"Point"}
}