{
  "type": "Feature",
  "properties": {
    "iso:country":"US",
    "sg:address":"295 Main St",
    "sg:city":"Buffalo",
    "sg:classifiers":[
        {
            "category":"Sports & Exercise",
            "subcategory":"Gym",
            "type":"Entertainment"
        }
    ],
    "sg:phone":"+1 716 332 3585",
    "sg:postcode":"14203",
    "sg:province":"NY",
    "sg:tags":[
        "club",
        "health",
        "studio",
        "gymnasium"
    ],
    "wof:name":"Curves",
    "wof:placetype":"venue"
},
  "geometry": {"coordinates":[-78.87536799999999,42.882251],"type":"Point"}
}