{
  "type": "Feature",
  "properties": {
    "addr:full":"110 William St New York NY 10038",
    "addr:housenumber":"110",
    "addr:postcode":"10038",
    "addr:street":"William St",
    "iso:country":"US",
    "sg:address":"110 William St",
    "sg:city":"New York",
    "sg:classifiers":[
        {
            "category":"Banks & Credit Unions",
            "subcategory":"Bank",
            "type":"Services"
        }
    ],
    "sg:phone":"+1 718 251 3300",
    "sg:postcode":"10038",
    "sg:province":"NY",
    "sg:tags":[
        "state",
        "commercial"
    ],
    "wof:name":"Republic National Bank",
    "wof:placetype":"venue"
},
  "geometry": {"coordinates":[-74.006411,40.709464],"type":"Point"}
}