{
  "type": "Feature",
  "properties": {
    "iso:country":"US",
    "sg:address":"21 Union Hill Dr",
    "sg:city":"Spencerport",
    "sg:classifiers":[
        {
            "category":"Insurance",
            "subcategory":"Hazard Insurance",
            "type":"Services"
        }
    ],
    "sg:phone":"+1 585 352 9899",
    "sg:postcode":"14559",
    "sg:province":"NY",
    "sg:tags":[
        "carrier"
    ],
    "wof:name":"Liberty Mutual Insurance Co",
    "wof:placetype":"venue"
},
  "geometry": {"coordinates":[-77.80280399999999,43.181591],"type":"Point"}
}