{
  "type": "Feature",
  "properties": {
    "addr:full":"6301 18th Ave Brooklyn NY 11204",
    "addr:housenumber":"6301",
    "addr:postcode":"11204",
    "addr:street":"18Th Ave",
    "iso:country":"US",
    "sg:address":"6301 18th Ave",
    "sg:city":"Brooklyn",
    "sg:classifiers":[
        {
            "category":"Restaurant",
            "type":"Food & Drink"
        },
        {
            "category":"Food & Beverages",
            "subcategory":"Groceries & Convenience Stores",
            "type":"Retail Goods"
        }
    ],
    "sg:phone":"+1 718 837 8651",
    "sg:postcode":"11204",
    "sg:province":"NY",
    "sg:tags":[
        "deli",
        "delicatessen"
    ],
    "wof:name":"High Grade Deli",
    "wof:placetype":"venue"
},
  "geometry": {"coordinates":[-73.988899,40.620201],"type":"Point"}
}