{
  "type": "Feature",
  "properties": {
    "addr:full":"1082 Grand Ave South Hempstead NY 11550",
    "addr:housenumber":"1082",
    "addr:postcode":"11550",
    "addr:street":"Grand Ave South",
    "iso:country":"US",
    "sg:address":"1082 Grand Ave",
    "sg:city":"South Hempstead",
    "sg:classifiers":[
        {
            "category":"Professional",
            "subcategory":"Accounting & Tax Preparation",
            "type":"Services"
        }
    ],
    "sg:phone":"+1 516 292 3886",
    "sg:postcode":"11550",
    "sg:province":"NY",
    "sg:tags":[
        "bookkeeping",
        "general"
    ],
    "wof:name":"CPA Lee LTD",
    "wof:placetype":"venue"
},
  "geometry": {"coordinates":[-73.61514,40.684482],"type":"Point"}
}