{
  "type": "Feature",
  "properties": {
    "iso:country":"US",
    "sg:address":"644 W 204th St",
    "sg:city":"New York",
    "sg:classifiers":[
        {
            "category":"Real Estate",
            "subcategory":"Real Estate Operator",
            "type":"Services"
        }
    ],
    "sg:phone":"+1 212 567 2211",
    "sg:postcode":"10034",
    "sg:province":"NY",
    "sg:tags":[
        "building",
        "apartment",
        "operates"
    ],
    "wof:name":"204th St Associates Inc",
    "wof:placetype":"venue"
},
  "geometry": {"coordinates":[-73.922946,40.866507],"type":"Point"}
}