{
  "type": "Feature",
  "properties": {
    "addr:full":"194 Stuyvesant Dr Selden NY 11784",
    "addr:housenumber":"194",
    "addr:postcode":"11784",
    "addr:street":"Stuyvesant Dr",
    "iso:country":"US",
    "sg:address":"194 Stuyvesant Dr",
    "sg:city":"Selden",
    "sg:classifiers":[
        {
            "category":"Real Estate",
            "subcategory":"Real Estate Services",
            "type":"Services"
        },
        {
            "category":"Real Estate",
            "subcategory":"Real Estate Agent",
            "type":"Services"
        }
    ],
    "sg:phone":"+1 631 828 5855",
    "sg:postcode":"11784",
    "sg:province":"NY",
    "sg:tags":[
        "buyer",
        "broker"
    ],
    "wof:name":"Romans Associates",
    "wof:placetype":"venue"
},
  "geometry": {"coordinates":[-73.046494,40.890011],"type":"Point"}
}