{
  "type": "Feature",
  "properties": {
    "addr:full":"8522 3rd Ave Brooklyn NY 11209",
    "addr:housenumber":"8522",
    "addr:postcode":"11209",
    "addr:street":"3Rd Ave",
    "iso:country":"US",
    "sg:address":"8522 3rd Ave",
    "sg:city":"Brooklyn",
    "sg:classifiers":[
        {
            "category":"Banks & Credit Unions",
            "subcategory":"Bank",
            "type":"Services"
        }
    ],
    "sg:phone":"+1 718 238 1793",
    "sg:postcode":"11209",
    "sg:province":"NY",
    "sg:website":"www.ridgewoodbank.com",
    "wof:name":"Ridgewood Savings Bank",
    "wof:placetype":"venue"
},
  "geometry": {"coordinates":[-74.095619,40.624185],"type":"Point"}
}