{
  "type": "Feature",
  "properties": {
    "iso:country":"US",
    "sg:address":"4471 Steelway Blvd S",
    "sg:city":"Liverpool",
    "sg:classifiers":[
        {
            "category":"Manufacturing",
            "subcategory":"Paper Products",
            "type":"Manufacturing & Wholesale Goods"
        }
    ],
    "sg:phone":"+1   ",
    "sg:postcode":"13090",
    "sg:province":"NY",
    "sg:tags":[
        "box",
        "packaging",
        "fiber",
        "mfg"
    ],
    "wof:name":"Packaging Corporation America",
    "wof:placetype":"venue"
},
  "geometry": {"coordinates":[-76.198196,43.127204],"type":"Point"}
}