{
  "type": "Feature",
  "properties": {
    "addr:full":"11443 Farmers Boulevard Saint Albans NY 11412",
    "addr:housenumber":"11443",
    "addr:postcode":"11412",
    "addr:street":"Farmers Boulevard",
    "iso:country":"US",
    "sg:address":"11443 Farmers Boulevard",
    "sg:city":"Saint Albans",
    "sg:classifiers":[
        {
            "category":"Food & Beverages",
            "subcategory":"Groceries & Convenience Stores",
            "type":"Retail Goods"
        }
    ],
    "sg:phone":"+1 718 217 1364",
    "sg:postcode":"11412",
    "sg:province":"NY",
    "wof:name":"J J Food Center",
    "wof:placetype":"venue"
},
  "geometry": {"coordinates":[-73.761777,40.696745],"type":"Point"}
}