{
  "type": "Feature",
  "properties": {
    "addr:full":"344 S 5th Ave Mt Vernon NY 10550",
    "addr:housenumber":"344",
    "addr:postcode":"10550",
    "addr:street":"S 5Th Ave",
    "iso:country":"US",
    "sg:address":"344 S 5th Ave",
    "sg:city":"Mt Vernon",
    "sg:classifiers":[
        {
            "category":"Organizations",
            "subcategory":"Religious Organization",
            "type":"Services"
        }
    ],
    "sg:phone":"+1 914 668 7292",
    "sg:postcode":"10550",
    "sg:province":"NY",
    "sg:tags":[
        "clergy"
    ],
    "wof:name":"Leon Dixon",
    "wof:placetype":"venue"
},
  "geometry": {"coordinates":[-73.834728,40.902809],"type":"Point"}
}