{
  "type": "Feature",
  "properties": {
    "addr:full":"5750 Sunrise Hwy Sayville NY 11782",
    "addr:housenumber":"5750",
    "addr:postcode":"11782",
    "addr:street":"Sunrise Hwy",
    "iso:country":"US",
    "sg:address":"5750 Sunrise Hwy",
    "sg:city":"Sayville",
    "sg:classifiers":[
        {
            "category":"Professional",
            "type":"Services"
        }
    ],
    "sg:phone":"+1 631 589 4605",
    "sg:postcode":"11782",
    "sg:province":"NY",
    "sg:tags":[
        "establishment"
    ],
    "wof:name":"New Best Silver Inc",
    "wof:placetype":"venue"
},
  "geometry": {"coordinates":[-73.071539,40.767647],"type":"Point"}
}