{
  "type": "Feature",
  "properties": {
    "addr:full":"10 E 52 St New York NY 10022",
    "addr:housenumber":"10;52",
    "addr:postcode":"10022",
    "addr:street":"E;St",
    "iso:country":"US",
    "sg:address":"10 E 52 St",
    "sg:city":"New York",
    "sg:classifiers":[
        {
            "category":"Professional",
            "subcategory":"Lawyer & Legal Services",
            "type":"Services"
        }
    ],
    "sg:phone":"+1 212 421 5475",
    "sg:postcode":"10022",
    "sg:province":"NY",
    "sg:tags":[
        "attorney"
    ],
    "wof:name":"Stuart M Nierenberg",
    "wof:placetype":"venue"
},
  "geometry": {"coordinates":[-73.975122,40.759272],"type":"Point"}
}