{
  "type": "Feature",
  "properties": {
    "addr:full":"13 Hudson St New York NY 10013",
    "addr:housenumber":"13",
    "addr:postcode":"10013",
    "addr:street":"Hudson St",
    "iso:country":"US",
    "sg:address":"13 Hudson St",
    "sg:city":"New York",
    "sg:classifiers":[
        {
            "category":"Farming",
            "subcategory":"Farm",
            "type":"Manufacturing & Wholesale Goods"
        }
    ],
    "sg:phone":"+1 212 941 7578",
    "sg:postcode":"10013",
    "sg:province":"NY",
    "sg:tags":[
        "crop",
        "general"
    ],
    "wof:name":"Tribeca Village Farm Inc",
    "wof:placetype":"venue"
},
  "geometry": {"coordinates":[-74.00911499999999,40.716919],"type":"Point"}
}