{
  "type": "Feature",
  "properties": {
    "iso:country":"US",
    "sg:address":"150 Western Ave",
    "sg:city":"Altamont",
    "sg:classifiers":[
        {
            "category":"Insurance",
            "subcategory":"Hazard Insurance",
            "type":"Services"
        }
    ],
    "sg:phone":"+1 518 861 5552",
    "sg:postcode":"12009",
    "sg:province":"NY",
    "sg:tags":[
        "group"
    ],
    "wof:name":"Residential Opportunities",
    "wof:placetype":"venue"
},
  "geometry": {"coordinates":[-74.032104,42.705984],"type":"Point"}
}