{
  "type": "Feature",
  "properties": {
    "iso:country":"US",
    "sg:address":"100 E 50th Street",
    "sg:city":"New York",
    "sg:classifiers":[
        {
            "category":"Health Services",
            "subcategory":"Doctor",
            "type":"Services"
        }
    ],
    "sg:phone":"+1 212 327 0444",
    "sg:postcode":"10022",
    "sg:province":"NY",
    "wof:name":"Alan M Kisner Facs",
    "wof:placetype":"venue"
},
  "geometry": {"coordinates":[-73.97386299999999,40.75712],"type":"Point"}
}