{
  "type": "Feature",
  "properties": {
    "addr:full":"781 8 Ave New York NY 10036",
    "addr:housenumber":"781",
    "addr:postcode":"10036",
    "addr:street":"8 Ave",
    "iso:country":"US",
    "sg:address":"781 8 Ave",
    "sg:city":"New York",
    "sg:classifiers":[
        {
            "category":"Wholesale",
            "subcategory":"Electrical",
            "type":"Manufacturing & Wholesale Goods"
        }
    ],
    "sg:phone":"+1 212 586 3939",
    "sg:postcode":"10036",
    "sg:province":"NY",
    "sg:tags":[
        "lighting",
        "fixture"
    ],
    "wof:name":"City Knickerbocker Inc",
    "wof:placetype":"venue"
},
  "geometry": {"coordinates":[-73.989791,40.757234],"type":"Point"}
}