{
  "type": "Feature",
  "properties": {
    "addr:full":"5 Pell Street New York NY 10013",
    "addr:housenumber":"5",
    "addr:postcode":"10013",
    "addr:street":"Pell Street",
    "iso:country":"US",
    "sg:address":"5 Pell Street",
    "sg:city":"New York",
    "sg:classifiers":[
        {
            "category":"Personal",
            "subcategory":"Beauty Salon",
            "type":"Services"
        },
        {
            "category":"Personal",
            "subcategory":"Barber",
            "type":"Services"
        }
    ],
    "sg:phone":"+1 212 267 4849",
    "sg:postcode":"10013",
    "sg:province":"NY",
    "sg:tags":[
        "hair"
    ],
    "wof:name":"Chung Wah Barber Shop",
    "wof:placetype":"venue"
},
  "geometry": {"coordinates":[-73.99746,40.714712],"type":"Point"}
}