{
  "type": "Feature",
  "properties": {
    "addr:full":"2 Montgomery Pl Jericho NY 11753",
    "addr:housenumber":"2",
    "addr:postcode":"11753",
    "addr:street":"Montgomery Pl",
    "iso:country":"US",
    "sg:address":"2 Montgomery Pl",
    "sg:city":"Jericho",
    "sg:classifiers":[
        {
            "category":"Home & Garden",
            "subcategory":"Furniture",
            "type":"Retail Goods"
        }
    ],
    "sg:phone":"+1   ",
    "sg:postcode":"11753",
    "sg:province":"NY",
    "wof:name":"Contemporary Dinette Inc",
    "wof:placetype":"venue"
},
  "geometry": {"coordinates":[-73.54754200000001,40.778805],"type":"Point"}
}