{
  "type": "Feature",
  "properties": {
    "addr:full":"673 Columbia Turnpike East Greenbush NY 12061",
    "addr:housenumber":"673",
    "addr:postcode":"12061",
    "addr:street":"Columbia Turnpike",
    "iso:country":"US",
    "sg:address":"673 Columbia Turnpike",
    "sg:city":"East Greenbush",
    "sg:classifiers":[
        {
            "category":"Professional",
            "subcategory":"Computer Services",
            "type":"Services"
        }
    ],
    "sg:phone":"+1 518 727 6843",
    "sg:postcode":"12061",
    "sg:province":"NY",
    "sg:tags":[
        "you-are-here",
        "map-and-directory",
        "online-map-and-directory",
        "interactive-map-and-directory",
        "event-directory",
        "event-marketing",
        "event-management",
        "exhibitor-marketing",
        "interactive-trade-show-map",
        "online-trade-show-map",
        "add-value",
        "increase-revenue",
        "enhance-expe"
    ],
    "sg:website":"http://www.marketart.com/",
    "wof:name":"MarketArt",
    "wof:placetype":"venue"
},
  "geometry": {"coordinates":[-73.700761,42.59003],"type":"Point"}
}