{
  "type": "Feature",
  "properties": {
    "addr:full":"10 Plaza St E Brooklyn NY 11238",
    "addr:housenumber":"10",
    "addr:postcode":"11238",
    "addr:street":"Plaza St E",
    "iso:country":"US",
    "sg:address":"10 Plaza St E",
    "sg:city":"Brooklyn",
    "sg:classifiers":[
        {
            "category":"Professional",
            "subcategory":"Lawyer & Legal Services",
            "type":"Services"
        }
    ],
    "sg:phone":"+1 718 857 8884",
    "sg:postcode":"11238",
    "sg:province":"NY",
    "wof:name":"Joel M Gluck Esquire",
    "wof:placetype":"venue"
},
  "geometry": {"coordinates":[-73.97030700000001,40.675591],"type":"Point"}
}