{
  "type": "Feature",
  "properties": {
    "iso:country":"US",
    "sg:address":"106 Main St",
    "sg:city":"Batavia",
    "sg:classifiers":[
        {
            "category":"Food & Beverages",
            "subcategory":"Bakery",
            "type":"Retail Goods"
        }
    ],
    "sg:phone":"+1 585 343 3954",
    "sg:postcode":"14020",
    "sg:province":"NY",
    "sg:tags":[
        "cookie",
        "cracker"
    ],
    "wof:name":"Cookies & Milk",
    "wof:placetype":"venue"
},
  "geometry": {"coordinates":[-78.183142,42.997599],"type":"Point"}
}