{
  "type": "Feature",
  "properties": {
    "iso:country":"US",
    "sg:address":"323 Beach 74th St",
    "sg:city":"Arverne",
    "sg:classifiers":[
        {
            "category":"Insurance",
            "subcategory":"Hazard Insurance",
            "type":"Services"
        }
    ],
    "sg:phone":"+1 212 680 1515",
    "sg:postcode":"11692",
    "sg:province":"NY",
    "sg:tags":[
        "commercial",
        "business"
    ],
    "wof:name":"Friedman Levine Inc",
    "wof:placetype":"venue"
},
  "geometry": {"coordinates":[-73.80228700000001,40.591165],"type":"Point"}
}