{
  "type": "Feature",
  "properties": {
    "addr:full":"510 Oakwood Ave East Aurora NY 14052",
    "addr:housenumber":"510",
    "addr:postcode":"14052",
    "addr:street":"Oakwood Ave",
    "iso:country":"US",
    "sg:address":"510 Oakwood Ave",
    "sg:city":"East Aurora",
    "sg:classifiers":[
        {
            "category":"Education",
            "subcategory":"School",
            "type":"Public Place"
        }
    ],
    "sg:phone":"+1 716 652 5855",
    "sg:postcode":"14052",
    "sg:province":"NY",
    "sg:tags":[
        "organization",
        "religious"
    ],
    "wof:name":"Immaculate Conception School",
    "wof:placetype":"venue"
},
  "geometry": {"coordinates":[-78.61487200000001,42.765722],"type":"Point"}
}