{
  "type": "Feature",
  "properties": {
    "addr:full":"159 Jervis Ave Copiague NY 11726",
    "addr:housenumber":"159",
    "addr:postcode":"11726",
    "addr:street":"Jervis Ave",
    "iso:country":"US",
    "sg:address":"159 Jervis Ave",
    "sg:city":"Copiague",
    "sg:classifiers":[
        {
            "category":"Building & Trades",
            "subcategory":"Construction",
            "type":"Services"
        }
    ],
    "sg:phone":"+1 631 842 2916",
    "sg:postcode":"11726",
    "sg:province":"NY",
    "sg:tags":[
        "carpentry",
        "contractor"
    ],
    "wof:name":"Clinton Home Design",
    "wof:placetype":"venue"
},
  "geometry": {"coordinates":[-73.395387,40.664869],"type":"Point"}
}