{
  "type": "Feature",
  "properties": {
    "iso:country":"US",
    "sg:address":"120 E Merrick Rd",
    "sg:city":"Freeport",
    "sg:classifiers":[
        {
            "category":"Retail",
            "subcategory":"Auto Repair",
            "type":"Services"
        }
    ],
    "sg:phone":"+1 516 223 9040",
    "sg:postcode":"11520",
    "sg:province":"NY",
    "sg:tags":[
        "body",
        "repairing",
        "painting",
        "automobile"
    ],
    "wof:name":"Auto Tech Collision 2",
    "wof:placetype":"venue"
},
  "geometry": {"coordinates":[-73.57519000000001,40.654603],"type":"Point"}
}