{
  "type": "Feature",
  "properties": {
    "iso:country":"US",
    "sg:address":"4300 Hylan Blvd # 2",
    "sg:city":"Staten Island",
    "sg:classifiers":[
        {
            "category":"Education",
            "subcategory":"Special Training",
            "type":"Public Place"
        }
    ],
    "sg:phone":"+1 718 984 9022",
    "sg:postcode":"10312",
    "sg:province":"NY",
    "sg:tags":[
        "school",
        "specialty"
    ],
    "sg:website":"www.chipny.com",
    "wof:name":"Children's Home Intervention Program",
    "wof:placetype":"venue"
},
  "geometry": {"coordinates":[-74.152507,40.535483],"type":"Point"}
}