{
  "type": "Feature",
  "properties": {
    "addr:full":"309 W Park Ave Long Beach NY 11561",
    "addr:housenumber":"309",
    "addr:postcode":"11561",
    "addr:street":"W Park Ave",
    "iso:country":"US",
    "sg:address":"309 W Park Ave",
    "sg:city":"Long Beach",
    "sg:classifiers":[
        {
            "category":"Health Services",
            "subcategory":"Doctor",
            "type":"Services"
        }
    ],
    "sg:phone":"+1 516 889 7733",
    "sg:postcode":"11561",
    "sg:province":"NY",
    "sg:tags":[
        "throat",
        "surgeon",
        "ear",
        "cosmetic",
        "nose"
    ],
    "wof:name":"Youngerman Jay S PC",
    "wof:placetype":"venue"
},
  "geometry": {"coordinates":[-73.672997,40.588299],"type":"Point"}
}