{
  "type": "Feature",
  "properties": {
    "iso:country":"US",
    "sg:address":"141 S 1st St",
    "sg:city":"Fulton",
    "sg:classifiers":[
        {
            "category":"Organizations",
            "subcategory":"Professional Association",
            "type":"Services"
        }
    ],
    "sg:phone":"+1 315 592 4581",
    "sg:postcode":"13069",
    "sg:province":"NY",
    "wof:name":"Fulton PBA",
    "wof:placetype":"venue"
},
  "geometry": {"coordinates":[-76.41626599999999,43.320847],"type":"Point"}
}