{
  "type": "Feature",
  "properties": {
    "addr:full":"11 Chapel St Elba NY 14058",
    "addr:housenumber":"11",
    "addr:postcode":"14058",
    "addr:street":"Chapel St",
    "iso:country":"US",
    "sg:address":"11 Chapel St",
    "sg:city":"Elba",
    "sg:classifiers":[
        {
            "category":"Restaurant",
            "type":"Food & Drink"
        }
    ],
    "sg:phone":"+1 585 757 2432",
    "sg:postcode":"14058",
    "sg:province":"NY",
    "sg:tags":[
        "caterer"
    ],
    "wof:name":"Penna's Catering",
    "wof:placetype":"venue"
},
  "geometry": {"coordinates":[-78.17997699999999,43.082443],"type":"Point"}
}