{
  "type": "Feature",
  "properties": {
    "iso:country":"US",
    "sg:address":"1258 Bay St",
    "sg:city":"Staten Island",
    "sg:classifiers":[
        {
            "category":"Bars & Pubs",
            "type":"Food & Drink"
        }
    ],
    "sg:phone":"+1   ",
    "sg:postcode":"10305",
    "sg:province":"NY",
    "sg:tags":[
        "drinking"
    ],
    "wof:name":"Rosebank Tavern",
    "wof:placetype":"venue"
},
  "geometry": {"coordinates":[-74.065315,40.612981],"type":"Point"}
}