{
  "type": "Feature",
  "properties": {
    "addr:full":"265 Union Ave Brooklyn NY 11211",
    "addr:housenumber":"265",
    "addr:postcode":"11211",
    "addr:street":"Union Ave",
    "iso:country":"US",
    "sg:address":"265 Union Ave",
    "sg:city":"Brooklyn",
    "sg:classifiers":[
        {
            "category":"Restaurant",
            "type":"Food & Drink"
        }
    ],
    "sg:phone":"+1 718 387 1361",
    "sg:postcode":"11211",
    "sg:province":"NY",
    "wof:name":"SUNNY Gardens",
    "wof:placetype":"venue"
},
  "geometry": {"coordinates":[-73.95053,40.707391],"type":"Point"}
}