{
  "type": "Feature",
  "properties": {
    "addr:full":"101 Crossways Park Dr W Woodbury NY 11797",
    "addr:housenumber":"101",
    "addr:postcode":"11797",
    "addr:street":"Crossways Park Dr W",
    "iso:country":"US",
    "sg:address":"101 Crossways Park Dr W",
    "sg:city":"Woodbury",
    "sg:classifiers":[
        {
            "category":"Professional",
            "type":"Services"
        }
    ],
    "sg:phone":"+1 516 576 0404",
    "sg:postcode":"11797",
    "sg:province":"NY",
    "sg:website":"www.cardworks.com",
    "wof:name":"CMS",
    "wof:placetype":"venue"
},
  "geometry": {"coordinates":[-73.487129,40.810294],"type":"Point"}
}