{
  "type": "Feature",
  "properties": {
    "addr:full":"145 Library Ln Mamaroneck NY 10543",
    "addr:housenumber":"145",
    "addr:postcode":"10543",
    "addr:street":"Library Ln",
    "iso:country":"US",
    "sg:address":"145 Library Ln",
    "sg:city":"Mamaroneck",
    "sg:classifiers":[
        {
            "category":"Professional",
            "subcategory":"Management & Consulting",
            "type":"Services"
        }
    ],
    "sg:phone":"+1   ",
    "sg:postcode":"10543",
    "sg:province":"NY",
    "sg:tags":[
        "retail",
        "direct",
        "sales"
    ],
    "wof:name":"Collage Balloons",
    "wof:placetype":"venue"
},
  "geometry": {"coordinates":[-73.73353899999999,40.948504],"type":"Point"}
}