{
  "type": "Feature",
  "properties": {
    "iso:country":"US",
    "sg:address":"2536 Frederick Douglass Blvd at 135th St",
    "sg:city":"New York",
    "sg:classifiers":[
        {
            "category":"Food & Beverages",
            "subcategory":"Bakery",
            "type":"Retail Goods"
        }
    ],
    "sg:postcode":"10027",
    "sg:province":"NY",
    "sg:tags":[
        "sandwich"
    ],
    "wof:name":"Food Inc.",
    "wof:placetype":"venue"
},
  "geometry": {"coordinates":[-73.94651399999999,40.816538],"type":"Point"}
}