{
  "type": "Feature",
  "properties": {
    "addr:full":"406 Buckingham Rd Cedarhurst NY 11516",
    "addr:housenumber":"406",
    "addr:postcode":"11516",
    "addr:street":"Buckingham Rd",
    "iso:country":"US",
    "sg:address":"406 Buckingham Rd",
    "sg:city":"Cedarhurst",
    "sg:classifiers":[
        {
            "category":"Banks & Credit Unions",
            "subcategory":"Investment Brokerage",
            "type":"Services"
        }
    ],
    "sg:phone":"+1 516 569 2211",
    "sg:postcode":"11516",
    "sg:province":"NY",
    "sg:tags":[
        "investing"
    ],
    "wof:name":"Shac Inc",
    "wof:placetype":"venue"
},
  "geometry": {"coordinates":[-73.73255399999999,40.626309],"type":"Point"}
}