{
  "type": "Feature",
  "properties": {
    "iso:country":"US",
    "sg:address":"150 E. 52nd Street",
    "sg:city":"New York",
    "sg:classifiers":[
        {
            "category":"Restaurant",
            "type":"Food & Drink"
        }
    ],
    "sg:phone":"+1 212 755 9754",
    "sg:postcode":"10001",
    "sg:province":"NY",
    "sg:tags":[
        "mexican"
    ],
    "wof:name":"Chipotle",
    "wof:placetype":"venue"
},
  "geometry": {"coordinates":[-73.971199,40.7575],"type":"Point"}
}