{
  "type": "Feature",
  "properties": {
    "iso:country":"US",
    "sg:address":"1972 Henry St",
    "sg:city":"North Bellmore",
    "sg:classifiers":[
        {
            "category":"Manufacturing",
            "subcategory":"Petroleum Products",
            "type":"Manufacturing & Wholesale Goods"
        }
    ],
    "sg:phone":"+1 516 221 7842",
    "sg:postcode":"11710",
    "sg:province":"NY",
    "wof:name":"Global Petroleum",
    "wof:placetype":"venue"
},
  "geometry": {"coordinates":[-73.522024,40.675801],"type":"Point"}
}