{
  "type": "Feature",
  "properties": {
    "addr:full":"2540 Davidson Ave Bronx NY 10468",
    "addr:housenumber":"2540",
    "addr:postcode":"10468",
    "addr:street":"Davidson Ave",
    "iso:country":"US",
    "sg:address":"2540 Davidson Ave",
    "sg:city":"Bronx",
    "sg:classifiers":[
        {
            "category":"Personal",
            "subcategory":"Beauty Salon",
            "type":"Services"
        }
    ],
    "sg:phone":"+1   ",
    "sg:postcode":"10468",
    "sg:province":"NY",
    "sg:tags":[
        "shop"
    ],
    "wof:name":"Dungs Nail Care",
    "wof:placetype":"venue"
},
  "geometry": {"coordinates":[-73.90021,40.865136],"type":"Point"}
}