{
  "type": "Feature",
  "properties": {
    "addr:full":"1313 Viele Ave Bronx NY 10474",
    "addr:housenumber":"1313",
    "addr:postcode":"10474",
    "addr:street":"Viele Ave",
    "iso:country":"US",
    "sg:address":"1313 Viele Ave",
    "sg:city":"Bronx",
    "sg:classifiers":[
        {
            "category":"Autos & Motor Vehicles",
            "subcategory":"Auto Supplies",
            "type":"Retail Goods"
        }
    ],
    "sg:phone":"+1 718 328 1326",
    "sg:postcode":"10474",
    "sg:province":"NY",
    "sg:tags":[
        "automobile",
        "parts"
    ],
    "wof:name":"A & J Auto Parts & Cars Inc",
    "wof:placetype":"venue"
},
  "geometry": {"coordinates":[-73.88403700000001,40.80695],"type":"Point"}
}