{
  "type": "Feature",
  "properties": {
    "addr:full":"500 Western Hwy Blauvelt NY 10913",
    "addr:housenumber":"500",
    "addr:postcode":"10913",
    "addr:street":"Western Hwy",
    "iso:country":"US",
    "sg:address":"500 Western Hwy",
    "sg:city":"Blauvelt",
    "sg:classifiers":[
        {
            "category":"Education",
            "subcategory":"University",
            "type":"Public Place"
        }
    ],
    "sg:phone":"+1 845 359 2964",
    "sg:postcode":"10913",
    "sg:province":"NY",
    "sg:tags":[
        "college"
    ],
    "wof:name":"Dominican College",
    "wof:placetype":"venue"
},
  "geometry": {"coordinates":[-73.955468,41.592034],"type":"Point"}
}