{
  "type": "Feature",
  "properties": {
    "addr:full":"15 Duer Ln Staten Island NY 10301",
    "addr:housenumber":"15",
    "addr:postcode":"10301",
    "addr:street":"Duer Ln",
    "iso:country":"US",
    "sg:address":"15 Duer Ln",
    "sg:city":"Staten Island",
    "sg:classifiers":[
        {
            "category":"Professional",
            "type":"Services"
        }
    ],
    "sg:phone":"+1 718 720 6815",
    "sg:postcode":"10301",
    "sg:province":"NY",
    "sg:tags":[
        "establishment"
    ],
    "wof:name":"Eccleston Associates Inc",
    "wof:placetype":"venue"
},
  "geometry": {"coordinates":[-74.090003,40.632051],"type":"Point"}
}