{
  "type": "Feature",
  "properties": {
    "addr:full":"119 E 233 New York NY 10001",
    "addr:housenumber":"119;233",
    "addr:postcode":"10001",
    "addr:street":"E",
    "iso:country":"US",
    "sg:address":"119 E 233",
    "sg:city":"New York",
    "sg:classifiers":[
        {
            "category":"Building & Trades",
            "subcategory":"Construction",
            "type":"Services"
        }
    ],
    "sg:phone":"+1 347 275 3775",
    "sg:postcode":"10001",
    "sg:province":"NY",
    "sg:tags":[
        "contractor"
    ],
    "wof:name":"Property Management",
    "wof:placetype":"venue"
},
  "geometry": {"coordinates":[-73.937157,40.799291],"type":"Point"}
}