{
  "type": "Feature",
  "properties": {
    "iso:country":"US",
    "sg:address":"6312 Hardwood Ln",
    "sg:city":"Cicero",
    "sg:classifiers":[
        {
            "category":"Real Estate",
            "subcategory":"Real Estate Operator",
            "type":"Services"
        }
    ],
    "sg:phone":"+1 315 699 3719",
    "sg:postcode":"13039",
    "sg:province":"NY",
    "sg:tags":[
        "apartment"
    ],
    "wof:name":"Liverpool Apartments",
    "wof:placetype":"venue"
},
  "geometry": {"coordinates":[-76.081659,43.186934],"type":"Point"}
}