{
  "type": "Feature",
  "properties": {
    "iso:country":"US",
    "sg:address":"15 Doyers Street",
    "sg:city":"New York",
    "sg:classifiers":[
        {
            "category":"Professional",
            "subcategory":"Employment Agencies",
            "type":"Services"
        }
    ],
    "sg:phone":"+1 212 571 8888",
    "sg:postcode":"10013",
    "sg:province":"NY",
    "wof:name":"Tina Employment Agency",
    "wof:placetype":"venue"
},
  "geometry": {"coordinates":[-73.99784699999999,40.714056],"type":"Point"}
}