{
  "type": "Feature",
  "properties": {
    "addr:full":"2483 Roman Ave Marcellus NY 13108",
    "addr:housenumber":"2483",
    "addr:postcode":"13108",
    "addr:street":"Roman Ave",
    "iso:country":"US",
    "sg:address":"2483 Roman Ave",
    "sg:city":"Marcellus",
    "sg:classifiers":[
        {
            "category":"Manufacturing",
            "subcategory":"Tools & Machinery",
            "type":"Manufacturing & Wholesale Goods"
        }
    ],
    "sg:phone":"+1 315 673 1343",
    "sg:postcode":"13108",
    "sg:province":"NY",
    "sg:tags":[
        "machine",
        "shop"
    ],
    "wof:name":"Sharlay Machine & Design",
    "wof:placetype":"venue"
},
  "geometry": {"coordinates":[-76.33735799999999,42.996603],"type":"Point"}
}