{
  "type": "Feature",
  "properties": {
    "addr:full":"5904 55th Drive Flushing NY 11378",
    "addr:housenumber":"5904",
    "addr:postcode":"11378",
    "addr:street":"55Th Drive",
    "iso:country":"US",
    "sg:address":"5904 55th Drive",
    "sg:city":"Flushing",
    "sg:classifiers":[
        {
            "category":"Restaurant",
            "type":"Food & Drink"
        }
    ],
    "sg:phone":"+1 718 326 4096",
    "sg:postcode":"11378",
    "sg:province":"NY",
    "wof:name":"Maurice Ave Deli",
    "wof:placetype":"venue"
},
  "geometry": {"coordinates":[-73.90854,40.725939],"type":"Point"}
}