{
  "type": "Feature",
  "properties": {
    "addr:full":"139 W 116th St New York NY 10026",
    "addr:housenumber":"139",
    "addr:postcode":"10026",
    "addr:street":"W 116Th St",
    "iso:country":"US",
    "sg:address":"139 W 116th St",
    "sg:city":"New York",
    "sg:classifiers":[
        {
            "category":"Home & Garden",
            "subcategory":"Building Materials",
            "type":"Retail Goods"
        }
    ],
    "sg:phone":"+1   ",
    "sg:postcode":"10026",
    "sg:province":"NY",
    "wof:name":"Ricks Store Front & Glass",
    "wof:placetype":"venue"
},
  "geometry": {"coordinates":[-73.95165299999999,40.802823],"type":"Point"}
}