{
  "type": "Feature",
  "properties": {
    "iso:country":"US",
    "sg:address":"2167 3rd Ave",
    "sg:city":"New York",
    "sg:classifiers":[
        {
            "category":"Health Services",
            "subcategory":"Doctor",
            "type":"Services"
        }
    ],
    "sg:phone":"+1 212 831 8940",
    "sg:postcode":"10035",
    "sg:province":"NY",
    "wof:name":"Pozner Regina MD",
    "wof:placetype":"venue"
},
  "geometry": {"coordinates":[-73.939003,40.7995],"type":"Point"}
}