{
  "type": "Feature",
  "properties": {
    "addr:full":"244 N Main St New City NY 10956",
    "addr:housenumber":"244",
    "addr:postcode":"10956",
    "addr:street":"N Main St",
    "iso:country":"US",
    "sg:address":"244 N Main St",
    "sg:city":"New City",
    "sg:classifiers":[
        {
            "category":"Banks & Credit Unions",
            "subcategory":"Investment Brokerage",
            "type":"Services"
        }
    ],
    "sg:phone":"+1 845 634 3939",
    "sg:postcode":"10956",
    "sg:province":"NY",
    "sg:tags":[
        "stock",
        "bond"
    ],
    "sg:website":"www.berklpl.com",
    "wof:name":"Linsco Private Ledger",
    "wof:placetype":"venue"
},
  "geometry": {"coordinates":[-73.988479,41.157845],"type":"Point"}
}