{
  "type": "Feature",
  "properties": {
    "iso:country":"US",
    "sg:address":"218 Ronkonkoma Ave",
    "sg:city":"Ronkonkoma",
    "sg:classifiers":[
        {
            "category":"Utilities",
            "subcategory":"Mobile Phone",
            "type":"Services"
        }
    ],
    "sg:phone":"+1 631 580 5006",
    "sg:postcode":"11779",
    "sg:province":"NY",
    "sg:tags":[
        "telephone",
        "cellular"
    ],
    "wof:name":"Wireless Choice",
    "wof:placetype":"venue"
},
  "geometry": {"coordinates":[-73.113134,40.820291],"type":"Point"}
}