{
  "type": "Feature",
  "properties": {
    "iso:country":"US",
    "sg:address":"5 Fox Hill Pl",
    "sg:city":"Selden",
    "sg:classifiers":[
        {
            "category":"Freight",
            "type":"Transportation"
        }
    ],
    "sg:phone":"+1   ",
    "sg:postcode":"11784",
    "sg:province":"NY",
    "sg:tags":[
        "operator",
        "local",
        "trucking"
    ],
    "wof:name":"Ndp Trucking Inc",
    "wof:placetype":"venue"
},
  "geometry": {"coordinates":[-73.030737,40.849487],"type":"Point"}
}