{
  "type": "Feature",
  "properties": {
    "addr:full":"225 Fuller Rd Jefferson NY 12010",
    "addr:housenumber":"225",
    "addr:postcode":"12010",
    "addr:street":"Fuller Rd",
    "iso:country":"US",
    "sg:address":"225 Fuller Rd",
    "sg:city":"Jefferson",
    "sg:classifiers":[
        {
            "category":"Building & Trades",
            "subcategory":"Construction",
            "type":"Services"
        }
    ],
    "sg:phone":"+1 607 652 7826",
    "sg:postcode":"12010",
    "sg:province":"NY",
    "sg:tags":[
        "water",
        "well",
        "drilling"
    ],
    "wof:name":"Van Loan Drilling",
    "wof:placetype":"venue"
},
  "geometry": {"coordinates":[-74.214625,42.902751],"type":"Point"}
}