{
  "type": "Feature",
  "properties": {
    "iso:country":"US",
    "sg:address":"22 W 15 St",
    "sg:city":"New York",
    "sg:classifiers":[
        {
            "category":"Professional",
            "subcategory":"Accounting & Tax Preparation",
            "type":"Services"
        }
    ],
    "sg:phone":"+1   ",
    "sg:postcode":"10011",
    "sg:province":"NY",
    "wof:name":"Bruce I Panock",
    "wof:placetype":"venue"
},
  "geometry": {"coordinates":[-73.99586499999999,40.737696],"type":"Point"}
}