{
  "type": "Feature",
  "properties": {
    "addr:full":"19153 US Hwy 11 Watertown NY 13601",
    "addr:postcode":"19153;13601",
    "addr:street":"Us Hwy 11",
    "iso:country":"US",
    "sg:address":"19153 US Hwy 11",
    "sg:city":"Watertown",
    "sg:classifiers":[
        {
            "category":"Retail",
            "subcategory":"Auto Rental",
            "type":"Services"
        }
    ],
    "sg:phone":"+1 315 788 8045",
    "sg:postcode":"13601",
    "sg:province":"NY",
    "sg:tags":[
        "renting",
        "truck",
        "leasing"
    ],
    "wof:name":"U-Haul Co",
    "wof:placetype":"venue"
},
  "geometry": {"coordinates":[-75.920761,43.940231],"type":"Point"}
}