{
  "type": "Feature",
  "properties": {
    "addr:full":"444 E 86 St New York NY 10028",
    "addr:housenumber":"444;86",
    "addr:postcode":"10028",
    "addr:street":"E;St",
    "iso:country":"US",
    "sg:address":"444 E 86 St",
    "sg:city":"New York",
    "sg:classifiers":[
        {
            "category":"Shopping",
            "type":"Retail Goods"
        }
    ],
    "sg:phone":"+1   ",
    "sg:postcode":"10028",
    "sg:province":"NY",
    "sg:tags":[
        "art",
        "dealer"
    ],
    "wof:name":"Lewis Lehr Inc",
    "wof:placetype":"venue"
},
  "geometry": {"coordinates":[-73.94778599999999,40.776211],"type":"Point"}
}