{
  "type": "Feature",
  "properties": {
    "iso:country":"US",
    "sg:address":"Temple Sholom 2075 E 68th St",
    "sg:city":"Brooklyn",
    "sg:classifiers":[
        {
            "category":"Professional",
            "type":"Services"
        },
        {
            "category":"Restaurant",
            "type":"Food & Drink"
        }
    ],
    "sg:phone":"+1 718 763 0300",
    "sg:postcode":"11234",
    "sg:province":"NY",
    "sg:tags":[
        "kosher",
        "caterer"
    ],
    "sg:website":"www.edencaterers.com",
    "wof:name":"Eden Caterers",
    "wof:placetype":"venue"
},
  "geometry": {"coordinates":[-73.910098,40.618765],"type":"Point"}
}