{
  "type": "Feature",
  "properties": {
    "iso:country":"US",
    "sg:address":"24 Longfellow Dr",
    "sg:city":"Huntington Sta",
    "sg:classifiers":[
        {
            "category":"Manufacturing",
            "subcategory":"Tools & Machinery",
            "type":"Manufacturing & Wholesale Goods"
        }
    ],
    "sg:phone":"+1 631 549 9136",
    "sg:postcode":"11746",
    "sg:province":"NY",
    "sg:tags":[
        "devices"
    ],
    "wof:name":"United Measuring Systems",
    "wof:placetype":"venue"
},
  "geometry": {"coordinates":[-73.38239900000001,40.8368],"type":"Point"}
}