{
  "type": "Feature",
  "properties": {
    "iso:country":"US",
    "sg:address":"600 Albany Ave",
    "sg:city":"Amityville",
    "sg:classifiers":[
        {
            "category":"Government",
            "subcategory":"Office",
            "type":"Public Place"
        }
    ],
    "sg:phone":"+1 631 842 2997",
    "sg:postcode":"11701",
    "sg:province":"NY",
    "sg:tags":[
        "station",
        "recruiting"
    ],
    "wof:name":"Recruiting Station",
    "wof:placetype":"venue"
},
  "geometry": {"coordinates":[-73.40298799999999,40.707977],"type":"Point"}
}