{
  "type": "Feature",
  "properties": {
    "addr:full":"6 Van Brunt Manor Rd East Setauket NY 11733",
    "addr:housenumber":"6",
    "addr:postcode":"11733",
    "addr:street":"Van Brunt Manor Rd",
    "iso:country":"US",
    "sg:address":"6 Van Brunt Manor Rd",
    "sg:city":"East Setauket",
    "sg:classifiers":[
        {
            "category":"Manufacturing",
            "subcategory":"Metals",
            "type":"Manufacturing & Wholesale Goods"
        }
    ],
    "sg:phone":"+1   ",
    "sg:postcode":"11733",
    "sg:province":"NY",
    "sg:tags":[
        "ornamental",
        "fabrication"
    ],
    "wof:name":"Torino Industrial Inc",
    "wof:placetype":"venue"
},
  "geometry": {"coordinates":[-73.092012,40.945903],"type":"Point"}
}