{
  "type": "Feature",
  "properties": {
    "addr:full":"300 Nassau Blvd West Hempstead NY 11552",
    "addr:housenumber":"300",
    "addr:postcode":"11552",
    "addr:street":"Nassau Blvd West",
    "iso:country":"US",
    "sg:address":"300 Nassau Blvd",
    "sg:city":"West Hempstead",
    "sg:classifiers":[
        {
            "category":"Building & Trades",
            "subcategory":"Plumbing",
            "type":"Services"
        }
    ],
    "sg:phone":"+1 516 483 0282",
    "sg:postcode":"11552",
    "sg:province":"NY",
    "sg:tags":[
        "air",
        "heating",
        "contractor"
    ],
    "wof:name":"R & R Mechanical Inc",
    "wof:placetype":"venue"
},
  "geometry": {"coordinates":[-73.66020899999999,40.697527],"type":"Point"}
}