{
  "type": "Feature",
  "properties": {
    "iso:country":"US",
    "sg:address":"14 Franklin St",
    "sg:city":"Rochester",
    "sg:classifiers":[
        {
            "category":"Retail",
            "subcategory":"Repair Shop",
            "type":"Services"
        },
        {
            "category":"Building & Trades",
            "subcategory":"Construction",
            "type":"Services"
        }
    ],
    "sg:phone":"+1 585 325 5040",
    "sg:postcode":"14604",
    "sg:province":"NY",
    "sg:tags":[
        "elevator"
    ],
    "wof:name":"Delta Elevator Svc",
    "wof:placetype":"venue"
},
  "geometry": {"coordinates":[-77.60459,43.157891],"type":"Point"}
}