{
  "type": "Feature",
  "properties": {
    "iso:country":"US",
    "sg:address":"2735 Erie Blvd E",
    "sg:city":"Syracuse",
    "sg:classifiers":[
        {
            "category":"Shopping",
            "type":"Retail Goods"
        }
    ],
    "sg:phone":"+1 315 445 2600",
    "sg:postcode":"13224",
    "sg:province":"NY",
    "sg:tags":[
        "telephone",
        "cellular"
    ],
    "wof:name":"Wireless Plus",
    "wof:placetype":"venue"
},
  "geometry": {"coordinates":[-76.09137,43.055299],"type":"Point"}
}