{
  "type": "Feature",
  "properties": {
    "addr:full":"2500 George Urban Blvd Depew NY 14043",
    "addr:housenumber":"2500",
    "addr:postcode":"14043",
    "addr:street":"George Urban Blvd",
    "iso:country":"US",
    "sg:address":"2500 George Urban Blvd",
    "sg:city":"Depew",
    "sg:classifiers":[
        {
            "category":"Bars & Pubs",
            "type":"Food & Drink"
        }
    ],
    "sg:phone":"+1   ",
    "sg:postcode":"14043",
    "sg:province":"NY",
    "sg:tags":[
        "drinking"
    ],
    "wof:name":"Urban Inn",
    "wof:placetype":"venue"
},
  "geometry": {"coordinates":[-78.71953999999999,42.918764],"type":"Point"}
}