{
  "type": "Feature",
  "properties": {
    "addr:full":"1674 1 Ave New York NY 10128",
    "addr:housenumber":"1674",
    "addr:postcode":"10128",
    "addr:street":"1 Ave",
    "iso:country":"US",
    "sg:address":"1674 1 Ave",
    "sg:city":"New York",
    "sg:classifiers":[
        {
            "category":"Professional",
            "subcategory":"Business Services",
            "type":"Services"
        }
    ],
    "sg:phone":"+1 212 472 9700",
    "sg:postcode":"10128",
    "sg:province":"NY",
    "sg:tags":[
        "water",
        "treatment"
    ],
    "wof:name":"Culligan Water Conditioning Co",
    "wof:placetype":"venue"
},
  "geometry": {"coordinates":[-73.94842199999999,40.778182],"type":"Point"}
}