{
  "type": "Feature",
  "properties": {
    "addr:full":"62 Humbert St Geneva NY 14456",
    "addr:housenumber":"62",
    "addr:postcode":"14456",
    "addr:street":"Humbert St",
    "iso:country":"US",
    "sg:address":"62 Humbert St",
    "sg:city":"Geneva",
    "sg:classifiers":[
        {
            "category":"Bars & Pubs",
            "type":"Food & Drink"
        }
    ],
    "sg:phone":"+1   ",
    "sg:postcode":"14456",
    "sg:province":"NY",
    "sg:tags":[
        "drinking"
    ],
    "wof:name":"Spiderman Bar",
    "wof:placetype":"venue"
},
  "geometry": {"coordinates":[-76.98524999999999,42.883099],"type":"Point"}
}