{
  "type": "Feature",
  "properties": {
    "addr:full":"170 Bedford Ave New Hyde Park NY 11040",
    "addr:housenumber":"170",
    "addr:postcode":"11040",
    "addr:street":"Bedford Ave",
    "iso:country":"US",
    "sg:address":"170 Bedford Ave",
    "sg:city":"New Hyde Park",
    "sg:classifiers":[
        {
            "category":"Building & Trades",
            "subcategory":"Cleaning & Sanitation",
            "type":"Services"
        }
    ],
    "sg:phone":"+1 516 873 0527",
    "sg:postcode":"11040",
    "sg:province":"NY",
    "sg:tags":[
        "janitor"
    ],
    "wof:name":"Nassau Cleaning Professionals",
    "wof:placetype":"venue"
},
  "geometry": {"coordinates":[-73.656733,40.739816],"type":"Point"}
}