{
  "type": "Feature",
  "properties": {
    "addr:full":"804 Lexington Ave New York NY 10021",
    "addr:housenumber":"804",
    "addr:postcode":"10021",
    "addr:street":"Lexington Ave",
    "iso:country":"US",
    "sg:address":"804 Lexington Ave",
    "sg:city":"New York",
    "sg:classifiers":[
        {
            "category":"Fast Food",
            "type":"Food & Drink"
        },
        {
            "category":"Food & Beverages",
            "subcategory":"Meat & Fish",
            "type":"Retail Goods"
        }
    ],
    "sg:phone":"+1 212 223 0868",
    "sg:postcode":"10021",
    "sg:province":"NY",
    "sg:tags":[
        "hot",
        "dog"
    ],
    "sg:website":"www.orderburgerheaven.com/public...",
    "wof:name":"Burger Heaven",
    "wof:placetype":"venue"
},
  "geometry": {"coordinates":[-73.966993,40.764309],"type":"Point"}
}