{
  "type": "Feature",
  "properties": {
    "iso:country":"US",
    "sg:address":"222 Wensley Ln",
    "sg:city":"East Islip",
    "sg:classifiers":[
        {
            "category":"Manufacturing",
            "subcategory":"Rubber & Plastics",
            "type":"Manufacturing & Wholesale Goods"
        }
    ],
    "sg:phone":"+1   ",
    "sg:postcode":"11730",
    "sg:province":"NY",
    "sg:tags":[
        "tube",
        "mfg"
    ],
    "wof:name":"BF Tool Co",
    "wof:placetype":"venue"
},
  "geometry": {"coordinates":[-73.16769600000001,40.723139],"type":"Point"}
}