{
  "type": "Feature",
  "properties": {
    "iso:country":"US",
    "sg:address":"3828 Teachers Ln",
    "sg:city":"Orchard Park",
    "sg:classifiers":[
        {
            "category":"Shopping",
            "subcategory":"Computers & Home Electronics",
            "type":"Retail Goods"
        }
    ],
    "sg:phone":"+1   ",
    "sg:postcode":"14127",
    "sg:province":"NY",
    "sg:tags":[
        "sales",
        "internet"
    ],
    "wof:name":"Dreamweaver Associates",
    "wof:placetype":"venue"
},
  "geometry": {"coordinates":[-78.798626,42.777728],"type":"Point"}
}