{
  "type": "Feature",
  "properties": {
    "iso:country":"US",
    "sg:address":"73 Roslyn Rd",
    "sg:city":"Roslyn Heights",
    "sg:classifiers":[
        {
            "category":"Real Estate",
            "subcategory":"Real Estate Agent",
            "type":"Services"
        }
    ],
    "sg:phone":"+1 516 625 3135",
    "sg:postcode":"11577",
    "sg:province":"NY",
    "sg:tags":[
        "consulting",
        "management"
    ],
    "wof:name":"T J Realty Svces",
    "wof:placetype":"venue"
},
  "geometry": {"coordinates":[-73.64077899999999,40.791476],"type":"Point"}
}