{
  "type": "Feature",
  "properties": {
    "addr:full":"40 E 52nd St Fl 22 New York NY 10022",
    "addr:housenumber":"40;22",
    "addr:postcode":"10022",
    "addr:street":"E 52Nd St Fl",
    "iso:country":"US",
    "sg:address":"40 E 52nd St Fl 22",
    "sg:city":"New York",
    "sg:classifiers":[
        {
            "category":"Banks & Credit Unions",
            "subcategory":"Bank",
            "type":"Services"
        }
    ],
    "sg:phone":"+1 212 326 8000",
    "sg:postcode":"10022",
    "sg:province":"NY",
    "wof:name":"National Bank of Egypt Ny",
    "wof:placetype":"venue"
},
  "geometry": {"coordinates":[-73.97441600000001,40.758987],"type":"Point"}
}