{
  "type": "Feature",
  "properties": {
    "iso:country":"US",
    "sg:address":"856 Montauk Hwy",
    "sg:city":"Copiague",
    "sg:classifiers":[
        {
            "category":"Personal",
            "subcategory":"Beauty Salon",
            "type":"Services"
        }
    ],
    "sg:phone":"+1   ",
    "sg:postcode":"11726",
    "sg:province":"NY",
    "sg:tags":[
        "shop"
    ],
    "wof:name":"Nail Plaza",
    "wof:placetype":"venue"
},
  "geometry": {"coordinates":[-73.393452,40.668791],"type":"Point"}
}