{
  "type": "Feature",
  "properties": {
    "addr:full":"75 Larkfield Rd East Northport NY 11731",
    "addr:housenumber":"75",
    "addr:postcode":"11731",
    "addr:street":"Larkfield Rd",
    "iso:country":"US",
    "sg:address":"75 Larkfield Rd",
    "sg:city":"East Northport",
    "sg:classifiers":[
        {
            "category":"Personal",
            "subcategory":"Beauty Salon",
            "type":"Services"
        }
    ],
    "sg:phone":"+1 631 262 9302",
    "sg:postcode":"11731",
    "sg:province":"NY",
    "sg:tags":[
        "make",
        "studio"
    ],
    "sg:website":"www.cosmeticmall.com",
    "wof:name":"Cosmetic Mall",
    "wof:placetype":"venue"
},
  "geometry": {"coordinates":[-73.325706,40.880679],"type":"Point"}
}