{
  "type": "Feature",
  "properties": {
    "addr:full":"14 Prospect St Trumansburg NY 14886",
    "addr:housenumber":"14",
    "addr:postcode":"14886",
    "addr:street":"Prospect St",
    "iso:country":"US",
    "sg:address":"14 Prospect St",
    "sg:city":"Trumansburg",
    "sg:classifiers":[
        {
            "category":"Building & Trades",
            "subcategory":"Construction",
            "type":"Services"
        },
        {
            "category":"Manufacturing",
            "subcategory":"Building Materials",
            "type":"Manufacturing & Wholesale Goods"
        }
    ],
    "sg:phone":"+1 607 387 9280",
    "sg:postcode":"14886",
    "sg:province":"NY",
    "sg:tags":[
        "cabinetmakers-commercial",
        "industrial",
        "maker",
        "cabinet"
    ],
    "sg:website":"http://www.violinvarnish.com",
    "wof:name":"Robson, Joe W",
    "wof:placetype":"venue"
},
  "geometry": {"coordinates":[-76.657149,42.543588],"type":"Point"}
}