{
  "type": "Feature",
  "properties": {
    "addr:full":"4612 S Salina St Syracuse NY 13205",
    "addr:housenumber":"4612",
    "addr:postcode":"13205",
    "addr:street":"S Salina St",
    "iso:country":"US",
    "sg:address":"4612 S Salina St",
    "sg:city":"Syracuse",
    "sg:classifiers":[
        {
            "category":"Retail",
            "subcategory":"Funeral Services",
            "type":"Services"
        }
    ],
    "sg:phone":"+1 315 492 3504",
    "sg:postcode":"13205",
    "sg:province":"NY",
    "sg:tags":[
        "mortician"
    ],
    "sg:website":"http://www.ballweg-lunsford.com",
    "wof:name":"Ballweg & Lunsford Funeral Home Inc",
    "wof:placetype":"venue"
},
  "geometry": {"coordinates":[-76.142853,43.002529],"type":"Point"}
}