{
  "type": "Feature",
  "properties": {
    "addr:full":"36 Keap St Brooklyn NY 11211",
    "addr:housenumber":"36",
    "addr:postcode":"11211",
    "addr:street":"Keap St",
    "iso:country":"US",
    "sg:address":"36 Keap St",
    "sg:city":"Brooklyn",
    "sg:classifiers":[
        {
            "category":"Building & Trades",
            "subcategory":"Plumbing",
            "type":"Services"
        }
    ],
    "sg:phone":"+1 718 782 4400",
    "sg:postcode":"11211",
    "sg:province":"NY",
    "sg:tags":[
        "plumbing",
        "contractor"
    ],
    "wof:name":"Plumber & Heating Systems Inc",
    "wof:placetype":"venue"
},
  "geometry": {"coordinates":[-73.962654,40.702181],"type":"Point"}
}