{
  "type": "Feature",
  "properties": {
    "addr:full":"7 Elm St Westbury NY 11590",
    "addr:housenumber":"7",
    "addr:postcode":"11590",
    "addr:street":"Elm St",
    "iso:country":"US",
    "sg:address":"7 Elm St",
    "sg:city":"Westbury",
    "sg:classifiers":[
        {
            "category":"Professional",
            "subcategory":"Engineering",
            "type":"Services"
        }
    ],
    "sg:phone":"+1 516 338 0500",
    "sg:postcode":"11590",
    "sg:province":"NY",
    "sg:tags":[
        "lighting",
        "engineer"
    ],
    "wof:name":"Gold Coast Lighting",
    "wof:placetype":"venue"
},
  "geometry": {"coordinates":[-73.59662400000001,40.757455],"type":"Point"}
}