{
  "type": "Feature",
  "properties": {
    "addr:full":"200 Varick St New York NY 10014",
    "addr:housenumber":"200",
    "addr:postcode":"10014",
    "addr:street":"Varick St",
    "iso:country":"US",
    "sg:address":"200 Varick St",
    "sg:city":"New York",
    "sg:classifiers":[
        {
            "category":"Wholesale",
            "subcategory":"Stationery",
            "type":"Manufacturing & Wholesale Goods"
        }
    ],
    "sg:phone":"+1 212 924 3300",
    "sg:postcode":"10014",
    "sg:province":"NY",
    "sg:tags":[
        "card"
    ],
    "wof:name":"Puck Enterprises Inc",
    "wof:placetype":"venue"
},
  "geometry": {"coordinates":[-74.005402,40.727901],"type":"Point"}
}