{
  "type": "Feature",
  "properties": {
    "addr:full":"125 Canal Street New York NY 10002",
    "addr:housenumber":"125",
    "addr:postcode":"10002",
    "addr:street":"Canal Street",
    "iso:country":"US",
    "sg:address":"125 Canal Street",
    "sg:city":"New York",
    "sg:classifiers":[
        {
            "category":"Building & Trades",
            "subcategory":"Locksmith",
            "type":"Services"
        }
    ],
    "sg:phone":"+1 212 518 2818",
    "sg:postcode":"10002",
    "sg:province":"NY",
    "sg:tags":[
        "key"
    ],
    "wof:name":"24 Hour Emergency Locksmith",
    "wof:placetype":"venue"
},
  "geometry": {"coordinates":[-73.99495400000001,40.715861],"type":"Point"}
}