{
  "type": "Feature",
  "properties": {
    "iso:country":"US",
    "sg:address":"68 E Suffolk Ave Unit 1",
    "sg:city":"Central Islip",
    "sg:classifiers":[
        {
            "category":"Professional",
            "subcategory":"Lawyer & Legal Services",
            "type":"Services"
        }
    ],
    "sg:phone":"+1 631 328 5040",
    "sg:postcode":"11722",
    "sg:province":"NY",
    "sg:website":"www.nortonlawgroup.com",
    "wof:name":"Norton Law Group",
    "wof:placetype":"venue"
},
  "geometry": {"coordinates":[-73.19761200000001,40.791795],"type":"Point"}
}