{
  "type": "Feature",
  "properties": {
    "addr:full":"1850 College Point Boulevard College Point NY 11356",
    "addr:housenumber":"1850",
    "addr:postcode":"11356",
    "addr:street":"College Point Boulevard",
    "iso:country":"US",
    "sg:address":"1850 College Point Boulevard",
    "sg:city":"College Point",
    "sg:classifiers":[
        {
            "category":"Shopping",
            "subcategory":"Clothing, Apparel, & Fashions",
            "type":"Retail Goods"
        }
    ],
    "sg:phone":"+1 718 358 3332",
    "sg:postcode":"11356",
    "sg:province":"NY",
    "sg:tags":[
        "accessory",
        "clothing",
        "women's"
    ],
    "wof:name":"Lahoya Enterprise",
    "wof:placetype":"venue"
},
  "geometry": {"coordinates":[-73.846034,40.782522],"type":"Point"}
}