{
  "type": "Feature",
  "properties": {
    "addr:full":"2530 Hylan Blvd Staten Island NY 10306",
    "addr:housenumber":"2530",
    "addr:postcode":"10306",
    "addr:street":"Hylan Blvd",
    "iso:country":"US",
    "sg:address":"2530 Hylan Blvd",
    "sg:city":"Staten Island",
    "sg:classifiers":[
        {
            "category":"Shopping",
            "subcategory":"Clothing, Apparel, & Fashions",
            "type":"Retail Goods"
        }
    ],
    "sg:phone":"+1 718 980 4863",
    "sg:postcode":"10306",
    "sg:province":"NY",
    "sg:website":"www.gap.com",
    "wof:name":"Gap",
    "wof:placetype":"venue"
},
  "geometry": {"coordinates":[-74.109762,40.570468],"type":"Point"}
}