{
  "type": "Feature",
  "properties": {
    "iso:country":"US",
    "sg:address":"15 Sylvia Way",
    "sg:city":"Purdys",
    "sg:classifiers":[
        {
            "category":"Building & Trades",
            "subcategory":"Construction",
            "type":"Services"
        }
    ],
    "sg:phone":"+1 914 276 0576",
    "sg:postcode":"10578",
    "sg:province":"NY",
    "sg:tags":[
        "painter"
    ],
    "wof:name":"Dunn-Rite Painting",
    "wof:placetype":"venue"
},
  "geometry": {"coordinates":[-73.664782,41.330588],"type":"Point"}
}