{
  "type": "Feature",
  "properties": {
    "iso:country":"US",
    "sg:address":"67 S Lake Ave",
    "sg:city":"Albany",
    "sg:classifiers":[
        {
            "category":"Professional",
            "subcategory":"Business Services",
            "type":"Services"
        }
    ],
    "sg:phone":"+1 518 449 7317",
    "sg:postcode":"12203",
    "sg:province":"NY",
    "sg:tags":[
        "holding"
    ],
    "wof:name":"Litch Street Co Lp",
    "wof:placetype":"venue"
},
  "geometry": {"coordinates":[-73.776346,42.659026],"type":"Point"}
}