{
  "type": "Feature",
  "properties": {
    "iso:country":"US",
    "sg:address":"134 Goodburlet Rd",
    "sg:city":"Henrietta",
    "sg:classifiers":[
        {
            "category":"Manufacturing",
            "subcategory":"Printing",
            "type":"Manufacturing & Wholesale Goods"
        }
    ],
    "sg:phone":"+1   ",
    "sg:postcode":"14467",
    "sg:province":"NY",
    "sg:tags":[
        "organization",
        "book",
        "religious"
    ],
    "sg:website":"www.caravelabooks.com",
    "wof:name":"Caravela Books",
    "wof:placetype":"venue"
},
  "geometry": {"coordinates":[-77.61018300000001,43.050197],"type":"Point"}
}