{
  "type": "Feature",
  "properties": {
    "iso:country":"US",
    "sg:address":"16 S Main St",
    "sg:city":"Pittsford",
    "sg:classifiers":[
        {
            "category":"Personal",
            "subcategory":"Beauty Salon",
            "type":"Services"
        }
    ],
    "sg:phone":"+1 585 586 2150",
    "sg:postcode":"14534",
    "sg:province":"NY",
    "wof:name":"Amy's Nails Plus",
    "wof:placetype":"venue"
},
  "geometry": {"coordinates":[-77.51607199999999,43.089611],"type":"Point"}
}