{
  "type": "Feature",
  "properties": {
    "iso:country":"US",
    "sg:address":"18 Maplegrove Dr",
    "sg:city":"Churchville",
    "sg:classifiers":[
        {
            "category":"Professional",
            "type":"Services"
        }
    ],
    "sg:phone":"+1 585 293 1091",
    "sg:postcode":"14428",
    "sg:province":"NY",
    "sg:tags":[
        "establishment"
    ],
    "wof:name":"Adhesives & Materials Tech",
    "wof:placetype":"venue"
},
  "geometry": {"coordinates":[-77.864744,43.139325],"type":"Point"}
}