{
  "type": "Feature",
  "properties": {
    "addr:full":"31935 Main Rd Cutchogue NY 11935",
    "addr:housenumber":"31935",
    "addr:postcode":"11935",
    "addr:street":"Main Rd",
    "iso:country":"US",
    "sg:address":"31935 Main Rd",
    "sg:city":"Cutchogue",
    "sg:classifiers":[
        {
            "category":"Shopping",
            "subcategory":"Used Merchandise",
            "type":"Retail Goods"
        }
    ],
    "sg:phone":"+1   ",
    "sg:postcode":"11935",
    "sg:province":"NY",
    "wof:name":"Antiques & Old Lace",
    "wof:placetype":"venue"
},
  "geometry": {"coordinates":[-72.478222,41.021046],"type":"Point"}
}