{
  "type": "Feature",
  "properties": {
    "iso:country":"US",
    "sg:address":"152 William St",
    "sg:city":"Catskill",
    "sg:classifiers":[
        {
            "category":"Manufacturing",
            "subcategory":"Apparel",
            "type":"Manufacturing & Wholesale Goods"
        }
    ],
    "sg:phone":"+1   ",
    "sg:postcode":"12414",
    "sg:province":"NY",
    "sg:tags":[
        "mfg",
        "textile",
        "bag",
        "man",
        "clothing",
        "utility"
    ],
    "wof:name":"Two Tsunami Productions Inc",
    "wof:placetype":"venue"
},
  "geometry": {"coordinates":[-73.857985,42.219555],"type":"Point"}
}