{
  "type": "Feature",
  "properties": {
    "iso:country":"US",
    "sg:address":"333 E 38th St",
    "sg:city":"New York",
    "sg:classifiers":[
        {
            "category":"Organizations",
            "subcategory":"Non-profit Organization",
            "type":"Services"
        }
    ],
    "sg:phone":"+1 212 686 5522",
    "sg:postcode":"10016",
    "sg:province":"NY",
    "sg:tags":[
        "fund",
        "raising"
    ],
    "wof:name":"United States Fund For Unicef",
    "wof:placetype":"venue"
},
  "geometry": {"coordinates":[-73.97188800000001,40.7465],"type":"Point"}
}