{
  "type": "Feature",
  "properties": {
    "iso:country":"US",
    "sg:address":"9909 Portville-Ceres Rd",
    "sg:city":"Portville",
    "sg:classifiers":[
        {
            "category":"Personal",
            "subcategory":"Beauty Salon",
            "type":"Services"
        }
    ],
    "sg:phone":"+1 585 933 6815",
    "sg:postcode":"14770",
    "sg:province":"NY",
    "wof:name":"Shear Magic",
    "wof:placetype":"venue"
},
  "geometry": {"coordinates":[-78.298,42.00722],"type":"Point"}
}