{
  "type": "Feature",
  "properties": {
    "iso:country":"US",
    "sg:address":"309 Walnut St",
    "sg:city":"Elmira",
    "sg:classifiers":[
        {
            "category":"Professional",
            "subcategory":"Accounting & Tax Preparation",
            "type":"Services"
        }
    ],
    "sg:phone":"+1 607 733 5680",
    "sg:postcode":"14901",
    "sg:province":"NY",
    "sg:tags":[
        "sec",
        "management",
        "return"
    ],
    "wof:name":"Cascio Financial Strategies",
    "wof:placetype":"venue"
},
  "geometry": {"coordinates":[-76.817684,42.0874],"type":"Point"}
}