{
  "type": "Feature",
  "properties": {
    "addr:full":"775 Marilyn Ln Baldwin NY 11510",
    "addr:housenumber":"775",
    "addr:postcode":"11510",
    "addr:street":"Marilyn Ln",
    "iso:country":"US",
    "sg:address":"775 Marilyn Ln",
    "sg:city":"Baldwin",
    "sg:classifiers":[
        {
            "category":"Arts & Performance",
            "subcategory":"Theater",
            "type":"Entertainment"
        }
    ],
    "sg:phone":"+1 516 868 0902",
    "sg:postcode":"11510",
    "sg:province":"NY",
    "sg:tags":[
        "bureau"
    ],
    "wof:name":"5 Star Entertainment",
    "wof:placetype":"venue"
},
  "geometry": {"coordinates":[-73.610806,40.629784],"type":"Point"}
}