{
  "type": "Feature",
  "properties": {
    "addr:full":"147 Avenue & 249 Rosedale NY 11422",
    "addr:housenumber":"147",
    "addr:postcode":"11422",
    "addr:street":"Avenue & 249",
    "iso:country":"US",
    "sg:address":"147 Avenue & 249",
    "sg:city":"Rosedale",
    "sg:classifiers":[
        {
            "category":"Education",
            "subcategory":"School",
            "type":"Public Place"
        },
        {
            "category":"Organizations",
            "subcategory":"Religious Organization",
            "type":"Services"
        }
    ],
    "sg:phone":"+1 718 525 7858",
    "sg:postcode":"11422",
    "sg:province":"NY",
    "sg:tags":[
        "high",
        "middle",
        "elementary"
    ],
    "wof:name":"St Pius X Rc Church",
    "wof:placetype":"venue"
},
  "geometry": {"coordinates":[-73.73460900000001,40.662641],"type":"Point"}
}