{
  "type": "Feature",
  "properties": {
    "addr:full":"6 Long Island Ave Holtsville NY 11742",
    "addr:housenumber":"6",
    "addr:postcode":"11742",
    "addr:street":"Long Island Ave",
    "iso:country":"US",
    "sg:address":"6 Long Island Ave",
    "sg:city":"Holtsville",
    "sg:classifiers":[
        {
            "category":"Manufacturing",
            "subcategory":"Chemicals & Compounds",
            "type":"Manufacturing & Wholesale Goods"
        },
        {
            "category":"Shopping",
            "subcategory":"Pharmacy",
            "type":"Retail Goods"
        }
    ],
    "sg:phone":"+1 631 758 0200",
    "sg:postcode":"11742",
    "sg:province":"NY",
    "sg:tags":[
        "medicines-patent",
        "manufacturer",
        "proprietary",
        "chemicals-wholesale"
    ],
    "wof:name":"Pride Solvents & Chemical Co Of New Jersey, Inc",
    "wof:placetype":"venue"
},
  "geometry": {"coordinates":[-73.061098,40.813866],"type":"Point"}
}