{
  "type": "Feature",
  "properties": {
    "iso:country":"US",
    "sg:address":"60 Carleton Ave",
    "sg:city":"Islip Terrace",
    "sg:classifiers":[
        {
            "category":"Real Estate",
            "subcategory":"Architect",
            "type":"Services"
        }
    ],
    "sg:phone":"+1 631 348 0356",
    "sg:postcode":"11752",
    "sg:province":"NY",
    "wof:name":"Techpro Designs",
    "wof:placetype":"venue"
},
  "geometry": {"coordinates":[-73.194603,40.7514],"type":"Point"}
}