{
  "type": "Feature",
  "properties": {
    "iso:country":"US",
    "sg:address":"1388 Old Northern Blvd",
    "sg:city":"Roslyn",
    "sg:classifiers":[
        {
            "category":"Shopping",
            "subcategory":"Clothing, Apparel, & Fashions",
            "type":"Retail Goods"
        }
    ],
    "sg:phone":"+1 516 625 5463",
    "sg:postcode":"11576",
    "sg:province":"NY",
    "wof:name":"Lsk Collection Inc",
    "wof:placetype":"venue"
},
  "geometry": {"coordinates":[-73.647218,40.80132],"type":"Point"}
}