{
  "type": "Feature",
  "properties": {
    "addr:full":"10 Indian Trail Rd Williamsville NY 14221",
    "addr:housenumber":"10",
    "addr:postcode":"14221",
    "addr:street":"Indian Trail Rd",
    "iso:country":"US",
    "sg:address":"10 Indian Trail Rd",
    "sg:city":"Williamsville",
    "sg:classifiers":[
        {
            "category":"Organizations",
            "subcategory":"Religious Organization",
            "type":"Services"
        }
    ],
    "sg:phone":"+1 716 631 8208",
    "sg:postcode":"14221",
    "sg:province":"NY",
    "sg:tags":[
        "church"
    ],
    "wof:name":"Niagara Reformed Presbyterian",
    "wof:placetype":"venue"
},
  "geometry": {"coordinates":[-78.764788,42.982652],"type":"Point"}
}