{
  "type": "Feature",
  "properties": {
    "addr:full":"50 Beaver St Albany NY 12207",
    "addr:housenumber":"50",
    "addr:postcode":"12207",
    "addr:street":"Beaver St",
    "iso:country":"US",
    "sg:address":"50 Beaver St",
    "sg:city":"Albany",
    "sg:classifiers":[
        {
            "category":"Professional",
            "subcategory":"Lawyer & Legal Services",
            "type":"Services"
        }
    ],
    "sg:phone":"+1 518 432 6857",
    "sg:postcode":"12207",
    "sg:province":"NY",
    "sg:tags":[
        "attorney"
    ],
    "wof:name":"Phillips & Assoc",
    "wof:placetype":"venue"
},
  "geometry": {"coordinates":[-73.75241800000001,42.648326],"type":"Point"}
}