{
  "type": "Feature",
  "properties": {
    "iso:country":"US",
    "sg:address":"16 Church St",
    "sg:city":"Cortland",
    "sg:classifiers":[
        {
            "category":"Professional",
            "subcategory":"Lawyer & Legal Services",
            "type":"Services"
        }
    ],
    "sg:phone":"+1 607 753 3058",
    "sg:postcode":"13045",
    "sg:province":"NY",
    "wof:name":"Avery Emerson R Sr",
    "wof:placetype":"venue"
},
  "geometry": {"coordinates":[-76.17804700000001,42.600679],"type":"Point"}
}