{
  "type": "Feature",
  "properties": {
    "iso:country":"US",
    "sg:address":"528 Merrick Rd",
    "sg:city":"Lynbrook",
    "sg:classifiers":[
        {
            "category":"Food & Beverages",
            "subcategory":"Groceries & Convenience Stores",
            "type":"Retail Goods"
        }
    ],
    "sg:phone":"+1 516 593 7281",
    "sg:postcode":"11563",
    "sg:province":"NY",
    "wof:name":"Vincent Food Mkt",
    "wof:placetype":"venue"
},
  "geometry": {"coordinates":[-73.678596,40.659199],"type":"Point"}
}