{
  "type": "Feature",
  "properties": {
    "addr:full":"510 King St Staten Island NY 10312",
    "addr:housenumber":"510",
    "addr:postcode":"10312",
    "addr:street":"King St",
    "iso:country":"US",
    "sg:address":"510 King St",
    "sg:city":"Staten Island",
    "sg:classifiers":[
        {
            "category":"Building & Trades",
            "subcategory":"Construction",
            "type":"Services"
        }
    ],
    "sg:phone":"+1 718 984 1508",
    "sg:postcode":"10312",
    "sg:province":"NY",
    "sg:tags":[
        "house"
    ],
    "wof:name":"Mm Home Improvement Inc",
    "wof:placetype":"venue"
},
  "geometry": {"coordinates":[-74.159057,40.53195],"type":"Point"}
}