{
  "type": "Feature",
  "properties": {
    "iso:country":"US",
    "sg:address":"1573 Islip Ave",
    "sg:city":"Central Islip",
    "sg:classifiers":[
        {
            "category":"Food & Beverages",
            "subcategory":"Groceries & Convenience Stores",
            "type":"Retail Goods"
        }
    ],
    "sg:phone":"+1   ",
    "sg:postcode":"11722",
    "sg:province":"NY",
    "sg:tags":[
        "filling",
        "station",
        "gasoline"
    ],
    "wof:name":"Route 111 Foodmart",
    "wof:placetype":"venue"
},
  "geometry": {"coordinates":[-73.21733500000001,40.781142],"type":"Point"}
}