{
  "type": "Feature",
  "properties": {
    "addr:full":"730 Columbus Ave New York NY 10025",
    "addr:housenumber":"730",
    "addr:postcode":"10025",
    "addr:street":"Columbus Ave",
    "iso:country":"US",
    "sg:address":"730 Columbus Ave",
    "sg:city":"New York",
    "sg:classifiers":[
        {
            "category":"Food & Beverages",
            "subcategory":"Liquor & Beverages",
            "type":"Retail Goods"
        }
    ],
    "sg:phone":"+1 212 865 7070",
    "sg:postcode":"10025",
    "sg:province":"NY",
    "sg:tags":[
        "beer",
        "spirit",
        "wine"
    ],
    "sg:website":"www.columbuswines.com",
    "wof:name":"Columbus Avenue Wine & Spirits",
    "wof:placetype":"venue"
},
  "geometry": {"coordinates":[-73.968014,40.792563],"type":"Point"}
}