{
  "type": "Feature",
  "properties": {
    "iso:country":"US",
    "sg:address":"730 Columbus Ave",
    "sg:city":"New York",
    "sg:classifiers":[
        {
            "category":"Food & Beverages",
            "subcategory":"Liquor & Beverages",
            "type":"Retail Goods"
        }
    ],
    "sg:phone":"+1 212 865 7070",
    "sg:postcode":"10025",
    "sg:province":"NY",
    "sg:tags":[
        "beer",
        "spirit",
        "wine"
    ],
    "sg:website":"www.columbuswines.com",
    "wof:name":"Columbus Avenue Wine & Spirits",
    "wof:placetype":"venue"
},
  "geometry": {"coordinates":[-73.96761100000001,40.792715],"type":"Point"}
}