{
  "type": "Feature",
  "properties": {
    "iso:country":"US",
    "sg:address":"82 Roslyn Rd",
    "sg:city":"Roslyn Heights",
    "sg:classifiers":[
        {
            "category":"Restaurant",
            "type":"Food & Drink"
        }
    ],
    "sg:phone":"+1 516 625 1420",
    "sg:postcode":"11577",
    "sg:province":"NY",
    "sg:tags":[
        "delicatessen"
    ],
    "wof:name":"Roslyn Heights Deli",
    "wof:placetype":"venue"
},
  "geometry": {"coordinates":[-73.640665,40.791656],"type":"Point"}
}