{
  "type": "Feature",
  "properties": {
    "iso:country":"US",
    "sg:address":"136 Radio Cir Dr",
    "sg:city":"Mount Kisco",
    "sg:classifiers":[
        {
            "category":"Banks & Credit Unions",
            "subcategory":"Financial Services",
            "type":"Services"
        }
    ],
    "sg:phone":"+1 914 666 7761",
    "sg:postcode":"10549",
    "sg:province":"NY",
    "sg:tags":[
        "investor",
        "real estate"
    ],
    "wof:name":"Radio Circle Realty Inc",
    "wof:placetype":"venue"
},
  "geometry": {"coordinates":[-73.736407,41.191865],"type":"Point"}
}