{
  "type": "Feature",
  "properties": {
    "iso:country":"US",
    "sg:address":"110 Main St",
    "sg:city":"S Glens Falls",
    "sg:classifiers":[
        {
            "category":"Government",
            "subcategory":"Post Office",
            "type":"Public Place"
        }
    ],
    "sg:phone":"+1 518 793 5961",
    "sg:postcode":"12803",
    "sg:province":"NY",
    "sg:tags":[
        "postal",
        "us"
    ],
    "wof:name":"US Post Office",
    "wof:placetype":"venue"
},
  "geometry": {"coordinates":[-73.63507300000001,43.298735],"type":"Point"}
}