{
  "type": "Feature",
  "properties": {
    "iso:country":"US",
    "sg:address":"22 Fishkill Rd",
    "sg:city":"Cold Spring",
    "sg:classifiers":[
        {
            "category":"Shopping",
            "subcategory":"Gifts & Souvenirs",
            "type":"Retail Goods"
        }
    ],
    "sg:phone":"+1   ",
    "sg:postcode":"10516",
    "sg:province":"NY",
    "wof:name":"Shadow Box Ink",
    "wof:placetype":"venue"
},
  "geometry": {"coordinates":[-73.93881500000001,41.429754],"type":"Point"}
}