{
  "type": "Feature",
  "properties": {
    "iso:country":"US",
    "sg:address":"400 Carleton Ave",
    "sg:city":"Central Islip",
    "sg:classifiers":[
        {
            "category":"Social Services",
            "subcategory":"Adult Care",
            "type":"Services"
        }
    ],
    "sg:phone":"+1 631 853 4509",
    "sg:postcode":"11722",
    "sg:province":"NY",
    "sg:tags":[
        "residential"
    ],
    "wof:name":"Cohalan Crt Complex Chld Svcs",
    "wof:placetype":"venue"
},
  "geometry": {"coordinates":[-73.199763,40.779865],"type":"Point"}
}