{
  "type": "Feature",
  "properties": {
    "iso:country":"US",
    "sg:address":"333 Adams St",
    "sg:city":"Brooklyn",
    "sg:classifiers":[
        {
            "category":"Real Estate",
            "subcategory":"Real Estate Agent",
            "type":"Services"
        }
    ],
    "sg:phone":"+1 718 855 4486",
    "sg:postcode":"11201",
    "sg:province":"NY",
    "wof:name":"Renaissance Property Plaza",
    "wof:placetype":"venue"
},
  "geometry": {"coordinates":[-73.988663,40.693478],"type":"Point"}
}