{
  "type": "Feature",
  "properties": {
    "iso:country":"US",
    "sg:address":"2008 Eastchester Rd",
    "sg:city":"Bronx",
    "sg:classifiers":[
        {
            "category":"Retail",
            "subcategory":"Auto Repair",
            "type":"Services"
        }
    ],
    "sg:phone":"+1 718 822 8654",
    "sg:postcode":"10461",
    "sg:province":"NY",
    "sg:tags":[
        "repairing",
        "automobile"
    ],
    "wof:name":"Bronx Boro Collision Inc",
    "wof:placetype":"venue"
},
  "geometry": {"coordinates":[-73.843524,40.854432],"type":"Point"}
}