{
  "type": "Feature",
  "properties": {
    "addr:full":"7 Bird Pl White Plains NY 10605",
    "addr:housenumber":"7",
    "addr:postcode":"10605",
    "addr:street":"Bird Pl",
    "iso:country":"US",
    "sg:address":"7 Bird Pl",
    "sg:city":"White Plains",
    "sg:classifiers":[
        {
            "category":"Professional",
            "subcategory":"Lawyer & Legal Services",
            "type":"Services"
        }
    ],
    "sg:phone":"+1 914 428 1040",
    "sg:postcode":"10605",
    "sg:province":"NY",
    "sg:tags":[
        "attorney"
    ],
    "wof:name":"Stacey M Glaser",
    "wof:placetype":"venue"
},
  "geometry": {"coordinates":[-73.73283499999999,41.0171],"type":"Point"}
}