{
  "type": "Feature",
  "properties": {
    "addr:full":"57 N Henry St Brooklyn NY 11222",
    "addr:housenumber":"57",
    "addr:postcode":"11222",
    "addr:street":"N Henry St",
    "iso:country":"US",
    "sg:address":"57 N Henry St",
    "sg:city":"Brooklyn",
    "sg:classifiers":[
        {
            "category":"Retail",
            "subcategory":"Laundry & Dry Cleaning",
            "type":"Services"
        },
        {
            "category":"Building & Trades",
            "subcategory":"Cleaning & Sanitation",
            "type":"Services"
        }
    ],
    "sg:phone":"+1 718 928 0393",
    "sg:postcode":"11222",
    "sg:province":"NY",
    "sg:tags":[
        "cleaner",
        "upholstery",
        "house",
        "rug",
        "window",
        "janitorial",
        "carpet"
    ],
    "sg:website":"http://www.yext.com/p/superpages/new-york-house-keeping-brooklyn-new-york.html",
    "wof:name":"New York House Keeping",
    "wof:placetype":"venue"
},
  "geometry": {"coordinates":[-73.942842,40.721194],"type":"Point"}
}