{
  "type": "Feature",
  "properties": {
    "addr:full":"715 Mamaroneck Ave Mamaroneck NY 10543",
    "addr:housenumber":"715",
    "addr:postcode":"10543",
    "addr:street":"Mamaroneck Ave",
    "iso:country":"US",
    "sg:address":"715 Mamaroneck Ave",
    "sg:city":"Mamaroneck",
    "sg:classifiers":[
        {
            "category":"Professional",
            "subcategory":"Computer Services",
            "type":"Services"
        }
    ],
    "sg:phone":"+1 914 220 5115",
    "sg:postcode":"10543",
    "sg:province":"NY",
    "sg:tags":[
        "website",
        "design"
    ],
    "wof:name":"CBL Path",
    "wof:placetype":"venue"
},
  "geometry": {"coordinates":[-73.738444,40.956112],"type":"Point"}
}