{
  "type": "Feature",
  "properties": {
    "iso:country":"US",
    "sg:address":"1046 University Ave",
    "sg:city":"Rochester",
    "sg:classifiers":[
        {
            "category":"Organizations",
            "subcategory":"Non-profit Organization",
            "type":"Services"
        }
    ],
    "sg:phone":"+1 585 442 0620",
    "sg:postcode":"14607",
    "sg:province":"NY",
    "sg:tags":[
        "action",
        "agency",
        "community"
    ],
    "wof:name":"Action For A Better Community",
    "wof:placetype":"venue"
},
  "geometry": {"coordinates":[-77.57232399999999,43.152148],"type":"Point"}
}