{
  "type": "Feature",
  "properties": {
    "iso:country":"US",
    "sg:address":"609 Main St",
    "sg:city":"Catskill",
    "sg:classifiers":[
        {
            "category":"Bars & Pubs",
            "type":"Food & Drink"
        }
    ],
    "sg:phone":"+1   ",
    "sg:postcode":"12414",
    "sg:province":"NY",
    "sg:tags":[
        "bar"
    ],
    "wof:name":"Jimmys Bar & Grill",
    "wof:placetype":"venue"
},
  "geometry": {"coordinates":[-73.87166000000001,42.227092],"type":"Point"}
}