{
  "type": "Feature",
  "properties": {
    "addr:full":"57 Kirkland Dr Greenlawn NY 11740",
    "addr:housenumber":"57",
    "addr:postcode":"11740",
    "addr:street":"Kirkland Dr",
    "iso:country":"US",
    "sg:address":"57 Kirkland Dr",
    "sg:city":"Greenlawn",
    "sg:classifiers":[
        {
            "category":"Professional",
            "subcategory":"Computer Services",
            "type":"Services"
        }
    ],
    "sg:phone":"+1   ",
    "sg:postcode":"11740",
    "sg:province":"NY",
    "sg:tags":[
        "development",
        "software"
    ],
    "wof:name":"Soft Tech Inc",
    "wof:placetype":"venue"
},
  "geometry": {"coordinates":[-73.368583,40.857641],"type":"Point"}
}