{
  "type": "Feature",
  "properties": {
    "iso:country":"US",
    "sg:address":"104 S Broadway",
    "sg:city":"Yonkers",
    "sg:classifiers":[
        {
            "category":"Organizations",
            "subcategory":"Labor Organization",
            "type":"Services"
        }
    ],
    "sg:phone":"+1   ",
    "sg:postcode":"10701",
    "sg:province":"NY",
    "sg:tags":[
        "business"
    ],
    "wof:name":"Police Bnvlent Assn of Yonkers",
    "wof:placetype":"venue"
},
  "geometry": {"coordinates":[-73.896463,40.928923],"type":"Point"}
}