{
  "type": "Feature",
  "properties": {
    "iso:country":"US",
    "sg:address":"3207 34th Ave",
    "sg:city":"Long Island City",
    "sg:classifiers":[
        {
            "category":"Restaurant",
            "type":"Food & Drink"
        }
    ],
    "sg:phone":"+1 718 626 2000",
    "sg:postcode":"11106",
    "sg:province":"NY",
    "sg:tags":[
        "greek",
        "mediterranean"
    ],
    "sg:website":"orderphiloxeniaqueens.com",
    "wof:name":"Philoxenia",
    "wof:placetype":"venue"
},
  "geometry": {"coordinates":[-73.925995,40.759331],"type":"Point"}
}