{
  "type": "Feature",
  "properties": {
    "addr:full":"41 Beverwyck Ln Ste 1 Slingerlands NY 12159",
    "addr:housenumber":"41",
    "addr:postcode":"12159",
    "addr:street":"Beverwyck Ln Ste 1",
    "iso:country":"US",
    "sg:address":"41 Beverwyck Ln Ste 1",
    "sg:city":"Slingerlands",
    "sg:classifiers":[
        {
            "category":"Building & Trades",
            "subcategory":"Landscaping Services",
            "type":"Services"
        }
    ],
    "sg:phone":"+1 518 459 4062",
    "sg:postcode":"12159",
    "sg:province":"NY",
    "sg:tags":[
        "aged",
        "homes-institutional"
    ],
    "wof:name":"Terrace At Beverwyck",
    "wof:placetype":"venue"
},
  "geometry": {"coordinates":[-73.836511,42.658734],"type":"Point"}
}