{
  "type": "Feature",
  "properties": {
    "iso:country":"US",
    "sg:address":"187 Saint Nicholas Avenue",
    "sg:city":"Brooklyn",
    "sg:classifiers":[
        {
            "category":"Health Services",
            "subcategory":"Dentist",
            "type":"Services"
        }
    ],
    "sg:phone":"+1 718 497 4080",
    "sg:postcode":"11237",
    "sg:province":"NY",
    "wof:name":"Alexsandr Grigoryan DDS",
    "wof:placetype":"venue"
},
  "geometry": {"coordinates":[-73.91550700000001,40.704031],"type":"Point"}
}