{
  "type": "Feature",
  "properties": {
    "iso:country":"US",
    "sg:address":"1705 Carroll St",
    "sg:city":"Brooklyn",
    "sg:classifiers":[
        {
            "category":"Organizations",
            "subcategory":"Religious Organization",
            "type":"Services"
        }
    ],
    "sg:phone":"+1 718 774 3501",
    "sg:postcode":"11213",
    "sg:province":"NY",
    "sg:tags":[
        "church"
    ],
    "wof:name":"Church Grace Assembly Of God",
    "wof:placetype":"venue"
},
  "geometry": {"coordinates":[-73.930612,40.666179],"type":"Point"}
}