{
  "type": "Feature",
  "properties": {
    "addr:full":"3638 35th St Astoria NY 11106",
    "addr:housenumber":"3638",
    "addr:postcode":"11106",
    "addr:street":"35Th St",
    "iso:country":"US",
    "sg:address":"3638 35th St",
    "sg:city":"Astoria",
    "sg:classifiers":[
        {
            "category":"Building & Trades",
            "subcategory":"Electrical",
            "type":"Services"
        }
    ],
    "sg:phone":"+1 718 784 7525",
    "sg:postcode":"11106",
    "sg:province":"NY",
    "sg:tags":[
        "electrician"
    ],
    "wof:name":"Blasko Electrical Contractors",
    "wof:placetype":"venue"
},
  "geometry": {"coordinates":[-73.92739899999999,40.7542],"type":"Point"}
}