{
  "type": "Feature",
  "properties": {
    "addr:full":"56 Yankee Folly Rd New Paltz NY 12561",
    "addr:housenumber":"56",
    "addr:postcode":"12561",
    "addr:street":"Yankee Folly Rd",
    "iso:country":"US",
    "sg:address":"56 Yankee Folly Rd",
    "sg:city":"New Paltz",
    "sg:classifiers":[
        {
            "category":"Building & Trades",
            "subcategory":"Construction",
            "type":"Services"
        }
    ],
    "sg:phone":"+1 845 255 8813",
    "sg:postcode":"12561",
    "sg:province":"NY",
    "sg:tags":[
        "house"
    ],
    "wof:name":"Hudson Valley Building Co",
    "wof:placetype":"venue"
},
  "geometry": {"coordinates":[-74.15192399999999,41.728502],"type":"Point"}
}