{
  "type": "Feature",
  "properties": {
    "iso:country":"US",
    "sg:address":"346 Sawkill Rd",
    "sg:city":"Kingston",
    "sg:classifiers":[
        {
            "category":"Real Estate",
            "subcategory":"Real Estate Operator",
            "type":"Services"
        }
    ],
    "sg:phone":"+1 845 331 2625",
    "sg:postcode":"12401",
    "sg:province":"NY",
    "sg:tags":[
        "field",
        "farm",
        "site",
        "crop",
        "mobile",
        "home"
    ],
    "wof:name":"Boices Mobile Home Estates",
    "wof:placetype":"venue"
},
  "geometry": {"coordinates":[-74.01542999999999,41.966401],"type":"Point"}
}