{
  "type": "Feature",
  "properties": {
    "addr:full":"5101 Avenue M Brooklyn NY 11234",
    "addr:housenumber":"5101",
    "addr:postcode":"11234",
    "addr:street":"Avenue M",
    "iso:country":"US",
    "sg:address":"5101 Avenue M",
    "sg:city":"Brooklyn",
    "sg:classifiers":[
        {
            "category":"Education",
            "subcategory":"School",
            "type":"Public Place"
        }
    ],
    "sg:phone":"+1 718 241 8488",
    "sg:postcode":"11234",
    "sg:province":"NY",
    "sg:tags":[
        "high",
        "middle",
        "elementary"
    ],
    "wof:name":"New York City Community School District 22 Region 6",
    "wof:placetype":"venue"
},
  "geometry": {"coordinates":[-73.92614,40.621413],"type":"Point"}
}