{
  "type": "Feature",
  "properties": {
    "iso:country":"US",
    "sg:address":"217 E 85th St",
    "sg:city":"New York",
    "sg:classifiers":[
        {
            "category":"Professional",
            "subcategory":"Computer Services",
            "type":"Services"
        }
    ],
    "sg:phone":"+1   ",
    "sg:postcode":"10028",
    "sg:province":"NY",
    "sg:tags":[
        "prepackaged",
        "book",
        "software"
    ],
    "wof:name":"Radius Press",
    "wof:placetype":"venue"
},
  "geometry": {"coordinates":[-73.95248100000001,40.777414],"type":"Point"}
}