{
  "type": "Feature",
  "properties": {
    "addr:full":"1726 Hertel Ave Buffalo NY 14216",
    "addr:housenumber":"1726",
    "addr:postcode":"14216",
    "addr:street":"Hertel Ave",
    "iso:country":"US",
    "sg:address":"1726 Hertel Ave",
    "sg:city":"Buffalo",
    "sg:classifiers":[
        {
            "category":"Banks & Credit Unions",
            "subcategory":"Bank",
            "type":"Services"
        }
    ],
    "sg:phone":"+1 716 837 1358",
    "sg:postcode":"14216",
    "sg:province":"NY",
    "wof:name":"HSBC Bank USA N.A.",
    "wof:placetype":"venue"
},
  "geometry": {"coordinates":[-78.84408000000001,42.947758],"type":"Point"}
}