{
  "type": "Feature",
  "properties": {
    "iso:country":"US",
    "sg:address":"57 W 57 St",
    "sg:city":"New York",
    "sg:classifiers":[
        {
            "category":"Health Services",
            "subcategory":"Doctor",
            "type":"Services"
        }
    ],
    "sg:phone":"+1 212 593 1499",
    "sg:postcode":"10019",
    "sg:province":"NY",
    "sg:tags":[
        "dentist"
    ],
    "wof:name":"Marvin M Grossman DDS",
    "wof:placetype":"venue"
},
  "geometry": {"coordinates":[-73.975762,40.763613],"type":"Point"}
}