{
  "type": "Feature",
  "properties": {
    "addr:full":"129 Hooper St Brooklyn NY 11211",
    "addr:housenumber":"129",
    "addr:postcode":"11211",
    "addr:street":"Hooper St",
    "iso:country":"US",
    "sg:address":"129 Hooper St",
    "sg:city":"Brooklyn",
    "sg:classifiers":[
        {
            "category":"Organizations",
            "subcategory":"Religious Organization",
            "type":"Services"
        }
    ],
    "sg:phone":"+1 718 384 7071",
    "sg:postcode":"11211",
    "sg:province":"NY",
    "wof:name":"Kahan Jenoe",
    "wof:placetype":"venue"
},
  "geometry": {"coordinates":[-73.958647,40.703979],"type":"Point"}
}