{
  "type": "Feature",
  "properties": {
    "addr:full":"472 6th Ave New York NY 10011",
    "addr:housenumber":"472",
    "addr:postcode":"10011",
    "addr:street":"6Th Ave",
    "iso:country":"US",
    "sg:address":"472 6th Ave",
    "sg:city":"New York",
    "sg:classifiers":[
        {
            "category":"Personal",
            "subcategory":"Day Spa",
            "type":"Services"
        },
        {
            "category":"Personal",
            "subcategory":"Skin Care",
            "type":"Services"
        },
        {
            "category":"Personal",
            "subcategory":"Nail Salon",
            "type":"Services"
        }
    ],
    "sg:phone":"+1 212 463 0246",
    "sg:postcode":"10011",
    "sg:province":"NY",
    "sg:website":"www.beautyandyouthshop.com",
    "wof:name":"Beauty & Youth Spa",
    "wof:placetype":"venue"
},
  "geometry": {"coordinates":[-73.997985,40.735741],"type":"Point"}
}