{
  "type": "Feature",
  "properties": {
    "addr:full":"3661 Horseblock Rd N Medford NY 11763",
    "addr:housenumber":"3661",
    "addr:postcode":"11763",
    "addr:street":"Horseblock Rd N",
    "iso:country":"US",
    "sg:address":"3661 Horseblock Rd N",
    "sg:city":"Medford",
    "sg:classifiers":[
        {
            "category":"Home & Garden",
            "subcategory":"Furniture",
            "type":"Retail Goods"
        }
    ],
    "sg:phone":"+1 631 345 0230",
    "sg:postcode":"11763",
    "sg:province":"NY",
    "sg:tags":[
        "mfg",
        "household",
        "contractor",
        "wood",
        "cabinet",
        "carpentry"
    ],
    "wof:name":"U S A Custom Mica",
    "wof:placetype":"venue"
},
  "geometry": {"coordinates":[-72.954903,40.813274],"type":"Point"}
}