{
  "type": "Feature",
  "properties": {
    "iso:country":"US",
    "sg:address":"254 Lafayette Blvd",
    "sg:city":"Long Beach",
    "sg:classifiers":[
        {
            "category":"Professional",
            "subcategory":"Detective & Security Services",
            "type":"Services"
        }
    ],
    "sg:phone":"+1 516 897 9727",
    "sg:postcode":"11561",
    "sg:province":"NY",
    "sg:tags":[
        "guard",
        "patrol"
    ],
    "wof:name":"Lyons Professional Svc Inc",
    "wof:placetype":"venue"
},
  "geometry": {"coordinates":[-73.675449,40.587483],"type":"Point"}
}