{
  "type": "Feature",
  "properties": {
    "iso:country":"US",
    "sg:address":"45 Boices Ln",
    "sg:city":"Kingston",
    "sg:classifiers":[
        {
            "category":"Food & Beverages",
            "subcategory":"Groceries & Convenience Stores",
            "type":"Retail Goods"
        }
    ],
    "sg:phone":"+1 845 383 0273",
    "sg:postcode":"12401",
    "sg:province":"NY",
    "sg:website":"www.stewartsicecream.com",
    "wof:name":"Stewart's Shop",
    "wof:placetype":"venue"
},
  "geometry": {"coordinates":[-73.991445,41.963296],"type":"Point"}
}