{
  "type": "Feature",
  "properties": {
    "addr:full":"522 W 24th Street New York NY 10011",
    "addr:housenumber":"522",
    "addr:postcode":"10011",
    "addr:street":"W 24Th Street",
    "iso:country":"US",
    "sg:address":"522 W 24th Street",
    "sg:city":"New York",
    "sg:classifiers":[
        {
            "category":"Arts & Performance",
            "subcategory":"Art Gallery",
            "type":"Entertainment"
        }
    ],
    "sg:phone":"+1 212 242 4514",
    "sg:postcode":"10011",
    "sg:province":"NY",
    "wof:name":"Baumgartner Verdross Gallery",
    "wof:placetype":"venue"
},
  "geometry": {"coordinates":[-74.005227,40.749126],"type":"Point"}
}