{
  "type": "Feature",
  "properties": {
    "addr:full":"1520 Metropolitan Ave Bronx NY 10462",
    "addr:housenumber":"1520",
    "addr:postcode":"10462",
    "addr:street":"Metropolitan Ave",
    "iso:country":"US",
    "sg:address":"1520 Metropolitan Ave",
    "sg:city":"Bronx",
    "sg:classifiers":[
        {
            "category":"Retail",
            "subcategory":"Repair Shop",
            "type":"Services"
        }
    ],
    "sg:phone":"+1 347 293 0046",
    "sg:postcode":"10462",
    "sg:province":"NY",
    "sg:tags":[
        "lock",
        "locksmith"
    ],
    "wof:name":"1 Hour Emergency Locksmith",
    "wof:placetype":"venue"
},
  "geometry": {"coordinates":[-73.858957,40.839149],"type":"Point"}
}