{
  "type": "Feature",
  "properties": {
    "addr:full":"21017 State Hwy 12F Watertown NY 13601",
    "addr:housenumber":"21017",
    "addr:postcode":"13601",
    "addr:street":"State Hwy 12F",
    "iso:country":"US",
    "sg:address":"21017 State Hwy 12F",
    "sg:city":"Watertown",
    "sg:classifiers":[
        {
            "category":"Health Services",
            "subcategory":"Doctor",
            "type":"Services"
        }
    ],
    "sg:phone":"+1 315 786 3436",
    "sg:postcode":"13601",
    "sg:province":"NY",
    "sg:tags":[
        "physician",
        "surgeon"
    ],
    "wof:name":"Urgent Care North Country",
    "wof:placetype":"venue"
},
  "geometry": {"coordinates":[-75.951942,43.990768],"type":"Point"}
}