{
  "type": "Feature",
  "properties": {
    "iso:country":"US",
    "sg:address":"73 Beverly Rd",
    "sg:city":"Massapequa",
    "sg:classifiers":[
        {
            "category":"Building & Trades",
            "subcategory":"Construction",
            "type":"Services"
        }
    ],
    "sg:phone":"+1 516 318 6198",
    "sg:postcode":"11758",
    "sg:province":"NY",
    "sg:tags":[
        "roofing",
        "industrial",
        "contractors-commercial",
        "contractor"
    ],
    "wof:name":"S S Roofing",
    "wof:placetype":"venue"
},
  "geometry": {"coordinates":[-73.465729,40.65649],"type":"Point"}
}