{
  "type": "Feature",
  "properties": {
    "iso:country":"US",
    "sg:address":"130 Madison Ave",
    "sg:city":"New York",
    "sg:classifiers":[
        {
            "category":"Home & Garden",
            "subcategory":"Furniture",
            "type":"Retail Goods"
        }
    ],
    "sg:phone":"+1 212 686 0246",
    "sg:postcode":"10016",
    "sg:province":"NY",
    "sg:tags":[
        "equipment",
        "work",
        "custom",
        "kitchen",
        "cabinet"
    ],
    "wof:name":"Dura Maid Industries",
    "wof:placetype":"venue"
},
  "geometry": {"coordinates":[-73.984702,40.745368],"type":"Point"}
}