{
  "type": "Feature",
  "properties": {
    "iso:country":"US",
    "sg:address":"146 Orchard St",
    "sg:city":"New York",
    "sg:classifiers":[
        {
            "category":"Freight",
            "type":"Transportation"
        }
    ],
    "sg:phone":"+1 212 982 6403",
    "sg:postcode":"10002",
    "sg:province":"NY",
    "sg:tags":[
        "commercial",
        "storage"
    ],
    "wof:name":"Little Warehouse",
    "wof:placetype":"venue"
},
  "geometry": {"coordinates":[-73.988488,40.721345],"type":"Point"}
}