{
  "type": "Feature",
  "properties": {
    "iso:country":"US",
    "sg:address":"2565 Delaware Ave",
    "sg:city":"Buffalo",
    "sg:classifiers":[
        {
            "category":"Deli",
            "type":"Food & Drink"
        }
    ],
    "sg:menulink":"http://www.allmenus.com/ny/buffalo/245648-jims-steakout/menu/",
    "sg:phone":"+1 716 877 7500",
    "sg:postcode":"14216",
    "sg:province":"NY",
    "sg:tags":[
        "american"
    ],
    "wof:name":"Jim's Steakout",
    "wof:placetype":"venue"
},
  "geometry": {"coordinates":[-78.86903,42.953922],"type":"Point"}
}