{
  "type": "Feature",
  "properties": {
    "iso:country":"US",
    "sg:address":"27 High St",
    "sg:city":"Poughkeepsie",
    "sg:classifiers":[
        {
            "category":"Government",
            "subcategory":"Office",
            "type":"Public Place"
        }
    ],
    "sg:phone":"+1 845 486 3660",
    "sg:postcode":"12601",
    "sg:province":"NY",
    "wof:name":"Dutchess County Youth Bureau",
    "wof:placetype":"venue"
},
  "geometry": {"coordinates":[-73.923193,41.70891],"type":"Point"}
}