{
  "type": "Feature",
  "properties": {
    "iso:country":"US",
    "sg:address":"4 Nott Ter",
    "sg:city":"Schenectady",
    "sg:classifiers":[
        {
            "category":"Wholesale",
            "subcategory":"Computers",
            "type":"Manufacturing & Wholesale Goods"
        }
    ],
    "sg:phone":"+1 518 382 9352",
    "sg:postcode":"12308",
    "sg:province":"NY",
    "sg:tags":[
        "information",
        "retrieval"
    ],
    "wof:name":"Meenan Information Svc",
    "wof:placetype":"venue"
},
  "geometry": {"coordinates":[-73.93361299999999,42.814066],"type":"Point"}
}