{
  "type": "Feature",
  "properties": {
    "addr:full":"17 Battery Pl New York NY 10004",
    "addr:housenumber":"17",
    "addr:postcode":"10004",
    "addr:street":"Battery Pl",
    "iso:country":"US",
    "sg:address":"17 Battery Pl",
    "sg:city":"New York",
    "sg:classifiers":[
        {
            "category":"Professional",
            "subcategory":"Business Services",
            "type":"Services"
        }
    ],
    "sg:phone":"+1 212 809 3131",
    "sg:postcode":"10004",
    "sg:province":"NY",
    "sg:tags":[
        "advertising",
        "promotional"
    ],
    "wof:name":"Renaissance Pharmaceuticals",
    "wof:placetype":"venue"
},
  "geometry": {"coordinates":[-74.01565600000001,40.704952],"type":"Point"}
}