{
  "type": "Feature",
  "properties": {
    "addr:full":"16 Court St Brooklyn NY 11241",
    "addr:housenumber":"16",
    "addr:postcode":"11241",
    "addr:street":"Court St",
    "iso:country":"US",
    "sg:address":"16 Court St",
    "sg:city":"Brooklyn",
    "sg:classifiers":[
        {
            "category":"Professional",
            "subcategory":"Lawyer & Legal Services",
            "type":"Services"
        }
    ],
    "sg:phone":"+1 718 237 1900",
    "sg:postcode":"11241",
    "sg:province":"NY",
    "wof:name":"Flamhaft Stephen Atty",
    "wof:placetype":"venue"
},
  "geometry": {"coordinates":[-73.9907,40.693298],"type":"Point"}
}