{
  "type": "Feature",
  "properties": {
    "addr:full":"1814 Hylan Blvd Staten Island NY 10305",
    "addr:housenumber":"1814",
    "addr:postcode":"10305",
    "addr:street":"Hylan Blvd",
    "iso:country":"US",
    "sg:address":"1814 Hylan Blvd",
    "sg:city":"Staten Island",
    "sg:classifiers":[
        {
            "category":"Personal",
            "subcategory":"Tanning Parlor",
            "type":"Services"
        }
    ],
    "sg:phone":"+1 718 979 5050",
    "sg:postcode":"10305",
    "sg:province":"NY",
    "wof:name":"Tanning Loft of Dongan Hills",
    "wof:placetype":"venue"
},
  "geometry": {"coordinates":[-74.094002,40.5849],"type":"Point"}
}