{
  "type": "Feature",
  "properties": {
    "addr:full":"202 Columbus Ave New York NY 10023",
    "addr:housenumber":"202",
    "addr:postcode":"10023",
    "addr:street":"Columbus Ave",
    "iso:country":"US",
    "sg:address":"202 Columbus Ave",
    "sg:city":"New York",
    "sg:classifiers":[
        {
            "category":"Restaurant",
            "type":"Food & Drink"
        }
    ],
    "sg:phone":"+1 212 799 9188",
    "sg:postcode":"10023",
    "sg:province":"NY",
    "wof:name":"Lenge Japanese Restrnt",
    "wof:placetype":"venue"
},
  "geometry": {"coordinates":[-73.979854,40.776064],"type":"Point"}
}