{
  "type": "Feature",
  "properties": {
    "iso:country":"US",
    "sg:address":"111 Hunter Ave",
    "sg:city":"Albany",
    "sg:classifiers":[
        {
            "category":"Building & Trades",
            "subcategory":"Plumbing",
            "type":"Services"
        }
    ],
    "sg:phone":"+1 518 489 0008",
    "sg:postcode":"12206",
    "sg:province":"NY",
    "sg:tags":[
        "contractor"
    ],
    "wof:name":"SPUD Plumbing & Heating",
    "wof:placetype":"venue"
},
  "geometry": {"coordinates":[-73.782076,42.674408],"type":"Point"}
}