{
  "type": "Feature",
  "properties": {
    "addr:full":"34 S Broadway White Plains NY 10601",
    "addr:housenumber":"34",
    "addr:postcode":"10601",
    "addr:street":"S Broadway",
    "iso:country":"US",
    "sg:address":"34 S Broadway",
    "sg:city":"White Plains",
    "sg:classifiers":[
        {
            "category":"Bars & Pubs",
            "type":"Food & Drink"
        }
    ],
    "sg:phone":"+1   ",
    "sg:postcode":"10601",
    "sg:province":"NY",
    "sg:tags":[
        "club"
    ],
    "wof:name":"Club OHM",
    "wof:placetype":"venue"
},
  "geometry": {"coordinates":[-73.762461,41.030466],"type":"Point"}
}