{
  "type": "Feature",
  "properties": {
    "iso:country":"US",
    "sg:address":"3856 Root Rd",
    "sg:city":"Gasport",
    "sg:classifiers":[
        {
            "category":"Utilities",
            "subcategory":"Refuse",
            "type":"Services"
        }
    ],
    "sg:phone":"+1   ",
    "sg:postcode":"14067",
    "sg:province":"NY",
    "sg:tags":[
        "system"
    ],
    "wof:name":"Dals Sanitation Svce",
    "wof:placetype":"venue"
},
  "geometry": {"coordinates":[-78.54178899999999,43.239899],"type":"Point"}
}