{
  "type": "Feature",
  "properties": {
    "addr:full":"42 Wooster St New York NY 10013",
    "addr:housenumber":"42",
    "addr:postcode":"10013",
    "addr:street":"Wooster St",
    "iso:country":"US",
    "sg:address":"42 Wooster St",
    "sg:city":"New York",
    "sg:classifiers":[
        {
            "category":"Personal",
            "subcategory":"Beauty Salon",
            "type":"Services"
        }
    ],
    "sg:phone":"+1 212 334 3777",
    "sg:postcode":"10013",
    "sg:province":"NY",
    "sg:tags":[
        "hair"
    ],
    "sg:website":"www.sambrocatosalon.com",
    "wof:name":"Sam Brocato Salon",
    "wof:placetype":"venue"
},
  "geometry": {"coordinates":[-74.002611,40.722378],"type":"Point"}
}