{
  "type": "Feature",
  "properties": {
    "addr:full":"45 Turner Dr Chappaqua NY 10514",
    "addr:housenumber":"45",
    "addr:postcode":"10514",
    "addr:street":"Turner Dr",
    "iso:country":"US",
    "sg:address":"45 Turner Dr",
    "sg:city":"Chappaqua",
    "sg:classifiers":[
        {
            "category":"Professional",
            "type":"Services"
        }
    ],
    "sg:phone":"+1 914 666 6266",
    "sg:postcode":"10514",
    "sg:province":"NY",
    "sg:tags":[
        "establishment"
    ],
    "wof:name":"Dr Jeffrey Donis",
    "wof:placetype":"venue"
},
  "geometry": {"coordinates":[-73.772413,41.197865],"type":"Point"}
}