{
  "type": "Feature",
  "properties": {
    "addr:full":"391 W 1st St Oswego NY 13126",
    "addr:housenumber":"391",
    "addr:postcode":"13126",
    "addr:street":"W 1St St",
    "iso:country":"US",
    "sg:address":"391 W 1st St",
    "sg:city":"Oswego",
    "sg:classifiers":[
        {
            "category":"Government",
            "subcategory":"Post Office",
            "type":"Public Place"
        }
    ],
    "sg:phone":"+1   ",
    "sg:postcode":"13126",
    "sg:province":"NY",
    "sg:tags":[
        "postal",
        "us"
    ],
    "wof:name":"US Post Office",
    "wof:placetype":"venue"
},
  "geometry": {"coordinates":[-76.506208,43.44866],"type":"Point"}
}