{
  "type": "Feature",
  "properties": {
    "iso:country":"US",
    "sg:address":"8314 Anglers Clb",
    "sg:city":"Cicero",
    "sg:classifiers":[
        {
            "category":"Professional",
            "subcategory":"Business Services",
            "type":"Services"
        }
    ],
    "sg:phone":"+1 315 569 5616",
    "sg:postcode":"13039",
    "sg:province":"NY",
    "sg:tags":[
        "consultant",
        "coach"
    ],
    "wof:name":"Jennifer Dietter",
    "wof:placetype":"venue"
},
  "geometry": {"coordinates":[-76.082162,43.170723],"type":"Point"}
}