{
  "type": "Feature",
  "properties": {
    "addr:full":"36 W Main St Sodus NY 14551",
    "addr:housenumber":"36",
    "addr:postcode":"14551",
    "addr:street":"W Main St",
    "iso:country":"US",
    "sg:address":"36 W Main St",
    "sg:city":"Sodus",
    "sg:classifiers":[
        {
            "category":"Shopping",
            "subcategory":"Discount & Variety Stores",
            "type":"Retail Goods"
        }
    ],
    "sg:phone":"+1   ",
    "sg:postcode":"14551",
    "sg:province":"NY",
    "wof:name":"Family Dollar Stores",
    "wof:placetype":"venue"
},
  "geometry": {"coordinates":[-77.063666,43.23617],"type":"Point"}
}