{
  "type": "Feature",
  "properties": {
    "iso:country":"US",
    "sg:address":"2688 Hamburg St",
    "sg:city":"Schenectady",
    "sg:classifiers":[
        {
            "category":"Restaurant",
            "type":"Food & Drink"
        }
    ],
    "sg:phone":"+1 518 355 9522",
    "sg:postcode":"12303",
    "sg:province":"NY",
    "wof:name":"Redwood Diner",
    "wof:placetype":"venue"
},
  "geometry": {"coordinates":[-73.934291,42.775717],"type":"Point"}
}