{
  "type": "Feature",
  "properties": {
    "addr:full":"2550 Troy Schenectady Rd Schenectady NY 12309",
    "addr:housenumber":"2550",
    "addr:postcode":"12309",
    "addr:street":"Troy Schenectady Rd",
    "iso:country":"US",
    "sg:address":"2550 Troy Schenectady Rd",
    "sg:city":"Schenectady",
    "sg:classifiers":[
        {
            "category":"Building & Trades",
            "subcategory":"Plumbing",
            "type":"Services"
        }
    ],
    "sg:phone":"+1 518 377 4950",
    "sg:postcode":"12309",
    "sg:province":"NY",
    "sg:tags":[
        "plumbing",
        "heating",
        "contractor"
    ],
    "wof:name":"A P Nitchman Plumbing & Htg",
    "wof:placetype":"venue"
},
  "geometry": {"coordinates":[-73.863209,42.785181],"type":"Point"}
}