{
  "type": "Feature",
  "properties": {
    "addr:full":"53 Woodhaven Blvd Ozone Park NY 11416",
    "addr:housenumber":"53",
    "addr:postcode":"11416",
    "addr:street":"Woodhaven Blvd",
    "iso:country":"US",
    "sg:address":"53 Woodhaven Blvd",
    "sg:city":"Ozone Park",
    "sg:classifiers":[
        {
            "category":"Shopping",
            "subcategory":"Clothing, Apparel, & Fashions",
            "type":"Retail Goods"
        }
    ],
    "sg:phone":"+1   ",
    "sg:postcode":"11416",
    "sg:province":"NY",
    "sg:tags":[
        "jean",
        "footwear"
    ],
    "wof:name":"City Jeans Inc",
    "wof:placetype":"venue"
},
  "geometry": {"coordinates":[-73.84751,40.687178],"type":"Point"}
}