{
  "type": "Feature",
  "properties": {
    "iso:country":"US",
    "sg:address":"121 Wooster St",
    "sg:city":"New York",
    "sg:classifiers":[
        {
            "category":"Home & Garden",
            "subcategory":"Furniture",
            "type":"Retail Goods"
        }
    ],
    "sg:phone":"+1 212 219 1110",
    "sg:postcode":"10012",
    "sg:province":"NY",
    "wof:name":"Atmosphere Home",
    "wof:placetype":"venue"
},
  "geometry": {"coordinates":[-74.00076900000001,40.724476],"type":"Point"}
}