{
  "type": "Feature",
  "properties": {
    "iso:country":"US",
    "sg:address":"644 Flatbush Ave",
    "sg:city":"Brooklyn",
    "sg:classifiers":[
        {
            "category":"Restaurant",
            "type":"Food & Drink"
        }
    ],
    "sg:menulink":"http://www.allmenus.com/ny/brooklyn/22614-china-city/menu/",
    "sg:phone":"+1 718 282 8890",
    "sg:postcode":"11225",
    "sg:province":"NY",
    "sg:tags":[
        "asian",
        "chinese"
    ],
    "wof:name":"China City",
    "wof:placetype":"venue"
},
  "geometry": {"coordinates":[-73.96033300000001,40.657625],"type":"Point"}
}