{
  "type": "Feature",
  "properties": {
    "iso:country":"US",
    "sg:address":"1100 Old Nichols Rd",
    "sg:city":"Islandia",
    "sg:classifiers":[
        {
            "category":"Government",
            "subcategory":"Office",
            "type":"Public Place"
        }
    ],
    "sg:phone":"+1 631 348 1133",
    "sg:postcode":"11749",
    "sg:province":"NY",
    "sg:tags":[
        "village"
    ],
    "wof:name":"Islandia Village General Info",
    "wof:placetype":"venue"
},
  "geometry": {"coordinates":[-73.16293,40.806174],"type":"Point"}
}