{
  "type": "Feature",
  "properties": {
    "addr:full":"775 Columbus Ave Manhattan NY 10025",
    "addr:housenumber":"775",
    "addr:postcode":"10025",
    "addr:street":"Columbus Ave",
    "iso:country":"US",
    "sg:address":"775 Columbus Ave",
    "sg:city":"Manhattan",
    "sg:classifiers":[
        {
            "category":"Banks & Credit Unions",
            "subcategory":"Bank",
            "type":"Services"
        }
    ],
    "sg:phone":"+1 212 222 5091",
    "sg:postcode":"10025",
    "sg:province":"NY",
    "sg:website":"www.chase.com",
    "wof:name":"Chase Bank - Columbus and 97th",
    "wof:placetype":"venue"
},
  "geometry": {"coordinates":[-73.96646800000001,40.794275],"type":"Point"}
}