{
  "type": "Feature",
  "properties": {
    "addr:full":"3101 S Salina St Syracuse NY 13205",
    "addr:housenumber":"3101",
    "addr:postcode":"13205",
    "addr:street":"S Salina St",
    "iso:country":"US",
    "sg:address":"3101 S Salina St",
    "sg:city":"Syracuse",
    "sg:classifiers":[
        {
            "category":"Banks & Credit Unions",
            "subcategory":"Investment Brokerage",
            "type":"Services"
        }
    ],
    "sg:phone":"+1 315 422 2208",
    "sg:postcode":"13205",
    "sg:province":"NY",
    "sg:tags":[
        "advisory"
    ],
    "wof:name":"Canery Real Estate And Capital Inc.",
    "wof:placetype":"venue"
},
  "geometry": {"coordinates":[-76.141777,43.018051],"type":"Point"}
}