{
  "type": "Feature",
  "properties": {
    "addr:full":"667 Main St East Aurora NY 14052",
    "addr:housenumber":"667",
    "addr:postcode":"14052",
    "addr:street":"Main St",
    "iso:country":"US",
    "sg:address":"667 Main St",
    "sg:city":"East Aurora",
    "sg:classifiers":[
        {
            "category":"Shopping",
            "subcategory":"Gifts & Souvenirs",
            "type":"Retail Goods"
        }
    ],
    "sg:phone":"+1   ",
    "sg:postcode":"14052",
    "sg:province":"NY",
    "wof:name":"Cozy Gifts & Crafts Inc",
    "wof:placetype":"venue"
},
  "geometry": {"coordinates":[-78.610805,42.767807],"type":"Point"}
}