{
  "type": "Feature",
  "properties": {
    "addr:full":"21 Birch Ln Glenville NY 12302",
    "addr:housenumber":"21",
    "addr:postcode":"12302",
    "addr:street":"Birch Ln",
    "iso:country":"US",
    "sg:address":"21 Birch Ln",
    "sg:city":"Glenville",
    "sg:classifiers":[
        {
            "category":"Building & Trades",
            "subcategory":"Cleaning & Sanitation",
            "type":"Services"
        }
    ],
    "sg:phone":"+1 518 817 2948",
    "sg:postcode":"12302",
    "sg:province":"NY",
    "sg:tags":[
        "home"
    ],
    "wof:name":"Clean by Nature",
    "wof:placetype":"venue"
},
  "geometry": {"coordinates":[-73.920238,42.884877],"type":"Point"}
}