{
  "type": "Feature",
  "properties": {
    "addr:full":"210 E Seneca Tpke Syracuse NY 13205",
    "addr:housenumber":"210",
    "addr:postcode":"13205",
    "addr:street":"E Seneca Tpke",
    "iso:country":"US",
    "sg:address":"210 E Seneca Tpke",
    "sg:city":"Syracuse",
    "sg:classifiers":[
        {
            "category":"Restaurant",
            "type":"Food & Drink"
        }
    ],
    "sg:phone":"+1 315 469 1234",
    "sg:postcode":"13205",
    "sg:province":"NY",
    "sg:tags":[
        "parlor",
        "ice",
        "cream"
    ],
    "wof:name":"Arctic Island Ice Cream",
    "wof:placetype":"venue"
},
  "geometry": {"coordinates":[-76.140123,43.000379],"type":"Point"}
}