{
  "type": "Feature",
  "properties": {
    "addr:full":"3089 Middle Rd Dunkirk NY 14048",
    "addr:housenumber":"3089",
    "addr:postcode":"14048",
    "addr:street":"Middle Rd",
    "iso:country":"US",
    "sg:address":"3089 Middle Rd",
    "sg:city":"Dunkirk",
    "sg:classifiers":[
        {
            "category":"Farming",
            "subcategory":"Vineyard",
            "type":"Manufacturing & Wholesale Goods"
        }
    ],
    "sg:phone":"+1 716 366 0302",
    "sg:postcode":"14048",
    "sg:province":"NY",
    "sg:tags":[
        "grape"
    ],
    "wof:name":"Alvin Martin",
    "wof:placetype":"venue"
},
  "geometry": {"coordinates":[-79.266932,42.502184],"type":"Point"}
}