{
  "type": "Feature",
  "properties": {
    "addr:full":"1 Lincklaen St Cazenovia NY 13035",
    "addr:housenumber":"1",
    "addr:postcode":"13035",
    "addr:street":"Lincklaen St",
    "iso:country":"US",
    "sg:address":"1 Lincklaen St",
    "sg:city":"Cazenovia",
    "sg:classifiers":[
        {
            "category":"Travel",
            "subcategory":"Travel Agent",
            "type":"Entertainment"
        }
    ],
    "sg:phone":"+1 315 655 8790",
    "sg:postcode":"13035",
    "sg:province":"NY",
    "sg:tags":[
        "agency",
        "bureau"
    ],
    "wof:name":"L B Herzig",
    "wof:placetype":"venue"
},
  "geometry": {"coordinates":[-75.853171,42.93105],"type":"Point"}
}