{
  "type": "Feature",
  "properties": {
    "addr:full":"621 Ave Z Brooklyn NY 11223",
    "addr:housenumber":"621",
    "addr:postcode":"11223",
    "addr:street":"Ave Z",
    "iso:country":"US",
    "sg:address":"621 Ave Z",
    "sg:city":"Brooklyn",
    "sg:classifiers":[
        {
            "category":"Real Estate",
            "subcategory":"Real Estate Agent",
            "type":"Services"
        }
    ],
    "sg:phone":"+1 718 648 8714",
    "sg:postcode":"11223",
    "sg:province":"NY",
    "wof:name":"67 Gates St Realty Corp",
    "wof:placetype":"venue"
},
  "geometry": {"coordinates":[-73.97061600000001,40.58624],"type":"Point"}
}