{
  "type": "Feature",
  "properties": {
    "addr:full":"1229 Walt Whitman Rd Melville NY 11747",
    "addr:housenumber":"1229",
    "addr:postcode":"11747",
    "addr:street":"Walt Whitman Rd",
    "iso:country":"US",
    "sg:address":"1229 Walt Whitman Rd",
    "sg:city":"Melville",
    "sg:classifiers":[
        {
            "category":"Autos & Motor Vehicles",
            "subcategory":"Auto Supplies",
            "type":"Retail Goods"
        }
    ],
    "sg:phone":"+1   ",
    "sg:postcode":"11747",
    "sg:province":"NY",
    "wof:name":"Noah Prfmce & Cstm ACC Inc",
    "wof:placetype":"venue"
},
  "geometry": {"coordinates":[-73.42229500000001,40.7844],"type":"Point"}
}