{
  "type": "Feature",
  "properties": {
    "iso:country":"US",
    "sg:address":"3901 State Hwy 281",
    "sg:city":"Cortland",
    "sg:classifiers":[
        {
            "category":"Arts & Performance",
            "subcategory":"Theater",
            "type":"Entertainment"
        }
    ],
    "sg:phone":"+1 607 753 3881",
    "sg:postcode":"13045",
    "sg:province":"NY",
    "wof:name":"Jill Reeners School Of Dance",
    "wof:placetype":"venue"
},
  "geometry": {"coordinates":[-76.205945,42.596115],"type":"Point"}
}