{
  "type": "Feature",
  "properties": {
    "iso:country":"US",
    "sg:address":"345 E 204th St",
    "sg:city":"Bronx",
    "sg:classifiers":[
        {
            "category":"Retail",
            "subcategory":"Self-service Laundry",
            "type":"Services"
        }
    ],
    "sg:phone":"+1 718 519 7400",
    "sg:postcode":"10467",
    "sg:province":"NY",
    "wof:name":"Clean Jeans Inc",
    "wof:placetype":"venue"
},
  "geometry": {"coordinates":[-73.87764900000001,40.872186],"type":"Point"}
}