{
  "type": "Feature",
  "properties": {
    "addr:full":"9 E 38th St Rm 4R New York NY 10016",
    "addr:housenumber":"9",
    "addr:postcode":"10016",
    "addr:street":"E 38Th St;4R",
    "iso:country":"US",
    "sg:address":"9 E 38th St Rm 4R",
    "sg:city":"New York",
    "sg:classifiers":[
        {
            "category":"Communications",
            "subcategory":"Newspaper",
            "type":"Services"
        }
    ],
    "sg:phone":"+1 914 428 8196",
    "sg:postcode":"10016",
    "sg:province":"NY",
    "sg:tags":[
        "print",
        "medium"
    ],
    "wof:name":"Westchester Parent",
    "wof:placetype":"venue"
},
  "geometry": {"coordinates":[-73.981796,40.750599],"type":"Point"}
}