{
  "type": "Feature",
  "properties": {
    "addr:full":"551 3rd Ave New York NY 10016",
    "addr:housenumber":"551",
    "addr:postcode":"10016",
    "addr:street":"3Rd Ave",
    "iso:country":"US",
    "sg:address":"551 3rd Ave",
    "sg:city":"New York",
    "sg:classifiers":[
        {
            "category":"Restaurant",
            "type":"Food & Drink"
        }
    ],
    "sg:phone":"+1 212 685 0210",
    "sg:postcode":"10016",
    "sg:province":"NY",
    "wof:name":"Tasti D Lite",
    "wof:placetype":"venue"
},
  "geometry": {"coordinates":[-73.976997,40.747299],"type":"Point"}
}