{
  "type": "Feature",
  "properties": {
    "addr:full":"4 Byron Ln Clinton NY 13323",
    "addr:housenumber":"4",
    "addr:postcode":"13323",
    "addr:street":"Byron Ln",
    "iso:country":"US",
    "sg:address":"4 Byron Ln",
    "sg:city":"Clinton",
    "sg:classifiers":[
        {
            "category":"Banks & Credit Unions",
            "subcategory":"Investment Brokerage",
            "type":"Services"
        }
    ],
    "sg:phone":"+1 315 853 3189",
    "sg:postcode":"13323",
    "sg:province":"NY",
    "sg:tags":[
        "security"
    ],
    "wof:name":"R Bonsel Financial Svc",
    "wof:placetype":"venue"
},
  "geometry": {"coordinates":[-75.376092,43.07106],"type":"Point"}
}