{
  "type": "Feature",
  "properties": {
    "addr:full":"240 E 4th St New York NY 10009",
    "addr:housenumber":"240",
    "addr:postcode":"10009",
    "addr:street":"E 4Th St",
    "iso:country":"US",
    "sg:address":"240 E 4th St",
    "sg:city":"New York",
    "sg:classifiers":[
        {
            "category":"Restaurant",
            "type":"Food & Drink"
        }
    ],
    "sg:menulink":"http://www.allmenus.com/ny/new-york/2833-no-1-chinese/menu/",
    "sg:phone":"+1 212 375 0677",
    "sg:postcode":"10009",
    "sg:province":"NY",
    "sg:tags":[
        "asian",
        "chinese"
    ],
    "wof:name":"No. 1 Chinese",
    "wof:placetype":"venue"
},
  "geometry": {"coordinates":[-73.982786,40.723395],"type":"Point"}
}