{
  "type": "Feature",
  "properties": {
    "addr:full":"200 Highbridge St Fayetteville NY 13066",
    "addr:housenumber":"200",
    "addr:postcode":"13066",
    "addr:street":"Highbridge St",
    "iso:country":"US",
    "sg:address":"200 Highbridge St",
    "sg:city":"Fayetteville",
    "sg:classifiers":[
        {
            "category":"Shopping",
            "subcategory":"Shoes",
            "type":"Retail Goods"
        }
    ],
    "sg:phone":"+1   ",
    "sg:postcode":"13066",
    "sg:province":"NY",
    "sg:tags":[
        "athletic",
        "boot",
        "footwear"
    ],
    "wof:name":"Kangaroo Crossing",
    "wof:placetype":"venue"
},
  "geometry": {"coordinates":[-76.01461399999999,43.02618],"type":"Point"}
}