{
  "type": "Feature",
  "properties": {
    "addr:full":"502 Palomino Manor Elmira NY 14901",
    "addr:housenumber":"502",
    "addr:postcode":"14901",
    "addr:street":"Palomino Manor",
    "iso:country":"US",
    "sg:address":"502 Palomino Manor",
    "sg:city":"Elmira",
    "sg:classifiers":[
        {
            "category":"Wholesale",
            "subcategory":"Motor Vehicles",
            "type":"Manufacturing & Wholesale Goods"
        }
    ],
    "sg:phone":"+1 607 734 8830",
    "sg:postcode":"14901",
    "sg:province":"NY",
    "wof:name":"Fire Fleet Service",
    "wof:placetype":"venue"
},
  "geometry": {"coordinates":[-76.78164200000001,42.055245],"type":"Point"}
}