{
  "type": "Feature",
  "properties": {
    "addr:full":"75 Main St Dobbs Ferry NY 10522",
    "addr:housenumber":"75",
    "addr:postcode":"10522",
    "addr:street":"Main St",
    "iso:country":"US",
    "sg:address":"75 Main St",
    "sg:city":"Dobbs Ferry",
    "sg:classifiers":[
        {
            "category":"Education",
            "subcategory":"Special Training",
            "type":"Public Place"
        }
    ],
    "sg:phone":"+1 914 693 8100",
    "sg:postcode":"10522",
    "sg:province":"NY",
    "sg:tags":[
        "educational"
    ],
    "sg:website":"www.oceanaonline.com",
    "wof:name":"Oceana Publications Inc",
    "wof:placetype":"venue"
},
  "geometry": {"coordinates":[-73.87517699999999,41.014888],"type":"Point"}
}