{
  "type": "Feature",
  "properties": {
    "addr:full":"1928 US Hwy 20 Waterloo NY 13165",
    "addr:housenumber":"1928",
    "addr:postcode":"13165",
    "addr:street":"Us Hwy 20",
    "iso:country":"US",
    "sg:address":"1928 US Hwy 20",
    "sg:city":"Waterloo",
    "sg:classifiers":[
        {
            "category":"Restaurant",
            "type":"Food & Drink"
        }
    ],
    "sg:phone":"+1 315 539 9231",
    "sg:postcode":"13165",
    "sg:province":"NY",
    "sg:tags":[
        "eating"
    ],
    "sg:website":"www.pizzahut.com",
    "wof:name":"Pizza Hut",
    "wof:placetype":"venue"
},
  "geometry": {"coordinates":[-76.827634,42.904538],"type":"Point"}
}