{
  "type": "Feature",
  "properties": {
    "addr:full":"118 Bessal Rd Hurley NY 12443",
    "addr:housenumber":"118",
    "addr:postcode":"12443",
    "addr:street":"Bessal Rd",
    "iso:country":"US",
    "sg:address":"118 Bessal Rd",
    "sg:city":"Hurley",
    "sg:classifiers":[
        {
            "category":"Freight",
            "type":"Transportation"
        }
    ],
    "sg:phone":"+1   ",
    "sg:postcode":"12443",
    "sg:province":"NY",
    "sg:tags":[
        "operator",
        "local",
        "trucking"
    ],
    "wof:name":"Mrh Trucking LLC",
    "wof:placetype":"venue"
},
  "geometry": {"coordinates":[-74.08139,41.907278],"type":"Point"}
}