{
  "type": "Feature",
  "properties": {
    "addr:full":"2320 Milton Ave Ste 4 Syracuse NY 13209",
    "addr:housenumber":"2320",
    "addr:postcode":"13209",
    "addr:street":"Milton Ave Ste 4",
    "iso:country":"US",
    "sg:address":"2320 Milton Ave Ste 4",
    "sg:city":"Syracuse",
    "sg:classifiers":[
        {
            "category":"Wholesale",
            "subcategory":"Hardware",
            "type":"Manufacturing & Wholesale Goods"
        },
        {
            "category":"Home & Garden",
            "subcategory":"Hardware",
            "type":"Retail Goods"
        },
        {
            "category":"Home & Garden",
            "subcategory":"Building Materials",
            "type":"Retail Goods"
        },
        {
            "category":"Building & Trades",
            "subcategory":"Construction",
            "type":"Services"
        }
    ],
    "sg:phone":"+1 315 468 2260",
    "sg:postcode":"13209",
    "sg:province":"NY",
    "sg:tags":[
        "product",
        "energy",
        "contractor",
        "conservation",
        "hardware-builders",
        "insulation",
        "store"
    ],
    "sg:website":"http://www.generalinsulation.com",
    "wof:name":"General Insulation Company",
    "wof:placetype":"venue"
},
  "geometry": {"coordinates":[-76.219652,43.061904],"type":"Point"}
}