{
  "type": "Feature",
  "properties": {
    "addr:full":"362 E 155th St Bronx NY 10455",
    "addr:housenumber":"362",
    "addr:postcode":"10455",
    "addr:street":"E 155Th St",
    "iso:country":"US",
    "sg:address":"362 E 155th St",
    "sg:city":"Bronx",
    "sg:classifiers":[
        {
            "category":"Freight",
            "type":"Transportation"
        }
    ],
    "sg:phone":"+1 718 742 4750",
    "sg:postcode":"10455",
    "sg:province":"NY",
    "sg:tags":[
        "shipping",
        "agent"
    ],
    "wof:name":"Lantiguay Cargo Express",
    "wof:placetype":"venue"
},
  "geometry": {"coordinates":[-73.916122,40.820172],"type":"Point"}
}