{
  "type": "Feature",
  "properties": {
    "iso:country":"US",
    "sg:address":"5 Pleasant St",
    "sg:city":"New Rochelle",
    "sg:classifiers":[
        {
            "category":"Retail",
            "subcategory":"Auto Repair",
            "type":"Services"
        }
    ],
    "sg:phone":"+1 914 632 5555",
    "sg:postcode":"10801",
    "sg:province":"NY",
    "sg:tags":[
        "wrecker"
    ],
    "wof:name":"Safeway Towing & Haulage Inc",
    "wof:placetype":"venue"
},
  "geometry": {"coordinates":[-73.766976,40.929581],"type":"Point"}
}