{
  "type": "Feature",
  "properties": {
    "iso:country":"US",
    "sg:address":"2960 Decatur Ave",
    "sg:city":"Bronx",
    "sg:classifiers":[
        {
            "category":"Professional",
            "subcategory":"Computer Services",
            "type":"Services"
        }
    ],
    "sg:phone":"+1   ",
    "sg:postcode":"10458",
    "sg:province":"NY",
    "sg:tags":[
        "programing",
        "custom"
    ],
    "wof:name":"Antam Computer Center",
    "wof:placetype":"venue"
},
  "geometry": {"coordinates":[-73.882625,40.868855],"type":"Point"}
}