{
  "type": "Feature",
  "properties": {
    "addr:full":"4140 Broadway Island Park NY 11558",
    "addr:housenumber":"4140",
    "addr:postcode":"11558",
    "addr:street":"Broadway",
    "iso:country":"US",
    "sg:address":"4140 Broadway",
    "sg:city":"Island Park",
    "sg:classifiers":[
        {
            "category":"Government",
            "subcategory":"Office",
            "type":"Public Place"
        }
    ],
    "sg:phone":"+1 516 432 0909",
    "sg:postcode":"11558",
    "sg:province":"NY",
    "sg:tags":[
        "village"
    ],
    "wof:name":"Barnum Island Fire Dist",
    "wof:placetype":"venue"
},
  "geometry": {"coordinates":[-73.64649,40.607983],"type":"Point"}
}