{
  "type": "Feature",
  "properties": {
    "iso:country":"US",
    "sg:address":"100 Airport Executive Park",
    "sg:city":"Nanuet",
    "sg:classifiers":[
        {
            "category":"Professional",
            "subcategory":"Engineering",
            "type":"Services"
        }
    ],
    "sg:phone":"+1 845 371 2500",
    "sg:postcode":"10954",
    "sg:province":"NY",
    "sg:tags":[
        "engineer"
    ],
    "sg:website":"www.flaregas.com",
    "wof:name":"Flaregas",
    "wof:placetype":"venue"
},
  "geometry": {"coordinates":[-74.027039,41.10864],"type":"Point"}
}