{
  "type": "Feature",
  "properties": {
    "iso:country":"US",
    "sg:address":"12 New St",
    "sg:city":"Saint Johnsville",
    "sg:classifiers":[
        {
            "category":"Manufacturing",
            "subcategory":"Rubber & Plastics",
            "type":"Manufacturing & Wholesale Goods"
        }
    ],
    "sg:phone":"+1   ",
    "sg:postcode":"13452",
    "sg:province":"NY",
    "sg:tags":[
        "unsupported",
        "mfg"
    ],
    "wof:name":"Sentinel Products Corp",
    "wof:placetype":"venue"
},
  "geometry": {"coordinates":[-74.678129,42.99662],"type":"Point"}
}