{
  "type": "Feature",
  "properties": {
    "addr:full":"2011 Grand Concourse Bronx NY 10453",
    "addr:housenumber":"2011",
    "addr:postcode":"10453",
    "addr:street":"Grand Concourse",
    "iso:country":"US",
    "sg:address":"2011 Grand Concourse",
    "sg:city":"Bronx",
    "sg:classifiers":[
        {
            "category":"Organizations",
            "subcategory":"Religious Organization",
            "type":"Services"
        }
    ],
    "sg:phone":"+1 718 299 0043",
    "sg:postcode":"10453",
    "sg:province":"NY",
    "wof:name":"Fountain Spring Baptist Church",
    "wof:placetype":"venue"
},
  "geometry": {"coordinates":[-73.90452999999999,40.8513],"type":"Point"}
}