{
  "type": "Feature",
  "properties": {
    "iso:country":"US",
    "sg:address":"12510 Queens Boulevard Suite 219",
    "sg:city":"Kew Gardens",
    "sg:classifiers":[
        {
            "category":"Health Services",
            "subcategory":"Dentist",
            "type":"Services"
        }
    ],
    "sg:phone":"+1 718 520 0732",
    "sg:postcode":"11415",
    "sg:province":"NY",
    "wof:name":"Weibman Robert DDS",
    "wof:placetype":"venue"
},
  "geometry": {"coordinates":[-73.826477,40.712292],"type":"Point"}
}