{
  "type": "Feature",
  "properties": {
    "addr:full":"170B Gardiners Ave Levittown NY 11756",
    "addr:housenumber":"170b",
    "addr:postcode":"11756",
    "addr:street":"Gardiners Ave",
    "iso:country":"US",
    "sg:address":"170B Gardiners Ave",
    "sg:city":"Levittown",
    "sg:classifiers":[
        {
            "category":"Arts & Performance",
            "subcategory":"Arts Center",
            "type":"Entertainment"
        }
    ],
    "sg:phone":"+1 516 731 1128",
    "sg:postcode":"11756",
    "sg:province":"NY",
    "sg:tags":[
        "performing"
    ],
    "sg:website":"www.5678dance.net",
    "wof:name":"5 6 7 8 Dance",
    "wof:placetype":"venue"
},
  "geometry": {"coordinates":[-73.51577899999999,40.721553],"type":"Point"}
}