{
  "type": "Feature",
  "properties": {
    "addr:full":"8204 3rd Ave Brooklyn NY 11209",
    "addr:housenumber":"8204",
    "addr:postcode":"11209",
    "addr:street":"3Rd Ave",
    "iso:country":"US",
    "sg:address":"8204 3rd Ave",
    "sg:city":"Brooklyn",
    "sg:classifiers":[
        {
            "category":"Food & Beverages",
            "subcategory":"Groceries & Convenience Stores",
            "type":"Retail Goods"
        }
    ],
    "sg:phone":"+1 718 833 2754",
    "sg:postcode":"11209",
    "sg:province":"NY",
    "wof:name":"N Y Clover Food Corp",
    "wof:placetype":"venue"
},
  "geometry": {"coordinates":[-74.00385,40.626394],"type":"Point"}
}