{
  "type": "Feature",
  "properties": {
    "addr:full":"42 7th St Valley Stream NY 11581",
    "addr:housenumber":"42",
    "addr:postcode":"11581",
    "addr:street":"7Th St",
    "iso:country":"US",
    "sg:address":"42 7th St",
    "sg:city":"Valley Stream",
    "sg:classifiers":[
        {
            "category":"Professional",
            "subcategory":"Detective & Security Services",
            "type":"Services"
        }
    ],
    "sg:phone":"+1   ",
    "sg:postcode":"11581",
    "sg:province":"NY",
    "sg:tags":[
        "car"
    ],
    "wof:name":"Americo Investigations Ltd",
    "wof:placetype":"venue"
},
  "geometry": {"coordinates":[-73.697934,40.657332],"type":"Point"}
}