{
  "type": "Feature",
  "properties": {
    "iso:country":"US",
    "sg:address":"41 Oakley Blvd",
    "sg:city":"Garnerville",
    "sg:classifiers":[
        {
            "category":"Building & Trades",
            "subcategory":"Construction",
            "type":"Services"
        }
    ],
    "sg:phone":"+1 845 786 7834",
    "sg:postcode":"10923",
    "sg:province":"NY",
    "sg:tags":[
        "repairing",
        "remodeling",
        "contractor"
    ],
    "wof:name":"Alfa Remodelers & Builders Inc",
    "wof:placetype":"venue"
},
  "geometry": {"coordinates":[-73.999748,41.196816],"type":"Point"}
}