{
  "type": "Feature",
  "properties": {
    "addr:full":"6197 Fritz Hill Rd Avoca NY 14809",
    "addr:housenumber":"6197",
    "addr:postcode":"14809",
    "addr:street":"Fritz Hill Rd",
    "iso:country":"US",
    "sg:address":"6197 Fritz Hill Rd",
    "sg:city":"Avoca",
    "sg:classifiers":[
        {
            "category":"Building & Trades",
            "subcategory":"Construction",
            "type":"Services"
        }
    ],
    "sg:phone":"+1 607 566 2641",
    "sg:postcode":"14809",
    "sg:province":"NY",
    "sg:tags":[
        "contractor"
    ],
    "wof:name":"Remchuk General Contracting",
    "wof:placetype":"venue"
},
  "geometry": {"coordinates":[-77.34443400000001,42.434881],"type":"Point"}
}