{
  "type": "Feature",
  "properties": {
    "addr:full":"8 Stratford Rd Farmingville NY 11738",
    "addr:housenumber":"8",
    "addr:postcode":"11738",
    "addr:street":"Stratford Rd",
    "iso:country":"US",
    "sg:address":"8 Stratford Rd",
    "sg:city":"Farmingville",
    "sg:classifiers":[
        {
            "category":"Building & Trades",
            "subcategory":"Construction",
            "type":"Services"
        }
    ],
    "sg:phone":"+1 631 698 5925",
    "sg:postcode":"11738",
    "sg:province":"NY",
    "sg:tags":[
        "painter"
    ],
    "wof:name":"Pegasus Contrctng Inc",
    "wof:placetype":"venue"
},
  "geometry": {"coordinates":[-73.04589799999999,40.826698],"type":"Point"}
}