{
  "type": "Feature",
  "properties": {
    "addr:full":"310 Audubon Ave New York NY 10033",
    "addr:housenumber":"310",
    "addr:postcode":"10033",
    "addr:street":"Audubon Ave",
    "iso:country":"US",
    "sg:address":"310 Audubon Ave",
    "sg:city":"New York",
    "sg:classifiers":[
        {
            "category":"Food & Beverages",
            "subcategory":"Groceries & Convenience Stores",
            "type":"Retail Goods"
        }
    ],
    "sg:phone":"+1 212 740 8662",
    "sg:postcode":"10033",
    "sg:province":"NY",
    "sg:tags":[
        "product"
    ],
    "wof:name":"Las Palmas Food Corp",
    "wof:placetype":"venue"
},
  "geometry": {"coordinates":[-73.93261699999999,40.848384],"type":"Point"}
}