{
  "type": "Feature",
  "properties": {
    "iso:country":"US",
    "sg:address":"1635 Welker Rd",
    "sg:city":"Penn Yan",
    "sg:classifiers":[
        {
            "category":"Farming",
            "subcategory":"Farm & Veterinary Services",
            "type":"Manufacturing & Wholesale Goods"
        }
    ],
    "sg:phone":"+1 607 243 5351",
    "sg:postcode":"14837",
    "sg:province":"NY",
    "wof:name":"All Riehl Holsteins",
    "wof:placetype":"venue"
},
  "geometry": {"coordinates":[-77.016424,42.559935],"type":"Point"}
}