{
  "type": "Feature",
  "properties": {
    "iso:country":"US",
    "sg:address":"5646 E Avon Lima Rd",
    "sg:city":"Avon",
    "sg:classifiers":[
        {
            "category":"Shopping",
            "subcategory":"Used Merchandise",
            "type":"Retail Goods"
        }
    ],
    "sg:phone":"+1 585 226 6990",
    "sg:postcode":"14414",
    "sg:province":"NY",
    "sg:tags":[
        "antique"
    ],
    "wof:name":"Wee Little Antiques",
    "wof:placetype":"venue"
},
  "geometry": {"coordinates":[-77.70433,42.908567],"type":"Point"}
}