{
  "type": "Feature",
  "properties": {
    "iso:country":"US",
    "sg:address":"1378 Norton St",
    "sg:city":"Rochester",
    "sg:classifiers":[
        {
            "category":"Shopping",
            "subcategory":"Jewelry",
            "type":"Retail Goods"
        }
    ],
    "sg:phone":"+1 585 266 1020",
    "sg:postcode":"14621",
    "sg:province":"NY",
    "sg:tags":[
        "jeweler"
    ],
    "wof:name":"B's Treasures",
    "wof:placetype":"venue"
},
  "geometry": {"coordinates":[-77.584794,43.187389],"type":"Point"}
}