{
  "type": "Feature",
  "properties": {
    "iso:country":"US",
    "sg:address":"135 Bedford Rd",
    "sg:city":"Katonah",
    "sg:classifiers":[
        {
            "category":"Insurance",
            "subcategory":"Insurance Agent",
            "type":"Services"
        }
    ],
    "sg:phone":"+1 914 941 6777",
    "sg:postcode":"10536",
    "sg:province":"NY",
    "sg:tags":[
        "real estate"
    ],
    "wof:name":"Robert W Sundermann Ltd",
    "wof:placetype":"venue"
},
  "geometry": {"coordinates":[-73.683233,41.250928],"type":"Point"}
}