{
  "type": "Feature",
  "properties": {
    "iso:country":"US",
    "sg:address":"85 Pike St",
    "sg:city":"Port Jervis",
    "sg:classifiers":[
        {
            "category":"Real Estate",
            "subcategory":"Real Estate Agent",
            "type":"Services"
        }
    ],
    "sg:phone":"+1 845 856 6700",
    "sg:postcode":"12771",
    "sg:province":"NY",
    "wof:name":"Dnh Realty Co",
    "wof:placetype":"venue"
},
  "geometry": {"coordinates":[-74.69318699999999,41.374848],"type":"Point"}
}