{
  "type": "Feature",
  "properties": {
    "iso:country":"US",
    "sg:address":"5 Perine St",
    "sg:city":"Dansville",
    "sg:classifiers":[
        {
            "category":"Manufacturing",
            "subcategory":"Printing",
            "type":"Manufacturing & Wholesale Goods"
        }
    ],
    "sg:phone":"+1   ",
    "sg:postcode":"14437",
    "sg:province":"NY",
    "sg:tags":[
        "publishes",
        "guide",
        "shopper"
    ],
    "wof:name":"Liberty Group Pubg Holdings NY",
    "wof:placetype":"venue"
},
  "geometry": {"coordinates":[-77.69663300000001,42.562449],"type":"Point"}
}