{
  "type": "Feature",
  "properties": {
    "addr:full":"85 S Central Ave Elmsford NY 10523",
    "addr:housenumber":"85",
    "addr:postcode":"10523",
    "addr:street":"S Central Ave",
    "iso:country":"US",
    "sg:address":"85 S Central Ave",
    "sg:city":"Elmsford",
    "sg:classifiers":[
        {
            "category":"Retail",
            "subcategory":"Auto Repair",
            "type":"Services"
        }
    ],
    "sg:phone":"+1 914 592 6767",
    "sg:postcode":"10523",
    "sg:province":"NY",
    "sg:tags":[
        "body",
        "automobile",
        "dent",
        "removal",
        "painting",
        "repairing"
    ],
    "wof:name":"Brendan's Auto Body",
    "wof:placetype":"venue"
},
  "geometry": {"coordinates":[-73.82168299999999,41.052038],"type":"Point"}
}