{
  "type": "Feature",
  "properties": {
    "addr:full":"33 Grand St Brooklyn NY 11211",
    "addr:housenumber":"33",
    "addr:postcode":"11211",
    "addr:street":"Grand St",
    "iso:country":"US",
    "sg:address":"33 Grand St",
    "sg:city":"Brooklyn",
    "sg:classifiers":[
        {
            "category":"Communications",
            "subcategory":"Film & Video Production",
            "type":"Services"
        }
    ],
    "sg:phone":"+1 718 218 0055",
    "sg:postcode":"11211",
    "sg:province":"NY",
    "sg:tags":[
        "studio",
        "rental"
    ],
    "sg:website":"www.northsidebank.net",
    "wof:name":"Northside Bank",
    "wof:placetype":"venue"
},
  "geometry": {"coordinates":[-73.964501,40.715825],"type":"Point"}
}