{
  "type": "Feature",
  "properties": {
    "iso:country":"US",
    "sg:address":"3197 Horseblock Rd",
    "sg:city":"Medford",
    "sg:classifiers":[
        {
            "category":"Ice Cream",
            "type":"Food & Drink"
        }
    ],
    "sg:menulink":"http://www.allmenus.com/ny/brookhaven/243592-baskin-robbins/menu/",
    "sg:phone":"+1 631 654 4936",
    "sg:postcode":"11763",
    "sg:province":"NY",
    "sg:tags":[
        "american"
    ],
    "wof:name":"Baskin-Robbins",
    "wof:placetype":"venue"
},
  "geometry": {"coordinates":[-72.981886,40.824901],"type":"Point"}
}