{
  "type": "Feature",
  "properties": {
    "iso:country":"US",
    "sg:address":"522 Erie Blvd W",
    "sg:city":"Rome",
    "sg:classifiers":[
        {
            "category":"Retail",
            "subcategory":"Self-service Laundry",
            "type":"Services"
        }
    ],
    "sg:phone":"+1   ",
    "sg:postcode":"13440",
    "sg:province":"NY",
    "sg:tags":[
        "coin"
    ],
    "wof:name":"Pinky-White Launderett",
    "wof:placetype":"venue"
},
  "geometry": {"coordinates":[-75.46816699999999,43.213933],"type":"Point"}
}