{
  "type": "Feature",
  "properties": {
    "addr:full":"45 W 34th St New York NY 10001",
    "addr:housenumber":"45",
    "addr:postcode":"10001",
    "addr:street":"W 34Th St",
    "iso:country":"US",
    "sg:address":"45 W 34th St",
    "sg:city":"New York",
    "sg:classifiers":[
        {
            "category":"Building & Trades",
            "subcategory":"Construction",
            "type":"Services"
        }
    ],
    "sg:phone":"+1 212 268 3840",
    "sg:postcode":"10001",
    "sg:province":"NY",
    "sg:tags":[
        "house"
    ],
    "wof:name":"Barrera Cnstr & Dev Corp",
    "wof:placetype":"venue"
},
  "geometry": {"coordinates":[-73.986649,40.749239],"type":"Point"}
}