{
  "type": "Feature",
  "properties": {
    "iso:country":"US",
    "sg:address":"5957 New Hartford St",
    "sg:city":"Wolcott",
    "sg:classifiers":[
        {
            "category":"Education",
            "subcategory":"School",
            "type":"Public Place"
        }
    ],
    "sg:phone":"+1 315 594 3130",
    "sg:postcode":"14590",
    "sg:province":"NY",
    "sg:website":"www.nrwcs.org",
    "wof:name":"Leavenworth Middle School",
    "wof:placetype":"venue"
},
  "geometry": {"coordinates":[-76.81490100000001,43.217099],"type":"Point"}
}