{
  "type": "Feature",
  "properties": {
    "addr:full":"4333 Trout Lily Ln Manlius NY 13104",
    "addr:housenumber":"4333",
    "addr:postcode":"13104",
    "addr:street":"Trout Lily Ln",
    "iso:country":"US",
    "sg:address":"4333 Trout Lily Ln",
    "sg:city":"Manlius",
    "sg:classifiers":[
        {
            "category":"Wholesale",
            "subcategory":"Durable Goods & Equipment",
            "type":"Manufacturing & Wholesale Goods"
        }
    ],
    "sg:phone":"+1 315 682 4377",
    "sg:postcode":"13104",
    "sg:province":"NY",
    "sg:tags":[
        "representative",
        "manufacturer"
    ],
    "wof:name":"Don Shaw Assoc Inc",
    "wof:placetype":"venue"
},
  "geometry": {"coordinates":[-75.96097399999999,42.983494],"type":"Point"}
}