{
  "type": "Feature",
  "properties": {
    "iso:country":"US",
    "sg:address":"104 Carolyn Ave",
    "sg:city":"Valley Stream",
    "sg:classifiers":[
        {
            "category":"Real Estate",
            "subcategory":"Developer",
            "type":"Services"
        }
    ],
    "sg:phone":"+1 516 872 9572",
    "sg:postcode":"11580",
    "sg:province":"NY",
    "sg:tags":[
        "subdivider"
    ],
    "wof:name":"Apache Associates",
    "wof:placetype":"venue"
},
  "geometry": {"coordinates":[-73.713444,40.682225],"type":"Point"}
}