{
  "type": "Feature",
  "properties": {
    "addr:full":"12 Sands Rd Middletown NY 10941",
    "addr:housenumber":"12",
    "addr:postcode":"10941",
    "addr:street":"Sands Rd",
    "iso:country":"US",
    "sg:address":"12 Sands Rd",
    "sg:city":"Middletown",
    "sg:classifiers":[
        {
            "category":"Autos & Motor Vehicles",
            "subcategory":"Automobile Sales",
            "type":"Retail Goods"
        }
    ],
    "sg:phone":"+1 845 361 3679",
    "sg:postcode":"10941",
    "sg:province":"NY",
    "sg:tags":[
        "car",
        "dealer"
    ],
    "wof:name":"Benko Motors",
    "wof:placetype":"venue"
},
  "geometry": {"coordinates":[-74.408395,41.50522],"type":"Point"}
}