{
  "type": "Feature",
  "properties": {
    "addr:full":"300 Turk Hill Rd Brewster NY 10509",
    "addr:housenumber":"300",
    "addr:postcode":"10509",
    "addr:street":"Turk Hill Rd",
    "iso:country":"US",
    "sg:address":"300 Turk Hill Rd",
    "sg:city":"Brewster",
    "sg:classifiers":[
        {
            "category":"Building & Trades",
            "subcategory":"Construction",
            "type":"Services"
        }
    ],
    "sg:phone":"+1 845 278 7189",
    "sg:postcode":"10509",
    "sg:province":"NY",
    "sg:tags":[
        "contractor"
    ],
    "wof:name":"Brett Holliday",
    "wof:placetype":"venue"
},
  "geometry": {"coordinates":[-73.606871,41.372014],"type":"Point"}
}