{
  "type": "Feature",
  "properties": {
    "iso:country":"US",
    "sg:address":"251 Pease Hill Rd",
    "sg:city":"Brant Lake",
    "sg:classifiers":[
        {
            "category":"Shopping",
            "subcategory":"Beauty & Cosmetics",
            "type":"Retail Goods"
        }
    ],
    "sg:phone":"+1   ",
    "sg:postcode":"12815",
    "sg:province":"NY",
    "sg:tags":[
        "merchandise"
    ],
    "wof:name":"Sylvia L Smith",
    "wof:placetype":"venue"
},
  "geometry": {"coordinates":[-73.739217,43.69768],"type":"Point"}
}