{
  "type": "Feature",
  "properties": {
    "addr:full":"21 Ann St New York NY 10038",
    "addr:housenumber":"21",
    "addr:postcode":"10038",
    "addr:street":"Ann St",
    "iso:country":"US",
    "sg:address":"21 Ann St",
    "sg:city":"New York",
    "sg:classifiers":[
        {
            "category":"Building & Trades",
            "subcategory":"Equipment Rental",
            "type":"Services"
        }
    ],
    "sg:phone":"+1   ",
    "sg:postcode":"10038",
    "sg:province":"NY",
    "sg:tags":[
        "adult",
        "entertainment"
    ],
    "wof:name":"Ann St Adult Entertainment",
    "wof:placetype":"venue"
},
  "geometry": {"coordinates":[-74.00737599999999,40.710578],"type":"Point"}
}