{
  "type": "Feature",
  "properties": {
    "iso:country":"US",
    "sg:address":"3708 Rath Ave",
    "sg:city":"Endicott",
    "sg:classifiers":[
        {
            "category":"Shopping",
            "type":"Retail Goods"
        }
    ],
    "sg:phone":"+1 607 484 9423",
    "sg:postcode":"13760",
    "sg:province":"NY",
    "sg:tags":[
        "pet",
        "shop"
    ],
    "wof:name":"Bird Haven Co",
    "wof:placetype":"venue"
},
  "geometry": {"coordinates":[-76.009297,42.114277],"type":"Point"}
}