{
  "type": "Feature",
  "properties": {
    "addr:full":"16 Bank St New York NY 10014",
    "addr:housenumber":"16",
    "addr:postcode":"10014",
    "addr:street":"Bank St",
    "iso:country":"US",
    "sg:address":"16 Bank St",
    "sg:city":"New York",
    "sg:classifiers":[
        {
            "category":"Bars & Pubs",
            "subcategory":"Lounge",
            "type":"Food & Drink"
        },
        {
            "category":"Restaurant",
            "type":"Food & Drink"
        }
    ],
    "sg:postcode":"10014",
    "sg:province":"NY",
    "sg:tags":[
        "new",
        "american"
    ],
    "wof:name":"The Waverly Inn & Garden",
    "wof:placetype":"venue"
},
  "geometry": {"coordinates":[-74.002195,40.736958],"type":"Point"}
}