{
  "type": "Feature",
  "properties": {
    "addr:full":"515 Monroe Ave Rochester NY 14607",
    "addr:housenumber":"515",
    "addr:postcode":"14607",
    "addr:street":"Monroe Ave",
    "iso:country":"US",
    "sg:address":"515 Monroe Ave",
    "sg:city":"Rochester",
    "sg:classifiers":[
        {
            "category":"Restaurant",
            "type":"Food & Drink"
        }
    ],
    "sg:phone":"+1 585 442 1414",
    "sg:postcode":"14607",
    "sg:province":"NY",
    "sg:tags":[
        "american",
        "sauce",
        "mfg"
    ],
    "wof:name":"Country Sweet Chicken and Ribs",
    "wof:placetype":"venue"
},
  "geometry": {"coordinates":[-77.593487,43.146371],"type":"Point"}
}