{
  "type": "Feature",
  "properties": {
    "iso:country":"US",
    "sg:address":"66 Westchester Sq",
    "sg:city":"Bronx",
    "sg:classifiers":[
        {
            "category":"Shopping",
            "subcategory":"Music",
            "type":"Retail Goods"
        }
    ],
    "sg:phone":"+1 718 822 9446",
    "sg:postcode":"10461",
    "sg:province":"NY",
    "sg:tags":[
        "compact",
        "record",
        "disc",
        "tape"
    ],
    "wof:name":"Records-N-Stuff",
    "wof:placetype":"venue"
},
  "geometry": {"coordinates":[-73.84313,40.841345],"type":"Point"}
}