{
  "type": "Feature",
  "properties": {
    "addr:full":"738 Smithtown Byp Smithtown NY 11787",
    "addr:housenumber":"738",
    "addr:postcode":"11787",
    "addr:street":"Byp",
    "iso:country":"US",
    "sg:address":"738 Smithtown Byp",
    "sg:city":"Smithtown",
    "sg:classifiers":[
        {
            "category":"Organizations",
            "subcategory":"Professional Association",
            "type":"Services"
        }
    ],
    "sg:phone":"+1 631 863 0532",
    "sg:postcode":"11787",
    "sg:province":"NY",
    "wof:name":"Cooley's Anemia Foundation Inc",
    "wof:placetype":"venue"
},
  "geometry": {"coordinates":[-73.171454,40.846961],"type":"Point"}
}