{
  "type": "Feature",
  "properties": {
    "addr:full":"62 W 125th St New York NY 10027",
    "addr:housenumber":"62",
    "addr:postcode":"10027",
    "addr:street":"W 125Th St",
    "iso:country":"US",
    "sg:address":"62 W 125th St",
    "sg:city":"New York",
    "sg:classifiers":[
        {
            "category":"Restaurant",
            "type":"Food & Drink"
        }
    ],
    "sg:menulink":"http://www.allmenus.com/ny/new-york/47373-shrimp-box/menu/",
    "sg:phone":"+1 212 369 3684",
    "sg:postcode":"10027",
    "sg:province":"NY",
    "sg:tags":[
        "seafood",
        "american"
    ],
    "wof:name":"Shrimp Box",
    "wof:placetype":"venue"
},
  "geometry": {"coordinates":[-73.944647,40.807118],"type":"Point"}
}