{
  "type": "Feature",
  "properties": {
    "addr:full":"229 Smith St Brooklyn NY 11231",
    "addr:housenumber":"229",
    "addr:postcode":"11231",
    "addr:street":"Smith St",
    "iso:country":"US",
    "sg:address":"229 Smith St",
    "sg:city":"Brooklyn",
    "sg:classifiers":[
        {
            "category":"Health Services",
            "subcategory":"Doctor",
            "type":"Services"
        }
    ],
    "sg:phone":"+1 718 625 7681",
    "sg:postcode":"11231",
    "sg:province":"NY",
    "sg:tags":[
        "physician",
        "surgeon"
    ],
    "wof:name":"Victor Alonso MD",
    "wof:placetype":"venue"
},
  "geometry": {"coordinates":[-73.992475,40.683668],"type":"Point"}
}