{
  "type": "Feature",
  "properties": {
    "iso:country":"US",
    "sg:address":"64 Young Ave",
    "sg:city":"New York Mills",
    "sg:classifiers":[
        {
            "category":"Building & Trades",
            "subcategory":"Construction",
            "type":"Services"
        }
    ],
    "sg:phone":"+1 315 736 1379",
    "sg:postcode":"13417",
    "sg:province":"NY",
    "sg:tags":[
        "specializing",
        "contractor",
        "remodeling",
        "custom"
    ],
    "wof:name":"Kitchen Store The",
    "wof:placetype":"venue"
},
  "geometry": {"coordinates":[-75.287909,43.096006],"type":"Point"}
}