{
  "type": "Feature",
  "properties": {
    "addr:full":"169 Thompson St New York NY 10012",
    "addr:housenumber":"169",
    "addr:postcode":"10012",
    "addr:street":"Thompson St",
    "iso:country":"US",
    "sg:address":"169 Thompson St",
    "sg:city":"New York",
    "sg:classifiers":[
        {
            "category":"Shopping",
            "subcategory":"Gifts & Souvenirs",
            "type":"Retail Goods"
        }
    ],
    "sg:phone":"+1   ",
    "sg:postcode":"10012",
    "sg:province":"NY",
    "wof:name":"Random Accessories",
    "wof:placetype":"venue"
},
  "geometry": {"coordinates":[-73.999886,40.728236],"type":"Point"}
}