{
  "type": "Feature",
  "properties": {
    "iso:country":"US",
    "sg:address":"105 Metzger Rd",
    "sg:city":"Red Hook",
    "sg:classifiers":[
        {
            "category":"Health Services",
            "subcategory":"Health Practitioner",
            "type":"Services"
        }
    ],
    "sg:phone":"+1 845 758 6181",
    "sg:postcode":"12571",
    "sg:province":"NY",
    "sg:tags":[
        "therapist",
        "physical"
    ],
    "wof:name":"Donald E Domkowski",
    "wof:placetype":"venue"
},
  "geometry": {"coordinates":[-73.881018,41.984369],"type":"Point"}
}