{
  "type": "Feature",
  "properties": {
    "iso:country":"US",
    "sg:address":"3044 E Henrietta Rd",
    "sg:city":"Henrietta",
    "sg:classifiers":[
        {
            "category":"Retail",
            "subcategory":"Car Wash",
            "type":"Services"
        }
    ],
    "sg:phone":"+1 585 321 1510",
    "sg:postcode":"14467",
    "sg:province":"NY",
    "sg:tags":[
        "polishing",
        "washing"
    ],
    "wof:name":"KLEE Corp",
    "wof:placetype":"venue"
},
  "geometry": {"coordinates":[-77.611969,43.06036],"type":"Point"}
}