{
  "type": "Feature",
  "properties": {
    "iso:country":"US",
    "sg:address":"760 Eldert Ln, Suite 4E",
    "sg:city":"Brooklyn",
    "sg:classifiers":[
        {
            "category":"Retail",
            "subcategory":"Repair Shop",
            "type":"Services"
        },
        {
            "category":"Shopping",
            "subcategory":"Computers & Home Electronics",
            "type":"Retail Goods"
        },
        {
            "category":"Professional",
            "subcategory":"Computer Services",
            "type":"Services"
        }
    ],
    "sg:phone":"+1 347 725 0046",
    "sg:postcode":"11208",
    "sg:province":"NY",
    "sg:tags":[
        "network",
        "supply",
        "technical",
        "repair-business",
        "assistance",
        "system",
        "hardware",
        "design",
        "online",
        "support"
    ],
    "wof:name":"NETOX",
    "wof:placetype":"venue"
},
  "geometry": {"coordinates":[-73.86326200000001,40.671267],"type":"Point"}
}