{
  "type": "Feature",
  "properties": {
    "iso:country":"US",
    "sg:address":"508 E 78th Street",
    "sg:city":"New York",
    "sg:classifiers":[
        {
            "category":"Building & Trades",
            "subcategory":"Construction",
            "type":"Services"
        }
    ],
    "sg:phone":"+1 212 794 3160",
    "sg:postcode":"10021",
    "sg:province":"NY",
    "sg:tags":[
        "interior",
        "design"
    ],
    "wof:name":"Noreen Interiors",
    "wof:placetype":"venue"
},
  "geometry": {"coordinates":[-73.94967699999999,40.770148],"type":"Point"}
}