{
  "type": "Feature",
  "properties": {
    "iso:country":"US",
    "sg:address":"1522 41st St",
    "sg:city":"Brooklyn",
    "sg:classifiers":[
        {
            "category":"Real Estate",
            "subcategory":"Real Estate Agent",
            "type":"Services"
        }
    ],
    "sg:phone":"+1 718 972 0726",
    "sg:postcode":"11218",
    "sg:province":"NY",
    "wof:name":"I M K Management LLC",
    "wof:placetype":"venue"
},
  "geometry": {"coordinates":[-73.98127100000001,40.635755],"type":"Point"}
}