{
  "type": "Feature",
  "properties": {
    "iso:country":"US",
    "sg:address":"37-28 Railroad Ave",
    "sg:city":"Long Island City",
    "sg:classifiers":[
        {
            "category":"Professional",
            "subcategory":"Lawyer & Legal Services",
            "type":"Services"
        }
    ],
    "sg:phone":"+1 718 786 9125",
    "sg:postcode":"11101",
    "sg:province":"NY",
    "wof:name":"Bartone Anthony Atty",
    "wof:placetype":"venue"
},
  "geometry": {"coordinates":[-73.93905700000001,40.732967],"type":"Point"}
}