{
  "type": "Feature",
  "properties": {
    "addr:full":"3751 Harlem Rd Buffalo NY 14215",
    "addr:housenumber":"3751",
    "addr:postcode":"14215",
    "addr:street":"Harlem Rd",
    "iso:country":"US",
    "sg:address":"3751 Harlem Rd",
    "sg:city":"Buffalo",
    "sg:classifiers":[
        {
            "category":"Wholesale",
            "subcategory":"Non-durable Goods",
            "type":"Manufacturing & Wholesale Goods"
        }
    ],
    "sg:phone":"+1 716 634 8870",
    "sg:postcode":"14215",
    "sg:province":"NY",
    "sg:tags":[
        "product",
        "surplus"
    ],
    "wof:name":"Surplus Source Inc",
    "wof:placetype":"venue"
},
  "geometry": {"coordinates":[-78.78398900000001,42.947785],"type":"Point"}
}