{
  "type": "Feature",
  "properties": {
    "iso:country":"US",
    "sg:address":"4234 Union Rd",
    "sg:city":"Buffalo",
    "sg:classifiers":[
        {
            "category":"Shopping",
            "type":"Retail Goods"
        }
    ],
    "sg:phone":"+1   ",
    "sg:postcode":"14225",
    "sg:province":"NY",
    "sg:tags":[
        "living",
        "equipment"
    ],
    "wof:name":"TLC Mobility Inc",
    "wof:placetype":"venue"
},
  "geometry": {"coordinates":[-78.754212,42.927185],"type":"Point"}
}