{
  "type": "Feature",
  "properties": {
    "addr:full":"49 W 57 St New York NY 10019",
    "addr:housenumber":"49",
    "addr:postcode":"10019",
    "addr:street":"W 57 St",
    "iso:country":"US",
    "sg:address":"49 W 57 St",
    "sg:city":"New York",
    "sg:classifiers":[
        {
            "category":"Shopping",
            "type":"Retail Goods"
        }
    ],
    "sg:phone":"+1 212 586 2405",
    "sg:postcode":"10019",
    "sg:province":"NY",
    "sg:tags":[
        "cosmetic",
        "perfume"
    ],
    "wof:name":"Freeze 24-7 INTL LLC",
    "wof:placetype":"venue"
},
  "geometry": {"coordinates":[-73.975961,40.763724],"type":"Point"}
}