{
  "type": "Feature",
  "properties": {
    "addr:full":"326 Jackson Ave Syosset NY 11791",
    "addr:housenumber":"326",
    "addr:postcode":"11791",
    "addr:street":"Jackson Ave",
    "iso:country":"US",
    "sg:address":"326 Jackson Ave",
    "sg:city":"Syosset",
    "sg:classifiers":[
        {
            "category":"Personal",
            "subcategory":"Beauty Salon",
            "type":"Services"
        }
    ],
    "sg:phone":"+1 516 921 3335",
    "sg:postcode":"11791",
    "sg:province":"NY",
    "sg:tags":[
        "manicuring"
    ],
    "wof:name":"M S Nail Studio",
    "wof:placetype":"venue"
},
  "geometry": {"coordinates":[-73.501873,40.810753],"type":"Point"}
}