{
  "type": "Feature",
  "properties": {
    "addr:full":"27 W. 20th Street New York City NY 10011",
    "addr:housenumber":"27",
    "addr:postcode":"10011",
    "addr:street":"W. 20Th Street",
    "iso:country":"US",
    "sg:address":"27 W. 20th Street",
    "sg:city":"New York City",
    "sg:classifiers":[
        {
            "category":"Shopping",
            "subcategory":"Gifts & Souvenirs",
            "type":"Retail Goods"
        }
    ],
    "sg:phone":"+1 212 620 0018",
    "sg:postcode":"10011",
    "sg:province":"NY",
    "sg:tags":[
        "flower"
    ],
    "sg:website":"papercutsnewyork.com",
    "wof:name":"Papercuts",
    "wof:placetype":"venue"
},
  "geometry": {"coordinates":[-73.991798,40.7402],"type":"Point"}
}