{
  "type": "Feature",
  "properties": {
    "addr:full":"202 W 125th St New York NY 10027",
    "addr:housenumber":"202",
    "addr:postcode":"10027",
    "addr:street":"W 125Th St",
    "iso:country":"US",
    "sg:address":"202 W 125th St",
    "sg:city":"New York",
    "sg:classifiers":[
        {
            "category":"Shopping",
            "subcategory":"Discount & Variety Stores",
            "type":"Retail Goods"
        }
    ],
    "sg:phone":"+1 212 678 4075",
    "sg:postcode":"10027",
    "sg:province":"NY",
    "sg:tags":[
        "outlet"
    ],
    "wof:name":"Electronic Outlets Incorporated",
    "wof:placetype":"venue"
},
  "geometry": {"coordinates":[-73.948516,40.808907],"type":"Point"}
}