{
  "type": "Feature",
  "properties": {
    "addr:full":"16 Flushing Ave Maspeth NY 11378",
    "addr:housenumber":"16",
    "addr:postcode":"11378",
    "addr:street":"Flushing Ave",
    "iso:country":"US",
    "sg:address":"16 Flushing Ave",
    "sg:city":"Maspeth",
    "sg:classifiers":[
        {
            "category":"Retail",
            "subcategory":"Repair Shop",
            "type":"Services"
        }
    ],
    "sg:phone":"+1   ",
    "sg:postcode":"11378",
    "sg:province":"NY",
    "wof:name":"Sure Energy LLC",
    "wof:placetype":"venue"
},
  "geometry": {"coordinates":[-73.912885,40.715246],"type":"Point"}
}