{
  "type": "Feature",
  "properties": {
    "iso:country":"US",
    "sg:address":"296 Richmond Ave",
    "sg:city":"Amityville",
    "sg:classifiers":[
        {
            "category":"Wholesale",
            "subcategory":"Groceries",
            "type":"Manufacturing & Wholesale Goods"
        }
    ],
    "sg:phone":"+1 631 264 2403",
    "sg:postcode":"11701",
    "sg:province":"NY",
    "sg:tags":[
        "import",
        "company",
        "export"
    ],
    "wof:name":"Phoenix Impex International In",
    "wof:placetype":"venue"
},
  "geometry": {"coordinates":[-73.41817,40.659795],"type":"Point"}
}