{
  "type": "Feature",
  "properties": {
    "iso:country":"US",
    "sg:address":"33 Kansas St",
    "sg:city":"Hicksville",
    "sg:classifiers":[
        {
            "category":"Building & Trades",
            "subcategory":"Plumbing",
            "type":"Services"
        }
    ],
    "sg:phone":"+1 516 681 5592",
    "sg:postcode":"11801",
    "sg:province":"NY",
    "sg:tags":[
        "plumbing",
        "contractor"
    ],
    "wof:name":"Plumbing Kru Inc",
    "wof:placetype":"venue"
},
  "geometry": {"coordinates":[-73.53925700000001,40.772976],"type":"Point"}
}