{
  "type": "Feature",
  "properties": {
    "addr:full":"252 W 102nd St New York NY 10025",
    "addr:housenumber":"252",
    "addr:postcode":"10025",
    "addr:street":"W 102Nd St",
    "iso:country":"US",
    "sg:address":"252 W 102nd St",
    "sg:city":"New York",
    "sg:classifiers":[
        {
            "category":"Retail",
            "subcategory":"Repair Shop",
            "type":"Services"
        }
    ],
    "sg:phone":"+1 646 224 9196",
    "sg:postcode":"10025",
    "sg:province":"NY",
    "sg:tags":[
        "lock",
        "locksmith"
    ],
    "wof:name":"Locksmith Number 1",
    "wof:placetype":"venue"
},
  "geometry": {"coordinates":[-73.970236,40.798882],"type":"Point"}
}