{
  "type": "Feature",
  "properties": {
    "addr:full":"15 Winchester Dr Monroe NY 10950",
    "addr:housenumber":"15",
    "addr:postcode":"10950",
    "addr:street":"Winchester Dr",
    "iso:country":"US",
    "sg:address":"15 Winchester Dr",
    "sg:city":"Monroe",
    "sg:classifiers":[
        {
            "category":"Health Services",
            "subcategory":"Chiropractor",
            "type":"Services"
        }
    ],
    "sg:phone":"+1 845 782 4311",
    "sg:postcode":"10950",
    "sg:province":"NY",
    "wof:name":"Newman Chiropractic",
    "wof:placetype":"venue"
},
  "geometry": {"coordinates":[-74.179604,41.314098],"type":"Point"}
}