{
  "type": "Feature",
  "properties": {
    "addr:full":"956 Redman Rd Hamlin NY 14464",
    "addr:housenumber":"956",
    "addr:postcode":"14464",
    "addr:street":"Redman Rd",
    "iso:country":"US",
    "sg:address":"956 Redman Rd",
    "sg:city":"Hamlin",
    "sg:classifiers":[
        {
            "category":"Shopping",
            "subcategory":"Gifts & Souvenirs",
            "type":"Retail Goods"
        }
    ],
    "sg:phone":"+1   ",
    "sg:postcode":"14464",
    "sg:province":"NY",
    "wof:name":"Timberden",
    "wof:placetype":"venue"
},
  "geometry": {"coordinates":[-77.96518,43.341631],"type":"Point"}
}