{
  "type": "Feature",
  "properties": {
    "addr:full":"205 E 16 St New York NY 10003",
    "addr:housenumber":"205;16",
    "addr:postcode":"10003",
    "addr:street":"E",
    "iso:country":"US",
    "sg:address":"205 E 16 St",
    "sg:city":"New York",
    "sg:classifiers":[
        {
            "category":"Professional",
            "type":"Services"
        }
    ],
    "sg:phone":"+1 212 677 0866",
    "sg:postcode":"10003",
    "sg:province":"NY",
    "sg:tags":[
        "establishment"
    ],
    "wof:name":"Galtville LLC",
    "wof:placetype":"venue"
},
  "geometry": {"coordinates":[-73.98477200000001,40.734012],"type":"Point"}
}