{
  "type": "Feature",
  "properties": {
    "addr:full":"362 W 23rd St New York NY 10011",
    "addr:housenumber":"362",
    "addr:postcode":"10011",
    "addr:street":"W 23Rd St",
    "iso:country":"US",
    "sg:address":"362 W 23rd St",
    "sg:city":"New York",
    "sg:classifiers":[
        {
            "category":"Restaurant",
            "type":"Food & Drink"
        }
    ],
    "sg:menulink":"http://www.allmenus.com/ny/new-york/2703-negril-chelsea/menu/",
    "sg:phone":"+1 212 807 6411",
    "sg:postcode":"10011",
    "sg:province":"NY",
    "sg:tags":[
        "caribbean"
    ],
    "wof:name":"Negril Chelsea",
    "wof:placetype":"venue"
},
  "geometry": {"coordinates":[-74.001081,40.746132],"type":"Point"}
}