{
  "type": "Feature",
  "properties": {
    "addr:full":"60 Jordache Ln Spencerport NY 14559",
    "addr:housenumber":"60",
    "addr:postcode":"14559",
    "addr:street":"Jordache Ln",
    "iso:country":"US",
    "sg:address":"60 Jordache Ln",
    "sg:city":"Spencerport",
    "sg:classifiers":[
        {
            "category":"Shopping",
            "subcategory":"Shoes",
            "type":"Retail Goods"
        }
    ],
    "sg:phone":"+1   ",
    "sg:postcode":"14559",
    "sg:province":"NY",
    "sg:tags":[
        "parlor",
        "shoe"
    ],
    "wof:name":"Sofia Shoe Service",
    "wof:placetype":"venue"
},
  "geometry": {"coordinates":[-77.756224,43.17037],"type":"Point"}
}