{
  "type": "Feature",
  "properties": {
    "addr:full":"1048 Raymond Rd Ballston Spa NY 12020",
    "addr:housenumber":"1048",
    "addr:postcode":"12020",
    "addr:street":"Raymond Rd",
    "iso:country":"US",
    "sg:address":"1048 Raymond Rd",
    "sg:city":"Ballston Spa",
    "sg:classifiers":[
        {
            "category":"Building & Trades",
            "subcategory":"Construction",
            "type":"Services"
        }
    ],
    "sg:phone":"+1 518 885 9725",
    "sg:postcode":"12020",
    "sg:province":"NY",
    "sg:tags":[
        "house"
    ],
    "wof:name":"JD Contracting",
    "wof:placetype":"venue"
},
  "geometry": {"coordinates":[-73.816585,42.9761],"type":"Point"}
}