{
  "type": "Feature",
  "properties": {
    "addr:full":"28 E 18th St New York NY 10003",
    "addr:housenumber":"28",
    "addr:postcode":"10003",
    "addr:street":"E 18Th St",
    "iso:country":"US",
    "sg:address":"28 E 18th St",
    "sg:city":"New York",
    "sg:classifiers":[
        {
            "category":"Restaurant",
            "type":"Food & Drink"
        }
    ],
    "sg:phone":"+1 212 228 1044",
    "sg:postcode":"10003",
    "sg:province":"NY",
    "sg:tags":[
        "korean"
    ],
    "sg:website":"www.mannakitchen.com",
    "wof:name":"Express Manna Kitchen",
    "wof:placetype":"venue"
},
  "geometry": {"coordinates":[-73.989998,40.737598],"type":"Point"}
}