{
  "type": "Feature",
  "properties": {
    "addr:full":"2781 Ocean Ave Brooklyn NY 11229",
    "addr:housenumber":"2781",
    "addr:postcode":"11229",
    "addr:street":"Ocean Ave",
    "iso:country":"US",
    "sg:address":"2781 Ocean Ave",
    "sg:city":"Brooklyn",
    "sg:classifiers":[
        {
            "category":"Shopping",
            "subcategory":"Jewelry",
            "type":"Retail Goods"
        }
    ],
    "sg:phone":"+1   ",
    "sg:postcode":"11229",
    "sg:province":"NY",
    "wof:name":"Yigal Jewelry Designs",
    "wof:placetype":"venue"
},
  "geometry": {"coordinates":[-73.950271,40.594107],"type":"Point"}
}