{
  "type": "Feature",
  "properties": {
    "iso:country":"US",
    "sg:address":"105 Maple Rd",
    "sg:city":"Buffalo",
    "sg:classifiers":[
        {
            "category":"Manufacturing",
            "subcategory":"Food",
            "type":"Manufacturing & Wholesale Goods"
        },
        {
            "category":"Food & Beverages",
            "subcategory":"Groceries & Convenience Stores",
            "type":"Retail Goods"
        }
    ],
    "sg:phone":"+1 716 565 0754",
    "sg:postcode":"14221",
    "sg:province":"NY",
    "sg:tags":[
        "product"
    ],
    "wof:name":"Va'ad Hakashrus Of Buffalo",
    "wof:placetype":"venue"
},
  "geometry": {"coordinates":[-78.784306,42.991318],"type":"Point"}
}