{
  "type": "Feature",
  "properties": {
    "addr:full":"738 E Delavan Ave Buffalo NY 14215",
    "addr:housenumber":"738",
    "addr:postcode":"14215",
    "addr:street":"E Delavan Ave",
    "iso:country":"US",
    "sg:address":"738 E Delavan Ave",
    "sg:city":"Buffalo",
    "sg:classifiers":[
        {
            "category":"Shopping",
            "subcategory":"Department Store",
            "type":"Retail Goods"
        }
    ],
    "sg:phone":"+1 716 892 2705",
    "sg:postcode":"14215",
    "sg:province":"NY",
    "sg:tags":[
        "variety"
    ],
    "sg:website":"http://www.familydollar.com",
    "wof:name":"Family Dollar Stores",
    "wof:placetype":"venue"
},
  "geometry": {"coordinates":[-78.829712,42.922111],"type":"Point"}
}