{
  "type": "Feature",
  "properties": {
    "addr:full":"7954 Transit Rd Williamsville NY 14221",
    "addr:housenumber":"7954",
    "addr:postcode":"14221",
    "addr:street":"Transit Rd",
    "iso:country":"US",
    "sg:address":"7954 Transit Rd",
    "sg:city":"Williamsville",
    "sg:classifiers":[
        {
            "category":"Professional",
            "subcategory":"Advertising",
            "type":"Services"
        }
    ],
    "sg:phone":"+1 716 632 7911",
    "sg:postcode":"14221",
    "sg:province":"NY",
    "sg:tags":[
        "mailing",
        "shipping"
    ],
    "wof:name":"UPS Store",
    "wof:placetype":"venue"
},
  "geometry": {"coordinates":[-78.697028,42.985865],"type":"Point"}
}