{
  "type": "Feature",
  "properties": {
    "iso:country":"US",
    "sg:address":"36-05 30th Ave",
    "sg:city":"New York",
    "sg:classifiers":[
        {
            "category":"Bars & Pubs",
            "subcategory":"Lounge",
            "type":"Food & Drink"
        }
    ],
    "sg:phone":"+1 718 715 4420",
    "sg:postcode":"11103",
    "sg:province":"NY",
    "sg:website":"www.revelrylounge.com",
    "wof:name":"Revelry Lounge",
    "wof:placetype":"venue"
},
  "geometry": {"coordinates":[-73.917091,40.764958],"type":"Point"}
}