{
  "type": "Feature",
  "properties": {
    "addr:full":"925 State Fair Blvd Syracuse NY 13209",
    "addr:housenumber":"925",
    "addr:postcode":"13209",
    "addr:street":"State Fair Blvd",
    "iso:country":"US",
    "sg:address":"925 State Fair Blvd",
    "sg:city":"Syracuse",
    "sg:classifiers":[
        {
            "category":"Building & Trades",
            "subcategory":"Electrical",
            "type":"Services"
        }
    ],
    "sg:phone":"+1 315 468 9783",
    "sg:postcode":"13209",
    "sg:province":"NY",
    "sg:tags":[
        "house",
        "electrical",
        "contractor"
    ],
    "wof:name":"Ncs Home Inc",
    "wof:placetype":"venue"
},
  "geometry": {"coordinates":[-76.245289,43.096082],"type":"Point"}
}