{
  "type": "Feature",
  "properties": {
    "addr:full":"376 Grant Blvd Syracuse NY 13206",
    "addr:housenumber":"376",
    "addr:postcode":"13206",
    "addr:street":"Grant Blvd",
    "iso:country":"US",
    "sg:address":"376 Grant Blvd",
    "sg:city":"Syracuse",
    "sg:classifiers":[
        {
            "category":"Shopping",
            "subcategory":"Computers & Home Electronics",
            "type":"Retail Goods"
        }
    ],
    "sg:phone":"+1 315 447 1120",
    "sg:postcode":"13206",
    "sg:province":"NY",
    "sg:tags":[
        "equipment",
        "dealer"
    ],
    "wof:name":"Computerz Central Inc",
    "wof:placetype":"venue"
},
  "geometry": {"coordinates":[-76.12032600000001,43.070968],"type":"Point"}
}