{
  "type": "Feature",
  "properties": {
    "addr:full":"26 E 40th Street Manhattan NY 10016",
    "addr:housenumber":"26",
    "addr:postcode":"10016",
    "addr:street":"E 40Th Street",
    "iso:country":"US",
    "sg:address":"26 E 40th Street",
    "sg:city":"Manhattan",
    "sg:classifiers":[
        {
            "category":"Deli",
            "type":"Food & Drink"
        },
        {
            "category":"Food & Beverages",
            "subcategory":"Bakery",
            "type":"Retail Goods"
        },
        {
            "category":"Professional",
            "subcategory":"Business Services",
            "type":"Services"
        }
    ],
    "sg:phone":"+1 212 687 0005",
    "sg:postcode":"10016",
    "sg:province":"NY",
    "sg:tags":[
        "delivery",
        "sandwich"
    ],
    "sg:website":"www.foodmerchantscafe.com",
    "wof:name":"Food Merchants Cafe",
    "wof:placetype":"venue"
},
  "geometry": {"coordinates":[-73.97975700000001,40.751303],"type":"Point"}
}