{
  "type": "Feature",
  "properties": {
    "addr:full":"318 Merrick Rd Amityville NY 11701",
    "addr:housenumber":"318",
    "addr:postcode":"11701",
    "addr:street":"Merrick Rd",
    "iso:country":"US",
    "sg:address":"318 Merrick Rd",
    "sg:city":"Amityville",
    "sg:classifiers":[
        {
            "category":"Autos & Motor Vehicles",
            "subcategory":"Fuel & Gas Station",
            "type":"Retail Goods"
        }
    ],
    "sg:phone":"+1 631 598 3330",
    "sg:postcode":"11701",
    "sg:province":"NY",
    "sg:tags":[
        "oil"
    ],
    "wof:name":"Sunoco",
    "wof:placetype":"venue"
},
  "geometry": {"coordinates":[-73.412227,40.66988],"type":"Point"}
}