{
  "type": "Feature",
  "properties": {
    "addr:full":"470 Port Richmond Ave Staten Island NY 10302",
    "addr:housenumber":"470",
    "addr:postcode":"10302",
    "addr:street":"Port Richmond Ave",
    "iso:country":"US",
    "sg:address":"470 Port Richmond Ave",
    "sg:city":"Staten Island",
    "sg:classifiers":[
        {
            "category":"Food & Beverages",
            "subcategory":"Bakery",
            "type":"Retail Goods"
        }
    ],
    "sg:phone":"+1 718 420 0112",
    "sg:postcode":"10302",
    "sg:province":"NY",
    "sg:tags":[
        "bagel"
    ],
    "wof:name":"Done Rite Bagels",
    "wof:placetype":"venue"
},
  "geometry": {"coordinates":[-74.13893400000001,40.631171],"type":"Point"}
}