{
  "type": "Feature",
  "properties": {
    "iso:country":"US",
    "sg:address":"300 Alpine Dr",
    "sg:city":"Cortlandt Manor",
    "sg:classifiers":[
        {
            "category":"Shopping",
            "subcategory":"Jewelry",
            "type":"Retail Goods"
        }
    ],
    "sg:phone":"+1 914 245 3305",
    "sg:postcode":"10567",
    "sg:province":"NY",
    "sg:tags":[
        "jeweler"
    ],
    "wof:name":"L J Wendy & Co",
    "wof:placetype":"venue"
},
  "geometry": {"coordinates":[-73.88831999999999,41.318433],"type":"Point"}
}