{
  "type": "Feature",
  "properties": {
    "iso:country":"US",
    "sg:address":"178 Industrial Loop",
    "sg:city":"Staten Island",
    "sg:classifiers":[
        {
            "category":"Wholesale",
            "subcategory":"Drugs",
            "type":"Manufacturing & Wholesale Goods"
        }
    ],
    "sg:phone":"+1 718 227 7016",
    "sg:postcode":"10309",
    "sg:province":"NY",
    "sg:tags":[
        "pharmaceutical",
        "product"
    ],
    "wof:name":"Americare Pharmaceutical Svc",
    "wof:placetype":"venue"
},
  "geometry": {"coordinates":[-74.23116400000001,40.548602],"type":"Point"}
}