{
  "type": "Feature",
  "properties": {
    "addr:full":"3030 Merrick Rd Wantagh NY 11793",
    "addr:housenumber":"3030",
    "addr:postcode":"11793",
    "addr:street":"Merrick Rd",
    "iso:country":"US",
    "sg:address":"3030 Merrick Rd",
    "sg:city":"Wantagh",
    "sg:classifiers":[
        {
            "category":"Personal",
            "subcategory":"Beauty Salon",
            "type":"Services"
        }
    ],
    "sg:phone":"+1 516 781 2649",
    "sg:postcode":"11793",
    "sg:province":"NY",
    "sg:tags":[
        "manicuring"
    ],
    "wof:name":"White Angel Nails",
    "wof:placetype":"venue"
},
  "geometry": {"coordinates":[-73.51424,40.663365],"type":"Point"}
}