{
  "type": "Feature",
  "properties": {
    "iso:country":"US",
    "sg:address":"998 Briarwood Dr",
    "sg:city":"Jamestown",
    "sg:classifiers":[
        {
            "category":"Building & Trades",
            "subcategory":"Construction",
            "type":"Services"
        }
    ],
    "sg:phone":"+1 716 665 1020",
    "sg:postcode":"14750",
    "sg:province":"NY",
    "sg:tags":[
        "residential"
    ],
    "wof:name":"Carlton Homes",
    "wof:placetype":"venue"
},
  "geometry": {"coordinates":[-79.32843,42.090891],"type":"Point"}
}