{
  "type": "Feature",
  "properties": {
    "iso:country":"US",
    "sg:address":"6935 Burke Hill Rd",
    "sg:city":"Perry",
    "sg:classifiers":[
        {
            "category":"Farming",
            "subcategory":"Dairy Farm",
            "type":"Manufacturing & Wholesale Goods"
        },
        {
            "category":"Farming",
            "subcategory":"Farm",
            "type":"Manufacturing & Wholesale Goods"
        }
    ],
    "sg:phone":"+1 585 237 3233",
    "sg:postcode":"14530",
    "sg:province":"NY",
    "sg:website":"http://www.woodvalefarms.com",
    "wof:name":"Robert Harwood",
    "wof:placetype":"venue"
},
  "geometry": {"coordinates":[-78.018446,42.778252],"type":"Point"}
}