{
  "type": "Feature",
  "properties": {
    "addr:full":"18 Sibley Pl Rochester NY 14607",
    "addr:housenumber":"18",
    "addr:postcode":"14607",
    "addr:street":"Sibley Pl",
    "iso:country":"US",
    "sg:address":"18 Sibley Pl",
    "sg:city":"Rochester",
    "sg:classifiers":[
        {
            "category":"Manufacturing",
            "subcategory":"Tools & Machinery",
            "type":"Manufacturing & Wholesale Goods"
        }
    ],
    "sg:phone":"+1   ",
    "sg:postcode":"14607",
    "sg:province":"NY",
    "sg:tags":[
        "mfg"
    ],
    "wof:name":"Bill Saunders",
    "wof:placetype":"venue"
},
  "geometry": {"coordinates":[-77.592974,43.152635],"type":"Point"}
}