{
  "type": "Feature",
  "properties": {
    "iso:country":"US",
    "sg:address":"252 W 31st St 4th Floor",
    "sg:city":"New York",
    "sg:classifiers":[
        {
            "category":"Professional",
            "type":"Services"
        }
    ],
    "sg:phone":"+1 646 208 5798",
    "sg:postcode":"10001",
    "sg:province":"NY",
    "sg:website":"www.grinstylez.com/",
    "wof:name":"Fort Apache Studio",
    "wof:placetype":"venue"
},
  "geometry": {"coordinates":[-73.994252,40.749896],"type":"Point"}
}