{
  "type": "Feature",
  "properties": {
    "addr:full":"68 Central Park W New York NY 10023",
    "addr:housenumber":"68",
    "addr:postcode":"10023",
    "addr:street":"Central Park W",
    "iso:country":"US",
    "sg:address":"68 Central Park W",
    "sg:city":"New York",
    "sg:classifiers":[
        {
            "category":"Building & Trades",
            "subcategory":"Plumbing",
            "type":"Services"
        }
    ],
    "sg:phone":"+1 212 937 1139",
    "sg:postcode":"10023",
    "sg:province":"NY",
    "sg:tags":[
        "plumbing",
        "contractor"
    ],
    "wof:name":"AA1 24 Hour Plumbing",
    "wof:placetype":"venue"
},
  "geometry": {"coordinates":[-73.977467,40.774259],"type":"Point"}
}