{
  "type": "Feature",
  "properties": {
    "addr:full":"36 Sutton Pl S New York NY 10022",
    "addr:housenumber":"36",
    "addr:postcode":"10022",
    "addr:street":"Sutton Pl S",
    "iso:country":"US",
    "sg:address":"36 Sutton Pl S",
    "sg:city":"New York",
    "sg:classifiers":[
        {
            "category":"Manufacturing",
            "subcategory":"Printing",
            "type":"Manufacturing & Wholesale Goods"
        }
    ],
    "sg:phone":"+1 212 406 7515",
    "sg:postcode":"10022",
    "sg:province":"NY",
    "sg:tags":[
        "printer"
    ],
    "wof:name":"Angelo De Caprio",
    "wof:placetype":"venue"
},
  "geometry": {"coordinates":[-73.96151,40.75621],"type":"Point"}
}