{
  "type": "Feature",
  "properties": {
    "iso:country":"US",
    "sg:address":"85 Oneida River Rd",
    "sg:city":"Pennellville",
    "sg:classifiers":[
        {
            "category":"Shopping",
            "subcategory":"Computers & Home Electronics",
            "type":"Retail Goods"
        }
    ],
    "sg:phone":"+1 315 695 7161",
    "sg:postcode":"13132",
    "sg:province":"NY",
    "sg:tags":[
        "equipment",
        "satellite",
        "system"
    ],
    "wof:name":"Stellar Electric & Comms",
    "wof:placetype":"venue"
},
  "geometry": {"coordinates":[-76.231528,43.211574],"type":"Point"}
}