{
  "type": "Feature",
  "properties": {
    "iso:country":"US",
    "sg:address":"22 Dartmouth Dr",
    "sg:city":"Smithtown",
    "sg:classifiers":[
        {
            "category":"Building & Trades",
            "subcategory":"Landscaping Services",
            "type":"Services"
        }
    ],
    "sg:phone":"+1 631 979 8230",
    "sg:postcode":"11787",
    "sg:province":"NY",
    "wof:name":"Malloy Lawn Care",
    "wof:placetype":"venue"
},
  "geometry": {"coordinates":[-73.173239,40.862921],"type":"Point"}
}