{
  "type": "Feature",
  "properties": {
    "addr:full":"375 W Broadway New York NY 10012",
    "addr:housenumber":"375",
    "addr:postcode":"10012",
    "addr:street":"W Broadway",
    "iso:country":"US",
    "sg:address":"375 W Broadway",
    "sg:city":"New York",
    "sg:classifiers":[
        {
            "category":"Personal",
            "subcategory":"Beauty Salon",
            "type":"Services"
        }
    ],
    "sg:phone":"+1 212 941 1296",
    "sg:postcode":"10012",
    "sg:province":"NY",
    "sg:tags":[
        "manicuring"
    ],
    "wof:name":"Design Nails",
    "wof:placetype":"venue"
},
  "geometry": {"coordinates":[-74.002002,40.724303],"type":"Point"}
}