{
  "type": "Feature",
  "properties": {
    "addr:full":"1078 Morton Blvd Kingston NY 12401",
    "addr:housenumber":"1078",
    "addr:postcode":"12401",
    "addr:street":"Morton Blvd",
    "iso:country":"US",
    "sg:address":"1078 Morton Blvd",
    "sg:city":"Kingston",
    "sg:classifiers":[
        {
            "category":"Restaurant",
            "type":"Food & Drink"
        }
    ],
    "sg:phone":"+1 845 382 1010",
    "sg:postcode":"12401",
    "sg:province":"NY",
    "sg:tags":[
        "pizza"
    ],
    "wof:name":"Savona's Plaza Pizza",
    "wof:placetype":"venue"
},
  "geometry": {"coordinates":[-73.992969,41.960726],"type":"Point"}
}