{
  "type": "Feature",
  "properties": {
    "iso:country":"US",
    "sg:address":"2010 Coney Island Ave",
    "sg:city":"Brooklyn",
    "sg:classifiers":[
        {
            "category":"Wholesale",
            "subcategory":"Office Equipment",
            "type":"Manufacturing & Wholesale Goods"
        }
    ],
    "sg:phone":"+1 718 266 0870",
    "sg:postcode":"11223",
    "sg:province":"NY",
    "sg:tags":[
        "retail",
        "cash",
        "register"
    ],
    "wof:name":"New York Cash Register Co Inc",
    "wof:placetype":"venue"
},
  "geometry": {"coordinates":[-73.9623,40.609609],"type":"Point"}
}