{
  "type": "Feature",
  "properties": {
    "addr:full":"24 Noel Ln Jericho NY 11753",
    "addr:housenumber":"24",
    "addr:postcode":"11753",
    "addr:street":"Noel Ln",
    "iso:country":"US",
    "sg:address":"24 Noel Ln",
    "sg:city":"Jericho",
    "sg:classifiers":[
        {
            "category":"Wholesale",
            "subcategory":"Auto Parts",
            "type":"Manufacturing & Wholesale Goods"
        }
    ],
    "sg:phone":"+1 516 681 9110",
    "sg:postcode":"11753",
    "sg:province":"NY",
    "sg:tags":[
        "used"
    ],
    "wof:name":"Belmont Automotive Co Inc",
    "wof:placetype":"venue"
},
  "geometry": {"coordinates":[-73.529826,40.804524],"type":"Point"}
}