{
  "type": "Feature",
  "properties": {
    "iso:country":"US",
    "sg:address":"1115 West St",
    "sg:city":"Utica",
    "sg:classifiers":[
        {
            "category":"Social Services",
            "subcategory":"Child Care",
            "type":"Services"
        }
    ],
    "sg:phone":"+1 315 735 3215",
    "sg:postcode":"13501",
    "sg:province":"NY",
    "sg:tags":[
        "day"
    ],
    "wof:name":"Day St Pauls Care Center",
    "wof:placetype":"venue"
},
  "geometry": {"coordinates":[-75.234517,43.094191],"type":"Point"}
}