{
  "type": "Feature",
  "properties": {
    "addr:full":"315 State Hwy 59 Nanuet NY 10954",
    "addr:housenumber":"315",
    "addr:postcode":"10954",
    "addr:street":"State Hwy 59",
    "iso:country":"US",
    "sg:address":"315 State Hwy 59",
    "sg:city":"Nanuet",
    "sg:classifiers":[
        {
            "category":"Real Estate",
            "subcategory":"Real Estate Operator",
            "type":"Services"
        }
    ],
    "sg:phone":"+1 845 623 5848",
    "sg:postcode":"10954",
    "sg:province":"NY",
    "sg:tags":[
        "co",
        "holding"
    ],
    "wof:name":"Wargo Realty Corp",
    "wof:placetype":"venue"
},
  "geometry": {"coordinates":[-74.003693,41.093989],"type":"Point"}
}