{
  "type": "Feature",
  "properties": {
    "addr:full":"306 Main St Huntington NY 11743",
    "addr:housenumber":"306",
    "addr:postcode":"11743",
    "addr:street":"Main St",
    "iso:country":"US",
    "sg:address":"306 Main St",
    "sg:city":"Huntington",
    "sg:classifiers":[
        {
            "category":"Restaurant",
            "type":"Food & Drink"
        }
    ],
    "sg:phone":"+1   ",
    "sg:postcode":"11743",
    "sg:province":"NY",
    "sg:tags":[
        "eating"
    ],
    "wof:name":"Fishers Catering",
    "wof:placetype":"venue"
},
  "geometry": {"coordinates":[-73.42782200000001,40.870959],"type":"Point"}
}