{
  "type": "Feature",
  "properties": {
    "addr:full":"1405 Deer Park Ave North Babylon NY 11703",
    "addr:housenumber":"1405",
    "addr:postcode":"11703",
    "addr:street":"Deer Park Ave North",
    "iso:country":"US",
    "sg:address":"1405 Deer Park Ave",
    "sg:city":"North Babylon",
    "sg:classifiers":[
        {
            "category":"Professional",
            "subcategory":"Accounting & Tax Preparation",
            "type":"Services"
        }
    ],
    "sg:phone":"+1 631 242 6700",
    "sg:postcode":"11703",
    "sg:province":"NY",
    "sg:tags":[
        "accountant"
    ],
    "wof:name":"Data Processing",
    "wof:placetype":"venue"
},
  "geometry": {"coordinates":[-73.322714,40.744932],"type":"Point"}
}