{
  "type": "Feature",
  "properties": {
    "addr:full":"3278 Union St North Chili NY 14514",
    "addr:housenumber":"3278",
    "addr:postcode":"14514",
    "addr:street":"Union St",
    "iso:country":"US",
    "sg:address":"3278 Union St",
    "sg:city":"North Chili",
    "sg:classifiers":[
        {
            "category":"Organizations",
            "subcategory":"Non-profit Organization",
            "type":"Services"
        }
    ],
    "sg:phone":"+1 585 594 0649",
    "sg:postcode":"14514",
    "sg:province":"NY",
    "wof:name":"Lions Club Of Chili Medical",
    "wof:placetype":"venue"
},
  "geometry": {"coordinates":[-77.805088,43.119549],"type":"Point"}
}