{
  "type": "Feature",
  "properties": {
    "addr:full":"3008 Merrick Rd Wantagh NY 11710",
    "addr:housenumber":"3008",
    "addr:postcode":"11710",
    "addr:street":"Merrick Rd",
    "iso:country":"US",
    "sg:address":"3008 Merrick Rd",
    "sg:city":"Wantagh",
    "sg:classifiers":[
        {
            "category":"Professional",
            "subcategory":"Computer Services",
            "type":"Services"
        }
    ],
    "sg:phone":"+1 516 409 6722",
    "sg:postcode":"11710",
    "sg:province":"NY",
    "wof:name":"Cyber Reality Communications",
    "wof:placetype":"venue"
},
  "geometry": {"coordinates":[-73.515156,40.663642],"type":"Point"}
}