{
  "type": "Feature",
  "properties": {
    "addr:full":"392 Bicycle Path Port Jefferson Station NY 11776",
    "addr:postcode":"11776",
    "addr:street":"Bicycle Path",
    "iso:country":"US",
    "sg:address":"392 Bicycle Path",
    "sg:city":"Port Jefferson Station",
    "sg:classifiers":[
        {
            "category":"Building & Trades",
            "subcategory":"Construction",
            "type":"Services"
        }
    ],
    "sg:phone":"+1 631 331 5602",
    "sg:postcode":"11776",
    "sg:province":"NY",
    "sg:tags":[
        "hanging",
        "contractor"
    ],
    "wof:name":"Tommys Painting",
    "wof:placetype":"venue"
},
  "geometry": {"coordinates":[-73.035606,40.89197],"type":"Point"}
}