{
  "type": "Feature",
  "properties": {
    "addr:full":"715 Herman Rd Webster NY 14580",
    "addr:housenumber":"715",
    "addr:postcode":"14580",
    "addr:street":"Herman Rd",
    "iso:country":"US",
    "sg:address":"715 Herman Rd",
    "sg:city":"Webster",
    "sg:classifiers":[
        {
            "category":"Building & Trades",
            "subcategory":"Landscaping Services",
            "type":"Services"
        }
    ],
    "sg:phone":"+1 585 671 8432",
    "sg:postcode":"14580",
    "sg:province":"NY",
    "sg:tags":[
        "tree"
    ],
    "wof:name":"Gary A St James Landscaping",
    "wof:placetype":"venue"
},
  "geometry": {"coordinates":[-77.486553,43.240541],"type":"Point"}
}