{
  "type": "Feature",
  "properties": {
    "addr:full":"5752 Transit Rd Depew NY 14043",
    "addr:housenumber":"5752",
    "addr:postcode":"14043",
    "addr:street":"Transit Rd",
    "iso:country":"US",
    "sg:address":"5752 Transit Rd",
    "sg:city":"Depew",
    "sg:classifiers":[
        {
            "category":"Retail",
            "subcategory":"Auto Repair",
            "type":"Services"
        }
    ],
    "sg:phone":"+1   ",
    "sg:postcode":"14043",
    "sg:province":"NY",
    "sg:tags":[
        "shop",
        "automotive",
        "radiator",
        "air"
    ],
    "wof:name":"Bauer Radiator & Automotive",
    "wof:placetype":"venue"
},
  "geometry": {"coordinates":[-78.696997,42.912607],"type":"Point"}
}