{
  "type": "Feature",
  "properties": {
    "addr:full":"207 Canal St New York NY 10013",
    "addr:housenumber":"207",
    "addr:postcode":"10013",
    "addr:street":"Canal St",
    "iso:country":"US",
    "sg:address":"207 Canal St",
    "sg:city":"New York",
    "sg:classifiers":[
        {
            "category":"Real Estate",
            "subcategory":"Real Estate Agent",
            "type":"Services"
        }
    ],
    "sg:phone":"+1 212 226 1520",
    "sg:postcode":"10013",
    "sg:province":"NY",
    "sg:tags":[
        "management"
    ],
    "wof:name":"1960 Williamsbridge Road",
    "wof:placetype":"venue"
},
  "geometry": {"coordinates":[-73.999128,40.717494],"type":"Point"}
}