{
  "type": "Feature",
  "properties": {
    "addr:full":"5271 Crittenden Rd Akron NY 14001",
    "addr:housenumber":"5271",
    "addr:postcode":"14001",
    "addr:street":"Crittenden Rd",
    "iso:country":"US",
    "sg:address":"5271 Crittenden Rd",
    "sg:city":"Akron",
    "sg:classifiers":[
        {
            "category":"Wholesale",
            "subcategory":"Hardware",
            "type":"Manufacturing & Wholesale Goods"
        },
        {
            "category":"Home & Garden",
            "subcategory":"Garden Supply",
            "type":"Retail Goods"
        },
        {
            "category":"Retail",
            "subcategory":"Repair Shop",
            "type":"Services"
        }
    ],
    "sg:phone":"+1 716 542 9839",
    "sg:postcode":"14001",
    "sg:province":"NY",
    "sg:tags":[
        "renting",
        "lawn",
        "outdoor",
        "power",
        "landscaping",
        "equipment-sales",
        "equipment",
        "saw"
    ],
    "sg:website":"http://www.stihlusa.com/",
    "wof:name":"Woodcutters Headquarters, Inc",
    "wof:placetype":"venue"
},
  "geometry": {"coordinates":[-78.477763,42.988701],"type":"Point"}
}