{
  "type": "Feature",
  "properties": {
    "addr:full":"765 Pawling Ave Troy NY 12180",
    "addr:housenumber":"765",
    "addr:postcode":"12180",
    "addr:street":"Pawling Ave",
    "iso:country":"US",
    "sg:address":"765 Pawling Ave",
    "sg:city":"Troy",
    "sg:classifiers":[
        {
            "category":"Health Services",
            "subcategory":"Doctor",
            "type":"Services"
        }
    ],
    "sg:phone":"+1   ",
    "sg:postcode":"12180",
    "sg:province":"NY",
    "wof:name":"Dr Vaccarro",
    "wof:placetype":"venue"
},
  "geometry": {"coordinates":[-73.65356199999999,42.700772],"type":"Point"}
}