{
  "type": "Feature",
  "properties": {
    "iso:country":"US",
    "sg:address":"3 Handley St",
    "sg:city":"Perry",
    "sg:classifiers":[
        {
            "category":"Health Services",
            "subcategory":"Health Practitioner",
            "type":"Services"
        }
    ],
    "sg:phone":"+1   ",
    "sg:postcode":"14530",
    "sg:province":"NY",
    "wof:name":"Step By Step Pt",
    "wof:placetype":"venue"
},
  "geometry": {"coordinates":[-77.995233,42.717616],"type":"Point"}
}