{
  "type": "Feature",
  "properties": {
    "addr:full":"11 Pruyn St Albany NY 12207",
    "addr:housenumber":"11",
    "addr:postcode":"12207",
    "addr:street":"Pruyn St",
    "iso:country":"US",
    "sg:address":"11 Pruyn St",
    "sg:city":"Albany",
    "sg:classifiers":[
        {
            "category":"Education",
            "subcategory":"College",
            "type":"Public Place"
        }
    ],
    "sg:phone":"+1 518 443 5662",
    "sg:postcode":"12207",
    "sg:province":"NY",
    "sg:tags":[
        "academic",
        "school"
    ],
    "wof:name":"State University Of New York",
    "wof:placetype":"venue"
},
  "geometry": {"coordinates":[-73.750816,42.645732],"type":"Point"}
}