{
  "type": "Feature",
  "properties": {
    "addr:full":"34 W 28 St New York NY 10001",
    "addr:housenumber":"34",
    "addr:postcode":"10001",
    "addr:street":"W 28 St",
    "iso:country":"US",
    "sg:address":"34 W 28 St",
    "sg:city":"New York",
    "sg:classifiers":[
        {
            "category":"Professional",
            "type":"Services"
        }
    ],
    "sg:phone":"+1 212 532 5787",
    "sg:postcode":"10001",
    "sg:province":"NY",
    "sg:tags":[
        "arts",
        "artist"
    ],
    "wof:name":"Gregory Kitchen Photographic",
    "wof:placetype":"venue"
},
  "geometry": {"coordinates":[-73.99031100000001,40.745837],"type":"Point"}
}