{
  "type": "Feature",
  "properties": {
    "addr:full":"132 Nethermont Ave White Plains NY 10603",
    "addr:housenumber":"132",
    "addr:postcode":"10603",
    "addr:street":"Nethermont Ave",
    "iso:country":"US",
    "sg:address":"132 Nethermont Ave",
    "sg:city":"White Plains",
    "sg:classifiers":[
        {
            "category":"Wholesale",
            "subcategory":"Meat",
            "type":"Manufacturing & Wholesale Goods"
        }
    ],
    "sg:phone":"+1 914 949 7665",
    "sg:postcode":"10603",
    "sg:province":"NY",
    "wof:name":"Meadowbrook Provisions Inc",
    "wof:placetype":"venue"
},
  "geometry": {"coordinates":[-73.764909,41.062814],"type":"Point"}
}