{
  "type": "Feature",
  "properties": {
    "iso:country":"US",
    "sg:address":"587 3rd Ave",
    "sg:city":"Brooklyn",
    "sg:classifiers":[
        {
            "category":"Autos & Motor Vehicles",
            "subcategory":"Auto Supplies",
            "type":"Retail Goods"
        }
    ],
    "sg:phone":"+1 718 832 3920",
    "sg:postcode":"11215",
    "sg:province":"NY",
    "sg:tags":[
        "tire"
    ],
    "wof:name":"Orio Tire Shop",
    "wof:placetype":"venue"
},
  "geometry": {"coordinates":[-73.99430099999999,40.667301],"type":"Point"}
}