{
  "type": "Feature",
  "properties": {
    "iso:country":"US",
    "sg:address":"3 Hugh J Grant Cir",
    "sg:city":"Bronx",
    "sg:classifiers":[
        {
            "category":"Shopping",
            "subcategory":"Photographic Equipment",
            "type":"Retail Goods"
        }
    ],
    "sg:phone":"+1   ",
    "sg:postcode":"10462",
    "sg:province":"NY",
    "sg:tags":[
        "camera",
        "accessory"
    ],
    "wof:name":"Parkchester Photo",
    "wof:placetype":"venue"
},
  "geometry": {"coordinates":[-73.860851,40.833614],"type":"Point"}
}