{
  "type": "Feature",
  "properties": {
    "addr:full":"156 5th Ave New York NY 10010",
    "addr:housenumber":"156",
    "addr:postcode":"10010",
    "addr:street":"5Th Ave",
    "iso:country":"US",
    "sg:address":"156 5th Ave",
    "sg:city":"New York",
    "sg:classifiers":[
        {
            "category":"Professional",
            "subcategory":"Management & Consulting",
            "type":"Services"
        }
    ],
    "sg:phone":"+1 212 675 9474",
    "sg:postcode":"10010",
    "sg:province":"NY",
    "sg:tags":[
        "fund",
        "raising",
        "consultant"
    ],
    "wof:name":"Susan Ulin Associates Ltd",
    "wof:placetype":"venue"
},
  "geometry": {"coordinates":[-73.990692,40.740101],"type":"Point"}
}