{
  "type": "Feature",
  "properties": {
    "addr:full":"416 Clarkson Hamlin Town Line Rd Hamlin NY 14464",
    "addr:housenumber":"416",
    "addr:postcode":"14464",
    "addr:street":"Clarkson Hamlin Town Line Rd",
    "iso:country":"US",
    "sg:address":"416 Clarkson Hamlin Town Line Rd",
    "sg:city":"Hamlin",
    "sg:classifiers":[
        {
            "category":"Restaurant",
            "type":"Food & Drink"
        }
    ],
    "sg:phone":"+1 585 964 7990",
    "sg:postcode":"14464",
    "sg:province":"NY",
    "wof:name":"North Of The Border Bar & Grll",
    "wof:placetype":"venue"
},
  "geometry": {"coordinates":[-77.919856,43.284575],"type":"Point"}
}