{
  "type": "Feature",
  "properties": {
    "iso:country":"US",
    "sg:address":"4591 State Hwy 21",
    "sg:city":"Atlanta",
    "sg:classifiers":[
        {
            "category":"Wholesale",
            "subcategory":"Construction Materials",
            "type":"Manufacturing & Wholesale Goods"
        }
    ],
    "sg:phone":"+1 585 534 5198",
    "sg:postcode":"14808",
    "sg:province":"NY",
    "wof:name":"Fleischman Farms Inc",
    "wof:placetype":"venue"
},
  "geometry": {"coordinates":[-77.458099,42.569367],"type":"Point"}
}