{
  "type": "Feature",
  "properties": {
    "iso:country":"US",
    "sg:address":"1865 Central Ave",
    "sg:city":"Albany",
    "sg:classifiers":[
        {
            "category":"Home & Garden",
            "subcategory":"Furniture",
            "type":"Retail Goods"
        }
    ],
    "sg:phone":"+1 518 456 7679",
    "sg:postcode":"12205",
    "sg:province":"NY",
    "wof:name":"Dining Furniture Ctr",
    "wof:placetype":"venue"
},
  "geometry": {"coordinates":[-73.84983699999999,42.732516],"type":"Point"}
}