{
  "type": "Feature",
  "properties": {
    "iso:country":"US",
    "sg:address":"32 Garfield Ave",
    "sg:city":"Endicott",
    "sg:classifiers":[
        {
            "category":"Shopping",
            "subcategory":"Optical Goods",
            "type":"Retail Goods"
        }
    ],
    "sg:phone":"+1   ",
    "sg:postcode":"13760",
    "sg:province":"NY",
    "wof:name":"Eye Contact By Kathy",
    "wof:placetype":"venue"
},
  "geometry": {"coordinates":[-76.047156,42.103278],"type":"Point"}
}