{
  "type": "Feature",
  "properties": {
    "addr:full":"1700 Bedford Ave Brooklyn NY 11225",
    "addr:housenumber":"1700",
    "addr:postcode":"11225",
    "addr:street":"Bedford Ave",
    "iso:country":"US",
    "sg:address":"1700 Bedford Ave",
    "sg:city":"Brooklyn",
    "sg:classifiers":[
        {
            "category":"Professional",
            "subcategory":"Employment Agencies",
            "type":"Services"
        }
    ],
    "sg:phone":"+1   ",
    "sg:postcode":"11225",
    "sg:province":"NY",
    "wof:name":"Ashley Wagner Agency",
    "wof:placetype":"venue"
},
  "geometry": {"coordinates":[-73.957229,40.665034],"type":"Point"}
}