{
  "type": "Feature",
  "properties": {
    "iso:country":"US",
    "sg:address":"69 E 167th St",
    "sg:city":"Bronx",
    "sg:classifiers":[
        {
            "category":"Banks & Credit Unions",
            "subcategory":"Financial Services",
            "type":"Services"
        }
    ],
    "sg:phone":"+1 718 292 2983",
    "sg:postcode":"10452",
    "sg:province":"NY",
    "wof:name":"Ariva",
    "wof:placetype":"venue"
},
  "geometry": {"coordinates":[-73.920328,40.835425],"type":"Point"}
}