{
  "type": "Feature",
  "properties": {
    "iso:country":"US",
    "sg:address":"6 W 33 St",
    "sg:city":"New York",
    "sg:classifiers":[
        {
            "category":"Wholesale",
            "subcategory":"Apparel",
            "type":"Manufacturing & Wholesale Goods"
        }
    ],
    "sg:phone":"+1 212 695 0103",
    "sg:postcode":"10001",
    "sg:province":"NY",
    "sg:tags":[
        "clothing"
    ],
    "wof:name":"Haddad & Sons LTD",
    "wof:placetype":"venue"
},
  "geometry": {"coordinates":[-73.98797999999999,40.748905],"type":"Point"}
}