{
  "type": "Feature",
  "properties": {
    "iso:country":"US",
    "sg:address":"40 South St",
    "sg:city":"Manorville",
    "sg:classifiers":[
        {
            "category":"Freight",
            "type":"Transportation"
        }
    ],
    "sg:phone":"+1   ",
    "sg:postcode":"11949",
    "sg:province":"NY",
    "sg:tags":[
        "forwarding",
        "contract",
        "carrier"
    ],
    "wof:name":"Jacks Nationwide Frt Fwdg Co",
    "wof:placetype":"venue"
},
  "geometry": {"coordinates":[-72.80257,40.851058],"type":"Point"}
}