{
  "type": "Feature",
  "properties": {
    "iso:country":"US",
    "sg:address":"47 Jackson Ave",
    "sg:city":"Buffalo",
    "sg:classifiers":[
        {
            "category":"Shopping",
            "subcategory":"Clothing, Apparel, & Fashions",
            "type":"Retail Goods"
        }
    ],
    "sg:phone":"+1   ",
    "sg:postcode":"14218",
    "sg:province":"NY",
    "wof:name":"Team Snyper",
    "wof:placetype":"venue"
},
  "geometry": {"coordinates":[-78.84413499999999,42.812542],"type":"Point"}
}