{
  "type": "Feature",
  "properties": {
    "addr:full":"Essex St and Canal St. New York NY 10002",
    "addr:postcode":"10002",
    "addr:street":"Essex St;St.",
    "iso:country":"US",
    "sg:address":"Essex St and Canal St.",
    "sg:city":"New York",
    "sg:classifiers":[
        {
            "category":"Park",
            "type":"Public Place"
        }
    ],
    "sg:postcode":"10002",
    "sg:province":"NY",
    "wof:name":"William H Seward Park",
    "wof:placetype":"venue"
},
  "geometry": {"coordinates":[-73.99020899999999,40.714415],"type":"Point"}
}