{
  "type": "Feature",
  "properties": {
    "iso:country":"US",
    "sg:address":"804 Fairmount Ave",
    "sg:city":"Jamestown",
    "sg:classifiers":[
        {
            "category":"Professional",
            "subcategory":"Advertising",
            "type":"Services"
        }
    ],
    "sg:phone":"+1 716 664 0235",
    "sg:postcode":"14701",
    "sg:province":"NY",
    "sg:tags":[
        "counselor"
    ],
    "sg:website":"www.unitedconcepts.com",
    "wof:name":"United Concepts Advertising",
    "wof:placetype":"venue"
},
  "geometry": {"coordinates":[-79.28407,42.097359],"type":"Point"}
}