{
  "type": "Feature",
  "properties": {
    "addr:full":"3859 10th Ave New York NY 10034",
    "addr:housenumber":"3859",
    "addr:postcode":"10034",
    "addr:street":"10Th Ave",
    "iso:country":"US",
    "sg:address":"3859 10th Ave",
    "sg:city":"New York",
    "sg:classifiers":[
        {
            "category":"Personal",
            "subcategory":"Barber",
            "type":"Services"
        }
    ],
    "sg:phone":"+1 212 304 0003",
    "sg:postcode":"10034",
    "sg:province":"NY",
    "wof:name":"L J Barber Shop & Hairroom Co Rp",
    "wof:placetype":"venue"
},
  "geometry": {"coordinates":[-73.91918800000001,40.863893],"type":"Point"}
}