{
  "type": "Feature",
  "properties": {
    "addr:full":"33 Irving Pl New York NY 10003",
    "addr:housenumber":"33",
    "addr:postcode":"10003",
    "addr:street":"Irving Pl",
    "iso:country":"US",
    "sg:address":"33 Irving Pl",
    "sg:city":"New York",
    "sg:classifiers":[
        {
            "category":"Professional",
            "type":"Services"
        },
        {
            "category":"Manufacturing",
            "subcategory":"Printing",
            "type":"Manufacturing & Wholesale Goods"
        }
    ],
    "sg:phone":"+1 212 475 8826",
    "sg:postcode":"10003",
    "sg:province":"NY",
    "sg:tags":[
        "development",
        "management",
        "computer",
        "establishment",
        "book",
        "software"
    ],
    "wof:name":"Metropolitan Teaching Lrng Co",
    "wof:placetype":"venue"
},
  "geometry": {"coordinates":[-73.988286,40.734659],"type":"Point"}
}