{
  "type": "Feature",
  "properties": {
    "addr:full":"221 E Hartsdale Ave Hartsdale NY 10530",
    "addr:housenumber":"221",
    "addr:postcode":"10530",
    "addr:street":"E Hartsdale Ave",
    "iso:country":"US",
    "sg:address":"221 E Hartsdale Ave",
    "sg:city":"Hartsdale",
    "sg:classifiers":[
        {
            "category":"Professional",
            "type":"Services"
        }
    ],
    "sg:phone":"+1 914 472 0589",
    "sg:postcode":"10530",
    "sg:province":"NY",
    "sg:tags":[
        "establishment"
    ],
    "wof:name":"Chelsea Enterprises",
    "wof:placetype":"venue"
},
  "geometry": {"coordinates":[-73.796226,41.012852],"type":"Point"}
}