{
  "type": "Feature",
  "properties": {
    "addr:full":"12 W End Avenue New York NY 10023",
    "addr:housenumber":"12",
    "addr:postcode":"10023",
    "addr:street":"W End Avenue",
    "iso:country":"US",
    "sg:address":"12 W End Avenue",
    "sg:city":"New York",
    "sg:classifiers":[
        {
            "category":"Retail",
            "subcategory":"Portrait Studio",
            "type":"Services"
        },
        {
            "category":"Professional",
            "subcategory":"Art Services",
            "type":"Services"
        }
    ],
    "sg:phone":"+1 212 634 9280",
    "sg:postcode":"10023",
    "sg:province":"NY",
    "sg:tags":[
        "photographer",
        "photography",
        "store"
    ],
    "wof:name":"Utopia the Agency",
    "wof:placetype":"venue"
},
  "geometry": {"coordinates":[-73.989987,40.772005],"type":"Point"}
}