{
  "type": "Feature",
  "properties": {
    "iso:country":"US",
    "sg:address":"2516 Barnes Ave",
    "sg:city":"Bronx",
    "sg:classifiers":[
        {
            "category":"Arts & Performance",
            "subcategory":"Festival",
            "type":"Entertainment"
        }
    ],
    "sg:phone":"+1 718 515 6753",
    "sg:postcode":"10467",
    "sg:province":"NY",
    "sg:tags":[
        "carnival"
    ],
    "sg:website":"http://www.ccamusements.com",
    "wof:name":"C & C Amusement Inc",
    "wof:placetype":"venue"
},
  "geometry": {"coordinates":[-73.86358199999999,40.863554],"type":"Point"}
}