{
  "type": "Feature",
  "properties": {
    "iso:country":"US",
    "sg:address":"39 State St",
    "sg:city":"Rochester",
    "sg:classifiers":[
        {
            "category":"Banks & Credit Unions",
            "subcategory":"Investment Brokerage",
            "type":"Services"
        }
    ],
    "sg:phone":"+1 585 325 1100",
    "sg:postcode":"14614",
    "sg:province":"NY",
    "sg:tags":[
        "consultant",
        "planning",
        "financial"
    ],
    "wof:name":"R & L Planning Assoc Inc",
    "wof:placetype":"venue"
},
  "geometry": {"coordinates":[-77.612686,43.155731],"type":"Point"}
}