{
  "type": "Feature",
  "properties": {
    "iso:country":"US",
    "sg:address":"66-26 Freshpond Rd",
    "sg:city":"Ridgewood",
    "sg:classifiers":[
        {
            "category":"Restaurant",
            "type":"Food & Drink"
        }
    ],
    "sg:phone":"+1 718 456 0222",
    "sg:postcode":"11385",
    "sg:province":"NY",
    "sg:tags":[
        "japanese"
    ],
    "wof:name":"Sapporoll",
    "wof:placetype":"venue"
},
  "geometry": {"coordinates":[-73.898168,40.708106],"type":"Point"}
}