{
  "type": "Feature",
  "properties": {
    "addr:full":"24 Chenango Bridge Rd Binghamton NY 13901",
    "addr:housenumber":"24",
    "addr:postcode":"13901",
    "addr:street":"Chenango Bridge Rd",
    "iso:country":"US",
    "sg:address":"24 Chenango Bridge Rd",
    "sg:city":"Binghamton",
    "sg:classifiers":[
        {
            "category":"Wholesale",
            "subcategory":"Auto Parts",
            "type":"Manufacturing & Wholesale Goods"
        }
    ],
    "sg:phone":"+1 607 724 1374",
    "sg:postcode":"13901",
    "sg:province":"NY",
    "sg:tags":[
        "supply"
    ],
    "wof:name":"Harco Auto Parts",
    "wof:placetype":"venue"
},
  "geometry": {"coordinates":[-75.886788,42.168187],"type":"Point"}
}