{
  "type": "Feature",
  "properties": {
    "iso:country":"US",
    "sg:address":"8 Whitewood Dr",
    "sg:city":"New City",
    "sg:classifiers":[
        {
            "category":"Professional",
            "subcategory":"Computer Services",
            "type":"Services"
        }
    ],
    "sg:phone":"+1   ",
    "sg:postcode":"10956",
    "sg:province":"NY",
    "sg:tags":[
        "related"
    ],
    "wof:name":"Connectivity Resource Inc",
    "wof:placetype":"venue"
},
  "geometry": {"coordinates":[-73.988597,41.121672],"type":"Point"}
}