{
  "type": "Feature",
  "properties": {
    "iso:country":"US",
    "sg:address":"173 Lafayette St",
    "sg:city":"New York",
    "sg:classifiers":[
        {
            "category":"Personal",
            "subcategory":"Massage",
            "type":"Services"
        }
    ],
    "sg:phone":"+1 212 925 4511",
    "sg:postcode":"10013",
    "sg:province":"NY",
    "wof:name":"The Best Chinese Back Rub and Relaxing Foot Rub and Integrate...",
    "wof:placetype":"venue"
},
  "geometry": {"coordinates":[-73.998767,40.720355],"type":"Point"}
}