{
  "type": "Feature",
  "properties": {
    "addr:full":"1548 Southern Blvd Bronx NY 10460",
    "addr:housenumber":"1548",
    "addr:postcode":"10460",
    "addr:street":"Southern Blvd",
    "iso:country":"US",
    "sg:address":"1548 Southern Blvd",
    "sg:city":"Bronx",
    "sg:classifiers":[
        {
            "category":"Wholesale",
            "subcategory":"Meat",
            "type":"Manufacturing & Wholesale Goods"
        }
    ],
    "sg:phone":"+1 718 378 7402",
    "sg:postcode":"10460",
    "sg:province":"NY",
    "sg:tags":[
        "poultry",
        "plant",
        "processing"
    ],
    "wof:name":"Casa LA Gallina",
    "wof:placetype":"venue"
},
  "geometry": {"coordinates":[-73.888825,40.835342],"type":"Point"}
}