{
  "type": "Feature",
  "properties": {
    "addr:full":"191 Intrepid Ln Syracuse NY 13205",
    "addr:housenumber":"191",
    "addr:postcode":"13205",
    "addr:street":"Intrepid Ln",
    "iso:country":"US",
    "sg:address":"191 Intrepid Ln",
    "sg:city":"Syracuse",
    "sg:classifiers":[
        {
            "category":"Professional",
            "subcategory":"Research",
            "type":"Services"
        }
    ],
    "sg:phone":"+1 315 498 9400",
    "sg:postcode":"13205",
    "sg:province":"NY",
    "sg:tags":[
        "development",
        "laboratory"
    ],
    "wof:name":"Credit Research Assoc",
    "wof:placetype":"venue"
},
  "geometry": {"coordinates":[-76.12987699999999,43.003491],"type":"Point"}
}