{
  "type": "Feature",
  "properties": {
    "addr:full":"369 E 198th St Bronx NY 10458",
    "addr:housenumber":"369",
    "addr:postcode":"10458",
    "addr:street":"E 198Th St",
    "iso:country":"US",
    "sg:address":"369 E 198th St",
    "sg:city":"Bronx",
    "sg:classifiers":[
        {
            "category":"Real Estate",
            "subcategory":"Real Estate Agent",
            "type":"Services"
        }
    ],
    "sg:phone":"+1 718 584 1211",
    "sg:postcode":"10458",
    "sg:province":"NY",
    "wof:name":"Carmine Alessandro Realty",
    "wof:placetype":"venue"
},
  "geometry": {"coordinates":[-73.886613,40.867053],"type":"Point"}
}