{
  "type": "Feature",
  "properties": {
    "iso:country":"US",
    "sg:address":"369 E 198th St",
    "sg:city":"Bronx",
    "sg:classifiers":[
        {
            "category":"Real Estate",
            "subcategory":"Real Estate Agent",
            "type":"Services"
        }
    ],
    "sg:phone":"+1 718 584 1211",
    "sg:postcode":"10458",
    "sg:province":"NY",
    "wof:name":"Carmine Alessandro Realty",
    "wof:placetype":"venue"
},
  "geometry": {"coordinates":[-73.886613,40.867053],"type":"Point"}
}