{
  "type": "Feature",
  "properties": {
    "addr:full":"33 W 34th St New York NY 10001",
    "addr:housenumber":"33",
    "addr:postcode":"10001",
    "addr:street":"W 34Th St",
    "iso:country":"US",
    "sg:address":"33 W 34th St",
    "sg:city":"New York",
    "sg:classifiers":[
        {
            "category":"Shopping",
            "subcategory":"Bicycles & Sporting Goods",
            "type":"Retail Goods"
        }
    ],
    "sg:phone":"+1 212 695 3354",
    "sg:postcode":"10001",
    "sg:province":"NY",
    "sg:website":"www.drjays.com/",
    "wof:name":"Dr Jay's",
    "wof:placetype":"venue"
},
  "geometry": {"coordinates":[-73.986766,40.749387],"type":"Point"}
}