{
  "type": "Feature",
  "properties": {
    "iso:country":"US",
    "sg:address":"4230 Consaul Rd",
    "sg:city":"Schenectady",
    "sg:classifiers":[
        {
            "category":"Building & Trades",
            "subcategory":"Construction",
            "type":"Services"
        }
    ],
    "sg:phone":"+1 518 331 6718",
    "sg:postcode":"12304",
    "sg:province":"NY",
    "sg:tags":[
        "general",
        "contractor"
    ],
    "wof:name":"American Building & Landscape",
    "wof:placetype":"venue"
},
  "geometry": {"coordinates":[-73.876486,42.773869],"type":"Point"}
}