{
  "type": "Feature",
  "properties": {
    "iso:country":"US",
    "sg:address":"475 S Oyster Bay Rd",
    "sg:city":"Plainview",
    "sg:classifiers":[
        {
            "category":"Professional",
            "subcategory":"Lawyer & Legal Services",
            "type":"Services"
        }
    ],
    "sg:phone":"+1 516 942 3242",
    "sg:postcode":"11803",
    "sg:province":"NY",
    "sg:tags":[
        "attorney"
    ],
    "wof:name":"Mark Balog",
    "wof:placetype":"venue"
},
  "geometry": {"coordinates":[-73.50251799999999,40.779075],"type":"Point"}
}