{
  "type": "Feature",
  "properties": {
    "iso:country":"US",
    "sg:address":"18 Oakley Rd",
    "sg:city":"White Plains",
    "sg:classifiers":[
        {
            "category":"Health Services",
            "subcategory":"Health Practitioner",
            "type":"Services"
        }
    ],
    "sg:phone":"+1 914 997 0363",
    "sg:postcode":"10606",
    "sg:province":"NY",
    "sg:tags":[
        "psychologist"
    ],
    "wof:name":"Psychology Line",
    "wof:placetype":"venue"
},
  "geometry": {"coordinates":[-73.771546,41.015404],"type":"Point"}
}