{
  "type": "Feature",
  "properties": {
    "addr:full":"8804 Glenwood Rd Brooklyn NY 11236",
    "addr:housenumber":"8804",
    "addr:postcode":"11236",
    "addr:street":"Glenwood Rd",
    "iso:country":"US",
    "sg:address":"8804 Glenwood Rd",
    "sg:city":"Brooklyn",
    "sg:classifiers":[
        {
            "category":"Health Services",
            "subcategory":"Medical Lab",
            "type":"Services"
        }
    ],
    "sg:phone":"+1 718 272 6900",
    "sg:postcode":"11236",
    "sg:province":"NY",
    "sg:tags":[
        "laboratory"
    ],
    "wof:name":"B Gooden Dental Laboratories",
    "wof:placetype":"venue"
},
  "geometry": {"coordinates":[-73.908377,40.641155],"type":"Point"}
}