{
  "type": "Feature",
  "properties": {
    "addr:full":"953 Southern Blvd Bronx NY 10459",
    "addr:housenumber":"953",
    "addr:postcode":"10459",
    "addr:street":"Southern Blvd",
    "iso:country":"US",
    "sg:address":"953 Southern Blvd",
    "sg:city":"Bronx",
    "sg:classifiers":[
        {
            "category":"Shopping",
            "subcategory":"Bicycles & Sporting Goods",
            "type":"Retail Goods"
        }
    ],
    "sg:phone":"+1 718 842 2234",
    "sg:postcode":"10459",
    "sg:province":"NY",
    "sg:website":"www.drjays.com",
    "wof:name":"Dr Jays Army & Navy Store",
    "wof:placetype":"venue"
},
  "geometry": {"coordinates":[-73.89173700000001,40.821223],"type":"Point"}
}