{
  "type": "Feature",
  "properties": {
    "iso:country":"US",
    "sg:address":"5335 Rte 474",
    "sg:city":"Ashville",
    "sg:classifiers":[
        {
            "category":"Building & Trades",
            "subcategory":"Construction",
            "type":"Services"
        }
    ],
    "sg:phone":"+1 716 782 2007",
    "sg:postcode":"14710",
    "sg:province":"NY",
    "sg:tags":[
        "concrete",
        "contractor"
    ],
    "wof:name":"Concrete Unlimited",
    "wof:placetype":"venue"
},
  "geometry": {"coordinates":[-79.407686,42.080752],"type":"Point"}
}