{
  "type": "Feature",
  "properties": {
    "addr:full":"125 White Spruce Blvd Rochester NY 14623",
    "addr:housenumber":"125",
    "addr:postcode":"14623",
    "addr:street":"White Spruce Blvd",
    "iso:country":"US",
    "sg:address":"125 White Spruce Blvd",
    "sg:city":"Rochester",
    "sg:classifiers":[
        {
            "category":"Restaurant",
            "type":"Food & Drink"
        }
    ],
    "sg:menulink":"http://www.allmenus.com/ny/brighton/23506-chopsticks-chinese-restaurant/menu/",
    "sg:phone":"+1 585 427 8878",
    "sg:postcode":"14623",
    "sg:province":"NY",
    "sg:tags":[
        "asian",
        "chinese"
    ],
    "wof:name":"Chopsticks Chinese Restaurant",
    "wof:placetype":"venue"
},
  "geometry": {"coordinates":[-77.617941,43.105501],"type":"Point"}
}