{
  "type": "Feature",
  "properties": {
    "iso:country":"US",
    "sg:address":"400 Old Liverpool Rd",
    "sg:city":"Liverpool",
    "sg:classifiers":[
        {
            "category":"Utilities",
            "subcategory":"Mobile Phone",
            "type":"Services"
        }
    ],
    "sg:phone":"+1 315 451 9341",
    "sg:postcode":"13088",
    "sg:province":"NY",
    "sg:tags":[
        "telephone",
        "cellular"
    ],
    "wof:name":"Wireless Alternatives",
    "wof:placetype":"venue"
},
  "geometry": {"coordinates":[-76.186333,43.086731],"type":"Point"}
}