{
  "type": "Feature",
  "properties": {
    "iso:country":"US",
    "sg:address":"61 Spencer Ave",
    "sg:city":"Lynbrook",
    "sg:classifiers":[
        {
            "category":"Food & Beverages",
            "subcategory":"Groceries & Convenience Stores",
            "type":"Retail Goods"
        }
    ],
    "sg:phone":"+1   ",
    "sg:postcode":"11563",
    "sg:province":"NY",
    "wof:name":"Natwest Markets",
    "wof:placetype":"venue"
},
  "geometry": {"coordinates":[-73.671295,40.650604],"type":"Point"}
}