{
  "type": "Feature",
  "properties": {
    "iso:country":"US",
    "sg:address":"204 Bay Ter",
    "sg:city":"Staten Island",
    "sg:classifiers":[
        {
            "category":"Building & Trades",
            "subcategory":"Landscaping Services",
            "type":"Services"
        }
    ],
    "sg:phone":"+1 718 667 5862",
    "sg:postcode":"10306",
    "sg:province":"NY",
    "sg:tags":[
        "landscape"
    ],
    "wof:name":"Sarni & Sons Landscaping",
    "wof:placetype":"venue"
},
  "geometry": {"coordinates":[-74.133397,40.55246],"type":"Point"}
}