{
  "type": "Feature",
  "properties": {
    "addr:full":"145 Commerce Dr Rochester NY 14623",
    "addr:housenumber":"145",
    "addr:postcode":"14623",
    "addr:street":"Commerce Dr",
    "iso:country":"US",
    "sg:address":"145 Commerce Dr",
    "sg:city":"Rochester",
    "sg:classifiers":[
        {
            "category":"Freight",
            "type":"Transportation"
        }
    ],
    "sg:phone":"+1   ",
    "sg:postcode":"14623",
    "sg:province":"NY",
    "sg:tags":[
        "local",
        "storage",
        "trucking"
    ],
    "wof:name":"United Van Lines",
    "wof:placetype":"venue"
},
  "geometry": {"coordinates":[-77.654377,43.083106],"type":"Point"}
}