{
  "type": "Feature",
  "properties": {
    "addr:full":"298 Sunrise Hwy Rockville Centre NY 11570",
    "addr:housenumber":"298",
    "addr:postcode":"11570",
    "addr:street":"Sunrise Hwy",
    "iso:country":"US",
    "sg:address":"298 Sunrise Hwy",
    "sg:city":"Rockville Centre",
    "sg:classifiers":[
        {
            "category":"Sports & Exercise",
            "subcategory":"Gym",
            "type":"Entertainment"
        }
    ],
    "sg:phone":"+1 516 766 8443",
    "sg:postcode":"11570",
    "sg:province":"NY",
    "wof:name":"Lucille Roberts Westbury Health Club",
    "wof:placetype":"venue"
},
  "geometry": {"coordinates":[-73.641701,40.657001],"type":"Point"}
}