{
  "type": "Feature",
  "properties": {
    "iso:country":"US",
    "sg:address":"1410 E 10th St",
    "sg:city":"Brooklyn",
    "sg:classifiers":[
        {
            "category":"Health Services",
            "subcategory":"Nursing And Care Facility",
            "type":"Services"
        }
    ],
    "sg:phone":"+1 718 998 5400",
    "sg:postcode":"11230",
    "sg:province":"NY",
    "sg:tags":[
        "home",
        "convalescent"
    ],
    "sg:website":"www.ateretavot.com",
    "wof:name":"Scharf's Ateret Avot",
    "wof:placetype":"venue"
},
  "geometry": {"coordinates":[-73.963966,40.612693],"type":"Point"}
}