{
  "type": "Feature",
  "properties": {
    "addr:full":"41 Flatbush Avenue Brooklyn NY 11217",
    "addr:housenumber":"41",
    "addr:postcode":"11217",
    "addr:street":"Flatbush Avenue",
    "iso:country":"US",
    "sg:address":"41 Flatbush Avenue",
    "sg:city":"Brooklyn",
    "sg:classifiers":[
        {
            "category":"Personal",
            "type":"Services"
        },
        {
            "category":"Shopping",
            "subcategory":"Mobile Phones",
            "type":"Retail Goods"
        },
        {
            "category":"Retail",
            "subcategory":"Storage",
            "type":"Services"
        }
    ],
    "sg:phone":"+1 718 596 4060",
    "sg:postcode":"11217",
    "sg:province":"NY",
    "sg:tags":[
        "mover",
        "self"
    ],
    "sg:website":"www.extraspace.com",
    "wof:name":"Extra Space Storage",
    "wof:placetype":"venue"
},
  "geometry": {"coordinates":[-73.97926200000001,40.68761],"type":"Point"}
}