{
  "type": "Feature",
  "properties": {
    "iso:country":"US",
    "sg:address":"1293 State Hwy 176",
    "sg:city":"Fulton",
    "sg:classifiers":[
        {
            "category":"Building & Trades",
            "subcategory":"Plumbing",
            "type":"Services"
        }
    ],
    "sg:phone":"+1 315 598 2523",
    "sg:postcode":"13069",
    "sg:province":"NY",
    "sg:tags":[
        "plumbing",
        "heating",
        "contractor"
    ],
    "wof:name":"Wettering Plumbing & Heating",
    "wof:placetype":"venue"
},
  "geometry": {"coordinates":[-76.429011,43.291665],"type":"Point"}
}