{
  "type": "Feature",
  "properties": {
    "addr:full":"63 Flushing Ave Brooklyn NY 11205",
    "addr:housenumber":"63",
    "addr:postcode":"11205",
    "addr:street":"Flushing Ave",
    "iso:country":"US",
    "sg:address":"63 Flushing Ave",
    "sg:city":"Brooklyn",
    "sg:classifiers":[
        {
            "category":"Wholesale",
            "subcategory":"Home Furnishings",
            "type":"Manufacturing & Wholesale Goods"
        }
    ],
    "sg:phone":"+1 718 222 3322",
    "sg:postcode":"11205",
    "sg:province":"NY",
    "sg:tags":[
        "blind",
        "window",
        "shade"
    ],
    "wof:name":"City View Blinds",
    "wof:placetype":"venue"
},
  "geometry": {"coordinates":[-73.974998,40.698002],"type":"Point"}
}