{
  "type": "Feature",
  "properties": {
    "iso:country":"US",
    "sg:address":"2100 Doubleday Ave",
    "sg:city":"Ballston Spa",
    "sg:classifiers":[
        {
            "category":"Restaurant",
            "type":"Food & Drink"
        }
    ],
    "sg:phone":"+1 518 885 4053",
    "sg:postcode":"12020",
    "sg:province":"NY",
    "wof:name":"J Oma's",
    "wof:placetype":"venue"
},
  "geometry": {"coordinates":[-73.84362400000001,43.017209],"type":"Point"}
}