{
  "type": "Feature",
  "properties": {
    "iso:country":"US",
    "sg:address":"871 Niagara Falls Blvd",
    "sg:city":"Buffalo",
    "sg:classifiers":[
        {
            "category":"Shopping",
            "subcategory":"Computers & Home Electronics",
            "type":"Retail Goods"
        }
    ],
    "sg:phone":"+1 716 835 2914",
    "sg:postcode":"14226",
    "sg:province":"NY",
    "sg:tags":[
        "software"
    ],
    "wof:name":"E A Software",
    "wof:placetype":"venue"
},
  "geometry": {"coordinates":[-78.822947,42.978046],"type":"Point"}
}