{
  "type": "Feature",
  "properties": {
    "iso:country":"US",
    "sg:address":"1111 Patterson St Ste 1",
    "sg:city":"Ogdensburg",
    "sg:classifiers":[
        {
            "category":"Autos & Motor Vehicles",
            "subcategory":"Automobile Sales",
            "type":"Retail Goods"
        },
        {
            "category":"Autos & Motor Vehicles",
            "subcategory":"Auto Supplies",
            "type":"Retail Goods"
        },
        {
            "category":"Retail",
            "subcategory":"Auto Repair",
            "type":"Services"
        }
    ],
    "sg:phone":"+1 315 393 8454",
    "sg:postcode":"13669",
    "sg:province":"NY",
    "sg:tags":[
        "body",
        "used",
        "tire",
        "removal",
        "dent",
        "car",
        "windshield",
        "painting",
        "repairing"
    ],
    "sg:website":"http://www.rishes.com",
    "wof:name":"Rishe's Auto Sales & Service",
    "wof:placetype":"venue"
},
  "geometry": {"coordinates":[-75.477402,44.692105],"type":"Point"}
}