{
  "type": "Feature",
  "properties": {
    "iso:country":"US",
    "sg:address":"15 Pondview Dr",
    "sg:city":"Pittsford",
    "sg:classifiers":[
        {
            "category":"Health Services",
            "subcategory":"Doctor",
            "type":"Services"
        }
    ],
    "sg:phone":"+1 585 385 6578",
    "sg:postcode":"14534",
    "sg:province":"NY",
    "sg:tags":[
        "physician",
        "surgeon"
    ],
    "wof:name":"Michael A Niles",
    "wof:placetype":"venue"
},
  "geometry": {"coordinates":[-77.469517,43.036968],"type":"Point"}
}