{
  "type": "Feature",
  "properties": {
    "addr:full":"251 S Ketcham Ave Amityville NY 11701",
    "addr:housenumber":"251",
    "addr:postcode":"11701",
    "addr:street":"S Ketcham Ave",
    "iso:country":"US",
    "sg:address":"251 S Ketcham Ave",
    "sg:city":"Amityville",
    "sg:classifiers":[
        {
            "category":"Bars & Pubs",
            "type":"Food & Drink"
        }
    ],
    "sg:phone":"+1 631 264 0564",
    "sg:postcode":"11701",
    "sg:province":"NY",
    "wof:name":"Toomey's Tavern",
    "wof:placetype":"venue"
},
  "geometry": {"coordinates":[-73.423496,40.662763],"type":"Point"}
}