{
  "type": "Feature",
  "properties": {
    "iso:country":"US",
    "sg:address":"538 Riverdale Ave",
    "sg:city":"Yonkers",
    "sg:classifiers":[
        {
            "category":"Insurance",
            "subcategory":"Insurance Agent",
            "type":"Services"
        }
    ],
    "sg:phone":"+1 914 378 1030",
    "sg:postcode":"10705",
    "sg:province":"NY",
    "wof:name":"Crowley Insurance",
    "wof:placetype":"venue"
},
  "geometry": {"coordinates":[-73.902294,40.913745],"type":"Point"}
}