{
  "type": "Feature",
  "properties": {
    "addr:full":"405 Lexington Ave New York NY 10174",
    "addr:housenumber":"405",
    "addr:postcode":"10174",
    "addr:street":"Lexington Ave",
    "iso:country":"US",
    "sg:address":"405 Lexington Ave",
    "sg:city":"New York",
    "sg:classifiers":[
        {
            "category":"Professional",
            "subcategory":"Lawyer & Legal Services",
            "type":"Services"
        }
    ],
    "sg:phone":"+1 212 704 6000",
    "sg:postcode":"10174",
    "sg:province":"NY",
    "wof:name":"Berkey Mitchell S Atty",
    "wof:placetype":"venue"
},
  "geometry": {"coordinates":[-73.9757,40.751499],"type":"Point"}
}