{
  "type": "Feature",
  "properties": {
    "addr:full":"810 Meeker Ave. Brooklyn NY 11222",
    "addr:housenumber":"810",
    "addr:postcode":"11222",
    "addr:street":"Meeker Ave.",
    "iso:country":"US",
    "sg:address":"810 Meeker Ave.",
    "sg:city":"Brooklyn",
    "sg:classifiers":[
        {
            "category":"Home & Garden",
            "subcategory":"Garden Supply",
            "type":"Retail Goods"
        }
    ],
    "sg:phone":"+1 718 218 8911",
    "sg:postcode":"11222",
    "sg:province":"NY",
    "sg:website":"www.conchumbrellas.com/",
    "wof:name":"Conch Umbrellas Co.",
    "wof:placetype":"venue"
},
  "geometry": {"coordinates":[-73.93650100000001,40.7248],"type":"Point"}
}