{
  "type": "Feature",
  "properties": {
    "addr:full":"105 Sprague Ave Middletown NY 10940",
    "addr:housenumber":"105",
    "addr:postcode":"10940",
    "addr:street":"Sprague Ave",
    "iso:country":"US",
    "sg:address":"105 Sprague Ave",
    "sg:city":"Middletown",
    "sg:classifiers":[
        {
            "category":"Real Estate",
            "subcategory":"Real Estate Operator",
            "type":"Services"
        }
    ],
    "sg:phone":"+1 845 342 9009",
    "sg:postcode":"10940",
    "sg:province":"NY",
    "sg:tags":[
        "building"
    ],
    "wof:name":"Carsar Realty Corp",
    "wof:placetype":"venue"
},
  "geometry": {"coordinates":[-74.41709299999999,41.439306],"type":"Point"}
}