{
  "type": "Feature",
  "properties": {
    "iso:country":"US",
    "sg:address":"415 Hillview Pl",
    "sg:city":"Ithaca",
    "sg:classifiers":[
        {
            "category":"Building & Trades",
            "subcategory":"Pest Control",
            "type":"Services"
        }
    ],
    "sg:phone":"+1 607 272 1591",
    "sg:postcode":"14850",
    "sg:province":"NY",
    "wof:name":"A-Arrow Exterminating Co",
    "wof:placetype":"venue"
},
  "geometry": {"coordinates":[-76.494619,42.434878],"type":"Point"}
}