{
  "type": "Feature",
  "properties": {
    "iso:country":"US",
    "sg:address":"4941 E Lake Rd",
    "sg:city":"Burt",
    "sg:classifiers":[
        {
            "category":"Farming",
            "subcategory":"Orchard",
            "type":"Manufacturing & Wholesale Goods"
        }
    ],
    "sg:phone":"+1 716 751 6191",
    "sg:postcode":"14028",
    "sg:province":"NY",
    "wof:name":"Lakeview Orchards Inc",
    "wof:placetype":"venue"
},
  "geometry": {"coordinates":[-78.769654,43.326453],"type":"Point"}
}