{
  "type": "Feature",
  "properties": {
    "addr:full":"381 Flatbush Avenue Ext Brooklyn NY 11201",
    "addr:housenumber":"381",
    "addr:postcode":"11201",
    "addr:street":"Flatbush Avenue Ext",
    "iso:country":"US",
    "sg:address":"381 Flatbush Avenue Ext",
    "sg:city":"Brooklyn",
    "sg:classifiers":[
        {
            "category":"Retail",
            "subcategory":"Laundry & Dry Cleaning",
            "type":"Services"
        }
    ],
    "sg:phone":"+1 718 622 2388",
    "sg:postcode":"11201",
    "sg:province":"NY",
    "wof:name":"Four Seasons Cleaner",
    "wof:placetype":"venue"
},
  "geometry": {"coordinates":[-73.981328,40.690119],"type":"Point"}
}