{
  "type": "Feature",
  "properties": {
    "iso:country":"US",
    "sg:address":"6 Scenic Dr",
    "sg:city":"Poughkeepsie",
    "sg:classifiers":[
        {
            "category":"Communications",
            "subcategory":"Film & Video Production",
            "type":"Services"
        }
    ],
    "sg:phone":"+1   ",
    "sg:postcode":"12603",
    "sg:province":"NY",
    "sg:tags":[
        "motion",
        "picture"
    ],
    "wof:name":"Video Ed Inc",
    "wof:placetype":"venue"
},
  "geometry": {"coordinates":[-73.902096,41.650011],"type":"Point"}
}