{
  "type": "Feature",
  "properties": {
    "iso:country":"US",
    "sg:address":"300 W 135th Street Apt 5U",
    "sg:city":"New York",
    "sg:classifiers":[
        {
            "category":"Shopping",
            "subcategory":"Pharmacy",
            "type":"Retail Goods"
        }
    ],
    "sg:phone":"+1 212 491 6015",
    "sg:postcode":"10030",
    "sg:province":"NY",
    "sg:tags":[
        "drugstore"
    ],
    "wof:name":"Duane Reade Drugs",
    "wof:placetype":"venue"
},
  "geometry": {"coordinates":[-73.942846,40.81909],"type":"Point"}
}