{
  "type": "Feature",
  "properties": {
    "addr:full":"50 Pine St New York NY 10005",
    "addr:housenumber":"50",
    "addr:postcode":"10005",
    "addr:street":"Pine St",
    "iso:country":"US",
    "sg:address":"50 Pine St",
    "sg:city":"New York",
    "sg:classifiers":[
        {
            "category":"Wholesale",
            "subcategory":"Electrical",
            "type":"Manufacturing & Wholesale Goods"
        }
    ],
    "sg:phone":"+1 212 269 0426",
    "sg:postcode":"10005",
    "sg:province":"NY",
    "sg:tags":[
        "copper",
        "telecommunication",
        "cable"
    ],
    "wof:name":"Kmm Telecommunications",
    "wof:placetype":"venue"
},
  "geometry": {"coordinates":[-74.007452,40.70605],"type":"Point"}
}