{
  "type": "Feature",
  "properties": {
    "addr:full":"814 Pacific St Brooklyn NY 11238",
    "addr:housenumber":"814",
    "addr:postcode":"11238",
    "addr:street":"Pacific St",
    "iso:country":"US",
    "sg:address":"814 Pacific St",
    "sg:city":"Brooklyn",
    "sg:classifiers":[
        {
            "category":"Building & Trades",
            "subcategory":"Plumbing",
            "type":"Services"
        }
    ],
    "sg:phone":"+1 718 857 1158",
    "sg:postcode":"11238",
    "sg:province":"NY",
    "sg:tags":[
        "conditioning",
        "air",
        "system",
        "contractor"
    ],
    "wof:name":"Delta Technical Corp",
    "wof:placetype":"venue"
},
  "geometry": {"coordinates":[-73.97004099999999,40.681529],"type":"Point"}
}