{
  "type": "Feature",
  "properties": {
    "addr:full":"8940 W Valley Rd West Valley NY 14171",
    "addr:housenumber":"8940",
    "addr:postcode":"14171",
    "addr:street":"W Valley Rd",
    "iso:country":"US",
    "sg:address":"8940 W Valley Rd",
    "sg:city":"West Valley",
    "sg:classifiers":[
        {
            "category":"Shopping",
            "subcategory":"Crafts & Fabrics",
            "type":"Retail Goods"
        }
    ],
    "sg:phone":"+1   ",
    "sg:postcode":"14171",
    "sg:province":"NY",
    "sg:tags":[
        "sewing"
    ],
    "wof:name":"Heddles Up",
    "wof:placetype":"venue"
},
  "geometry": {"coordinates":[-78.60400199999999,42.382035],"type":"Point"}
}