{
  "type": "Feature",
  "properties": {
    "iso:country":"US",
    "sg:address":"1779 2 Ave",
    "sg:city":"New York",
    "sg:classifiers":[
        {
            "category":"Travel",
            "subcategory":"Travel Agent",
            "type":"Entertainment"
        }
    ],
    "sg:phone":"+1 212 348 2000",
    "sg:postcode":"10128",
    "sg:province":"NY",
    "sg:tags":[
        "agency",
        "bureau"
    ],
    "wof:name":"Best Deal Travel",
    "wof:placetype":"venue"
},
  "geometry": {"coordinates":[-73.95079200000001,40.779179],"type":"Point"}
}