{
  "type": "Feature",
  "properties": {
    "iso:country":"US",
    "sg:address":"4502 3rd Ave",
    "sg:city":"Brooklyn",
    "sg:classifiers":[
        {
            "category":"Wholesale",
            "subcategory":"Fruits & Vegetables",
            "type":"Manufacturing & Wholesale Goods"
        }
    ],
    "sg:phone":"+1 718 492 5700",
    "sg:postcode":"11220",
    "sg:province":"NY",
    "wof:name":"V M J Esposito",
    "wof:placetype":"venue"
},
  "geometry": {"coordinates":[-74.011968,40.649773],"type":"Point"}
}