{
  "type": "Feature",
  "properties": {
    "iso:country":"US",
    "sg:address":"519 Gateway Dr",
    "sg:city":"Brooklyn",
    "sg:classifiers":[
        {
            "category":"Shopping",
            "subcategory":"Department Store",
            "type":"Retail Goods"
        }
    ],
    "sg:phone":"+1 718 235 6032",
    "sg:postcode":"11239",
    "sg:province":"NY",
    "wof:name":"Target",
    "wof:placetype":"venue"
},
  "geometry": {"coordinates":[-73.870153,40.65289],"type":"Point"}
}