{
  "type": "Feature",
  "properties": {
    "addr:full":"88 Bowery Unit 1 New York NY 10013",
    "addr:housenumber":"88;unit 1",
    "addr:postcode":"10013",
    "addr:street":"Bowery",
    "iso:country":"US",
    "sg:address":"88 Bowery Unit 1",
    "sg:city":"New York",
    "sg:classifiers":[
        {
            "category":"Shopping",
            "subcategory":"Jewelry",
            "type":"Retail Goods"
        }
    ],
    "sg:phone":"+1 212 431 5370",
    "sg:postcode":"10013",
    "sg:province":"NY",
    "wof:name":"M A N Mfg",
    "wof:placetype":"venue"
},
  "geometry": {"coordinates":[-73.99539900000001,40.7174],"type":"Point"}
}