{
  "type": "Feature",
  "properties": {
    "iso:country":"US",
    "sg:address":"70 Niagara St",
    "sg:city":"Buffalo",
    "sg:classifiers":[
        {
            "category":"Professional",
            "subcategory":"Lawyer & Legal Services",
            "type":"Services"
        }
    ],
    "sg:phone":"+1 716 849 1700",
    "sg:postcode":"14202",
    "sg:province":"NY",
    "wof:name":"Finnerty Joseph M Atty",
    "wof:placetype":"venue"
},
  "geometry": {"coordinates":[-78.87750200000001,42.885502],"type":"Point"}
}