{
  "type": "Feature",
  "properties": {
    "addr:full":"113 Belmont Pkwy Hempstead NY 11550",
    "addr:housenumber":"113",
    "addr:postcode":"11550",
    "addr:street":"Belmont Pkwy",
    "iso:country":"US",
    "sg:address":"113 Belmont Pkwy",
    "sg:city":"Hempstead",
    "sg:classifiers":[
        {
            "category":"Real Estate",
            "subcategory":"Real Estate Agent",
            "type":"Services"
        }
    ],
    "sg:phone":"+1 516 481 9378",
    "sg:postcode":"11550",
    "sg:province":"NY",
    "wof:name":"Constant Realty Co",
    "wof:placetype":"venue"
},
  "geometry": {"coordinates":[-73.604861,40.699778],"type":"Point"}
}