{
  "type": "Feature",
  "properties": {
    "iso:country":"US",
    "sg:address":"115 Fairmont Ave",
    "sg:city":"Watertown",
    "sg:classifiers":[
        {
            "category":"Shopping",
            "type":"Retail Goods"
        }
    ],
    "sg:phone":"+1   ",
    "sg:postcode":"13601",
    "sg:province":"NY",
    "sg:tags":[
        "merchandise"
    ],
    "wof:name":"Eglubooks",
    "wof:placetype":"venue"
},
  "geometry": {"coordinates":[-75.883645,43.967258],"type":"Point"}
}