{
  "type": "Feature",
  "properties": {
    "iso:country":"US",
    "sg:address":"8 Cutchogue Ln",
    "sg:city":"Commack",
    "sg:classifiers":[
        {
            "category":"Professional",
            "subcategory":"Lawyer & Legal Services",
            "type":"Services"
        }
    ],
    "sg:phone":"+1   ",
    "sg:postcode":"11725",
    "sg:province":"NY",
    "wof:name":"Eric S Pillischer",
    "wof:placetype":"venue"
},
  "geometry": {"coordinates":[-73.279359,40.833473],"type":"Point"}
}