{
  "type": "Feature",
  "properties": {
    "addr:full":"83 Rockaway Ave Brooklyn NY 11233",
    "addr:housenumber":"83",
    "addr:postcode":"11233",
    "addr:street":"Rockaway Ave",
    "iso:country":"US",
    "sg:address":"83 Rockaway Ave",
    "sg:city":"Brooklyn",
    "sg:classifiers":[
        {
            "category":"Organizations",
            "subcategory":"Religious Organization",
            "type":"Services"
        }
    ],
    "sg:phone":"+1 718 455 3373",
    "sg:postcode":"11233",
    "sg:province":"NY",
    "sg:tags":[
        "church"
    ],
    "wof:name":"All People Church Of Apostolic",
    "wof:placetype":"venue"
},
  "geometry": {"coordinates":[-73.91101999999999,40.679606],"type":"Point"}
}