{
  "type": "Feature",
  "properties": {
    "addr:full":"6151 State Rte 21 Williamson NY 14589",
    "addr:housenumber":"6151",
    "addr:postcode":"14589",
    "addr:street":"State Rte 21",
    "iso:country":"US",
    "sg:address":"6151 State Rte 21",
    "sg:city":"Williamson",
    "sg:classifiers":[
        {
            "category":"Autos & Motor Vehicles",
            "subcategory":"Automobile Sales",
            "type":"Retail Goods"
        }
    ],
    "sg:phone":"+1 315 589 9240",
    "sg:postcode":"14589",
    "sg:province":"NY",
    "sg:tags":[
        "car",
        "dealer"
    ],
    "wof:name":"Kings Auto Svc Inc",
    "wof:placetype":"venue"
},
  "geometry": {"coordinates":[-77.187883,43.219102],"type":"Point"}
}