{
  "type": "Feature",
  "properties": {
    "addr:full":"300 Saltmakers Rd Liverpool NY 13088",
    "addr:housenumber":"300",
    "addr:postcode":"13088",
    "addr:street":"Saltmakers Rd",
    "iso:country":"US",
    "sg:address":"300 Saltmakers Rd",
    "sg:city":"Liverpool",
    "sg:classifiers":[
        {
            "category":"Shopping",
            "subcategory":"Tobacco",
            "type":"Retail Goods"
        }
    ],
    "sg:phone":"+1 315 457 1396",
    "sg:postcode":"13088",
    "sg:province":"NY",
    "sg:tags":[
        "cigarette",
        "cigar"
    ],
    "wof:name":"Durston's",
    "wof:placetype":"venue"
},
  "geometry": {"coordinates":[-76.186348,43.084721],"type":"Point"}
}