{
  "type": "Feature",
  "properties": {
    "iso:country":"US",
    "sg:address":"452 5th Ave",
    "sg:city":"New York",
    "sg:classifiers":[
        {
            "category":"Insurance",
            "subcategory":"Insurance Agent",
            "type":"Services"
        }
    ],
    "sg:phone":"+1 212 525 2249",
    "sg:postcode":"10018",
    "sg:province":"NY",
    "wof:name":"First Central National Life In",
    "wof:placetype":"venue"
},
  "geometry": {"coordinates":[-73.982133,40.75179],"type":"Point"}
}