{
  "type": "Feature",
  "properties": {
    "addr:full":"552 Driggs Ave Brooklyn NY 11211",
    "addr:housenumber":"552",
    "addr:postcode":"11211",
    "addr:street":"Driggs Ave",
    "iso:country":"US",
    "sg:address":"552 Driggs Ave",
    "sg:city":"Brooklyn",
    "sg:classifiers":[
        {
            "category":"Deli",
            "type":"Food & Drink"
        }
    ],
    "sg:menulink":"http://www.allmenus.com/ny/brooklyn/107500-joes-busy-gourmet-deli/menu/",
    "sg:phone":"+1 718 388 6372",
    "sg:postcode":"11211",
    "sg:province":"NY",
    "sg:tags":[
        "american"
    ],
    "wof:name":"Joe's Busy Gourmet Deli",
    "wof:placetype":"venue"
},
  "geometry": {"coordinates":[-73.95634099999999,40.717112],"type":"Point"}
}