{
  "type": "Feature",
  "properties": {
    "addr:full":"183 Ivory Foster Rd Owego NY 13827",
    "addr:housenumber":"183",
    "addr:postcode":"13827",
    "addr:street":"Ivory Foster Rd",
    "iso:country":"US",
    "sg:address":"183 Ivory Foster Rd",
    "sg:city":"Owego",
    "sg:classifiers":[
        {
            "category":"Shopping",
            "subcategory":"Computers & Home Electronics",
            "type":"Retail Goods"
        }
    ],
    "sg:phone":"+1   ",
    "sg:postcode":"13827",
    "sg:province":"NY",
    "wof:name":"Owego Computers",
    "wof:placetype":"venue"
},
  "geometry": {"coordinates":[-76.205883,42.113288],"type":"Point"}
}