{
  "type": "Feature",
  "properties": {
    "addr:full":"1158 Leland Ave Bronx NY 10472",
    "addr:housenumber":"1158",
    "addr:postcode":"10472",
    "addr:street":"Leland Ave",
    "iso:country":"US",
    "sg:address":"1158 Leland Ave",
    "sg:city":"Bronx",
    "sg:classifiers":[
        {
            "category":"Building & Trades",
            "subcategory":"Construction",
            "type":"Services"
        }
    ],
    "sg:phone":"+1 718 842 7083",
    "sg:postcode":"10472",
    "sg:province":"NY",
    "sg:tags":[
        "roofing",
        "industrial",
        "contractors-commercial",
        "contractor"
    ],
    "wof:name":"Bx Roofing Co",
    "wof:placetype":"venue"
},
  "geometry": {"coordinates":[-73.862934,40.829437],"type":"Point"}
}