{
  "type": "Feature",
  "properties": {
    "iso:country":"US",
    "sg:address":"2205 College Ave",
    "sg:city":"Elmira",
    "sg:classifiers":[
        {
            "category":"Communications",
            "subcategory":"Radio Station",
            "type":"Services"
        }
    ],
    "sg:phone":"+1   ",
    "sg:postcode":"14903",
    "sg:province":"NY",
    "sg:tags":[
        "broadcast"
    ],
    "wof:name":"W P G I-1009 F M",
    "wof:placetype":"venue"
},
  "geometry": {"coordinates":[-76.82629900000001,42.130214],"type":"Point"}
}