{
  "type": "Feature",
  "properties": {
    "iso:country":"US",
    "sg:address":"896 State Hwy 50",
    "sg:city":"Ballston Lake",
    "sg:classifiers":[
        {
            "category":"Building & Trades",
            "subcategory":"Construction",
            "type":"Services"
        }
    ],
    "sg:phone":"+1 518 399 3572",
    "sg:postcode":"12019",
    "sg:province":"NY",
    "sg:tags":[
        "builder",
        "patio",
        "deck"
    ],
    "wof:name":"Deck Crafters Inc",
    "wof:placetype":"venue"
},
  "geometry": {"coordinates":[-73.87873999999999,42.929901],"type":"Point"}
}