{
  "type": "Feature",
  "properties": {
    "iso:country":"US",
    "sg:address":"6876 Lakeview Ter",
    "sg:city":"Bath",
    "sg:classifiers":[
        {
            "category":"Building & Trades",
            "subcategory":"Construction",
            "type":"Services"
        }
    ],
    "sg:phone":"+1 607 776 6083",
    "sg:postcode":"14810",
    "sg:province":"NY",
    "sg:tags":[
        "residential"
    ],
    "wof:name":"Corell Contracting",
    "wof:placetype":"venue"
},
  "geometry": {"coordinates":[-77.294397,42.332833],"type":"Point"}
}