{
  "type": "Feature",
  "properties": {
    "addr:full":"84 Chatham Pl West Hempstead NY 11552",
    "addr:housenumber":"84",
    "addr:postcode":"11552",
    "addr:street":"Chatham Pl West",
    "iso:country":"US",
    "sg:address":"84 Chatham Pl",
    "sg:city":"West Hempstead",
    "sg:classifiers":[
        {
            "category":"Building & Trades",
            "subcategory":"Construction",
            "type":"Services"
        }
    ],
    "sg:phone":"+1 516 656 9509",
    "sg:postcode":"11552",
    "sg:province":"NY",
    "sg:tags":[
        "resurfacing",
        "refinishing",
        "floor"
    ],
    "wof:name":"All Floors",
    "wof:placetype":"venue"
},
  "geometry": {"coordinates":[-73.64241800000001,40.709637],"type":"Point"}
}