{
  "type": "Feature",
  "properties": {
    "addr:full":"1622 Route 22 Brewster NY 10509",
    "addr:housenumber":"1622",
    "addr:postcode":"10509",
    "addr:street":"Route 22",
    "iso:country":"US",
    "sg:address":"1622 Route 22",
    "sg:city":"Brewster",
    "sg:classifiers":[
        {
            "category":"Professional",
            "subcategory":"Business Services",
            "type":"Services"
        }
    ],
    "sg:phone":"+1 845 279 2905",
    "sg:postcode":"10509",
    "sg:province":"NY",
    "sg:tags":[
        "medical",
        "administration"
    ],
    "wof:name":"Wassaic Dvlpmntl Dsblts Serv",
    "wof:placetype":"venue"
},
  "geometry": {"coordinates":[-73.577172,41.428707],"type":"Point"}
}