{
  "type": "Feature",
  "properties": {
    "addr:full":"120 Mineola Blvd Mineola NY 11501",
    "addr:housenumber":"120",
    "addr:postcode":"11501",
    "addr:street":"Mineola Blvd",
    "iso:country":"US",
    "sg:address":"120 Mineola Blvd",
    "sg:city":"Mineola",
    "sg:classifiers":[
        {
            "category":"Health Services",
            "subcategory":"Doctor",
            "type":"Services"
        }
    ],
    "sg:phone":"+1 516 248 4848",
    "sg:postcode":"11501",
    "sg:province":"NY",
    "sg:tags":[
        "medical"
    ],
    "wof:name":"Helou N Pierre MD PC",
    "wof:placetype":"venue"
},
  "geometry": {"coordinates":[-73.64031900000001,40.741716],"type":"Point"}
}