{
  "type": "Feature",
  "properties": {
    "addr:full":"19 Fulton St New York NY 10038",
    "addr:housenumber":"19",
    "addr:postcode":"10038",
    "addr:street":"Fulton St",
    "iso:country":"US",
    "sg:address":"19 Fulton St",
    "sg:city":"New York",
    "sg:classifiers":[
        {
            "category":"Organizations",
            "subcategory":"Professional Association",
            "type":"Services"
        }
    ],
    "sg:phone":"+1   ",
    "sg:postcode":"10038",
    "sg:province":"NY",
    "sg:tags":[
        "book",
        "business"
    ],
    "wof:name":"Bkr International",
    "wof:placetype":"venue"
},
  "geometry": {"coordinates":[-74.003941,40.707228],"type":"Point"}
}