{
  "type": "Feature",
  "properties": {
    "iso:country":"US",
    "sg:address":"603 W 168th Street",
    "sg:city":"New York",
    "sg:classifiers":[
        {
            "category":"Deli",
            "type":"Food & Drink"
        }
    ],
    "sg:phone":"+1 212 568 3838",
    "sg:postcode":"10032",
    "sg:province":"NY",
    "wof:name":"University Deli",
    "wof:placetype":"venue"
},
  "geometry": {"coordinates":[-73.93997299999999,40.841049],"type":"Point"}
}