{
  "type": "Feature",
  "properties": {
    "iso:country":"US",
    "sg:address":"44 Stuyvesant Rd",
    "sg:city":"Oakdale",
    "sg:classifiers":[
        {
            "category":"Freight",
            "type":"Transportation"
        }
    ],
    "sg:phone":"+1   ",
    "sg:postcode":"11769",
    "sg:province":"NY",
    "sg:tags":[
        "operator",
        "local",
        "trucking"
    ],
    "wof:name":"Rovin Trucking",
    "wof:placetype":"venue"
},
  "geometry": {"coordinates":[-73.133633,40.741794],"type":"Point"}
}