{
  "type": "Feature",
  "properties": {
    "iso:country":"US",
    "sg:address":"126 Thatford Ave",
    "sg:city":"Brooklyn",
    "sg:classifiers":[
        {
            "category":"Shopping",
            "subcategory":"Music",
            "type":"Retail Goods"
        }
    ],
    "sg:phone":"+1   ",
    "sg:postcode":"11212",
    "sg:province":"NY",
    "wof:name":"Mundo Musical Shop",
    "wof:placetype":"venue"
},
  "geometry": {"coordinates":[-73.909803,40.669824],"type":"Point"}
}