{
  "type": "Feature",
  "properties": {
    "addr:full":"2176 Eisenhower Dr Seneca Falls NY 13148",
    "addr:housenumber":"2176",
    "addr:postcode":"13148",
    "addr:street":"Eisenhower Dr",
    "iso:country":"US",
    "sg:address":"2176 Eisenhower Dr",
    "sg:city":"Seneca Falls",
    "sg:classifiers":[
        {
            "category":"Health Services",
            "subcategory":"Chiropractor",
            "type":"Services"
        }
    ],
    "sg:phone":"+1   ",
    "sg:postcode":"13148",
    "sg:province":"NY",
    "wof:name":"Seneca FLS Chiropractic Group",
    "wof:placetype":"venue"
},
  "geometry": {"coordinates":[-76.759483,42.919143],"type":"Point"}
}