{
  "type": "Feature",
  "properties": {
    "addr:full":"3265 Johnson Ave Bronx NY 10463",
    "addr:housenumber":"3265",
    "addr:postcode":"10463",
    "addr:street":"Johnson Ave",
    "iso:country":"US",
    "sg:address":"3265 Johnson Ave",
    "sg:city":"Bronx",
    "sg:classifiers":[
        {
            "category":"Building & Trades",
            "subcategory":"Construction",
            "type":"Services"
        }
    ],
    "sg:phone":"+1 718 543 9011",
    "sg:postcode":"10463",
    "sg:province":"NY",
    "sg:tags":[
        "general",
        "contractor"
    ],
    "wof:name":"Burtis Construction",
    "wof:placetype":"venue"
},
  "geometry": {"coordinates":[-73.910113,40.885191],"type":"Point"}
}