{
  "type": "Feature",
  "properties": {
    "addr:full":"36 Main St Mount Morris NY 14510",
    "addr:housenumber":"36",
    "addr:postcode":"14510",
    "addr:street":"Main St",
    "iso:country":"US",
    "sg:address":"36 Main St",
    "sg:city":"Mount Morris",
    "sg:classifiers":[
        {
            "category":"Bars & Pubs",
            "type":"Food & Drink"
        }
    ],
    "sg:phone":"+1   ",
    "sg:postcode":"14510",
    "sg:province":"NY",
    "sg:tags":[
        "drinking"
    ],
    "wof:name":"Freds",
    "wof:placetype":"venue"
},
  "geometry": {"coordinates":[-77.874527,42.726296],"type":"Point"}
}