{
  "type": "Feature",
  "properties": {
    "addr:full":"292 Madison Ave New York NY 10017",
    "addr:housenumber":"292",
    "addr:postcode":"10017",
    "addr:street":"Madison Ave",
    "iso:country":"US",
    "sg:address":"292 Madison Ave",
    "sg:city":"New York",
    "sg:classifiers":[
        {
            "category":"Professional",
            "subcategory":"Lawyer & Legal Services",
            "type":"Services"
        }
    ],
    "sg:phone":"+1 212 532 1200",
    "sg:postcode":"10017",
    "sg:province":"NY",
    "sg:tags":[
        "attorney"
    ],
    "wof:name":"Alvin M Bernstone Law Offices",
    "wof:placetype":"venue"
},
  "geometry": {"coordinates":[-73.980048,40.75179],"type":"Point"}
}