{
  "type": "Feature",
  "properties": {
    "iso:country":"US",
    "sg:address":"420 Georgia Ave",
    "sg:city":"Brooklyn",
    "sg:classifiers":[
        {
            "category":"Education",
            "subcategory":"Special Training",
            "type":"Public Place"
        }
    ],
    "sg:phone":"+1   ",
    "sg:postcode":"11207",
    "sg:province":"NY",
    "sg:tags":[
        "educational"
    ],
    "wof:name":"Diana Books Plus & Culture Ctr",
    "wof:placetype":"venue"
},
  "geometry": {"coordinates":[-73.896635,40.667285],"type":"Point"}
}