{
  "type": "Feature",
  "properties": {
    "addr:full":"49-04 Vernon Blvd Long Island City NY 11101",
    "addr:housenumber":"49-04",
    "addr:postcode":"11101",
    "addr:street":"Vernon Blvd",
    "iso:country":"US",
    "sg:address":"49-04 Vernon Blvd",
    "sg:city":"Long Island City",
    "sg:classifiers":[
        {
            "category":"Shopping",
            "subcategory":"Bicycles & Sporting Goods",
            "type":"Retail Goods"
        },
        {
            "category":"Sports & Exercise",
            "subcategory":"Bicycle Rental",
            "type":"Entertainment"
        }
    ],
    "sg:phone":"+1 718 433 0450",
    "sg:postcode":"11101",
    "sg:province":"NY",
    "sg:tags":[
        "bike"
    ],
    "sg:website":"www.spokesmancycles.com",
    "wof:name":"Spokesman Cycles",
    "wof:placetype":"venue"
},
  "geometry": {"coordinates":[-73.95387700000001,40.743376],"type":"Point"}
}