{
  "type": "Feature",
  "properties": {
    "addr:full":"92 W Milton St Freeport NY 11520",
    "addr:housenumber":"92",
    "addr:postcode":"11520",
    "addr:street":"W Milton St",
    "iso:country":"US",
    "sg:address":"92 W Milton St",
    "sg:city":"Freeport",
    "sg:classifiers":[
        {
            "category":"Social Services",
            "subcategory":"Child Care",
            "type":"Services"
        }
    ],
    "sg:phone":"+1 516 223 0636",
    "sg:postcode":"11520",
    "sg:province":"NY",
    "wof:name":"Susie's Daycare",
    "wof:placetype":"venue"
},
  "geometry": {"coordinates":[-73.59077600000001,40.663435],"type":"Point"}
}