{
  "type": "Feature",
  "properties": {
    "iso:country":"US",
    "sg:address":"3517 Long Beach Rd",
    "sg:city":"Oceanside",
    "sg:classifiers":[
        {
            "category":"Shopping",
            "subcategory":"Clothing, Apparel, & Fashions",
            "type":"Retail Goods"
        }
    ],
    "sg:phone":"+1 516 599 2687",
    "sg:postcode":"11572",
    "sg:province":"NY",
    "sg:tags":[
        "accessory"
    ],
    "sg:website":"lanebryant.charmingshoppes.com",
    "wof:name":"Lane Bryant",
    "wof:placetype":"venue"
},
  "geometry": {"coordinates":[-73.639397,40.624599],"type":"Point"}
}