{
  "type": "Feature",
  "properties": {
    "iso:country":"US",
    "sg:address":"1 Executive Blvd",
    "sg:city":"Yonkers",
    "sg:classifiers":[
        {
            "category":"Professional",
            "subcategory":"Computer Services",
            "type":"Services"
        }
    ],
    "sg:phone":"+1 914 963 6600",
    "sg:postcode":"10701",
    "sg:province":"NY",
    "sg:tags":[
        "development",
        "software"
    ],
    "wof:name":"Cybra Corporation",
    "wof:placetype":"venue"
},
  "geometry": {"coordinates":[-73.881176,40.970659],"type":"Point"}
}