{
  "type": "Feature",
  "properties": {
    "addr:full":"511 Bolton Ave Bronx NY 10473",
    "addr:housenumber":"511",
    "addr:postcode":"10473",
    "addr:street":"Bolton Ave",
    "iso:country":"US",
    "sg:address":"511 Bolton Ave",
    "sg:city":"Bronx",
    "sg:classifiers":[
        {
            "category":"Building & Trades",
            "subcategory":"Landscaping Services",
            "type":"Services"
        }
    ],
    "sg:phone":"+1 718 842 5356",
    "sg:postcode":"10473",
    "sg:province":"NY",
    "sg:tags":[
        "landscape"
    ],
    "wof:name":"Nestler Walter",
    "wof:placetype":"venue"
},
  "geometry": {"coordinates":[-73.858327,40.81751],"type":"Point"}
}