{
  "type": "Feature",
  "properties": {
    "addr:full":"8304 Cole Rd Colden NY 14033",
    "addr:housenumber":"8304",
    "addr:postcode":"14033",
    "addr:street":"Cole Rd",
    "iso:country":"US",
    "sg:address":"8304 Cole Rd",
    "sg:city":"Colden",
    "sg:classifiers":[
        {
            "category":"Organizations",
            "subcategory":"Religious Organization",
            "type":"Services"
        }
    ],
    "sg:phone":"+1 716 941 3335",
    "sg:postcode":"14033",
    "sg:province":"NY",
    "sg:tags":[
        "church"
    ],
    "wof:name":"St Martin's Lutheran Church",
    "wof:placetype":"venue"
},
  "geometry": {"coordinates":[-78.71635000000001,42.659311],"type":"Point"}
}