{
  "type": "Feature",
  "properties": {
    "addr:full":"10807 Corona Avenue Corona NY 11368",
    "addr:housenumber":"10807",
    "addr:postcode":"11368",
    "addr:street":"Corona Avenue",
    "iso:country":"US",
    "sg:address":"10807 Corona Avenue",
    "sg:city":"Corona",
    "sg:classifiers":[
        {
            "category":"Shopping",
            "subcategory":"Pharmacy",
            "type":"Retail Goods"
        }
    ],
    "sg:phone":"+1 800 471 7172",
    "sg:postcode":"11368",
    "sg:province":"NY",
    "sg:tags":[
        "drugstore"
    ],
    "wof:name":"Drug Meadow Park",
    "wof:placetype":"venue"
},
  "geometry": {"coordinates":[-73.854152,40.742716],"type":"Point"}
}