{
  "type": "Feature",
  "properties": {
    "addr:full":"73 Grand St Newburgh NY 12550",
    "addr:housenumber":"73",
    "addr:postcode":"12550",
    "addr:street":"Grand St",
    "iso:country":"US",
    "sg:address":"73 Grand St",
    "sg:city":"Newburgh",
    "sg:classifiers":[
        {
            "category":"Health Services",
            "subcategory":"Nursing And Care Facility",
            "type":"Services"
        }
    ],
    "sg:phone":"+1 845 561 1342",
    "sg:postcode":"12550",
    "sg:province":"NY",
    "sg:tags":[
        "home",
        "convalescent"
    ],
    "sg:website":"www.holdenhome.org",
    "wof:name":"Amos & Sarah Holden Home",
    "wof:placetype":"venue"
},
  "geometry": {"coordinates":[-74.00969499999999,41.500706],"type":"Point"}
}