{
  "type": "Feature",
  "properties": {
    "addr:full":"48 Macy Rd Briarcliff Manor NY 10510",
    "addr:housenumber":"48",
    "addr:postcode":"10510",
    "addr:street":"Macy Rd",
    "iso:country":"US",
    "sg:address":"48 Macy Rd",
    "sg:city":"Briarcliff Manor",
    "sg:classifiers":[
        {
            "category":"Government",
            "subcategory":"Office",
            "type":"Public Place"
        }
    ],
    "sg:phone":"+1 914 941 6534",
    "sg:postcode":"10510",
    "sg:province":"NY",
    "sg:tags":[
        "village"
    ],
    "wof:name":"Briarcliff Manor Youth Dept",
    "wof:placetype":"venue"
},
  "geometry": {"coordinates":[-73.855789,41.155146],"type":"Point"}
}