{
  "type": "Feature",
  "properties": {
    "iso:country":"US",
    "sg:address":"1584 86th St",
    "sg:city":"Brooklyn",
    "sg:classifiers":[
        {
            "category":"Shopping",
            "subcategory":"Florist",
            "type":"Retail Goods"
        }
    ],
    "sg:phone":"+1 718 837 4944",
    "sg:postcode":"11228",
    "sg:province":"NY",
    "wof:name":"Artistic 86 St Florist",
    "wof:placetype":"venue"
},
  "geometry": {"coordinates":[-74.007694,40.609961],"type":"Point"}
}