{
  "type": "Feature",
  "properties": {
    "iso:country":"US",
    "sg:address":"1531 Central Ave",
    "sg:city":"Albany",
    "sg:classifiers":[
        {
            "category":"Professional",
            "subcategory":"Lawyer & Legal Services",
            "type":"Services"
        }
    ],
    "sg:phone":"+1 518 452 7080",
    "sg:postcode":"12205",
    "sg:province":"NY",
    "sg:tags":[
        "attorney"
    ],
    "wof:name":"Samuel N Iroegdu Law Firm",
    "wof:placetype":"venue"
},
  "geometry": {"coordinates":[-73.828228,42.71351],"type":"Point"}
}