{
  "type": "Feature",
  "properties": {
    "addr:full":"9091 Hawkinsville Rd Boonville NY 13309",
    "addr:housenumber":"9091",
    "addr:postcode":"13309",
    "addr:street":"Hawkinsville Rd",
    "iso:country":"US",
    "sg:address":"9091 Hawkinsville Rd",
    "sg:city":"Boonville",
    "sg:classifiers":[
        {
            "category":"Building & Trades",
            "subcategory":"Landscaping Services",
            "type":"Services"
        }
    ],
    "sg:phone":"+1 315 942 4325",
    "sg:postcode":"13309",
    "sg:province":"NY",
    "wof:name":"Keith Gardner Lawn Care",
    "wof:placetype":"venue"
},
  "geometry": {"coordinates":[-75.284671,43.490094],"type":"Point"}
}