{
  "type": "Feature",
  "properties": {
    "addr:full":"21 Maplemoor Ln White Plains NY 10605",
    "addr:housenumber":"21",
    "addr:postcode":"10605",
    "addr:street":"Maplemoor Ln",
    "iso:country":"US",
    "sg:address":"21 Maplemoor Ln",
    "sg:city":"White Plains",
    "sg:classifiers":[
        {
            "category":"Building & Trades",
            "subcategory":"Landscaping Services",
            "type":"Services"
        }
    ],
    "sg:phone":"+1 914 997 5666",
    "sg:postcode":"10605",
    "sg:province":"NY",
    "sg:tags":[
        "landscaper"
    ],
    "wof:name":"Tony Portanova Landscaping",
    "wof:placetype":"venue"
},
  "geometry": {"coordinates":[-73.73598699999999,41.004768],"type":"Point"}
}