{
  "type": "Feature",
  "properties": {
    "addr:full":"259 Columbia St Brooklyn NY 11231",
    "addr:housenumber":"259",
    "addr:postcode":"11231",
    "addr:street":"Columbia St",
    "iso:country":"US",
    "sg:address":"259 Columbia St",
    "sg:city":"Brooklyn",
    "sg:classifiers":[
        {
            "category":"Recreation",
            "type":"Entertainment"
        }
    ],
    "sg:phone":"+1 718 403 0305",
    "sg:postcode":"11231",
    "sg:province":"NY",
    "sg:tags":[
        "instruction",
        "yoga"
    ],
    "wof:name":"Vayu Yoga Ctr",
    "wof:placetype":"venue"
},
  "geometry": {"coordinates":[-74.00341400000001,40.683494],"type":"Point"}
}