{
  "type": "Feature",
  "properties": {
    "addr:full":"301 Winding Rd Old Bethpage NY 11804",
    "addr:housenumber":"301",
    "addr:postcode":"11804",
    "addr:street":"Winding Rd",
    "iso:country":"US",
    "sg:address":"301 Winding Rd",
    "sg:city":"Old Bethpage",
    "sg:classifiers":[
        {
            "category":"Building & Trades",
            "subcategory":"Construction",
            "type":"Services"
        }
    ],
    "sg:phone":"+1 516 249 7500",
    "sg:postcode":"11804",
    "sg:province":"NY",
    "sg:tags":[
        "general",
        "contractor"
    ],
    "wof:name":"CIA Construction Inc",
    "wof:placetype":"venue"
},
  "geometry": {"coordinates":[-73.448587,40.763082],"type":"Point"}
}