{
  "type": "Feature",
  "properties": {
    "addr:full":"9 Crossover Rd Ronkonkoma NY 11779",
    "addr:housenumber":"9",
    "addr:postcode":"11779",
    "addr:street":"Crossover Rd",
    "iso:country":"US",
    "sg:address":"9 Crossover Rd",
    "sg:city":"Ronkonkoma",
    "sg:classifiers":[
        {
            "category":"Health Services",
            "subcategory":"Medical Lab",
            "type":"Services"
        }
    ],
    "sg:phone":"+1 631 471 4430",
    "sg:postcode":"11779",
    "sg:province":"NY",
    "sg:tags":[
        "laboratory"
    ],
    "wof:name":"Lake Imaging Inc",
    "wof:placetype":"venue"
},
  "geometry": {"coordinates":[-73.078609,40.843227],"type":"Point"}
}