{
  "type": "Feature",
  "properties": {
    "iso:country":"US",
    "sg:address":"210 Centre St",
    "sg:city":"New York",
    "sg:classifiers":[
        {
            "category":"Professional",
            "subcategory":"Printing & Photocopies",
            "type":"Services"
        }
    ],
    "sg:phone":"+1 212 226 9065",
    "sg:postcode":"10013",
    "sg:province":"NY",
    "wof:name":"G & P Printing",
    "wof:placetype":"venue"
},
  "geometry": {"coordinates":[-73.99873100000001,40.718999],"type":"Point"}
}