{
  "type": "Feature",
  "properties": {
    "iso:country":"US",
    "sg:address":"6910 Myrtle Avenue",
    "sg:city":"Glendale",
    "sg:classifiers":[
        {
            "category":"Restaurant",
            "type":"Food & Drink"
        }
    ],
    "sg:phone":"+1 718 381 3727",
    "sg:postcode":"11385",
    "sg:province":"NY",
    "wof:name":"King Wok",
    "wof:placetype":"venue"
},
  "geometry": {"coordinates":[-73.88236499999999,40.701702],"type":"Point"}
}