{
  "type": "Feature",
  "properties": {
    "addr:full":"158 Francis Ave Buffalo NY 14212",
    "addr:housenumber":"158",
    "addr:postcode":"14212",
    "addr:street":"Francis Ave",
    "iso:country":"US",
    "sg:address":"158 Francis Ave",
    "sg:city":"Buffalo",
    "sg:classifiers":[
        {
            "category":"Building & Trades",
            "subcategory":"Construction",
            "type":"Services"
        }
    ],
    "sg:phone":"+1 716 896 8785",
    "sg:postcode":"14212",
    "sg:province":"NY",
    "sg:tags":[
        "painting",
        "contractor"
    ],
    "wof:name":"Excel Painting Co",
    "wof:placetype":"venue"
},
  "geometry": {"coordinates":[-78.78743,42.897489],"type":"Point"}
}