{
  "type": "Feature",
  "properties": {
    "addr:full":"210 E 64th St New York NY 10065",
    "addr:housenumber":"210",
    "addr:postcode":"10065",
    "addr:street":"E 64Th St",
    "iso:country":"US",
    "sg:address":"210 E 64th St",
    "sg:city":"New York",
    "sg:classifiers":[
        {
            "category":"Health Services",
            "subcategory":"Doctor",
            "type":"Services"
        }
    ],
    "sg:phone":"+1 212 434 4343",
    "sg:postcode":"10065",
    "sg:province":"NY",
    "wof:name":"Craig S Radnay",
    "wof:placetype":"venue"
},
  "geometry": {"coordinates":[-73.964122,40.764457],"type":"Point"}
}