{
  "type": "Feature",
  "properties": {
    "addr:full":"940 Roanoke Ave Riverhead NY 11901",
    "addr:housenumber":"940",
    "addr:postcode":"11901",
    "addr:street":"Roanoke Ave",
    "iso:country":"US",
    "sg:address":"940 Roanoke Ave",
    "sg:city":"Riverhead",
    "sg:classifiers":[
        {
            "category":"Health Services",
            "subcategory":"Dentist",
            "type":"Services"
        }
    ],
    "sg:phone":"+1 631 727 4040",
    "sg:postcode":"11901",
    "sg:province":"NY",
    "sg:tags":[
        "orthodontist"
    ],
    "wof:name":"Northeast Orthodontic Associates",
    "wof:placetype":"venue"
},
  "geometry": {"coordinates":[-72.67040299999999,40.928699],"type":"Point"}
}