{
  "type": "Feature",
  "properties": {
    "iso:country":"US",
    "sg:address":"237 25th St",
    "sg:city":"Brooklyn",
    "sg:classifiers":[
        {
            "category":"Wholesale",
            "subcategory":"Furniture",
            "type":"Manufacturing & Wholesale Goods"
        }
    ],
    "sg:phone":"+1 718 832 6441",
    "sg:postcode":"11232",
    "sg:province":"NY",
    "wof:name":"World Wide Furniture Warehouse",
    "wof:placetype":"venue"
},
  "geometry": {"coordinates":[-73.995861,40.659289],"type":"Point"}
}