{
  "type": "Feature",
  "properties": {
    "addr:full":"790 E Delavan Ave Buffalo NY 14215",
    "addr:housenumber":"790",
    "addr:postcode":"14215",
    "addr:street":"E Delavan Ave",
    "iso:country":"US",
    "sg:address":"790 E Delavan Ave",
    "sg:city":"Buffalo",
    "sg:classifiers":[
        {
            "category":"Building & Trades",
            "subcategory":"Electrical",
            "type":"Services"
        }
    ],
    "sg:phone":"+1 716 892 4240",
    "sg:postcode":"14215",
    "sg:province":"NY",
    "sg:tags":[
        "electrician"
    ],
    "wof:name":"American Rated Cable & Communications Inc",
    "wof:placetype":"venue"
},
  "geometry": {"coordinates":[-78.82782,42.922279],"type":"Point"}
}