{
  "type": "Feature",
  "properties": {
    "addr:full":"113 Gold St Brooklyn NY 11201",
    "addr:housenumber":"113",
    "addr:postcode":"11201",
    "addr:street":"Gold St",
    "iso:country":"US",
    "sg:address":"113 Gold St",
    "sg:city":"Brooklyn",
    "sg:classifiers":[
        {
            "category":"Shopping",
            "subcategory":"Pharmacy",
            "type":"Retail Goods"
        }
    ],
    "sg:phone":"+1 718 852 4625",
    "sg:postcode":"11201",
    "sg:province":"NY",
    "sg:tags":[
        "drugstore"
    ],
    "wof:name":"York Pharmacy Inc",
    "wof:placetype":"venue"
},
  "geometry": {"coordinates":[-73.98281,40.701553],"type":"Point"}
}