{
  "type": "Feature",
  "properties": {
    "iso:country":"US",
    "sg:address":"1999 Mount Read Blvd",
    "sg:city":"Rochester",
    "sg:classifiers":[
        {
            "category":"Shopping",
            "subcategory":"Stationery & Office Supplies",
            "type":"Retail Goods"
        }
    ],
    "sg:phone":"+1   ",
    "sg:postcode":"14615",
    "sg:province":"NY",
    "sg:tags":[
        "stationary"
    ],
    "wof:name":"Boise Cascade",
    "wof:placetype":"venue"
},
  "geometry": {"coordinates":[-77.659542,43.193911],"type":"Point"}
}