{
  "type": "Feature",
  "properties": {
    "addr:full":"1444 County Route 23 Constantia NY 13044",
    "addr:housenumber":"1444",
    "addr:postcode":"13044",
    "addr:street":"County Route 23",
    "iso:country":"US",
    "sg:address":"1444 County Route 23",
    "sg:city":"Constantia",
    "sg:classifiers":[
        {
            "category":"Professional",
            "subcategory":"Management & Consulting",
            "type":"Services"
        }
    ],
    "sg:phone":"+1 315 623 9694",
    "sg:postcode":"13044",
    "sg:province":"NY",
    "sg:tags":[
        "science",
        "consultant",
        "academic"
    ],
    "wof:name":"Cooper Environmental",
    "wof:placetype":"venue"
},
  "geometry": {"coordinates":[-76.000247,43.335482],"type":"Point"}
}