{
  "type": "Feature",
  "properties": {
    "addr:full":"6893 Canadice Lake Rd Springwater NY 14560",
    "addr:postcode":"6893;14560",
    "addr:street":"Canadice Lake Rd",
    "iso:country":"US",
    "sg:address":"6893 Canadice Lake Rd",
    "sg:city":"Springwater",
    "sg:classifiers":[
        {
            "category":"Manufacturing",
            "subcategory":"Wood Products",
            "type":"Manufacturing & Wholesale Goods"
        }
    ],
    "sg:phone":"+1   ",
    "sg:postcode":"14560",
    "sg:province":"NY",
    "sg:tags":[
        "mfg"
    ],
    "wof:name":"Canadice Wood Products",
    "wof:placetype":"venue"
},
  "geometry": {"coordinates":[-77.57089000000001,42.687148],"type":"Point"}
}