{
  "type": "Feature",
  "properties": {
    "iso:country":"US",
    "sg:address":"24 W 45 St",
    "sg:city":"New York",
    "sg:classifiers":[
        {
            "category":"Restaurant",
            "type":"Food & Drink"
        }
    ],
    "sg:phone":"+1   ",
    "sg:postcode":"10036",
    "sg:province":"NY",
    "sg:tags":[
        "eating"
    ],
    "wof:name":"Breads From Beirut",
    "wof:placetype":"venue"
},
  "geometry": {"coordinates":[-73.982187,40.756392],"type":"Point"}
}