{
  "type": "Feature",
  "properties": {
    "addr:full":"99 State Hwy 197 Fort Edward NY 12828",
    "addr:housenumber":"99",
    "addr:postcode":"12828",
    "addr:street":"State Hwy 197",
    "iso:country":"US",
    "sg:address":"99 State Hwy 197",
    "sg:city":"Fort Edward",
    "sg:classifiers":[
        {
            "category":"Building & Trades",
            "subcategory":"Plumbing",
            "type":"Services"
        }
    ],
    "sg:phone":"+1 518 747 7060",
    "sg:postcode":"12828",
    "sg:province":"NY",
    "sg:tags":[
        "plumbing",
        "contractor"
    ],
    "wof:name":"Wetherby Plumbing & Heating",
    "wof:placetype":"venue"
},
  "geometry": {"coordinates":[-73.58860799999999,43.265632],"type":"Point"}
}