{
  "type": "Feature",
  "properties": {
    "iso:country":"US",
    "sg:address":"105 E 37th St",
    "sg:city":"New York",
    "sg:classifiers":[
        {
            "category":"Health Services",
            "subcategory":"Doctor",
            "type":"Services"
        }
    ],
    "sg:phone":"+1 212 725 4555",
    "sg:postcode":"10016",
    "sg:province":"NY",
    "sg:tags":[
        "dermatologist"
    ],
    "sg:website":"www.mdskincare.com",
    "wof:name":"GROSS DENNIS",
    "wof:placetype":"venue"
},
  "geometry": {"coordinates":[-73.97949199999999,40.748944],"type":"Point"}
}