{
  "type": "Feature",
  "properties": {
    "addr:full":"42 White Church Ln Troy NY 12180",
    "addr:housenumber":"42",
    "addr:postcode":"12180",
    "addr:street":"White Church Ln",
    "iso:country":"US",
    "sg:address":"42 White Church Ln",
    "sg:city":"Troy",
    "sg:classifiers":[
        {
            "category":"Social Services",
            "subcategory":"Child Care",
            "type":"Services"
        }
    ],
    "sg:phone":"+1 518 279 1140",
    "sg:postcode":"12180",
    "sg:province":"NY",
    "sg:tags":[
        "day"
    ],
    "wof:name":"Tender Loving Care Chrn Dcc",
    "wof:placetype":"venue"
},
  "geometry": {"coordinates":[-73.561652,42.732771],"type":"Point"}
}