{
  "type": "Feature",
  "properties": {
    "iso:country":"US",
    "sg:address":"5041 Galen Rd",
    "sg:city":"Wolcott",
    "sg:classifiers":[
        {
            "category":"Manufacturing",
            "subcategory":"Jewelry",
            "type":"Manufacturing & Wholesale Goods"
        }
    ],
    "sg:phone":"+1   ",
    "sg:postcode":"14590",
    "sg:province":"NY",
    "sg:tags":[
        "material",
        "mfg"
    ],
    "wof:name":"Earthly Designs",
    "wof:placetype":"venue"
},
  "geometry": {"coordinates":[-76.83453900000001,43.189295],"type":"Point"}
}