{
  "type": "Feature",
  "properties": {
    "addr:full":"299 Guyon Ave Staten Island NY 10306",
    "addr:housenumber":"299",
    "addr:postcode":"10306",
    "addr:street":"Guyon Ave",
    "iso:country":"US",
    "sg:address":"299 Guyon Ave",
    "sg:city":"Staten Island",
    "sg:classifiers":[
        {
            "category":"Health Services",
            "subcategory":"Doctor",
            "type":"Services"
        }
    ],
    "sg:phone":"+1 718 987 5840",
    "sg:postcode":"10306",
    "sg:province":"NY",
    "sg:tags":[
        "medical"
    ],
    "wof:name":"Arnold H Nussbaum",
    "wof:placetype":"venue"
},
  "geometry": {"coordinates":[-74.120842,40.560866],"type":"Point"}
}