{
  "type": "Feature",
  "properties": {
    "iso:country":"US",
    "sg:address":"20 Churchill St",
    "sg:city":"Buffalo",
    "sg:classifiers":[
        {
            "category":"Food & Beverages",
            "subcategory":"Liquor & Beverages",
            "type":"Retail Goods"
        }
    ],
    "sg:phone":"+1 716 332 2541",
    "sg:postcode":"14207",
    "sg:province":"NY",
    "sg:tags":[
        "wine"
    ],
    "wof:name":"Concord Wine",
    "wof:placetype":"venue"
},
  "geometry": {"coordinates":[-78.895702,42.93803],"type":"Point"}
}