{
  "type": "Feature",
  "properties": {
    "addr:full":"466 Ballston Rd Schenectady NY 12302",
    "addr:housenumber":"466",
    "addr:postcode":"12302",
    "addr:street":"Ballston Rd",
    "iso:country":"US",
    "sg:address":"466 Ballston Rd",
    "sg:city":"Schenectady",
    "sg:classifiers":[
        {
            "category":"Banks & Credit Unions",
            "subcategory":"Bank",
            "type":"Services"
        }
    ],
    "sg:phone":"+1 518 370 7755",
    "sg:postcode":"12302",
    "sg:province":"NY",
    "sg:tags":[
        "state",
        "commercial"
    ],
    "wof:name":"Fleet",
    "wof:placetype":"venue"
},
  "geometry": {"coordinates":[-73.94413,42.847018],"type":"Point"}
}