{
  "type": "Feature",
  "properties": {
    "iso:country":"US",
    "sg:address":"199 Malcolm X Blvd Ste 1",
    "sg:city":"Brooklyn",
    "sg:classifiers":[
        {
            "category":"Sports & Exercise",
            "subcategory":"Sports Center",
            "type":"Entertainment"
        }
    ],
    "sg:phone":"+1 718 443 0744",
    "sg:postcode":"11221",
    "sg:province":"NY",
    "wof:name":"Club",
    "wof:placetype":"venue"
},
  "geometry": {"coordinates":[-73.929732,40.686279],"type":"Point"}
}