{
  "type": "Feature",
  "properties": {
    "addr:full":"2032 Bedford Ave. Brooklyn NY 11226",
    "addr:housenumber":"2032",
    "addr:postcode":"11226",
    "addr:street":"Bedford Ave.",
    "iso:country":"US",
    "sg:address":"2032 Bedford Ave.",
    "sg:city":"Brooklyn",
    "sg:classifiers":[
        {
            "category":"Restaurant",
            "type":"Food & Drink"
        }
    ],
    "sg:phone":"+1 718 282 7012",
    "sg:postcode":"11226",
    "sg:province":"NY",
    "sg:tags":[
        "indian"
    ],
    "wof:name":"Gandhi Fine Indian Cuisine",
    "wof:placetype":"venue"
},
  "geometry": {"coordinates":[-73.956328,40.655103],"type":"Point"}
}