{
  "type": "Feature",
  "properties": {
    "addr:full":"316 Lafayette Rd Rochester NY 14609",
    "addr:housenumber":"316",
    "addr:postcode":"14609",
    "iso:country":"US",
    "sg:address":"316 Lafayette Rd",
    "sg:city":"Rochester",
    "sg:classifiers":[
        {
            "category":"Retail",
            "subcategory":"Animal Services",
            "type":"Services"
        }
    ],
    "sg:phone":"+1 585 288 0780",
    "sg:postcode":"14609",
    "sg:province":"NY",
    "wof:name":"Minchlla Bob Dog Owner Cnsling",
    "wof:placetype":"venue"
},
  "geometry": {"coordinates":[-77.546402,43.182564],"type":"Point"}
}