{
  "type": "Feature",
  "properties": {
    "iso:country":"US",
    "sg:address":"3144 N Gravel Rd",
    "sg:city":"Medina",
    "sg:classifiers":[
        {
            "category":"Retail",
            "subcategory":"Veterinary Services",
            "type":"Services"
        }
    ],
    "sg:phone":"+1 585 798 0274",
    "sg:postcode":"14103",
    "sg:province":"NY",
    "sg:tags":[
        "veterinarian"
    ],
    "wof:name":"Medina Veterinary Clinic",
    "wof:placetype":"venue"
},
  "geometry": {"coordinates":[-78.39538,43.262265],"type":"Point"}
}