{
  "type": "Feature",
  "properties": {
    "addr:full":"1977 Fulton St Brooklyn NY 11233",
    "addr:housenumber":"1977",
    "addr:postcode":"11233",
    "addr:street":"Fulton St",
    "iso:country":"US",
    "sg:address":"1977 Fulton St",
    "sg:city":"Brooklyn",
    "sg:classifiers":[
        {
            "category":"Organizations",
            "subcategory":"Religious Organization",
            "type":"Services"
        }
    ],
    "sg:phone":"+1 718 485 8100",
    "sg:postcode":"11233",
    "sg:province":"NY",
    "sg:tags":[
        "church"
    ],
    "wof:name":"World Outreach Christian Ctr",
    "wof:placetype":"venue"
},
  "geometry": {"coordinates":[-73.91401500000001,40.678535],"type":"Point"}
}