{
  "type": "Feature",
  "properties": {
    "addr:full":"137 W 72nd St 2nd Fl New York NY 10023",
    "addr:housenumber":"137",
    "addr:postcode":"10023",
    "addr:street":"W 72Nd St",
    "iso:country":"US",
    "sg:address":"137 W 72nd St 2nd Fl",
    "sg:city":"New York",
    "sg:classifiers":[
        {
            "category":"Personal",
            "subcategory":"Beauty Salon",
            "type":"Services"
        }
    ],
    "sg:phone":"+1 347 583 0809",
    "sg:postcode":"10023",
    "sg:province":"NY",
    "sg:tags":[
        "hair"
    ],
    "sg:website":"www.jeromestyles.com",
    "wof:name":"Jerome Styles Hair Care",
    "wof:placetype":"venue"
},
  "geometry": {"coordinates":[-73.980183,40.778004],"type":"Point"}
}