{
  "type": "Feature",
  "properties": {
    "iso:country":"US",
    "sg:address":"710 Prospect Pl",
    "sg:city":"Bellmore",
    "sg:classifiers":[
        {
            "category":"Social Services",
            "type":"Services"
        }
    ],
    "sg:phone":"+1   ",
    "sg:postcode":"11710",
    "sg:province":"NY",
    "wof:name":"Solz William",
    "wof:placetype":"venue"
},
  "geometry": {"coordinates":[-73.529996,40.660148],"type":"Point"}
}