{
  "type": "Feature",
  "properties": {
    "iso:country":"US",
    "sg:address":"45 Old Orchard Rd",
    "sg:city":"New Rochelle",
    "sg:classifiers":[
        {
            "category":"Professional",
            "subcategory":"Business Services",
            "type":"Services"
        }
    ],
    "sg:phone":"+1   ",
    "sg:postcode":"10804",
    "sg:province":"NY",
    "wof:name":"Crm Assoc Ltd",
    "wof:placetype":"venue"
},
  "geometry": {"coordinates":[-73.798918,40.945026],"type":"Point"}
}