{
  "type": "Feature",
  "properties": {
    "addr:full":"163 W 80th St New York NY 10024",
    "addr:housenumber":"163",
    "addr:postcode":"10024",
    "addr:street":"W 80Th St",
    "iso:country":"US",
    "sg:address":"163 W 80th St",
    "sg:city":"New York",
    "sg:classifiers":[
        {
            "category":"Wholesale",
            "subcategory":"Computers",
            "type":"Manufacturing & Wholesale Goods"
        }
    ],
    "sg:phone":"+1 800 819 0400",
    "sg:postcode":"10024",
    "sg:province":"NY",
    "wof:name":"Computer Help Inc",
    "wof:placetype":"venue"
},
  "geometry": {"coordinates":[-73.97722400000001,40.783738],"type":"Point"}
}