{
  "type": "Feature",
  "properties": {
    "addr:full":"401 Union St Schenectady NY 12305",
    "addr:housenumber":"401",
    "addr:postcode":"12305",
    "addr:street":"Union St",
    "iso:country":"US",
    "sg:address":"401 Union St",
    "sg:city":"Schenectady",
    "sg:classifiers":[
        {
            "category":"Health Services",
            "subcategory":"Hospital",
            "type":"Services"
        }
    ],
    "sg:phone":"+1 518 372 9375",
    "sg:postcode":"12305",
    "sg:province":"NY",
    "sg:tags":[
        "mental"
    ],
    "wof:name":"Mohawk Opportunites In Mental",
    "wof:placetype":"venue"
},
  "geometry": {"coordinates":[-73.939718,42.816179],"type":"Point"}
}