{
  "type": "Feature",
  "properties": {
    "addr:full":"50 Raymond Ave Poughkeepsie NY 12603",
    "addr:housenumber":"50",
    "addr:postcode":"12603",
    "addr:street":"Raymond Ave",
    "iso:country":"US",
    "sg:address":"50 Raymond Ave",
    "sg:city":"Poughkeepsie",
    "sg:classifiers":[
        {
            "category":"Restaurant",
            "type":"Food & Drink"
        }
    ],
    "sg:menulink":"http://www.allmenus.com/ny/poughkeepsie/38000-kismat-indian-restaurant/menu/",
    "sg:phone":"+1 845 473 5850",
    "sg:postcode":"12603",
    "sg:province":"NY",
    "sg:tags":[
        "indian",
        "asian"
    ],
    "wof:name":"Kismat Indian Restaurant",
    "wof:placetype":"venue"
},
  "geometry": {"coordinates":[-73.900216,41.69237],"type":"Point"}
}