{
  "type": "Feature",
  "properties": {
    "iso:country":"US",
    "sg:address":"125 Maple St",
    "sg:city":"Massena",
    "sg:classifiers":[
        {
            "category":"Autos & Motor Vehicles",
            "subcategory":"Auto Supplies",
            "type":"Retail Goods"
        },
        {
            "category":"Retail",
            "subcategory":"Auto Repair",
            "type":"Services"
        }
    ],
    "sg:phone":"+1 315 769 6035",
    "sg:postcode":"13662",
    "sg:province":"NY",
    "sg:tags":[
        "automotive",
        "who",
        "general",
        "parts",
        "truck",
        "automobile"
    ],
    "wof:name":"Layo's Auto Parts & Svc",
    "wof:placetype":"venue"
},
  "geometry": {"coordinates":[-74.90179999999999,44.935595],"type":"Point"}
}