{
  "type": "Feature",
  "properties": {
    "addr:full":"100 Kingsley Rd Rochester NY 14612",
    "addr:housenumber":"100",
    "addr:postcode":"14612",
    "addr:street":"Kingsley Rd",
    "iso:country":"US",
    "sg:address":"100 Kingsley Rd",
    "sg:city":"Rochester",
    "sg:classifiers":[
        {
            "category":"Retail",
            "subcategory":"Portrait Studio",
            "type":"Services"
        }
    ],
    "sg:phone":"+1   ",
    "sg:postcode":"14612",
    "sg:province":"NY",
    "sg:tags":[
        "photo"
    ],
    "wof:name":"Paw Prints Studio",
    "wof:placetype":"venue"
},
  "geometry": {"coordinates":[-77.626318,43.233705],"type":"Point"}
}