{
  "type": "Feature",
  "properties": {
    "addr:full":"790 11th Avenue New York NY 10019",
    "addr:housenumber":"790",
    "addr:postcode":"10019",
    "addr:street":"11Th Avenue",
    "iso:country":"US",
    "sg:address":"790 11th Avenue",
    "sg:city":"New York",
    "sg:classifiers":[
        {
            "category":"Home & Garden",
            "subcategory":"Garden Supply",
            "type":"Retail Goods"
        },
        {
            "category":"Shopping",
            "subcategory":"Florist",
            "type":"Retail Goods"
        }
    ],
    "sg:phone":"+1 212 707 8477",
    "sg:postcode":"10019",
    "sg:province":"NY",
    "sg:tags":[
        "nursery",
        "gardening"
    ],
    "wof:name":"Manhattan Tower Florists",
    "wof:placetype":"venue"
},
  "geometry": {"coordinates":[-73.992599,40.768662],"type":"Point"}
}