{
  "type": "Feature",
  "properties": {
    "iso:country":"US",
    "sg:address":"235 Brooksite Dr",
    "sg:city":"Hauppauge",
    "sg:classifiers":[
        {
            "category":"Professional",
            "type":"Services"
        }
    ],
    "sg:phone":"+1 631 361 7326",
    "sg:postcode":"11787",
    "sg:province":"NY",
    "sg:tags":[
        "establishment"
    ],
    "wof:name":"Kings Park School District",
    "wof:placetype":"venue"
},
  "geometry": {"coordinates":[-73.205834,40.828084],"type":"Point"}
}