{
  "type": "Feature",
  "properties": {
    "iso:country":"US",
    "sg:address":"290 Taylor St",
    "sg:city":"Staten Island",
    "sg:classifiers":[
        {
            "category":"Shopping",
            "subcategory":"Musical Instruments",
            "type":"Retail Goods"
        }
    ],
    "sg:phone":"+1   ",
    "sg:postcode":"10310",
    "sg:province":"NY",
    "sg:tags":[
        "equipment"
    ],
    "wof:name":"Services On Time Entertainment",
    "wof:placetype":"venue"
},
  "geometry": {"coordinates":[-74.122596,40.629998],"type":"Point"}
}