{
  "type": "Feature",
  "properties": {
    "addr:full":"1350 Carlisle Rd Sprakers NY 12166",
    "addr:housenumber":"1350",
    "addr:postcode":"12166",
    "addr:street":"Carlisle Rd",
    "iso:country":"US",
    "sg:address":"1350 Carlisle Rd",
    "sg:city":"Sprakers",
    "sg:classifiers":[
        {
            "category":"Travel",
            "subcategory":"Campground",
            "type":"Entertainment"
        }
    ],
    "sg:phone":"+1 518 673 2886",
    "sg:postcode":"12166",
    "sg:province":"NY",
    "sg:tags":[
        "nudist",
        "parks"
    ],
    "wof:name":"Full-Tan Sun Club",
    "wof:placetype":"venue"
},
  "geometry": {"coordinates":[-74.48855,42.829094],"type":"Point"}
}