{
  "type": "Feature",
  "properties": {
    "addr:full":"6221 State Hwy 31 Cicero NY 13039",
    "addr:housenumber":"6221",
    "addr:postcode":"13039",
    "addr:street":"State Hwy 31",
    "iso:country":"US",
    "sg:address":"6221 State Hwy 31",
    "sg:city":"Cicero",
    "sg:classifiers":[
        {
            "category":"Building & Trades",
            "subcategory":"Construction",
            "type":"Services"
        }
    ],
    "sg:phone":"+1 315 699 4359",
    "sg:postcode":"13039",
    "sg:province":"NY",
    "sg:tags":[
        "residential",
        "house"
    ],
    "wof:name":"Jmc Construction Svces Ltd",
    "wof:placetype":"venue"
},
  "geometry": {"coordinates":[-76.090099,43.176814],"type":"Point"}
}