{
  "type": "Feature",
  "properties": {
    "addr:full":"1520 Main St Port Jefferson NY 11777",
    "addr:housenumber":"1520",
    "addr:postcode":"11777",
    "addr:street":"Main St",
    "iso:country":"US",
    "sg:address":"1520 Main St",
    "sg:city":"Port Jefferson",
    "sg:classifiers":[
        {
            "category":"Restaurant",
            "type":"Food & Drink"
        }
    ],
    "sg:menulink":"http://www.allmenus.com/ny/brookhaven/257853-little-hong-kong/menu/",
    "sg:phone":"+1 631 331 5009",
    "sg:postcode":"11777",
    "sg:province":"NY",
    "sg:tags":[
        "asian",
        "chinese"
    ],
    "wof:name":"Little Hong Kong",
    "wof:placetype":"venue"
},
  "geometry": {"coordinates":[-73.055825,40.935557],"type":"Point"}
}