{
  "type": "Feature",
  "properties": {
    "addr:full":"530 Smithtown Byp Smithtown NY 11787",
    "addr:housenumber":"530",
    "addr:postcode":"11787",
    "addr:street":"Byp",
    "iso:country":"US",
    "sg:address":"530 Smithtown Byp",
    "sg:city":"Smithtown",
    "sg:classifiers":[
        {
            "category":"Casinos & Gambling",
            "type":"Entertainment"
        }
    ],
    "sg:phone":"+1 800 244 9467",
    "sg:postcode":"11787",
    "sg:province":"NY",
    "wof:name":"Suffolk Regional Off-Track Betting Corp",
    "wof:placetype":"venue"
},
  "geometry": {"coordinates":[-73.19433100000001,40.832295],"type":"Point"}
}