{
  "type": "Feature",
  "properties": {
    "addr:full":"3946 Vine Rd Penn Yan NY 14527",
    "addr:housenumber":"3946",
    "addr:postcode":"14527",
    "addr:street":"Vine Rd",
    "iso:country":"US",
    "sg:address":"3946 Vine Rd",
    "sg:city":"Penn Yan",
    "sg:classifiers":[
        {
            "category":"Organizations",
            "subcategory":"Religious Organization",
            "type":"Services"
        }
    ],
    "sg:phone":"+1 315 536 7951",
    "sg:postcode":"14527",
    "sg:province":"NY",
    "sg:tags":[
        "clergy"
    ],
    "wof:name":"Gerard T Remsen Jr",
    "wof:placetype":"venue"
},
  "geometry": {"coordinates":[-77.11329499999999,42.566638],"type":"Point"}
}