{
  "type": "Feature",
  "properties": {
    "addr:full":"320 Pearl St New York NY 10038",
    "addr:housenumber":"320",
    "addr:postcode":"10038",
    "addr:street":"Pearl St",
    "iso:country":"US",
    "sg:address":"320 Pearl St",
    "sg:city":"New York",
    "sg:classifiers":[
        {
            "category":"Travel",
            "subcategory":"Hotels & Motels",
            "type":"Entertainment"
        }
    ],
    "sg:phone":"+1 212 571 4400",
    "sg:postcode":"10038",
    "sg:province":"NY",
    "sg:website":"www.hamptoninn.com/en/hp/hotels/...",
    "wof:name":"Hampton Inn Manhattan-Seaport/Financial District",
    "wof:placetype":"venue"
},
  "geometry": {"coordinates":[-74.00183,40.709288],"type":"Point"}
}