{
  "type": "Feature",
  "properties": {
    "addr:full":"645 Cleveland St Brooklyn NY 11208",
    "addr:housenumber":"645",
    "addr:postcode":"11208",
    "addr:street":"Cleveland St",
    "iso:country":"US",
    "sg:address":"645 Cleveland St",
    "sg:city":"Brooklyn",
    "sg:classifiers":[
        {
            "category":"Building & Trades",
            "subcategory":"Construction",
            "type":"Services"
        }
    ],
    "sg:phone":"+1 718 483 8217",
    "sg:postcode":"11208",
    "sg:province":"NY",
    "sg:tags":[
        "contractor"
    ],
    "wof:name":"World To World Construction",
    "wof:placetype":"venue"
},
  "geometry": {"coordinates":[-73.88274199999999,40.668647],"type":"Point"}
}