{
  "type": "Feature",
  "properties": {
    "iso:country":"US",
    "sg:address":"23 Griswold St",
    "sg:city":"Binghamton",
    "sg:classifiers":[
        {
            "category":"Manufacturing",
            "subcategory":"Metals",
            "type":"Manufacturing & Wholesale Goods"
        }
    ],
    "sg:phone":"+1   ",
    "sg:postcode":"13904",
    "sg:province":"NY",
    "sg:tags":[
        "metalwork",
        "architectural",
        "mfg"
    ],
    "sg:website":"www.mcgregorindustries.com",
    "wof:name":"Titchener Iron Works",
    "wof:placetype":"venue"
},
  "geometry": {"coordinates":[-75.892493,42.107326],"type":"Point"}
}