{
  "type": "Feature",
  "properties": {
    "iso:country":"US",
    "sg:address":"373 Whipple Ln",
    "sg:city":"Rochester",
    "sg:classifiers":[
        {
            "category":"Real Estate",
            "subcategory":"Real Estate Agent",
            "type":"Services"
        }
    ],
    "sg:phone":"+1 585 342 5480",
    "sg:postcode":"14622",
    "sg:province":"NY",
    "wof:name":"Oxia LLC",
    "wof:placetype":"venue"
},
  "geometry": {"coordinates":[-77.565485,43.209854],"type":"Point"}
}