{
  "type": "Feature",
  "properties": {
    "addr:full":"325 Fayette St Manlius NY 13104",
    "addr:housenumber":"325",
    "addr:postcode":"13104",
    "addr:street":"Fayette St",
    "iso:country":"US",
    "sg:address":"325 Fayette St",
    "sg:city":"Manlius",
    "sg:classifiers":[
        {
            "category":"Autos & Motor Vehicles",
            "subcategory":"Fuel & Gas Station",
            "type":"Retail Goods"
        }
    ],
    "sg:phone":"+1 315 682 2330",
    "sg:postcode":"13104",
    "sg:province":"NY",
    "sg:tags":[
        "oil"
    ],
    "wof:name":"Manlius Mobil",
    "wof:placetype":"venue"
},
  "geometry": {"coordinates":[-75.98360099999999,43.005052],"type":"Point"}
}