{
  "type": "Feature",
  "properties": {
    "addr:full":"40 Lake Dr Greenwood Lake NY 10925",
    "addr:housenumber":"40",
    "addr:postcode":"10925",
    "addr:street":"Lake Dr",
    "iso:country":"US",
    "sg:address":"40 Lake Dr",
    "sg:city":"Greenwood Lake",
    "sg:classifiers":[
        {
            "category":"Organizations",
            "subcategory":"Community Association",
            "type":"Services"
        }
    ],
    "sg:phone":"+1   ",
    "sg:postcode":"10925",
    "sg:province":"NY",
    "wof:name":"American Legion Post 1443",
    "wof:placetype":"venue"
},
  "geometry": {"coordinates":[-74.28400999999999,41.225744],"type":"Point"}
}