{
  "type": "Feature",
  "properties": {
    "iso:country":"US",
    "sg:address":"3281 Elk Ct",
    "sg:city":"Yorktown Heights",
    "sg:classifiers":[
        {
            "category":"Professional",
            "subcategory":"Business Services",
            "type":"Services"
        }
    ],
    "sg:phone":"+1 914 243 5817",
    "sg:postcode":"10598",
    "sg:province":"NY",
    "sg:tags":[
        "process",
        "server"
    ],
    "wof:name":"State Process Svc Co",
    "wof:placetype":"venue"
},
  "geometry": {"coordinates":[-73.782076,41.320822],"type":"Point"}
}