{
  "type": "Feature",
  "properties": {
    "iso:country":"US",
    "sg:address":"800 Conklin St",
    "sg:city":"Farmingdale",
    "sg:classifiers":[
        {
            "category":"Retail",
            "subcategory":"Auto Repair",
            "type":"Services"
        }
    ],
    "sg:phone":"+1 631 420 0565",
    "sg:postcode":"11735",
    "sg:province":"NY",
    "sg:tags":[
        "automobile",
        "inspection"
    ],
    "wof:name":"Richard's Foreign Auto Repair",
    "wof:placetype":"venue"
},
  "geometry": {"coordinates":[-73.434915,40.73473],"type":"Point"}
}