{
  "type": "Feature",
  "properties": {
    "addr:full":"541 Fulton St Brooklyn NY 11201",
    "addr:housenumber":"541",
    "addr:postcode":"11201",
    "addr:street":"Fulton St",
    "iso:country":"US",
    "sg:address":"541 Fulton St",
    "sg:city":"Brooklyn",
    "sg:classifiers":[
        {
            "category":"Shopping",
            "subcategory":"Computers & Home Electronics",
            "type":"Retail Goods"
        }
    ],
    "sg:phone":"+1 718 522 3847",
    "sg:postcode":"11201",
    "sg:province":"NY",
    "sg:tags":[
        "equipment",
        "electronic",
        "supply"
    ],
    "wof:name":"Panarama Electronics Inc",
    "wof:placetype":"venue"
},
  "geometry": {"coordinates":[-73.98106300000001,40.689056],"type":"Point"}
}