{
  "type": "Feature",
  "properties": {
    "iso:country":"US",
    "sg:address":"9 James Ct",
    "sg:city":"Port Jervis",
    "sg:classifiers":[
        {
            "category":"Cinema",
            "subcategory":"Movie Theater",
            "type":"Entertainment"
        }
    ],
    "sg:phone":"+1 845 361 5774",
    "sg:postcode":"12771",
    "sg:province":"NY",
    "wof:name":"Fair Oaks Drive In Theater",
    "wof:placetype":"venue"
},
  "geometry": {"coordinates":[-74.62528399999999,41.360493],"type":"Point"}
}