{
  "type": "Feature",
  "properties": {
    "addr:full":"1325 E Campville Rd Endicott NY 13760",
    "addr:housenumber":"1325",
    "addr:postcode":"13760",
    "addr:street":"E Campville Rd",
    "iso:country":"US",
    "sg:address":"1325 E Campville Rd",
    "sg:city":"Endicott",
    "sg:classifiers":[
        {
            "category":"Personal",
            "type":"Services"
        },
        {
            "category":"Retail",
            "subcategory":"Laundry & Dry Cleaning",
            "type":"Services"
        },
        {
            "category":"Building & Trades",
            "subcategory":"Cleaning & Sanitation",
            "type":"Services"
        }
    ],
    "sg:phone":"+1 607 785 3221",
    "sg:postcode":"13760",
    "sg:province":"NY",
    "sg:tags":[
        "cleaner",
        "butlers'",
        "maids'",
        "house"
    ],
    "sg:website":"http://www.cinderella.net",
    "wof:name":"Judy And The Broom Inc",
    "wof:placetype":"venue"
},
  "geometry": {"coordinates":[-76.115921,42.095815],"type":"Point"}
}