{
  "type": "Feature",
  "properties": {
    "iso:country":"US",
    "sg:address":"926 5th Ave",
    "sg:city":"New York",
    "sg:classifiers":[
        {
            "category":"Banks & Credit Unions",
            "subcategory":"Financial Services",
            "type":"Services"
        }
    ],
    "sg:phone":"+1 212 249 0600",
    "sg:postcode":"10021",
    "sg:province":"NY",
    "sg:tags":[
        "other",
        "investment",
        "holding"
    ],
    "wof:name":"Watermark Investments LLC",
    "wof:placetype":"venue"
},
  "geometry": {"coordinates":[-73.966218,40.773357],"type":"Point"}
}