{
  "type": "Feature",
  "properties": {
    "iso:country":"US",
    "sg:address":"521 Clinton Ave",
    "sg:city":"Brooklyn",
    "sg:classifiers":[
        {
            "category":"Social Services",
            "type":"Services"
        }
    ],
    "sg:phone":"+1 718 789 2911",
    "sg:postcode":"11238",
    "sg:province":"NY",
    "sg:tags":[
        "organization",
        "religious"
    ],
    "wof:name":"Lutheran Scial Svcs of Mtro NY",
    "wof:placetype":"venue"
},
  "geometry": {"coordinates":[-73.966568,40.682312],"type":"Point"}
}