{
  "type": "Feature",
  "properties": {
    "addr:full":"35 Main St Ste A Hamburg NY 14075",
    "addr:housenumber":"35",
    "addr:postcode":"14075",
    "addr:street":"Main St Ste A",
    "iso:country":"US",
    "sg:address":"35 Main St Ste A",
    "sg:city":"Hamburg",
    "sg:classifiers":[
        {
            "category":"Restaurant",
            "type":"Food & Drink"
        },
        {
            "category":"Ice Cream",
            "type":"Food & Drink"
        }
    ],
    "sg:phone":"+1 716 648 4536",
    "sg:postcode":"14075",
    "sg:province":"NY",
    "sg:tags":[
        "frozen",
        "dessert"
    ],
    "wof:name":"Main Street Ice Cream",
    "wof:placetype":"venue"
},
  "geometry": {"coordinates":[-78.831045,42.715971],"type":"Point"}
}