{
  "type": "Feature",
  "properties": {
    "iso:country":"US",
    "sg:address":"3252 Lake Ave",
    "sg:city":"Rochester",
    "sg:classifiers":[
        {
            "category":"Insurance",
            "subcategory":"Insurance Agent",
            "type":"Services"
        }
    ],
    "sg:phone":"+1 585 621 4220",
    "sg:postcode":"14612",
    "sg:province":"NY",
    "wof:name":"Peck Agency Inc",
    "wof:placetype":"venue"
},
  "geometry": {"coordinates":[-77.62652,43.229744],"type":"Point"}
}