{
  "type": "Feature",
  "properties": {
    "iso:country":"US",
    "sg:address":"234 Tompkins St",
    "sg:city":"Cortland",
    "sg:classifiers":[
        {
            "category":"Shopping",
            "subcategory":"Florist",
            "type":"Retail Goods"
        }
    ],
    "sg:phone":"+1 607 756 7569",
    "sg:postcode":"13045",
    "sg:province":"NY",
    "wof:name":"Arnold's Florists",
    "wof:placetype":"venue"
},
  "geometry": {"coordinates":[-76.198357,42.586588],"type":"Point"}
}