{
  "type": "Feature",
  "properties": {
    "addr:full":"85 E Main St Victor NY 14564",
    "addr:housenumber":"85",
    "addr:postcode":"14564",
    "addr:street":"E Main St",
    "iso:country":"US",
    "sg:address":"85 E Main St",
    "sg:city":"Victor",
    "sg:classifiers":[
        {
            "category":"Government",
            "subcategory":"Office",
            "type":"Public Place"
        }
    ],
    "sg:phone":"+1 585 742 5020",
    "sg:postcode":"14564",
    "sg:province":"NY",
    "sg:tags":[
        "village"
    ],
    "wof:name":"Victor Town Supervisor",
    "wof:placetype":"venue"
},
  "geometry": {"coordinates":[-77.40736800000001,42.98208],"type":"Point"}
}