{
  "type": "Feature",
  "properties": {
    "iso:country":"US",
    "sg:address":"22 Robin Dr",
    "sg:city":"Hauppauge",
    "sg:classifiers":[
        {
            "category":"Shopping",
            "type":"Retail Goods"
        }
    ],
    "sg:phone":"+1   ",
    "sg:postcode":"11788",
    "sg:province":"NY",
    "sg:tags":[
        "medical",
        "supply"
    ],
    "wof:name":"Physicians Lab Systems Ltd",
    "wof:placetype":"venue"
},
  "geometry": {"coordinates":[-73.24455500000001,40.824286],"type":"Point"}
}