{
  "type": "Feature",
  "properties": {
    "addr:full":"385 Larkfield Rd East Northport NY 11731",
    "addr:housenumber":"385",
    "addr:postcode":"11731",
    "addr:street":"Larkfield Rd",
    "iso:country":"US",
    "sg:address":"385 Larkfield Rd",
    "sg:city":"East Northport",
    "sg:classifiers":[
        {
            "category":"Banks & Credit Unions",
            "subcategory":"Bank",
            "type":"Services"
        }
    ],
    "sg:phone":"+1 631 368 6050",
    "sg:postcode":"11731",
    "sg:province":"NY",
    "sg:tags":[
        "national",
        "commercial"
    ],
    "wof:name":"Fleet",
    "wof:placetype":"venue"
},
  "geometry": {"coordinates":[-73.321945,40.867985],"type":"Point"}
}