{
  "type": "Feature",
  "properties": {
    "addr:full":"569 66th St Niagara Falls NY 14304",
    "addr:housenumber":"569",
    "addr:postcode":"14304",
    "addr:street":"66Th St",
    "iso:country":"US",
    "sg:address":"569 66th St",
    "sg:city":"Niagara Falls",
    "sg:classifiers":[
        {
            "category":"Organizations",
            "subcategory":"Membership Organization",
            "type":"Services"
        }
    ],
    "sg:phone":"+1   ",
    "sg:postcode":"14304",
    "sg:province":"NY",
    "wof:name":"Lamarca Association",
    "wof:placetype":"venue"
},
  "geometry": {"coordinates":[-78.98805299999999,43.083623],"type":"Point"}
}