{
  "type": "Feature",
  "properties": {
    "addr:full":"57-06 31st Ave Woodside NY 11377",
    "addr:housenumber":"57-06",
    "addr:postcode":"11377",
    "addr:street":"31St Ave",
    "iso:country":"US",
    "sg:address":"57-06 31st Ave",
    "sg:city":"Woodside",
    "sg:classifiers":[
        {
            "category":"Retail",
            "subcategory":"Auto Repair",
            "type":"Services"
        }
    ],
    "sg:phone":"+1 888 711 0548",
    "sg:postcode":"11377",
    "sg:province":"NY",
    "sg:website":"www.paragonhonda.com/ou/paragon-...",
    "wof:name":"Paragon Honda Service Center",
    "wof:placetype":"venue"
},
  "geometry": {"coordinates":[-73.90425500000001,40.75671],"type":"Point"}
}