{
  "type": "Feature",
  "properties": {
    "addr:full":"2380 Broadway New York NY 10024",
    "addr:housenumber":"2380",
    "addr:postcode":"10024",
    "addr:street":"Broadway",
    "iso:country":"US",
    "sg:address":"2380 Broadway",
    "sg:city":"New York",
    "sg:classifiers":[
        {
            "category":"Banks & Credit Unions",
            "subcategory":"Bank",
            "type":"Services"
        }
    ],
    "sg:phone":"+1 212 724 2402",
    "sg:postcode":"10024",
    "sg:province":"NY",
    "wof:name":"Bank of America",
    "wof:placetype":"venue"
},
  "geometry": {"coordinates":[-73.975684,40.788838],"type":"Point"}
}