{
  "type": "Feature",
  "properties": {
    "addr:full":"1354 Jerome Ave Bronx NY 10452",
    "addr:housenumber":"1354",
    "addr:postcode":"10452",
    "addr:street":"Jerome Ave",
    "iso:country":"US",
    "sg:address":"1354 Jerome Ave",
    "sg:city":"Bronx",
    "sg:classifiers":[
        {
            "category":"Personal",
            "subcategory":"Beauty Salon",
            "type":"Services"
        }
    ],
    "sg:phone":"+1 718 590 9578",
    "sg:postcode":"10452",
    "sg:province":"NY",
    "wof:name":"Aicha African Hair Brading",
    "wof:placetype":"venue"
},
  "geometry": {"coordinates":[-73.91819599999999,40.839344],"type":"Point"}
}