{
  "type": "Feature",
  "properties": {
    "iso:country":"US",
    "sg:address":"59 W Main St",
    "sg:city":"Shortsville",
    "sg:classifiers":[
        {
            "category":"Place Of Worship",
            "subcategory":"Church",
            "type":"Public Place"
        },
        {
            "category":"Place Of Worship",
            "type":"Public Place"
        }
    ],
    "sg:phone":"+1 585 289 9123",
    "sg:postcode":"14548",
    "sg:province":"NY",
    "sg:tags":[
        "churches-presbyterian-arp",
        "churches-presbyterian"
    ],
    "sg:website":"http://www.fpcjackson.org",
    "wof:name":"Presbyterian Church",
    "wof:placetype":"venue"
},
  "geometry": {"coordinates":[-77.224842,42.955335],"type":"Point"}
}