{
  "type": "Feature",
  "properties": {
    "iso:country":"US",
    "sg:address":"1253 Castle Hill Ave",
    "sg:city":"Bronx",
    "sg:classifiers":[
        {
            "category":"Restaurant",
            "type":"Food & Drink"
        }
    ],
    "sg:phone":"+1 718 822 9750",
    "sg:postcode":"10462",
    "sg:province":"NY",
    "wof:name":"El Ancon Tropical Restaurant",
    "wof:placetype":"venue"
},
  "geometry": {"coordinates":[-73.85135099999999,40.832778],"type":"Point"}
}