{
  "type": "Feature",
  "properties": {
    "iso:country":"US",
    "sg:address":"10552 Sisson Hwy",
    "sg:city":"Eden",
    "sg:classifiers":[
        {
            "category":"Retail",
            "subcategory":"Repair Shop",
            "type":"Services"
        }
    ],
    "sg:phone":"+1   ",
    "sg:postcode":"14057",
    "sg:province":"NY",
    "sg:tags":[
        "refuse",
        "system"
    ],
    "wof:name":"South Towns Disposal & Svcs",
    "wof:placetype":"venue"
},
  "geometry": {"coordinates":[-78.841881,42.595088],"type":"Point"}
}