{
  "type": "Feature",
  "properties": {
    "iso:country":"US",
    "sg:address":"1912 Wantagh Ave",
    "sg:city":"Wantagh",
    "sg:classifiers":[
        {
            "category":"Bars & Pubs",
            "type":"Food & Drink"
        }
    ],
    "sg:phone":"+1 516 785 9614",
    "sg:postcode":"11793",
    "sg:province":"NY",
    "sg:tags":[
        "drinking",
        "eating"
    ],
    "wof:name":"R P Mc Murphy's",
    "wof:placetype":"venue"
},
  "geometry": {"coordinates":[-73.51008299999999,40.674968],"type":"Point"}
}