{
  "type": "Feature",
  "properties": {
    "addr:full":"12 Holt Rd Hyde Park NY 12538",
    "addr:housenumber":"12",
    "addr:postcode":"12538",
    "addr:street":"Holt Rd",
    "iso:country":"US",
    "sg:address":"12 Holt Rd",
    "sg:city":"Hyde Park",
    "sg:classifiers":[
        {
            "category":"Building & Trades",
            "subcategory":"Construction",
            "type":"Services"
        }
    ],
    "sg:phone":"+1 845 473 2530",
    "sg:postcode":"12538",
    "sg:province":"NY",
    "sg:tags":[
        "house"
    ],
    "wof:name":"David Briggs Home Improvements",
    "wof:placetype":"venue"
},
  "geometry": {"coordinates":[-73.910274,41.751733],"type":"Point"}
}