{
  "type": "Feature",
  "properties": {
    "iso:country":"US",
    "sg:address":"664 Stoneleigh Ave Ste 300",
    "sg:city":"Carmel",
    "sg:classifiers":[
        {
            "category":"Health Services",
            "subcategory":"Doctor",
            "type":"Services"
        }
    ],
    "sg:phone":"+1 845 278 8400",
    "sg:postcode":"10512",
    "sg:province":"NY",
    "wof:name":"Fauser Douglas J Md",
    "wof:placetype":"venue"
},
  "geometry": {"coordinates":[-73.664036,41.385888],"type":"Point"}
}