{
  "type": "Feature",
  "properties": {
    "addr:full":"100 Graves St Staten Island NY 10314",
    "addr:housenumber":"100",
    "addr:postcode":"10314",
    "addr:street":"Graves St",
    "iso:country":"US",
    "sg:address":"100 Graves St",
    "sg:city":"Staten Island",
    "sg:classifiers":[
        {
            "category":"Restaurant",
            "type":"Food & Drink"
        }
    ],
    "sg:menulink":"http://www.allmenus.com/ny/staten-island/107289-soup-man/menu/",
    "sg:phone":"+1 718 967 6788",
    "sg:postcode":"10314",
    "sg:province":"NY",
    "sg:tags":[
        "soup",
        "american",
        "salad"
    ],
    "wof:name":"Soup Man",
    "wof:placetype":"venue"
},
  "geometry": {"coordinates":[-74.12961799999999,40.603197],"type":"Point"}
}