{
  "type": "Feature",
  "properties": {
    "addr:full":"1133 Avenue of the Americ New York NY 10036",
    "addr:housenumber":"1133",
    "addr:postcode":"10036",
    "addr:street":"Avenue Of The",
    "iso:country":"US",
    "sg:address":"1133 Avenue of the Americ",
    "sg:city":"New York",
    "sg:classifiers":[
        {
            "category":"Professional",
            "subcategory":"Lawyer & Legal Services",
            "type":"Services"
        }
    ],
    "sg:phone":"+1 212 790 9263",
    "sg:postcode":"10036",
    "sg:province":"NY",
    "wof:name":"Speciner Mark J Atty",
    "wof:placetype":"venue"
},
  "geometry": {"coordinates":[-73.98344299999999,40.755778],"type":"Point"}
}