{
  "type": "Feature",
  "properties": {
    "addr:full":"932 E 174th Street Bronx NY 10460",
    "addr:housenumber":"932",
    "addr:postcode":"10460",
    "addr:street":"E 174Th Street",
    "iso:country":"US",
    "sg:address":"932 E 174th Street",
    "sg:city":"Bronx",
    "sg:classifiers":[
        {
            "category":"Restaurant",
            "type":"Food & Drink"
        }
    ],
    "sg:phone":"+1 718 328 4700",
    "sg:postcode":"10460",
    "sg:province":"NY",
    "wof:name":"Amanini Pizzeria",
    "wof:placetype":"venue"
},
  "geometry": {"coordinates":[-73.887686,40.837332],"type":"Point"}
}