{
  "type": "Feature",
  "properties": {
    "addr:full":"1094 Robin Rd Franklin Square NY 11010",
    "addr:housenumber":"1094",
    "addr:postcode":"11010",
    "addr:street":"Robin Rd",
    "iso:country":"US",
    "sg:address":"1094 Robin Rd",
    "sg:city":"Franklin Square",
    "sg:classifiers":[
        {
            "category":"Wholesale",
            "subcategory":"Home Furnishings",
            "type":"Manufacturing & Wholesale Goods"
        }
    ],
    "sg:phone":"+1 516 872 0212",
    "sg:postcode":"11010",
    "sg:province":"NY",
    "sg:tags":[
        "retail",
        "floor",
        "covering"
    ],
    "wof:name":"Norwood Floors",
    "wof:placetype":"venue"
},
  "geometry": {"coordinates":[-73.682862,40.688541],"type":"Point"}
}