{
  "type": "Feature",
  "properties": {
    "iso:country":"US",
    "sg:address":"123 Elizabeth St",
    "sg:city":"New York",
    "sg:classifiers":[
        {
            "category":"Shopping",
            "subcategory":"Hobbies, Toys, & Games",
            "type":"Retail Goods"
        }
    ],
    "sg:phone":"+1   ",
    "sg:postcode":"10013",
    "sg:province":"NY",
    "wof:name":"Jin Hong Wu",
    "wof:placetype":"venue"
},
  "geometry": {"coordinates":[-73.99551099999999,40.719301],"type":"Point"}
}