{
  "type": "Feature",
  "properties": {
    "iso:country":"US",
    "sg:address":"347 Empire Blvd",
    "sg:city":"Brooklyn",
    "sg:classifiers":[
        {
            "category":"Shopping",
            "subcategory":"Clothing, Apparel, & Fashions",
            "type":"Retail Goods"
        }
    ],
    "sg:phone":"+1 718 467 8897",
    "sg:postcode":"11225",
    "sg:province":"NY",
    "wof:name":"Ayah Fashion",
    "wof:placetype":"venue"
},
  "geometry": {"coordinates":[-73.949611,40.664062],"type":"Point"}
}