{
  "type": "Feature",
  "properties": {
    "addr:full":"6144 South Ave Williamson NY 14589",
    "addr:housenumber":"6144",
    "addr:postcode":"14589",
    "addr:street":"South Ave",
    "iso:country":"US",
    "sg:address":"6144 South Ave",
    "sg:city":"Williamson",
    "sg:classifiers":[
        {
            "category":"Government",
            "subcategory":"Post Office",
            "type":"Public Place"
        }
    ],
    "sg:phone":"+1 315 589 5621",
    "sg:postcode":"14589",
    "sg:province":"NY",
    "wof:name":"US Post Office",
    "wof:placetype":"venue"
},
  "geometry": {"coordinates":[-77.18771599999999,43.219117],"type":"Point"}
}