{
  "type": "Feature",
  "properties": {
    "addr:full":"1127 Tonawanda St Buffalo NY 14207",
    "addr:housenumber":"1127",
    "addr:postcode":"14207",
    "addr:street":"Tonawanda St",
    "iso:country":"US",
    "sg:address":"1127 Tonawanda St",
    "sg:city":"Buffalo",
    "sg:classifiers":[
        {
            "category":"Restaurant",
            "type":"Food & Drink"
        }
    ],
    "sg:phone":"+1 716 876 1500",
    "sg:postcode":"14207",
    "sg:province":"NY",
    "sg:tags":[
        "pizza"
    ],
    "wof:name":"Zip's Pizza",
    "wof:placetype":"venue"
},
  "geometry": {"coordinates":[-78.90823899999999,42.958687],"type":"Point"}
}