{
  "type": "Feature",
  "properties": {
    "addr:full":"7427 37th Ave Jackson Heights NY 11372",
    "addr:housenumber":"7427",
    "addr:postcode":"11372",
    "addr:street":"37Th Ave",
    "iso:country":"US",
    "sg:address":"7427 37th Ave",
    "sg:city":"Jackson Heights",
    "sg:classifiers":[
        {
            "category":"Restaurant",
            "type":"Food & Drink"
        }
    ],
    "sg:menulink":"http://www.allmenus.com/ny/queens/30220-armondos/menu/",
    "sg:phone":"+1 718 898 0113",
    "sg:postcode":"11372",
    "sg:province":"NY",
    "sg:tags":[
        "italian"
    ],
    "wof:name":"Armondo's",
    "wof:placetype":"venue"
},
  "geometry": {"coordinates":[-73.89154000000001,40.748988],"type":"Point"}
}