{
  "type": "Feature",
  "properties": {
    "addr:full":"2753 Nostrand Ave Brooklyn NY 11210",
    "addr:housenumber":"2753",
    "addr:postcode":"11210",
    "addr:street":"Nostrand Ave",
    "iso:country":"US",
    "sg:address":"2753 Nostrand Ave",
    "sg:city":"Brooklyn",
    "sg:classifiers":[
        {
            "category":"Shopping",
            "subcategory":"Clothing, Apparel, & Fashions",
            "type":"Retail Goods"
        }
    ],
    "sg:phone":"+1 718 338 2201",
    "sg:postcode":"11210",
    "sg:province":"NY",
    "sg:tags":[
        "lingerie"
    ],
    "wof:name":"Olga's Corset & Specialty Shop",
    "wof:placetype":"venue"
},
  "geometry": {"coordinates":[-73.945099,40.618],"type":"Point"}
}