{
  "type": "Feature",
  "properties": {
    "addr:full":"45 Main St Akron NY 14001",
    "addr:housenumber":"45",
    "addr:postcode":"14001",
    "addr:street":"Main St",
    "iso:country":"US",
    "sg:address":"45 Main St",
    "sg:city":"Akron",
    "sg:classifiers":[
        {
            "category":"Insurance",
            "subcategory":"Insurance Agent",
            "type":"Services"
        }
    ],
    "sg:phone":"+1 585 542 1544",
    "sg:postcode":"14001",
    "sg:province":"NY",
    "wof:name":"Insurite Agency Inc",
    "wof:placetype":"venue"
},
  "geometry": {"coordinates":[-78.50135400000001,43.020106],"type":"Point"}
}