{
  "type": "Feature",
  "properties": {
    "iso:country":"US",
    "sg:address":"317 New South Rd",
    "sg:city":"Hicksville",
    "sg:classifiers":[
        {
            "category":"Freight",
            "type":"Transportation"
        }
    ],
    "sg:phone":"+1 516 931 0672",
    "sg:postcode":"11801",
    "sg:province":"NY",
    "sg:tags":[
        "trucking"
    ],
    "wof:name":"Niatco Trucking Corp",
    "wof:placetype":"venue"
},
  "geometry": {"coordinates":[-73.50580600000001,40.757096],"type":"Point"}
}