{
  "type": "Feature",
  "properties": {
    "iso:country":"US",
    "sg:address":"63 Riverside Dr",
    "sg:city":"Phoenix",
    "sg:classifiers":[
        {
            "category":"Building & Trades",
            "subcategory":"Construction",
            "type":"Services"
        }
    ],
    "sg:phone":"+1 315 695 7053",
    "sg:postcode":"13135",
    "sg:province":"NY",
    "sg:tags":[
        "house"
    ],
    "wof:name":"Candees Construction",
    "wof:placetype":"venue"
},
  "geometry": {"coordinates":[-76.26633699999999,43.220394],"type":"Point"}
}