{
  "type": "Feature",
  "properties": {
    "addr:full":"848 Greenthorne Blvd Schenectady NY 12303",
    "addr:housenumber":"848",
    "addr:postcode":"12303",
    "addr:street":"Greenthorne Blvd",
    "iso:country":"US",
    "sg:address":"848 Greenthorne Blvd",
    "sg:city":"Schenectady",
    "sg:classifiers":[
        {
            "category":"Wholesale",
            "subcategory":"Drugs",
            "type":"Manufacturing & Wholesale Goods"
        }
    ],
    "sg:phone":"+1 518 857 2921",
    "sg:postcode":"12303",
    "sg:province":"NY",
    "wof:name":"Solidus Biosciences",
    "wof:placetype":"venue"
},
  "geometry": {"coordinates":[-73.921972,42.716721],"type":"Point"}
}