{
  "type": "Feature",
  "properties": {
    "addr:full":"1950 Fulton St Brooklyn NY 11233",
    "addr:housenumber":"1950",
    "addr:postcode":"11233",
    "addr:street":"Fulton St",
    "iso:country":"US",
    "sg:address":"1950 Fulton St",
    "sg:city":"Brooklyn",
    "sg:classifiers":[
        {
            "category":"Banks & Credit Unions",
            "subcategory":"Bank",
            "type":"Services"
        }
    ],
    "sg:phone":"+1 718 221 2900",
    "sg:postcode":"11233",
    "sg:province":"NY",
    "wof:name":"State Farm Ins Cos",
    "wof:placetype":"venue"
},
  "geometry": {"coordinates":[-73.92089799999999,40.678799],"type":"Point"}
}