{
  "type": "Feature",
  "properties": {
    "iso:country":"US",
    "sg:address":"301 E 90 St",
    "sg:city":"New York",
    "sg:classifiers":[
        {
            "category":"Retail",
            "subcategory":"Laundry & Dry Cleaning",
            "type":"Services"
        }
    ],
    "sg:phone":"+1   ",
    "sg:postcode":"10128",
    "sg:province":"NY",
    "sg:tags":[
        "power"
    ],
    "wof:name":"Chu-Ching Kin",
    "wof:placetype":"venue"
},
  "geometry": {"coordinates":[-73.947508,40.779438],"type":"Point"}
}