{
  "type": "Feature",
  "properties": {
    "addr:full":"64 Ash St Yonkers NY 10701",
    "addr:housenumber":"64",
    "addr:postcode":"10701",
    "addr:street":"Ash St",
    "iso:country":"US",
    "sg:address":"64 Ash St",
    "sg:city":"Yonkers",
    "sg:classifiers":[
        {
            "category":"Wholesale",
            "subcategory":"Durable Goods & Equipment",
            "type":"Manufacturing & Wholesale Goods"
        }
    ],
    "sg:phone":"+1 914 963 9767",
    "sg:postcode":"10701",
    "sg:province":"NY",
    "sg:tags":[
        "exporter"
    ],
    "wof:name":"2KMG Corp",
    "wof:placetype":"venue"
},
  "geometry": {"coordinates":[-73.887951,40.931955],"type":"Point"}
}