{
  "type": "Feature",
  "properties": {
    "addr:full":"630 Corporate Way Valley Cottage NY 10989",
    "addr:housenumber":"630",
    "addr:postcode":"10989",
    "addr:street":"Corporate Way",
    "iso:country":"US",
    "sg:address":"630 Corporate Way",
    "sg:city":"Valley Cottage",
    "sg:classifiers":[
        {
            "category":"Wholesale",
            "subcategory":"Wine & Distilled Alcoholic Beverages",
            "type":"Manufacturing & Wholesale Goods"
        }
    ],
    "sg:phone":"+1 845 268 3600",
    "sg:postcode":"10989",
    "sg:province":"NY",
    "sg:tags":[
        "liquor"
    ],
    "sg:website":"www.danadistributors.com",
    "wof:name":"Dana Distributors Inc",
    "wof:placetype":"venue"
},
  "geometry": {"coordinates":[-73.943794,41.129517],"type":"Point"}
}