{
  "type": "Feature",
  "properties": {
    "addr:full":"901 Madison Avenue New York NY 10021",
    "addr:housenumber":"901",
    "addr:postcode":"10021",
    "addr:street":"Madison Avenue",
    "iso:country":"US",
    "sg:address":"901 Madison Avenue",
    "sg:city":"New York",
    "sg:classifiers":[
        {
            "category":"Shopping",
            "subcategory":"Antiques",
            "type":"Retail Goods"
        }
    ],
    "sg:phone":"+1 212 737 3775",
    "sg:postcode":"10021",
    "sg:province":"NY",
    "wof:name":"Bardith Ltd",
    "wof:placetype":"venue"
},
  "geometry": {"coordinates":[-73.96538700000001,40.772056],"type":"Point"}
}