{
  "type": "Feature",
  "properties": {
    "addr:full":"2037 Jerome Ave Bronx NY 10453",
    "addr:housenumber":"2037",
    "addr:postcode":"10453",
    "addr:street":"Jerome Ave",
    "iso:country":"US",
    "sg:address":"2037 Jerome Ave",
    "sg:city":"Bronx",
    "sg:classifiers":[
        {
            "category":"Restaurant",
            "type":"Food & Drink"
        }
    ],
    "sg:phone":"+1 718 583 2979",
    "sg:postcode":"10453",
    "sg:province":"NY",
    "wof:name":"Martinez Restaurant Corp",
    "wof:placetype":"venue"
},
  "geometry": {"coordinates":[-73.908998,40.851961],"type":"Point"}
}