{
  "type": "Feature",
  "properties": {
    "iso:country":"US",
    "sg:address":"19 Preston Ct",
    "sg:city":"Brooklyn",
    "sg:classifiers":[
        {
            "category":"Building & Trades",
            "subcategory":"Plumbing",
            "type":"Services"
        }
    ],
    "sg:phone":"+1 718 927 1600",
    "sg:postcode":"11234",
    "sg:province":"NY",
    "sg:tags":[
        "repair",
        "contractor"
    ],
    "wof:name":"Fritz Plumbing & Heating Co",
    "wof:placetype":"venue"
},
  "geometry": {"coordinates":[-73.92321699999999,40.638892],"type":"Point"}
}