{
  "type": "Feature",
  "properties": {
    "addr:full":"2070 Jericho Tpke Commack NY 11725",
    "addr:postcode":"2070;11725",
    "addr:street":"Jericho Tpke",
    "iso:country":"US",
    "sg:address":"2070 Jericho Tpke",
    "sg:city":"Commack",
    "sg:classifiers":[
        {
            "category":"Organizations",
            "subcategory":"Professional Association",
            "type":"Services"
        }
    ],
    "sg:phone":"+1 631 864 4577",
    "sg:postcode":"11725",
    "sg:province":"NY",
    "wof:name":"Commackteachers Association",
    "wof:placetype":"venue"
},
  "geometry": {"coordinates":[-73.271998,40.845168],"type":"Point"}
}