{
  "type": "Feature",
  "properties": {
    "addr:full":"27 W 84 St New York NY 10024",
    "addr:housenumber":"27",
    "addr:postcode":"10024",
    "addr:street":"W 84 St",
    "iso:country":"US",
    "sg:address":"27 W 84 St",
    "sg:city":"New York",
    "sg:classifiers":[
        {
            "category":"Arts & Performance",
            "subcategory":"Theater",
            "type":"Entertainment"
        }
    ],
    "sg:phone":"+1 212 712 9210",
    "sg:postcode":"10024",
    "sg:province":"NY",
    "sg:tags":[
        "music",
        "agent"
    ],
    "wof:name":"Lonardo There Is Light",
    "wof:placetype":"venue"
},
  "geometry": {"coordinates":[-73.972528,40.784918],"type":"Point"}
}