{
  "type": "Feature",
  "properties": {
    "iso:country":"US",
    "sg:address":"500 Executive Blvd",
    "sg:city":"Ossining",
    "sg:classifiers":[
        {
            "category":"Professional",
            "subcategory":"Lawyer & Legal Services",
            "type":"Services"
        }
    ],
    "sg:phone":"+1 914 941 3800",
    "sg:postcode":"10562",
    "sg:province":"NY",
    "wof:name":"Barlaam Raymond R",
    "wof:placetype":"venue"
},
  "geometry": {"coordinates":[-73.851997,41.171001],"type":"Point"}
}