{
  "type": "Feature",
  "properties": {
    "iso:country":"US",
    "sg:address":"252 9th St",
    "sg:city":"Brooklyn",
    "sg:classifiers":[
        {
            "category":"Banks & Credit Unions",
            "subcategory":"Bank",
            "type":"Services"
        }
    ],
    "sg:phone":"+1 718 768 1144",
    "sg:postcode":"11215",
    "sg:province":"NY",
    "sg:tags":[
        "depository",
        "banking"
    ],
    "wof:name":"A&T Check",
    "wof:placetype":"venue"
},
  "geometry": {"coordinates":[-73.990452,40.671359],"type":"Point"}
}