{
  "type": "Feature",
  "properties": {
    "iso:country":"US",
    "sg:address":"51 Grand St",
    "sg:city":"New City",
    "sg:classifiers":[
        {
            "category":"Building & Trades",
            "subcategory":"Construction",
            "type":"Services"
        }
    ],
    "sg:phone":"+1 845 634 7894",
    "sg:postcode":"10956",
    "sg:province":"NY",
    "sg:tags":[
        "house"
    ],
    "wof:name":"Blackjack Construction Inc",
    "wof:placetype":"venue"
},
  "geometry": {"coordinates":[-74.004683,41.141477],"type":"Point"}
}