{
  "type": "Feature",
  "properties": {
    "iso:country":"US",
    "sg:address":"2373 Middle Country Rd",
    "sg:city":"Centereach",
    "sg:classifiers":[
        {
            "category":"Restaurant",
            "type":"Food & Drink"
        }
    ],
    "sg:phone":"+1 631 981 0918",
    "sg:postcode":"11720",
    "sg:province":"NY",
    "sg:tags":[
        "pizza"
    ],
    "wof:name":"Caronnas Italian Cuisine & Pizza Inc",
    "wof:placetype":"venue"
},
  "geometry": {"coordinates":[-73.09579100000001,40.858081],"type":"Point"}
}