{
  "type": "Feature",
  "properties": {
    "iso:country":"US",
    "sg:address":"281 Rte 25A",
    "sg:city":"Mt Sinai",
    "sg:classifiers":[
        {
            "category":"Social Services",
            "type":"Services"
        }
    ],
    "sg:phone":"+1 631 331 9534",
    "sg:postcode":"11766",
    "sg:province":"NY",
    "sg:tags":[
        "counselor",
        "marriage",
        "family"
    ],
    "wof:name":"Gail Beekman",
    "wof:placetype":"venue"
},
  "geometry": {"coordinates":[-73.029884,40.932849],"type":"Point"}
}