{
  "type": "Feature",
  "properties": {
    "addr:full":"21 Wooleys Ln Great Neck NY 11023",
    "addr:housenumber":"21",
    "addr:postcode":"11023",
    "addr:street":"Wooleys Ln",
    "iso:country":"US",
    "sg:address":"21 Wooleys Ln",
    "sg:city":"Great Neck",
    "sg:classifiers":[
        {
            "category":"Real Estate",
            "subcategory":"Real Estate Agent",
            "type":"Services"
        }
    ],
    "sg:phone":"+1 973 244 0004",
    "sg:postcode":"11023",
    "sg:province":"NY",
    "wof:name":"Eleven Wooleys Lane Assoc",
    "wof:placetype":"venue"
},
  "geometry": {"coordinates":[-73.73349899999999,40.797157],"type":"Point"}
}