{
  "type": "Feature",
  "properties": {
    "iso:country":"US",
    "sg:address":"69 Morris Rd",
    "sg:city":"Schenectady",
    "sg:classifiers":[
        {
            "category":"Recreation",
            "type":"Entertainment"
        }
    ],
    "sg:phone":"+1   ",
    "sg:postcode":"12303",
    "sg:province":"NY",
    "wof:name":"Colonie Riding & Racing Stable",
    "wof:placetype":"venue"
},
  "geometry": {"coordinates":[-73.88009599999999,42.749624],"type":"Point"}
}