{
  "type": "Feature",
  "properties": {
    "addr:full":"2160 Flatbush Ave Brooklyn NY 11234",
    "addr:housenumber":"2160",
    "addr:postcode":"11234",
    "addr:street":"Flatbush Ave",
    "iso:country":"US",
    "sg:address":"2160 Flatbush Ave",
    "sg:city":"Brooklyn",
    "sg:classifiers":[
        {
            "category":"Retail",
            "subcategory":"Auto Rental",
            "type":"Services"
        }
    ],
    "sg:phone":"+1 718 338 7509",
    "sg:postcode":"11234",
    "sg:province":"NY",
    "sg:tags":[
        "renting",
        "truck",
        "leasing"
    ],
    "sg:website":"http://www.budgettruck.com",
    "wof:name":"Budget Truck Rental",
    "wof:placetype":"venue"
},
  "geometry": {"coordinates":[-73.93086599999999,40.617155],"type":"Point"}
}