{
  "type": "Feature",
  "properties": {
    "iso:country":"US",
    "sg:address":"16 Crystal St",
    "sg:city":"Elmont",
    "sg:classifiers":[
        {
            "category":"Health Services",
            "subcategory":"Doctor",
            "type":"Services"
        }
    ],
    "sg:phone":"+1 516 808 1854",
    "sg:postcode":"11003",
    "sg:province":"NY",
    "sg:tags":[
        "physician",
        "surgeon"
    ],
    "wof:name":"Ez Healthcare Cleaning Solutions",
    "wof:placetype":"venue"
},
  "geometry": {"coordinates":[-73.715422,40.6932],"type":"Point"}
}