{
  "type": "Feature",
  "properties": {
    "addr:full":"5 Limestone Dr Williamsville NY 14221",
    "addr:housenumber":"5",
    "addr:postcode":"14221",
    "addr:street":"Limestone Dr",
    "iso:country":"US",
    "sg:address":"5 Limestone Dr",
    "sg:city":"Williamsville",
    "sg:classifiers":[
        {
            "category":"Real Estate",
            "subcategory":"Developer",
            "type":"Services"
        }
    ],
    "sg:phone":"+1 716 632 6946",
    "sg:postcode":"14221",
    "sg:province":"NY",
    "wof:name":"CRS Properties Inc",
    "wof:placetype":"venue"
},
  "geometry": {"coordinates":[-78.71275799999999,42.96313],"type":"Point"}
}