{
  "type": "Feature",
  "properties": {
    "iso:country":"US",
    "sg:address":"337 Hamilton St",
    "sg:city":"Geneva",
    "sg:classifiers":[
        {
            "category":"Professional",
            "subcategory":"Business Services",
            "type":"Services"
        }
    ],
    "sg:phone":"+1   ",
    "sg:postcode":"14456",
    "sg:province":"NY",
    "sg:tags":[
        "box",
        "mail",
        "facsimile",
        "rental",
        "mailing"
    ],
    "wof:name":"UPS Stores 1625 The",
    "wof:placetype":"venue"
},
  "geometry": {"coordinates":[-76.994426,42.858791],"type":"Point"}
}