{
  "type": "Feature",
  "properties": {
    "iso:country":"US",
    "sg:address":"2532 State Hwy 38B",
    "sg:city":"Newark Valley",
    "sg:classifiers":[
        {
            "category":"Farming",
            "subcategory":"Farm",
            "type":"Manufacturing & Wholesale Goods"
        }
    ],
    "sg:phone":"+1 607 642 3437",
    "sg:postcode":"13811",
    "sg:province":"NY",
    "wof:name":"Bi-Way Farms",
    "wof:placetype":"venue"
},
  "geometry": {"coordinates":[-76.150491,42.201513],"type":"Point"}
}