{
  "type": "Feature",
  "properties": {
    "addr:full":"855 Brush Ave Bronx NY 10465",
    "addr:housenumber":"855",
    "addr:postcode":"10465",
    "addr:street":"Brush Ave",
    "iso:country":"US",
    "sg:address":"855 Brush Ave",
    "sg:city":"Bronx",
    "sg:classifiers":[
        {
            "category":"Banks & Credit Unions",
            "subcategory":"Bank",
            "type":"Services"
        }
    ],
    "sg:phone":"+1 718 931 9700",
    "sg:postcode":"10465",
    "sg:province":"NY",
    "sg:tags":[
        "financing"
    ],
    "wof:name":"Bronx Funding",
    "wof:placetype":"venue"
},
  "geometry": {"coordinates":[-73.838538,40.817457],"type":"Point"}
}