{
  "type": "Feature",
  "properties": {
    "iso:country":"US",
    "sg:address":"1821 Monroe St",
    "sg:city":"Meredith",
    "sg:classifiers":[
        {
            "category":"Wholesale",
            "subcategory":"Construction Materials",
            "type":"Manufacturing & Wholesale Goods"
        },
        {
            "category":"Building & Trades",
            "subcategory":"Construction",
            "type":"Services"
        }
    ],
    "sg:phone":"+1 607 746 2261",
    "sg:postcode":"13760",
    "sg:province":"NY",
    "sg:tags":[
        "fence",
        "contractor"
    ],
    "wof:name":"Catskill Fence",
    "wof:placetype":"venue"
},
  "geometry": {"coordinates":[-76.04105300000001,42.102898],"type":"Point"}
}