{
  "type": "Feature",
  "properties": {
    "addr:full":"3259 Richmond Ave Staten Island NY 10312",
    "addr:housenumber":"3259",
    "addr:postcode":"10312",
    "addr:street":"Richmond Ave",
    "iso:country":"US",
    "sg:address":"3259 Richmond Ave",
    "sg:city":"Staten Island",
    "sg:classifiers":[
        {
            "category":"Shopping",
            "subcategory":"Gifts & Souvenirs",
            "type":"Retail Goods"
        }
    ],
    "sg:phone":"+1 718 317 8700",
    "sg:postcode":"10312",
    "sg:province":"NY",
    "sg:tags":[
        "stationery",
        "greeting",
        "card"
    ],
    "wof:name":"Greenridge Cards & Gifts",
    "wof:placetype":"venue"
},
  "geometry": {"coordinates":[-74.16950199999999,40.560101],"type":"Point"}
}