{
  "type": "Feature",
  "properties": {
    "addr:full":"105 Circle Dr Elbridge NY 13060",
    "addr:housenumber":"105",
    "addr:postcode":"13060",
    "addr:street":"Circle Dr",
    "iso:country":"US",
    "sg:address":"105 Circle Dr",
    "sg:city":"Elbridge",
    "sg:classifiers":[
        {
            "category":"Manufacturing",
            "subcategory":"Printing",
            "type":"Manufacturing & Wholesale Goods"
        }
    ],
    "sg:phone":"+1 315 689 3518",
    "sg:postcode":"13060",
    "sg:province":"NY",
    "sg:tags":[
        "screen"
    ],
    "wof:name":"Shirt Co Home Town",
    "wof:placetype":"venue"
},
  "geometry": {"coordinates":[-76.436058,43.034753],"type":"Point"}
}