{
  "type": "Feature",
  "properties": {
    "iso:country":"US",
    "sg:address":"422 Kipp Rd",
    "sg:city":"Parish",
    "sg:classifiers":[
        {
            "category":"Government",
            "subcategory":"Office",
            "type":"Public Place"
        }
    ],
    "sg:phone":"+1 315 625 7238",
    "sg:postcode":"13131",
    "sg:province":"NY",
    "sg:tags":[
        "city",
        "planning",
        "dev"
    ],
    "wof:name":"Parish Zoning Officer",
    "wof:placetype":"venue"
},
  "geometry": {"coordinates":[-76.104274,43.439001],"type":"Point"}
}