{
  "type": "Feature",
  "properties": {
    "addr:full":"591 Shannon Corners Rd Dundee NY 14837",
    "addr:housenumber":"591",
    "addr:postcode":"14837",
    "addr:street":"Shannon Corners Rd",
    "iso:country":"US",
    "sg:address":"591 Shannon Corners Rd",
    "sg:city":"Dundee",
    "sg:classifiers":[
        {
            "category":"Manufacturing",
            "subcategory":"Lumber",
            "type":"Manufacturing & Wholesale Goods"
        }
    ],
    "sg:phone":"+1 607 243 8803",
    "sg:postcode":"14837",
    "sg:province":"NY",
    "sg:tags":[
        "sawmill"
    ],
    "wof:name":"Woodcorner Saw Mill",
    "wof:placetype":"venue"
},
  "geometry": {"coordinates":[-76.94762299999999,42.544412],"type":"Point"}
}