{
  "type": "Feature",
  "properties": {
    "addr:full":"125 Baylis Rd Melville NY 11747",
    "addr:housenumber":"125",
    "addr:postcode":"11747",
    "addr:street":"Baylis Rd",
    "iso:country":"US",
    "sg:address":"125 Baylis Rd",
    "sg:city":"Melville",
    "sg:classifiers":[
        {
            "category":"Professional",
            "subcategory":"Lawyer & Legal Services",
            "type":"Services"
        }
    ],
    "sg:phone":"+1 631 420 1212",
    "sg:postcode":"11747",
    "sg:province":"NY",
    "sg:tags":[
        "attorney"
    ],
    "wof:name":"Howard J Atlas",
    "wof:placetype":"venue"
},
  "geometry": {"coordinates":[-73.407775,40.768352],"type":"Point"}
}