{
  "type": "Feature",
  "properties": {
    "addr:full":"31 Washington Square W New York NY 10011",
    "addr:housenumber":"31",
    "addr:postcode":"10011",
    "addr:street":"Washington Square W",
    "iso:country":"US",
    "sg:address":"31 Washington Square W",
    "sg:city":"New York",
    "sg:classifiers":[
        {
            "category":"Health Services",
            "subcategory":"Dentist",
            "type":"Services"
        }
    ],
    "sg:phone":"+1 212 420 7680",
    "sg:postcode":"10011",
    "sg:province":"NY",
    "wof:name":"Enhanced Oral Health & Beauty",
    "wof:placetype":"venue"
},
  "geometry": {"coordinates":[-73.99920400000001,40.731959],"type":"Point"}
}