{
  "type": "Feature",
  "properties": {
    "addr:full":"405 Barretto St Bronx NY 10474",
    "addr:housenumber":"405",
    "addr:postcode":"10474",
    "addr:street":"Barretto St",
    "iso:country":"US",
    "sg:address":"405 Barretto St",
    "sg:city":"Bronx",
    "sg:classifiers":[
        {
            "category":"Real Estate",
            "subcategory":"Real Estate Agent",
            "type":"Services"
        }
    ],
    "sg:phone":"+1 718 860 2260",
    "sg:postcode":"10474",
    "sg:province":"NY",
    "wof:name":"Amt Realty LLC",
    "wof:placetype":"venue"
},
  "geometry": {"coordinates":[-73.88821,40.809835],"type":"Point"}
}