{
  "type": "Feature",
  "properties": {
    "addr:full":"1697 Broadway New York NY 10019",
    "addr:housenumber":"1697",
    "addr:postcode":"10019",
    "addr:street":"Broadway",
    "iso:country":"US",
    "sg:address":"1697 Broadway",
    "sg:city":"New York",
    "sg:classifiers":[
        {
            "category":"Museum",
            "type":"Entertainment"
        }
    ],
    "sg:phone":"+1 212 586 1925",
    "sg:postcode":"10019",
    "sg:province":"NY",
    "sg:tags":[
        "organization",
        "arts",
        "information"
    ],
    "wof:name":"American Dance Festival",
    "wof:placetype":"venue"
},
  "geometry": {"coordinates":[-73.98265600000001,40.763764],"type":"Point"}
}