{
  "type": "Feature",
  "properties": {
    "addr:full":"372 Kingston Ave Brooklyn NY 11213",
    "addr:housenumber":"372",
    "addr:postcode":"11213",
    "addr:street":"Kingston Ave",
    "iso:country":"US",
    "sg:address":"372 Kingston Ave",
    "sg:city":"Brooklyn",
    "sg:classifiers":[
        {
            "category":"Health Services",
            "subcategory":"Chiropractor",
            "type":"Services"
        }
    ],
    "sg:phone":"+1 718 221 3999",
    "sg:postcode":"11213",
    "sg:province":"NY",
    "sg:tags":[
        "chiropractic"
    ],
    "wof:name":"Keller Chiropractic Of Crown Heights",
    "wof:placetype":"venue"
},
  "geometry": {"coordinates":[-73.94265900000001,40.666295],"type":"Point"}
}