{
  "type": "Feature",
  "properties": {
    "addr:full":"7414 Niagara Falls Blvd Niagara Falls NY 14304",
    "addr:housenumber":"7414",
    "addr:postcode":"14304",
    "addr:street":"Niagara Falls Blvd",
    "iso:country":"US",
    "sg:address":"7414 Niagara Falls Blvd",
    "sg:city":"Niagara Falls",
    "sg:classifiers":[
        {
            "category":"Shopping",
            "subcategory":"Department Store",
            "type":"Retail Goods"
        }
    ],
    "sg:phone":"+1   ",
    "sg:postcode":"14304",
    "sg:province":"NY",
    "sg:website":"www.target.com",
    "wof:name":"Target",
    "wof:placetype":"venue"
},
  "geometry": {"coordinates":[-78.979659,43.087957],"type":"Point"}
}