{
  "type": "Feature",
  "properties": {
    "addr:full":"514 Turtle St Syracuse NY 13208",
    "addr:housenumber":"514",
    "addr:postcode":"13208",
    "addr:street":"Turtle St",
    "iso:country":"US",
    "sg:address":"514 Turtle St",
    "sg:city":"Syracuse",
    "sg:classifiers":[
        {
            "category":"Retail",
            "subcategory":"Funeral Services",
            "type":"Services"
        }
    ],
    "sg:phone":"+1 315 422 2417",
    "sg:postcode":"13208",
    "sg:province":"NY",
    "sg:tags":[
        "director"
    ],
    "wof:name":"Pirro & Sons Inc",
    "wof:placetype":"venue"
},
  "geometry": {"coordinates":[-76.158034,43.071223],"type":"Point"}
}