{
  "type": "Feature",
  "properties": {
    "addr:full":"263 Boerum St Brooklyn NY 11206",
    "addr:housenumber":"263",
    "addr:postcode":"11206",
    "addr:street":"Boerum St",
    "iso:country":"US",
    "sg:address":"263 Boerum St",
    "sg:city":"Brooklyn",
    "sg:phone":"+1 718 381 5770",
    "sg:postcode":"11206",
    "sg:province":"NY",
    "sg:tags":[
        "industrial",
        "shelving"
    ],
    "wof:name":"A B Steel Equipment",
    "wof:placetype":"venue"
},
  "geometry": {"coordinates":[-73.93703600000001,40.706489],"type":"Point"}
}