{
  "type": "Feature",
  "properties": {
    "addr:full":"68 81st St East Elmhurst NY 11370",
    "addr:housenumber":"68",
    "addr:postcode":"11370",
    "addr:street":"81St St",
    "iso:country":"US",
    "sg:address":"68 81st St",
    "sg:city":"East Elmhurst",
    "sg:classifiers":[
        {
            "category":"Food & Beverages",
            "subcategory":"Liquor & Beverages",
            "type":"Retail Goods"
        }
    ],
    "sg:phone":"+1   ",
    "sg:postcode":"11370",
    "sg:province":"NY",
    "sg:tags":[
        "alcoholic"
    ],
    "wof:name":"Grays Liquors",
    "wof:placetype":"venue"
},
  "geometry": {"coordinates":[-73.888069,40.764791],"type":"Point"}
}