{
  "type": "Feature",
  "properties": {
    "addr:full":"10 Chesebro Dr Schenectady NY 12309",
    "addr:housenumber":"10",
    "addr:postcode":"12309",
    "addr:street":"Chesebro Dr",
    "iso:country":"US",
    "sg:address":"10 Chesebro Dr",
    "sg:city":"Schenectady",
    "sg:classifiers":[
        {
            "category":"Building & Trades",
            "subcategory":"Landscaping Services",
            "type":"Services"
        }
    ],
    "sg:phone":"+1 518 456 4161",
    "sg:postcode":"12309",
    "sg:province":"NY",
    "wof:name":"Creative Land Design of NY",
    "wof:placetype":"venue"
},
  "geometry": {"coordinates":[-73.83618,42.751293],"type":"Point"}
}