{
  "type": "Feature",
  "properties": {
    "addr:full":"548 E 35 Bronx NY 10451",
    "addr:housenumber":"548;35",
    "addr:postcode":"10451",
    "addr:street":"E",
    "iso:country":"US",
    "sg:address":"548 E 35",
    "sg:city":"Bronx",
    "sg:classifiers":[
        {
            "category":"Building & Trades",
            "subcategory":"Construction",
            "type":"Services"
        }
    ],
    "sg:phone":"+1 718 618 0745",
    "sg:postcode":"10451",
    "sg:province":"NY",
    "sg:tags":[
        "contractor"
    ],
    "wof:name":"Brute Force Construction",
    "wof:placetype":"venue"
},
  "geometry": {"coordinates":[-73.913034,40.845077],"type":"Point"}
}