{
  "type": "Feature",
  "properties": {
    "addr:full":"626 Nostrand Avenue Brooklyn NY 11216",
    "addr:housenumber":"626",
    "addr:postcode":"11216",
    "addr:street":"Nostrand Avenue",
    "iso:country":"US",
    "sg:address":"626 Nostrand Avenue",
    "sg:city":"Brooklyn",
    "sg:classifiers":[
        {
            "category":"Restaurant",
            "type":"Food & Drink"
        }
    ],
    "sg:phone":"+1 718 735 8899",
    "sg:postcode":"11216",
    "sg:province":"NY",
    "sg:tags":[
        "chinese"
    ],
    "wof:name":"China City",
    "wof:placetype":"venue"
},
  "geometry": {"coordinates":[-73.949967,40.677036],"type":"Point"}
}