{
  "type": "Feature",
  "properties": {
    "addr:full":"250 W 90th Street Apt 11K New York NY 10024",
    "addr:housenumber":"250",
    "addr:postcode":"10024",
    "addr:street":"W 90Th Street Apt 11K",
    "iso:country":"US",
    "sg:address":"250 W 90th Street Apt 11K",
    "sg:city":"New York",
    "sg:classifiers":[
        {
            "category":"Professional",
            "subcategory":"Computer Services",
            "type":"Services"
        }
    ],
    "sg:phone":"+1 212 874 5963",
    "sg:postcode":"10024",
    "sg:province":"NY",
    "sg:tags":[
        "repair"
    ],
    "wof:name":"Logical Business Systems",
    "wof:placetype":"venue"
},
  "geometry": {"coordinates":[-73.97534,40.791142],"type":"Point"}
}