{
  "type": "Feature",
  "properties": {
    "iso:country":"US",
    "sg:address":"11430 Maple Ridge Rd",
    "sg:city":"Medina",
    "sg:classifiers":[
        {
            "category":"Retail",
            "subcategory":"Car Wash",
            "type":"Services"
        }
    ],
    "sg:phone":"+1 585 798 0213",
    "sg:postcode":"14103",
    "sg:province":"NY",
    "sg:tags":[
        "polishing",
        "washing"
    ],
    "wof:name":"Medina Auto Wash",
    "wof:placetype":"venue"
},
  "geometry": {"coordinates":[-78.383532,43.207422],"type":"Point"}
}