{
  "type": "Feature",
  "properties": {
    "iso:country":"US",
    "sg:address":"6315 State Rte 227",
    "sg:city":"Trumansburg",
    "sg:classifiers":[
        {
            "category":"Building & Trades",
            "subcategory":"Construction",
            "type":"Services"
        }
    ],
    "sg:phone":"+1 607 387 6855",
    "sg:postcode":"14886",
    "sg:province":"NY",
    "sg:tags":[
        "roofing",
        "contractor"
    ],
    "wof:name":"Reasonable Roofing",
    "wof:placetype":"venue"
},
  "geometry": {"coordinates":[-76.693538,42.49975],"type":"Point"}
}