{
  "type": "Feature",
  "properties": {
    "iso:country":"US",
    "sg:address":"170 Canal St Frnt 1",
    "sg:city":"New York",
    "sg:classifiers":[
        {
            "category":"Shopping",
            "subcategory":"Jewelry",
            "type":"Retail Goods"
        }
    ],
    "sg:phone":"+1 212 343 7060",
    "sg:postcode":"10013",
    "sg:province":"NY",
    "wof:name":"Ling Ling Wu Jewelry",
    "wof:placetype":"venue"
},
  "geometry": {"coordinates":[-73.99730599999999,40.71646],"type":"Point"}
}