{
  "type": "Feature",
  "properties": {
    "addr:full":"52 Hudson Ave Peekskill NY 10566",
    "addr:housenumber":"52",
    "addr:postcode":"10566",
    "addr:street":"Hudson Ave",
    "iso:country":"US",
    "sg:address":"52 Hudson Ave",
    "sg:city":"Peekskill",
    "sg:classifiers":[
        {
            "category":"Wholesale",
            "subcategory":"Durable Goods & Equipment",
            "type":"Manufacturing & Wholesale Goods"
        }
    ],
    "sg:phone":"+1 914 777 2501",
    "sg:postcode":"10566",
    "sg:province":"NY",
    "sg:tags":[
        "fire",
        "extinguisher"
    ],
    "wof:name":"Hudson Valley Fire & Safety",
    "wof:placetype":"venue"
},
  "geometry": {"coordinates":[-73.92995999999999,41.285943],"type":"Point"}
}