{
  "type": "Feature",
  "properties": {
    "addr:full":"43 Erlfrd Dr Lakewood NY 14750",
    "addr:housenumber":"43",
    "addr:postcode":"14750",
    "addr:street":"Erlfrd Dr",
    "iso:country":"US",
    "sg:address":"43 Erlfrd Dr",
    "sg:city":"Lakewood",
    "sg:classifiers":[
        {
            "category":"Organizations",
            "subcategory":"Membership Organization",
            "type":"Services"
        }
    ],
    "sg:phone":"+1   ",
    "sg:postcode":"14750",
    "sg:province":"NY",
    "wof:name":"Naval Reserve Association Inc",
    "wof:placetype":"venue"
},
  "geometry": {"coordinates":[-79.33239500000001,42.101279],"type":"Point"}
}