{
  "type": "Feature",
  "properties": {
    "addr:full":"56 Market St Brockport NY 14420",
    "addr:housenumber":"56",
    "addr:postcode":"14420",
    "addr:street":"Market St",
    "iso:country":"US",
    "sg:address":"56 Market St",
    "sg:city":"Brockport",
    "sg:classifiers":[
        {
            "category":"Health Services",
            "subcategory":"Doctor",
            "type":"Services"
        }
    ],
    "sg:phone":"+1 585 637 4430",
    "sg:postcode":"14420",
    "sg:province":"NY",
    "sg:tags":[
        "physician",
        "surgery",
        "oral",
        "dentist",
        "surgeons"
    ],
    "wof:name":"Frederick H Clasquin Dmd",
    "wof:placetype":"venue"
},
  "geometry": {"coordinates":[-77.936571,43.215243],"type":"Point"}
}