{
  "type": "Feature",
  "properties": {
    "addr:full":"390 Main St New Canaan NY 06840",
    "addr:housenumber":"390",
    "addr:postcode":"06840",
    "addr:street":"Main St",
    "iso:country":"US",
    "sg:address":"390 Main St",
    "sg:city":"New Canaan",
    "sg:classifiers":[
        {
            "category":"Government",
            "subcategory":"Office",
            "type":"Public Place"
        }
    ],
    "sg:phone":"+1 203 594 3703",
    "sg:postcode":"06840",
    "sg:province":"NY",
    "sg:tags":[
        "village"
    ],
    "wof:name":"New Canaan Transfer Station",
    "wof:placetype":"venue"
},
  "geometry": {"coordinates":[-73.48360599999999,41.140502],"type":"Point"}
}