{
  "type": "Feature",
  "properties": {
    "addr:full":"4920 3rd Ave Brooklyn NY 11220",
    "addr:housenumber":"4920",
    "addr:postcode":"11220",
    "addr:street":"3Rd Ave",
    "iso:country":"US",
    "sg:address":"4920 3rd Ave",
    "sg:city":"Brooklyn",
    "sg:classifiers":[
        {
            "category":"Professional",
            "type":"Services"
        }
    ],
    "sg:phone":"+1 718 680 2268",
    "sg:postcode":"11220",
    "sg:province":"NY",
    "sg:tags":[
        "establishment"
    ],
    "wof:name":"KCC Stone Trading",
    "wof:placetype":"venue"
},
  "geometry": {"coordinates":[-74.014332,40.647712],"type":"Point"}
}