{
  "type": "Feature",
  "properties": {
    "iso:country":"US",
    "sg:address":"1155 Fulton St",
    "sg:city":"Brooklyn",
    "sg:classifiers":[
        {
            "category":"Home & Garden",
            "subcategory":"Building Materials",
            "type":"Retail Goods"
        }
    ],
    "sg:phone":"+1 718 857 6626",
    "sg:postcode":"11216",
    "sg:province":"NY",
    "sg:tags":[
        "supply"
    ],
    "wof:name":"First Brooklyn Supply",
    "wof:placetype":"venue"
},
  "geometry": {"coordinates":[-73.955455,40.68109],"type":"Point"}
}