{
  "type": "Feature",
  "properties": {
    "addr:full":"1475 E 222nd St Bronx NY 10469",
    "addr:housenumber":"1475",
    "addr:postcode":"10469",
    "addr:street":"E 222Nd St",
    "iso:country":"US",
    "sg:address":"1475 E 222nd St",
    "sg:city":"Bronx",
    "sg:classifiers":[
        {
            "category":"Building & Trades",
            "subcategory":"Construction",
            "type":"Services"
        }
    ],
    "sg:phone":"+1 718 320 7000",
    "sg:postcode":"10469",
    "sg:province":"NY",
    "sg:tags":[
        "contractor"
    ],
    "wof:name":"Metrotech Contracting Corp",
    "wof:placetype":"venue"
},
  "geometry": {"coordinates":[-73.836185,40.876268],"type":"Point"}
}