{
  "type": "Feature",
  "properties": {
    "iso:country":"US",
    "sg:address":"50 Dante Ave",
    "sg:city":"Hicksville",
    "sg:classifiers":[
        {
            "category":"Health Services",
            "subcategory":"Doctor",
            "type":"Services"
        }
    ],
    "sg:phone":"+1 516 735 8803",
    "sg:postcode":"11801",
    "sg:province":"NY",
    "sg:tags":[
        "surgeon",
        "oral"
    ],
    "wof:name":"Finocchio John DDS",
    "wof:placetype":"venue"
},
  "geometry": {"coordinates":[-73.518501,40.7458],"type":"Point"}
}