{
  "type": "Feature",
  "properties": {
    "iso:country":"US",
    "sg:address":"180 Marble Ave",
    "sg:city":"Pleasantville",
    "sg:classifiers":[
        {
            "category":"Health Services",
            "subcategory":"Doctor",
            "type":"Services"
        }
    ],
    "sg:phone":"+1 914 773 9167",
    "sg:postcode":"10570",
    "sg:province":"NY",
    "sg:tags":[
        "medical"
    ],
    "wof:name":"Sarina J Di Stefano",
    "wof:placetype":"venue"
},
  "geometry": {"coordinates":[-73.786948,41.12753],"type":"Point"}
}