{
  "type": "Feature",
  "properties": {
    "iso:country":"US",
    "sg:address":"175 Pinelawn Rd Ste 300",
    "sg:city":"Melville",
    "sg:classifiers":[
        {
            "category":"Banks & Credit Unions",
            "subcategory":"Financial Services",
            "type":"Services"
        }
    ],
    "sg:phone":"+1 516 663 0780",
    "sg:postcode":"11747",
    "sg:province":"NY",
    "sg:tags":[
        "mortgage"
    ],
    "wof:name":"Consumer Settlement",
    "wof:placetype":"venue"
},
  "geometry": {"coordinates":[-73.405777,40.769161],"type":"Point"}
}