{
  "type": "Feature",
  "properties": {
    "iso:country":"US",
    "sg:address":"992 E 174th Street",
    "sg:city":"Bronx",
    "sg:classifiers":[
        {
            "category":"Personal",
            "subcategory":"Barber",
            "type":"Services"
        }
    ],
    "sg:phone":"+1 718 378 8903",
    "sg:postcode":"10460",
    "sg:province":"NY",
    "wof:name":"Dave's Barber Shop",
    "wof:placetype":"venue"
},
  "geometry": {"coordinates":[-73.884691,40.836208],"type":"Point"}
}