{
  "type": "Feature",
  "properties": {
    "addr:full":"457 Hawkins Ave Lake Ronkonkoma NY 11779",
    "addr:housenumber":"457",
    "addr:postcode":"11779",
    "addr:street":"Hawkins Ave",
    "iso:country":"US",
    "sg:address":"457 Hawkins Ave",
    "sg:city":"Lake Ronkonkoma",
    "sg:classifiers":[
        {
            "category":"Building & Trades",
            "subcategory":"Construction",
            "type":"Services"
        }
    ],
    "sg:phone":"+1 631 588 1485",
    "sg:postcode":"11779",
    "sg:province":"NY",
    "sg:tags":[
        "masonry",
        "contractor"
    ],
    "wof:name":"LRM Lake Ronkonkoma Masons",
    "wof:placetype":"venue"
},
  "geometry": {"coordinates":[-73.107429,40.824973],"type":"Point"}
}