{
  "type": "Feature",
  "properties": {
    "addr:full":"110 Toledo St Farmingdale NY 11735",
    "addr:housenumber":"110",
    "addr:postcode":"11735",
    "addr:street":"Toledo St",
    "iso:country":"US",
    "sg:address":"110 Toledo St",
    "sg:city":"Farmingdale",
    "sg:classifiers":[
        {
            "category":"Building & Trades",
            "subcategory":"Plumbing",
            "type":"Services"
        }
    ],
    "sg:phone":"+1 631 420 2848",
    "sg:postcode":"11735",
    "sg:province":"NY",
    "sg:tags":[
        "repair",
        "e",
        "doing",
        "heating",
        "contractor",
        "conditioning",
        "air"
    ],
    "wof:name":"Omni Air Systems Corp",
    "wof:placetype":"venue"
},
  "geometry": {"coordinates":[-73.419635,40.71202],"type":"Point"}
}