{
  "type": "Feature",
  "properties": {
    "addr:full":"60 W 72nd St New York NY 10023",
    "addr:housenumber":"60",
    "addr:postcode":"10023",
    "addr:street":"W 72Nd St",
    "iso:country":"US",
    "sg:address":"60 W 72nd St",
    "sg:city":"New York",
    "sg:classifiers":[
        {
            "category":"Building & Trades",
            "subcategory":"Locksmith",
            "type":"Services"
        }
    ],
    "sg:phone":"+1 212 937 2936",
    "sg:postcode":"10023",
    "sg:province":"NY",
    "sg:tags":[
        "key"
    ],
    "wof:name":"Aravy Locksmith",
    "wof:placetype":"venue"
},
  "geometry": {"coordinates":[-73.982201,40.776402],"type":"Point"}
}