{
  "type": "Feature",
  "properties": {
    "addr:full":"318 Stormville Mountain Rd Stormville NY 12582",
    "addr:housenumber":"318",
    "addr:postcode":"12582",
    "addr:street":"Stormville Mountain Rd",
    "iso:country":"US",
    "sg:address":"318 Stormville Mountain Rd",
    "sg:city":"Stormville",
    "sg:classifiers":[
        {
            "category":"Building & Trades",
            "subcategory":"Construction",
            "type":"Services"
        }
    ],
    "sg:phone":"+1 845 878 9043",
    "sg:postcode":"12582",
    "sg:province":"NY",
    "wof:name":"Signal Tower Inc",
    "wof:placetype":"venue"
},
  "geometry": {"coordinates":[-73.71405,41.541481],"type":"Point"}
}