{
  "type": "Feature",
  "properties": {
    "iso:country":"US",
    "sg:address":"1159 Town Line Rd",
    "sg:city":"Alden",
    "sg:classifiers":[
        {
            "category":"Social Services",
            "subcategory":"Child Care",
            "type":"Services"
        }
    ],
    "sg:phone":"+1 716 684 1467",
    "sg:postcode":"14004",
    "sg:province":"NY",
    "sg:tags":[
        "school",
        "nursery",
        "church"
    ],
    "wof:name":"Town Line Nursery School",
    "wof:placetype":"venue"
},
  "geometry": {"coordinates":[-78.57835799999999,42.919092],"type":"Point"}
}