{
  "type": "Feature",
  "properties": {
    "iso:country":"US",
    "sg:address":"1649 Amsterdam Ave",
    "sg:city":"New York",
    "sg:classifiers":[
        {
            "category":"Social Services",
            "type":"Services"
        }
    ],
    "sg:phone":"+1   ",
    "sg:postcode":"10031",
    "sg:province":"NY",
    "wof:name":"Mica Program",
    "wof:placetype":"venue"
},
  "geometry": {"coordinates":[-73.94913,40.822938],"type":"Point"}
}