{
  "type": "Feature",
  "properties": {
    "iso:country":"US",
    "sg:address":"15 N Seneca St",
    "sg:city":"West Seneca",
    "sg:classifiers":[
        {
            "category":"Restaurant",
            "type":"Food & Drink"
        }
    ],
    "sg:phone":"+1 716 674 5999",
    "sg:postcode":"14224",
    "sg:province":"NY",
    "sg:tags":[
        "snack",
        "appetizer"
    ],
    "wof:name":"Troyer Potato Products",
    "wof:placetype":"venue"
},
  "geometry": {"coordinates":[-78.788055,42.847825],"type":"Point"}
}