{
  "type": "Feature",
  "properties": {
    "iso:country":"US",
    "sg:address":"519 S 6th St",
    "sg:city":"Lindenhurst",
    "sg:classifiers":[
        {
            "category":"Building & Trades",
            "subcategory":"Landscaping Services",
            "type":"Services"
        }
    ],
    "sg:phone":"+1 631 957 1590",
    "sg:postcode":"11757",
    "sg:province":"NY",
    "sg:tags":[
        "landscape"
    ],
    "wof:name":"Ed Mikuseks Landscaping",
    "wof:placetype":"venue"
},
  "geometry": {"coordinates":[-73.37415799999999,40.674573],"type":"Point"}
}