{
  "type": "Feature",
  "properties": {
    "iso:country":"US",
    "sg:address":"16 Bridgewater St",
    "sg:city":"Brooklyn",
    "sg:classifiers":[
        {
            "category":"Wholesale",
            "subcategory":"Wine & Distilled Alcoholic Beverages",
            "type":"Manufacturing & Wholesale Goods"
        }
    ],
    "sg:phone":"+1 718 383 5500",
    "sg:postcode":"11222",
    "sg:province":"NY",
    "sg:tags":[
        "liquor"
    ],
    "sg:website":"www.peerimp.com",
    "wof:name":"Peerless Importers Inc",
    "wof:placetype":"venue"
},
  "geometry": {"coordinates":[-73.935697,40.727348],"type":"Point"}
}