{
  "type": "Feature",
  "properties": {
    "addr:full":"507 Bicycle Path Port Jefferson Station NY 11776",
    "addr:postcode":"11776",
    "addr:street":"Bicycle Path",
    "iso:country":"US",
    "sg:address":"507 Bicycle Path",
    "sg:city":"Port Jefferson Station",
    "sg:classifiers":[
        {
            "category":"Manufacturing",
            "subcategory":"Printing",
            "type":"Manufacturing & Wholesale Goods"
        }
    ],
    "sg:phone":"+1   ",
    "sg:postcode":"11776",
    "sg:province":"NY",
    "sg:tags":[
        "printer",
        "offset"
    ],
    "wof:name":"St Gerard Printing",
    "wof:placetype":"venue"
},
  "geometry": {"coordinates":[-73.036889,40.902663],"type":"Point"}
}