{
  "type": "Feature",
  "properties": {
    "addr:full":"382 Sprague Ave Staten Island NY 10307",
    "addr:housenumber":"382",
    "addr:postcode":"10307",
    "addr:street":"Sprague Ave",
    "iso:country":"US",
    "sg:address":"382 Sprague Ave",
    "sg:city":"Staten Island",
    "sg:classifiers":[
        {
            "category":"Shopping",
            "type":"Retail Goods"
        }
    ],
    "sg:phone":"+1   ",
    "sg:postcode":"10307",
    "sg:province":"NY",
    "sg:tags":[
        "merchandise"
    ],
    "wof:name":"Channel Pet Supplies",
    "wof:placetype":"venue"
},
  "geometry": {"coordinates":[-74.237177,40.502213],"type":"Point"}
}