{
  "type": "Feature",
  "properties": {
    "iso:country":"US",
    "sg:address":"130 S Elmwood Ave",
    "sg:city":"Buffalo",
    "sg:classifiers":[
        {
            "category":"Organizations",
            "subcategory":"Community Association",
            "type":"Services"
        }
    ],
    "sg:phone":"+1 716 856 0684",
    "sg:postcode":"14202",
    "sg:province":"NY",
    "sg:tags":[
        "military"
    ],
    "wof:name":"Paralized Veterans",
    "wof:placetype":"venue"
},
  "geometry": {"coordinates":[-78.878969,42.889236],"type":"Point"}
}