{
  "type": "Feature",
  "properties": {
    "addr:full":"34 Linden St Huntington NY 11743",
    "addr:housenumber":"34",
    "addr:postcode":"11743",
    "addr:street":"Linden St",
    "iso:country":"US",
    "sg:address":"34 Linden St",
    "sg:city":"Huntington",
    "sg:classifiers":[
        {
            "category":"Professional",
            "subcategory":"Computer Services",
            "type":"Services"
        }
    ],
    "sg:phone":"+1 631 385 1797",
    "sg:postcode":"11743",
    "sg:province":"NY",
    "wof:name":"Ny Exhibit Works",
    "wof:placetype":"venue"
},
  "geometry": {"coordinates":[-73.36875999999999,40.838076],"type":"Point"}
}