{
  "type": "Feature",
  "properties": {
    "addr:full":"199 Prince St New York NY 10012",
    "addr:housenumber":"199",
    "addr:postcode":"10012",
    "addr:street":"Prince St",
    "iso:country":"US",
    "sg:address":"199 Prince St",
    "sg:city":"New York",
    "sg:classifiers":[
        {
            "category":"Restaurant",
            "type":"Food & Drink"
        }
    ],
    "sg:phone":"+1   ",
    "sg:postcode":"10012",
    "sg:province":"NY",
    "sg:tags":[
        "eating"
    ],
    "wof:name":"Elysee Bar & Grill",
    "wof:placetype":"venue"
},
  "geometry": {"coordinates":[-74.00275499999999,40.726729],"type":"Point"}
}