{
  "type": "Feature",
  "properties": {
    "addr:full":"150 Islip Ave Islip NY 11751",
    "addr:housenumber":"150",
    "addr:postcode":"11751",
    "addr:street":"Islip Ave",
    "iso:country":"US",
    "sg:address":"150 Islip Ave",
    "sg:city":"Islip",
    "sg:classifiers":[
        {
            "category":"Shopping",
            "subcategory":"Discount & Variety Stores",
            "type":"Retail Goods"
        }
    ],
    "sg:phone":"+1 631 563 3340",
    "sg:postcode":"11751",
    "sg:province":"NY",
    "wof:name":"Dollar Temporary Svc",
    "wof:placetype":"venue"
},
  "geometry": {"coordinates":[-73.20787199999999,40.736258],"type":"Point"}
}