{
  "type": "Feature",
  "properties": {
    "addr:full":"450 E Main St Middletown NY 10940",
    "addr:housenumber":"450",
    "addr:postcode":"10940",
    "addr:street":"E Main St",
    "iso:country":"US",
    "sg:address":"450 E Main St",
    "sg:city":"Middletown",
    "sg:classifiers":[
        {
            "category":"Professional",
            "subcategory":"Management & Consulting",
            "type":"Services"
        }
    ],
    "sg:phone":"+1 845 343 0172",
    "sg:postcode":"10940",
    "sg:province":"NY",
    "sg:tags":[
        "public",
        "relations"
    ],
    "wof:name":"Civil Svc Employees Assn Inc",
    "wof:placetype":"venue"
},
  "geometry": {"coordinates":[-74.387311,41.444555],"type":"Point"}
}