{
  "type": "Feature",
  "properties": {
    "addr:full":"105 Wortman Ave Brooklyn NY 11207",
    "addr:housenumber":"105",
    "addr:postcode":"11207",
    "addr:street":"Wortman Ave",
    "iso:country":"US",
    "sg:address":"105 Wortman Ave",
    "sg:city":"Brooklyn",
    "sg:classifiers":[
        {
            "category":"Autos & Motor Vehicles",
            "subcategory":"Automobile Sales",
            "type":"Retail Goods"
        }
    ],
    "sg:phone":"+1 718 272 9600",
    "sg:postcode":"11207",
    "sg:province":"NY",
    "sg:tags":[
        "car",
        "dealer"
    ],
    "wof:name":"3 J's Auto Sales Inc",
    "wof:placetype":"venue"
},
  "geometry": {"coordinates":[-73.888587,40.655428],"type":"Point"}
}