{
  "type": "Feature",
  "properties": {
    "iso:country":"US",
    "sg:address":"53 Merrick Ave",
    "sg:city":"Merrick",
    "sg:classifiers":[
        {
            "category":"Restaurant",
            "type":"Food & Drink"
        }
    ],
    "sg:phone":"+1 516 223 7476",
    "sg:postcode":"11566",
    "sg:province":"NY",
    "wof:name":"Roma Pizzeria",
    "wof:placetype":"venue"
},
  "geometry": {"coordinates":[-73.559799,40.6819],"type":"Point"}
}