{
  "type": "Feature",
  "properties": {
    "addr:full":"3560 Rochambeau Ave 3G Bronx NY 10467",
    "addr:housenumber":"3560;3g",
    "addr:postcode":"10467",
    "addr:street":"Rochambeau Ave",
    "iso:country":"US",
    "sg:address":"3560 Rochambeau Ave 3G",
    "sg:city":"Bronx",
    "sg:classifiers":[
        {
            "category":"Taxi",
            "type":"Transportation"
        }
    ],
    "sg:phone":"+1 646 382 2750",
    "sg:postcode":"10467",
    "sg:province":"NY",
    "wof:name":"Ema Car Corp",
    "wof:placetype":"venue"
},
  "geometry": {"coordinates":[-73.878877,40.882913],"type":"Point"}
}