{
  "type": "Feature",
  "properties": {
    "addr:full":"141 Phillips Ave Riverhead NY 11901",
    "addr:housenumber":"141",
    "addr:postcode":"11901",
    "addr:street":"Phillips Ave",
    "iso:country":"US",
    "sg:address":"141 Phillips Ave",
    "sg:city":"Riverhead",
    "sg:classifiers":[
        {
            "category":"Education",
            "subcategory":"School",
            "type":"Public Place"
        }
    ],
    "sg:phone":"+1 631 369 6786",
    "sg:postcode":"11901",
    "sg:province":"NY",
    "sg:tags":[
        "high",
        "middle",
        "elementary"
    ],
    "sg:website":"www.riverhead.net",
    "wof:name":"Riverhead Central School District",
    "wof:placetype":"venue"
},
  "geometry": {"coordinates":[-72.650729,40.908779],"type":"Point"}
}