{
  "type": "Feature",
  "properties": {
    "addr:full":"306 Charles St Jamestown NY 14701",
    "addr:housenumber":"306",
    "addr:postcode":"14701",
    "addr:street":"Charles St",
    "iso:country":"US",
    "sg:address":"306 Charles St",
    "sg:city":"Jamestown",
    "sg:classifiers":[
        {
            "category":"Organizations",
            "subcategory":"Religious Organization",
            "type":"Services"
        }
    ],
    "sg:phone":"+1 716 484 9541",
    "sg:postcode":"14701",
    "sg:province":"NY",
    "sg:tags":[
        "clergy"
    ],
    "wof:name":"Don Zampogna",
    "wof:placetype":"venue"
},
  "geometry": {"coordinates":[-79.244975,42.083822],"type":"Point"}
}