{
  "type": "Feature",
  "properties": {
    "iso:country":"US",
    "sg:address":"70 Lambert Ave",
    "sg:city":"Copiague",
    "sg:classifiers":[
        {
            "category":"Professional",
            "type":"Services"
        }
    ],
    "sg:phone":"+1 631 888 7701",
    "sg:postcode":"11726",
    "sg:province":"NY",
    "sg:tags":[
        "establishment"
    ],
    "wof:name":"Vac-Lock Corp",
    "wof:placetype":"venue"
},
  "geometry": {"coordinates":[-73.38832600000001,40.681518],"type":"Point"}
}