{
  "type": "Feature",
  "properties": {
    "addr:full":"225 E 24th St New York NY 10010",
    "addr:housenumber":"225",
    "addr:postcode":"10010",
    "addr:street":"E 24Th St",
    "iso:country":"US",
    "sg:address":"225 E 24th St",
    "sg:city":"New York",
    "sg:classifiers":[
        {
            "category":"Manufacturing",
            "subcategory":"Furniture",
            "type":"Manufacturing & Wholesale Goods"
        }
    ],
    "sg:phone":"+1   ",
    "sg:postcode":"10010",
    "sg:province":"NY",
    "sg:tags":[
        "mfg",
        "wood",
        "cabinet"
    ],
    "wof:name":"Custom Art Furniture",
    "wof:placetype":"venue"
},
  "geometry": {"coordinates":[-73.98079799999999,40.738847],"type":"Point"}
}