{
  "type": "Feature",
  "properties": {
    "addr:full":"5961 Palisade Ave Bronx NY 10471",
    "addr:housenumber":"5961",
    "addr:postcode":"10471",
    "addr:street":"Palisade Ave",
    "iso:country":"US",
    "sg:address":"5961 Palisade Ave",
    "sg:city":"Bronx",
    "sg:classifiers":[
        {
            "category":"Retail",
            "subcategory":"Repair Shop",
            "type":"Services"
        }
    ],
    "sg:phone":"+1 347 332 1433",
    "sg:postcode":"10471",
    "sg:province":"NY",
    "sg:tags":[
        "lock",
        "locksmith"
    ],
    "wof:name":"24 Hour Locksmith",
    "wof:placetype":"venue"
},
  "geometry": {"coordinates":[-73.90701799999999,40.910695],"type":"Point"}
}