{
  "type": "Feature",
  "properties": {
    "addr:full":"7811 Flatlands Ave  Brooklyn NY 11236",
    "addr:housenumber":"7811",
    "addr:postcode":"11236",
    "addr:street":"Flatlands Ave",
    "iso:country":"US",
    "sg:address":"7811 Flatlands Ave ",
    "sg:city":"Brooklyn",
    "sg:classifiers":[
        {
            "category":"Restaurant",
            "type":"Food & Drink"
        }
    ],
    "sg:menulink":"http://www.allmenus.com/ny/brooklyn/181878-wendys/menu/",
    "sg:phone":"+1 718 251 1801",
    "sg:postcode":"11236",
    "sg:province":"NY",
    "sg:tags":[
        "burger",
        "american",
        "soup"
    ],
    "wof:name":"Wendy's",
    "wof:placetype":"venue"
},
  "geometry": {"coordinates":[-73.914727,40.634636],"type":"Point"}
}