{
  "type": "Feature",
  "properties": {
    "addr:full":"177 N Bourndale Rd Manhasset NY 11030",
    "addr:housenumber":"177",
    "addr:postcode":"11030",
    "addr:street":"N Bourndale Rd",
    "iso:country":"US",
    "sg:address":"177 N Bourndale Rd",
    "sg:city":"Manhasset",
    "sg:classifiers":[
        {
            "category":"Banks & Credit Unions",
            "subcategory":"Investment Brokerage",
            "type":"Services"
        }
    ],
    "sg:phone":"+1 516 627 2314",
    "sg:postcode":"11030",
    "sg:province":"NY",
    "wof:name":"Crown Bridge Asset MGT LLC",
    "wof:placetype":"venue"
},
  "geometry": {"coordinates":[-73.69810099999999,40.802392],"type":"Point"}
}