{
  "type": "Feature",
  "properties": {
    "addr:full":"49 Main St Hempstead NY 11550",
    "addr:housenumber":"49",
    "addr:postcode":"11550",
    "addr:street":"Main St",
    "iso:country":"US",
    "sg:address":"49 Main St",
    "sg:city":"Hempstead",
    "sg:classifiers":[
        {
            "category":"Shopping",
            "subcategory":"Clothing, Apparel, & Fashions",
            "type":"Retail Goods"
        }
    ],
    "sg:phone":"+1 516 292 7478",
    "sg:postcode":"11550",
    "sg:province":"NY",
    "wof:name":"Sister Clara's Unique Boutique",
    "wof:placetype":"venue"
},
  "geometry": {"coordinates":[-73.62383800000001,40.706529],"type":"Point"}
}