{
  "type": "Feature",
  "properties": {
    "addr:full":"554 Amherst Dr Woodmere NY 11598",
    "addr:housenumber":"554",
    "addr:postcode":"11598",
    "addr:street":"Amherst Dr",
    "iso:country":"US",
    "sg:address":"554 Amherst Dr",
    "sg:city":"Woodmere",
    "sg:classifiers":[
        {
            "category":"Professional",
            "subcategory":"Management & Consulting",
            "type":"Services"
        }
    ],
    "sg:phone":"+1 516 902 4285",
    "sg:postcode":"11598",
    "sg:province":"NY",
    "wof:name":"Rush Hour Solutions LLC",
    "wof:placetype":"venue"
},
  "geometry": {"coordinates":[-73.714484,40.641199],"type":"Point"}
}