{
  "type": "Feature",
  "properties": {
    "addr:full":"4112 Quentin Rd Brooklyn NY 11234",
    "addr:housenumber":"4112",
    "addr:postcode":"11234",
    "addr:street":"Quentin Rd",
    "iso:country":"US",
    "sg:address":"4112 Quentin Rd",
    "sg:city":"Brooklyn",
    "sg:classifiers":[
        {
            "category":"Professional",
            "subcategory":"Advertising",
            "type":"Services"
        }
    ],
    "sg:phone":"+1 718 998 0666",
    "sg:postcode":"11234",
    "sg:province":"NY",
    "sg:tags":[
        "agency"
    ],
    "wof:name":"Splash Media Group Inc",
    "wof:placetype":"venue"
},
  "geometry": {"coordinates":[-73.93250500000001,40.617318],"type":"Point"}
}