{
  "type": "Feature",
  "properties": {
    "addr:full":"2157 Main St Buffalo NY 14214",
    "addr:housenumber":"2157",
    "addr:postcode":"14214",
    "addr:street":"Main St",
    "iso:country":"US",
    "sg:address":"2157 Main St",
    "sg:city":"Buffalo",
    "sg:classifiers":[
        {
            "category":"Health Services",
            "subcategory":"Doctor",
            "type":"Services"
        },
        {
            "category":"Health Services",
            "subcategory":"Hospital",
            "type":"Services"
        }
    ],
    "sg:phone":"+1 716 862 1982",
    "sg:postcode":"14214",
    "sg:province":"NY",
    "wof:name":"Saroff Marie MD",
    "wof:placetype":"venue"
},
  "geometry": {"coordinates":[-78.849791,42.92905],"type":"Point"}
}