{
  "type": "Feature",
  "properties": {
    "iso:country":"US",
    "sg:address":"216 N Main St",
    "sg:city":"Freeport",
    "sg:classifiers":[
        {
            "category":"Manufacturing",
            "subcategory":"Tools & Machinery",
            "type":"Manufacturing & Wholesale Goods"
        }
    ],
    "sg:phone":"+1 516 223 5055",
    "sg:postcode":"11520",
    "sg:province":"NY",
    "sg:tags":[
        "manufacture",
        "steel",
        "maker",
        "rule",
        "die"
    ],
    "wof:name":"Imperial Steel Rule Die Co",
    "wof:placetype":"venue"
},
  "geometry": {"coordinates":[-73.58639599999999,40.664352],"type":"Point"}
}