{
  "type": "Feature",
  "properties": {
    "addr:full":"890 E 51st St Brooklyn NY 11203",
    "addr:housenumber":"890",
    "addr:postcode":"11203",
    "addr:street":"E 51St St",
    "iso:country":"US",
    "sg:address":"890 E 51st St",
    "sg:city":"Brooklyn",
    "sg:classifiers":[
        {
            "category":"Home & Garden",
            "subcategory":"Furniture",
            "type":"Retail Goods"
        }
    ],
    "sg:phone":"+1 718 629 3113",
    "sg:postcode":"11203",
    "sg:province":"NY",
    "wof:name":"Utica Furniture Distributors",
    "wof:placetype":"venue"
},
  "geometry": {"coordinates":[-73.927954,40.637892],"type":"Point"}
}