{
  "type": "Feature",
  "properties": {
    "iso:country":"US",
    "sg:address":"22518 Linden Boulevard",
    "sg:city":"Cambria Heights",
    "sg:classifiers":[
        {
            "category":"Education",
            "subcategory":"Special Training",
            "type":"Public Place"
        },
        {
            "category":"Education",
            "subcategory":"School",
            "type":"Public Place"
        }
    ],
    "sg:phone":"+1 718 527 6258",
    "sg:postcode":"11411",
    "sg:province":"NY",
    "sg:tags":[
        "high",
        "middle",
        "specialty",
        "elementary"
    ],
    "wof:name":"Helping Hand Learning Center",
    "wof:placetype":"venue"
},
  "geometry": {"coordinates":[-73.735119,40.693455],"type":"Point"}
}