{
  "type": "Feature",
  "properties": {
    "iso:country":"US",
    "sg:address":"200 Clearbrook Rd",
    "sg:city":"Elmsford",
    "sg:classifiers":[
        {
            "category":"Wholesale",
            "subcategory":"Electrical",
            "type":"Manufacturing & Wholesale Goods"
        }
    ],
    "sg:phone":"+1 914 592 2260",
    "sg:postcode":"10523",
    "sg:province":"NY",
    "sg:tags":[
        "equipment"
    ],
    "wof:name":"Honeywell",
    "wof:placetype":"venue"
},
  "geometry": {"coordinates":[-73.81396100000001,41.072551],"type":"Point"}
}