{
  "type": "Feature",
  "properties": {
    "addr:full":"423 Orange St Albany NY 12206",
    "addr:housenumber":"423",
    "addr:postcode":"12206",
    "addr:street":"Orange St",
    "iso:country":"US",
    "sg:address":"423 Orange St",
    "sg:city":"Albany",
    "sg:classifiers":[
        {
            "category":"Retail",
            "subcategory":"Repair Shop",
            "type":"Services"
        }
    ],
    "sg:phone":"+1 518 462 3454",
    "sg:postcode":"12206",
    "sg:province":"NY",
    "sg:tags":[
        "operator",
        "welding",
        "local",
        "trucking"
    ],
    "wof:name":"Nelson Brothers",
    "wof:placetype":"venue"
},
  "geometry": {"coordinates":[-73.767179,42.663325],"type":"Point"}
}