{
  "type": "Feature",
  "properties": {
    "addr:full":"4000 Middle Country Rd Lake Grove NY 11755",
    "addr:housenumber":"4000",
    "addr:postcode":"11755",
    "addr:street":"Middle Country Rd",
    "iso:country":"US",
    "sg:address":"4000 Middle Country Rd",
    "sg:city":"Lake Grove",
    "sg:classifiers":[
        {
            "category":"Bars & Pubs",
            "type":"Food & Drink"
        },
        {
            "category":"Restaurant",
            "type":"Food & Drink"
        }
    ],
    "sg:phone":"+1 631 588 0500",
    "sg:postcode":"11755",
    "sg:province":"NY",
    "sg:tags":[
        "new",
        "american"
    ],
    "sg:website":"houlihans.com/",
    "wof:name":"Houlihan's",
    "wof:placetype":"venue"
},
  "geometry": {"coordinates":[-73.130208,40.86206],"type":"Point"}
}