{
  "type": "Feature",
  "properties": {
    "iso:country":"US",
    "sg:address":"154 Lake Hill Rd",
    "sg:city":"Burnt Hills",
    "sg:classifiers":[
        {
            "category":"Health Services",
            "subcategory":"Dentist",
            "type":"Services"
        }
    ],
    "sg:phone":"+1 518 399 5528",
    "sg:postcode":"12027",
    "sg:province":"NY",
    "wof:name":"Di Gesare Lawrence E Dntst",
    "wof:placetype":"venue"
},
  "geometry": {"coordinates":[-73.90329699999999,42.91],"type":"Point"}
}