{
  "type": "Feature",
  "properties": {
    "addr:full":"944 Route 6 Mahopac NY 10541",
    "addr:housenumber":"944",
    "addr:postcode":"10541",
    "addr:street":"Route 6",
    "iso:country":"US",
    "sg:address":"944 Route 6",
    "sg:city":"Mahopac",
    "sg:classifiers":[
        {
            "category":"Restaurant",
            "type":"Food & Drink"
        }
    ],
    "sg:phone":"+1 845 628 3304",
    "sg:postcode":"10541",
    "sg:province":"NY",
    "sg:tags":[
        "pizza"
    ],
    "wof:name":"Russo Pizzeria",
    "wof:placetype":"venue"
},
  "geometry": {"coordinates":[-73.724722,41.390348],"type":"Point"}
}