{
  "type": "Feature",
  "properties": {
    "iso:country":"US",
    "sg:address":"18 W Sunrise Hwy",
    "sg:city":"Freeport",
    "sg:classifiers":[
        {
            "category":"Professional",
            "subcategory":"Lawyer & Legal Services",
            "type":"Services"
        }
    ],
    "sg:phone":"+1 516 208 6787",
    "sg:postcode":"11520",
    "sg:province":"NY",
    "sg:tags":[
        "naturalization",
        "immigration"
    ],
    "wof:name":"Services Immigration",
    "wof:placetype":"venue"
},
  "geometry": {"coordinates":[-73.582579,40.656468],"type":"Point"}
}