{
  "type": "Feature",
  "properties": {
    "iso:country":"US",
    "sg:address":"629 5th Ave",
    "sg:city":"Pelham",
    "sg:classifiers":[
        {
            "category":"Professional",
            "type":"Services"
        }
    ],
    "sg:phone":"+1 914 738 1178",
    "sg:postcode":"10803",
    "sg:province":"NY",
    "sg:tags":[
        "establishment"
    ],
    "wof:name":"Peregrine Assoc",
    "wof:placetype":"venue"
},
  "geometry": {"coordinates":[-73.804378,40.920616],"type":"Point"}
}