{
  "type": "Feature",
  "properties": {
    "addr:full":"1176 5th Ave New York NY 10029",
    "addr:housenumber":"1176",
    "addr:postcode":"10029",
    "addr:street":"5Th Ave",
    "iso:country":"US",
    "sg:address":"1176 5th Ave",
    "sg:city":"New York",
    "sg:classifiers":[
        {
            "category":"Health Services",
            "subcategory":"Doctor",
            "type":"Services"
        }
    ],
    "sg:phone":"+1 212 831 4393",
    "sg:postcode":"10029",
    "sg:province":"NY",
    "wof:name":"Aron Alan M MD",
    "wof:placetype":"venue"
},
  "geometry": {"coordinates":[-73.95410200000001,40.789902],"type":"Point"}
}