{
  "type": "Feature",
  "properties": {
    "addr:full":"2444 Wiedrick Rd Macedon NY 14568",
    "addr:housenumber":"2444",
    "addr:postcode":"14568",
    "addr:street":"Wiedrick Rd",
    "iso:country":"US",
    "sg:address":"2444 Wiedrick Rd",
    "sg:city":"Macedon",
    "sg:classifiers":[
        {
            "category":"Building & Trades",
            "subcategory":"Plumbing",
            "type":"Services"
        }
    ],
    "sg:phone":"+1 315 986 4127",
    "sg:postcode":"14568",
    "sg:province":"NY",
    "sg:tags":[
        "contractor"
    ],
    "wof:name":"Cloverdale Heating & Cooling",
    "wof:placetype":"venue"
},
  "geometry": {"coordinates":[-77.30293399999999,43.106182],"type":"Point"}
}