{
  "type": "Feature",
  "properties": {
    "iso:country":"US",
    "sg:address":"601 W 110th Street",
    "sg:city":"New York",
    "sg:classifiers":[
        {
            "category":"Education",
            "subcategory":"Special Training",
            "type":"Public Place"
        }
    ],
    "sg:phone":"+1 212 932 3049",
    "sg:postcode":"10025",
    "sg:province":"NY",
    "sg:tags":[
        "school",
        "specialty"
    ],
    "wof:name":"Oxbridge Academic Resources",
    "wof:placetype":"venue"
},
  "geometry": {"coordinates":[-73.966791,40.804232],"type":"Point"}
}