{
  "type": "Feature",
  "properties": {
    "iso:country":"US",
    "sg:address":"437 Main St",
    "sg:city":"Dunkirk",
    "sg:classifiers":[
        {
            "category":"Government",
            "subcategory":"Office",
            "type":"Public Place"
        }
    ],
    "sg:phone":"+1 716 366 8211",
    "sg:postcode":"14048",
    "sg:province":"NY",
    "sg:tags":[
        "federal",
        "human"
    ],
    "sg:website":"www.ssa.gov",
    "wof:name":"US Social Security Adm",
    "wof:placetype":"venue"
},
  "geometry": {"coordinates":[-79.328171,42.483454],"type":"Point"}
}