{
  "type": "Feature",
  "properties": {
    "iso:country":"US",
    "sg:address":"384 Ocean Ave",
    "sg:city":"Massapequa",
    "sg:classifiers":[
        {
            "category":"Professional",
            "subcategory":"Accounting & Tax Preparation",
            "type":"Services"
        }
    ],
    "sg:phone":"+1   ",
    "sg:postcode":"11758",
    "sg:province":"NY",
    "wof:name":"Daniel McVeigh CPA",
    "wof:placetype":"venue"
},
  "geometry": {"coordinates":[-73.47054300000001,40.673217],"type":"Point"}
}