{
  "type": "Feature",
  "properties": {
    "addr:full":"200 Rogers Ave Hoosick Falls NY 12090",
    "addr:housenumber":"200",
    "addr:postcode":"12090",
    "addr:street":"Rogers Ave",
    "iso:country":"US",
    "sg:address":"200 Rogers Ave",
    "sg:city":"Hoosick Falls",
    "sg:phone":"+1 518 686 1812",
    "sg:postcode":"12090",
    "sg:province":"NY",
    "sg:tags":[
        "farm",
        "field",
        "crop"
    ],
    "wof:name":"Two Ponds",
    "wof:placetype":"venue"
},
  "geometry": {"coordinates":[-73.34190099999999,42.89369],"type":"Point"}
}