{
  "type": "Feature",
  "properties": {
    "addr:full":"3967 Sedgwick Ave Bronx NY 10463",
    "addr:housenumber":"3967",
    "addr:postcode":"10463",
    "addr:street":"Sedgwick Ave",
    "iso:country":"US",
    "sg:address":"3967 Sedgwick Ave",
    "sg:city":"Bronx",
    "sg:classifiers":[
        {
            "category":"Professional",
            "subcategory":"Accounting & Tax Preparation",
            "type":"Services"
        }
    ],
    "sg:phone":"+1 718 432 1693",
    "sg:postcode":"10463",
    "sg:province":"NY",
    "sg:tags":[
        "firm",
        "business"
    ],
    "wof:name":"K&K Tax & Accounting Svcs LLC",
    "wof:placetype":"venue"
},
  "geometry": {"coordinates":[-73.887896,40.88285],"type":"Point"}
}