{
  "type": "Feature",
  "properties": {
    "iso:country":"US",
    "sg:address":"1568 State Hwy 206",
    "sg:city":"Greene",
    "sg:classifiers":[
        {
            "category":"Personal",
            "subcategory":"Beauty Salon",
            "type":"Services"
        }
    ],
    "sg:phone":"+1 607 656 7080",
    "sg:postcode":"13778",
    "sg:province":"NY",
    "wof:name":"Darlene's Hair & Tanning",
    "wof:placetype":"venue"
},
  "geometry": {"coordinates":[-75.72536100000001,42.319396],"type":"Point"}
}