{
  "type": "Feature",
  "properties": {
    "iso:country":"US",
    "sg:address":"340 Hewlett Pkwy",
    "sg:city":"Hewlett",
    "sg:classifiers":[
        {
            "category":"Building & Trades",
            "subcategory":"Construction",
            "type":"Services"
        }
    ],
    "sg:phone":"+1 516 374 0624",
    "sg:postcode":"11557",
    "sg:province":"NY",
    "sg:tags":[
        "contractor"
    ],
    "wof:name":"Natans Contracting Corp",
    "wof:placetype":"venue"
},
  "geometry": {"coordinates":[-73.703778,40.64005],"type":"Point"}
}