{
  "type": "Feature",
  "properties": {
    "addr:full":"1589 2nd Ave Frnt New York NY 10028",
    "addr:housenumber":"1589",
    "addr:postcode":"10028",
    "addr:street":"2Nd Ave",
    "iso:country":"US",
    "sg:address":"1589 2nd Ave Frnt",
    "sg:city":"New York",
    "sg:classifiers":[
        {
            "category":"Restaurant",
            "type":"Food & Drink"
        }
    ],
    "sg:phone":"+1 212 517 4448",
    "sg:postcode":"10028",
    "sg:province":"NY",
    "sg:tags":[
        "kosher",
        "italian"
    ],
    "sg:website":"www.vabenenyc.com/",
    "wof:name":"Va Bene Italian Kosher Restaurant",
    "wof:placetype":"venue"
},
  "geometry": {"coordinates":[-73.953598,40.775501],"type":"Point"}
}