{
  "type": "Feature",
  "properties": {
    "addr:full":"461 Railroad Ave Westbury NY 11590",
    "addr:housenumber":"461",
    "addr:postcode":"11590",
    "addr:street":"Railroad Ave",
    "iso:country":"US",
    "sg:address":"461 Railroad Ave",
    "sg:city":"Westbury",
    "sg:classifiers":[
        {
            "category":"Wholesale",
            "subcategory":"Groceries",
            "type":"Manufacturing & Wholesale Goods"
        }
    ],
    "sg:phone":"+1 631 543 8540",
    "sg:postcode":"11590",
    "sg:province":"NY",
    "sg:tags":[
        "food",
        "distributor"
    ],
    "wof:name":"Creative Food Distribution",
    "wof:placetype":"venue"
},
  "geometry": {"coordinates":[-73.586541,40.752722],"type":"Point"}
}