{
  "type": "Feature",
  "properties": {
    "iso:country":"US",
    "sg:address":"33 Peuquet Pkwy",
    "sg:city":"Tonawanda",
    "sg:classifiers":[
        {
            "category":"Freight",
            "type":"Transportation"
        }
    ],
    "sg:phone":"+1 716 693 5077",
    "sg:postcode":"14150",
    "sg:province":"NY",
    "sg:tags":[
        "commercial",
        "storage"
    ],
    "wof:name":"Mini Storage",
    "wof:placetype":"venue"
},
  "geometry": {"coordinates":[-78.865858,43.014971],"type":"Point"}
}