{
  "type": "Feature",
  "properties": {
    "addr:full":"274 E 10th St New York NY 10009",
    "addr:housenumber":"274",
    "addr:postcode":"10009",
    "addr:street":"E 10Th St",
    "iso:country":"US",
    "sg:address":"274 E 10th St",
    "sg:city":"New York",
    "sg:classifiers":[
        {
            "category":"Building & Trades",
            "subcategory":"Construction",
            "type":"Services"
        }
    ],
    "sg:phone":"+1 646 486 1652",
    "sg:postcode":"10009",
    "sg:province":"NY",
    "sg:tags":[
        "contractor"
    ],
    "wof:name":"Bullfighter Construction",
    "wof:placetype":"venue"
},
  "geometry": {"coordinates":[-73.983355,40.728066],"type":"Point"}
}