{
  "type": "Feature",
  "properties": {
    "iso:country":"US",
    "sg:address":"4685 Ide Rd",
    "sg:city":"Wilson",
    "sg:classifiers":[
        {
            "category":"Freight",
            "type":"Transportation"
        }
    ],
    "sg:phone":"+1   ",
    "sg:postcode":"14172",
    "sg:province":"NY",
    "sg:tags":[
        "operator",
        "local",
        "trucking"
    ],
    "wof:name":"Vosburgh Trucking",
    "wof:placetype":"venue"
},
  "geometry": {"coordinates":[-78.79337099999999,43.28744],"type":"Point"}
}