{
  "type": "Feature",
  "properties": {
    "iso:country":"US",
    "sg:address":"30 E Main St",
    "sg:city":"Walden",
    "sg:classifiers":[
        {
            "category":"Health Services",
            "subcategory":"Podiatrist",
            "type":"Services"
        }
    ],
    "sg:phone":"+1   ",
    "sg:postcode":"12586",
    "sg:province":"NY",
    "wof:name":"Dr Bojsiuk  Stefan",
    "wof:placetype":"venue"
},
  "geometry": {"coordinates":[-74.186351,41.560783],"type":"Point"}
}