{
  "type": "Feature",
  "properties": {
    "iso:country":"US",
    "sg:address":"460 Nostrand Avenue",
    "sg:city":"Brooklyn",
    "sg:classifiers":[
        {
            "category":"Building & Trades",
            "subcategory":"Pest Control",
            "type":"Services"
        }
    ],
    "sg:phone":"+1 718 469 9474",
    "sg:postcode":"11216",
    "sg:province":"NY",
    "wof:name":"Hibbert Calvin Exterminating Company",
    "wof:placetype":"venue"
},
  "geometry": {"coordinates":[-73.95021,40.683371],"type":"Point"}
}