{
  "type": "Feature",
  "properties": {
    "addr:full":"Sacndga Rd Schenectady NY 12302",
    "addr:postcode":"12302",
    "addr:street":"Sacndga Rd",
    "iso:country":"US",
    "sg:address":"Sacndga Rd",
    "sg:city":"Schenectady",
    "sg:classifiers":[
        {
            "category":"Retail",
            "subcategory":"Funeral Services",
            "type":"Services"
        }
    ],
    "sg:phone":"+1 518 370 0217",
    "sg:postcode":"12302",
    "sg:province":"NY",
    "sg:tags":[
        "cemetery"
    ],
    "wof:name":"Park Cemetery",
    "wof:placetype":"venue"
},
  "geometry": {"coordinates":[-73.949501,42.860298],"type":"Point"}
}