{
  "type": "Feature",
  "properties": {
    "iso:country":"US",
    "sg:address":"4588 Old Bath Rd",
    "sg:city":"Dundee",
    "sg:classifiers":[
        {
            "category":"Building & Trades",
            "subcategory":"Construction",
            "type":"Services"
        }
    ],
    "sg:phone":"+1 607 243 7678",
    "sg:postcode":"14527",
    "sg:province":"NY",
    "sg:tags":[
        "house"
    ],
    "wof:name":"Harvs Construction",
    "wof:placetype":"venue"
},
  "geometry": {"coordinates":[-77.05607999999999,42.54281],"type":"Point"}
}