{
  "type": "Feature",
  "properties": {
    "iso:country":"US",
    "sg:address":"36 Hudson Dr",
    "sg:city":"Stony Point",
    "sg:classifiers":[
        {
            "category":"Autos & Motor Vehicles",
            "subcategory":"Boat Sales",
            "type":"Retail Goods"
        }
    ],
    "sg:phone":"+1 845 786 8731",
    "sg:postcode":"10980",
    "sg:province":"NY",
    "sg:tags":[
        "yacht"
    ],
    "wof:name":"Seaweed Yacht Club",
    "wof:placetype":"venue"
},
  "geometry": {"coordinates":[-73.977208,41.232556],"type":"Point"}
}