{
  "type": "Feature",
  "properties": {
    "addr:full":"211 Skyview Ln New Canaan NY 06840",
    "addr:housenumber":"211",
    "addr:postcode":"06840",
    "addr:street":"Skyview Ln",
    "iso:country":"US",
    "sg:address":"211 Skyview Ln",
    "sg:city":"New Canaan",
    "sg:classifiers":[
        {
            "category":"Professional",
            "subcategory":"Computer Services",
            "type":"Services"
        }
    ],
    "sg:phone":"+1   ",
    "sg:postcode":"06840",
    "sg:province":"NY",
    "sg:tags":[
        "development",
        "information",
        "management",
        "software"
    ],
    "wof:name":"Digital Multimedia LLc",
    "wof:placetype":"venue"
},
  "geometry": {"coordinates":[-73.52145299999999,41.120792],"type":"Point"}
}