{
  "type": "Feature",
  "properties": {
    "iso:country":"US",
    "sg:address":"17 N 4th St",
    "sg:city":"Hudson",
    "sg:classifiers":[
        {
            "category":"Education",
            "subcategory":"Music School",
            "type":"Public Place"
        }
    ],
    "sg:phone":"+1 518 828 1045",
    "sg:postcode":"12534",
    "sg:province":"NY",
    "sg:tags":[
        "instrument",
        "teacher",
        "musical"
    ],
    "wof:name":"Musica",
    "wof:placetype":"venue"
},
  "geometry": {"coordinates":[-73.788225,42.2517],"type":"Point"}
}