{
  "type": "Feature",
  "properties": {
    "addr:full":"81 Larkfield Rd East Northport NY 11731",
    "addr:housenumber":"81",
    "addr:postcode":"11731",
    "addr:street":"Larkfield Rd",
    "iso:country":"US",
    "sg:address":"81 Larkfield Rd",
    "sg:city":"East Northport",
    "sg:classifiers":[
        {
            "category":"Banks & Credit Unions",
            "subcategory":"Bank",
            "type":"Services"
        }
    ],
    "sg:phone":"+1 631 757 4580",
    "sg:postcode":"11731",
    "sg:province":"NY",
    "sg:tags":[
        "financing"
    ],
    "wof:name":"BLD Finance",
    "wof:placetype":"venue"
},
  "geometry": {"coordinates":[-73.32554399999999,40.87982],"type":"Point"}
}