{
  "type": "Feature",
  "properties": {
    "iso:country":"US",
    "sg:address":"1943 5th Ave",
    "sg:city":"Troy",
    "sg:classifiers":[
        {
            "category":"Insurance",
            "subcategory":"Insurance Agent",
            "type":"Services"
        }
    ],
    "sg:phone":"+1 518 274 6557",
    "sg:postcode":"12180",
    "sg:province":"NY",
    "wof:name":"Perfetti & Perfetti Insurance",
    "wof:placetype":"venue"
},
  "geometry": {"coordinates":[-73.687431,42.732939],"type":"Point"}
}