{
  "type": "Feature",
  "properties": {
    "addr:full":"200 Parkway Dr S Ste 301 Hauppauge NY 11788",
    "addr:housenumber":"200",
    "addr:postcode":"11788",
    "addr:street":"Parkway Dr S Ste 301",
    "iso:country":"US",
    "sg:address":"200 Parkway Dr S Ste 301",
    "sg:city":"Hauppauge",
    "sg:classifiers":[
        {
            "category":"Professional",
            "type":"Services"
        }
    ],
    "sg:phone":"+1 631 864 4166",
    "sg:postcode":"11788",
    "sg:province":"NY",
    "sg:tags":[
        "transportation"
    ],
    "wof:name":"Creative Logistics Inc.",
    "wof:placetype":"venue"
},
  "geometry": {"coordinates":[-73.26007799999999,40.823502],"type":"Point"}
}