{
  "type": "Feature",
  "properties": {
    "iso:country":"US",
    "sg:address":"49 Warren St",
    "sg:city":"New York",
    "sg:classifiers":[
        {
            "category":"Travel",
            "subcategory":"Hotels & Motels",
            "type":"Entertainment"
        },
        {
            "category":"Travel",
            "subcategory":"Bed & Breakfast",
            "type":"Entertainment"
        }
    ],
    "sg:phone":"+1 212 732 9666",
    "sg:postcode":"10007",
    "sg:province":"NY",
    "wof:name":"Nicolena's B And B",
    "wof:placetype":"venue"
},
  "geometry": {"coordinates":[-74.94815,40.714462],"type":"Point"}
}