{
  "type": "Feature",
  "properties": {
    "addr:full":"2350 N Forest Rd Getzville NY 14068",
    "addr:housenumber":"2350",
    "addr:postcode":"14068",
    "addr:street":"N Forest Rd",
    "iso:country":"US",
    "sg:address":"2350 N Forest Rd",
    "sg:city":"Getzville",
    "sg:classifiers":[
        {
            "category":"Banks & Credit Unions",
            "subcategory":"Investment Brokerage",
            "type":"Services"
        }
    ],
    "sg:phone":"+1 716 636 8811",
    "sg:postcode":"14068",
    "sg:province":"NY",
    "sg:tags":[
        "security"
    ],
    "wof:name":"First National Investors",
    "wof:placetype":"venue"
},
  "geometry": {"coordinates":[-78.778318,43.010229],"type":"Point"}
}