{
  "type": "Feature",
  "properties": {
    "addr:full":"2066 Story Ave Bronx NY 10473",
    "addr:housenumber":"2066",
    "addr:postcode":"10473",
    "addr:street":"Story Ave",
    "iso:country":"US",
    "sg:address":"2066 Story Ave",
    "sg:city":"Bronx",
    "sg:classifiers":[
        {
            "category":"Insurance",
            "subcategory":"Insurance Agent",
            "type":"Services"
        }
    ],
    "sg:phone":"+1 718 823 2743",
    "sg:postcode":"10473",
    "sg:province":"NY",
    "wof:name":"Reliance Insurance Agency",
    "wof:placetype":"venue"
},
  "geometry": {"coordinates":[-73.854134,40.824693],"type":"Point"}
}