{
  "type": "Feature",
  "properties": {
    "addr:full":"14 Collier Dr Carmel NY 10512",
    "addr:housenumber":"14",
    "addr:postcode":"10512",
    "addr:street":"Collier Dr",
    "iso:country":"US",
    "sg:address":"14 Collier Dr",
    "sg:city":"Carmel",
    "sg:classifiers":[
        {
            "category":"Retail",
            "subcategory":"Repair Shop",
            "type":"Services"
        }
    ],
    "sg:phone":"+1 845 255 3668",
    "sg:postcode":"10512",
    "sg:province":"NY",
    "sg:tags":[
        "television",
        "radio"
    ],
    "wof:name":"Carmel Television Svc & Repair",
    "wof:placetype":"venue"
},
  "geometry": {"coordinates":[-73.683307,41.42701],"type":"Point"}
}