{
  "type": "Feature",
  "properties": {
    "addr:full":"98 Transverse Rd Garden City NY 11530",
    "addr:housenumber":"98",
    "addr:postcode":"11530",
    "addr:street":"Transverse Rd",
    "iso:country":"US",
    "sg:address":"98 Transverse Rd",
    "sg:city":"Garden City",
    "sg:classifiers":[
        {
            "category":"Shopping",
            "subcategory":"Bicycles & Sporting Goods",
            "type":"Retail Goods"
        }
    ],
    "sg:phone":"+1   ",
    "sg:postcode":"11530",
    "sg:province":"NY",
    "wof:name":"Garden City Rifle & Pistol",
    "wof:placetype":"venue"
},
  "geometry": {"coordinates":[-73.623187,40.736738],"type":"Point"}
}