{
  "type": "Feature",
  "properties": {
    "iso:country":"US",
    "sg:address":"143 Smith Rd",
    "sg:city":"Nanuet",
    "sg:classifiers":[
        {
            "category":"Retail",
            "subcategory":"Auto Repair",
            "type":"Services"
        }
    ],
    "sg:phone":"+1   ",
    "sg:postcode":"10954",
    "sg:province":"NY",
    "sg:tags":[
        "general"
    ],
    "wof:name":"Tri Star Auto Tech Inc",
    "wof:placetype":"venue"
},
  "geometry": {"coordinates":[-74.019132,41.111946],"type":"Point"}
}