{
  "type": "Feature",
  "properties": {
    "iso:country":"US",
    "sg:address":"41 Broadway",
    "sg:city":"Greenlawn",
    "sg:classifiers":[
        {
            "category":"Building & Trades",
            "subcategory":"Construction",
            "type":"Services"
        }
    ],
    "sg:phone":"+1 631 757 6216",
    "sg:postcode":"11740",
    "sg:province":"NY",
    "sg:tags":[
        "contractor"
    ],
    "wof:name":"Pizzonia Constr",
    "wof:placetype":"venue"
},
  "geometry": {"coordinates":[-73.3657,40.871201],"type":"Point"}
}