{
  "type": "Feature",
  "properties": {
    "iso:country":"US",
    "sg:address":"272 Huntington Ave",
    "sg:city":"Buffalo",
    "sg:classifiers":[
        {
            "category":"Real Estate",
            "subcategory":"Architect",
            "type":"Services"
        }
    ],
    "sg:phone":"+1 716 833 5009",
    "sg:postcode":"14214",
    "sg:province":"NY",
    "sg:website":"www.wingfelder.com",
    "wof:name":"John W Wingfelder",
    "wof:placetype":"venue"
},
  "geometry": {"coordinates":[-78.842381,42.946145],"type":"Point"}
}