{
  "type": "Feature",
  "properties": {
    "iso:country":"US",
    "sg:address":"151 Stowe Rd",
    "sg:city":"Ogdensburg",
    "sg:phone":"+1 315 375 8950",
    "sg:postcode":"13669",
    "sg:province":"NY",
    "sg:tags":[
        "farm",
        "corn",
        "dairy"
    ],
    "wof:name":"Brooks James & Melinda",
    "wof:placetype":"venue"
},
  "geometry": {"coordinates":[-75.609343,44.593407],"type":"Point"}
}