{
  "type": "Feature",
  "properties": {
    "addr:full":"26 Cindy Ln Putnam Valley NY 10579",
    "addr:housenumber":"26",
    "addr:postcode":"10579",
    "addr:street":"Cindy Ln Putnam",
    "iso:country":"US",
    "sg:address":"26 Cindy Ln",
    "sg:city":"Putnam Valley",
    "sg:classifiers":[
        {
            "category":"Real Estate",
            "subcategory":"Real Estate Agent",
            "type":"Services"
        }
    ],
    "sg:phone":"+1 845 528 6629",
    "sg:postcode":"10579",
    "sg:province":"NY",
    "wof:name":"Drt Realty Corp",
    "wof:placetype":"venue"
},
  "geometry": {"coordinates":[-73.847965,41.341959],"type":"Point"}
}