{
  "type": "Feature",
  "properties": {
    "addr:full":"40 W 21 St New York NY 10010",
    "addr:housenumber":"40",
    "addr:postcode":"10010",
    "addr:street":"W 21 St",
    "iso:country":"US",
    "sg:address":"40 W 21 St",
    "sg:city":"New York",
    "sg:classifiers":[
        {
            "category":"Real Estate",
            "subcategory":"Real Estate Operator",
            "type":"Services"
        }
    ],
    "sg:phone":"+1 212 505 5088",
    "sg:postcode":"10010",
    "sg:province":"NY",
    "sg:tags":[
        "commercial"
    ],
    "wof:name":"First Jam Development Corp",
    "wof:placetype":"venue"
},
  "geometry": {"coordinates":[-73.99280899999999,40.741015],"type":"Point"}
}