{
  "type": "Feature",
  "properties": {
    "addr:full":"76 Balbach Dr Buffalo NY 14225",
    "addr:housenumber":"76",
    "addr:postcode":"14225",
    "addr:street":"Balbach Dr",
    "iso:country":"US",
    "sg:address":"76 Balbach Dr",
    "sg:city":"Buffalo",
    "sg:classifiers":[
        {
            "category":"Building & Trades",
            "subcategory":"Construction",
            "type":"Services"
        }
    ],
    "sg:phone":"+1 716 634 0023",
    "sg:postcode":"14225",
    "sg:province":"NY",
    "sg:tags":[
        "carpentry",
        "contractor"
    ],
    "wof:name":"Denessias Wood N Things",
    "wof:placetype":"venue"
},
  "geometry": {"coordinates":[-78.761436,42.937743],"type":"Point"}
}