{
  "type": "Feature",
  "properties": {
    "addr:full":"1932 Arthur Ave Bronx NY 10457",
    "addr:housenumber":"1932",
    "addr:postcode":"10457",
    "addr:street":"Arthur Ave",
    "iso:country":"US",
    "sg:address":"1932 Arthur Ave",
    "sg:city":"Bronx",
    "sg:classifiers":[
        {
            "category":"Government",
            "subcategory":"Office",
            "type":"Public Place"
        }
    ],
    "sg:phone":"+1 718 579 6900",
    "sg:postcode":"10457",
    "sg:province":"NY",
    "sg:tags":[
        "program",
        "administrative"
    ],
    "wof:name":"Commission On Human Rights",
    "wof:placetype":"venue"
},
  "geometry": {"coordinates":[-73.893407,40.845142],"type":"Point"}
}