{
  "type": "Feature",
  "properties": {
    "addr:full":"213 Carleton Ave East Islip NY 11730",
    "addr:housenumber":"213",
    "addr:postcode":"11730",
    "addr:street":"Carleton Ave",
    "iso:country":"US",
    "sg:address":"213 Carleton Ave",
    "sg:city":"East Islip",
    "sg:classifiers":[
        {
            "category":"Restaurant",
            "type":"Food & Drink"
        }
    ],
    "sg:menulink":"http://www.allmenus.com/ny/islip/240616-gios-pizzeria/menu/",
    "sg:phone":"+1 631 581 0886",
    "sg:postcode":"11730",
    "sg:province":"NY",
    "sg:tags":[
        "american",
        "pizza"
    ],
    "wof:name":"Gio's Pizzeria",
    "wof:placetype":"venue"
},
  "geometry": {"coordinates":[-73.192498,40.74028],"type":"Point"}
}