{
  "type": "Feature",
  "properties": {
    "addr:full":"10 Norwich St Huntington Station NY 11746",
    "addr:housenumber":"10",
    "addr:postcode":"11746",
    "addr:street":"Norwich St",
    "iso:country":"US",
    "sg:address":"10 Norwich St",
    "sg:city":"Huntington Station",
    "sg:classifiers":[
        {
            "category":"Building & Trades",
            "subcategory":"Construction",
            "type":"Services"
        }
    ],
    "sg:phone":"+1 631 549 5678",
    "sg:postcode":"11746",
    "sg:province":"NY",
    "sg:tags":[
        "house",
        "contractor"
    ],
    "wof:name":"Marlina Builders Inc",
    "wof:placetype":"venue"
},
  "geometry": {"coordinates":[-73.41374,40.819287],"type":"Point"}
}