{
  "type": "Feature",
  "properties": {
    "addr:full":"15 Canal Pl Bronx NY 10451",
    "addr:housenumber":"15",
    "addr:postcode":"10451",
    "addr:street":"Canal Pl",
    "iso:country":"US",
    "sg:address":"15 Canal Pl",
    "sg:city":"Bronx",
    "sg:classifiers":[
        {
            "category":"Building & Trades",
            "subcategory":"Plumbing",
            "type":"Services"
        }
    ],
    "sg:phone":"+1 718 292 6499",
    "sg:postcode":"10451",
    "sg:province":"NY",
    "wof:name":"F Js Plumbing Incorporated",
    "wof:placetype":"venue"
},
  "geometry": {"coordinates":[-73.930504,40.810722],"type":"Point"}
}