{
  "type": "Feature",
  "properties": {
    "addr:full":"3 Marion Ave Glens Falls NY 12801",
    "addr:housenumber":"3",
    "addr:postcode":"12801",
    "addr:street":"Marion Ave",
    "iso:country":"US",
    "sg:address":"3 Marion Ave",
    "sg:city":"Glens Falls",
    "sg:classifiers":[
        {
            "category":"Organizations",
            "subcategory":"Religious Organization",
            "type":"Services"
        }
    ],
    "sg:phone":"+1   ",
    "sg:postcode":"12801",
    "sg:province":"NY",
    "wof:name":"Temple Beth El",
    "wof:placetype":"venue"
},
  "geometry": {"coordinates":[-73.65282999999999,43.313294],"type":"Point"}
}