{
  "type": "Feature",
  "properties": {
    "iso:country":"US",
    "sg:address":"18 Main St",
    "sg:city":"Warwick",
    "sg:classifiers":[
        {
            "category":"Shopping",
            "subcategory":"Gifts & Souvenirs",
            "type":"Retail Goods"
        }
    ],
    "sg:phone":"+1   ",
    "sg:postcode":"10990",
    "sg:province":"NY",
    "wof:name":"Samaya Gifts & Arts",
    "wof:placetype":"venue"
},
  "geometry": {"coordinates":[-74.356893,41.260804],"type":"Point"}
}