{
  "type": "Feature",
  "properties": {
    "addr:full":"New Plaza Beach Club 1751 Ocean Blvd Atlantic Beach NY 11509",
    "addr:housenumber":"1751",
    "addr:postcode":"11509",
    "addr:street":"Ocean Blvd",
    "iso:country":"US",
    "sg:address":"New Plaza Beach Club 1751 Ocean Blvd",
    "sg:city":"Atlantic Beach",
    "sg:classifiers":[
        {
            "category":"Bars & Pubs",
            "type":"Food & Drink"
        },
        {
            "category":"Restaurant",
            "type":"Food & Drink"
        }
    ],
    "sg:phone":"+1 516 239 2936",
    "sg:postcode":"11509",
    "sg:province":"NY",
    "sg:tags":[
        "new",
        "american"
    ],
    "sg:website":"www.newplazabeachclub.com",
    "wof:name":"The Restaurant at New Plaza",
    "wof:placetype":"venue"
},
  "geometry": {"coordinates":[-73.724917,40.586301],"type":"Point"}
}