{
  "type": "Feature",
  "properties": {
    "addr:full":"708 9th Avenue New York NY 10019",
    "addr:housenumber":"708",
    "addr:postcode":"10019",
    "addr:street":"9Th Avenue",
    "iso:country":"US",
    "sg:address":"708 9th Avenue",
    "sg:city":"New York",
    "sg:classifiers":[
        {
            "category":"Building & Trades",
            "subcategory":"Locksmith",
            "type":"Services"
        }
    ],
    "sg:phone":"+1 212 492 9888",
    "sg:postcode":"10019",
    "sg:province":"NY",
    "sg:tags":[
        "key"
    ],
    "wof:name":"A 24 Hour Always Emergency Locksmith",
    "wof:placetype":"venue"
},
  "geometry": {"coordinates":[-73.989447,40.762789],"type":"Point"}
}