{
  "type": "Feature",
  "properties": {
    "iso:country":"US",
    "sg:address":"1850 Stuart St",
    "sg:city":"Brooklyn",
    "sg:classifiers":[
        {
            "category":"Professional",
            "subcategory":"Accounting & Tax Preparation",
            "type":"Services"
        }
    ],
    "sg:phone":"+1 212 245 4094",
    "sg:postcode":"11229",
    "sg:province":"NY",
    "sg:tags":[
        "accountant"
    ],
    "wof:name":"Robert G Weinert",
    "wof:placetype":"venue"
},
  "geometry": {"coordinates":[-73.940489,40.607919],"type":"Point"}
}