{
  "type": "Feature",
  "properties": {
    "addr:full":"1241 State St Schenectady NY 12304",
    "addr:housenumber":"1241",
    "addr:postcode":"12304",
    "addr:street":"State St",
    "iso:country":"US",
    "sg:address":"1241 State St",
    "sg:city":"Schenectady",
    "sg:classifiers":[
        {
            "category":"Organizations",
            "subcategory":"Religious Organization",
            "type":"Services"
        }
    ],
    "sg:phone":"+1 518 346 3405",
    "sg:postcode":"12304",
    "sg:province":"NY",
    "sg:tags":[
        "church"
    ],
    "wof:name":"St Luke's Catholic Church",
    "wof:placetype":"venue"
},
  "geometry": {"coordinates":[-73.924476,42.798807],"type":"Point"}
}