{
  "type": "Feature",
  "properties": {
    "iso:country":"US",
    "sg:address":"95 Carlough Rd",
    "sg:city":"Bohemia",
    "sg:classifiers":[
        {
            "category":"Wholesale",
            "subcategory":"Hardware",
            "type":"Manufacturing & Wholesale Goods"
        }
    ],
    "sg:phone":"+1 631 218 3485",
    "sg:postcode":"11716",
    "sg:province":"NY",
    "sg:tags":[
        "fastener"
    ],
    "sg:website":"www.fastenal.com",
    "wof:name":"Fastenal Co",
    "wof:placetype":"venue"
},
  "geometry": {"coordinates":[-73.091483,40.775118],"type":"Point"}
}