{
  "type": "Feature",
  "properties": {
    "addr:full":"1330 Bristow St Bronx NY 10459",
    "addr:housenumber":"1330",
    "addr:postcode":"10459",
    "addr:street":"Bristow St",
    "iso:country":"US",
    "sg:address":"1330 Bristow St",
    "sg:city":"Bronx",
    "sg:classifiers":[
        {
            "category":"Education",
            "subcategory":"School",
            "type":"Public Place"
        }
    ],
    "sg:phone":"+1 718 589 3126",
    "sg:postcode":"10459",
    "sg:province":"NY",
    "wof:name":"Emolior Academy",
    "wof:placetype":"venue"
},
  "geometry": {"coordinates":[-73.89459600000001,40.831328],"type":"Point"}
}