{
  "type": "Feature",
  "properties": {
    "addr:full":"698 Central Ave Brooklyn NY 11207",
    "addr:housenumber":"698",
    "addr:postcode":"11207",
    "addr:street":"Central Ave",
    "iso:country":"US",
    "sg:address":"698 Central Ave",
    "sg:city":"Brooklyn",
    "sg:classifiers":[
        {
            "category":"Manufacturing",
            "subcategory":"Metals",
            "type":"Manufacturing & Wholesale Goods"
        }
    ],
    "sg:phone":"+1 718 919 4343",
    "sg:postcode":"11207",
    "sg:province":"NY",
    "wof:name":"Custom Metal Crafters Inc",
    "wof:placetype":"venue"
},
  "geometry": {"coordinates":[-73.906486,40.687461],"type":"Point"}
}