{
  "type": "Feature",
  "properties": {
    "addr:full":"6581 Hylan Boulevard Staten Island NY 10309",
    "addr:housenumber":"6581",
    "addr:postcode":"10309",
    "addr:street":"Hylan Boulevard",
    "iso:country":"US",
    "sg:address":"6581 Hylan Boulevard",
    "sg:city":"Staten Island",
    "sg:classifiers":[
        {
            "category":"Education",
            "subcategory":"School",
            "type":"Public Place"
        }
    ],
    "sg:phone":"+1 718 227 2854",
    "sg:postcode":"10309",
    "sg:province":"NY",
    "sg:tags":[
        "high",
        "middle",
        "elementary"
    ],
    "wof:name":"N Y City of",
    "wof:placetype":"venue"
},
  "geometry": {"coordinates":[-74.222596,40.508617],"type":"Point"}
}