{
  "type": "Feature",
  "properties": {
    "addr:full":"470 Wheeler Rd Hauppauge NY 11788",
    "addr:housenumber":"470",
    "addr:postcode":"11788",
    "addr:street":"Wheeler Rd",
    "iso:country":"US",
    "sg:address":"470 Wheeler Rd",
    "sg:city":"Hauppauge",
    "sg:classifiers":[
        {
            "category":"Bars & Pubs",
            "type":"Food & Drink"
        },
        {
            "category":"Restaurant",
            "type":"Food & Drink"
        }
    ],
    "sg:phone":"+1 631 761 5602",
    "sg:postcode":"11788",
    "sg:province":"NY",
    "sg:tags":[
        "tapa",
        "new",
        "american"
    ],
    "sg:website":"venue56.com/",
    "wof:name":"Venue 56",
    "wof:placetype":"venue"
},
  "geometry": {"coordinates":[-73.219093,40.813259],"type":"Point"}
}