{
  "type": "Feature",
  "properties": {
    "iso:country":"US",
    "sg:address":"21 Borthwick Ave",
    "sg:city":"Delmar",
    "sg:classifiers":[
        {
            "category":"Social Services",
            "subcategory":"Child Care",
            "type":"Services"
        }
    ],
    "sg:phone":"+1   ",
    "sg:postcode":"12054",
    "sg:province":"NY",
    "sg:tags":[
        "day"
    ],
    "wof:name":"Donovan/Mitchell Day Care",
    "wof:placetype":"venue"
},
  "geometry": {"coordinates":[-73.840334,42.619841],"type":"Point"}
}