{
  "type": "Feature",
  "properties": {
    "addr:full":"130 Toledo St Farmingdale NY 11735",
    "addr:housenumber":"130",
    "addr:postcode":"11735",
    "addr:street":"Toledo St",
    "iso:country":"US",
    "sg:address":"130 Toledo St",
    "sg:city":"Farmingdale",
    "sg:classifiers":[
        {
            "category":"Manufacturing",
            "subcategory":"Tools & Machinery",
            "type":"Manufacturing & Wholesale Goods"
        }
    ],
    "sg:phone":"+1   ",
    "sg:postcode":"11735",
    "sg:province":"NY",
    "sg:tags":[
        "die",
        "machining",
        "precision",
        "contract"
    ],
    "wof:name":"Z-Works Inc",
    "wof:placetype":"venue"
},
  "geometry": {"coordinates":[-73.41722900000001,40.712158],"type":"Point"}
}