{
  "type": "Feature",
  "properties": {
    "iso:country":"US",
    "sg:address":"20 W 47 St",
    "sg:city":"New York",
    "sg:classifiers":[
        {
            "category":"Manufacturing",
            "subcategory":"Jewelry",
            "type":"Manufacturing & Wholesale Goods"
        },
        {
            "category":"Wholesale",
            "subcategory":"Metals & Minerals",
            "type":"Manufacturing & Wholesale Goods"
        }
    ],
    "sg:phone":"+1 212 575 4646",
    "sg:postcode":"10036",
    "sg:province":"NY",
    "sg:tags":[
        "refiner"
    ],
    "wof:name":"Max Kahan Inc",
    "wof:placetype":"venue"
},
  "geometry": {"coordinates":[-73.98137199999999,40.757699],"type":"Point"}
}