{
  "type": "Feature",
  "properties": {
    "addr:full":"331 Rockaway Tpke Lawrence NY 11559",
    "addr:housenumber":"331",
    "addr:postcode":"11559",
    "addr:street":"Rockaway Tpke",
    "iso:country":"US",
    "sg:address":"331 Rockaway Tpke",
    "sg:city":"Lawrence",
    "sg:classifiers":[
        {
            "category":"Restaurant",
            "type":"Food & Drink"
        }
    ],
    "sg:phone":"+1   ",
    "sg:postcode":"11559",
    "sg:province":"NY",
    "sg:tags":[
        "eating"
    ],
    "wof:name":"Wendys",
    "wof:placetype":"venue"
},
  "geometry": {"coordinates":[-73.734239,40.622449],"type":"Point"}
}