{
  "type": "Feature",
  "properties": {
    "addr:full":"5808 Mosholu Ave Bronx NY 10471",
    "addr:housenumber":"5808",
    "addr:postcode":"10471",
    "addr:street":"Mosholu Ave",
    "iso:country":"US",
    "sg:address":"5808 Mosholu Ave",
    "sg:city":"Bronx",
    "sg:classifiers":[
        {
            "category":"Professional",
            "type":"Services"
        }
    ],
    "sg:phone":"+1 718 601 3299",
    "sg:postcode":"10471",
    "sg:province":"NY",
    "sg:tags":[
        "establishment"
    ],
    "wof:name":"Approvals Plus Inc",
    "wof:placetype":"venue"
},
  "geometry": {"coordinates":[-73.897345,40.905227],"type":"Point"}
}