{
  "type": "Feature",
  "properties": {
    "iso:country":"US",
    "sg:address":"122 Prospect St",
    "sg:city":"Attica",
    "sg:classifiers":[
        {
            "category":"Government",
            "subcategory":"Office",
            "type":"Public Place"
        }
    ],
    "sg:phone":"+1 585 591 2595",
    "sg:postcode":"14011",
    "sg:province":"NY",
    "sg:tags":[
        "village"
    ],
    "wof:name":"Attica Waste Water Plant",
    "wof:placetype":"venue"
},
  "geometry": {"coordinates":[-78.277806,42.868349],"type":"Point"}
}