{
  "type": "Feature",
  "properties": {
    "iso:country":"US",
    "sg:address":"7353 State Hwy 96",
    "sg:city":"Victor",
    "sg:classifiers":[
        {
            "category":"Wholesale",
            "subcategory":"Electrical",
            "type":"Manufacturing & Wholesale Goods"
        }
    ],
    "sg:phone":"+1 585 924 9101",
    "sg:postcode":"14564",
    "sg:province":"NY",
    "sg:tags":[
        "parts",
        "representative",
        "manufacturer"
    ],
    "wof:name":"T-Squared Electronics Co Inc",
    "wof:placetype":"venue"
},
  "geometry": {"coordinates":[-77.44417799999999,43.009308],"type":"Point"}
}