{
  "type": "Feature",
  "properties": {
    "addr:full":"3252 Harlem Rd Buffalo NY 14225",
    "addr:housenumber":"3252",
    "addr:postcode":"14225",
    "addr:street":"Harlem Rd",
    "iso:country":"US",
    "sg:address":"3252 Harlem Rd",
    "sg:city":"Buffalo",
    "sg:classifiers":[
        {
            "category":"Restaurant",
            "type":"Food & Drink"
        }
    ],
    "sg:phone":"+1 716 332 3700",
    "sg:postcode":"14225",
    "sg:province":"NY",
    "sg:tags":[
        "pizza"
    ],
    "sg:website":"www.justpizzausa.com",
    "wof:name":"Just Pizza",
    "wof:placetype":"venue"
},
  "geometry": {"coordinates":[-78.784177,42.932587],"type":"Point"}
}