{
  "type": "Feature",
  "properties": {
    "addr:full":"625 Bryant Ave Roslyn NY 11576",
    "addr:housenumber":"625",
    "addr:postcode":"11576",
    "addr:street":"Bryant Ave",
    "iso:country":"US",
    "sg:address":"625 Bryant Ave",
    "sg:city":"Roslyn",
    "sg:classifiers":[
        {
            "category":"Insurance",
            "subcategory":"Insurance Agent",
            "type":"Services"
        }
    ],
    "sg:phone":"+1 516 484 1292",
    "sg:postcode":"11576",
    "sg:province":"NY",
    "wof:name":"Tsui Moo Kit",
    "wof:placetype":"venue"
},
  "geometry": {"coordinates":[-73.638673,40.816523],"type":"Point"}
}