{
  "type": "Feature",
  "properties": {
    "iso:country":"US",
    "sg:address":"630 Hoosick Rd",
    "sg:city":"Troy",
    "sg:classifiers":[
        {
            "category":"Retail",
            "subcategory":"Auto Repair",
            "type":"Services"
        }
    ],
    "sg:phone":"+1   ",
    "sg:postcode":"12180",
    "sg:province":"NY",
    "sg:tags":[
        "body"
    ],
    "wof:name":"Nazs Body Shop Inc",
    "wof:placetype":"venue"
},
  "geometry": {"coordinates":[-73.645921,42.743338],"type":"Point"}
}