{
  "type": "Feature",
  "properties": {
    "addr:full":"2623 Main Rd East Pembroke NY 14036",
    "addr:housenumber":"2623",
    "addr:postcode":"14036",
    "addr:street":"Main Rd East",
    "iso:country":"US",
    "sg:address":"2623 Main Rd",
    "sg:city":"East Pembroke",
    "sg:classifiers":[
        {
            "category":"Government",
            "subcategory":"Fire Station",
            "type":"Public Place"
        }
    ],
    "sg:phone":"+1 585 762 9044",
    "sg:postcode":"14036",
    "sg:province":"NY",
    "sg:tags":[
        "protection"
    ],
    "wof:name":"Fire Department",
    "wof:placetype":"venue"
},
  "geometry": {"coordinates":[-78.396608,42.961782],"type":"Point"}
}