{
  "type": "Feature",
  "properties": {
    "iso:country":"US",
    "sg:address":"36 Rockwood Ave",
    "sg:city":"Port Washington",
    "sg:classifiers":[
        {
            "category":"Education",
            "subcategory":"School",
            "type":"Public Place"
        }
    ],
    "sg:phone":"+1 516 767 4446",
    "sg:postcode":"11050",
    "sg:province":"NY",
    "sg:tags":[
        "elementary"
    ],
    "sg:website":"www.portnet.k12.ny.us",
    "wof:name":"Daly Elementary School",
    "wof:placetype":"venue"
},
  "geometry": {"coordinates":[-73.69274299999999,40.84844],"type":"Point"}
}