{
  "type": "Feature",
  "properties": {
    "iso:country":"US",
    "sg:address":"6 James St",
    "sg:city":"East Rockaway",
    "sg:classifiers":[
        {
            "category":"Government",
            "subcategory":"Police Station",
            "type":"Public Place"
        }
    ],
    "sg:phone":"+1 516 887 6319",
    "sg:postcode":"11518",
    "sg:province":"NY",
    "sg:tags":[
        "department"
    ],
    "wof:name":"East Rockaway Police Dept",
    "wof:placetype":"venue"
},
  "geometry": {"coordinates":[-73.65804799999999,40.635207],"type":"Point"}
}