{
  "type": "Feature",
  "properties": {
    "addr:full":"3313 108th St Corona NY 11368",
    "addr:housenumber":"3313",
    "addr:postcode":"11368",
    "addr:street":"108Th St",
    "iso:country":"US",
    "sg:address":"3313 108th St",
    "sg:city":"Corona",
    "sg:classifiers":[
        {
            "category":"Restaurant",
            "type":"Food & Drink"
        }
    ],
    "sg:menulink":"http://www.allmenus.com/ny/queens/114588-polancos-restaurant/menu/",
    "sg:phone":"+1 718 565 9598",
    "sg:postcode":"11368",
    "sg:province":"NY",
    "sg:tags":[
        "dominican"
    ],
    "wof:name":"Polanco's Restaurant",
    "wof:placetype":"venue"
},
  "geometry": {"coordinates":[-73.86095899999999,40.757594],"type":"Point"}
}