{
  "type": "Feature",
  "properties": {
    "addr:full":"3300 W Henrietta Rd Rochester NY 14623",
    "addr:housenumber":"3300",
    "addr:postcode":"14623",
    "addr:street":"W Henrietta Rd",
    "iso:country":"US",
    "sg:address":"3300 W Henrietta Rd",
    "sg:city":"Rochester",
    "sg:classifiers":[
        {
            "category":"Home & Garden",
            "subcategory":"Home Furnishings",
            "type":"Retail Goods"
        },
        {
            "category":"Home & Garden",
            "subcategory":"Carpets & Floor Coverings",
            "type":"Retail Goods"
        }
    ],
    "sg:phone":"+1 585 424 3779",
    "sg:postcode":"14623",
    "sg:province":"NY",
    "sg:tags":[
        "bedding",
        "mattress"
    ],
    "sg:website":"http://www.sleepcitynewyork.com",
    "wof:name":"Sleep City USA Inc",
    "wof:placetype":"venue"
},
  "geometry": {"coordinates":[-77.636848,43.087009],"type":"Point"}
}