{
  "type": "Feature",
  "properties": {
    "addr:full":"485 Madison Ave New York NY 10022",
    "addr:housenumber":"485",
    "addr:postcode":"10022",
    "addr:street":"Madison Ave",
    "iso:country":"US",
    "sg:address":"485 Madison Ave",
    "sg:city":"New York",
    "sg:classifiers":[
        {
            "category":"Professional",
            "subcategory":"Lawyer & Legal Services",
            "type":"Services"
        }
    ],
    "sg:phone":"+1 212 319 8500",
    "sg:postcode":"10022",
    "sg:province":"NY",
    "wof:name":"Jocelyn Keynes Atty",
    "wof:placetype":"venue"
},
  "geometry": {"coordinates":[-73.974643,40.758802],"type":"Point"}
}