{
  "type": "Feature",
  "properties": {
    "addr:full":"100 W 37th St New York NY 10018",
    "addr:housenumber":"100",
    "addr:postcode":"10018",
    "addr:street":"W 37Th St",
    "iso:country":"US",
    "sg:address":"100 W 37th St",
    "sg:city":"New York",
    "sg:classifiers":[
        {
            "category":"Retail",
            "subcategory":"Repair Shop",
            "type":"Services"
        }
    ],
    "sg:phone":"+1 917 591 2046",
    "sg:postcode":"10018",
    "sg:province":"NY",
    "sg:tags":[
        "lock",
        "key",
        "locksmith"
    ],
    "wof:name":"Ashimi Locksmith",
    "wof:placetype":"venue"
},
  "geometry": {"coordinates":[-73.987503,40.7523],"type":"Point"}
}