{
  "type": "Feature",
  "properties": {
    "addr:full":"151 Noble St Brooklyn NY 11222",
    "addr:housenumber":"151",
    "addr:postcode":"11222",
    "addr:street":"Noble St",
    "iso:country":"US",
    "sg:address":"151 Noble St",
    "sg:city":"Brooklyn",
    "sg:classifiers":[
        {
            "category":"Organizations",
            "subcategory":"Religious Organization",
            "type":"Services"
        }
    ],
    "sg:phone":"+1 718 383 8603",
    "sg:postcode":"11222",
    "sg:province":"NY",
    "sg:tags":[
        "church"
    ],
    "wof:name":"Uni0n Baptist Church",
    "wof:placetype":"venue"
},
  "geometry": {"coordinates":[-73.953799,40.728879],"type":"Point"}
}