{
  "type": "Feature",
  "properties": {
    "addr:full":"1846 Hendrickson St Brooklyn NY 11234",
    "addr:housenumber":"1846",
    "addr:postcode":"11234",
    "addr:street":"Hendrickson St",
    "iso:country":"US",
    "sg:address":"1846 Hendrickson St",
    "sg:city":"Brooklyn",
    "sg:classifiers":[
        {
            "category":"Shopping",
            "subcategory":"Hobbies, Toys, & Games",
            "type":"Retail Goods"
        }
    ],
    "sg:phone":"+1   ",
    "sg:postcode":"11234",
    "sg:province":"NY",
    "wof:name":"Tri-State Chess",
    "wof:placetype":"venue"
},
  "geometry": {"coordinates":[-73.929558,40.614886],"type":"Point"}
}