{
  "type": "Feature",
  "properties": {
    "addr:full":"188 Harvard Dr Hartsdale NY 10530",
    "addr:housenumber":"188",
    "addr:postcode":"10530",
    "addr:street":"Harvard Dr",
    "iso:country":"US",
    "sg:address":"188 Harvard Dr",
    "sg:city":"Hartsdale",
    "sg:classifiers":[
        {
            "category":"Retail",
            "subcategory":"Repair Shop",
            "type":"Services"
        }
    ],
    "sg:phone":"+1 914 946 9335",
    "sg:postcode":"10530",
    "sg:province":"NY",
    "sg:tags":[
        "repairing",
        "piano",
        "refinishing"
    ],
    "wof:name":"George Oran",
    "wof:placetype":"venue"
},
  "geometry": {"coordinates":[-73.78641,41.023405],"type":"Point"}
}