{
  "type": "Feature",
  "properties": {
    "iso:country":"US",
    "sg:address":"43 Lawrence Ave",
    "sg:city":"Inwood",
    "sg:classifiers":[
        {
            "category":"Building & Trades",
            "subcategory":"Plumbing",
            "type":"Services"
        }
    ],
    "sg:phone":"+1 516 239 7785",
    "sg:postcode":"11096",
    "sg:province":"NY",
    "sg:tags":[
        "plumber",
        "contractor"
    ],
    "wof:name":"Toad Plumbing & Heating",
    "wof:placetype":"venue"
},
  "geometry": {"coordinates":[-73.737765,40.616485],"type":"Point"}
}