{
  "type": "Feature",
  "properties": {
    "addr:full":"5601 Myrtle Ave Ridgewood NY 11385",
    "addr:housenumber":"5601",
    "addr:postcode":"11385",
    "addr:street":"Myrtle Ave",
    "iso:country":"US",
    "sg:address":"5601 Myrtle Ave",
    "sg:city":"Ridgewood",
    "sg:classifiers":[
        {
            "category":"Professional",
            "subcategory":"Lawyer & Legal Services",
            "type":"Services"
        }
    ],
    "sg:phone":"+1 800 215 1415",
    "sg:postcode":"11385",
    "sg:province":"NY",
    "wof:name":"Robles Edna i atty",
    "wof:placetype":"venue"
},
  "geometry": {"coordinates":[-73.906221,40.700256],"type":"Point"}
}