{
  "type": "Feature",
  "properties": {
    "addr:full":"218 Shaker Ridge Dr Schenectady NY 12309",
    "addr:housenumber":"218",
    "addr:postcode":"12309",
    "addr:street":"Shaker Ridge Dr",
    "iso:country":"US",
    "sg:address":"218 Shaker Ridge Dr",
    "sg:city":"Schenectady",
    "sg:classifiers":[
        {
            "category":"Restaurant",
            "type":"Food & Drink"
        }
    ],
    "sg:phone":"+1   ",
    "sg:postcode":"12309",
    "sg:province":"NY",
    "sg:tags":[
        "eating"
    ],
    "wof:name":"Sweetheart Cup Corp",
    "wof:placetype":"venue"
},
  "geometry": {"coordinates":[-73.82779600000001,42.758279],"type":"Point"}
}