{
  "type": "Feature",
  "properties": {
    "addr:full":"410 Park Ave New York NY 10022",
    "addr:housenumber":"410",
    "addr:postcode":"10022",
    "addr:street":"Park Ave",
    "iso:country":"US",
    "sg:address":"410 Park Ave",
    "sg:city":"New York",
    "sg:classifiers":[
        {
            "category":"Banks & Credit Unions",
            "subcategory":"Investment Brokerage",
            "type":"Services"
        }
    ],
    "sg:phone":"+1 212 688 1077",
    "sg:postcode":"10022",
    "sg:province":"NY",
    "sg:tags":[
        "investing"
    ],
    "wof:name":"Pyrford International USA",
    "wof:placetype":"venue"
},
  "geometry": {"coordinates":[-73.964996,40.7575],"type":"Point"}
}