{
  "type": "Feature",
  "properties": {
    "iso:country":"US",
    "sg:address":"12410 Townsend Rd",
    "sg:city":"Springville",
    "sg:classifiers":[
        {
            "category":"Building & Trades",
            "subcategory":"Construction",
            "type":"Services"
        }
    ],
    "sg:phone":"+1 716 592 3578",
    "sg:postcode":"14141",
    "sg:province":"NY",
    "sg:tags":[
        "excavating",
        "contractor"
    ],
    "wof:name":"E & A Excavating",
    "wof:placetype":"venue"
},
  "geometry": {"coordinates":[-78.67871599999999,42.540542],"type":"Point"}
}