{
  "type": "Feature",
  "properties": {
    "iso:country":"US",
    "sg:address":"29 Birch Ln Ofc 23D",
    "sg:city":"Oswego",
    "sg:classifiers":[
        {
            "category":"Real Estate",
            "subcategory":"Real Estate Operator",
            "type":"Services"
        }
    ],
    "sg:phone":"+1 315 343 8921",
    "sg:postcode":"13126",
    "sg:province":"NY",
    "sg:tags":[
        "apartment"
    ],
    "wof:name":"Wine Creek Apartments",
    "wof:placetype":"venue"
},
  "geometry": {"coordinates":[-76.472443,43.452976],"type":"Point"}
}