{
  "type": "Feature",
  "properties": {
    "addr:full":"128 Edgecombe Ave New York NY 10030",
    "addr:housenumber":"128",
    "addr:postcode":"10030",
    "addr:street":"Edgecombe Ave",
    "iso:country":"US",
    "sg:address":"128 Edgecombe Ave",
    "sg:city":"New York",
    "sg:classifiers":[
        {
            "category":"Retail",
            "subcategory":"Repair Shop",
            "type":"Services"
        }
    ],
    "sg:phone":"+1 212 518 2112",
    "sg:postcode":"10030",
    "sg:province":"NY",
    "sg:tags":[
        "lock",
        "locksmith"
    ],
    "wof:name":"Emergency Locksmith",
    "wof:placetype":"venue"
},
  "geometry": {"coordinates":[-73.94561299999999,40.820254],"type":"Point"}
}