{
  "type": "Feature",
  "properties": {
    "addr:full":"174 Fifth Ave Ste 300 Manhattan NY 10010",
    "addr:housenumber":"174",
    "addr:postcode":"10010",
    "addr:street":"Fifth Ave Ste 300",
    "iso:country":"US",
    "sg:address":"174 Fifth Ave Ste 300",
    "sg:city":"Manhattan",
    "sg:classifiers":[
        {
            "category":"Real Estate",
            "subcategory":"Real Estate Operator",
            "type":"Services"
        }
    ],
    "sg:phone":"+1 212 924 4847",
    "sg:postcode":"10010",
    "sg:province":"NY",
    "sg:tags":[
        "apartment"
    ],
    "sg:website":"www.toshiapartments.com",
    "wof:name":"Toshi Apartments",
    "wof:placetype":"venue"
},
  "geometry": {"coordinates":[-73.990257,40.74119],"type":"Point"}
}