{
  "type": "Feature",
  "properties": {
    "addr:full":"1214 Johnson Rd Churchville NY 14428",
    "addr:housenumber":"1214",
    "addr:postcode":"14428",
    "addr:street":"Johnson Rd",
    "iso:country":"US",
    "sg:address":"1214 Johnson Rd",
    "sg:city":"Churchville",
    "sg:classifiers":[
        {
            "category":"Retail",
            "subcategory":"Laundry & Dry Cleaning",
            "type":"Services"
        }
    ],
    "sg:phone":"+1 585 494 2017",
    "sg:postcode":"14428",
    "sg:province":"NY",
    "sg:tags":[
        "chimney"
    ],
    "wof:name":"Jennifers Clean Sweep",
    "wof:placetype":"venue"
},
  "geometry": {"coordinates":[-77.917805,43.050427],"type":"Point"}
}