{
  "type": "Feature",
  "properties": {
    "addr:full":"1170 Broadway New York NY 10001",
    "addr:housenumber":"1170",
    "addr:postcode":"10001",
    "addr:street":"Broadway",
    "iso:country":"US",
    "sg:address":"1170 Broadway",
    "sg:city":"New York",
    "sg:classifiers":[
        {
            "category":"Professional",
            "subcategory":"Management & Consulting",
            "type":"Services"
        }
    ],
    "sg:phone":"+1 212 532 1408",
    "sg:postcode":"10001",
    "sg:province":"NY",
    "sg:tags":[
        "marketing",
        "consultant"
    ],
    "wof:name":"European-American Lumber Inc",
    "wof:placetype":"venue"
},
  "geometry": {"coordinates":[-73.988725,40.744773],"type":"Point"}
}