{
  "type": "Feature",
  "properties": {
    "addr:full":"60 Parrott Pl Brooklyn NY 11228",
    "addr:housenumber":"60",
    "addr:postcode":"11228",
    "addr:street":"Parrott Pl",
    "iso:country":"US",
    "sg:address":"60 Parrott Pl",
    "sg:city":"Brooklyn",
    "sg:classifiers":[
        {
            "category":"Real Estate",
            "subcategory":"Real Estate Operator",
            "type":"Services"
        }
    ],
    "sg:phone":"+1 718 745 0059",
    "sg:postcode":"11228",
    "sg:province":"NY",
    "sg:tags":[
        "building",
        "apartment"
    ],
    "wof:name":"Three M Real Estate",
    "wof:placetype":"venue"
},
  "geometry": {"coordinates":[-74.02230299999999,40.617417],"type":"Point"}
}