{
  "type": "Feature",
  "properties": {
    "iso:country":"US",
    "sg:address":"91 Montgomery St",
    "sg:city":"Rhinebeck",
    "sg:classifiers":[
        {
            "category":"Health Services",
            "subcategory":"Doctor",
            "type":"Services"
        }
    ],
    "sg:phone":"+1 845 876 7081",
    "sg:postcode":"12572",
    "sg:province":"NY",
    "sg:tags":[
        "physician",
        "surgeon",
        "medical"
    ],
    "wof:name":"Jose A Tejero MD PC",
    "wof:placetype":"venue"
},
  "geometry": {"coordinates":[-73.91318,41.932978],"type":"Point"}
}