{
  "type": "Feature",
  "properties": {
    "iso:country":"US",
    "sg:address":"2366 Adam Clayton Powell Jr Blvd",
    "sg:city":"New York",
    "sg:classifiers":[
        {
            "category":"Real Estate",
            "subcategory":"Real Estate Services",
            "type":"Services"
        }
    ],
    "sg:phone":"+1 212 491 7800",
    "sg:postcode":"10030",
    "sg:province":"NY",
    "sg:tags":[
        "management",
        "property"
    ],
    "wof:name":"Baker and Dibbell",
    "wof:placetype":"venue"
},
  "geometry": {"coordinates":[-73.942503,40.817587],"type":"Point"}
}