{
  "type": "Feature",
  "properties": {
    "iso:country":"US",
    "sg:address":"349 Bean Hill Rd",
    "sg:city":"Amsterdam",
    "sg:classifiers":[
        {
            "category":"Farming",
            "subcategory":"Dairy Farm",
            "type":"Manufacturing & Wholesale Goods"
        }
    ],
    "sg:phone":"+1 518 842 8529",
    "sg:postcode":"12010",
    "sg:province":"NY",
    "wof:name":"William R Gaugler",
    "wof:placetype":"venue"
},
  "geometry": {"coordinates":[-74.24143100000001,42.881523],"type":"Point"}
}