{
  "type": "Feature",
  "properties": {
    "iso:country":"US",
    "sg:address":"1595 Ocean Ave",
    "sg:city":"Bohemia",
    "sg:classifiers":[
        {
            "category":"Freight",
            "type":"Transportation"
        }
    ],
    "sg:phone":"+1 631 218 1922",
    "sg:postcode":"11716",
    "sg:province":"NY",
    "sg:tags":[
        "warehouse",
        "self",
        "storage"
    ],
    "wof:name":"Avanti Kitchen Bath Inc",
    "wof:placetype":"venue"
},
  "geometry": {"coordinates":[-73.120955,40.786642],"type":"Point"}
}