{
  "type": "Feature",
  "properties": {
    "addr:full":"11905 101st Ave South Richmond Hill NY 11419",
    "addr:housenumber":"11905",
    "addr:postcode":"11419",
    "addr:street":"101St Ave South",
    "iso:country":"US",
    "sg:address":"11905 101st Ave",
    "sg:city":"South Richmond Hill",
    "sg:classifiers":[
        {
            "category":"Shopping",
            "subcategory":"Mobile Phones",
            "type":"Retail Goods"
        }
    ],
    "sg:phone":"+1 718 441 0355",
    "sg:postcode":"11419",
    "sg:province":"NY",
    "wof:name":"101 Wireless Inc",
    "wof:placetype":"venue"
},
  "geometry": {"coordinates":[-73.82559999999999,40.690201],"type":"Point"}
}