{
  "type": "Feature",
  "properties": {
    "iso:country":"US",
    "sg:address":"1564 Main St E",
    "sg:city":"Rochester",
    "sg:classifiers":[
        {
            "category":"Building & Trades",
            "subcategory":"Construction",
            "type":"Services"
        }
    ],
    "sg:phone":"+1 585 288 0460",
    "sg:postcode":"14609",
    "sg:province":"NY",
    "sg:tags":[
        "home",
        "builder"
    ],
    "wof:name":"Home Sweet Home",
    "wof:placetype":"venue"
},
  "geometry": {"coordinates":[-77.56980299999999,43.160314],"type":"Point"}
}