{
  "type": "Feature",
  "properties": {
    "iso:country":"US",
    "sg:address":"4815 Avenue N",
    "sg:city":"Brooklyn",
    "sg:classifiers":[
        {
            "category":"Professional",
            "subcategory":"Employment Agencies",
            "type":"Services"
        }
    ],
    "sg:phone":"+1 718 209 6286",
    "sg:postcode":"11234",
    "sg:province":"NY",
    "sg:tags":[
        "help",
        "supply"
    ],
    "wof:name":"Wisdom Staffing Inc",
    "wof:placetype":"venue"
},
  "geometry": {"coordinates":[-73.92799100000001,40.618954],"type":"Point"}
}