{
  "type": "Feature",
  "properties": {
    "addr:full":"2673 State Rte 14 Penn Yan NY 14527",
    "addr:housenumber":"2673",
    "addr:postcode":"14527",
    "addr:street":"State Rte 14",
    "iso:country":"US",
    "sg:address":"2673 State Rte 14",
    "sg:city":"Penn Yan",
    "sg:classifiers":[
        {
            "category":"Autos & Motor Vehicles",
            "subcategory":"Automobile Sales",
            "type":"Retail Goods"
        }
    ],
    "sg:phone":"+1   ",
    "sg:postcode":"14527",
    "sg:province":"NY",
    "wof:name":"Cooters",
    "wof:placetype":"venue"
},
  "geometry": {"coordinates":[-76.943777,42.633042],"type":"Point"}
}