{
  "type": "Feature",
  "properties": {
    "iso:country":"US",
    "sg:address":"1893 Ocean Avenue",
    "sg:city":"Brooklyn",
    "sg:classifiers":[
        {
            "category":"Education",
            "subcategory":"School",
            "type":"Public Place"
        }
    ],
    "sg:phone":"+1 718 258 6504",
    "sg:postcode":"11230",
    "sg:province":"NY",
    "sg:tags":[
        "high",
        "middle",
        "elementary"
    ],
    "wof:name":"Brooklyn Hebrew School For Special Children",
    "wof:placetype":"venue"
},
  "geometry": {"coordinates":[-73.953979,40.613755],"type":"Point"}
}