{
  "type": "Feature",
  "properties": {
    "iso:country":"US",
    "sg:address":"307 N Franklin St",
    "sg:city":"Watkins Glen",
    "sg:classifiers":[
        {
            "category":"Shopping",
            "subcategory":"Used Merchandise",
            "type":"Retail Goods"
        }
    ],
    "sg:phone":"+1   ",
    "sg:postcode":"14891",
    "sg:province":"NY",
    "wof:name":"Putty Jug",
    "wof:placetype":"venue"
},
  "geometry": {"coordinates":[-76.873752,42.38089],"type":"Point"}
}