{
  "type": "Feature",
  "properties": {
    "iso:country":"US",
    "sg:address":"91 Pine Hollow Rd",
    "sg:city":"Oyster Bay",
    "sg:classifiers":[
        {
            "category":"Retail",
            "subcategory":"Auto Repair",
            "type":"Services"
        }
    ],
    "sg:phone":"+1 516 496 4484",
    "sg:postcode":"11771",
    "sg:province":"NY",
    "sg:tags":[
        "repairing",
        "automobile"
    ],
    "wof:name":"Park Exxon",
    "wof:placetype":"venue"
},
  "geometry": {"coordinates":[-73.534188,40.862726],"type":"Point"}
}