{
  "type": "Feature",
  "properties": {
    "iso:country":"US",
    "sg:address":"1 Hoffman St",
    "sg:city":"Poughkeepsie",
    "sg:classifiers":[
        {
            "category":"Wholesale",
            "subcategory":"Construction Materials",
            "type":"Manufacturing & Wholesale Goods"
        }
    ],
    "sg:phone":"+1 845 454 7000",
    "sg:postcode":"12601",
    "sg:province":"NY",
    "sg:tags":[
        "lumber"
    ],
    "wof:name":"A C Dutton Lumber Corp",
    "wof:placetype":"venue"
},
  "geometry": {"coordinates":[-73.937544,41.711962],"type":"Point"}
}