{
  "type": "Feature",
  "properties": {
    "addr:full":"2184 Dean St Brooklyn NY 11233",
    "addr:housenumber":"2184",
    "addr:postcode":"11233",
    "addr:street":"Dean St",
    "iso:country":"US",
    "sg:address":"2184 Dean St",
    "sg:city":"Brooklyn",
    "sg:classifiers":[
        {
            "category":"Shopping",
            "subcategory":"Clothing, Apparel, & Fashions",
            "type":"Retail Goods"
        }
    ],
    "sg:phone":"+1 347 295 9167",
    "sg:postcode":"11233",
    "sg:province":"NY",
    "sg:tags":[
        "consultant"
    ],
    "wof:name":"Perfected Apparel",
    "wof:placetype":"venue"
},
  "geometry": {"coordinates":[-73.915323,40.674996],"type":"Point"}
}