{
  "type": "Feature",
  "properties": {
    "addr:full":"3625 Broadway New York NY 10031",
    "addr:housenumber":"3625",
    "addr:postcode":"10031",
    "addr:street":"Broadway",
    "iso:country":"US",
    "sg:address":"3625 Broadway",
    "sg:city":"New York",
    "sg:classifiers":[
        {
            "category":"Food & Beverages",
            "subcategory":"Groceries & Convenience Stores",
            "type":"Retail Goods"
        }
    ],
    "sg:phone":"+1 212 283 8412",
    "sg:postcode":"10031",
    "sg:province":"NY",
    "sg:tags":[
        "grocer"
    ],
    "wof:name":"Crucey Grocery",
    "wof:placetype":"venue"
},
  "geometry": {"coordinates":[-73.948291,40.829479],"type":"Point"}
}