{
  "type": "Feature",
  "properties": {
    "addr:full":"319 Bowery New York NY 10003",
    "addr:housenumber":"319",
    "addr:postcode":"10003",
    "addr:street":"Bowery",
    "iso:country":"US",
    "sg:address":"319 Bowery",
    "sg:city":"New York",
    "sg:classifiers":[
        {
            "category":"Organizations",
            "subcategory":"Non-profit Organization",
            "type":"Services"
        }
    ],
    "sg:phone":"+1 212 228 8200",
    "sg:postcode":"10003",
    "sg:province":"NY",
    "sg:website":"www.amato.org",
    "wof:name":"Amato Opera Theatre Inc",
    "wof:placetype":"venue"
},
  "geometry": {"coordinates":[-73.992068,40.725329],"type":"Point"}
}