{
  "type": "Feature",
  "properties": {
    "iso:country":"US",
    "sg:address":"2022 Old Rte 22",
    "sg:city":"Brewster",
    "sg:classifiers":[
        {
            "category":"Banks & Credit Unions",
            "subcategory":"Investment Brokerage",
            "type":"Services"
        },
        {
            "category":"Professional",
            "subcategory":"Computer Services",
            "type":"Services"
        }
    ],
    "sg:phone":"+1 845 278 9262",
    "sg:postcode":"10509",
    "sg:province":"NY",
    "sg:tags":[
        "consultant",
        "financing",
        "related"
    ],
    "sg:website":"www.jmtconsulting.com",
    "wof:name":"JMT Consulting Group",
    "wof:placetype":"venue"
},
  "geometry": {"coordinates":[-73.58202,41.461121],"type":"Point"}
}