{
  "type": "Feature",
  "properties": {
    "iso:country":"US",
    "sg:address":"408 Balltown Rd",
    "sg:city":"Schenectady",
    "sg:classifiers":[
        {
            "category":"Home & Garden",
            "subcategory":"Furniture",
            "type":"Retail Goods"
        }
    ],
    "sg:phone":"+1 518 382 3001",
    "sg:postcode":"12304",
    "sg:province":"NY",
    "sg:tags":[
        "mattress"
    ],
    "wof:name":"Metro Mattress Inc",
    "wof:placetype":"venue"
},
  "geometry": {"coordinates":[-73.893339,42.772141],"type":"Point"}
}