{
  "type": "Feature",
  "properties": {
    "addr:full":"7 Lynn Rd Port Washington NY 11050",
    "addr:housenumber":"7",
    "addr:postcode":"11050",
    "addr:street":"Lynn Rd",
    "iso:country":"US",
    "sg:address":"7 Lynn Rd",
    "sg:city":"Port Washington",
    "sg:classifiers":[
        {
            "category":"Social Services",
            "type":"Services"
        }
    ],
    "sg:phone":"+1 516 767 2592",
    "sg:postcode":"11050",
    "sg:province":"NY",
    "sg:tags":[
        "worker"
    ],
    "wof:name":"Nancy N O'Sullivan",
    "wof:placetype":"venue"
},
  "geometry": {"coordinates":[-73.676163,40.81783],"type":"Point"}
}