{
  "type": "Feature",
  "properties": {
    "addr:full":"1 Sturges St Binghamton NY 13901",
    "addr:housenumber":"1",
    "addr:postcode":"13901",
    "addr:street":"Sturges St",
    "iso:country":"US",
    "sg:address":"1 Sturges St",
    "sg:city":"Binghamton",
    "sg:classifiers":[
        {
            "category":"Retail",
            "subcategory":"Auto Repair",
            "type":"Services"
        }
    ],
    "sg:phone":"+1 607 723 9826",
    "sg:postcode":"13901",
    "sg:province":"NY",
    "sg:tags":[
        "automotive",
        "brake",
        "general"
    ],
    "wof:name":"Marv's Auto Repair Shop",
    "wof:placetype":"venue"
},
  "geometry": {"coordinates":[-75.898753,42.116657],"type":"Point"}
}