{
  "type": "Feature",
  "properties": {
    "addr:full":"4301 21st St Long Island City NY 11101",
    "addr:housenumber":"4301",
    "addr:postcode":"11101",
    "addr:street":"21St St",
    "iso:country":"US",
    "sg:address":"4301 21st St",
    "sg:city":"Long Island City",
    "sg:classifiers":[
        {
            "category":"Retail",
            "subcategory":"Repair Shop",
            "type":"Services"
        }
    ],
    "sg:phone":"+1 718 482 7840",
    "sg:postcode":"11101",
    "sg:province":"NY",
    "sg:tags":[
        "reupholstery",
        "furniture"
    ],
    "wof:name":"Classic Pillow",
    "wof:placetype":"venue"
},
  "geometry": {"coordinates":[-73.945528,40.750538],"type":"Point"}
}