{
  "type": "Feature",
  "properties": {
    "addr:full":"311 Stockholm St Brooklyn NY 11237",
    "addr:housenumber":"311",
    "addr:postcode":"11237",
    "addr:street":"Stockholm St",
    "iso:country":"US",
    "sg:address":"311 Stockholm St",
    "sg:city":"Brooklyn",
    "sg:classifiers":[
        {
            "category":"Manufacturing",
            "subcategory":"Metals",
            "type":"Manufacturing & Wholesale Goods"
        },
        {
            "category":"Retail",
            "subcategory":"Repair Shop",
            "type":"Services"
        }
    ],
    "sg:phone":"+1 718 628 5462",
    "sg:postcode":"11237",
    "sg:province":"NY",
    "sg:tags":[
        "steel",
        "ironwork",
        "fabrication"
    ],
    "wof:name":"Sydney Iron Works Inc",
    "wof:placetype":"venue"
},
  "geometry": {"coordinates":[-73.919265,40.702962],"type":"Point"}
}