{
  "type": "Feature",
  "properties": {
    "addr:full":"515 Portland Ave Rochester NY 14605",
    "addr:housenumber":"515",
    "addr:postcode":"14605",
    "addr:street":"Portland Ave",
    "iso:country":"US",
    "sg:address":"515 Portland Ave",
    "sg:city":"Rochester",
    "sg:classifiers":[
        {
            "category":"Shopping",
            "type":"Retail Goods"
        }
    ],
    "sg:phone":"+1 585 467 8212",
    "sg:postcode":"14605",
    "sg:province":"NY",
    "sg:tags":[
        "cosmetic",
        "perfume"
    ],
    "wof:name":"Harlem 125 Beauty Supplies",
    "wof:placetype":"venue"
},
  "geometry": {"coordinates":[-77.59157399999999,43.174943],"type":"Point"}
}