{
  "type": "Feature",
  "properties": {
    "iso:country":"US",
    "sg:address":"5 Spencer Pl",
    "sg:city":"Ossining",
    "sg:classifiers":[
        {
            "category":"Professional",
            "subcategory":"Management & Consulting",
            "type":"Services"
        }
    ],
    "sg:phone":"+1   ",
    "sg:postcode":"10562",
    "sg:province":"NY",
    "sg:tags":[
        "public",
        "relations"
    ],
    "wof:name":"Locke Associates Inc",
    "wof:placetype":"venue"
},
  "geometry": {"coordinates":[-73.845617,41.170407],"type":"Point"}
}