{
  "type": "Feature",
  "properties": {
    "addr:full":"54 Kings Hwy Orangeburg NY 10962",
    "addr:housenumber":"54",
    "addr:postcode":"10962",
    "addr:street":"Kings Hwy",
    "iso:country":"US",
    "sg:address":"54 Kings Hwy",
    "sg:city":"Orangeburg",
    "sg:classifiers":[
        {
            "category":"Building & Trades",
            "subcategory":"Plumbing",
            "type":"Services"
        }
    ],
    "sg:phone":"+1 845 359 0296",
    "sg:postcode":"10962",
    "sg:province":"NY",
    "wof:name":"Bob Romano & Son Plumbing & Heating Inc",
    "wof:placetype":"venue"
},
  "geometry": {"coordinates":[-73.941413,41.535922],"type":"Point"}
}