{
  "type": "Feature",
  "properties": {
    "iso:country":"US",
    "sg:address":"71 Upper Station Rd",
    "sg:city":"Garrison",
    "sg:classifiers":[
        {
            "category":"Government",
            "subcategory":"Fire Station",
            "type":"Public Place"
        }
    ],
    "sg:phone":"+1 845 424 3709",
    "sg:postcode":"10524",
    "sg:province":"NY",
    "sg:tags":[
        "protection"
    ],
    "wof:name":"Garrison Volunteer Fire Co",
    "wof:placetype":"venue"
},
  "geometry": {"coordinates":[-73.942584,41.381261],"type":"Point"}
}