{
  "type": "Feature",
  "properties": {
    "iso:country":"US",
    "sg:address":"82 Washington Sq E",
    "sg:city":"New York",
    "sg:classifiers":[
        {
            "category":"Shopping",
            "subcategory":"Musical Instruments",
            "type":"Retail Goods"
        }
    ],
    "sg:phone":"+1 212 998 5151",
    "sg:postcode":"10003",
    "sg:province":"NY",
    "sg:tags":[
        "music",
        "dealer"
    ],
    "wof:name":"Nordoff-Robbins Music Therapy",
    "wof:placetype":"venue"
},
  "geometry": {"coordinates":[-73.996318,40.729894],"type":"Point"}
}