{
  "type": "Feature",
  "properties": {
    "addr:full":"325 Clock Tower Commons Dr Brewster NY 10509",
    "addr:housenumber":"325",
    "addr:postcode":"10509",
    "addr:street":"Clock;Commons Dr",
    "iso:country":"US",
    "sg:address":"325 Clock Tower Commons Dr",
    "sg:city":"Brewster",
    "sg:classifiers":[
        {
            "category":"Professional",
            "subcategory":"Lawyer & Legal Services",
            "type":"Services"
        }
    ],
    "sg:phone":"+1 845 279 5366",
    "sg:postcode":"10509",
    "sg:province":"NY",
    "sg:tags":[
        "attorney"
    ],
    "wof:name":"Brennan & Ponnambalam",
    "wof:placetype":"venue"
},
  "geometry": {"coordinates":[-73.573362,41.420372],"type":"Point"}
}