{
  "type": "Feature",
  "properties": {
    "addr:full":"65 Everett Rd Albany NY 12205",
    "addr:housenumber":"65",
    "addr:postcode":"12205",
    "addr:street":"Everett Rd",
    "iso:country":"US",
    "sg:address":"65 Everett Rd",
    "sg:city":"Albany",
    "sg:phone":"+1 518 482 5406",
    "sg:postcode":"12205",
    "sg:province":"NY",
    "sg:tags":[
        "farm",
        "ornamental",
        "nursery"
    ],
    "wof:name":"Krug Farms",
    "wof:placetype":"venue"
},
  "geometry": {"coordinates":[-73.77722199999999,42.691589],"type":"Point"}
}