{
  "type": "Feature",
  "properties": {
    "iso:country":"US",
    "sg:address":"1005 Glen Cove Ave",
    "sg:city":"Glen Head",
    "sg:classifiers":[
        {
            "category":"Local Transit",
            "type":"Transportation"
        }
    ],
    "sg:phone":"+1 516 609 8400",
    "sg:postcode":"11545",
    "sg:province":"NY",
    "sg:tags":[
        "interior",
        "design"
    ],
    "sg:website":"www.sterlingdecor.com",
    "wof:name":"Sterling Decor Concepts",
    "wof:placetype":"venue"
},
  "geometry": {"coordinates":[-73.626701,40.823002],"type":"Point"}
}