{
  "type": "Feature",
  "properties": {
    "addr:full":"80 8th Ave Ste 1605 New York NY 10011",
    "addr:housenumber":"80",
    "addr:postcode":"1605;10011",
    "addr:street":"8Th Ave Ste",
    "iso:country":"US",
    "sg:address":"80 8th Ave Ste 1605",
    "sg:city":"New York",
    "sg:classifiers":[
        {
            "category":"Health Services",
            "subcategory":"Clinic",
            "type":"Services"
        }
    ],
    "sg:phone":"+1 212 337 3565",
    "sg:postcode":"10011",
    "sg:province":"NY",
    "sg:tags":[
        "counseling",
        "mental"
    ],
    "sg:website":"www.courtneyrennicke.com",
    "wof:name":"Courtney Rennicke, Ph.D.",
    "wof:placetype":"venue"
},
  "geometry": {"coordinates":[-74.00236099999999,40.739754],"type":"Point"}
}