{
  "type": "Feature",
  "properties": {
    "iso:country":"US",
    "sg:address":"1431 Fulton St",
    "sg:city":"Brooklyn",
    "sg:classifiers":[
        {
            "category":"Shopping",
            "subcategory":"Computers & Home Electronics",
            "type":"Retail Goods"
        }
    ],
    "sg:phone":"+1 718 622 5770",
    "sg:postcode":"11216",
    "sg:province":"NY",
    "sg:tags":[
        "equipment",
        "electronic",
        "supply"
    ],
    "wof:name":"Fulton Electronics & Appl Inc",
    "wof:placetype":"venue"
},
  "geometry": {"coordinates":[-73.94326100000001,40.680051],"type":"Point"}
}