{
  "type": "Feature",
  "properties": {
    "addr:full":"600 Old Country Rd Garden City NY 11530",
    "addr:housenumber":"600",
    "addr:postcode":"11530",
    "addr:street":"Old Country Rd",
    "iso:country":"US",
    "sg:address":"600 Old Country Rd",
    "sg:city":"Garden City",
    "sg:classifiers":[
        {
            "category":"Banks & Credit Unions",
            "subcategory":"Bank",
            "type":"Services"
        }
    ],
    "sg:phone":"+1 516 228 8508",
    "sg:postcode":"11530",
    "sg:province":"NY",
    "wof:name":"Citibank N A",
    "wof:placetype":"venue"
},
  "geometry": {"coordinates":[-73.6241,40.741699],"type":"Point"}
}