{
  "type": "Feature",
  "properties": {
    "addr:full":"662 Commander Ave West Babylon NY 11704",
    "addr:housenumber":"662",
    "addr:postcode":"11704",
    "addr:street":"Commander Ave",
    "iso:country":"US",
    "sg:address":"662 Commander Ave",
    "sg:city":"West Babylon",
    "sg:classifiers":[
        {
            "category":"Building & Trades",
            "subcategory":"Construction",
            "type":"Services"
        }
    ],
    "sg:phone":"+1 631 643 9276",
    "sg:postcode":"11704",
    "sg:province":"NY",
    "sg:tags":[
        "contractor"
    ],
    "wof:name":"F J W Inc",
    "wof:placetype":"venue"
},
  "geometry": {"coordinates":[-73.37042599999999,40.731344],"type":"Point"}
}