{
  "type": "Feature",
  "properties": {
    "iso:country":"US",
    "sg:address":"31 Park St",
    "sg:city":"Whitney Point",
    "sg:classifiers":[
        {
            "category":"Professional",
            "subcategory":"Art Services",
            "type":"Services"
        }
    ],
    "sg:phone":"+1   ",
    "sg:postcode":"13862",
    "sg:province":"NY",
    "sg:tags":[
        "commercial",
        "design",
        "typesetting"
    ],
    "wof:name":"Type People II",
    "wof:placetype":"venue"
},
  "geometry": {"coordinates":[-75.965486,42.324003],"type":"Point"}
}