{
  "type": "Feature",
  "properties": {
    "addr:full":"30 Clark Ave Lynbrook NY 11563",
    "addr:housenumber":"30",
    "addr:postcode":"11563",
    "addr:street":"Clark Ave",
    "iso:country":"US",
    "sg:address":"30 Clark Ave",
    "sg:city":"Lynbrook",
    "sg:classifiers":[
        {
            "category":"Education",
            "subcategory":"School",
            "type":"Public Place"
        }
    ],
    "sg:phone":"+1 516 887 0288",
    "sg:postcode":"11563",
    "sg:province":"NY",
    "sg:tags":[
        "high",
        "middle",
        "elementary"
    ],
    "wof:name":"Lynbrook Public Schools",
    "wof:placetype":"venue"
},
  "geometry": {"coordinates":[-73.67988,40.662283],"type":"Point"}
}