{
  "type": "Feature",
  "properties": {
    "iso:country":"US",
    "sg:address":"24 S Eckar St",
    "sg:city":"Irvington",
    "sg:classifiers":[
        {
            "category":"Health Services",
            "subcategory":"Doctor",
            "type":"Services"
        }
    ],
    "sg:phone":"+1 914 542 0123",
    "sg:postcode":"10533",
    "sg:province":"NY",
    "sg:tags":[
        "medical"
    ],
    "wof:name":"Jerome S Turner MD",
    "wof:placetype":"venue"
},
  "geometry": {"coordinates":[-73.86945900000001,41.038202],"type":"Point"}
}