{
  "type": "Feature",
  "properties": {
    "addr:full":"1444 Commerce Ave Bronx NY 10461",
    "addr:housenumber":"1444",
    "addr:postcode":"10461",
    "addr:street":"Commerce Ave",
    "iso:country":"US",
    "sg:address":"1444 Commerce Ave",
    "sg:city":"Bronx",
    "sg:classifiers":[
        {
            "category":"Retail",
            "subcategory":"Auto Repair",
            "type":"Services"
        }
    ],
    "sg:phone":"+1 718 904 0020",
    "sg:postcode":"10461",
    "sg:province":"NY",
    "sg:tags":[
        "body",
        "automobile",
        "painting"
    ],
    "wof:name":"American Collision Inc",
    "wof:placetype":"venue"
},
  "geometry": {"coordinates":[-73.842423,40.839217],"type":"Point"}
}