{
  "type": "Feature",
  "properties": {
    "iso:country":"US",
    "sg:address":"1017 Broadway St",
    "sg:city":"Buffalo",
    "sg:classifiers":[
        {
            "category":"Banks & Credit Unions",
            "subcategory":"Bank",
            "type":"Services"
        }
    ],
    "sg:phone":"+1 716 892 4052",
    "sg:postcode":"14212",
    "sg:province":"NY",
    "wof:name":"HSBC Bank USA N.A.",
    "wof:placetype":"venue"
},
  "geometry": {"coordinates":[-78.8369,42.893359],"type":"Point"}
}