{
  "type": "Feature",
  "properties": {
    "iso:country":"US",
    "sg:address":"23 Mill St",
    "sg:city":"Arcade",
    "sg:classifiers":[
        {
            "category":"Retail",
            "subcategory":"Repair Shop",
            "type":"Services"
        },
        {
            "category":"Wholesale",
            "subcategory":"Durable Goods & Equipment",
            "type":"Manufacturing & Wholesale Goods"
        }
    ],
    "sg:phone":"+1 585 492 1068",
    "sg:postcode":"14009",
    "sg:province":"NY",
    "sg:tags":[
        "laboratory",
        "testing",
        "supply"
    ],
    "sg:website":"www.gentechscientific.com",
    "wof:name":"Gent Tech Scientific Inc",
    "wof:placetype":"venue"
},
  "geometry": {"coordinates":[-78.42238,42.532217],"type":"Point"}
}