{
  "type": "Feature",
  "properties": {
    "addr:full":"439 E 153rd St Bronx NY 10455",
    "addr:housenumber":"439",
    "addr:postcode":"10455",
    "addr:street":"E 153Rd St",
    "iso:country":"US",
    "sg:address":"439 E 153rd St",
    "sg:city":"Bronx",
    "sg:classifiers":[
        {
            "category":"Restaurant",
            "type":"Food & Drink"
        }
    ],
    "sg:phone":"+1 718 401 3595",
    "sg:postcode":"10455",
    "sg:province":"NY",
    "wof:name":"In God We Trust African & Amer",
    "wof:placetype":"venue"
},
  "geometry": {"coordinates":[-73.915451,40.818736],"type":"Point"}
}