{
  "type": "Feature",
  "properties": {
    "addr:full":"214 W 116th St # 216 New York NY 10026",
    "addr:housenumber":"214;216",
    "addr:postcode":"10026",
    "addr:street":"W 116Th St #",
    "iso:country":"US",
    "sg:address":"214 W 116th St # 216",
    "sg:city":"New York",
    "sg:classifiers":[
        {
            "category":"Education",
            "subcategory":"School",
            "type":"Public Place"
        }
    ],
    "sg:phone":"+1 646 432 4600",
    "sg:postcode":"10026",
    "sg:province":"NY",
    "wof:name":"Cornerstone Of Rhinebeck Ny",
    "wof:placetype":"venue"
},
  "geometry": {"coordinates":[-73.95318399999999,40.80335],"type":"Point"}
}