{
  "type": "Feature",
  "properties": {
    "addr:full":"16 Orchard Ln Hopewell Junction NY 12533",
    "addr:housenumber":"16",
    "addr:postcode":"12533",
    "addr:street":"Orchard Ln",
    "iso:country":"US",
    "sg:address":"16 Orchard Ln",
    "sg:city":"Hopewell Junction",
    "sg:classifiers":[
        {
            "category":"Shopping",
            "subcategory":"Bicycles & Sporting Goods",
            "type":"Retail Goods"
        }
    ],
    "sg:phone":"+1   ",
    "sg:postcode":"12533",
    "sg:province":"NY",
    "wof:name":"Brecan Athltics Tchniques Sups",
    "wof:placetype":"venue"
},
  "geometry": {"coordinates":[-73.835742,41.591535],"type":"Point"}
}