{
  "type": "Feature",
  "properties": {
    "addr:full":"1 Washington Sq N New York NY 10003",
    "addr:housenumber":"1",
    "addr:postcode":"10003",
    "addr:street":"Washington Sq N",
    "iso:country":"US",
    "sg:address":"1 Washington Sq N",
    "sg:city":"New York",
    "sg:classifiers":[
        {
            "category":"Education",
            "subcategory":"University",
            "type":"Public Place"
        }
    ],
    "sg:phone":"+1 212 998 7040",
    "sg:postcode":"10003",
    "sg:province":"NY",
    "sg:tags":[
        "college"
    ],
    "sg:website":"www.nyu.edu",
    "wof:name":"American Language Institute of New York University",
    "wof:placetype":"venue"
},
  "geometry": {"coordinates":[-73.995598,40.730701],"type":"Point"}
}