{
  "type": "Feature",
  "properties": {
    "addr:full":"1880 Sterling Pl Brooklyn NY 11233",
    "addr:housenumber":"1880",
    "addr:postcode":"11233",
    "addr:street":"Sterling Pl",
    "iso:country":"US",
    "sg:address":"1880 Sterling Pl",
    "sg:city":"Brooklyn",
    "sg:classifiers":[
        {
            "category":"Wholesale",
            "subcategory":"Hardware",
            "type":"Manufacturing & Wholesale Goods"
        },
        {
            "category":"Wholesale",
            "subcategory":"Electrical",
            "type":"Manufacturing & Wholesale Goods"
        }
    ],
    "sg:phone":"+1 718 495 3500",
    "sg:postcode":"11233",
    "sg:province":"NY",
    "sg:tags":[
        "refrigeration",
        "refrigerating"
    ],
    "wof:name":"Elite Refrigeration Co Inc",
    "wof:placetype":"venue"
},
  "geometry": {"coordinates":[-73.91539299999999,40.670558],"type":"Point"}
}