{
  "type": "Feature",
  "properties": {
    "addr:full":"251 5th Ave New York NY 10016",
    "addr:housenumber":"251",
    "addr:postcode":"10016",
    "addr:street":"5Th Ave",
    "iso:country":"US",
    "sg:address":"251 5th Ave",
    "sg:city":"New York",
    "sg:classifiers":[
        {
            "category":"Professional",
            "subcategory":"Management & Consulting",
            "type":"Services"
        }
    ],
    "sg:phone":"+1 212 545 8600",
    "sg:postcode":"10016",
    "sg:province":"NY",
    "sg:tags":[
        "communications",
        "consultant"
    ],
    "wof:name":"Network Communications",
    "wof:placetype":"venue"
},
  "geometry": {"coordinates":[-73.986846,40.745301],"type":"Point"}
}