{
  "type": "Feature",
  "properties": {
    "iso:country":"US",
    "sg:address":"511 W 25th St",
    "sg:city":"New York",
    "sg:classifiers":[
        {
            "category":"Personal",
            "type":"Services"
        },
        {
            "category":"Retail",
            "subcategory":"Storage",
            "type":"Services"
        }
    ],
    "sg:phone":"+1 212 587 0500",
    "sg:postcode":"10001",
    "sg:province":"NY",
    "sg:tags":[
        "mover",
        "self"
    ],
    "wof:name":"Commercial Whitehall Storage",
    "wof:placetype":"venue"
},
  "geometry": {"coordinates":[-73.993599,40.748199],"type":"Point"}
}