{
  "type": "Feature",
  "properties": {
    "addr:full":"1050 2 Ave New York NY 10022",
    "addr:housenumber":"1050",
    "addr:postcode":"10022",
    "addr:street":"2 Ave",
    "iso:country":"US",
    "sg:address":"1050 2 Ave",
    "sg:city":"New York",
    "sg:classifiers":[
        {
            "category":"Shopping",
            "subcategory":"Used Merchandise",
            "type":"Retail Goods"
        }
    ],
    "sg:phone":"+1   ",
    "sg:postcode":"10022",
    "sg:province":"NY",
    "sg:tags":[
        "store"
    ],
    "wof:name":"Unique Finds Inc",
    "wof:placetype":"venue"
},
  "geometry": {"coordinates":[-73.96852,40.754877],"type":"Point"}
}