{
  "type": "Feature",
  "properties": {
    "addr:full":"137 W 37th St New York NY 10018",
    "addr:housenumber":"137",
    "addr:postcode":"10018",
    "addr:street":"W 37Th St",
    "iso:country":"US",
    "sg:address":"137 W 37th St",
    "sg:city":"New York",
    "sg:classifiers":[
        {
            "category":"Shopping",
            "subcategory":"Clothing, Apparel, & Fashions",
            "type":"Retail Goods"
        }
    ],
    "sg:phone":"+1 212 997 2332",
    "sg:postcode":"10018",
    "sg:province":"NY",
    "sg:tags":[
        "accessory",
        "clothing",
        "women's"
    ],
    "wof:name":"Maxim's Perfection In Fashion Ltd",
    "wof:placetype":"venue"
},
  "geometry": {"coordinates":[-73.988052,40.752564],"type":"Point"}
}