{
  "type": "Feature",
  "properties": {
    "addr:full":"439 Saratoga Rd Schenectady NY 12302",
    "addr:housenumber":"439",
    "addr:postcode":"12302",
    "addr:street":"Saratoga Rd",
    "iso:country":"US",
    "sg:address":"439 Saratoga Rd",
    "sg:city":"Schenectady",
    "sg:classifiers":[
        {
            "category":"Farming",
            "subcategory":"Nursery",
            "type":"Manufacturing & Wholesale Goods"
        }
    ],
    "sg:phone":"+1 518 399 1870",
    "sg:postcode":"12302",
    "sg:province":"NY",
    "sg:tags":[
        "ornamental"
    ],
    "wof:name":"McKenna Greenhouses",
    "wof:placetype":"venue"
},
  "geometry": {"coordinates":[-73.92661200000001,42.883324],"type":"Point"}
}