{
  "type": "Feature",
  "properties": {
    "addr:full":"902 Broadway New York NY 10010",
    "addr:housenumber":"902",
    "addr:postcode":"10010",
    "addr:street":"Broadway",
    "iso:country":"US",
    "sg:address":"902 Broadway",
    "sg:city":"New York",
    "sg:classifiers":[
        {
            "category":"Health Services",
            "subcategory":"Health Practitioner",
            "type":"Services"
        }
    ],
    "sg:phone":"+1 646 654 1835",
    "sg:postcode":"10010",
    "sg:province":"NY",
    "sg:tags":[
        "therapy",
        "physical"
    ],
    "sg:website":"www.recoverypt.com/Flat-Iron-Dis...",
    "wof:name":"Recovery Physical Therapy",
    "wof:placetype":"venue"
},
  "geometry": {"coordinates":[-73.989373,40.739409],"type":"Point"}
}