{
  "type": "Feature",
  "properties": {
    "addr:full":"1150 Ogden Avenue Bronx NY 10452",
    "addr:housenumber":"1150",
    "addr:postcode":"10452",
    "addr:street":"Ogden Avenue",
    "iso:country":"US",
    "sg:address":"1150 Ogden Avenue",
    "sg:city":"Bronx",
    "sg:classifiers":[
        {
            "category":"Restaurant",
            "type":"Food & Drink"
        }
    ],
    "sg:phone":"+1 718 538 9042",
    "sg:postcode":"10452",
    "sg:province":"NY",
    "wof:name":"Happy Garden",
    "wof:placetype":"venue"
},
  "geometry": {"coordinates":[-73.927263,40.836671],"type":"Point"}
}