{
  "type": "Feature",
  "properties": {
    "iso:country":"US",
    "sg:address":"86 Mangin St",
    "sg:city":"New York",
    "sg:classifiers":[
        {
            "category":"Shopping",
            "subcategory":"Antiques",
            "type":"Retail Goods"
        }
    ],
    "sg:phone":"+1 518 523 3047",
    "sg:postcode":"10002",
    "sg:province":"NY",
    "wof:name":"Log Cabin Antiques",
    "wof:placetype":"venue"
},
  "geometry": {"coordinates":[-73.976007,40.717855],"type":"Point"}
}