{
  "type": "Feature",
  "properties": {
    "addr:full":"2321 48th St Astoria NY 11103",
    "addr:housenumber":"2321",
    "addr:postcode":"11103",
    "addr:street":"48Th St",
    "iso:country":"US",
    "sg:address":"2321 48th St",
    "sg:city":"Astoria",
    "sg:classifiers":[
        {
            "category":"Building & Trades",
            "subcategory":"Plumbing",
            "type":"Services"
        }
    ],
    "sg:phone":"+1 718 777 9227",
    "sg:postcode":"11103",
    "sg:province":"NY",
    "wof:name":"Bletsas Plumbing",
    "wof:placetype":"venue"
},
  "geometry": {"coordinates":[-73.903441,40.766984],"type":"Point"}
}