{
  "type": "Feature",
  "properties": {
    "addr:full":"568 Hancock St Brooklyn NY 11233",
    "addr:housenumber":"568",
    "addr:postcode":"11233",
    "addr:street":"Hancock St",
    "iso:country":"US",
    "sg:address":"568 Hancock St",
    "sg:city":"Brooklyn",
    "sg:classifiers":[
        {
            "category":"Building & Trades",
            "subcategory":"Pest Control",
            "type":"Services"
        }
    ],
    "sg:phone":"+1 718 443 4343",
    "sg:postcode":"11233",
    "sg:province":"NY",
    "wof:name":"Exterminator Plus",
    "wof:placetype":"venue"
},
  "geometry": {"coordinates":[-73.93430600000001,40.684196],"type":"Point"}
}