{
  "type": "Feature",
  "properties": {
    "addr:full":"1727 Taylor Ave Bronx NY 10460",
    "addr:housenumber":"1727",
    "addr:postcode":"10460",
    "addr:street":"Taylor Ave",
    "iso:country":"US",
    "sg:address":"1727 Taylor Ave",
    "sg:city":"Bronx",
    "sg:classifiers":[
        {
            "category":"Food & Beverages",
            "subcategory":"Meat & Fish",
            "type":"Retail Goods"
        }
    ],
    "sg:phone":"+1   ",
    "sg:postcode":"10460",
    "sg:province":"NY",
    "wof:name":"Genova Meat Market Inc",
    "wof:placetype":"venue"
},
  "geometry": {"coordinates":[-73.870037,40.843104],"type":"Point"}
}