{
  "type": "Feature",
  "properties": {
    "iso:country":"US",
    "sg:address":"629 Scarsdale Rd",
    "sg:city":"Tuckahoe",
    "sg:classifiers":[
        {
            "category":"Building & Trades",
            "subcategory":"Construction",
            "type":"Services"
        }
    ],
    "sg:phone":"+1 914 337 1056",
    "sg:postcode":"10707",
    "sg:province":"NY",
    "sg:tags":[
        "house"
    ],
    "wof:name":"Grippo Construction",
    "wof:placetype":"venue"
},
  "geometry": {"coordinates":[-73.82292700000001,40.97258],"type":"Point"}
}