{
  "type": "Feature",
  "properties": {
    "addr:full":"4522 18th Avenue Brooklyn NY 11204",
    "addr:housenumber":"4522",
    "addr:postcode":"11204",
    "addr:street":"18Th Avenue",
    "iso:country":"US",
    "sg:address":"4522 18th Avenue",
    "sg:city":"Brooklyn",
    "sg:classifiers":[
        {
            "category":"Shopping",
            "subcategory":"Mobile Phones",
            "type":"Retail Goods"
        }
    ],
    "sg:phone":"+1 718 686 6200",
    "sg:postcode":"11204",
    "sg:province":"NY",
    "sg:website":"www.amigo-us.com",
    "wof:name":"One Hour Cellular",
    "wof:placetype":"venue"
},
  "geometry": {"coordinates":[-73.978978,40.630014],"type":"Point"}
}