{
  "type": "Feature",
  "properties": {
    "addr:full":"183 Maytime Dr Jericho NY 11753",
    "addr:housenumber":"183",
    "addr:postcode":"11753",
    "addr:street":"Maytime Dr",
    "iso:country":"US",
    "sg:address":"183 Maytime Dr",
    "sg:city":"Jericho",
    "sg:classifiers":[
        {
            "category":"Health Services",
            "subcategory":"Clinic",
            "type":"Services"
        }
    ],
    "sg:phone":"+1 516 822 3377",
    "sg:postcode":"11753",
    "sg:province":"NY",
    "sg:tags":[
        "counseling",
        "mental"
    ],
    "wof:name":"Israeli Nurit Nora Dr",
    "wof:placetype":"venue"
},
  "geometry": {"coordinates":[-73.52510100000001,40.794701],"type":"Point"}
}