{
  "type": "Feature",
  "properties": {
    "addr:full":"9 Collegeview Ave Poughkeepsie NY 12603",
    "addr:housenumber":"9",
    "addr:postcode":"12603",
    "addr:street":"Collegeview Ave",
    "iso:country":"US",
    "sg:address":"9 Collegeview Ave",
    "sg:city":"Poughkeepsie",
    "sg:classifiers":[
        {
            "category":"Personal",
            "subcategory":"Tattoo Parlor",
            "type":"Services"
        }
    ],
    "sg:phone":"+1 845 473 2789",
    "sg:postcode":"12603",
    "sg:province":"NY",
    "sg:tags":[
        "tattooing"
    ],
    "wof:name":"Absolute Ink",
    "wof:placetype":"venue"
},
  "geometry": {"coordinates":[-73.89783300000001,41.69146],"type":"Point"}
}