{
  "type": "Feature",
  "properties": {
    "iso:country":"US",
    "sg:address":"175 Jericho Tpke",
    "sg:city":"Syosset",
    "sg:classifiers":[
        {
            "category":"Restaurant",
            "type":"Food & Drink"
        }
    ],
    "sg:phone":"+1 516 496 7179",
    "sg:postcode":"11791",
    "sg:province":"NY",
    "sg:tags":[
        "shop",
        "coffee"
    ],
    "wof:name":"Sunny's Coffee Shop",
    "wof:placetype":"venue"
},
  "geometry": {"coordinates":[-73.509568,40.810105],"type":"Point"}
}