{
  "type": "Feature",
  "properties": {
    "addr:full":"4 Gannett Dr White Plains NY 10604",
    "addr:housenumber":"4",
    "addr:postcode":"10604",
    "addr:street":"Gannett Dr",
    "iso:country":"US",
    "sg:address":"4 Gannett Dr",
    "sg:city":"White Plains",
    "sg:classifiers":[
        {
            "category":"Social Services",
            "subcategory":"Child Care",
            "type":"Services"
        }
    ],
    "sg:phone":"+1   ",
    "sg:postcode":"10604",
    "sg:province":"NY",
    "sg:tags":[
        "day"
    ],
    "sg:website":"www.lccc.com",
    "wof:name":"Lipton Corporate Child Care",
    "wof:placetype":"venue"
},
  "geometry": {"coordinates":[-73.726055,41.021122],"type":"Point"}
}