{
  "type": "Feature",
  "properties": {
    "addr:full":"6560 W Main St Turin NY 13473",
    "addr:housenumber":"6560",
    "addr:postcode":"13473",
    "addr:street":"W Main St",
    "iso:country":"US",
    "sg:address":"6560 W Main St",
    "sg:city":"Turin",
    "sg:classifiers":[
        {
            "category":"Education",
            "subcategory":"Special Training",
            "type":"Public Place"
        }
    ],
    "sg:phone":"+1 315 348 4599",
    "sg:postcode":"13473",
    "sg:province":"NY",
    "sg:tags":[
        "educational"
    ],
    "wof:name":"Vocational Education Svc",
    "wof:placetype":"venue"
},
  "geometry": {"coordinates":[-75.419606,43.623009],"type":"Point"}
}