{
  "type": "Feature",
  "properties": {
    "addr:full":"3215 Netherland Ave Bronx NY 10463",
    "addr:housenumber":"3215",
    "addr:postcode":"10463",
    "addr:street":"Netherland Ave",
    "iso:country":"US",
    "sg:address":"3215 Netherland Ave",
    "sg:city":"Bronx",
    "sg:classifiers":[
        {
            "category":"Professional",
            "type":"Services"
        }
    ],
    "sg:phone":"+1 212 288 1453",
    "sg:postcode":"10463",
    "sg:province":"NY",
    "sg:tags":[
        "establishment"
    ],
    "wof:name":"Leeds F",
    "wof:placetype":"venue"
},
  "geometry": {"coordinates":[-73.911029,40.885756],"type":"Point"}
}