{
  "type": "Feature",
  "properties": {
    "iso:country":"US",
    "sg:address":"4 Cedar St",
    "sg:city":"Bronxville",
    "sg:classifiers":[
        {
            "category":"Wholesale",
            "subcategory":"Seafood",
            "type":"Manufacturing & Wholesale Goods"
        }
    ],
    "sg:phone":"+1 914 793 6907",
    "sg:postcode":"10708",
    "sg:province":"NY",
    "sg:tags":[
        "fish"
    ],
    "wof:name":"Bronxville Fish Market",
    "wof:placetype":"venue"
},
  "geometry": {"coordinates":[-73.834794,40.938473],"type":"Point"}
}