{
  "type": "Feature",
  "properties": {
    "iso:country":"US",
    "sg:address":"1804 Holland Ave",
    "sg:city":"Bronx",
    "sg:classifiers":[
        {
            "category":"Education",
            "subcategory":"School",
            "type":"Public Place"
        }
    ],
    "sg:phone":"+1 718 823 9044",
    "sg:postcode":"10462",
    "sg:province":"NY",
    "wof:name":"Our Lady of Solace Religious Ed Center",
    "wof:placetype":"venue"
},
  "geometry": {"coordinates":[-73.864378,40.845745],"type":"Point"}
}