{
  "type": "Feature",
  "properties": {
    "addr:full":"8 Shetland Ct Dix Hills NY 11746",
    "addr:housenumber":"8",
    "addr:postcode":"11746",
    "addr:street":"Shetland Ct",
    "iso:country":"US",
    "sg:address":"8 Shetland Ct",
    "sg:city":"Dix Hills",
    "sg:classifiers":[
        {
            "category":"Professional",
            "subcategory":"Employment Agencies",
            "type":"Services"
        }
    ],
    "sg:phone":"+1 631 864 2650",
    "sg:postcode":"11746",
    "sg:province":"NY",
    "sg:tags":[
        "opportunity"
    ],
    "wof:name":"Brandon Becker",
    "wof:placetype":"venue"
},
  "geometry": {"coordinates":[-73.346872,40.785559],"type":"Point"}
}