{
  "type": "Feature",
  "properties": {
    "iso:country":"US",
    "sg:address":"5394 Merrick Rd",
    "sg:city":"Massapequa",
    "sg:classifiers":[
        {
            "category":"Personal",
            "subcategory":"Beauty Salon",
            "type":"Services"
        }
    ],
    "sg:phone":"+1 516 798 4456",
    "sg:postcode":"11758",
    "sg:province":"NY",
    "wof:name":"Deana's Hair Design",
    "wof:placetype":"venue"
},
  "geometry": {"coordinates":[-73.434741,40.668711],"type":"Point"}
}