{
  "type": "Feature",
  "properties": {
    "addr:full":"501 Burnside Ave Inwood NY 11096",
    "addr:housenumber":"501",
    "addr:postcode":"11096",
    "addr:street":"Burnside Ave",
    "iso:country":"US",
    "sg:address":"501 Burnside Ave",
    "sg:city":"Inwood",
    "sg:classifiers":[
        {
            "category":"Retail",
            "subcategory":"Auto Rental",
            "type":"Services"
        }
    ],
    "sg:phone":"+1 516 239 0202",
    "sg:postcode":"11096",
    "sg:province":"NY",
    "sg:tags":[
        "renting",
        "car",
        "automobile"
    ],
    "sg:website":"www.enterprise.com",
    "wof:name":"Enterprise Rent-A Car",
    "wof:placetype":"venue"
},
  "geometry": {"coordinates":[-73.746696,40.6222],"type":"Point"}
}