{
  "type": "Feature",
  "properties": {
    "addr:full":"344 Fulton Ave Hempstead NY 11550",
    "addr:housenumber":"344",
    "addr:postcode":"11550",
    "addr:street":"Fulton Ave",
    "iso:country":"US",
    "sg:address":"344 Fulton Ave",
    "sg:city":"Hempstead",
    "sg:classifiers":[
        {
            "category":"Government",
            "subcategory":"Office",
            "type":"Public Place"
        }
    ],
    "sg:phone":"+1 516 486 3435",
    "sg:postcode":"11550",
    "sg:province":"NY",
    "sg:tags":[
        "state",
        "resource"
    ],
    "wof:name":"Unemployment Division",
    "wof:placetype":"venue"
},
  "geometry": {"coordinates":[-73.62379300000001,40.708323],"type":"Point"}
}