{
  "type": "Feature",
  "properties": {
    "addr:full":"29 Maria Ln Buffalo NY 14227",
    "addr:housenumber":"29",
    "addr:postcode":"14227",
    "addr:street":"Maria Ln",
    "iso:country":"US",
    "sg:address":"29 Maria Ln",
    "sg:city":"Buffalo",
    "sg:classifiers":[
        {
            "category":"Professional",
            "subcategory":"Computer Services",
            "type":"Services"
        }
    ],
    "sg:phone":"+1 716 668 0189",
    "sg:postcode":"14227",
    "sg:province":"NY",
    "wof:name":"Spectrum Office Support",
    "wof:placetype":"venue"
},
  "geometry": {"coordinates":[-78.72935,42.864302],"type":"Point"}
}