{
  "type": "Feature",
  "properties": {
    "addr:full":"241 E 32nd St New York NY 10016",
    "addr:housenumber":"241",
    "addr:postcode":"10016",
    "addr:street":"E 32Nd St",
    "iso:country":"US",
    "sg:address":"241 E 32nd St",
    "sg:city":"New York",
    "sg:classifiers":[
        {
            "category":"Organizations",
            "subcategory":"Non-profit Organization",
            "type":"Services"
        }
    ],
    "sg:phone":"+1 212 481 3569",
    "sg:postcode":"10016",
    "sg:province":"NY",
    "sg:tags":[
        "service/non-profit",
        "community"
    ],
    "wof:name":"US Tibet Committee",
    "wof:placetype":"venue"
},
  "geometry": {"coordinates":[-73.9785,40.744301],"type":"Point"}
}