{
  "type": "Feature",
  "properties": {
    "addr:full":"127 S Broadway Ave Nyack NY 10960",
    "addr:housenumber":"127",
    "addr:postcode":"10960",
    "addr:street":"S Broadway Ave",
    "iso:country":"US",
    "sg:address":"127 S Broadway Ave",
    "sg:city":"Nyack",
    "sg:classifiers":[
        {
            "category":"Social Services",
            "type":"Services"
        }
    ],
    "sg:phone":"+1   ",
    "sg:postcode":"10960",
    "sg:province":"NY",
    "wof:name":"Rockland Intrfith Cnseling Ctr",
    "wof:placetype":"venue"
},
  "geometry": {"coordinates":[-73.91958200000001,41.085446],"type":"Point"}
}