{
  "type": "Feature",
  "properties": {
    "iso:country":"US",
    "sg:address":"143 Jericho Tpke",
    "sg:city":"Mineola",
    "sg:classifiers":[
        {
            "category":"Banks & Credit Unions",
            "subcategory":"Financial Services",
            "type":"Services"
        }
    ],
    "sg:phone":"+1 516 248 4422",
    "sg:postcode":"11501",
    "sg:province":"NY",
    "sg:tags":[
        "broker",
        "mortgage"
    ],
    "wof:name":"Mortgage Acceptance",
    "wof:placetype":"venue"
},
  "geometry": {"coordinates":[-73.641076,40.748968],"type":"Point"}
}