{
  "type": "Feature",
  "properties": {
    "iso:country":"US",
    "sg:address":"605 Rockaway Ave",
    "sg:city":"Valley Stream",
    "sg:classifiers":[
        {
            "category":"Retail",
            "subcategory":"Auto Repair",
            "type":"Services"
        }
    ],
    "sg:phone":"+1 516 256 7559",
    "sg:postcode":"11581",
    "sg:province":"NY",
    "wof:name":"Car O Practors",
    "wof:placetype":"venue"
},
  "geometry": {"coordinates":[-73.700104,40.655602],"type":"Point"}
}