{
  "type": "Feature",
  "properties": {
    "addr:full":"48 Highland Blvd Dix Hills NY 11746",
    "addr:housenumber":"48",
    "addr:postcode":"11746",
    "addr:street":"Highland Blvd",
    "iso:country":"US",
    "sg:address":"48 Highland Blvd",
    "sg:city":"Dix Hills",
    "sg:classifiers":[
        {
            "category":"Health Services",
            "subcategory":"Doctor",
            "type":"Services"
        }
    ],
    "sg:phone":"+1 631 242 8648",
    "sg:postcode":"11746",
    "sg:province":"NY",
    "sg:tags":[
        "physician",
        "surgeon"
    ],
    "wof:name":"Eliza Kaganowicz MD",
    "wof:placetype":"venue"
},
  "geometry": {"coordinates":[-73.328627,40.792835],"type":"Point"}
}