{
  "type": "Feature",
  "properties": {
    "iso:country":"US",
    "sg:address":"1580 Montauk Hwy",
    "sg:city":"Mastic",
    "sg:classifiers":[
        {
            "category":"Travel",
            "subcategory":"Hotels & Motels",
            "type":"Entertainment"
        }
    ],
    "sg:phone":"+1 631 281 2412",
    "sg:postcode":"11950",
    "sg:province":"NY",
    "sg:tags":[
        "resort"
    ],
    "wof:name":"Resort Properties Corp",
    "wof:placetype":"venue"
},
  "geometry": {"coordinates":[-72.84179399999999,40.806404],"type":"Point"}
}