{
  "type": "Feature",
  "properties": {
    "iso:country":"US",
    "sg:address":"600 E Main St",
    "sg:city":"Middletown",
    "sg:classifiers":[
        {
            "category":"Health Services",
            "subcategory":"Doctor",
            "type":"Services"
        }
    ],
    "sg:phone":"+1 845 342 4611",
    "sg:postcode":"10940",
    "sg:province":"NY",
    "sg:tags":[
        "medical"
    ],
    "wof:name":"Michael S Fruchter",
    "wof:placetype":"venue"
},
  "geometry": {"coordinates":[-74.377484,41.442444],"type":"Point"}
}