{
  "type": "Feature",
  "properties": {
    "addr:full":"45 Executive Blvd Jericho NY 11735",
    "addr:housenumber":"45",
    "addr:postcode":"11735",
    "addr:street":"Executive Blvd",
    "iso:country":"US",
    "sg:address":"45 Executive Blvd",
    "sg:city":"Jericho",
    "sg:classifiers":[
        {
            "category":"Insurance",
            "subcategory":"Insurance Agent",
            "type":"Services"
        }
    ],
    "sg:phone":"+1 516 333 3000",
    "sg:postcode":"11735",
    "sg:province":"NY",
    "wof:name":"Halland Companies",
    "wof:placetype":"venue"
},
  "geometry": {"coordinates":[-73.42968500000001,40.720027],"type":"Point"}
}