{
  "type": "Feature",
  "properties": {
    "addr:full":"197 Grand St New York NY 10013",
    "addr:housenumber":"197",
    "addr:postcode":"10013",
    "addr:street":"Grand St",
    "iso:country":"US",
    "sg:address":"197 Grand St",
    "sg:city":"New York",
    "sg:classifiers":[
        {
            "category":"Communications",
            "subcategory":"Film & Video Production",
            "type":"Services"
        }
    ],
    "sg:phone":"+1 212 965 8600",
    "sg:postcode":"10013",
    "sg:province":"NY",
    "sg:tags":[
        "director",
        "audio",
        "producer"
    ],
    "sg:website":"www.corrafilms.com",
    "wof:name":"Corra Films Inc",
    "wof:placetype":"venue"
},
  "geometry": {"coordinates":[-73.996821,40.719117],"type":"Point"}
}