{
  "type": "Feature",
  "properties": {
    "addr:full":"918 Morris Ave Bronx NY 10451",
    "addr:housenumber":"918",
    "addr:postcode":"10451",
    "addr:street":"Morris Ave",
    "iso:country":"US",
    "sg:address":"918 Morris Ave",
    "sg:city":"Bronx",
    "sg:classifiers":[
        {
            "category":"Social Services",
            "subcategory":"Adult Care",
            "type":"Services"
        }
    ],
    "sg:phone":"+1 718 293 2700",
    "sg:postcode":"10451",
    "sg:province":"NY",
    "sg:tags":[
        "organization",
        "senior",
        "citizen"
    ],
    "wof:name":"Mid-Bronx Sr Citizen's Council",
    "wof:placetype":"venue"
},
  "geometry": {"coordinates":[-73.917602,40.826887],"type":"Point"}
}