{
  "type": "Feature",
  "properties": {
    "iso:country":"US",
    "sg:address":"54 Village Gate Way",
    "sg:city":"Nyack",
    "sg:classifiers":[
        {
            "category":"Real Estate",
            "subcategory":"Real Estate Operator",
            "type":"Services"
        }
    ],
    "sg:phone":"+1 845 353 6263",
    "sg:postcode":"10960",
    "sg:province":"NY",
    "sg:tags":[
        "condominium"
    ],
    "wof:name":"Village Gate Homeowners Assn",
    "wof:placetype":"venue"
},
  "geometry": {"coordinates":[-73.927494,41.099573],"type":"Point"}
}