{
  "type": "Feature",
  "properties": {
    "iso:country":"US",
    "sg:address":"2956 Union Rd",
    "sg:city":"Cheektowaga",
    "sg:classifiers":[
        {
            "category":"Professional",
            "subcategory":"Lawyer & Legal Services",
            "type":"Services"
        }
    ],
    "sg:phone":"+1 716 651 1000",
    "sg:postcode":"14227",
    "sg:province":"NY",
    "sg:tags":[
        "attorney"
    ],
    "wof:name":"Thomas E Wojtan",
    "wof:placetype":"venue"
},
  "geometry": {"coordinates":[-78.754535,42.892731],"type":"Point"}
}