{
  "type": "Feature",
  "properties": {
    "addr:full":"11013 Jamaica Ave Richmond Hill NY 11418",
    "addr:housenumber":"11013",
    "addr:postcode":"11418",
    "addr:street":"Jamaica Ave",
    "iso:country":"US",
    "sg:address":"11013 Jamaica Ave",
    "sg:city":"Richmond Hill",
    "sg:classifiers":[
        {
            "category":"Professional",
            "subcategory":"Lawyer & Legal Services",
            "type":"Services"
        }
    ],
    "sg:phone":"+1 718 846 6380",
    "sg:postcode":"11418",
    "sg:province":"NY",
    "wof:name":"Law Office of Shawn D Chand",
    "wof:placetype":"venue"
},
  "geometry": {"coordinates":[-73.837569,40.696631],"type":"Point"}
}