{
  "type": "Feature",
  "properties": {
    "iso:country":"US",
    "sg:address":"8 Creighton Ave",
    "sg:city":"Lake Ronkonkoma",
    "sg:classifiers":[
        {
            "category":"Building & Trades",
            "subcategory":"Construction",
            "type":"Services"
        }
    ],
    "sg:phone":"+1 631 467 1827",
    "sg:postcode":"11779",
    "sg:province":"NY",
    "sg:tags":[
        "siding",
        "contractor"
    ],
    "wof:name":"Action Siding Inc",
    "wof:placetype":"venue"
},
  "geometry": {"coordinates":[-73.098736,40.827766],"type":"Point"}
}