{
  "type": "Feature",
  "properties": {
    "addr:full":"1 Irving Pl New York NY 10003",
    "addr:housenumber":"1",
    "addr:postcode":"10003",
    "addr:street":"Irving Pl",
    "iso:country":"US",
    "sg:address":"1 Irving Pl",
    "sg:city":"New York",
    "sg:classifiers":[
        {
            "category":"Health Services",
            "subcategory":"Doctor",
            "type":"Services"
        }
    ],
    "sg:phone":"+1 212 979 8595",
    "sg:postcode":"10003",
    "sg:province":"NY",
    "sg:tags":[
        "physician",
        "surgeon",
        "medical"
    ],
    "wof:name":"David Halio MD",
    "wof:placetype":"venue"
},
  "geometry": {"coordinates":[-73.988286,40.734659],"type":"Point"}
}