{
  "type": "Feature",
  "properties": {
    "addr:full":"659 W 179th St New York NY 10033",
    "addr:housenumber":"659",
    "addr:postcode":"10033",
    "addr:street":"W 179Th St",
    "iso:country":"US",
    "sg:address":"659 W 179th St",
    "sg:city":"New York",
    "sg:classifiers":[
        {
            "category":"Health Services",
            "subcategory":"Doctor",
            "type":"Services"
        }
    ],
    "sg:phone":"+1 212 568 1838",
    "sg:postcode":"10033",
    "sg:province":"NY",
    "sg:tags":[
        "medical"
    ],
    "wof:name":"Luis Morales MD",
    "wof:placetype":"venue"
},
  "geometry": {"coordinates":[-73.936892,40.848937],"type":"Point"}
}