{
  "type": "Feature",
  "properties": {
    "addr:full":"3539 Decatur Ave Bronx NY 10467",
    "addr:housenumber":"3539",
    "addr:postcode":"10467",
    "addr:street":"Decatur Ave",
    "iso:country":"US",
    "sg:address":"3539 Decatur Ave",
    "sg:city":"Bronx",
    "sg:classifiers":[
        {
            "category":"Building & Trades",
            "subcategory":"Plumbing",
            "type":"Services"
        }
    ],
    "sg:phone":"+1 718 652 1689",
    "sg:postcode":"10467",
    "sg:province":"NY",
    "sg:tags":[
        "contractor"
    ],
    "wof:name":"King Plumbing & Heating Inc",
    "wof:placetype":"venue"
},
  "geometry": {"coordinates":[-73.872173,40.879682],"type":"Point"}
}