{
  "type": "Feature",
  "properties": {
    "iso:country":"US",
    "sg:address":"229 Beach 137th St",
    "sg:city":"Far Rockaway",
    "sg:classifiers":[
        {
            "category":"Organizations",
            "subcategory":"Religious Organization",
            "type":"Services"
        }
    ],
    "sg:phone":"+1 718 945 5463",
    "sg:postcode":"11694",
    "sg:province":"NY",
    "wof:name":"Congregation Bais Yehudah",
    "wof:placetype":"venue"
},
  "geometry": {"coordinates":[-73.855602,40.575253],"type":"Point"}
}