{
  "type": "Feature",
  "properties": {
    "addr:full":"47 State Highway 345 Potsdam NY 13676",
    "addr:housenumber":"47",
    "addr:postcode":"13676",
    "addr:street":"State Highway 345",
    "iso:country":"US",
    "sg:address":"47 State Highway 345",
    "sg:city":"Potsdam",
    "sg:classifiers":[
        {
            "category":"Personal",
            "subcategory":"Beauty Salon",
            "type":"Services"
        }
    ],
    "sg:phone":"+1 315 262 0482",
    "sg:postcode":"13676",
    "sg:province":"NY",
    "wof:name":"Body Shop, Fitness & Salon, Inc.",
    "wof:placetype":"venue"
},
  "geometry": {"coordinates":[-75.01009500000001,44.676998],"type":"Point"}
}