{
  "type": "Feature",
  "properties": {
    "iso:country":"US",
    "sg:address":"70 Comsewogue Rd",
    "sg:city":"East Setauket",
    "sg:classifiers":[
        {
            "category":"Utilities",
            "subcategory":"Refuse",
            "type":"Services"
        },
        {
            "category":"Manufacturing",
            "subcategory":"Tools & Machinery",
            "type":"Manufacturing & Wholesale Goods"
        }
    ],
    "sg:phone":"+1 631 473 0330",
    "sg:postcode":"11733",
    "sg:province":"NY",
    "sg:tags":[
        "garbage",
        "system",
        "collection",
        "mfg"
    ],
    "wof:name":"Suffolk Materials Corp",
    "wof:placetype":"venue"
},
  "geometry": {"coordinates":[-73.083279,40.933737],"type":"Point"}
}