{
  "type": "Feature",
  "properties": {
    "addr:full":"183 Smith St Brooklyn NY 11201",
    "addr:housenumber":"183",
    "addr:postcode":"11201",
    "addr:street":"Smith St",
    "iso:country":"US",
    "sg:address":"183 Smith St",
    "sg:city":"Brooklyn",
    "sg:classifiers":[
        {
            "category":"Retail",
            "subcategory":"Self-service Laundry",
            "type":"Services"
        }
    ],
    "sg:phone":"+1 718 643 9155",
    "sg:postcode":"11201",
    "sg:province":"NY",
    "sg:tags":[
        "coin"
    ],
    "wof:name":"Splishy Splashy Laundromat",
    "wof:placetype":"venue"
},
  "geometry": {"coordinates":[-73.991058,40.685817],"type":"Point"}
}