{
  "type": "Feature",
  "properties": {
    "addr:full":"441 Main St Farmingdale NY 11735",
    "addr:housenumber":"441",
    "addr:postcode":"11735",
    "addr:street":"Main St",
    "iso:country":"US",
    "sg:address":"441 Main St",
    "sg:city":"Farmingdale",
    "sg:classifiers":[
        {
            "category":"Shopping",
            "subcategory":"Used Merchandise",
            "type":"Retail Goods"
        }
    ],
    "sg:phone":"+1 516 293 2828",
    "sg:postcode":"11735",
    "sg:province":"NY",
    "sg:tags":[
        "furniture"
    ],
    "wof:name":"Second Hand Store",
    "wof:placetype":"venue"
},
  "geometry": {"coordinates":[-73.444581,40.728541],"type":"Point"}
}