{
  "type": "Feature",
  "properties": {
    "addr:full":"20 Dickson St Newburgh NY 12550",
    "addr:housenumber":"20",
    "addr:postcode":"12550",
    "addr:street":"Dickson St",
    "iso:country":"US",
    "sg:address":"20 Dickson St",
    "sg:city":"Newburgh",
    "sg:classifiers":[
        {
            "category":"Building & Trades",
            "subcategory":"Construction",
            "type":"Services"
        }
    ],
    "sg:phone":"+1 845 565 1888",
    "sg:postcode":"12550",
    "sg:province":"NY",
    "sg:tags":[
        "concrete",
        "contractor"
    ],
    "wof:name":"Concrete Scientific",
    "wof:placetype":"venue"
},
  "geometry": {"coordinates":[-74.020883,41.494386],"type":"Point"}
}