{
  "type": "Feature",
  "properties": {
    "addr:full":"354 E 74 St New York NY 10021",
    "addr:housenumber":"354;74",
    "addr:postcode":"10021",
    "addr:street":"E;St",
    "iso:country":"US",
    "sg:address":"354 E 74 St",
    "sg:city":"New York",
    "sg:classifiers":[
        {
            "category":"Restaurant",
            "type":"Food & Drink"
        }
    ],
    "sg:phone":"+1 212 249 6619",
    "sg:postcode":"10021",
    "sg:province":"NY",
    "wof:name":"Andree's Restaurant",
    "wof:placetype":"venue"
},
  "geometry": {"coordinates":[-73.95606100000001,40.769606],"type":"Point"}
}