{
  "type": "Feature",
  "properties": {
    "addr:full":"65 Main St West Sayville NY 11796",
    "addr:housenumber":"65",
    "addr:postcode":"11796",
    "addr:street":"Main St",
    "iso:country":"US",
    "sg:address":"65 Main St",
    "sg:city":"West Sayville",
    "sg:classifiers":[
        {
            "category":"Restaurant",
            "type":"Food & Drink"
        }
    ],
    "sg:phone":"+1   ",
    "sg:postcode":"11796",
    "sg:province":"NY",
    "sg:tags":[
        "drinking",
        "eating"
    ],
    "wof:name":"Mackeys Cactus Cafe",
    "wof:placetype":"venue"
},
  "geometry": {"coordinates":[-73.092592,40.730418],"type":"Point"}
}