{
  "type": "Feature",
  "properties": {
    "iso:country":"US",
    "sg:address":"498 Jefferson Ave",
    "sg:city":"Fairport",
    "sg:classifiers":[
        {
            "category":"Professional",
            "type":"Services"
        }
    ],
    "sg:phone":"+1 585 388 5199",
    "sg:postcode":"14450",
    "sg:province":"NY",
    "sg:tags":[
        "establishment"
    ],
    "wof:name":"Heritage Christian Hm Inc",
    "wof:placetype":"venue"
},
  "geometry": {"coordinates":[-77.462147,43.082647],"type":"Point"}
}