{
  "type": "Feature",
  "properties": {
    "addr:full":"51 Champlain Ave Staten Island NY 10306",
    "addr:housenumber":"51",
    "addr:postcode":"10306",
    "addr:street":"Champlain Ave",
    "iso:country":"US",
    "sg:address":"51 Champlain Ave",
    "sg:city":"Staten Island",
    "sg:classifiers":[
        {
            "category":"Wholesale",
            "subcategory":"Non-durable Goods",
            "type":"Manufacturing & Wholesale Goods"
        }
    ],
    "sg:phone":"+1 718 351 7775",
    "sg:postcode":"10306",
    "sg:province":"NY",
    "wof:name":"Jealan Distributors Inc",
    "wof:placetype":"venue"
},
  "geometry": {"coordinates":[-74.12679799999999,40.561801],"type":"Point"}
}