{
  "type": "Feature",
  "properties": {
    "addr:full":"10390 Cedar Rd Clarence Center NY 14032",
    "addr:housenumber":"10390",
    "addr:postcode":"14032",
    "addr:street":"Cedar Rd",
    "iso:country":"US",
    "sg:address":"10390 Cedar Rd",
    "sg:city":"Clarence Center",
    "sg:classifiers":[
        {
            "category":"Organizations",
            "subcategory":"Community Association",
            "type":"Services"
        }
    ],
    "sg:phone":"+1 716 741 3238",
    "sg:postcode":"14032",
    "sg:province":"NY",
    "sg:tags":[
        "membership"
    ],
    "wof:name":"National Grange",
    "wof:placetype":"venue"
},
  "geometry": {"coordinates":[-78.590969,43.057327],"type":"Point"}
}