{
  "type": "Feature",
  "properties": {
    "addr:full":"151 Wentworth Ave Albertson NY 11507",
    "addr:housenumber":"151",
    "addr:postcode":"11507",
    "addr:street":"Wentworth Ave",
    "iso:country":"US",
    "sg:address":"151 Wentworth Ave",
    "sg:city":"Albertson",
    "sg:classifiers":[
        {
            "category":"Real Estate",
            "subcategory":"Real Estate Agent",
            "type":"Services"
        }
    ],
    "sg:phone":"+1 516 877 7794",
    "sg:postcode":"11507",
    "sg:province":"NY",
    "wof:name":"Akj Management Corp",
    "wof:placetype":"venue"
},
  "geometry": {"coordinates":[-73.651493,40.763582],"type":"Point"}
}