{
  "type": "Feature",
  "properties": {
    "iso:country":"US",
    "sg:address":"216 Main St",
    "sg:city":"Greenport",
    "sg:classifiers":[
        {
            "category":"Insurance",
            "subcategory":"Hazard Insurance",
            "type":"Services"
        }
    ],
    "sg:phone":"+1 631 477 0153",
    "sg:postcode":"11944",
    "sg:province":"NY",
    "sg:tags":[
        "commercial",
        "business"
    ],
    "wof:name":"Joseph L Townsend Inc",
    "wof:placetype":"venue"
},
  "geometry": {"coordinates":[-72.35930399999999,41.103],"type":"Point"}
}