{
  "type": "Feature",
  "properties": {
    "addr:full":"8030 State Hwy 12 Sherburne NY 13460",
    "addr:housenumber":"8030",
    "addr:postcode":"13460",
    "addr:street":"State Hwy 12 Sherburne",
    "iso:country":"US",
    "sg:address":"8030 State Hwy 12",
    "sg:city":"Sherburne",
    "sg:classifiers":[
        {
            "category":"Shopping",
            "subcategory":"Hobbies, Toys, & Games",
            "type":"Retail Goods"
        }
    ],
    "sg:phone":"+1 607 674 9600",
    "sg:postcode":"13460",
    "sg:province":"NY",
    "sg:tags":[
        "model",
        "supply"
    ],
    "wof:name":"A J's Machine's Rc Hobby Shop",
    "wof:placetype":"venue"
},
  "geometry": {"coordinates":[-75.49036599999999,42.665326],"type":"Point"}
}