{
  "type": "Feature",
  "properties": {
    "addr:full":"162 Quarry Rd Plattsburgh NY 12901",
    "addr:housenumber":"162",
    "addr:postcode":"12901",
    "addr:street":"Quarry Rd",
    "iso:country":"US",
    "sg:address":"162 Quarry Rd",
    "sg:city":"Plattsburgh",
    "sg:classifiers":[
        {
            "category":"Organizations",
            "subcategory":"Community Association",
            "type":"Services"
        }
    ],
    "sg:phone":"+1 518 563 3650",
    "sg:postcode":"12901",
    "sg:province":"NY",
    "sg:tags":[
        "military"
    ],
    "wof:name":"American Legion",
    "wof:placetype":"venue"
},
  "geometry": {"coordinates":[-73.47618300000001,44.708048],"type":"Point"}
}