{
  "type": "Feature",
  "properties": {
    "iso:country":"US",
    "sg:address":"9204 3rd Ave",
    "sg:city":"Brooklyn",
    "sg:classifiers":[
        {
            "category":"Food & Beverages",
            "subcategory":"Groceries & Convenience Stores",
            "type":"Retail Goods"
        }
    ],
    "sg:phone":"+1 718 513 0071",
    "sg:postcode":"11209",
    "sg:province":"NY",
    "sg:tags":[
        "grocer"
    ],
    "wof:name":"Piazza Mercato",
    "wof:placetype":"venue"
},
  "geometry": {"coordinates":[-74.032991,40.618966],"type":"Point"}
}