{
  "type": "Feature",
  "properties": {
    "addr:full":"1930 Rockaway Pkwy Brooklyn NY 11236",
    "addr:housenumber":"1930",
    "addr:postcode":"11236",
    "addr:street":"Rockaway Pkwy",
    "iso:country":"US",
    "sg:address":"1930 Rockaway Pkwy",
    "sg:city":"Brooklyn",
    "sg:classifiers":[
        {
            "category":"Manufacturing",
            "subcategory":"Printing",
            "type":"Manufacturing & Wholesale Goods"
        }
    ],
    "sg:phone":"+1 718 763 7785",
    "sg:postcode":"11236",
    "sg:province":"NY",
    "sg:tags":[
        "newspaper"
    ],
    "wof:name":"New York Liberty Star",
    "wof:placetype":"venue"
},
  "geometry": {"coordinates":[-73.89337399999999,40.637108],"type":"Point"}
}