{
  "type": "Feature",
  "properties": {
    "iso:country":"US",
    "sg:address":"117 Finney Blvd",
    "sg:city":"Malone",
    "sg:classifiers":[
        {
            "category":"Real Estate",
            "subcategory":"Real Estate Agent",
            "type":"Services"
        }
    ],
    "sg:phone":"+1 518 481 5425",
    "sg:postcode":"12953",
    "sg:province":"NY",
    "sg:tags":[
        "authorities",
        "housing"
    ],
    "wof:name":"L'Esperance Housing",
    "wof:placetype":"venue"
},
  "geometry": {"coordinates":[-74.30121,44.840665],"type":"Point"}
}