{
  "type": "Feature",
  "properties": {
    "iso:country":"US",
    "sg:address":"165 60th St",
    "sg:city":"Niagara Falls",
    "sg:classifiers":[
        {
            "category":"Building & Trades",
            "subcategory":"Construction",
            "type":"Services"
        }
    ],
    "sg:phone":"+1 716 283 7853",
    "sg:postcode":"14304",
    "sg:province":"NY",
    "sg:tags":[
        "carpentry",
        "contractor"
    ],
    "wof:name":"Bidaks Carpentry & Cnstr",
    "wof:placetype":"venue"
},
  "geometry": {"coordinates":[-78.995105,43.078536],"type":"Point"}
}