{
  "type": "Feature",
  "properties": {
    "addr:full":"60 Innsbruck Dr Buffalo NY 14227",
    "addr:housenumber":"60",
    "addr:postcode":"14227",
    "addr:street":"Innsbruck Dr",
    "iso:country":"US",
    "sg:address":"60 Innsbruck Dr",
    "sg:city":"Buffalo",
    "sg:classifiers":[
        {
            "category":"Health Services",
            "subcategory":"Medical Lab",
            "type":"Services"
        }
    ],
    "sg:phone":"+1 716 614 9000",
    "sg:postcode":"14227",
    "sg:province":"NY",
    "wof:name":"Case Management Concept, Inc",
    "wof:placetype":"venue"
},
  "geometry": {"coordinates":[-78.751589,42.873513],"type":"Point"}
}