{
  "type": "Feature",
  "properties": {
    "iso:country":"US",
    "sg:address":"70 Harrison St",
    "sg:city":"West Harrison",
    "sg:classifiers":[
        {
            "category":"Banks & Credit Unions",
            "subcategory":"Bank",
            "type":"Services"
        }
    ],
    "sg:phone":"+1 914 697 7651",
    "sg:postcode":"10604",
    "sg:province":"NY",
    "sg:tags":[
        "financing"
    ],
    "wof:name":"Premier Funding Corp",
    "wof:placetype":"venue"
},
  "geometry": {"coordinates":[-73.749087,41.039628],"type":"Point"}
}