{
  "type": "Feature",
  "properties": {
    "addr:full":"49 Franklin Ave Saranac Lake NY 12983",
    "addr:housenumber":"49",
    "addr:postcode":"12983",
    "addr:street":"Franklin Ave",
    "iso:country":"US",
    "sg:address":"49 Franklin Ave",
    "sg:city":"Saranac Lake",
    "sg:classifiers":[
        {
            "category":"Building & Trades",
            "subcategory":"Construction",
            "type":"Services"
        }
    ],
    "sg:phone":"+1 518 891 0949",
    "sg:postcode":"12983",
    "sg:province":"NY",
    "sg:tags":[
        "hanging",
        "contractor"
    ],
    "wof:name":"R S J Painting",
    "wof:placetype":"venue"
},
  "geometry": {"coordinates":[-74.12522199999999,44.326226],"type":"Point"}
}