{
  "type": "Feature",
  "properties": {
    "addr:full":"305 E Kingsbridge Rd Bronx NY 10458",
    "addr:housenumber":"305",
    "addr:postcode":"10458",
    "addr:street":"E Kingsbridge Rd",
    "iso:country":"US",
    "sg:address":"305 E Kingsbridge Rd",
    "sg:city":"Bronx",
    "sg:classifiers":[
        {
            "category":"Shopping",
            "subcategory":"Shoes",
            "type":"Retail Goods"
        }
    ],
    "sg:phone":"+1 718 329 6185",
    "sg:postcode":"10458",
    "sg:province":"NY",
    "wof:name":"Nine West Outlet",
    "wof:placetype":"venue"
},
  "geometry": {"coordinates":[-73.893998,40.862467],"type":"Point"}
}