{
  "type": "Feature",
  "properties": {
    "addr:full":"235 W 116th St New York NY 10026",
    "addr:housenumber":"235",
    "addr:postcode":"10026",
    "addr:street":"W 116Th St",
    "iso:country":"US",
    "sg:address":"235 W 116th St",
    "sg:city":"New York",
    "sg:classifiers":[
        {
            "category":"Wholesale",
            "subcategory":"Durable Goods & Equipment",
            "type":"Manufacturing & Wholesale Goods"
        }
    ],
    "sg:phone":"+1 212 222 1937",
    "sg:postcode":"10026",
    "sg:province":"NY",
    "sg:tags":[
        "importer"
    ],
    "wof:name":"Ar Amine Import Export",
    "wof:placetype":"venue"
},
  "geometry": {"coordinates":[-73.95458499999999,40.80407],"type":"Point"}
}