{
  "type": "Feature",
  "properties": {
    "addr:full":"132 S Main St Northville NY 12134",
    "addr:housenumber":"132",
    "addr:postcode":"12134",
    "addr:street":"S Main St",
    "iso:country":"US",
    "sg:address":"132 S Main St",
    "sg:city":"Northville",
    "sg:classifiers":[
        {
            "category":"Shopping",
            "subcategory":"Music",
            "type":"Retail Goods"
        }
    ],
    "sg:phone":"+1 518 863 9190",
    "sg:postcode":"12134",
    "sg:province":"NY",
    "sg:tags":[
        "video",
        "disc",
        "tape",
        "cassette"
    ],
    "wof:name":"Captain Video",
    "wof:placetype":"venue"
},
  "geometry": {"coordinates":[-74.17172100000001,43.225552],"type":"Point"}
}