{
  "type": "Feature",
  "properties": {
    "iso:country":"US",
    "sg:address":"65 W 95th Street",
    "sg:city":"New York",
    "sg:classifiers":[
        {
            "category":"Organizations",
            "subcategory":"Non-profit Organization",
            "type":"Services"
        }
    ],
    "sg:phone":"+1 212 663 3036",
    "sg:postcode":"10025",
    "sg:province":"NY",
    "sg:tags":[
        "service/non-profit",
        "community"
    ],
    "wof:name":"Counseling In Schools",
    "wof:placetype":"venue"
},
  "geometry": {"coordinates":[-73.96818,40.797043],"type":"Point"}
}