{
  "type": "Feature",
  "properties": {
    "iso:country":"US",
    "sg:address":"330 Madison Ave",
    "sg:city":"New York",
    "sg:classifiers":[
        {
            "category":"Professional",
            "subcategory":"Research",
            "type":"Services"
        }
    ],
    "sg:phone":"+1 646 495 5076",
    "sg:postcode":"10017",
    "sg:province":"NY",
    "sg:tags":[
        "laboratory"
    ],
    "wof:name":"Fitech Labs",
    "wof:placetype":"venue"
},
  "geometry": {"coordinates":[-73.979287,40.752801],"type":"Point"}
}