{
  "type": "Feature",
  "properties": {
    "iso:country":"US",
    "sg:address":"3660 Harlem Rd",
    "sg:city":"Buffalo",
    "sg:classifiers":[
        {
            "category":"Professional",
            "type":"Services"
        }
    ],
    "sg:phone":"+1 716 831 7060",
    "sg:postcode":"14215",
    "sg:province":"NY",
    "sg:tags":[
        "establishment"
    ],
    "wof:name":"Cleveland Hill UFSD",
    "wof:placetype":"venue"
},
  "geometry": {"coordinates":[-78.784167,42.943815],"type":"Point"}
}