{
  "type": "Feature",
  "properties": {
    "iso:country":"US",
    "sg:address":"155 S Wellwood Ave",
    "sg:city":"Lindenhurst",
    "sg:classifiers":[
        {
            "category":"Professional",
            "type":"Services"
        }
    ],
    "sg:phone":"+1 631 884 4141",
    "sg:postcode":"11757",
    "sg:province":"NY",
    "sg:tags":[
        "establishment"
    ],
    "wof:name":"Jay Lindenhurst Inc",
    "wof:placetype":"venue"
},
  "geometry": {"coordinates":[-73.37121,40.684934],"type":"Point"}
}