{
  "type": "Feature",
  "properties": {
    "iso:country":"US",
    "sg:address":"1378 Standard Ave",
    "sg:city":"Elmont",
    "sg:classifiers":[
        {
            "category":"Professional",
            "subcategory":"Advertising",
            "type":"Services"
        }
    ],
    "sg:phone":"+1 516 326 3818",
    "sg:postcode":"11003",
    "sg:province":"NY",
    "sg:tags":[
        "related"
    ],
    "wof:name":"Memons & Memons Intl Inc",
    "wof:placetype":"venue"
},
  "geometry": {"coordinates":[-73.691981,40.698939],"type":"Point"}
}