{
  "type": "Feature",
  "properties": {
    "addr:full":"37 W 46th St 2nd Fl New York NY 10036",
    "addr:housenumber":"37",
    "addr:postcode":"10036",
    "addr:street":"W 46Th St",
    "iso:country":"US",
    "sg:address":"37 W 46th St 2nd Fl",
    "sg:city":"New York",
    "sg:classifiers":[
        {
            "category":"Personal",
            "subcategory":"Beauty Salon",
            "type":"Services"
        }
    ],
    "sg:phone":"+1 212 221 2306",
    "sg:postcode":"10036",
    "sg:province":"NY",
    "sg:tags":[
        "hair"
    ],
    "sg:website":"www.anjelssalon.com",
    "wof:name":"An'jels Salon",
    "wof:placetype":"venue"
},
  "geometry": {"coordinates":[-73.98045999999999,40.756707],"type":"Point"}
}