{
  "type": "Feature",
  "properties": {
    "addr:full":"8 Willow St Potsdam NY 13676",
    "addr:housenumber":"8",
    "addr:postcode":"13676",
    "addr:street":"Willow St",
    "iso:country":"US",
    "sg:address":"8 Willow St",
    "sg:city":"Potsdam",
    "sg:classifiers":[
        {
            "category":"Shopping",
            "subcategory":"Used Merchandise",
            "type":"Retail Goods"
        }
    ],
    "sg:phone":"+1   ",
    "sg:postcode":"13676",
    "sg:province":"NY",
    "wof:name":"CORC",
    "wof:placetype":"venue"
},
  "geometry": {"coordinates":[-74.987244,44.671238],"type":"Point"}
}