{
  "type": "Feature",
  "properties": {
    "addr:full":"31 Crescent Dr Akron NY 14001",
    "addr:housenumber":"31",
    "addr:postcode":"14001",
    "addr:street":"Crescent Dr",
    "iso:country":"US",
    "sg:address":"31 Crescent Dr",
    "sg:city":"Akron",
    "sg:classifiers":[
        {
            "category":"Building & Trades",
            "subcategory":"Electrical",
            "type":"Services"
        }
    ],
    "sg:phone":"+1 716 542 4286",
    "sg:postcode":"14001",
    "sg:province":"NY",
    "sg:tags":[
        "electrical",
        "contractor"
    ],
    "wof:name":"Mast Electric",
    "wof:placetype":"venue"
},
  "geometry": {"coordinates":[-78.495088,43.009094],"type":"Point"}
}