{
  "type": "Feature",
  "properties": {
    "addr:full":"406 E 50 St New York NY 10022",
    "addr:housenumber":"406;50",
    "addr:postcode":"10022",
    "addr:street":"E;St",
    "iso:country":"US",
    "sg:address":"406 E 50 St",
    "sg:city":"New York",
    "sg:classifiers":[
        {
            "category":"Banks & Credit Unions",
            "subcategory":"Investment Brokerage",
            "type":"Services"
        }
    ],
    "sg:phone":"+1 212 688 8886",
    "sg:postcode":"10022",
    "sg:province":"NY",
    "sg:tags":[
        "security",
        "dealer"
    ],
    "sg:website":"www.kesusa.com",
    "wof:name":"Kim Eng Securities USA Inc",
    "wof:placetype":"venue"
},
  "geometry": {"coordinates":[-73.96506599999999,40.753368],"type":"Point"}
}