{
  "type": "Feature",
  "properties": {
    "addr:full":"104 Mineola Ave Roslyn Heights NY 11577",
    "addr:housenumber":"104",
    "addr:postcode":"11577",
    "addr:street":"Mineola Ave",
    "iso:country":"US",
    "sg:address":"104 Mineola Ave",
    "sg:city":"Roslyn Heights",
    "sg:classifiers":[
        {
            "category":"Restaurant",
            "type":"Food & Drink"
        }
    ],
    "sg:phone":"+1 516 621 2060",
    "sg:postcode":"11577",
    "sg:province":"NY",
    "sg:tags":[
        "chinese"
    ],
    "wof:name":"China Tasty No 1 Kitchn Inc",
    "wof:placetype":"venue"
},
  "geometry": {"coordinates":[-73.651178,40.788799],"type":"Point"}
}