{
  "type": "Feature",
  "properties": {
    "iso:country":"US",
    "sg:address":"38 Church St",
    "sg:city":"Patchogue",
    "sg:classifiers":[
        {
            "category":"Professional",
            "subcategory":"Lawyer & Legal Services",
            "type":"Services"
        }
    ],
    "sg:phone":"+1   ",
    "sg:postcode":"11772",
    "sg:province":"NY",
    "sg:tags":[
        "attorney"
    ],
    "wof:name":"Francis L Bosco",
    "wof:placetype":"venue"
},
  "geometry": {"coordinates":[-73.015964,40.764017],"type":"Point"}
}