{
  "type": "Feature",
  "properties": {
    "iso:country":"US",
    "sg:address":"11940 Metropolitan Avenue",
    "sg:city":"Kew Gardens",
    "sg:classifiers":[
        {
            "category":"Personal",
            "subcategory":"Tanning Parlor",
            "type":"Services"
        },
        {
            "category":"Sports & Exercise",
            "subcategory":"Gym",
            "type":"Entertainment"
        }
    ],
    "sg:phone":"+1 718 847 9690",
    "sg:postcode":"11415",
    "sg:province":"NY",
    "wof:name":"Kew Gardens Health & Fitness Center",
    "wof:placetype":"venue"
},
  "geometry": {"coordinates":[-73.831495,40.706039],"type":"Point"}
}