{
  "type": "Feature",
  "properties": {
    "addr:full":"64 Southside Ave Freeport NY 11520",
    "addr:housenumber":"64",
    "addr:postcode":"11520",
    "addr:street":"Southside Ave",
    "iso:country":"US",
    "sg:address":"64 Southside Ave",
    "sg:city":"Freeport",
    "sg:classifiers":[
        {
            "category":"Autos & Motor Vehicles",
            "subcategory":"Automobile Sales",
            "type":"Retail Goods"
        }
    ],
    "sg:phone":"+1 516 312 1576",
    "sg:postcode":"11520",
    "sg:province":"NY",
    "sg:tags":[
        "new",
        "car"
    ],
    "wof:name":"Nissan Legend",
    "wof:placetype":"venue"
},
  "geometry": {"coordinates":[-73.578822,40.647949],"type":"Point"}
}