{
  "type": "Feature",
  "properties": {
    "addr:full":"6 Pleasantville Rd Ossining NY 10562",
    "addr:housenumber":"6",
    "addr:postcode":"10562",
    "addr:street":"Pleasantville Rd",
    "iso:country":"US",
    "sg:address":"6 Pleasantville Rd",
    "sg:city":"Ossining",
    "sg:classifiers":[
        {
            "category":"Retail",
            "subcategory":"Repair Shop",
            "type":"Services"
        }
    ],
    "sg:phone":"+1 914 923 1230",
    "sg:postcode":"10562",
    "sg:province":"NY",
    "sg:tags":[
        "caning"
    ],
    "wof:name":"Alexis Mohr Caning",
    "wof:placetype":"venue"
},
  "geometry": {"coordinates":[-73.849289,41.166711],"type":"Point"}
}