{
  "type": "Feature",
  "properties": {
    "addr:full":"71 E River St Waterloo NY 13165",
    "addr:housenumber":"71",
    "addr:postcode":"13165",
    "addr:street":"E River St",
    "iso:country":"US",
    "sg:address":"71 E River St",
    "sg:city":"Waterloo",
    "sg:classifiers":[
        {
            "category":"Freight",
            "type":"Transportation"
        }
    ],
    "sg:phone":"+1   ",
    "sg:postcode":"13165",
    "sg:province":"NY",
    "sg:tags":[
        "operator",
        "local",
        "trucking"
    ],
    "wof:name":"Jack Harris Trucking",
    "wof:placetype":"venue"
},
  "geometry": {"coordinates":[-76.84808,42.899566],"type":"Point"}
}