{
  "type": "Feature",
  "properties": {
    "addr:full":"2338 Hermany Ave Bronx NY 10473",
    "addr:housenumber":"2338",
    "addr:postcode":"10473",
    "addr:street":"Hermany Ave",
    "iso:country":"US",
    "sg:address":"2338 Hermany Ave",
    "sg:city":"Bronx",
    "sg:classifiers":[
        {
            "category":"Food & Beverages",
            "subcategory":"Dairy",
            "type":"Retail Goods"
        }
    ],
    "sg:phone":"+1 718 892 4500",
    "sg:postcode":"10473",
    "sg:province":"NY",
    "sg:tags":[
        "grocery",
        "product"
    ],
    "wof:name":"Morris Park Farms",
    "wof:placetype":"venue"
},
  "geometry": {"coordinates":[-73.84420299999999,40.825407],"type":"Point"}
}