{
  "type": "Feature",
  "properties": {
    "iso:country":"US",
    "sg:address":"53 Bay Rd",
    "sg:city":"Plattsburgh",
    "sg:classifiers":[
        {
            "category":"Manufacturing",
            "subcategory":"Tools & Machinery",
            "type":"Manufacturing & Wholesale Goods"
        }
    ],
    "sg:phone":"+1 518 562 9911",
    "sg:postcode":"12901",
    "sg:province":"NY",
    "sg:tags":[
        "aid",
        "first",
        "supply"
    ],
    "sg:website":"www.efapny.com",
    "wof:name":"Emergency First Aid Products",
    "wof:placetype":"venue"
},
  "geometry": {"coordinates":[-73.40499,44.736509],"type":"Point"}
}