{
  "type": "Feature",
  "properties": {
    "addr:full":"246 Krumville Rd Olivebridge NY 12461",
    "addr:housenumber":"246",
    "addr:postcode":"12461",
    "addr:street":"Krumville Rd",
    "iso:country":"US",
    "sg:address":"246 Krumville Rd",
    "sg:city":"Olivebridge",
    "sg:classifiers":[
        {
            "category":"Professional",
            "subcategory":"Art Services",
            "type":"Services"
        }
    ],
    "sg:phone":"+1 845 657 2246",
    "sg:postcode":"12461",
    "sg:province":"NY",
    "sg:tags":[
        "designer",
        "display",
        "producer"
    ],
    "sg:website":"http://www.mayabranmandesign.com",
    "wof:name":"Maya Branman Design",
    "wof:placetype":"venue"
},
  "geometry": {"coordinates":[-74.223951,41.903129],"type":"Point"}
}