{
  "type": "Feature",
  "properties": {
    "iso:country":"US",
    "sg:address":"1452 Stony Brook Rd",
    "sg:city":"Stony Brook",
    "sg:classifiers":[
        {
            "category":"Health Services",
            "subcategory":"Chiropractor",
            "type":"Services"
        }
    ],
    "sg:phone":"+1 631 751 3123",
    "sg:postcode":"11790",
    "sg:province":"NY",
    "wof:name":"I Linkoff Chiropractic Offices",
    "wof:placetype":"venue"
},
  "geometry": {"coordinates":[-73.129212,40.896504],"type":"Point"}
}