{
  "type": "Feature",
  "properties": {
    "addr:full":"15 W 17 St New York NY 10011",
    "addr:housenumber":"15",
    "addr:postcode":"10011",
    "addr:street":"W 17 St",
    "iso:country":"US",
    "sg:address":"15 W 17 St",
    "sg:city":"New York",
    "sg:classifiers":[
        {
            "category":"Building & Trades",
            "subcategory":"Construction",
            "type":"Services"
        }
    ],
    "sg:phone":"+1 212 280 2900",
    "sg:postcode":"10011",
    "sg:province":"NY",
    "sg:tags":[
        "general",
        "contractor"
    ],
    "wof:name":"Aames Home Remodelers",
    "wof:placetype":"venue"
},
  "geometry": {"coordinates":[-73.99506100000001,40.739144],"type":"Point"}
}