{
  "type": "Feature",
  "properties": {
    "addr:full":"97 Guyon Ave Staten Island NY 10306",
    "addr:housenumber":"97",
    "addr:postcode":"10306",
    "addr:street":"Guyon Ave",
    "iso:country":"US",
    "sg:address":"97 Guyon Ave",
    "sg:city":"Staten Island",
    "sg:classifiers":[
        {
            "category":"Personal",
            "subcategory":"Barber",
            "type":"Services"
        }
    ],
    "sg:phone":"+1 718 667 4732",
    "sg:postcode":"10306",
    "sg:province":"NY",
    "wof:name":"Aces Barber Shop",
    "wof:placetype":"venue"
},
  "geometry": {"coordinates":[-74.127612,40.564911],"type":"Point"}
}