{
  "type": "Feature",
  "properties": {
    "iso:country":"US",
    "sg:address":"289 Sunrise Mall",
    "sg:city":"Massapequa",
    "sg:classifiers":[
        {
            "category":"Retail",
            "subcategory":"Portrait Studio",
            "type":"Services"
        }
    ],
    "sg:phone":"+1 516 797 4717",
    "sg:postcode":"11758",
    "sg:province":"NY",
    "sg:tags":[
        "photographer"
    ],
    "sg:website":"www.picturepeople.com",
    "wof:name":"Picture People Inc",
    "wof:placetype":"venue"
},
  "geometry": {"coordinates":[-73.435147,40.682145],"type":"Point"}
}