{
  "type": "Feature",
  "properties": {
    "addr:full":"5 Bethpage Rd Hicksville NY 11801",
    "addr:housenumber":"5",
    "addr:postcode":"11801",
    "addr:street":"Bethpage Rd",
    "iso:country":"US",
    "sg:address":"5 Bethpage Rd",
    "sg:city":"Hicksville",
    "sg:classifiers":[
        {
            "category":"Professional",
            "subcategory":"Lawyer & Legal Services",
            "type":"Services"
        }
    ],
    "sg:phone":"+1   ",
    "sg:postcode":"11801",
    "sg:province":"NY",
    "wof:name":"Rerisi Gail A",
    "wof:placetype":"venue"
},
  "geometry": {"coordinates":[-73.51689,40.772772],"type":"Point"}
}