{
  "type": "Feature",
  "properties": {
    "addr:full":"175 N 9th St Brooklyn NY 11211",
    "addr:housenumber":"175",
    "addr:postcode":"11211",
    "addr:street":"N 9Th St",
    "iso:country":"US",
    "sg:address":"175 N 9th St",
    "sg:city":"Brooklyn",
    "sg:classifiers":[
        {
            "category":"Professional",
            "type":"Services"
        }
    ],
    "sg:phone":"+1 718 388 6502",
    "sg:postcode":"11211",
    "sg:province":"NY",
    "sg:tags":[
        "establishment"
    ],
    "wof:name":"Star Cork Group",
    "wof:placetype":"venue"
},
  "geometry": {"coordinates":[-73.955581,40.718509],"type":"Point"}
}