{
  "type": "Feature",
  "properties": {
    "iso:country":"US",
    "sg:address":"4188 Rigel Course",
    "sg:city":"Liverpool",
    "sg:classifiers":[
        {
            "category":"Shopping",
            "type":"Retail Goods"
        }
    ],
    "sg:phone":"+1 315 622 5797",
    "sg:postcode":"13090",
    "sg:province":"NY",
    "sg:tags":[
        "material",
        "artist",
        "supply"
    ],
    "sg:website":"www.ktartstudio.com",
    "wof:name":"K T Art Studio",
    "wof:placetype":"venue"
},
  "geometry": {"coordinates":[-76.22216400000001,43.151873],"type":"Point"}
}