{
  "type": "Feature",
  "properties": {
    "iso:country":"US",
    "sg:address":"227 24th St",
    "sg:city":"Brooklyn",
    "sg:classifiers":[
        {
            "category":"Building & Trades",
            "subcategory":"Construction",
            "type":"Services"
        }
    ],
    "sg:phone":"+1 718 369 1168",
    "sg:postcode":"11232",
    "sg:province":"NY",
    "sg:tags":[
        "contractor"
    ],
    "wof:name":"Hugo Construction Corp",
    "wof:placetype":"venue"
},
  "geometry": {"coordinates":[-73.99846100000001,40.661945],"type":"Point"}
}