{
  "type": "Feature",
  "properties": {
    "iso:country":"US",
    "sg:address":"110 Greene St",
    "sg:city":"New York",
    "sg:classifiers":[
        {
            "category":"Manufacturing",
            "subcategory":"Printing",
            "type":"Manufacturing & Wholesale Goods"
        }
    ],
    "sg:phone":"+1 212 966 5190",
    "sg:postcode":"10012",
    "sg:province":"NY",
    "sg:tags":[
        "publisher"
    ],
    "wof:name":"Gatsby Publishing",
    "wof:placetype":"venue"
},
  "geometry": {"coordinates":[-73.999782,40.724182],"type":"Point"}
}