{
  "type": "Feature",
  "properties": {
    "iso:country":"US",
    "sg:address":"2703 W Main St",
    "sg:city":"Wappingers Falls",
    "sg:classifiers":[
        {
            "category":"Coffee & Tea",
            "type":"Food & Drink"
        },
        {
            "category":"Autos & Motor Vehicles",
            "subcategory":"Motorcycle Sales",
            "type":"Retail Goods"
        }
    ],
    "sg:phone":"+1 845 298 3333",
    "sg:postcode":"12590",
    "sg:province":"NY",
    "sg:website":"www.groundhogcoffee.com",
    "wof:name":"The Ground Hog",
    "wof:placetype":"venue"
},
  "geometry": {"coordinates":[-73.92072,41.601264],"type":"Point"}
}