{
  "type": "Feature",
  "properties": {
    "iso:country":"US",
    "sg:address":"305 E 61 St",
    "sg:city":"New York",
    "sg:classifiers":[
        {
            "category":"Professional",
            "type":"Services"
        }
    ],
    "sg:phone":"+1 212 888 8858",
    "sg:postcode":"10065",
    "sg:province":"NY",
    "sg:tags":[
        "arts",
        "artist"
    ],
    "wof:name":"Aaron Payne Fine Art",
    "wof:placetype":"venue"
},
  "geometry": {"coordinates":[-73.962569,40.761601],"type":"Point"}
}