{
  "type": "Feature",
  "properties": {
    "addr:full":"10-42 Mitchell Ave Binghamton NY 13903",
    "addr:housenumber":"10-42",
    "addr:postcode":"13903",
    "addr:street":"Mitchell Ave",
    "iso:country":"US",
    "sg:address":"10-42 Mitchell Ave",
    "sg:city":"Binghamton",
    "sg:classifiers":[
        {
            "category":"Health Services",
            "subcategory":"Clinic",
            "type":"Services"
        },
        {
            "category":"Professional",
            "subcategory":"Business Services",
            "type":"Services"
        }
    ],
    "sg:phone":"+1 607 762 3057",
    "sg:postcode":"13903",
    "sg:province":"NY",
    "sg:tags":[
        "medical",
        "consultants-medical",
        "billing"
    ],
    "wof:name":"United Health Services Hospitals Medical Rehabilitation Services",
    "wof:placetype":"venue"
},
  "geometry": {"coordinates":[-75.914169,42.088421],"type":"Point"}
}