{
  "type": "Feature",
  "properties": {
    "addr:full":"100 Pixley Rd Rochester NY 14624",
    "addr:housenumber":"100",
    "addr:postcode":"14624",
    "addr:street":"Pixley Rd",
    "iso:country":"US",
    "sg:address":"100 Pixley Rd",
    "sg:city":"Rochester",
    "sg:classifiers":[
        {
            "category":"Banks & Credit Unions",
            "subcategory":"Bank",
            "type":"Services"
        },
        {
            "category":"Banks & Credit Unions",
            "subcategory":"Financial Services",
            "type":"Services"
        }
    ],
    "sg:phone":"+1 585 247 8200",
    "sg:postcode":"14624",
    "sg:province":"NY",
    "sg:tags":[
        "commercial",
        "loan",
        "internet",
        "saving",
        "banking"
    ],
    "sg:website":"http://locators.bankofamerica.com/a/BC-13547",
    "wof:name":"Bank Of America",
    "wof:placetype":"venue"
},
  "geometry": {"coordinates":[-77.709203,43.146133],"type":"Point"}
}