{
  "type": "Feature",
  "properties": {
    "addr:full":"32 Vanderwater Ave Floral Park NY 11001",
    "addr:housenumber":"32",
    "addr:postcode":"11001",
    "addr:street":"Vanderwater Ave",
    "iso:country":"US",
    "sg:address":"32 Vanderwater Ave",
    "sg:city":"Floral Park",
    "sg:classifiers":[
        {
            "category":"Building & Trades",
            "subcategory":"Construction",
            "type":"Services"
        }
    ],
    "sg:phone":"+1 516 326 7515",
    "sg:postcode":"11001",
    "sg:province":"NY",
    "wof:name":"F Copagna Construction Corp",
    "wof:placetype":"venue"
},
  "geometry": {"coordinates":[-73.707123,40.713671],"type":"Point"}
}