{
  "type": "Feature",
  "properties": {
    "iso:country":"US",
    "sg:address":"8780 Brewerton Rd",
    "sg:city":"Brewerton",
    "sg:classifiers":[
        {
            "category":"Travel",
            "subcategory":"Hotels & Motels",
            "type":"Entertainment"
        }
    ],
    "sg:phone":"+1 315 699 4347",
    "sg:postcode":"13029",
    "sg:province":"NY",
    "sg:tags":[
        "operator",
        "operation",
        "dwelling"
    ],
    "wof:name":"Friendly Bdgt APT Efficiencies",
    "wof:placetype":"venue"
},
  "geometry": {"coordinates":[-76.126037,43.194019],"type":"Point"}
}