{
  "type": "Feature",
  "properties": {
    "iso:country":"US",
    "sg:address":"547 W 27th St Rm 204",
    "sg:city":"New York",
    "sg:classifiers":[
        {
            "category":"Arts & Performance",
            "subcategory":"Art Gallery",
            "type":"Entertainment"
        }
    ],
    "sg:phone":"+1 212 947 6100",
    "sg:postcode":"10001",
    "sg:province":"NY",
    "wof:name":"Ceres Gallery",
    "wof:placetype":"venue"
},
  "geometry": {"coordinates":[-74.777861,40.750988],"type":"Point"}
}