{
  "type": "Feature",
  "properties": {
    "iso:country":"US",
    "sg:address":"1843 Empire Blvd",
    "sg:city":"Webster",
    "sg:classifiers":[
        {
            "category":"Restaurant",
            "type":"Food & Drink"
        }
    ],
    "sg:phone":"+1   ",
    "sg:postcode":"14580",
    "sg:province":"NY",
    "sg:tags":[
        "eating"
    ],
    "wof:name":"Joan B Inc",
    "wof:placetype":"venue"
},
  "geometry": {"coordinates":[-77.505234,43.186854],"type":"Point"}
}