{
  "type": "Feature",
  "properties": {
    "iso:country":"US",
    "sg:address":"65 W Hills Rd",
    "sg:city":"Huntington Station",
    "sg:classifiers":[
        {
            "category":"Insurance",
            "subcategory":"Insurance Agent",
            "type":"Services"
        }
    ],
    "sg:phone":"+1 631 673 3399",
    "sg:postcode":"11746",
    "sg:province":"NY",
    "sg:website":"www.islandrisk.com",
    "wof:name":"Island Risk Management Assoc",
    "wof:placetype":"venue"
},
  "geometry": {"coordinates":[-73.416122,40.835972],"type":"Point"}
}