{
  "type": "Feature",
  "properties": {
    "iso:country":"US",
    "sg:address":"156 E 65 St",
    "sg:city":"New York",
    "sg:classifiers":[
        {
            "category":"Professional",
            "subcategory":"Lawyer & Legal Services",
            "type":"Services"
        }
    ],
    "sg:phone":"+1   ",
    "sg:postcode":"10065",
    "sg:province":"NY",
    "wof:name":"Kaming and Kaming",
    "wof:placetype":"venue"
},
  "geometry": {"coordinates":[-73.963843,40.765308],"type":"Point"}
}