{
  "type": "Feature",
  "properties": {
    "iso:country":"US",
    "sg:address":"1901 Vestal Pkwy E",
    "sg:city":"Vestal",
    "sg:classifiers":[
        {
            "category":"Manufacturing",
            "subcategory":"Printing",
            "type":"Manufacturing & Wholesale Goods"
        }
    ],
    "sg:phone":"+1 607 785 7555",
    "sg:postcode":"13850",
    "sg:province":"NY",
    "sg:tags":[
        "newspaper"
    ],
    "wof:name":"Broome Pennysaver Plus",
    "wof:placetype":"venue"
},
  "geometry": {"coordinates":[-76.022183,42.093242],"type":"Point"}
}