{
  "type": "Feature",
  "properties": {
    "addr:full":"4730 Junction Blvd Corona NY 11368",
    "addr:housenumber":"4730",
    "addr:postcode":"11368",
    "addr:street":"Junction Blvd",
    "iso:country":"US",
    "sg:address":"4730 Junction Blvd",
    "sg:city":"Corona",
    "sg:classifiers":[
        {
            "category":"Building & Trades",
            "subcategory":"Locksmith",
            "type":"Services"
        }
    ],
    "sg:phone":"+1 718 269 1300",
    "sg:postcode":"11368",
    "sg:province":"NY",
    "sg:tags":[
        "key"
    ],
    "wof:name":"A Twenty Four Hour A Corona Emergency",
    "wof:placetype":"venue"
},
  "geometry": {"coordinates":[-73.86763999999999,40.743124],"type":"Point"}
}