{
  "type": "Feature",
  "properties": {
    "addr:full":"4720 Lockport Rd Lockport NY 14094",
    "addr:postcode":"4720;14094",
    "addr:street":"Lockport Rd",
    "iso:country":"US",
    "sg:address":"4720 Lockport Rd",
    "sg:city":"Lockport",
    "sg:phone":"+1 716 625 8745",
    "sg:postcode":"14094",
    "sg:province":"NY",
    "sg:tags":[
        "wheat",
        "farm",
        "corn",
        "cash",
        "grain",
        "soybean"
    ],
    "wof:name":"Don Walck Farm",
    "wof:placetype":"venue"
},
  "geometry": {"coordinates":[-78.770189,43.133321],"type":"Point"}
}