{
  "type": "Feature",
  "properties": {
    "iso:country":"US",
    "sg:address":"149 Taylor Rd",
    "sg:city":"Richfield Springs",
    "sg:classifiers":[
        {
            "category":"Shopping",
            "subcategory":"Bicycles & Sporting Goods",
            "type":"Retail Goods"
        }
    ],
    "sg:phone":"+1   ",
    "sg:postcode":"13439",
    "sg:province":"NY",
    "wof:name":"4 Seasons Sports",
    "wof:placetype":"venue"
},
  "geometry": {"coordinates":[-75.02651899999999,42.792338],"type":"Point"}
}