{
  "type": "Feature",
  "properties": {
    "addr:full":"114 W Main St Patchogue NY 11772",
    "addr:housenumber":"114",
    "addr:postcode":"11772",
    "addr:street":"W Main St",
    "iso:country":"US",
    "sg:address":"114 W Main St",
    "sg:city":"Patchogue",
    "sg:classifiers":[
        {
            "category":"Restaurant",
            "type":"Food & Drink"
        }
    ],
    "sg:phone":"+1 631 447 7766",
    "sg:postcode":"11772",
    "sg:province":"NY",
    "wof:name":"Donato's Restaurant",
    "wof:placetype":"venue"
},
  "geometry": {"coordinates":[-73.017737,40.765795],"type":"Point"}
}