{
  "type": "Feature",
  "properties": {
    "iso:country":"US",
    "sg:address":"8 E 63rd St",
    "sg:city":"New York",
    "sg:classifiers":[
        {
            "category":"Health Services",
            "subcategory":"Doctor",
            "type":"Services"
        },
        {
            "category":"Health Services",
            "subcategory":"Dentist",
            "type":"Services"
        }
    ],
    "sg:phone":"+1 212 317 1392",
    "sg:postcode":"10065",
    "sg:province":"NY",
    "wof:name":"Rozenberg Lana Dds",
    "wof:placetype":"venue"
},
  "geometry": {"coordinates":[-73.970792,40.766443],"type":"Point"}
}