{
  "type": "Feature",
  "properties": {
    "addr:full":"182 Throop Ave Brooklyn NY 11206",
    "addr:housenumber":"182",
    "addr:postcode":"11206",
    "addr:street":"Throop Ave",
    "iso:country":"US",
    "sg:address":"182 Throop Ave",
    "sg:city":"Brooklyn",
    "sg:classifiers":[
        {
            "category":"Manufacturing",
            "subcategory":"Paper Products",
            "type":"Manufacturing & Wholesale Goods"
        }
    ],
    "sg:phone":"+1 718 782 3200",
    "sg:postcode":"11206",
    "sg:province":"NY",
    "sg:tags":[
        "bag"
    ],
    "wof:name":"Morris Brown Tobacco Co",
    "wof:placetype":"venue"
},
  "geometry": {"coordinates":[-73.944039,40.698318],"type":"Point"}
}