{
  "type": "Feature",
  "properties": {
    "addr:full":"1219 Avenue J Brooklyn NY 11230",
    "addr:housenumber":"1219",
    "addr:postcode":"11230",
    "addr:street":"Avenue J",
    "iso:country":"US",
    "sg:address":"1219 Avenue J",
    "sg:city":"Brooklyn",
    "sg:classifiers":[
        {
            "category":"Restaurant",
            "type":"Food & Drink"
        }
    ],
    "sg:menulink":"http://www.allmenus.com/ny/brooklyn/148175-subway/menu/",
    "sg:phone":"+1 718 252 1716",
    "sg:postcode":"11230",
    "sg:province":"NY",
    "sg:tags":[
        "american",
        "sandwich"
    ],
    "wof:name":"Subway",
    "wof:placetype":"venue"
},
  "geometry": {"coordinates":[-73.963999,40.624889],"type":"Point"}
}