{
  "type": "Feature",
  "properties": {
    "iso:country":"US",
    "sg:address":"525 East Ave",
    "sg:city":"Medina",
    "sg:classifiers":[
        {
            "category":"Wholesale",
            "subcategory":"Sporting Goods",
            "type":"Manufacturing & Wholesale Goods"
        }
    ],
    "sg:phone":"+1 585 798 0056",
    "sg:postcode":"14103",
    "sg:province":"NY",
    "sg:tags":[
        "equipment",
        "pool",
        "swimming"
    ],
    "wof:name":"Oasis Pool Supplies",
    "wof:placetype":"venue"
},
  "geometry": {"coordinates":[-78.379757,43.219492],"type":"Point"}
}