{
  "type": "Feature",
  "properties": {
    "addr:full":"3848 N Buffalo St Orchard Park NY 14127",
    "addr:housenumber":"3848",
    "addr:postcode":"14127",
    "addr:street":"N Buffalo St",
    "iso:country":"US",
    "sg:address":"3848 N Buffalo St",
    "sg:city":"Orchard Park",
    "sg:classifiers":[
        {
            "category":"Personal",
            "subcategory":"Beauty Salon",
            "type":"Services"
        }
    ],
    "sg:phone":"+1 716 662 2626",
    "sg:postcode":"14127",
    "sg:province":"NY",
    "sg:tags":[
        "shop"
    ],
    "wof:name":"F/X",
    "wof:placetype":"venue"
},
  "geometry": {"coordinates":[-78.74602299999999,42.781731],"type":"Point"}
}