{
  "type": "Feature",
  "properties": {
    "addr:full":"12 Birch Hill Rd Locust Valley NY 11560",
    "addr:housenumber":"12",
    "addr:postcode":"11560",
    "addr:street":"Birch Hill Rd",
    "iso:country":"US",
    "sg:address":"12 Birch Hill Rd",
    "sg:city":"Locust Valley",
    "sg:classifiers":[
        {
            "category":"Shopping",
            "subcategory":"Clothing, Apparel, & Fashions",
            "type":"Retail Goods"
        }
    ],
    "sg:phone":"+1 516 609 9090",
    "sg:postcode":"11560",
    "sg:province":"NY",
    "sg:tags":[
        "item",
        "boutique"
    ],
    "wof:name":"Pomponner",
    "wof:placetype":"venue"
},
  "geometry": {"coordinates":[-73.596897,40.875271],"type":"Point"}
}