{
  "type": "Feature",
  "properties": {
    "iso:country":"US",
    "sg:address":"834 2nd Ave",
    "sg:city":"New York",
    "sg:classifiers":[
        {
            "category":"Restaurant",
            "type":"Food & Drink"
        }
    ],
    "sg:menulink":"http://www.allmenus.com/ny/new-york/53123-subway/menu/",
    "sg:phone":"+1 212 808 8018",
    "sg:postcode":"10017",
    "sg:province":"NY",
    "sg:tags":[
        "american",
        "sandwich"
    ],
    "wof:name":"Subway",
    "wof:placetype":"venue"
},
  "geometry": {"coordinates":[-73.971008,40.751467],"type":"Point"}
}