{
  "type": "Feature",
  "properties": {
    "iso:country":"US",
    "sg:address":"802 Manhattan Avenue",
    "sg:city":"Brooklyn",
    "sg:classifiers":[
        {
            "category":"Food & Beverages",
            "subcategory":"Groceries & Convenience Stores",
            "type":"Retail Goods"
        }
    ],
    "sg:postcode":"11222",
    "sg:province":"NY",
    "wof:name":"Associated Supermarket",
    "wof:placetype":"venue"
},
  "geometry": {"coordinates":[-73.952904,40.727798],"type":"Point"}
}