{
  "type": "Feature",
  "properties": {
    "iso:country":"US",
    "sg:address":"1401 College Point Blvd",
    "sg:city":"College Point",
    "sg:classifiers":[
        {
            "category":"Retail",
            "subcategory":"Portrait Studio",
            "type":"Services"
        },
        {
            "category":"Shopping",
            "subcategory":"Pharmacy",
            "type":"Retail Goods"
        }
    ],
    "sg:phone":"+1 718 353 3204",
    "sg:postcode":"11356",
    "sg:province":"NY",
    "sg:tags":[
        "photography",
        "drugstore",
        "store"
    ],
    "sg:website":"www.walgreens.com",
    "wof:name":"Walgreens",
    "wof:placetype":"venue"
},
  "geometry": {"coordinates":[-73.845727,40.785216],"type":"Point"}
}