{
  "type": "Feature",
  "properties": {
    "iso:country":"US",
    "sg:address":"41 Van Wagner Rd",
    "sg:city":"Willow",
    "sg:classifiers":[
        {
            "category":"Professional",
            "subcategory":"Business Services",
            "type":"Services"
        },
        {
            "category":"Government",
            "subcategory":"Post Office",
            "type":"Public Place"
        }
    ],
    "sg:phone":"+1 800 275 8777",
    "sg:postcode":"12495",
    "sg:province":"NY",
    "sg:tags":[
        "mail",
        "shipping"
    ],
    "sg:website":"http://www.usps.com",
    "wof:name":"United States Postal Service",
    "wof:placetype":"venue"
},
  "geometry": {"coordinates":[-74.22512399999999,42.07422],"type":"Point"}
}