{
  "type": "Feature",
  "properties": {
    "addr:full":"188 Central Ave Albany NY 12206",
    "addr:housenumber":"188",
    "addr:postcode":"12206",
    "addr:street":"Central Ave",
    "iso:country":"US",
    "sg:address":"188 Central Ave",
    "sg:city":"Albany",
    "sg:classifiers":[
        {
            "category":"Autos & Motor Vehicles",
            "subcategory":"Auto Supplies",
            "type":"Retail Goods"
        },
        {
            "category":"Retail",
            "subcategory":"Auto Repair",
            "type":"Services"
        }
    ],
    "sg:phone":"+1 518 462 5429",
    "sg:postcode":"12206",
    "sg:province":"NY",
    "sg:tags":[
        "lube",
        "oil",
        "tire"
    ],
    "sg:website":"http://www.firestonecompleteautocare.com/?s_kwcid=IYP_NTL",
    "wof:name":"Firestone Complete Auto Care Store",
    "wof:placetype":"venue"
},
  "geometry": {"coordinates":[-73.76913999999999,42.661818],"type":"Point"}
}