{
  "type": "Feature",
  "properties": {
    "iso:country":"US",
    "sg:address":"128 Duffy Ave",
    "sg:city":"Hicksville",
    "sg:classifiers":[
        {
            "category":"Wholesale",
            "subcategory":"Metals & Minerals",
            "type":"Manufacturing & Wholesale Goods"
        }
    ],
    "sg:phone":"+1 516 938 8507",
    "sg:postcode":"11801",
    "sg:province":"NY",
    "sg:tags":[
        "warehouse",
        "steel",
        "distributor"
    ],
    "wof:name":"Hicksville Steel Corp",
    "wof:placetype":"venue"
},
  "geometry": {"coordinates":[-73.53396100000001,40.76469],"type":"Point"}
}