{
  "type": "Feature",
  "properties": {
    "addr:full":"9556 State Hwy 7 Worcester NY 12197",
    "addr:housenumber":"9556",
    "addr:postcode":"12197",
    "addr:street":"State Hwy 7",
    "iso:country":"US",
    "sg:address":"9556 State Hwy 7",
    "sg:city":"Worcester",
    "sg:classifiers":[
        {
            "category":"Restaurant",
            "type":"Food & Drink"
        }
    ],
    "sg:phone":"+1 607 397 9153",
    "sg:postcode":"12197",
    "sg:province":"NY",
    "wof:name":"Buds Bar & Grill",
    "wof:placetype":"venue"
},
  "geometry": {"coordinates":[-74.723648,42.595581],"type":"Point"}
}