{
  "type": "Feature",
  "properties": {
    "addr:full":"89 Plad Blvd Holtsville NY 11742",
    "addr:housenumber":"89",
    "addr:postcode":"11742",
    "addr:street":"Plad Blvd",
    "iso:country":"US",
    "sg:address":"89 Plad Blvd",
    "sg:city":"Holtsville",
    "sg:classifiers":[
        {
            "category":"Professional",
            "subcategory":"Computer Services",
            "type":"Services"
        }
    ],
    "sg:phone":"+1   ",
    "sg:postcode":"11742",
    "sg:province":"NY",
    "sg:tags":[
        "programing",
        "custom"
    ],
    "wof:name":"Inetmicro",
    "wof:placetype":"venue"
},
  "geometry": {"coordinates":[-73.047337,40.811424],"type":"Point"}
}