{
  "type": "Feature",
  "properties": {
    "iso:country":"US",
    "sg:address":"2 Heather Ln",
    "sg:city":"Rensselaer",
    "sg:classifiers":[
        {
            "category":"Real Estate",
            "subcategory":"Real Estate Agent",
            "type":"Services"
        }
    ],
    "sg:phone":"+1 518 426 2364",
    "sg:postcode":"12144",
    "sg:province":"NY",
    "sg:tags":[
        "appraiser"
    ],
    "wof:name":"Capital Appraisal & Inspection",
    "wof:placetype":"venue"
},
  "geometry": {"coordinates":[-73.726563,42.628637],"type":"Point"}
}