{
  "type": "Feature",
  "properties": {
    "iso:country":"US",
    "sg:address":"1345 Military Rd",
    "sg:city":"Buffalo",
    "sg:classifiers":[
        {
            "category":"Shopping",
            "type":"Retail Goods"
        },
        {
            "category":"Wholesale",
            "subcategory":"Non-durable Goods",
            "type":"Manufacturing & Wholesale Goods"
        }
    ],
    "sg:phone":"+1 716 874 1951",
    "sg:postcode":"14217",
    "sg:province":"NY",
    "sg:tags":[
        "pet",
        "tropical",
        "fish",
        "shop",
        "supply"
    ],
    "wof:name":"Niagara Aquarium Co Inc",
    "wof:placetype":"venue"
},
  "geometry": {"coordinates":[-78.886365,42.974619],"type":"Point"}
}