{
  "type": "Feature",
  "properties": {
    "iso:country":"US",
    "sg:address":"15 Valley Dr",
    "sg:city":"Thiells",
    "sg:classifiers":[
        {
            "category":"Building & Trades",
            "subcategory":"Plumbing",
            "type":"Services"
        }
    ],
    "sg:phone":"+1 845 429 5693",
    "sg:postcode":"10984",
    "sg:province":"NY",
    "sg:tags":[
        "plumber",
        "industrial",
        "contractors-commercial"
    ],
    "wof:name":"Harris, Bob Plumbing & Heating",
    "wof:placetype":"venue"
},
  "geometry": {"coordinates":[-74.01773799999999,41.20319],"type":"Point"}
}