{
  "type": "Feature",
  "properties": {
    "iso:country":"US",
    "sg:address":"626 Montgomery St",
    "sg:city":"Brooklyn",
    "sg:classifiers":[
        {
            "category":"Recreation",
            "type":"Entertainment"
        }
    ],
    "sg:phone":"+1   ",
    "sg:postcode":"11225",
    "sg:province":"NY",
    "wof:name":"Scandinavia Trio Tour",
    "wof:placetype":"venue"
},
  "geometry": {"coordinates":[-73.94364299999999,40.664946],"type":"Point"}
}