{
  "type": "Feature",
  "properties": {
    "addr:full":"76 Lee Ave Brooklyn NY 11211",
    "addr:housenumber":"76",
    "addr:postcode":"11211",
    "addr:street":"Lee Ave",
    "iso:country":"US",
    "sg:address":"76 Lee Ave",
    "sg:city":"Brooklyn",
    "sg:classifiers":[
        {
            "category":"Shopping",
            "subcategory":"Clothing, Apparel, & Fashions",
            "type":"Retail Goods"
        }
    ],
    "sg:phone":"+1 718 387 5480",
    "sg:postcode":"11211",
    "sg:province":"NY",
    "sg:tags":[
        "nightwear",
        "lingerie",
        "corset"
    ],
    "wof:name":"B M G Corset & Lingerie Boutique",
    "wof:placetype":"venue"
},
  "geometry": {"coordinates":[-73.95970199999999,40.705399],"type":"Point"}
}