{
  "type": "Feature",
  "properties": {
    "iso:country":"US",
    "sg:address":"21410 42nd Ave # A",
    "sg:city":"Bayside",
    "sg:classifiers":[
        {
            "category":"Banks & Credit Unions",
            "subcategory":"Financial Services",
            "type":"Services"
        }
    ],
    "sg:phone":"+1 718 767 6900",
    "sg:postcode":"11361",
    "sg:province":"NY",
    "sg:tags":[
        "intercoms-systems"
    ],
    "wof:name":"Atlantis Security",
    "wof:placetype":"venue"
},
  "geometry": {"coordinates":[-73.774609,40.761946],"type":"Point"}
}