{
  "type": "Feature",
  "properties": {
    "iso:country":"US",
    "sg:address":"1605 Broadway",
    "sg:city":"Hewlett",
    "sg:classifiers":[
        {
            "category":"Health Services",
            "subcategory":"Doctor",
            "type":"Services"
        }
    ],
    "sg:phone":"+1 516 374 4422",
    "sg:postcode":"11557",
    "sg:province":"NY",
    "sg:tags":[
        "dermatologist"
    ],
    "wof:name":"Reinsod Donald B MD PC & Associates",
    "wof:placetype":"venue"
},
  "geometry": {"coordinates":[-73.692497,40.6455],"type":"Point"}
}