{
  "type": "Feature",
  "properties": {
    "iso:country":"US",
    "sg:address":"75 Rockefeller Plaza",
    "sg:city":"New York",
    "sg:classifiers":[
        {
            "category":"Social Services",
            "subcategory":"Child Care",
            "type":"Services"
        },
        {
            "category":"Education",
            "subcategory":"Preschool",
            "type":"Public Place"
        },
        {
            "category":"Education",
            "subcategory":"School",
            "type":"Public Place"
        }
    ],
    "sg:phone":"+1 212 757 2301",
    "sg:postcode":"10019",
    "sg:province":"NY",
    "sg:tags":[
        "elementary",
        "day"
    ],
    "wof:name":"Bright Horizons At 75 Rockefeller Plaza",
    "wof:placetype":"venue"
},
  "geometry": {"coordinates":[-73.981387,40.761157],"type":"Point"}
}