{
  "type": "Feature",
  "properties": {
    "iso:country":"US",
    "sg:address":"114 N Main St",
    "sg:city":"Wellsville",
    "sg:classifiers":[
        {
            "category":"Organizations",
            "subcategory":"Professional Association",
            "type":"Services"
        }
    ],
    "sg:phone":"+1 585 593 5080",
    "sg:postcode":"14895",
    "sg:province":"NY",
    "sg:tags":[
        "chambers",
        "commerce"
    ],
    "wof:name":"Wellsville Chamber Of Commerce",
    "wof:placetype":"venue"
},
  "geometry": {"coordinates":[-77.947682,42.12172],"type":"Point"}
}