{
  "type": "Feature",
  "properties": {
    "addr:full":"3418 Carey Ln Baldwin NY 11510",
    "addr:housenumber":"3418",
    "addr:postcode":"11510",
    "addr:street":"Carey Ln",
    "iso:country":"US",
    "sg:address":"3418 Carey Ln",
    "sg:city":"Baldwin",
    "sg:classifiers":[
        {
            "category":"Wholesale",
            "subcategory":"Apparel",
            "type":"Manufacturing & Wholesale Goods"
        }
    ],
    "sg:phone":"+1 516 868 4186",
    "sg:postcode":"11510",
    "sg:province":"NY",
    "sg:tags":[
        "clothing"
    ],
    "wof:name":"Gertrude Scheige Co",
    "wof:placetype":"venue"
},
  "geometry": {"coordinates":[-73.600432,40.624779],"type":"Point"}
}