{
  "type": "Feature",
  "properties": {
    "iso:country":"US",
    "sg:address":"15 Union St",
    "sg:city":"Sodus",
    "sg:classifiers":[
        {
            "category":"Food & Beverages",
            "subcategory":"Liquor & Beverages",
            "type":"Retail Goods"
        }
    ],
    "sg:phone":"+1   ",
    "sg:postcode":"14551",
    "sg:province":"NY",
    "sg:tags":[
        "alcoholic"
    ],
    "wof:name":"J & R Country Spirits",
    "wof:placetype":"venue"
},
  "geometry": {"coordinates":[-77.064331,43.238657],"type":"Point"}
}