{
  "type": "Feature",
  "properties": {
    "addr:full":"291 W Sunrise Hwy Freeport NY 11520",
    "addr:housenumber":"291",
    "addr:postcode":"11520",
    "addr:street":"W Sunrise Hwy",
    "iso:country":"US",
    "sg:address":"291 W Sunrise Hwy",
    "sg:city":"Freeport",
    "sg:classifiers":[
        {
            "category":"Autos & Motor Vehicles",
            "subcategory":"Automobile Sales",
            "type":"Retail Goods"
        },
        {
            "category":"Retail",
            "subcategory":"Auto Rental",
            "type":"Services"
        }
    ],
    "sg:phone":"+1 516 665 1658",
    "sg:postcode":"11520",
    "sg:province":"NY",
    "sg:tags":[
        "car",
        "used",
        "leasing",
        "truck",
        "new"
    ],
    "sg:website":"http://hasselbmw3.reachlocal.com/?scid=1661881",
    "wof:name":"Hassel BMW on Long Island",
    "wof:placetype":"venue"
},
  "geometry": {"coordinates":[-73.594533,40.655813],"type":"Point"}
}