{
  "type": "Feature",
  "properties": {
    "addr:full":"165 Randolph St Brooklyn NY 11237",
    "addr:housenumber":"165",
    "addr:postcode":"11237",
    "addr:street":"Randolph St",
    "iso:country":"US",
    "sg:address":"165 Randolph St",
    "sg:city":"Brooklyn",
    "sg:classifiers":[
        {
            "category":"Freight",
            "type":"Transportation"
        }
    ],
    "sg:phone":"+1   ",
    "sg:postcode":"11237",
    "sg:province":"NY",
    "sg:tags":[
        "warehouse"
    ],
    "wof:name":"Brooklyn Distribution Center",
    "wof:placetype":"venue"
},
  "geometry": {"coordinates":[-73.924536,40.709928],"type":"Point"}
}