{
  "type": "Feature",
  "properties": {
    "addr:full":"2 Ellish Pkwy Spring Valley NY 10977",
    "addr:housenumber":"2",
    "addr:postcode":"10977",
    "addr:street":"Ellish Pkwy",
    "iso:country":"US",
    "sg:address":"2 Ellish Pkwy",
    "sg:city":"Spring Valley",
    "sg:classifiers":[
        {
            "category":"Organizations",
            "subcategory":"Religious Organization",
            "type":"Services"
        }
    ],
    "sg:phone":"+1 845 425 9846",
    "sg:postcode":"10977",
    "sg:province":"NY",
    "sg:tags":[
        "clergy"
    ],
    "wof:name":"Yechtel Moskowitz",
    "wof:placetype":"venue"
},
  "geometry": {"coordinates":[-74.05659199999999,41.117706],"type":"Point"}
}