{
  "type": "Feature",
  "properties": {
    "addr:full":"1416 Burnet Ave Syracuse NY 13206",
    "addr:housenumber":"1416",
    "addr:postcode":"13206",
    "addr:street":"Burnet Ave",
    "iso:country":"US",
    "sg:address":"1416 Burnet Ave",
    "sg:city":"Syracuse",
    "sg:classifiers":[
        {
            "category":"Home & Garden",
            "subcategory":"Household Appliances",
            "type":"Retail Goods"
        }
    ],
    "sg:phone":"+1 315 471 3603",
    "sg:postcode":"13206",
    "sg:province":"NY",
    "sg:tags":[
        "installs",
        "improvement",
        "full",
        "kitchen",
        "bath"
    ],
    "wof:name":"Home Traditions",
    "wof:placetype":"venue"
},
  "geometry": {"coordinates":[-76.117114,43.055489],"type":"Point"}
}