{
  "type": "Feature",
  "properties": {
    "addr:full":"757 3rd Ave 20th Fl New York NY 10017",
    "addr:housenumber":"757",
    "addr:postcode":"10017",
    "addr:street":"3Rd Ave 20Th Fl",
    "iso:country":"US",
    "sg:address":"757 3rd Ave 20th Fl",
    "sg:city":"New York",
    "sg:classifiers":[
        {
            "category":"Banks & Credit Unions",
            "subcategory":"Financial Services",
            "type":"Services"
        }
    ],
    "sg:phone":"+1 212 376 4799",
    "sg:postcode":"10017",
    "sg:province":"NY",
    "sg:tags":[
        "advising"
    ],
    "sg:website":"www.isakovgroup.com/",
    "wof:name":"Isakov Planning Group",
    "wof:placetype":"venue"
},
  "geometry": {"coordinates":[-73.971475,40.753935],"type":"Point"}
}