{
  "type": "Feature",
  "properties": {
    "addr:full":"703 E Main St Endicott NY 13760",
    "addr:housenumber":"703",
    "addr:postcode":"13760",
    "addr:street":"E Main St",
    "iso:country":"US",
    "sg:address":"703 E Main St",
    "sg:city":"Endicott",
    "sg:classifiers":[
        {
            "category":"Shopping",
            "subcategory":"Used Merchandise",
            "type":"Retail Goods"
        }
    ],
    "sg:phone":"+1   ",
    "sg:postcode":"13760",
    "sg:province":"NY",
    "sg:tags":[
        "organization",
        "religious"
    ],
    "wof:name":"Western Territorial Salvation",
    "wof:placetype":"venue"
},
  "geometry": {"coordinates":[-76.053201,42.096338],"type":"Point"}
}