{
  "type": "Feature",
  "properties": {
    "iso:country":"US",
    "sg:address":"1670 Old Country Rd # 125",
    "sg:city":"Plainview",
    "sg:classifiers":[
        {
            "category":"Communications",
            "subcategory":"Film & Video Production",
            "type":"Services"
        }
    ],
    "sg:phone":"+1 516 349 5218",
    "sg:postcode":"11803",
    "sg:province":"NY",
    "sg:tags":[
        "services-commercial"
    ],
    "sg:website":"http://www.digitalvideodynamix.com",
    "wof:name":"Digital Video Dynamix Inc",
    "wof:placetype":"venue"
},
  "geometry": {"coordinates":[-73.44721199999999,40.781029],"type":"Point"}
}