{
  "type": "Feature",
  "properties": {
    "iso:country":"US",
    "sg:address":"300 Delaware Ave",
    "sg:city":"Buffalo",
    "sg:classifiers":[
        {
            "category":"Professional",
            "subcategory":"Lawyer & Legal Services",
            "type":"Services"
        }
    ],
    "sg:phone":"+1 716 854 7525",
    "sg:postcode":"14202",
    "sg:province":"NY",
    "wof:name":"Apa Jill A Lwyr",
    "wof:placetype":"venue"
},
  "geometry": {"coordinates":[-78.876198,42.892502],"type":"Point"}
}