{
  "type": "Feature",
  "properties": {
    "addr:full":"2484 Co Rd 20 Clifton Springs NY 14432",
    "addr:housenumber":"2484;20",
    "addr:postcode":"14432",
    "addr:street":"Co Rd",
    "iso:country":"US",
    "sg:address":"2484 Co Rd 20",
    "sg:city":"Clifton Springs",
    "sg:classifiers":[
        {
            "category":"Banks & Credit Unions",
            "subcategory":"Bank",
            "type":"Services"
        }
    ],
    "sg:phone":"+1 585 526 6559",
    "sg:postcode":"14432",
    "sg:province":"NY",
    "wof:name":"Wells Fargo Bank",
    "wof:placetype":"venue"
},
  "geometry": {"coordinates":[-77.11907100000001,42.915053],"type":"Point"}
}