{
  "type": "Feature",
  "properties": {
    "iso:country":"US",
    "sg:address":"2418 15th St",
    "sg:city":"Troy",
    "sg:classifiers":[
        {
            "category":"Personal",
            "subcategory":"Shoe Repair & Shine",
            "type":"Services"
        }
    ],
    "sg:phone":"+1 518 272 0864",
    "sg:postcode":"12180",
    "sg:province":"NY",
    "sg:tags":[
        "repairing",
        "boot"
    ],
    "wof:name":"Jim's Quick Shoe Repair",
    "wof:placetype":"venue"
},
  "geometry": {"coordinates":[-73.67425900000001,42.741082],"type":"Point"}
}