{
  "type": "Feature",
  "properties": {
    "iso:country":"US",
    "sg:address":"126 Indian Creek Rd",
    "sg:city":"Ithaca",
    "sg:classifiers":[
        {
            "category":"Social Services",
            "type":"Services"
        },
        {
            "category":"Organizations",
            "subcategory":"Community Association",
            "type":"Services"
        }
    ],
    "sg:phone":"+1 607 277 0488",
    "sg:postcode":"14850",
    "sg:province":"NY",
    "sg:website":"http://www.saexplorers.org",
    "wof:name":"South American Explorers Club",
    "wof:placetype":"venue"
},
  "geometry": {"coordinates":[-76.54243200000001,42.473757],"type":"Point"}
}