{
  "type": "Feature",
  "properties": {
    "iso:country":"US",
    "sg:address":"541 Falmouth Rd",
    "sg:city":"West Babylon",
    "sg:classifiers":[
        {
            "category":"Retail",
            "subcategory":"Auto Repair",
            "type":"Services"
        }
    ],
    "sg:phone":"+1 631 669 3212",
    "sg:postcode":"11704",
    "sg:province":"NY",
    "sg:tags":[
        "repairing",
        "automobile"
    ],
    "wof:name":"Lenmar Auto Svc",
    "wof:placetype":"venue"
},
  "geometry": {"coordinates":[-73.334643,40.716641],"type":"Point"}
}