{
  "type": "Feature",
  "properties": {
    "iso:country":"US",
    "sg:address":"681 Montauk Hwy",
    "sg:city":"Shirley",
    "sg:classifiers":[
        {
            "category":"Travel",
            "subcategory":"Hotels & Motels",
            "type":"Entertainment"
        }
    ],
    "sg:phone":"+1 631 281 9418",
    "sg:postcode":"11967",
    "sg:province":"NY",
    "sg:website":"www.shirleymotel.com",
    "wof:name":"Shirley Motel",
    "wof:placetype":"venue"
},
  "geometry": {"coordinates":[-72.87550400000001,40.800598],"type":"Point"}
}