{
  "type": "Feature",
  "properties": {
    "iso:country":"US",
    "sg:address":"107 Georgian Court Rd",
    "sg:city":"Rochester",
    "sg:classifiers":[
        {
            "category":"Professional",
            "subcategory":"Lawyer & Legal Services",
            "type":"Services"
        }
    ],
    "sg:phone":"+1   ",
    "sg:postcode":"14610",
    "sg:province":"NY",
    "wof:name":"Dominic Pellegrino Atty",
    "wof:placetype":"venue"
},
  "geometry": {"coordinates":[-77.541157,43.132679],"type":"Point"}
}