{
  "type": "Feature",
  "properties": {
    "addr:full":"9 Orchard St Port Washington NY 11050",
    "addr:housenumber":"9",
    "addr:postcode":"11050",
    "addr:street":"Orchard St",
    "iso:country":"US",
    "sg:address":"9 Orchard St",
    "sg:city":"Port Washington",
    "sg:classifiers":[
        {
            "category":"Building & Trades",
            "subcategory":"Construction",
            "type":"Services"
        }
    ],
    "sg:phone":"+1 516 570 2649",
    "sg:postcode":"11050",
    "sg:province":"NY",
    "sg:tags":[
        "contractor"
    ],
    "wof:name":"North Shore Signature Homes",
    "wof:placetype":"venue"
},
  "geometry": {"coordinates":[-73.68003899999999,40.824145],"type":"Point"}
}