{
  "type": "Feature",
  "properties": {
    "addr:full":"3167 Coney Island Ave Brooklyn NY 11235",
    "addr:housenumber":"3167",
    "addr:postcode":"11235",
    "addr:street":"Coney Island Ave",
    "iso:country":"US",
    "sg:address":"3167 Coney Island Ave",
    "sg:city":"Brooklyn",
    "sg:classifiers":[
        {
            "category":"Home & Garden",
            "subcategory":"Hardware",
            "type":"Retail Goods"
        }
    ],
    "sg:phone":"+1   ",
    "sg:postcode":"11235",
    "sg:province":"NY",
    "wof:name":"Stanleys Hardware",
    "wof:placetype":"venue"
},
  "geometry": {"coordinates":[-73.95957799999999,40.578218],"type":"Point"}
}