{
  "type": "Feature",
  "properties": {
    "addr:full":"244 Bullet Hole Rd Mahopac NY 10541",
    "addr:housenumber":"244",
    "addr:postcode":"10541",
    "addr:street":"Bullet Hole Rd",
    "iso:country":"US",
    "sg:address":"244 Bullet Hole Rd",
    "sg:city":"Mahopac",
    "sg:classifiers":[
        {
            "category":"Arts & Performance",
            "subcategory":"Theater",
            "type":"Entertainment"
        }
    ],
    "sg:phone":"+1 845 621 3816",
    "sg:postcode":"10541",
    "sg:province":"NY",
    "sg:tags":[
        "magician"
    ],
    "wof:name":"Jo Jo's Party Pals",
    "wof:placetype":"venue"
},
  "geometry": {"coordinates":[-73.792743,41.387981],"type":"Point"}
}