{
  "type": "Feature",
  "properties": {
    "iso:country":"US",
    "sg:address":"2101 Broadway",
    "sg:city":"Watervliet",
    "sg:classifiers":[
        {
            "category":"Food & Beverages",
            "subcategory":"Specialty",
            "type":"Retail Goods"
        }
    ],
    "sg:phone":"+1   ",
    "sg:postcode":"12189",
    "sg:province":"NY",
    "sg:tags":[
        "holistic",
        "health",
        "care"
    ],
    "wof:name":"Niagara & Herbs Ashanta",
    "wof:placetype":"venue"
},
  "geometry": {"coordinates":[-73.699786,42.731608],"type":"Point"}
}