{
  "type": "Feature",
  "properties": {
    "addr:full":"184 Highland Ave Hamburg NY 14075",
    "addr:housenumber":"184",
    "addr:postcode":"14075",
    "addr:street":"Highland Ave",
    "iso:country":"US",
    "sg:address":"184 Highland Ave",
    "sg:city":"Hamburg",
    "sg:classifiers":[
        {
            "category":"Professional",
            "subcategory":"Management & Consulting",
            "type":"Services"
        }
    ],
    "sg:phone":"+1 716 649 2700",
    "sg:postcode":"14075",
    "sg:province":"NY",
    "sg:tags":[
        "consultant",
        "safety"
    ],
    "wof:name":"Gilham-De Beer Corp",
    "wof:placetype":"venue"
},
  "geometry": {"coordinates":[-78.834102,42.723274],"type":"Point"}
}