{
  "type": "Feature",
  "properties": {
    "addr:full":"6626 Grand Avenue Maspeth NY 11378",
    "addr:housenumber":"6626",
    "addr:postcode":"11378",
    "addr:street":"Grand Avenue",
    "iso:country":"US",
    "sg:address":"6626 Grand Avenue",
    "sg:city":"Maspeth",
    "sg:classifiers":[
        {
            "category":"Food & Beverages",
            "subcategory":"Liquor & Beverages",
            "type":"Retail Goods"
        }
    ],
    "sg:phone":"+1 718 335 6305",
    "sg:postcode":"11378",
    "sg:province":"NY",
    "sg:tags":[
        "beer",
        "spirit",
        "wine"
    ],
    "wof:name":"Happy Spirits",
    "wof:placetype":"venue"
},
  "geometry": {"coordinates":[-73.897997,40.724364],"type":"Point"}
}