{
  "type": "Feature",
  "properties": {
    "addr:full":"8381 Boston State Rd Boston NY 14025",
    "addr:housenumber":"8381",
    "addr:postcode":"14025",
    "addr:street":"Boston State Rd",
    "iso:country":"US",
    "sg:address":"8381 Boston State Rd",
    "sg:city":"Boston",
    "sg:classifiers":[
        {
            "category":"Building & Trades",
            "subcategory":"Electrical",
            "type":"Services"
        }
    ],
    "sg:phone":"+1 716 662 9042",
    "sg:postcode":"14025",
    "sg:province":"NY",
    "sg:tags":[
        "sound",
        "equipment",
        "security",
        "specialization"
    ],
    "wof:name":"Dotzler Security",
    "wof:placetype":"venue"
},
  "geometry": {"coordinates":[-78.746308,42.655614],"type":"Point"}
}