{
  "type": "Feature",
  "properties": {
    "addr:full":"1357 51st St Brooklyn NY 11219",
    "addr:housenumber":"1357",
    "addr:postcode":"11219",
    "addr:street":"51St St",
    "iso:country":"US",
    "sg:address":"1357 51st St",
    "sg:city":"Brooklyn",
    "sg:classifiers":[
        {
            "category":"Organizations",
            "subcategory":"Religious Organization",
            "type":"Services"
        }
    ],
    "sg:phone":"+1 718 633 9344",
    "sg:postcode":"11219",
    "sg:province":"NY",
    "wof:name":"Mrc Inc",
    "wof:placetype":"venue"
},
  "geometry": {"coordinates":[-73.99189800000001,40.633202],"type":"Point"}
}