{
  "type": "Feature",
  "properties": {
    "addr:full":"315 Central Park W New York NY 10025",
    "addr:housenumber":"315",
    "addr:postcode":"10025",
    "addr:street":"Central Park W",
    "iso:country":"US",
    "sg:address":"315 Central Park W",
    "sg:city":"New York",
    "sg:classifiers":[
        {
            "category":"Health Services",
            "subcategory":"Health Practitioner",
            "type":"Services"
        }
    ],
    "sg:phone":"+1   ",
    "sg:postcode":"10025",
    "sg:province":"NY",
    "wof:name":"Kind Deeanne",
    "wof:placetype":"venue"
},
  "geometry": {"coordinates":[-73.96682,40.788775],"type":"Point"}
}