{
  "type": "Feature",
  "properties": {
    "iso:country":"US",
    "sg:address":"832 King St",
    "sg:city":"Woodmere",
    "sg:classifiers":[
        {
            "category":"Home & Garden",
            "subcategory":"Household Appliances",
            "type":"Retail Goods"
        }
    ],
    "sg:phone":"+1 516 295 3445",
    "sg:postcode":"11598",
    "sg:province":"NY",
    "sg:tags":[
        "wholesale",
        "vacuum",
        "cleaners"
    ],
    "wof:name":"Air-Way Sales Corp",
    "wof:placetype":"venue"
},
  "geometry": {"coordinates":[-73.723078,40.636589],"type":"Point"}
}