{
  "type": "Feature",
  "properties": {
    "addr:full":"968 Cauldwell Ave Bronx NY 10456",
    "addr:housenumber":"968",
    "addr:postcode":"10456",
    "addr:street":"Cauldwell Ave",
    "iso:country":"US",
    "sg:address":"968 Cauldwell Ave",
    "sg:city":"Bronx",
    "sg:classifiers":[
        {
            "category":"Education",
            "subcategory":"School",
            "type":"Public Place"
        }
    ],
    "sg:phone":"+1 718 589 1805",
    "sg:postcode":"10456",
    "sg:province":"NY",
    "wof:name":"New York City Teacher Ctr",
    "wof:placetype":"venue"
},
  "geometry": {"coordinates":[-73.90631,40.824342],"type":"Point"}
}