{
  "type": "Feature",
  "properties": {
    "iso:country":"US",
    "sg:address":"925 Prospect Pl",
    "sg:city":"Brooklyn",
    "sg:classifiers":[
        {
            "category":"Sports & Exercise",
            "subcategory":"Gym",
            "type":"Entertainment"
        }
    ],
    "sg:phone":"+1 718 771 0097",
    "sg:postcode":"11213",
    "sg:province":"NY",
    "sg:tags":[
        "fitness",
        "physical",
        "facility"
    ],
    "wof:name":"Five Plus One Inc",
    "wof:placetype":"venue"
},
  "geometry": {"coordinates":[-73.94569300000001,40.674166],"type":"Point"}
}