{
  "type": "Feature",
  "properties": {
    "addr:full":"1811 Curry Rd Schenectady NY 12306",
    "addr:housenumber":"1811",
    "addr:postcode":"12306",
    "addr:street":"Curry Rd",
    "iso:country":"US",
    "sg:address":"1811 Curry Rd",
    "sg:city":"Schenectady",
    "sg:classifiers":[
        {
            "category":"Insurance",
            "subcategory":"Hazard Insurance",
            "type":"Services"
        },
        {
            "category":"Insurance",
            "subcategory":"Insurance Agent",
            "type":"Services"
        },
        {
            "category":"Insurance",
            "subcategory":"Life Insurance",
            "type":"Services"
        }
    ],
    "sg:phone":"+1 518 348 8374",
    "sg:postcode":"12306",
    "sg:province":"NY",
    "sg:tags":[
        "auto"
    ],
    "sg:website":"http://statefarm.mqgroup.com/url.asp?usr=527231",
    "wof:name":"Ochs, Tim - State Farm Insurance Agent",
    "wof:placetype":"venue"
},
  "geometry": {"coordinates":[-73.95939300000001,42.781694],"type":"Point"}
}