{
  "type": "Feature",
  "properties": {
    "iso:country":"US",
    "sg:address":"7 Nostrand Ave",
    "sg:city":"Brentwood",
    "sg:classifiers":[
        {
            "category":"Building & Trades",
            "subcategory":"Cleaning & Sanitation",
            "type":"Services"
        }
    ],
    "sg:phone":"+1 631 231 5409",
    "sg:postcode":"11717",
    "sg:province":"NY",
    "sg:tags":[
        "window"
    ],
    "wof:name":"Shore To Shore Window Cleaning",
    "wof:placetype":"venue"
},
  "geometry": {"coordinates":[-73.237132,40.788305],"type":"Point"}
}