{
  "type": "Feature",
  "properties": {
    "iso:country":"US",
    "sg:address":"3075 Veterans Hwy Ste 201",
    "sg:city":"Ronkonkoma",
    "sg:classifiers":[
        {
            "category":"Professional",
            "subcategory":"Lawyer & Legal Services",
            "type":"Services"
        },
        {
            "category":"Banks & Credit Unions",
            "subcategory":"Financial Services",
            "type":"Services"
        }
    ],
    "sg:phone":"+1 347 200 9307",
    "sg:postcode":"11779",
    "sg:province":"NY",
    "sg:tags":[
        "notary"
    ],
    "sg:website":"www.sapphireconsulting.net",
    "wof:name":"Sapphire Consulting",
    "wof:placetype":"venue"
},
  "geometry": {"coordinates":[-73.13705,40.789294],"type":"Point"}
}