{
  "type": "Feature",
  "properties": {
    "addr:full":"328 Smith Haven Mall Lake Grove NY 11755",
    "addr:housenumber":"328",
    "addr:postcode":"11755",
    "addr:street":"Smith Haven Mall",
    "iso:country":"US",
    "sg:address":"328 Smith Haven Mall",
    "sg:city":"Lake Grove",
    "sg:classifiers":[
        {
            "category":"Restaurant",
            "type":"Food & Drink"
        }
    ],
    "sg:phone":"+1 631 366 6289",
    "sg:postcode":"11755",
    "sg:province":"NY",
    "wof:name":"Friday's",
    "wof:placetype":"venue"
},
  "geometry": {"coordinates":[-73.133202,40.865002],"type":"Point"}
}