{
  "type": "Feature",
  "properties": {
    "iso:country":"US",
    "sg:address":"420 Convent Ave",
    "sg:city":"New York",
    "sg:classifiers":[
        {
            "category":"Professional",
            "subcategory":"Accounting & Tax Preparation",
            "type":"Services"
        }
    ],
    "sg:phone":"+1 212 862 2255",
    "sg:postcode":"10031",
    "sg:province":"NY",
    "sg:tags":[
        "accountant"
    ],
    "wof:name":"Adedeji Barrie CPA",
    "wof:placetype":"venue"
},
  "geometry": {"coordinates":[-73.94436399999999,40.827194],"type":"Point"}
}