{
  "type": "Feature",
  "properties": {
    "addr:full":"210 Cornelia St Plattsburgh NY 12901",
    "addr:housenumber":"210",
    "addr:postcode":"12901",
    "addr:street":"Cornelia St",
    "iso:country":"US",
    "sg:address":"210 Cornelia St",
    "sg:city":"Plattsburgh",
    "sg:classifiers":[
        {
            "category":"Health Services",
            "subcategory":"Doctor",
            "type":"Services"
        }
    ],
    "sg:phone":"+1 518 562 2800",
    "sg:postcode":"12901",
    "sg:province":"NY",
    "wof:name":"Saha Usha MD",
    "wof:placetype":"venue"
},
  "geometry": {"coordinates":[-73.46774000000001,44.698365],"type":"Point"}
}