{
  "type": "Feature",
  "properties": {
    "addr:full":"112 6th St Watkins Glen NY 14891",
    "addr:housenumber":"112",
    "addr:postcode":"14891",
    "addr:street":"6Th St",
    "iso:country":"US",
    "sg:address":"112 6th St",
    "sg:city":"Watkins Glen",
    "sg:classifiers":[
        {
            "category":"Communications",
            "subcategory":"Radio Station",
            "type":"Services"
        }
    ],
    "sg:phone":"+1 607 546 8560",
    "sg:postcode":"14891",
    "sg:province":"NY",
    "sg:tags":[
        "company",
        "broadcasting"
    ],
    "wof:name":"WFLR",
    "wof:placetype":"venue"
},
  "geometry": {"coordinates":[-76.870994,42.37981],"type":"Point"}
}