{
  "type": "Feature",
  "properties": {
    "addr:full":"380 New York Ave Huntington NY 11743",
    "addr:housenumber":"380",
    "addr:postcode":"11743",
    "addr:street":"New York Ave",
    "iso:country":"US",
    "sg:address":"380 New York Ave",
    "sg:city":"Huntington",
    "sg:classifiers":[
        {
            "category":"Professional",
            "subcategory":"Computer Services",
            "type":"Services"
        }
    ],
    "sg:phone":"+1 631 271 0690",
    "sg:postcode":"11743",
    "sg:province":"NY",
    "sg:tags":[
        "programming"
    ],
    "wof:name":"Autotraker",
    "wof:placetype":"venue"
},
  "geometry": {"coordinates":[-73.425978,40.869779],"type":"Point"}
}