{
  "type": "Feature",
  "properties": {
    "addr:full":"100 Luten Ave Staten Island NY 10312",
    "addr:housenumber":"100",
    "addr:postcode":"10312",
    "addr:street":"Luten Ave",
    "iso:country":"US",
    "sg:address":"100 Luten Ave",
    "sg:city":"Staten Island",
    "sg:classifiers":[
        {
            "category":"Recreation",
            "type":"Entertainment"
        }
    ],
    "sg:phone":"+1 718 605 1771",
    "sg:postcode":"10312",
    "sg:province":"NY",
    "sg:tags":[
        "hall",
        "auditorium"
    ],
    "wof:name":"Jewish Community Ctr",
    "wof:placetype":"venue"
},
  "geometry": {"coordinates":[-74.19217399999999,40.528315],"type":"Point"}
}