{
  "type": "Feature",
  "properties": {
    "iso:country":"US",
    "sg:address":"11 Crescent Cir",
    "sg:city":"Holbrook",
    "sg:classifiers":[
        {
            "category":"Real Estate",
            "subcategory":"Real Estate Agent",
            "type":"Services"
        }
    ],
    "sg:phone":"+1 631 563 7516",
    "sg:postcode":"11741",
    "sg:province":"NY",
    "wof:name":"Autumn Ridge Home Owners Assoc",
    "wof:placetype":"venue"
},
  "geometry": {"coordinates":[-73.050133,40.77857],"type":"Point"}
}