{
  "type": "Feature",
  "properties": {
    "addr:full":"60 Willoughby St Brooklyn NY 11201",
    "addr:housenumber":"60",
    "addr:postcode":"11201",
    "addr:street":"Willoughby St",
    "iso:country":"US",
    "sg:address":"60 Willoughby St",
    "sg:city":"Brooklyn",
    "sg:classifiers":[
        {
            "category":"Personal",
            "subcategory":"Shoe Repair & Shine",
            "type":"Services"
        }
    ],
    "sg:phone":"+1 718 875 6392",
    "sg:postcode":"11201",
    "sg:province":"NY",
    "sg:tags":[
        "repairing",
        "boot"
    ],
    "wof:name":"Kim's Shoe Repair",
    "wof:placetype":"venue"
},
  "geometry": {"coordinates":[-73.986977,40.692155],"type":"Point"}
}