{
  "type": "Feature",
  "properties": {
    "addr:full":"3018 31st St Astoria NY 11102",
    "addr:housenumber":"3018",
    "addr:postcode":"11102",
    "addr:street":"31St St",
    "iso:country":"US",
    "sg:address":"3018 31st St",
    "sg:city":"Astoria",
    "sg:classifiers":[
        {
            "category":"Health Services",
            "subcategory":"Dentist",
            "type":"Services"
        }
    ],
    "sg:phone":"+1 718 545 7046",
    "sg:postcode":"11102",
    "sg:province":"NY",
    "sg:website":"www.newsmile4u.com",
    "wof:name":"Mejia Wanda",
    "wof:placetype":"venue"
},
  "geometry": {"coordinates":[-73.92189500000001,40.766515],"type":"Point"}
}