{
  "type": "Feature",
  "properties": {
    "iso:country":"US",
    "sg:address":"29 Kisco Ave",
    "sg:city":"Mt Kisco",
    "sg:classifiers":[
        {
            "category":"Arts & Performance",
            "subcategory":"Theater",
            "type":"Entertainment"
        }
    ],
    "sg:phone":"+1 914 241 7500",
    "sg:postcode":"10549",
    "sg:province":"NY",
    "sg:tags":[
        "television",
        "program",
        "producer"
    ],
    "wof:name":"Urban Picture Works LLC",
    "wof:placetype":"venue"
},
  "geometry": {"coordinates":[-73.728004,41.211503],"type":"Point"}
}