{
  "type": "Feature",
  "properties": {
    "iso:country":"US",
    "sg:address":"13 E 37th Street",
    "sg:city":"New York",
    "sg:classifiers":[
        {
            "category":"Building & Trades",
            "subcategory":"Construction",
            "type":"Services"
        }
    ],
    "sg:phone":"+1 212 683 7173",
    "sg:postcode":"10016",
    "sg:province":"NY",
    "sg:tags":[
        "contractor"
    ],
    "wof:name":"Kowal & Manis Construction",
    "wof:placetype":"venue"
},
  "geometry": {"coordinates":[-73.981781,40.74977],"type":"Point"}
}