{
  "type": "Feature",
  "properties": {
    "addr:full":"3116 W Lake Rd Skaneateles NY 13152",
    "addr:housenumber":"3116",
    "addr:postcode":"13152",
    "addr:street":"W Lake Rd",
    "iso:country":"US",
    "sg:address":"3116 W Lake Rd",
    "sg:city":"Skaneateles",
    "sg:classifiers":[
        {
            "category":"Wholesale",
            "subcategory":"Non-durable Goods",
            "type":"Manufacturing & Wholesale Goods"
        }
    ],
    "sg:phone":"+1 315 685 1725",
    "sg:postcode":"13152",
    "sg:province":"NY",
    "sg:tags":[
        "advertising"
    ],
    "wof:name":"Goldman Promotions",
    "wof:placetype":"venue"
},
  "geometry": {"coordinates":[-76.436606,42.922484],"type":"Point"}
}