{
  "type": "Feature",
  "properties": {
    "iso:country":"US",
    "sg:address":"119 Main St",
    "sg:city":"Irvington",
    "sg:classifiers":[
        {
            "category":"Real Estate",
            "subcategory":"Real Estate Agent",
            "type":"Services"
        }
    ],
    "sg:phone":"+1 914 674 1193",
    "sg:postcode":"10533",
    "sg:province":"NY",
    "wof:name":"Striano Realty Corp",
    "wof:placetype":"venue"
},
  "geometry": {"coordinates":[-73.866083,41.039046],"type":"Point"}
}