{
  "type": "Feature",
  "properties": {
    "iso:country":"US",
    "sg:address":"436 Kenmore Ave",
    "sg:city":"Schenectady",
    "sg:classifiers":[
        {
            "category":"Building & Trades",
            "subcategory":"Construction",
            "type":"Services"
        }
    ],
    "sg:phone":"+1 518 346 5215",
    "sg:postcode":"12306",
    "sg:province":"NY",
    "wof:name":"American Blacktop Paving",
    "wof:placetype":"venue"
},
  "geometry": {"coordinates":[-73.980801,42.791832],"type":"Point"}
}