{
  "type": "Feature",
  "properties": {
    "iso:country":"US",
    "sg:address":"29 W Sunrise Hwy",
    "sg:city":"Lindenhurst",
    "sg:classifiers":[
        {
            "category":"Retail",
            "subcategory":"Auto Rental",
            "type":"Services"
        }
    ],
    "sg:phone":"+1 631 789 8838",
    "sg:postcode":"11757",
    "sg:province":"NY",
    "sg:tags":[
        "renting",
        "automobile"
    ],
    "wof:name":"Avis Rent A Car",
    "wof:placetype":"venue"
},
  "geometry": {"coordinates":[-73.384693,40.697271],"type":"Point"}
}