{
  "type": "Feature",
  "properties": {
    "iso:country":"US",
    "sg:address":"38 Market St Ste 1",
    "sg:city":"Potsdam",
    "sg:classifiers":[
        {
            "category":"Restaurant",
            "type":"Food & Drink"
        }
    ],
    "sg:phone":"+1 315 274 9300",
    "sg:postcode":"13676",
    "sg:province":"NY",
    "sg:tags":[
        "style",
        "family"
    ],
    "wof:name":"Julian's",
    "wof:placetype":"venue"
},
  "geometry": {"coordinates":[-74.986862,44.669788],"type":"Point"}
}