{
  "type": "Feature",
  "properties": {
    "addr:full":"226 Leona St Holbrook NY 11741",
    "addr:housenumber":"226",
    "addr:postcode":"11741",
    "addr:street":"Leona St",
    "iso:country":"US",
    "sg:address":"226 Leona St",
    "sg:city":"Holbrook",
    "sg:classifiers":[
        {
            "category":"Real Estate",
            "subcategory":"Real Estate Agent",
            "type":"Services"
        }
    ],
    "sg:phone":"+1 631 654 1777",
    "sg:postcode":"11741",
    "sg:province":"NY",
    "wof:name":"Realty Connection Of LI Inc",
    "wof:placetype":"venue"
},
  "geometry": {"coordinates":[-73.062837,40.784832],"type":"Point"}
}