{
  "type": "Feature",
  "properties": {
    "iso:country":"US",
    "sg:address":"7069 State St",
    "sg:city":"Sodus",
    "sg:classifiers":[
        {
            "category":"Home & Garden",
            "subcategory":"Garden Supply",
            "type":"Retail Goods"
        }
    ],
    "sg:phone":"+1 315 483 2066",
    "sg:postcode":"14551",
    "sg:province":"NY",
    "sg:tags":[
        "lawn",
        "mower"
    ],
    "wof:name":"Bill's Small Engine & Lawn",
    "wof:placetype":"venue"
},
  "geometry": {"coordinates":[-77.037543,43.23908],"type":"Point"}
}