{
  "type": "Feature",
  "properties": {
    "addr:full":"12 Railroad Ave Eastport NY 11941",
    "addr:housenumber":"12",
    "addr:postcode":"11941",
    "addr:street":"Railroad Ave",
    "iso:country":"US",
    "sg:address":"12 Railroad Ave",
    "sg:city":"Eastport",
    "sg:classifiers":[
        {
            "category":"Retail",
            "subcategory":"Animal Services",
            "type":"Services"
        }
    ],
    "sg:phone":"+1 516 852 7560",
    "sg:postcode":"11941",
    "sg:province":"NY",
    "sg:tags":[
        "equestrian"
    ],
    "wof:name":"Circle of Life Farm Inc",
    "wof:placetype":"venue"
},
  "geometry": {"coordinates":[-72.73137800000001,40.824366],"type":"Point"}
}