{
  "type": "Feature",
  "properties": {
    "iso:country":"US",
    "sg:address":"2010 Seagirt Blvd",
    "sg:city":"Far Rockaway",
    "sg:classifiers":[
        {
            "category":"Home & Garden",
            "subcategory":"Garden Supply",
            "type":"Retail Goods"
        },
        {
            "category":"Real Estate",
            "subcategory":"Real Estate Operator",
            "type":"Services"
        }
    ],
    "sg:phone":"+1 718 471 7800",
    "sg:postcode":"11691",
    "sg:province":"NY",
    "sg:tags":[
        "apartment",
        "nursery",
        "gardening"
    ],
    "sg:website":"www.rentwavecrest.com",
    "wof:name":"Wavecrest Gardens",
    "wof:placetype":"venue"
},
  "geometry": {"coordinates":[-73.754204,40.5952],"type":"Point"}
}