{
  "type": "Feature",
  "properties": {
    "addr:full":"52 Green St Rensselaer NY 12144",
    "addr:housenumber":"52",
    "addr:postcode":"12144",
    "addr:street":"Green St",
    "iso:country":"US",
    "sg:address":"52 Green St",
    "sg:city":"Rensselaer",
    "sg:classifiers":[
        {
            "category":"Professional",
            "subcategory":"Lawyer & Legal Services",
            "type":"Services"
        }
    ],
    "sg:phone":"+1 518 434 0446",
    "sg:postcode":"12144",
    "sg:province":"NY",
    "sg:tags":[
        "attorney"
    ],
    "wof:name":"Millea & Robichaud",
    "wof:placetype":"venue"
},
  "geometry": {"coordinates":[-73.74511099999999,42.637474],"type":"Point"}
}