{
  "type": "Feature",
  "properties": {
    "iso:country":"US",
    "sg:address":"1050 Union Rd",
    "sg:city":"Buffalo",
    "sg:classifiers":[
        {
            "category":"Shopping",
            "subcategory":"Discount & Variety Stores",
            "type":"Retail Goods"
        }
    ],
    "sg:phone":"+1   ",
    "sg:postcode":"14224",
    "sg:province":"NY",
    "sg:tags":[
        "merchandise",
        "general"
    ],
    "wof:name":"Decades Rock Shop",
    "wof:placetype":"venue"
},
  "geometry": {"coordinates":[-78.75354900000001,42.827963],"type":"Point"}
}