{
  "type": "Feature",
  "properties": {
    "addr:full":"61 E Main St Allegany NY 14706",
    "addr:housenumber":"61",
    "addr:postcode":"14706",
    "addr:street":"E Main St",
    "iso:country":"US",
    "sg:address":"61 E Main St",
    "sg:city":"Allegany",
    "sg:classifiers":[
        {
            "category":"Autos & Motor Vehicles",
            "subcategory":"Fuel & Gas Station",
            "type":"Retail Goods"
        }
    ],
    "sg:phone":"+1   ",
    "sg:postcode":"14706",
    "sg:province":"NY",
    "sg:tags":[
        "grocery",
        "station",
        "gasoline"
    ],
    "wof:name":"Kwik - Fill",
    "wof:placetype":"venue"
},
  "geometry": {"coordinates":[-78.49197100000001,42.088403],"type":"Point"}
}