{
  "type": "Feature",
  "properties": {
    "addr:full":"202 Avenue C Brooklyn NY 11218",
    "addr:housenumber":"202",
    "addr:postcode":"11218",
    "addr:street":"Avenue C",
    "iso:country":"US",
    "sg:address":"202 Avenue C",
    "sg:city":"Brooklyn",
    "sg:classifiers":[
        {
            "category":"Education",
            "subcategory":"School",
            "type":"Public Place"
        }
    ],
    "sg:phone":"+1 718 438 4010",
    "sg:postcode":"11218",
    "sg:province":"NY",
    "sg:tags":[
        "high",
        "middle",
        "elementary"
    ],
    "wof:name":"N Y City of",
    "wof:placetype":"venue"
},
  "geometry": {"coordinates":[-73.97746600000001,40.640374],"type":"Point"}
}