{
  "type": "Feature",
  "properties": {
    "iso:country":"US",
    "sg:address":"211 Roxbury Rd",
    "sg:city":"Garden City",
    "sg:classifiers":[
        {
            "category":"Building & Trades",
            "subcategory":"Construction",
            "type":"Services"
        }
    ],
    "sg:phone":"+1 516 351 7696",
    "sg:postcode":"11530",
    "sg:province":"NY",
    "sg:tags":[
        "house"
    ],
    "wof:name":"Roxwell Construction",
    "wof:placetype":"venue"
},
  "geometry": {"coordinates":[-73.663599,40.733285],"type":"Point"}
}