{
  "type": "Feature",
  "properties": {
    "addr:full":"202 Meserole Ave Brooklyn NY 11222",
    "addr:housenumber":"202",
    "addr:postcode":"11222",
    "addr:street":"Meserole Ave",
    "iso:country":"US",
    "sg:address":"202 Meserole Ave",
    "sg:city":"Brooklyn",
    "sg:classifiers":[
        {
            "category":"Building & Trades",
            "subcategory":"Construction",
            "type":"Services"
        }
    ],
    "sg:phone":"+1 718 472 5544",
    "sg:postcode":"11222",
    "sg:province":"NY",
    "sg:tags":[
        "marble",
        "contractor"
    ],
    "wof:name":"Planet Marble & Granite Inc",
    "wof:placetype":"venue"
},
  "geometry": {"coordinates":[-73.94683999999999,40.729031],"type":"Point"}
}