{
  "type": "Feature",
  "properties": {
    "iso:country":"US",
    "sg:address":"395 Adams St",
    "sg:city":"Bedford Hills",
    "sg:classifiers":[
        {
            "category":"Real Estate",
            "subcategory":"Real Estate Agent",
            "type":"Services"
        }
    ],
    "sg:phone":"+1 914 241 3418",
    "sg:postcode":"10507",
    "sg:province":"NY",
    "sg:tags":[
        "inspection"
    ],
    "wof:name":"Lancaster Pest Management",
    "wof:placetype":"venue"
},
  "geometry": {"coordinates":[-73.686925,41.242342],"type":"Point"}
}