{
  "type": "Feature",
  "properties": {
    "addr:full":"1757 Merrick Ave Merrick NY 11566",
    "addr:housenumber":"1757",
    "addr:postcode":"11566",
    "addr:street":"Merrick Ave",
    "iso:country":"US",
    "sg:address":"1757 Merrick Ave",
    "sg:city":"Merrick",
    "sg:classifiers":[
        {
            "category":"Professional",
            "subcategory":"Accounting & Tax Preparation",
            "type":"Services"
        }
    ],
    "sg:phone":"+1 516 623 6500",
    "sg:postcode":"11566",
    "sg:province":"NY",
    "sg:tags":[
        "accountant"
    ],
    "wof:name":"Daniel J Guida CPA",
    "wof:placetype":"venue"
},
  "geometry": {"coordinates":[-73.556972,40.675632],"type":"Point"}
}