{
  "type": "Feature",
  "properties": {
    "addr:full":"2262 Palmer Ave New Rochelle NY 10801",
    "addr:housenumber":"2262",
    "addr:postcode":"10801",
    "addr:street":"Palmer Ave",
    "iso:country":"US",
    "sg:address":"2262 Palmer Ave",
    "sg:city":"New Rochelle",
    "sg:classifiers":[
        {
            "category":"Building & Trades",
            "subcategory":"Construction",
            "type":"Services"
        }
    ],
    "sg:phone":"+1 914 632 6926",
    "sg:postcode":"10801",
    "sg:province":"NY",
    "sg:tags":[
        "contractor"
    ],
    "wof:name":"Demarco Mason Contract",
    "wof:placetype":"venue"
},
  "geometry": {"coordinates":[-73.770381,40.92402],"type":"Point"}
}