{
  "type": "Feature",
  "properties": {
    "iso:country":"US",
    "sg:address":"127 Cuttermill Rd",
    "sg:city":"Great Neck",
    "sg:classifiers":[
        {
            "category":"Shopping",
            "type":"Retail Goods"
        }
    ],
    "sg:phone":"+1 516 466 6240",
    "sg:postcode":"11021",
    "sg:province":"NY",
    "sg:tags":[
        "plant",
        "flower",
        "tree",
        "artificial"
    ],
    "wof:name":"Reliance Trading Corp",
    "wof:placetype":"venue"
},
  "geometry": {"coordinates":[-73.73396,40.782843],"type":"Point"}
}