{
  "type": "Feature",
  "properties": {
    "iso:country":"US",
    "sg:address":"526 Williams Ave",
    "sg:city":"Brooklyn",
    "sg:classifiers":[
        {
            "category":"Retail",
            "subcategory":"Repair Shop",
            "type":"Services"
        }
    ],
    "sg:phone":"+1 718 766 2654",
    "sg:postcode":"11207",
    "sg:province":"NY",
    "sg:tags":[
        "lock",
        "locksmith"
    ],
    "wof:name":"USA Locksmith",
    "wof:placetype":"venue"
},
  "geometry": {"coordinates":[-73.897682,40.6639],"type":"Point"}
}