{
  "type": "Feature",
  "properties": {
    "addr:full":"2710 Edgehill Ave Bronx NY 10463",
    "addr:housenumber":"2710",
    "addr:postcode":"10463",
    "addr:street":"Edgehill Ave",
    "iso:country":"US",
    "sg:address":"2710 Edgehill Ave",
    "sg:city":"Bronx",
    "sg:classifiers":[
        {
            "category":"Real Estate",
            "subcategory":"Real Estate Operator",
            "type":"Services"
        }
    ],
    "sg:phone":"+1 718 546 4007",
    "sg:postcode":"10463",
    "sg:province":"NY",
    "sg:tags":[
        "property"
    ],
    "wof:name":"Bertels Geogina",
    "wof:placetype":"venue"
},
  "geometry": {"coordinates":[-73.913571,40.879721],"type":"Point"}
}