{
  "type": "Feature",
  "properties": {
    "iso:country":"US",
    "sg:address":"1350 King St",
    "sg:city":"Greenwich",
    "sg:classifiers":[
        {
            "category":"Building & Trades",
            "subcategory":"Landscaping Services",
            "type":"Services"
        }
    ],
    "sg:phone":"+1 203 531 9500",
    "sg:postcode":"06831",
    "sg:province":"NY",
    "sg:tags":[
        "construction",
        "landscape"
    ],
    "wof:name":"Diroma L D C",
    "wof:placetype":"venue"
},
  "geometry": {"coordinates":[-73.717044,41.087793],"type":"Point"}
}