{
  "type": "Feature",
  "properties": {
    "addr:full":"875 Manhattan Ave Brooklyn NY 11222",
    "addr:housenumber":"875",
    "addr:postcode":"11222",
    "addr:street":"Manhattan Ave",
    "iso:country":"US",
    "sg:address":"875 Manhattan Ave",
    "sg:city":"Brooklyn",
    "sg:classifiers":[
        {
            "category":"Professional",
            "type":"Services"
        }
    ],
    "sg:phone":"+1 718 383 6709",
    "sg:postcode":"11222",
    "sg:province":"NY",
    "sg:tags":[
        "establishment"
    ],
    "wof:name":"New York City HHC Woodhull",
    "wof:placetype":"venue"
},
  "geometry": {"coordinates":[-73.954283,40.730068],"type":"Point"}
}