{
  "type": "Feature",
  "properties": {
    "addr:full":"721 Ridge Rd Buffalo NY 14218",
    "addr:housenumber":"721",
    "addr:postcode":"14218",
    "addr:street":"Ridge Rd",
    "iso:country":"US",
    "sg:address":"721 Ridge Rd",
    "sg:city":"Buffalo",
    "sg:classifiers":[
        {
            "category":"Restaurant",
            "type":"Food & Drink"
        }
    ],
    "sg:phone":"+1 716 823 0844",
    "sg:postcode":"14218",
    "sg:province":"NY",
    "sg:tags":[
        "eating"
    ],
    "wof:name":"Chopstick House",
    "wof:placetype":"venue"
},
  "geometry": {"coordinates":[-78.824799,42.825901],"type":"Point"}
}