{
  "type": "Feature",
  "properties": {
    "iso:country":"US",
    "sg:address":"16 Lincoln St",
    "sg:city":"Elmont",
    "sg:classifiers":[
        {
            "category":"Personal",
            "type":"Services"
        }
    ],
    "sg:phone":"+1 516 503 0306",
    "sg:postcode":"11003",
    "sg:province":"NY",
    "sg:tags":[
        "assistant"
    ],
    "wof:name":"Altay Trade, Inc.",
    "wof:placetype":"venue"
},
  "geometry": {"coordinates":[-73.69822600000001,40.706977],"type":"Point"}
}