{
  "type": "Feature",
  "properties": {
    "iso:country":"US",
    "sg:address":"307 Rte 22",
    "sg:city":"Goldens Bridge",
    "sg:classifiers":[
        {
            "category":"Social Services",
            "type":"Services"
        }
    ],
    "sg:phone":"+1 914 232 1631",
    "sg:postcode":"10526",
    "sg:province":"NY",
    "sg:tags":[
        "psychologist"
    ],
    "wof:name":"Goldens Bridge Counseling",
    "wof:placetype":"venue"
},
  "geometry": {"coordinates":[-73.67644,41.297298],"type":"Point"}
}