{
  "type": "Feature",
  "properties": {
    "addr:full":"78 Vineyard Ave Yonkers NY 10703",
    "addr:housenumber":"78",
    "addr:postcode":"10703",
    "addr:street":"Vineyard Ave",
    "iso:country":"US",
    "sg:address":"78 Vineyard Ave",
    "sg:city":"Yonkers",
    "sg:classifiers":[
        {
            "category":"Place Of Worship",
            "type":"Public Place"
        }
    ],
    "sg:phone":"+1 914 968 7370",
    "sg:postcode":"10703",
    "sg:province":"NY",
    "sg:tags":[
        "church"
    ],
    "wof:name":"Source Of Life Inc",
    "wof:placetype":"venue"
},
  "geometry": {"coordinates":[-73.88696899999999,40.942374],"type":"Point"}
}