{
  "type": "Feature",
  "properties": {
    "iso:country":"US",
    "sg:address":"4802 10th Ave",
    "sg:city":"Brooklyn",
    "sg:classifiers":[
        {
            "category":"Health Services",
            "subcategory":"Doctor",
            "type":"Services"
        },
        {
            "category":"Health Services",
            "subcategory":"Hospital",
            "type":"Services"
        },
        {
            "category":"Social Services",
            "subcategory":"Child Care",
            "type":"Services"
        },
        {
            "category":"Community Center",
            "type":"Public Place"
        },
        {
            "category":"Health Services",
            "subcategory":"Clinic",
            "type":"Services"
        }
    ],
    "sg:phone":"+1 718 283 6000",
    "sg:postcode":"11219",
    "sg:province":"NY",
    "sg:tags":[
        "educational",
        "cancer",
        "support",
        "treatment",
        "referral",
        "medical"
    ],
    "sg:website":"www.maimonidesmed.org/",
    "wof:name":"Maimonides Medical Center",
    "wof:placetype":"venue"
},
  "geometry": {"coordinates":[-73.998199,40.639599],"type":"Point"}
}