{
  "type": "Feature",
  "properties": {
    "addr:full":"5141 Nesconset Hwy Port Jefferson Sta NY 11776",
    "addr:postcode":"5141;11776",
    "addr:street":"Nesconset Hwy",
    "iso:country":"US",
    "sg:address":"5141 Nesconset Hwy",
    "sg:city":"Port Jefferson Sta",
    "sg:classifiers":[
        {
            "category":"Shopping",
            "subcategory":"Stationery & Office Supplies",
            "type":"Retail Goods"
        },
        {
            "category":"Professional",
            "subcategory":"Printing & Photocopies",
            "type":"Services"
        }
    ],
    "sg:phone":"+1 631 476 9860",
    "sg:postcode":"11776",
    "sg:province":"NY",
    "sg:tags":[
        "equipment"
    ],
    "wof:name":"Staples the Office Superstore",
    "wof:placetype":"venue"
},
  "geometry": {"coordinates":[-73.04969800000001,40.9231],"type":"Point"}
}