{
  "type": "Feature",
  "properties": {
    "addr:full":"10 Ganna Ln Huntington Sta NY 11746",
    "addr:housenumber":"10",
    "addr:postcode":"11746",
    "addr:street":"Ganna Ln",
    "iso:country":"US",
    "sg:address":"10 Ganna Ln",
    "sg:city":"Huntington Sta",
    "sg:classifiers":[
        {
            "category":"Health Services",
            "subcategory":"Health Practitioner",
            "type":"Services"
        }
    ],
    "sg:phone":"+1 631 470 0953",
    "sg:postcode":"11746",
    "sg:province":"NY",
    "sg:tags":[
        "hypnotist"
    ],
    "wof:name":"Stone To Water Therapeutics",
    "wof:placetype":"venue"
},
  "geometry": {"coordinates":[-73.385092,40.848998],"type":"Point"}
}