{
  "type": "Feature",
  "properties": {
    "iso:country":"US",
    "sg:address":"145 Plymouth St",
    "sg:city":"New York",
    "sg:classifiers":[
        {
            "category":"Communications",
            "subcategory":"Newspaper",
            "type":"Services"
        }
    ],
    "sg:phone":"+1 718 722 9204",
    "sg:postcode":"11201",
    "sg:province":"NY",
    "sg:tags":[
        "print",
        "medium"
    ],
    "sg:website":"www.mhpbooks.com",
    "wof:name":"Melville House Publishing",
    "wof:placetype":"venue"
},
  "geometry": {"coordinates":[-73.98750800000001,40.703789],"type":"Point"}
}