{
  "type": "Feature",
  "properties": {
    "addr:full":"58 W Bridge St Oswego NY 13126",
    "addr:housenumber":"58",
    "addr:postcode":"13126",
    "addr:street":"W Bridge St",
    "iso:country":"US",
    "sg:address":"58 W Bridge St",
    "sg:city":"Oswego",
    "sg:classifiers":[
        {
            "category":"Professional",
            "subcategory":"Business Services",
            "type":"Services"
        }
    ],
    "sg:phone":"+1   ",
    "sg:postcode":"13126",
    "sg:province":"NY",
    "wof:name":"Xtreme Underground",
    "wof:placetype":"venue"
},
  "geometry": {"coordinates":[-76.513938,43.455591],"type":"Point"}
}