{
  "type": "Feature",
  "properties": {
    "addr:full":"136 W Main St Batavia NY 14020",
    "addr:housenumber":"136",
    "addr:postcode":"14020",
    "addr:street":"W Main St",
    "iso:country":"US",
    "sg:address":"136 W Main St",
    "sg:city":"Batavia",
    "sg:phone":"+1 718 367 7022",
    "sg:postcode":"14020",
    "sg:province":"NY",
    "sg:website":"http://www.dunkindonuts.com",
    "wof:name":"Dunkin' Donuts",
    "wof:placetype":"venue"
},
  "geometry": {"coordinates":[-78.19149,42.999802],"type":"Point"}
}