{
  "type": "Feature",
  "properties": {
    "addr:full":"93 Cleveland Ave Rockville Centre NY 11570",
    "addr:housenumber":"93",
    "addr:postcode":"11570",
    "addr:street":"Cleveland Ave",
    "iso:country":"US",
    "sg:address":"93 Cleveland Ave",
    "sg:city":"Rockville Centre",
    "sg:classifiers":[
        {
            "category":"Professional",
            "type":"Services"
        }
    ],
    "sg:phone":"+1   ",
    "sg:postcode":"11570",
    "sg:province":"NY",
    "wof:name":"John D Conger Inc",
    "wof:placetype":"venue"
},
  "geometry": {"coordinates":[-73.64389799999999,40.647687],"type":"Point"}
}