{
  "type": "Feature",
  "properties": {
    "addr:full":"40 Rellim Blvd Rochester NY 14606",
    "addr:housenumber":"40",
    "addr:postcode":"14606",
    "addr:street":"Rellim Blvd",
    "iso:country":"US",
    "sg:address":"40 Rellim Blvd",
    "sg:city":"Rochester",
    "sg:classifiers":[
        {
            "category":"Building & Trades",
            "subcategory":"Construction",
            "type":"Services"
        }
    ],
    "sg:phone":"+1 585 426 2267",
    "sg:postcode":"14606",
    "sg:province":"NY",
    "sg:tags":[
        "house"
    ],
    "wof:name":"Cipollas Construction",
    "wof:placetype":"venue"
},
  "geometry": {"coordinates":[-77.693471,43.154889],"type":"Point"}
}