{
  "type": "Feature",
  "properties": {
    "iso:country":"US",
    "sg:address":"747 3rd Ave",
    "sg:city":"New York",
    "sg:classifiers":[
        {
            "category":"Professional",
            "subcategory":"Lawyer & Legal Services",
            "type":"Services"
        }
    ],
    "sg:phone":"+1 212 223 1100",
    "sg:postcode":"10017",
    "sg:province":"NY",
    "wof:name":"Rosen Sanford P Atty",
    "wof:placetype":"venue"
},
  "geometry": {"coordinates":[-73.972397,40.753601],"type":"Point"}
}