{
  "type": "Feature",
  "properties": {
    "iso:country":"US",
    "sg:address":"120 W Park Ave",
    "sg:city":"Long Beach",
    "sg:classifiers":[
        {
            "category":"Personal",
            "subcategory":"Massage",
            "type":"Services"
        }
    ],
    "sg:phone":"+1 516 889 5719",
    "sg:postcode":"11561",
    "sg:province":"NY",
    "wof:name":"New Alternatives Physical Therapy & Massage",
    "wof:placetype":"venue"
},
  "geometry": {"coordinates":[-73.667503,40.5886],"type":"Point"}
}