{
  "type": "Feature",
  "properties": {
    "addr:full":"104 Wolf Rd Albany NY 12205",
    "addr:housenumber":"104",
    "addr:postcode":"12205",
    "addr:street":"Wolf Rd",
    "iso:country":"US",
    "sg:address":"104 Wolf Rd",
    "sg:city":"Albany",
    "sg:classifiers":[
        {
            "category":"Shopping",
            "subcategory":"Books",
            "type":"Retail Goods"
        }
    ],
    "sg:phone":"+1   ",
    "sg:postcode":"12205",
    "sg:province":"NY",
    "wof:name":"Waldenbooks",
    "wof:placetype":"venue"
},
  "geometry": {"coordinates":[-73.808047,42.717631],"type":"Point"}
}