{
  "type": "Feature",
  "properties": {
    "iso:country":"US",
    "sg:address":"29 British American Blvd",
    "sg:city":"Latham",
    "sg:classifiers":[
        {
            "category":"Professional",
            "subcategory":"Engineering",
            "type":"Services"
        }
    ],
    "sg:phone":"+1 518 785 3633",
    "sg:postcode":"12110",
    "sg:province":"NY",
    "sg:tags":[
        "engineer"
    ],
    "wof:name":"Mechanical Dynamics Analysis",
    "wof:placetype":"venue"
},
  "geometry": {"coordinates":[-73.821011,42.759734],"type":"Point"}
}