{
  "type": "Feature",
  "properties": {
    "addr:full":"247 W 37th St New York NY 10018",
    "addr:housenumber":"247",
    "addr:postcode":"10018",
    "addr:street":"W 37Th St",
    "iso:country":"US",
    "sg:address":"247 W 37th St",
    "sg:city":"New York",
    "sg:classifiers":[
        {
            "category":"Manufacturing",
            "subcategory":"Apparel",
            "type":"Manufacturing & Wholesale Goods"
        }
    ],
    "sg:phone":"+1 212 869 9884",
    "sg:postcode":"10018",
    "sg:province":"NY",
    "sg:tags":[
        "sewing",
        "contractor"
    ],
    "wof:name":"Leeman Fashions",
    "wof:placetype":"venue"
},
  "geometry": {"coordinates":[-73.991033,40.753594],"type":"Point"}
}