{
  "type": "Feature",
  "properties": {
    "iso:country":"US",
    "sg:address":"815 Caffrey Ave",
    "sg:city":"Far Rockaway",
    "sg:classifiers":[
        {
            "category":"Organizations",
            "subcategory":"Religious Organization",
            "type":"Services"
        }
    ],
    "sg:phone":"+1 718 327 8646",
    "sg:postcode":"11691",
    "sg:province":"NY",
    "sg:tags":[
        "clergy"
    ],
    "wof:name":"Akiva M Owsianka",
    "wof:placetype":"venue"
},
  "geometry": {"coordinates":[-73.74517400000001,40.601918],"type":"Point"}
}