{
  "type": "Feature",
  "properties": {
    "iso:country":"US",
    "sg:address":"1449 Fillmore Ave",
    "sg:city":"Buffalo",
    "sg:classifiers":[
        {
            "category":"Organizations",
            "subcategory":"Religious Organization",
            "type":"Services"
        }
    ],
    "sg:phone":"+1 716 896 0180",
    "sg:postcode":"14211",
    "sg:province":"NY",
    "sg:tags":[
        "church"
    ],
    "wof:name":"Stairway To Heaven Chr Of God",
    "wof:placetype":"venue"
},
  "geometry": {"coordinates":[-78.839006,42.913721],"type":"Point"}
}