{
  "type": "Feature",
  "properties": {
    "addr:full":"323 Halstead Ave Harrison NY 10528",
    "addr:housenumber":"323",
    "addr:postcode":"10528",
    "addr:street":"Halstead Ave",
    "iso:country":"US",
    "sg:address":"323 Halstead Ave",
    "sg:city":"Harrison",
    "sg:classifiers":[
        {
            "category":"Restaurant",
            "type":"Food & Drink"
        }
    ],
    "sg:phone":"+1 914 777 3477",
    "sg:postcode":"10528",
    "sg:province":"NY",
    "wof:name":"Sansiro Restaurant",
    "wof:placetype":"venue"
},
  "geometry": {"coordinates":[-73.710161,40.969329],"type":"Point"}
}