{
  "type": "Feature",
  "properties": {
    "iso:country":"US",
    "sg:address":"111 Sunset Ave",
    "sg:city":"Syracuse",
    "sg:classifiers":[
        {
            "category":"Wholesale",
            "subcategory":"Machinery & Supplies",
            "type":"Manufacturing & Wholesale Goods"
        }
    ],
    "sg:phone":"+1 315 479 7262",
    "sg:postcode":"13208",
    "sg:province":"NY",
    "sg:tags":[
        "glass",
        "tank",
        "plastic"
    ],
    "wof:name":"Process Control",
    "wof:placetype":"venue"
},
  "geometry": {"coordinates":[-76.15879700000001,43.06457],"type":"Point"}
}