{
  "type": "Feature",
  "properties": {
    "iso:country":"US",
    "sg:address":"10825 72nd Avenue",
    "sg:city":"Forest Hills",
    "sg:classifiers":[
        {
            "category":"Health Services",
            "subcategory":"Doctor",
            "type":"Services"
        }
    ],
    "sg:phone":"+1 718 544 5533",
    "sg:postcode":"11375",
    "sg:province":"NY",
    "wof:name":"Downtown Ophthalmology PC",
    "wof:placetype":"venue"
},
  "geometry": {"coordinates":[-73.842477,40.719594],"type":"Point"}
}