{
  "type": "Feature",
  "properties": {
    "addr:full":"3858 Nostrand Avenue Brooklyn NY 11235",
    "addr:housenumber":"3858",
    "addr:postcode":"11235",
    "addr:street":"Nostrand Avenue",
    "iso:country":"US",
    "sg:address":"3858 Nostrand Avenue",
    "sg:city":"Brooklyn",
    "sg:classifiers":[
        {
            "category":"Insurance",
            "subcategory":"Hazard Insurance",
            "type":"Services"
        }
    ],
    "sg:phone":"+1 718 743 6988",
    "sg:postcode":"11235",
    "sg:province":"NY",
    "sg:website":"www.jillsullivan.com/",
    "wof:name":"State Farm Brooklyn Insurance - Jill Sullivan",
    "wof:placetype":"venue"
},
  "geometry": {"coordinates":[-73.939753,40.589756],"type":"Point"}
}