{
  "type": "Feature",
  "properties": {
    "iso:country":"US",
    "sg:address":"31 Lewis Rd",
    "sg:city":"Binghamton",
    "sg:classifiers":[
        {
            "category":"Manufacturing",
            "subcategory":"Tools & Machinery",
            "type":"Manufacturing & Wholesale Goods"
        }
    ],
    "sg:phone":"+1 607 352 1100",
    "sg:postcode":"13905",
    "sg:province":"NY",
    "sg:tags":[
        "training",
        "devices",
        "simulator"
    ],
    "sg:website":"www.rockwellcollins.com",
    "wof:name":"Rockwell Collins Simulation",
    "wof:placetype":"venue"
},
  "geometry": {"coordinates":[-75.935762,42.143891],"type":"Point"}
}