{
  "type": "Feature",
  "properties": {
    "iso:country":"US",
    "sg:address":"410 W Green St",
    "sg:city":"Ithaca",
    "sg:classifiers":[
        {
            "category":"Professional",
            "subcategory":"Art Services",
            "type":"Services"
        }
    ],
    "sg:phone":"+1 607 272 0771",
    "sg:postcode":"14850",
    "sg:province":"NY",
    "sg:tags":[
        "graphic",
        "designer"
    ],
    "wof:name":"Art Department",
    "wof:placetype":"venue"
},
  "geometry": {"coordinates":[-76.50275000000001,42.43859],"type":"Point"}
}