{
  "type": "Feature",
  "properties": {
    "addr:full":"70 Jane Dr Cheektowaga NY 14227",
    "addr:housenumber":"70",
    "addr:postcode":"14227",
    "addr:street":"Jane Dr",
    "iso:country":"US",
    "sg:address":"70 Jane Dr",
    "sg:city":"Cheektowaga",
    "sg:classifiers":[
        {
            "category":"Building & Trades",
            "subcategory":"Construction",
            "type":"Services"
        }
    ],
    "sg:phone":"+1 716 895 5327",
    "sg:postcode":"14227",
    "sg:province":"NY",
    "sg:tags":[
        "layer",
        "carpet"
    ],
    "wof:name":"John Cummings Carpet Instlltn",
    "wof:placetype":"venue"
},
  "geometry": {"coordinates":[-78.768676,42.880674],"type":"Point"}
}