{
  "type": "Feature",
  "properties": {
    "addr:full":"76 Saranac Ave Lake Placid NY 12946",
    "addr:housenumber":"76",
    "addr:postcode":"12946",
    "addr:street":"Saranac Ave",
    "iso:country":"US",
    "sg:address":"76 Saranac Ave",
    "sg:city":"Lake Placid",
    "sg:classifiers":[
        {
            "category":"Restaurant",
            "type":"Food & Drink"
        }
    ],
    "sg:phone":"+1   ",
    "sg:postcode":"12946",
    "sg:province":"NY",
    "sg:tags":[
        "eating"
    ],
    "wof:name":"Paradox Lodge",
    "wof:placetype":"venue"
},
  "geometry": {"coordinates":[-73.99641,44.294722],"type":"Point"}
}