{
  "type": "Feature",
  "properties": {
    "addr:full":"2 Mullen Rd Shandaken NY 12480",
    "addr:housenumber":"2",
    "addr:postcode":"12480",
    "addr:street":"Mullen Rd",
    "iso:country":"US",
    "sg:address":"2 Mullen Rd",
    "sg:city":"Shandaken",
    "sg:classifiers":[
        {
            "category":"Building & Trades",
            "subcategory":"Cleaning & Sanitation",
            "type":"Services"
        }
    ],
    "sg:phone":"+1 845 688 2000",
    "sg:postcode":"12480",
    "sg:province":"NY",
    "sg:tags":[
        "janitor"
    ],
    "wof:name":"Duoserv Systems Corp",
    "wof:placetype":"venue"
},
  "geometry": {"coordinates":[-74.41342,42.112778],"type":"Point"}
}