{
  "type": "Feature",
  "properties": {
    "addr:full":"286 Spring St Frnt New York NY 10013",
    "addr:housenumber":"286",
    "addr:postcode":"10013",
    "addr:street":"Spring St",
    "iso:country":"US",
    "sg:address":"286 Spring St Frnt",
    "sg:city":"New York",
    "sg:classifiers":[
        {
            "category":"Retail",
            "subcategory":"Portrait Studio",
            "type":"Services"
        },
        {
            "category":"Professional",
            "subcategory":"Art Services",
            "type":"Services"
        }
    ],
    "sg:phone":"+1 212 337 9933",
    "sg:postcode":"10013",
    "sg:province":"NY",
    "sg:tags":[
        "photographer",
        "photography",
        "store"
    ],
    "sg:website":"www.timothybell.com",
    "wof:name":"Bell Timothy Photography",
    "wof:placetype":"venue"
},
  "geometry": {"coordinates":[-74.007401,40.7258],"type":"Point"}
}