{
  "type": "Feature",
  "properties": {
    "addr:full":"731 Erie Blvd W Rome NY 13440",
    "addr:housenumber":"731",
    "addr:postcode":"13440",
    "addr:street":"Erie Blvd W",
    "iso:country":"US",
    "sg:address":"731 Erie Blvd W",
    "sg:city":"Rome",
    "sg:classifiers":[
        {
            "category":"Professional",
            "type":"Services"
        }
    ],
    "sg:phone":"+1 315 336 8450",
    "sg:postcode":"13440",
    "sg:province":"NY",
    "sg:tags":[
        "establishment"
    ],
    "wof:name":"Rome Vaccums",
    "wof:placetype":"venue"
},
  "geometry": {"coordinates":[-75.47251799999999,43.215568],"type":"Point"}
}