{
  "type": "Feature",
  "properties": {
    "iso:country":"US",
    "sg:address":"31 Janet Dr",
    "sg:city":"Plainview",
    "sg:classifiers":[
        {
            "category":"Building & Trades",
            "subcategory":"Construction",
            "type":"Services"
        }
    ],
    "sg:phone":"+1 718 782 9348",
    "sg:postcode":"11803",
    "sg:province":"NY",
    "sg:tags":[
        "nonresidential"
    ],
    "wof:name":"Dynasty Store Front & Cnstr",
    "wof:placetype":"venue"
},
  "geometry": {"coordinates":[-73.496582,40.769743],"type":"Point"}
}