{
  "type": "Feature",
  "properties": {
    "addr:full":"110 Pennsylvania Ave Medford NY 11763",
    "addr:housenumber":"110",
    "addr:postcode":"11763",
    "addr:street":"Pennsylvania Ave",
    "iso:country":"US",
    "sg:address":"110 Pennsylvania Ave",
    "sg:city":"Medford",
    "sg:classifiers":[
        {
            "category":"Retail",
            "subcategory":"Animal Services",
            "type":"Services"
        }
    ],
    "sg:phone":"+1 631 447 6757",
    "sg:postcode":"11763",
    "sg:province":"NY",
    "wof:name":"Megaspirit",
    "wof:placetype":"venue"
},
  "geometry": {"coordinates":[-72.993707,40.805699],"type":"Point"}
}