{
  "type": "Feature",
  "properties": {
    "addr:full":"47 Herb Hill Rd Glen Cove NY 11542",
    "addr:housenumber":"47",
    "addr:postcode":"11542",
    "addr:street":"Herb Hill Rd",
    "iso:country":"US",
    "sg:address":"47 Herb Hill Rd",
    "sg:city":"Glen Cove",
    "sg:classifiers":[
        {
            "category":"Wholesale",
            "subcategory":"Construction Materials",
            "type":"Manufacturing & Wholesale Goods"
        }
    ],
    "sg:phone":"+1 516 671 1842",
    "sg:postcode":"11542",
    "sg:province":"NY",
    "sg:tags":[
        "ready",
        "mix",
        "concrete"
    ],
    "wof:name":"Bona Fide Ready Mix",
    "wof:placetype":"venue"
},
  "geometry": {"coordinates":[-73.636078,40.863268],"type":"Point"}
}