{
  "type": "Feature",
  "properties": {
    "addr:full":"22 Jackson St New York NY 10002",
    "addr:housenumber":"22",
    "addr:postcode":"10002",
    "addr:street":"Jackson St",
    "iso:country":"US",
    "sg:address":"22 Jackson St",
    "sg:city":"New York",
    "sg:classifiers":[
        {
            "category":"Wholesale",
            "subcategory":"Apparel",
            "type":"Manufacturing & Wholesale Goods"
        }
    ],
    "sg:phone":"+1 212 343 9411",
    "sg:postcode":"10002",
    "sg:province":"NY",
    "sg:tags":[
        "lady",
        "sportswear"
    ],
    "wof:name":"Nalsin Sports Ltd",
    "wof:placetype":"venue"
},
  "geometry": {"coordinates":[-73.980672,40.712639],"type":"Point"}
}