{
  "type": "Feature",
  "properties": {
    "addr:full":"231 Commack Road Commack NY 11725",
    "addr:housenumber":"231",
    "addr:postcode":"11725",
    "addr:street":"Commack Road",
    "iso:country":"US",
    "sg:address":"231 Commack Road",
    "sg:city":"Commack",
    "sg:classifiers":[
        {
            "category":"Wholesale",
            "subcategory":"Fruits & Vegetables",
            "type":"Manufacturing & Wholesale Goods"
        }
    ],
    "sg:phone":"+1 631 462 4624",
    "sg:postcode":"11725",
    "sg:province":"NY",
    "sg:tags":[
        "veggie"
    ],
    "sg:website":"www.ediblearrangements.com/",
    "wof:name":"Edible Arrangements",
    "wof:placetype":"venue"
},
  "geometry": {"coordinates":[-73.295331,40.837076],"type":"Point"}
}