{
  "type": "Feature",
  "properties": {
    "addr:full":"17 S Main St Franklinville NY 14737",
    "addr:housenumber":"17",
    "addr:postcode":"14737",
    "addr:street":"S Main St",
    "iso:country":"US",
    "sg:address":"17 S Main St",
    "sg:city":"Franklinville",
    "sg:classifiers":[
        {
            "category":"Food & Beverages",
            "subcategory":"Groceries & Convenience Stores",
            "type":"Retail Goods"
        }
    ],
    "sg:phone":"+1   ",
    "sg:postcode":"14737",
    "sg:province":"NY",
    "sg:tags":[
        "chain"
    ],
    "wof:name":"Rogers Sure Fine",
    "wof:placetype":"venue"
},
  "geometry": {"coordinates":[-78.45809,42.336618],"type":"Point"}
}