{
  "type": "Feature",
  "properties": {
    "addr:full":"2095 Flatbush Ave Brooklyn NY 11234",
    "addr:housenumber":"2095",
    "addr:postcode":"11234",
    "addr:street":"Flatbush Ave",
    "iso:country":"US",
    "sg:address":"2095 Flatbush Ave",
    "sg:city":"Brooklyn",
    "sg:classifiers":[
        {
            "category":"Health Services",
            "subcategory":"Medical Lab",
            "type":"Services"
        },
        {
            "category":"Health Services",
            "subcategory":"Doctor",
            "type":"Services"
        }
    ],
    "sg:phone":"+1 718 338 6868",
    "sg:postcode":"11234",
    "sg:province":"NY",
    "sg:tags":[
        "radiologist",
        "resonance",
        "magnetic",
        "imaging"
    ],
    "wof:name":"Highway Imaging Associates",
    "wof:placetype":"venue"
},
  "geometry": {"coordinates":[-73.93253,40.618791],"type":"Point"}
}