{
  "type": "Feature",
  "properties": {
    "addr:full":"364 Ontario St Hornell NY 14843",
    "addr:housenumber":"364",
    "addr:postcode":"14843",
    "addr:street":"Ontario St",
    "iso:country":"US",
    "sg:address":"364 Ontario St",
    "sg:city":"Hornell",
    "sg:classifiers":[
        {
            "category":"Building & Trades",
            "subcategory":"Electrical",
            "type":"Services"
        }
    ],
    "sg:phone":"+1 607 324 5909",
    "sg:postcode":"14843",
    "sg:province":"NY",
    "sg:tags":[
        "electrical",
        "electric",
        "contractor"
    ],
    "wof:name":"Cappy's Electric",
    "wof:placetype":"venue"
},
  "geometry": {"coordinates":[-77.656677,42.316307],"type":"Point"}
}