{
  "type": "Feature",
  "properties": {
    "iso:country":"US",
    "sg:address":"8 Fairfield Ave",
    "sg:city":"Jamestown",
    "sg:classifiers":[
        {
            "category":"Personal",
            "subcategory":"Beauty Salon",
            "type":"Services"
        }
    ],
    "sg:phone":"+1   ",
    "sg:postcode":"14701",
    "sg:province":"NY",
    "sg:tags":[
        "shop"
    ],
    "wof:name":"House Of Curl",
    "wof:placetype":"venue"
},
  "geometry": {"coordinates":[-79.23977499999999,42.084479],"type":"Point"}
}