{
  "type": "Feature",
  "properties": {
    "iso:country":"US",
    "sg:address":"2424 Jerome Ave",
    "sg:city":"Bronx",
    "sg:classifiers":[
        {
            "category":"Social Services",
            "type":"Services"
        }
    ],
    "sg:phone":"+1 718 563 2274",
    "sg:postcode":"10468",
    "sg:province":"NY",
    "sg:tags":[
        "youth",
        "organization",
        "center"
    ],
    "wof:name":"Youth For Real",
    "wof:placetype":"venue"
},
  "geometry": {"coordinates":[-73.90168300000001,40.861405],"type":"Point"}
}