{
  "type": "Feature",
  "properties": {
    "iso:country":"US",
    "sg:address":"3159 Coney Island Ave",
    "sg:city":"Brooklyn",
    "sg:classifiers":[
        {
            "category":"Cafe",
            "type":"Food & Drink"
        }
    ],
    "sg:menulink":"http://www.allmenus.com/ny/brooklyn/53295-glechik-cafe/menu/",
    "sg:phone":"+1 718 616 0494",
    "sg:postcode":"11235",
    "sg:province":"NY",
    "sg:tags":[
        "american"
    ],
    "wof:name":"Glechik Cafe",
    "wof:placetype":"venue"
},
  "geometry": {"coordinates":[-73.959705,40.578652],"type":"Point"}
}