{
  "type": "Feature",
  "properties": {
    "iso:country":"US",
    "sg:address":"6632 3rd Avenue",
    "sg:city":"Brooklyn",
    "sg:classifiers":[
        {
            "category":"Personal",
            "type":"Services"
        }
    ],
    "sg:phone":"+1 718 492 8997",
    "sg:postcode":"11220",
    "sg:province":"NY",
    "sg:tags":[
        "party",
        "planning",
        "event"
    ],
    "wof:name":"Little People Parties",
    "wof:placetype":"venue"
},
  "geometry": {"coordinates":[-74.025092,40.637971],"type":"Point"}
}