{
  "type": "Feature",
  "properties": {
    "iso:country":"US",
    "sg:address":"41 Pinewood Dr",
    "sg:city":"Commack",
    "sg:classifiers":[
        {
            "category":"Building & Trades",
            "subcategory":"Landscaping Services",
            "type":"Services"
        }
    ],
    "sg:phone":"+1 631 543 2747",
    "sg:postcode":"11725",
    "sg:province":"NY",
    "sg:tags":[
        "lawn",
        "garden"
    ],
    "wof:name":"F & V Landscaping",
    "wof:placetype":"venue"
},
  "geometry": {"coordinates":[-73.278541,40.807501],"type":"Point"}
}