{
  "type": "Feature",
  "properties": {
    "iso:country":"US",
    "sg:address":"1921 Walton Ave",
    "sg:city":"Bronx",
    "sg:classifiers":[
        {
            "category":"Organizations",
            "subcategory":"Religious Organization",
            "type":"Services"
        }
    ],
    "sg:phone":"+1 718 299 7230",
    "sg:postcode":"10453",
    "sg:province":"NY",
    "sg:tags":[
        "church"
    ],
    "wof:name":"Ptl Temple Of The Living God",
    "wof:placetype":"venue"
},
  "geometry": {"coordinates":[-73.90867900000001,40.850858],"type":"Point"}
}