{
  "type": "Feature",
  "properties": {
    "addr:full":"1912 Mott Ave Far Rockaway NY 11691",
    "addr:housenumber":"1912",
    "addr:postcode":"11691",
    "addr:street":"Mott Ave",
    "iso:country":"US",
    "sg:address":"1912 Mott Ave",
    "sg:city":"Far Rockaway",
    "sg:classifiers":[
        {
            "category":"Shopping",
            "subcategory":"Computers & Home Electronics",
            "type":"Retail Goods"
        }
    ],
    "sg:phone":"+1 718 935 9354",
    "sg:postcode":"11691",
    "sg:province":"NY",
    "wof:name":"Satellite Dish Installation",
    "wof:placetype":"venue"
},
  "geometry": {"coordinates":[-73.75203,40.603939],"type":"Point"}
}