{
  "type": "Feature",
  "properties": {
    "addr:full":"7 Arbor Ln Hauppauge NY 11788",
    "addr:housenumber":"7",
    "addr:postcode":"11788",
    "addr:street":"Arbor Ln",
    "iso:country":"US",
    "sg:address":"7 Arbor Ln",
    "sg:city":"Hauppauge",
    "sg:classifiers":[
        {
            "category":"Wholesale",
            "subcategory":"Durable Goods & Equipment",
            "type":"Manufacturing & Wholesale Goods"
        }
    ],
    "sg:phone":"+1 631 724 3744",
    "sg:postcode":"11788",
    "sg:province":"NY",
    "sg:tags":[
        "representative",
        "manufacturer"
    ],
    "wof:name":"D Z Announcements",
    "wof:placetype":"venue"
},
  "geometry": {"coordinates":[-73.194063,40.828928],"type":"Point"}
}