{
  "type": "Feature",
  "properties": {
    "iso:country":"US",
    "sg:address":"180 Winspear Rd",
    "sg:city":"Elma",
    "sg:classifiers":[
        {
            "category":"Building & Trades",
            "subcategory":"Landscaping Services",
            "type":"Services"
        }
    ],
    "sg:phone":"+1 716 655 4385",
    "sg:postcode":"14059",
    "sg:province":"NY",
    "sg:tags":[
        "landscape"
    ],
    "wof:name":"Northwoods Landscape",
    "wof:placetype":"venue"
},
  "geometry": {"coordinates":[-78.67691000000001,42.844636],"type":"Point"}
}