{
  "type": "Feature",
  "properties": {
    "addr:full":"236 5th Ave New York NY 10001",
    "addr:housenumber":"236",
    "addr:postcode":"10001",
    "addr:street":"5Th Ave",
    "iso:country":"US",
    "sg:address":"236 5th Ave",
    "sg:city":"New York",
    "sg:classifiers":[
        {
            "category":"Wholesale",
            "subcategory":"Durable Goods & Equipment",
            "type":"Manufacturing & Wholesale Goods"
        }
    ],
    "sg:phone":"+1 212 213 5504",
    "sg:postcode":"10001",
    "sg:province":"NY",
    "sg:tags":[
        "importer"
    ],
    "wof:name":"Cartina Eyewear Co Inc",
    "wof:placetype":"venue"
},
  "geometry": {"coordinates":[-73.98742,40.744616],"type":"Point"}
}