{
  "type": "Feature",
  "properties": {
    "iso:country":"US",
    "sg:address":"107 Rivington St",
    "sg:city":"New York",
    "sg:classifiers":[
        {
            "category":"Professional",
            "type":"Services"
        }
    ],
    "sg:phone":"+1 212 420 2258",
    "sg:postcode":"10002",
    "sg:province":"NY",
    "sg:tags":[
        "establishment"
    ],
    "wof:name":"Deanna's",
    "wof:placetype":"venue"
},
  "geometry": {"coordinates":[-73.98779999999999,40.719855],"type":"Point"}
}