{
  "type": "Feature",
  "properties": {
    "addr:full":"75 Carson Ave Newburgh NY 12550",
    "addr:housenumber":"75",
    "addr:postcode":"12550",
    "addr:street":"Carson Ave",
    "iso:country":"US",
    "sg:address":"75 Carson Ave",
    "sg:city":"Newburgh",
    "sg:classifiers":[
        {
            "category":"Manufacturing",
            "subcategory":"Building Materials",
            "type":"Manufacturing & Wholesale Goods"
        }
    ],
    "sg:phone":"+1   ",
    "sg:postcode":"12550",
    "sg:province":"NY",
    "sg:tags":[
        "woodwork",
        "custom",
        "cabinet"
    ],
    "wof:name":"Royal Fine Woodworking LTD",
    "wof:placetype":"venue"
},
  "geometry": {"coordinates":[-74.014737,41.493903],"type":"Point"}
}