{
  "type": "Feature",
  "properties": {
    "addr:full":"10 Augusta Ct Purchase NY 10577",
    "addr:postcode":"10577",
    "addr:street":"10 Augusta Ct",
    "iso:country":"US",
    "sg:address":"10 Augusta Ct",
    "sg:city":"Purchase",
    "sg:classifiers":[
        {
            "category":"Building & Trades",
            "subcategory":"Construction",
            "type":"Services"
        }
    ],
    "sg:phone":"+1 914 390 0090",
    "sg:postcode":"10577",
    "sg:province":"NY",
    "sg:tags":[
        "home",
        "builder"
    ],
    "wof:name":"Braeburn Home & Land Co",
    "wof:placetype":"venue"
},
  "geometry": {"coordinates":[-73.735598,41.049032],"type":"Point"}
}