{
  "type": "Feature",
  "properties": {
    "iso:country":"US",
    "sg:address":"1636 State Hwy 9g",
    "sg:city":"Hyde Park",
    "sg:classifiers":[
        {
            "category":"Home & Garden",
            "subcategory":"Carpets & Floor Coverings",
            "type":"Retail Goods"
        }
    ],
    "sg:phone":"+1 845 229 7172",
    "sg:postcode":"12538",
    "sg:province":"NY",
    "sg:tags":[
        "dealer",
        "rug"
    ],
    "wof:name":"John Buchanan Carpet Co",
    "wof:placetype":"venue"
},
  "geometry": {"coordinates":[-73.911404,41.804952],"type":"Point"}
}