{
  "type": "Feature",
  "properties": {
    "iso:country":"US",
    "sg:address":"291 5th Ave",
    "sg:city":"Brooklyn",
    "sg:classifiers":[
        {
            "category":"Restaurant",
            "type":"Food & Drink"
        }
    ],
    "sg:phone":"+1 718 369 3455",
    "sg:postcode":"11215",
    "sg:province":"NY",
    "sg:tags":[
        "peruvian",
        "american",
        "latin"
    ],
    "wof:name":"El Pollo",
    "wof:placetype":"venue"
},
  "geometry": {"coordinates":[-73.982601,40.673611],"type":"Point"}
}