{
  "type": "Feature",
  "properties": {
    "iso:country":"US",
    "sg:address":"4307 Katonah Ave",
    "sg:city":"Bronx",
    "sg:classifiers":[
        {
            "category":"Restaurant",
            "type":"Food & Drink"
        }
    ],
    "sg:phone":"+1 718 994 8337",
    "sg:postcode":"10470",
    "sg:province":"NY",
    "wof:name":"Katonah Pizza & Pasta",
    "wof:placetype":"venue"
},
  "geometry": {"coordinates":[-73.867627,40.899475],"type":"Point"}
}