{
  "type": "Feature",
  "properties": {
    "iso:country":"US",
    "sg:address":"325 Co Rd 30",
    "sg:city":"Salem",
    "sg:classifiers":[
        {
            "category":"Bars & Pubs",
            "type":"Food & Drink"
        }
    ],
    "sg:phone":"+1   ",
    "sg:postcode":"12865",
    "sg:province":"NY",
    "sg:tags":[
        "drinking"
    ],
    "wof:name":"Roadside",
    "wof:placetype":"venue"
},
  "geometry": {"coordinates":[-73.35209999999999,43.170573],"type":"Point"}
}