{
  "type": "Feature",
  "properties": {
    "iso:country":"US",
    "sg:address":"47 N 5th St",
    "sg:city":"Hudson",
    "sg:classifiers":[
        {
            "category":"Social Services",
            "type":"Services"
        }
    ],
    "sg:phone":"+1 518 828 9300",
    "sg:postcode":"12534",
    "sg:province":"NY",
    "sg:tags":[
        "organization",
        "human"
    ],
    "wof:name":"Twin County Alcohol & Substanc",
    "wof:placetype":"venue"
},
  "geometry": {"coordinates":[-73.785236,42.250653],"type":"Point"}
}