{
  "type": "Feature",
  "properties": {
    "iso:country":"US",
    "sg:address":"379 E 10 St",
    "sg:city":"New York",
    "sg:classifiers":[
        {
            "category":"Professional",
            "type":"Services"
        }
    ],
    "sg:phone":"+1 212 979 5463",
    "sg:postcode":"10009",
    "sg:province":"NY",
    "sg:tags":[
        "establishment"
    ],
    "wof:name":"379 E 10 Street LLC",
    "wof:placetype":"venue"
},
  "geometry": {"coordinates":[-73.978605,40.726551],"type":"Point"}
}