{
  "type": "Feature",
  "properties": {
    "addr:full":"137 Cypress Dr Kings Park NY 11754",
    "addr:housenumber":"137",
    "addr:postcode":"11754",
    "addr:street":"Cypress Dr",
    "iso:country":"US",
    "sg:address":"137 Cypress Dr",
    "sg:city":"Kings Park",
    "sg:classifiers":[
        {
            "category":"Building & Trades",
            "subcategory":"Electrical",
            "type":"Services"
        }
    ],
    "sg:phone":"+1 631 724 2103",
    "sg:postcode":"11754",
    "sg:province":"NY",
    "sg:tags":[
        "electric",
        "contractor"
    ],
    "wof:name":"North Harbor Electric",
    "wof:placetype":"venue"
},
  "geometry": {"coordinates":[-73.220845,40.895675],"type":"Point"}
}