{
  "type": "Feature",
  "properties": {
    "iso:country":"US",
    "sg:address":"192 Woodland Ave",
    "sg:city":"New Rochelle",
    "sg:classifiers":[
        {
            "category":"Building & Trades",
            "subcategory":"Construction",
            "type":"Services"
        }
    ],
    "sg:phone":"+1 914 636 4431",
    "sg:postcode":"10805",
    "sg:province":"NY",
    "sg:tags":[
        "house"
    ],
    "wof:name":"Gc Constructors",
    "wof:placetype":"venue"
},
  "geometry": {"coordinates":[-73.78537799999999,40.900378],"type":"Point"}
}