{
  "type": "Feature",
  "properties": {
    "addr:full":"7 Wintergreen Dr Melville NY 11747",
    "addr:housenumber":"7",
    "addr:postcode":"11747",
    "addr:street":"Wintergreen Dr",
    "iso:country":"US",
    "sg:address":"7 Wintergreen Dr",
    "sg:city":"Melville",
    "sg:classifiers":[
        {
            "category":"Building & Trades",
            "subcategory":"Construction",
            "type":"Services"
        }
    ],
    "sg:phone":"+1 631 427 4825",
    "sg:postcode":"11747",
    "sg:province":"NY",
    "sg:tags":[
        "roofing",
        "siding",
        "masonry",
        "contractor"
    ],
    "wof:name":"A & B Roofing Inc",
    "wof:placetype":"venue"
},
  "geometry": {"coordinates":[-73.38633799999999,40.80876],"type":"Point"}
}