{
  "type": "Feature",
  "properties": {
    "iso:country":"US",
    "sg:address":"235 Remsen St",
    "sg:city":"Cohoes",
    "sg:classifiers":[
        {
            "category":"Shopping",
            "type":"Retail Goods"
        }
    ],
    "sg:phone":"+1 518 237 0105",
    "sg:postcode":"12047",
    "sg:province":"NY",
    "sg:tags":[
        "wedding",
        "supply"
    ],
    "wof:name":"Rizzo's Florists",
    "wof:placetype":"venue"
},
  "geometry": {"coordinates":[-73.700395,42.771019],"type":"Point"}
}