{
  "type": "Feature",
  "properties": {
    "iso:country":"US",
    "sg:address":"137 Sands Point Rd",
    "sg:city":"Port Washington",
    "sg:classifiers":[
        {
            "category":"Banks & Credit Unions",
            "subcategory":"Financial Services",
            "type":"Services"
        }
    ],
    "sg:phone":"+1 516 883 3540",
    "sg:postcode":"11050",
    "sg:province":"NY",
    "sg:tags":[
        "company",
        "holding"
    ],
    "wof:name":"Jadx Holdings Inc",
    "wof:placetype":"venue"
},
  "geometry": {"coordinates":[-73.714252,40.848661],"type":"Point"}
}