{
  "type": "Feature",
  "properties": {
    "iso:country":"US",
    "sg:address":"202 State Hwy 146",
    "sg:city":"Mechanicville",
    "sg:classifiers":[
        {
            "category":"Autos & Motor Vehicles",
            "subcategory":"Automobile Sales",
            "type":"Retail Goods"
        }
    ],
    "sg:phone":"+1 518 664 1086",
    "sg:postcode":"12118",
    "sg:province":"NY",
    "sg:tags":[
        "car",
        "dealer"
    ],
    "wof:name":"Jeep Chrysler Plymouth",
    "wof:placetype":"venue"
},
  "geometry": {"coordinates":[-73.726089,42.870065],"type":"Point"}
}