{
  "type": "Feature",
  "properties": {
    "addr:full":"1103 Lower Rd New Hampton NY 10958",
    "addr:housenumber":"1103",
    "addr:postcode":"10958",
    "addr:street":"Lower Rd",
    "iso:country":"US",
    "sg:address":"1103 Lower Rd",
    "sg:city":"New Hampton",
    "sg:classifiers":[
        {
            "category":"Shopping",
            "subcategory":"Computers & Home Electronics",
            "type":"Retail Goods"
        }
    ],
    "sg:phone":"+1 845 374 3522",
    "sg:postcode":"10958",
    "sg:province":"NY",
    "sg:tags":[
        "television",
        "radio"
    ],
    "wof:name":"Grant Charles",
    "wof:placetype":"venue"
},
  "geometry": {"coordinates":[-74.434658,41.37726],"type":"Point"}
}