{
  "type": "Feature",
  "properties": {
    "addr:full":"400 Shaker Rd Albany NY 12211",
    "addr:housenumber":"400",
    "addr:postcode":"12211",
    "addr:street":"Shaker Rd",
    "iso:country":"US",
    "sg:address":"400 Shaker Rd",
    "sg:city":"Albany",
    "sg:classifiers":[
        {
            "category":"Organizations",
            "subcategory":"Religious Organization",
            "type":"Services"
        }
    ],
    "sg:phone":"+1 518 438 6862",
    "sg:postcode":"12211",
    "sg:province":"NY",
    "sg:tags":[
        "church"
    ],
    "wof:name":"Jehovah's Witnesses",
    "wof:placetype":"venue"
},
  "geometry": {"coordinates":[-73.767685,42.69676],"type":"Point"}
}