{
  "type": "Feature",
  "properties": {
    "addr:full":"29 Glade Rd East Hampton NY 11937",
    "addr:housenumber":"29",
    "addr:postcode":"11937",
    "addr:street":"Glade Rd",
    "iso:country":"US",
    "sg:address":"29 Glade Rd",
    "sg:city":"East Hampton",
    "sg:classifiers":[
        {
            "category":"Building & Trades",
            "subcategory":"Electrical",
            "type":"Services"
        }
    ],
    "sg:phone":"+1 631 324 9392",
    "sg:postcode":"11937",
    "sg:province":"NY",
    "sg:tags":[
        "electrical",
        "electric",
        "contractor"
    ],
    "wof:name":"Bridge View Electrics Inc",
    "wof:placetype":"venue"
},
  "geometry": {"coordinates":[-72.162226,41.012579],"type":"Point"}
}