{
  "type": "Feature",
  "properties": {
    "iso:country":"US",
    "sg:address":"303 7th Ave at 8th St",
    "sg:city":"Brooklyn",
    "sg:classifiers":[
        {
            "category":"Personal",
            "subcategory":"Tanning Parlor",
            "type":"Services"
        }
    ],
    "sg:phone":"+1 718 499 9191",
    "sg:postcode":"11215",
    "sg:province":"NY",
    "sg:website":"parkslopetanning.com",
    "wof:name":"Park Slope Tanning",
    "wof:placetype":"venue"
},
  "geometry": {"coordinates":[-73.980923,40.667642],"type":"Point"}
}