{
  "type": "Feature",
  "properties": {
    "addr:full":"795 Kent Ave Brooklyn NY 11205",
    "addr:housenumber":"795",
    "addr:postcode":"11205",
    "addr:street":"Kent Ave",
    "iso:country":"US",
    "sg:address":"795 Kent Ave",
    "sg:city":"Brooklyn",
    "sg:classifiers":[
        {
            "category":"Shopping",
            "subcategory":"Luggage & Leather Goods",
            "type":"Retail Goods"
        }
    ],
    "sg:phone":"+1 718 855 1100",
    "sg:postcode":"11205",
    "sg:province":"NY",
    "wof:name":"Imperial Luggage",
    "wof:placetype":"venue"
},
  "geometry": {"coordinates":[-73.95988199999999,40.697615],"type":"Point"}
}