{
  "type": "Feature",
  "properties": {
    "iso:country":"US",
    "sg:address":"2271 Airport Rd",
    "sg:city":"Johnson City",
    "sg:classifiers":[
        {
            "category":"Building & Trades",
            "subcategory":"Construction",
            "type":"Services"
        }
    ],
    "sg:phone":"+1 607 729 9200",
    "sg:postcode":"13790",
    "sg:province":"NY",
    "sg:tags":[
        "fencing",
        "specialty",
        "contractor"
    ],
    "wof:name":"Universal Fence & Supply Co",
    "wof:placetype":"venue"
},
  "geometry": {"coordinates":[-75.993077,42.20546],"type":"Point"}
}