{
  "type": "Feature",
  "properties": {
    "addr:full":"999 Lehigh Station Rd Henrietta NY 14467",
    "addr:housenumber":"999",
    "addr:postcode":"14467",
    "addr:street":"Lehigh Station Rd",
    "iso:country":"US",
    "sg:address":"999 Lehigh Station Rd",
    "sg:city":"Henrietta",
    "sg:classifiers":[
        {
            "category":"Organizations",
            "subcategory":"Professional Association",
            "type":"Services"
        }
    ],
    "sg:phone":"+1 585 359 9310",
    "sg:postcode":"14467",
    "sg:province":"NY",
    "wof:name":"United Inventors Assn",
    "wof:placetype":"venue"
},
  "geometry": {"coordinates":[-77.64002600000001,43.058793],"type":"Point"}
}