{
  "type": "Feature",
  "properties": {
    "addr:full":"486 Potters Rd Buffalo NY 14220",
    "addr:housenumber":"486",
    "addr:postcode":"14220",
    "addr:street":"Potters Rd",
    "iso:country":"US",
    "sg:address":"486 Potters Rd",
    "sg:city":"Buffalo",
    "sg:classifiers":[
        {
            "category":"Professional",
            "subcategory":"Lawyer & Legal Services",
            "type":"Services"
        }
    ],
    "sg:phone":"+1 716 822 8969",
    "sg:postcode":"14220",
    "sg:province":"NY",
    "wof:name":"Manka Simon F Atty",
    "wof:placetype":"venue"
},
  "geometry": {"coordinates":[-78.79575800000001,42.839385],"type":"Point"}
}