{
  "type": "Feature",
  "properties": {
    "addr:full":"711 Linden St Ogdensburg NY 13669",
    "addr:housenumber":"711",
    "addr:postcode":"13669",
    "addr:street":"Linden St",
    "iso:country":"US",
    "sg:address":"711 Linden St",
    "sg:city":"Ogdensburg",
    "sg:classifiers":[
        {
            "category":"Home & Garden",
            "subcategory":"Household Appliances",
            "type":"Retail Goods"
        }
    ],
    "sg:phone":"+1 315 393 1908",
    "sg:postcode":"13669",
    "sg:province":"NY",
    "wof:name":"Vac Shop",
    "wof:placetype":"venue"
},
  "geometry": {"coordinates":[-75.468361,44.7021],"type":"Point"}
}