{
  "type": "Feature",
  "properties": {
    "addr:full":"70 Lafayette St Frnt New York NY 10013",
    "addr:housenumber":"70",
    "addr:postcode":"10013",
    "addr:street":"Lafayette St",
    "iso:country":"US",
    "sg:address":"70 Lafayette St Frnt",
    "sg:city":"New York",
    "sg:classifiers":[
        {
            "category":"Professional",
            "subcategory":"Lawyer & Legal Services",
            "type":"Services"
        }
    ],
    "sg:phone":"+1 212 571 5500",
    "sg:postcode":"10013",
    "sg:province":"NY",
    "wof:name":"Soloway Robert",
    "wof:placetype":"venue"
},
  "geometry": {"coordinates":[-74.001999,40.716801],"type":"Point"}
}