{
  "type": "Feature",
  "properties": {
    "iso:country":"US",
    "sg:address":"101 3 St",
    "sg:city":"Staten Island",
    "sg:classifiers":[
        {
            "category":"Health Services",
            "subcategory":"Doctor",
            "type":"Services"
        }
    ],
    "sg:phone":"+1 718 987 1880",
    "sg:postcode":"10306",
    "sg:province":"NY",
    "sg:tags":[
        "physician",
        "surgeon"
    ],
    "wof:name":"Daniel Wilen MD",
    "wof:placetype":"venue"
},
  "geometry": {"coordinates":[-74.116871,40.576623],"type":"Point"}
}