{
  "type": "Feature",
  "properties": {
    "iso:country":"US",
    "sg:address":"4408 Jordan Rd",
    "sg:city":"Skaneateles",
    "sg:classifiers":[
        {
            "category":"Shopping",
            "subcategory":"Computers & Home Electronics",
            "type":"Retail Goods"
        }
    ],
    "sg:phone":"+1 315 415 4993",
    "sg:postcode":"13152",
    "sg:province":"NY",
    "sg:tags":[
        "equipment",
        "electronic",
        "supply"
    ],
    "wof:name":"Grady Electronics",
    "wof:placetype":"venue"
},
  "geometry": {"coordinates":[-76.448584,42.982534],"type":"Point"}
}