{
  "type": "Feature",
  "properties": {
    "iso:country":"US",
    "sg:address":"647 Bray Rd",
    "sg:city":"Arcade",
    "sg:classifiers":[
        {
            "category":"Farming",
            "subcategory":"Farm",
            "type":"Manufacturing & Wholesale Goods"
        }
    ],
    "sg:phone":"+1 716 492 5649",
    "sg:postcode":"14009",
    "sg:province":"NY",
    "wof:name":"Hoffman, Francis Martin Farm",
    "wof:placetype":"venue"
},
  "geometry": {"coordinates":[-78.34129299999999,42.52076],"type":"Point"}
}