{
  "type": "Feature",
  "properties": {
    "addr:full":"126 Mill Rd Valley Stream NY 11581",
    "addr:housenumber":"126",
    "addr:postcode":"11581",
    "addr:street":"Mill Rd",
    "iso:country":"US",
    "sg:address":"126 Mill Rd",
    "sg:city":"Valley Stream",
    "sg:classifiers":[
        {
            "category":"Food & Beverages",
            "subcategory":"Groceries & Convenience Stores",
            "type":"Retail Goods"
        }
    ],
    "sg:phone":"+1 516 295 2343",
    "sg:postcode":"11581",
    "sg:province":"NY",
    "wof:name":"A & H Milk Mart",
    "wof:placetype":"venue"
},
  "geometry": {"coordinates":[-73.709765,40.65835],"type":"Point"}
}