{
  "type": "Feature",
  "properties": {
    "iso:country":"US",
    "sg:address":"10 Fair St",
    "sg:city":"Cooperstown",
    "sg:classifiers":[
        {
            "category":"Travel",
            "subcategory":"Hotels & Motels",
            "type":"Entertainment"
        }
    ],
    "sg:phone":"+1 607 547 9511",
    "sg:postcode":"13326",
    "sg:province":"NY",
    "sg:tags":[
        "marina"
    ],
    "wof:name":"Lake Front Motel",
    "wof:placetype":"venue"
},
  "geometry": {"coordinates":[-74.92187699999999,42.701978],"type":"Point"}
}