{
  "type": "Feature",
  "properties": {
    "iso:country":"US",
    "sg:address":"140 Boylan Ln",
    "sg:city":"Blue Point",
    "sg:classifiers":[
        {
            "category":"Professional",
            "subcategory":"Business Services",
            "type":"Services"
        }
    ],
    "sg:phone":"+1 631 363 5299",
    "sg:postcode":"11715",
    "sg:province":"NY",
    "wof:name":"Scb Enterprises",
    "wof:placetype":"venue"
},
  "geometry": {"coordinates":[-73.037132,40.734014],"type":"Point"}
}