{
  "type": "Feature",
  "properties": {
    "addr:full":"4 Campbell Ave Suffern NY 10901",
    "addr:housenumber":"4",
    "addr:postcode":"10901",
    "addr:street":"Campbell Ave",
    "iso:country":"US",
    "sg:address":"4 Campbell Ave",
    "sg:city":"Suffern",
    "sg:classifiers":[
        {
            "category":"Education",
            "subcategory":"School",
            "type":"Public Place"
        }
    ],
    "sg:phone":"+1 845 357 0774",
    "sg:postcode":"10901",
    "sg:province":"NY",
    "sg:tags":[
        "girl",
        "for",
        "secondary"
    ],
    "wof:name":"Bat Torah Academy of Rockland",
    "wof:placetype":"venue"
},
  "geometry": {"coordinates":[-74.127561,41.110406],"type":"Point"}
}