{
  "type": "Feature",
  "properties": {
    "iso:country":"US",
    "sg:address":"1025 Clinton Ave N",
    "sg:city":"Rochester",
    "sg:classifiers":[
        {
            "category":"Organizations",
            "subcategory":"Religious Organization",
            "type":"Services"
        }
    ],
    "sg:phone":"+1 585 544 9540",
    "sg:postcode":"14621",
    "sg:province":"NY",
    "sg:tags":[
        "church"
    ],
    "wof:name":"Triumph The Church & Kingdom",
    "wof:placetype":"venue"
},
  "geometry": {"coordinates":[-77.613508,43.177305],"type":"Point"}
}