{
  "type": "Feature",
  "properties": {
    "addr:full":"160 Elmwood Ave Buffalo NY 14201",
    "addr:housenumber":"160",
    "addr:postcode":"14201",
    "addr:street":"Elmwood Ave",
    "iso:country":"US",
    "sg:address":"160 Elmwood Ave",
    "sg:city":"Buffalo",
    "sg:classifiers":[
        {
            "category":"Personal",
            "subcategory":"Beauty Salon",
            "type":"Services"
        }
    ],
    "sg:phone":"+1 716 882 5365",
    "sg:postcode":"14201",
    "sg:province":"NY",
    "wof:name":"Kenneth James",
    "wof:placetype":"venue"
},
  "geometry": {"coordinates":[-78.877236,42.900351],"type":"Point"}
}