{
  "type": "Feature",
  "properties": {
    "iso:country":"US",
    "sg:address":"1725 Coon Hill Rd",
    "sg:city":"Skaneateles",
    "sg:classifiers":[
        {
            "category":"Recreation",
            "type":"Entertainment"
        }
    ],
    "sg:phone":"+1 315 685 2290",
    "sg:postcode":"13152",
    "sg:province":"NY",
    "sg:tags":[
        "stable"
    ],
    "wof:name":"Omega Dressage Ctr",
    "wof:placetype":"venue"
},
  "geometry": {"coordinates":[-76.38018599999999,42.917936],"type":"Point"}
}