{
  "type": "Feature",
  "properties": {
    "iso:country":"US",
    "sg:address":"2234 3 Ave",
    "sg:city":"New York",
    "sg:classifiers":[
        {
            "category":"Recreation",
            "type":"Entertainment"
        }
    ],
    "sg:phone":"+1   ",
    "sg:postcode":"10035",
    "sg:province":"NY",
    "wof:name":"East Side Gym",
    "wof:placetype":"venue"
},
  "geometry": {"coordinates":[-73.939522,40.798625],"type":"Point"}
}