{
  "type": "Feature",
  "properties": {
    "addr:full":"1042 Oriskany St W Utica NY 13502",
    "addr:housenumber":"1042",
    "addr:postcode":"13502",
    "addr:street":"Oriskany St W",
    "iso:country":"US",
    "sg:address":"1042 Oriskany St W",
    "sg:city":"Utica",
    "sg:classifiers":[
        {
            "category":"Retail",
            "subcategory":"Auto Repair",
            "type":"Services"
        }
    ],
    "sg:phone":"+1 315 798 3713",
    "sg:postcode":"13502",
    "sg:province":"NY",
    "sg:tags":[
        "automobile",
        "inspection"
    ],
    "wof:name":"Sal's Auto Repair",
    "wof:placetype":"venue"
},
  "geometry": {"coordinates":[-75.246298,43.108087],"type":"Point"}
}