{
  "type": "Feature",
  "properties": {
    "addr:full":"21902 Linden Boulevard Cambria Heights NY 11411",
    "addr:housenumber":"21902",
    "addr:postcode":"11411",
    "addr:street":"Linden Boulevard",
    "iso:country":"US",
    "sg:address":"21902 Linden Boulevard",
    "sg:city":"Cambria Heights",
    "sg:classifiers":[
        {
            "category":"Health Services",
            "subcategory":"Doctor",
            "type":"Services"
        }
    ],
    "sg:phone":"+1 718 527 2850",
    "sg:postcode":"11411",
    "sg:province":"NY",
    "wof:name":"Robinson Sandra MD",
    "wof:placetype":"venue"
},
  "geometry": {"coordinates":[-73.74076700000001,40.695225],"type":"Point"}
}