{
  "type": "Feature",
  "properties": {
    "addr:full":"92 State St Staten Island NY 10310",
    "addr:housenumber":"92",
    "addr:postcode":"10310",
    "addr:street":"State St",
    "iso:country":"US",
    "sg:address":"92 State St",
    "sg:city":"Staten Island",
    "sg:classifiers":[
        {
            "category":"Building & Trades",
            "subcategory":"Construction",
            "type":"Services"
        }
    ],
    "sg:phone":"+1 718 981 0770",
    "sg:postcode":"10310",
    "sg:province":"NY",
    "sg:tags":[
        "contractor",
        "architectural",
        "metalwork",
        "mfg"
    ],
    "wof:name":"Pino Ornamental Iron Works",
    "wof:placetype":"venue"
},
  "geometry": {"coordinates":[-74.11782599999999,40.634366],"type":"Point"}
}