{
  "type": "Feature",
  "properties": {
    "addr:full":"3456 Fulton St Brooklyn NY 11208",
    "addr:housenumber":"3456",
    "addr:postcode":"11208",
    "addr:street":"Fulton St",
    "iso:country":"US",
    "sg:address":"3456 Fulton St",
    "sg:city":"Brooklyn",
    "sg:classifiers":[
        {
            "category":"Wholesale",
            "subcategory":"Auto Parts",
            "type":"Manufacturing & Wholesale Goods"
        }
    ],
    "sg:phone":"+1 718 277 4130",
    "sg:postcode":"11208",
    "sg:province":"NY",
    "sg:tags":[
        "automobile",
        "supply"
    ],
    "wof:name":"Jolan Transportation",
    "wof:placetype":"venue"
},
  "geometry": {"coordinates":[-73.867986,40.684731],"type":"Point"}
}