{
  "type": "Feature",
  "properties": {
    "addr:full":"5510 8th Avenue Brooklyn NY 11220",
    "addr:housenumber":"5510",
    "addr:postcode":"11220",
    "addr:street":"8Th Avenue",
    "iso:country":"US",
    "sg:address":"5510 8th Avenue",
    "sg:city":"Brooklyn",
    "sg:classifiers":[
        {
            "category":"Coffee & Tea",
            "type":"Food & Drink"
        }
    ],
    "sg:postcode":"11220",
    "sg:province":"NY",
    "sg:website":"www.korimono.com/",
    "wof:name":"Korimono",
    "wof:placetype":"venue"
},
  "geometry": {"coordinates":[-74.007053,40.638239],"type":"Point"}
}