{
  "type": "Feature",
  "properties": {
    "addr:full":"5893 Camp Rd Hamburg NY 14075",
    "addr:housenumber":"5893",
    "addr:postcode":"14075",
    "addr:street":"Camp Rd",
    "iso:country":"US",
    "sg:address":"5893 Camp Rd",
    "sg:city":"Hamburg",
    "sg:classifiers":[
        {
            "category":"Banks & Credit Unions",
            "subcategory":"Bank",
            "type":"Services"
        }
    ],
    "sg:phone":"+1 716 312 0055",
    "sg:postcode":"14075",
    "sg:province":"NY",
    "sg:tags":[
        "loan",
        "real estate"
    ],
    "wof:name":"Expert Funding",
    "wof:placetype":"venue"
},
  "geometry": {"coordinates":[-78.836646,42.728907],"type":"Point"}
}