{
  "type": "Feature",
  "properties": {
    "iso:country":"US",
    "sg:address":"2701 Decatur Ave",
    "sg:city":"Bronx",
    "sg:classifiers":[
        {
            "category":"Restaurant",
            "type":"Food & Drink"
        }
    ],
    "sg:phone":"+1 718 741 0432",
    "sg:postcode":"10458",
    "sg:province":"NY",
    "sg:tags":[
        "delicatessen"
    ],
    "wof:name":"Ocoa Deli Grocery",
    "wof:placetype":"venue"
},
  "geometry": {"coordinates":[-73.88809999999999,40.865473],"type":"Point"}
}