{
  "type": "Feature",
  "properties": {
    "addr:full":"313 W Jericho Tpke Huntington NY 11743",
    "addr:housenumber":"313",
    "addr:postcode":"11743",
    "addr:street":"W Jericho Tpke",
    "iso:country":"US",
    "sg:address":"313 W Jericho Tpke",
    "sg:city":"Huntington",
    "sg:classifiers":[
        {
            "category":"Retail",
            "subcategory":"Car Wash",
            "type":"Services"
        }
    ],
    "sg:phone":"+1 631 271 3810",
    "sg:postcode":"11743",
    "sg:province":"NY",
    "sg:tags":[
        "automobile",
        "detail",
        "clean"
    ],
    "wof:name":"Gold Coast Detailing Inc",
    "wof:placetype":"venue"
},
  "geometry": {"coordinates":[-73.42694400000001,40.82882],"type":"Point"}
}