{
  "type": "Feature",
  "properties": {
    "iso:country":"US",
    "sg:address":"308 92nd St",
    "sg:city":"Brooklyn",
    "sg:classifiers":[
        {
            "category":"Home & Garden",
            "subcategory":"Carpets & Floor Coverings",
            "type":"Retail Goods"
        }
    ],
    "sg:phone":"+1 718 233 3815",
    "sg:postcode":"11209",
    "sg:province":"NY",
    "sg:tags":[
        "flooring"
    ],
    "wof:name":"Marble Repairs & Installation",
    "wof:placetype":"venue"
},
  "geometry": {"coordinates":[-74.03238,40.619424],"type":"Point"}
}