{
  "type": "Feature",
  "properties": {
    "iso:country":"US",
    "sg:address":"2631 Phelps Rd",
    "sg:city":"Mc Graw",
    "sg:classifiers":[
        {
            "category":"Manufacturing",
            "subcategory":"Printing",
            "type":"Manufacturing & Wholesale Goods"
        }
    ],
    "sg:phone":"+1 607 756 8434",
    "sg:postcode":"13101",
    "sg:province":"NY",
    "sg:tags":[
        "publisher"
    ],
    "sg:website":"www.goldstardirectory.com",
    "wof:name":"Lee Publications Inc",
    "wof:placetype":"venue"
},
  "geometry": {"coordinates":[-76.10060799999999,42.629677],"type":"Point"}
}