{
  "type": "Feature",
  "properties": {
    "addr:full":"152 E 110th St Manhattan NY 10029",
    "addr:housenumber":"152",
    "addr:postcode":"10029",
    "addr:street":"E 110Th St",
    "iso:country":"US",
    "sg:address":"152 E 110th St",
    "sg:city":"Manhattan",
    "sg:classifiers":[
        {
            "category":"Restaurant",
            "type":"Food & Drink"
        }
    ],
    "sg:phone":"+1 212 369 1657",
    "sg:postcode":"10029",
    "sg:province":"NY",
    "sg:tags":[
        "pizza"
    ],
    "sg:website":"dolcevitapizzerianyc.com",
    "wof:name":"Dolce Vita Pizzeria",
    "wof:placetype":"venue"
},
  "geometry": {"coordinates":[-73.94431,40.79451],"type":"Point"}
}