{
  "type": "Feature",
  "properties": {
    "addr:full":"111 S Kensico Ave White Plains NY 10601",
    "addr:housenumber":"111",
    "addr:postcode":"10601",
    "addr:street":"S Kensico Ave",
    "iso:country":"US",
    "sg:address":"111 S Kensico Ave",
    "sg:city":"White Plains",
    "sg:classifiers":[
        {
            "category":"Social Services",
            "type":"Services"
        }
    ],
    "sg:phone":"+1 914 422 1378",
    "sg:postcode":"10601",
    "sg:province":"NY",
    "sg:tags":[
        "government"
    ],
    "wof:name":"White Plains Youth Svc",
    "wof:placetype":"venue"
},
  "geometry": {"coordinates":[-73.759135,41.037417],"type":"Point"}
}