{
  "type": "Feature",
  "properties": {
    "iso:country":"US",
    "sg:address":"6928 US Hwy 11",
    "sg:city":"Potsdam",
    "sg:classifiers":[
        {
            "category":"Shopping",
            "subcategory":"Gifts & Souvenirs",
            "type":"Retail Goods"
        }
    ],
    "sg:phone":"+1   ",
    "sg:postcode":"13676",
    "sg:province":"NY",
    "sg:tags":[
        "shop",
        "jewelry",
        "costume",
        "accessory"
    ],
    "wof:name":"Colonial House Gift Shop",
    "wof:placetype":"venue"
},
  "geometry": {"coordinates":[-75.053078,44.647165],"type":"Point"}
}