{
  "type": "Feature",
  "properties": {
    "addr:full":"95 Highland Ave Eastchester NY 10709",
    "addr:housenumber":"95",
    "addr:postcode":"10709",
    "addr:street":"Highland Ave",
    "iso:country":"US",
    "sg:address":"95 Highland Ave",
    "sg:city":"Eastchester",
    "sg:classifiers":[
        {
            "category":"Professional",
            "subcategory":"Business Services",
            "type":"Services"
        }
    ],
    "sg:phone":"+1   ",
    "sg:postcode":"10709",
    "sg:province":"NY",
    "wof:name":"Luciano Associates Inc",
    "wof:placetype":"venue"
},
  "geometry": {"coordinates":[-73.810581,40.948402],"type":"Point"}
}