{
  "type": "Feature",
  "properties": {
    "iso:country":"US",
    "sg:address":"222 W 38th St",
    "sg:city":"New York",
    "sg:classifiers":[
        {
            "category":"Shopping",
            "subcategory":"Used Merchandise",
            "type":"Retail Goods"
        }
    ],
    "sg:phone":"+1 212 221 6433",
    "sg:postcode":"10018",
    "sg:province":"NY",
    "sg:tags":[
        "clothing"
    ],
    "wof:name":"Top Tex Trimming Inc",
    "wof:placetype":"venue"
},
  "geometry": {"coordinates":[-73.991185,40.754373],"type":"Point"}
}