{
  "type": "Feature",
  "properties": {
    "addr:full":"15 Brower Ave Saratoga Springs NY 12866",
    "addr:housenumber":"15",
    "addr:postcode":"12866",
    "addr:street":"Brower Ave",
    "iso:country":"US",
    "sg:address":"15 Brower Ave",
    "sg:city":"Saratoga Springs",
    "sg:classifiers":[
        {
            "category":"Building & Trades",
            "subcategory":"Electrical",
            "type":"Services"
        }
    ],
    "sg:phone":"+1 518 587 3306",
    "sg:postcode":"12866",
    "sg:province":"NY",
    "sg:tags":[
        "work",
        "electrical"
    ],
    "wof:name":"Faiola Electric",
    "wof:placetype":"venue"
},
  "geometry": {"coordinates":[-73.77282,43.104578],"type":"Point"}
}