{
  "type": "Feature",
  "properties": {
    "iso:country":"US",
    "sg:address":"469 Fishkill Ave",
    "sg:city":"Beacon",
    "sg:classifiers":[
        {
            "category":"Restaurant",
            "type":"Food & Drink"
        }
    ],
    "sg:phone":"+1   ",
    "sg:postcode":"12508",
    "sg:province":"NY",
    "sg:tags":[
        "drinking",
        "eating"
    ],
    "wof:name":"Di Nardis Restrnt",
    "wof:placetype":"venue"
},
  "geometry": {"coordinates":[-73.947447,41.515192],"type":"Point"}
}