{
  "type": "Feature",
  "properties": {
    "addr:full":"2823 Squab Hollow Rd Troupsburg NY 14885",
    "addr:housenumber":"2823",
    "addr:postcode":"14885",
    "addr:street":"Squab Hollow Rd",
    "iso:country":"US",
    "sg:address":"2823 Squab Hollow Rd",
    "sg:city":"Troupsburg",
    "sg:classifiers":[
        {
            "category":"Farming",
            "subcategory":"Farm & Veterinary Services",
            "type":"Manufacturing & Wholesale Goods"
        }
    ],
    "sg:phone":"+1 607 525 6274",
    "sg:postcode":"14885",
    "sg:province":"NY",
    "sg:tags":[
        "insemination"
    ],
    "wof:name":"Sire Power Inc",
    "wof:placetype":"venue"
},
  "geometry": {"coordinates":[-77.590684,42.025976],"type":"Point"}
}