{
  "type": "Feature",
  "properties": {
    "addr:full":"17 Seth Canyon Dr Mount Kisco NY 10549",
    "addr:housenumber":"17",
    "addr:postcode":"10549",
    "addr:street":"Seth Canyon Dr",
    "iso:country":"US",
    "sg:address":"17 Seth Canyon Dr",
    "sg:city":"Mount Kisco",
    "sg:classifiers":[
        {
            "category":"Communications",
            "subcategory":"Film & Video Production",
            "type":"Services"
        }
    ],
    "sg:phone":"+1 914 242 5112",
    "sg:postcode":"10549",
    "sg:province":"NY",
    "sg:tags":[
        "distribution",
        "television"
    ],
    "wof:name":"Otto Preminger Films Ltd",
    "wof:placetype":"venue"
},
  "geometry": {"coordinates":[-73.74325399999999,41.232744],"type":"Point"}
}