{
  "type": "Feature",
  "properties": {
    "addr:full":"130 Ave P Brooklyn NY 11204",
    "addr:housenumber":"130",
    "addr:postcode":"11204",
    "addr:street":"Ave P",
    "iso:country":"US",
    "sg:address":"130 Ave P",
    "sg:city":"Brooklyn",
    "sg:classifiers":[
        {
            "category":"Health Services",
            "subcategory":"Doctor",
            "type":"Services"
        },
        {
            "category":"Health Services",
            "subcategory":"Health Practitioner",
            "type":"Services"
        }
    ],
    "sg:phone":"+1 718 372 7434",
    "sg:postcode":"11204",
    "sg:province":"NY",
    "sg:tags":[
        "medicine",
        "nutritionist",
        "practice",
        "internal",
        "family"
    ],
    "sg:website":"www.guptagastro.com",
    "wof:name":"Gupta Gastro Associates - Brooklyn Gastroenterology",
    "wof:placetype":"venue"
},
  "geometry": {"coordinates":[-73.983437,40.607666],"type":"Point"}
}