{
  "type": "Feature",
  "properties": {
    "addr:full":"132 Thimbleberry Rd Ballston Spa NY 12020",
    "addr:housenumber":"132",
    "addr:postcode":"12020",
    "addr:street":"Thimbleberry Rd",
    "iso:country":"US",
    "sg:address":"132 Thimbleberry Rd",
    "sg:city":"Ballston Spa",
    "sg:classifiers":[
        {
            "category":"Shopping",
            "type":"Retail Goods"
        }
    ],
    "sg:phone":"+1 518 899 4790",
    "sg:postcode":"12020",
    "sg:province":"NY",
    "sg:tags":[
        "plaque"
    ],
    "wof:name":"A M Tech Inc",
    "wof:placetype":"venue"
},
  "geometry": {"coordinates":[-73.771418,42.976507],"type":"Point"}
}