{
  "type": "Feature",
  "properties": {
    "addr:full":"22 Laura Ln Warwick NY 10990",
    "addr:housenumber":"22",
    "addr:postcode":"10990",
    "addr:street":"Laura Ln",
    "iso:country":"US",
    "sg:address":"22 Laura Ln",
    "sg:city":"Warwick",
    "sg:classifiers":[
        {
            "category":"Wholesale",
            "subcategory":"Medical Equipment & Supplies",
            "type":"Manufacturing & Wholesale Goods"
        }
    ],
    "sg:phone":"+1 845 986 8824",
    "sg:postcode":"10990",
    "sg:province":"NY",
    "sg:tags":[
        "physician",
        "surgeon"
    ],
    "wof:name":"Physicians Debif Resources LLC",
    "wof:placetype":"venue"
},
  "geometry": {"coordinates":[-74.364874,41.267278],"type":"Point"}
}