{
  "type": "Feature",
  "properties": {
    "addr:full":"7 Wendy Rd Wappingers Falls NY 12590",
    "addr:housenumber":"7",
    "addr:postcode":"12590",
    "addr:street":"Wendy Rd",
    "iso:country":"US",
    "sg:address":"7 Wendy Rd",
    "sg:city":"Wappingers Falls",
    "sg:classifiers":[
        {
            "category":"Building & Trades",
            "subcategory":"Electrical",
            "type":"Services"
        }
    ],
    "sg:phone":"+1 845 298 0033",
    "sg:postcode":"12590",
    "sg:province":"NY",
    "sg:tags":[
        "electrician"
    ],
    "wof:name":"Jmv Electrical Contractor",
    "wof:placetype":"venue"
},
  "geometry": {"coordinates":[-73.89340199999999,41.6105],"type":"Point"}
}