{
  "type": "Feature",
  "properties": {
    "iso:country":"US",
    "sg:address":"2693 Middle Country Rd",
    "sg:city":"Lake Grove",
    "sg:classifiers":[
        {
            "category":"Education",
            "subcategory":"Special Training",
            "type":"Public Place"
        }
    ],
    "sg:phone":"+1 631 544 1100",
    "sg:postcode":"11755",
    "sg:province":"NY",
    "sg:tags":[
        "school",
        "instruction",
        "driving"
    ],
    "sg:website":"suffolkautodrivingschools.com",
    "wof:name":"Suffolk Auto Driving School",
    "wof:placetype":"venue"
},
  "geometry": {"coordinates":[-73.108662,40.859714],"type":"Point"}
}