{
  "type": "Feature",
  "properties": {
    "addr:full":"175 King St Chappaqua NY 10514",
    "addr:housenumber":"175",
    "addr:postcode":"10514",
    "addr:street":"King St",
    "iso:country":"US",
    "sg:address":"175 King St",
    "sg:city":"Chappaqua",
    "sg:classifiers":[
        {
            "category":"Health Services",
            "subcategory":"Health Practitioner",
            "type":"Services"
        }
    ],
    "sg:phone":"+1 914 238 0041",
    "sg:postcode":"10514",
    "sg:province":"NY",
    "sg:tags":[
        "therapist",
        "physical"
    ],
    "wof:name":"Chappaqua Chiropractic Care",
    "wof:placetype":"venue"
},
  "geometry": {"coordinates":[-73.77221900000001,41.159153],"type":"Point"}
}