{
  "type": "Feature",
  "properties": {
    "addr:full":"197 N 8th St Brooklyn NY 11211",
    "addr:housenumber":"197",
    "addr:postcode":"11211",
    "addr:street":"N 8Th St",
    "iso:country":"US",
    "sg:address":"197 N 8th St",
    "sg:city":"Brooklyn",
    "sg:classifiers":[
        {
            "category":"Food & Beverages",
            "subcategory":"Liquor & Beverages",
            "type":"Retail Goods"
        }
    ],
    "sg:phone":"+1 718 554 0385",
    "sg:postcode":"11211",
    "sg:province":"NY",
    "sg:tags":[
        "beer",
        "spirit",
        "wine"
    ],
    "wof:name":"Eight & Driggs Wine and Liquors",
    "wof:placetype":"venue"
},
  "geometry": {"coordinates":[-73.95567699999999,40.717635],"type":"Point"}
}