{
  "type": "Feature",
  "properties": {
    "addr:full":"15 E 4th St Jamestown NY 14701",
    "addr:housenumber":"15",
    "addr:postcode":"14701",
    "addr:street":"E 4Th St",
    "iso:country":"US",
    "sg:address":"15 E 4th St",
    "sg:city":"Jamestown",
    "sg:classifiers":[
        {
            "category":"Banks & Credit Unions",
            "subcategory":"Investment Brokerage",
            "type":"Services"
        }
    ],
    "sg:phone":"+1 716 483 2003",
    "sg:postcode":"14701",
    "sg:province":"NY",
    "sg:tags":[
        "consultant",
        "planning",
        "management",
        "retirement"
    ],
    "wof:name":"Chautauqua 401k",
    "wof:placetype":"venue"
},
  "geometry": {"coordinates":[-79.240863,42.097332],"type":"Point"}
}