{
  "type": "Feature",
  "properties": {
    "addr:full":"200 Carpenter Ave Mount Kisco NY 10549",
    "addr:housenumber":"200",
    "addr:postcode":"10549",
    "addr:street":"Carpenter Ave",
    "iso:country":"US",
    "sg:address":"200 Carpenter Ave",
    "sg:city":"Mount Kisco",
    "sg:classifiers":[
        {
            "category":"Real Estate",
            "subcategory":"Real Estate Services",
            "type":"Services"
        }
    ],
    "sg:phone":"+1 914 666 7578",
    "sg:postcode":"10549",
    "sg:province":"NY",
    "sg:tags":[
        "management",
        "property"
    ],
    "wof:name":"Mt Kisco Housing Authority",
    "wof:placetype":"venue"
},
  "geometry": {"coordinates":[-73.72519699999999,41.212101],"type":"Point"}
}