{
  "type": "Feature",
  "properties": {
    "iso:country":"US",
    "sg:address":"47 Allen Blvd",
    "sg:city":"Farmingdale",
    "sg:classifiers":[
        {
            "category":"Professional",
            "subcategory":"Management & Consulting",
            "type":"Services"
        }
    ],
    "sg:phone":"+1 631 293 9240",
    "sg:postcode":"11735",
    "sg:province":"NY",
    "sg:tags":[
        "marketing",
        "promotional"
    ],
    "wof:name":"TPI Marketing Promotions Inc",
    "wof:placetype":"venue"
},
  "geometry": {"coordinates":[-73.42335799999999,40.715494],"type":"Point"}
}