{
  "type": "Feature",
  "properties": {
    "addr:full":"2410 Arthur Ave Bronx NY 10458",
    "addr:housenumber":"2410",
    "addr:postcode":"10458",
    "addr:street":"Arthur Ave",
    "iso:country":"US",
    "sg:address":"2410 Arthur Ave",
    "sg:city":"Bronx",
    "sg:classifiers":[
        {
            "category":"Deli",
            "type":"Food & Drink"
        },
        {
            "category":"Restaurant",
            "type":"Food & Drink"
        }
    ],
    "sg:menulink":"http://www.allmenus.com/ny/bronx/284941-tinos-delicatessen/menu/",
    "sg:phone":"+1 718 733 9879",
    "sg:postcode":"10458",
    "sg:province":"NY",
    "sg:tags":[
        "deli",
        "american"
    ],
    "wof:name":"Tino's Delicatessen",
    "wof:placetype":"venue"
},
  "geometry": {"coordinates":[-73.88739200000001,40.855771],"type":"Point"}
}