{
  "type": "Feature",
  "properties": {
    "iso:country":"US",
    "sg:address":"4919 State Hwy 233",
    "sg:city":"Westmoreland",
    "sg:classifiers":[
        {
            "category":"Wholesale",
            "subcategory":"Office Equipment",
            "type":"Manufacturing & Wholesale Goods"
        }
    ],
    "sg:phone":"+1 315 463 7811",
    "sg:postcode":"13490",
    "sg:province":"NY",
    "sg:tags":[
        "machine",
        "duplicating",
        "copying"
    ],
    "sg:website":"www.uoe.com",
    "wof:name":"Upstate Office Equipment",
    "wof:placetype":"venue"
},
  "geometry": {"coordinates":[-75.403316,43.114621],"type":"Point"}
}