{
  "type": "Feature",
  "properties": {
    "addr:full":"1201 E 73rd St Brooklyn NY 11234",
    "addr:housenumber":"1201",
    "addr:postcode":"11234",
    "addr:street":"E 73Rd St",
    "iso:country":"US",
    "sg:address":"1201 E 73rd St",
    "sg:city":"Brooklyn",
    "sg:classifiers":[
        {
            "category":"Travel",
            "subcategory":"Hotels & Motels",
            "type":"Entertainment"
        },
        {
            "category":"Personal",
            "type":"Services"
        }
    ],
    "sg:phone":"+1 718 777 2646",
    "sg:postcode":"11234",
    "sg:province":"NY",
    "sg:tags":[
        "concierge",
        "assistant"
    ],
    "wof:name":"Adam And Eve Tanning And Day Spa",
    "wof:placetype":"venue"
},
  "geometry": {"coordinates":[-73.914001,40.626961],"type":"Point"}
}