{
  "type": "Feature",
  "properties": {
    "addr:full":"524 Lowell St Westbury NY 11590",
    "addr:housenumber":"524",
    "addr:postcode":"11590",
    "addr:street":"Lowell St",
    "iso:country":"US",
    "sg:address":"524 Lowell St",
    "sg:city":"Westbury",
    "sg:classifiers":[
        {
            "category":"Building & Trades",
            "subcategory":"Landscaping Services",
            "type":"Services"
        }
    ],
    "sg:phone":"+1 516 997 4921",
    "sg:postcode":"11590",
    "sg:province":"NY",
    "sg:tags":[
        "lawn"
    ],
    "wof:name":"Sal Iannucci Landscaping",
    "wof:placetype":"venue"
},
  "geometry": {"coordinates":[-73.57951,40.753031],"type":"Point"}
}