{
  "type": "Feature",
  "properties": {
    "addr:full":"682 Bay St Staten Island NY 10304",
    "addr:housenumber":"682",
    "addr:postcode":"10304",
    "addr:street":"Bay St",
    "iso:country":"US",
    "sg:address":"682 Bay St",
    "sg:city":"Staten Island",
    "sg:classifiers":[
        {
            "category":"Building & Trades",
            "subcategory":"Cleaning & Sanitation",
            "type":"Services"
        }
    ],
    "sg:phone":"+1 718 727 9427",
    "sg:postcode":"10304",
    "sg:province":"NY",
    "sg:tags":[
        "carpet"
    ],
    "wof:name":"Bentco Services",
    "wof:placetype":"venue"
},
  "geometry": {"coordinates":[-74.073502,40.623402],"type":"Point"}
}