{
  "type": "Feature",
  "properties": {
    "iso:country":"US",
    "sg:address":"7 Golf Course Dr",
    "sg:city":"Suffern",
    "sg:classifiers":[
        {
            "category":"Shopping",
            "subcategory":"Gifts & Souvenirs",
            "type":"Retail Goods"
        }
    ],
    "sg:phone":"+1   ",
    "sg:postcode":"10901",
    "sg:province":"NY",
    "wof:name":"Affairs From Heart",
    "wof:placetype":"venue"
},
  "geometry": {"coordinates":[-74.105942,41.124411],"type":"Point"}
}