{
  "type": "Feature",
  "properties": {
    "addr:full":"1913 Long Pond Rd Rochester NY 14606",
    "addr:housenumber":"1913",
    "addr:postcode":"14606",
    "addr:street":"Long Pond Rd",
    "iso:country":"US",
    "sg:address":"1913 Long Pond Rd",
    "sg:city":"Rochester",
    "sg:classifiers":[
        {
            "category":"Personal",
            "subcategory":"Beauty Salon",
            "type":"Services"
        }
    ],
    "sg:phone":"+1   ",
    "sg:postcode":"14606",
    "sg:province":"NY",
    "sg:tags":[
        "shop",
        "jewelry"
    ],
    "wof:name":"Faggianos Charisma Salon",
    "wof:placetype":"venue"
},
  "geometry": {"coordinates":[-77.701588,43.175581],"type":"Point"}
}