{
  "type": "Feature",
  "properties": {
    "addr:full":"60 Madison Ave Ste 914 New York NY 10010",
    "addr:housenumber":"60;914",
    "addr:postcode":"10010",
    "addr:street":"Madison Ave Ste",
    "iso:country":"US",
    "sg:address":"60 Madison Ave Ste 914",
    "sg:city":"New York",
    "sg:classifiers":[
        {
            "category":"Building & Trades",
            "subcategory":"Construction",
            "type":"Services"
        }
    ],
    "sg:phone":"+1 212 779 7505",
    "sg:postcode":"10010",
    "sg:province":"NY",
    "sg:tags":[
        "contractor"
    ],
    "sg:website":"www.centralconsulting.com",
    "wof:name":"Central Consulting & Contracting",
    "wof:placetype":"venue"
},
  "geometry": {"coordinates":[-73.98615100000001,40.743387],"type":"Point"}
}