{
  "type": "Feature",
  "properties": {
    "iso:country":"US",
    "sg:address":"13340 Allen Rd",
    "sg:city":"Chaffee",
    "sg:classifiers":[
        {
            "category":"Home & Garden",
            "subcategory":"Building Materials",
            "type":"Retail Goods"
        }
    ],
    "sg:phone":"+1 716 496 7279",
    "sg:postcode":"14030",
    "sg:province":"NY",
    "sg:tags":[
        "glass",
        "window",
        "plate"
    ],
    "wof:name":"Chaffee Glass Svc",
    "wof:placetype":"venue"
},
  "geometry": {"coordinates":[-78.484443,42.567922],"type":"Point"}
}