{
  "type": "Feature",
  "properties": {
    "iso:country":"US",
    "sg:address":"1994 Peruville Rd",
    "sg:city":"Freeville",
    "sg:classifiers":[
        {
            "category":"Manufacturing",
            "subcategory":"Printing",
            "type":"Manufacturing & Wholesale Goods"
        }
    ],
    "sg:phone":"+1   ",
    "sg:postcode":"13068",
    "sg:province":"NY",
    "sg:tags":[
        "book"
    ],
    "wof:name":"Jordans Unlimited",
    "wof:placetype":"venue"
},
  "geometry": {"coordinates":[-76.29380399999999,42.549684],"type":"Point"}
}