{
  "type": "Feature",
  "properties": {
    "addr:full":"726 Pelham Pkwy S Bronx NY 10462",
    "addr:housenumber":"726",
    "addr:postcode":"10462",
    "addr:street":"Pelham Pkwy S",
    "iso:country":"US",
    "sg:address":"726 Pelham Pkwy S",
    "sg:city":"Bronx",
    "sg:classifiers":[
        {
            "category":"Health Services",
            "subcategory":"Doctor",
            "type":"Services"
        }
    ],
    "sg:phone":"+1 845 634 6767",
    "sg:postcode":"10462",
    "sg:province":"NY",
    "sg:tags":[
        "dentist"
    ],
    "wof:name":"Richard P Herman DDS",
    "wof:placetype":"venue"
},
  "geometry": {"coordinates":[-73.86576100000001,40.856592],"type":"Point"}
}