{
  "type": "Feature",
  "properties": {
    "addr:full":"128 Musgnug Ave Mineola NY 11501",
    "addr:housenumber":"128",
    "addr:postcode":"11501",
    "addr:street":"Musgnug Ave",
    "iso:country":"US",
    "sg:address":"128 Musgnug Ave",
    "sg:city":"Mineola",
    "sg:classifiers":[
        {
            "category":"Communications",
            "subcategory":"Film & Video Production",
            "type":"Services"
        }
    ],
    "sg:phone":"+1 516 294 2949",
    "sg:postcode":"11501",
    "sg:province":"NY",
    "sg:tags":[
        "recording",
        "rehearsal",
        "audio",
        "studio",
        "consultant"
    ],
    "wof:name":"Metro A V",
    "wof:placetype":"venue"
},
  "geometry": {"coordinates":[-73.641502,40.7509],"type":"Point"}
}