{
  "type": "Feature",
  "properties": {
    "addr:full":"397A Jericho Tpke Mineola NY 11501",
    "addr:housenumber":"397a",
    "addr:postcode":"11501",
    "addr:street":"Jericho Tpke",
    "iso:country":"US",
    "sg:address":"397A Jericho Tpke",
    "sg:city":"Mineola",
    "sg:classifiers":[
        {
            "category":"Retail",
            "subcategory":"Auto Rental",
            "type":"Services"
        }
    ],
    "sg:phone":"+1 516 746 0505",
    "sg:postcode":"11501",
    "sg:province":"NY",
    "sg:tags":[
        "car"
    ],
    "sg:website":"www.enterprise.com/car_rental/de...",
    "wof:name":"Enterprise Rent-A-Car",
    "wof:placetype":"venue"
},
  "geometry": {"coordinates":[-73.651242,40.745722],"type":"Point"}
}