{
  "type": "Feature",
  "properties": {
    "addr:full":"423 William Floyd Pkwy Shirley NY 11967",
    "addr:housenumber":"423",
    "addr:postcode":"11967",
    "addr:street":"William Floyd Pkwy",
    "iso:country":"US",
    "sg:address":"423 William Floyd Pkwy",
    "sg:city":"Shirley",
    "sg:classifiers":[
        {
            "category":"Shopping",
            "subcategory":"Musical Instruments",
            "type":"Retail Goods"
        }
    ],
    "sg:phone":"+1 631 281 0611",
    "sg:postcode":"11967",
    "sg:province":"NY",
    "sg:tags":[
        "music",
        "dealer"
    ],
    "wof:name":"Maximo Music Ctr",
    "wof:placetype":"venue"
},
  "geometry": {"coordinates":[-72.864698,40.782583],"type":"Point"}
}