{
  "type": "Feature",
  "properties": {
    "iso:country":"US",
    "sg:address":"14 Avenue T",
    "sg:city":"Brooklyn",
    "sg:classifiers":[
        {
            "category":"Professional",
            "subcategory":"Lawyer & Legal Services",
            "type":"Services"
        }
    ],
    "sg:phone":"+1 718 372 2511",
    "sg:postcode":"11223",
    "sg:province":"NY",
    "sg:website":"www.pklnyc.com",
    "wof:name":"Phillips Krantz and Levi Llp",
    "wof:placetype":"venue"
},
  "geometry": {"coordinates":[-73.98525100000001,40.597822],"type":"Point"}
}