{
  "type": "Feature",
  "properties": {
    "iso:country":"US",
    "sg:address":"220 N Central Ave",
    "sg:city":"Hartsdale",
    "sg:classifiers":[
        {
            "category":"Health Services",
            "subcategory":"Doctor",
            "type":"Services"
        }
    ],
    "sg:phone":"+1 914 681 9750",
    "sg:postcode":"10530",
    "sg:province":"NY",
    "sg:tags":[
        "medical"
    ],
    "wof:name":"Sathish Modugu MD",
    "wof:placetype":"venue"
},
  "geometry": {"coordinates":[-73.795979,41.021317],"type":"Point"}
}