{
  "type": "Feature",
  "properties": {
    "addr:full":"177 Dreiser Loop Bronx NY 10475",
    "addr:housenumber":"177",
    "addr:postcode":"10475",
    "addr:street":"Dreiser Loop",
    "iso:country":"US",
    "sg:address":"177 Dreiser Loop",
    "sg:city":"Bronx",
    "sg:classifiers":[
        {
            "category":"Banks & Credit Unions",
            "subcategory":"Bank",
            "type":"Services"
        }
    ],
    "sg:phone":"+1 718 379 7017",
    "sg:postcode":"10475",
    "sg:province":"NY",
    "wof:name":"Spanish American Comm Club Fcu",
    "wof:placetype":"venue"
},
  "geometry": {"coordinates":[-73.828187,40.878066],"type":"Point"}
}