{
  "type": "Feature",
  "properties": {
    "addr:full":"13 Dittrick St Endicott NY 13760",
    "addr:housenumber":"13",
    "addr:postcode":"13760",
    "addr:street":"Dittrick St",
    "iso:country":"US",
    "sg:address":"13 Dittrick St",
    "sg:city":"Endicott",
    "sg:classifiers":[
        {
            "category":"Wholesale",
            "subcategory":"Auto Parts",
            "type":"Manufacturing & Wholesale Goods"
        }
    ],
    "sg:phone":"+1 607 785 2831",
    "sg:postcode":"13760",
    "sg:province":"NY",
    "sg:tags":[
        "automobile",
        "rebuilt"
    ],
    "wof:name":"Endicott Auto Wrecking Co",
    "wof:placetype":"venue"
},
  "geometry": {"coordinates":[-76.03482,42.107705],"type":"Point"}
}