{
  "type": "Feature",
  "properties": {
    "addr:full":"157 E Commercial St East Rochester NY 14445",
    "addr:housenumber":"157",
    "addr:postcode":"14445",
    "addr:street":"E Commercial St",
    "iso:country":"US",
    "sg:address":"157 E Commercial St",
    "sg:city":"East Rochester",
    "sg:classifiers":[
        {
            "category":"Professional",
            "subcategory":"Advertising",
            "type":"Services"
        }
    ],
    "sg:phone":"+1 585 586 3030",
    "sg:postcode":"14445",
    "sg:province":"NY",
    "sg:tags":[
        "counselor"
    ],
    "wof:name":"Commercial Success Inc",
    "wof:placetype":"venue"
},
  "geometry": {"coordinates":[-77.484156,43.112768],"type":"Point"}
}