{
  "type": "Feature",
  "properties": {
    "iso:country":"US",
    "sg:address":"201 Willow St",
    "sg:city":"Lockport",
    "sg:classifiers":[
        {
            "category":"Government",
            "subcategory":"Office",
            "type":"Public Place"
        }
    ],
    "sg:phone":"+1 716 434 3071",
    "sg:postcode":"14094",
    "sg:province":"NY",
    "sg:tags":[
        "village"
    ],
    "wof:name":"Lockport City Youth & Rec",
    "wof:placetype":"venue"
},
  "geometry": {"coordinates":[-78.69897,43.160545],"type":"Point"}
}