{
  "type": "Feature",
  "properties": {
    "addr:full":"738 Smithtown Byp Smithtown NY 11787",
    "addr:housenumber":"738",
    "addr:postcode":"11787",
    "addr:street":"Byp",
    "iso:country":"US",
    "sg:address":"738 Smithtown Byp",
    "sg:city":"Smithtown",
    "sg:classifiers":[
        {
            "category":"Banks & Credit Unions",
            "subcategory":"Bank",
            "type":"Services"
        }
    ],
    "sg:phone":"+1 631 360 7217",
    "sg:postcode":"11787",
    "sg:province":"NY",
    "sg:tags":[
        "loan",
        "real estate"
    ],
    "wof:name":"First Capital Home Mortgage",
    "wof:placetype":"venue"
},
  "geometry": {"coordinates":[-73.171454,40.846961],"type":"Point"}
}