{
  "type": "Feature",
  "properties": {
    "iso:country":"US",
    "sg:address":"124 Colonial Ave",
    "sg:city":"Mineola",
    "sg:classifiers":[
        {
            "category":"Shopping",
            "subcategory":"Crafts & Fabrics",
            "type":"Retail Goods"
        }
    ],
    "sg:phone":"+1 516 741 4135",
    "sg:postcode":"11501",
    "sg:province":"NY",
    "sg:tags":[
        "sewing",
        "machines-household"
    ],
    "wof:name":"Cindy Sewing",
    "wof:placetype":"venue"
},
  "geometry": {"coordinates":[-73.62901100000001,40.746364],"type":"Point"}
}