{
  "type": "Feature",
  "properties": {
    "iso:country":"US",
    "sg:address":"132 Dutchtown Rd",
    "sg:city":"Saugerties",
    "sg:classifiers":[
        {
            "category":"Building & Trades",
            "subcategory":"Plumbing",
            "type":"Services"
        },
        {
            "category":"Building & Trades",
            "subcategory":"Construction",
            "type":"Services"
        },
        {
            "category":"Building & Trades",
            "subcategory":"Cleaning & Sanitation",
            "type":"Services"
        }
    ],
    "sg:phone":"+1 845 878 0361",
    "sg:postcode":"12477",
    "sg:province":"NY",
    "sg:tags":[
        "cleaner",
        "plumber",
        "industrial",
        "repairer",
        "heating",
        "specialty",
        "sewer",
        "contractors-commercial",
        "contractor",
        "plumbing-drain"
    ],
    "sg:website":"http://www.yext.com/p/superpages/joe-s-plumbing-saugerties-new-york.html",
    "wof:name":"Joe's Plumbing & Heating",
    "wof:placetype":"venue"
},
  "geometry": {"coordinates":[-74.024784,42.035598],"type":"Point"}
}