{
  "type": "Feature",
  "properties": {
    "addr:full":"291 E 170th St Bronx NY 10456",
    "addr:housenumber":"291",
    "addr:postcode":"10456",
    "addr:street":"E 170Th St",
    "iso:country":"US",
    "sg:address":"291 E 170th St",
    "sg:city":"Bronx",
    "sg:classifiers":[
        {
            "category":"Travel",
            "subcategory":"Travel Agent",
            "type":"Entertainment"
        }
    ],
    "sg:phone":"+1   ",
    "sg:postcode":"10456",
    "sg:province":"NY",
    "sg:tags":[
        "agency"
    ],
    "wof:name":"Anarela Tours Inc",
    "wof:placetype":"venue"
},
  "geometry": {"coordinates":[-73.91098599999999,40.837826],"type":"Point"}
}