{
  "type": "Feature",
  "properties": {
    "iso:country":"US",
    "sg:address":"68 Bergen St",
    "sg:city":"Brooklyn",
    "sg:classifiers":[
        {
            "category":"Retail",
            "subcategory":"Laundry & Dry Cleaning",
            "type":"Services"
        }
    ],
    "sg:postcode":"11201",
    "sg:province":"NY",
    "wof:name":"Super Laundromat",
    "wof:placetype":"venue"
},
  "geometry": {"coordinates":[-73.990848,40.686863],"type":"Point"}
}