{
  "type": "Feature",
  "properties": {
    "iso:country":"US",
    "sg:address":"440 Park Ave",
    "sg:city":"New York",
    "sg:classifiers":[
        {
            "category":"Retail",
            "subcategory":"Repair Shop",
            "type":"Services"
        }
    ],
    "sg:phone":"+1 917 546 1710",
    "sg:postcode":"10022",
    "sg:province":"NY",
    "sg:tags":[
        "lock",
        "locksmith"
    ],
    "wof:name":"24 Hour Emergency Locksmith",
    "wof:placetype":"venue"
},
  "geometry": {"coordinates":[-73.970951,40.761401],"type":"Point"}
}