{
  "type": "Feature",
  "properties": {
    "addr:full":"67 E 11 St New York NY 10003",
    "addr:housenumber":"67;11",
    "addr:postcode":"10003",
    "addr:street":"E",
    "iso:country":"US",
    "sg:address":"67 E 11 St",
    "sg:city":"New York",
    "sg:classifiers":[
        {
            "category":"Real Estate",
            "subcategory":"Real Estate Agent",
            "type":"Services"
        }
    ],
    "sg:phone":"+1 212 477 8271",
    "sg:postcode":"10003",
    "sg:province":"NY",
    "sg:tags":[
        "cooperative"
    ],
    "wof:name":"Cast Iron Building",
    "wof:placetype":"venue"
},
  "geometry": {"coordinates":[-73.991938,40.732896],"type":"Point"}
}