{
  "type": "Feature",
  "properties": {
    "addr:full":"2374 Frederick Douglass Blvd New York NY 10027",
    "addr:housenumber":"2374",
    "addr:postcode":"10027",
    "addr:street":"Frederick Douglass Blvd",
    "iso:country":"US",
    "sg:address":"2374 Frederick Douglass Blvd",
    "sg:city":"New York",
    "sg:classifiers":[
        {
            "category":"Education",
            "subcategory":"School",
            "type":"Public Place"
        }
    ],
    "sg:phone":"+1 212 864 2370",
    "sg:postcode":"10027",
    "sg:province":"NY",
    "wof:name":"Harlem Childrens Zone",
    "wof:placetype":"venue"
},
  "geometry": {"coordinates":[-73.949933,40.811575],"type":"Point"}
}