{
  "type": "Feature",
  "properties": {
    "iso:country":"US",
    "sg:address":"157 E Main St",
    "sg:city":"Huntington",
    "sg:classifiers":[
        {
            "category":"Health Services",
            "subcategory":"Chiropractor",
            "type":"Services"
        }
    ],
    "sg:phone":"+1 631 427 4700",
    "sg:postcode":"11743",
    "sg:province":"NY",
    "wof:name":"Fluhr Craig M Chirprctr",
    "wof:placetype":"venue"
},
  "geometry": {"coordinates":[-73.40270200000001,40.880001],"type":"Point"}
}