{
  "type": "Feature",
  "properties": {
    "addr:full":"2440 Bronx Park E Bronx NY 10467",
    "addr:housenumber":"2440",
    "addr:postcode":"10467",
    "addr:street":"Bronx Park E",
    "iso:country":"US",
    "sg:address":"2440 Bronx Park E",
    "sg:city":"Bronx",
    "sg:classifiers":[
        {
            "category":"Real Estate",
            "subcategory":"Real Estate Agent",
            "type":"Services"
        }
    ],
    "sg:phone":"+1 718 231 9265",
    "sg:postcode":"10467",
    "sg:province":"NY",
    "wof:name":"Metropolitan Land Mark Realty",
    "wof:placetype":"venue"
},
  "geometry": {"coordinates":[-73.870423,40.862506],"type":"Point"}
}