{
  "type": "Feature",
  "properties": {
    "iso:country":"US",
    "sg:address":"1007 President St",
    "sg:city":"Brooklyn",
    "sg:classifiers":[
        {
            "category":"Shopping",
            "subcategory":"Music",
            "type":"Retail Goods"
        }
    ],
    "sg:phone":"+1   ",
    "sg:postcode":"11225",
    "sg:province":"NY",
    "wof:name":"Hollaback Records Entrmt & Tal",
    "wof:placetype":"venue"
},
  "geometry": {"coordinates":[-73.956107,40.66849],"type":"Point"}
}