{
  "type": "Feature",
  "properties": {
    "addr:full":"104 Gulino Ave Camillus NY 13031",
    "addr:housenumber":"104",
    "addr:postcode":"13031",
    "addr:street":"Gulino Ave",
    "iso:country":"US",
    "sg:address":"104 Gulino Ave",
    "sg:city":"Camillus",
    "sg:classifiers":[
        {
            "category":"Organizations",
            "subcategory":"Community Association",
            "type":"Services"
        }
    ],
    "sg:phone":"+1 315 487 1482",
    "sg:postcode":"13031",
    "sg:province":"NY",
    "wof:name":"Royal Order of Jesters",
    "wof:placetype":"venue"
},
  "geometry": {"coordinates":[-76.278248,43.038459],"type":"Point"}
}