{
  "type": "Feature",
  "properties": {
    "iso:country":"US",
    "sg:address":"11849 E Corning Rd # 106",
    "sg:city":"Corning",
    "sg:classifiers":[
        {
            "category":"Manufacturing",
            "subcategory":"Buildings",
            "type":"Manufacturing & Wholesale Goods"
        },
        {
            "category":"Building & Trades",
            "subcategory":"Construction",
            "type":"Services"
        }
    ],
    "sg:phone":"+1 607 936 1575",
    "sg:postcode":"14830",
    "sg:province":"NY",
    "sg:tags":[
        "industrial",
        "system",
        "specialty",
        "builder",
        "heating",
        "contractor",
        "contractors-commercial",
        "home",
        "air conditioning"
    ],
    "wof:name":"Klugo Construction Inc",
    "wof:placetype":"venue"
},
  "geometry": {"coordinates":[-76.993959,42.123061],"type":"Point"}
}