{
  "type": "Feature",
  "properties": {
    "addr:full":"201 E Molloy Rd Syracuse NY 13211",
    "addr:housenumber":"201",
    "addr:postcode":"13211",
    "addr:street":"E Molloy Rd",
    "iso:country":"US",
    "sg:address":"201 E Molloy Rd",
    "sg:city":"Syracuse",
    "sg:classifiers":[
        {
            "category":"Organizations",
            "subcategory":"Religious Organization",
            "type":"Services"
        }
    ],
    "sg:phone":"+1 315 454 0432",
    "sg:postcode":"13211",
    "sg:province":"NY",
    "wof:name":"Calvary United Methodist Chr",
    "wof:placetype":"venue"
},
  "geometry": {"coordinates":[-76.14058199999999,43.097992],"type":"Point"}
}