{
  "type": "Feature",
  "properties": {
    "iso:country":"US",
    "sg:address":"337 Wantagh Ave",
    "sg:city":"Levittown",
    "sg:classifiers":[
        {
            "category":"Restaurant",
            "type":"Food & Drink"
        }
    ],
    "sg:phone":"+1 516 731 3600",
    "sg:postcode":"11756",
    "sg:province":"NY",
    "sg:tags":[
        "delicatessen"
    ],
    "wof:name":"Deli Zone",
    "wof:placetype":"venue"
},
  "geometry": {"coordinates":[-73.499426,40.717074],"type":"Point"}
}