{
  "type": "Feature",
  "properties": {
    "addr:full":"93 Capital Dr Washingtonville NY 10992",
    "addr:housenumber":"93",
    "addr:postcode":"10992",
    "addr:street":"Capital Dr",
    "iso:country":"US",
    "sg:address":"93 Capital Dr",
    "sg:city":"Washingtonville",
    "sg:classifiers":[
        {
            "category":"Building & Trades",
            "subcategory":"Electrical",
            "type":"Services"
        }
    ],
    "sg:phone":"+1 845 496 5060",
    "sg:postcode":"10992",
    "sg:province":"NY",
    "sg:tags":[
        "electrician"
    ],
    "sg:website":"http://www.zamelectric.com",
    "wof:name":"Zam Electric Inc",
    "wof:placetype":"venue"
},
  "geometry": {"coordinates":[-74.144734,41.437411],"type":"Point"}
}