{
  "type": "Feature",
  "properties": {
    "addr:full":"651 9th Ave New York NY 10036",
    "addr:housenumber":"651",
    "addr:postcode":"10036",
    "addr:street":"9Th Ave",
    "iso:country":"US",
    "sg:address":"651 9th Ave",
    "sg:city":"New York",
    "sg:classifiers":[
        {
            "category":"Restaurant",
            "type":"Food & Drink"
        }
    ],
    "sg:menulink":"http://www.allmenus.com/ny/new-york/7193-bali-nusa-indian-indonesian-restaurant/menu/",
    "sg:phone":"+1 212 974 1875",
    "sg:postcode":"10036",
    "sg:province":"NY",
    "sg:tags":[
        "indian",
        "asian"
    ],
    "wof:name":"Bali-Nusa-Indian Indonesian Restaurant",
    "wof:placetype":"venue"
},
  "geometry": {"coordinates":[-73.99100300000001,40.760671],"type":"Point"}
}