{
  "type": "Feature",
  "properties": {
    "addr:full":"4020 Hempstead Tpke Bethpage NY 11714",
    "addr:housenumber":"4020",
    "addr:postcode":"11714",
    "addr:street":"Hempstead Tpke",
    "iso:country":"US",
    "sg:address":"4020 Hempstead Tpke",
    "sg:city":"Bethpage",
    "sg:classifiers":[
        {
            "category":"Utilities",
            "subcategory":"Mobile Phone",
            "type":"Services"
        },
        {
            "category":"Shopping",
            "subcategory":"Mobile Phones",
            "type":"Retail Goods"
        },
        {
            "category":"Utilities",
            "subcategory":"Telephone",
            "type":"Services"
        },
        {
            "category":"Professional",
            "subcategory":"Computer Services",
            "type":"Services"
        }
    ],
    "sg:phone":"+1 516 731 8500",
    "sg:postcode":"11714",
    "sg:province":"NY",
    "sg:tags":[
        "telecommunication",
        "supply",
        "communication",
        "system",
        "wireless",
        "equipment",
        "cellular"
    ],
    "sg:website":"http://clickserve.dartsearch.net/link/click?lid=43000000308049899",
    "wof:name":"T-Mobile",
    "wof:placetype":"venue"
},
  "geometry": {"coordinates":[-73.48768200000001,40.725159],"type":"Point"}
}