{
  "type": "Feature",
  "properties": {
    "addr:full":"10855 Queens Blvd Forest Hills NY 11375",
    "addr:housenumber":"10855",
    "addr:postcode":"11375",
    "addr:street":"Queens Blvd",
    "iso:country":"US",
    "sg:address":"10855 Queens Blvd",
    "sg:city":"Forest Hills",
    "sg:classifiers":[
        {
            "category":"Health Services",
            "subcategory":"Dentist",
            "type":"Services"
        }
    ],
    "sg:phone":"+1 718 263 2933",
    "sg:postcode":"11375",
    "sg:province":"NY",
    "wof:name":"Afford Dental PC",
    "wof:placetype":"venue"
},
  "geometry": {"coordinates":[-73.84339900000001,40.721401],"type":"Point"}
}