{
  "type": "Feature",
  "properties": {
    "addr:full":"53 E Rock Cut Rd Walden NY 12586",
    "addr:housenumber":"53",
    "addr:postcode":"12586",
    "addr:street":"E Rock Cut Rd",
    "iso:country":"US",
    "sg:address":"53 E Rock Cut Rd",
    "sg:city":"Walden",
    "sg:classifiers":[
        {
            "category":"Banks & Credit Unions",
            "subcategory":"Financial Services",
            "type":"Services"
        }
    ],
    "sg:phone":"+1 845 566 0825",
    "sg:postcode":"12586",
    "sg:province":"NY",
    "sg:tags":[
        "investor"
    ],
    "wof:name":"Spampinato Enterprises Inc",
    "wof:placetype":"venue"
},
  "geometry": {"coordinates":[-74.108716,41.575697],"type":"Point"}
}