{
  "type": "Feature",
  "properties": {
    "addr:full":"1126 Morton Blvd Kingston NY 12401",
    "addr:housenumber":"1126",
    "addr:postcode":"12401",
    "addr:street":"Morton Blvd",
    "iso:country":"US",
    "sg:address":"1126 Morton Blvd",
    "sg:city":"Kingston",
    "sg:classifiers":[
        {
            "category":"Retail",
            "subcategory":"Self-service Laundry",
            "type":"Services"
        }
    ],
    "sg:phone":"+1   ",
    "sg:postcode":"12401",
    "sg:province":"NY",
    "sg:tags":[
        "coin"
    ],
    "wof:name":"Washboards Laundromats",
    "wof:placetype":"venue"
},
  "geometry": {"coordinates":[-73.992897,41.962435],"type":"Point"}
}