{
  "type": "Feature",
  "properties": {
    "addr:full":"140 S Columbus Ave Mount Vernon NY 10553",
    "addr:housenumber":"140",
    "addr:postcode":"10553",
    "addr:street":"S Columbus Ave",
    "iso:country":"US",
    "sg:address":"140 S Columbus Ave",
    "sg:city":"Mount Vernon",
    "sg:classifiers":[
        {
            "category":"Professional",
            "subcategory":"Detective & Security Services",
            "type":"Services"
        }
    ],
    "sg:phone":"+1 914 667 4822",
    "sg:postcode":"10553",
    "sg:province":"NY",
    "sg:tags":[
        "monitoring",
        "alarm",
        "installation",
        "maintenance",
        "burglar"
    ],
    "wof:name":"District Central Station Alarm",
    "wof:placetype":"venue"
},
  "geometry": {"coordinates":[-73.82248,40.910847],"type":"Point"}
}