{
  "type": "Feature",
  "properties": {
    "iso:country":"US",
    "sg:address":"16711 73rd Ave",
    "sg:city":"Fresh Meadows",
    "sg:classifiers":[
        {
            "category":"Organizations",
            "subcategory":"Religious Organization",
            "type":"Services"
        }
    ],
    "sg:phone":"+1   ",
    "sg:postcode":"11366",
    "sg:province":"NY",
    "wof:name":"Israel Cntr of Hillcrest Mnr",
    "wof:placetype":"venue"
},
  "geometry": {"coordinates":[-73.802193,40.728128],"type":"Point"}
}