{
  "type": "Feature",
  "properties": {
    "iso:country":"US",
    "sg:address":"4417 Chautauqua Blvd",
    "sg:city":"Lakewood",
    "sg:classifiers":[
        {
            "category":"Retail",
            "subcategory":"Auto Repair",
            "type":"Services"
        }
    ],
    "sg:phone":"+1 716 763 1946",
    "sg:postcode":"14750",
    "sg:province":"NY",
    "sg:tags":[
        "repairing",
        "automobile",
        "used",
        "merchandise",
        "general"
    ],
    "wof:name":"Swanson Gene Keystone",
    "wof:placetype":"venue"
},
  "geometry": {"coordinates":[-79.34966,42.098684],"type":"Point"}
}