{
  "type": "Feature",
  "properties": {
    "addr:full":"1762 First Ave Manhattan NY 10128",
    "addr:housenumber":"1762",
    "addr:postcode":"10128",
    "addr:street":"First Ave",
    "iso:country":"US",
    "sg:address":"1762 First Ave",
    "sg:city":"Manhattan",
    "sg:classifiers":[
        {
            "category":"Restaurant",
            "type":"Food & Drink"
        }
    ],
    "sg:phone":"+1 212 828 2088",
    "sg:postcode":"10128",
    "sg:province":"NY",
    "sg:website":"www.sparkfoods.com",
    "wof:name":"Spark",
    "wof:placetype":"venue"
},
  "geometry": {"coordinates":[-73.946534,40.78021],"type":"Point"}
}