{
  "type": "Feature",
  "properties": {
    "addr:full":"2199 E Henrietta Rd Rochester NY 14623",
    "addr:housenumber":"2199",
    "addr:postcode":"14623",
    "addr:street":"E Henrietta Rd",
    "iso:country":"US",
    "sg:address":"2199 E Henrietta Rd",
    "sg:city":"Rochester",
    "sg:classifiers":[
        {
            "category":"Retail",
            "subcategory":"Laundry & Dry Cleaning",
            "type":"Services"
        }
    ],
    "sg:phone":"+1 585 334 7010",
    "sg:postcode":"14623",
    "sg:province":"NY",
    "sg:tags":[
        "cleaner",
        "commercial"
    ],
    "sg:website":"http://www.unitedcleaners.com",
    "wof:name":"United Cleaners",
    "wof:placetype":"venue"
},
  "geometry": {"coordinates":[-77.607063,43.072441],"type":"Point"}
}