{
  "type": "Feature",
  "properties": {
    "iso:country":"US",
    "sg:address":"2547 Cropsey Ave",
    "sg:city":"Brooklyn",
    "sg:classifiers":[
        {
            "category":"Restaurant",
            "type":"Food & Drink"
        }
    ],
    "sg:phone":"+1 347 673 5411",
    "sg:postcode":"11214",
    "sg:province":"NY",
    "sg:tags":[
        "fusion",
        "asian"
    ],
    "sg:website":"orangegrill.com",
    "wof:name":"Orange Grill",
    "wof:placetype":"venue"
},
  "geometry": {"coordinates":[-73.992058,40.591158],"type":"Point"}
}