{
  "type": "Feature",
  "properties": {
    "addr:full":"404 N Terrace Ave Mount Vernon NY 10552",
    "addr:housenumber":"404",
    "addr:postcode":"10552",
    "addr:street":"N Terrace Ave",
    "iso:country":"US",
    "sg:address":"404 N Terrace Ave",
    "sg:city":"Mount Vernon",
    "sg:classifiers":[
        {
            "category":"Wholesale",
            "subcategory":"Hardware",
            "type":"Manufacturing & Wholesale Goods"
        }
    ],
    "sg:phone":"+1 914 699 6716",
    "sg:postcode":"10552",
    "sg:province":"NY",
    "sg:tags":[
        "product",
        "mfg"
    ],
    "wof:name":"Chains Way",
    "wof:placetype":"venue"
},
  "geometry": {"coordinates":[-73.841401,40.920918],"type":"Point"}
}