{
  "type": "Feature",
  "properties": {
    "iso:country":"US",
    "sg:address":"5254 State Highway 56",
    "sg:city":"Colton",
    "sg:classifiers":[
        {
            "category":"Manufacturing",
            "subcategory":"Lumber",
            "type":"Manufacturing & Wholesale Goods"
        }
    ],
    "sg:phone":"+1 315 262 2527",
    "sg:postcode":"13625",
    "sg:province":"NY",
    "sg:tags":[
        "timberland",
        "timber"
    ],
    "wof:name":"Schyler, Shea",
    "wof:placetype":"venue"
},
  "geometry": {"coordinates":[-74.964388,44.575494],"type":"Point"}
}