{
  "type": "Feature",
  "properties": {
    "addr:full":"261 W 36th St 2nd Fl New York NY 10079",
    "addr:housenumber":"261",
    "addr:postcode":"10079",
    "addr:street":"W 36Th St",
    "iso:country":"US",
    "sg:address":"261 W 36th St 2nd Fl",
    "sg:city":"New York",
    "sg:classifiers":[
        {
            "category":"Shopping",
            "subcategory":"Clothing, Apparel, & Fashions",
            "type":"Retail Goods"
        }
    ],
    "sg:postcode":"10079",
    "sg:province":"NY",
    "sg:tags":[
        "men's",
        "clothing",
        "women's"
    ],
    "sg:website":"www.clothingline.com",
    "wof:name":"Clothingline - SSS Sample Sales",
    "wof:placetype":"venue"
},
  "geometry": {"coordinates":[-73.99140800000001,40.753006],"type":"Point"}
}