{
  "type": "Feature",
  "properties": {
    "addr:full":"605 W 45th St New York NY 10036",
    "addr:housenumber":"605",
    "addr:postcode":"10036",
    "addr:street":"W 45Th St",
    "iso:country":"US",
    "sg:address":"605 W 45th St",
    "sg:city":"New York",
    "sg:classifiers":[
        {
            "category":"Retail",
            "subcategory":"Auto Repair",
            "type":"Services"
        }
    ],
    "sg:phone":"+1 800 339 7124",
    "sg:postcode":"10036",
    "sg:province":"NY",
    "wof:name":"General Auto Repair",
    "wof:placetype":"venue"
},
  "geometry": {"coordinates":[-73.996971,40.76295],"type":"Point"}
}