{
  "type": "Feature",
  "properties": {
    "addr:full":"7520 Astoria Boulevard East Elmhurst NY 11370",
    "addr:housenumber":"7520",
    "addr:postcode":"11370",
    "addr:street":"Astoria Boulevard",
    "iso:country":"US",
    "sg:address":"7520 Astoria Boulevard",
    "sg:city":"East Elmhurst",
    "sg:classifiers":[
        {
            "category":"Banks & Credit Unions",
            "subcategory":"Bank",
            "type":"Services"
        }
    ],
    "sg:phone":"+1 718 426 4600",
    "sg:postcode":"11370",
    "sg:province":"NY",
    "wof:name":"State Bank of Long Island Lending Division",
    "wof:placetype":"venue"
},
  "geometry": {"coordinates":[-73.89202,40.765692],"type":"Point"}
}