{
  "type": "Feature",
  "properties": {
    "iso:country":"US",
    "sg:address":"827 Cliffside Ave",
    "sg:city":"Valley Stream",
    "sg:classifiers":[
        {
            "category":"Insurance",
            "subcategory":"Insurance Agent",
            "type":"Services"
        }
    ],
    "sg:phone":"+1 516 791 3312",
    "sg:postcode":"11581",
    "sg:province":"NY",
    "wof:name":"Elliot Altman",
    "wof:placetype":"venue"
},
  "geometry": {"coordinates":[-73.733744,40.643632],"type":"Point"}
}