{
  "type": "Feature",
  "properties": {
    "iso:country":"US",
    "sg:address":"1090 William Floyd Pkwy",
    "sg:city":"Shirley",
    "sg:classifiers":[
        {
            "category":"Building & Trades",
            "subcategory":"Construction",
            "type":"Services"
        }
    ],
    "sg:phone":"+1 631 399 9440",
    "sg:postcode":"11967",
    "sg:province":"NY",
    "sg:tags":[
        "insulation",
        "heat",
        "contractor"
    ],
    "wof:name":"T & T Insulation",
    "wof:placetype":"venue"
},
  "geometry": {"coordinates":[-72.87378099999999,40.810236],"type":"Point"}
}