{
  "type": "Feature",
  "properties": {
    "addr:full":"266 E Delavan Ave Buffalo NY 14208",
    "addr:housenumber":"266",
    "addr:postcode":"14208",
    "addr:street":"E Delavan Ave",
    "iso:country":"US",
    "sg:address":"266 E Delavan Ave",
    "sg:city":"Buffalo",
    "sg:classifiers":[
        {
            "category":"Insurance",
            "subcategory":"Insurance Agent",
            "type":"Services"
        }
    ],
    "sg:phone":"+1 716 882 4343",
    "sg:postcode":"14208",
    "sg:province":"NY",
    "wof:name":"Disco Insurance Service Co",
    "wof:placetype":"venue"
},
  "geometry": {"coordinates":[-78.847578,42.922085],"type":"Point"}
}