{
  "type": "Feature",
  "properties": {
    "addr:full":"555 E 242nd St Bronx NY 10470",
    "addr:housenumber":"555",
    "addr:postcode":"10470",
    "addr:street":"E 242Nd St",
    "iso:country":"US",
    "sg:address":"555 E 242nd St",
    "sg:city":"Bronx",
    "sg:classifiers":[
        {
            "category":"Wholesale",
            "subcategory":"Machinery & Supplies",
            "type":"Manufacturing & Wholesale Goods"
        }
    ],
    "sg:phone":"+1 718 325 3000",
    "sg:postcode":"10470",
    "sg:province":"NY",
    "sg:tags":[
        "shoe",
        "findings"
    ],
    "sg:website":"www.premier-brands.com",
    "wof:name":"Premier Brands Of America Inc",
    "wof:placetype":"venue"
},
  "geometry": {"coordinates":[-73.852548,40.906788],"type":"Point"}
}