{
  "type": "Feature",
  "properties": {
    "iso:country":"US",
    "sg:address":"555 E 242nd St",
    "sg:city":"Bronx",
    "sg:classifiers":[
        {
            "category":"Wholesale",
            "subcategory":"Machinery & Supplies",
            "type":"Manufacturing & Wholesale Goods"
        }
    ],
    "sg:phone":"+1 718 325 3000",
    "sg:postcode":"10470",
    "sg:province":"NY",
    "sg:tags":[
        "shoe",
        "findings"
    ],
    "sg:website":"www.premier-brands.com",
    "wof:name":"Premier Brands Of America Inc",
    "wof:placetype":"venue"
},
  "geometry": {"coordinates":[-73.852548,40.906788],"type":"Point"}
}