{
  "type": "Feature",
  "properties": {
    "iso:country":"US",
    "sg:address":"88 William St",
    "sg:city":"Lyons",
    "sg:classifiers":[
        {
            "category":"Professional",
            "subcategory":"Lawyer & Legal Services",
            "type":"Services"
        }
    ],
    "sg:phone":"+1 315 946 3397",
    "sg:postcode":"14489",
    "sg:province":"NY",
    "sg:tags":[
        "attorney"
    ],
    "wof:name":"Nancy M Lord",
    "wof:placetype":"venue"
},
  "geometry": {"coordinates":[-76.99154299999999,43.064592],"type":"Point"}
}