{
  "type": "Feature",
  "properties": {
    "iso:country":"US",
    "sg:address":"432 Evans St",
    "sg:city":"Williamsville",
    "sg:classifiers":[
        {
            "category":"Shopping",
            "subcategory":"Department Store",
            "type":"Retail Goods"
        }
    ],
    "sg:phone":"+1 716 626 6660",
    "sg:postcode":"14221",
    "sg:province":"NY",
    "sg:tags":[
        "shop"
    ],
    "wof:name":"Campus Outfitters",
    "wof:placetype":"venue"
},
  "geometry": {"coordinates":[-78.73956,42.974478],"type":"Point"}
}