{
  "type": "Feature",
  "properties": {
    "iso:country":"US",
    "sg:address":"5291 Starr Rd",
    "sg:city":"Campbell",
    "sg:classifiers":[
        {
            "category":"Food & Beverages",
            "subcategory":"Groceries & Convenience Stores",
            "type":"Retail Goods"
        }
    ],
    "sg:phone":"+1   ",
    "sg:postcode":"14821",
    "sg:province":"NY",
    "wof:name":"Raccoon Corner Mart",
    "wof:placetype":"venue"
},
  "geometry": {"coordinates":[-77.26918499999999,42.230129],"type":"Point"}
}