{
  "type": "Feature",
  "properties": {
    "addr:full":"133 3 Ave New York NY 10003",
    "addr:housenumber":"133",
    "addr:postcode":"10003",
    "addr:street":"3 Ave",
    "iso:country":"US",
    "sg:address":"133 3 Ave",
    "sg:city":"New York",
    "sg:classifiers":[
        {
            "category":"Personal",
            "type":"Services"
        }
    ],
    "sg:phone":"+1 212 673 1866",
    "sg:postcode":"10003",
    "sg:province":"NY",
    "sg:tags":[
        "consultant",
        "program",
        "health",
        "fitness"
    ],
    "sg:website":"www.nypersonaltraining.com",
    "wof:name":"New York Personal Trnng Inc",
    "wof:placetype":"venue"
},
  "geometry": {"coordinates":[-73.989634,40.729761],"type":"Point"}
}