{
  "type": "Feature",
  "properties": {
    "addr:full":"180 Varick St New York NY 10014",
    "addr:housenumber":"180",
    "addr:postcode":"10014",
    "addr:street":"Varick St",
    "iso:country":"US",
    "sg:address":"180 Varick St",
    "sg:city":"New York",
    "sg:classifiers":[
        {
            "category":"Professional",
            "subcategory":"Business Services",
            "type":"Services"
        }
    ],
    "sg:phone":"+1 212 352 1350",
    "sg:postcode":"10014",
    "sg:province":"NY",
    "sg:tags":[
        "interior",
        "designer",
        "design"
    ],
    "wof:name":"Mager Stuart Incorporated",
    "wof:placetype":"venue"
},
  "geometry": {"coordinates":[-74.005501,40.7272],"type":"Point"}
}