{
  "type": "Feature",
  "properties": {
    "addr:full":"6 Trinity Way Lagrangeville NY 12540",
    "addr:housenumber":"6",
    "addr:postcode":"12540",
    "addr:street":"Trinity Way",
    "iso:country":"US",
    "sg:address":"6 Trinity Way",
    "sg:city":"Lagrangeville",
    "sg:classifiers":[
        {
            "category":"Banks & Credit Unions",
            "subcategory":"Bank",
            "type":"Services"
        }
    ],
    "sg:phone":"+1 845 226 2993",
    "sg:postcode":"12540",
    "sg:province":"NY",
    "sg:tags":[
        "mortgage",
        "loan",
        "broker",
        "real estate"
    ],
    "wof:name":"Horizon Financial Group Inc",
    "wof:placetype":"venue"
},
  "geometry": {"coordinates":[-73.745746,41.67392],"type":"Point"}
}