{
  "type": "Feature",
  "properties": {
    "iso:country":"US",
    "sg:address":"417 Remsen Avenue",
    "sg:city":"Brooklyn",
    "sg:classifiers":[
        {
            "category":"Autos & Motor Vehicles",
            "subcategory":"Auto Supplies",
            "type":"Retail Goods"
        }
    ],
    "sg:phone":"+1 718 498 1871",
    "sg:postcode":"11212",
    "sg:province":"NY",
    "sg:tags":[
        "tire"
    ],
    "wof:name":"B & S Tire & Auto",
    "wof:placetype":"venue"
},
  "geometry": {"coordinates":[-73.922855,40.65556],"type":"Point"}
}