{
  "type": "Feature",
  "properties": {
    "iso:country":"US",
    "sg:address":"5916 N Elm Ave",
    "sg:city":"Millerton",
    "sg:classifiers":[
        {
            "category":"Home & Garden",
            "subcategory":"Home Furnishings",
            "type":"Retail Goods"
        }
    ],
    "sg:phone":"+1 518 789 6603",
    "sg:postcode":"12546",
    "sg:province":"NY",
    "sg:tags":[
        "fixture",
        "lighting"
    ],
    "wof:name":"Shandells",
    "wof:placetype":"venue"
},
  "geometry": {"coordinates":[-73.51295,41.953194],"type":"Point"}
}