{
  "type": "Feature",
  "properties": {
    "iso:country":"US",
    "sg:address":"40 Center St",
    "sg:city":"Waterloo",
    "sg:classifiers":[
        {
            "category":"Organizations",
            "subcategory":"Non-profit Organization",
            "type":"Services"
        }
    ],
    "sg:phone":"+1 315 539 2969",
    "sg:postcode":"13165",
    "sg:province":"NY",
    "wof:name":"Seneca White Deer Inc",
    "wof:placetype":"venue"
},
  "geometry": {"coordinates":[-76.86501199999999,42.912808],"type":"Point"}
}