{
  "type": "Feature",
  "properties": {
    "addr:full":"7651 Seneca St East Aurora NY 14052",
    "addr:housenumber":"7651",
    "addr:postcode":"14052",
    "addr:street":"Seneca St",
    "iso:country":"US",
    "sg:address":"7651 Seneca St",
    "sg:city":"East Aurora",
    "sg:classifiers":[
        {
            "category":"Local Transit",
            "type":"Transportation"
        }
    ],
    "sg:phone":"+1 716 652 5857",
    "sg:postcode":"14052",
    "sg:province":"NY",
    "sg:tags":[
        "limousine"
    ],
    "wof:name":"Affordable Limousine Svc",
    "wof:placetype":"venue"
},
  "geometry": {"coordinates":[-78.652383,42.790484],"type":"Point"}
}