{
  "type": "Feature",
  "properties": {
    "addr:full":"145 Ave of the Americas New York NY 10013",
    "addr:housenumber":"145",
    "addr:postcode":"10013",
    "addr:street":"Ave Of The Americas",
    "iso:country":"US",
    "sg:address":"145 Ave of the Americas",
    "sg:city":"New York",
    "sg:classifiers":[
        {
            "category":"Professional",
            "subcategory":"Computer Services",
            "type":"Services"
        }
    ],
    "sg:phone":"+1 212 627 2077",
    "sg:postcode":"10013",
    "sg:province":"NY",
    "sg:tags":[
        "consultant",
        "designer"
    ],
    "wof:name":"Castle Computer Systems",
    "wof:placetype":"venue"
},
  "geometry": {"coordinates":[-74.004031,40.725513],"type":"Point"}
}