{
  "type": "Feature",
  "properties": {
    "addr:full":"1034 Coney Island Avenue Brooklyn NY 11230",
    "addr:housenumber":"1034",
    "addr:postcode":"11230",
    "addr:street":"Coney Island Avenue",
    "iso:country":"US",
    "sg:address":"1034 Coney Island Avenue",
    "sg:city":"Brooklyn",
    "sg:classifiers":[
        {
            "category":"Food & Beverages",
            "subcategory":"Groceries & Convenience Stores",
            "type":"Retail Goods"
        }
    ],
    "sg:phone":"+1 718 434 0480",
    "sg:postcode":"11230",
    "sg:province":"NY",
    "wof:name":"Apna Wattan Groceries and Halal Meat",
    "wof:placetype":"venue"
},
  "geometry": {"coordinates":[-73.96704800000001,40.632433],"type":"Point"}
}