{
  "type": "Feature",
  "properties": {
    "addr:full":"4763 Salina St Pulaski NY 13142",
    "addr:housenumber":"4763",
    "addr:postcode":"13142",
    "addr:street":"Salina St",
    "iso:country":"US",
    "sg:address":"4763 Salina St",
    "sg:city":"Pulaski",
    "sg:classifiers":[
        {
            "category":"Banks & Credit Unions",
            "subcategory":"Bank",
            "type":"Services"
        }
    ],
    "sg:phone":"+1 315 298 6661",
    "sg:postcode":"13142",
    "sg:province":"NY",
    "wof:name":"Key Bank",
    "wof:placetype":"venue"
},
  "geometry": {"coordinates":[-76.12660200000001,43.561811],"type":"Point"}
}