{
  "type": "Feature",
  "properties": {
    "addr:full":"7864 Turin Rd Rome NY 13440",
    "addr:housenumber":"7864",
    "addr:postcode":"13440",
    "addr:street":"Turin Rd",
    "iso:country":"US",
    "sg:address":"7864 Turin Rd",
    "sg:city":"Rome",
    "sg:classifiers":[
        {
            "category":"Health Services",
            "subcategory":"Chiropractor",
            "type":"Services"
        }
    ],
    "sg:phone":"+1   ",
    "sg:postcode":"13440",
    "sg:province":"NY",
    "wof:name":"Stuart W Anken DC",
    "wof:placetype":"venue"
},
  "geometry": {"coordinates":[-75.456047,43.24284],"type":"Point"}
}