{
  "type": "Feature",
  "properties": {
    "addr:full":"327 Hamilton Ave Brooklyn NY 11231",
    "addr:housenumber":"327",
    "addr:postcode":"11231",
    "addr:street":"Hamilton Ave",
    "iso:country":"US",
    "sg:address":"327 Hamilton Ave",
    "sg:city":"Brooklyn",
    "sg:classifiers":[
        {
            "category":"Building & Trades",
            "subcategory":"Construction",
            "type":"Services"
        }
    ],
    "sg:phone":"+1 718 875 0933",
    "sg:postcode":"11231",
    "sg:province":"NY",
    "sg:tags":[
        "maintenance",
        "contractor"
    ],
    "wof:name":"Sesa Maintenance",
    "wof:placetype":"venue"
},
  "geometry": {"coordinates":[-74.00035099999999,40.675176],"type":"Point"}
}