{
  "type": "Feature",
  "properties": {
    "iso:country":"US",
    "sg:address":"70 Chardonnay Dr",
    "sg:city":"Fairport",
    "sg:classifiers":[
        {
            "category":"Professional",
            "subcategory":"Management & Consulting",
            "type":"Services"
        }
    ],
    "sg:phone":"+1 585 377 8491",
    "sg:postcode":"14450",
    "sg:province":"NY",
    "sg:tags":[
        "consultant",
        "business"
    ],
    "wof:name":"Havens Management Group",
    "wof:placetype":"venue"
},
  "geometry": {"coordinates":[-77.43418,43.065746],"type":"Point"}
}