{
  "type": "Feature",
  "properties": {
    "iso:country":"US",
    "sg:address":"209 Willow Ave",
    "sg:city":"Ithaca",
    "sg:classifiers":[
        {
            "category":"Professional",
            "type":"Services"
        }
    ],
    "sg:phone":"+1   ",
    "sg:postcode":"14850",
    "sg:province":"NY",
    "wof:name":"Anne Mazer",
    "wof:placetype":"venue"
},
  "geometry": {"coordinates":[-76.500888,42.446956],"type":"Point"}
}