{
  "type": "Feature",
  "properties": {
    "addr:full":"257 Columbus Avenue New York NY 10023",
    "addr:housenumber":"257",
    "addr:postcode":"10023",
    "addr:street":"Columbus Avenue",
    "iso:country":"US",
    "sg:address":"257 Columbus Avenue",
    "sg:city":"New York",
    "sg:classifiers":[
        {
            "category":"Building & Trades",
            "subcategory":"Locksmith",
            "type":"Services"
        }
    ],
    "sg:phone":"+1 917 464 2563",
    "sg:postcode":"10023",
    "sg:province":"NY",
    "sg:tags":[
        "key"
    ],
    "wof:name":"0 0 0 1 24 Hour A Emerg Locksmith",
    "wof:placetype":"venue"
},
  "geometry": {"coordinates":[-73.978978,40.777345],"type":"Point"}
}