{
  "type": "Feature",
  "properties": {
    "iso:country":"US",
    "sg:address":"382 State Hwy 59",
    "sg:city":"Monsey",
    "sg:classifiers":[
        {
            "category":"Manufacturing",
            "subcategory":"Tools & Machinery",
            "type":"Manufacturing & Wholesale Goods"
        }
    ],
    "sg:phone":"+1   ",
    "sg:postcode":"10952",
    "sg:province":"NY",
    "sg:tags":[
        "management",
        "asset",
        "mfg"
    ],
    "wof:name":"Awid",
    "wof:placetype":"venue"
},
  "geometry": {"coordinates":[-74.094004,41.11059],"type":"Point"}
}