{
  "type": "Feature",
  "properties": {
    "iso:country":"US",
    "sg:address":"12517 Ridge Rd",
    "sg:city":"Medina",
    "sg:classifiers":[
        {
            "category":"Retail",
            "subcategory":"Auto Repair",
            "type":"Services"
        }
    ],
    "sg:phone":"+1 585 798 1234",
    "sg:postcode":"14103",
    "sg:province":"NY",
    "sg:tags":[
        "body",
        "automobile",
        "painting",
        "repairing"
    ],
    "wof:name":"Richard Thaine Repair",
    "wof:placetype":"venue"
},
  "geometry": {"coordinates":[-78.31255899999999,43.278724],"type":"Point"}
}