{
  "type": "Feature",
  "properties": {
    "iso:country":"US",
    "sg:address":"523 Longfellow Ave",
    "sg:city":"Bronx",
    "sg:classifiers":[
        {
            "category":"Retail",
            "subcategory":"Auto Repair",
            "type":"Services"
        }
    ],
    "sg:phone":"+1 718 684 7939",
    "sg:postcode":"10474",
    "sg:province":"NY",
    "sg:tags":[
        "repairing",
        "automobile"
    ],
    "wof:name":"TNT Auto Svc",
    "wof:placetype":"venue"
},
  "geometry": {"coordinates":[-73.884032,40.812055],"type":"Point"}
}