{
  "type": "Feature",
  "properties": {
    "addr:full":"4765 Broadway New York NY 10034",
    "addr:housenumber":"4765",
    "addr:postcode":"10034",
    "addr:street":"Broadway",
    "iso:country":"US",
    "sg:address":"4765 Broadway",
    "sg:city":"New York",
    "sg:classifiers":[
        {
            "category":"Professional",
            "type":"Services"
        }
    ],
    "sg:phone":"+1 212 544 2323",
    "sg:postcode":"10034",
    "sg:province":"NY",
    "sg:tags":[
        "establishment"
    ],
    "wof:name":"Maldonado Berkys",
    "wof:placetype":"venue"
},
  "geometry": {"coordinates":[-73.926221,40.86595],"type":"Point"}
}