{
  "type": "Feature",
  "properties": {
    "addr:full":"705 E 6th Street New York NY 10009",
    "addr:housenumber":"705",
    "addr:postcode":"10009",
    "addr:street":"E 6Th Street",
    "iso:country":"US",
    "sg:address":"705 E 6th Street",
    "sg:city":"New York",
    "sg:classifiers":[
        {
            "category":"Organizations",
            "subcategory":"Non-profit Organization",
            "type":"Services"
        }
    ],
    "sg:phone":"+1 212 375 1074",
    "sg:postcode":"10009",
    "sg:province":"NY",
    "sg:tags":[
        "service/non-profit",
        "community"
    ],
    "wof:name":"Grand Street Settlement",
    "wof:placetype":"venue"
},
  "geometry": {"coordinates":[-73.978352,40.723225],"type":"Point"}
}