{
  "type": "Feature",
  "properties": {
    "iso:country":"US",
    "sg:address":"334 E Shore Rd",
    "sg:city":"Lindenhurst",
    "sg:classifiers":[
        {
            "category":"Freight",
            "type":"Transportation"
        }
    ],
    "sg:phone":"+1   ",
    "sg:postcode":"11757",
    "sg:province":"NY",
    "sg:tags":[
        "operator",
        "local",
        "trucking"
    ],
    "wof:name":"Dads Transport Inc",
    "wof:placetype":"venue"
},
  "geometry": {"coordinates":[-73.35696299999999,40.675052],"type":"Point"}
}