{
  "type": "Feature",
  "properties": {
    "addr:full":"30 Christine Ln Yaphank NY 11980",
    "addr:housenumber":"30",
    "addr:postcode":"11980",
    "addr:street":"Christine Ln",
    "iso:country":"US",
    "sg:address":"30 Christine Ln",
    "sg:city":"Yaphank",
    "sg:classifiers":[
        {
            "category":"Building & Trades",
            "subcategory":"Pest Control",
            "type":"Services"
        }
    ],
    "sg:phone":"+1 631 924 6355",
    "sg:postcode":"11980",
    "sg:province":"NY",
    "wof:name":"Bug Fighters",
    "wof:placetype":"venue"
},
  "geometry": {"coordinates":[-72.901623,40.804901],"type":"Point"}
}