{
  "type": "Feature",
  "properties": {
    "iso:country":"US",
    "sg:address":"2714 Beverley Road",
    "sg:city":"Brooklyn",
    "sg:classifiers":[
        {
            "category":"Retail",
            "subcategory":"Auto Repair",
            "type":"Services"
        }
    ],
    "sg:phone":"+1 718 693 7625",
    "sg:postcode":"11226",
    "sg:province":"NY",
    "wof:name":"Jean Auto Repair",
    "wof:placetype":"venue"
},
  "geometry": {"coordinates":[-73.951686,40.644842],"type":"Point"}
}