{
  "type": "Feature",
  "properties": {
    "iso:country":"US",
    "sg:address":"179 Glen St",
    "sg:city":"Glens Falls",
    "sg:classifiers":[
        {
            "category":"Shopping",
            "subcategory":"Used Merchandise",
            "type":"Retail Goods"
        }
    ],
    "sg:phone":"+1 518 745 1285",
    "sg:postcode":"12801",
    "sg:province":"NY",
    "sg:tags":[
        "antique"
    ],
    "wof:name":"Poor Richard's Antiques",
    "wof:placetype":"venue"
},
  "geometry": {"coordinates":[-73.645116,43.310166],"type":"Point"}
}