{
  "type": "Feature",
  "properties": {
    "addr:full":"1 Lowndes Ave # A Huntington Station NY 11746",
    "addr:housenumber":"1",
    "addr:postcode":"11746",
    "addr:street":"Lowndes Ave # A Huntington",
    "iso:country":"US",
    "sg:address":"1 Lowndes Ave # A",
    "sg:city":"Huntington Station",
    "sg:classifiers":[
        {
            "category":"Real Estate",
            "subcategory":"Real Estate Operator",
            "type":"Services"
        }
    ],
    "sg:phone":"+1 631 427 6220",
    "sg:postcode":"11746",
    "sg:province":"NY",
    "sg:tags":[
        "apartment"
    ],
    "wof:name":"Gateway Gardens",
    "wof:placetype":"venue"
},
  "geometry": {"coordinates":[-73.416602,40.857167],"type":"Point"}
}