{
  "type": "Feature",
  "properties": {
    "addr:full":"8 S Franklin St Cortland NY 13045",
    "addr:housenumber":"8",
    "addr:postcode":"13045",
    "addr:street":"S Franklin St",
    "iso:country":"US",
    "sg:address":"8 S Franklin St",
    "sg:city":"Cortland",
    "sg:classifiers":[
        {
            "category":"Personal",
            "subcategory":"Beauty Salon",
            "type":"Services"
        }
    ],
    "sg:phone":"+1 607 753 1553",
    "sg:postcode":"13045",
    "sg:province":"NY",
    "wof:name":"Lisa's Beauty Shop",
    "wof:placetype":"venue"
},
  "geometry": {"coordinates":[-76.164475,42.597827],"type":"Point"}
}