{
  "type": "Feature",
  "properties": {
    "iso:country":"US",
    "sg:address":"130 William St 5th Floor",
    "sg:city":"New York",
    "sg:classifiers":[
        {
            "category":"Real Estate",
            "subcategory":"Real Estate Services",
            "type":"Services"
        }
    ],
    "sg:phone":"+1 646 783 7501",
    "sg:postcode":"10038",
    "sg:province":"NY",
    "sg:tags":[
        "management",
        "property"
    ],
    "sg:website":"earproperties.com",
    "wof:name":"E.A.R. Properties International LLC",
    "wof:placetype":"venue"
},
  "geometry": {"coordinates":[-74.006439,40.709079],"type":"Point"}
}