{
  "type": "Feature",
  "properties": {
    "addr:full":"173 E 3rd Street New York NY 10009",
    "addr:housenumber":"173",
    "addr:postcode":"10009",
    "addr:street":"E 3Rd Street",
    "iso:country":"US",
    "sg:address":"173 E 3rd Street",
    "sg:city":"New York",
    "sg:classifiers":[
        {
            "category":"Organizations",
            "subcategory":"Religious Organization",
            "type":"Services"
        }
    ],
    "sg:phone":"+1 212 673 4224",
    "sg:postcode":"10009",
    "sg:province":"NY",
    "wof:name":"Most Holy Redeemer Church",
    "wof:placetype":"venue"
},
  "geometry": {"coordinates":[-73.98406199999999,40.723243],"type":"Point"}
}