{
  "type": "Feature",
  "properties": {
    "addr:full":"340 Delaware Ave Buffalo NY 14202",
    "addr:housenumber":"340",
    "addr:postcode":"14202",
    "addr:street":"Delaware Ave",
    "iso:country":"US",
    "sg:address":"340 Delaware Ave",
    "sg:city":"Buffalo",
    "sg:classifiers":[
        {
            "category":"Arts & Performance",
            "subcategory":"Art Gallery",
            "type":"Entertainment"
        }
    ],
    "sg:phone":"+1 716 842 1525",
    "sg:postcode":"14202",
    "sg:province":"NY",
    "wof:name":"Starlight Studio And Art Gallery",
    "wof:placetype":"venue"
},
  "geometry": {"coordinates":[-78.87599400000001,42.893636],"type":"Point"}
}