{
  "type": "Feature",
  "properties": {
    "iso:country":"US",
    "sg:address":"5375 Hill Rd",
    "sg:city":"Albion",
    "sg:classifiers":[
        {
            "category":"Building & Trades",
            "subcategory":"Landscaping Services",
            "type":"Services"
        }
    ],
    "sg:phone":"+1 585 589 8393",
    "sg:postcode":"14411",
    "sg:province":"NY",
    "wof:name":"Doctor Toms Lawn & Garden",
    "wof:placetype":"venue"
},
  "geometry": {"coordinates":[-78.23838000000001,43.149064],"type":"Point"}
}