{
  "type": "Feature",
  "properties": {
    "iso:country":"US",
    "sg:address":"1655 Elmwood Ave",
    "sg:city":"Rochester",
    "sg:classifiers":[
        {
            "category":"Insurance",
            "subcategory":"Insurance Agent",
            "type":"Services"
        }
    ],
    "sg:phone":"+1 585 244 6800",
    "sg:postcode":"14620",
    "sg:province":"NY",
    "wof:name":"Optima Group",
    "wof:placetype":"venue"
},
  "geometry": {"coordinates":[-77.589843,43.125626],"type":"Point"}
}