{
  "type": "Feature",
  "properties": {
    "addr:full":"716 Sunrise Hwy Rockville Centre NY 11570",
    "addr:housenumber":"716",
    "addr:postcode":"11570",
    "addr:street":"Sunrise Hwy",
    "iso:country":"US",
    "sg:address":"716 Sunrise Hwy",
    "sg:city":"Rockville Centre",
    "sg:classifiers":[
        {
            "category":"Restaurant",
            "type":"Food & Drink"
        }
    ],
    "sg:phone":"+1   ",
    "sg:postcode":"11570",
    "sg:province":"NY",
    "sg:tags":[
        "drinking",
        "eating"
    ],
    "wof:name":"TGI Fridays",
    "wof:placetype":"venue"
},
  "geometry": {"coordinates":[-73.634491,40.657362],"type":"Point"}
}