{
  "type": "Feature",
  "properties": {
    "iso:country":"US",
    "sg:address":"566 East Ave",
    "sg:city":"Rochester",
    "sg:classifiers":[
        {
            "category":"Professional",
            "type":"Services"
        }
    ],
    "sg:phone":"+1 585 271 0580",
    "sg:postcode":"14607",
    "sg:province":"NY",
    "sg:tags":[
        "arts",
        "artist"
    ],
    "wof:name":"John Wagner",
    "wof:placetype":"venue"
},
  "geometry": {"coordinates":[-77.589658,43.153841],"type":"Point"}
}