{
  "type": "Feature",
  "properties": {
    "addr:full":"26 Berry Hill Rd Syosset NY 11791",
    "addr:housenumber":"26",
    "addr:postcode":"11791",
    "addr:street":"Berry Hill Rd",
    "iso:country":"US",
    "sg:address":"26 Berry Hill Rd",
    "sg:city":"Syosset",
    "sg:classifiers":[
        {
            "category":"Health Services",
            "subcategory":"Doctor",
            "type":"Services"
        },
        {
            "category":"Health Services",
            "subcategory":"Clinic",
            "type":"Services"
        }
    ],
    "sg:phone":"+1 516 921 2327",
    "sg:postcode":"11791",
    "sg:province":"NY",
    "sg:tags":[
        "psychological",
        "psychologist"
    ],
    "sg:website":"http://www.michaelsteinberg.com",
    "wof:name":"Michael Steinberg",
    "wof:placetype":"venue"
},
  "geometry": {"coordinates":[-73.50224300000001,40.82703],"type":"Point"}
}