{
  "type": "Feature",
  "properties": {
    "iso:country":"US",
    "sg:address":"172 Center Ln",
    "sg:city":"Levittown",
    "sg:classifiers":[
        {
            "category":"Shopping",
            "subcategory":"Discount & Variety Stores",
            "type":"Retail Goods"
        }
    ],
    "sg:phone":"+1   ",
    "sg:postcode":"11756",
    "sg:province":"NY",
    "sg:tags":[
        "stationery",
        "cards",
        "candy",
        "gift"
    ],
    "wof:name":"Center Lane Stationery",
    "wof:placetype":"venue"
},
  "geometry": {"coordinates":[-73.524323,40.71416],"type":"Point"}
}