{
  "type": "Feature",
  "properties": {
    "addr:full":"146 S Country Rd Bellport NY 11713",
    "addr:housenumber":"146",
    "addr:postcode":"11713",
    "addr:street":"S Country Rd",
    "iso:country":"US",
    "sg:address":"146 S Country Rd",
    "sg:city":"Bellport",
    "sg:classifiers":[
        {
            "category":"Shopping",
            "subcategory":"News",
            "type":"Retail Goods"
        }
    ],
    "sg:phone":"+1   ",
    "sg:postcode":"11713",
    "sg:province":"NY",
    "wof:name":"Senior News Long Island",
    "wof:placetype":"venue"
},
  "geometry": {"coordinates":[-72.93809400000001,40.758254],"type":"Point"}
}