{
  "type": "Feature",
  "properties": {
    "addr:full":"2922 30th Avenue Astoria NY 11102",
    "addr:housenumber":"2922",
    "addr:postcode":"11102",
    "addr:street":"30Th Avenue",
    "iso:country":"US",
    "sg:address":"2922 30th Avenue",
    "sg:city":"Astoria",
    "sg:classifiers":[
        {
            "category":"Health Services",
            "subcategory":"Doctor",
            "type":"Services"
        }
    ],
    "sg:phone":"+1 718 545 2500",
    "sg:postcode":"11102",
    "sg:province":"NY",
    "wof:name":"Astoria Pediatrics",
    "wof:placetype":"venue"
},
  "geometry": {"coordinates":[-73.922923,40.76758],"type":"Point"}
}