{
  "type": "Feature",
  "properties": {
    "addr:full":"200 W Houston St New York NY 10014",
    "addr:housenumber":"200",
    "addr:postcode":"10014",
    "addr:street":"W Houston St",
    "iso:country":"US",
    "sg:address":"200 W Houston St",
    "sg:city":"New York",
    "sg:classifiers":[
        {
            "category":"Real Estate",
            "subcategory":"Real Estate Agent",
            "type":"Services"
        }
    ],
    "sg:phone":"+1 212 691 7588",
    "sg:postcode":"10014",
    "sg:province":"NY",
    "wof:name":"Apran Associates Inc",
    "wof:placetype":"venue"
},
  "geometry": {"coordinates":[-74.00492800000001,40.728631],"type":"Point"}
}