{
  "type": "Feature",
  "properties": {
    "iso:country":"US",
    "sg:address":"17 New Paltz Byp",
    "sg:city":"New Paltz",
    "sg:classifiers":[
        {
            "category":"Shopping",
            "type":"Retail Goods"
        }
    ],
    "sg:phone":"+1 845 255 1241",
    "sg:postcode":"12561",
    "sg:province":"NY",
    "sg:tags":[
        "art",
        "gallery",
        "dealer"
    ],
    "wof:name":"Mark Gruber Gallery",
    "wof:placetype":"venue"
},
  "geometry": {"coordinates":[-74.068438,41.739878],"type":"Point"}
}