{
  "type": "Feature",
  "properties": {
    "iso:country":"US",
    "sg:address":"16 Tobias St",
    "sg:city":"Hicksville",
    "sg:classifiers":[
        {
            "category":"Home & Garden",
            "subcategory":"Furniture",
            "type":"Retail Goods"
        }
    ],
    "sg:phone":"+1 516 931 8505",
    "sg:postcode":"11801",
    "sg:province":"NY",
    "sg:tags":[
        "store"
    ],
    "wof:name":"M&J Furniture Service",
    "wof:placetype":"venue"
},
  "geometry": {"coordinates":[-73.516947,40.75026],"type":"Point"}
}