{
  "type": "Feature",
  "properties": {
    "iso:country":"US",
    "sg:address":"2108 Ocean Pkwy",
    "sg:city":"Brooklyn",
    "sg:classifiers":[
        {
            "category":"Place Of Worship",
            "subcategory":"Synagogue",
            "type":"Public Place"
        }
    ],
    "sg:phone":"+1 718 645 0448",
    "sg:postcode":"11223",
    "sg:province":"NY",
    "wof:name":"Congregation Beth Yosef",
    "wof:placetype":"venue"
},
  "geometry": {"coordinates":[-73.965897,40.597698],"type":"Point"}
}