{
  "type": "Feature",
  "properties": {
    "iso:country":"US",
    "sg:address":"1372 Broadway",
    "sg:city":"New York",
    "sg:classifiers":[
        {
            "category":"Building & Trades",
            "subcategory":"Construction",
            "type":"Services"
        }
    ],
    "sg:phone":"+1 646 366 9909",
    "sg:postcode":"10018",
    "sg:province":"NY",
    "sg:tags":[
        "contractor"
    ],
    "wof:name":"Ibex Construction Corporation",
    "wof:placetype":"venue"
},
  "geometry": {"coordinates":[-73.987504,40.75204],"type":"Point"}
}