{
  "type": "Feature",
  "properties": {
    "addr:full":"2023 Steinway Street Astoria NY 11105",
    "addr:housenumber":"2023",
    "addr:postcode":"11105",
    "addr:street":"Steinway Street",
    "iso:country":"US",
    "sg:address":"2023 Steinway Street",
    "sg:city":"Astoria",
    "sg:classifiers":[
        {
            "category":"Retail",
            "subcategory":"Auto Repair",
            "type":"Services"
        }
    ],
    "sg:phone":"+1 212 786 4949",
    "sg:postcode":"11105",
    "sg:province":"NY",
    "wof:name":"Yes Private Car Svc",
    "wof:placetype":"venue"
},
  "geometry": {"coordinates":[-73.902311,40.775893],"type":"Point"}
}