{
  "type": "Feature",
  "properties": {
    "addr:full":"228 Kingsley St Buffalo NY 14208",
    "addr:housenumber":"228",
    "addr:postcode":"14208",
    "addr:street":"Kingsley St",
    "iso:country":"US",
    "sg:address":"228 Kingsley St",
    "sg:city":"Buffalo",
    "sg:classifiers":[
        {
            "category":"Organizations",
            "subcategory":"Religious Organization",
            "type":"Services"
        }
    ],
    "sg:phone":"+1 716 883 2093",
    "sg:postcode":"14208",
    "sg:province":"NY",
    "sg:tags":[
        "clergy"
    ],
    "wof:name":"June M Williams",
    "wof:placetype":"venue"
},
  "geometry": {"coordinates":[-78.845187,42.908223],"type":"Point"}
}