{
  "type": "Feature",
  "properties": {
    "addr:full":"3170 Spawn Rd Schenectady NY 12303",
    "addr:postcode":"3170;12303",
    "addr:street":"Spawn Rd",
    "iso:country":"US",
    "sg:address":"3170 Spawn Rd",
    "sg:city":"Schenectady",
    "sg:classifiers":[
        {
            "category":"Professional",
            "type":"Services"
        }
    ],
    "sg:phone":"+1 518 356 6619",
    "sg:postcode":"12303",
    "sg:province":"NY",
    "sg:tags":[
        "establishment"
    ],
    "wof:name":"Nielsen Assoc",
    "wof:placetype":"venue"
},
  "geometry": {"coordinates":[-73.923177,42.730993],"type":"Point"}
}