{
  "type": "Feature",
  "properties": {
    "iso:country":"US",
    "sg:address":"61 Murray St",
    "sg:city":"New York",
    "sg:classifiers":[
        {
            "category":"Restaurant",
            "type":"Food & Drink"
        }
    ],
    "sg:menulink":"http://www.allmenus.com/ny/new-york/279800-palermo-pizza/menu/",
    "sg:phone":"+1 212 732 5627",
    "sg:postcode":"10007",
    "sg:province":"NY",
    "sg:tags":[
        "pasta",
        "calzones",
        "american",
        "salad",
        "pizza"
    ],
    "wof:name":"Palermo Pizza",
    "wof:placetype":"venue"
},
  "geometry": {"coordinates":[-74.009997,40.714335],"type":"Point"}
}