{
  "type": "Feature",
  "properties": {
    "addr:full":"38 E South St Geneseo NY 14454",
    "addr:housenumber":"38 e",
    "addr:postcode":"14454",
    "addr:street":"South St",
    "iso:country":"US",
    "sg:address":"38 E South St",
    "sg:city":"Geneseo",
    "sg:classifiers":[
        {
            "category":"Professional",
            "subcategory":"Engineering",
            "type":"Services"
        }
    ],
    "sg:phone":"+1 585 243 1320",
    "sg:postcode":"14454",
    "sg:province":"NY",
    "sg:tags":[
        "construction"
    ],
    "wof:name":"Garrett Engineering PC",
    "wof:placetype":"venue"
},
  "geometry": {"coordinates":[-77.803022,42.793381],"type":"Point"}
}