{
  "type": "Feature",
  "properties": {
    "addr:full":"2958 W 8th St Brooklyn NY 11224",
    "addr:housenumber":"2958",
    "addr:postcode":"11224",
    "addr:street":"W 8Th St",
    "iso:country":"US",
    "sg:address":"2958 W 8th St",
    "sg:city":"Brooklyn",
    "sg:classifiers":[
        {
            "category":"Freight",
            "type":"Transportation"
        }
    ],
    "sg:phone":"+1 212 932 2020",
    "sg:postcode":"11224",
    "sg:province":"NY",
    "sg:tags":[
        "mover"
    ],
    "wof:name":"Athletic Movers Inc",
    "wof:placetype":"venue"
},
  "geometry": {"coordinates":[-73.97667,40.575613],"type":"Point"}
}