{
  "type": "Feature",
  "properties": {
    "addr:full":"1015 Madison Ave Rm 303 New York NY 10075",
    "addr:housenumber":"1015;303",
    "addr:postcode":"10075",
    "addr:street":"Madison Ave Rm",
    "iso:country":"US",
    "sg:address":"1015 Madison Ave Rm 303",
    "sg:city":"New York",
    "sg:classifiers":[
        {
            "category":"Health Services",
            "subcategory":"Health Practitioner",
            "type":"Services"
        }
    ],
    "sg:phone":"+1 212 439 9303",
    "sg:postcode":"10075",
    "sg:province":"NY",
    "sg:tags":[
        "therapy",
        "physical"
    ],
    "wof:name":"Physiocare Physical Therapy",
    "wof:placetype":"venue"
},
  "geometry": {"coordinates":[-73.962352,40.775709],"type":"Point"}
}