{
  "type": "Feature",
  "properties": {
    "iso:country":"US",
    "sg:address":"70 Cliffside Dr",
    "sg:city":"Canandaigua",
    "sg:classifiers":[
        {
            "category":"Travel",
            "subcategory":"Travel Agent",
            "type":"Entertainment"
        }
    ],
    "sg:phone":"+1   ",
    "sg:postcode":"14424",
    "sg:province":"NY",
    "sg:tags":[
        "agency"
    ],
    "wof:name":"I Travel",
    "wof:placetype":"venue"
},
  "geometry": {"coordinates":[-77.33642,42.748839],"type":"Point"}
}