{
  "type": "Feature",
  "properties": {
    "addr:full":"767 Washington St New York NY 10014",
    "addr:housenumber":"767",
    "addr:postcode":"10014",
    "addr:street":"Washington St",
    "iso:country":"US",
    "sg:address":"767 Washington St",
    "sg:city":"New York",
    "sg:classifiers":[
        {
            "category":"Bars & Pubs",
            "type":"Food & Drink"
        },
        {
            "category":"Restaurant",
            "type":"Food & Drink"
        }
    ],
    "sg:phone":"+1 212 243 1053",
    "sg:postcode":"10014",
    "sg:province":"NY",
    "sg:tags":[
        "mexican"
    ],
    "sg:website":"www.tortillaflatsnyc.com",
    "wof:name":"Tortilla Flats",
    "wof:placetype":"venue"
},
  "geometry": {"coordinates":[-74.007957,40.737439],"type":"Point"}
}