{
  "type": "Feature",
  "properties": {
    "addr:full":"265 Guyon Avenue Staten Island NY 10306",
    "addr:housenumber":"265",
    "addr:postcode":"10306",
    "addr:street":"Guyon Avenue",
    "iso:country":"US",
    "sg:address":"265 Guyon Avenue",
    "sg:city":"Staten Island",
    "sg:classifiers":[
        {
            "category":"Health Services",
            "subcategory":"Dentist",
            "type":"Services"
        }
    ],
    "sg:phone":"+1 718 980 4600",
    "sg:postcode":"10306",
    "sg:province":"NY",
    "wof:name":"Zona Joseph M DDS",
    "wof:placetype":"venue"
},
  "geometry": {"coordinates":[-74.121025,40.561115],"type":"Point"}
}