{
  "type": "Feature",
  "properties": {
    "iso:country":"US",
    "sg:address":"169 54th St",
    "sg:city":"Brooklyn",
    "sg:classifiers":[
        {
            "category":"Shopping",
            "subcategory":"Computers & Home Electronics",
            "type":"Retail Goods"
        }
    ],
    "sg:phone":"+1 718 439 4026",
    "sg:postcode":"11220",
    "sg:province":"NY",
    "sg:tags":[
        "equipment",
        "dealer"
    ],
    "wof:name":"B S Computers Inc",
    "wof:placetype":"venue"
},
  "geometry": {"coordinates":[-74.020369,40.647834],"type":"Point"}
}