{
  "type": "Feature",
  "properties": {
    "iso:country":"US",
    "sg:address":"21 Howard St",
    "sg:city":"New York",
    "sg:classifiers":[
        {
            "category":"Personal",
            "subcategory":"Beauty Salon",
            "type":"Services"
        }
    ],
    "sg:phone":"+1 212 219 0356",
    "sg:postcode":"10013",
    "sg:province":"NY",
    "wof:name":"Hazel Beauty & Fitness Intl",
    "wof:placetype":"venue"
},
  "geometry": {"coordinates":[-74.000291,40.719263],"type":"Point"}
}