{
  "type": "Feature",
  "properties": {
    "addr:full":"837 S 1st St Ronkonkoma NY 11779",
    "addr:housenumber":"837",
    "addr:postcode":"11779",
    "addr:street":"S 1St St",
    "iso:country":"US",
    "sg:address":"837 S 1st St",
    "sg:city":"Ronkonkoma",
    "sg:classifiers":[
        {
            "category":"Home & Garden",
            "subcategory":"Building Materials",
            "type":"Retail Goods"
        }
    ],
    "sg:phone":"+1 631 471 1906",
    "sg:postcode":"11779",
    "sg:province":"NY",
    "sg:tags":[
        "windows"
    ],
    "wof:name":"Dress Up Your Windows",
    "wof:placetype":"venue"
},
  "geometry": {"coordinates":[-73.11752799999999,40.798944],"type":"Point"}
}