{
  "type": "Feature",
  "properties": {
    "iso:country":"US",
    "sg:address":"4948 Bigford Rd",
    "sg:city":"Medina",
    "sg:classifiers":[
        {
            "category":"Farming",
            "subcategory":"Farm",
            "type":"Manufacturing & Wholesale Goods"
        }
    ],
    "sg:phone":"+1 585 798 0673",
    "sg:postcode":"14103",
    "sg:province":"NY",
    "sg:tags":[
        "crop",
        "general"
    ],
    "wof:name":"Boyce Farms",
    "wof:placetype":"venue"
},
  "geometry": {"coordinates":[-78.352991,43.174654],"type":"Point"}
}