{
  "type": "Feature",
  "properties": {
    "addr:full":"2107 E 9th St Brooklyn NY 11223",
    "addr:housenumber":"2107",
    "addr:postcode":"11223",
    "addr:street":"E 9Th St",
    "iso:country":"US",
    "sg:address":"2107 E 9th St",
    "sg:city":"Brooklyn",
    "sg:classifiers":[
        {
            "category":"Wholesale",
            "subcategory":"Medical Equipment & Supplies",
            "type":"Manufacturing & Wholesale Goods"
        }
    ],
    "sg:phone":"+1 718 627 5257",
    "sg:postcode":"11223",
    "sg:province":"NY",
    "sg:tags":[
        "physician",
        "surgeon"
    ],
    "wof:name":"Amol Inc",
    "wof:placetype":"venue"
},
  "geometry": {"coordinates":[-73.961647,40.596232],"type":"Point"}
}