{
  "type": "Feature",
  "properties": {
    "addr:full":"305 Broadway New York NY 10007",
    "addr:housenumber":"305",
    "addr:postcode":"10007",
    "addr:street":"Broadway",
    "iso:country":"US",
    "sg:address":"305 Broadway",
    "sg:city":"New York",
    "sg:classifiers":[
        {
            "category":"Professional",
            "subcategory":"Lawyer & Legal Services",
            "type":"Services"
        }
    ],
    "sg:phone":"+1 212 267 5800",
    "sg:postcode":"10007",
    "sg:province":"NY",
    "wof:name":"Zalewski Steven Atty",
    "wof:placetype":"venue"
},
  "geometry": {"coordinates":[-74.005312,40.715369],"type":"Point"}
}