{
  "type": "Feature",
  "properties": {
    "iso:country":"US",
    "sg:address":"804 Karenwald Ln",
    "sg:city":"Schenectady",
    "sg:classifiers":[
        {
            "category":"Banks & Credit Unions",
            "subcategory":"Investment Brokerage",
            "type":"Services"
        }
    ],
    "sg:phone":"+1 518 370 0375",
    "sg:postcode":"12309",
    "sg:province":"NY",
    "sg:tags":[
        "advisory"
    ],
    "wof:name":"New York State Of The Capital D",
    "wof:placetype":"venue"
},
  "geometry": {"coordinates":[-73.903831,42.799613],"type":"Point"}
}