{
  "type": "Feature",
  "properties": {
    "addr:full":"6541 Grand Ave Maspeth NY 11378",
    "addr:housenumber":"6541",
    "addr:postcode":"11378",
    "addr:street":"Grand Ave",
    "iso:country":"US",
    "sg:address":"6541 Grand Ave",
    "sg:city":"Maspeth",
    "sg:classifiers":[
        {
            "category":"Restaurant",
            "type":"Food & Drink"
        }
    ],
    "sg:menulink":"http://www.allmenus.com/ny/queens/116446-asia-chinese-restaurant/menu/",
    "sg:phone":"+1 718 386 9688",
    "sg:postcode":"11378",
    "sg:province":"NY",
    "sg:tags":[
        "asian",
        "chinese"
    ],
    "wof:name":"Asia Chinese Restaurant",
    "wof:placetype":"venue"
},
  "geometry": {"coordinates":[-73.899444,40.723769],"type":"Point"}
}