{
  "type": "Feature",
  "properties": {
    "addr:full":"3436 Broadway New York NY 10031",
    "addr:housenumber":"3436",
    "addr:postcode":"10031",
    "addr:street":"Broadway",
    "iso:country":"US",
    "sg:address":"3436 Broadway",
    "sg:city":"New York",
    "sg:classifiers":[
        {
            "category":"Personal",
            "subcategory":"Beauty Salon",
            "type":"Services"
        }
    ],
    "sg:phone":"+1   ",
    "sg:postcode":"10031",
    "sg:province":"NY",
    "sg:tags":[
        "shop"
    ],
    "wof:name":"Juan Unisex Beauty Salon",
    "wof:placetype":"venue"
},
  "geometry": {"coordinates":[-73.952972,40.822731],"type":"Point"}
}