{
  "type": "Feature",
  "properties": {
    "addr:full":"1656 Central Ave Albany NY 12205",
    "addr:housenumber":"1656",
    "addr:postcode":"12205",
    "addr:street":"Central Ave",
    "iso:country":"US",
    "sg:address":"1656 Central Ave",
    "sg:city":"Albany",
    "sg:classifiers":[
        {
            "category":"Manufacturing",
            "subcategory":"Tools & Machinery",
            "type":"Manufacturing & Wholesale Goods"
        },
        {
            "category":"Wholesale",
            "subcategory":"Electrical",
            "type":"Manufacturing & Wholesale Goods"
        }
    ],
    "sg:phone":"+1 518 869 2283",
    "sg:postcode":"12205",
    "sg:province":"NY",
    "sg:tags":[
        "appliance"
    ],
    "wof:name":"Jacobys Appliance Parts",
    "wof:placetype":"venue"
},
  "geometry": {"coordinates":[-73.837053,42.721083],"type":"Point"}
}