{
  "type": "Feature",
  "properties": {
    "addr:full":"4713 Church Rd Pierrepont Manor NY 13674",
    "addr:housenumber":"4713",
    "addr:postcode":"13674",
    "addr:street":"Church Rd",
    "iso:country":"US",
    "sg:address":"4713 Church Rd",
    "sg:city":"Pierrepont Manor",
    "sg:classifiers":[
        {
            "category":"Government",
            "subcategory":"Post Office",
            "type":"Public Place"
        }
    ],
    "sg:phone":"+1 315 465 6995",
    "sg:postcode":"13674",
    "sg:province":"NY",
    "wof:name":"US Post Office",
    "wof:placetype":"venue"
},
  "geometry": {"coordinates":[-76.058875,43.735475],"type":"Point"}
}