{
  "type": "Feature",
  "properties": {
    "iso:country":"US",
    "sg:address":"4 Glatter Ln",
    "sg:city":"South Setauket",
    "sg:classifiers":[
        {
            "category":"Professional",
            "type":"Services"
        }
    ],
    "sg:phone":"+1 631 585 0290",
    "sg:postcode":"11720",
    "sg:province":"NY",
    "sg:tags":[
        "establishment"
    ],
    "wof:name":"Disability Resources Inc",
    "wof:placetype":"venue"
},
  "geometry": {"coordinates":[-73.08565900000001,40.886408],"type":"Point"}
}