{
  "type": "Feature",
  "properties": {
    "addr:full":"90 Meyer Rd Buffalo NY 14226",
    "addr:housenumber":"90",
    "addr:postcode":"14226",
    "addr:street":"Meyer Rd",
    "iso:country":"US",
    "sg:address":"90 Meyer Rd",
    "sg:city":"Buffalo",
    "sg:classifiers":[
        {
            "category":"Professional",
            "subcategory":"Lawyer & Legal Services",
            "type":"Services"
        }
    ],
    "sg:phone":"+1   ",
    "sg:postcode":"14226",
    "sg:province":"NY",
    "wof:name":"Nathan Ostroff",
    "wof:placetype":"venue"
},
  "geometry": {"coordinates":[-78.82190799999999,42.992703],"type":"Point"}
}