{
  "type": "Feature",
  "properties": {
    "addr:full":"101 Davis St Falconer NY 14733",
    "addr:housenumber":"101",
    "addr:postcode":"14733",
    "addr:street":"Davis St",
    "iso:country":"US",
    "sg:address":"101 Davis St",
    "sg:city":"Falconer",
    "sg:classifiers":[
        {
            "category":"Government",
            "subcategory":"Fire Station",
            "type":"Public Place"
        }
    ],
    "sg:phone":"+1 716 665 2523",
    "sg:postcode":"14733",
    "sg:province":"NY",
    "sg:tags":[
        "department"
    ],
    "wof:name":"Exempt Volunteer Firemens Assn",
    "wof:placetype":"venue"
},
  "geometry": {"coordinates":[-79.198387,42.11731],"type":"Point"}
}