{
  "type": "Feature",
  "properties": {
    "iso:country":"US",
    "sg:address":"9146 Oswego Rd",
    "sg:city":"Baldwinsville",
    "sg:classifiers":[
        {
            "category":"Autos & Motor Vehicles",
            "subcategory":"Automobile Sales",
            "type":"Retail Goods"
        }
    ],
    "sg:phone":"+1   ",
    "sg:postcode":"13027",
    "sg:province":"NY",
    "sg:tags":[
        "used"
    ],
    "wof:name":"Newcombes Auto Sales",
    "wof:placetype":"venue"
},
  "geometry": {"coordinates":[-76.35987799999999,43.215834],"type":"Point"}
}