{
  "type": "Feature",
  "properties": {
    "addr:full":"174 W 72 St New York NY 10023",
    "addr:housenumber":"174",
    "addr:postcode":"10023",
    "addr:street":"W 72 St",
    "iso:country":"US",
    "sg:address":"174 W 72 St",
    "sg:city":"New York",
    "sg:classifiers":[
        {
            "category":"Restaurant",
            "type":"Food & Drink"
        }
    ],
    "sg:phone":"+1   ",
    "sg:postcode":"10023",
    "sg:province":"NY",
    "sg:tags":[
        "eating"
    ],
    "wof:name":"Pd OHurleys Bar & Grill",
    "wof:placetype":"venue"
},
  "geometry": {"coordinates":[-73.98004400000001,40.777637],"type":"Point"}
}