{
  "type": "Feature",
  "properties": {
    "addr:full":"8261 Main St Williamsville NY 14221",
    "addr:housenumber":"8261",
    "addr:postcode":"14221",
    "addr:street":"Main St",
    "iso:country":"US",
    "sg:address":"8261 Main St",
    "sg:city":"Williamsville",
    "sg:classifiers":[
        {
            "category":"Professional",
            "type":"Services"
        }
    ],
    "sg:phone":"+1 716 634 1280",
    "sg:postcode":"14221",
    "sg:province":"NY",
    "sg:tags":[
        "establishment"
    ],
    "wof:name":"De Maio Della",
    "wof:placetype":"venue"
},
  "geometry": {"coordinates":[-78.68356,42.964917],"type":"Point"}
}