{
  "type": "Feature",
  "properties": {
    "addr:full":"1386 Coney Island Ave Brooklyn NY 11230",
    "addr:housenumber":"1386",
    "addr:postcode":"11230",
    "addr:street":"Coney Island Ave",
    "iso:country":"US",
    "sg:address":"1386 Coney Island Ave",
    "sg:city":"Brooklyn",
    "sg:classifiers":[
        {
            "category":"Professional",
            "subcategory":"Lawyer & Legal Services",
            "type":"Services"
        }
    ],
    "sg:phone":"+1 718 377 7800",
    "sg:postcode":"11230",
    "sg:province":"NY",
    "wof:name":"Feinzeig Jacob S Atty",
    "wof:placetype":"venue"
},
  "geometry": {"coordinates":[-73.965103,40.623699],"type":"Point"}
}