{
  "type": "Feature",
  "properties": {
    "iso:country":"US",
    "sg:address":"43 Elm St",
    "sg:city":"Hoosick Falls",
    "sg:classifiers":[
        {
            "category":"Retail",
            "subcategory":"Repair Shop",
            "type":"Services"
        }
    ],
    "sg:phone":"+1 518 686 5884",
    "sg:postcode":"12090",
    "sg:province":"NY",
    "sg:tags":[
        "upholsterer"
    ],
    "wof:name":"Odell & Sons Upholstery Co",
    "wof:placetype":"venue"
},
  "geometry": {"coordinates":[-73.352717,42.899543],"type":"Point"}
}