{
  "type": "Feature",
  "properties": {
    "addr:full":"216 6th Ave Apt 2D Brooklyn NY 11215",
    "addr:housenumber":"216",
    "addr:postcode":"11215",
    "addr:street":"6Th Ave Apt 2D",
    "iso:country":"US",
    "sg:address":"216 6th Ave Apt 2D",
    "sg:city":"Brooklyn",
    "sg:classifiers":[
        {
            "category":"Communications",
            "subcategory":"Film & Video Production",
            "type":"Services"
        }
    ],
    "sg:phone":"+1 718 789 9460",
    "sg:postcode":"11215",
    "sg:province":"NY",
    "sg:tags":[
        "dvd",
        "cassette",
        "duplicating",
        "cd"
    ],
    "sg:website":"http://www.donmilitello.com",
    "wof:name":"Video Profiles Of New York",
    "wof:placetype":"venue"
},
  "geometry": {"coordinates":[-73.978329,40.674908],"type":"Point"}
}