{
  "type": "Feature",
  "properties": {
    "addr:full":"109 York Ave Staten Island NY 10301",
    "addr:housenumber":"109",
    "addr:postcode":"10301",
    "addr:street":"York Ave",
    "iso:country":"US",
    "sg:address":"109 York Ave",
    "sg:city":"Staten Island",
    "sg:classifiers":[
        {
            "category":"Organizations",
            "subcategory":"Religious Organization",
            "type":"Services"
        }
    ],
    "sg:phone":"+1 718 447 3937",
    "sg:postcode":"10301",
    "sg:province":"NY",
    "sg:tags":[
        "church"
    ],
    "sg:website":"www.stkostka.org",
    "wof:name":"Saint Stanislaus Kostka Church",
    "wof:placetype":"venue"
},
  "geometry": {"coordinates":[-74.087575,40.642525],"type":"Point"}
}