{
  "type": "Feature",
  "properties": {
    "addr:full":"31 Underhill Rd Hillsdale NY 12529",
    "addr:housenumber":"31",
    "addr:postcode":"12529",
    "addr:street":"Underhill Rd",
    "iso:country":"US",
    "sg:address":"31 Underhill Rd",
    "sg:city":"Hillsdale",
    "sg:classifiers":[
        {
            "category":"Building & Trades",
            "subcategory":"Landscaping Services",
            "type":"Services"
        }
    ],
    "sg:phone":"+1 518 325 4725",
    "sg:postcode":"12529",
    "sg:province":"NY",
    "sg:tags":[
        "landscape",
        "contractor"
    ],
    "wof:name":"Underhill Lawn & Landscaping",
    "wof:placetype":"venue"
},
  "geometry": {"coordinates":[-73.520234,42.173136],"type":"Point"}
}