{
  "type": "Feature",
  "properties": {
    "addr:full":"4 Fleetwood Ct Great Neck NY 11024",
    "addr:housenumber":"4",
    "addr:postcode":"11024",
    "addr:street":"Fleetwood Ct",
    "iso:country":"US",
    "sg:address":"4 Fleetwood Ct",
    "sg:city":"Great Neck",
    "sg:classifiers":[
        {
            "category":"Professional",
            "subcategory":"Business Services",
            "type":"Services"
        }
    ],
    "sg:phone":"+1   ",
    "sg:postcode":"11024",
    "sg:province":"NY",
    "sg:tags":[
        "agent"
    ],
    "wof:name":"Team Invizage  Corp",
    "wof:placetype":"venue"
},
  "geometry": {"coordinates":[-73.737517,40.814081],"type":"Point"}
}