{
  "type": "Feature",
  "properties": {
    "iso:country":"US",
    "sg:address":"264 Cobb St",
    "sg:city":"Groton",
    "sg:classifiers":[
        {
            "category":"Wholesale",
            "subcategory":"Machinery & Supplies",
            "type":"Manufacturing & Wholesale Goods"
        }
    ],
    "sg:phone":"+1 607 898 4825",
    "sg:postcode":"13073",
    "sg:province":"NY",
    "sg:tags":[
        "farm"
    ],
    "wof:name":"Benson Farm Equipment Inc",
    "wof:placetype":"venue"
},
  "geometry": {"coordinates":[-76.443293,42.561317],"type":"Point"}
}