{
  "type": "Feature",
  "properties": {
    "addr:full":"10 W 10 St New York NY 10011",
    "addr:housenumber":"10",
    "addr:postcode":"10011",
    "addr:street":"W 10 St",
    "iso:country":"US",
    "sg:address":"10 W 10 St",
    "sg:city":"New York",
    "sg:classifiers":[
        {
            "category":"Professional",
            "subcategory":"Computer Services",
            "type":"Services"
        }
    ],
    "sg:phone":"+1 212 260 0894",
    "sg:postcode":"10011",
    "sg:province":"NY",
    "sg:tags":[
        "consultant",
        "designer"
    ],
    "sg:website":"www.nystar.com",
    "wof:name":"NYSTAR.COM",
    "wof:placetype":"venue"
},
  "geometry": {"coordinates":[-73.998547,40.734606],"type":"Point"}
}