{
  "type": "Feature",
  "properties": {
    "addr:full":"372 W Pulteney St Corning NY 14830",
    "addr:housenumber":"372",
    "addr:postcode":"14830",
    "addr:street":"W Pulteney St",
    "iso:country":"US",
    "sg:address":"372 W Pulteney St",
    "sg:city":"Corning",
    "sg:classifiers":[
        {
            "category":"Restaurant",
            "type":"Food & Drink"
        }
    ],
    "sg:phone":"+1 607 962 7497",
    "sg:postcode":"14830",
    "sg:province":"NY",
    "sg:tags":[
        "parlor",
        "ice",
        "cream"
    ],
    "sg:website":"www.friendlys.com",
    "wof:name":"Friendly's Ice Cream Shop",
    "wof:placetype":"venue"
},
  "geometry": {"coordinates":[-77.081739,42.155664],"type":"Point"}
}