{
  "type": "Feature",
  "properties": {
    "iso:country":"US",
    "sg:address":"3 Rieger Dr",
    "sg:city":"Monroe",
    "sg:classifiers":[
        {
            "category":"Real Estate",
            "subcategory":"Developer",
            "type":"Services"
        }
    ],
    "sg:phone":"+1 845 782 8333",
    "sg:postcode":"10950",
    "sg:province":"NY",
    "sg:tags":[
        "company",
        "holding"
    ],
    "wof:name":"Rieger Home",
    "wof:placetype":"venue"
},
  "geometry": {"coordinates":[-74.193971,41.351964],"type":"Point"}
}