{
  "type": "Feature",
  "properties": {
    "iso:country":"US",
    "sg:address":"136 Lawrence St",
    "sg:city":"Brooklyn",
    "sg:classifiers":[
        {
            "category":"Food & Beverages",
            "subcategory":"Groceries & Convenience Stores",
            "type":"Retail Goods"
        }
    ],
    "sg:phone":"+1 718 855 6551",
    "sg:postcode":"11201",
    "sg:province":"NY",
    "wof:name":"Lawrence Grocery & Vegetable",
    "wof:placetype":"venue"
},
  "geometry": {"coordinates":[-73.98652800000001,40.69204],"type":"Point"}
}