{
  "type": "Feature",
  "properties": {
    "iso:country":"US",
    "sg:address":"158 Medford Ave",
    "sg:city":"Patchogue",
    "sg:classifiers":[
        {
            "category":"Retail",
            "subcategory":"Auto Repair",
            "type":"Services"
        }
    ],
    "sg:phone":"+1   ",
    "sg:postcode":"11772",
    "sg:province":"NY",
    "sg:tags":[
        "glass"
    ],
    "wof:name":"Bens Glass Service Inc",
    "wof:placetype":"venue"
},
  "geometry": {"coordinates":[-73.007577,40.77195],"type":"Point"}
}