{
  "type": "Feature",
  "properties": {
    "addr:full":"100 Adams Blvd Farmingdale NY 11735",
    "addr:housenumber":"100",
    "addr:postcode":"11735",
    "addr:street":"Adams Blvd",
    "iso:country":"US",
    "sg:address":"100 Adams Blvd",
    "sg:city":"Farmingdale",
    "sg:classifiers":[
        {
            "category":"Wholesale",
            "subcategory":"Drugs",
            "type":"Manufacturing & Wholesale Goods"
        }
    ],
    "sg:phone":"+1 631 501 2020",
    "sg:postcode":"11735",
    "sg:province":"NY",
    "sg:tags":[
        "hair",
        "product",
        "beauty",
        "supply"
    ],
    "wof:name":"Belco Distributors",
    "wof:placetype":"venue"
},
  "geometry": {"coordinates":[-73.41324299999999,40.717287],"type":"Point"}
}