{
  "type": "Feature",
  "properties": {
    "addr:full":"4203 Hylan Blvd Staten Island NY 10308",
    "addr:housenumber":"4203",
    "addr:postcode":"10308",
    "addr:street":"Hylan Blvd",
    "iso:country":"US",
    "sg:address":"4203 Hylan Blvd",
    "sg:city":"Staten Island",
    "sg:classifiers":[
        {
            "category":"Travel",
            "subcategory":"Travel Agent",
            "type":"Entertainment"
        }
    ],
    "sg:phone":"+1   ",
    "sg:postcode":"10308",
    "sg:province":"NY",
    "sg:tags":[
        "agency"
    ],
    "wof:name":"Classic World Travel L M T",
    "wof:placetype":"venue"
},
  "geometry": {"coordinates":[-74.15051200000001,40.537374],"type":"Point"}
}