{
  "type": "Feature",
  "properties": {
    "addr:full":"14 E 63rd St Apt 1 New York NY 10065",
    "addr:housenumber":"14;1",
    "addr:postcode":"10065",
    "addr:street":"E 63Rd St Apt",
    "iso:country":"US",
    "sg:address":"14 E 63rd St Apt 1",
    "sg:city":"New York",
    "sg:classifiers":[
        {
            "category":"Building & Trades",
            "subcategory":"Construction",
            "type":"Services"
        }
    ],
    "sg:phone":"+1 212 980 9222",
    "sg:postcode":"10065",
    "sg:province":"NY",
    "sg:tags":[
        "interior",
        "design"
    ],
    "wof:name":"David Lawrence Studio LLC",
    "wof:placetype":"venue"
},
  "geometry": {"coordinates":[-73.970356,40.766263],"type":"Point"}
}