{
  "type": "Feature",
  "properties": {
    "iso:country":"US",
    "sg:address":"29 Hudson Ave",
    "sg:city":"Chatham",
    "sg:classifiers":[
        {
            "category":"Shopping",
            "subcategory":"Hobbies, Toys, & Games",
            "type":"Retail Goods"
        }
    ],
    "sg:phone":"+1 518 392 1033",
    "sg:postcode":"12037",
    "sg:province":"NY",
    "sg:tags":[
        "craft",
        "supply"
    ],
    "wof:name":"Scrappy Lynn's",
    "wof:placetype":"venue"
},
  "geometry": {"coordinates":[-73.598192,42.360513],"type":"Point"}
}