{
  "type": "Feature",
  "properties": {
    "addr:full":"108 Wooster St New York NY 10012",
    "addr:housenumber":"108",
    "addr:postcode":"10012",
    "addr:street":"Wooster St",
    "iso:country":"US",
    "sg:address":"108 Wooster St",
    "sg:city":"New York",
    "sg:classifiers":[
        {
            "category":"Shopping",
            "subcategory":"Clothing, Apparel, & Fashions",
            "type":"Retail Goods"
        }
    ],
    "sg:phone":"+1   ",
    "sg:postcode":"10012",
    "sg:province":"NY",
    "sg:tags":[
        "family"
    ],
    "wof:name":"Costume National America Inc",
    "wof:placetype":"venue"
},
  "geometry": {"coordinates":[-74.00035800000001,40.72484],"type":"Point"}
}