{
  "type": "Feature",
  "properties": {
    "addr:full":"1809 Watson Blvd Endicott NY 13760",
    "addr:housenumber":"1809",
    "addr:postcode":"13760",
    "addr:street":"Watson Blvd",
    "iso:country":"US",
    "sg:address":"1809 Watson Blvd",
    "sg:city":"Endicott",
    "sg:classifiers":[
        {
            "category":"Personal",
            "subcategory":"Beauty Salon",
            "type":"Services"
        }
    ],
    "sg:phone":"+1 607 785 4400",
    "sg:postcode":"13760",
    "sg:province":"NY",
    "wof:name":"Cuts 4 You",
    "wof:placetype":"venue"
},
  "geometry": {"coordinates":[-76.041735,42.109566],"type":"Point"}
}