{
  "type": "Feature",
  "properties": {
    "iso:country":"US",
    "sg:address":"1 Rockefeller Plz",
    "sg:city":"New York",
    "sg:classifiers":[
        {
            "category":"Wholesale",
            "subcategory":"Medical Equipment & Supplies",
            "type":"Manufacturing & Wholesale Goods"
        }
    ],
    "sg:phone":"+1 212 247 6667",
    "sg:postcode":"10020",
    "sg:province":"NY",
    "wof:name":"Medical World Inc",
    "wof:placetype":"venue"
},
  "geometry": {"coordinates":[-73.978911,40.758435],"type":"Point"}
}