{
  "type": "Feature",
  "properties": {
    "iso:country":"US",
    "sg:address":"26 Snedecor Ave",
    "sg:city":"Lindenhurst",
    "sg:classifiers":[
        {
            "category":"Professional",
            "type":"Services"
        }
    ],
    "sg:phone":"+1 631 888 7399",
    "sg:postcode":"11757",
    "sg:province":"NY",
    "sg:tags":[
        "establishment"
    ],
    "wof:name":"Coming Attractions",
    "wof:placetype":"venue"
},
  "geometry": {"coordinates":[-73.366012,40.680962],"type":"Point"}
}