{
  "type": "Feature",
  "properties": {
    "addr:full":"599 Lexington Ave New York NY 10022",
    "addr:housenumber":"599",
    "addr:postcode":"10022",
    "addr:street":"Lexington Ave",
    "iso:country":"US",
    "sg:address":"599 Lexington Ave",
    "sg:city":"New York",
    "sg:classifiers":[
        {
            "category":"Restaurant",
            "type":"Food & Drink"
        }
    ],
    "sg:postcode":"10022",
    "sg:province":"NY",
    "wof:name":"Toasties",
    "wof:placetype":"venue"
},
  "geometry": {"coordinates":[-73.970744,40.757868],"type":"Point"}
}