{
  "type": "Feature",
  "properties": {
    "iso:country":"US",
    "sg:address":"1355 Niagara Falls Blvd",
    "sg:city":"Buffalo",
    "sg:classifiers":[
        {
            "category":"Autos & Motor Vehicles",
            "subcategory":"Fuel & Gas Station",
            "type":"Retail Goods"
        },
        {
            "category":"Retail",
            "subcategory":"Car Wash",
            "type":"Services"
        }
    ],
    "sg:phone":"+1 716 834 0897",
    "sg:postcode":"14226",
    "sg:province":"NY",
    "wof:name":"Delta Sonic Detail Shop",
    "wof:placetype":"venue"
},
  "geometry": {"coordinates":[-78.82244799999999,42.991035],"type":"Point"}
}