{
  "type": "Feature",
  "properties": {
    "iso:country":"US",
    "sg:address":"270 Lake St",
    "sg:city":"Penn Yan",
    "sg:classifiers":[
        {
            "category":"Restaurant",
            "type":"Food & Drink"
        }
    ],
    "sg:phone":"+1 315 536 7019",
    "sg:postcode":"14527",
    "sg:province":"NY",
    "wof:name":"Rock Garden Restaurant",
    "wof:placetype":"venue"
},
  "geometry": {"coordinates":[-77.060351,42.652165],"type":"Point"}
}