{
  "type": "Feature",
  "properties": {
    "addr:full":"2280 Marks Rd Clymer NY 14724",
    "addr:housenumber":"2280",
    "addr:postcode":"14724",
    "addr:street":"Marks Rd",
    "iso:country":"US",
    "sg:address":"2280 Marks Rd",
    "sg:city":"Clymer",
    "sg:classifiers":[
        {
            "category":"Farming",
            "subcategory":"Dairy Farm",
            "type":"Manufacturing & Wholesale Goods"
        }
    ],
    "sg:phone":"+1 716 761 6842",
    "sg:postcode":"14724",
    "sg:province":"NY",
    "wof:name":"Tenpas Pastor Farms",
    "wof:placetype":"venue"
},
  "geometry": {"coordinates":[-79.658778,42.116606],"type":"Point"}
}