{
  "type": "Feature",
  "properties": {
    "addr:full":"1066 Shoemaker Rd Webster NY 14580",
    "addr:housenumber":"1066",
    "addr:postcode":"14580",
    "addr:street":"Shoemaker Rd",
    "iso:country":"US",
    "sg:address":"1066 Shoemaker Rd",
    "sg:city":"Webster",
    "sg:classifiers":[
        {
            "category":"Shopping",
            "type":"Retail Goods"
        }
    ],
    "sg:phone":"+1   ",
    "sg:postcode":"14580",
    "sg:province":"NY",
    "sg:tags":[
        "merchandise"
    ],
    "wof:name":"Lake Fx",
    "wof:placetype":"venue"
},
  "geometry": {"coordinates":[-77.451346,43.238753],"type":"Point"}
}