{
  "type": "Feature",
  "properties": {
    "addr:full":"315 E 86 St New York NY 10028",
    "addr:housenumber":"315;86",
    "addr:postcode":"10028",
    "addr:street":"E;St",
    "iso:country":"US",
    "sg:address":"315 E 86 St",
    "sg:city":"New York",
    "sg:classifiers":[
        {
            "category":"Professional",
            "type":"Services"
        }
    ],
    "sg:phone":"+1   ",
    "sg:postcode":"10028",
    "sg:province":"NY",
    "wof:name":"Infiniti Gem Corp",
    "wof:placetype":"venue"
},
  "geometry": {"coordinates":[-73.94959299999999,40.777084],"type":"Point"}
}