{
  "type": "Feature",
  "properties": {
    "addr:full":"340 Campbell Hill Rd Owego NY 13827",
    "addr:housenumber":"340",
    "addr:postcode":"13827",
    "addr:street":"Campbell Hill Rd",
    "iso:country":"US",
    "sg:address":"340 Campbell Hill Rd",
    "sg:city":"Owego",
    "sg:classifiers":[
        {
            "category":"Shopping",
            "subcategory":"Computers & Home Electronics",
            "type":"Retail Goods"
        }
    ],
    "sg:phone":"+1   ",
    "sg:postcode":"13827",
    "sg:province":"NY",
    "wof:name":"J & K Systems",
    "wof:placetype":"venue"
},
  "geometry": {"coordinates":[-76.322053,42.147697],"type":"Point"}
}