{
  "type": "Feature",
  "properties": {
    "iso:country":"US",
    "sg:address":"235 Brook Ave",
    "sg:city":"Bronx",
    "sg:classifiers":[
        {
            "category":"Insurance",
            "subcategory":"Insurance Agent",
            "type":"Services"
        }
    ],
    "sg:phone":"+1 718 585 9060",
    "sg:postcode":"10454",
    "sg:province":"NY",
    "wof:name":"Cardoza Business Svces",
    "wof:placetype":"venue"
},
  "geometry": {"coordinates":[-73.918887,40.808259],"type":"Point"}
}