{
  "type": "Feature",
  "properties": {
    "addr:full":"6025 Broadway Bronx NY 10471",
    "addr:housenumber":"6025",
    "addr:postcode":"10471",
    "addr:street":"Broadway",
    "iso:country":"US",
    "sg:address":"6025 Broadway",
    "sg:city":"Bronx",
    "sg:classifiers":[
        {
            "category":"Retail",
            "subcategory":"Repair Shop",
            "type":"Services"
        }
    ],
    "sg:phone":"+1 347 332 2946",
    "sg:postcode":"10471",
    "sg:province":"NY",
    "sg:tags":[
        "lock",
        "locksmith"
    ],
    "wof:name":"USA Locksmiths",
    "wof:placetype":"venue"
},
  "geometry": {"coordinates":[-73.89789399999999,40.890608],"type":"Point"}
}