{
  "type": "Feature",
  "properties": {
    "iso:country":"US",
    "sg:address":"212 Merrick Rd",
    "sg:city":"Rockville Centre",
    "sg:classifiers":[
        {
            "category":"Shopping",
            "subcategory":"Antiques",
            "type":"Retail Goods"
        },
        {
            "category":"Home & Garden",
            "subcategory":"Furniture",
            "type":"Retail Goods"
        }
    ],
    "sg:phone":"+1 516 763 0190",
    "sg:postcode":"11570",
    "sg:province":"NY",
    "sg:tags":[
        "store"
    ],
    "sg:website":"www.europinefurniture.com",
    "wof:name":"Euro Pine Collection International Inc",
    "wof:placetype":"venue"
},
  "geometry": {"coordinates":[-73.64679700000001,40.6563],"type":"Point"}
}