{
  "type": "Feature",
  "properties": {
    "addr:full":"1270 Broadway Ste 703 Manhattan NY 10001",
    "addr:housenumber":"1270",
    "addr:postcode":"10001",
    "addr:street":"Broadway Ste 703",
    "iso:country":"US",
    "sg:address":"1270 Broadway Ste 703",
    "sg:city":"Manhattan",
    "sg:classifiers":[
        {
            "category":"Community Center",
            "subcategory":"Social",
            "type":"Public Place"
        }
    ],
    "sg:phone":"+1 212 465 8391",
    "sg:postcode":"10001",
    "sg:province":"NY",
    "sg:tags":[
        "club"
    ],
    "sg:website":"www.asianlife.com",
    "wof:name":"AsianLife",
    "wof:placetype":"venue"
},
  "geometry": {"coordinates":[-73.987787,40.748693],"type":"Point"}
}