{
  "type": "Feature",
  "properties": {
    "addr:full":"16 Brienna Ct Staten Island NY 10309",
    "addr:housenumber":"16",
    "addr:postcode":"10309",
    "addr:street":"Brienna Ct",
    "iso:country":"US",
    "sg:address":"16 Brienna Ct",
    "sg:city":"Staten Island",
    "sg:classifiers":[
        {
            "category":"Food & Beverages",
            "subcategory":"Liquor & Beverages",
            "type":"Retail Goods"
        }
    ],
    "sg:phone":"+1 718 356 1810",
    "sg:postcode":"10309",
    "sg:province":"NY",
    "sg:tags":[
        "beer",
        "spirit",
        "wine"
    ],
    "wof:name":"Giant Beverage Co Inc",
    "wof:placetype":"venue"
},
  "geometry": {"coordinates":[-74.23849300000001,40.538369],"type":"Point"}
}