{
  "type": "Feature",
  "properties": {
    "iso:country":"US",
    "sg:address":"7 W 45th St",
    "sg:city":"New York",
    "sg:classifiers":[
        {
            "category":"Restaurant",
            "type":"Food & Drink"
        }
    ],
    "sg:phone":"+1 212 719 1788",
    "sg:postcode":"10036",
    "sg:province":"NY",
    "sg:tags":[
        "chinese"
    ],
    "wof:name":"Sun Yip",
    "wof:placetype":"venue"
},
  "geometry": {"coordinates":[-73.979668,40.755479],"type":"Point"}
}