{
  "type": "Feature",
  "properties": {
    "addr:full":"60 Oceana Dr W Brooklyn NY 11235",
    "addr:housenumber":"60",
    "addr:postcode":"11235",
    "addr:street":"Oceana Dr W",
    "iso:country":"US",
    "sg:address":"60 Oceana Dr W",
    "sg:city":"Brooklyn",
    "sg:classifiers":[
        {
            "category":"Building & Trades",
            "subcategory":"Construction",
            "type":"Services"
        }
    ],
    "sg:phone":"+1 718 332 4210",
    "sg:postcode":"11235",
    "sg:province":"NY",
    "sg:tags":[
        "development",
        "real estate"
    ],
    "wof:name":"Dover Development Inc",
    "wof:placetype":"venue"
},
  "geometry": {"coordinates":[-73.959524,40.576527],"type":"Point"}
}