{
  "type": "Feature",
  "properties": {
    "iso:country":"US",
    "sg:address":"585 Main St",
    "sg:city":"Poughkeepsie",
    "sg:classifiers":[
        {
            "category":"Autos & Motor Vehicles",
            "subcategory":"Automobile Sales",
            "type":"Retail Goods"
        }
    ],
    "sg:phone":"+1   ",
    "sg:postcode":"12601",
    "sg:province":"NY",
    "sg:tags":[
        "repair",
        "used",
        "general"
    ],
    "wof:name":"Sabia Auto Exchange",
    "wof:placetype":"venue"
},
  "geometry": {"coordinates":[-73.913282,41.698877],"type":"Point"}
}