{
  "type": "Feature",
  "properties": {
    "addr:full":"5314 16th Avenue Brooklyn NY 11204",
    "addr:housenumber":"5314",
    "addr:postcode":"11204",
    "addr:street":"16Th Avenue",
    "iso:country":"US",
    "sg:address":"5314 16th Avenue",
    "sg:city":"Brooklyn",
    "sg:classifiers":[
        {
            "category":"Real Estate",
            "subcategory":"Real Estate Services",
            "type":"Services"
        }
    ],
    "sg:phone":"+1 718 435 0808",
    "sg:postcode":"11204",
    "sg:province":"NY",
    "wof:name":"Select Land Services",
    "wof:placetype":"venue"
},
  "geometry": {"coordinates":[-73.987906,40.628726],"type":"Point"}
}