{
  "type": "Feature",
  "properties": {
    "iso:country":"US",
    "sg:address":"1339 Bay Ridge Ave",
    "sg:city":"Brooklyn",
    "sg:classifiers":[
        {
            "category":"Local Transit",
            "type":"Transportation"
        }
    ],
    "sg:phone":"+1   ",
    "sg:postcode":"11219",
    "sg:province":"NY",
    "sg:tags":[
        "bus"
    ],
    "wof:name":"Dream Lines Express Ltd",
    "wof:placetype":"venue"
},
  "geometry": {"coordinates":[-74.00229400000001,40.622946],"type":"Point"}
}