{
  "type": "Feature",
  "properties": {
    "iso:country":"US",
    "sg:address":"632 Middle Country Rd",
    "sg:city":"Selden",
    "sg:classifiers":[
        {
            "category":"Personal",
            "subcategory":"Nail Salon",
            "type":"Services"
        }
    ],
    "sg:phone":"+1 631 696 2300",
    "sg:postcode":"11784",
    "sg:province":"NY",
    "wof:name":"Aroma Nail Foot Spa",
    "wof:placetype":"venue"
},
  "geometry": {"coordinates":[-73.0382,40.866199],"type":"Point"}
}