{
  "type": "Feature",
  "properties": {
    "addr:full":"11907 Rockaway Boulevard South Ozone Park NY 11420",
    "addr:housenumber":"11907",
    "addr:postcode":"11420",
    "addr:street":"Rockaway Boulevard",
    "iso:country":"US",
    "sg:address":"11907 Rockaway Boulevard",
    "sg:city":"South Ozone Park",
    "sg:classifiers":[
        {
            "category":"Education",
            "subcategory":"School",
            "type":"Public Place"
        }
    ],
    "sg:phone":"+1 718 659 2600",
    "sg:postcode":"11420",
    "sg:province":"NY",
    "wof:name":"Rich Knowledge",
    "wof:placetype":"venue"
},
  "geometry": {"coordinates":[-73.81884100000001,40.676226],"type":"Point"}
}