{
  "type": "Feature",
  "properties": {
    "addr:full":"76 Main St Westhampton Bch NY 11978",
    "addr:housenumber":"76",
    "addr:postcode":"11978",
    "addr:street":"Main St",
    "iso:country":"US",
    "sg:address":"76 Main St",
    "sg:city":"Westhampton Bch",
    "sg:classifiers":[
        {
            "category":"Professional",
            "type":"Services"
        }
    ],
    "sg:phone":"+1 631 288 1500",
    "sg:postcode":"11978",
    "sg:province":"NY",
    "sg:tags":[
        "establishment"
    ],
    "wof:name":"Westhampton Beach Performing",
    "wof:placetype":"venue"
},
  "geometry": {"coordinates":[-72.644661,40.809273],"type":"Point"}
}