{
  "type": "Feature",
  "properties": {
    "iso:country":"US",
    "sg:address":"900 Broadway",
    "sg:city":"New York",
    "sg:classifiers":[
        {
            "category":"Building & Trades",
            "subcategory":"Construction",
            "type":"Services"
        }
    ],
    "sg:phone":"+1 212 529 4550",
    "sg:postcode":"10003",
    "sg:province":"NY",
    "sg:tags":[
        "house"
    ],
    "wof:name":"Vertigo Design Inc",
    "wof:placetype":"venue"
},
  "geometry": {"coordinates":[-73.989952,40.738488],"type":"Point"}
}