{
  "type": "Feature",
  "properties": {
    "addr:full":"33 Lewis Rd Akron NY 14001",
    "addr:housenumber":"33",
    "addr:postcode":"14001",
    "addr:street":"Lewis Rd",
    "iso:country":"US",
    "sg:address":"33 Lewis Rd",
    "sg:city":"Akron",
    "sg:classifiers":[
        {
            "category":"Utilities",
            "subcategory":"Refuse",
            "type":"Services"
        }
    ],
    "sg:phone":"+1   ",
    "sg:postcode":"14001",
    "sg:province":"NY",
    "sg:tags":[
        "executive",
        "system"
    ],
    "wof:name":"Sewer Treatment Plant",
    "wof:placetype":"venue"
},
  "geometry": {"coordinates":[-78.50660000000001,43.028083],"type":"Point"}
}