{
  "type": "Feature",
  "properties": {
    "iso:country":"US",
    "sg:address":"24 Woodwaye Rd",
    "sg:city":"Plainview",
    "sg:classifiers":[
        {
            "category":"Manufacturing",
            "subcategory":"Tools & Machinery",
            "type":"Manufacturing & Wholesale Goods"
        }
    ],
    "sg:phone":"+1   ",
    "sg:postcode":"11803",
    "sg:province":"NY",
    "sg:tags":[
        "x",
        "mfg"
    ],
    "wof:name":"SIS",
    "wof:placetype":"venue"
},
  "geometry": {"coordinates":[-73.499605,40.782286],"type":"Point"}
}