{
  "type": "Feature",
  "properties": {
    "addr:full":"10 Squiretown Rd Hampton Bays NY 11946",
    "addr:housenumber":"10",
    "addr:postcode":"11946",
    "addr:street":"Squiretown Rd",
    "iso:country":"US",
    "sg:address":"10 Squiretown Rd",
    "sg:city":"Hampton Bays",
    "sg:classifiers":[
        {
            "category":"Real Estate",
            "subcategory":"Real Estate Operator",
            "type":"Services"
        }
    ],
    "sg:phone":"+1 631 728 2413",
    "sg:postcode":"11946",
    "sg:province":"NY",
    "sg:tags":[
        "apartment"
    ],
    "wof:name":"Ryan Bishop Village",
    "wof:placetype":"venue"
},
  "geometry": {"coordinates":[-72.52388500000001,40.879346],"type":"Point"}
}