{
  "type": "Feature",
  "properties": {
    "addr:full":"2857 Niagara St Buffalo NY 14207",
    "addr:housenumber":"2857",
    "addr:postcode":"14207",
    "addr:street":"Niagara St",
    "iso:country":"US",
    "sg:address":"2857 Niagara St",
    "sg:city":"Buffalo",
    "sg:classifiers":[
        {
            "category":"Retail",
            "subcategory":"Auto Repair",
            "type":"Services"
        }
    ],
    "sg:phone":"+1 716 877 1350",
    "sg:postcode":"14207",
    "sg:province":"NY",
    "sg:tags":[
        "repairing",
        "automobile"
    ],
    "wof:name":"Riverview Garage Inc",
    "wof:placetype":"venue"
},
  "geometry": {"coordinates":[-78.914001,42.957699],"type":"Point"}
}