{
  "type": "Feature",
  "properties": {
    "addr:full":"8 Melwood Dr Commack NY 11725",
    "addr:housenumber":"8",
    "addr:postcode":"11725",
    "addr:street":"Melwood Dr",
    "iso:country":"US",
    "sg:address":"8 Melwood Dr",
    "sg:city":"Commack",
    "sg:classifiers":[
        {
            "category":"Professional",
            "subcategory":"Computer Services",
            "type":"Services"
        }
    ],
    "sg:phone":"+1   ",
    "sg:postcode":"11725",
    "sg:province":"NY",
    "sg:tags":[
        "programing",
        "custom"
    ],
    "wof:name":"Futuristic Info Systems Inc",
    "wof:placetype":"venue"
},
  "geometry": {"coordinates":[-73.277244,40.80735],"type":"Point"}
}