{
  "type": "Feature",
  "properties": {
    "iso:country":"US",
    "sg:address":"200 High St",
    "sg:city":"Canastota",
    "sg:classifiers":[
        {
            "category":"Education",
            "subcategory":"School",
            "type":"Public Place"
        }
    ],
    "sg:phone":"+1 315 697 6372",
    "sg:postcode":"13032",
    "sg:province":"NY",
    "wof:name":"South Side Elementary School",
    "wof:placetype":"venue"
},
  "geometry": {"coordinates":[-75.749809,43.074646],"type":"Point"}
}