{
  "type": "Feature",
  "properties": {
    "addr:full":"300 Chestnut St Liberty NY 12754",
    "addr:housenumber":"300",
    "addr:postcode":"12754",
    "addr:street":"Chestnut St",
    "iso:country":"US",
    "sg:address":"300 Chestnut St",
    "sg:city":"Liberty",
    "sg:classifiers":[
        {
            "category":"Shopping",
            "subcategory":"Used Merchandise",
            "type":"Retail Goods"
        }
    ],
    "sg:phone":"+1 845 292 2270",
    "sg:postcode":"12754",
    "sg:province":"NY",
    "sg:tags":[
        "antique",
        "furniture"
    ],
    "wof:name":"Antique Palace Emporium Inc",
    "wof:placetype":"venue"
},
  "geometry": {"coordinates":[-74.757199,41.8006],"type":"Point"}
}