{
  "type": "Feature",
  "properties": {
    "iso:country":"US",
    "sg:address":"2920 Broadway",
    "sg:city":"New York",
    "sg:classifiers":[
        {
            "category":"Communications",
            "subcategory":"Radio Station",
            "type":"Services"
        }
    ],
    "sg:phone":"+1 212 854 9920",
    "sg:postcode":"10027",
    "sg:province":"NY",
    "sg:website":"www.columbia.edu/cu/wkcr/",
    "wof:name":"WKCR 89.9 FM",
    "wof:placetype":"venue"
},
  "geometry": {"coordinates":[-73.9645,40.806702],"type":"Point"}
}