{
  "type": "Feature",
  "properties": {
    "iso:country":"US",
    "sg:address":"970 Ferngate Dr",
    "sg:city":"Franklin Square",
    "sg:classifiers":[
        {
            "category":"Professional",
            "type":"Services"
        }
    ],
    "sg:phone":"+1   ",
    "sg:postcode":"11010",
    "sg:province":"NY",
    "wof:name":"Dennis R Binda Inc",
    "wof:placetype":"venue"
},
  "geometry": {"coordinates":[-73.67765,40.689532],"type":"Point"}
}