{
  "type": "Feature",
  "properties": {
    "iso:country":"US",
    "sg:address":"175 Maple Ave",
    "sg:city":"Westbury",
    "sg:classifiers":[
        {
            "category":"Personal",
            "type":"Services"
        }
    ],
    "sg:phone":"+1 516 279 3056",
    "sg:postcode":"11590",
    "sg:province":"NY",
    "sg:tags":[
        "mover"
    ],
    "wof:name":"CLINTON MOVERS",
    "wof:placetype":"venue"
},
  "geometry": {"coordinates":[-73.591436,40.755274],"type":"Point"}
}