{
  "type": "Feature",
  "properties": {
    "iso:country":"US",
    "sg:address":"444 Madison Ave",
    "sg:city":"New York",
    "sg:classifiers":[
        {
            "category":"Communications",
            "type":"Services"
        }
    ],
    "sg:phone":"+1 212 893 1320",
    "sg:postcode":"10022",
    "sg:province":"NY",
    "wof:name":"K III Communication Corp",
    "wof:placetype":"venue"
},
  "geometry": {"coordinates":[-73.975853,40.757537],"type":"Point"}
}