{
  "type": "Feature",
  "properties": {
    "addr:full":"1254 New Loudon Rd Cohoes NY 12047",
    "addr:housenumber":"1254",
    "addr:postcode":"12047",
    "addr:street":"New Loudon Rd",
    "iso:country":"US",
    "sg:address":"1254 New Loudon Rd",
    "sg:city":"Cohoes",
    "sg:classifiers":[
        {
            "category":"Shopping",
            "type":"Retail Goods"
        }
    ],
    "sg:phone":"+1 518 783 3474",
    "sg:postcode":"12047",
    "sg:province":"NY",
    "sg:tags":[
        "public",
        "aquarium"
    ],
    "sg:website":"www.eddiesaqua.com",
    "wof:name":"Eddie's Aquarium Ctr Inc",
    "wof:placetype":"venue"
},
  "geometry": {"coordinates":[-73.73339799999999,42.800977],"type":"Point"}
}