{
  "type": "Feature",
  "properties": {
    "iso:country":"US",
    "sg:address":"445 Metropolitan Ave",
    "sg:city":"Brooklyn",
    "sg:classifiers":[
        {
            "category":"Retail",
            "subcategory":"Auto Repair",
            "type":"Services"
        }
    ],
    "sg:phone":"+1 718 782 2881",
    "sg:postcode":"11211",
    "sg:province":"NY",
    "sg:tags":[
        "general"
    ],
    "wof:name":"Joes Corner Inc",
    "wof:placetype":"venue"
},
  "geometry": {"coordinates":[-73.954013,40.714146],"type":"Point"}
}