{
  "type": "Feature",
  "properties": {
    "addr:full":"2240 Western Ave Guilderland NY 12084",
    "addr:housenumber":"2240",
    "addr:postcode":"12084",
    "addr:street":"Western Ave",
    "iso:country":"US",
    "sg:address":"2240 Western Ave",
    "sg:city":"Guilderland",
    "sg:classifiers":[
        {
            "category":"Professional",
            "subcategory":"Management & Consulting",
            "type":"Services"
        }
    ],
    "sg:phone":"+1 518 464 1158",
    "sg:postcode":"12084",
    "sg:province":"NY",
    "sg:tags":[
        "consultant",
        "motel",
        "hotel"
    ],
    "wof:name":"Mariott Management",
    "wof:placetype":"venue"
},
  "geometry": {"coordinates":[-73.90530699999999,42.701553],"type":"Point"}
}