{
  "type": "Feature",
  "properties": {
    "addr:full":"400 W Morris St Bath NY 14810",
    "addr:housenumber":"400",
    "addr:postcode":"14810",
    "addr:street":"W Morris St",
    "iso:country":"US",
    "sg:address":"400 W Morris St",
    "sg:city":"Bath",
    "sg:classifiers":[
        {
            "category":"Shopping",
            "subcategory":"Pharmacy",
            "type":"Retail Goods"
        }
    ],
    "sg:phone":"+1   ",
    "sg:postcode":"14810",
    "sg:province":"NY",
    "sg:tags":[
        "photofinishing",
        "laboratory"
    ],
    "wof:name":"Eckerd",
    "wof:placetype":"venue"
},
  "geometry": {"coordinates":[-77.33849499999999,42.343626],"type":"Point"}
}