{
  "type": "Feature",
  "properties": {
    "iso:country":"US",
    "sg:address":"49 S Main St",
    "sg:city":"Gloversville",
    "sg:classifiers":[
        {
            "category":"Professional",
            "subcategory":"Employment Agencies",
            "type":"Services"
        }
    ],
    "sg:phone":"+1 205 981 1141",
    "sg:postcode":"12078",
    "sg:province":"NY",
    "sg:tags":[
        "opportunity",
        "temporary",
        "contractor"
    ],
    "sg:website":"http://gloversvilleny.expresspros.com",
    "wof:name":"Express Employment Professionals",
    "wof:placetype":"venue"
},
  "geometry": {"coordinates":[-74.34662899999999,43.049161],"type":"Point"}
}