{
  "type": "Feature",
  "properties": {
    "addr:full":"8020 Flatlands Ave Brooklyn NY 11236",
    "addr:housenumber":"8020",
    "addr:postcode":"11236",
    "addr:street":"Flatlands Ave",
    "iso:country":"US",
    "sg:address":"8020 Flatlands Ave",
    "sg:city":"Brooklyn",
    "sg:classifiers":[
        {
            "category":"Banks & Credit Unions",
            "subcategory":"Bank",
            "type":"Services"
        }
    ],
    "sg:phone":"+1 718 531 7710",
    "sg:postcode":"11236",
    "sg:province":"NY",
    "sg:tags":[
        "commercial"
    ],
    "wof:name":"Banco Popular",
    "wof:placetype":"venue"
},
  "geometry": {"coordinates":[-73.912578,40.635846],"type":"Point"}
}