{
  "type": "Feature",
  "properties": {
    "addr:full":"2350 Cambreleng Ave Bronx NY 10458",
    "addr:housenumber":"2350",
    "addr:postcode":"10458",
    "addr:street":"Cambreleng Ave",
    "iso:country":"US",
    "sg:address":"2350 Cambreleng Ave",
    "sg:city":"Bronx",
    "sg:classifiers":[
        {
            "category":"Manufacturing",
            "subcategory":"Printing",
            "type":"Manufacturing & Wholesale Goods"
        }
    ],
    "sg:phone":"+1   ",
    "sg:postcode":"10458",
    "sg:province":"NY",
    "sg:tags":[
        "book"
    ],
    "wof:name":"Kurtis Publishing",
    "wof:placetype":"venue"
},
  "geometry": {"coordinates":[-73.885323,40.854417],"type":"Point"}
}