{
  "type": "Feature",
  "properties": {
    "iso:country":"US",
    "sg:address":"237 Madison Ave",
    "sg:city":"New York",
    "sg:classifiers":[
        {
            "category":"Restaurant",
            "type":"Food & Drink"
        }
    ],
    "sg:menulink":"http://www.allmenus.com/ny/new-york/247084-asia-de-cuba/menu/",
    "sg:phone":"+1 212 726 7755",
    "sg:postcode":"10016",
    "sg:province":"NY",
    "sg:tags":[
        "asian",
        "chinese"
    ],
    "wof:name":"Asia de Cuba",
    "wof:placetype":"venue"
},
  "geometry": {"coordinates":[-73.98112,40.749771],"type":"Point"}
}