{
  "type": "Feature",
  "properties": {
    "iso:country":"US",
    "sg:address":"25 Spring Forest Ave",
    "sg:city":"Binghamton",
    "sg:classifiers":[
        {
            "category":"Building & Trades",
            "subcategory":"Construction",
            "type":"Services"
        }
    ],
    "sg:phone":"+1 607 723 2877",
    "sg:postcode":"13905",
    "sg:province":"NY",
    "sg:tags":[
        "house"
    ],
    "wof:name":"Keefe Construction Inc",
    "wof:placetype":"venue"
},
  "geometry": {"coordinates":[-75.918018,42.109398],"type":"Point"}
}