{
  "type": "Feature",
  "properties": {
    "iso:country":"US",
    "sg:address":"1562 Dewey Ave",
    "sg:city":"Rochester",
    "sg:classifiers":[
        {
            "category":"Insurance",
            "subcategory":"Insurance Agent",
            "type":"Services"
        }
    ],
    "sg:phone":"+1 585 254 8373",
    "sg:postcode":"14615",
    "sg:province":"NY",
    "wof:name":"Dougherty/Fuino Agency",
    "wof:placetype":"venue"
},
  "geometry": {"coordinates":[-77.638774,43.19605],"type":"Point"}
}