{
  "type": "Feature",
  "properties": {
    "iso:country":"US",
    "sg:address":"21 New St",
    "sg:city":"Newburgh",
    "sg:classifiers":[
        {
            "category":"Professional",
            "subcategory":"Accounting & Tax Preparation",
            "type":"Services"
        }
    ],
    "sg:phone":"+1 845 562 1280",
    "sg:postcode":"12550",
    "sg:province":"NY",
    "sg:tags":[
        "return",
        "filing"
    ],
    "wof:name":"Robert V Gould",
    "wof:placetype":"venue"
},
  "geometry": {"coordinates":[-74.05844999999999,41.518495],"type":"Point"}
}