{
  "type": "Feature",
  "properties": {
    "iso:country":"US",
    "sg:address":"276 Woodland Ave",
    "sg:city":"Manorville",
    "sg:classifiers":[
        {
            "category":"Communications",
            "subcategory":"Radio Station",
            "type":"Services"
        }
    ],
    "sg:phone":"+1 631 874 3558",
    "sg:postcode":"11949",
    "sg:province":"NY",
    "sg:tags":[
        "company",
        "broadcasting"
    ],
    "wof:name":"Radio Amateur K2m C",
    "wof:placetype":"venue"
},
  "geometry": {"coordinates":[-72.834327,40.841139],"type":"Point"}
}