{
  "type": "Feature",
  "properties": {
    "iso:country":"US",
    "sg:address":"97 Old Rte 6",
    "sg:city":"Carmel",
    "sg:classifiers":[
        {
            "category":"Professional",
            "type":"Services"
        }
    ],
    "sg:phone":"+1 845 225 5295",
    "sg:postcode":"10512",
    "sg:province":"NY",
    "sg:tags":[
        "establishment"
    ],
    "wof:name":"Golden Apples",
    "wof:placetype":"venue"
},
  "geometry": {"coordinates":[-73.660605,41.412553],"type":"Point"}
}