{
  "type": "Feature",
  "properties": {
    "iso:country":"US",
    "sg:address":"116 Court St",
    "sg:city":"Brooklyn",
    "sg:classifiers":[
        {
            "category":"Food & Beverages",
            "subcategory":"Groceries & Convenience Stores",
            "type":"Retail Goods"
        }
    ],
    "sg:phone":"+1 718 222 0585",
    "sg:postcode":"11201",
    "sg:province":"NY",
    "wof:name":"Ibb Halal Meats",
    "wof:placetype":"venue"
},
  "geometry": {"coordinates":[-73.992302,40.690102],"type":"Point"}
}