{
  "type": "Feature",
  "properties": {
    "iso:country":"US",
    "sg:address":"288 N Plank Rd",
    "sg:city":"Newburgh",
    "sg:classifiers":[
        {
            "category":"Professional",
            "subcategory":"Lawyer & Legal Services",
            "type":"Services"
        }
    ],
    "sg:phone":"+1 800 610 4401",
    "sg:postcode":"12550",
    "sg:province":"NY",
    "sg:website":"www.denniskennylaw.com",
    "wof:name":"Dennis Kenny Attorney At Law P C",
    "wof:placetype":"venue"
},
  "geometry": {"coordinates":[-74.040604,41.538101],"type":"Point"}
}