{
  "type": "Feature",
  "properties": {
    "iso:country":"US",
    "sg:address":"250 Brookside Ave",
    "sg:city":"Amsterdam",
    "sg:classifiers":[
        {
            "category":"Government",
            "subcategory":"Office",
            "type":"Public Place"
        }
    ],
    "sg:phone":"+1 518 843 3253",
    "sg:postcode":"12010",
    "sg:province":"NY",
    "sg:tags":[
        "village"
    ],
    "wof:name":"Amsterdam Water Meter Dept",
    "wof:placetype":"venue"
},
  "geometry": {"coordinates":[-74.180038,42.951736],"type":"Point"}
}