{
  "type": "Feature",
  "properties": {
    "iso:country":"US",
    "sg:address":"5569 Legionnaire Dr",
    "sg:city":"Cicero",
    "sg:classifiers":[
        {
            "category":"Building & Trades",
            "subcategory":"Landscaping Services",
            "type":"Services"
        }
    ],
    "sg:phone":"+1 315 424 1821",
    "sg:postcode":"13039",
    "sg:province":"NY",
    "sg:tags":[
        "aged",
        "homes-institutional"
    ],
    "wof:name":"Cicero Commons Senior H D F Co",
    "wof:placetype":"venue"
},
  "geometry": {"coordinates":[-76.13240500000001,43.176682],"type":"Point"}
}