{
  "type": "Feature",
  "properties": {
    "iso:country":"US",
    "sg:address":"16 Richman Plz",
    "sg:city":"Bronx",
    "sg:classifiers":[
        {
            "category":"Real Estate",
            "subcategory":"Real Estate Services",
            "type":"Services"
        }
    ],
    "sg:phone":"+1 718 583 8760",
    "sg:postcode":"10453",
    "sg:province":"NY",
    "sg:tags":[
        "management",
        "property"
    ],
    "wof:name":"River Park Towers Managmnt Office",
    "wof:placetype":"venue"
},
  "geometry": {"coordinates":[-73.922516,40.851897],"type":"Point"}
}