{
  "type": "Feature",
  "properties": {
    "addr:full":"325 W Jericho Tpke Huntington NY 11743",
    "addr:housenumber":"325",
    "addr:postcode":"11743",
    "addr:street":"W Jericho Tpke",
    "iso:country":"US",
    "sg:address":"325 W Jericho Tpke",
    "sg:city":"Huntington",
    "sg:classifiers":[
        {
            "category":"Restaurant",
            "type":"Food & Drink"
        }
    ],
    "sg:menulink":"http://www.allmenus.com/ny/huntington/169926-burger-king/menu/",
    "sg:phone":"+1 631 423 6063",
    "sg:postcode":"11743",
    "sg:province":"NY",
    "sg:tags":[
        "burger",
        "american"
    ],
    "wof:name":"Burger King",
    "wof:placetype":"venue"
},
  "geometry": {"coordinates":[-73.42446,40.829013],"type":"Point"}
}