{
  "type": "Feature",
  "properties": {
    "iso:country":"US",
    "sg:address":"2124 Grand Central Ave",
    "sg:city":"Horseheads",
    "sg:classifiers":[
        {
            "category":"Real Estate",
            "subcategory":"Real Estate Operator",
            "type":"Services"
        }
    ],
    "sg:phone":"+1 607 739 4151",
    "sg:postcode":"14845",
    "sg:province":"NY",
    "sg:tags":[
        "building",
        "apartment"
    ],
    "wof:name":"Victory Heights Apts",
    "wof:placetype":"venue"
},
  "geometry": {"coordinates":[-76.82129500000001,42.153998],"type":"Point"}
}