{
  "type": "Feature",
  "properties": {
    "addr:full":"140 W 30 St New York NY 10001",
    "addr:housenumber":"140",
    "addr:postcode":"10001",
    "addr:street":"W 30 St",
    "iso:country":"US",
    "sg:address":"140 W 30 St",
    "sg:city":"New York",
    "sg:classifiers":[
        {
            "category":"Manufacturing",
            "subcategory":"Apparel",
            "type":"Manufacturing & Wholesale Goods"
        }
    ],
    "sg:phone":"+1   ",
    "sg:postcode":"10001",
    "sg:province":"NY",
    "sg:tags":[
        "home",
        "furnishing",
        "mfg"
    ],
    "wof:name":"Wildcat Territory Inc",
    "wof:placetype":"venue"
},
  "geometry": {"coordinates":[-73.991619,40.747917],"type":"Point"}
}