{
  "type": "Feature",
  "properties": {
    "addr:full":"82 Main St Kings Park NY 11754",
    "addr:housenumber":"82",
    "addr:postcode":"11754",
    "addr:street":"Main St",
    "iso:country":"US",
    "sg:address":"82 Main St",
    "sg:city":"Kings Park",
    "sg:classifiers":[
        {
            "category":"Real Estate",
            "subcategory":"Real Estate Agent",
            "type":"Services"
        }
    ],
    "sg:phone":"+1 631 269 4141",
    "sg:postcode":"11754",
    "sg:province":"NY",
    "wof:name":"Olita Real Estate",
    "wof:placetype":"venue"
},
  "geometry": {"coordinates":[-73.25662800000001,40.885527],"type":"Point"}
}