{
  "type": "Feature",
  "properties": {
    "addr:full":"1617 New York Ave Huntington Sta NY 11746",
    "addr:housenumber":"1617",
    "addr:postcode":"11746",
    "addr:street":"New York Ave",
    "iso:country":"US",
    "sg:address":"1617 New York Ave",
    "sg:city":"Huntington Sta",
    "sg:classifiers":[
        {
            "category":"Travel",
            "subcategory":"Travel Agent",
            "type":"Entertainment"
        }
    ],
    "sg:phone":"+1 631 423 5222",
    "sg:postcode":"11746",
    "sg:province":"NY",
    "sg:tags":[
        "agency",
        "bureau"
    ],
    "wof:name":"Paul Sabatino II",
    "wof:placetype":"venue"
},
  "geometry": {"coordinates":[-73.412099,40.842851],"type":"Point"}
}