{
  "type": "Feature",
  "properties": {
    "addr:full":"Fort Tryon Park Manhattan NY 10040",
    "addr:postcode":"10040",
    "iso:country":"US",
    "sg:address":"Fort Tryon Park",
    "sg:city":"Manhattan",
    "sg:classifiers":[
        {
            "category":"Shopping",
            "subcategory":"Pets & Pet Supplies",
            "type":"Retail Goods"
        }
    ],
    "sg:postcode":"10040",
    "sg:province":"NY",
    "sg:website":"www.ftdog.org",
    "wof:name":"Sir William's Dog Run",
    "wof:placetype":"venue"
},
  "geometry": {"coordinates":[-73.932075,40.862671],"type":"Point"}
}