{
  "type": "Feature",
  "properties": {
    "addr:full":"3175 State Hwy 77 Varysburg NY 14167",
    "addr:housenumber":"3175",
    "addr:postcode":"14167",
    "addr:street":"State Hwy 77",
    "iso:country":"US",
    "sg:address":"3175 State Hwy 77",
    "sg:city":"Varysburg",
    "sg:phone":"+1 585 535 7006",
    "sg:postcode":"14167",
    "sg:province":"NY",
    "sg:tags":[
        "farm",
        "field",
        "corn",
        "crop"
    ],
    "wof:name":"T Kirsch",
    "wof:placetype":"venue"
},
  "geometry": {"coordinates":[-78.388165,42.730797],"type":"Point"}
}