{
  "type": "Feature",
  "properties": {
    "iso:country":"US",
    "sg:address":"290 State Hwy 303",
    "sg:city":"Tappan",
    "sg:classifiers":[
        {
            "category":"Retail",
            "subcategory":"Funeral Services",
            "type":"Services"
        }
    ],
    "sg:phone":"+1 845 359 0890",
    "sg:postcode":"10983",
    "sg:province":"NY",
    "wof:name":"Moritz Funeral Home Inc",
    "wof:placetype":"venue"
},
  "geometry": {"coordinates":[-73.9434,41.02674],"type":"Point"}
}