{
  "type": "Feature",
  "properties": {
    "addr:full":"3520 Broadway New York NY 10031",
    "addr:housenumber":"3520",
    "addr:postcode":"10031",
    "addr:street":"Broadway",
    "iso:country":"US",
    "sg:address":"3520 Broadway",
    "sg:city":"New York",
    "sg:classifiers":[
        {
            "category":"Deli",
            "type":"Food & Drink"
        },
        {
            "category":"Food & Beverages",
            "subcategory":"Bakery",
            "type":"Retail Goods"
        }
    ],
    "sg:phone":"+1 212 926 2222",
    "sg:postcode":"10031",
    "sg:province":"NY",
    "sg:tags":[
        "sandwich"
    ],
    "wof:name":"Majestic Deli Inc",
    "wof:placetype":"venue"
},
  "geometry": {"coordinates":[-73.950671,40.82563],"type":"Point"}
}