{
  "type": "Feature",
  "properties": {
    "addr:full":"3375 Royal Ave Oceanside NY 11572",
    "addr:housenumber":"3375",
    "addr:postcode":"11572",
    "addr:street":"Royal Ave",
    "iso:country":"US",
    "sg:address":"3375 Royal Ave",
    "sg:city":"Oceanside",
    "sg:classifiers":[
        {
            "category":"Building & Trades",
            "subcategory":"Construction",
            "type":"Services"
        }
    ],
    "sg:phone":"+1 516 255 5481",
    "sg:postcode":"11572",
    "sg:province":"NY",
    "sg:tags":[
        "wireless",
        "telecommunication"
    ],
    "wof:name":"Tristate Telecommunications",
    "wof:placetype":"venue"
},
  "geometry": {"coordinates":[-73.653499,40.628629],"type":"Point"}
}