{
  "type": "Feature",
  "properties": {
    "addr:full":"260 Park Hill Ave Staten Island NY 10304",
    "addr:housenumber":"260",
    "addr:postcode":"10304",
    "addr:street":"Park Hill Ave",
    "iso:country":"US",
    "sg:address":"260 Park Hill Ave",
    "sg:city":"Staten Island",
    "sg:classifiers":[
        {
            "category":"Building & Trades",
            "subcategory":"Cleaning & Sanitation",
            "type":"Services"
        }
    ],
    "sg:phone":"+1   ",
    "sg:postcode":"10304",
    "sg:province":"NY",
    "sg:tags":[
        "maintenance"
    ],
    "wof:name":"Gods Way Cleaning Inc",
    "wof:placetype":"venue"
},
  "geometry": {"coordinates":[-74.082808,40.613255],"type":"Point"}
}