{
  "type": "Feature",
  "properties": {
    "iso:country":"US",
    "sg:address":"1268 Myrtle Ave",
    "sg:city":"Brooklyn",
    "sg:classifiers":[
        {
            "category":"Personal",
            "subcategory":"Barber",
            "type":"Services"
        }
    ],
    "sg:phone":"+1 718 452 9556",
    "sg:postcode":"11221",
    "sg:province":"NY",
    "wof:name":"Lourdes Unisex",
    "wof:placetype":"venue"
},
  "geometry": {"coordinates":[-73.926399,40.6978],"type":"Point"}
}