{
  "type": "Feature",
  "properties": {
    "iso:country":"US",
    "sg:address":"1976 1st Avenue",
    "sg:city":"New York",
    "sg:classifiers":[
        {
            "category":"Restaurant",
            "type":"Food & Drink"
        }
    ],
    "sg:phone":"+1 212 996 2866",
    "sg:postcode":"10029",
    "sg:province":"NY",
    "sg:tags":[
        "pizza"
    ],
    "wof:name":"M J Pizza",
    "wof:placetype":"venue"
},
  "geometry": {"coordinates":[-73.94165099999999,40.787206],"type":"Point"}
}