{
  "type": "Feature",
  "properties": {
    "iso:country":"US",
    "sg:address":"747 Main St",
    "sg:city":"Buffalo",
    "sg:classifiers":[
        {
            "category":"Shopping",
            "subcategory":"Clothing, Apparel, & Fashions",
            "type":"Retail Goods"
        }
    ],
    "sg:phone":"+1 716 847 0180",
    "sg:postcode":"14203",
    "sg:province":"NY",
    "sg:tags":[
        "theatrical",
        "costume"
    ],
    "sg:website":"www.costume.com",
    "wof:name":"D C Theatricks",
    "wof:placetype":"venue"
},
  "geometry": {"coordinates":[-78.871803,42.894299],"type":"Point"}
}