{
  "type": "Feature",
  "properties": {
    "iso:country":"US",
    "sg:address":"2403 8th Ave",
    "sg:city":"New York",
    "sg:classifiers":[
        {
            "category":"Food & Beverages",
            "subcategory":"Groceries & Convenience Stores",
            "type":"Retail Goods"
        }
    ],
    "sg:phone":"+1 212 665 9953",
    "sg:postcode":"10027",
    "sg:province":"NY",
    "sg:tags":[
        "product"
    ],
    "wof:name":"Harlem Post Food Corp",
    "wof:placetype":"venue"
},
  "geometry": {"coordinates":[-73.949685,40.812203],"type":"Point"}
}