{
  "type": "Feature",
  "properties": {
    "addr:full":"39 Country Club Rd Bellport NY 11713",
    "addr:housenumber":"39",
    "addr:postcode":"11713",
    "addr:street":"Country Club Rd",
    "iso:country":"US",
    "sg:address":"39 Country Club Rd",
    "sg:city":"Bellport",
    "sg:classifiers":[
        {
            "category":"Personal",
            "subcategory":"Beauty Salon",
            "type":"Services"
        }
    ],
    "sg:phone":"+1   ",
    "sg:postcode":"11713",
    "sg:province":"NY",
    "sg:tags":[
        "shop"
    ],
    "wof:name":"Lookin Good Landscaping",
    "wof:placetype":"venue"
},
  "geometry": {"coordinates":[-72.948097,40.758258],"type":"Point"}
}