{
  "type": "Feature",
  "properties": {
    "iso:country":"US",
    "sg:address":"480 Balltown Rd",
    "sg:city":"Schenectady",
    "sg:classifiers":[
        {
            "category":"Real Estate",
            "subcategory":"Real Estate Agent",
            "type":"Services"
        }
    ],
    "sg:phone":"+1 518 370 3170",
    "sg:postcode":"12304",
    "sg:province":"NY",
    "sg:tags":[
        "consultant"
    ],
    "sg:website":"www.realtyusa.com",
    "wof:name":"Realty USA",
    "wof:placetype":"venue"
},
  "geometry": {"coordinates":[-73.89346999999999,42.776417],"type":"Point"}
}