{
  "type": "Feature",
  "properties": {
    "iso:country":"US",
    "sg:address":"1684 Montauk Hwy",
    "sg:city":"Mastic",
    "sg:classifiers":[
        {
            "category":"Social Services",
            "subcategory":"Job Training",
            "type":"Services"
        }
    ],
    "sg:phone":"+1 631 399 8499",
    "sg:postcode":"11950",
    "sg:province":"NY",
    "sg:tags":[
        "rehabilitation"
    ],
    "wof:name":"Sports Therapy",
    "wof:placetype":"venue"
},
  "geometry": {"coordinates":[-72.838536,40.80629],"type":"Point"}
}