{
  "type": "Feature",
  "properties": {
    "addr:full":"1605 Hylan Blvd Staten Island NY 10305",
    "addr:housenumber":"1605",
    "addr:postcode":"10305",
    "addr:street":"Hylan Blvd",
    "iso:country":"US",
    "sg:address":"1605 Hylan Blvd",
    "sg:city":"Staten Island",
    "sg:classifiers":[
        {
            "category":"Autos & Motor Vehicles",
            "subcategory":"Automobile Sales",
            "type":"Retail Goods"
        }
    ],
    "sg:phone":"+1   ",
    "sg:postcode":"10305",
    "sg:province":"NY",
    "sg:tags":[
        "used"
    ],
    "wof:name":"Staten Island Used Cars",
    "wof:placetype":"venue"
},
  "geometry": {"coordinates":[-74.089879,40.589037],"type":"Point"}
}