{
  "type": "Feature",
  "properties": {
    "iso:country":"US",
    "sg:address":"17 Drowne Rd",
    "sg:city":"Old Chatham",
    "sg:classifiers":[
        {
            "category":"Professional",
            "subcategory":"Advertising",
            "type":"Services"
        }
    ],
    "sg:phone":"+1 518 766 2466",
    "sg:postcode":"12136",
    "sg:province":"NY",
    "sg:tags":[
        "agency"
    ],
    "sg:website":"www.blasscommunications.com",
    "wof:name":"Blass Communications LLC",
    "wof:placetype":"venue"
},
  "geometry": {"coordinates":[-73.570015,42.469505],"type":"Point"}
}