{
  "type": "Feature",
  "properties": {
    "addr:full":"148 W 24th St Fl 12 New York NY 10011",
    "addr:housenumber":"148;12",
    "addr:postcode":"10011",
    "addr:street":"W 24Th St Fl",
    "iso:country":"US",
    "sg:address":"148 W 24th St Fl 12",
    "sg:city":"New York",
    "sg:classifiers":[
        {
            "category":"Professional",
            "subcategory":"Computer Services",
            "type":"Services"
        }
    ],
    "sg:phone":"+1 212 675 9800",
    "sg:postcode":"10011",
    "sg:province":"NY",
    "sg:tags":[
        "repair"
    ],
    "sg:website":"www.purelogic.com",
    "wof:name":"Pure Logic",
    "wof:placetype":"venue"
},
  "geometry": {"coordinates":[-73.99369799999999,40.744099],"type":"Point"}
}