{
  "type": "Feature",
  "properties": {
    "iso:country":"US",
    "sg:address":"800 2nd Avenue",
    "sg:city":"New York",
    "sg:classifiers":[
        {
            "category":"Shopping",
            "subcategory":"Pharmacy",
            "type":"Retail Goods"
        }
    ],
    "sg:phone":"+1 212 986 2928",
    "sg:postcode":"10017",
    "sg:province":"NY",
    "sg:tags":[
        "drugstore"
    ],
    "wof:name":"Miller's Pharmacy",
    "wof:placetype":"venue"
},
  "geometry": {"coordinates":[-73.972184,40.749794],"type":"Point"}
}