{
  "type": "Feature",
  "properties": {
    "iso:country":"US",
    "sg:address":"408 E Broadway",
    "sg:city":"Fulton",
    "sg:classifiers":[
        {
            "category":"Social Services",
            "type":"Services"
        }
    ],
    "sg:phone":"+1 315 593 1220",
    "sg:postcode":"13069",
    "sg:province":"NY",
    "sg:tags":[
        "worker"
    ],
    "wof:name":"Maria Grimshaw Clark Csw",
    "wof:placetype":"venue"
},
  "geometry": {"coordinates":[-76.40876299999999,43.319919],"type":"Point"}
}