{
  "type": "Feature",
  "properties": {
    "addr:full":"607 Henry St Brooklyn NY 11231",
    "addr:housenumber":"607",
    "addr:postcode":"11231",
    "addr:street":"Henry St",
    "iso:country":"US",
    "sg:address":"607 Henry St",
    "sg:city":"Brooklyn",
    "sg:classifiers":[
        {
            "category":"Professional",
            "subcategory":"Computer Services",
            "type":"Services"
        }
    ],
    "sg:phone":"+1   ",
    "sg:postcode":"11231",
    "sg:province":"NY",
    "sg:tags":[
        "programing",
        "custom"
    ],
    "wof:name":"Anthony Diaz",
    "wof:placetype":"venue"
},
  "geometry": {"coordinates":[-74.001018,40.680792],"type":"Point"}
}