{
  "type": "Feature",
  "properties": {
    "iso:country":"US",
    "sg:address":"5296 Log London Rd",
    "sg:city":"Mannsville",
    "sg:classifiers":[
        {
            "category":"Personal",
            "type":"Services"
        },
        {
            "category":"Professional",
            "subcategory":"Art Services",
            "type":"Services"
        }
    ],
    "sg:phone":"+1 315 232 2844",
    "sg:postcode":"13661",
    "sg:province":"NY",
    "sg:tags":[
        "photography",
        "videography",
        "wedding"
    ],
    "wof:name":"Onies Moments Photography",
    "wof:placetype":"venue"
},
  "geometry": {"coordinates":[-76.090177,43.742952],"type":"Point"}
}