{
  "type": "Feature",
  "properties": {
    "addr:full":"402 Union St Hudson NY 12534",
    "addr:housenumber":"402",
    "addr:postcode":"12534",
    "addr:street":"Union St",
    "iso:country":"US",
    "sg:address":"402 Union St",
    "sg:city":"Hudson",
    "sg:classifiers":[
        {
            "category":"Government",
            "subcategory":"Post Office",
            "type":"Public Place"
        }
    ],
    "sg:phone":"+1 518 828 3210",
    "sg:postcode":"12534",
    "sg:province":"NY",
    "wof:name":"US Post Office",
    "wof:placetype":"venue"
},
  "geometry": {"coordinates":[-73.789147,42.250313],"type":"Point"}
}