{
  "type": "Feature",
  "properties": {
    "addr:full":"213 W Merrick Rd Valley Stream NY 11580",
    "addr:housenumber":"213",
    "addr:postcode":"11580",
    "addr:street":"W Merrick Rd",
    "iso:country":"US",
    "sg:address":"213 W Merrick Rd",
    "sg:city":"Valley Stream",
    "sg:classifiers":[
        {
            "category":"Health Services",
            "subcategory":"Optometrist",
            "type":"Services"
        }
    ],
    "sg:phone":"+1 516 256 2020",
    "sg:postcode":"11580",
    "sg:province":"NY",
    "wof:name":"Broadway Optix",
    "wof:placetype":"venue"
},
  "geometry": {"coordinates":[-73.704944,40.66681],"type":"Point"}
}