{
  "type": "Feature",
  "properties": {
    "addr:full":"119 N Cliff Ave Sayville NY 11782",
    "addr:housenumber":"119",
    "addr:postcode":"11782",
    "addr:street":"N Cliff Ave",
    "iso:country":"US",
    "sg:address":"119 N Cliff Ave",
    "sg:city":"Sayville",
    "sg:classifiers":[
        {
            "category":"Building & Trades",
            "subcategory":"Construction",
            "type":"Services"
        }
    ],
    "sg:phone":"+1 631 567 8117",
    "sg:postcode":"11782",
    "sg:province":"NY",
    "sg:tags":[
        "residential"
    ],
    "wof:name":"Sawcut 1 Inc",
    "wof:placetype":"venue"
},
  "geometry": {"coordinates":[-73.09244,40.746862],"type":"Point"}
}