{
  "type": "Feature",
  "properties": {
    "addr:full":"3811 27th Street Long Island City NY 11101",
    "addr:housenumber":"3811",
    "addr:postcode":"11101",
    "addr:street":"27Th Street",
    "iso:country":"US",
    "sg:address":"3811 27th Street",
    "sg:city":"Long Island City",
    "sg:classifiers":[
        {
            "category":"Social Services",
            "subcategory":"Child Care",
            "type":"Services"
        }
    ],
    "sg:phone":"+1 718 937 7640",
    "sg:postcode":"11101",
    "sg:province":"NY",
    "sg:tags":[
        "day"
    ],
    "wof:name":"Quensbridge Astoria Child Care",
    "wof:placetype":"venue"
},
  "geometry": {"coordinates":[-73.935273,40.754947],"type":"Point"}
}