{
  "type": "Feature",
  "properties": {
    "addr:full":"901 Avenue of The Americas New York NY 10001",
    "addr:housenumber":"901",
    "addr:postcode":"10001",
    "addr:street":"Avenue Of The Americas",
    "iso:country":"US",
    "sg:address":"901 Avenue of The Americas",
    "sg:city":"New York",
    "sg:classifiers":[
        {
            "category":"Restaurant",
            "type":"Food & Drink"
        }
    ],
    "sg:menulink":"http://www.allmenus.com/ny/new-york/189312-mcdonalds/menu/",
    "sg:postcode":"10001",
    "sg:province":"NY",
    "sg:tags":[
        "burger",
        "american"
    ],
    "wof:name":"McDonald's",
    "wof:placetype":"venue"
},
  "geometry": {"coordinates":[-73.988265,40.749132],"type":"Point"}
}