{
  "type": "Feature",
  "properties": {
    "addr:full":"1000 Hoe Ave Bronx NY 10459",
    "addr:housenumber":"1000",
    "addr:postcode":"10459",
    "addr:street":"Hoe Ave",
    "iso:country":"US",
    "sg:address":"1000 Hoe Ave",
    "sg:city":"Bronx",
    "sg:classifiers":[
        {
            "category":"Retail",
            "subcategory":"Repair Shop",
            "type":"Services"
        }
    ],
    "sg:phone":"+1 718 301 7353",
    "sg:postcode":"10459",
    "sg:province":"NY",
    "sg:tags":[
        "lock",
        "locksmith"
    ],
    "wof:name":"Emergency Locksmith",
    "wof:placetype":"venue"
},
  "geometry": {"coordinates":[-73.89055399999999,40.825102],"type":"Point"}
}