{
  "type": "Feature",
  "properties": {
    "addr:full":"4806 13th Avenue Brooklyn NY 11219",
    "addr:housenumber":"4806",
    "addr:postcode":"11219",
    "addr:street":"13Th Avenue",
    "iso:country":"US",
    "sg:address":"4806 13th Avenue",
    "sg:city":"Brooklyn",
    "sg:classifiers":[
        {
            "category":"Shopping",
            "subcategory":"Mobile Phones",
            "type":"Retail Goods"
        }
    ],
    "sg:phone":"+1 718 851 3459",
    "sg:postcode":"11219",
    "sg:province":"NY",
    "wof:name":"Wireless Tech Corporation",
    "wof:placetype":"venue"
},
  "geometry": {"coordinates":[-73.991834,40.635482],"type":"Point"}
}