{
  "type": "Feature",
  "properties": {
    "addr:full":"4 Killian Way Clifton Park NY 12065",
    "addr:housenumber":"4",
    "addr:postcode":"12065",
    "addr:street":"Killian Way",
    "iso:country":"US",
    "sg:address":"4 Killian Way",
    "sg:city":"Clifton Park",
    "sg:classifiers":[
        {
            "category":"Banks & Credit Unions",
            "subcategory":"Bank",
            "type":"Services"
        }
    ],
    "sg:phone":"+1 518 664 0789",
    "sg:postcode":"12065",
    "sg:province":"NY",
    "sg:tags":[
        "depository",
        "banking"
    ],
    "wof:name":"Electronic Transfer Consulting",
    "wof:placetype":"venue"
},
  "geometry": {"coordinates":[-73.757138,42.875781],"type":"Point"}
}