{
  "type": "Feature",
  "properties": {
    "addr:full":"161 Corbin Pl Brooklyn NY 11235",
    "addr:housenumber":"161",
    "addr:postcode":"11235",
    "addr:street":"Corbin Pl",
    "iso:country":"US",
    "sg:address":"161 Corbin Pl",
    "sg:city":"Brooklyn",
    "sg:classifiers":[
        {
            "category":"Government",
            "subcategory":"Office",
            "type":"Public Place"
        }
    ],
    "sg:phone":"+1 718 743 3000",
    "sg:postcode":"11235",
    "sg:province":"NY",
    "sg:tags":[
        "organization",
        "senior",
        "association",
        "citizen"
    ],
    "wof:name":"Manhattan Beach Housing",
    "wof:placetype":"venue"
},
  "geometry": {"coordinates":[-73.95402,40.577761],"type":"Point"}
}