{
  "type": "Feature",
  "properties": {
    "addr:full":"7 Gouverneur Ln New York NY 10005",
    "addr:housenumber":"7",
    "addr:postcode":"10005",
    "addr:street":"Gouverneur Ln",
    "iso:country":"US",
    "sg:address":"7 Gouverneur Ln",
    "sg:city":"New York",
    "sg:classifiers":[
        {
            "category":"Education",
            "subcategory":"School",
            "type":"Public Place"
        }
    ],
    "sg:phone":"+1 212 566 7613",
    "sg:postcode":"10005",
    "sg:province":"NY",
    "wof:name":"General Information",
    "wof:placetype":"venue"
},
  "geometry": {"coordinates":[-74.007302,40.703948],"type":"Point"}
}