{
  "type": "Feature",
  "properties": {
    "iso:country":"US",
    "sg:address":"63 Colonial Dr",
    "sg:city":"Horseheads",
    "sg:classifiers":[
        {
            "category":"Home & Garden",
            "subcategory":"Home Furnishings",
            "type":"Retail Goods"
        }
    ],
    "sg:phone":"+1 607 796 2856",
    "sg:postcode":"14845",
    "sg:province":"NY",
    "sg:tags":[
        "mirror"
    ],
    "wof:name":"Express Glass",
    "wof:placetype":"venue"
},
  "geometry": {"coordinates":[-76.855524,42.16176],"type":"Point"}
}