{
  "type": "Feature",
  "properties": {
    "addr:full":"26 Fox Meadow Ln Huntington NY 11743",
    "addr:housenumber":"26",
    "addr:postcode":"11743",
    "addr:street":"Fox Meadow Ln",
    "iso:country":"US",
    "sg:address":"26 Fox Meadow Ln",
    "sg:city":"Huntington",
    "sg:classifiers":[
        {
            "category":"Manufacturing",
            "subcategory":"Furniture",
            "type":"Manufacturing & Wholesale Goods"
        }
    ],
    "sg:phone":"+1   ",
    "sg:postcode":"11743",
    "sg:province":"NY",
    "sg:tags":[
        "drapery",
        "mfg"
    ],
    "wof:name":"Solomon Venetian Blind",
    "wof:placetype":"venue"
},
  "geometry": {"coordinates":[-73.460615,40.908452],"type":"Point"}
}