{
  "type": "Feature",
  "properties": {
    "addr:full":"940 Morris Ave Bronx NY 10456",
    "addr:housenumber":"940",
    "addr:postcode":"10456",
    "addr:street":"Morris Ave",
    "iso:country":"US",
    "sg:address":"940 Morris Ave",
    "sg:city":"Bronx",
    "sg:classifiers":[
        {
            "category":"Shopping",
            "subcategory":"Discount & Variety Stores",
            "type":"Retail Goods"
        }
    ],
    "sg:phone":"+1 718 293 0022",
    "sg:postcode":"10456",
    "sg:province":"NY",
    "sg:tags":[
        "merchandise",
        "general"
    ],
    "wof:name":"FBZ Inc",
    "wof:placetype":"venue"
},
  "geometry": {"coordinates":[-73.91753199999999,40.82725],"type":"Point"}
}