{
  "type": "Feature",
  "properties": {
    "addr:full":"40 Smith St Farmingdale NY 11735",
    "addr:housenumber":"40",
    "addr:postcode":"11735",
    "addr:street":"Smith St",
    "iso:country":"US",
    "sg:address":"40 Smith St",
    "sg:city":"Farmingdale",
    "sg:classifiers":[
        {
            "category":"Real Estate",
            "subcategory":"Surveying",
            "type":"Services"
        }
    ],
    "sg:phone":"+1 631 752 8577",
    "sg:postcode":"11735",
    "sg:province":"NY",
    "sg:tags":[
        "surveyor"
    ],
    "wof:name":"Survey Technologly Inc",
    "wof:placetype":"venue"
},
  "geometry": {"coordinates":[-73.415639,40.754557],"type":"Point"}
}