{
  "type": "Feature",
  "properties": {
    "iso:country":"US",
    "sg:address":"35 Polo Rd",
    "sg:city":"Great Neck",
    "sg:classifiers":[
        {
            "category":"Education",
            "subcategory":"School",
            "type":"Public Place"
        }
    ],
    "sg:phone":"+1 516 773 1519",
    "sg:postcode":"11023",
    "sg:province":"NY",
    "sg:website":"www.greatneck.k12.ny.us",
    "wof:name":"North High School",
    "wof:placetype":"venue"
},
  "geometry": {"coordinates":[-73.73953,40.800262],"type":"Point"}
}