{
  "type": "Feature",
  "properties": {
    "iso:country":"US",
    "sg:address":"6010 New Hartford St",
    "sg:city":"Wolcott",
    "sg:classifiers":[
        {
            "category":"Shopping",
            "subcategory":"Discount & Variety Stores",
            "type":"Retail Goods"
        }
    ],
    "sg:phone":"+1 315 594 1556",
    "sg:postcode":"14590",
    "sg:province":"NY",
    "sg:website":"http://www.dollargeneral.com",
    "wof:name":"Dollar General",
    "wof:placetype":"venue"
},
  "geometry": {"coordinates":[-76.81503499999999,43.219741],"type":"Point"}
}