{
  "type": "Feature",
  "properties": {
    "iso:country":"US",
    "sg:address":"501 E 85th St",
    "sg:city":"New York",
    "sg:classifiers":[
        {
            "category":"Retail",
            "subcategory":"Laundry & Dry Cleaning",
            "type":"Services"
        }
    ],
    "sg:phone":"+1 212 988 2040",
    "sg:postcode":"10028",
    "sg:province":"NY",
    "sg:tags":[
        "cleaners"
    ],
    "wof:name":"Nu-Look Cleaners & Dyers",
    "wof:placetype":"venue"
},
  "geometry": {"coordinates":[-73.945267,40.774252],"type":"Point"}
}