{
  "type": "Feature",
  "properties": {
    "addr:full":"2 Cherry St Walden NY 12586",
    "addr:housenumber":"2",
    "addr:postcode":"12586",
    "addr:street":"Cherry St",
    "iso:country":"US",
    "sg:address":"2 Cherry St",
    "sg:city":"Walden",
    "sg:classifiers":[
        {
            "category":"Manufacturing",
            "subcategory":"Signs",
            "type":"Manufacturing & Wholesale Goods"
        }
    ],
    "sg:phone":"+1   ",
    "sg:postcode":"12586",
    "sg:province":"NY",
    "sg:tags":[
        "specialty",
        "mfg"
    ],
    "wof:name":"Nub Grafix",
    "wof:placetype":"venue"
},
  "geometry": {"coordinates":[-74.18534,41.558481],"type":"Point"}
}