{
  "type": "Feature",
  "properties": {
    "iso:country":"US",
    "sg:address":"20 Jareds Path",
    "sg:city":"Brookhaven",
    "sg:classifiers":[
        {
            "category":"Building & Trades",
            "subcategory":"Construction",
            "type":"Services"
        }
    ],
    "sg:phone":"+1 516 356 5227",
    "sg:postcode":"11719",
    "sg:province":"NY",
    "sg:tags":[
        "house",
        "engineering",
        "carpentry"
    ],
    "wof:name":"Lns Construction",
    "wof:placetype":"venue"
},
  "geometry": {"coordinates":[-72.910042,40.765715],"type":"Point"}
}