{
  "type": "Feature",
  "properties": {
    "iso:country":"US",
    "sg:address":"625 7th Ave",
    "sg:city":"Troy",
    "sg:classifiers":[
        {
            "category":"Education",
            "subcategory":"School",
            "type":"Public Place"
        }
    ],
    "sg:phone":"+1 518 235 7100",
    "sg:postcode":"12182",
    "sg:province":"NY",
    "sg:tags":[
        "high"
    ],
    "sg:website":"www.cchstroy.org",
    "wof:name":"Catholic Central High School",
    "wof:placetype":"venue"
},
  "geometry": {"coordinates":[-73.670773,42.77461],"type":"Point"}
}