{
  "type": "Feature",
  "properties": {
    "addr:full":"1417 Hertel Ave Buffalo NY 14216",
    "addr:housenumber":"1417",
    "addr:postcode":"14216",
    "addr:street":"Hertel Ave",
    "iso:country":"US",
    "sg:address":"1417 Hertel Ave",
    "sg:city":"Buffalo",
    "sg:classifiers":[
        {
            "category":"Shopping",
            "subcategory":"Antiques",
            "type":"Retail Goods"
        }
    ],
    "sg:phone":"+1 716 838 3930",
    "sg:postcode":"14216",
    "sg:province":"NY",
    "wof:name":"Decorum",
    "wof:placetype":"venue"
},
  "geometry": {"coordinates":[-78.85558399999999,42.947584],"type":"Point"}
}