{
  "type": "Feature",
  "properties": {
    "addr:full":"1902 E 28th St Brooklyn NY 11229",
    "addr:housenumber":"1902",
    "addr:postcode":"11229",
    "addr:street":"E 28Th St",
    "iso:country":"US",
    "sg:address":"1902 E 28th St",
    "sg:city":"Brooklyn",
    "sg:classifiers":[
        {
            "category":"Health Services",
            "subcategory":"Medical Lab",
            "type":"Services"
        }
    ],
    "sg:phone":"+1   ",
    "sg:postcode":"11229",
    "sg:province":"NY",
    "sg:tags":[
        "laboratory",
        "dental"
    ],
    "wof:name":"Welladent Restorations",
    "wof:placetype":"venue"
},
  "geometry": {"coordinates":[-73.944323,40.60251],"type":"Point"}
}