{
  "type": "Feature",
  "properties": {
    "iso:country":"US",
    "sg:address":"2359 State Rte 14A",
    "sg:city":"Penn Yan",
    "sg:classifiers":[
        {
            "category":"Autos & Motor Vehicles",
            "subcategory":"Auto Supplies",
            "type":"Retail Goods"
        }
    ],
    "sg:phone":"+1 315 536 3593",
    "sg:postcode":"14527",
    "sg:province":"NY",
    "sg:tags":[
        "alternator",
        "generator"
    ],
    "wof:name":"Turner AS & B",
    "wof:placetype":"venue"
},
  "geometry": {"coordinates":[-77.05225299999999,42.649597],"type":"Point"}
}