{
  "type": "Feature",
  "properties": {
    "iso:country":"US",
    "sg:address":"57 Aberdeen Rd",
    "sg:city":"Smithtown",
    "sg:classifiers":[
        {
            "category":"Building & Trades",
            "subcategory":"Electrical",
            "type":"Services"
        }
    ],
    "sg:phone":"+1 631 265 6800",
    "sg:postcode":"11787",
    "sg:province":"NY",
    "sg:tags":[
        "electrical",
        "contractor"
    ],
    "wof:name":"All Service Electric Inc",
    "wof:placetype":"venue"
},
  "geometry": {"coordinates":[-73.21233700000001,40.832829],"type":"Point"}
}