{
  "type": "Feature",
  "properties": {
    "addr:full":"93 Broadway Haverstraw NY 10927",
    "addr:housenumber":"93",
    "addr:postcode":"10927",
    "addr:street":"Broadway",
    "iso:country":"US",
    "sg:address":"93 Broadway",
    "sg:city":"Haverstraw",
    "sg:classifiers":[
        {
            "category":"Restaurant",
            "type":"Food & Drink"
        }
    ],
    "sg:phone":"+1 845 269 3566",
    "sg:postcode":"10927",
    "sg:province":"NY",
    "wof:name":"La Fonda Mexican Restaurant Inc.",
    "wof:placetype":"venue"
},
  "geometry": {"coordinates":[-73.965749,41.199976],"type":"Point"}
}