{
  "type": "Feature",
  "properties": {
    "iso:country":"US",
    "sg:address":"27 Hawthorne Ave",
    "sg:city":"Warwick",
    "sg:classifiers":[
        {
            "category":"Social Services",
            "subcategory":"Child Care",
            "type":"Services"
        }
    ],
    "sg:phone":"+1 845 987 8414",
    "sg:postcode":"10990",
    "sg:province":"NY",
    "sg:tags":[
        "day"
    ],
    "wof:name":"Park Avenue Care Inc",
    "wof:placetype":"venue"
},
  "geometry": {"coordinates":[-74.348388,41.245833],"type":"Point"}
}