{
  "type": "Feature",
  "properties": {
    "iso:country":"US",
    "sg:address":"79 Wolverine St",
    "sg:city":"Staten Island",
    "sg:classifiers":[
        {
            "category":"Wholesale",
            "subcategory":"Groceries",
            "type":"Manufacturing & Wholesale Goods"
        }
    ],
    "sg:phone":"+1 718 667 1302",
    "sg:postcode":"10306",
    "sg:province":"NY",
    "sg:tags":[
        "cookie"
    ],
    "wof:name":"Double Delight Inc",
    "wof:placetype":"venue"
},
  "geometry": {"coordinates":[-74.129012,40.567108],"type":"Point"}
}