{
  "type": "Feature",
  "properties": {
    "addr:full":"13210 Crossbay Blvd Ozone Park NY 11417",
    "addr:postcode":"13210;11417",
    "addr:street":"Crossbay Blvd",
    "iso:country":"US",
    "sg:address":"13210 Crossbay Blvd",
    "sg:city":"Ozone Park",
    "sg:classifiers":[
        {
            "category":"Real Estate",
            "subcategory":"Real Estate Services",
            "type":"Services"
        }
    ],
    "sg:phone":"+1 718 529 2072",
    "sg:postcode":"11417",
    "sg:province":"NY",
    "sg:tags":[
        "management",
        "property"
    ],
    "wof:name":"Residential Development Group",
    "wof:placetype":"venue"
},
  "geometry": {"coordinates":[-73.84395000000001,40.676493],"type":"Point"}
}