{
  "type": "Feature",
  "properties": {
    "addr:full":"505 Foote Ave Jamestown NY 14701",
    "addr:housenumber":"505",
    "addr:postcode":"14701",
    "addr:street":"Foote Ave",
    "iso:country":"US",
    "sg:address":"505 Foote Ave",
    "sg:city":"Jamestown",
    "sg:classifiers":[
        {
            "category":"Health Services",
            "subcategory":"Doctor",
            "type":"Services"
        }
    ],
    "sg:phone":"+1 716 483 5480",
    "sg:postcode":"14701",
    "sg:province":"NY",
    "sg:tags":[
        "physician",
        "surgeon"
    ],
    "wof:name":"Jeffrey Morgan MD LLC",
    "wof:placetype":"venue"
},
  "geometry": {"coordinates":[-79.230979,42.085415],"type":"Point"}
}