{
  "type": "Feature",
  "properties": {
    "addr:full":"1641 Central Ave Albany NY 12205",
    "addr:housenumber":"1641",
    "addr:postcode":"12205",
    "addr:street":"Central Ave",
    "iso:country":"US",
    "sg:address":"1641 Central Ave",
    "sg:city":"Albany",
    "sg:classifiers":[
        {
            "category":"Real Estate",
            "subcategory":"Real Estate Agent",
            "type":"Services"
        }
    ],
    "sg:phone":"+1 518 456 0202",
    "sg:postcode":"12205",
    "sg:province":"NY",
    "wof:name":"Partner's Realty",
    "wof:placetype":"venue"
},
  "geometry": {"coordinates":[-73.835239,42.719766],"type":"Point"}
}