{
  "type": "Feature",
  "properties": {
    "addr:full":"2917 Middletown Rd Bronx NY 10461",
    "addr:housenumber":"2917",
    "addr:postcode":"10461",
    "addr:street":"Middletown Rd",
    "iso:country":"US",
    "sg:address":"2917 Middletown Rd",
    "sg:city":"Bronx",
    "sg:classifiers":[
        {
            "category":"Personal",
            "subcategory":"Beauty Salon",
            "type":"Services"
        }
    ],
    "sg:phone":"+1 718 824 7089",
    "sg:postcode":"10461",
    "sg:province":"NY",
    "wof:name":"Gigi's Hair Design",
    "wof:placetype":"venue"
},
  "geometry": {"coordinates":[-73.832446,40.843653],"type":"Point"}
}