{
  "type": "Feature",
  "properties": {
    "iso:country":"US",
    "sg:address":"7522 13th Ave",
    "sg:city":"Brooklyn",
    "sg:classifiers":[
        {
            "category":"Food & Beverages",
            "subcategory":"Bakery",
            "type":"Retail Goods"
        }
    ],
    "sg:phone":"+1   ",
    "sg:postcode":"11228",
    "sg:province":"NY",
    "wof:name":"Satellite Baking Co",
    "wof:placetype":"venue"
},
  "geometry": {"coordinates":[-74.00800599999999,40.619882],"type":"Point"}
}