{
  "type": "Feature",
  "properties": {
    "iso:country":"US",
    "sg:address":"110 Lake Shore Dr",
    "sg:city":"Brewster",
    "sg:classifiers":[
        {
            "category":"Professional",
            "type":"Services"
        }
    ],
    "sg:phone":"+1 845 669 8238",
    "sg:postcode":"10509",
    "sg:province":"NY",
    "sg:tags":[
        "establishment"
    ],
    "wof:name":"Regional Aquatic Control",
    "wof:placetype":"venue"
},
  "geometry": {"coordinates":[-73.541524,41.47076],"type":"Point"}
}