{
  "type": "Feature",
  "properties": {
    "addr:full":"11 Gulls Cove Manhasset NY 11030",
    "addr:housenumber":"11",
    "addr:postcode":"11030",
    "addr:street":"Gulls Cove",
    "iso:country":"US",
    "sg:address":"11 Gulls Cove",
    "sg:city":"Manhasset",
    "sg:classifiers":[
        {
            "category":"Professional",
            "subcategory":"Management & Consulting",
            "type":"Services"
        }
    ],
    "sg:phone":"+1 516 767 7812",
    "sg:postcode":"11030",
    "sg:province":"NY",
    "sg:tags":[
        "business"
    ],
    "wof:name":"Dara S Sagar PE PC",
    "wof:placetype":"venue"
},
  "geometry": {"coordinates":[-73.702164,40.81855],"type":"Point"}
}