{
  "type": "Feature",
  "properties": {
    "addr:full":"77 Main St Brewster NY 10509",
    "addr:housenumber":"77",
    "addr:postcode":"10509",
    "addr:street":"Main St",
    "iso:country":"US",
    "sg:address":"77 Main St",
    "sg:city":"Brewster",
    "sg:classifiers":[
        {
            "category":"Wholesale",
            "subcategory":"Construction Materials",
            "type":"Manufacturing & Wholesale Goods"
        }
    ],
    "sg:phone":"+1 845 278 6655",
    "sg:postcode":"10509",
    "sg:province":"NY",
    "sg:tags":[
        "sand",
        "gravel"
    ],
    "wof:name":"Brewster Supply",
    "wof:placetype":"venue"
},
  "geometry": {"coordinates":[-73.61638499999999,41.394393],"type":"Point"}
}