{
  "type": "Feature",
  "properties": {
    "iso:country":"US",
    "sg:address":"680 Lincoln Ave",
    "sg:city":"Brooklyn",
    "sg:classifiers":[
        {
            "category":"Social Services",
            "subcategory":"Child Care",
            "type":"Services"
        }
    ],
    "sg:phone":"+1 718 277 1058",
    "sg:postcode":"11208",
    "sg:province":"NY",
    "sg:tags":[
        "day"
    ],
    "wof:name":"Lincoln Day Care Corp",
    "wof:placetype":"venue"
},
  "geometry": {"coordinates":[-73.866501,40.672298],"type":"Point"}
}