{
  "type": "Feature",
  "properties": {
    "iso:country":"US",
    "sg:address":"20 Woodward Ln",
    "sg:city":"Cambridge",
    "sg:classifiers":[
        {
            "category":"Transit Center",
            "subcategory":"Freight",
            "type":"Transportation"
        },
        {
            "category":"Freight",
            "type":"Transportation"
        }
    ],
    "sg:phone":"+1 518 677 8958",
    "sg:postcode":"12816",
    "sg:province":"NY",
    "sg:tags":[
        "trucking-motor",
        "trucking"
    ],
    "wof:name":"Transport Felix",
    "wof:placetype":"venue"
},
  "geometry": {"coordinates":[-73.438672,42.994363],"type":"Point"}
}