{
  "type": "Feature",
  "properties": {
    "addr:full":"333 Flatbush Ave Brooklyn NY 11217",
    "addr:housenumber":"333",
    "addr:postcode":"11217",
    "addr:street":"Flatbush Ave",
    "iso:country":"US",
    "sg:address":"333 Flatbush Ave",
    "sg:city":"Brooklyn",
    "sg:classifiers":[
        {
            "category":"Shopping",
            "type":"Retail Goods"
        }
    ],
    "sg:phone":"+1 718 230 0310",
    "sg:postcode":"11217",
    "sg:province":"NY",
    "sg:tags":[
        "material",
        "artist",
        "supply"
    ],
    "wof:name":"Nouveau Decor Inc",
    "wof:placetype":"venue"
},
  "geometry": {"coordinates":[-73.972819,40.677876],"type":"Point"}
}