{
  "type": "Feature",
  "properties": {
    "addr:full":"395 Atlantic Ave Oceanside NY 11572",
    "addr:housenumber":"395",
    "addr:postcode":"11572",
    "addr:street":"Atlantic Ave",
    "iso:country":"US",
    "sg:address":"395 Atlantic Ave",
    "sg:city":"Oceanside",
    "sg:classifiers":[
        {
            "category":"Home & Garden",
            "subcategory":"Garden Supply",
            "type":"Retail Goods"
        }
    ],
    "sg:phone":"+1 516 766 6663",
    "sg:postcode":"11572",
    "sg:province":"NY",
    "sg:tags":[
        "nurseryman"
    ],
    "wof:name":"A Plant Nursery & Garden Ctr",
    "wof:placetype":"venue"
},
  "geometry": {"coordinates":[-73.648549,40.640374],"type":"Point"}
}