{
  "type": "Feature",
  "properties": {
    "addr:full":"1378 White Rd Phelps NY 14532",
    "addr:housenumber":"1378",
    "addr:postcode":"14532",
    "addr:street":"White Rd",
    "iso:country":"US",
    "sg:address":"1378 White Rd",
    "sg:city":"Phelps",
    "sg:classifiers":[
        {
            "category":"Retail",
            "subcategory":"Repair Shop",
            "type":"Services"
        }
    ],
    "sg:phone":"+1 315 462 9030",
    "sg:postcode":"14532",
    "sg:province":"NY",
    "sg:tags":[
        "trade",
        "welding",
        "contractor"
    ],
    "wof:name":"Dorgan Welding Service",
    "wof:placetype":"venue"
},
  "geometry": {"coordinates":[-77.054478,42.964946],"type":"Point"}
}