{
  "type": "Feature",
  "properties": {
    "iso:country":"US",
    "sg:address":"8828 Sutphin Blvd",
    "sg:city":"Jamaica",
    "sg:classifiers":[
        {
            "category":"Coffee & Tea",
            "type":"Food & Drink"
        },
        {
            "category":"Restaurant",
            "type":"Food & Drink"
        }
    ],
    "sg:phone":"+1 718 206 3444",
    "sg:postcode":"11435",
    "sg:province":"NY",
    "sg:tags":[
        "shop",
        "espresso"
    ],
    "wof:name":"Little Star Coffee Shop",
    "wof:placetype":"venue"
},
  "geometry": {"coordinates":[-73.79709200000001,40.690319],"type":"Point"}
}