{
  "type": "Feature",
  "properties": {
    "iso:country":"US",
    "sg:address":"189 Orchard St",
    "sg:city":"New York",
    "sg:classifiers":[
        {
            "category":"Personal",
            "subcategory":"Beauty Salon",
            "type":"Services"
        }
    ],
    "sg:phone":"+1 917 472 5390",
    "sg:postcode":"10002",
    "sg:province":"NY",
    "sg:tags":[
        "hair",
        "shop"
    ],
    "sg:website":"www.arena-salon.com/",
    "wof:name":"Arena Salon",
    "wof:placetype":"venue"
},
  "geometry": {"coordinates":[-73.988406,40.7222],"type":"Point"}
}