{
  "type": "Feature",
  "properties": {
    "iso:country":"US",
    "sg:address":"157 E 64 St",
    "sg:city":"New York",
    "sg:classifiers":[
        {
            "category":"Personal",
            "subcategory":"Beauty Salon",
            "type":"Services"
        }
    ],
    "sg:phone":"+1 212 517 3400",
    "sg:postcode":"10065",
    "sg:province":"NY",
    "wof:name":"Manhattan Color Studio",
    "wof:placetype":"venue"
},
  "geometry": {"coordinates":[-73.96431800000001,40.764779],"type":"Point"}
}