{
  "type": "Feature",
  "properties": {
    "iso:country":"US",
    "sg:address":"290 Broadway",
    "sg:city":"Newburgh",
    "sg:classifiers":[
        {
            "category":"Shopping",
            "subcategory":"Clothing, Apparel, & Fashions",
            "type":"Retail Goods"
        }
    ],
    "sg:phone":"+1   ",
    "sg:postcode":"12550",
    "sg:province":"NY",
    "wof:name":"Four One One",
    "wof:placetype":"venue"
},
  "geometry": {"coordinates":[-74.020366,41.500685],"type":"Point"}
}