{
  "type": "Feature",
  "properties": {
    "addr:full":"49 Smith Ln Medford NY 11763",
    "addr:housenumber":"49",
    "addr:postcode":"11763",
    "addr:street":"Smith Ln",
    "iso:country":"US",
    "sg:address":"49 Smith Ln",
    "sg:city":"Medford",
    "sg:classifiers":[
        {
            "category":"Professional",
            "type":"Services"
        }
    ],
    "sg:phone":"+1 631 716 1908",
    "sg:postcode":"11763",
    "sg:province":"NY",
    "sg:tags":[
        "establishment"
    ],
    "wof:name":"Nicholson Enterprises",
    "wof:placetype":"venue"
},
  "geometry": {"coordinates":[-72.96176800000001,40.855102],"type":"Point"}
}