{
  "type": "Feature",
  "properties": {
    "addr:full":"750 3rd Ave New York NY 10017",
    "addr:housenumber":"750",
    "addr:postcode":"10017",
    "addr:street":"3Rd Ave",
    "iso:country":"US",
    "sg:address":"750 3rd Ave",
    "sg:city":"New York",
    "sg:classifiers":[
        {
            "category":"Personal",
            "subcategory":"Hair Removal",
            "type":"Services"
        },
        {
            "category":"Personal",
            "subcategory":"Barber",
            "type":"Services"
        },
        {
            "category":"Personal",
            "subcategory":"Nail Salon",
            "type":"Services"
        }
    ],
    "sg:phone":"+1 212 983 3240",
    "sg:postcode":"10017",
    "sg:province":"NY",
    "sg:website":"www.spiffnyc.com",
    "wof:name":"Spiff",
    "wof:placetype":"venue"
},
  "geometry": {"coordinates":[-73.972797,40.753814],"type":"Point"}
}