{
  "type": "Feature",
  "properties": {
    "addr:full":"1014 Castle Hill Ave Bronx NY 10472",
    "addr:housenumber":"1014",
    "addr:postcode":"10472",
    "addr:street":"Castle Hill Ave",
    "iso:country":"US",
    "sg:address":"1014 Castle Hill Ave",
    "sg:city":"Bronx",
    "sg:classifiers":[
        {
            "category":"Personal",
            "type":"Services"
        }
    ],
    "sg:phone":"+1 718 904 8663",
    "sg:postcode":"10472",
    "sg:province":"NY",
    "sg:tags":[
        "therapist",
        "massage"
    ],
    "sg:website":"www.tonesspa.com",
    "wof:name":"Tones Spa",
    "wof:placetype":"venue"
},
  "geometry": {"coordinates":[-73.85006300000001,40.827977],"type":"Point"}
}