{
  "type": "Feature",
  "properties": {
    "iso:country":"US",
    "sg:address":"656 Middle Rd",
    "sg:city":"Caledonia",
    "sg:classifiers":[
        {
            "category":"Building & Trades",
            "subcategory":"Construction",
            "type":"Services"
        }
    ],
    "sg:phone":"+1 585 538 6178",
    "sg:postcode":"14423",
    "sg:province":"NY",
    "sg:tags":[
        "new",
        "restoration",
        "family",
        "home"
    ],
    "wof:name":"David C Nusbickel",
    "wof:placetype":"venue"
},
  "geometry": {"coordinates":[-77.84985,42.955072],"type":"Point"}
}