{
  "type": "Feature",
  "properties": {
    "addr:full":"298 Atlantic Ave Brooklyn NY 11201",
    "addr:housenumber":"298",
    "addr:postcode":"11201",
    "addr:street":"Atlantic Ave",
    "iso:country":"US",
    "sg:address":"298 Atlantic Ave",
    "sg:city":"Brooklyn",
    "sg:classifiers":[
        {
            "category":"Professional",
            "type":"Services"
        }
    ],
    "sg:phone":"+1 718 722 1305",
    "sg:postcode":"11201",
    "sg:province":"NY",
    "sg:website":"www.badapplebailbonds.com",
    "wof:name":"A Bad Apple Bail Bonds",
    "wof:placetype":"venue"
},
  "geometry": {"coordinates":[-73.988899,40.688499],"type":"Point"}
}