{
  "type": "Feature",
  "properties": {
    "addr:full":"200 S Main Ave Albany NY 12208",
    "addr:housenumber":"200",
    "addr:postcode":"12208",
    "addr:street":"S Main Ave",
    "iso:country":"US",
    "sg:address":"200 S Main Ave",
    "sg:city":"Albany",
    "sg:classifiers":[
        {
            "category":"Real Estate",
            "subcategory":"Real Estate Agent",
            "type":"Services"
        }
    ],
    "sg:phone":"+1 518 489 1550",
    "sg:postcode":"12208",
    "sg:province":"NY",
    "wof:name":"Mabin Realty",
    "wof:placetype":"venue"
},
  "geometry": {"coordinates":[-73.797229,42.656701],"type":"Point"}
}