{
  "type": "Feature",
  "properties": {
    "iso:country":"US",
    "sg:address":"52 Radford Pl",
    "sg:city":"Yonkers",
    "sg:classifiers":[
        {
            "category":"Professional",
            "subcategory":"Lawyer & Legal Services",
            "type":"Services"
        }
    ],
    "sg:phone":"+1 914 963 4433",
    "sg:postcode":"10701",
    "sg:province":"NY",
    "sg:tags":[
        "attorney"
    ],
    "wof:name":"Ellen M Boyle",
    "wof:placetype":"venue"
},
  "geometry": {"coordinates":[-73.896405,40.93143],"type":"Point"}
}