{
  "type": "Feature",
  "properties": {
    "iso:country":"US",
    "sg:address":"19 Roberts Dr",
    "sg:city":"Accord",
    "sg:classifiers":[
        {
            "category":"Shopping",
            "subcategory":"Computers & Home Electronics",
            "type":"Retail Goods"
        }
    ],
    "sg:phone":"+1 845 626 5617",
    "sg:postcode":"12404",
    "sg:province":"NY",
    "sg:tags":[
        "equipment",
        "electronic",
        "supply"
    ],
    "wof:name":"Custom Electronics",
    "wof:placetype":"venue"
},
  "geometry": {"coordinates":[-74.263577,41.805566],"type":"Point"}
}