{
  "type": "Feature",
  "properties": {
    "addr:full":"5 Crescent St Northport NY 11768",
    "addr:housenumber":"5",
    "addr:postcode":"11768",
    "addr:street":"Crescent St",
    "iso:country":"US",
    "sg:address":"5 Crescent St",
    "sg:city":"Northport",
    "sg:classifiers":[
        {
            "category":"Professional",
            "type":"Services"
        }
    ],
    "sg:phone":"+1   ",
    "sg:postcode":"11768",
    "sg:province":"NY",
    "wof:name":"Oakleaf Inc",
    "wof:placetype":"venue"
},
  "geometry": {"coordinates":[-73.33803899999999,40.900206],"type":"Point"}
}