{
  "type": "Feature",
  "properties": {
    "addr:full":"82 South Ave Hilton NY 14468",
    "addr:housenumber":"82",
    "addr:postcode":"14468",
    "addr:street":"South Ave",
    "iso:country":"US",
    "sg:address":"82 South Ave",
    "sg:city":"Hilton",
    "sg:classifiers":[
        {
            "category":"Shopping",
            "subcategory":"Department Store",
            "type":"Retail Goods"
        }
    ],
    "sg:phone":"+1 585 392 7311",
    "sg:postcode":"14468",
    "sg:province":"NY",
    "wof:name":"Family Dollar Store",
    "wof:placetype":"venue"
},
  "geometry": {"coordinates":[-77.79141799999999,43.285453],"type":"Point"}
}