{
  "type": "Feature",
  "properties": {
    "addr:full":"485 Dahill Rd Brooklyn NY 11218",
    "addr:housenumber":"485",
    "addr:postcode":"11218",
    "addr:street":"Dahill Rd",
    "iso:country":"US",
    "sg:address":"485 Dahill Rd",
    "sg:city":"Brooklyn",
    "sg:classifiers":[
        {
            "category":"Shopping",
            "subcategory":"Clothing, Apparel, & Fashions",
            "type":"Retail Goods"
        }
    ],
    "sg:phone":"+1   ",
    "sg:postcode":"11218",
    "sg:province":"NY",
    "wof:name":"Moe Penn Hatter",
    "wof:placetype":"venue"
},
  "geometry": {"coordinates":[-73.97928,40.636119],"type":"Point"}
}