{
  "type": "Feature",
  "properties": {
    "iso:country":"US",
    "sg:address":"130 New Valley Rd",
    "sg:city":"New City",
    "sg:classifiers":[
        {
            "category":"Building & Trades",
            "subcategory":"Construction",
            "type":"Services"
        }
    ],
    "sg:phone":"+1 845 634 0894",
    "sg:postcode":"10956",
    "sg:province":"NY",
    "sg:tags":[
        "general",
        "contractor"
    ],
    "wof:name":"Five Star Landscape Cntrctng",
    "wof:placetype":"venue"
},
  "geometry": {"coordinates":[-74.01281400000001,41.131003],"type":"Point"}
}