{
  "type": "Feature",
  "properties": {
    "addr:full":"269 Osborne Rd Ste B Albany NY 12211",
    "addr:housenumber":"269",
    "addr:postcode":"12211",
    "addr:street":"Osborne Rd Ste B",
    "iso:country":"US",
    "sg:address":"269 Osborne Rd Ste B",
    "sg:city":"Albany",
    "sg:classifiers":[
        {
            "category":"Banks & Credit Unions",
            "subcategory":"Investment Brokerage",
            "type":"Services"
        }
    ],
    "sg:phone":"+1 518 453 3456",
    "sg:postcode":"12211",
    "sg:province":"NY",
    "sg:tags":[
        "tape",
        "video",
        "sale",
        "dvds-rental"
    ],
    "wof:name":"Hollywood Video",
    "wof:placetype":"venue"
},
  "geometry": {"coordinates":[-73.773933,42.707119],"type":"Point"}
}