{
  "type": "Feature",
  "properties": {
    "iso:country":"US",
    "sg:address":"414 E 89th St Bsmt",
    "sg:city":"New York",
    "sg:classifiers":[
        {
            "category":"Building & Trades",
            "subcategory":"Construction",
            "type":"Services"
        }
    ],
    "sg:phone":"+1 212 722 7312",
    "sg:postcode":"10128",
    "sg:province":"NY",
    "sg:tags":[
        "painter"
    ],
    "wof:name":"Thomas Lent Painting Co Inc",
    "wof:placetype":"venue"
},
  "geometry": {"coordinates":[-73.947701,40.7785],"type":"Point"}
}