{
  "type": "Feature",
  "properties": {
    "iso:country":"US",
    "sg:address":"281 Main St",
    "sg:city":"Cornwall",
    "sg:classifiers":[
        {
            "category":"Retail",
            "subcategory":"Animal Services",
            "type":"Services"
        }
    ],
    "sg:phone":"+1 845 534 0500",
    "sg:postcode":"12518",
    "sg:province":"NY",
    "sg:tags":[
        "pet",
        "grooming",
        "washing"
    ],
    "wof:name":"Stephanie's Doggie Boutique",
    "wof:placetype":"venue"
},
  "geometry": {"coordinates":[-74.033243,41.435557],"type":"Point"}
}