{
  "type": "Feature",
  "properties": {
    "iso:country":"US",
    "sg:address":"272 Glasco Tpke",
    "sg:city":"Saugerties",
    "sg:classifiers":[
        {
            "category":"Professional",
            "subcategory":"Business Services",
            "type":"Services"
        }
    ],
    "sg:phone":"+1 845 246 4067",
    "sg:postcode":"12477",
    "sg:province":"NY",
    "sg:tags":[
        "trust",
        "nonprofit",
        "management"
    ],
    "wof:name":"League of Women Voters of",
    "wof:placetype":"venue"
},
  "geometry": {"coordinates":[-73.957151,42.043115],"type":"Point"}
}