{
  "type": "Feature",
  "properties": {
    "iso:country":"US",
    "sg:address":"8136 Oswego Rd",
    "sg:city":"Liverpool",
    "sg:classifiers":[
        {
            "category":"Health Services",
            "subcategory":"Doctor",
            "type":"Services"
        }
    ],
    "sg:phone":"+1 315 652 8474",
    "sg:postcode":"13090",
    "sg:province":"NY",
    "sg:tags":[
        "clinic"
    ],
    "wof:name":"Seneca Hemodialysis",
    "wof:placetype":"venue"
},
  "geometry": {"coordinates":[-76.236203,43.163948],"type":"Point"}
}