{
  "type": "Feature",
  "properties": {
    "addr:full":"1520 E 13th St Brooklyn NY 11230",
    "addr:housenumber":"1520",
    "addr:postcode":"11230",
    "addr:street":"E 13Th St",
    "iso:country":"US",
    "sg:address":"1520 E 13th St",
    "sg:city":"Brooklyn",
    "sg:classifiers":[
        {
            "category":"Organizations",
            "subcategory":"Membership Organization",
            "type":"Services"
        }
    ],
    "sg:phone":"+1 718 382 0142",
    "sg:postcode":"11230",
    "sg:province":"NY",
    "wof:name":"New Brooklyn Society-The Df",
    "wof:placetype":"venue"
},
  "geometry": {"coordinates":[-73.96059099999999,40.610702],"type":"Point"}
}