{
  "type": "Feature",
  "properties": {
    "addr:full":"4250 Broadway New York NY 10033",
    "addr:housenumber":"4250",
    "addr:postcode":"10033",
    "addr:street":"Broadway",
    "iso:country":"US",
    "sg:address":"4250 Broadway",
    "sg:city":"New York",
    "sg:classifiers":[
        {
            "category":"Food & Beverages",
            "subcategory":"Meat & Fish",
            "type":"Retail Goods"
        }
    ],
    "sg:phone":"+1 212 923 1600",
    "sg:postcode":"10033",
    "sg:province":"NY",
    "sg:tags":[
        "seafood",
        "market"
    ],
    "wof:name":"Discount Fish Market",
    "wof:placetype":"venue"
},
  "geometry": {"coordinates":[-73.93589799999999,40.8498],"type":"Point"}
}