{
  "type": "Feature",
  "properties": {
    "iso:country":"US",
    "sg:address":"3000 Marcus Ave Ste 1W5",
    "sg:city":"New Hyde Park",
    "sg:classifiers":[
        {
            "category":"Professional",
            "subcategory":"Accounting & Tax Preparation",
            "type":"Services"
        }
    ],
    "sg:phone":"+1 516 352 7297",
    "sg:postcode":"11042",
    "sg:province":"NY",
    "sg:tags":[
        "accountant"
    ],
    "wof:name":"Moses & Schreiber",
    "wof:placetype":"venue"
},
  "geometry": {"coordinates":[-73.709999,40.7589],"type":"Point"}
}