{
  "type": "Feature",
  "properties": {
    "addr:full":"116 Wilson Ave Apt 2 Endicott NY 13760",
    "addr:housenumber":"116;2",
    "addr:postcode":"13760",
    "addr:street":"Wilson Ave Apt",
    "iso:country":"US",
    "sg:address":"116 Wilson Ave Apt 2",
    "sg:city":"Endicott",
    "sg:classifiers":[
        {
            "category":"Retail",
            "subcategory":"Laundry & Dry Cleaning",
            "type":"Services"
        },
        {
            "category":"Building & Trades",
            "subcategory":"Cleaning & Sanitation",
            "type":"Services"
        }
    ],
    "sg:phone":"+1 607 754 8835",
    "sg:postcode":"13760",
    "sg:province":"NY",
    "sg:tags":[
        "cleaner",
        "carpet",
        "rug",
        "janitorial"
    ],
    "wof:name":"Tri Cities Carpet Care & Janitorial Services",
    "wof:placetype":"venue"
},
  "geometry": {"coordinates":[-76.035875,42.110025],"type":"Point"}
}