{
  "type": "Feature",
  "properties": {
    "addr:full":"24 45th St Astoria NY 11103",
    "addr:housenumber":"24",
    "addr:postcode":"11103",
    "addr:street":"45Th St",
    "iso:country":"US",
    "sg:address":"24 45th St",
    "sg:city":"Astoria",
    "sg:classifiers":[
        {
            "category":"Home & Garden",
            "subcategory":"Home Furnishings",
            "type":"Retail Goods"
        }
    ],
    "sg:phone":"+1   ",
    "sg:postcode":"11103",
    "sg:province":"NY",
    "wof:name":"Gelb Lighting Inc",
    "wof:placetype":"venue"
},
  "geometry": {"coordinates":[-73.911227,40.761963],"type":"Point"}
}