{
  "type": "Feature",
  "properties": {
    "addr:full":"276 Long Island Ave Wyandanch NY 11798",
    "addr:housenumber":"276",
    "addr:postcode":"11798",
    "addr:street":"Long Island Ave",
    "iso:country":"US",
    "sg:address":"276 Long Island Ave",
    "sg:city":"Wyandanch",
    "sg:classifiers":[
        {
            "category":"Wholesale",
            "subcategory":"Auto Parts",
            "type":"Manufacturing & Wholesale Goods"
        }
    ],
    "sg:phone":"+1 631 643 9700",
    "sg:postcode":"11798",
    "sg:province":"NY",
    "sg:tags":[
        "equipment",
        "towing"
    ],
    "sg:website":"www.weldbuilt.com",
    "wof:name":"Weld-Built Body Co",
    "wof:placetype":"venue"
},
  "geometry": {"coordinates":[-73.363677,40.753316],"type":"Point"}
}