{
  "type": "Feature",
  "properties": {
    "addr:full":"171 53rd St Brooklyn NY 11232",
    "addr:housenumber":"171",
    "addr:postcode":"11232",
    "addr:street":"53Rd St",
    "iso:country":"US",
    "sg:address":"171 53rd St",
    "sg:city":"Brooklyn",
    "sg:classifiers":[
        {
            "category":"Professional",
            "type":"Services"
        }
    ],
    "sg:phone":"+1 718 439 1044",
    "sg:postcode":"11232",
    "sg:province":"NY",
    "sg:tags":[
        "establishment"
    ],
    "wof:name":"Judaica Maven",
    "wof:placetype":"venue"
},
  "geometry": {"coordinates":[-74.01963600000001,40.64785],"type":"Point"}
}