{
  "type": "Feature",
  "properties": {
    "iso:country":"US",
    "sg:address":"43 Kisco Ave",
    "sg:city":"Mt Kisco",
    "sg:classifiers":[
        {
            "category":"Wholesale",
            "subcategory":"Durable Goods & Equipment",
            "type":"Manufacturing & Wholesale Goods"
        }
    ],
    "sg:phone":"+1 914 244 9111",
    "sg:postcode":"10549",
    "sg:province":"NY",
    "sg:tags":[
        "representative",
        "manufacturer"
    ],
    "wof:name":"Schwarz & Schwarz Assoc",
    "wof:placetype":"venue"
},
  "geometry": {"coordinates":[-73.728244,41.210854],"type":"Point"}
}