{
  "type": "Feature",
  "properties": {
    "iso:country":"US",
    "sg:address":"353 Fairport Rd",
    "sg:city":"East Rochester",
    "sg:classifiers":[
        {
            "category":"Insurance",
            "subcategory":"Insurance Agent",
            "type":"Services"
        }
    ],
    "sg:phone":"+1 585 264 9610",
    "sg:postcode":"14445",
    "sg:province":"NY",
    "wof:name":"Met Life",
    "wof:placetype":"venue"
},
  "geometry": {"coordinates":[-77.487632,43.104435],"type":"Point"}
}