{
  "type": "Feature",
  "properties": {
    "iso:country":"US",
    "sg:address":"175 Garretson Ave",
    "sg:city":"Staten Island",
    "sg:classifiers":[
        {
            "category":"Food & Beverages",
            "subcategory":"Groceries & Convenience Stores",
            "type":"Retail Goods"
        }
    ],
    "sg:phone":"+1 718 351 0662",
    "sg:postcode":"10305",
    "sg:province":"NY",
    "sg:tags":[
        "grocer"
    ],
    "wof:name":"Miceli's Supermarket",
    "wof:placetype":"venue"
},
  "geometry": {"coordinates":[-74.095826,40.589227],"type":"Point"}
}