{
  "type": "Feature",
  "properties": {
    "addr:full":"14 Washington Pl New York NY 10003",
    "addr:housenumber":"14",
    "addr:postcode":"10003",
    "addr:street":"Washington Pl",
    "iso:country":"US",
    "sg:address":"14 Washington Pl",
    "sg:city":"New York",
    "sg:classifiers":[
        {
            "category":"Arts & Performance",
            "subcategory":"Arts Center",
            "type":"Entertainment"
        },
        {
            "category":"Education",
            "subcategory":"School",
            "type":"Public Place"
        }
    ],
    "sg:phone":"+1 212 777 3232",
    "sg:postcode":"10003",
    "sg:province":"NY",
    "sg:tags":[
        "performing"
    ],
    "sg:website":"www.skateguru.com",
    "wof:name":"Lezly Escate School",
    "wof:placetype":"venue"
},
  "geometry": {"coordinates":[-73.995102,40.729698],"type":"Point"}
}