{
  "type": "Feature",
  "properties": {
    "addr:full":"2252 George Urban Blvd Depew NY 14043",
    "addr:housenumber":"2252",
    "addr:postcode":"14043",
    "addr:street":"George Urban Blvd",
    "iso:country":"US",
    "sg:address":"2252 George Urban Blvd",
    "sg:city":"Depew",
    "sg:classifiers":[
        {
            "category":"Professional",
            "subcategory":"Art Services",
            "type":"Services"
        }
    ],
    "sg:phone":"+1 716 683 7009",
    "sg:postcode":"14043",
    "sg:province":"NY",
    "sg:tags":[
        "photographer"
    ],
    "wof:name":"M M Impressions Photography",
    "wof:placetype":"venue"
},
  "geometry": {"coordinates":[-78.72848399999999,42.918804],"type":"Point"}
}