{
  "type": "Feature",
  "properties": {
    "iso:country":"US",
    "sg:address":"107 Mountain Rest Rd",
    "sg:city":"New Paltz",
    "sg:classifiers":[
        {
            "category":"Wholesale",
            "subcategory":"Plants",
            "type":"Manufacturing & Wholesale Goods"
        }
    ],
    "sg:phone":"+1 845 255 1245",
    "sg:postcode":"12561",
    "sg:province":"NY",
    "sg:tags":[
        "supply"
    ],
    "wof:name":"Ruslyn Nursery",
    "wof:placetype":"venue"
},
  "geometry": {"coordinates":[-74.11541699999999,41.759395],"type":"Point"}
}