{
  "type": "Feature",
  "properties": {
    "iso:country":"US",
    "sg:address":"657 W Ferry St",
    "sg:city":"Buffalo",
    "sg:classifiers":[
        {
            "category":"Health Services",
            "subcategory":"Doctor",
            "type":"Services"
        }
    ],
    "sg:phone":"+1 716 882 3956",
    "sg:postcode":"14222",
    "sg:province":"NY",
    "wof:name":"Hafezi Bijan MD",
    "wof:placetype":"venue"
},
  "geometry": {"coordinates":[-78.87539700000001,42.915501],"type":"Point"}
}