{
  "type": "Feature",
  "properties": {
    "addr:full":"43 Clay Hill Rd Hoosick Falls NY 12090",
    "addr:housenumber":"43",
    "addr:postcode":"12090",
    "addr:street":"Clay Hill Rd",
    "iso:country":"US",
    "sg:address":"43 Clay Hill Rd",
    "sg:city":"Hoosick Falls",
    "sg:classifiers":[
        {
            "category":"Shopping",
            "subcategory":"Books",
            "type":"Retail Goods"
        }
    ],
    "sg:phone":"+1   ",
    "sg:postcode":"12090",
    "sg:province":"NY",
    "wof:name":"Good Reason Computers",
    "wof:placetype":"venue"
},
  "geometry": {"coordinates":[-73.418954,42.901909],"type":"Point"}
}