{
  "type": "Feature",
  "properties": {
    "addr:full":"5 Medical Park Dr Pomona NY 10970",
    "addr:housenumber":"5",
    "addr:postcode":"10970",
    "addr:street":"Medical Park Dr",
    "iso:country":"US",
    "sg:address":"5 Medical Park Dr",
    "sg:city":"Pomona",
    "sg:classifiers":[
        {
            "category":"Health Services",
            "subcategory":"Dentist",
            "type":"Services"
        }
    ],
    "sg:phone":"+1 845 354 1655",
    "sg:postcode":"10970",
    "sg:province":"NY",
    "sg:tags":[
        "dentists-orthodontists",
        "dentists-cosmetic",
        "dentists-pediatric",
        "dentistry"
    ],
    "wof:name":"Pomona Sethi Dental Pllc",
    "wof:placetype":"venue"
},
  "geometry": {"coordinates":[-74.0338,41.16698],"type":"Point"}
}