{
  "type": "Feature",
  "properties": {
    "addr:full":"6186 S Transit Rd Lockport NY 14094",
    "addr:housenumber":"6186",
    "addr:postcode":"14094",
    "addr:street":"S Transit Rd",
    "iso:country":"US",
    "sg:address":"6186 S Transit Rd",
    "sg:city":"Lockport",
    "sg:classifiers":[
        {
            "category":"Manufacturing",
            "subcategory":"Metals",
            "type":"Manufacturing & Wholesale Goods"
        }
    ],
    "sg:phone":"+1 716 625 4068",
    "sg:postcode":"14094",
    "sg:province":"NY",
    "sg:tags":[
        "treating",
        "heat"
    ],
    "wof:name":"Frey's Tasty Treat Inc",
    "wof:placetype":"venue"
},
  "geometry": {"coordinates":[-78.696884,43.128762],"type":"Point"}
}