{
  "type": "Feature",
  "properties": {
    "iso:country":"US",
    "sg:address":"224 Church Ave",
    "sg:city":"Ballston Spa",
    "sg:classifiers":[
        {
            "category":"Banks & Credit Unions",
            "subcategory":"Bank",
            "type":"Services"
        }
    ],
    "sg:phone":"+1 518 884 7313",
    "sg:postcode":"12020",
    "sg:province":"NY",
    "wof:name":"Adirondack Trust Co",
    "wof:placetype":"venue"
},
  "geometry": {"coordinates":[-73.850746,42.992419],"type":"Point"}
}