{
  "type": "Feature",
  "properties": {
    "addr:full":"247 Cayuga Rd Cheektowaga NY 14225",
    "addr:housenumber":"247",
    "addr:postcode":"14225",
    "addr:street":"Cayuga Rd",
    "iso:country":"US",
    "sg:address":"247 Cayuga Rd",
    "sg:city":"Cheektowaga",
    "sg:classifiers":[
        {
            "category":"Organizations",
            "subcategory":"Non-profit Organization",
            "type":"Services"
        }
    ],
    "sg:phone":"+1 716 681 7394",
    "sg:postcode":"14225",
    "sg:province":"NY",
    "sg:tags":[
        "charitable",
        "institution"
    ],
    "wof:name":"Catholic Charities-Buffalo",
    "wof:placetype":"venue"
},
  "geometry": {"coordinates":[-78.744371,42.941441],"type":"Point"}
}