{
  "type": "Feature",
  "properties": {
    "iso:country":"US",
    "sg:address":"1804 W Seamans Neck Rd",
    "sg:city":"Seaford",
    "sg:classifiers":[
        {
            "category":"Restaurant",
            "type":"Food & Drink"
        }
    ],
    "sg:phone":"+1   ",
    "sg:postcode":"11783",
    "sg:province":"NY",
    "sg:tags":[
        "eating"
    ],
    "wof:name":"Drop Dead Comedy",
    "wof:placetype":"venue"
},
  "geometry": {"coordinates":[-73.495734,40.680416],"type":"Point"}
}