{
  "type": "Feature",
  "properties": {
    "iso:country":"US",
    "sg:address":"955 E 163rd St",
    "sg:city":"Bronx",
    "sg:classifiers":[
        {
            "category":"Building & Trades",
            "subcategory":"Cleaning & Sanitation",
            "type":"Services"
        },
        {
            "category":"Building & Trades",
            "subcategory":"Construction",
            "type":"Services"
        }
    ],
    "sg:phone":"+1 718 328 6312",
    "sg:postcode":"10459",
    "sg:province":"NY",
    "sg:tags":[
        "plumbing",
        "maintenance",
        "contractor"
    ],
    "wof:name":"Triboro Maintenance Corp",
    "wof:placetype":"venue"
},
  "geometry": {"coordinates":[-73.895403,40.821354],"type":"Point"}
}