{
  "type": "Feature",
  "properties": {
    "iso:country":"US",
    "sg:address":"3170 Erie Blvd E",
    "sg:city":"De Witt",
    "sg:classifiers":[
        {
            "category":"Retail",
            "subcategory":"Car Wash",
            "type":"Services"
        }
    ],
    "sg:phone":"+1 315 449 1457",
    "sg:postcode":"13214",
    "sg:province":"NY",
    "sg:tags":[
        "polishing",
        "washing"
    ],
    "wof:name":"Clearwater Car Wash & Detail",
    "wof:placetype":"venue"
},
  "geometry": {"coordinates":[-76.07146899999999,43.049617],"type":"Point"}
}