{
  "type": "Feature",
  "properties": {
    "addr:full":"3787 Broadway New York NY 10032",
    "addr:housenumber":"3787",
    "addr:postcode":"10032",
    "addr:street":"Broadway",
    "iso:country":"US",
    "sg:address":"3787 Broadway",
    "sg:city":"New York",
    "sg:classifiers":[
        {
            "category":"Food & Beverages",
            "subcategory":"Specialty",
            "type":"Retail Goods"
        }
    ],
    "sg:phone":"+1 212 234 0562",
    "sg:postcode":"10032",
    "sg:province":"NY",
    "sg:tags":[
        "beauty",
        "health",
        "cosmetic",
        "diet",
        "supply"
    ],
    "wof:name":"Beauty Supply & Health Food Corp",
    "wof:placetype":"venue"
},
  "geometry": {"coordinates":[-73.945297,40.8339],"type":"Point"}
}