{
  "type": "Feature",
  "properties": {
    "iso:country":"US",
    "sg:address":"614 Kenmore Ave",
    "sg:city":"Copiague",
    "sg:classifiers":[
        {
            "category":"Building & Trades",
            "subcategory":"Landscaping Services",
            "type":"Services"
        }
    ],
    "sg:phone":"+1 631 789 0659",
    "sg:postcode":"11726",
    "sg:province":"NY",
    "sg:tags":[
        "landscape"
    ],
    "wof:name":"Long Island Landscape Designs",
    "wof:placetype":"venue"
},
  "geometry": {"coordinates":[-73.39798,40.67018],"type":"Point"}
}