{
  "type": "Feature",
  "properties": {
    "iso:country":"US",
    "sg:address":"100 Raynor Ave",
    "sg:city":"Ronkonkoma",
    "sg:classifiers":[
        {
            "category":"Building & Trades",
            "subcategory":"Construction",
            "type":"Services"
        }
    ],
    "sg:phone":"+1 631 471 1256",
    "sg:postcode":"11779",
    "sg:province":"NY",
    "sg:tags":[
        "dry wall",
        "contractor"
    ],
    "wof:name":"Aurora Contractors Inc",
    "wof:placetype":"venue"
},
  "geometry": {"coordinates":[-73.113602,40.8018],"type":"Point"}
}