{
  "type": "Feature",
  "properties": {
    "iso:country":"US",
    "sg:address":"167 Thompson St",
    "sg:city":"New York",
    "sg:classifiers":[
        {
            "category":"Recreation",
            "type":"Entertainment"
        }
    ],
    "sg:phone":"+1   ",
    "sg:postcode":"10012",
    "sg:province":"NY",
    "wof:name":"Vision of Tibet",
    "wof:placetype":"venue"
},
  "geometry": {"coordinates":[-73.99985,40.728293],"type":"Point"}
}