{
  "type": "Feature",
  "properties": {
    "addr:full":"8620 18th Ave Brooklyn NY 11214",
    "addr:housenumber":"8620",
    "addr:postcode":"11214",
    "addr:street":"18Th Ave",
    "iso:country":"US",
    "sg:address":"8620 18th Ave",
    "sg:city":"Brooklyn",
    "sg:classifiers":[
        {
            "category":"Health Services",
            "subcategory":"Hospital",
            "type":"Services"
        }
    ],
    "sg:phone":"+1 718 232 3697",
    "sg:postcode":"11214",
    "sg:province":"NY",
    "sg:tags":[
        "mental"
    ],
    "wof:name":"Bensonhurst Mental Health Clnc",
    "wof:placetype":"venue"
},
  "geometry": {"coordinates":[-74.004183,40.60599],"type":"Point"}
}