{
  "type": "Feature",
  "properties": {
    "addr:full":"235 E 22nd St New York NY 10010",
    "addr:housenumber":"235",
    "addr:postcode":"10010",
    "addr:street":"E 22Nd St",
    "iso:country":"US",
    "sg:address":"235 E 22nd St",
    "sg:city":"New York",
    "sg:classifiers":[
        {
            "category":"Health Services",
            "subcategory":"Dentist",
            "type":"Services"
        }
    ],
    "sg:phone":"+1 212 532 3636",
    "sg:postcode":"10010",
    "sg:province":"NY",
    "wof:name":"Deblinger Jason",
    "wof:placetype":"venue"
},
  "geometry": {"coordinates":[-73.98275700000001,40.737962],"type":"Point"}
}