{
  "type": "Feature",
  "properties": {
    "addr:full":"10 Vernon Pl Mt Vernon NY 10552",
    "addr:housenumber":"10",
    "addr:postcode":"10552",
    "addr:street":"Vernon Pl",
    "iso:country":"US",
    "sg:address":"10 Vernon Pl",
    "sg:city":"Mt Vernon",
    "sg:classifiers":[
        {
            "category":"Social Services",
            "subcategory":"Child Care",
            "type":"Services"
        }
    ],
    "sg:phone":"+1 914 668 4503",
    "sg:postcode":"10552",
    "sg:province":"NY",
    "wof:name":"Eagle Daycare",
    "wof:placetype":"venue"
},
  "geometry": {"coordinates":[-73.829201,40.922449],"type":"Point"}
}