{
  "type": "Feature",
  "properties": {
    "addr:full":"20 Hawley St Binghamton NY 13901",
    "addr:housenumber":"20",
    "addr:postcode":"13901",
    "addr:street":"Hawley St",
    "iso:country":"US",
    "sg:address":"20 Hawley St",
    "sg:city":"Binghamton",
    "sg:classifiers":[
        {
            "category":"Professional",
            "subcategory":"Lawyer & Legal Services",
            "type":"Services"
        }
    ],
    "sg:phone":"+1   ",
    "sg:postcode":"13901",
    "sg:province":"NY",
    "wof:name":"Feyi Gaji",
    "wof:placetype":"venue"
},
  "geometry": {"coordinates":[-75.91283300000001,42.097062],"type":"Point"}
}