{
  "type": "Feature",
  "properties": {
    "iso:country":"US",
    "sg:address":"4 Lamarcus Ave",
    "sg:city":"Glen Cove",
    "sg:classifiers":[
        {
            "category":"Building & Trades",
            "subcategory":"Landscaping Services",
            "type":"Services"
        }
    ],
    "sg:phone":"+1 516 674 9303",
    "sg:postcode":"11542",
    "sg:province":"NY",
    "sg:tags":[
        "landscape"
    ],
    "wof:name":"Pink Flower Landscaping",
    "wof:placetype":"venue"
},
  "geometry": {"coordinates":[-73.634516,40.852378],"type":"Point"}
}