{
  "type": "Feature",
  "properties": {
    "addr:full":"29 Prince St New York NY 10012",
    "addr:housenumber":"29",
    "addr:postcode":"10012",
    "addr:street":"Prince St",
    "iso:country":"US",
    "sg:address":"29 Prince St",
    "sg:city":"New York",
    "sg:classifiers":[
        {
            "category":"Shopping",
            "subcategory":"Clothing, Apparel, & Fashions",
            "type":"Retail Goods"
        }
    ],
    "sg:phone":"+1 212 334 3006",
    "sg:postcode":"10012",
    "sg:province":"NY",
    "sg:tags":[
        "clothing",
        "women's"
    ],
    "sg:website":"www.bio-nyc.com",
    "wof:name":"Bio Emerging Designers",
    "wof:placetype":"venue"
},
  "geometry": {"coordinates":[-73.994618,40.723112],"type":"Point"}
}