{
  "type": "Feature",
  "properties": {
    "iso:country":"US",
    "sg:address":"153 Academy St",
    "sg:city":"Poughkeepsie",
    "sg:classifiers":[
        {
            "category":"Health Services",
            "subcategory":"Doctor",
            "type":"Services"
        }
    ],
    "sg:phone":"+1 845 454 0560",
    "sg:postcode":"12601",
    "sg:province":"NY",
    "sg:tags":[
        "dentist"
    ],
    "wof:name":"Nizam Jabbour DDS",
    "wof:placetype":"venue"
},
  "geometry": {"coordinates":[-73.92841799999999,41.695772],"type":"Point"}
}