{
  "type": "Feature",
  "properties": {
    "iso:country":"US",
    "sg:address":"62 Bethpage Rd",
    "sg:city":"Hicksville",
    "sg:classifiers":[
        {
            "category":"Wholesale",
            "subcategory":"Groceries",
            "type":"Manufacturing & Wholesale Goods"
        }
    ],
    "sg:phone":"+1 516 935 3404",
    "sg:postcode":"11801",
    "sg:province":"NY",
    "sg:tags":[
        "confectionery",
        "candy"
    ],
    "wof:name":"American International Cncssn",
    "wof:placetype":"venue"
},
  "geometry": {"coordinates":[-73.52077,40.774299],"type":"Point"}
}