{
  "type": "Feature",
  "properties": {
    "iso:country":"US",
    "sg:address":"250 W 39th St Rm 1602",
    "sg:city":"New York",
    "sg:classifiers":[
        {
            "category":"Shopping",
            "subcategory":"Clothing, Apparel, & Fashions",
            "type":"Retail Goods"
        }
    ],
    "sg:phone":"+1 212 278 8686",
    "sg:postcode":"10018",
    "sg:province":"NY",
    "sg:tags":[
        "accessory",
        "clothing",
        "women's"
    ],
    "wof:name":"Sobgn",
    "wof:placetype":"venue"
},
  "geometry": {"coordinates":[-73.989752,40.754733],"type":"Point"}
}