{
  "type": "Feature",
  "properties": {
    "addr:full":"1190 Old Country Rd Riverhead NY 11901",
    "addr:housenumber":"1190",
    "addr:postcode":"11901",
    "addr:street":"Old Country Rd",
    "iso:country":"US",
    "sg:address":"1190 Old Country Rd",
    "sg:city":"Riverhead",
    "sg:classifiers":[
        {
            "category":"Health Services",
            "subcategory":"Doctor",
            "type":"Services"
        }
    ],
    "sg:phone":"+1 631 727 1818",
    "sg:postcode":"11901",
    "sg:province":"NY",
    "wof:name":"Dempsey Michael W MD",
    "wof:placetype":"venue"
},
  "geometry": {"coordinates":[-72.683296,40.9291],"type":"Point"}
}