{
  "type": "Feature",
  "properties": {
    "iso:country":"US",
    "sg:address":"20 S Station Plz",
    "sg:city":"Great Neck",
    "sg:classifiers":[
        {
            "category":"Restaurant",
            "type":"Food & Drink"
        }
    ],
    "sg:phone":"+1 516 487 9700",
    "sg:postcode":"11021",
    "sg:province":"NY",
    "wof:name":"Magic Cook Inc",
    "wof:placetype":"venue"
},
  "geometry": {"coordinates":[-73.725533,40.7871],"type":"Point"}
}