{
  "type": "Feature",
  "properties": {
    "addr:full":"33 E 17 St New York NY 10003",
    "addr:housenumber":"33;17",
    "addr:postcode":"10003",
    "addr:street":"E;St",
    "iso:country":"US",
    "sg:address":"33 E 17 St",
    "sg:city":"New York",
    "sg:classifiers":[
        {
            "category":"Retail",
            "subcategory":"Photofinishing",
            "type":"Services"
        }
    ],
    "sg:phone":"+1 212 242 8787",
    "sg:postcode":"10003",
    "sg:province":"NY",
    "sg:tags":[
        "photo"
    ],
    "wof:name":"Graphic Systems Group",
    "wof:placetype":"venue"
},
  "geometry": {"coordinates":[-73.989062,40.736643],"type":"Point"}
}