{
  "type": "Feature",
  "properties": {
    "addr:full":"301 W 215th St New York NY 10034",
    "addr:housenumber":"301",
    "addr:postcode":"10034",
    "addr:street":"W 215Th St",
    "iso:country":"US",
    "sg:address":"301 W 215th St",
    "sg:city":"New York",
    "sg:classifiers":[
        {
            "category":"Government",
            "subcategory":"Office",
            "type":"Public Place"
        }
    ],
    "sg:phone":"+1 212 567 4600",
    "sg:postcode":"10034",
    "sg:province":"NY",
    "sg:tags":[
        "city",
        "program"
    ],
    "wof:name":"New York City Sanitation Dept",
    "wof:placetype":"venue"
},
  "geometry": {"coordinates":[-73.913352,40.868777],"type":"Point"}
}