{
  "type": "Feature",
  "properties": {
    "addr:full":"4200 Hutchinson River Pkwy E Bronx NY 10475",
    "addr:housenumber":"4200",
    "addr:postcode":"10475",
    "addr:street":"Hutchinson River Pkwy E",
    "iso:country":"US",
    "sg:address":"4200 Hutchinson River Pkwy E",
    "sg:city":"Bronx",
    "sg:classifiers":[
        {
            "category":"Organizations",
            "subcategory":"Religious Organization",
            "type":"Services"
        }
    ],
    "sg:phone":"+1 718 320 1331",
    "sg:postcode":"10475",
    "sg:province":"NY",
    "sg:tags":[
        "clergy"
    ],
    "wof:name":"Calvin Owens",
    "wof:placetype":"venue"
},
  "geometry": {"coordinates":[-73.82272500000001,40.866222],"type":"Point"}
}