{
  "type": "Feature",
  "properties": {
    "iso:country":"US",
    "sg:address":"102 Gleneida Ave",
    "sg:city":"Carmel",
    "sg:classifiers":[
        {
            "category":"Professional",
            "subcategory":"Lawyer & Legal Services",
            "type":"Services"
        }
    ],
    "sg:phone":"+1 845 225 8404",
    "sg:postcode":"10512",
    "sg:province":"NY",
    "sg:website":"www.danielsporco.com",
    "wof:name":"Daniels & Porco Llp Atty",
    "wof:placetype":"venue"
},
  "geometry": {"coordinates":[-73.679497,41.429798],"type":"Point"}
}