{
  "type": "Feature",
  "properties": {
    "iso:country":"US",
    "sg:address":"2224 Mt Hope Rd",
    "sg:city":"Middletown",
    "sg:classifiers":[
        {
            "category":"Sports & Exercise",
            "subcategory":"Gym",
            "type":"Entertainment"
        }
    ],
    "sg:phone":"+1 845 386 1496",
    "sg:postcode":"10940",
    "sg:province":"NY",
    "sg:tags":[
        "club",
        "health",
        "studio",
        "gymnasium"
    ],
    "wof:name":"M Fitness",
    "wof:placetype":"venue"
},
  "geometry": {"coordinates":[-74.517319,41.445194],"type":"Point"}
}