{
  "type": "Feature",
  "properties": {
    "addr:full":"33 Mulligan Ln Irvington NY 10533",
    "addr:housenumber":"33",
    "addr:postcode":"ny 10533",
    "addr:street":"Mulligan Ln",
    "iso:country":"US",
    "sg:address":"33 Mulligan Ln",
    "sg:city":"Irvington",
    "sg:classifiers":[
        {
            "category":"Retail",
            "subcategory":"Laundry & Dry Cleaning",
            "type":"Services"
        }
    ],
    "sg:phone":"+1 203 324 1744",
    "sg:postcode":"10533",
    "sg:province":"NY",
    "sg:tags":[
        "cleaner",
        "commercial"
    ],
    "wof:name":"Magic Touch",
    "wof:placetype":"venue"
},
  "geometry": {"coordinates":[-73.844041,41.046349],"type":"Point"}
}