{
  "type": "Feature",
  "properties": {
    "iso:country":"US",
    "sg:address":"903 W State St",
    "sg:city":"Olean",
    "sg:classifiers":[
        {
            "category":"Restaurant",
            "type":"Food & Drink"
        }
    ],
    "sg:menulink":"http://www.allmenus.com/ny/olean/211388-kfc---kentucky-fried-chicken/menu/",
    "sg:phone":"+1 716 372 7239",
    "sg:postcode":"14760",
    "sg:province":"NY",
    "sg:tags":[
        "american",
        "chicken"
    ],
    "wof:name":"KFC - Kentucky Fried Chicken",
    "wof:placetype":"venue"
},
  "geometry": {"coordinates":[-78.44017100000001,42.07715],"type":"Point"}
}