{
  "type": "Feature",
  "properties": {
    "addr:full":"76 Sand Ln Staten Island NY 10305",
    "addr:housenumber":"76",
    "addr:postcode":"10305",
    "addr:street":"Sand Ln",
    "iso:country":"US",
    "sg:address":"76 Sand Ln",
    "sg:city":"Staten Island",
    "sg:classifiers":[
        {
            "category":"Organizations",
            "subcategory":"Religious Organization",
            "type":"Services"
        }
    ],
    "sg:phone":"+1 718 984 6060",
    "sg:postcode":"10305",
    "sg:province":"NY",
    "sg:tags":[
        "clergy"
    ],
    "wof:name":"F Schraplau",
    "wof:placetype":"venue"
},
  "geometry": {"coordinates":[-74.071134,40.597383],"type":"Point"}
}