{
  "type": "Feature",
  "properties": {
    "iso:country":"US",
    "sg:address":"319 Park Ave",
    "sg:city":"Mechanicville",
    "sg:classifiers":[
        {
            "category":"Retail",
            "subcategory":"Funeral Services",
            "type":"Services"
        }
    ],
    "sg:phone":"+1 518 664 3731",
    "sg:postcode":"12118",
    "sg:province":"NY",
    "sg:tags":[
        "director"
    ],
    "wof:name":"Dunn Funeral Homes Inc",
    "wof:placetype":"venue"
},
  "geometry": {"coordinates":[-73.690545,42.903389],"type":"Point"}
}