{
  "type": "Feature",
  "properties": {
    "iso:country":"US",
    "sg:address":"912 Pulaski Hwy",
    "sg:city":"Goshen",
    "sg:classifiers":[
        {
            "category":"Wholesale",
            "subcategory":"Fruits & Vegetables",
            "type":"Manufacturing & Wholesale Goods"
        }
    ],
    "sg:phone":"+1 845 651 7870",
    "sg:postcode":"10924",
    "sg:province":"NY",
    "wof:name":"Myruski Farms Inc",
    "wof:placetype":"venue"
},
  "geometry": {"coordinates":[-74.39824900000001,41.340927],"type":"Point"}
}