{
  "type": "Feature",
  "properties": {
    "iso:country":"US",
    "sg:address":"18 Weeks St",
    "sg:city":"Blue Point",
    "sg:classifiers":[
        {
            "category":"Personal",
            "type":"Services"
        }
    ],
    "sg:phone":"+1 631 363 0036",
    "sg:postcode":"11715",
    "sg:province":"NY",
    "sg:tags":[
        "amuse",
        "therapist",
        "massage"
    ],
    "wof:name":"Blue Point Wellness Center",
    "wof:placetype":"venue"
},
  "geometry": {"coordinates":[-73.02558399999999,40.75355],"type":"Point"}
}