{
  "type": "Feature",
  "properties": {
    "iso:country":"US",
    "sg:address":"969 Westchester Ave",
    "sg:city":"Bronx",
    "sg:classifiers":[
        {
            "category":"Restaurant",
            "type":"Food & Drink"
        }
    ],
    "sg:phone":"+1 718 842 9504",
    "sg:postcode":"10459",
    "sg:province":"NY",
    "sg:tags":[
        "mexican"
    ],
    "wof:name":"San Marcus Inc Mexican Food",
    "wof:placetype":"venue"
},
  "geometry": {"coordinates":[-73.895422,40.822858],"type":"Point"}
}