{
  "type": "Feature",
  "properties": {
    "addr:full":"509 Madison Ave New York NY 10022",
    "addr:housenumber":"509",
    "addr:postcode":"10022",
    "addr:street":"Madison Ave",
    "iso:country":"US",
    "sg:address":"509 Madison Ave",
    "sg:city":"New York",
    "sg:classifiers":[
        {
            "category":"Real Estate",
            "subcategory":"Real Estate Agent",
            "type":"Services"
        }
    ],
    "sg:phone":"+1 212 753 1385",
    "sg:postcode":"10022",
    "sg:province":"NY",
    "wof:name":"Grosfeld Realty",
    "wof:placetype":"venue"
},
  "geometry": {"coordinates":[-73.974434,40.759203],"type":"Point"}
}