{
  "type": "Feature",
  "properties": {
    "iso:country":"US",
    "sg:address":"52 Citation Dr",
    "sg:city":"Henrietta",
    "sg:classifiers":[
        {
            "category":"Building & Trades",
            "subcategory":"Construction",
            "type":"Services"
        }
    ],
    "sg:phone":"+1 585 334 1849",
    "sg:postcode":"14467",
    "sg:province":"NY",
    "sg:tags":[
        "residential"
    ],
    "wof:name":"WRG Property Maintenance",
    "wof:placetype":"venue"
},
  "geometry": {"coordinates":[-77.607308,43.04142],"type":"Point"}
}