{
  "type": "Feature",
  "properties": {
    "addr:full":"2845 Forrest Hill Dr Auburn NY 13021",
    "addr:housenumber":"2845",
    "addr:postcode":"13021",
    "addr:street":"Forrest Hill Dr",
    "iso:country":"US",
    "sg:address":"2845 Forrest Hill Dr",
    "sg:city":"Auburn",
    "sg:classifiers":[
        {
            "category":"Organizations",
            "subcategory":"Religious Organization",
            "type":"Services"
        }
    ],
    "sg:phone":"+1 315 252 1233",
    "sg:postcode":"13021",
    "sg:province":"NY",
    "sg:tags":[
        "clergy"
    ],
    "wof:name":"J Burton Nusse",
    "wof:placetype":"venue"
},
  "geometry": {"coordinates":[-76.55115499999999,42.895325],"type":"Point"}
}