{
  "type": "Feature",
  "properties": {
    "addr:full":"459 Thieriot Avenue Bronx NY 10473",
    "addr:housenumber":"459",
    "addr:postcode":"10473",
    "addr:street":"Thieriot Avenue",
    "iso:country":"US",
    "sg:address":"459 Thieriot Avenue",
    "sg:city":"Bronx",
    "sg:classifiers":[
        {
            "category":"Organizations",
            "subcategory":"Religious Organization",
            "type":"Services"
        }
    ],
    "sg:phone":"+1 718 893 3271",
    "sg:postcode":"10473",
    "sg:province":"NY",
    "wof:name":"Bethel 2nd Christian Church Assemblies of God",
    "wof:placetype":"venue"
},
  "geometry": {"coordinates":[-73.86066700000001,40.81501],"type":"Point"}
}