{
  "type": "Feature",
  "properties": {
    "addr:full":"4168 Victory Blvd Ste A1115 Staten Island NY 10314",
    "addr:housenumber":"4168",
    "addr:postcode":"10314",
    "addr:street":"Victory Blvd Ste A1115",
    "iso:country":"US",
    "sg:address":"4168 Victory Blvd Ste A1115",
    "sg:city":"Staten Island",
    "sg:classifiers":[
        {
            "category":"Building & Trades",
            "subcategory":"Pest Control",
            "type":"Services"
        }
    ],
    "sg:phone":"+1 718 924 2408",
    "sg:postcode":"10314",
    "sg:province":"NY",
    "wof:name":"Ecochoice Bed Bug Control",
    "wof:placetype":"venue"
},
  "geometry": {"coordinates":[-74.192204,40.590599],"type":"Point"}
}