{
  "type": "Feature",
  "properties": {
    "addr:full":"724 Othello Ave Franklin Square NY 11010",
    "addr:housenumber":"724",
    "addr:postcode":"11010",
    "addr:street":"Othello Ave",
    "iso:country":"US",
    "sg:address":"724 Othello Ave",
    "sg:city":"Franklin Square",
    "sg:classifiers":[
        {
            "category":"Wholesale",
            "subcategory":"Durable Goods & Equipment",
            "type":"Manufacturing & Wholesale Goods"
        }
    ],
    "sg:phone":"+1 516 486 8728",
    "sg:postcode":"11010",
    "sg:province":"NY",
    "wof:name":"Quick College Supply",
    "wof:placetype":"venue"
},
  "geometry": {"coordinates":[-73.67393300000001,40.692094],"type":"Point"}
}