{
  "type": "Feature",
  "properties": {
    "addr:full":"730 Main St Poughkeepsie NY 12603",
    "addr:housenumber":"730",
    "addr:postcode":"12603",
    "addr:street":"Main St",
    "iso:country":"US",
    "sg:address":"730 Main St",
    "sg:city":"Poughkeepsie",
    "sg:classifiers":[
        {
            "category":"Shopping",
            "subcategory":"Music",
            "type":"Retail Goods"
        }
    ],
    "sg:phone":"+1 845 483 9402",
    "sg:postcode":"12603",
    "sg:province":"NY",
    "sg:tags":[
        "compact",
        "record",
        "disc",
        "tape"
    ],
    "wof:name":"Latino Mania Cd & Dvd 1",
    "wof:placetype":"venue"
},
  "geometry": {"coordinates":[-73.906592,41.697016],"type":"Point"}
}