{
  "type": "Feature",
  "properties": {
    "iso:country":"US",
    "name:eng_x_preferred":[
        "Simpson St"
    ],
    "wof:name":"Simpson St",
    "wof:placetype":"venue"
},
  "geometry": {"coordinates":[-73.893064,40.824073],"type":"Point"}
}