{
  "type": "Feature",
  "properties": {
    "addr:full":"55 Irving Ave Wyandanch NY 11798",
    "addr:housenumber":"55",
    "addr:postcode":"11798",
    "addr:street":"Irving Ave",
    "iso:country":"US",
    "sg:address":"55 Irving Ave",
    "sg:city":"Wyandanch",
    "sg:classifiers":[
        {
            "category":"Arts & Performance",
            "subcategory":"Theater",
            "type":"Entertainment"
        }
    ],
    "sg:phone":"+1   ",
    "sg:postcode":"11798",
    "sg:province":"NY",
    "sg:tags":[
        "gospel",
        "for"
    ],
    "wof:name":"Ettg",
    "wof:placetype":"venue"
},
  "geometry": {"coordinates":[-73.358315,40.750809],"type":"Point"}
}