{
  "type": "Feature",
  "properties": {
    "addr:full":"1212 Ave L Brooklyn NY 11230",
    "addr:housenumber":"1212",
    "addr:postcode":"11230",
    "addr:street":"Ave L",
    "iso:country":"US",
    "sg:address":"1212 Ave L",
    "sg:city":"Brooklyn",
    "sg:classifiers":[
        {
            "category":"Organizations",
            "subcategory":"Religious Organization",
            "type":"Services"
        }
    ],
    "sg:phone":"+1 718 252 3969",
    "sg:postcode":"11230",
    "sg:province":"NY",
    "sg:tags":[
        "insurance"
    ],
    "wof:name":"Mitnick Yitzchok",
    "wof:placetype":"venue"
},
  "geometry": {"coordinates":[-73.96241499999999,40.620109],"type":"Point"}
}