{
  "type": "Feature",
  "properties": {
    "addr:full":"104 Hillside Blvd New Hyde Park NY 11040",
    "addr:housenumber":"104",
    "addr:postcode":"11040",
    "addr:street":"Hillside Blvd;Park",
    "iso:country":"US",
    "sg:address":"104 Hillside Blvd",
    "sg:city":"New Hyde Park",
    "sg:classifiers":[
        {
            "category":"Building & Trades",
            "subcategory":"Construction",
            "type":"Services"
        }
    ],
    "sg:phone":"+1 516 326 6938",
    "sg:postcode":"11040",
    "sg:province":"NY",
    "sg:tags":[
        "painter"
    ],
    "wof:name":"Euro Finish",
    "wof:placetype":"venue"
},
  "geometry": {"coordinates":[-73.69209600000001,40.734012],"type":"Point"}
}