{
  "type": "Feature",
  "properties": {
    "addr:full":"330 E 39th Street New York NY 10016",
    "addr:housenumber":"330",
    "addr:postcode":"10016",
    "addr:street":"E 39Th Street",
    "iso:country":"US",
    "sg:address":"330 E 39th Street",
    "sg:city":"New York",
    "sg:classifiers":[
        {
            "category":"Retail",
            "subcategory":"Laundry & Dry Cleaning",
            "type":"Services"
        }
    ],
    "sg:phone":"+1 212 922 9488",
    "sg:postcode":"10016",
    "sg:province":"NY",
    "wof:name":"Valet At New Yorker",
    "wof:placetype":"venue"
},
  "geometry": {"coordinates":[-73.97264300000001,40.747482],"type":"Point"}
}