{
  "type": "Feature",
  "properties": {
    "addr:full":"94-06 63rd Dr Rego Park NY 11374",
    "addr:housenumber":"94-06",
    "addr:postcode":"11374",
    "addr:street":"63Rd Dr",
    "iso:country":"US",
    "sg:address":"94-06 63rd Dr",
    "sg:city":"Rego Park",
    "sg:classifiers":[
        {
            "category":"Food & Beverages",
            "subcategory":"Groceries & Convenience Stores",
            "type":"Retail Goods"
        }
    ],
    "sg:phone":"+1 718 520 0679",
    "sg:postcode":"11374",
    "sg:province":"NY",
    "sg:website":"www.metfoods.com",
    "wof:name":"Met Food Markets",
    "wof:placetype":"venue"
},
  "geometry": {"coordinates":[-73.86322800000001,40.728702],"type":"Point"}
}