{
  "type": "Feature",
  "properties": {
    "iso:country":"US",
    "sg:address":"46 Blind Creek Cir",
    "sg:city":"Henrietta",
    "sg:classifiers":[
        {
            "category":"Real Estate",
            "subcategory":"Real Estate Agent",
            "type":"Services"
        }
    ],
    "sg:phone":"+1 585 359 2654",
    "sg:postcode":"14467",
    "sg:province":"NY",
    "wof:name":"225 Tech Park LLC",
    "wof:placetype":"venue"
},
  "geometry": {"coordinates":[-77.594077,43.053719],"type":"Point"}
}