{
  "type": "Feature",
  "properties": {
    "iso:country":"US",
    "sg:address":"289 Broadway",
    "sg:city":"Lynbrook",
    "sg:classifiers":[
        {
            "category":"Building & Trades",
            "subcategory":"Pest Control",
            "type":"Services"
        }
    ],
    "sg:phone":"+1 631 754 2705",
    "sg:postcode":"11563",
    "sg:province":"NY",
    "sg:website":"www.arrowexterminating.com",
    "wof:name":"Arrow Exterminating Co",
    "wof:placetype":"venue"
},
  "geometry": {"coordinates":[-73.678398,40.653099],"type":"Point"}
}