{
  "type": "Feature",
  "properties": {
    "addr:full":"31 Homan Ave Bay Shore NY 11706",
    "addr:housenumber":"31",
    "addr:postcode":"11706",
    "addr:street":"Homan Ave",
    "iso:country":"US",
    "sg:address":"31 Homan Ave",
    "sg:city":"Bay Shore",
    "sg:classifiers":[
        {
            "category":"Building & Trades",
            "subcategory":"Construction",
            "type":"Services"
        }
    ],
    "sg:phone":"+1 631 969 1461",
    "sg:postcode":"11706",
    "sg:province":"NY",
    "sg:tags":[
        "contractor"
    ],
    "wof:name":"Complete Genl Contrctng",
    "wof:placetype":"venue"
},
  "geometry": {"coordinates":[-73.24154799999999,40.721381],"type":"Point"}
}