{
  "type": "Feature",
  "properties": {
    "addr:full":"2335 Union Rd Cheektowaga NY 14227",
    "addr:housenumber":"2335",
    "addr:postcode":"14227",
    "addr:street":"Union Rd",
    "iso:country":"US",
    "sg:address":"2335 Union Rd",
    "sg:city":"Cheektowaga",
    "sg:classifiers":[
        {
            "category":"Home & Garden",
            "subcategory":"Household Appliances",
            "type":"Retail Goods"
        }
    ],
    "sg:phone":"+1 716 668 3234",
    "sg:postcode":"14227",
    "sg:province":"NY",
    "wof:name":"Rosa's Home Appliances",
    "wof:placetype":"venue"
},
  "geometry": {"coordinates":[-78.753156,42.877037],"type":"Point"}
}