{
  "type": "Feature",
  "properties": {
    "addr:full":"1173 New Loudon Rd Cohoes NY 12047",
    "addr:housenumber":"1173",
    "addr:postcode":"12047",
    "addr:street":"New Loudon Rd",
    "iso:country":"US",
    "sg:address":"1173 New Loudon Rd",
    "sg:city":"Cohoes",
    "sg:classifiers":[
        {
            "category":"Wholesale",
            "subcategory":"Machinery & Supplies",
            "type":"Manufacturing & Wholesale Goods"
        },
        {
            "category":"Building & Trades",
            "subcategory":"Plumbing",
            "type":"Services"
        }
    ],
    "sg:phone":"+1 518 785 1192",
    "sg:postcode":"12047",
    "sg:province":"NY",
    "sg:tags":[
        "lawn",
        "sprinkler",
        "installs",
        "irrigation",
        "system",
        "equipment"
    ],
    "wof:name":"A-J Lawn Sprinkler Company",
    "wof:placetype":"venue"
},
  "geometry": {"coordinates":[-73.73606100000001,42.79159],"type":"Point"}
}