{
  "type": "Feature",
  "properties": {
    "addr:full":"133 Wolf Rd Albany NY 12205",
    "addr:housenumber":"133",
    "addr:postcode":"12205",
    "addr:street":"Wolf Rd",
    "iso:country":"US",
    "sg:address":"133 Wolf Rd",
    "sg:city":"Albany",
    "sg:classifiers":[
        {
            "category":"Manufacturing",
            "subcategory":"Printing",
            "type":"Manufacturing & Wholesale Goods"
        }
    ],
    "sg:phone":"+1 518 689 2222",
    "sg:postcode":"12205",
    "sg:province":"NY",
    "sg:tags":[
        "printer"
    ],
    "sg:website":"www.alphagraphics.com",
    "wof:name":"Alpha Graphics",
    "wof:placetype":"venue"
},
  "geometry": {"coordinates":[-73.806629,42.718338],"type":"Point"}
}