{
  "type": "Feature",
  "properties": {
    "iso:country":"US",
    "sg:address":"220 Nassau Blvd",
    "sg:city":"Garden City",
    "sg:classifiers":[
        {
            "category":"Professional",
            "subcategory":"Lawyer & Legal Services",
            "type":"Services"
        }
    ],
    "sg:phone":"+1 516 538 0060",
    "sg:postcode":"11530",
    "sg:province":"NY",
    "wof:name":"Beth A Swendsen-Dowd Esq",
    "wof:placetype":"venue"
},
  "geometry": {"coordinates":[-73.66097000000001,40.730659],"type":"Point"}
}