{
  "type": "Feature",
  "properties": {
    "iso:country":"US",
    "sg:address":"106 Morningside Dr",
    "sg:city":"New York",
    "sg:classifiers":[
        {
            "category":"Professional",
            "type":"Services"
        }
    ],
    "sg:phone":"+1   ",
    "sg:postcode":"10027",
    "sg:province":"NY",
    "wof:name":"Derald Wing Sue Phd A",
    "wof:placetype":"venue"
},
  "geometry": {"coordinates":[-73.957526,40.808881],"type":"Point"}
}