{
  "type": "Feature",
  "properties": {
    "addr:full":"369 Main St Center Moriches NY 11934",
    "addr:housenumber":"369",
    "addr:postcode":"11934",
    "addr:street":"Main St",
    "iso:country":"US",
    "sg:address":"369 Main St",
    "sg:city":"Center Moriches",
    "sg:classifiers":[
        {
            "category":"Insurance",
            "subcategory":"Insurance Agent",
            "type":"Services"
        }
    ],
    "sg:phone":"+1 631 847 3827",
    "sg:postcode":"11934",
    "sg:province":"NY",
    "sg:tags":[
        "sewing",
        "alteration"
    ],
    "wof:name":"Allstate Insurance Company",
    "wof:placetype":"venue"
},
  "geometry": {"coordinates":[-72.793297,40.800201],"type":"Point"}
}