{
  "type": "Feature",
  "properties": {
    "iso:country":"US",
    "sg:address":"250 5th Avenue",
    "sg:city":"New York",
    "sg:classifiers":[
        {
            "category":"Personal",
            "subcategory":"Massage",
            "type":"Services"
        }
    ],
    "sg:phone":"+1 212 447 5649",
    "sg:postcode":"10001",
    "sg:province":"NY",
    "wof:name":"Alexander Technique Midtown Center For",
    "wof:placetype":"venue"
},
  "geometry": {"coordinates":[-73.987188,40.744628],"type":"Point"}
}