{
  "type": "Feature",
  "properties": {
    "iso:country":"US",
    "sg:address":"295 Antlers Dr",
    "sg:city":"Rochester",
    "sg:classifiers":[
        {
            "category":"Real Estate",
            "subcategory":"Architect",
            "type":"Services"
        }
    ],
    "sg:phone":"+1 585 271 6622",
    "sg:postcode":"14618",
    "sg:province":"NY",
    "wof:name":"Lisa Lee Whasoon Architects",
    "wof:placetype":"venue"
},
  "geometry": {"coordinates":[-77.570868,43.127174],"type":"Point"}
}