{
  "type": "Feature",
  "properties": {
    "addr:full":"101 Erie Blvd Canajoharie NY 13317",
    "addr:housenumber":"101",
    "addr:postcode":"13317",
    "addr:street":"Erie Blvd",
    "iso:country":"US",
    "sg:address":"101 Erie Blvd",
    "sg:city":"Canajoharie",
    "sg:classifiers":[
        {
            "category":"Manufacturing",
            "subcategory":"Food",
            "type":"Manufacturing & Wholesale Goods"
        }
    ],
    "sg:phone":"+1   ",
    "sg:postcode":"13317",
    "sg:province":"NY",
    "sg:tags":[
        "chewing",
        "gum",
        "mfg"
    ],
    "wof:name":"Joyco USA",
    "wof:placetype":"venue"
},
  "geometry": {"coordinates":[-74.58481999999999,42.905167],"type":"Point"}
}