{
  "type": "Feature",
  "properties": {
    "addr:full":"2580 Baird Rd Penfield NY 14526",
    "addr:housenumber":"2580",
    "addr:postcode":"14526",
    "addr:street":"Baird Rd",
    "iso:country":"US",
    "sg:address":"2580 Baird Rd",
    "sg:city":"Penfield",
    "sg:classifiers":[
        {
            "category":"Building & Trades",
            "subcategory":"Construction",
            "type":"Services"
        }
    ],
    "sg:phone":"+1 585 248 6000",
    "sg:postcode":"14526",
    "sg:province":"NY",
    "sg:tags":[
        "general",
        "contractor"
    ],
    "wof:name":"R J Taylor General Contractors",
    "wof:placetype":"venue"
},
  "geometry": {"coordinates":[-77.462648,43.111188],"type":"Point"}
}