{
  "type": "Feature",
  "properties": {
    "iso:country":"US",
    "sg:address":"1000 N Franklin St",
    "sg:city":"Watkins Glen",
    "sg:classifiers":[
        {
            "category":"Wholesale",
            "subcategory":"Construction Materials",
            "type":"Manufacturing & Wholesale Goods"
        }
    ],
    "sg:phone":"+1 607 535 2940",
    "sg:postcode":"14891",
    "sg:province":"NY",
    "sg:tags":[
        "sand",
        "gravel"
    ],
    "wof:name":"Siri Enterprises",
    "wof:placetype":"venue"
},
  "geometry": {"coordinates":[-76.87090499999999,42.375964],"type":"Point"}
}