{
  "type": "Feature",
  "properties": {
    "iso:country":"US",
    "sg:address":"4373 Winding Creek Rd",
    "sg:city":"Manlius",
    "sg:classifiers":[
        {
            "category":"Real Estate",
            "subcategory":"Real Estate Agent",
            "type":"Services"
        }
    ],
    "sg:phone":"+1 315 682 3787",
    "sg:postcode":"13104",
    "sg:province":"NY",
    "wof:name":"Doc Real Estate LLC",
    "wof:placetype":"venue"
},
  "geometry": {"coordinates":[-75.956452,42.984196],"type":"Point"}
}