{
  "type": "Feature",
  "properties": {
    "addr:full":"3925 State Hwy 281 Cortland NY 13045",
    "addr:housenumber":"3925",
    "addr:postcode":"13045",
    "addr:street":"State Hwy 281",
    "iso:country":"US",
    "sg:address":"3925 State Hwy 281",
    "sg:city":"Cortland",
    "sg:classifiers":[
        {
            "category":"Shopping",
            "type":"Retail Goods"
        }
    ],
    "sg:phone":"+1 607 753 9213",
    "sg:postcode":"13045",
    "sg:province":"NY",
    "sg:tags":[
        "pet",
        "shop"
    ],
    "wof:name":"Pets-A-Plenty",
    "wof:placetype":"venue"
},
  "geometry": {"coordinates":[-76.205945,42.596115],"type":"Point"}
}