{
  "type": "Feature",
  "properties": {
    "addr:full":"37 Uxbridge St Staten Island NY 10314",
    "addr:housenumber":"37",
    "addr:postcode":"10314",
    "addr:street":"Uxbridge St",
    "iso:country":"US",
    "sg:address":"37 Uxbridge St",
    "sg:city":"Staten Island",
    "sg:classifiers":[
        {
            "category":"Shopping",
            "subcategory":"Gifts & Souvenirs",
            "type":"Retail Goods"
        }
    ],
    "sg:phone":"+1 718 494 1950",
    "sg:postcode":"10314",
    "sg:province":"NY",
    "sg:tags":[
        "collectible"
    ],
    "wof:name":"Specialties & Collectibles",
    "wof:placetype":"venue"
},
  "geometry": {"coordinates":[-74.139416,40.602283],"type":"Point"}
}