{
  "type": "Feature",
  "properties": {
    "addr:full":"9410 Ave L Brooklyn NY 11236",
    "addr:postcode":"11236",
    "addr:street":"9410 Ave L",
    "iso:country":"US",
    "sg:address":"9410 Ave L",
    "sg:city":"Brooklyn",
    "sg:classifiers":[
        {
            "category":"Retail",
            "subcategory":"Repair Shop",
            "type":"Services"
        }
    ],
    "sg:phone":"+1 718 444 4443",
    "sg:postcode":"11236",
    "sg:province":"NY",
    "sg:tags":[
        "lock",
        "locksmith"
    ],
    "wof:name":"Aladdin Locksmiths",
    "wof:placetype":"venue"
},
  "geometry": {"coordinates":[-73.89687499999999,40.637553],"type":"Point"}
}