{
  "type": "Feature",
  "properties": {
    "iso:country":"US",
    "sg:address":"28 Reeves Ave",
    "sg:city":"Riverhead",
    "sg:classifiers":[
        {
            "category":"Home & Garden",
            "subcategory":"Garden Supply",
            "type":"Retail Goods"
        }
    ],
    "sg:phone":"+1 631 727 0009",
    "sg:postcode":"11901",
    "sg:province":"NY",
    "sg:tags":[
        "nurseryman"
    ],
    "wof:name":"Long Island Perennial Farm",
    "wof:placetype":"venue"
},
  "geometry": {"coordinates":[-72.70847999999999,40.947663],"type":"Point"}
}