{
  "type": "Feature",
  "properties": {
    "addr:full":"2600 Netherland Ave Bronx NY 10463",
    "addr:housenumber":"2600",
    "addr:postcode":"10463",
    "addr:street":"Netherland Ave",
    "iso:country":"US",
    "sg:address":"2600 Netherland Ave",
    "sg:city":"Bronx",
    "sg:classifiers":[
        {
            "category":"Health Services",
            "subcategory":"Chiropractor",
            "type":"Services"
        }
    ],
    "sg:phone":"+1 718 432 4747",
    "sg:postcode":"10463",
    "sg:province":"NY",
    "wof:name":"Nicolas Dean DC",
    "wof:placetype":"venue"
},
  "geometry": {"coordinates":[-73.91448699999999,40.879612],"type":"Point"}
}