{
  "type": "Feature",
  "properties": {
    "iso:country":"US",
    "sg:address":"3040 Amsdell Rd",
    "sg:city":"Hamburg",
    "sg:classifiers":[
        {
            "category":"Health Services",
            "subcategory":"Doctor",
            "type":"Services"
        }
    ],
    "sg:phone":"+1 716 646 1084",
    "sg:postcode":"14075",
    "sg:province":"NY",
    "sg:tags":[
        "physician",
        "surgeon"
    ],
    "wof:name":"Lakeshore Primary Care Asso",
    "wof:placetype":"venue"
},
  "geometry": {"coordinates":[-78.880774,42.73557],"type":"Point"}
}