{
  "type": "Feature",
  "properties": {
    "addr:full":"3200 Expressway Dr S Islandia NY 11749",
    "addr:housenumber":"3200",
    "addr:postcode":"11749",
    "addr:street":"Expressway Dr S Islandia",
    "iso:country":"US",
    "sg:address":"3200 Expressway Dr S",
    "sg:city":"Islandia",
    "sg:classifiers":[
        {
            "category":"Communications",
            "subcategory":"Radio Station",
            "type":"Services"
        }
    ],
    "sg:phone":"+1 631 234 4151",
    "sg:postcode":"11749",
    "sg:province":"NY",
    "sg:tags":[
        "company",
        "broadcasting"
    ],
    "wof:name":"WFRS",
    "wof:placetype":"venue"
},
  "geometry": {"coordinates":[-73.151128,40.809732],"type":"Point"}
}