{
  "type": "Feature",
  "properties": {
    "addr:full":"717 Covert Ave New Hyde Park NY 11040",
    "addr:housenumber":"717",
    "addr:postcode":"11040",
    "addr:street":"Covert Ave New",
    "iso:country":"US",
    "sg:address":"717 Covert Ave",
    "sg:city":"New Hyde Park",
    "sg:classifiers":[
        {
            "category":"Professional",
            "subcategory":"Management & Consulting",
            "type":"Services"
        }
    ],
    "sg:phone":"+1 516 352 5991",
    "sg:postcode":"11040",
    "sg:province":"NY",
    "sg:tags":[
        "consultant"
    ],
    "wof:name":"CTM Consulting",
    "wof:placetype":"venue"
},
  "geometry": {"coordinates":[-73.68713700000001,40.726261],"type":"Point"}
}