{
  "type": "Feature",
  "properties": {
    "iso:country":"US",
    "sg:address":"155 Crystal Run Rd",
    "sg:city":"Middletown",
    "sg:classifiers":[
        {
            "category":"Health Services",
            "subcategory":"Doctor",
            "type":"Services"
        }
    ],
    "sg:phone":"+1 845 703 6999",
    "sg:postcode":"10941",
    "sg:province":"NY",
    "sg:tags":[
        "medicine",
        "obstetrician",
        "internal",
        "cardiologist",
        "gynecologist"
    ],
    "sg:website":"www.crystalrunhealthcare.com",
    "wof:name":"Ronen Tal MD",
    "wof:placetype":"venue"
},
  "geometry": {"coordinates":[-74.355904,41.451599],"type":"Point"}
}