{
  "type": "Feature",
  "properties": {
    "addr:full":"140 Milbar Blvd Farmingdale NY 11735",
    "addr:housenumber":"140",
    "addr:postcode":"11735",
    "addr:street":"Milbar Blvd",
    "iso:country":"US",
    "sg:address":"140 Milbar Blvd",
    "sg:city":"Farmingdale",
    "sg:classifiers":[
        {
            "category":"Wholesale",
            "subcategory":"Hardware",
            "type":"Manufacturing & Wholesale Goods"
        }
    ],
    "sg:phone":"+1 631 249 9577",
    "sg:postcode":"11735",
    "sg:province":"NY",
    "sg:tags":[
        "tool"
    ],
    "wof:name":"Top Line Tool Warehouse Inc",
    "wof:placetype":"venue"
},
  "geometry": {"coordinates":[-73.418745,40.750031],"type":"Point"}
}