{
  "type": "Feature",
  "properties": {
    "addr:full":"275 Central Park W Apt 1E New York NY 10024",
    "addr:housenumber":"275",
    "addr:postcode":"10024",
    "addr:street":"Central Park W Apt 1E",
    "iso:country":"US",
    "sg:address":"275 Central Park W Apt 1E",
    "sg:city":"New York",
    "sg:classifiers":[
        {
            "category":"Health Services",
            "subcategory":"Doctor",
            "type":"Services"
        }
    ],
    "sg:phone":"+1 212 280 2537",
    "sg:postcode":"10024",
    "sg:province":"NY",
    "wof:name":"Selzer Michael Dr",
    "wof:placetype":"venue"
},
  "geometry": {"coordinates":[-73.968943,40.786513],"type":"Point"}
}