{
  "type": "Feature",
  "properties": {
    "addr:full":"325 Norwood Ave Rochester NY 14606",
    "addr:housenumber":"325",
    "addr:postcode":"14606",
    "addr:street":"Norwood Ave",
    "iso:country":"US",
    "sg:address":"325 Norwood Ave",
    "sg:city":"Rochester",
    "sg:classifiers":[
        {
            "category":"Building & Trades",
            "subcategory":"Construction",
            "type":"Services"
        }
    ],
    "sg:phone":"+1 585 426 6177",
    "sg:postcode":"14606",
    "sg:province":"NY",
    "sg:tags":[
        "house"
    ],
    "wof:name":"McKnight Home Improvement",
    "wof:placetype":"venue"
},
  "geometry": {"coordinates":[-77.71069900000001,43.177167],"type":"Point"}
}