{
  "type": "Feature",
  "properties": {
    "addr:full":"124 W Main St Babylon NY 11702",
    "addr:housenumber":"124",
    "addr:postcode":"11702",
    "addr:street":"W Main St",
    "iso:country":"US",
    "sg:address":"124 W Main St",
    "sg:city":"Babylon",
    "sg:classifiers":[
        {
            "category":"Banks & Credit Unions",
            "subcategory":"Bank",
            "type":"Services"
        }
    ],
    "sg:phone":"+1 631 893 4610",
    "sg:postcode":"11702",
    "sg:province":"NY",
    "wof:name":"North Fork Bank",
    "wof:placetype":"venue"
},
  "geometry": {"coordinates":[-73.32508799999999,40.696019],"type":"Point"}
}