{
  "type": "Feature",
  "properties": {
    "addr:full":"111 Cedar St Corning NY 14830",
    "addr:housenumber":"111",
    "addr:postcode":"14830",
    "addr:street":"Cedar St",
    "iso:country":"US",
    "sg:address":"111 Cedar St",
    "sg:city":"Corning",
    "sg:classifiers":[
        {
            "category":"Museum",
            "type":"Entertainment"
        }
    ],
    "sg:phone":"+1   ",
    "sg:postcode":"14830",
    "sg:province":"NY",
    "sg:website":"www.rockwellmuseum.org",
    "wof:name":"Rockwell Museum Of Western Art",
    "wof:placetype":"venue"
},
  "geometry": {"coordinates":[-77.052435,42.143049],"type":"Point"}
}