{
  "type": "Feature",
  "properties": {
    "addr:full":"1510 Waters Pl Bronx NY 10461",
    "addr:housenumber":"1510",
    "addr:postcode":"10461",
    "addr:street":"Waters Pl",
    "iso:country":"US",
    "sg:address":"1510 Waters Pl",
    "sg:city":"Bronx",
    "sg:classifiers":[
        {
            "category":"Education",
            "subcategory":"University",
            "type":"Public Place"
        }
    ],
    "sg:phone":"+1 347 493 8500",
    "sg:postcode":"10461",
    "sg:province":"NY",
    "sg:tags":[
        "college"
    ],
    "wof:name":"Albert Einstein College of Medicine",
    "wof:placetype":"venue"
},
  "geometry": {"coordinates":[-73.841061,40.845806],"type":"Point"}
}