{
  "type": "Feature",
  "properties": {
    "addr:full":"87 Utica Ave Brooklyn NY 11213",
    "addr:housenumber":"87",
    "addr:postcode":"11213",
    "addr:street":"Utica Ave",
    "iso:country":"US",
    "sg:address":"87 Utica Ave",
    "sg:city":"Brooklyn",
    "sg:classifiers":[
        {
            "category":"Restaurant",
            "type":"Food & Drink"
        }
    ],
    "sg:phone":"+1 718 493 5907",
    "sg:postcode":"11213",
    "sg:province":"NY",
    "wof:name":"Carolina Creek Restaurant Corp",
    "wof:placetype":"venue"
},
  "geometry": {"coordinates":[-73.930331,40.676505],"type":"Point"}
}