{
  "type": "Feature",
  "properties": {
    "addr:full":"3339 Fulton Street Brooklyn NY 11208",
    "addr:housenumber":"3339",
    "addr:postcode":"11208",
    "addr:street":"Fulton Street",
    "iso:country":"US",
    "sg:address":"3339 Fulton Street",
    "sg:city":"Brooklyn",
    "sg:classifiers":[
        {
            "category":"Food & Beverages",
            "subcategory":"Groceries & Convenience Stores",
            "type":"Retail Goods"
        }
    ],
    "sg:phone":"+1 718 277 0029",
    "sg:postcode":"11208",
    "sg:province":"NY",
    "wof:name":"Bin Kee Minne Market",
    "wof:placetype":"venue"
},
  "geometry": {"coordinates":[-73.872328,40.683724],"type":"Point"}
}