{
  "type": "Feature",
  "properties": {
    "iso:country":"US",
    "sg:address":"225 Elizabeth St",
    "sg:city":"Ogdensburg",
    "sg:classifiers":[
        {
            "category":"Organizations",
            "subcategory":"Community Association",
            "type":"Services"
        }
    ],
    "sg:phone":"+1 315 394 7919",
    "sg:postcode":"13669",
    "sg:province":"NY",
    "sg:tags":[
        "club"
    ],
    "wof:name":"Disabled American Veterans Med",
    "wof:placetype":"venue"
},
  "geometry": {"coordinates":[-75.48972500000001,44.700026],"type":"Point"}
}