{
  "type": "Feature",
  "properties": {
    "addr:full":"4300 Eddy Ridge Rd Marion NY 14505",
    "addr:housenumber":"4300",
    "addr:postcode":"14505",
    "addr:street":"Eddy Ridge Rd",
    "iso:country":"US",
    "sg:address":"4300 Eddy Ridge Rd",
    "sg:city":"Marion",
    "sg:classifiers":[
        {
            "category":"Shopping",
            "subcategory":"Used Merchandise",
            "type":"Retail Goods"
        }
    ],
    "sg:phone":"+1   ",
    "sg:postcode":"14505",
    "sg:province":"NY",
    "wof:name":"Good Old Days Country Shop",
    "wof:placetype":"venue"
},
  "geometry": {"coordinates":[-77.20552000000001,43.160108],"type":"Point"}
}