{
  "type": "Feature",
  "properties": {
    "addr:full":"36 Fernboro Rd Rochester NY 14618",
    "addr:housenumber":"36",
    "addr:postcode":"14618",
    "addr:street":"Fernboro Rd",
    "iso:country":"US",
    "sg:address":"36 Fernboro Rd",
    "sg:city":"Rochester",
    "sg:classifiers":[
        {
            "category":"Building & Trades",
            "subcategory":"Construction",
            "type":"Services"
        }
    ],
    "sg:phone":"+1 585 271 1510",
    "sg:postcode":"14618",
    "sg:province":"NY",
    "sg:tags":[
        "hanging",
        "contractor"
    ],
    "wof:name":"Vincent A Curcio",
    "wof:placetype":"venue"
},
  "geometry": {"coordinates":[-77.558637,43.129547],"type":"Point"}
}