{
  "type": "Feature",
  "properties": {
    "addr:full":"7 Daniel Rd North Salem NY 10560",
    "addr:housenumber":"7",
    "addr:postcode":"10560",
    "addr:street":"Daniel Rd",
    "iso:country":"US",
    "sg:address":"7 Daniel Rd",
    "sg:city":"North Salem",
    "sg:classifiers":[
        {
            "category":"Building & Trades",
            "subcategory":"Construction",
            "type":"Services"
        }
    ],
    "sg:phone":"+1 914 438 8185",
    "sg:postcode":"10560",
    "sg:province":"NY",
    "sg:tags":[
        "general",
        "contractor"
    ],
    "wof:name":"Estate Maintenance",
    "wof:placetype":"venue"
},
  "geometry": {"coordinates":[-73.649978,41.345114],"type":"Point"}
}