{
  "type": "Feature",
  "properties": {
    "iso:country":"US",
    "sg:address":"225 W 39 St",
    "sg:city":"New York",
    "sg:classifiers":[
        {
            "category":"Professional",
            "subcategory":"Accounting & Tax Preparation",
            "type":"Services"
        }
    ],
    "sg:phone":"+1 212 398 3127",
    "sg:postcode":"10018",
    "sg:province":"NY",
    "sg:tags":[
        "accountant"
    ],
    "wof:name":"Siegfried Dollman CPA",
    "wof:placetype":"venue"
},
  "geometry": {"coordinates":[-73.990613,40.755102],"type":"Point"}
}