{
  "type": "Feature",
  "properties": {
    "iso:country":"US",
    "sg:address":"540 Jefferson Ave",
    "sg:city":"Rochester",
    "sg:classifiers":[
        {
            "category":"Retail",
            "subcategory":"Auto Repair",
            "type":"Services"
        }
    ],
    "sg:phone":"+1   ",
    "sg:postcode":"14611",
    "sg:province":"NY",
    "sg:tags":[
        "automotive"
    ],
    "wof:name":"Rickys AAA Garage",
    "wof:placetype":"venue"
},
  "geometry": {"coordinates":[-77.628906,43.143859],"type":"Point"}
}