{
  "type": "Feature",
  "properties": {
    "iso:country":"US",
    "sg:address":"454 Old Rte 17",
    "sg:city":"Livingston Manor",
    "sg:classifiers":[
        {
            "category":"Building & Trades",
            "subcategory":"Construction",
            "type":"Services"
        }
    ],
    "sg:phone":"+1 845 439 5287",
    "sg:postcode":"12758",
    "sg:province":"NY",
    "sg:tags":[
        "house"
    ],
    "wof:name":"Ken Hyzer Construction",
    "wof:placetype":"venue"
},
  "geometry": {"coordinates":[-74.793132,41.871676],"type":"Point"}
}