{
  "type": "Feature",
  "properties": {
    "iso:country":"US",
    "sg:address":"14601 45th Avenue",
    "sg:city":"Flushing",
    "sg:classifiers":[
        {
            "category":"Health Services",
            "subcategory":"Doctor",
            "type":"Services"
        }
    ],
    "sg:phone":"+1 718 358 3057",
    "sg:postcode":"11355",
    "sg:province":"NY",
    "wof:name":"Chaudhri Farida P MD",
    "wof:placetype":"venue"
},
  "geometry": {"coordinates":[-73.817054,40.754737],"type":"Point"}
}