{
  "type": "Feature",
  "properties": {
    "iso:country":"US",
    "sg:address":"631 S Geddes St",
    "sg:city":"Syracuse",
    "sg:classifiers":[
        {
            "category":"Autos & Motor Vehicles",
            "subcategory":"Fuel & Gas Station",
            "type":"Retail Goods"
        }
    ],
    "sg:phone":"+1 315 471 4397",
    "sg:postcode":"13204",
    "sg:province":"NY",
    "sg:tags":[
        "oil"
    ],
    "wof:name":"Kelly's Self Svc",
    "wof:placetype":"venue"
},
  "geometry": {"coordinates":[-76.171661,43.041733],"type":"Point"}
}