{
  "type": "Feature",
  "properties": {
    "addr:full":"129 Harbour Ln Massapequa NY 11758",
    "addr:housenumber":"129",
    "addr:postcode":"11758",
    "addr:street":"Harbour Ln",
    "iso:country":"US",
    "sg:address":"129 Harbour Ln",
    "sg:city":"Massapequa",
    "sg:classifiers":[
        {
            "category":"Professional",
            "subcategory":"Detective & Security Services",
            "type":"Services"
        }
    ],
    "sg:phone":"+1 516 798 5980",
    "sg:postcode":"11758",
    "sg:province":"NY",
    "sg:tags":[
        "private",
        "investigator"
    ],
    "wof:name":"Terriman Assocs Inc",
    "wof:placetype":"venue"
},
  "geometry": {"coordinates":[-73.457808,40.662819],"type":"Point"}
}