{
  "type": "Feature",
  "properties": {
    "iso:country":"US",
    "sg:address":"53 Bloomingdale Rd",
    "sg:city":"Hicksville",
    "sg:classifiers":[
        {
            "category":"Retail",
            "subcategory":"Auto Repair",
            "type":"Services"
        }
    ],
    "sg:phone":"+1 516 935 5200",
    "sg:postcode":"11801",
    "sg:province":"NY",
    "sg:tags":[
        "glass",
        "replacement"
    ],
    "wof:name":"Triumph Auto Glass",
    "wof:placetype":"venue"
},
  "geometry": {"coordinates":[-73.50533,40.750142],"type":"Point"}
}