{
  "type": "Feature",
  "properties": {
    "addr:full":"7503 20th Ave Brooklyn NY 11214",
    "addr:housenumber":"7503",
    "addr:postcode":"11214",
    "addr:street":"20Th Ave",
    "iso:country":"US",
    "sg:address":"7503 20th Ave",
    "sg:city":"Brooklyn",
    "sg:classifiers":[
        {
            "category":"Personal",
            "subcategory":"Beauty Salon",
            "type":"Services"
        }
    ],
    "sg:phone":"+1 718 236 9794",
    "sg:postcode":"11214",
    "sg:province":"NY",
    "wof:name":"Touch Of Elegance",
    "wof:placetype":"venue"
},
  "geometry": {"coordinates":[-73.992324,40.610206],"type":"Point"}
}