{
  "type": "Feature",
  "properties": {
    "addr:full":"19 Vanderbilt Ave Brooklyn NY 11205",
    "addr:housenumber":"19",
    "addr:postcode":"11205",
    "addr:street":"Vanderbilt Ave",
    "iso:country":"US",
    "sg:address":"19 Vanderbilt Ave",
    "sg:city":"Brooklyn",
    "sg:classifiers":[
        {
            "category":"Wholesale",
            "subcategory":"Metals & Minerals",
            "type":"Manufacturing & Wholesale Goods"
        }
    ],
    "sg:phone":"+1 718 246 7484",
    "sg:postcode":"11205",
    "sg:province":"NY",
    "sg:tags":[
        "specialty"
    ],
    "wof:name":"Studio 40 Inc",
    "wof:placetype":"venue"
},
  "geometry": {"coordinates":[-73.970426,40.696677],"type":"Point"}
}