{
  "type": "Feature",
  "properties": {
    "iso:country":"US",
    "sg:address":"269 Co Rte 35",
    "sg:city":"Fulton",
    "sg:classifiers":[
        {
            "category":"Wholesale",
            "subcategory":"Farm Supplies",
            "type":"Manufacturing & Wholesale Goods"
        }
    ],
    "sg:phone":"+1 315 598 6338",
    "sg:postcode":"13069",
    "sg:province":"NY",
    "sg:tags":[
        "livestock"
    ],
    "wof:name":"Brook Seeley Farm",
    "wof:placetype":"venue"
},
  "geometry": {"coordinates":[-76.279729,43.398803],"type":"Point"}
}