{
  "type": "Feature",
  "properties": {
    "addr:full":"8963 Oakland Rd Weedsport NY 13166",
    "addr:housenumber":"8963",
    "addr:postcode":"13166",
    "addr:street":"Oakland Rd",
    "iso:country":"US",
    "sg:address":"8963 Oakland Rd",
    "sg:city":"Weedsport",
    "sg:classifiers":[
        {
            "category":"Farming",
            "subcategory":"Farm",
            "type":"Manufacturing & Wholesale Goods"
        }
    ],
    "sg:phone":"+1 315 834 6065",
    "sg:postcode":"13166",
    "sg:province":"NY",
    "wof:name":"Oakland Farms",
    "wof:placetype":"venue"
},
  "geometry": {"coordinates":[-76.57929799999999,43.051669],"type":"Point"}
}