{
  "type": "Feature",
  "properties": {
    "iso:country":"US",
    "sg:address":"6 Sparrow Ln",
    "sg:city":"Woodbury",
    "sg:classifiers":[
        {
            "category":"Organizations",
            "subcategory":"Membership Organization",
            "type":"Services"
        }
    ],
    "sg:phone":"+1   ",
    "sg:postcode":"11797",
    "sg:province":"NY",
    "wof:name":"Production Management Assn",
    "wof:placetype":"venue"
},
  "geometry": {"coordinates":[-73.482359,40.797527],"type":"Point"}
}