{
  "type": "Feature",
  "properties": {
    "addr:full":"75 Grand St New York NY 10013",
    "addr:housenumber":"75",
    "addr:postcode":"10013",
    "addr:street":"Grand St",
    "iso:country":"US",
    "sg:address":"75 Grand St",
    "sg:city":"New York",
    "sg:classifiers":[
        {
            "category":"Home & Garden",
            "subcategory":"Carpets & Floor Coverings",
            "type":"Retail Goods"
        }
    ],
    "sg:phone":"+1 212 219 8022",
    "sg:postcode":"10013",
    "sg:province":"NY",
    "sg:tags":[
        "mattress"
    ],
    "sg:website":"www.hbeds.com",
    "wof:name":"Hastens Beds",
    "wof:placetype":"venue"
},
  "geometry": {"coordinates":[-74.002647,40.721598],"type":"Point"}
}