{
  "type": "Feature",
  "properties": {
    "iso:country":"US",
    "sg:address":"12 Vassar St",
    "sg:city":"Poughkeepsie",
    "sg:classifiers":[
        {
            "category":"Museum",
            "type":"Entertainment"
        }
    ],
    "sg:phone":"+1 845 471 7477",
    "sg:postcode":"12601",
    "sg:province":"NY",
    "sg:tags":[
        "organization",
        "arts",
        "information"
    ],
    "wof:name":"Dutchess Arts Camp",
    "wof:placetype":"venue"
},
  "geometry": {"coordinates":[-73.93138999999999,41.705352],"type":"Point"}
}