{
  "type": "Feature",
  "properties": {
    "addr:full":"26013 Hillside Ave Glen Oaks NY 11004",
    "addr:housenumber":"26013",
    "addr:postcode":"11004",
    "addr:street":"Hillside Ave",
    "iso:country":"US",
    "sg:address":"26013 Hillside Ave",
    "sg:city":"Glen Oaks",
    "sg:classifiers":[
        {
            "category":"Personal",
            "subcategory":"Barber",
            "type":"Services"
        }
    ],
    "sg:phone":"+1 718 962 2991",
    "sg:postcode":"11004",
    "sg:province":"NY",
    "wof:name":"Mehak Beauty Parlor",
    "wof:placetype":"venue"
},
  "geometry": {"coordinates":[-73.707703,40.737598],"type":"Point"}
}