{
  "type": "Feature",
  "properties": {
    "addr:full":"214 Sullivan St New York NY 10012",
    "addr:housenumber":"214",
    "addr:postcode":"10012",
    "addr:street":"Sullivan St",
    "iso:country":"US",
    "sg:address":"214 Sullivan St",
    "sg:city":"New York",
    "sg:classifiers":[
        {
            "category":"Communications",
            "subcategory":"Film & Video Production",
            "type":"Services"
        }
    ],
    "sg:phone":"+1 212 253 5510",
    "sg:postcode":"10012",
    "sg:province":"NY",
    "sg:tags":[
        "director",
        "casting"
    ],
    "wof:name":"Louis Di Giaimo & Assoc LTD",
    "wof:placetype":"venue"
},
  "geometry": {"coordinates":[-73.99966499999999,40.72973],"type":"Point"}
}