{
  "type": "Feature",
  "properties": {
    "iso:country":"US",
    "sg:address":"12 E Village Grn",
    "sg:city":"Levittown",
    "sg:classifiers":[
        {
            "category":"Shopping",
            "subcategory":"Stationery & Office Supplies",
            "type":"Retail Goods"
        }
    ],
    "sg:phone":"+1 516 731 9665",
    "sg:postcode":"11756",
    "sg:province":"NY",
    "sg:tags":[
        "equipment"
    ],
    "wof:name":"ISY Services Inc",
    "wof:placetype":"venue"
},
  "geometry": {"coordinates":[-73.513711,40.734975],"type":"Point"}
}