{
  "type": "Feature",
  "properties": {
    "addr:full":"1569 Flatbush Ave Brooklyn NY 11210",
    "addr:housenumber":"1569",
    "addr:postcode":"11210",
    "addr:street":"Flatbush Ave",
    "iso:country":"US",
    "sg:address":"1569 Flatbush Ave",
    "sg:city":"Brooklyn",
    "sg:classifiers":[
        {
            "category":"Travel",
            "subcategory":"Travel Agent",
            "type":"Entertainment"
        }
    ],
    "sg:phone":"+1 718 859 3007",
    "sg:postcode":"11210",
    "sg:province":"NY",
    "sg:tags":[
        "agency",
        "bureau"
    ],
    "wof:name":"Travelspan Vacations",
    "wof:placetype":"venue"
},
  "geometry": {"coordinates":[-73.947124,40.632538],"type":"Point"}
}