{
  "type": "Feature",
  "properties": {
    "iso:country":"US",
    "sg:address":"700 Varick St",
    "sg:city":"Utica",
    "sg:classifiers":[
        {
            "category":"Building & Trades",
            "subcategory":"Electrical",
            "type":"Services"
        }
    ],
    "sg:phone":"+1 315 792 9271",
    "sg:postcode":"13502",
    "sg:province":"NY",
    "sg:tags":[
        "electric",
        "contractor"
    ],
    "wof:name":"Electric Co",
    "wof:placetype":"venue"
},
  "geometry": {"coordinates":[-75.243228,43.103635],"type":"Point"}
}