{
  "type": "Feature",
  "properties": {
    "addr:full":"44 E 32 St New York NY 10016",
    "addr:housenumber":"44;32",
    "addr:postcode":"10016",
    "addr:street":"E;St",
    "iso:country":"US",
    "sg:address":"44 E 32 St",
    "sg:city":"New York",
    "sg:classifiers":[
        {
            "category":"Professional",
            "subcategory":"Business Services",
            "type":"Services"
        }
    ],
    "sg:phone":"+1 212 679 3940",
    "sg:postcode":"10016",
    "sg:province":"NY",
    "sg:tags":[
        "interior",
        "consultant",
        "design",
        "decorator"
    ],
    "wof:name":"Farah Tanny Interiors",
    "wof:placetype":"venue"
},
  "geometry": {"coordinates":[-73.98262099999999,40.745901],"type":"Point"}
}