{
  "type": "Feature",
  "properties": {
    "addr:full":"3316 38th Ave Long Island City NY 11101",
    "addr:housenumber":"3316",
    "addr:postcode":"11101",
    "addr:street":"38Th Ave",
    "iso:country":"US",
    "sg:address":"3316 38th Ave",
    "sg:city":"Long Island City",
    "sg:classifiers":[
        {
            "category":"Building & Trades",
            "subcategory":"Electrical",
            "type":"Services"
        }
    ],
    "sg:phone":"+1 718 343 1570",
    "sg:postcode":"11101",
    "sg:province":"NY",
    "sg:tags":[
        "electrician"
    ],
    "wof:name":"Deboccia Electl Constr Corp",
    "wof:placetype":"venue"
},
  "geometry": {"coordinates":[-73.929901,40.752499],"type":"Point"}
}