{
  "type": "Feature",
  "properties": {
    "iso:country":"US",
    "sg:address":"9 Duvall Dr",
    "sg:city":"Hampton Bays",
    "sg:classifiers":[
        {
            "category":"Sports & Exercise",
            "subcategory":"Gym",
            "type":"Entertainment"
        }
    ],
    "sg:phone":"+1 631 728 2831",
    "sg:postcode":"11946",
    "sg:province":"NY",
    "sg:tags":[
        "spa",
        "health"
    ],
    "wof:name":"Laface To Lafeet Skin & Spa",
    "wof:placetype":"venue"
},
  "geometry": {"coordinates":[-72.5209,40.863283],"type":"Point"}
}