{
  "type": "Feature",
  "properties": {
    "iso:country":"US",
    "sg:address":"1037 State Hwy 166",
    "sg:city":"Cooperstown",
    "sg:classifiers":[
        {
            "category":"Shopping",
            "subcategory":"Crafts & Fabrics",
            "type":"Retail Goods"
        }
    ],
    "sg:phone":"+1   ",
    "sg:postcode":"13326",
    "sg:province":"NY",
    "sg:tags":[
        "sewing"
    ],
    "wof:name":"Sybils Yarn Shop",
    "wof:placetype":"venue"
},
  "geometry": {"coordinates":[-74.892004,42.629436],"type":"Point"}
}