{
  "type": "Feature",
  "properties": {
    "addr:full":"1594 Westchester Ave Bronx NY 10472",
    "addr:housenumber":"1594",
    "addr:postcode":"10472",
    "addr:street":"Westchester Ave",
    "iso:country":"US",
    "sg:address":"1594 Westchester Ave",
    "sg:city":"Bronx",
    "sg:classifiers":[
        {
            "category":"Shopping",
            "subcategory":"Optical Goods",
            "type":"Retail Goods"
        }
    ],
    "sg:phone":"+1   ",
    "sg:postcode":"10472",
    "sg:province":"NY",
    "wof:name":"Family Optical Shoppe Corp",
    "wof:placetype":"venue"
},
  "geometry": {"coordinates":[-73.876007,40.828963],"type":"Point"}
}