{
  "type": "Feature",
  "properties": {
    "addr:full":"45 State Hwy 146 Mechanicville NY 12118",
    "addr:housenumber":"45",
    "addr:postcode":"12118",
    "addr:street":"State Hwy 146",
    "iso:country":"US",
    "sg:address":"45 State Hwy 146",
    "sg:city":"Mechanicville",
    "sg:classifiers":[
        {
            "category":"Wholesale",
            "subcategory":"Groceries",
            "type":"Manufacturing & Wholesale Goods"
        }
    ],
    "sg:phone":"+1 518 665 8318",
    "sg:postcode":"12118",
    "sg:province":"NY",
    "sg:tags":[
        "chips",
        "potato"
    ],
    "wof:name":"Bachman Co",
    "wof:placetype":"venue"
},
  "geometry": {"coordinates":[-73.70200800000001,42.885469],"type":"Point"}
}