{
  "type": "Feature",
  "properties": {
    "addr:full":"77 S Rossler Ave Buffalo NY 14206",
    "addr:housenumber":"77",
    "addr:postcode":"14206",
    "addr:street":"S Rossler Ave",
    "iso:country":"US",
    "sg:address":"77 S Rossler Ave",
    "sg:city":"Buffalo",
    "sg:classifiers":[
        {
            "category":"Deli",
            "type":"Food & Drink"
        },
        {
            "category":"Food & Beverages",
            "subcategory":"Bakery",
            "type":"Retail Goods"
        },
        {
            "category":"Food & Beverages",
            "subcategory":"Groceries & Convenience Stores",
            "type":"Retail Goods"
        }
    ],
    "sg:phone":"+1 716 824 7160",
    "sg:postcode":"14206",
    "sg:province":"NY",
    "sg:tags":[
        "sandwich"
    ],
    "wof:name":"Save-A-Lot",
    "wof:placetype":"venue"
},
  "geometry": {"coordinates":[-78.794732,42.874312],"type":"Point"}
}