{
  "type": "Feature",
  "properties": {
    "addr:full":"1335 Jefferson Rd Rochester NY 14623",
    "addr:housenumber":"1335",
    "addr:postcode":"14623",
    "addr:street":"Jefferson Rd",
    "iso:country":"US",
    "sg:address":"1335 Jefferson Rd",
    "sg:city":"Rochester",
    "sg:classifiers":[
        {
            "category":"Manufacturing",
            "subcategory":"Printing",
            "type":"Manufacturing & Wholesale Goods"
        }
    ],
    "sg:phone":"+1 585 383 1540",
    "sg:postcode":"14623",
    "sg:province":"NY",
    "sg:tags":[
        "foil",
        "metal",
        "label"
    ],
    "wof:name":"Frontier Graphics Inc",
    "wof:placetype":"venue"
},
  "geometry": {"coordinates":[-77.59422499999999,43.086971],"type":"Point"}
}