{
  "type": "Feature",
  "properties": {
    "addr:full":"47 High St Carthage NY 13619",
    "addr:housenumber":"47",
    "addr:postcode":"13619",
    "addr:street":"High St",
    "iso:country":"US",
    "sg:address":"47 High St",
    "sg:city":"Carthage",
    "sg:classifiers":[
        {
            "category":"Freight",
            "type":"Transportation"
        }
    ],
    "sg:phone":"+1 315 493 3707",
    "sg:postcode":"13619",
    "sg:province":"NY",
    "sg:tags":[
        "commercial",
        "storage",
        "special"
    ],
    "wof:name":"Franklin Street Mini Storage",
    "wof:placetype":"venue"
},
  "geometry": {"coordinates":[-75.6221,43.971335],"type":"Point"}
}