{
  "type": "Feature",
  "properties": {
    "addr:full":"437 Lyell Ave Rochester NY 14606",
    "addr:housenumber":"437",
    "addr:postcode":"14606",
    "addr:street":"Lyell Ave",
    "iso:country":"US",
    "sg:address":"437 Lyell Ave",
    "sg:city":"Rochester",
    "sg:classifiers":[
        {
            "category":"Shopping",
            "subcategory":"Pharmacy",
            "type":"Retail Goods"
        }
    ],
    "sg:phone":"+1   ",
    "sg:postcode":"14606",
    "sg:province":"NY",
    "sg:tags":[
        "drug",
        "store"
    ],
    "wof:name":"Rite Aid",
    "wof:placetype":"venue"
},
  "geometry": {"coordinates":[-77.638831,43.164636],"type":"Point"}
}