{
  "type": "Feature",
  "properties": {
    "addr:full":"240 W 44th St New York NY 10036",
    "addr:housenumber":"240",
    "addr:postcode":"10036",
    "addr:street":"W 44Th St",
    "iso:country":"US",
    "sg:address":"240 W 44th St",
    "sg:city":"New York",
    "sg:classifiers":[
        {
            "category":"Real Estate",
            "subcategory":"Real Estate Operator",
            "type":"Services"
        }
    ],
    "sg:phone":"+1 212 944 9450",
    "sg:postcode":"10036",
    "sg:province":"NY",
    "sg:tags":[
        "owner",
        "performing",
        "art"
    ],
    "wof:name":"Helen Hayes Theatre",
    "wof:placetype":"venue"
},
  "geometry": {"coordinates":[-73.9879,40.758301],"type":"Point"}
}