{
  "type": "Feature",
  "properties": {
    "addr:full":"910 W End Avenue Apt 1C New York NY 10025",
    "addr:housenumber":"910",
    "addr:postcode":"10025",
    "addr:street":"W End Avenue Apt 1C",
    "iso:country":"US",
    "sg:address":"910 W End Avenue Apt 1C",
    "sg:city":"New York",
    "sg:classifiers":[
        {
            "category":"Health Services",
            "subcategory":"Doctor",
            "type":"Services"
        }
    ],
    "sg:phone":"+1 212 662 9200",
    "sg:postcode":"10025",
    "sg:province":"NY",
    "wof:name":"Psychassociates Group",
    "wof:placetype":"venue"
},
  "geometry": {"coordinates":[-73.96922000000001,40.80066],"type":"Point"}
}