{
  "type": "Feature",
  "properties": {
    "addr:full":"3894 Richmond Avenue Staten Island NY 10312",
    "addr:housenumber":"3894",
    "addr:postcode":"10312",
    "addr:street":"Richmond Avenue",
    "iso:country":"US",
    "sg:address":"3894 Richmond Avenue",
    "sg:city":"Staten Island",
    "sg:classifiers":[
        {
            "category":"Shopping",
            "subcategory":"Pets & Pet Supplies",
            "type":"Retail Goods"
        }
    ],
    "sg:phone":"+1 718 227 9453",
    "sg:postcode":"10312",
    "sg:province":"NY",
    "sg:tags":[
        "store"
    ],
    "wof:name":"Animal Kingdom's Waterworld",
    "wof:placetype":"venue"
},
  "geometry": {"coordinates":[-74.16274199999999,40.541542],"type":"Point"}
}