{
  "type": "Feature",
  "properties": {
    "addr:full":"717 Ridge Rd Buffalo NY 14218",
    "addr:housenumber":"717",
    "addr:postcode":"14218",
    "addr:street":"Ridge Rd",
    "iso:country":"US",
    "sg:address":"717 Ridge Rd",
    "sg:city":"Buffalo",
    "sg:classifiers":[
        {
            "category":"Restaurant",
            "type":"Food & Drink"
        }
    ],
    "sg:phone":"+1 716 825 6627",
    "sg:postcode":"14218",
    "sg:province":"NY",
    "wof:name":"Victoria Square Restaurant",
    "wof:placetype":"venue"
},
  "geometry": {"coordinates":[-78.824997,42.825901],"type":"Point"}
}