{
  "type": "Feature",
  "properties": {
    "iso:country":"US",
    "sg:address":"21 Geranium Dr",
    "sg:city":"Mahopac",
    "sg:classifiers":[
        {
            "category":"Home & Garden",
            "subcategory":"Furniture",
            "type":"Retail Goods"
        }
    ],
    "sg:phone":"+1 914 592 6320",
    "sg:postcode":"10540",
    "sg:province":"NY",
    "wof:name":"Oriental Furniture Warehouse",
    "wof:placetype":"venue"
},
  "geometry": {"coordinates":[-73.72592899999999,41.346877],"type":"Point"}
}