{
  "type": "Feature",
  "properties": {
    "iso:country":"US",
    "sg:address":"854 State Hwy 6n",
    "sg:city":"Mahopac",
    "sg:classifiers":[
        {
            "category":"Professional",
            "subcategory":"Management & Consulting",
            "type":"Services"
        }
    ],
    "sg:phone":"+1 845 621 0155",
    "sg:postcode":"10541",
    "sg:province":"NY",
    "sg:tags":[
        "personnel",
        "consultant"
    ],
    "wof:name":"Elder Care Staffing Solutions",
    "wof:placetype":"venue"
},
  "geometry": {"coordinates":[-73.742963,41.372441],"type":"Point"}
}