{
  "type": "Feature",
  "properties": {
    "addr:full":"254 Larkfield Rd East Northport NY 11731",
    "addr:housenumber":"254",
    "addr:postcode":"11731",
    "addr:street":"Larkfield Rd",
    "iso:country":"US",
    "sg:address":"254 Larkfield Rd",
    "sg:city":"East Northport",
    "sg:classifiers":[
        {
            "category":"Utilities",
            "subcategory":"Mobile Phone",
            "type":"Services"
        }
    ],
    "sg:phone":"+1 631 262 1200",
    "sg:postcode":"11731",
    "sg:province":"NY",
    "sg:tags":[
        "telephone",
        "cellular"
    ],
    "wof:name":"Zoom Wireless",
    "wof:placetype":"venue"
},
  "geometry": {"coordinates":[-73.32467800000001,40.876246],"type":"Point"}
}