{
  "type": "Feature",
  "properties": {
    "iso:country":"US",
    "sg:address":"119 Times Sq",
    "sg:city":"Olean",
    "sg:classifiers":[
        {
            "category":"Government",
            "subcategory":"Office",
            "type":"Public Place"
        }
    ],
    "sg:phone":"+1 716 372 6464",
    "sg:postcode":"14760",
    "sg:province":"NY",
    "sg:tags":[
        "national",
        "security"
    ],
    "wof:name":"Armory Co C 127th Armor",
    "wof:placetype":"venue"
},
  "geometry": {"coordinates":[-78.428161,42.078063],"type":"Point"}
}