{
  "type": "Feature",
  "properties": {
    "addr:full":"10 Gateway Blvd #1258 Patchogue NY 11772",
    "addr:housenumber":"10",
    "addr:postcode":"11772",
    "addr:street":"Gateway Blvd # 1258",
    "iso:country":"US",
    "sg:address":"10 Gateway Blvd #1258",
    "sg:city":"Patchogue",
    "sg:classifiers":[
        {
            "category":"Home & Garden",
            "subcategory":"Hardware",
            "type":"Retail Goods"
        }
    ],
    "sg:phone":"+1 631 286 4665",
    "sg:postcode":"11772",
    "sg:province":"NY",
    "sg:tags":[
        "store"
    ],
    "wof:name":"Home Depot the",
    "wof:placetype":"venue"
},
  "geometry": {"coordinates":[-73.04080999999999,40.780955],"type":"Point"}
}