{
  "type": "Feature",
  "properties": {
    "iso:country":"US",
    "sg:address":"369 Hudson River Rd",
    "sg:city":"Waterford",
    "sg:classifiers":[
        {
            "category":"Utilities",
            "subcategory":"Fuel Oil & Lpg",
            "type":"Services"
        }
    ],
    "sg:phone":"+1 518 235 4517",
    "sg:postcode":"12188",
    "sg:province":"NY",
    "wof:name":"Richard's Fuel",
    "wof:placetype":"venue"
},
  "geometry": {"coordinates":[-73.667134,42.824566],"type":"Point"}
}