{
  "type": "Feature",
  "properties": {
    "addr:full":"16783 State Hwy 22 Putnam Station NY 12861",
    "addr:housenumber":"16783",
    "addr:postcode":"12861",
    "addr:street":"State Hwy 22 Putnam Station",
    "iso:country":"US",
    "sg:address":"16783 State Hwy 22",
    "sg:city":"Putnam Station",
    "sg:classifiers":[
        {
            "category":"Government",
            "subcategory":"Post Office",
            "type":"Public Place"
        }
    ],
    "sg:phone":"+1 518 547 8357",
    "sg:postcode":"12861",
    "sg:province":"NY",
    "wof:name":"US Post Office",
    "wof:placetype":"venue"
},
  "geometry": {"coordinates":[-73.40897699999999,43.759627],"type":"Point"}
}