{
  "type": "Feature",
  "properties": {
    "addr:full":"161 E 86 St New York NY 10028",
    "addr:housenumber":"161;86",
    "addr:postcode":"10028",
    "addr:street":"E;St",
    "iso:country":"US",
    "sg:address":"161 E 86 St",
    "sg:city":"New York",
    "sg:classifiers":[
        {
            "category":"Professional",
            "type":"Services"
        }
    ],
    "sg:phone":"+1 212 996 1006",
    "sg:postcode":"10028",
    "sg:province":"NY",
    "sg:tags":[
        "establishment"
    ],
    "wof:name":"Bolton's",
    "wof:placetype":"venue"
},
  "geometry": {"coordinates":[-73.954273,40.779069],"type":"Point"}
}