{
  "type": "Feature",
  "properties": {
    "addr:full":"209 W 37th St # A New York NY 10018",
    "addr:housenumber":"209",
    "addr:postcode":"10018",
    "addr:street":"W 37Th St # A",
    "iso:country":"US",
    "sg:address":"209 W 37th St # A",
    "sg:city":"New York",
    "sg:classifiers":[
        {
            "category":"Manufacturing",
            "subcategory":"Leather Goods",
            "type":"Manufacturing & Wholesale Goods"
        }
    ],
    "sg:phone":"+1 212 221 7977",
    "sg:postcode":"10018",
    "sg:province":"NY",
    "wof:name":"Happening Fashion Inc",
    "wof:placetype":"venue"
},
  "geometry": {"coordinates":[-73.989799,40.752998],"type":"Point"}
}