{
  "type": "Feature",
  "properties": {
    "iso:country":"US",
    "sg:address":"112 10th St",
    "sg:city":"Watkins Glen",
    "sg:classifiers":[
        {
            "category":"Health Services",
            "subcategory":"Clinic",
            "type":"Services"
        }
    ],
    "sg:phone":"+1 607 535 5133",
    "sg:postcode":"14891",
    "sg:province":"NY",
    "wof:name":"Nutrition Otrach Edcatn Prgram",
    "wof:placetype":"venue"
},
  "geometry": {"coordinates":[-76.869407,42.376873],"type":"Point"}
}