{
  "type": "Feature",
  "properties": {
    "iso:country":"US",
    "sg:address":"136 Pfohl Rd",
    "sg:city":"Cheektowaga",
    "sg:classifiers":[
        {
            "category":"Building & Trades",
            "subcategory":"Construction",
            "type":"Services"
        }
    ],
    "sg:phone":"+1 716 632 3866",
    "sg:postcode":"14225",
    "sg:province":"NY",
    "sg:tags":[
        "foundation",
        "concrete",
        "contractor"
    ],
    "wof:name":"Zelasko Construction Inc",
    "wof:placetype":"venue"
},
  "geometry": {"coordinates":[-78.702939,42.940264],"type":"Point"}
}