{
  "type": "Feature",
  "properties": {
    "addr:full":"125 Oakland Ave Port Jefferson NY 11777",
    "addr:housenumber":"125",
    "addr:postcode":"11777",
    "addr:street":"Oakland Ave",
    "iso:country":"US",
    "sg:address":"125 Oakland Ave",
    "sg:city":"Port Jefferson",
    "sg:classifiers":[
        {
            "category":"Health Services",
            "subcategory":"Clinic",
            "type":"Services"
        }
    ],
    "sg:phone":"+1 631 642 3287",
    "sg:postcode":"11777",
    "sg:province":"NY",
    "wof:name":"Sunrest Health Facilities Inc",
    "wof:placetype":"venue"
},
  "geometry": {"coordinates":[-73.053855,40.936165],"type":"Point"}
}