{
  "type": "Feature",
  "properties": {
    "iso:country":"US",
    "sg:address":"8258 Oswego Rd",
    "sg:city":"Liverpool",
    "sg:classifiers":[
        {
            "category":"Building & Trades",
            "subcategory":"Construction",
            "type":"Services"
        }
    ],
    "sg:phone":"+1 315 652 3580",
    "sg:postcode":"13090",
    "sg:province":"NY",
    "sg:tags":[
        "contractor"
    ],
    "wof:name":"Paradise General Contracting",
    "wof:placetype":"venue"
},
  "geometry": {"coordinates":[-76.249656,43.175039],"type":"Point"}
}