{
  "type": "Feature",
  "properties": {
    "iso:country":"US",
    "sg:address":"10 Atlantic St",
    "sg:city":"Holtsville",
    "sg:classifiers":[
        {
            "category":"Real Estate",
            "subcategory":"Real Estate Agent",
            "type":"Services"
        }
    ],
    "sg:phone":"+1 631 716 8700",
    "sg:postcode":"11742",
    "sg:province":"NY",
    "wof:name":"Realty 3000 Properties",
    "wof:placetype":"venue"
},
  "geometry": {"coordinates":[-73.05332300000001,40.82465],"type":"Point"}
}