{
  "type": "Feature",
  "properties": {
    "addr:full":"1187 Fenwood Dr Valley Stream NY 11580",
    "addr:housenumber":"1187",
    "addr:postcode":"11580",
    "addr:street":"Fenwood Dr",
    "iso:country":"US",
    "sg:address":"1187 Fenwood Dr",
    "sg:city":"Valley Stream",
    "sg:classifiers":[
        {
            "category":"Building & Trades",
            "subcategory":"Construction",
            "type":"Services"
        }
    ],
    "sg:phone":"+1 516 285 9151",
    "sg:postcode":"11580",
    "sg:province":"NY",
    "sg:tags":[
        "masonry",
        "contractor"
    ],
    "wof:name":"Joseph Beksinski",
    "wof:placetype":"venue"
},
  "geometry": {"coordinates":[-73.71791399999999,40.677846],"type":"Point"}
}