{
  "type": "Feature",
  "properties": {
    "addr:full":"424 W 33 St New York NY 10001",
    "addr:housenumber":"424",
    "addr:postcode":"10001",
    "addr:street":"W 33 St",
    "iso:country":"US",
    "sg:address":"424 W 33 St",
    "sg:city":"New York",
    "sg:classifiers":[
        {
            "category":"Wholesale",
            "subcategory":"Electrical",
            "type":"Manufacturing & Wholesale Goods"
        }
    ],
    "sg:phone":"+1 212 889 6869",
    "sg:postcode":"10001",
    "sg:province":"NY",
    "sg:tags":[
        "recording",
        "studio"
    ],
    "sg:website":"www.euphonix.com",
    "wof:name":"Euphonix",
    "wof:placetype":"venue"
},
  "geometry": {"coordinates":[-73.99789,40.753003],"type":"Point"}
}