{
  "type": "Feature",
  "properties": {
    "addr:full":"146 Maple St Buffalo NY 14204",
    "addr:housenumber":"146",
    "addr:postcode":"14204",
    "addr:street":"Maple St",
    "iso:country":"US",
    "sg:address":"146 Maple St",
    "sg:city":"Buffalo",
    "sg:classifiers":[
        {
            "category":"Travel",
            "subcategory":"Hotels & Motels",
            "type":"Entertainment"
        }
    ],
    "sg:phone":"+1 716 633 1100",
    "sg:postcode":"14204",
    "sg:province":"NY",
    "sg:website":"www.redroof.com",
    "wof:name":"Red Roof Inns",
    "wof:placetype":"venue"
},
  "geometry": {"coordinates":[-78.85900100000001,42.882702],"type":"Point"}
}