{
  "type": "Feature",
  "properties": {
    "addr:full":"681 E 136th St Bronx NY 10454",
    "addr:housenumber":"681",
    "addr:postcode":"10454",
    "addr:street":"E 136Th St",
    "iso:country":"US",
    "sg:address":"681 E 136th St",
    "sg:city":"Bronx",
    "sg:classifiers":[
        {
            "category":"Personal",
            "type":"Services"
        }
    ],
    "sg:phone":"+1 718 292 1200",
    "sg:postcode":"10454",
    "sg:province":"NY",
    "sg:tags":[
        "towing"
    ],
    "sg:website":"www.jnstowing.com",
    "wof:name":"J & S Towing Inc",
    "wof:placetype":"venue"
},
  "geometry": {"coordinates":[-73.91467799999999,40.803945],"type":"Point"}
}