{
  "type": "Feature",
  "properties": {
    "addr:full":"100 W 57th Street New York NY 10019",
    "addr:housenumber":"100",
    "addr:postcode":"10019",
    "addr:street":"W 57Th Street",
    "iso:country":"US",
    "sg:address":"100 W 57th Street",
    "sg:city":"New York",
    "sg:classifiers":[
        {
            "category":"Arts & Performance",
            "subcategory":"Art Gallery",
            "type":"Entertainment"
        }
    ],
    "sg:phone":"+1 212 242 9001",
    "sg:postcode":"10019",
    "sg:province":"NY",
    "wof:name":"Sarina Tang Fine Art",
    "wof:placetype":"venue"
},
  "geometry": {"coordinates":[-73.977226,40.764458],"type":"Point"}
}