{
  "type": "Feature",
  "properties": {
    "addr:full":"242 E 79th St New York NY 10075",
    "addr:housenumber":"242",
    "addr:postcode":"10075",
    "addr:street":"E 79Th St",
    "iso:country":"US",
    "sg:address":"242 E 79th St",
    "sg:city":"New York",
    "sg:classifiers":[
        {
            "category":"Restaurant",
            "type":"Food & Drink"
        }
    ],
    "sg:phone":"+1 212 288 4888",
    "sg:postcode":"10075",
    "sg:province":"NY",
    "sg:tags":[
        "chinese"
    ],
    "wof:name":"Our Place",
    "wof:placetype":"venue"
},
  "geometry": {"coordinates":[-73.95576,40.773478],"type":"Point"}
}