{
  "type": "Feature",
  "properties": {
    "iso:country":"US",
    "sg:address":"1 W Main St",
    "sg:city":"Dryden",
    "sg:classifiers":[
        {
            "category":"Real Estate",
            "subcategory":"Architect",
            "type":"Services"
        }
    ],
    "sg:phone":"+1   ",
    "sg:postcode":"13053",
    "sg:province":"NY",
    "sg:tags":[
        "firm",
        "design",
        "commercial",
        "architectural",
        "residential"
    ],
    "wof:name":"GA Architects",
    "wof:placetype":"venue"
},
  "geometry": {"coordinates":[-76.29770499999999,42.490559],"type":"Point"}
}