{
  "type": "Feature",
  "properties": {
    "addr:full":"4330 Bullard Ave Bronx NY 10466",
    "addr:housenumber":"4330",
    "addr:postcode":"10466",
    "addr:street":"Bullard Ave",
    "iso:country":"US",
    "sg:address":"4330 Bullard Ave",
    "sg:city":"Bronx",
    "sg:classifiers":[
        {
            "category":"Manufacturing",
            "subcategory":"Musical Instruments",
            "type":"Manufacturing & Wholesale Goods"
        }
    ],
    "sg:phone":"+1 718 994 1613",
    "sg:postcode":"10466",
    "sg:province":"NY",
    "wof:name":"Glasser Violin Bow Mfg Co",
    "wof:placetype":"venue"
},
  "geometry": {"coordinates":[-73.859847,40.89736],"type":"Point"}
}