{
  "type": "Feature",
  "properties": {
    "addr:full":"975 Albany St Schenectady NY 12307",
    "addr:housenumber":"975",
    "addr:postcode":"12307",
    "addr:street":"Albany St",
    "iso:country":"US",
    "sg:address":"975 Albany St",
    "sg:city":"Schenectady",
    "sg:classifiers":[
        {
            "category":"Personal",
            "subcategory":"Barber",
            "type":"Services"
        }
    ],
    "sg:phone":"+1 518 370 5411",
    "sg:postcode":"12307",
    "sg:province":"NY",
    "wof:name":"Mr Marc's Barber & Beauty Shop",
    "wof:placetype":"venue"
},
  "geometry": {"coordinates":[-73.929886,42.801725],"type":"Point"}
}