{
  "type": "Feature",
  "properties": {
    "iso:country":"US",
    "sg:address":"6034 Barclay Rd",
    "sg:city":"Sodus",
    "sg:classifiers":[
        {
            "category":"Building & Trades",
            "subcategory":"Construction",
            "type":"Services"
        }
    ],
    "sg:phone":"+1 315 483 4622",
    "sg:postcode":"14551",
    "sg:province":"NY",
    "sg:tags":[
        "house"
    ],
    "wof:name":"Saxon A Heidenreich",
    "wof:placetype":"venue"
},
  "geometry": {"coordinates":[-77.02434100000001,43.220314],"type":"Point"}
}