{
  "type": "Feature",
  "properties": {
    "iso:country":"US",
    "sg:address":"305 Elmwood Ave",
    "sg:city":"Buffalo",
    "sg:classifiers":[
        {
            "category":"Professional",
            "subcategory":"Advertising",
            "type":"Services"
        }
    ],
    "sg:phone":"+1 716 887 3828",
    "sg:postcode":"14222",
    "sg:province":"NY",
    "sg:tags":[
        "counselor"
    ],
    "wof:name":"Donna Evans Ashby-Marketing",
    "wof:placetype":"venue"
},
  "geometry": {"coordinates":[-78.877028,42.908801],"type":"Point"}
}