{
  "type": "Feature",
  "properties": {
    "iso:country":"US",
    "sg:address":"66 Mamaroneck Rd",
    "sg:city":"Scarsdale",
    "sg:classifiers":[
        {
            "category":"Shopping",
            "subcategory":"Clothing, Apparel, & Fashions",
            "type":"Retail Goods"
        }
    ],
    "sg:phone":"+1   ",
    "sg:postcode":"10583",
    "sg:province":"NY",
    "sg:tags":[
        "ready",
        "accessory"
    ],
    "wof:name":"Cachet Sportswear",
    "wof:placetype":"venue"
},
  "geometry": {"coordinates":[-73.777495,40.99847],"type":"Point"}
}