{
  "type": "Feature",
  "properties": {
    "iso:country":"US",
    "sg:address":"640 W 42nd St",
    "sg:city":"New York",
    "sg:classifiers":[
        {
            "category":"Parking",
            "type":"Transportation"
        }
    ],
    "sg:phone":"+1 212 643 8178",
    "sg:postcode":"10036",
    "sg:province":"NY",
    "sg:tags":[
        "automobile"
    ],
    "wof:name":"Edison River Garage L L C",
    "wof:placetype":"venue"
},
  "geometry": {"coordinates":[-74.00031799999999,40.761466],"type":"Point"}
}