{
  "type": "Feature",
  "properties": {
    "addr:full":"640 W 42nd St New York NY 10036",
    "addr:housenumber":"640",
    "addr:postcode":"10036",
    "addr:street":"W 42Nd St",
    "iso:country":"US",
    "sg:address":"640 W 42nd St",
    "sg:city":"New York",
    "sg:classifiers":[
        {
            "category":"Parking",
            "type":"Transportation"
        }
    ],
    "sg:phone":"+1 212 643 8178",
    "sg:postcode":"10036",
    "sg:province":"NY",
    "sg:tags":[
        "automobile"
    ],
    "wof:name":"Edison River Garage L L C",
    "wof:placetype":"venue"
},
  "geometry": {"coordinates":[-74.00031799999999,40.761466],"type":"Point"}
}