{
  "type": "Feature",
  "properties": {
    "addr:full":"1101 Webster Ave Bronx NY 10456",
    "addr:housenumber":"1101",
    "addr:postcode":"10456",
    "addr:street":"Webster Ave",
    "iso:country":"US",
    "sg:address":"1101 Webster Ave",
    "sg:city":"Bronx",
    "sg:classifiers":[
        {
            "category":"Parking",
            "type":"Transportation"
        }
    ],
    "sg:phone":"+1 718 538 1400",
    "sg:postcode":"10456",
    "sg:province":"NY",
    "sg:tags":[
        "attendant"
    ],
    "wof:name":"Paradise Parking",
    "wof:placetype":"venue"
},
  "geometry": {"coordinates":[-73.91049,40.830737],"type":"Point"}
}