{
  "type": "Feature",
  "properties": {
    "iso:country":"US",
    "sg:address":"37 New Dorp Plaza Suite 201",
    "sg:city":"Staten Island",
    "sg:classifiers":[
        {
            "category":"Professional",
            "subcategory":"Lawyer & Legal Services",
            "type":"Services"
        }
    ],
    "sg:phone":"+1 718 667 8700",
    "sg:postcode":"10306",
    "sg:province":"NY",
    "wof:name":"DeFilippo And Associates, PLLC",
    "wof:placetype":"venue"
},
  "geometry": {"coordinates":[-74.117249,40.57374],"type":"Point"}
}