{
  "type": "Feature",
  "properties": {
    "iso:country":"US",
    "sg:address":"85 W 59 St",
    "sg:city":"New York",
    "sg:classifiers":[
        {
            "category":"Recreation",
            "type":"Entertainment"
        }
    ],
    "sg:phone":"+1 212 974 2250",
    "sg:postcode":"10019",
    "sg:province":"NY",
    "wof:name":"City Climbers Club of New York",
    "wof:placetype":"venue"
},
  "geometry": {"coordinates":[-73.974569,40.764654],"type":"Point"}
}