{
  "type": "Feature",
  "properties": {
    "addr:full":"1865 51st St Brooklyn NY 11204",
    "addr:housenumber":"1865",
    "addr:postcode":"11204",
    "addr:street":"51St St",
    "iso:country":"US",
    "sg:address":"1865 51st St",
    "sg:city":"Brooklyn",
    "sg:classifiers":[
        {
            "category":"Education",
            "subcategory":"School",
            "type":"Public Place"
        }
    ],
    "sg:phone":"+1 718 236 1175",
    "sg:postcode":"11204",
    "sg:province":"NY",
    "wof:name":"Yeshiva Rabbi Solomon Kluger",
    "wof:placetype":"venue"
},
  "geometry": {"coordinates":[-73.98163700000001,40.627041],"type":"Point"}
}