{
  "type": "Feature",
  "properties": {
    "addr:full":"1133 Route 55 Lagrangeville NY 12540",
    "addr:housenumber":"1133",
    "addr:postcode":"12540",
    "addr:street":"Route 55",
    "iso:country":"US",
    "sg:address":"1133 Route 55",
    "sg:city":"Lagrangeville",
    "sg:classifiers":[
        {
            "category":"Professional",
            "subcategory":"Lawyer & Legal Services",
            "type":"Services"
        }
    ],
    "sg:phone":"+1 845 483 0983",
    "sg:postcode":"12540",
    "sg:province":"NY",
    "sg:tags":[
        "plan"
    ],
    "wof:name":"Edmund V Caplicki Jr",
    "wof:placetype":"venue"
},
  "geometry": {"coordinates":[-73.79852200000001,41.671494],"type":"Point"}
}