{
  "type": "Feature",
  "properties": {
    "iso:country":"US",
    "sg:address":"1111 Stewart Ave",
    "sg:city":"Bethpage",
    "sg:classifiers":[
        {
            "category":"Shopping",
            "subcategory":"Computers & Home Electronics",
            "type":"Retail Goods"
        }
    ],
    "sg:phone":"+1   ",
    "sg:postcode":"11714",
    "sg:province":"NY",
    "sg:tags":[
        "radio",
        "television",
        "consumer"
    ],
    "wof:name":"Wiz The",
    "wof:placetype":"venue"
},
  "geometry": {"coordinates":[-73.49412700000001,40.762245],"type":"Point"}
}