{
  "type": "Feature",
  "properties": {
    "iso:country":"US",
    "sg:address":"19 Lyle Rd",
    "sg:city":"Smithboro",
    "sg:classifiers":[
        {
            "category":"Autos & Motor Vehicles",
            "subcategory":"Automobile Sales",
            "type":"Retail Goods"
        }
    ],
    "sg:phone":"+1   ",
    "sg:postcode":"13734",
    "sg:province":"NY",
    "sg:tags":[
        "used"
    ],
    "wof:name":"Lets Trade Cars",
    "wof:placetype":"venue"
},
  "geometry": {"coordinates":[-76.40172,42.03683],"type":"Point"}
}