{
  "type": "Feature",
  "properties": {
    "iso:country":"US",
    "sg:address":"440 E Water St",
    "sg:city":"Elmira",
    "sg:classifiers":[
        {
            "category":"Health Services",
            "subcategory":"Doctor",
            "type":"Services"
        }
    ],
    "sg:phone":"+1 607 733 7163",
    "sg:postcode":"14901",
    "sg:province":"NY",
    "sg:tags":[
        "orthodontist"
    ],
    "wof:name":"Bellohusen Ronald M",
    "wof:placetype":"venue"
},
  "geometry": {"coordinates":[-76.799988,42.088341],"type":"Point"}
}