{
  "type": "Feature",
  "properties": {
    "iso:country":"US",
    "sg:address":"50 S Main St",
    "sg:city":"Belfast",
    "sg:classifiers":[
        {
            "category":"Organizations",
            "subcategory":"Professional Association",
            "type":"Services"
        }
    ],
    "sg:phone":"+1 585 365 9380",
    "sg:postcode":"14711",
    "sg:province":"NY",
    "wof:name":"New York State Assn Of Town",
    "wof:placetype":"venue"
},
  "geometry": {"coordinates":[-78.111963,42.341394],"type":"Point"}
}