{
  "type": "Feature",
  "properties": {
    "addr:full":"284 Jessamine Ave Yonkers NY 10701",
    "addr:housenumber":"284",
    "addr:postcode":"10701",
    "addr:street":"Jessamine Ave",
    "iso:country":"US",
    "sg:address":"284 Jessamine Ave",
    "sg:city":"Yonkers",
    "sg:classifiers":[
        {
            "category":"Building & Trades",
            "subcategory":"Construction",
            "type":"Services"
        }
    ],
    "sg:phone":"+1 914 476 4535",
    "sg:postcode":"10701",
    "sg:province":"NY",
    "sg:tags":[
        "house"
    ],
    "wof:name":"Barreira Const Corp",
    "wof:placetype":"venue"
},
  "geometry": {"coordinates":[-73.868904,40.945822],"type":"Point"}
}