{
  "type": "Feature",
  "properties": {
    "iso:country":"US",
    "sg:address":"13104 Broadway St",
    "sg:city":"Alden",
    "sg:classifiers":[
        {
            "category":"Health Services",
            "subcategory":"Podiatrist",
            "type":"Services"
        }
    ],
    "sg:phone":"+1 716 937 3310",
    "sg:postcode":"14004",
    "sg:province":"NY",
    "wof:name":"Alden Cheektowaga Podiatry",
    "wof:placetype":"venue"
},
  "geometry": {"coordinates":[-78.499284,42.898999],"type":"Point"}
}