{
  "type": "Feature",
  "properties": {
    "addr:full":"29 Westwind Dr Bohemia NY 11716",
    "addr:housenumber":"29",
    "addr:postcode":"11716",
    "addr:street":"Westwind Dr",
    "iso:country":"US",
    "sg:address":"29 Westwind Dr",
    "sg:city":"Bohemia",
    "sg:classifiers":[
        {
            "category":"Professional",
            "subcategory":"Accounting & Tax Preparation",
            "type":"Services"
        }
    ],
    "sg:phone":"+1 631 589 7900",
    "sg:postcode":"11716",
    "sg:province":"NY",
    "sg:tags":[
        "payroll"
    ],
    "sg:website":"www.certpay.com",
    "wof:name":"Certified Payroll & Tax Svc",
    "wof:placetype":"venue"
},
  "geometry": {"coordinates":[-73.117766,40.755359],"type":"Point"}
}