{
  "type": "Feature",
  "properties": {
    "addr:full":"203 Nicholas Ave Johnson City NY 13790",
    "addr:housenumber":"203",
    "addr:postcode":"13790",
    "addr:street":"Nicholas Ave",
    "iso:country":"US",
    "sg:address":"203 Nicholas Ave",
    "sg:city":"Johnson City",
    "sg:classifiers":[
        {
            "category":"Building & Trades",
            "subcategory":"Construction",
            "type":"Services"
        }
    ],
    "sg:phone":"+1 607 797 1333",
    "sg:postcode":"13790",
    "sg:province":"NY",
    "sg:tags":[
        "house",
        "residential"
    ],
    "wof:name":"Gary E Dobransky",
    "wof:placetype":"venue"
},
  "geometry": {"coordinates":[-75.947783,42.126785],"type":"Point"}
}