{
  "type": "Feature",
  "properties": {
    "addr:full":"2655 Richmond Ave Staten Island NY 10314",
    "addr:housenumber":"2655",
    "addr:postcode":"10314",
    "addr:street":"Richmond Ave",
    "iso:country":"US",
    "sg:address":"2655 Richmond Ave",
    "sg:city":"Staten Island",
    "sg:classifiers":[
        {
            "category":"Personal",
            "subcategory":"Beauty Salon",
            "type":"Services"
        }
    ],
    "sg:phone":"+1 718 761 7671",
    "sg:postcode":"10314",
    "sg:province":"NY",
    "wof:name":"Unisex Hair Design Salon",
    "wof:placetype":"venue"
},
  "geometry": {"coordinates":[-74.16588835260001,40.5825743542],"type":"Point"}
}