{
  "type": "Feature",
  "properties": {
    "iso:country":"US",
    "sg:address":"9 Watson Ave",
    "sg:city":"Binghamton",
    "sg:classifiers":[
        {
            "category":"Organizations",
            "subcategory":"Religious Organization",
            "type":"Services"
        }
    ],
    "sg:phone":"+1 607 722 1063",
    "sg:postcode":"13901",
    "sg:province":"NY",
    "sg:tags":[
        "church"
    ],
    "wof:name":"Baha'i Faith",
    "wof:placetype":"venue"
},
  "geometry": {"coordinates":[-75.897535,42.132706],"type":"Point"}
}