{
  "type": "Feature",
  "properties": {
    "iso:country":"US",
    "sg:address":"160 Hill Rise",
    "sg:city":"Calverton",
    "sg:classifiers":[
        {
            "category":"Communications",
            "subcategory":"Film & Video Production",
            "type":"Services"
        }
    ],
    "sg:phone":"+1   ",
    "sg:postcode":"11933",
    "sg:province":"NY",
    "sg:tags":[
        "motion"
    ],
    "wof:name":"Hollywood East New York",
    "wof:placetype":"venue"
},
  "geometry": {"coordinates":[-72.739824,40.902358],"type":"Point"}
}