{
  "type": "Feature",
  "properties": {
    "iso:country":"US",
    "sg:address":"12 Monroe Ave",
    "sg:city":"Hicksville",
    "sg:classifiers":[
        {
            "category":"Professional",
            "subcategory":"Lawyer & Legal Services",
            "type":"Services"
        }
    ],
    "sg:phone":"+1 516 933 9760",
    "sg:postcode":"11801",
    "sg:province":"NY",
    "sg:tags":[
        "attorney"
    ],
    "wof:name":"Dino Di Rienzo Law Offices",
    "wof:placetype":"venue"
},
  "geometry": {"coordinates":[-73.53093,40.760764],"type":"Point"}
}