{
  "type": "Feature",
  "properties": {
    "addr:full":"225 Park Pl Apt 5E Brooklyn NY 11238",
    "addr:housenumber":"225",
    "addr:postcode":"11238",
    "addr:street":"Park Pl Apt 5E",
    "iso:country":"US",
    "sg:address":"225 Park Pl Apt 5E",
    "sg:city":"Brooklyn",
    "sg:classifiers":[
        {
            "category":"Professional",
            "subcategory":"Art Services",
            "type":"Services"
        }
    ],
    "sg:phone":"+1 917 674 1477",
    "sg:postcode":"11238",
    "sg:province":"NY",
    "sg:tags":[
        "designer",
        "display",
        "producer"
    ],
    "wof:name":"Jumpseed Design",
    "wof:placetype":"venue"
},
  "geometry": {"coordinates":[-73.970516,40.67704],"type":"Point"}
}