{
  "type": "Feature",
  "properties": {
    "addr:full":"4261 Austin Blvd Island Park NY 11558",
    "addr:housenumber":"4261",
    "addr:postcode":"11558",
    "addr:street":"Austin Blvd;Park",
    "iso:country":"US",
    "sg:address":"4261 Austin Blvd",
    "sg:city":"Island Park",
    "sg:classifiers":[
        {
            "category":"Bagels",
            "type":"Food & Drink"
        },
        {
            "category":"Coffee & Tea",
            "type":"Food & Drink"
        },
        {
            "category":"Food & Beverages",
            "subcategory":"Bakery",
            "type":"Retail Goods"
        },
        {
            "category":"Bakery",
            "type":"Food & Drink"
        },
        {
            "category":"Donuts",
            "type":"Food & Drink"
        }
    ],
    "sg:menulink":"http://www.allmenus.com/ny/island-park/138438-dunkin-donuts/menu/",
    "sg:phone":"+1 518 783 2063",
    "sg:postcode":"11558",
    "sg:province":"NY",
    "sg:tags":[
        "coffee",
        "tea",
        "american",
        "bagel",
        "bakery",
        "pastry"
    ],
    "wof:name":"Dunkin' Donuts",
    "wof:placetype":"venue"
},
  "geometry": {"coordinates":[-73.649365,40.605203],"type":"Point"}
}