{
  "type": "Feature",
  "properties": {
    "addr:full":"44 Ash St Brooklyn NY 11222",
    "addr:housenumber":"44",
    "addr:postcode":"11222",
    "addr:street":"Ash St",
    "iso:country":"US",
    "sg:address":"44 Ash St",
    "sg:city":"Brooklyn",
    "sg:classifiers":[
        {
            "category":"Shopping",
            "subcategory":"Clothing, Apparel, & Fashions",
            "type":"Retail Goods"
        }
    ],
    "sg:phone":"+1   ",
    "sg:postcode":"11222",
    "sg:province":"NY",
    "wof:name":"HI Style",
    "wof:placetype":"venue"
},
  "geometry": {"coordinates":[-73.95469,40.737952],"type":"Point"}
}