{
  "type": "Feature",
  "properties": {
    "addr:full":"335 E Fordham Rd Bronx NY 10458",
    "addr:housenumber":"335",
    "addr:postcode":"10458",
    "addr:street":"E Fordham Rd",
    "iso:country":"US",
    "sg:address":"335 E Fordham Rd",
    "sg:city":"Bronx",
    "sg:classifiers":[
        {
            "category":"Shopping",
            "subcategory":"Jewelry",
            "type":"Retail Goods"
        }
    ],
    "sg:phone":"+1 718 562 3916",
    "sg:postcode":"10458",
    "sg:province":"NY",
    "sg:tags":[
        "diamond"
    ],
    "wof:name":"Oro Uno Jewelry Inc",
    "wof:placetype":"venue"
},
  "geometry": {"coordinates":[-73.892962,40.861928],"type":"Point"}
}