{
  "type": "Feature",
  "properties": {
    "iso:country":"US",
    "sg:address":"148 Madison Ave",
    "sg:city":"New York",
    "sg:classifiers":[
        {
            "category":"Wholesale",
            "subcategory":"Office Equipment",
            "type":"Manufacturing & Wholesale Goods"
        }
    ],
    "sg:phone":"+1 212 779 7171",
    "sg:postcode":"10016",
    "sg:province":"NY",
    "sg:tags":[
        "machine",
        "duplicating",
        "copying"
    ],
    "wof:name":"Century Business Solutions",
    "wof:placetype":"venue"
},
  "geometry": {"coordinates":[-73.98425899999999,40.745974],"type":"Point"}
}