{
  "type": "Feature",
  "properties": {
    "addr:full":"7523 State Hwy 20A Bloomfield NY 14469",
    "addr:housenumber":"7523",
    "addr:postcode":"14469",
    "addr:street":"State Hwy 20A",
    "iso:country":"US",
    "sg:address":"7523 State Hwy 20A",
    "sg:city":"Bloomfield",
    "sg:classifiers":[
        {
            "category":"Retail",
            "subcategory":"Laundry & Dry Cleaning",
            "type":"Services"
        }
    ],
    "sg:phone":"+1 585 229 2722",
    "sg:postcode":"14469",
    "sg:province":"NY",
    "wof:name":"Bristol View Carpet Cleaning",
    "wof:placetype":"venue"
},
  "geometry": {"coordinates":[-77.443929,42.822787],"type":"Point"}
}