{
  "type": "Feature",
  "properties": {
    "addr:full":"330 Harrison Dr Centerport NY 11721",
    "addr:housenumber":"330",
    "addr:postcode":"11721",
    "addr:street":"Harrison Dr",
    "iso:country":"US",
    "sg:address":"330 Harrison Dr",
    "sg:city":"Centerport",
    "sg:classifiers":[
        {
            "category":"Building & Trades",
            "subcategory":"Construction",
            "type":"Services"
        }
    ],
    "sg:phone":"+1 631 421 9556",
    "sg:postcode":"11721",
    "sg:province":"NY",
    "sg:tags":[
        "contractor"
    ],
    "wof:name":"Nelson W Roberts Masonry",
    "wof:placetype":"venue"
},
  "geometry": {"coordinates":[-73.38040700000001,40.895477],"type":"Point"}
}