{
  "type": "Feature",
  "properties": {
    "iso:country":"US",
    "sg:address":"8427 Penelope Avenue",
    "sg:city":"Middle Village",
    "sg:classifiers":[
        {
            "category":"Health Services",
            "subcategory":"Dentist",
            "type":"Services"
        }
    ],
    "sg:phone":"+1 718 424 5336",
    "sg:postcode":"11379",
    "sg:province":"NY",
    "wof:name":"Kiel Hugo DDS",
    "wof:placetype":"venue"
},
  "geometry": {"coordinates":[-73.86899699999999,40.722172],"type":"Point"}
}