{
  "type": "Feature",
  "properties": {
    "addr:full":"727 Katan Ave Staten Island NY 10312",
    "addr:housenumber":"727",
    "addr:postcode":"10312",
    "addr:street":"Katan Ave",
    "iso:country":"US",
    "sg:address":"727 Katan Ave",
    "sg:city":"Staten Island",
    "sg:classifiers":[
        {
            "category":"Wholesale",
            "subcategory":"Non-durable Goods",
            "type":"Manufacturing & Wholesale Goods"
        }
    ],
    "sg:phone":"+1 718 605 1490",
    "sg:postcode":"10312",
    "sg:province":"NY",
    "sg:tags":[
        "sponge",
        "specialty",
        "impregnated"
    ],
    "wof:name":"Soapers Inc",
    "wof:placetype":"venue"
},
  "geometry": {"coordinates":[-74.170761,40.550294],"type":"Point"}
}