{
  "type": "Feature",
  "properties": {
    "iso:country":"US",
    "sg:address":"80 Irwin Ave",
    "sg:city":"Middletown",
    "sg:classifiers":[
        {
            "category":"Professional",
            "subcategory":"Lawyer & Legal Services",
            "type":"Services"
        }
    ],
    "sg:phone":"+1 845 342 4900",
    "sg:postcode":"10940",
    "sg:province":"NY",
    "sg:tags":[
        "attorney"
    ],
    "wof:name":"Christopher Dalgoutte",
    "wof:placetype":"venue"
},
  "geometry": {"coordinates":[-74.403622,41.450676],"type":"Point"}
}