{
  "type": "Feature",
  "properties": {
    "addr:full":"87 Woodman Park Rochester NY 14609",
    "addr:housenumber":"87",
    "addr:postcode":"14609",
    "addr:street":"Woodman Park",
    "iso:country":"US",
    "sg:address":"87 Woodman Park",
    "sg:city":"Rochester",
    "sg:classifiers":[
        {
            "category":"Building & Trades",
            "subcategory":"Construction",
            "type":"Services"
        }
    ],
    "sg:phone":"+1 585 233 6289",
    "sg:postcode":"14609",
    "sg:province":"NY",
    "sg:tags":[
        "home",
        "commercial",
        "remodeling",
        "general"
    ],
    "wof:name":"A Best Construction Inc",
    "wof:placetype":"venue"
},
  "geometry": {"coordinates":[-77.56047,43.177105],"type":"Point"}
}