{
  "type": "Feature",
  "properties": {
    "addr:full":"1 Ogden Mills Plz Cohoes NY 12047",
    "addr:housenumber":"1",
    "addr:postcode":"12047",
    "addr:street":"Ogden Mills Plz",
    "iso:country":"US",
    "sg:address":"1 Ogden Mills Plz",
    "sg:city":"Cohoes",
    "sg:classifiers":[
        {
            "category":"Real Estate",
            "subcategory":"Real Estate Operator",
            "type":"Services"
        }
    ],
    "sg:phone":"+1 518 235 9508",
    "sg:postcode":"12047",
    "sg:province":"NY",
    "sg:tags":[
        "building",
        "nonresidential"
    ],
    "wof:name":"American Properties Team Inc",
    "wof:placetype":"venue"
},
  "geometry": {"coordinates":[-73.70237299999999,42.774437],"type":"Point"}
}