{
  "type": "Feature",
  "properties": {
    "addr:full":"54 Adelaide St Rochester NY 14606",
    "addr:housenumber":"54",
    "addr:postcode":"14606",
    "addr:street":"Adelaide St",
    "iso:country":"US",
    "sg:address":"54 Adelaide St",
    "sg:city":"Rochester",
    "sg:classifiers":[
        {
            "category":"Wholesale",
            "subcategory":"Auto Parts",
            "type":"Manufacturing & Wholesale Goods"
        }
    ],
    "sg:phone":"+1 585 458 3970",
    "sg:postcode":"14606",
    "sg:province":"NY",
    "sg:tags":[
        "automobile",
        "supply"
    ],
    "wof:name":"Rick's Distributing",
    "wof:placetype":"venue"
},
  "geometry": {"coordinates":[-77.66777,43.166347],"type":"Point"}
}