{
  "type": "Feature",
  "properties": {
    "iso:country":"US",
    "sg:address":"3075 Gracie Rd",
    "sg:city":"Cortland",
    "sg:classifiers":[
        {
            "category":"Government",
            "subcategory":"Office",
            "type":"Public Place"
        }
    ],
    "sg:phone":"+1 607 753 9391",
    "sg:postcode":"13045",
    "sg:province":"NY",
    "wof:name":"US Geological Servey",
    "wof:placetype":"venue"
},
  "geometry": {"coordinates":[-76.244591,42.557162],"type":"Point"}
}