{
  "type": "Feature",
  "properties": {
    "iso:country":"US",
    "sg:address":"34 Pleasant Ridge Rd",
    "sg:city":"Spring Valley",
    "sg:classifiers":[
        {
            "category":"Insurance",
            "subcategory":"Insurance Agent",
            "type":"Services"
        }
    ],
    "sg:phone":"+1 845 354 9397",
    "sg:postcode":"10977",
    "sg:province":"NY",
    "wof:name":"Claimstop Inc",
    "wof:placetype":"venue"
},
  "geometry": {"coordinates":[-74.062455,41.143828],"type":"Point"}
}