{
  "type": "Feature",
  "properties": {
    "iso:country":"US",
    "sg:address":"129 Graef Rd",
    "sg:city":"Norwich",
    "sg:classifiers":[
        {
            "category":"Building & Trades",
            "subcategory":"Construction",
            "type":"Services"
        }
    ],
    "sg:phone":"+1 607 336 2750",
    "sg:postcode":"13815",
    "sg:province":"NY",
    "sg:tags":[
        "house"
    ],
    "wof:name":"S F Construction",
    "wof:placetype":"venue"
},
  "geometry": {"coordinates":[-75.48095000000001,42.531759],"type":"Point"}
}