{
  "type": "Feature",
  "properties": {
    "addr:full":"33 E End Ave New York NY 10028",
    "addr:housenumber":"33",
    "addr:postcode":"10028",
    "addr:street":"E End Ave",
    "iso:country":"US",
    "sg:address":"33 E End Ave",
    "sg:city":"New York",
    "sg:classifiers":[
        {
            "category":"Real Estate",
            "subcategory":"Real Estate Operator",
            "type":"Services"
        }
    ],
    "sg:phone":"+1 212 744 8219",
    "sg:postcode":"10028",
    "sg:province":"NY",
    "sg:tags":[
        "apartment"
    ],
    "wof:name":"River View House",
    "wof:placetype":"venue"
},
  "geometry": {"coordinates":[-73.9487,40.7724],"type":"Point"}
}