{
  "type": "Feature",
  "properties": {
    "iso:country":"US",
    "sg:address":"3116 Lawson Blvd",
    "sg:city":"Oceanside",
    "sg:classifiers":[
        {
            "category":"Restaurant",
            "type":"Food & Drink"
        }
    ],
    "sg:phone":"+1 516 678 3592",
    "sg:postcode":"11572",
    "sg:province":"NY",
    "sg:tags":[
        "deli",
        "delicatessen"
    ],
    "wof:name":"Lawson Delicatessen",
    "wof:placetype":"venue"
},
  "geometry": {"coordinates":[-73.65419799999999,40.635201],"type":"Point"}
}