{
  "type": "Feature",
  "properties": {
    "iso:country":"US",
    "sg:address":"55 E 65 St",
    "sg:city":"New York",
    "sg:classifiers":[
        {
            "category":"Professional",
            "type":"Services"
        }
    ],
    "sg:phone":"+1 917 595 4179",
    "sg:postcode":"10065",
    "sg:province":"NY",
    "sg:tags":[
        "establishment"
    ],
    "wof:name":"Inter Section AA",
    "wof:placetype":"venue"
},
  "geometry": {"coordinates":[-73.967501,40.766995],"type":"Point"}
}