{
  "type": "Feature",
  "properties": {
    "iso:country":"US",
    "sg:address":"88 Bowery",
    "sg:city":"New York",
    "sg:classifiers":[
        {
            "category":"Shopping",
            "subcategory":"Jewelry",
            "type":"Retail Goods"
        }
    ],
    "sg:phone":"+1 212 941 7756",
    "sg:postcode":"10013",
    "sg:province":"NY",
    "sg:tags":[
        "jeweler"
    ],
    "wof:name":"Natalie Creative Jewelry Inc",
    "wof:placetype":"venue"
},
  "geometry": {"coordinates":[-73.996078,40.716196],"type":"Point"}
}