{
  "type": "Feature",
  "properties": {
    "iso:country":"US",
    "sg:address":"443 Muselbeck Rd",
    "sg:city":"Pattersonville",
    "sg:classifiers":[
        {
            "category":"Building & Trades",
            "subcategory":"Construction",
            "type":"Services"
        }
    ],
    "sg:phone":"+1 518 887 2919",
    "sg:postcode":"12137",
    "sg:province":"NY",
    "sg:tags":[
        "general",
        "contractor"
    ],
    "wof:name":"Zappia Construction",
    "wof:placetype":"venue"
},
  "geometry": {"coordinates":[-74.093476,42.867226],"type":"Point"}
}