{
  "type": "Feature",
  "properties": {
    "addr:full":"5 Greenwich Ave New York NY 10014",
    "addr:housenumber":"5",
    "addr:postcode":"10014",
    "addr:street":"Greenwich Ave",
    "iso:country":"US",
    "sg:address":"5 Greenwich Ave",
    "sg:city":"New York",
    "sg:classifiers":[
        {
            "category":"Health Services",
            "subcategory":"Optometrist",
            "type":"Services"
        }
    ],
    "sg:phone":"+1 212 645 1395",
    "sg:postcode":"10014",
    "sg:province":"NY",
    "sg:website":"www.cohensfashionoptical.com",
    "wof:name":"Cohen's Fashion Optical",
    "wof:placetype":"venue"
},
  "geometry": {"coordinates":[-73.999555,40.73361],"type":"Point"}
}