{
  "type": "Feature",
  "properties": {
    "addr:full":"61 Chichester Rd Huntington NY 11743",
    "addr:housenumber":"61",
    "addr:postcode":"11743",
    "addr:street":"Chichester Rd",
    "iso:country":"US",
    "sg:address":"61 Chichester Rd",
    "sg:city":"Huntington",
    "sg:classifiers":[
        {
            "category":"Professional",
            "subcategory":"Lawyer & Legal Services",
            "type":"Services"
        }
    ],
    "sg:phone":"+1 631 425 4155",
    "sg:postcode":"11743",
    "sg:province":"NY",
    "sg:tags":[
        "attorney"
    ],
    "wof:name":"Mielo & Stasko LLP",
    "wof:placetype":"venue"
},
  "geometry": {"coordinates":[-73.421397,40.819958],"type":"Point"}
}