{
  "type": "Feature",
  "properties": {
    "iso:country":"US",
    "sg:address":"205 Coachman Pl E",
    "sg:city":"Syosset",
    "sg:classifiers":[
        {
            "category":"Wholesale",
            "subcategory":"Drugs",
            "type":"Manufacturing & Wholesale Goods"
        }
    ],
    "sg:phone":"+1 516 921 6100",
    "sg:postcode":"11791",
    "sg:province":"NY",
    "sg:tags":[
        "perfume"
    ],
    "wof:name":"Eternal Love Parfums Corp",
    "wof:placetype":"venue"
},
  "geometry": {"coordinates":[-73.51499200000001,40.815233],"type":"Point"}
}