{
  "type": "Feature",
  "properties": {
    "addr:full":"1625 Fulton Ave Bronx NY 10457",
    "addr:housenumber":"1625",
    "addr:postcode":"10457",
    "addr:street":"Fulton Ave",
    "iso:country":"US",
    "sg:address":"1625 Fulton Ave",
    "sg:city":"Bronx",
    "sg:classifiers":[
        {
            "category":"Real Estate",
            "subcategory":"Real Estate Agent",
            "type":"Services"
        }
    ],
    "sg:phone":"+1 718 731 3440",
    "sg:postcode":"10457",
    "sg:province":"NY",
    "wof:name":"1992 Fulton Realty",
    "wof:placetype":"venue"
},
  "geometry": {"coordinates":[-73.89840100000001,40.840565],"type":"Point"}
}