{
  "type": "Feature",
  "properties": {
    "addr:full":"1059 Ridge Rd W Rochester NY 14615",
    "addr:housenumber":"1059",
    "addr:postcode":"14615",
    "addr:street":"Ridge Rd W",
    "iso:country":"US",
    "sg:address":"1059 Ridge Rd W",
    "sg:city":"Rochester",
    "sg:classifiers":[
        {
            "category":"Professional",
            "subcategory":"Computer Services",
            "type":"Services"
        }
    ],
    "sg:phone":"+1 585 581 4106",
    "sg:postcode":"14615",
    "sg:province":"NY",
    "sg:tags":[
        "consulting"
    ],
    "wof:name":"Electronic Data Systems Corp",
    "wof:placetype":"venue"
},
  "geometry": {"coordinates":[-77.659105,43.204163],"type":"Point"}
}