{
  "type": "Feature",
  "properties": {
    "addr:full":"266 Bleecker St Brooklyn NY 11237",
    "addr:housenumber":"266",
    "addr:postcode":"11237",
    "addr:street":"Bleecker St",
    "iso:country":"US",
    "sg:address":"266 Bleecker St",
    "sg:city":"Brooklyn",
    "sg:classifiers":[
        {
            "category":"Deli",
            "type":"Food & Drink"
        },
        {
            "category":"Food & Beverages",
            "subcategory":"Bakery",
            "type":"Retail Goods"
        }
    ],
    "sg:phone":"+1 718 366 6175",
    "sg:postcode":"11237",
    "sg:province":"NY",
    "sg:tags":[
        "sandwich"
    ],
    "wof:name":"El Paisa Deli",
    "wof:placetype":"venue"
},
  "geometry": {"coordinates":[-73.917052,40.699106],"type":"Point"}
}