{
  "type": "Feature",
  "properties": {
    "addr:full":"10807 Bennett Rd Dunkirk NY 14048",
    "addr:housenumber":"10807",
    "addr:postcode":"14048",
    "addr:street":"Bennett Rd",
    "iso:country":"US",
    "sg:address":"10807 Bennett Rd",
    "sg:city":"Dunkirk",
    "sg:classifiers":[
        {
            "category":"Organizations",
            "subcategory":"Community Association",
            "type":"Services"
        }
    ],
    "sg:phone":"+1 716 366 2255",
    "sg:postcode":"14048",
    "sg:province":"NY",
    "sg:tags":[
        "student",
        "faculty"
    ],
    "wof:name":"Faculty Student Assoc Jamestwn",
    "wof:placetype":"venue"
},
  "geometry": {"coordinates":[-79.31802999999999,42.468568],"type":"Point"}
}