{
  "type": "Feature",
  "properties": {
    "iso:country":"US",
    "sg:address":"3949 Main St",
    "sg:city":"Warrensburg",
    "sg:classifiers":[
        {
            "category":"Wholesale",
            "subcategory":"Auto Parts",
            "type":"Manufacturing & Wholesale Goods"
        }
    ],
    "sg:phone":"+1 518 623 2881",
    "sg:postcode":"12885",
    "sg:province":"NY",
    "sg:tags":[
        "supply"
    ],
    "wof:name":"NAPA Auto Parts",
    "wof:placetype":"venue"
},
  "geometry": {"coordinates":[-73.78114600000001,43.500178],"type":"Point"}
}