{
  "type": "Feature",
  "properties": {
    "addr:full":"1211 E 21st St Brooklyn NY 11210",
    "addr:housenumber":"1211",
    "addr:postcode":"11210",
    "addr:street":"E 21St St",
    "iso:country":"US",
    "sg:address":"1211 E 21st St",
    "sg:city":"Brooklyn",
    "sg:classifiers":[
        {
            "category":"Organizations",
            "subcategory":"Religious Organization",
            "type":"Services"
        }
    ],
    "sg:phone":"+1 718 253 3780",
    "sg:postcode":"11210",
    "sg:province":"NY",
    "sg:tags":[
        "clergy"
    ],
    "wof:name":"Sirher Kramer",
    "wof:placetype":"venue"
},
  "geometry": {"coordinates":[-73.955144,40.625606],"type":"Point"}
}