{
  "type": "Feature",
  "properties": {
    "addr:full":"135 Main St Port Washington NY 11050",
    "addr:housenumber":"135",
    "addr:postcode":"11050",
    "addr:street":"Main St",
    "iso:country":"US",
    "sg:address":"135 Main St",
    "sg:city":"Port Washington",
    "sg:classifiers":[
        {
            "category":"Shopping",
            "subcategory":"Mobile Phones",
            "type":"Retail Goods"
        }
    ],
    "sg:phone":"+1 516 944 5600",
    "sg:postcode":"11050",
    "sg:province":"NY",
    "wof:name":"Wireless Media of Port Washington",
    "wof:placetype":"venue"
},
  "geometry": {"coordinates":[-73.690399,40.830299],"type":"Point"}
}