{
  "type": "Feature",
  "properties": {
    "iso:country":"US",
    "sg:address":"2601 Guilderland Ave",
    "sg:city":"Schenectady",
    "sg:classifiers":[
        {
            "category":"Shopping",
            "subcategory":"Stationery & Office Supplies",
            "type":"Retail Goods"
        },
        {
            "category":"Professional",
            "subcategory":"Printing & Photocopies",
            "type":"Services"
        },
        {
            "category":"Wholesale",
            "subcategory":"Computers",
            "type":"Manufacturing & Wholesale Goods"
        }
    ],
    "sg:phone":"+1 518 372 3995",
    "sg:postcode":"12306",
    "sg:province":"NY",
    "sg:tags":[
        "equipment",
        "store",
        "envelope",
        "duplicating",
        "copying"
    ],
    "wof:name":"National Direct Reprographics",
    "wof:placetype":"venue"
},
  "geometry": {"coordinates":[-73.96928800000001,42.789234],"type":"Point"}
}