{
  "type": "Feature",
  "properties": {
    "addr:full":"200 Princeton Ave Staten Island NY 10306",
    "addr:housenumber":"200",
    "addr:postcode":"10306",
    "addr:street":"Princeton Ave",
    "iso:country":"US",
    "sg:address":"200 Princeton Ave",
    "sg:city":"Staten Island",
    "sg:classifiers":[
        {
            "category":"Building & Trades",
            "subcategory":"Construction",
            "type":"Services"
        }
    ],
    "sg:phone":"+1 718 351 0443",
    "sg:postcode":"10306",
    "sg:province":"NY",
    "sg:tags":[
        "excavation",
        "contractor"
    ],
    "wof:name":"J E J Excavating Corp",
    "wof:placetype":"venue"
},
  "geometry": {"coordinates":[-74.114816,40.566161],"type":"Point"}
}