{
  "type": "Feature",
  "properties": {
    "addr:full":"1804 Main St Keeseville NY 12944",
    "addr:housenumber":"1804",
    "addr:postcode":"12944",
    "addr:street":"Main St",
    "iso:country":"US",
    "sg:address":"1804 Main St",
    "sg:city":"Keeseville",
    "sg:classifiers":[
        {
            "category":"Organizations",
            "subcategory":"Religious Organization",
            "type":"Services"
        }
    ],
    "sg:phone":"+1 518 834 7100",
    "sg:postcode":"12944",
    "sg:province":"NY",
    "sg:tags":[
        "church"
    ],
    "wof:name":"Catholic Community-Keeseville",
    "wof:placetype":"venue"
},
  "geometry": {"coordinates":[-73.484398,44.506099],"type":"Point"}
}