{
  "type": "Feature",
  "properties": {
    "iso:country":"US",
    "sg:address":"351 Walker St",
    "sg:city":"Staten Island",
    "sg:classifiers":[
        {
            "category":"Food & Beverages",
            "subcategory":"Candy",
            "type":"Retail Goods"
        }
    ],
    "sg:phone":"+1 718 556 2838",
    "sg:postcode":"10303",
    "sg:province":"NY",
    "sg:tags":[
        "store"
    ],
    "wof:name":"Verrazano Wholesale Dist Inc",
    "wof:placetype":"venue"
},
  "geometry": {"coordinates":[-74.151177,40.631886],"type":"Point"}
}