{
  "type": "Feature",
  "properties": {
    "iso:country":"US",
    "sg:address":"131 Andrus St",
    "sg:city":"Malone",
    "sg:classifiers":[
        {
            "category":"Wholesale",
            "subcategory":"Electrical",
            "type":"Manufacturing & Wholesale Goods"
        }
    ],
    "sg:phone":"+1 518 483 1555",
    "sg:postcode":"12953",
    "sg:province":"NY",
    "sg:tags":[
        "electric",
        "motor"
    ],
    "wof:name":"Sullivan Electric",
    "wof:placetype":"venue"
},
  "geometry": {"coordinates":[-74.274495,44.845268],"type":"Point"}
}