{
  "type": "Feature",
  "properties": {
    "addr:full":"55 W 39 St New York NY 10018",
    "addr:housenumber":"55",
    "addr:postcode":"10018",
    "addr:street":"W 39 St",
    "iso:country":"US",
    "sg:address":"55 W 39 St",
    "sg:city":"New York",
    "sg:classifiers":[
        {
            "category":"Insurance",
            "subcategory":"Hazard Insurance",
            "type":"Services"
        }
    ],
    "sg:phone":"+1 212 580 9092",
    "sg:postcode":"10018",
    "sg:province":"NY",
    "sg:tags":[
        "funds",
        "pension"
    ],
    "wof:name":"I A T S E Nat Pension Fund",
    "wof:placetype":"venue"
},
  "geometry": {"coordinates":[-73.98411,40.752252],"type":"Point"}
}