{
  "type": "Feature",
  "properties": {
    "addr:full":"1805 University Ave Bronx NY 10453",
    "addr:housenumber":"1805",
    "addr:postcode":"10453",
    "addr:street":"University Ave",
    "iso:country":"US",
    "sg:address":"1805 University Ave",
    "sg:city":"Bronx",
    "sg:classifiers":[
        {
            "category":"Banks & Credit Unions",
            "subcategory":"Financial Services",
            "type":"Services"
        }
    ],
    "sg:phone":"+1 718 466 1225",
    "sg:postcode":"10453",
    "sg:province":"NY",
    "sg:tags":[
        "company",
        "holding"
    ],
    "wof:name":"University Holding",
    "wof:placetype":"venue"
},
  "geometry": {"coordinates":[-73.91499899999999,40.851008],"type":"Point"}
}