{
  "type": "Feature",
  "properties": {
    "addr:full":"50 Fountain Park Buffalo NY 14223",
    "addr:housenumber":"50",
    "addr:postcode":"14223",
    "iso:country":"US",
    "sg:address":"50 Fountain Park",
    "sg:city":"Buffalo",
    "sg:classifiers":[
        {
            "category":"Professional",
            "subcategory":"Accounting & Tax Preparation",
            "type":"Services"
        }
    ],
    "sg:phone":"+1 716 843 5000",
    "sg:postcode":"14223",
    "sg:province":"NY",
    "sg:tags":[
        "account",
        "management",
        "accountant",
        "auditor",
        "consult",
        "public",
        "certified"
    ],
    "sg:website":"www.ey.com",
    "wof:name":"Ernst & Young LLP",
    "wof:placetype":"venue"
},
  "geometry": {"coordinates":[-78.824359,42.977909],"type":"Point"}
}