{
  "type": "Feature",
  "properties": {
    "iso:country":"US",
    "sg:address":"781 Madison Ave",
    "sg:city":"Albany",
    "sg:classifiers":[
        {
            "category":"Retail",
            "subcategory":"Laundry & Dry Cleaning",
            "type":"Services"
        },
        {
            "category":"Building & Trades",
            "subcategory":"Cleaning & Sanitation",
            "type":"Services"
        }
    ],
    "sg:phone":"+1 518 465 2345",
    "sg:postcode":"12208",
    "sg:province":"NY",
    "sg:tags":[
        "cleaner",
        "janitorial",
        "drapery",
        "curtain"
    ],
    "wof:name":"Towne Cleaners",
    "wof:placetype":"venue"
},
  "geometry": {"coordinates":[-73.779861,42.65942],"type":"Point"}
}