{
  "type": "Feature",
  "properties": {
    "iso:country":"US",
    "sg:address":"909 Center St",
    "sg:city":"Horseheads",
    "sg:classifiers":[
        {
            "category":"Personal",
            "type":"Services"
        }
    ],
    "sg:phone":"+1 607 739 7598",
    "sg:postcode":"14845",
    "sg:province":"NY",
    "sg:tags":[
        "therapist",
        "massage"
    ],
    "wof:name":"Four Fathers Therapeutic",
    "wof:placetype":"venue"
},
  "geometry": {"coordinates":[-76.822739,42.159146],"type":"Point"}
}