{
  "type": "Feature",
  "properties": {
    "addr:full":"937 Madison Ave New York NY 10021",
    "addr:housenumber":"937",
    "addr:postcode":"10021",
    "addr:street":"Madison Ave",
    "iso:country":"US",
    "sg:address":"937 Madison Ave",
    "sg:city":"New York",
    "sg:classifiers":[
        {
            "category":"Shopping",
            "type":"Retail Goods"
        }
    ],
    "sg:phone":"+1   ",
    "sg:postcode":"10021",
    "sg:province":"NY",
    "sg:tags":[
        "decoration",
        "art"
    ],
    "wof:name":"Sol L Quinto L C",
    "wof:placetype":"venue"
},
  "geometry": {"coordinates":[-73.964016,40.77357],"type":"Point"}
}