{
  "type": "Feature",
  "properties": {
    "iso:country":"US",
    "sg:address":"3826 Maple St",
    "sg:city":"Seaford",
    "sg:classifiers":[
        {
            "category":"Retail",
            "subcategory":"Laundry & Dry Cleaning",
            "type":"Services"
        }
    ],
    "sg:phone":"+1 516 679 2580",
    "sg:postcode":"11783",
    "sg:province":"NY",
    "sg:tags":[
        "cleaners"
    ],
    "wof:name":"Cleanforce",
    "wof:placetype":"venue"
},
  "geometry": {"coordinates":[-73.487898,40.672195],"type":"Point"}
}