{
  "type": "Feature",
  "properties": {
    "addr:full":"2 Petty Ln Medford NY 11763",
    "addr:housenumber":"2",
    "addr:postcode":"11763",
    "addr:street":"Petty Ln",
    "iso:country":"US",
    "sg:address":"2 Petty Ln",
    "sg:city":"Medford",
    "sg:classifiers":[
        {
            "category":"Food & Beverages",
            "subcategory":"Groceries & Convenience Stores",
            "type":"Retail Goods"
        }
    ],
    "sg:phone":"+1   ",
    "sg:postcode":"11763",
    "sg:province":"NY",
    "wof:name":"A & D Food & Gas",
    "wof:placetype":"venue"
},
  "geometry": {"coordinates":[-73.01459699999999,40.82081],"type":"Point"}
}