{
  "type": "Feature",
  "properties": {
    "iso:country":"US",
    "sg:address":"177 Remsen St",
    "sg:city":"Cohoes",
    "sg:classifiers":[
        {
            "category":"Restaurant",
            "type":"Food & Drink"
        }
    ],
    "sg:phone":"+1 518 237 6808",
    "sg:postcode":"12047",
    "sg:province":"NY",
    "wof:name":"Fortune Star",
    "wof:placetype":"venue"
},
  "geometry": {"coordinates":[-73.700669,42.771994],"type":"Point"}
}