{
  "type": "Feature",
  "properties": {
    "iso:country":"US",
    "sg:address":"215 E Main St",
    "sg:city":"Smithtown",
    "sg:classifiers":[
        {
            "category":"Health Services",
            "subcategory":"Doctor",
            "type":"Services"
        }
    ],
    "sg:phone":"+1 631 265 5858",
    "sg:postcode":"11787",
    "sg:province":"NY",
    "wof:name":"Lerner Anna MD",
    "wof:placetype":"venue"
},
  "geometry": {"coordinates":[-73.18559999999999,40.8563],"type":"Point"}
}