{
  "type": "Feature",
  "properties": {
    "iso:country":"US",
    "sg:address":"7799 Wetzel Rd",
    "sg:city":"Liverpool",
    "sg:classifiers":[
        {
            "category":"Building & Trades",
            "subcategory":"Construction",
            "type":"Services"
        }
    ],
    "sg:phone":"+1 315 457 2280",
    "sg:postcode":"13090",
    "sg:province":"NY",
    "sg:tags":[
        "contractor"
    ],
    "wof:name":"Russ Newel Heli-ARC Field Svc",
    "wof:placetype":"venue"
},
  "geometry": {"coordinates":[-76.17429799999999,43.146975],"type":"Point"}
}