{
  "type": "Feature",
  "properties": {
    "addr:full":"440 Park Ave New York NY 10022",
    "addr:housenumber":"440",
    "addr:postcode":"10022",
    "addr:street":"Park Ave",
    "iso:country":"US",
    "sg:address":"440 Park Ave",
    "sg:city":"New York",
    "sg:classifiers":[
        {
            "category":"Travel",
            "subcategory":"Hotels & Motels",
            "type":"Entertainment"
        }
    ],
    "sg:phone":"+1   ",
    "sg:postcode":"10022",
    "sg:province":"NY",
    "sg:tags":[
        "resort"
    ],
    "wof:name":"Raffles Resort-Canouan Island",
    "wof:placetype":"venue"
},
  "geometry": {"coordinates":[-73.970951,40.761401],"type":"Point"}
}