{
  "type": "Feature",
  "properties": {
    "iso:country":"US",
    "sg:address":"10 Withers St",
    "sg:city":"Brooklyn",
    "sg:classifiers":[
        {
            "category":"Social Services",
            "subcategory":"Child Care",
            "type":"Services"
        }
    ],
    "sg:phone":"+1 718 782 4181",
    "sg:postcode":"11211",
    "sg:province":"NY",
    "sg:tags":[
        "kindergarten",
        "academic",
        "school"
    ],
    "wof:name":"Williamburg Neighborhood Nrsy",
    "wof:placetype":"venue"
},
  "geometry": {"coordinates":[-73.952423,40.71652],"type":"Point"}
}