{
  "type": "Feature",
  "properties": {
    "iso:country":"US",
    "sg:address":"2517 E Henrietta Rd",
    "sg:city":"Rochester",
    "sg:classifiers":[
        {
            "category":"Personal",
            "subcategory":"Barber",
            "type":"Services"
        }
    ],
    "sg:phone":"+1   ",
    "sg:postcode":"14623",
    "sg:province":"NY",
    "sg:tags":[
        "shop"
    ],
    "wof:name":"Westover Barber Shop",
    "wof:placetype":"venue"
},
  "geometry": {"coordinates":[-77.607373,43.071357],"type":"Point"}
}