{
  "type": "Feature",
  "properties": {
    "addr:full":"1 River St Niskayuna NY 12309",
    "addr:housenumber":"1",
    "addr:postcode":"12309",
    "addr:street":"River St",
    "iso:country":"US",
    "sg:address":"1 River St",
    "sg:city":"Niskayuna",
    "sg:classifiers":[
        {
            "category":"Wholesale",
            "subcategory":"Electrical",
            "type":"Manufacturing & Wholesale Goods"
        }
    ],
    "sg:phone":"+1 518 385 1413",
    "sg:postcode":"12309",
    "sg:province":"NY",
    "sg:tags":[
        "equipment",
        "plant",
        "power"
    ],
    "wof:name":"GE Power Systems",
    "wof:placetype":"venue"
},
  "geometry": {"coordinates":[-73.881199,42.849269],"type":"Point"}
}