{
  "type": "Feature",
  "properties": {
    "addr:full":"8290 Northgate Dr Rome NY 13440",
    "addr:housenumber":"8290",
    "addr:postcode":"13440",
    "addr:street":"Northgate Dr",
    "iso:country":"US",
    "sg:address":"8290 Northgate Dr",
    "sg:city":"Rome",
    "sg:classifiers":[
        {
            "category":"Organizations",
            "subcategory":"Religious Organization",
            "type":"Services"
        }
    ],
    "sg:phone":"+1 315 337 3632",
    "sg:postcode":"13440",
    "sg:province":"NY",
    "sg:tags":[
        "church"
    ],
    "wof:name":"Rome Christian Ctr",
    "wof:placetype":"venue"
},
  "geometry": {"coordinates":[-75.456869,43.261441],"type":"Point"}
}