{
  "type": "Feature",
  "properties": {
    "addr:full":"70 E 161st St Bronx NY 10451",
    "addr:housenumber":"70",
    "addr:postcode":"10451",
    "addr:street":"E 161St St",
    "iso:country":"US",
    "sg:address":"70 E 161st St",
    "sg:city":"Bronx",
    "sg:classifiers":[
        {
            "category":"Shopping",
            "subcategory":"Pharmacy",
            "type":"Retail Goods"
        }
    ],
    "sg:phone":"+1   ",
    "sg:postcode":"10451",
    "sg:province":"NY",
    "sg:tags":[
        "drug",
        "store"
    ],
    "wof:name":"Leff Drugs",
    "wof:placetype":"venue"
},
  "geometry": {"coordinates":[-73.925602,40.827696],"type":"Point"}
}