{
  "type": "Feature",
  "properties": {
    "addr:full":"34 W 134th St New York NY 10037",
    "addr:housenumber":"34",
    "addr:postcode":"10037",
    "addr:street":"W 134Th St",
    "iso:country":"US",
    "sg:address":"34 W 134th St",
    "sg:city":"New York",
    "sg:classifiers":[
        {
            "category":"Organizations",
            "subcategory":"Non-profit Organization",
            "type":"Services"
        }
    ],
    "sg:phone":"+1 212 694 3939",
    "sg:postcode":"10037",
    "sg:province":"NY",
    "sg:tags":[
        "service/non-profit",
        "community"
    ],
    "wof:name":"Catholic Charities of the Archdiocese of Ny",
    "wof:placetype":"venue"
},
  "geometry": {"coordinates":[-73.939598,40.812801],"type":"Point"}
}