{
  "type": "Feature",
  "properties": {
    "iso:country":"US",
    "sg:address":"1 Bowling Grn",
    "sg:city":"New York",
    "sg:classifiers":[
        {
            "category":"Professional",
            "subcategory":"Lawyer & Legal Services",
            "type":"Services"
        }
    ],
    "sg:phone":"+1 212 514 8210",
    "sg:postcode":"10004",
    "sg:province":"NY",
    "wof:name":"AkalSecurities",
    "wof:placetype":"venue"
},
  "geometry": {"coordinates":[-74.421924,40.704466],"type":"Point"}
}