{
  "type": "Feature",
  "properties": {
    "addr:full":"622 Ave U Brooklyn NY 11223",
    "addr:housenumber":"622",
    "addr:postcode":"11223",
    "addr:street":"Ave U",
    "iso:country":"US",
    "sg:address":"622 Ave U",
    "sg:city":"Brooklyn",
    "sg:classifiers":[
        {
            "category":"Health Services",
            "subcategory":"Doctor",
            "type":"Services"
        }
    ],
    "sg:phone":"+1 718 627 8080",
    "sg:postcode":"11223",
    "sg:province":"NY",
    "sg:tags":[
        "dentist"
    ],
    "wof:name":"A Brooklyn Denture Ctr",
    "wof:placetype":"venue"
},
  "geometry": {"coordinates":[-73.96432900000001,40.597878],"type":"Point"}
}