{
  "type": "Feature",
  "properties": {
    "addr:full":"1465 Amsterdam Ave New York NY 10027",
    "addr:housenumber":"1465",
    "addr:postcode":"10027",
    "addr:street":"Amsterdam Ave",
    "iso:country":"US",
    "sg:address":"1465 Amsterdam Ave",
    "sg:city":"New York",
    "sg:classifiers":[
        {
            "category":"Deli",
            "type":"Food & Drink"
        },
        {
            "category":"Food & Beverages",
            "subcategory":"Bakery",
            "type":"Retail Goods"
        }
    ],
    "sg:phone":"+1 212 281 6054",
    "sg:postcode":"10027",
    "sg:province":"NY",
    "sg:tags":[
        "sandwich"
    ],
    "wof:name":"Mexi Deli Grocery Corp",
    "wof:placetype":"venue"
},
  "geometry": {"coordinates":[-73.953333,40.817109],"type":"Point"}
}