{
  "type": "Feature",
  "properties": {
    "addr:full":"2374 Chili Ave Rochester NY 14624",
    "addr:housenumber":"2374",
    "addr:postcode":"14624",
    "addr:street":"Chili Ave",
    "iso:country":"US",
    "sg:address":"2374 Chili Ave",
    "sg:city":"Rochester",
    "sg:classifiers":[
        {
            "category":"Building & Trades",
            "subcategory":"Construction",
            "type":"Services"
        }
    ],
    "sg:phone":"+1 585 247 3375",
    "sg:postcode":"14624",
    "sg:province":"NY",
    "sg:tags":[
        "roofing",
        "contractor"
    ],
    "wof:name":"Robert C Gould Co Inc",
    "wof:placetype":"venue"
},
  "geometry": {"coordinates":[-77.69255,43.130437],"type":"Point"}
}