{
  "type": "Feature",
  "properties": {
    "iso:country":"US",
    "sg:address":"1332 Blondell Ave",
    "sg:city":"Bronx",
    "sg:classifiers":[
        {
            "category":"Professional",
            "subcategory":"Management & Consulting",
            "type":"Services"
        }
    ],
    "sg:phone":"+1 718 823 3182",
    "sg:postcode":"10461",
    "sg:province":"NY",
    "wof:name":"Richard Bonilla Management",
    "wof:placetype":"venue"
},
  "geometry": {"coordinates":[-73.841533,40.841056],"type":"Point"}
}