{
  "type": "Feature",
  "properties": {
    "iso:country":"US",
    "sg:address":"3731 Luker Rd",
    "sg:city":"Cortland",
    "sg:classifiers":[
        {
            "category":"Retail",
            "subcategory":"Repair Shop",
            "type":"Services"
        }
    ],
    "sg:phone":"+1 607 758 8922",
    "sg:postcode":"13045",
    "sg:province":"NY",
    "wof:name":"P R S & Associates Inc",
    "wof:placetype":"venue"
},
  "geometry": {"coordinates":[-76.217534,42.587195],"type":"Point"}
}