{
  "type": "Feature",
  "properties": {
    "addr:full":"34 Clovis Rd Staten Island NY 10308",
    "addr:housenumber":"34",
    "addr:postcode":"10308",
    "addr:street":"Clovis Rd",
    "iso:country":"US",
    "sg:address":"34 Clovis Rd",
    "sg:city":"Staten Island",
    "sg:classifiers":[
        {
            "category":"Building & Trades",
            "subcategory":"Electrical",
            "type":"Services"
        }
    ],
    "sg:phone":"+1 718 984 3393",
    "sg:postcode":"10308",
    "sg:province":"NY",
    "sg:tags":[
        "electrical",
        "contractor"
    ],
    "wof:name":"HI Tech Electric Inc",
    "wof:placetype":"venue"
},
  "geometry": {"coordinates":[-74.148252,40.550736],"type":"Point"}
}