{
  "type": "Feature",
  "properties": {
    "iso:country":"US",
    "sg:address":"183 Elvin St",
    "sg:city":"Staten Island",
    "sg:classifiers":[
        {
            "category":"Autos & Motor Vehicles",
            "subcategory":"Auto Supplies",
            "type":"Retail Goods"
        }
    ],
    "sg:phone":"+1   ",
    "sg:postcode":"10314",
    "sg:province":"NY",
    "wof:name":"Mahala Tire & Wheels Inc",
    "wof:placetype":"venue"
},
  "geometry": {"coordinates":[-74.121889,40.607572],"type":"Point"}
}