{
  "type": "Feature",
  "properties": {
    "addr:full":"600 E 14th St New York NY 10009",
    "addr:housenumber":"600",
    "addr:postcode":"10009",
    "addr:street":"E 14Th St",
    "iso:country":"US",
    "sg:address":"600 E 14th St",
    "sg:city":"New York",
    "sg:classifiers":[
        {
            "category":"Building & Trades",
            "subcategory":"Locksmith",
            "type":"Services"
        }
    ],
    "sg:phone":"+1 212 209 0583",
    "sg:postcode":"10009",
    "sg:province":"NY",
    "sg:tags":[
        "key"
    ],
    "wof:name":"A 24 Hour A Locksmith",
    "wof:placetype":"venue"
},
  "geometry": {"coordinates":[-73.9776,40.729099],"type":"Point"}
}