{
  "type": "Feature",
  "properties": {
    "iso:country":"US",
    "sg:address":"3062 Whitestone Expy",
    "sg:city":"Flushing",
    "sg:classifiers":[
        {
            "category":"Professional",
            "subcategory":"Engineering",
            "type":"Services"
        }
    ],
    "sg:phone":"+1 718 670 0100",
    "sg:postcode":"11354",
    "sg:province":"NY",
    "sg:tags":[
        "engineer"
    ],
    "wof:name":"Purvis Systems Inc",
    "wof:placetype":"venue"
},
  "geometry": {"coordinates":[-73.836825,40.769492],"type":"Point"}
}