{
  "type": "Feature",
  "properties": {
    "addr:full":"2114 66th St Brooklyn NY 11204",
    "addr:housenumber":"2114",
    "addr:postcode":"11204",
    "addr:street":"66Th St",
    "iso:country":"US",
    "sg:address":"2114 66th St",
    "sg:city":"Brooklyn",
    "sg:classifiers":[
        {
            "category":"Manufacturing",
            "subcategory":"Metals",
            "type":"Manufacturing & Wholesale Goods"
        }
    ],
    "sg:phone":"+1   ",
    "sg:postcode":"11204",
    "sg:province":"NY",
    "sg:tags":[
        "product",
        "wire",
        "fabricated",
        "mfg"
    ],
    "wof:name":"Rui Qiang",
    "wof:placetype":"venue"
},
  "geometry": {"coordinates":[-73.98401800000001,40.614278],"type":"Point"}
}