{
  "type": "Feature",
  "properties": {
    "addr:full":"21 Parrot St Cold Spring NY 10516",
    "addr:housenumber":"21",
    "addr:postcode":"10516",
    "addr:street":"Parrot St",
    "iso:country":"US",
    "sg:address":"21 Parrot St",
    "sg:city":"Cold Spring",
    "sg:classifiers":[
        {
            "category":"Retail",
            "subcategory":"Funeral Services",
            "type":"Services"
        }
    ],
    "sg:phone":"+1 845 265 3333",
    "sg:postcode":"10516",
    "sg:province":"NY",
    "sg:tags":[
        "director"
    ],
    "wof:name":"Clinton Inc Funeral Homes",
    "wof:placetype":"venue"
},
  "geometry": {"coordinates":[-73.94929999999999,41.421078],"type":"Point"}
}