{
  "type": "Feature",
  "properties": {
    "addr:full":"237 W 35 St New York NY 10001",
    "addr:housenumber":"237",
    "addr:postcode":"10001",
    "addr:street":"W 35 St",
    "iso:country":"US",
    "sg:address":"237 W 35 St",
    "sg:city":"New York",
    "sg:classifiers":[
        {
            "category":"Wholesale",
            "subcategory":"Apparel",
            "type":"Manufacturing & Wholesale Goods"
        }
    ],
    "sg:phone":"+1 212 239 1995",
    "sg:postcode":"10001",
    "sg:province":"NY",
    "sg:tags":[
        "lining",
        "fabric"
    ],
    "wof:name":"Alsi International Trading",
    "wof:placetype":"venue"
},
  "geometry": {"coordinates":[-73.99215,40.752481],"type":"Point"}
}