{
  "type": "Feature",
  "properties": {
    "iso:country":"US",
    "sg:address":"216 Glen Dr",
    "sg:city":"Fultonville",
    "sg:classifiers":[
        {
            "category":"Professional",
            "subcategory":"Advertising",
            "type":"Services"
        }
    ],
    "sg:phone":"+1 518 853 3133",
    "sg:postcode":"12072",
    "sg:province":"NY",
    "wof:name":"Snyder Engineering",
    "wof:placetype":"venue"
},
  "geometry": {"coordinates":[-74.34589099999999,42.940882],"type":"Point"}
}