{
  "type": "Feature",
  "properties": {
    "addr:full":"23 Lakewood Dr Orchard Park NY 14127",
    "addr:housenumber":"23",
    "addr:postcode":"14127",
    "addr:street":"Lakewood Dr",
    "iso:country":"US",
    "sg:address":"23 Lakewood Dr",
    "sg:city":"Orchard Park",
    "sg:classifiers":[
        {
            "category":"Building & Trades",
            "subcategory":"Electrical",
            "type":"Services"
        }
    ],
    "sg:phone":"+1 716 837 5466",
    "sg:postcode":"14127",
    "sg:province":"NY",
    "sg:tags":[
        "consulting",
        "electrical",
        "electric",
        "business",
        "contractor"
    ],
    "wof:name":"Ries Electrical Construction",
    "wof:placetype":"venue"
},
  "geometry": {"coordinates":[-78.767534,42.799086],"type":"Point"}
}