{
  "type": "Feature",
  "properties": {
    "addr:full":"1 Tornado Dr Tuxedo Park NY 10987",
    "addr:housenumber":"1",
    "addr:postcode":"10987",
    "addr:street":"Tornado Dr",
    "iso:country":"US",
    "sg:address":"1 Tornado Dr",
    "sg:city":"Tuxedo Park",
    "sg:classifiers":[
        {
            "category":"Education",
            "subcategory":"School",
            "type":"Public Place"
        }
    ],
    "sg:phone":"+1 845 351 4786",
    "sg:postcode":"10987",
    "sg:province":"NY",
    "sg:website":"www.tuxedoschooldistrict.com",
    "wof:name":"Tuxedo Public School",
    "wof:placetype":"venue"
},
  "geometry": {"coordinates":[-74.184843,41.188991],"type":"Point"}
}