{
  "type": "Feature",
  "properties": {
    "iso:country":"US",
    "sg:address":"141 E Service Rd",
    "sg:city":"Staten Island",
    "sg:classifiers":[
        {
            "category":"Education",
            "subcategory":"Kindergarten",
            "type":"Public Place"
        },
        {
            "category":"Autos & Motor Vehicles",
            "subcategory":"Motorcycle Sales",
            "type":"Retail Goods"
        }
    ],
    "sg:phone":"+1 718 494 4500",
    "sg:postcode":"10314",
    "sg:province":"NY",
    "sg:tags":[
        "school",
        "driving"
    ],
    "wof:name":"Roth Insurance",
    "wof:placetype":"venue"
},
  "geometry": {"coordinates":[-74.18049600000001,40.609001],"type":"Point"}
}