{
  "type": "Feature",
  "properties": {
    "iso:country":"US",
    "sg:address":"22 Stymus Ave",
    "sg:city":"Bethpage",
    "sg:classifiers":[
        {
            "category":"Local Transit",
            "type":"Transportation"
        }
    ],
    "sg:phone":"+1 516 938 2199",
    "sg:postcode":"11714",
    "sg:province":"NY",
    "sg:tags":[
        "limousine"
    ],
    "wof:name":"J & P Limousine Svc Inc",
    "wof:placetype":"venue"
},
  "geometry": {"coordinates":[-73.471717,40.738653],"type":"Point"}
}