{
  "type": "Feature",
  "properties": {
    "addr:full":"175 US Hwy 9w Congers NY 10920",
    "addr:housenumber":"175",
    "addr:postcode":"10920",
    "addr:street":"Us Hwy 9W",
    "iso:country":"US",
    "sg:address":"175 US Hwy 9w",
    "sg:city":"Congers",
    "sg:classifiers":[
        {
            "category":"Retail",
            "subcategory":"Repair Shop",
            "type":"Services"
        }
    ],
    "sg:phone":"+1 845 268 0851",
    "sg:postcode":"10920",
    "sg:province":"NY",
    "sg:tags":[
        "upholsterer"
    ],
    "wof:name":"KMHI",
    "wof:placetype":"venue"
},
  "geometry": {"coordinates":[-73.92808100000001,41.157425],"type":"Point"}
}