{
  "type": "Feature",
  "properties": {
    "iso:country":"US",
    "sg:address":"266 Little Briggs Street Rd",
    "sg:city":"Constable",
    "sg:classifiers":[
        {
            "category":"Farming",
            "subcategory":"Dairy Farm",
            "type":"Manufacturing & Wholesale Goods"
        }
    ],
    "sg:phone":"+1 518 358 4466",
    "sg:postcode":"12926",
    "sg:province":"NY",
    "wof:name":"St Onge Daniel",
    "wof:placetype":"venue"
},
  "geometry": {"coordinates":[-74.401956,44.967294],"type":"Point"}
}