{
  "type": "Feature",
  "properties": {
    "addr:full":"33 W 94 St New York NY 10025",
    "addr:housenumber":"33",
    "addr:postcode":"10025",
    "addr:street":"W 94 St",
    "iso:country":"US",
    "sg:address":"33 W 94 St",
    "sg:city":"New York",
    "sg:classifiers":[
        {
            "category":"Professional",
            "subcategory":"Management & Consulting",
            "type":"Services"
        }
    ],
    "sg:phone":"+1 212 222 2644",
    "sg:postcode":"10025",
    "sg:province":"NY",
    "sg:tags":[
        "marketing",
        "photography"
    ],
    "wof:name":"Cinergy Communications Corp",
    "wof:placetype":"venue"
},
  "geometry": {"coordinates":[-73.96772799999999,40.791237],"type":"Point"}
}