{
  "type": "Feature",
  "properties": {
    "iso:country":"US",
    "sg:address":"2445 Parker Blvd",
    "sg:city":"Tonawanda",
    "sg:classifiers":[
        {
            "category":"Wholesale",
            "subcategory":"Home Furnishings",
            "type":"Manufacturing & Wholesale Goods"
        }
    ],
    "sg:phone":"+1 716 694 9273",
    "sg:postcode":"14150",
    "sg:province":"NY",
    "wof:name":"Richard Lesses Window Design",
    "wof:placetype":"venue"
},
  "geometry": {"coordinates":[-78.835902,43.008853],"type":"Point"}
}