{
  "type": "Feature",
  "properties": {
    "addr:full":"1415 Coney Island Avenue Brooklyn NY 11230",
    "addr:housenumber":"1415",
    "addr:postcode":"11230",
    "addr:street":"Coney Island Avenue",
    "iso:country":"US",
    "sg:address":"1415 Coney Island Avenue",
    "sg:city":"Brooklyn",
    "sg:classifiers":[
        {
            "category":"Personal",
            "subcategory":"Skin Care",
            "type":"Services"
        }
    ],
    "sg:phone":"+1 718 258 0035",
    "sg:postcode":"11230",
    "sg:province":"NY",
    "wof:name":"Classic Beauty Ltd",
    "wof:placetype":"venue"
},
  "geometry": {"coordinates":[-73.96462699999999,40.623042],"type":"Point"}
}