{
  "type": "Feature",
  "properties": {
    "addr:full":"4178 Park Ave Bronx NY 10457",
    "addr:housenumber":"4178",
    "addr:postcode":"10457",
    "addr:street":"Park Ave",
    "iso:country":"US",
    "sg:address":"4178 Park Ave",
    "sg:city":"Bronx",
    "sg:classifiers":[
        {
            "category":"Autos & Motor Vehicles",
            "subcategory":"Auto Supplies",
            "type":"Retail Goods"
        },
        {
            "category":"Retail",
            "subcategory":"Auto Repair",
            "type":"Services"
        }
    ],
    "sg:phone":"+1 718 901 2067",
    "sg:postcode":"10457",
    "sg:province":"NY",
    "sg:tags":[
        "tire"
    ],
    "wof:name":"Selos Auto Repair",
    "wof:placetype":"venue"
},
  "geometry": {"coordinates":[-73.899687,40.846615],"type":"Point"}
}