{
  "type": "Feature",
  "properties": {
    "iso:country":"US",
    "sg:address":"784 Pre Emption Rd",
    "sg:city":"Geneva",
    "sg:classifiers":[
        {
            "category":"Health Services",
            "subcategory":"Doctor",
            "type":"Services"
        }
    ],
    "sg:phone":"+1 585 396 3210",
    "sg:postcode":"14456",
    "sg:province":"NY",
    "wof:name":"Brian J Dunster MD",
    "wof:placetype":"venue"
},
  "geometry": {"coordinates":[-77.011064,42.864452],"type":"Point"}
}