{
  "type": "Feature",
  "properties": {
    "iso:country":"US",
    "sg:address":"130 S Highland Ave",
    "sg:city":"Nyack",
    "sg:classifiers":[
        {
            "category":"Education",
            "subcategory":"College",
            "type":"Public Place"
        }
    ],
    "sg:phone":"+1 845 358 5360",
    "sg:postcode":"10960",
    "sg:province":"NY",
    "sg:tags":[
        "academic",
        "school"
    ],
    "sg:website":"www.nyackadulted.org",
    "wof:name":"Adult Degree Completion Prgrm",
    "wof:placetype":"venue"
},
  "geometry": {"coordinates":[-73.92897000000001,41.088315],"type":"Point"}
}