{
  "type": "Feature",
  "properties": {
    "addr:full":"60 Canal St New York NY 10002",
    "addr:housenumber":"60",
    "addr:postcode":"10002",
    "addr:street":"Canal St",
    "iso:country":"US",
    "sg:address":"60 Canal St",
    "sg:city":"New York",
    "sg:classifiers":[
        {
            "category":"Manufacturing",
            "subcategory":"Retail Goods",
            "type":"Manufacturing & Wholesale Goods"
        }
    ],
    "sg:phone":"+1   ",
    "sg:postcode":"10002",
    "sg:province":"NY",
    "sg:tags":[
        "manufacture",
        "hair",
        "accessory"
    ],
    "wof:name":"Design By Richard Inc",
    "wof:placetype":"venue"
},
  "geometry": {"coordinates":[-73.99189,40.714898],"type":"Point"}
}