{
  "type": "Feature",
  "properties": {
    "addr:full":"3903 Carman Rd Schenectady NY 12303",
    "addr:housenumber":"3903",
    "addr:postcode":"12303",
    "addr:street":"Carman Rd",
    "iso:country":"US",
    "sg:address":"3903 Carman Rd",
    "sg:city":"Schenectady",
    "sg:classifiers":[
        {
            "category":"Autos & Motor Vehicles",
            "subcategory":"Fuel & Gas Station",
            "type":"Retail Goods"
        }
    ],
    "sg:phone":"+1 518 356 1068",
    "sg:postcode":"12303",
    "sg:province":"NY",
    "sg:tags":[
        "oil"
    ],
    "wof:name":"Guilderland Mobil Mart",
    "wof:placetype":"venue"
},
  "geometry": {"coordinates":[-73.931984,42.716015],"type":"Point"}
}