{
  "type": "Feature",
  "properties": {
    "addr:full":"355 Elmira Rd Ithaca NY 14850",
    "addr:housenumber":"355",
    "addr:postcode":"14850",
    "addr:street":"Elmira Rd",
    "iso:country":"US",
    "sg:address":"355 Elmira Rd",
    "sg:city":"Ithaca",
    "sg:classifiers":[
        {
            "category":"Retail",
            "subcategory":"Auto Repair",
            "type":"Services"
        }
    ],
    "sg:phone":"+1 607 273 3557",
    "sg:postcode":"14850",
    "sg:province":"NY",
    "sg:tags":[
        "transmission",
        "automotive"
    ],
    "wof:name":"Superior Transmission Inc",
    "wof:placetype":"venue"
},
  "geometry": {"coordinates":[-76.51555399999999,42.422964],"type":"Point"}
}