{
  "type": "Feature",
  "properties": {
    "addr:full":"767 Lexington Ave New York NY 10021",
    "addr:housenumber":"767",
    "addr:postcode":"10021",
    "addr:street":"Lexington Ave",
    "iso:country":"US",
    "sg:address":"767 Lexington Ave",
    "sg:city":"New York",
    "sg:classifiers":[
        {
            "category":"Building & Trades",
            "subcategory":"Cleaning & Sanitation",
            "type":"Services"
        },
        {
            "category":"Home & Garden",
            "subcategory":"Carpets & Floor Coverings",
            "type":"Retail Goods"
        }
    ],
    "sg:phone":"+1 212 809 0082",
    "sg:postcode":"10021",
    "sg:province":"NY",
    "sg:tags":[
        "carpeting"
    ],
    "wof:name":"Kalfaian D & Sons Rug Cleaning",
    "wof:placetype":"venue"
},
  "geometry": {"coordinates":[-73.967598,40.762901],"type":"Point"}
}