{
  "type": "Feature",
  "properties": {
    "addr:full":"166 E 63 St New York NY 10065",
    "addr:housenumber":"166;63",
    "addr:postcode":"10065",
    "addr:street":"E;St",
    "iso:country":"US",
    "sg:address":"166 E 63 St",
    "sg:city":"New York",
    "sg:classifiers":[
        {
            "category":"Professional",
            "type":"Services"
        }
    ],
    "sg:phone":"+1 212 421 9097",
    "sg:postcode":"10065",
    "sg:province":"NY",
    "sg:tags":[
        "establishment"
    ],
    "wof:name":"Crossborder Capital",
    "wof:placetype":"venue"
},
  "geometry": {"coordinates":[-73.96535799999999,40.764306],"type":"Point"}
}