{
  "type": "Feature",
  "properties": {
    "addr:full":"2054 Putnam Rd Schenectady NY 12306",
    "addr:housenumber":"2054",
    "addr:postcode":"12306",
    "addr:street":"Putnam Rd",
    "iso:country":"US",
    "sg:address":"2054 Putnam Rd",
    "sg:city":"Schenectady",
    "sg:classifiers":[
        {
            "category":"Real Estate",
            "subcategory":"Real Estate Agent",
            "type":"Services"
        }
    ],
    "sg:phone":"+1 518 374 0602",
    "sg:postcode":"12306",
    "sg:province":"NY",
    "wof:name":"Bradley W James",
    "wof:placetype":"venue"
},
  "geometry": {"coordinates":[-74.03904,42.810582],"type":"Point"}
}