{
  "type": "Feature",
  "properties": {
    "iso:country":"US",
    "sg:address":"377 Split Rock Rd",
    "sg:city":"Syosset",
    "sg:classifiers":[
        {
            "category":"Building & Trades",
            "subcategory":"Construction",
            "type":"Services"
        }
    ],
    "sg:phone":"+1 516 922 1117",
    "sg:postcode":"11791",
    "sg:province":"NY",
    "sg:tags":[
        "general",
        "contractor"
    ],
    "wof:name":"A J General Contractor",
    "wof:placetype":"venue"
},
  "geometry": {"coordinates":[-73.515095,40.839431],"type":"Point"}
}