{
  "type": "Feature",
  "properties": {
    "iso:country":"US",
    "sg:address":"601 E Tremont Ave",
    "sg:city":"Bronx",
    "sg:classifiers":[
        {
            "category":"Real Estate",
            "subcategory":"Architect",
            "type":"Services"
        }
    ],
    "sg:phone":"+1   ",
    "sg:postcode":"10457",
    "sg:province":"NY",
    "sg:tags":[
        "architectural"
    ],
    "wof:name":"Carlo Nuzzi Architect",
    "wof:placetype":"venue"
},
  "geometry": {"coordinates":[-73.89290099999999,40.846269],"type":"Point"}
}