{
  "type": "Feature",
  "properties": {
    "addr:full":"80 River St Oneonta NY 13820",
    "addr:housenumber":"80",
    "addr:postcode":"13820",
    "addr:street":"River St",
    "iso:country":"US",
    "sg:address":"80 River St",
    "sg:city":"Oneonta",
    "sg:classifiers":[
        {
            "category":"Manufacturing",
            "subcategory":"Pet Food",
            "type":"Manufacturing & Wholesale Goods"
        }
    ],
    "sg:phone":"+1 607 432 7984",
    "sg:postcode":"13820",
    "sg:province":"NY",
    "sg:tags":[
        "feed",
        "livestock"
    ],
    "wof:name":"Lutz Feed Co Inc",
    "wof:placetype":"venue"
},
  "geometry": {"coordinates":[-75.07124899999999,42.446901],"type":"Point"}
}