{
  "type": "Feature",
  "properties": {
    "iso:country":"US",
    "sg:address":"168 State St",
    "sg:city":"Auburn",
    "sg:classifiers":[
        {
            "category":"Organizations",
            "subcategory":"Community Association",
            "type":"Services"
        }
    ],
    "sg:phone":"+1 315 252 5016",
    "sg:postcode":"13021",
    "sg:province":"NY",
    "sg:tags":[
        "military"
    ],
    "wof:name":"American Legion",
    "wof:placetype":"venue"
},
  "geometry": {"coordinates":[-76.571703,42.938479],"type":"Point"}
}