{
  "type": "Feature",
  "properties": {
    "addr:full":"224 Centre St New York NY 10013",
    "addr:housenumber":"224",
    "addr:postcode":"10013",
    "addr:street":"Centre St",
    "iso:country":"US",
    "sg:address":"224 Centre St",
    "sg:city":"New York",
    "sg:classifiers":[
        {
            "category":"Museum",
            "type":"Entertainment"
        }
    ],
    "sg:phone":"+1 212 431 6430",
    "sg:postcode":"10013",
    "sg:province":"NY",
    "sg:tags":[
        "organization",
        "arts",
        "information"
    ],
    "sg:website":"www.experimentalintermedia.org",
    "wof:name":"Experimental Intermedia",
    "wof:placetype":"venue"
},
  "geometry": {"coordinates":[-73.998915,40.719008],"type":"Point"}
}