{
  "type": "Feature",
  "properties": {
    "addr:full":"434 Eastern Blvd Watertown NY 13601",
    "addr:housenumber":"434",
    "addr:postcode":"13601",
    "addr:street":"Eastern Blvd",
    "iso:country":"US",
    "sg:address":"434 Eastern Blvd",
    "sg:city":"Watertown",
    "sg:classifiers":[
        {
            "category":"Home & Garden",
            "subcategory":"Building Materials",
            "type":"Retail Goods"
        },
        {
            "category":"Building & Trades",
            "subcategory":"Construction",
            "type":"Services"
        }
    ],
    "sg:phone":"+1 315 782 6850",
    "sg:postcode":"13601",
    "sg:province":"NY",
    "sg:tags":[
        "roofing",
        "industrial",
        "installation",
        "windows-repair",
        "specialty",
        "contractor",
        "window",
        "contractors-commercial",
        "insulation",
        "siding",
        "replacement"
    ],
    "wof:name":"Griffin Roofing Inc",
    "wof:placetype":"venue"
},
  "geometry": {"coordinates":[-75.87722599999999,43.97405],"type":"Point"}
}