{
  "type": "Feature",
  "properties": {
    "addr:full":"21 Vermont Ave West Babylon NY 11704",
    "addr:housenumber":"21",
    "addr:postcode":"11704",
    "addr:street":"Vermont Ave",
    "iso:country":"US",
    "sg:address":"21 Vermont Ave",
    "sg:city":"West Babylon",
    "sg:classifiers":[
        {
            "category":"Professional",
            "subcategory":"Management & Consulting",
            "type":"Services"
        }
    ],
    "sg:phone":"+1 631 669 6295",
    "sg:postcode":"11704",
    "sg:province":"NY",
    "wof:name":"Levine Management Inc",
    "wof:placetype":"venue"
},
  "geometry": {"coordinates":[-73.359774,40.727559],"type":"Point"}
}