{
  "type": "Feature",
  "properties": {
    "addr:full":"494 Palmer Rd Yonkers NY 10701",
    "addr:housenumber":"494",
    "addr:postcode":"10701",
    "addr:street":"Palmer Rd",
    "iso:country":"US",
    "sg:address":"494 Palmer Rd",
    "sg:city":"Yonkers",
    "sg:classifiers":[
        {
            "category":"Shopping",
            "subcategory":"Gifts & Souvenirs",
            "type":"Retail Goods"
        }
    ],
    "sg:phone":"+1 914 965 2055",
    "sg:postcode":"10701",
    "sg:province":"NY",
    "sg:tags":[
        "basket",
        "fruit"
    ],
    "wof:name":"Bryn Mawr Station Market",
    "wof:placetype":"venue"
},
  "geometry": {"coordinates":[-73.85917000000001,40.94457],"type":"Point"}
}