{
  "type": "Feature",
  "properties": {
    "addr:full":"1090 Broad Hollow Rd Farmingdale NY 11735",
    "addr:housenumber":"1090",
    "addr:postcode":"11735",
    "addr:street":"Broad Hollow Rd",
    "iso:country":"US",
    "sg:address":"1090 Broad Hollow Rd",
    "sg:city":"Farmingdale",
    "sg:classifiers":[
        {
            "category":"Wholesale",
            "subcategory":"Groceries",
            "type":"Manufacturing & Wholesale Goods"
        }
    ],
    "sg:phone":"+1 631 249 2421",
    "sg:postcode":"11735",
    "sg:province":"NY",
    "sg:tags":[
        "food",
        "health"
    ],
    "wof:name":"Sports Supplements North East",
    "wof:placetype":"venue"
},
  "geometry": {"coordinates":[-73.42353199999999,40.733995],"type":"Point"}
}