{
  "type": "Feature",
  "properties": {
    "iso:country":"US",
    "sg:address":"135 E 55 St",
    "sg:city":"New York",
    "sg:classifiers":[
        {
            "category":"Professional",
            "subcategory":"Management & Consulting",
            "type":"Services"
        }
    ],
    "sg:phone":"+1 212 759 1991",
    "sg:postcode":"10022",
    "sg:province":"NY",
    "sg:tags":[
        "promotion",
        "agency",
        "advertising",
        "sales"
    ],
    "wof:name":"Susan M Rafaj",
    "wof:placetype":"venue"
},
  "geometry": {"coordinates":[-73.96848,40.75895],"type":"Point"}
}