{
  "type": "Feature",
  "properties": {
    "iso:country":"US",
    "sg:address":"110 Main St",
    "sg:city":"Saugerties",
    "sg:classifiers":[
        {
            "category":"Organizations",
            "subcategory":"Membership Organization",
            "type":"Services"
        }
    ],
    "sg:phone":"+1 845 246 0134",
    "sg:postcode":"12487",
    "sg:province":"NY",
    "wof:name":"Central Ulster Children's Svc",
    "wof:placetype":"venue"
},
  "geometry": {"coordinates":[-73.965305,41.831845],"type":"Point"}
}