{
  "type": "Feature",
  "properties": {
    "addr:full":"101 Bundy Rd Ithaca NY 14850",
    "addr:housenumber":"101",
    "addr:postcode":"14850",
    "addr:street":"Bundy Rd",
    "iso:country":"US",
    "sg:address":"101 Bundy Rd",
    "sg:city":"Ithaca",
    "sg:classifiers":[
        {
            "category":"Social Services",
            "type":"Services"
        }
    ],
    "sg:phone":"+1 607 256 5094",
    "sg:postcode":"14850",
    "sg:province":"NY",
    "sg:tags":[
        "senior",
        "citizen"
    ],
    "sg:website":"www.assisted.com",
    "wof:name":"Alterra Clare Bridge",
    "wof:placetype":"venue"
},
  "geometry": {"coordinates":[-76.52961999999999,42.460532],"type":"Point"}
}