{
  "type": "Feature",
  "properties": {
    "iso:country":"US",
    "sg:address":"67 New Dorp Plz",
    "sg:city":"Staten Island",
    "sg:classifiers":[
        {
            "category":"Professional",
            "subcategory":"Business Services",
            "type":"Services"
        }
    ],
    "sg:phone":"+1 718 351 9300",
    "sg:postcode":"10306",
    "sg:province":"NY",
    "sg:tags":[
        "abstract",
        "title"
    ],
    "wof:name":"Traditional Abstract Corp",
    "wof:placetype":"venue"
},
  "geometry": {"coordinates":[-74.117144,40.574086],"type":"Point"}
}