{
  "type": "Feature",
  "properties": {
    "iso:country":"US",
    "sg:address":"215 E 161st St",
    "sg:city":"Bronx",
    "sg:classifiers":[
        {
            "category":"Professional",
            "subcategory":"Business Services",
            "type":"Services"
        }
    ],
    "sg:phone":"+1 718 410 2136",
    "sg:postcode":"10451",
    "sg:province":"NY",
    "sg:tags":[
        "arbitration"
    ],
    "wof:name":"Legal Aid",
    "wof:placetype":"venue"
},
  "geometry": {"coordinates":[-73.92075800000001,40.826414],"type":"Point"}
}