{
  "type": "Feature",
  "properties": {
    "addr:full":"75-15 Northern Blvd Queens NY 11370",
    "addr:housenumber":"75-15",
    "addr:postcode":"11370",
    "addr:street":"Northern Blvd",
    "iso:country":"US",
    "sg:address":"75-15 Northern Blvd",
    "sg:city":"Queens",
    "sg:classifiers":[
        {
            "category":"Retail",
            "subcategory":"Auto Repair",
            "type":"Services"
        }
    ],
    "sg:phone":"+1 718 446 9800",
    "sg:postcode":"11370",
    "sg:province":"NY",
    "wof:name":"Northern Blvd Auto Service",
    "wof:placetype":"venue"
},
  "geometry": {"coordinates":[-73.89171,40.754864],"type":"Point"}
}