{
  "type": "Feature",
  "properties": {
    "addr:full":"55 Bay St Glens Falls NY 12801",
    "addr:housenumber":"55",
    "addr:postcode":"12801",
    "addr:street":"Bay St",
    "iso:country":"US",
    "sg:address":"55 Bay St",
    "sg:city":"Glens Falls",
    "sg:classifiers":[
        {
            "category":"Professional",
            "subcategory":"Engineering",
            "type":"Services"
        }
    ],
    "sg:phone":"+1 518 615 0201",
    "sg:postcode":"12801",
    "sg:province":"NY",
    "sg:tags":[
        "engineer"
    ],
    "wof:name":"Engineering America Co",
    "wof:placetype":"venue"
},
  "geometry": {"coordinates":[-73.64724099999999,43.313435],"type":"Point"}
}