{
  "type": "Feature",
  "properties": {
    "addr:full":"43 Cedar Rd East Northport NY 11731",
    "addr:housenumber":"43",
    "addr:postcode":"11731",
    "addr:street":"Cedar Rd",
    "iso:country":"US",
    "sg:address":"43 Cedar Rd",
    "sg:city":"East Northport",
    "sg:classifiers":[
        {
            "category":"Building & Trades",
            "subcategory":"Construction",
            "type":"Services"
        }
    ],
    "sg:phone":"+1 631 368 5428",
    "sg:postcode":"11731",
    "sg:province":"NY",
    "sg:tags":[
        "carpet",
        "installation",
        "contractor"
    ],
    "wof:name":"Bonded Carpet",
    "wof:placetype":"venue"
},
  "geometry": {"coordinates":[-73.32881999999999,40.855156],"type":"Point"}
}