{
  "type": "Feature",
  "properties": {
    "addr:full":"657 Allerton Ave Bronx NY 10467",
    "addr:housenumber":"657",
    "addr:postcode":"10467",
    "addr:street":"Allerton Ave",
    "iso:country":"US",
    "sg:address":"657 Allerton Ave",
    "sg:city":"Bronx",
    "sg:classifiers":[
        {
            "category":"Retail",
            "subcategory":"Repair Shop",
            "type":"Services"
        }
    ],
    "sg:phone":"+1 718 887 2373",
    "sg:postcode":"10467",
    "sg:province":"NY",
    "sg:tags":[
        "lock",
        "locksmith"
    ],
    "wof:name":"Emergency 7 Day Locksmith",
    "wof:placetype":"venue"
},
  "geometry": {"coordinates":[-73.868562,40.865477],"type":"Point"}
}