{
  "type": "Feature",
  "properties": {
    "addr:full":"726 Sound View Rd Oyster Bay NY 11771",
    "addr:housenumber":"726",
    "addr:postcode":"11771",
    "addr:street":"Sound View Rd",
    "iso:country":"US",
    "sg:address":"726 Sound View Rd",
    "sg:city":"Oyster Bay",
    "sg:classifiers":[
        {
            "category":"Professional",
            "subcategory":"Research",
            "type":"Services"
        }
    ],
    "sg:phone":"+1 516 624 7378",
    "sg:postcode":"11771",
    "sg:province":"NY",
    "sg:tags":[
        "nonphysical",
        "commercial"
    ],
    "wof:name":"Global Focus",
    "wof:placetype":"venue"
},
  "geometry": {"coordinates":[-73.552103,40.900644],"type":"Point"}
}