{
  "type": "Feature",
  "properties": {
    "iso:country":"US",
    "sg:address":"5419 US Hwy 9w",
    "sg:city":"Newburgh",
    "sg:classifiers":[
        {
            "category":"Real Estate",
            "subcategory":"Real Estate Services",
            "type":"Services"
        }
    ],
    "sg:phone":"+1 845 565 8111",
    "sg:postcode":"12550",
    "sg:province":"NY",
    "sg:tags":[
        "abstract",
        "title"
    ],
    "wof:name":"American Real Estate Search &",
    "wof:placetype":"venue"
},
  "geometry": {"coordinates":[-74.003575,41.558761],"type":"Point"}
}