{
  "type": "Feature",
  "properties": {
    "iso:country":"US",
    "sg:address":"337 Northern Lights Plz",
    "sg:city":"Syracuse",
    "sg:classifiers":[
        {
            "category":"Shopping",
            "subcategory":"Hobbies, Toys, & Games",
            "type":"Retail Goods"
        }
    ],
    "sg:phone":"+1 315 455 3066",
    "sg:postcode":"13212",
    "sg:province":"NY",
    "sg:tags":[
        "craft",
        "supply"
    ],
    "wof:name":"Michaels Stores",
    "wof:placetype":"venue"
},
  "geometry": {"coordinates":[-76.143404,43.11046],"type":"Point"}
}