{
  "type": "Feature",
  "properties": {
    "addr:full":"960 Oliver St North Tonawanda NY 14120",
    "addr:housenumber":"960",
    "addr:postcode":"14120",
    "addr:street":"Oliver St",
    "iso:country":"US",
    "sg:address":"960 Oliver St",
    "sg:city":"North Tonawanda",
    "sg:classifiers":[
        {
            "category":"Building & Trades",
            "subcategory":"Plumbing",
            "type":"Services"
        }
    ],
    "sg:phone":"+1 716 693 6695",
    "sg:postcode":"14120",
    "sg:province":"NY",
    "sg:tags":[
        "heating",
        "contractor"
    ],
    "wof:name":"Connell-Pane Heating & Cooling",
    "wof:placetype":"venue"
},
  "geometry": {"coordinates":[-78.88524099999999,43.048082],"type":"Point"}
}