{
  "type": "Feature",
  "properties": {
    "addr:full":"322 E Riverside Dr Olean NY 14760",
    "addr:housenumber":"322",
    "addr:postcode":"14760",
    "addr:street":"E Riverside Dr",
    "iso:country":"US",
    "sg:address":"322 E Riverside Dr",
    "sg:city":"Olean",
    "sg:classifiers":[
        {
            "category":"Wholesale",
            "subcategory":"Meat",
            "type":"Manufacturing & Wholesale Goods"
        }
    ],
    "sg:phone":"+1   ",
    "sg:postcode":"14760",
    "sg:province":"NY",
    "sg:tags":[
        "house",
        "slaughter"
    ],
    "wof:name":"Kamerys Wholesale Meats Inc",
    "wof:placetype":"venue"
},
  "geometry": {"coordinates":[-78.420987,42.069655],"type":"Point"}
}