{
  "type": "Feature",
  "properties": {
    "iso:country":"US",
    "sg:address":"504 Main St",
    "sg:city":"Beacon",
    "sg:classifiers":[
        {
            "category":"Sports & Exercise",
            "subcategory":"Gym",
            "type":"Entertainment"
        }
    ],
    "sg:phone":"+1 845 440 7339",
    "sg:postcode":"12508",
    "sg:province":"NY",
    "sg:tags":[
        "yoga"
    ],
    "wof:name":"Hearts To Heaven",
    "wof:placetype":"venue"
},
  "geometry": {"coordinates":[-73.963544,41.50225],"type":"Point"}
}