{
  "type": "Feature",
  "properties": {
    "addr:full":"1676 53rd St Brooklyn NY 11204",
    "addr:housenumber":"1676",
    "addr:postcode":"11204",
    "addr:street":"53Rd St",
    "iso:country":"US",
    "sg:address":"1676 53rd St",
    "sg:city":"Brooklyn",
    "sg:classifiers":[
        {
            "category":"Organizations",
            "subcategory":"Religious Organization",
            "type":"Services"
        }
    ],
    "sg:phone":"+1 718 438 2920",
    "sg:postcode":"11204",
    "sg:province":"NY",
    "sg:tags":[
        "clergy"
    ],
    "wof:name":"Carl Katlowitz",
    "wof:placetype":"venue"
},
  "geometry": {"coordinates":[-73.98687700000001,40.628405],"type":"Point"}
}