{
  "type": "Feature",
  "properties": {
    "addr:full":"120 E 34 St New York NY 10016",
    "addr:housenumber":"120;34",
    "addr:postcode":"10016",
    "addr:street":"E;St",
    "iso:country":"US",
    "sg:address":"120 E 34 St",
    "sg:city":"New York",
    "sg:classifiers":[
        {
            "category":"Professional",
            "subcategory":"Employment Agencies",
            "type":"Services"
        }
    ],
    "sg:phone":"+1 212 687 2626",
    "sg:postcode":"10016",
    "sg:province":"NY",
    "sg:tags":[
        "leasing"
    ],
    "wof:name":"Laszlo Calderon Consltng Inc",
    "wof:placetype":"venue"
},
  "geometry": {"coordinates":[-73.980491,40.746774],"type":"Point"}
}