{
  "type": "Feature",
  "properties": {
    "iso:country":"US",
    "sg:address":"255 E Bank St",
    "sg:city":"Albion",
    "sg:classifiers":[
        {
            "category":"Utilities",
            "subcategory":"Refuse",
            "type":"Services"
        },
        {
            "category":"Wholesale",
            "subcategory":"Scrap",
            "type":"Manufacturing & Wholesale Goods"
        }
    ],
    "sg:phone":"+1 585 589 0377",
    "sg:postcode":"14411",
    "sg:province":"NY",
    "sg:tags":[
        "recycling",
        "center",
        "system"
    ],
    "wof:name":"Albion Redemption Center",
    "wof:placetype":"venue"
},
  "geometry": {"coordinates":[-78.18810000000001,43.247375],"type":"Point"}
}