{
  "type": "Feature",
  "properties": {
    "addr:full":"230 E 73 St New York NY 10021",
    "addr:housenumber":"230;73",
    "addr:postcode":"10021",
    "addr:street":"E;St",
    "iso:country":"US",
    "sg:address":"230 E 73 St",
    "sg:city":"New York",
    "sg:classifiers":[
        {
            "category":"Restaurant",
            "type":"Food & Drink"
        }
    ],
    "sg:phone":"+1   ",
    "sg:postcode":"10021",
    "sg:province":"NY",
    "sg:tags":[
        "eating"
    ],
    "wof:name":"Red Dragon Research",
    "wof:placetype":"venue"
},
  "geometry": {"coordinates":[-73.958423,40.769709],"type":"Point"}
}