{
  "type": "Feature",
  "properties": {
    "iso:country":"US",
    "sg:address":"33 Highland Ave",
    "sg:city":"Yonkers",
    "sg:classifiers":[
        {
            "category":"Professional",
            "subcategory":"Accounting & Tax Preparation",
            "type":"Services"
        }
    ],
    "sg:phone":"+1 914 793 6193",
    "sg:postcode":"10705",
    "sg:province":"NY",
    "sg:tags":[
        "accountant"
    ],
    "wof:name":"A J Financial Svc",
    "wof:placetype":"venue"
},
  "geometry": {"coordinates":[-73.898202,40.924835],"type":"Point"}
}