{
  "type": "Feature",
  "properties": {
    "addr:full":"20 Beechwood Pl Massapequa Park NY 11762",
    "addr:housenumber":"20",
    "addr:postcode":"11762",
    "addr:street":"Beechwood Pl",
    "iso:country":"US",
    "sg:address":"20 Beechwood Pl",
    "sg:city":"Massapequa Park",
    "sg:classifiers":[
        {
            "category":"Building & Trades",
            "subcategory":"Landscaping Services",
            "type":"Services"
        }
    ],
    "sg:phone":"+1 516 798 6309",
    "sg:postcode":"11762",
    "sg:province":"NY",
    "sg:tags":[
        "lawn",
        "maintenance",
        "grounds"
    ],
    "wof:name":"KMN Lawn Svc",
    "wof:placetype":"venue"
},
  "geometry": {"coordinates":[-73.434318,40.689194],"type":"Point"}
}