{
  "type": "Feature",
  "properties": {
    "addr:full":"296 Bay Rd Queensbury NY 12804",
    "addr:housenumber":"296",
    "addr:postcode":"12804",
    "addr:street":"Bay Rd",
    "iso:country":"US",
    "sg:address":"296 Bay Rd",
    "sg:city":"Queensbury",
    "sg:classifiers":[
        {
            "category":"Organizations",
            "subcategory":"Non-profit Organization",
            "type":"Services"
        },
        {
            "category":"Organizations",
            "subcategory":"Professional Association",
            "type":"Services"
        }
    ],
    "sg:phone":"+1 518 798 3425",
    "sg:postcode":"12804",
    "sg:province":"NY",
    "sg:tags":[
        "realtor"
    ],
    "wof:name":"Warren County Assn of Realtors",
    "wof:placetype":"venue"
},
  "geometry": {"coordinates":[-73.652216,43.328416],"type":"Point"}
}