{
  "type": "Feature",
  "properties": {
    "iso:country":"US",
    "sg:address":"88 N Main St",
    "sg:city":"Spring Valley",
    "sg:classifiers":[
        {
            "category":"Taxi",
            "type":"Transportation"
        }
    ],
    "sg:phone":"+1   ",
    "sg:postcode":"10977",
    "sg:province":"NY",
    "sg:tags":[
        "taxicab"
    ],
    "wof:name":"S O S Taxi",
    "wof:placetype":"venue"
},
  "geometry": {"coordinates":[-74.044336,41.115144],"type":"Point"}
}