{
  "type": "Feature",
  "properties": {
    "addr:full":"966 E 180th St Bronx NY 10460",
    "addr:housenumber":"966",
    "addr:postcode":"10460",
    "addr:street":"E 180Th St",
    "iso:country":"US",
    "sg:address":"966 E 180th St",
    "sg:city":"Bronx",
    "sg:classifiers":[
        {
            "category":"Personal",
            "subcategory":"Beauty Salon",
            "type":"Services"
        }
    ],
    "sg:phone":"+1 718 589 5414",
    "sg:postcode":"10460",
    "sg:province":"NY",
    "wof:name":"Lolin Unisex",
    "wof:placetype":"venue"
},
  "geometry": {"coordinates":[-73.879222,40.843208],"type":"Point"}
}