{
  "type": "Feature",
  "properties": {
    "addr:full":"12 Washington Ave Hastings On Hdsn NY 10706",
    "addr:housenumber":"12",
    "addr:postcode":"10706",
    "addr:street":"Washington Ave",
    "iso:country":"US",
    "sg:address":"12 Washington Ave",
    "sg:city":"Hastings On Hdsn",
    "sg:classifiers":[
        {
            "category":"Shopping",
            "subcategory":"Used Merchandise",
            "type":"Retail Goods"
        }
    ],
    "sg:phone":"+1 914 478 1339",
    "sg:postcode":"10706",
    "sg:province":"NY",
    "sg:tags":[
        "book",
        "rare",
        "dealer"
    ],
    "wof:name":"Riverrun Rare Book Room",
    "wof:placetype":"venue"
},
  "geometry": {"coordinates":[-73.88397000000001,40.992651],"type":"Point"}
}