{
  "type": "Feature",
  "properties": {
    "addr:full":"226 Ryan Rd Saranac NY 12981",
    "addr:housenumber":"226",
    "addr:postcode":"12981",
    "addr:street":"Ryan Rd",
    "iso:country":"US",
    "sg:address":"226 Ryan Rd",
    "sg:city":"Saranac",
    "sg:classifiers":[
        {
            "category":"Retail",
            "subcategory":"Auto Repair",
            "type":"Services"
        }
    ],
    "sg:phone":"+1   ",
    "sg:postcode":"12981",
    "sg:province":"NY",
    "sg:tags":[
        "general"
    ],
    "wof:name":"Oneills Garage",
    "wof:placetype":"venue"
},
  "geometry": {"coordinates":[-73.71808,44.704332],"type":"Point"}
}