{
  "type": "Feature",
  "properties": {
    "addr:full":"486 Dublin Rd Granville NY 12832",
    "addr:housenumber":"486",
    "addr:postcode":"12832",
    "addr:street":"Dublin Rd",
    "iso:country":"US",
    "sg:address":"486 Dublin Rd",
    "sg:city":"Granville",
    "sg:classifiers":[
        {
            "category":"Retail",
            "subcategory":"Auto Repair",
            "type":"Services"
        }
    ],
    "sg:phone":"+1 518 642 2473",
    "sg:postcode":"12832",
    "sg:province":"NY",
    "sg:tags":[
        "repairing",
        "automobile"
    ],
    "wof:name":"J M Automotive",
    "wof:placetype":"venue"
},
  "geometry": {"coordinates":[-73.339598,43.409769],"type":"Point"}
}