{
  "type": "Feature",
  "properties": {
    "addr:full":"1144 Wehrle Dr Buffalo NY 14221",
    "addr:housenumber":"1144",
    "addr:postcode":"14221",
    "addr:street":"Wehrle Dr",
    "iso:country":"US",
    "sg:address":"1144 Wehrle Dr",
    "sg:city":"Buffalo",
    "sg:classifiers":[
        {
            "category":"Banks & Credit Unions",
            "subcategory":"Bank",
            "type":"Services"
        }
    ],
    "sg:phone":"+1 716 631 9300",
    "sg:postcode":"14221",
    "sg:province":"NY",
    "sg:tags":[
        "originator",
        "indirect",
        "loan"
    ],
    "wof:name":"Ada Capital Corp",
    "wof:placetype":"venue"
},
  "geometry": {"coordinates":[-78.743191,42.949695],"type":"Point"}
}