{
  "type": "Feature",
  "properties": {
    "addr:full":"236 W 26th St New York NY 10001",
    "addr:housenumber":"236",
    "addr:postcode":"10001",
    "addr:street":"W 26Th St",
    "iso:country":"US",
    "sg:address":"236 W 26th St",
    "sg:city":"New York",
    "sg:classifiers":[
        {
            "category":"Retail",
            "subcategory":"Auto Repair",
            "type":"Services"
        }
    ],
    "sg:phone":"+1 212 792 0757",
    "sg:postcode":"10001",
    "sg:province":"NY",
    "sg:tags":[
        "wrecker"
    ],
    "wof:name":"Emergency Anytime Towing",
    "wof:placetype":"venue"
},
  "geometry": {"coordinates":[-73.996574,40.746826],"type":"Point"}
}