{
  "type": "Feature",
  "properties": {
    "addr:full":"6780 Northern Blvd East Syracuse NY 13057",
    "addr:housenumber":"6780",
    "addr:postcode":"13057",
    "addr:street":"Northern Blvd",
    "iso:country":"US",
    "sg:address":"6780 Northern Blvd",
    "sg:city":"East Syracuse",
    "sg:classifiers":[
        {
            "category":"Wholesale",
            "subcategory":"Stationery",
            "type":"Manufacturing & Wholesale Goods"
        }
    ],
    "sg:phone":"+1 315 432 0168",
    "sg:postcode":"13057",
    "sg:province":"NY",
    "sg:tags":[
        "mill",
        "paper",
        "broker",
        "representative"
    ],
    "wof:name":"Brown Marketing",
    "wof:placetype":"venue"
},
  "geometry": {"coordinates":[-76.077094,43.104581],"type":"Point"}
}