{
  "type": "Feature",
  "properties": {
    "iso:country":"US",
    "sg:address":"13864 Francis Lewis Boulevard",
    "sg:city":"Rosedale",
    "sg:classifiers":[
        {
            "category":"Banks & Credit Unions",
            "subcategory":"Financial Services",
            "type":"Services"
        }
    ],
    "sg:phone":"+1 718 276 5255",
    "sg:postcode":"11422",
    "sg:province":"NY",
    "sg:tags":[
        "broker",
        "mortgage"
    ],
    "wof:name":"USA Mortgage Bankers of America",
    "wof:placetype":"venue"
},
  "geometry": {"coordinates":[-73.737306,40.667321],"type":"Point"}
}