{
  "type": "Feature",
  "properties": {
    "addr:full":"1700 Nereid Ave Bronx NY 10466",
    "addr:housenumber":"1700",
    "addr:postcode":"10466",
    "addr:street":"Nereid Ave",
    "iso:country":"US",
    "sg:address":"1700 Nereid Ave",
    "sg:city":"Bronx",
    "sg:classifiers":[
        {
            "category":"Home & Garden",
            "subcategory":"Household Appliances",
            "type":"Retail Goods"
        }
    ],
    "sg:phone":"+1 718 798 4819",
    "sg:postcode":"10466",
    "sg:province":"NY",
    "wof:name":"Lloyds Appliance",
    "wof:placetype":"venue"
},
  "geometry": {"coordinates":[-73.85122200000001,40.898115],"type":"Point"}
}