{
  "type": "Feature",
  "properties": {
    "iso:country":"US",
    "sg:address":"2140 Boston Post Rd",
    "sg:city":"Larchmont",
    "sg:classifiers":[
        {
            "category":"Shopping",
            "subcategory":"Musical Instruments",
            "type":"Retail Goods"
        }
    ],
    "sg:phone":"+1 914 833 9710",
    "sg:postcode":"10538",
    "sg:province":"NY",
    "sg:tags":[
        "music",
        "dealer"
    ],
    "wof:name":"Peter Hand Music",
    "wof:placetype":"venue"
},
  "geometry": {"coordinates":[-73.75239500000001,40.927042],"type":"Point"}
}