{
  "type": "Feature",
  "properties": {
    "addr:full":"1 Entrance Way Purdys NY 10578",
    "addr:postcode":"10578",
    "addr:street":"Entrance Way",
    "iso:country":"US",
    "sg:address":"1 Entrance Way",
    "sg:city":"Purdys",
    "sg:classifiers":[
        {
            "category":"Building & Trades",
            "subcategory":"Plumbing",
            "type":"Services"
        }
    ],
    "sg:phone":"+1 914 277 4115",
    "sg:postcode":"10578",
    "sg:province":"NY",
    "sg:tags":[
        "plumbing",
        "contractor"
    ],
    "wof:name":"Viking Plumbing & Heating",
    "wof:placetype":"venue"
},
  "geometry": {"coordinates":[-73.673902,41.328545],"type":"Point"}
}