{
  "type": "Feature",
  "properties": {
    "iso:country":"US",
    "sg:address":"658 Hemlock St",
    "sg:city":"Brooklyn",
    "sg:classifiers":[
        {
            "category":"Travel",
            "subcategory":"Travel Agent",
            "type":"Entertainment"
        }
    ],
    "sg:phone":"+1 718 623 8972",
    "sg:postcode":"11208",
    "sg:province":"NY",
    "sg:tags":[
        "agency",
        "bureau"
    ],
    "wof:name":"Atlantic Travel & Tour Inc",
    "wof:placetype":"venue"
},
  "geometry": {"coordinates":[-73.86830399999999,40.672202],"type":"Point"}
}