{
  "type": "Feature",
  "properties": {
    "iso:country":"US",
    "sg:address":"100 E 9th St",
    "sg:city":"Oswego",
    "sg:classifiers":[
        {
            "category":"Bars & Pubs",
            "type":"Food & Drink"
        }
    ],
    "sg:phone":"+1 315 343 9886",
    "sg:postcode":"13126",
    "sg:province":"NY",
    "wof:name":"Port City Tavern",
    "wof:placetype":"venue"
},
  "geometry": {"coordinates":[-76.501423,43.463834],"type":"Point"}
}