{
  "type": "Feature",
  "properties": {
    "iso:country":"US",
    "sg:address":"42 New St",
    "sg:city":"Middletown",
    "sg:classifiers":[
        {
            "category":"Food & Beverages",
            "subcategory":"Groceries & Convenience Stores",
            "type":"Retail Goods"
        }
    ],
    "sg:phone":"+1   ",
    "sg:postcode":"10940",
    "sg:province":"NY",
    "wof:name":"A & M Mini Market",
    "wof:placetype":"venue"
},
  "geometry": {"coordinates":[-74.40998,41.447168],"type":"Point"}
}