{
  "type": "Feature",
  "properties": {
    "addr:full":"215 E 24th St Ste 603 New York NY 10010",
    "addr:housenumber":"215;603",
    "addr:postcode":"10010",
    "addr:street":"E 24Th St Ste",
    "iso:country":"US",
    "sg:address":"215 E 24th St Ste 603",
    "sg:city":"New York",
    "sg:classifiers":[
        {
            "category":"Personal",
            "subcategory":"Beauty Salon",
            "type":"Services"
        }
    ],
    "sg:phone":"+1 845 664 2609",
    "sg:postcode":"10010",
    "sg:province":"NY",
    "sg:tags":[
        "hair"
    ],
    "sg:website":"www.quicktint.net",
    "wof:name":"QuickTint",
    "wof:placetype":"venue"
},
  "geometry": {"coordinates":[-73.98232,40.739342],"type":"Point"}
}