{
  "type": "Feature",
  "properties": {
    "addr:full":"1546 52nd St Brooklyn NY 11219",
    "addr:housenumber":"1546",
    "addr:postcode":"11219",
    "addr:street":"52Nd St",
    "iso:country":"US",
    "sg:address":"1546 52nd St",
    "sg:city":"Brooklyn",
    "sg:classifiers":[
        {
            "category":"Wholesale",
            "subcategory":"Groceries",
            "type":"Manufacturing & Wholesale Goods"
        }
    ],
    "sg:phone":"+1 718 972 0423",
    "sg:postcode":"11219",
    "sg:province":"NY",
    "sg:tags":[
        "food",
        "product",
        "health"
    ],
    "wof:name":"Quality Food Intl",
    "wof:placetype":"venue"
},
  "geometry": {"coordinates":[-73.98809,40.629921],"type":"Point"}
}