{
  "type": "Feature",
  "properties": {
    "iso:country":"US",
    "sg:address":"1680 Atlantic Ave",
    "sg:city":"Brooklyn",
    "sg:classifiers":[
        {
            "category":"Freight",
            "type":"Transportation"
        }
    ],
    "sg:phone":"+1 718 735 1600",
    "sg:postcode":"11213",
    "sg:province":"NY",
    "sg:tags":[
        "commercial",
        "storage"
    ],
    "wof:name":"Safeguard Self Storage",
    "wof:placetype":"venue"
},
  "geometry": {"coordinates":[-73.933617,40.677425],"type":"Point"}
}