{
  "type": "Feature",
  "properties": {
    "iso:country":"US",
    "sg:address":"774 Manhattan Ave",
    "sg:city":"Brooklyn",
    "sg:classifiers":[
        {
            "category":"Shopping",
            "subcategory":"Jewelry",
            "type":"Retail Goods"
        }
    ],
    "sg:phone":"+1 718 383 3623",
    "sg:postcode":"11222",
    "sg:province":"NY",
    "sg:tags":[
        "jeweler"
    ],
    "wof:name":"Jozef & Sons Jewelry LTD",
    "wof:placetype":"venue"
},
  "geometry": {"coordinates":[-73.953182,40.728111],"type":"Point"}
}