{
  "type": "Feature",
  "properties": {
    "addr:full":"2246 Grandconcourse Bronx NY 10457",
    "addr:housenumber":"2246",
    "addr:postcode":"10457",
    "addr:street":"Grandconcourse",
    "iso:country":"US",
    "sg:address":"2246 Grandconcourse",
    "sg:city":"Bronx",
    "sg:classifiers":[
        {
            "category":"Professional",
            "subcategory":"Computer Services",
            "type":"Services"
        }
    ],
    "sg:phone":"+1 718 584 2600",
    "sg:postcode":"10457",
    "sg:province":"NY",
    "sg:tags":[
        "repair"
    ],
    "sg:website":"compusettings.com",
    "wof:name":"Compusetting Inc",
    "wof:placetype":"venue"
},
  "geometry": {"coordinates":[-73.899996,40.856384],"type":"Point"}
}