{
  "type": "Feature",
  "properties": {
    "iso:country":"US",
    "sg:address":"109 Croton Ave",
    "sg:city":"Ossining",
    "sg:classifiers":[
        {
            "category":"Shopping",
            "subcategory":"Jewelry",
            "type":"Retail Goods"
        }
    ],
    "sg:phone":"+1   ",
    "sg:postcode":"10562",
    "sg:province":"NY",
    "wof:name":"Phillippvs",
    "wof:placetype":"venue"
},
  "geometry": {"coordinates":[-73.855023,41.166373],"type":"Point"}
}