{
  "type": "Feature",
  "properties": {
    "iso:country":"US",
    "sg:address":"302 Bowery",
    "sg:city":"New York",
    "sg:phone":"+1 212 777 3927",
    "sg:postcode":"10012",
    "sg:province":"NY",
    "sg:tags":[
        "equipment",
        "supply"
    ],
    "wof:name":"Marks Restaurant Eqp Corp",
    "wof:placetype":"venue"
},
  "geometry": {"coordinates":[-73.992524,40.724465],"type":"Point"}
}