{
  "type": "Feature",
  "properties": {
    "iso:country":"US",
    "sg:address":"15 Lawn St",
    "sg:city":"Rochester",
    "sg:classifiers":[
        {
            "category":"Building & Trades",
            "subcategory":"Construction",
            "type":"Services"
        }
    ],
    "sg:phone":"+1 585 546 5570",
    "sg:postcode":"14607",
    "sg:province":"NY",
    "sg:tags":[
        "utility",
        "contractor"
    ],
    "wof:name":"Rochester District Heating Co",
    "wof:placetype":"venue"
},
  "geometry": {"coordinates":[-77.600758,43.155701],"type":"Point"}
}