{
  "type": "Feature",
  "properties": {
    "addr:full":"3553 Crittenden Rd Crittenden NY 14004",
    "addr:housenumber":"3553",
    "addr:postcode":"14004",
    "addr:street":"Crittenden Rd",
    "iso:country":"US",
    "sg:address":"3553 Crittenden Rd",
    "sg:city":"Crittenden",
    "sg:classifiers":[
        {
            "category":"Professional",
            "subcategory":"Management & Consulting",
            "type":"Services"
        }
    ],
    "sg:phone":"+1 716 937 6527",
    "sg:postcode":"14004",
    "sg:province":"NY",
    "sg:tags":[
        "environmental",
        "consultant",
        "testing",
        "contractor"
    ],
    "wof:name":"Natures Way Envmtl Cons Contrs",
    "wof:placetype":"venue"
},
  "geometry": {"coordinates":[-78.493826,42.935621],"type":"Point"}
}