{
  "type": "Feature",
  "properties": {
    "addr:full":"1623 Unionport Road Bronx NY 10462",
    "addr:housenumber":"1623",
    "addr:postcode":"10462",
    "addr:street":"Unionport Road",
    "iso:country":"US",
    "sg:address":"1623 Unionport Road",
    "sg:city":"Bronx",
    "sg:classifiers":[
        {
            "category":"Health Services",
            "subcategory":"Doctor",
            "type":"Services"
        },
        {
            "category":"Sports & Exercise",
            "subcategory":"Gym",
            "type":"Entertainment"
        },
        {
            "category":"Arena",
            "subcategory":"Sports Club",
            "type":"Entertainment"
        }
    ],
    "sg:phone":"+1 718 824 9600",
    "sg:postcode":"10462",
    "sg:province":"NY",
    "sg:tags":[
        "martial art"
    ],
    "wof:name":"Alm's Tae Kwon DO",
    "wof:placetype":"venue"
},
  "geometry": {"coordinates":[-73.856505,40.842058],"type":"Point"}
}