{
  "type": "Feature",
  "properties": {
    "addr:full":"200 E Garden St Rome NY 13440",
    "addr:housenumber":"200",
    "addr:postcode":"13440",
    "addr:street":"E Garden St",
    "iso:country":"US",
    "sg:address":"200 E Garden St",
    "sg:city":"Rome",
    "sg:classifiers":[
        {
            "category":"Insurance",
            "subcategory":"Insurance Agent",
            "type":"Services"
        },
        {
            "category":"Insurance",
            "subcategory":"Hazard Insurance",
            "type":"Services"
        },
        {
            "category":"Insurance",
            "subcategory":"Title Insurance",
            "type":"Services"
        },
        {
            "category":"Insurance",
            "subcategory":"Life Insurance",
            "type":"Services"
        },
        {
            "category":"Professional",
            "subcategory":"Lawyer & Legal Services",
            "type":"Services"
        }
    ],
    "sg:phone":"+1 315 336 8875",
    "sg:postcode":"13440",
    "sg:province":"NY",
    "sg:tags":[
        "attorney",
        "business",
        "auto",
        "commercial",
        "homeowner",
        "renter"
    ],
    "wof:name":"Croad ML Insurance Agency",
    "wof:placetype":"venue"
},
  "geometry": {"coordinates":[-75.447517,43.219109],"type":"Point"}
}