{
  "type": "Feature",
  "properties": {
    "iso:country":"US",
    "sg:address":"426 Abbott Rd",
    "sg:city":"Buffalo",
    "sg:classifiers":[
        {
            "category":"Retail",
            "subcategory":"Auto Repair",
            "type":"Services"
        }
    ],
    "sg:phone":"+1 716 883 8996",
    "sg:postcode":"14220",
    "sg:province":"NY",
    "sg:tags":[
        "body",
        "automobile",
        "shop"
    ],
    "sg:website":"http://www.rootscollisionservice.com",
    "wof:name":"Root Collision Service",
    "wof:placetype":"venue"
},
  "geometry": {"coordinates":[-78.816399,42.851101],"type":"Point"}
}