{
  "type": "Feature",
  "properties": {
    "iso:country":"US",
    "sg:address":"149 5th Ave",
    "sg:city":"New York",
    "sg:classifiers":[
        {
            "category":"Manufacturing",
            "subcategory":"Printing",
            "type":"Manufacturing & Wholesale Goods"
        }
    ],
    "sg:phone":"+1 212 473 8200",
    "sg:postcode":"10010",
    "sg:province":"NY",
    "sg:tags":[
        "publisher",
        "publishing",
        "periodical"
    ],
    "sg:website":"www.brownstone.com",
    "wof:name":"Brownstone Publishers Inc",
    "wof:placetype":"venue"
},
  "geometry": {"coordinates":[-73.99007,40.74088],"type":"Point"}
}