{
  "type": "Feature",
  "properties": {
    "addr:full":"801 Prospect Ave Westbury NY 11590",
    "addr:housenumber":"801",
    "addr:postcode":"11590",
    "addr:street":"Prospect Ave",
    "iso:country":"US",
    "sg:address":"801 Prospect Ave",
    "sg:city":"Westbury",
    "sg:classifiers":[
        {
            "category":"Personal",
            "subcategory":"Barber",
            "type":"Services"
        }
    ],
    "sg:phone":"+1 516 338 9640",
    "sg:postcode":"11590",
    "sg:province":"NY",
    "wof:name":"McBride's Barber & Beauty Salon of Westbury",
    "wof:placetype":"venue"
},
  "geometry": {"coordinates":[-73.570503,40.7621],"type":"Point"}
}