{
  "type": "Feature",
  "properties": {
    "iso:country":"US",
    "sg:address":"217 New York Avenue",
    "sg:city":"Halesite",
    "sg:classifiers":[
        {
            "category":"Deli",
            "type":"Food & Drink"
        }
    ],
    "sg:phone":"+1 631 470 9480",
    "sg:postcode":"11743",
    "sg:province":"NY",
    "sg:website":"www.taxisgrille.com",
    "wof:name":"Taxi's Grille",
    "wof:placetype":"venue"
},
  "geometry": {"coordinates":[-73.421375,40.879941],"type":"Point"}
}