{
  "type": "Feature",
  "properties": {
    "addr:full":"88 Leonard St New York NY 10013",
    "addr:housenumber":"88",
    "addr:postcode":"10013",
    "addr:street":"Leonard St",
    "iso:country":"US",
    "sg:address":"88 Leonard St",
    "sg:city":"New York",
    "sg:classifiers":[
        {
            "category":"Building & Trades",
            "subcategory":"Electrical",
            "type":"Services"
        }
    ],
    "sg:phone":"+1 212 925 0289",
    "sg:postcode":"10013",
    "sg:province":"NY",
    "sg:tags":[
        "electric",
        "contractor"
    ],
    "wof:name":"Five Star Electric",
    "wof:placetype":"venue"
},
  "geometry": {"coordinates":[-74.004977,40.71736],"type":"Point"}
}