{
  "type": "Feature",
  "properties": {
    "addr:full":"28 Endor Ave Staten Island NY 10301",
    "addr:housenumber":"28",
    "addr:postcode":"10301",
    "addr:street":"Endor Ave",
    "iso:country":"US",
    "sg:address":"28 Endor Ave",
    "sg:city":"Staten Island",
    "sg:classifiers":[
        {
            "category":"Building & Trades",
            "subcategory":"Construction",
            "type":"Services"
        }
    ],
    "sg:phone":"+1 718 815 7123",
    "sg:postcode":"10301",
    "sg:province":"NY",
    "wof:name":"Stylo Construction Corporation",
    "wof:placetype":"venue"
},
  "geometry": {"coordinates":[-74.10055699999999,40.60834],"type":"Point"}
}