{
  "type": "Feature",
  "properties": {
    "addr:full":"318 Cypress Ave Bronx NY 10454",
    "addr:housenumber":"318",
    "addr:postcode":"10454",
    "addr:street":"Cypress Ave",
    "iso:country":"US",
    "sg:address":"318 Cypress Ave",
    "sg:city":"Bronx",
    "sg:classifiers":[
        {
            "category":"Professional",
            "type":"Services"
        }
    ],
    "sg:phone":"+1 718 292 6238",
    "sg:postcode":"10454",
    "sg:province":"NY",
    "sg:tags":[
        "establishment"
    ],
    "wof:name":"Glamour",
    "wof:placetype":"venue"
},
  "geometry": {"coordinates":[-73.913746,40.806942],"type":"Point"}
}