{
  "type": "Feature",
  "properties": {
    "addr:full":"2118 Seneca St Buffalo NY 14210",
    "addr:housenumber":"2118",
    "addr:postcode":"14210",
    "addr:street":"Seneca St",
    "iso:country":"US",
    "sg:address":"2118 Seneca St",
    "sg:city":"Buffalo",
    "sg:classifiers":[
        {
            "category":"Real Estate",
            "subcategory":"Real Estate Agent",
            "type":"Services"
        }
    ],
    "sg:phone":"+1 716 828 0005",
    "sg:postcode":"14210",
    "sg:province":"NY",
    "wof:name":"Jim Roberts Realty",
    "wof:placetype":"venue"
},
  "geometry": {"coordinates":[-78.80889500000001,42.854798],"type":"Point"}
}