{
  "type": "Feature",
  "properties": {
    "iso:country":"US",
    "sg:address":"322 Center Ave",
    "sg:city":"Mamaroneck",
    "sg:classifiers":[
        {
            "category":"Retail",
            "subcategory":"Auto Repair",
            "type":"Services"
        }
    ],
    "sg:phone":"+1 914 698 7295",
    "sg:postcode":"10543",
    "sg:province":"NY",
    "sg:tags":[
        "body",
        "repairing",
        "shop",
        "automobile",
        "automotive",
        "painting"
    ],
    "wof:name":"Sal & Vito's Auto Body Shop",
    "wof:placetype":"venue"
},
  "geometry": {"coordinates":[-73.74203,40.951815],"type":"Point"}
}