{
  "type": "Feature",
  "properties": {
    "addr:full":"86 Horan Rd Slate Hill NY 10973",
    "addr:housenumber":"86",
    "addr:postcode":"10973",
    "addr:street":"Horan Rd",
    "iso:country":"US",
    "sg:address":"86 Horan Rd",
    "sg:city":"Slate Hill",
    "sg:classifiers":[
        {
            "category":"Real Estate",
            "subcategory":"Architect",
            "type":"Services"
        }
    ],
    "sg:phone":"+1   ",
    "sg:postcode":"10973",
    "sg:province":"NY",
    "sg:tags":[
        "architectural"
    ],
    "wof:name":"Peter A Cirillo",
    "wof:placetype":"venue"
},
  "geometry": {"coordinates":[-74.514825,41.377373],"type":"Point"}
}