{
  "type": "Feature",
  "properties": {
    "iso:country":"US",
    "sg:address":"119 1st St",
    "sg:city":"Newburgh",
    "sg:classifiers":[
        {
            "category":"Deli",
            "type":"Food & Drink"
        },
        {
            "category":"Food & Beverages",
            "subcategory":"Bakery",
            "type":"Retail Goods"
        }
    ],
    "sg:phone":"+1 845 562 1055",
    "sg:postcode":"12550",
    "sg:province":"NY",
    "sg:tags":[
        "sandwich"
    ],
    "wof:name":"G & H Deli Inc",
    "wof:placetype":"venue"
},
  "geometry": {"coordinates":[-74.010507,41.502078],"type":"Point"}
}