{
  "type": "Feature",
  "properties": {
    "iso:country":"US",
    "sg:address":"112 4 Ave",
    "sg:city":"New York",
    "sg:classifiers":[
        {
            "category":"Professional",
            "type":"Services"
        }
    ],
    "sg:phone":"+1 212 473 8400",
    "sg:postcode":"10003",
    "sg:province":"NY",
    "sg:tags":[
        "establishment"
    ],
    "wof:name":"Lessinleslie",
    "wof:placetype":"venue"
},
  "geometry": {"coordinates":[-73.990583,40.730562],"type":"Point"}
}