{
  "type": "Feature",
  "properties": {
    "addr:full":"7 Irving Pl White Plains NY 10606",
    "addr:housenumber":"7",
    "addr:postcode":"10606",
    "addr:street":"Irving Pl",
    "iso:country":"US",
    "sg:address":"7 Irving Pl",
    "sg:city":"White Plains",
    "sg:classifiers":[
        {
            "category":"Retail",
            "subcategory":"Auto Repair",
            "type":"Services"
        }
    ],
    "sg:phone":"+1 914 946 1661",
    "sg:postcode":"10606",
    "sg:province":"NY",
    "sg:tags":[
        "repairing",
        "automobile"
    ],
    "wof:name":"Bart's Auto Svc",
    "wof:placetype":"venue"
},
  "geometry": {"coordinates":[-73.775818,41.028223],"type":"Point"}
}