{
  "type": "Feature",
  "properties": {
    "addr:full":"434 E 10 St New York NY 10009",
    "addr:housenumber":"434;10",
    "addr:postcode":"10009",
    "addr:street":"E",
    "iso:country":"US",
    "sg:address":"434 E 10 St",
    "sg:city":"New York",
    "sg:classifiers":[
        {
            "category":"Real Estate",
            "subcategory":"Real Estate Operator",
            "type":"Services"
        }
    ],
    "sg:phone":"+1 212 505 7679",
    "sg:postcode":"10009",
    "sg:province":"NY",
    "sg:tags":[
        "building",
        "apartment"
    ],
    "wof:name":"432-34 East 10 St Corp",
    "wof:placetype":"venue"
},
  "geometry": {"coordinates":[-73.975641,40.725061],"type":"Point"}
}