{
  "type": "Feature",
  "properties": {
    "iso:country":"US",
    "sg:address":"311 N 15th St",
    "sg:city":"Olean",
    "sg:classifiers":[
        {
            "category":"Home & Garden",
            "subcategory":"Carpets & Floor Coverings",
            "type":"Retail Goods"
        }
    ],
    "sg:phone":"+1   ",
    "sg:postcode":"14760",
    "sg:province":"NY",
    "sg:tags":[
        "cleaning"
    ],
    "wof:name":"Norbys Wndrful Wrld Crpt Uphol",
    "wof:placetype":"venue"
},
  "geometry": {"coordinates":[-78.448273,42.081949],"type":"Point"}
}