{
  "type": "Feature",
  "properties": {
    "addr:full":"21 Robin Hood Ct Nesconset NY 11767",
    "addr:housenumber":"21",
    "addr:postcode":"11767",
    "addr:street":"Robin Hood Ct",
    "iso:country":"US",
    "sg:address":"21 Robin Hood Ct",
    "sg:city":"Nesconset",
    "sg:classifiers":[
        {
            "category":"Insurance",
            "subcategory":"Insurance Agent",
            "type":"Services"
        }
    ],
    "sg:phone":"+1 631 979 5632",
    "sg:postcode":"11767",
    "sg:province":"NY",
    "wof:name":"Knights Of Columbus Insurance",
    "wof:placetype":"venue"
},
  "geometry": {"coordinates":[-73.144417,40.846088],"type":"Point"}
}