{
  "type": "Feature",
  "properties": {
    "iso:country":"US",
    "sg:address":"50 Grant St",
    "sg:city":"Cortland",
    "sg:classifiers":[
        {
            "category":"Retail",
            "subcategory":"Auto Repair",
            "type":"Services"
        }
    ],
    "sg:phone":"+1 607 753 9858",
    "sg:postcode":"13045",
    "sg:province":"NY",
    "sg:tags":[
        "body",
        "automobile",
        "top",
        "upholstery"
    ],
    "wof:name":"Don's Auto Upholstery Inc",
    "wof:placetype":"venue"
},
  "geometry": {"coordinates":[-76.176006,42.605633],"type":"Point"}
}