{
  "type": "Feature",
  "properties": {
    "iso:country":"US",
    "sg:address":"35 Rainer St",
    "sg:city":"Melville",
    "sg:classifiers":[
        {
            "category":"Shopping",
            "subcategory":"Computers & Home Electronics",
            "type":"Retail Goods"
        }
    ],
    "sg:phone":"+1 631 421 0761",
    "sg:postcode":"11747",
    "sg:province":"NY",
    "sg:tags":[
        "software"
    ],
    "wof:name":"Superior Software Logic Inc",
    "wof:placetype":"venue"
},
  "geometry": {"coordinates":[-73.401268,40.802078],"type":"Point"}
}