{
  "type": "Feature",
  "properties": {
    "iso:country":"US",
    "sg:address":"59 Maiden Ln",
    "sg:city":"New York",
    "sg:classifiers":[
        {
            "category":"Government",
            "subcategory":"Office",
            "type":"Public Place"
        }
    ],
    "sg:phone":"+1 212 487 6865",
    "sg:postcode":"10038",
    "sg:province":"NY",
    "sg:tags":[
        "dept",
        "transportation"
    ],
    "wof:name":"Dept of Transportation",
    "wof:placetype":"venue"
},
  "geometry": {"coordinates":[-74.00850199999999,40.708906],"type":"Point"}
}