{
  "type": "Feature",
  "properties": {
    "iso:country":"US",
    "sg:address":"2 Magnolia Ln",
    "sg:city":"Huntington",
    "sg:classifiers":[
        {
            "category":"Building & Trades",
            "subcategory":"Construction",
            "type":"Services"
        }
    ],
    "sg:phone":"+1 631 367 7081",
    "sg:postcode":"11743",
    "sg:province":"NY",
    "sg:tags":[
        "concrete",
        "contractor"
    ],
    "wof:name":"Christy Concrete Corp",
    "wof:placetype":"venue"
},
  "geometry": {"coordinates":[-73.45211999999999,40.826294],"type":"Point"}
}