{
  "type": "Feature",
  "properties": {
    "iso:country":"US",
    "sg:address":"1170 Lexington Ave",
    "sg:city":"Rochester",
    "sg:classifiers":[
        {
            "category":"Wholesale",
            "subcategory":"Machinery & Supplies",
            "type":"Manufacturing & Wholesale Goods"
        }
    ],
    "sg:phone":"+1 585 254 6840",
    "sg:postcode":"14606",
    "sg:province":"NY",
    "sg:tags":[
        "industrial"
    ],
    "wof:name":"Garston/Signline",
    "wof:placetype":"venue"
},
  "geometry": {"coordinates":[-77.660155,43.179278],"type":"Point"}
}