{
  "type": "Feature",
  "properties": {
    "addr:full":"1400 Madison Ave New York NY 10029",
    "addr:housenumber":"1400",
    "addr:postcode":"10029",
    "addr:street":"Madison Ave",
    "iso:country":"US",
    "sg:address":"1400 Madison Ave",
    "sg:city":"New York",
    "sg:classifiers":[
        {
            "category":"Retail",
            "subcategory":"Auto Repair",
            "type":"Services"
        }
    ],
    "sg:phone":"+1 646 307 4742",
    "sg:postcode":"10029",
    "sg:province":"NY",
    "sg:tags":[
        "wrecker"
    ],
    "wof:name":"A Mitzva 24 Hr Towing",
    "wof:placetype":"venue"
},
  "geometry": {"coordinates":[-73.95321,40.788533],"type":"Point"}
}