{
  "type": "Feature",
  "properties": {
    "iso:country":"US",
    "sg:address":"17 Old Eastport Manor Rd",
    "sg:city":"Eastport",
    "sg:classifiers":[
        {
            "category":"Building & Trades",
            "subcategory":"Plumbing",
            "type":"Services"
        }
    ],
    "sg:phone":"+1 631 325 5520",
    "sg:postcode":"11941",
    "sg:province":"NY",
    "sg:tags":[
        "heating",
        "contractor"
    ],
    "wof:name":"Eastport Air Inc",
    "wof:placetype":"venue"
},
  "geometry": {"coordinates":[-72.739519,40.832413],"type":"Point"}
}