{
  "type": "Feature",
  "properties": {
    "iso:country":"US",
    "sg:address":"77 Medford Ave Ste D",
    "sg:city":"Patchogue",
    "sg:classifiers":[
        {
            "category":"Health Services",
            "subcategory":"Doctor",
            "type":"Services"
        }
    ],
    "sg:phone":"+1 631 758 2762",
    "sg:postcode":"11772",
    "sg:province":"NY",
    "wof:name":"Neuropsychological",
    "wof:placetype":"venue"
},
  "geometry": {"coordinates":[-73.971006,40.768635],"type":"Point"}
}