{
  "type": "Feature",
  "properties": {
    "iso:country":"US",
    "sg:address":"1212 Ave of the Americas",
    "sg:city":"New York",
    "sg:classifiers":[
        {
            "category":"Arts & Performance",
            "subcategory":"Theater",
            "type":"Entertainment"
        }
    ],
    "sg:phone":"+1 212 944 5530",
    "sg:postcode":"10036",
    "sg:province":"NY",
    "sg:tags":[
        "bureau"
    ],
    "wof:name":"Eerieworld Entertainment",
    "wof:placetype":"venue"
},
  "geometry": {"coordinates":[-73.981504,40.758193],"type":"Point"}
}