{
  "type": "Feature",
  "properties": {
    "addr:full":"15 Harmony Hill Rd Albany NY 12203",
    "addr:housenumber":"15",
    "addr:postcode":"12203",
    "addr:street":"Harmony Hill Rd",
    "iso:country":"US",
    "sg:address":"15 Harmony Hill Rd",
    "sg:city":"Albany",
    "sg:classifiers":[
        {
            "category":"Real Estate",
            "subcategory":"Real Estate Operator",
            "type":"Services"
        }
    ],
    "sg:phone":"+1 518 456 4435",
    "sg:postcode":"12203",
    "sg:province":"NY",
    "sg:tags":[
        "apartment"
    ],
    "wof:name":"Harmony Hill Apartments",
    "wof:placetype":"venue"
},
  "geometry": {"coordinates":[-73.86632,42.681464],"type":"Point"}
}