{
  "type": "Feature",
  "properties": {
    "iso:country":"US",
    "sg:address":"208 Blanding Rd",
    "sg:city":"Sherburne",
    "sg:classifiers":[
        {
            "category":"Farming",
            "subcategory":"Dairy Farm",
            "type":"Manufacturing & Wholesale Goods"
        }
    ],
    "sg:phone":"+1 607 674 4153",
    "sg:postcode":"13460",
    "sg:province":"NY",
    "wof:name":"Harmony Haven Farms",
    "wof:placetype":"venue"
},
  "geometry": {"coordinates":[-75.51638,42.656494],"type":"Point"}
}