{
  "type": "Feature",
  "properties": {
    "addr:full":"100 E 42nd St New York NY 10017",
    "addr:housenumber":"100",
    "addr:postcode":"10017",
    "addr:street":"E 42Nd St",
    "iso:country":"US",
    "sg:address":"100 E 42nd St",
    "sg:city":"New York",
    "sg:classifiers":[
        {
            "category":"Shopping",
            "subcategory":"Computers & Home Electronics",
            "type":"Retail Goods"
        }
    ],
    "sg:phone":"+1 212 682 4929",
    "sg:postcode":"10017",
    "sg:province":"NY",
    "sg:tags":[
        "equipment",
        "electronic",
        "supply"
    ],
    "wof:name":"Consolidated Electronics Corp",
    "wof:placetype":"venue"
},
  "geometry": {"coordinates":[-73.97604699999999,40.751441],"type":"Point"}
}