{
  "type": "Feature",
  "properties": {
    "addr:full":"801 W State St Ithaca NY 14850",
    "addr:housenumber":"801",
    "addr:postcode":"14850",
    "addr:street":"W State St",
    "iso:country":"US",
    "sg:address":"801 W State St",
    "sg:city":"Ithaca",
    "sg:classifiers":[
        {
            "category":"Home & Garden",
            "subcategory":"Building Materials",
            "type":"Retail Goods"
        }
    ],
    "sg:phone":"+1 607 273 0245",
    "sg:postcode":"14850",
    "sg:province":"NY",
    "sg:tags":[
        "lumber",
        "center"
    ],
    "wof:name":"Cayuga Lumber Inc",
    "wof:placetype":"venue"
},
  "geometry": {"coordinates":[-76.51221700000001,42.439492],"type":"Point"}
}