{
  "type": "Feature",
  "properties": {
    "addr:full":"3510 Main St Buffalo NY 14226",
    "addr:housenumber":"3510",
    "addr:postcode":"14226",
    "addr:street":"Main St",
    "iso:country":"US",
    "sg:address":"3510 Main St",
    "sg:city":"Buffalo",
    "sg:classifiers":[
        {
            "category":"Shopping",
            "subcategory":"Department Store",
            "type":"Retail Goods"
        }
    ],
    "sg:phone":"+1 716 833 3083",
    "sg:postcode":"14226",
    "sg:province":"NY",
    "wof:name":"AJWright",
    "wof:placetype":"venue"
},
  "geometry": {"coordinates":[-78.818393,42.957909],"type":"Point"}
}