{
  "type": "Feature",
  "properties": {
    "addr:full":"1164 Broadway New York NY 10001",
    "addr:housenumber":"1164",
    "addr:postcode":"10001",
    "addr:street":"Broadway",
    "iso:country":"US",
    "sg:address":"1164 Broadway",
    "sg:city":"New York",
    "sg:classifiers":[
        {
            "category":"Insurance",
            "subcategory":"Insurance Agent",
            "type":"Services"
        }
    ],
    "sg:phone":"+1 212 447 1084",
    "sg:postcode":"10001",
    "sg:province":"NY",
    "wof:name":"Allstate Perfumes",
    "wof:placetype":"venue"
},
  "geometry": {"coordinates":[-73.98868899999999,40.745024],"type":"Point"}
}