{
  "type": "Feature",
  "properties": {
    "addr:full":"100 Vernon Ave Mt Vernon NY 10553",
    "addr:housenumber":"100",
    "addr:postcode":"10553",
    "addr:street":"Vernon Ave",
    "iso:country":"US",
    "sg:address":"100 Vernon Ave",
    "sg:city":"Mt Vernon",
    "sg:classifiers":[
        {
            "category":"Health Services",
            "subcategory":"Health Practitioner",
            "type":"Services"
        }
    ],
    "sg:phone":"+1 914 667 2900",
    "sg:postcode":"10553",
    "sg:province":"NY",
    "sg:tags":[
        "psychologist"
    ],
    "wof:name":"Guidance & Consultation Ctr",
    "wof:placetype":"venue"
},
  "geometry": {"coordinates":[-73.81721,40.907377],"type":"Point"}
}