{
  "type": "Feature",
  "properties": {
    "addr:full":"44-02 11th St Ste 308 Long Island City NY 11101",
    "addr:housenumber":"44-02",
    "addr:postcode":"11101",
    "addr:street":"11Th St Ste 308",
    "iso:country":"US",
    "sg:address":"44-02 11th St Ste 308",
    "sg:city":"Long Island City",
    "sg:classifiers":[
        {
            "category":"Education",
            "subcategory":"Music School",
            "type":"Public Place"
        },
        {
            "category":"Health Services",
            "subcategory":"Clinic",
            "type":"Services"
        }
    ],
    "sg:phone":"+1 718 323 9181",
    "sg:postcode":"11101",
    "sg:province":"NY",
    "sg:tags":[
        "instrument",
        "medical",
        "musical",
        "teacher"
    ],
    "sg:website":"www.creativewellnessllc.com",
    "wof:name":"Creative Wellness, LLC",
    "wof:placetype":"venue"
},
  "geometry": {"coordinates":[-73.94975100000001,40.749721],"type":"Point"}
}