{
  "type": "Feature",
  "properties": {
    "addr:full":"64 Lake Rd E Congers NY 10920",
    "addr:housenumber":"64",
    "addr:postcode":"10920",
    "addr:street":"Lake Rd E",
    "iso:country":"US",
    "sg:address":"64 Lake Rd E",
    "sg:city":"Congers",
    "sg:classifiers":[
        {
            "category":"Government",
            "subcategory":"Fire Station",
            "type":"Public Place"
        }
    ],
    "sg:phone":"+1 845 268 6562",
    "sg:postcode":"10920",
    "sg:province":"NY",
    "sg:tags":[
        "protection"
    ],
    "wof:name":"Alert Hook Ladder",
    "wof:placetype":"venue"
},
  "geometry": {"coordinates":[-73.93809899999999,41.149577],"type":"Point"}
}