{
  "type": "Feature",
  "properties": {
    "addr:full":"636 19th St Niagara Falls NY 14301",
    "addr:housenumber":"636",
    "addr:postcode":"14301",
    "addr:street":"19Th St",
    "iso:country":"US",
    "sg:address":"636 19th St",
    "sg:city":"Niagara Falls",
    "sg:classifiers":[
        {
            "category":"Restaurant",
            "type":"Food & Drink"
        }
    ],
    "sg:phone":"+1   ",
    "sg:postcode":"14301",
    "sg:province":"NY",
    "sg:tags":[
        "membership",
        "eating",
        "lodging"
    ],
    "wof:name":"Italian Sons & Daughters",
    "wof:placetype":"venue"
},
  "geometry": {"coordinates":[-79.039039,43.094492],"type":"Point"}
}