{
  "type": "Feature",
  "properties": {
    "iso:country":"US",
    "sg:address":"360 W 34th St",
    "sg:city":"New York",
    "sg:classifiers":[
        {
            "category":"Professional",
            "subcategory":"Computer Services",
            "type":"Services"
        }
    ],
    "sg:phone":"+1 212 695 1838",
    "sg:postcode":"10001",
    "sg:province":"NY",
    "sg:tags":[
        "procurement",
        "solution",
        "for",
        "software"
    ],
    "wof:name":"Cmyk Corporation",
    "wof:placetype":"venue"
},
  "geometry": {"coordinates":[-73.995023,40.752589],"type":"Point"}
}