{
  "type": "Feature",
  "properties": {
    "addr:full":"135 E 57th St Fl 21 New York NY 10022",
    "addr:housenumber":"135;21",
    "addr:postcode":"10022",
    "addr:street":"E 57Th St Fl",
    "iso:country":"US",
    "sg:address":"135 E 57th St Fl 21",
    "sg:city":"New York",
    "sg:classifiers":[
        {
            "category":"Banks & Credit Unions",
            "subcategory":"Investment Brokerage",
            "type":"Services"
        }
    ],
    "sg:phone":"+1 212 371 1350",
    "sg:postcode":"10022",
    "sg:province":"NY",
    "sg:tags":[
        "investing"
    ],
    "wof:name":"Cheyne Capital Mangement Ny Llc",
    "wof:placetype":"venue"
},
  "geometry": {"coordinates":[-73.969133,40.761081],"type":"Point"}
}