{
  "type": "Feature",
  "properties": {
    "iso:country":"US",
    "sg:address":"2017 63rd St",
    "sg:city":"Brooklyn",
    "sg:classifiers":[
        {
            "category":"Health Services",
            "subcategory":"Doctor",
            "type":"Services"
        }
    ],
    "sg:phone":"+1   ",
    "sg:postcode":"11204",
    "sg:province":"NY",
    "sg:tags":[
        "osteopathic"
    ],
    "wof:name":"Salvatore Zelano",
    "wof:placetype":"venue"
},
  "geometry": {"coordinates":[-73.982676,40.616629],"type":"Point"}
}