{
  "type": "Feature",
  "properties": {
    "iso:country":"US",
    "sg:address":"37 Fieldhouse Ave",
    "sg:city":"East Setauket",
    "sg:classifiers":[
        {
            "category":"Building & Trades",
            "subcategory":"Electrical",
            "type":"Services"
        }
    ],
    "sg:phone":"+1 631 689 3268",
    "sg:postcode":"11733",
    "sg:province":"NY",
    "sg:tags":[
        "electric",
        "contractor"
    ],
    "wof:name":"Konsker Electric",
    "wof:placetype":"venue"
},
  "geometry": {"coordinates":[-73.09379199999999,40.900957],"type":"Point"}
}