{
  "type": "Feature",
  "properties": {
    "addr:full":"69 Spiral Rd Holtsville NY 11742",
    "addr:housenumber":"69",
    "addr:postcode":"11742",
    "addr:street":"Spiral Rd",
    "iso:country":"US",
    "sg:address":"69 Spiral Rd",
    "sg:city":"Holtsville",
    "sg:classifiers":[
        {
            "category":"Personal",
            "type":"Services"
        }
    ],
    "sg:phone":"+1 631 472 6085",
    "sg:postcode":"11742",
    "sg:province":"NY",
    "sg:tags":[
        "butlers'",
        "maids'"
    ],
    "wof:name":"Swept Away Cleaning",
    "wof:placetype":"venue"
},
  "geometry": {"coordinates":[-73.047737,40.793968],"type":"Point"}
}