{
  "type": "Feature",
  "properties": {
    "addr:full":"132 Spruce St Cedarhurst NY 11516",
    "addr:housenumber":"132",
    "addr:postcode":"11516",
    "addr:street":"Spruce St",
    "iso:country":"US",
    "sg:address":"132 Spruce St",
    "sg:city":"Cedarhurst",
    "sg:classifiers":[
        {
            "category":"Professional",
            "subcategory":"Lawyer & Legal Services",
            "type":"Services"
        }
    ],
    "sg:phone":"+1 516 295 2070",
    "sg:postcode":"11516",
    "sg:province":"NY",
    "sg:tags":[
        "attorney"
    ],
    "wof:name":"Todd Gabor",
    "wof:placetype":"venue"
},
  "geometry": {"coordinates":[-73.72599599999999,40.621676],"type":"Point"}
}