{
  "type": "Feature",
  "properties": {
    "iso:country":"US",
    "sg:address":"1477 Long Pond Rd",
    "sg:city":"Rochester",
    "sg:classifiers":[
        {
            "category":"Social Services",
            "subcategory":"Retirement Home",
            "type":"Services"
        }
    ],
    "sg:phone":"+1 585 368 4060",
    "sg:postcode":"14626",
    "sg:province":"NY",
    "sg:tags":[
        "convalescent",
        "nursing"
    ],
    "wof:name":"Woodland Village Inc",
    "wof:placetype":"venue"
},
  "geometry": {"coordinates":[-77.701459,43.195928],"type":"Point"}
}