{
  "type": "Feature",
  "properties": {
    "addr:full":"255 E 49th St New York NY 10017",
    "addr:housenumber":"255",
    "addr:postcode":"10017",
    "addr:street":"E 49Th St",
    "iso:country":"US",
    "sg:address":"255 E 49th St",
    "sg:city":"New York",
    "sg:classifiers":[
        {
            "category":"Professional",
            "type":"Services"
        }
    ],
    "sg:phone":"+1 212 832 4758",
    "sg:postcode":"10017",
    "sg:province":"NY",
    "sg:tags":[
        "establishment"
    ],
    "wof:name":"Fay Corp",
    "wof:placetype":"venue"
},
  "geometry": {"coordinates":[-73.969876,40.754836],"type":"Point"}
}