{
  "type": "Feature",
  "properties": {
    "addr:full":"512 73rd St Brooklyn NY 11209",
    "addr:housenumber":"512",
    "addr:postcode":"11209",
    "addr:street":"73Rd St",
    "iso:country":"US",
    "sg:address":"512 73rd St",
    "sg:city":"Brooklyn",
    "sg:classifiers":[
        {
            "category":"Shopping",
            "subcategory":"Gifts & Souvenirs",
            "type":"Retail Goods"
        }
    ],
    "sg:phone":"+1 718 921 0096",
    "sg:postcode":"11209",
    "sg:province":"NY",
    "sg:tags":[
        "shop"
    ],
    "wof:name":"Ariadna's Fantasy",
    "wof:placetype":"venue"
},
  "geometry": {"coordinates":[-74.019819,40.629929],"type":"Point"}
}