{
  "type": "Feature",
  "properties": {
    "iso:country":"US",
    "sg:address":"524 W 57 St",
    "sg:city":"New York",
    "sg:classifiers":[
        {
            "category":"Restaurant",
            "type":"Food & Drink"
        }
    ],
    "sg:phone":"+1   ",
    "sg:postcode":"10019",
    "sg:province":"NY",
    "sg:tags":[
        "eating"
    ],
    "wof:name":"Aramark",
    "wof:placetype":"venue"
},
  "geometry": {"coordinates":[-73.99021,40.76968],"type":"Point"}
}