{
  "type": "Feature",
  "properties": {
    "iso:country":"US",
    "sg:address":"140 2nd Avenue",
    "sg:city":"New York",
    "sg:classifiers":[
        {
            "category":"Retail",
            "subcategory":"Event Space",
            "type":"Services"
        }
    ],
    "sg:phone":"+1 212 529 6287",
    "sg:postcode":"10003",
    "sg:province":"NY",
    "sg:tags":[
        "venue"
    ],
    "wof:name":"Ukrainian National Home",
    "wof:placetype":"venue"
},
  "geometry": {"coordinates":[-73.987247,40.728925],"type":"Point"}
}