{
  "type": "Feature",
  "properties": {
    "iso:country":"US",
    "sg:address":"5705 Brockport Spencerport Rd",
    "sg:city":"Brockport",
    "sg:classifiers":[
        {
            "category":"Building & Trades",
            "subcategory":"Landscaping Services",
            "type":"Services"
        }
    ],
    "sg:phone":"+1 585 350 6453",
    "sg:postcode":"14420",
    "sg:province":"NY",
    "sg:tags":[
        "tree"
    ],
    "wof:name":"Oakes Tree Service",
    "wof:placetype":"venue"
},
  "geometry": {"coordinates":[-77.904922,43.198055],"type":"Point"}
}