{
  "type": "Feature",
  "properties": {
    "iso:country":"US",
    "sg:address":"108 Water St",
    "sg:city":"Newburgh",
    "sg:classifiers":[
        {
            "category":"Building & Trades",
            "subcategory":"Construction",
            "type":"Services"
        }
    ],
    "sg:phone":"+1 845 565 1755",
    "sg:postcode":"12550",
    "sg:province":"NY",
    "sg:tags":[
        "general",
        "contractor"
    ],
    "wof:name":"Genesis Contractors",
    "wof:placetype":"venue"
},
  "geometry": {"coordinates":[-74.006142,41.504672],"type":"Point"}
}