{
  "type": "Feature",
  "properties": {
    "addr:full":"910 Utica Ave Brooklyn NY 11203",
    "addr:housenumber":"910",
    "addr:postcode":"11203",
    "addr:street":"Utica Ave",
    "iso:country":"US",
    "sg:address":"910 Utica Ave",
    "sg:city":"Brooklyn",
    "sg:classifiers":[
        {
            "category":"Wholesale",
            "subcategory":"Meat",
            "type":"Manufacturing & Wholesale Goods"
        }
    ],
    "sg:phone":"+1 718 462 6400",
    "sg:postcode":"11203",
    "sg:province":"NY",
    "sg:tags":[
        "shop"
    ],
    "wof:name":"Utica Meat Warehouse",
    "wof:placetype":"venue"
},
  "geometry": {"coordinates":[-73.930397,40.650501],"type":"Point"}
}