{
  "type": "Feature",
  "properties": {
    "iso:country":"US",
    "sg:address":"19130 Northern Blvd",
    "sg:city":"Flushing",
    "sg:classifiers":[
        {
            "category":"Manufacturing",
            "subcategory":"Chemicals & Compounds",
            "type":"Manufacturing & Wholesale Goods"
        },
        {
            "category":"Shopping",
            "subcategory":"Gifts & Souvenirs",
            "type":"Retail Goods"
        },
        {
            "category":"Home & Garden",
            "subcategory":"Home Furnishings",
            "type":"Retail Goods"
        }
    ],
    "sg:phone":"+1 718 539 0115",
    "sg:postcode":"11358",
    "sg:province":"NY",
    "sg:tags":[
        "shop",
        "wicker",
        "product",
        "house"
    ],
    "sg:website":"http://www.pier1imports.com",
    "wof:name":"Pier 1",
    "wof:placetype":"venue"
},
  "geometry": {"coordinates":[-73.804592,40.7626],"type":"Point"}
}