{
  "type": "Feature",
  "properties": {
    "addr:full":"244 Darlington Ave Staten Island NY 10312",
    "addr:housenumber":"244",
    "addr:postcode":"10312",
    "addr:street":"Darlington Ave",
    "iso:country":"US",
    "sg:address":"244 Darlington Ave",
    "sg:city":"Staten Island",
    "sg:classifiers":[
        {
            "category":"Building & Trades",
            "subcategory":"Construction",
            "type":"Services"
        }
    ],
    "sg:phone":"+1 718 948 2968",
    "sg:postcode":"10312",
    "sg:province":"NY",
    "sg:tags":[
        "concrete",
        "contractor"
    ],
    "wof:name":"David Fredricksen",
    "wof:placetype":"venue"
},
  "geometry": {"coordinates":[-74.19292299999999,40.536639],"type":"Point"}
}