{
  "type": "Feature",
  "properties": {
    "addr:full":"24 S Main St New Berlin NY 13411",
    "addr:housenumber":"24",
    "addr:postcode":"13411",
    "addr:street":"S Main St",
    "iso:country":"US",
    "sg:address":"24 S Main St",
    "sg:city":"New Berlin",
    "sg:classifiers":[
        {
            "category":"Personal",
            "type":"Services"
        }
    ],
    "sg:phone":"+1 607 847 6866",
    "sg:postcode":"13411",
    "sg:province":"NY",
    "sg:tags":[
        "therapist",
        "massage"
    ],
    "wof:name":"Healing Waters Massage",
    "wof:placetype":"venue"
},
  "geometry": {"coordinates":[-75.33196599999999,42.621241],"type":"Point"}
}