{
  "type": "Feature",
  "properties": {
    "addr:full":"281 Fall St Seneca Falls NY 13148",
    "addr:housenumber":"281",
    "addr:postcode":"13148",
    "addr:street":"Fall St",
    "iso:country":"US",
    "sg:address":"281 Fall St",
    "sg:city":"Seneca Falls",
    "sg:classifiers":[
        {
            "category":"Manufacturing",
            "subcategory":"Signs",
            "type":"Manufacturing & Wholesale Goods"
        }
    ],
    "sg:phone":"+1 315 568 6955",
    "sg:postcode":"13148",
    "sg:province":"NY",
    "sg:website":"www.legrandsignworks.com",
    "wof:name":"Legrand Lettering & Sign Works",
    "wof:placetype":"venue"
},
  "geometry": {"coordinates":[-76.815023,42.910252],"type":"Point"}
}