{
  "type": "Feature",
  "properties": {
    "addr:full":"2070 Grand Concourse Bronx NY 10457",
    "addr:housenumber":"2070",
    "addr:postcode":"10457",
    "addr:street":"Grand Concourse",
    "iso:country":"US",
    "sg:address":"2070 Grand Concourse",
    "sg:city":"Bronx",
    "sg:classifiers":[
        {
            "category":"Professional",
            "subcategory":"Management & Consulting",
            "type":"Services"
        }
    ],
    "sg:phone":"+1 718 294 1600",
    "sg:postcode":"10457",
    "sg:province":"NY",
    "sg:tags":[
        "promotion",
        "sales"
    ],
    "wof:name":"Albuez Promotions",
    "wof:placetype":"venue"
},
  "geometry": {"coordinates":[-73.903175,40.852671],"type":"Point"}
}