{
  "type": "Feature",
  "properties": {
    "iso:country":"US",
    "sg:address":"12218 Sutphin Blvd",
    "sg:city":"Jamaica",
    "sg:classifiers":[
        {
            "category":"Organizations",
            "subcategory":"Religious Organization",
            "type":"Services"
        }
    ],
    "sg:phone":"+1 718 529 2843",
    "sg:postcode":"11434",
    "sg:province":"NY",
    "wof:name":"Norman Jerome Rev",
    "wof:placetype":"venue"
},
  "geometry": {"coordinates":[-73.790604,40.676102],"type":"Point"}
}