{
  "type": "Feature",
  "properties": {
    "addr:full":"4101 1st Ave Brooklyn NY 11232",
    "addr:housenumber":"4101",
    "addr:postcode":"11232",
    "addr:street":"1St Ave",
    "iso:country":"US",
    "sg:address":"4101 1st Ave",
    "sg:city":"Brooklyn",
    "sg:classifiers":[
        {
            "category":"Wholesale",
            "subcategory":"Hardware",
            "type":"Manufacturing & Wholesale Goods"
        }
    ],
    "sg:phone":"+1 718 965 9614",
    "sg:postcode":"11232",
    "sg:province":"NY",
    "sg:tags":[
        "plumbing",
        "fixture",
        "supply"
    ],
    "wof:name":"Gilmour Supply Co",
    "wof:placetype":"venue"
},
  "geometry": {"coordinates":[-74.01446799999999,40.65491],"type":"Point"}
}