{
  "type": "Feature",
  "properties": {
    "addr:full":"86 34th St Brooklyn NY 11232",
    "addr:housenumber":"86",
    "addr:postcode":"11232",
    "addr:street":"34Th St",
    "iso:country":"US",
    "sg:address":"86 34th St",
    "sg:city":"Brooklyn",
    "sg:classifiers":[
        {
            "category":"Freight",
            "type":"Transportation"
        }
    ],
    "sg:phone":"+1   ",
    "sg:postcode":"11232",
    "sg:province":"NY",
    "sg:tags":[
        "general"
    ],
    "wof:name":"Ward Textile Corporation",
    "wof:placetype":"venue"
},
  "geometry": {"coordinates":[-74.00664999999999,40.657635],"type":"Point"}
}