{
  "type": "Feature",
  "properties": {
    "iso:country":"US",
    "sg:address":"160 Mount Hope Ave",
    "sg:city":"Rochester",
    "sg:classifiers":[
        {
            "category":"Social Services",
            "type":"Services"
        }
    ],
    "sg:phone":"+1 585 473 9027",
    "sg:postcode":"14620",
    "sg:province":"NY",
    "sg:tags":[
        "individual",
        "family"
    ],
    "wof:name":"Operation Friendship",
    "wof:placetype":"venue"
},
  "geometry": {"coordinates":[-77.60848300000001,43.146831],"type":"Point"}
}