{
  "type": "Feature",
  "properties": {
    "iso:country":"US",
    "sg:address":"4306 47th Ave",
    "sg:city":"Sunnyside",
    "sg:phone":"+1 718 937 6067",
    "sg:postcode":"11104",
    "sg:province":"NY",
    "wof:name":"Peter's Hair Impressions",
    "wof:placetype":"venue"
},
  "geometry": {"coordinates":[-73.91774700000001,40.743145],"type":"Point"}
}