{
  "type": "Feature",
  "properties": {
    "iso:country":"US",
    "sg:address":"229 W 97th St",
    "sg:city":"New York",
    "sg:classifiers":[
        {
            "category":"Communications",
            "subcategory":"Film & Video Production",
            "type":"Services"
        },
        {
            "category":"Professional",
            "subcategory":"Business Services",
            "type":"Services"
        }
    ],
    "sg:phone":"+1 212 665 2446",
    "sg:postcode":"10025",
    "sg:province":"NY",
    "sg:tags":[
        "motion"
    ],
    "sg:website":"www.monarchclassics.com",
    "wof:name":"Monarch Classics Productions",
    "wof:placetype":"venue"
},
  "geometry": {"coordinates":[-73.97046400000001,40.794958],"type":"Point"}
}