{
  "type": "Feature",
  "properties": {
    "addr:full":"535 Plandome Rd Frnt 4 Manhasset NY 11030",
    "addr:housenumber":"535;4",
    "addr:postcode":"11030",
    "addr:street":"Plandome Rd Frnt",
    "iso:country":"US",
    "sg:address":"535 Plandome Rd Frnt 4",
    "sg:city":"Manhasset",
    "sg:classifiers":[
        {
            "category":"Health Services",
            "subcategory":"Doctor",
            "type":"Services"
        }
    ],
    "sg:phone":"+1 516 773 0101",
    "sg:postcode":"11030",
    "sg:province":"NY",
    "wof:name":"North Shore Urology",
    "wof:placetype":"venue"
},
  "geometry": {"coordinates":[-73.70100600000001,40.799515],"type":"Point"}
}