{
  "type": "Feature",
  "properties": {
    "addr:full":"626 Commerce Dr Buffalo NY 14228",
    "addr:housenumber":"626",
    "addr:postcode":"14228",
    "addr:street":"Commerce Dr",
    "iso:country":"US",
    "sg:address":"626 Commerce Dr",
    "sg:city":"Buffalo",
    "sg:classifiers":[
        {
            "category":"Banks & Credit Unions",
            "subcategory":"Bank",
            "type":"Services"
        }
    ],
    "sg:phone":"+1 716 842 5385",
    "sg:postcode":"14228",
    "sg:province":"NY",
    "sg:tags":[
        "state",
        "commercial"
    ],
    "wof:name":"M&T Bank Corp",
    "wof:placetype":"venue"
},
  "geometry": {"coordinates":[-78.800883,43.026737],"type":"Point"}
}