{
  "type": "Feature",
  "properties": {
    "addr:full":"706 Erie Blvd W Rome NY 13440",
    "addr:housenumber":"706",
    "addr:postcode":"13440",
    "addr:street":"Erie Blvd W",
    "iso:country":"US",
    "sg:address":"706 Erie Blvd W",
    "sg:city":"Rome",
    "sg:classifiers":[
        {
            "category":"Retail",
            "subcategory":"Auto Rental",
            "type":"Services"
        }
    ],
    "sg:phone":"+1 315 337 6000",
    "sg:postcode":"13440",
    "sg:province":"NY",
    "sg:tags":[
        "automobile"
    ],
    "wof:name":"Enterprise Rent-A-Car Company",
    "wof:placetype":"venue"
},
  "geometry": {"coordinates":[-75.47170199999999,43.215416],"type":"Point"}
}