{
  "type": "Feature",
  "properties": {
    "iso:country":"US",
    "sg:address":"349 New York Ave",
    "sg:city":"Huntington",
    "sg:classifiers":[
        {
            "category":"Health Services",
            "subcategory":"Clinic",
            "type":"Services"
        },
        {
            "category":"Shopping",
            "subcategory":"Pharmacy",
            "type":"Retail Goods"
        }
    ],
    "sg:phone":"+1 631 427 2919",
    "sg:postcode":"11743",
    "sg:province":"NY",
    "sg:tags":[
        "medical",
        "drugstore"
    ],
    "sg:website":"www.valuedrugspharmacy.com",
    "wof:name":"Value Drugs Pharmacy",
    "wof:placetype":"venue"
},
  "geometry": {"coordinates":[-73.42600299999999,40.870602],"type":"Point"}
}