{
  "type": "Feature",
  "properties": {
    "addr:full":"65 Sherman Ave New York NY 10040",
    "addr:housenumber":"65",
    "addr:postcode":"10040",
    "addr:street":"Sherman Ave",
    "iso:country":"US",
    "sg:address":"65 Sherman Ave",
    "sg:city":"New York",
    "sg:classifiers":[
        {
            "category":"Bars & Pubs",
            "type":"Food & Drink"
        }
    ],
    "sg:phone":"+1 212 304 0244",
    "sg:postcode":"10040",
    "sg:province":"NY",
    "wof:name":"Los Compadres Bar",
    "wof:placetype":"venue"
},
  "geometry": {"coordinates":[-73.926011,40.863575],"type":"Point"}
}