{
  "type": "Feature",
  "properties": {
    "iso:country":"US",
    "sg:address":"742 S Crouse Ave",
    "sg:city":"Syracuse",
    "sg:classifiers":[
        {
            "category":"Shopping",
            "subcategory":"Computers & Home Electronics",
            "type":"Retail Goods"
        }
    ],
    "sg:phone":"+1 315 952 1498",
    "sg:postcode":"13210",
    "sg:province":"NY",
    "sg:tags":[
        "equipment",
        "dealer"
    ],
    "wof:name":"Computerz Central",
    "wof:placetype":"venue"
},
  "geometry": {"coordinates":[-76.13668699999999,43.039485],"type":"Point"}
}