{
  "type": "Feature",
  "properties": {
    "addr:full":"210 W 89 St New York NY 10024",
    "addr:housenumber":"210",
    "addr:postcode":"10024",
    "addr:street":"W 89 St",
    "iso:country":"US",
    "sg:address":"210 W 89 St",
    "sg:city":"New York",
    "sg:classifiers":[
        {
            "category":"Professional",
            "subcategory":"Computer Services",
            "type":"Services"
        }
    ],
    "sg:phone":"+1 212 579 9189",
    "sg:postcode":"10024",
    "sg:province":"NY",
    "sg:tags":[
        "consulting"
    ],
    "wof:name":"Diamond Consulting Inc",
    "wof:placetype":"venue"
},
  "geometry": {"coordinates":[-73.974839,40.790023],"type":"Point"}
}