{
  "type": "Feature",
  "properties": {
    "iso:country":"US",
    "sg:address":"12 Parr Cir",
    "sg:city":"Rochester",
    "sg:classifiers":[
        {
            "category":"Social Services",
            "type":"Services"
        }
    ],
    "sg:phone":"+1 585 342 2430",
    "sg:postcode":"14617",
    "sg:province":"NY",
    "sg:tags":[
        "organization",
        "welfare"
    ],
    "wof:name":"Marriage Encounter",
    "wof:placetype":"venue"
},
  "geometry": {"coordinates":[-77.596745,43.206009],"type":"Point"}
}