{
  "type": "Feature",
  "properties": {
    "iso:country":"US",
    "sg:address":"545 5th Ave",
    "sg:city":"New York",
    "sg:classifiers":[
        {
            "category":"Professional",
            "subcategory":"Business Services",
            "type":"Services"
        }
    ],
    "sg:phone":"+1 212 557 5720",
    "sg:postcode":"10017",
    "sg:province":"NY",
    "sg:tags":[
        "on",
        "lending",
        "library",
        "recording",
        "studio",
        "textbook",
        "au"
    ],
    "wof:name":"FRB&d",
    "wof:placetype":"venue"
},
  "geometry": {"coordinates":[-73.979936,40.754782],"type":"Point"}
}