{
  "type": "Feature",
  "properties": {
    "addr:full":"12 Collins Way Bloomingburg NY 12721",
    "addr:housenumber":"12",
    "addr:postcode":"12721",
    "addr:street":"Collins Way",
    "iso:country":"US",
    "sg:address":"12 Collins Way",
    "sg:city":"Bloomingburg",
    "sg:classifiers":[
        {
            "category":"Building & Trades",
            "subcategory":"Construction",
            "type":"Services"
        }
    ],
    "sg:phone":"+1 845 386 8811",
    "sg:postcode":"12721",
    "sg:province":"NY",
    "sg:tags":[
        "home",
        "improvement"
    ],
    "wof:name":"M J Design",
    "wof:placetype":"venue"
},
  "geometry": {"coordinates":[-74.47917099999999,41.541841],"type":"Point"}
}