{
  "type": "Feature",
  "properties": {
    "iso:country":"US",
    "sg:address":"623 Wagner Hill Rd",
    "sg:city":"Fort Plain",
    "sg:classifiers":[
        {
            "category":"Home & Garden",
            "subcategory":"Building Materials",
            "type":"Retail Goods"
        },
        {
            "category":"Retail",
            "subcategory":"Auto Repair",
            "type":"Services"
        }
    ],
    "sg:phone":"+1 518 993 2091",
    "sg:postcode":"13339",
    "sg:province":"NY",
    "sg:tags":[
        "automotive",
        "window",
        "plate",
        "glass"
    ],
    "wof:name":"Jay's Auto & Accessories",
    "wof:placetype":"venue"
},
  "geometry": {"coordinates":[-74.78044800000001,42.905248],"type":"Point"}
}