{
  "type": "Feature",
  "properties": {
    "addr:full":"Empire State Building 350 FIfth Ave 59th Fl Manhattan NY 10118",
    "addr:housenumber":"350",
    "addr:postcode":"10118",
    "addr:street":"Fifth Ave 59Th Fl",
    "iso:country":"US",
    "sg:address":"Empire State Building 350 FIfth Ave 59th Fl",
    "sg:city":"Manhattan",
    "sg:classifiers":[
        {
            "category":"Personal",
            "subcategory":"Massage",
            "type":"Services"
        },
        {
            "category":"Personal",
            "subcategory":"Skin Care",
            "type":"Services"
        }
    ],
    "sg:phone":"+1 212 601 2890",
    "sg:postcode":"10118",
    "sg:province":"NY",
    "sg:website":"www.cherryblossomk.com",
    "wof:name":"Cherry Blossom Kanazawa",
    "wof:placetype":"venue"
},
  "geometry": {"coordinates":[-73.985311,40.748266],"type":"Point"}
}