{
  "type": "Feature",
  "properties": {
    "addr:full":"347 Long Beach Rd Ofc Island Park NY 11558",
    "addr:housenumber":"347",
    "addr:postcode":"11558",
    "addr:street":"Long Beach Rd;Park",
    "iso:country":"US",
    "sg:address":"347 Long Beach Rd Ofc",
    "sg:city":"Island Park",
    "sg:classifiers":[
        {
            "category":"Real Estate",
            "subcategory":"Real Estate Services",
            "type":"Services"
        }
    ],
    "sg:phone":"+1 516 889 7570",
    "sg:postcode":"11558",
    "sg:province":"NY",
    "sg:tags":[
        "management",
        "property"
    ],
    "wof:name":"Jeffrey Managmnt Corp",
    "wof:placetype":"venue"
},
  "geometry": {"coordinates":[-73.65540300000001,40.6064],"type":"Point"}
}