{
  "type": "Feature",
  "properties": {
    "addr:full":"146 E Rockaway Rd Hewlett NY 11557",
    "addr:housenumber":"146",
    "addr:postcode":"11557",
    "addr:street":"E Rockaway Rd",
    "iso:country":"US",
    "sg:address":"146 E Rockaway Rd",
    "sg:city":"Hewlett",
    "sg:classifiers":[
        {
            "category":"Real Estate",
            "subcategory":"Real Estate Operator",
            "type":"Services"
        }
    ],
    "sg:phone":"+1 516 295 1754",
    "sg:postcode":"11557",
    "sg:province":"NY",
    "sg:tags":[
        "building",
        "nonresidential"
    ],
    "wof:name":"Raifer Enterprises",
    "wof:placetype":"venue"
},
  "geometry": {"coordinates":[-73.69076699999999,40.640961],"type":"Point"}
}