{
  "type": "Feature",
  "properties": {
    "addr:full":"1010 Park St Peekskill NY 10566",
    "addr:housenumber":"1010",
    "addr:postcode":"10566",
    "addr:street":"Park St",
    "iso:country":"US",
    "sg:address":"1010 Park St",
    "sg:city":"Peekskill",
    "sg:classifiers":[
        {
            "category":"Professional",
            "subcategory":"Lawyer & Legal Services",
            "type":"Services"
        }
    ],
    "sg:phone":"+1 914 737 0020",
    "sg:postcode":"10566",
    "sg:province":"NY",
    "sg:tags":[
        "attorney"
    ],
    "wof:name":"Edward W Doyle",
    "wof:placetype":"venue"
},
  "geometry": {"coordinates":[-73.919685,41.290835],"type":"Point"}
}