{
  "type": "Feature",
  "properties": {
    "iso:country":"US",
    "sg:address":"1756 Grand Ave",
    "sg:city":"Merrick",
    "sg:classifiers":[
        {
            "category":"Building & Trades",
            "subcategory":"Pest Control",
            "type":"Services"
        }
    ],
    "sg:phone":"+1 516 546 4700",
    "sg:postcode":"11566",
    "sg:province":"NY",
    "wof:name":"Amex Pest Control Inc",
    "wof:placetype":"venue"
},
  "geometry": {"coordinates":[-73.562359,40.665639],"type":"Point"}
}