{
  "type": "Feature",
  "properties": {
    "addr:full":"67 E 3 St New York NY 10003",
    "addr:housenumber":"67;3",
    "addr:postcode":"10003",
    "addr:street":"E",
    "iso:country":"US",
    "sg:address":"67 E 3 St",
    "sg:city":"New York",
    "sg:classifiers":[
        {
            "category":"Professional",
            "type":"Services"
        }
    ],
    "sg:phone":"+1 212 505 3535",
    "sg:postcode":"10003",
    "sg:province":"NY",
    "sg:tags":[
        "establishment"
    ],
    "wof:name":"Barnaby Draper Studio",
    "wof:placetype":"venue"
},
  "geometry": {"coordinates":[-73.98823400000001,40.725077],"type":"Point"}
}