{
  "type": "Feature",
  "properties": {
    "iso:country":"US",
    "sg:address":"3689 Lockport Rd",
    "sg:city":"Oakfield",
    "sg:classifiers":[
        {
            "category":"Retail",
            "subcategory":"Repair Shop",
            "type":"Services"
        }
    ],
    "sg:phone":"+1 585 948 8022",
    "sg:postcode":"14125",
    "sg:province":"NY",
    "wof:name":"Fab Tech",
    "wof:placetype":"venue"
},
  "geometry": {"coordinates":[-78.243803,43.098295],"type":"Point"}
}