{
  "type": "Feature",
  "properties": {
    "addr:full":"7401 4th Avenue Brooklyn NY 11209",
    "addr:housenumber":"7401",
    "addr:postcode":"11209",
    "addr:street":"4Th Avenue",
    "iso:country":"US",
    "sg:address":"7401 4th Avenue",
    "sg:city":"Brooklyn",
    "sg:classifiers":[
        {
            "category":"Health Services",
            "subcategory":"Doctor",
            "type":"Services"
        },
        {
            "category":"Health Services",
            "subcategory":"Hospital",
            "type":"Services"
        }
    ],
    "sg:phone":"+1 718 238 7000",
    "sg:postcode":"11209",
    "sg:province":"NY",
    "wof:name":"Abiri Shahrokh MD",
    "wof:placetype":"venue"
},
  "geometry": {"coordinates":[-74.024767,40.631493],"type":"Point"}
}