{
  "type": "Feature",
  "properties": {
    "iso:country":"US",
    "sg:address":"36 Lexington Avenue",
    "sg:city":"New York",
    "sg:classifiers":[
        {
            "category":"Restaurant",
            "type":"Food & Drink"
        }
    ],
    "sg:phone":"+1 212 979 6871",
    "sg:postcode":"10010",
    "sg:province":"NY",
    "sg:tags":[
        "mexican",
        "tex-mex"
    ],
    "wof:name":"Fresco Tortilla - DUPLICATE",
    "wof:placetype":"venue"
},
  "geometry": {"coordinates":[-73.98442300000001,40.739933],"type":"Point"}
}