{
  "type": "Feature",
  "properties": {
    "iso:country":"US",
    "sg:address":"214 W 95th St",
    "sg:city":"New York",
    "sg:classifiers":[
        {
            "category":"Retail",
            "subcategory":"Auto Rental",
            "type":"Services"
        }
    ],
    "sg:phone":"+1 212 486 5914",
    "sg:postcode":"10025",
    "sg:province":"NY",
    "sg:tags":[
        "car"
    ],
    "sg:website":"www.hertz.com",
    "wof:name":"Hertz Rent-A-Car",
    "wof:placetype":"venue"
},
  "geometry": {"coordinates":[-73.971276,40.793403],"type":"Point"}
}