{
  "type": "Feature",
  "properties": {
    "iso:country":"US",
    "sg:address":"3000 Coney Island Ave",
    "sg:city":"Brooklyn",
    "sg:classifiers":[
        {
            "category":"Building & Trades",
            "subcategory":"Equipment Rental",
            "type":"Services"
        }
    ],
    "sg:phone":"+1 718 769 7804",
    "sg:postcode":"11235",
    "sg:province":"NY",
    "sg:tags":[
        "yard"
    ],
    "wof:name":"Partners Rental",
    "wof:placetype":"venue"
},
  "geometry": {"coordinates":[-73.959993,40.582634],"type":"Point"}
}