{
  "type": "Feature",
  "properties": {
    "iso:country":"US",
    "sg:address":"36 Cain Dr",
    "sg:city":"Plainview",
    "sg:classifiers":[
        {
            "category":"Shopping",
            "subcategory":"Discount & Variety Stores",
            "type":"Retail Goods"
        }
    ],
    "sg:phone":"+1 516 420 0572",
    "sg:postcode":"11803",
    "sg:province":"NY",
    "sg:tags":[
        "merchandise",
        "general"
    ],
    "wof:name":"OJC Sales",
    "wof:placetype":"venue"
},
  "geometry": {"coordinates":[-73.450897,40.785222],"type":"Point"}
}