{
  "type": "Feature",
  "properties": {
    "iso:country":"US",
    "sg:address":"10031 4th Ave",
    "sg:city":"Brooklyn",
    "sg:classifiers":[
        {
            "category":"Health Services",
            "subcategory":"Doctor",
            "type":"Services"
        }
    ],
    "sg:phone":"+1 718 488 8600",
    "sg:postcode":"11209",
    "sg:province":"NY",
    "sg:tags":[
        "physician",
        "surgeon"
    ],
    "wof:name":"Brooklyn Ob Gyn Assoc LLP",
    "wof:placetype":"venue"
},
  "geometry": {"coordinates":[-74.034257,40.612016],"type":"Point"}
}