{
  "type": "Feature",
  "properties": {
    "addr:full":"2801 State Hwy 67 Johnstown NY 12095",
    "addr:housenumber":"2801",
    "addr:postcode":"12095",
    "addr:street":"State Hwy 67",
    "iso:country":"US",
    "sg:address":"2801 State Hwy 67",
    "sg:city":"Johnstown",
    "sg:classifiers":[
        {
            "category":"Building & Trades",
            "subcategory":"Construction",
            "type":"Services"
        }
    ],
    "sg:phone":"+1 518 762 5803",
    "sg:postcode":"12095",
    "sg:province":"NY",
    "sg:tags":[
        "general",
        "contractor"
    ],
    "wof:name":"Turner Construction Co",
    "wof:placetype":"venue"
},
  "geometry": {"coordinates":[-74.31213,42.985459],"type":"Point"}
}