{
  "type": "Feature",
  "properties": {
    "addr:full":"1133 Broadway New York NY 10010",
    "addr:housenumber":"1133",
    "addr:postcode":"10010",
    "addr:street":"Broadway",
    "iso:country":"US",
    "sg:address":"1133 Broadway",
    "sg:city":"New York",
    "sg:classifiers":[
        {
            "category":"Manufacturing",
            "subcategory":"Glass & Minerals",
            "type":"Manufacturing & Wholesale Goods"
        },
        {
            "category":"Wholesale",
            "subcategory":"Electrical",
            "type":"Manufacturing & Wholesale Goods"
        }
    ],
    "sg:phone":"+1 212 675 7830",
    "sg:postcode":"10010",
    "sg:province":"NY",
    "sg:tags":[
        "decorative",
        "light",
        "imported",
        "reflector",
        "bulb"
    ],
    "wof:name":"Jerry Bloch Inc",
    "wof:placetype":"venue"
},
  "geometry": {"coordinates":[-73.989161,40.74327],"type":"Point"}
}