{
  "type": "Feature",
  "properties": {
    "iso:country":"US",
    "sg:address":"521 Vosburg Rd",
    "sg:city":"Webster",
    "sg:classifiers":[
        {
            "category":"Building & Trades",
            "subcategory":"Landscaping Services",
            "type":"Services"
        }
    ],
    "sg:phone":"+1 585 671 5006",
    "sg:postcode":"14580",
    "sg:province":"NY",
    "sg:tags":[
        "landscape"
    ],
    "wof:name":"Great Yards N Gardens",
    "wof:placetype":"venue"
},
  "geometry": {"coordinates":[-77.503533,43.242186],"type":"Point"}
}