{
  "type": "Feature",
  "properties": {
    "iso:country":"US",
    "sg:address":"30 E 60th St Ste 208",
    "sg:city":"New York",
    "sg:classifiers":[
        {
            "category":"Personal",
            "subcategory":"Day Spa",
            "type":"Services"
        }
    ],
    "sg:phone":"+1 212 260 9372",
    "sg:postcode":"10022",
    "sg:province":"NY",
    "sg:website":"www.mamiesskincare.com",
    "wof:name":"Mamie's Skin Care Center",
    "wof:placetype":"venue"
},
  "geometry": {"coordinates":[-73.97070100000001,40.764117],"type":"Point"}
}