{
  "type": "Feature",
  "properties": {
    "addr:full":"3507 Union Rd Cheektowaga NY 14225",
    "addr:housenumber":"3507",
    "addr:postcode":"14225",
    "addr:street":"Union Rd",
    "iso:country":"US",
    "sg:address":"3507 Union Rd",
    "sg:city":"Cheektowaga",
    "sg:classifiers":[
        {
            "category":"Health Services",
            "subcategory":"Doctor",
            "type":"Services"
        }
    ],
    "sg:phone":"+1 716 683 1881",
    "sg:postcode":"14225",
    "sg:province":"NY",
    "sg:tags":[
        "physician",
        "surgeon"
    ],
    "wof:name":"Anthony M De Perio MD",
    "wof:placetype":"venue"
},
  "geometry": {"coordinates":[-78.754232,42.908245],"type":"Point"}
}