{
  "type": "Feature",
  "properties": {
    "iso:country":"US",
    "sg:address":"326 Walt Whitman Rd Unit F",
    "sg:city":"Huntington Station",
    "sg:classifiers":[
        {
            "category":"Retail",
            "subcategory":"Portrait Studio",
            "type":"Services"
        }
    ],
    "sg:phone":"+1 631 425 2900",
    "sg:postcode":"11746",
    "sg:province":"NY",
    "sg:tags":[
        "photography",
        "store"
    ],
    "sg:website":"www.clixlongisland.com",
    "wof:name":"Clix Portrait Studios",
    "wof:placetype":"venue"
},
  "geometry": {"coordinates":[-73.412266,40.824822],"type":"Point"}
}