{
  "type": "Feature",
  "properties": {
    "addr:full":"417 Laurens St Olean NY 14760",
    "addr:housenumber":"417",
    "addr:postcode":"14760",
    "addr:street":"Laurens St",
    "iso:country":"US",
    "sg:address":"417 Laurens St",
    "sg:city":"Olean",
    "sg:classifiers":[
        {
            "category":"Organizations",
            "subcategory":"Religious Organization",
            "type":"Services"
        }
    ],
    "sg:phone":"+1 716 372 0650",
    "sg:postcode":"14760",
    "sg:province":"NY",
    "sg:tags":[
        "child",
        "care",
        "day",
        "churches-lutheran",
        "church"
    ],
    "sg:website":"www.ilclcms.org",
    "wof:name":"Immanuel Lutheran Church",
    "wof:placetype":"venue"
},
  "geometry": {"coordinates":[-78.434118,42.079447],"type":"Point"}
}