{
  "type": "Feature",
  "properties": {
    "iso:country":"US",
    "sg:address":"3980 Cedarvale Rd",
    "sg:city":"Syracuse",
    "sg:classifiers":[
        {
            "category":"Building & Trades",
            "subcategory":"Construction",
            "type":"Services"
        }
    ],
    "sg:phone":"+1 315 492 4574",
    "sg:postcode":"13215",
    "sg:province":"NY",
    "sg:tags":[
        "house"
    ],
    "wof:name":"RE Brunelle Builder",
    "wof:placetype":"venue"
},
  "geometry": {"coordinates":[-76.243522,42.964616],"type":"Point"}
}