{
  "type": "Feature",
  "properties": {
    "addr:full":"1504 Old Country Rd Ste 216 Westbury NY 11590",
    "addr:housenumber":"1504",
    "addr:postcode":"11590",
    "addr:street":"Old Country Rd Ste 216",
    "iso:country":"US",
    "sg:address":"1504 Old Country Rd Ste 216",
    "sg:city":"Westbury",
    "sg:classifiers":[
        {
            "category":"Restaurant",
            "type":"Food & Drink"
        }
    ],
    "sg:phone":"+1 516 222 9200",
    "sg:postcode":"11590",
    "sg:province":"NY",
    "sg:tags":[
        "chinese"
    ],
    "sg:website":"www.pfchangs.com",
    "wof:name":"P F Chang's China Bistro Inc",
    "wof:placetype":"venue"
},
  "geometry": {"coordinates":[-73.55740400000001,40.7551],"type":"Point"}
}