{
  "type": "Feature",
  "properties": {
    "iso:country":"US",
    "sg:address":"1577 Westchester Ave",
    "sg:city":"Bronx",
    "sg:classifiers":[
        {
            "category":"Home & Garden",
            "subcategory":"Hardware",
            "type":"Retail Goods"
        }
    ],
    "sg:phone":"+1   ",
    "sg:postcode":"10472",
    "sg:province":"NY",
    "wof:name":"Westchester Hardware Supply",
    "wof:placetype":"venue"
},
  "geometry": {"coordinates":[-73.87703,40.828839],"type":"Point"}
}