{
  "type": "Feature",
  "properties": {
    "addr:full":"9 Fairview Ave Hudson NY 12534",
    "addr:housenumber":"9",
    "addr:postcode":"12534",
    "addr:street":"Fairview Ave",
    "iso:country":"US",
    "sg:address":"9 Fairview Ave",
    "sg:city":"Hudson",
    "sg:classifiers":[
        {
            "category":"Autos & Motor Vehicles",
            "subcategory":"Fuel & Gas Station",
            "type":"Retail Goods"
        }
    ],
    "sg:phone":"+1   ",
    "sg:postcode":"12534",
    "sg:province":"NY",
    "sg:tags":[
        "station",
        "gasoline"
    ],
    "wof:name":"Hess",
    "wof:placetype":"venue"
},
  "geometry": {"coordinates":[-73.773779,42.246682],"type":"Point"}
}