{
  "type": "Feature",
  "properties": {
    "iso:country":"US",
    "sg:address":"400 Atlantic Ave",
    "sg:city":"East Rockaway",
    "sg:classifiers":[
        {
            "category":"Health Services",
            "subcategory":"Doctor",
            "type":"Services"
        }
    ],
    "sg:phone":"+1 516 599 2732",
    "sg:postcode":"11518",
    "sg:province":"NY",
    "wof:name":"Dr John R Gavencak",
    "wof:placetype":"venue"
},
  "geometry": {"coordinates":[-73.664902,40.6474],"type":"Point"}
}