{
  "type": "Feature",
  "properties": {
    "addr:full":"123 Katonah Ave Katonah NY 10536",
    "addr:housenumber":"123",
    "addr:postcode":"10536",
    "addr:street":"Katonah Ave",
    "iso:country":"US",
    "sg:address":"123 Katonah Ave",
    "sg:city":"Katonah",
    "sg:classifiers":[
        {
            "category":"Restaurant",
            "type":"Food & Drink"
        }
    ],
    "sg:phone":"+1 914 232 3493",
    "sg:postcode":"10536",
    "sg:province":"NY",
    "sg:tags":[
        "delicatessen"
    ],
    "wof:name":"Wooden Nickel Deli",
    "wof:placetype":"venue"
},
  "geometry": {"coordinates":[-73.684044,41.257668],"type":"Point"}
}