{
  "type": "Feature",
  "properties": {
    "iso:country":"US",
    "sg:address":"1775 Grand Concourse",
    "sg:city":"Bronx",
    "sg:classifiers":[
        {
            "category":"Government",
            "subcategory":"Office",
            "type":"Public Place"
        }
    ],
    "sg:phone":"+1 718 716 0300",
    "sg:postcode":"10453",
    "sg:province":"NY",
    "sg:tags":[
        "village"
    ],
    "wof:name":"Field Offices",
    "wof:placetype":"venue"
},
  "geometry": {"coordinates":[-73.905805,40.849733],"type":"Point"}
}