{
  "type": "Feature",
  "properties": {
    "addr:full":"7212 18th Ave Brooklyn NY 11204",
    "addr:housenumber":"7212",
    "addr:postcode":"11204",
    "addr:street":"18Th Ave",
    "iso:country":"US",
    "sg:address":"7212 18th Ave",
    "sg:city":"Brooklyn",
    "sg:classifiers":[
        {
            "category":"Manufacturing",
            "subcategory":"Printing",
            "type":"Manufacturing & Wholesale Goods"
        }
    ],
    "sg:phone":"+1   ",
    "sg:postcode":"11204",
    "sg:province":"NY",
    "sg:tags":[
        "publishing"
    ],
    "wof:name":"Move Smart Publishing",
    "wof:placetype":"venue"
},
  "geometry": {"coordinates":[-73.99480200000001,40.614677],"type":"Point"}
}