{
  "type": "Feature",
  "properties": {
    "addr:full":"73 W Main St Babylon NY 11702",
    "addr:housenumber":"73",
    "addr:postcode":"11702",
    "addr:street":"W Main St",
    "iso:country":"US",
    "sg:address":"73 W Main St",
    "sg:city":"Babylon",
    "sg:classifiers":[
        {
            "category":"Professional",
            "subcategory":"Lawyer & Legal Services",
            "type":"Services"
        }
    ],
    "sg:phone":"+1 631 661 8631",
    "sg:postcode":"11702",
    "sg:province":"NY",
    "wof:name":"Patrick K Brsnahan Jr Law Offs",
    "wof:placetype":"venue"
},
  "geometry": {"coordinates":[-73.32449099999999,40.696307],"type":"Point"}
}