{
  "type": "Feature",
  "properties": {
    "addr:full":"80 Parkhurst Rd Gansevoort NY 12831",
    "addr:housenumber":"80",
    "addr:postcode":"12831",
    "addr:street":"Parkhurst Rd",
    "iso:country":"US",
    "sg:address":"80 Parkhurst Rd",
    "sg:city":"Gansevoort",
    "sg:classifiers":[
        {
            "category":"Local Transit",
            "type":"Transportation"
        }
    ],
    "sg:phone":"+1 518 581 9734",
    "sg:postcode":"12831",
    "sg:province":"NY",
    "sg:tags":[
        "passenger"
    ],
    "wof:name":"Dave's Transport Svc",
    "wof:placetype":"venue"
},
  "geometry": {"coordinates":[-73.761431,43.170285],"type":"Point"}
}