{
  "type": "Feature",
  "properties": {
    "addr:full":"43 Barkwood Ln Spencerport NY 14559",
    "addr:housenumber":"43",
    "addr:postcode":"14559",
    "addr:street":"Barkwood Ln",
    "iso:country":"US",
    "sg:address":"43 Barkwood Ln",
    "sg:city":"Spencerport",
    "sg:classifiers":[
        {
            "category":"Shopping",
            "subcategory":"Discount & Variety Stores",
            "type":"Retail Goods"
        }
    ],
    "sg:phone":"+1 585 349 1266",
    "sg:postcode":"14559",
    "sg:province":"NY",
    "wof:name":"Melissa's World Variety",
    "wof:placetype":"venue"
},
  "geometry": {"coordinates":[-77.811442,43.180239],"type":"Point"}
}