{
  "type": "Feature",
  "properties": {
    "addr:full":"14 Great Neck Rd Great Neck NY 11021",
    "addr:housenumber":"14",
    "addr:postcode":"11021",
    "addr:street":"Great Neck Rd",
    "iso:country":"US",
    "sg:address":"14 Great Neck Rd",
    "sg:city":"Great Neck",
    "sg:classifiers":[
        {
            "category":"Restaurant",
            "type":"Food & Drink"
        }
    ],
    "sg:menulink":"http://www.allmenus.com/ny/great-neck/37162-yogurteria/menu/",
    "sg:phone":"+1 516 829 7474",
    "sg:postcode":"11021",
    "sg:province":"NY",
    "sg:tags":[
        "american"
    ],
    "wof:name":"Yogurteria",
    "wof:placetype":"venue"
},
  "geometry": {"coordinates":[-73.727115,40.786436],"type":"Point"}
}