{
  "type": "Feature",
  "properties": {
    "iso:country":"US",
    "sg:address":"1625 Brentwood Rd",
    "sg:city":"Brentwood",
    "sg:classifiers":[
        {
            "category":"Place Of Worship",
            "subcategory":"Church",
            "type":"Public Place"
        },
        {
            "category":"Place Of Worship",
            "type":"Public Place"
        }
    ],
    "sg:phone":"+1 631 273 1101",
    "sg:postcode":"11717",
    "sg:province":"NY",
    "sg:tags":[
        "churches-interdenominational",
        "churches-various",
        "denomination"
    ],
    "wof:name":"Brentwood Congrg Of Jehovahs",
    "wof:placetype":"venue"
},
  "geometry": {"coordinates":[-73.24619300000001,40.768614],"type":"Point"}
}