{
  "type": "Feature",
  "properties": {
    "addr:full":"31 Hampton Rd Southampton NY 11968",
    "addr:housenumber":"31",
    "addr:postcode":"11968",
    "addr:street":"Hampton Rd",
    "iso:country":"US",
    "sg:address":"31 Hampton Rd",
    "sg:city":"Southampton",
    "sg:classifiers":[
        {
            "category":"Home & Garden",
            "subcategory":"Building Materials",
            "type":"Retail Goods"
        }
    ],
    "sg:phone":"+1 631 283 6116",
    "sg:postcode":"11968",
    "sg:province":"NY",
    "sg:tags":[
        "paint"
    ],
    "wof:name":"Aboff's Paint & Wallcovering",
    "wof:placetype":"venue"
},
  "geometry": {"coordinates":[-72.388912,40.887337],"type":"Point"}
}