{
  "type": "Feature",
  "properties": {
    "iso:country":"US",
    "sg:address":"465 S Oyster Bay Rd",
    "sg:city":"Plainview",
    "sg:classifiers":[
        {
            "category":"Real Estate",
            "subcategory":"Real Estate Agent",
            "type":"Services"
        }
    ],
    "sg:phone":"+1 516 822 1300",
    "sg:postcode":"11803",
    "sg:province":"NY",
    "wof:name":"Alpha Realty Corp",
    "wof:placetype":"venue"
},
  "geometry": {"coordinates":[-73.502426,40.778391],"type":"Point"}
}