{
  "type": "Feature",
  "properties": {
    "addr:full":"23 E Broadway New York NY 10002",
    "addr:housenumber":"23",
    "addr:postcode":"10002",
    "addr:street":"E Broadway",
    "iso:country":"US",
    "sg:address":"23 E Broadway",
    "sg:city":"New York",
    "sg:classifiers":[
        {
            "category":"Food & Beverages",
            "subcategory":"Specialty",
            "type":"Retail Goods"
        }
    ],
    "sg:phone":"+1 212 962 6633",
    "sg:postcode":"10002",
    "sg:province":"NY",
    "sg:tags":[
        "herb"
    ],
    "wof:name":"Masterpiece USA Inc",
    "wof:placetype":"venue"
},
  "geometry": {"coordinates":[-73.99479700000001,40.713592],"type":"Point"}
}