{
  "type": "Feature",
  "properties": {
    "addr:full":"5023 Clinton Rd Whitesboro NY 13492",
    "addr:housenumber":"5023",
    "addr:postcode":"13492",
    "addr:street":"Clinton Rd",
    "iso:country":"US",
    "sg:address":"5023 Clinton Rd",
    "sg:city":"Whitesboro",
    "sg:classifiers":[
        {
            "category":"Shopping",
            "subcategory":"Gifts & Souvenirs",
            "type":"Retail Goods"
        }
    ],
    "sg:phone":"+1 315 736 1616",
    "sg:postcode":"13492",
    "sg:province":"NY",
    "sg:tags":[
        "basket"
    ],
    "wof:name":"Cottage Gate",
    "wof:placetype":"venue"
},
  "geometry": {"coordinates":[-75.317234,43.104373],"type":"Point"}
}