{
  "type": "Feature",
  "properties": {
    "iso:country":"US",
    "sg:address":"1276 Fulton St",
    "sg:city":"Brooklyn",
    "sg:classifiers":[
        {
            "category":"Food & Beverages",
            "subcategory":"Specialty",
            "type":"Retail Goods"
        }
    ],
    "sg:phone":"+1   ",
    "sg:postcode":"11216",
    "sg:province":"NY",
    "wof:name":"Fresh Health Food Emporium",
    "wof:placetype":"venue"
},
  "geometry": {"coordinates":[-73.950723,40.6804],"type":"Point"}
}