{
  "type": "Feature",
  "properties": {
    "addr:full":"34 Spinnaker Ct Patchogue NY 11772",
    "addr:housenumber":"34",
    "addr:postcode":"11772",
    "addr:street":"Spinnaker Ct",
    "iso:country":"US",
    "sg:address":"34 Spinnaker Ct",
    "sg:city":"Patchogue",
    "sg:classifiers":[
        {
            "category":"Professional",
            "subcategory":"Computer Services",
            "type":"Services"
        }
    ],
    "sg:phone":"+1 631 654 5478",
    "sg:postcode":"11772",
    "sg:province":"NY",
    "sg:tags":[
        "consultant"
    ],
    "wof:name":"Integrated Data Services Inc",
    "wof:placetype":"venue"
},
  "geometry": {"coordinates":[-72.98218199999999,40.750396],"type":"Point"}
}