{
  "type": "Feature",
  "properties": {
    "iso:country":"US",
    "sg:address":"3699 W Henrietta Rd",
    "sg:city":"Rochester",
    "sg:classifiers":[
        {
            "category":"Personal",
            "subcategory":"Tanning Parlor",
            "type":"Services"
        }
    ],
    "sg:phone":"+1 585 334 2370",
    "sg:postcode":"14623",
    "sg:province":"NY",
    "sg:tags":[
        "salon"
    ],
    "wof:name":"Exquisite Touch",
    "wof:placetype":"venue"
},
  "geometry": {"coordinates":[-77.63997500000001,43.081582],"type":"Point"}
}