{
  "type": "Feature",
  "properties": {
    "iso:country":"US",
    "sg:address":"1 Watkins Ter",
    "sg:city":"Amityville",
    "sg:classifiers":[
        {
            "category":"Professional",
            "type":"Services"
        }
    ],
    "sg:phone":"+1 516 921 4906",
    "sg:postcode":"11701",
    "sg:province":"NY",
    "wof:name":"Pat's Cesspool Svc",
    "wof:placetype":"venue"
},
  "geometry": {"coordinates":[-73.40448000000001,40.714569],"type":"Point"}
}