{
  "type": "Feature",
  "properties": {
    "addr:full":"4601 1st Ave Brooklyn NY 11232",
    "addr:housenumber":"4601",
    "addr:postcode":"11232",
    "addr:street":"1St Ave",
    "iso:country":"US",
    "sg:address":"4601 1st Ave",
    "sg:city":"Brooklyn",
    "sg:classifiers":[
        {
            "category":"Wholesale",
            "subcategory":"Painting Supplies",
            "type":"Manufacturing & Wholesale Goods"
        }
    ],
    "sg:phone":"+1 718 439 8513",
    "sg:postcode":"11232",
    "sg:province":"NY",
    "sg:tags":[
        "paint"
    ],
    "wof:name":"Kalmen Reiss",
    "wof:placetype":"venue"
},
  "geometry": {"coordinates":[-74.016431,40.653184],"type":"Point"}
}