{
  "type": "Feature",
  "properties": {
    "iso:country":"US",
    "sg:address":"669 Central Ave",
    "sg:city":"Cedarhurst",
    "sg:classifiers":[
        {
            "category":"Personal",
            "subcategory":"Nail Salon",
            "type":"Services"
        }
    ],
    "sg:phone":"+1 516 374 7004",
    "sg:postcode":"11516",
    "sg:province":"NY",
    "wof:name":"Q's Corner Nail Salon",
    "wof:placetype":"venue"
},
  "geometry": {"coordinates":[-73.720398,40.624298],"type":"Point"}
}