{
  "type": "Feature",
  "properties": {
    "iso:country":"US",
    "sg:address":"78 Mount Vernon Ave",
    "sg:city":"Patchogue",
    "sg:classifiers":[
        {
            "category":"Real Estate",
            "subcategory":"Real Estate Operator",
            "type":"Services"
        }
    ],
    "sg:phone":"+1 631 475 1667",
    "sg:postcode":"11772",
    "sg:province":"NY",
    "sg:tags":[
        "apartment"
    ],
    "wof:name":"Fairfield N Patchogue LLC",
    "wof:placetype":"venue"
},
  "geometry": {"coordinates":[-73.821923,40.790091],"type":"Point"}
}