{
  "type": "Feature",
  "properties": {
    "iso:country":"US",
    "sg:address":"406 S Franklin St",
    "sg:city":"Syracuse",
    "sg:classifiers":[
        {
            "category":"Food & Beverages",
            "subcategory":"Bakery",
            "type":"Retail Goods"
        }
    ],
    "sg:phone":"+1   ",
    "sg:postcode":"13202",
    "sg:province":"NY",
    "wof:name":"Dewitt Bagelry Cafe",
    "wof:placetype":"venue"
},
  "geometry": {"coordinates":[-76.155607,43.047524],"type":"Point"}
}