{
  "type": "Feature",
  "properties": {
    "addr:full":"Stotzky Memorial Park Columbus Avenue & Pulaski St. Riverhead NY 11901",
    "addr:postcode":"11901",
    "addr:street":"Columbus Avenue & Pulaski St.",
    "iso:country":"US",
    "sg:address":"Stotzky Memorial Park Columbus Avenue & Pulaski St.",
    "sg:city":"Riverhead",
    "sg:classifiers":[
        {
            "category":"Recreation",
            "type":"Entertainment"
        }
    ],
    "sg:phone":"+1 631 208 3826",
    "sg:postcode":"11901",
    "sg:province":"NY",
    "sg:tags":[
        "active",
        "life"
    ],
    "sg:website":"www.riverheadli.com/skatepark.html",
    "wof:name":"Riverhead Skate Park",
    "wof:placetype":"venue"
},
  "geometry": {"coordinates":[-72.68010099999999,40.919271],"type":"Point"}
}