{
  "type": "Feature",
  "properties": {
    "addr:full":"404 Country Club Ln Pomona NY 10970",
    "addr:housenumber":"404",
    "addr:postcode":"10970",
    "addr:street":"Country Club Ln",
    "iso:country":"US",
    "sg:address":"404 Country Club Ln",
    "sg:city":"Pomona",
    "sg:classifiers":[
        {
            "category":"Professional",
            "subcategory":"Computer Services",
            "type":"Services"
        }
    ],
    "sg:phone":"+1 845 354 8953",
    "sg:postcode":"10970",
    "sg:province":"NY",
    "sg:tags":[
        "related"
    ],
    "wof:name":"Decisionone",
    "wof:placetype":"venue"
},
  "geometry": {"coordinates":[-74.030394,41.191376],"type":"Point"}
}