{
  "type": "Feature",
  "properties": {
    "addr:full":"30-00 47th Avenue Long Island City NY NY IIIOI.",
    "addr:housenumber":"30-00",
    "addr:street":"47Th Avenue",
    "iso:country":"US",
    "sg:address":"30-00 47th Avenue",
    "sg:city":"Long Island City",
    "sg:classifiers":[
        {
            "category":"Professional",
            "subcategory":"Computer Services",
            "type":"Services"
        }
    ],
    "sg:phone":"+1 207257854",
    "sg:postcode":"NY IIIOI.",
    "sg:province":"NY",
    "sg:tags":[
        "officialvirtualdj",
        "official-virtual-dj",
        "officialvirtualdjmusic",
        "dj-armz"
    ],
    "sg:website":"http://www.officialvirtualdj.com",
    "wof:name":"Official Limited Virtual",
    "wof:placetype":"venue"
},
  "geometry": {"coordinates":[-73.93450199999999,40.744622],"type":"Point"}
}