{
  "type": "Feature",
  "properties": {
    "addr:full":"4777 Austin Rd Elbridge NY 13060",
    "addr:housenumber":"4777",
    "addr:postcode":"13060",
    "addr:street":"Austin Rd",
    "iso:country":"US",
    "sg:address":"4777 Austin Rd",
    "sg:city":"Elbridge",
    "sg:classifiers":[
        {
            "category":"Retail",
            "subcategory":"Photofinishing",
            "type":"Services"
        }
    ],
    "sg:phone":"+1 315 685 2703",
    "sg:postcode":"13060",
    "sg:province":"NY",
    "sg:tags":[
        "photo",
        "finishing"
    ],
    "wof:name":"Vedder Enterprises",
    "wof:placetype":"venue"
},
  "geometry": {"coordinates":[-76.42548600000001,43.002829],"type":"Point"}
}