{
  "type": "Feature",
  "properties": {
    "addr:full":"128 MacDougal Street New York NY 10012",
    "addr:housenumber":"128",
    "addr:postcode":"10012",
    "addr:street":"Macdougal Street",
    "iso:country":"US",
    "sg:address":"128 MacDougal Street",
    "sg:city":"New York",
    "sg:classifiers":[
        {
            "category":"Bars & Pubs",
            "subcategory":"Hookah Bar",
            "type":"Food & Drink"
        }
    ],
    "sg:phone":"+1 212 979 1004",
    "sg:postcode":"10012",
    "sg:province":"NY",
    "wof:name":"Luxor Cafe",
    "wof:placetype":"venue"
},
  "geometry": {"coordinates":[-74.000122,40.730152],"type":"Point"}
}