{
  "type": "Feature",
  "properties": {
    "addr:full":"701 Dingens St Buffalo NY 14206",
    "addr:housenumber":"701",
    "addr:postcode":"14206",
    "addr:street":"Dingens St",
    "iso:country":"US",
    "sg:address":"701 Dingens St",
    "sg:city":"Buffalo",
    "sg:classifiers":[
        {
            "category":"Recreation",
            "type":"Entertainment"
        }
    ],
    "sg:phone":"+1 716 896 0002",
    "sg:postcode":"14206",
    "sg:province":"NY",
    "sg:tags":[
        "pool",
        "swimming"
    ],
    "wof:name":"Dingens St Swimming Pool",
    "wof:placetype":"venue"
},
  "geometry": {"coordinates":[-78.788549,42.87743],"type":"Point"}
}