{
  "type": "Feature",
  "properties": {
    "addr:full":"59 W Burnside Ave Bronx NY 10453",
    "addr:housenumber":"59",
    "addr:postcode":"10453",
    "addr:street":"W Burnside Ave",
    "iso:country":"US",
    "sg:address":"59 W Burnside Ave",
    "sg:city":"Bronx",
    "sg:classifiers":[
        {
            "category":"Deli",
            "type":"Food & Drink"
        },
        {
            "category":"Food & Beverages",
            "subcategory":"Bakery",
            "type":"Retail Goods"
        }
    ],
    "sg:phone":"+1 718 731 5922",
    "sg:postcode":"10453",
    "sg:province":"NY",
    "sg:tags":[
        "sandwich"
    ],
    "wof:name":"Pop's Caribbean Deli",
    "wof:placetype":"venue"
},
  "geometry": {"coordinates":[-73.90974,40.854166],"type":"Point"}
}