{
  "type": "Feature",
  "properties": {
    "iso:country":"US",
    "sg:address":"175 Great Neck Rd",
    "sg:city":"Great Neck",
    "sg:classifiers":[
        {
            "category":"Professional",
            "type":"Services"
        }
    ],
    "sg:phone":"+1 516 466 5525",
    "sg:postcode":"11021",
    "sg:province":"NY",
    "sg:tags":[
        "establishment"
    ],
    "wof:name":"Call-Putter Co",
    "wof:placetype":"venue"
},
  "geometry": {"coordinates":[-73.732079,40.781954],"type":"Point"}
}