{
  "type": "Feature",
  "properties": {
    "iso:country":"US",
    "sg:address":"200 Central Park S",
    "sg:city":"New York",
    "sg:classifiers":[
        {
            "category":"Health Services",
            "subcategory":"Doctor",
            "type":"Services"
        }
    ],
    "sg:phone":"+1 212 246 0800",
    "sg:postcode":"10019",
    "sg:province":"NY",
    "wof:name":"Hiv Testing Assoc",
    "wof:placetype":"venue"
},
  "geometry": {"coordinates":[-73.97910299999999,40.766899],"type":"Point"}
}