{
  "type": "Feature",
  "properties": {
    "iso:country":"US",
    "sg:address":"81 Buell St",
    "sg:city":"Akron",
    "sg:classifiers":[
        {
            "category":"Restaurant",
            "type":"Food & Drink"
        }
    ],
    "sg:phone":"+1 716 542 4155",
    "sg:postcode":"14001",
    "sg:province":"NY",
    "sg:tags":[
        "eating"
    ],
    "wof:name":"Candy Apple Cafe Inc",
    "wof:placetype":"venue"
},
  "geometry": {"coordinates":[-78.502983,43.014923],"type":"Point"}
}