{
  "type": "Feature",
  "properties": {
    "iso:country":"US",
    "sg:address":"8122 E Genesee St",
    "sg:city":"Fayetteville",
    "sg:classifiers":[
        {
            "category":"Shopping",
            "subcategory":"Pets & Pet Supplies",
            "type":"Retail Goods"
        },
        {
            "category":"Retail",
            "subcategory":"Pet Boarding",
            "type":"Services"
        },
        {
            "category":"Retail",
            "subcategory":"Animal Services",
            "type":"Services"
        }
    ],
    "sg:phone":"+1 315 637 1775",
    "sg:postcode":"13066",
    "sg:province":"NY",
    "sg:tags":[
        "grooming",
        "kennel",
        "exercising",
        "specialty",
        "sitting"
    ],
    "sg:website":"http://www.villagegroomer.com",
    "wof:name":"A Village Groomer",
    "wof:placetype":"venue"
},
  "geometry": {"coordinates":[-75.96549400000001,43.03941],"type":"Point"}
}