{
  "type": "Feature",
  "properties": {
    "iso:country":"US",
    "sg:address":"3135 Coney Island Ave",
    "sg:city":"Brooklyn",
    "sg:classifiers":[
        {
            "category":"Professional",
            "type":"Services"
        }
    ],
    "sg:phone":"+1 718 332 1231",
    "sg:postcode":"11235",
    "sg:province":"NY",
    "sg:tags":[
        "establishment"
    ],
    "wof:name":"Iadc Inc",
    "wof:placetype":"venue"
},
  "geometry": {"coordinates":[-73.959703,40.57992],"type":"Point"}
}