{
  "type": "Feature",
  "properties": {
    "iso:country":"US",
    "sg:address":"936 N Broadway",
    "sg:city":"Massapequa",
    "sg:classifiers":[
        {
            "category":"Food & Beverages",
            "subcategory":"Meat & Fish",
            "type":"Retail Goods"
        }
    ],
    "sg:phone":"+1 516 541 6688",
    "sg:postcode":"11758",
    "sg:province":"NY",
    "wof:name":"Francesco's Meat Market",
    "wof:placetype":"venue"
},
  "geometry": {"coordinates":[-73.46208799999999,40.702434],"type":"Point"}
}