{
  "type": "Feature",
  "properties": {
    "addr:full":"172 Neilsen Rd Cherry Valley NY 13320",
    "addr:housenumber":"172",
    "addr:postcode":"13320",
    "addr:street":"Neilsen Rd",
    "iso:country":"US",
    "sg:address":"172 Neilsen Rd",
    "sg:city":"Cherry Valley",
    "sg:phone":"+1 607 264 3000",
    "sg:postcode":"13320",
    "sg:province":"NY",
    "sg:tags":[
        "farm",
        "corn",
        "crop",
        "harvesting"
    ],
    "wof:name":"Brian Ethington",
    "wof:placetype":"venue"
},
  "geometry": {"coordinates":[-74.765697,42.815986],"type":"Point"}
}