{
  "type": "Feature",
  "properties": {
    "addr:full":"207 Wickham Ave Middletown NY 10940",
    "addr:housenumber":"207",
    "addr:postcode":"10940",
    "addr:street":"Wickham Ave",
    "iso:country":"US",
    "sg:address":"207 Wickham Ave",
    "sg:city":"Middletown",
    "sg:classifiers":[
        {
            "category":"Home & Garden",
            "subcategory":"Furniture",
            "type":"Retail Goods"
        }
    ],
    "sg:phone":"+1 845 342 1880",
    "sg:postcode":"10940",
    "sg:province":"NY",
    "sg:tags":[
        "household"
    ],
    "sg:website":"www.goldenarea.com",
    "wof:name":"Golden Area Furniture LLC",
    "wof:placetype":"venue"
},
  "geometry": {"coordinates":[-74.40595500000001,41.453082],"type":"Point"}
}