{
  "type": "Feature",
  "properties": {
    "addr:full":"4 Sweetgrass Rd Westhampton NY 11977",
    "addr:housenumber":"4",
    "addr:postcode":"11977",
    "addr:street":"Sweetgrass Rd",
    "iso:country":"US",
    "sg:address":"4 Sweetgrass Rd",
    "sg:city":"Westhampton",
    "sg:classifiers":[
        {
            "category":"Building & Trades",
            "subcategory":"Landscaping Services",
            "type":"Services"
        }
    ],
    "sg:phone":"+1 631 288 0686",
    "sg:postcode":"11977",
    "sg:province":"NY",
    "sg:tags":[
        "lawn",
        "maintenance",
        "grounds"
    ],
    "wof:name":"Complete Management Inc",
    "wof:placetype":"venue"
},
  "geometry": {"coordinates":[-72.682934,40.810602],"type":"Point"}
}