{
  "type": "Feature",
  "properties": {
    "addr:full":"38115 State Hwy 12E Clayton NY 13624",
    "addr:housenumber":"38115",
    "addr:postcode":"13624",
    "addr:street":"State Hwy 12E",
    "iso:country":"US",
    "sg:address":"38115 State Hwy 12E",
    "sg:city":"Clayton",
    "sg:classifiers":[
        {
            "category":"Travel",
            "subcategory":"Campground",
            "type":"Entertainment"
        }
    ],
    "sg:phone":"+1   ",
    "sg:postcode":"13624",
    "sg:province":"NY",
    "sg:tags":[
        "operation",
        "trailer"
    ],
    "wof:name":"Merry Knoll Campground",
    "wof:placetype":"venue"
},
  "geometry": {"coordinates":[-76.126296,44.220303],"type":"Point"}
}