{
  "type": "Feature",
  "properties": {
    "addr:full":"601 Old Willets Path Hauppauge NY 11788",
    "addr:housenumber":"601",
    "addr:postcode":"11788",
    "addr:street":"Old Willets Path",
    "iso:country":"US",
    "sg:address":"601 Old Willets Path",
    "sg:city":"Hauppauge",
    "sg:classifiers":[
        {
            "category":"Manufacturing",
            "subcategory":"Metals",
            "type":"Manufacturing & Wholesale Goods"
        }
    ],
    "sg:phone":"+1 631 348 4800",
    "sg:postcode":"11788",
    "sg:province":"NY",
    "sg:tags":[
        "shop",
        "plate",
        "work",
        "fabricated"
    ],
    "sg:website":"www.kamthermal.com",
    "wof:name":"Kam Thermal Equipment LTD",
    "wof:placetype":"venue"
},
  "geometry": {"coordinates":[-73.233904,40.81032],"type":"Point"}
}