{
  "type": "Feature",
  "properties": {
    "addr:full":"1270 North Ave New Rochelle NY 10804",
    "addr:housenumber":"1270",
    "addr:postcode":"10804",
    "addr:street":"North Ave",
    "iso:country":"US",
    "sg:address":"1270 North Ave",
    "sg:city":"New Rochelle",
    "sg:classifiers":[
        {
            "category":"Taxi",
            "type":"Transportation"
        }
    ],
    "sg:phone":"+1 914 725 3124",
    "sg:postcode":"10804",
    "sg:province":"NY",
    "sg:tags":[
        "taxicab"
    ],
    "wof:name":"Dependable Car Svc",
    "wof:placetype":"venue"
},
  "geometry": {"coordinates":[-73.795491,40.945919],"type":"Point"}
}