{
  "type": "Feature",
  "properties": {
    "addr:full":"1360 Pleasantville Rd Briarcliff Manor NY 10510",
    "addr:housenumber":"1360",
    "addr:postcode":"10510",
    "addr:street":"Pleasantville Rd",
    "iso:country":"US",
    "sg:address":"1360 Pleasantville Rd",
    "sg:city":"Briarcliff Manor",
    "sg:classifiers":[
        {
            "category":"Organizations",
            "subcategory":"Labor Organization",
            "type":"Services"
        }
    ],
    "sg:phone":"+1 914 762 0600",
    "sg:postcode":"10510",
    "sg:province":"NY",
    "wof:name":"Ivoe Local 137 Pension-Welfare",
    "wof:placetype":"venue"
},
  "geometry": {"coordinates":[-73.83175199999999,41.151909],"type":"Point"}
}