{
  "type": "Feature",
  "properties": {
    "iso:country":"US",
    "sg:address":"6351 Waterburg Rd",
    "sg:city":"Trumansburg",
    "sg:classifiers":[
        {
            "category":"Government",
            "subcategory":"Office",
            "type":"Public Place"
        }
    ],
    "sg:phone":"+1 607 387 5327",
    "sg:postcode":"14886",
    "sg:province":"NY",
    "sg:tags":[
        "state"
    ],
    "wof:name":"Environmental Conservation Ofc",
    "wof:placetype":"venue"
},
  "geometry": {"coordinates":[-76.66730800000001,42.519963],"type":"Point"}
}