{
  "type": "Feature",
  "properties": {
    "addr:full":"38 Martin Rd Hopewell Junction NY 12533",
    "addr:housenumber":"38",
    "addr:postcode":"12533",
    "addr:street":"Martin Rd",
    "iso:country":"US",
    "sg:address":"38 Martin Rd",
    "sg:city":"Hopewell Junction",
    "sg:classifiers":[
        {
            "category":"Real Estate",
            "subcategory":"Real Estate Services",
            "type":"Services"
        }
    ],
    "sg:phone":"+1 845 226 2391",
    "sg:postcode":"12533",
    "sg:province":"NY",
    "sg:tags":[
        "abstract",
        "title"
    ],
    "wof:name":"Transaction Title Agency Inc",
    "wof:placetype":"venue"
},
  "geometry": {"coordinates":[-73.72868,41.623982],"type":"Point"}
}