{
  "type": "Feature",
  "properties": {
    "iso:country":"US",
    "sg:address":"20 Barker Ave",
    "sg:city":"White Plains",
    "sg:classifiers":[
        {
            "category":"Personal",
            "type":"Services"
        }
    ],
    "sg:phone":"+1 914 949 2551",
    "sg:postcode":"10601",
    "sg:province":"NY",
    "sg:tags":[
        "consultant",
        "program",
        "health",
        "fitness"
    ],
    "wof:name":"Herbalife Distributor",
    "wof:placetype":"venue"
},
  "geometry": {"coordinates":[-73.77056899999999,41.03449],"type":"Point"}
}