{
  "type": "Feature",
  "properties": {
    "iso:country":"US",
    "sg:address":"600 6th Ave",
    "sg:city":"New York",
    "sg:classifiers":[
        {
            "category":"Shopping",
            "subcategory":"Clothing, Apparel, & Fashions",
            "type":"Retail Goods"
        },
        {
            "category":"Shopping",
            "subcategory":"Jewelry",
            "type":"Retail Goods"
        }
    ],
    "sg:phone":"+1 212 647 0002",
    "sg:postcode":"10011",
    "sg:province":"NY",
    "sg:tags":[
        "accessory"
    ],
    "sg:website":"www.lailarowe.com",
    "wof:name":"Laila Rowe",
    "wof:placetype":"venue"
},
  "geometry": {"coordinates":[-73.99520099999999,40.739597],"type":"Point"}
}