{
  "type": "Feature",
  "properties": {
    "addr:full":"960 E Broadway Woodmere NY 11598",
    "addr:housenumber":"960",
    "addr:postcode":"11598",
    "addr:street":"E Broadway",
    "iso:country":"US",
    "sg:address":"960 E Broadway",
    "sg:city":"Woodmere",
    "sg:classifiers":[
        {
            "category":"Professional",
            "subcategory":"Business Services",
            "type":"Services"
        }
    ],
    "sg:phone":"+1   ",
    "sg:postcode":"11598",
    "sg:province":"NY",
    "wof:name":"Superior Home Inspectors",
    "wof:placetype":"venue"
},
  "geometry": {"coordinates":[-73.702917,40.62694],"type":"Point"}
}