{
  "type": "Feature",
  "properties": {
    "iso:country":"US",
    "sg:address":"224 W 35th St",
    "sg:city":"New York",
    "sg:classifiers":[
        {
            "category":"Professional",
            "subcategory":"Management & Consulting",
            "type":"Services"
        }
    ],
    "sg:phone":"+1 212 564 6711",
    "sg:postcode":"10001",
    "sg:province":"NY",
    "sg:tags":[
        "agency",
        "public",
        "relations",
        "advertising"
    ],
    "wof:name":"The Baron Company",
    "wof:placetype":"venue"
},
  "geometry": {"coordinates":[-73.992487,40.752496],"type":"Point"}
}