{
  "type": "Feature",
  "properties": {
    "iso:country":"US",
    "sg:address":"7981 Refinery Rd",
    "sg:city":"Bolivar",
    "sg:classifiers":[
        {
            "category":"Manufacturing",
            "subcategory":"Tools & Machinery",
            "type":"Manufacturing & Wholesale Goods"
        }
    ],
    "sg:phone":"+1 585 928 1540",
    "sg:postcode":"14715",
    "sg:province":"NY",
    "sg:tags":[
        "pattern",
        "industrial"
    ],
    "wof:name":"Industrial Patterns Inc",
    "wof:placetype":"venue"
},
  "geometry": {"coordinates":[-78.18725999999999,42.047462],"type":"Point"}
}