{
  "type": "Feature",
  "properties": {
    "addr:full":"360 Lexington Ave New York NY 10017",
    "addr:housenumber":"360",
    "addr:postcode":"10017",
    "addr:street":"Lexington Ave",
    "iso:country":"US",
    "sg:address":"360 Lexington Ave",
    "sg:city":"New York",
    "sg:classifiers":[
        {
            "category":"Social Services",
            "type":"Services"
        }
    ],
    "sg:phone":"+1 212 983 0700",
    "sg:postcode":"10017",
    "sg:province":"NY",
    "sg:tags":[
        "organization",
        "welfare"
    ],
    "sg:website":"www.alznyc.org",
    "wof:name":"Alzheimer's Assn Of NYC",
    "wof:placetype":"venue"
},
  "geometry": {"coordinates":[-73.976737,40.750564],"type":"Point"}
}