{
  "type": "Feature",
  "properties": {
    "addr:full":"283 Warner Ave Roslyn Heights NY 11577",
    "addr:housenumber":"283",
    "addr:postcode":"11577",
    "addr:street":"Warner Ave",
    "iso:country":"US",
    "sg:address":"283 Warner Ave",
    "sg:city":"Roslyn Heights",
    "sg:classifiers":[
        {
            "category":"Wholesale",
            "subcategory":"Auto Parts",
            "type":"Manufacturing & Wholesale Goods"
        }
    ],
    "sg:phone":"+1 516 625 2570",
    "sg:postcode":"11577",
    "sg:province":"NY",
    "sg:tags":[
        "supply"
    ],
    "wof:name":"Long Island Foreign Auto Parts",
    "wof:placetype":"venue"
},
  "geometry": {"coordinates":[-73.64456800000001,40.791905],"type":"Point"}
}