{
  "type": "Feature",
  "properties": {
    "addr:full":"171 Chautauqua Ave Lakewood NY 14750",
    "addr:housenumber":"171",
    "addr:postcode":"14750",
    "addr:street":"Chautauqua Ave",
    "iso:country":"US",
    "sg:address":"171 Chautauqua Ave",
    "sg:city":"Lakewood",
    "sg:classifiers":[
        {
            "category":"Professional",
            "type":"Services"
        }
    ],
    "sg:phone":"+1 716 763 0273",
    "sg:postcode":"14750",
    "sg:province":"NY",
    "sg:tags":[
        "establishment"
    ],
    "wof:name":"Standard Call Inc",
    "wof:placetype":"venue"
},
  "geometry": {"coordinates":[-79.326009,42.098187],"type":"Point"}
}