{
  "type": "Feature",
  "properties": {
    "iso:country":"US",
    "sg:address":"309 N Tioga St",
    "sg:city":"Ithaca",
    "sg:classifiers":[
        {
            "category":"Social Services",
            "type":"Services"
        }
    ],
    "sg:phone":"+1 607 592 4852",
    "sg:postcode":"14850",
    "sg:province":"NY",
    "sg:tags":[
        "counselor",
        "marriage",
        "family"
    ],
    "wof:name":"J Colleen Brown",
    "wof:placetype":"venue"
},
  "geometry": {"coordinates":[-76.49688399999999,42.442548],"type":"Point"}
}