{
  "type": "Feature",
  "properties": {
    "iso:country":"US",
    "sg:address":"2 Highland St",
    "sg:city":"Port Chester",
    "sg:classifiers":[
        {
            "category":"Professional",
            "subcategory":"Computer Services",
            "type":"Services"
        }
    ],
    "sg:phone":"+1 914 934 2223",
    "sg:postcode":"10573",
    "sg:province":"NY",
    "sg:tags":[
        "programing",
        "custom"
    ],
    "wof:name":"Cace New York",
    "wof:placetype":"venue"
},
  "geometry": {"coordinates":[-73.660129,41.003256],"type":"Point"}
}