{
  "type": "Feature",
  "properties": {
    "addr:full":"199 E 4th St New York NY 10009",
    "addr:housenumber":"199",
    "addr:postcode":"10009",
    "addr:street":"E 4Th St",
    "iso:country":"US",
    "sg:address":"199 E 4th St",
    "sg:city":"New York",
    "sg:classifiers":[
        {
            "category":"Personal",
            "subcategory":"Tattoo Parlor",
            "type":"Services"
        },
        {
            "category":"Personal",
            "subcategory":"Piercing",
            "type":"Services"
        }
    ],
    "sg:phone":"+1 212 473 1954",
    "sg:postcode":"10009",
    "sg:province":"NY",
    "sg:website":"www.venusmodernbodyarts.com",
    "wof:name":"Venus Modern Body Arts",
    "wof:placetype":"venue"
},
  "geometry": {"coordinates":[-73.983981,40.724132],"type":"Point"}
}