{
  "type": "Feature",
  "properties": {
    "iso:country":"US",
    "sg:address":"2 Bank St",
    "sg:city":"Rhinebeck",
    "sg:classifiers":[
        {
            "category":"Social Services",
            "type":"Services"
        }
    ],
    "sg:phone":"+1 845 876 4331",
    "sg:postcode":"12512",
    "sg:province":"NY",
    "wof:name":"Louis August Jonas Foundation",
    "wof:placetype":"venue"
},
  "geometry": {"coordinates":[-73.966753,41.553799],"type":"Point"}
}