{
  "type": "Feature",
  "properties": {
    "iso:country":"US",
    "sg:address":"224 Roebling St",
    "sg:city":"Brooklyn",
    "sg:classifiers":[
        {
            "category":"Arts & Performance",
            "subcategory":"Art Gallery",
            "type":"Entertainment"
        }
    ],
    "sg:phone":"+1 718 388 5388",
    "sg:postcode":"11211",
    "sg:province":"NY",
    "sg:website":"www.likethespice.com",
    "wof:name":"Like the Spice",
    "wof:placetype":"venue"
},
  "geometry": {"coordinates":[-73.95923500000001,40.711891],"type":"Point"}
}