{
  "type": "Feature",
  "properties": {
    "iso:country":"US",
    "sg:address":"2384 Monroe Ave",
    "sg:city":"Rochester",
    "sg:classifiers":[
        {
            "category":"Health Services",
            "subcategory":"Doctor",
            "type":"Services"
        }
    ],
    "sg:phone":"+1 585 442 1710",
    "sg:postcode":"14618",
    "sg:province":"NY",
    "sg:tags":[
        "dentist"
    ],
    "wof:name":"Charles O Kolthoff DDS",
    "wof:placetype":"venue"
},
  "geometry": {"coordinates":[-77.556799,43.119612],"type":"Point"}
}