{
  "type": "Feature",
  "properties": {
    "iso:country":"US",
    "sg:address":"3 Malin Ln",
    "sg:city":"Penfield",
    "sg:classifiers":[
        {
            "category":"Shopping",
            "subcategory":"Hobbies, Toys, & Games",
            "type":"Retail Goods"
        }
    ],
    "sg:phone":"+1   ",
    "sg:postcode":"14526",
    "sg:province":"NY",
    "wof:name":"Fossils By Five",
    "wof:placetype":"venue"
},
  "geometry": {"coordinates":[-77.47775799999999,43.123403],"type":"Point"}
}