{
  "type": "Feature",
  "properties": {
    "iso:country":"US",
    "sg:address":"23 Livingston Rd",
    "sg:city":"Carmel",
    "sg:classifiers":[
        {
            "category":"Building & Trades",
            "subcategory":"Plumbing",
            "type":"Services"
        }
    ],
    "sg:phone":"+1 516 228 5016",
    "sg:postcode":"10512",
    "sg:province":"NY",
    "sg:tags":[
        "plumbing",
        "contractor"
    ],
    "wof:name":"Mid-Westchester Plumbing",
    "wof:placetype":"venue"
},
  "geometry": {"coordinates":[-73.66013,41.476203],"type":"Point"}
}