{
  "type": "Feature",
  "properties": {
    "iso:country":"US",
    "sg:address":"351 5th Ave",
    "sg:city":"Troy",
    "sg:classifiers":[
        {
            "category":"Building & Trades",
            "subcategory":"Equipment Rental",
            "type":"Services"
        }
    ],
    "sg:phone":"+1 518 233 9000",
    "sg:postcode":"12182",
    "sg:province":"NY",
    "sg:tags":[
        "leasing",
        "furniture"
    ],
    "wof:name":"Aaron's Rental Purchase",
    "wof:placetype":"venue"
},
  "geometry": {"coordinates":[-73.677285,42.766024],"type":"Point"}
}