{
  "type": "Feature",
  "properties": {
    "addr:full":"1655 Dutch Broadway Elmont NY 11003",
    "addr:housenumber":"1655",
    "addr:postcode":"11003",
    "addr:street":"Dutch Broadway",
    "iso:country":"US",
    "sg:address":"1655 Dutch Broadway",
    "sg:city":"Elmont",
    "sg:classifiers":[
        {
            "category":"Government",
            "subcategory":"Police Station",
            "type":"Public Place"
        }
    ],
    "sg:phone":"+1 516 573 6500",
    "sg:postcode":"11003",
    "sg:province":"NY",
    "sg:tags":[
        "protection"
    ],
    "wof:name":"Police 5th Precinct",
    "wof:placetype":"venue"
},
  "geometry": {"coordinates":[-73.703491,40.687368],"type":"Point"}
}