{
  "type": "Feature",
  "properties": {
    "iso:country":"US",
    "sg:address":"490 Chenango St",
    "sg:city":"Binghamton",
    "sg:classifiers":[
        {
            "category":"Restaurant",
            "type":"Food & Drink"
        }
    ],
    "sg:phone":"+1 607 724 9886",
    "sg:postcode":"13901",
    "sg:province":"NY",
    "wof:name":"Nite-Cap Restaurant",
    "wof:placetype":"venue"
},
  "geometry": {"coordinates":[-75.901955,42.116118],"type":"Point"}
}