{
  "type": "Feature",
  "properties": {
    "addr:full":"1535 Hewlett Ave Hewlett NY 11557",
    "addr:housenumber":"1535",
    "addr:postcode":"11557",
    "addr:street":"Hewlett Ave",
    "iso:country":"US",
    "sg:address":"1535 Hewlett Ave",
    "sg:city":"Hewlett",
    "sg:classifiers":[
        {
            "category":"Wholesale",
            "subcategory":"Groceries",
            "type":"Manufacturing & Wholesale Goods"
        }
    ],
    "sg:phone":"+1 516 569 0661",
    "sg:postcode":"11557",
    "sg:province":"NY",
    "sg:tags":[
        "general"
    ],
    "wof:name":"H Zucker Inc",
    "wof:placetype":"venue"
},
  "geometry": {"coordinates":[-73.69418,40.643056],"type":"Point"}
}