{
  "type": "Feature",
  "properties": {
    "addr:full":"3707 82nd St Jackson Heights NY 11372",
    "addr:housenumber":"3707",
    "addr:postcode":"11372",
    "addr:street":"82Nd St",
    "iso:country":"US",
    "sg:address":"3707 82nd St",
    "sg:city":"Jackson Heights",
    "sg:classifiers":[
        {
            "category":"Restaurant",
            "type":"Food & Drink"
        }
    ],
    "sg:menulink":"http://www.allmenus.com/ny/queens/169931-burger-king/menu/",
    "sg:phone":"+1 718 507 7366",
    "sg:postcode":"11372",
    "sg:province":"NY",
    "sg:tags":[
        "burger",
        "american"
    ],
    "wof:name":"Burger King",
    "wof:placetype":"venue"
},
  "geometry": {"coordinates":[-73.884308,40.749697],"type":"Point"}
}