{
  "type": "Feature",
  "properties": {
    "iso:country":"US",
    "sg:address":"11144 Lefferts Blvd",
    "sg:city":"South Ozone Park",
    "sg:classifiers":[
        {
            "category":"Building & Trades",
            "subcategory":"Electrical",
            "type":"Services"
        }
    ],
    "sg:phone":"+1 718 641 4019",
    "sg:postcode":"11420",
    "sg:province":"NY",
    "sg:tags":[
        "electrician"
    ],
    "wof:name":"All Nite Electric Corp",
    "wof:placetype":"venue"
},
  "geometry": {"coordinates":[-73.821297,40.680199],"type":"Point"}
}