{
  "type": "Feature",
  "properties": {
    "addr:full":"9902 Rockaway Beach Blvd Rockaway Park NY 11694",
    "addr:housenumber":"9902",
    "addr:postcode":"11694",
    "addr:street":"Rockaway Beach Blvd",
    "iso:country":"US",
    "sg:address":"9902 Rockaway Beach Blvd",
    "sg:city":"Rockaway Park",
    "sg:classifiers":[
        {
            "category":"Restaurant",
            "type":"Food & Drink"
        }
    ],
    "sg:phone":"+1 718 474 0770",
    "sg:postcode":"11694",
    "sg:province":"NY",
    "sg:tags":[
        "mexican"
    ],
    "wof:name":"Brisas Del Mar Corp",
    "wof:placetype":"venue"
},
  "geometry": {"coordinates":[-73.82042300000001,40.584336],"type":"Point"}
}