{
  "type": "Feature",
  "properties": {
    "addr:full":"1087 Flushing Ave Brooklyn NY 11237",
    "addr:housenumber":"1087",
    "addr:postcode":"11237",
    "addr:street":"Flushing Ave",
    "iso:country":"US",
    "sg:address":"1087 Flushing Ave",
    "sg:city":"Brooklyn",
    "sg:classifiers":[
        {
            "category":"Coffee & Tea",
            "type":"Food & Drink"
        },
        {
            "category":"Shopping",
            "subcategory":"Crafts & Fabrics",
            "type":"Retail Goods"
        }
    ],
    "sg:phone":"+1 718 381 0920",
    "sg:postcode":"11237",
    "sg:province":"NY",
    "sg:tags":[
        "store"
    ],
    "sg:website":"www.brooklynyarncafe.com",
    "wof:name":"Brooklyn Yarn Cafe",
    "wof:placetype":"venue"
},
  "geometry": {"coordinates":[-73.928354,40.70501],"type":"Point"}
}