{
  "type": "Feature",
  "properties": {
    "addr:full":"3275 Mohawk St Sauquoit NY 13456",
    "addr:housenumber":"3275",
    "addr:postcode":"13456",
    "addr:street":"Mohawk St",
    "iso:country":"US",
    "sg:address":"3275 Mohawk St",
    "sg:city":"Sauquoit",
    "sg:classifiers":[
        {
            "category":"Building & Trades",
            "subcategory":"Construction",
            "type":"Services"
        }
    ],
    "sg:phone":"+1 315 737 5681",
    "sg:postcode":"13456",
    "sg:province":"NY",
    "sg:tags":[
        "house"
    ],
    "wof:name":"Stephen C Madaras",
    "wof:placetype":"venue"
},
  "geometry": {"coordinates":[-75.252804,43.02272],"type":"Point"}
}