{
  "type": "Feature",
  "properties": {
    "addr:full":"36 Berry St Norwich NY 13815",
    "addr:housenumber":"36",
    "addr:postcode":"13815",
    "addr:street":"Berry St",
    "iso:country":"US",
    "sg:address":"36 Berry St",
    "sg:city":"Norwich",
    "sg:classifiers":[
        {
            "category":"Organizations",
            "subcategory":"Non-profit Organization",
            "type":"Services"
        }
    ],
    "sg:phone":"+1 607 336 7897",
    "sg:postcode":"13815",
    "sg:province":"NY",
    "sg:tags":[
        "charitable",
        "institution"
    ],
    "wof:name":"Roots & Wings",
    "wof:placetype":"venue"
},
  "geometry": {"coordinates":[-75.517431,42.538236],"type":"Point"}
}