{
  "type": "Feature",
  "properties": {
    "addr:full":"1806 E Gun Hill Rd #1221 Bronx NY 10469",
    "addr:housenumber":"1806",
    "addr:postcode":"10469",
    "addr:street":"E Gun Hill Rd # 1221",
    "iso:country":"US",
    "sg:address":"1806 E Gun Hill Rd #1221",
    "sg:city":"Bronx",
    "sg:classifiers":[
        {
            "category":"Home & Garden",
            "subcategory":"Building Materials",
            "type":"Retail Goods"
        }
    ],
    "sg:phone":"+1 718 862 9800",
    "sg:postcode":"10469",
    "sg:province":"NY",
    "sg:tags":[
        "supply"
    ],
    "wof:name":"The Home Depot",
    "wof:placetype":"venue"
},
  "geometry": {"coordinates":[-73.832543,40.861907],"type":"Point"}
}