{
  "type": "Feature",
  "properties": {
    "iso:country":"US",
    "sg:address":"2055 E 57th St",
    "sg:city":"Brooklyn",
    "sg:classifiers":[
        {
            "category":"Organizations",
            "subcategory":"Religious Organization",
            "type":"Services"
        }
    ],
    "sg:phone":"+1 718 377 6687",
    "sg:postcode":"11234",
    "sg:province":"NY",
    "sg:tags":[
        "clergy"
    ],
    "wof:name":"John L Taylor",
    "wof:placetype":"venue"
},
  "geometry": {"coordinates":[-73.91826,40.614003],"type":"Point"}
}