{
  "type": "Feature",
  "properties": {
    "addr:full":"386 Park Ave S New York NY 10016",
    "addr:housenumber":"386",
    "addr:postcode":"10016",
    "addr:street":"Park Ave S",
    "iso:country":"US",
    "sg:address":"386 Park Ave S",
    "sg:city":"New York",
    "sg:classifiers":[
        {
            "category":"Health Services",
            "subcategory":"Clinic",
            "type":"Services"
        }
    ],
    "sg:phone":"+1 212 725 0973",
    "sg:postcode":"10016",
    "sg:province":"NY",
    "wof:name":"Karaghsian Hward Commemorative",
    "wof:placetype":"venue"
},
  "geometry": {"coordinates":[-73.984078,40.743325],"type":"Point"}
}