{
  "type": "Feature",
  "properties": {
    "iso:country":"US",
    "sg:address":"556 Manatuck Blvd",
    "sg:city":"Brightwaters",
    "sg:classifiers":[
        {
            "category":"Social Services",
            "type":"Services"
        }
    ],
    "sg:phone":"+1 631 665 2609",
    "sg:postcode":"11718",
    "sg:province":"NY",
    "sg:tags":[
        "organization",
        "welfare"
    ],
    "wof:name":"St Mary's Children Family Svc",
    "wof:placetype":"venue"
},
  "geometry": {"coordinates":[-73.26562699999999,40.730285],"type":"Point"}
}