{
  "type": "Feature",
  "properties": {
    "iso:country":"US",
    "sg:address":"15 Industrial Blvd",
    "sg:city":"Medford",
    "sg:classifiers":[
        {
            "category":"Wholesale",
            "subcategory":"Construction Materials",
            "type":"Manufacturing & Wholesale Goods"
        }
    ],
    "sg:phone":"+1 631 244 3744",
    "sg:postcode":"11763",
    "sg:province":"NY",
    "sg:tags":[
        "granite"
    ],
    "wof:name":"Prostone Marble & Granite",
    "wof:placetype":"venue"
},
  "geometry": {"coordinates":[-72.960022,40.815585],"type":"Point"}
}