{
  "type": "Feature",
  "properties": {
    "addr:full":"2373 Flatbush Ave Brooklyn NY 11234",
    "addr:housenumber":"2373",
    "addr:postcode":"11234",
    "addr:street":"Flatbush Ave",
    "iso:country":"US",
    "sg:address":"2373 Flatbush Ave",
    "sg:city":"Brooklyn",
    "sg:classifiers":[
        {
            "category":"Banks & Credit Unions",
            "subcategory":"Bank",
            "type":"Services"
        }
    ],
    "sg:phone":"+1 718 951 7111",
    "sg:postcode":"11234",
    "sg:province":"NY",
    "sg:tags":[
        "cashing",
        "check"
    ],
    "wof:name":"I & B Check Cashing",
    "wof:placetype":"venue"
},
  "geometry": {"coordinates":[-73.92433800000001,40.611545],"type":"Point"}
}