{
  "type": "Feature",
  "properties": {
    "addr:full":"80 Broadway Ter New York NY 10040",
    "addr:housenumber":"80",
    "addr:postcode":"10040",
    "addr:street":"Broadway Ter",
    "iso:country":"US",
    "sg:address":"80 Broadway Ter",
    "sg:city":"New York",
    "sg:classifiers":[
        {
            "category":"Professional",
            "subcategory":"Lawyer & Legal Services",
            "type":"Services"
        }
    ],
    "sg:phone":"+1 212 837 7908",
    "sg:postcode":"10040",
    "sg:province":"NY",
    "sg:tags":[
        "attorney"
    ],
    "wof:name":"Maddox Hargett & Carusso",
    "wof:placetype":"venue"
},
  "geometry": {"coordinates":[-73.93147399999999,40.856851],"type":"Point"}
}