{
  "type": "Feature",
  "properties": {
    "addr:full":"39 Kisco Ave Mt Kisco NY 10549",
    "addr:housenumber":"39",
    "addr:postcode":"10549",
    "addr:street":"Kisco Ave Mt Kisco",
    "iso:country":"US",
    "sg:address":"39 Kisco Ave",
    "sg:city":"Mt Kisco",
    "sg:classifiers":[
        {
            "category":"Health Services",
            "subcategory":"Clinic",
            "type":"Services"
        }
    ],
    "sg:phone":"+1 914 244 9393",
    "sg:postcode":"10549",
    "sg:province":"NY",
    "sg:tags":[
        "holistic",
        "practitioner"
    ],
    "wof:name":"Center For Health & Healing",
    "wof:placetype":"venue"
},
  "geometry": {"coordinates":[-73.72817499999999,41.21104],"type":"Point"}
}