{
  "type": "Feature",
  "properties": {
    "iso:country":"US",
    "sg:address":"3219 Woods Edge Rd",
    "sg:city":"Walworth",
    "sg:classifiers":[
        {
            "category":"Insurance",
            "subcategory":"Insurance Agent",
            "type":"Services"
        }
    ],
    "sg:phone":"+1 585 987 8326",
    "sg:postcode":"14568",
    "sg:province":"NY",
    "wof:name":"Forman Cogan & Cline",
    "wof:placetype":"venue"
},
  "geometry": {"coordinates":[-77.300414,43.125036],"type":"Point"}
}