{
  "type": "Feature",
  "properties": {
    "addr:full":"505 E 116th St New York NY 10029",
    "addr:housenumber":"505",
    "addr:postcode":"10029",
    "addr:street":"E 116Th St",
    "iso:country":"US",
    "sg:address":"505 E 116th St",
    "sg:city":"New York",
    "sg:classifiers":[
        {
            "category":"Personal",
            "type":"Services"
        }
    ],
    "sg:phone":"+1 212 213 8144",
    "sg:postcode":"10029",
    "sg:province":"NY",
    "sg:tags":[
        "towing"
    ],
    "wof:name":"A Big Apple Towing",
    "wof:placetype":"venue"
},
  "geometry": {"coordinates":[-73.93270099999999,40.794998],"type":"Point"}
}