{
  "type": "Feature",
  "properties": {
    "iso:country":"US",
    "sg:address":"630 State Hwy 312",
    "sg:city":"Brewster",
    "sg:classifiers":[
        {
            "category":"Professional",
            "subcategory":"Computer Services",
            "type":"Services"
        }
    ],
    "sg:phone":"+1 845 278 2764",
    "sg:postcode":"10509",
    "sg:province":"NY",
    "sg:tags":[
        "prepackaged",
        "software"
    ],
    "wof:name":"Upstate Software Associates",
    "wof:placetype":"venue"
},
  "geometry": {"coordinates":[-73.599457,41.431948],"type":"Point"}
}