{
  "type": "Feature",
  "properties": {
    "iso:country":"US",
    "sg:address":"9700 Hilton Dr",
    "sg:city":"Clarence Center",
    "sg:classifiers":[
        {
            "category":"Real Estate",
            "subcategory":"Real Estate Operator",
            "type":"Services"
        }
    ],
    "sg:phone":"+1 716 741 2648",
    "sg:postcode":"14032",
    "sg:province":"NY",
    "sg:tags":[
        "building",
        "residential",
        "operation",
        "speculative"
    ],
    "wof:name":"C Thompson Builders",
    "wof:placetype":"venue"
},
  "geometry": {"coordinates":[-78.62932000000001,43.01183],"type":"Point"}
}