{
  "type": "Feature",
  "properties": {
    "addr:full":"54 Driftwood Dr Port Washington NY 11050",
    "addr:housenumber":"54",
    "addr:postcode":"11050",
    "addr:street":"Driftwood Dr",
    "iso:country":"US",
    "sg:address":"54 Driftwood Dr",
    "sg:city":"Port Washington",
    "sg:classifiers":[
        {
            "category":"Wholesale",
            "subcategory":"Furniture",
            "type":"Manufacturing & Wholesale Goods"
        }
    ],
    "sg:phone":"+1 516 767 5606",
    "sg:postcode":"11050",
    "sg:province":"NY",
    "wof:name":"Ewp",
    "wof:placetype":"venue"
},
  "geometry": {"coordinates":[-73.70417399999999,40.848701],"type":"Point"}
}