{
  "type": "Feature",
  "properties": {
    "addr:full":"66 W Market St Corning NY 14830",
    "addr:housenumber":"66",
    "addr:postcode":"14830",
    "addr:street":"W Market St",
    "iso:country":"US",
    "sg:address":"66 W Market St",
    "sg:city":"Corning",
    "sg:classifiers":[
        {
            "category":"Restaurant",
            "type":"Food & Drink"
        }
    ],
    "sg:phone":"+1   ",
    "sg:postcode":"14830",
    "sg:province":"NY",
    "sg:tags":[
        "full",
        "bar",
        "italian"
    ],
    "wof:name":"Sorges Rest",
    "wof:placetype":"venue"
},
  "geometry": {"coordinates":[-77.058316,42.144011],"type":"Point"}
}