{
  "type": "Feature",
  "properties": {
    "iso:country":"US",
    "sg:address":"137 E Main St",
    "sg:city":"Bay Shore",
    "sg:classifiers":[
        {
            "category":"Shopping",
            "subcategory":"Mobile Phones",
            "type":"Retail Goods"
        }
    ],
    "sg:phone":"+1 631 392 0626",
    "sg:postcode":"11706",
    "sg:province":"NY",
    "sg:website":"verizonwireless.com/bestnetwork",
    "wof:name":"CELLULAR CITY INC",
    "wof:placetype":"venue"
},
  "geometry": {"coordinates":[-73.244406,40.723978],"type":"Point"}
}