{
  "type": "Feature",
  "properties": {
    "addr:full":"41 Maple Ave Rock Tavern NY 12575",
    "addr:housenumber":"41",
    "addr:postcode":"12575",
    "addr:street":"Maple Ave",
    "iso:country":"US",
    "sg:address":"41 Maple Ave",
    "sg:city":"Rock Tavern",
    "sg:classifiers":[
        {
            "category":"Wholesale",
            "subcategory":"Machinery & Supplies",
            "type":"Manufacturing & Wholesale Goods"
        }
    ],
    "sg:phone":"+1 845 564 2696",
    "sg:postcode":"12575",
    "sg:province":"NY",
    "wof:name":"Pimm Bros Inc",
    "wof:placetype":"venue"
},
  "geometry": {"coordinates":[-74.147173,41.521716],"type":"Point"}
}