{
  "type": "Feature",
  "properties": {
    "addr:full":"305 7th Ave New York NY 10001",
    "addr:housenumber":"305",
    "addr:postcode":"10001",
    "addr:street":"7Th Ave",
    "iso:country":"US",
    "sg:address":"305 7th Ave",
    "sg:city":"New York",
    "sg:classifiers":[
        {
            "category":"Professional",
            "type":"Services"
        },
        {
            "category":"Education",
            "subcategory":"Special Training",
            "type":"Public Place"
        }
    ],
    "sg:phone":"+1 212 387 8536",
    "sg:postcode":"10001",
    "sg:province":"NY",
    "sg:tags":[
        "adult"
    ],
    "sg:website":"www.brennaworkshops.com",
    "wof:name":"Brenna Workshops",
    "wof:placetype":"venue"
},
  "geometry": {"coordinates":[-73.99131199999999,40.750005],"type":"Point"}
}