{
  "type": "Feature",
  "properties": {
    "addr:full":"130 W 25th St New York NY 10001",
    "addr:housenumber":"130",
    "addr:postcode":"10001",
    "addr:street":"W 25Th St",
    "iso:country":"US",
    "sg:address":"130 W 25th St",
    "sg:city":"New York",
    "sg:classifiers":[
        {
            "category":"Building & Trades",
            "subcategory":"Construction",
            "type":"Services"
        }
    ],
    "sg:phone":"+1 212 337 9534",
    "sg:postcode":"10001",
    "sg:province":"NY",
    "sg:tags":[
        "designer"
    ],
    "wof:name":"Color Works",
    "wof:placetype":"venue"
},
  "geometry": {"coordinates":[-73.99408699999999,40.744951],"type":"Point"}
}