{
  "type": "Feature",
  "properties": {
    "addr:full":"33 Front St Ste 302 Hempstead NY 11550",
    "addr:housenumber":"33",
    "addr:postcode":"11550",
    "addr:street":"Front St Ste 302",
    "iso:country":"US",
    "sg:address":"33 Front St Ste 302",
    "sg:city":"Hempstead",
    "sg:classifiers":[
        {
            "category":"Health Services",
            "subcategory":"Chiropractor",
            "type":"Services"
        }
    ],
    "sg:phone":"+1 516 565 4816",
    "sg:postcode":"11550",
    "sg:province":"NY",
    "wof:name":"Island Medical Pain Relief PC",
    "wof:placetype":"venue"
},
  "geometry": {"coordinates":[-73.636703,40.704102],"type":"Point"}
}