{
  "type": "Feature",
  "properties": {
    "iso:country":"US",
    "sg:address":"1488 Lakeshore Dr",
    "sg:city":"Massapequa Park",
    "sg:classifiers":[
        {
            "category":"Building & Trades",
            "subcategory":"Construction",
            "type":"Services"
        }
    ],
    "sg:phone":"+1 516 229 0347",
    "sg:postcode":"11762",
    "sg:province":"NY",
    "sg:tags":[
        "installation",
        "system",
        "furniture"
    ],
    "wof:name":"Demino Services",
    "wof:placetype":"venue"
},
  "geometry": {"coordinates":[-73.44878199999999,40.701556],"type":"Point"}
}