{
  "type": "Feature",
  "properties": {
    "iso:country":"US",
    "sg:address":"32 Drysdale Street",
    "sg:city":"Staten Island",
    "sg:classifiers":[
        {
            "category":"Building & Trades",
            "subcategory":"Pest Control",
            "type":"Services"
        }
    ],
    "sg:phone":"+1 718 983 0004",
    "sg:postcode":"10314",
    "sg:province":"NY",
    "sg:website":"www.pestproservices.com",
    "wof:name":"Pest Pro Services Inc",
    "wof:placetype":"venue"
},
  "geometry": {"coordinates":[-74.13851200000001,40.599386],"type":"Point"}
}