{
  "type": "Feature",
  "properties": {
    "addr:full":"1967 Wehrle Dr Buffalo NY 14221",
    "addr:housenumber":"1967",
    "addr:postcode":"14221",
    "addr:street":"Wehrle Dr",
    "iso:country":"US",
    "sg:address":"1967 Wehrle Dr",
    "sg:city":"Buffalo",
    "sg:classifiers":[
        {
            "category":"Professional",
            "subcategory":"Business Services",
            "type":"Services"
        }
    ],
    "sg:phone":"+1 716 250 2775",
    "sg:postcode":"14221",
    "sg:province":"NY",
    "sg:tags":[
        "broker",
        "merchandise"
    ],
    "wof:name":"Empire Business Brokers",
    "wof:placetype":"venue"
},
  "geometry": {"coordinates":[-78.72204000000001,42.95657],"type":"Point"}
}