{
  "type": "Feature",
  "properties": {
    "addr:full":"540 Amsterdam Ave New York NY 10024",
    "addr:housenumber":"540",
    "addr:postcode":"10024",
    "addr:street":"Amsterdam Ave",
    "iso:country":"US",
    "sg:address":"540 Amsterdam Ave",
    "sg:city":"New York",
    "sg:classifiers":[
        {
            "category":"Retail",
            "subcategory":"Repair Shop",
            "type":"Services"
        }
    ],
    "sg:phone":"+1 212 993 8215",
    "sg:postcode":"10024",
    "sg:province":"NY",
    "sg:tags":[
        "lock",
        "locksmith"
    ],
    "wof:name":"New York Locksmiths",
    "wof:placetype":"venue"
},
  "geometry": {"coordinates":[-73.974625,40.788329],"type":"Point"}
}