{
  "type": "Feature",
  "properties": {
    "addr:full":"130 Kinsella Ave Massapequa Park NY 11762",
    "addr:housenumber":"130",
    "addr:postcode":"11762",
    "addr:street":"Kinsella Ave",
    "iso:country":"US",
    "sg:address":"130 Kinsella Ave",
    "sg:city":"Massapequa Park",
    "sg:classifiers":[
        {
            "category":"Building & Trades",
            "subcategory":"Electrical",
            "type":"Services"
        }
    ],
    "sg:phone":"+1 516 795 9170",
    "sg:postcode":"11762",
    "sg:province":"NY",
    "sg:tags":[
        "electrical",
        "contractor"
    ],
    "wof:name":"Rnd Electric",
    "wof:placetype":"venue"
},
  "geometry": {"coordinates":[-73.456232,40.670055],"type":"Point"}
}