{
  "type": "Feature",
  "properties": {
    "iso:country":"US",
    "sg:address":"303 Park Ave S",
    "sg:city":"New York",
    "sg:classifiers":[
        {
            "category":"Shopping",
            "subcategory":"Florist",
            "type":"Retail Goods"
        }
    ],
    "sg:phone":"+1   ",
    "sg:postcode":"10010",
    "sg:province":"NY",
    "wof:name":"Floraculture",
    "wof:placetype":"venue"
},
  "geometry": {"coordinates":[-73.98585,40.74075],"type":"Point"}
}