{
  "type": "Feature",
  "properties": {
    "iso:country":"US",
    "sg:address":"621 3rd Ave",
    "sg:city":"Watervliet",
    "sg:classifiers":[
        {
            "category":"Shopping",
            "type":"Retail Goods"
        }
    ],
    "sg:phone":"+1   ",
    "sg:postcode":"12189",
    "sg:province":"NY",
    "sg:tags":[
        "stamp",
        "coin"
    ],
    "wof:name":"Uncle Sam Stamp & Coin Shop",
    "wof:placetype":"venue"
},
  "geometry": {"coordinates":[-73.706531,42.714145],"type":"Point"}
}