{
  "type": "Feature",
  "properties": {
    "addr:full":"3201 Quentin Road Brooklyn NY 11234",
    "addr:housenumber":"3201",
    "addr:postcode":"11234",
    "addr:street":"Quentin Road",
    "iso:country":"US",
    "sg:address":"3201 Quentin Road",
    "sg:city":"Brooklyn",
    "sg:classifiers":[
        {
            "category":"Health Services",
            "subcategory":"Health Practitioner",
            "type":"Services"
        }
    ],
    "sg:phone":"+1 718 382 9505",
    "sg:postcode":"11234",
    "sg:province":"NY",
    "sg:tags":[
        "therapy",
        "physical"
    ],
    "wof:name":"Rebound Physical Therapy & Rehabilitation Services",
    "wof:placetype":"venue"
},
  "geometry": {"coordinates":[-73.93969,40.612907],"type":"Point"}
}