{
  "type": "Feature",
  "properties": {
    "addr:full":"2067 Broadway New York NY 10023",
    "addr:housenumber":"2067",
    "addr:postcode":"10023",
    "addr:street":"Broadway",
    "iso:country":"US",
    "sg:address":"2067 Broadway",
    "sg:city":"New York",
    "sg:classifiers":[
        {
            "category":"Manufacturing",
            "subcategory":"Printing",
            "type":"Manufacturing & Wholesale Goods"
        }
    ],
    "sg:phone":"+1   ",
    "sg:postcode":"10023",
    "sg:province":"NY",
    "sg:tags":[
        "publisher",
        "music"
    ],
    "wof:name":"Seesaw Music Corporation",
    "wof:placetype":"venue"
},
  "geometry": {"coordinates":[-73.982066,40.778441],"type":"Point"}
}