{
  "type": "Feature",
  "properties": {
    "iso:country":"US",
    "sg:address":"298 Broadway",
    "sg:city":"Brooklyn",
    "sg:classifiers":[
        {
            "category":"Wholesale",
            "subcategory":"Machinery & Supplies",
            "type":"Manufacturing & Wholesale Goods"
        }
    ],
    "sg:phone":"+1 718 387 1545",
    "sg:postcode":"11211",
    "sg:province":"NY",
    "sg:tags":[
        "equipment",
        "establishment"
    ],
    "wof:name":"Esayi House & Beauty Supplies",
    "wof:placetype":"venue"
},
  "geometry": {"coordinates":[-73.9589,40.708809],"type":"Point"}
}