{
  "type": "Feature",
  "properties": {
    "addr:full":"7555 Morgan Rd Liverpool NY 13090",
    "addr:housenumber":"7555",
    "addr:postcode":"13090",
    "addr:street":"Morgan Rd",
    "iso:country":"US",
    "sg:address":"7555 Morgan Rd",
    "sg:city":"Liverpool",
    "sg:classifiers":[
        {
            "category":"Banks & Credit Unions",
            "subcategory":"Bank",
            "type":"Services"
        }
    ],
    "sg:phone":"+1 315 457 9301",
    "sg:postcode":"13090",
    "sg:province":"NY",
    "wof:name":"ACMG Federal Credit Union",
    "wof:placetype":"venue"
},
  "geometry": {"coordinates":[-76.206457,43.136988],"type":"Point"}
}