{
  "type": "Feature",
  "properties": {
    "iso:country":"US",
    "sg:address":"5814 Clarendon Rd",
    "sg:city":"Brooklyn",
    "sg:classifiers":[
        {
            "category":"Retail",
            "subcategory":"Auto Repair",
            "type":"Services"
        }
    ],
    "sg:phone":"+1 718 451 5580",
    "sg:postcode":"11203",
    "sg:province":"NY",
    "sg:tags":[
        "wrecker"
    ],
    "wof:name":"J & K Towing Inc",
    "wof:placetype":"venue"
},
  "geometry": {"coordinates":[-73.921077,40.64489],"type":"Point"}
}