{
  "type": "Feature",
  "properties": {
    "addr:full":"70 Round Hill Rd Greenwich NY 06831",
    "addr:housenumber":"70",
    "addr:postcode":"06831",
    "addr:street":"Round Hill Rd",
    "iso:country":"US",
    "sg:address":"70 Round Hill Rd",
    "sg:city":"Greenwich",
    "sg:classifiers":[
        {
            "category":"Real Estate",
            "subcategory":"Architect",
            "type":"Services"
        }
    ],
    "sg:phone":"+1   ",
    "sg:postcode":"06831",
    "sg:province":"NY",
    "sg:tags":[
        "architectural"
    ],
    "wof:name":"Halper Owens Assocs",
    "wof:placetype":"venue"
},
  "geometry": {"coordinates":[-73.64325700000001,41.054014],"type":"Point"}
}