{
  "type": "Feature",
  "properties": {
    "iso:country":"US",
    "sg:address":"1737 York Ave",
    "sg:city":"Manhattan",
    "sg:classifiers":[
        {
            "category":"Shopping",
            "subcategory":"Bicycles & Sporting Goods",
            "type":"Retail Goods"
        }
    ],
    "sg:phone":"+1 212 876 3483",
    "sg:postcode":"10128",
    "sg:province":"NY",
    "sg:tags":[
        "diving",
        "equipment",
        "diver",
        "supply"
    ],
    "sg:website":"www.adventurescubany.com",
    "wof:name":"Adventure Scuba",
    "wof:placetype":"venue"
},
  "geometry": {"coordinates":[-73.944992,40.778833],"type":"Point"}
}