{
  "type": "Feature",
  "properties": {
    "addr:full":"45 W 36 St New York NY 10018",
    "addr:housenumber":"45",
    "addr:postcode":"10018",
    "addr:street":"W 36 St",
    "iso:country":"US",
    "sg:address":"45 W 36 St",
    "sg:city":"New York",
    "sg:classifiers":[
        {
            "category":"Social Services",
            "subcategory":"Job Training",
            "type":"Services"
        }
    ],
    "sg:phone":"+1 212 947 3180",
    "sg:postcode":"10018",
    "sg:province":"NY",
    "sg:tags":[
        "career",
        "counseling",
        "vocational"
    ],
    "wof:name":"Career Mentors Inc",
    "wof:placetype":"venue"
},
  "geometry": {"coordinates":[-73.985715,40.750538],"type":"Point"}
}