{
  "type": "Feature",
  "properties": {
    "addr:full":"171 Whitesboro St Yorkville NY 13495",
    "addr:housenumber":"171",
    "addr:postcode":"13495",
    "addr:street":"Whitesboro St",
    "iso:country":"US",
    "sg:address":"171 Whitesboro St",
    "sg:city":"Yorkville",
    "sg:classifiers":[
        {
            "category":"Retail",
            "subcategory":"Auto Repair",
            "type":"Services"
        }
    ],
    "sg:phone":"+1 315 768 6087",
    "sg:postcode":"13495",
    "sg:province":"NY",
    "sg:tags":[
        "repairing",
        "automobile"
    ],
    "wof:name":"Smith Auto Svc & Tire",
    "wof:placetype":"venue"
},
  "geometry": {"coordinates":[-75.284137,43.116888],"type":"Point"}
}