{
  "type": "Feature",
  "properties": {
    "addr:full":"123 Marshall St Syracuse NY 13210",
    "addr:housenumber":"123",
    "addr:postcode":"13210",
    "addr:street":"Marshall St",
    "iso:country":"US",
    "sg:address":"123 Marshall St",
    "sg:city":"Syracuse",
    "sg:classifiers":[
        {
            "category":"Restaurant",
            "type":"Food & Drink"
        }
    ],
    "sg:phone":"+1 315 422 1702",
    "sg:postcode":"13210",
    "sg:province":"NY",
    "wof:name":"Berry Town Restaurant",
    "wof:placetype":"venue"
},
  "geometry": {"coordinates":[-76.13480300000001,43.04167],"type":"Point"}
}