{
  "type": "Feature",
  "properties": {
    "iso:country":"US",
    "sg:address":"233 E Hill Rd",
    "sg:city":"Binghamton",
    "sg:classifiers":[
        {
            "category":"Autos & Motor Vehicles",
            "subcategory":"Motorcycle Sales",
            "type":"Retail Goods"
        }
    ],
    "sg:phone":"+1 607 648 4172",
    "sg:postcode":"13901",
    "sg:province":"NY",
    "sg:tags":[
        "scooter"
    ],
    "sg:website":"www.ssrpowersports.com",
    "wof:name":"SSR Powersports",
    "wof:placetype":"venue"
},
  "geometry": {"coordinates":[-75.901433,42.228364],"type":"Point"}
}