{
  "type": "Feature",
  "properties": {
    "iso:country":"US",
    "sg:address":"663 Adee Ave",
    "sg:city":"Bronx",
    "sg:classifiers":[
        {
            "category":"Shopping",
            "subcategory":"Discount & Variety Stores",
            "type":"Retail Goods"
        }
    ],
    "sg:phone":"+1   ",
    "sg:postcode":"10467",
    "sg:province":"NY",
    "wof:name":"Save A Lot 99 Cents",
    "wof:placetype":"venue"
},
  "geometry": {"coordinates":[-73.868692,40.869754],"type":"Point"}
}