{
  "type": "Feature",
  "properties": {
    "addr:full":"60 Brookside Ave Chester NY 10918",
    "addr:housenumber":"60",
    "addr:postcode":"10918",
    "addr:street":"Brookside Ave",
    "iso:country":"US",
    "sg:address":"60 Brookside Ave",
    "sg:city":"Chester",
    "sg:phone":"+1 845 469 6191",
    "sg:postcode":"10918",
    "sg:province":"NY",
    "sg:tags":[
        "oil"
    ],
    "wof:name":"Vin-J's Oil & Lube",
    "wof:placetype":"venue"
},
  "geometry": {"coordinates":[-74.282096,41.355657],"type":"Point"}
}