{
  "type": "Feature",
  "properties": {
    "iso:country":"US",
    "sg:address":"1307 E Gun Hill Rd",
    "sg:city":"Bronx",
    "sg:classifiers":[
        {
            "category":"Personal",
            "subcategory":"Beauty Salon",
            "type":"Services"
        }
    ],
    "sg:phone":"+1 718 652 6332",
    "sg:postcode":"10469",
    "sg:province":"NY",
    "sg:tags":[
        "shop"
    ],
    "wof:name":"Salon Desole",
    "wof:placetype":"venue"
},
  "geometry": {"coordinates":[-73.847348,40.871145],"type":"Point"}
}