{
  "type": "Feature",
  "properties": {
    "iso:country":"US",
    "sg:address":"8386 N Main St",
    "sg:city":"Eden",
    "sg:classifiers":[
        {
            "category":"Manufacturing",
            "subcategory":"Printing",
            "type":"Manufacturing & Wholesale Goods"
        }
    ],
    "sg:phone":"+1 716 992 3765",
    "sg:postcode":"14057",
    "sg:province":"NY",
    "sg:tags":[
        "screen",
        "commercial"
    ],
    "wof:name":"Pine Ridge Enterprises Inc",
    "wof:placetype":"venue"
},
  "geometry": {"coordinates":[-78.89395500000001,42.658486],"type":"Point"}
}