{
  "type": "Feature",
  "properties": {
    "addr:full":"1 Rockaway Ave Woodmere NY 11590",
    "addr:housenumber":"1",
    "addr:postcode":"11590",
    "addr:street":"Rockaway Ave",
    "iso:country":"US",
    "sg:address":"1 Rockaway Ave",
    "sg:city":"Woodmere",
    "sg:classifiers":[
        {
            "category":"Shopping",
            "subcategory":"Department Store",
            "type":"Retail Goods"
        }
    ],
    "sg:phone":"+1 516 295 4186",
    "sg:postcode":"11590",
    "sg:province":"NY",
    "sg:website":"www.mykmart.com",
    "wof:name":"Kmart",
    "wof:placetype":"venue"
},
  "geometry": {"coordinates":[-73.59754100000001,40.748416],"type":"Point"}
}