{
  "type": "Feature",
  "properties": {
    "iso:country":"US",
    "sg:address":"218 State Hwy 32",
    "sg:city":"New Paltz",
    "sg:classifiers":[
        {
            "category":"Shopping",
            "subcategory":"Gifts & Souvenirs",
            "type":"Retail Goods"
        }
    ],
    "sg:phone":"+1   ",
    "sg:postcode":"12561",
    "sg:province":"NY",
    "wof:name":"Whispers of Joy",
    "wof:placetype":"venue"
},
  "geometry": {"coordinates":[-74.08463999999999,41.716083],"type":"Point"}
}