{
  "type": "Feature",
  "properties": {
    "addr:full":"3344 Walden Ave Depew NY 14043",
    "addr:housenumber":"3344",
    "addr:postcode":"14043",
    "addr:street":"Walden Ave",
    "iso:country":"US",
    "sg:address":"3344 Walden Ave",
    "sg:city":"Depew",
    "sg:classifiers":[
        {
            "category":"Manufacturing",
            "subcategory":"Rubber & Plastics",
            "type":"Manufacturing & Wholesale Goods"
        },
        {
            "category":"Shopping",
            "type":"Retail Goods"
        }
    ],
    "sg:phone":"+1 716 989 3720",
    "sg:postcode":"14043",
    "sg:province":"NY",
    "sg:tags":[
        "equipment",
        "clothing",
        "safety",
        "clothing-wholesale",
        "manufacturer"
    ],
    "wof:name":"Lane Fire & Safety",
    "wof:placetype":"venue"
},
  "geometry": {"coordinates":[-78.691428,42.912799],"type":"Point"}
}