{
  "type": "Feature",
  "properties": {
    "addr:full":"66 Kenmare St New York NY 10012",
    "addr:housenumber":"66",
    "addr:postcode":"10012",
    "addr:street":"Kenmare St",
    "iso:country":"US",
    "sg:address":"66 Kenmare St",
    "sg:city":"New York",
    "sg:classifiers":[
        {
            "category":"Building & Trades",
            "subcategory":"Locksmith",
            "type":"Services"
        }
    ],
    "sg:phone":"+1 646 822 6816",
    "sg:postcode":"10012",
    "sg:province":"NY",
    "sg:tags":[
        "key"
    ],
    "wof:name":"0 1 Al L O C K Smith",
    "wof:placetype":"venue"
},
  "geometry": {"coordinates":[-73.99604100000001,40.720852],"type":"Point"}
}