{
  "type": "Feature",
  "properties": {
    "addr:full":"21812 136th Avenue Springfield Gardens NY 11413",
    "addr:housenumber":"21812",
    "addr:postcode":"11413",
    "addr:street":"136Th Avenue",
    "iso:country":"US",
    "sg:address":"21812 136th Avenue",
    "sg:city":"Springfield Gardens",
    "sg:classifiers":[
        {
            "category":"Organizations",
            "subcategory":"Religious Organization",
            "type":"Services"
        }
    ],
    "sg:phone":"+1 718 949 4311",
    "sg:postcode":"11413",
    "sg:province":"NY",
    "wof:name":"St Mary Magdalene Church",
    "wof:placetype":"venue"
},
  "geometry": {"coordinates":[-73.75281200000001,40.677137],"type":"Point"}
}