{
  "type": "Feature",
  "properties": {
    "iso:country":"US",
    "sg:address":"480 Austin Place",
    "sg:city":"Bronx",
    "sg:classifiers":[
        {
            "category":"Food & Beverages",
            "subcategory":"Groceries & Convenience Stores",
            "type":"Retail Goods"
        }
    ],
    "sg:phone":"+1 718 585 1907",
    "sg:postcode":"10455",
    "sg:province":"NY",
    "wof:name":"F & J Masters Sales Corporation",
    "wof:placetype":"venue"
},
  "geometry": {"coordinates":[-73.90419799999999,40.810134],"type":"Point"}
}