{
  "type": "Feature",
  "properties": {
    "addr:full":"1512 Co Rd 19 Burlington Flats NY 13315",
    "addr:housenumber":"1512;19",
    "addr:postcode":"13315",
    "addr:street":"Co Rd",
    "iso:country":"US",
    "sg:address":"1512 Co Rd 19",
    "sg:city":"Burlington Flats",
    "sg:classifiers":[
        {
            "category":"Government",
            "subcategory":"Office",
            "type":"Public Place"
        }
    ],
    "sg:phone":"+1 607 965 2138",
    "sg:postcode":"13315",
    "sg:province":"NY",
    "sg:tags":[
        "county"
    ],
    "wof:name":"Otsego County-Burlington",
    "wof:placetype":"venue"
},
  "geometry": {"coordinates":[-75.15987199999999,42.765881],"type":"Point"}
}