{
  "type": "Feature",
  "properties": {
    "iso:country":"US",
    "sg:address":"1755 Monroe Ave",
    "sg:city":"Rochester",
    "sg:classifiers":[
        {
            "category":"Banks & Credit Unions",
            "subcategory":"Bank",
            "type":"Services"
        }
    ],
    "sg:phone":"+1 585 242 0360",
    "sg:postcode":"14618",
    "sg:province":"NY",
    "sg:tags":[
        "state",
        "commercial"
    ],
    "wof:name":"Chase Manhattan",
    "wof:placetype":"venue"
},
  "geometry": {"coordinates":[-77.567027,43.128595],"type":"Point"}
}