{
  "type": "Feature",
  "properties": {
    "iso:country":"US",
    "sg:address":"133 W 22 St",
    "sg:city":"New York",
    "sg:classifiers":[
        {
            "category":"Retail",
            "subcategory":"Photofinishing",
            "type":"Services"
        }
    ],
    "sg:phone":"+1 212 741 1348",
    "sg:postcode":"10011",
    "sg:province":"NY",
    "sg:tags":[
        "photo",
        "finishing",
        "custom",
        "lab",
        "developing"
    ],
    "wof:name":"Image Source Inc",
    "wof:placetype":"venue"
},
  "geometry": {"coordinates":[-73.995391,40.743105],"type":"Point"}
}