{
  "type": "Feature",
  "properties": {
    "iso:country":"US",
    "sg:address":"3080 Main St",
    "sg:city":"Buffalo",
    "sg:classifiers":[
        {
            "category":"Shopping",
            "subcategory":"Bicycles & Sporting Goods",
            "type":"Retail Goods"
        }
    ],
    "sg:phone":"+1 716 834 6151",
    "sg:postcode":"14214",
    "sg:province":"NY",
    "sg:website":"www.jerseyexpress.com",
    "wof:name":"Jersey Express Inc",
    "wof:placetype":"venue"
},
  "geometry": {"coordinates":[-78.828796,42.948399],"type":"Point"}
}