{
  "type": "Feature",
  "properties": {
    "addr:full":"102 Dekalb Ave Brooklyn NY 11201",
    "addr:housenumber":"102",
    "addr:postcode":"11201",
    "addr:street":"Dekalb Ave",
    "iso:country":"US",
    "sg:address":"102 Dekalb Ave",
    "sg:city":"Brooklyn",
    "sg:classifiers":[
        {
            "category":"Personal",
            "subcategory":"Shoe Repair & Shine",
            "type":"Services"
        }
    ],
    "sg:phone":"+1 718 596 9221",
    "sg:postcode":"11201",
    "sg:province":"NY",
    "wof:name":"Emilio Shoe Repr",
    "wof:placetype":"venue"
},
  "geometry": {"coordinates":[-73.97910299999999,40.689701],"type":"Point"}
}