{
  "type": "Feature",
  "properties": {
    "addr:full":"6 N 3rd Ave Mt Vernon NY 10550",
    "addr:housenumber":"6",
    "addr:postcode":"10550",
    "addr:street":"N 3Rd Ave",
    "iso:country":"US",
    "sg:address":"6 N 3rd Ave",
    "sg:city":"Mt Vernon",
    "sg:classifiers":[
        {
            "category":"Taxi",
            "type":"Transportation"
        }
    ],
    "sg:phone":"+1 914 664 3333",
    "sg:postcode":"10550",
    "sg:province":"NY",
    "sg:tags":[
        "taxicab"
    ],
    "wof:name":"Dan Frank Realty Corp",
    "wof:placetype":"venue"
},
  "geometry": {"coordinates":[-73.836387,40.912721],"type":"Point"}
}