{
  "type": "Feature",
  "properties": {
    "iso:country":"US",
    "sg:address":"1000 Park Ave",
    "sg:city":"New York",
    "sg:classifiers":[
        {
            "category":"Health Services",
            "subcategory":"Doctor",
            "type":"Services"
        }
    ],
    "sg:phone":"+1 212 879 2353",
    "sg:postcode":"10028",
    "sg:province":"NY",
    "sg:tags":[
        "cardiologist"
    ],
    "wof:name":"Gertler Menard M Md P C",
    "wof:placetype":"venue"
},
  "geometry": {"coordinates":[-73.957846,40.77939],"type":"Point"}
}