{
  "type": "Feature",
  "properties": {
    "iso:country":"US",
    "sg:address":"862 Manhattan Ave",
    "sg:city":"Brooklyn",
    "sg:classifiers":[
        {
            "category":"Organizations",
            "subcategory":"Religious Organization",
            "type":"Services"
        }
    ],
    "sg:phone":"+1 718 383 3339",
    "sg:postcode":"11222",
    "sg:province":"NY",
    "sg:tags":[
        "school"
    ],
    "wof:name":"Saint Alphonsus",
    "wof:placetype":"venue"
},
  "geometry": {"coordinates":[-73.953723,40.729041],"type":"Point"}
}