{
  "type": "Feature",
  "properties": {
    "addr:full":"9720 Rockaway Beach Blvd Rockaway Beach NY 11693",
    "addr:housenumber":"9720",
    "addr:postcode":"11693",
    "addr:street":"Rockaway Beach Blvd",
    "iso:country":"US",
    "sg:address":"9720 Rockaway Beach Blvd",
    "sg:city":"Rockaway Beach",
    "sg:classifiers":[
        {
            "category":"Deli",
            "type":"Food & Drink"
        }
    ],
    "sg:menulink":"http://www.allmenus.com/ny/queens/240686-the-tap--grill/menu/",
    "sg:phone":"+1 718 474 9582",
    "sg:postcode":"11693",
    "sg:province":"NY",
    "sg:tags":[
        "american"
    ],
    "wof:name":"The Tap & Grill",
    "wof:placetype":"venue"
},
  "geometry": {"coordinates":[-73.818799,40.58495],"type":"Point"}
}