{
  "type": "Feature",
  "properties": {
    "iso:country":"US",
    "sg:address":"670 Manhattan Ave",
    "sg:city":"Brooklyn",
    "sg:classifiers":[
        {
            "category":"Shopping",
            "subcategory":"Jewelry",
            "type":"Retail Goods"
        }
    ],
    "sg:phone":"+1 718 784 2340",
    "sg:postcode":"11222",
    "sg:province":"NY",
    "wof:name":"Bejeweled",
    "wof:placetype":"venue"
},
  "geometry": {"coordinates":[-73.95137699999999,40.724788],"type":"Point"}
}