{
  "type": "Feature",
  "properties": {
    "iso:country":"US",
    "sg:address":"137 S Main St",
    "sg:city":"Naples",
    "sg:classifiers":[
        {
            "category":"Food & Beverages",
            "subcategory":"Liquor & Beverages",
            "type":"Retail Goods"
        }
    ],
    "sg:phone":"+1 585 374 2460",
    "sg:postcode":"14512",
    "sg:province":"NY",
    "wof:name":"Main St Wine & Liquor",
    "wof:placetype":"venue"
},
  "geometry": {"coordinates":[-77.40361300000001,42.613789],"type":"Point"}
}