{
  "type": "Feature",
  "properties": {
    "addr:full":"8723 Ditmas Ave Brooklyn NY 11236",
    "addr:housenumber":"8723",
    "addr:postcode":"11236",
    "addr:street":"Ditmas Ave",
    "iso:country":"US",
    "sg:address":"8723 Ditmas Ave",
    "sg:city":"Brooklyn",
    "sg:classifiers":[
        {
            "category":"Retail",
            "subcategory":"Auto Repair",
            "type":"Services"
        }
    ],
    "sg:phone":"+1 718 629 2986",
    "sg:postcode":"11236",
    "sg:province":"NY",
    "sg:tags":[
        "repairing",
        "automobile"
    ],
    "wof:name":"B & E Auto Repair Inc",
    "wof:placetype":"venue"
},
  "geometry": {"coordinates":[-73.916381,40.647103],"type":"Point"}
}