{
  "type": "Feature",
  "properties": {
    "addr:full":"20 Corporate Circle Dr Albany NY 12203",
    "addr:housenumber":"20",
    "addr:postcode":"12203",
    "addr:street":"Corporate Circle Dr",
    "iso:country":"US",
    "sg:address":"20 Corporate Circle Dr",
    "sg:city":"Albany",
    "sg:classifiers":[
        {
            "category":"Building & Trades",
            "subcategory":"Plumbing",
            "type":"Services"
        }
    ],
    "sg:phone":"+1 518 862 2214",
    "sg:postcode":"12203",
    "sg:province":"NY",
    "sg:tags":[
        "mechanical",
        "contractor"
    ],
    "wof:name":"Collett Mechanical",
    "wof:placetype":"venue"
},
  "geometry": {"coordinates":[-73.862748,42.705456],"type":"Point"}
}