{
  "type": "Feature",
  "properties": {
    "addr:full":"20 Banfi Plz W Farmingdale NY 11735",
    "addr:housenumber":"20",
    "addr:postcode":"11735",
    "addr:street":"Banfi Plz W",
    "iso:country":"US",
    "sg:address":"20 Banfi Plz W",
    "sg:city":"Farmingdale",
    "sg:classifiers":[
        {
            "category":"Professional",
            "subcategory":"Engineering",
            "type":"Services"
        },
        {
            "category":"Professional",
            "subcategory":"Computer Services",
            "type":"Services"
        }
    ],
    "sg:phone":"+1 718 352 4505",
    "sg:postcode":"11735",
    "sg:province":"NY",
    "sg:tags":[
        "engineer",
        "consultant",
        "designer",
        "system",
        "integration"
    ],
    "wof:name":"Mita Copiers By Carr Business",
    "wof:placetype":"venue"
},
  "geometry": {"coordinates":[-73.420384,40.717594],"type":"Point"}
}