{
  "type": "Feature",
  "properties": {
    "addr:full":"13 W Genesee St Baldwinsville NY 13027",
    "addr:housenumber":"13",
    "addr:postcode":"13027",
    "addr:street":"W Genesee St",
    "iso:country":"US",
    "sg:address":"13 W Genesee St",
    "sg:city":"Baldwinsville",
    "sg:classifiers":[
        {
            "category":"Shopping",
            "subcategory":"Books",
            "type":"Retail Goods"
        }
    ],
    "sg:phone":"+1 315 635 7854",
    "sg:postcode":"13027",
    "sg:province":"NY",
    "sg:tags":[
        "dealer"
    ],
    "wof:name":"Book Nook",
    "wof:placetype":"venue"
},
  "geometry": {"coordinates":[-76.33292299999999,43.158568],"type":"Point"}
}