{
  "type": "Feature",
  "properties": {
    "iso:country":"US",
    "sg:address":"1177 Avenue of the Americas Fl 10",
    "sg:city":"New York",
    "sg:classifiers":[
        {
            "category":"Banks & Credit Unions",
            "subcategory":"Bank",
            "type":"Services"
        }
    ],
    "sg:phone":"+1 212 292 0133",
    "sg:postcode":"10036",
    "sg:province":"NY",
    "sg:website":"www.signature-bank.com",
    "wof:name":"Signature Bank",
    "wof:placetype":"venue"
},
  "geometry": {"coordinates":[-73.98244800000001,40.757405],"type":"Point"}
}