{
  "type": "Feature",
  "properties": {
    "addr:full":"516 Woodland Hills Rd White Plains NY 10603",
    "addr:housenumber":"516",
    "addr:postcode":"10603",
    "addr:street":"Woodland Hills Rd",
    "iso:country":"US",
    "sg:address":"516 Woodland Hills Rd",
    "sg:city":"White Plains",
    "sg:classifiers":[
        {
            "category":"Real Estate",
            "subcategory":"Real Estate Operator",
            "type":"Services"
        }
    ],
    "sg:phone":"+1 914 949 9125",
    "sg:postcode":"10603",
    "sg:province":"NY",
    "sg:tags":[
        "building",
        "apartment"
    ],
    "wof:name":"Woodlands Hills Condominium",
    "wof:placetype":"venue"
},
  "geometry": {"coordinates":[-73.777175,41.050219],"type":"Point"}
}