{
  "type": "Feature",
  "properties": {
    "iso:country":"US",
    "sg:address":"13 Cherry Ln",
    "sg:city":"Cortland",
    "sg:classifiers":[
        {
            "category":"Health Services",
            "subcategory":"Clinic",
            "type":"Services"
        }
    ],
    "sg:phone":"+1 607 753 3675",
    "sg:postcode":"13045",
    "sg:province":"NY",
    "wof:name":"Cherry Lane",
    "wof:placetype":"venue"
},
  "geometry": {"coordinates":[-76.164998,42.612796],"type":"Point"}
}