{
  "type": "Feature",
  "properties": {
    "iso:country":"US",
    "sg:address":"109 Adee St",
    "sg:city":"Port Chester",
    "sg:classifiers":[
        {
            "category":"Real Estate",
            "subcategory":"Real Estate Operator",
            "type":"Services"
        }
    ],
    "sg:phone":"+1 914 690 1268",
    "sg:postcode":"10573",
    "sg:province":"NY",
    "sg:tags":[
        "mobile",
        "home",
        "community"
    ],
    "wof:name":"Jet Peru Money Remitters Inc",
    "wof:placetype":"venue"
},
  "geometry": {"coordinates":[-73.66294600000001,41.001859],"type":"Point"}
}