{
  "type": "Feature",
  "properties": {
    "addr:full":"107 W 18 St New York NY 10011",
    "addr:housenumber":"107",
    "addr:postcode":"10011",
    "addr:street":"W 18 St",
    "iso:country":"US",
    "sg:address":"107 W 18 St",
    "sg:city":"New York",
    "sg:classifiers":[
        {
            "category":"Restaurant",
            "type":"Food & Drink"
        }
    ],
    "sg:phone":"+1   ",
    "sg:postcode":"10011",
    "sg:province":"NY",
    "wof:name":"Petite Abeille",
    "wof:placetype":"venue"
},
  "geometry": {"coordinates":[-73.997694,40.741048],"type":"Point"}
}