{
  "type": "Feature",
  "properties": {
    "iso:country":"US",
    "sg:address":"84 Zena Rd",
    "sg:city":"Kingston",
    "sg:classifiers":[
        {
            "category":"Education",
            "subcategory":"School",
            "type":"Public Place"
        }
    ],
    "sg:phone":"+1 845 679 3820",
    "sg:postcode":"12401",
    "sg:province":"NY",
    "wof:name":"Hudson Valley Sudbury School",
    "wof:placetype":"venue"
},
  "geometry": {"coordinates":[-74.083754,41.993815],"type":"Point"}
}