{
  "type": "Feature",
  "properties": {
    "addr:full":"4127 Hylan Boulevard Staten Island NY 10308",
    "addr:housenumber":"4127",
    "addr:postcode":"10308",
    "addr:street":"Hylan Boulevard",
    "iso:country":"US",
    "sg:address":"4127 Hylan Boulevard",
    "sg:city":"Staten Island",
    "sg:classifiers":[
        {
            "category":"Professional",
            "subcategory":"Accounting & Tax Preparation",
            "type":"Services"
        }
    ],
    "sg:phone":"+1 718 984 6754",
    "sg:postcode":"10308",
    "sg:province":"NY",
    "sg:tags":[
        "accountant"
    ],
    "wof:name":"Diguardia Joseph Accountant",
    "wof:placetype":"venue"
},
  "geometry": {"coordinates":[-74.14856899999999,40.539147],"type":"Point"}
}