{
  "type": "Feature",
  "properties": {
    "iso:country":"US",
    "sg:address":"227 Millsburg Rd",
    "sg:city":"Middletown",
    "sg:classifiers":[
        {
            "category":"Freight",
            "type":"Transportation"
        }
    ],
    "sg:phone":"+1 845 355 1198",
    "sg:postcode":"10940",
    "sg:province":"NY",
    "sg:tags":[
        "trucking"
    ],
    "wof:name":"JPCT Trucking Inc",
    "wof:placetype":"venue"
},
  "geometry": {"coordinates":[-74.537031,41.377638],"type":"Point"}
}