{
  "type": "Feature",
  "properties": {
    "iso:country":"US",
    "sg:address":"160 Lowndes Ave Apt A",
    "sg:city":"Huntington Station",
    "sg:classifiers":[
        {
            "category":"Real Estate",
            "subcategory":"Real Estate Services",
            "type":"Services"
        }
    ],
    "sg:phone":"+1 631 549 0330",
    "sg:postcode":"11746",
    "sg:province":"NY",
    "sg:tags":[
        "management",
        "property"
    ],
    "wof:name":"Arco Management Corp",
    "wof:placetype":"venue"
},
  "geometry": {"coordinates":[-73.41374999999999,40.854239],"type":"Point"}
}