{
  "type": "Feature",
  "properties": {
    "addr:full":"54 Bayside Ave Oyster Bay NY 11771",
    "addr:housenumber":"54",
    "addr:postcode":"11771",
    "addr:street":"Bayside Ave",
    "iso:country":"US",
    "sg:address":"54 Bayside Ave",
    "sg:city":"Oyster Bay",
    "sg:classifiers":[
        {
            "category":"Building & Trades",
            "subcategory":"Construction",
            "type":"Services"
        }
    ],
    "sg:phone":"+1 516 922 5437",
    "sg:postcode":"11771",
    "sg:province":"NY",
    "sg:tags":[
        "hanging",
        "contractor"
    ],
    "wof:name":"Patricios Painting",
    "wof:placetype":"venue"
},
  "geometry": {"coordinates":[-73.53736000000001,40.875242],"type":"Point"}
}