{
  "type": "Feature",
  "properties": {
    "addr:full":"81 Harding St Blauvelt NY 10913",
    "addr:housenumber":"81",
    "addr:postcode":"10913",
    "addr:street":"Harding St",
    "iso:country":"US",
    "sg:address":"81 Harding St",
    "sg:city":"Blauvelt",
    "sg:classifiers":[
        {
            "category":"Building & Trades",
            "subcategory":"Plumbing",
            "type":"Services"
        }
    ],
    "sg:phone":"+1 845 359 3939",
    "sg:postcode":"10913",
    "sg:province":"NY",
    "sg:tags":[
        "plumbing",
        "contractor"
    ],
    "wof:name":"Traynor's Plumbing & Heating",
    "wof:placetype":"venue"
},
  "geometry": {"coordinates":[-73.979726,41.061207],"type":"Point"}
}