{
  "type": "Feature",
  "properties": {
    "addr:full":"1099 Jericho Tpke Commack NY 11725",
    "addr:housenumber":"1099",
    "addr:postcode":"11725",
    "addr:street":"Jericho Tpke",
    "iso:country":"US",
    "sg:address":"1099 Jericho Tpke",
    "sg:city":"Commack",
    "sg:classifiers":[
        {
            "category":"Home & Garden",
            "subcategory":"Garden Supply",
            "type":"Retail Goods"
        }
    ],
    "sg:phone":"+1 631 543 0112",
    "sg:postcode":"11725",
    "sg:province":"NY",
    "sg:tags":[
        "nursery",
        "gardening"
    ],
    "wof:name":"Michael's Garden Center",
    "wof:placetype":"venue"
},
  "geometry": {"coordinates":[-73.2705,40.845402],"type":"Point"}
}