{
  "type": "Feature",
  "properties": {
    "addr:full":"4336 Wetzel Rd Liverpool NY 13090",
    "addr:housenumber":"4336",
    "addr:postcode":"13090",
    "addr:street":"Wetzel Rd",
    "iso:country":"US",
    "sg:address":"4336 Wetzel Rd",
    "sg:city":"Liverpool",
    "sg:classifiers":[
        {
            "category":"Banks & Credit Unions",
            "subcategory":"Bank",
            "type":"Services"
        }
    ],
    "sg:phone":"+1 315 622 4391",
    "sg:postcode":"13090",
    "sg:province":"NY",
    "wof:name":"Syracuse Police Federal Credit",
    "wof:placetype":"venue"
},
  "geometry": {"coordinates":[-76.21511,43.150078],"type":"Point"}
}