{
  "type": "Feature",
  "properties": {
    "iso:country":"US",
    "sg:address":"201 East 10th Street #104",
    "sg:city":"New York",
    "sg:classifiers":[
        {
            "category":"Building & Trades",
            "subcategory":"Plumbing",
            "type":"Services"
        },
        {
            "category":"Building & Trades",
            "subcategory":"Construction",
            "type":"Services"
        },
        {
            "category":"Building & Trades",
            "subcategory":"Electrical",
            "type":"Services"
        }
    ],
    "sg:phone":"+1 917 297 4911",
    "sg:postcode":"10079",
    "sg:province":"NY",
    "sg:tags":[
        "electrician",
        "painter"
    ],
    "sg:website":"handymantohelpyou.googlepages.com",
    "wof:name":"Handyman to Help You",
    "wof:placetype":"venue"
},
  "geometry": {"coordinates":[-73.986766,40.72976],"type":"Point"}
}