{
  "type": "Feature",
  "properties": {
    "addr:full":"152 Gravesend Neck Rd Brooklyn NY 11223",
    "addr:housenumber":"152",
    "addr:postcode":"11223",
    "addr:street":"Gravesend Neck Rd",
    "iso:country":"US",
    "sg:address":"152 Gravesend Neck Rd",
    "sg:city":"Brooklyn",
    "sg:classifiers":[
        {
            "category":"Restaurant",
            "type":"Food & Drink"
        }
    ],
    "sg:phone":"+1   ",
    "sg:postcode":"11223",
    "sg:province":"NY",
    "sg:tags":[
        "eating"
    ],
    "wof:name":"Carlo Diagostino",
    "wof:placetype":"venue"
},
  "geometry": {"coordinates":[-73.96979,40.594857],"type":"Point"}
}