{
  "type": "Feature",
  "properties": {
    "iso:country":"US",
    "sg:address":"88 S Swan St",
    "sg:city":"Albany",
    "sg:classifiers":[
        {
            "category":"Building & Trades",
            "subcategory":"Electrical",
            "type":"Services"
        }
    ],
    "sg:phone":"+1 518 465 1234",
    "sg:postcode":"12210",
    "sg:province":"NY",
    "sg:tags":[
        "electric",
        "contractor"
    ],
    "sg:website":"www.oconnellelectric.com",
    "wof:name":"Oconnell Electric",
    "wof:placetype":"venue"
},
  "geometry": {"coordinates":[-73.760503,42.652854],"type":"Point"}
}