{
  "type": "Feature",
  "properties": {
    "iso:country":"US",
    "sg:address":"247 Main St",
    "sg:city":"Johnson City",
    "sg:classifiers":[
        {
            "category":"Shopping",
            "subcategory":"Gifts & Souvenirs",
            "type":"Retail Goods"
        }
    ],
    "sg:phone":"+1 607 797 5330",
    "sg:postcode":"13790",
    "sg:province":"NY",
    "sg:tags":[
        "collectible"
    ],
    "wof:name":"Valley Forge Baseball Cards",
    "wof:placetype":"venue"
},
  "geometry": {"coordinates":[-75.955507,42.115305],"type":"Point"}
}