{
  "type": "Feature",
  "properties": {
    "addr:full":"6151 State Rte 21 Williamson NY 14589",
    "addr:housenumber":"6151",
    "addr:postcode":"14589",
    "addr:street":"State Rte 21",
    "iso:country":"US",
    "sg:address":"6151 State Rte 21",
    "sg:city":"Williamson",
    "sg:classifiers":[
        {
            "category":"Building & Trades",
            "subcategory":"Construction",
            "type":"Services"
        }
    ],
    "sg:phone":"+1 585 330 4204",
    "sg:postcode":"14589",
    "sg:province":"NY",
    "sg:tags":[
        "woodworker"
    ],
    "wof:name":"Tri-County Woodworks",
    "wof:placetype":"venue"
},
  "geometry": {"coordinates":[-77.187883,43.219102],"type":"Point"}
}