{
  "type": "Feature",
  "properties": {
    "iso:country":"US",
    "sg:address":"385 Watervliet Shaker Rd",
    "sg:city":"Latham",
    "sg:classifiers":[
        {
            "category":"Organizations",
            "subcategory":"Religious Organization",
            "type":"Services"
        }
    ],
    "sg:phone":"+1 518 783 3538",
    "sg:postcode":"12110",
    "sg:province":"NY",
    "sg:tags":[
        "congregation",
        "sister"
    ],
    "wof:name":"St Josephs Provincial",
    "wof:placetype":"venue"
},
  "geometry": {"coordinates":[-73.742391,42.729769],"type":"Point"}
}