{
  "type": "Feature",
  "properties": {
    "addr:full":"2640 Foxdale Ave Oceanside NY 11572",
    "addr:postcode":"2640;11572",
    "addr:street":"Foxdale Ave",
    "iso:country":"US",
    "sg:address":"2640 Foxdale Ave",
    "sg:city":"Oceanside",
    "sg:classifiers":[
        {
            "category":"Education",
            "subcategory":"Special Training",
            "type":"Public Place"
        }
    ],
    "sg:phone":"+1 516 763 6743",
    "sg:postcode":"11572",
    "sg:province":"NY",
    "sg:tags":[
        "tutoring"
    ],
    "wof:name":"Great Neck Tutorial Center",
    "wof:placetype":"venue"
},
  "geometry": {"coordinates":[-73.624802,40.6455],"type":"Point"}
}