{
  "type": "Feature",
  "properties": {
    "addr:full":"2429 Merrick Rd Bellmore NY 11710",
    "addr:housenumber":"2429",
    "addr:postcode":"11710",
    "addr:street":"Merrick Rd",
    "iso:country":"US",
    "sg:address":"2429 Merrick Rd",
    "sg:city":"Bellmore",
    "sg:classifiers":[
        {
            "category":"Health Services",
            "subcategory":"Chiropractor",
            "type":"Services"
        }
    ],
    "sg:phone":"+1 516 679 3100",
    "sg:postcode":"11710",
    "sg:province":"NY",
    "wof:name":"John Giugliano DC",
    "wof:placetype":"venue"
},
  "geometry": {"coordinates":[-73.53476000000001,40.661972],"type":"Point"}
}