{
  "type": "Feature",
  "properties": {
    "addr:full":"333 S Fulton Ave Mount Vernon NY 10553",
    "addr:housenumber":"333",
    "addr:postcode":"10553",
    "addr:street":"S Fulton Ave",
    "iso:country":"US",
    "sg:address":"333 S Fulton Ave",
    "sg:city":"Mount Vernon",
    "sg:classifiers":[
        {
            "category":"Food & Beverages",
            "subcategory":"Groceries & Convenience Stores",
            "type":"Retail Goods"
        }
    ],
    "sg:phone":"+1   ",
    "sg:postcode":"10553",
    "sg:province":"NY",
    "sg:tags":[
        "supermarket"
    ],
    "wof:name":"Met Food",
    "wof:placetype":"venue"
},
  "geometry": {"coordinates":[-73.827243,40.904551],"type":"Point"}
}