{
  "type": "Feature",
  "properties": {
    "addr:full":"8901 Northern Boulevard Flushing NY 11372",
    "addr:housenumber":"8901",
    "addr:postcode":"11372",
    "addr:street":"Northern Boulevard",
    "iso:country":"US",
    "sg:address":"8901 Northern Boulevard",
    "sg:city":"Flushing",
    "sg:classifiers":[
        {
            "category":"Banks & Credit Unions",
            "subcategory":"Bank",
            "type":"Services"
        }
    ],
    "sg:phone":"+1 718 446 2336",
    "sg:postcode":"11372",
    "sg:province":"NY",
    "wof:name":"Independence Community Bank",
    "wof:placetype":"venue"
},
  "geometry": {"coordinates":[-73.878393,40.75627],"type":"Point"}
}