{
  "type": "Feature",
  "properties": {
    "addr:full":"114 E 32 St New York NY 10016",
    "addr:housenumber":"114;32",
    "addr:postcode":"10016",
    "addr:street":"E;St",
    "iso:country":"US",
    "sg:address":"114 E 32 St",
    "sg:city":"New York",
    "sg:classifiers":[
        {
            "category":"Home & Garden",
            "subcategory":"Furniture",
            "type":"Retail Goods"
        },
        {
            "category":"Professional",
            "subcategory":"Management & Consulting",
            "type":"Services"
        }
    ],
    "sg:phone":"+1 212 684 2300",
    "sg:postcode":"10016",
    "sg:province":"NY",
    "sg:tags":[
        "project",
        "consultant",
        "builder",
        "corporate",
        "custom"
    ],
    "wof:name":"Brescia Goldin Partners Inc",
    "wof:placetype":"venue"
},
  "geometry": {"coordinates":[-73.98123200000001,40.745347],"type":"Point"}
}