{
  "type": "Feature",
  "properties": {
    "addr:full":"575 Halleck St Bronx NY 10474",
    "addr:housenumber":"575",
    "addr:postcode":"10474",
    "addr:street":"Halleck St",
    "iso:country":"US",
    "sg:address":"575 Halleck St",
    "sg:city":"Bronx",
    "sg:classifiers":[
        {
            "category":"Food & Beverages",
            "subcategory":"Groceries & Convenience Stores",
            "type":"Retail Goods"
        }
    ],
    "sg:phone":"+1 718 837 3652",
    "sg:postcode":"10474",
    "sg:province":"NY",
    "wof:name":"Argento Food Corporation",
    "wof:placetype":"venue"
},
  "geometry": {"coordinates":[-73.88131799999999,40.812433],"type":"Point"}
}