{
  "type": "Feature",
  "properties": {
    "iso:country":"US",
    "sg:address":"1283 Route 52",
    "sg:city":"Fishkill",
    "sg:classifiers":[
        {
            "category":"Personal",
            "subcategory":"Massage",
            "type":"Services"
        }
    ],
    "sg:phone":"+1 845 897 4717",
    "sg:postcode":"12524",
    "sg:province":"NY",
    "wof:name":"Village Theraputic Massage",
    "wof:placetype":"venue"
},
  "geometry": {"coordinates":[-73.89473,41.536694],"type":"Point"}
}