{
  "type": "Feature",
  "properties": {
    "addr:full":"1994 Bruckner Blvd Bronx NY 10473",
    "addr:housenumber":"1994",
    "addr:postcode":"10473",
    "addr:street":"Bruckner Blvd",
    "iso:country":"US",
    "sg:address":"1994 Bruckner Blvd",
    "sg:city":"Bronx",
    "sg:classifiers":[
        {
            "category":"Restaurant",
            "type":"Food & Drink"
        }
    ],
    "sg:phone":"+1 718 822 9005",
    "sg:postcode":"10473",
    "sg:province":"NY",
    "sg:tags":[
        "delicatessen"
    ],
    "wof:name":"Quick Pick Foods",
    "wof:placetype":"venue"
},
  "geometry": {"coordinates":[-73.85863000000001,40.825562],"type":"Point"}
}