{
  "type": "Feature",
  "properties": {
    "addr:full":"15344 S Conduit Ave Jamaica NY 11434",
    "addr:housenumber":"15344",
    "addr:postcode":"11434",
    "addr:street":"S Conduit Ave",
    "iso:country":"US",
    "sg:address":"15344 S Conduit Ave",
    "sg:city":"Jamaica",
    "sg:classifiers":[
        {
            "category":"Bakery",
            "type":"Food & Drink"
        }
    ],
    "sg:menulink":"http://www.allmenus.com/ny/queens/108770-au-bon-pain/menu/",
    "sg:phone":"+1 718 751 4788",
    "sg:postcode":"11434",
    "sg:province":"NY",
    "sg:tags":[
        "american",
        "pastry"
    ],
    "wof:name":"Au Bon Pain",
    "wof:placetype":"venue"
},
  "geometry": {"coordinates":[-73.78523,40.666376],"type":"Point"}
}