{
  "type": "Feature",
  "properties": {
    "iso:country":"US",
    "sg:address":"45 Magnolia Dr",
    "sg:city":"Kings Park",
    "sg:classifiers":[
        {
            "category":"Wholesale",
            "subcategory":"Electrical",
            "type":"Manufacturing & Wholesale Goods"
        }
    ],
    "sg:phone":"+1 631 360 3899",
    "sg:postcode":"11754",
    "sg:province":"NY",
    "wof:name":"Cactus Studios Audio-Video Whl",
    "wof:placetype":"venue"
},
  "geometry": {"coordinates":[-73.225587,40.893448],"type":"Point"}
}