{
  "type": "Feature",
  "properties": {
    "addr:full":"186 Clinton Ave Brooklyn NY 11205",
    "addr:housenumber":"186",
    "addr:postcode":"11205",
    "addr:street":"Clinton Ave",
    "iso:country":"US",
    "sg:address":"186 Clinton Ave",
    "sg:city":"Brooklyn",
    "sg:classifiers":[
        {
            "category":"Insurance",
            "subcategory":"Hazard Insurance",
            "type":"Services"
        },
        {
            "category":"Insurance",
            "subcategory":"Health Insurance",
            "type":"Services"
        }
    ],
    "sg:phone":"+1 718 596 5537",
    "sg:postcode":"11205",
    "sg:province":"NY",
    "sg:tags":[
        "dental"
    ],
    "wof:name":"Terry Unchali & Co",
    "wof:placetype":"venue"
},
  "geometry": {"coordinates":[-73.968699,40.692472],"type":"Point"}
}