{
  "type": "Feature",
  "properties": {
    "addr:full":"22 E 59th Street New York NY 10022",
    "addr:housenumber":"22",
    "addr:postcode":"10022",
    "addr:street":"E 59Th Street",
    "iso:country":"US",
    "sg:address":"22 E 59th Street",
    "sg:city":"New York",
    "sg:classifiers":[
        {
            "category":"Building & Trades",
            "subcategory":"Locksmith",
            "type":"Services"
        }
    ],
    "sg:phone":"+1 646 237 9257",
    "sg:postcode":"10022",
    "sg:province":"NY",
    "sg:tags":[
        "key"
    ],
    "wof:name":"Always 24 Hr Towing",
    "wof:placetype":"venue"
},
  "geometry": {"coordinates":[-73.97157799999999,40.763524],"type":"Point"}
}