{
  "type": "Feature",
  "properties": {
    "iso:country":"US",
    "sg:address":"62 Leroy St",
    "sg:city":"Potsdam",
    "sg:classifiers":[
        {
            "category":"Food & Beverages",
            "subcategory":"Groceries & Convenience Stores",
            "type":"Retail Goods"
        }
    ],
    "sg:phone":"+1   ",
    "sg:postcode":"13676",
    "sg:province":"NY",
    "wof:name":"C JS Kegs Cases & More Int",
    "wof:placetype":"venue"
},
  "geometry": {"coordinates":[-74.981534,44.676235],"type":"Point"}
}