{
  "type": "Feature",
  "properties": {
    "addr:full":"44 Grange Hall Rd Stephentown NY 12168",
    "addr:housenumber":"44",
    "addr:postcode":"12168",
    "addr:street":"Grange Hall Rd",
    "iso:country":"US",
    "sg:address":"44 Grange Hall Rd",
    "sg:city":"Stephentown",
    "sg:classifiers":[
        {
            "category":"Social Services",
            "type":"Services"
        }
    ],
    "sg:phone":"+1 518 733 5429",
    "sg:postcode":"12168",
    "sg:province":"NY",
    "sg:tags":[
        "organization",
        "welfare"
    ],
    "wof:name":"Taconic Valley Svc",
    "wof:placetype":"venue"
},
  "geometry": {"coordinates":[-73.377999,42.552654],"type":"Point"}
}