{
  "type": "Feature",
  "properties": {
    "addr:full":"1351 Galley St Uniondale NY 11553",
    "addr:housenumber":"1351",
    "addr:postcode":"11553",
    "addr:street":"Galley St",
    "iso:country":"US",
    "sg:address":"1351 Galley St",
    "sg:city":"Uniondale",
    "sg:classifiers":[
        {
            "category":"Building & Trades",
            "subcategory":"Construction",
            "type":"Services"
        }
    ],
    "sg:phone":"+1 516 481 4216",
    "sg:postcode":"11553",
    "sg:province":"NY",
    "sg:tags":[
        "handyman"
    ],
    "wof:name":"Wright Wheel Repair",
    "wof:placetype":"venue"
},
  "geometry": {"coordinates":[-73.582785,40.714005],"type":"Point"}
}