{
  "type": "Feature",
  "properties": {
    "addr:full":"1875 Central Ave Albany NY 12205",
    "addr:housenumber":"1875",
    "addr:postcode":"12205",
    "addr:street":"Central Ave",
    "iso:country":"US",
    "sg:address":"1875 Central Ave",
    "sg:city":"Albany",
    "sg:classifiers":[
        {
            "category":"Shopping",
            "subcategory":"Clothing, Apparel, & Fashions",
            "type":"Retail Goods"
        }
    ],
    "sg:phone":"+1   ",
    "sg:postcode":"12205",
    "sg:province":"NY",
    "sg:tags":[
        "a",
        "dance",
        "studio",
        "operates"
    ],
    "wof:name":"Eleanors School of Dance",
    "wof:placetype":"venue"
},
  "geometry": {"coordinates":[-73.85242599999999,42.734863],"type":"Point"}
}