{
  "type": "Feature",
  "properties": {
    "addr:full":"36 Davidson Ave Buffalo NY 14215",
    "addr:housenumber":"36",
    "addr:postcode":"14215",
    "addr:street":"Davidson Ave",
    "iso:country":"US",
    "sg:address":"36 Davidson Ave",
    "sg:city":"Buffalo",
    "sg:classifiers":[
        {
            "category":"Organizations",
            "subcategory":"Religious Organization",
            "type":"Services"
        }
    ],
    "sg:phone":"+1 716 836 7835",
    "sg:postcode":"14215",
    "sg:province":"NY",
    "sg:tags":[
        "church"
    ],
    "wof:name":"St James Roman Catholic Chr",
    "wof:placetype":"venue"
},
  "geometry": {"coordinates":[-78.810688,42.937402],"type":"Point"}
}