{
  "type": "Feature",
  "properties": {
    "iso:country":"US",
    "sg:address":"52 E 72nd St",
    "sg:city":"New York",
    "sg:classifiers":[
        {
            "category":"Health Services",
            "subcategory":"Optometrist",
            "type":"Services"
        }
    ],
    "sg:phone":"+1 212 439 9600",
    "sg:postcode":"10021",
    "sg:province":"NY",
    "sg:tags":[
        "ophthalmologist"
    ],
    "sg:website":"www.maculacare.com",
    "wof:name":"MaculaCare",
    "wof:placetype":"venue"
},
  "geometry": {"coordinates":[-73.964449,40.771244],"type":"Point"}
}