{
  "type": "Feature",
  "properties": {
    "iso:country":"US",
    "sg:address":"104 Bank St",
    "sg:city":"Batavia",
    "sg:classifiers":[
        {
            "category":"Professional",
            "subcategory":"Lawyer & Legal Services",
            "type":"Services"
        }
    ],
    "sg:phone":"+1 585 344 3602",
    "sg:postcode":"14020",
    "sg:province":"NY",
    "sg:tags":[
        "attorney"
    ],
    "wof:name":"Cole Sorrentino Hurley Hewner",
    "wof:placetype":"venue"
},
  "geometry": {"coordinates":[-78.18046699999999,43.002285],"type":"Point"}
}