{
  "type": "Feature",
  "properties": {
    "addr:full":"745 Nepperhan Ave Yonkers NY 10703",
    "addr:housenumber":"745",
    "addr:postcode":"10703",
    "addr:street":"Nepperhan Ave",
    "iso:country":"US",
    "sg:address":"745 Nepperhan Ave",
    "sg:city":"Yonkers",
    "sg:classifiers":[
        {
            "category":"Retail",
            "subcategory":"Auto Repair",
            "type":"Services"
        }
    ],
    "sg:phone":"+1 914 963 4200",
    "sg:postcode":"10703",
    "sg:province":"NY",
    "sg:tags":[
        "wrecker"
    ],
    "wof:name":"Affordable Towing",
    "wof:placetype":"venue"
},
  "geometry": {"coordinates":[-73.87967399999999,40.950266],"type":"Point"}
}