{
  "type": "Feature",
  "properties": {
    "addr:full":"76 Pheasant Ln Buffalo NY 14227",
    "addr:housenumber":"76",
    "addr:postcode":"14227",
    "addr:street":"Pheasant Ln",
    "iso:country":"US",
    "sg:address":"76 Pheasant Ln",
    "sg:city":"Buffalo",
    "sg:classifiers":[
        {
            "category":"Shopping",
            "subcategory":"Optical Goods",
            "type":"Retail Goods"
        }
    ],
    "sg:phone":"+1   ",
    "sg:postcode":"14227",
    "sg:province":"NY",
    "wof:name":"Krueger Rolfe Optician",
    "wof:placetype":"venue"
},
  "geometry": {"coordinates":[-78.714671,42.867077],"type":"Point"}
}