{
  "type": "Feature",
  "properties": {
    "iso:country":"US",
    "sg:address":"6 Autumn Ln",
    "sg:city":"Amenia",
    "sg:classifiers":[
        {
            "category":"Restaurant",
            "type":"Food & Drink"
        }
    ],
    "sg:phone":"+1 845 373 9800",
    "sg:postcode":"12518",
    "sg:province":"NY",
    "wof:name":"Serevan Restaurant",
    "wof:placetype":"venue"
},
  "geometry": {"coordinates":[-74.031412,41.433583],"type":"Point"}
}