{
  "type": "Feature",
  "properties": {
    "addr:full":"115 W 29th St New York NY 10001",
    "addr:housenumber":"115",
    "addr:postcode":"10001",
    "addr:street":"W 29Th St",
    "iso:country":"US",
    "sg:address":"115 W 29th St",
    "sg:city":"New York",
    "sg:classifiers":[
        {
            "category":"Communications",
            "subcategory":"Film & Video Production",
            "type":"Services"
        },
        {
            "category":"Professional",
            "subcategory":"Advertising",
            "type":"Services"
        }
    ],
    "sg:phone":"+1 212 216 9155",
    "sg:postcode":"10001",
    "sg:province":"NY",
    "sg:tags":[
        "videographers",
        "video/film"
    ],
    "sg:website":"www.simbaproductions.net",
    "wof:name":"Simba Productions Inc.",
    "wof:placetype":"venue"
},
  "geometry": {"coordinates":[-73.990847,40.747193],"type":"Point"}
}