{
  "type": "Feature",
  "properties": {
    "addr:full":"1841 1st Ave New York NY 10128",
    "addr:housenumber":"1841",
    "addr:postcode":"10128",
    "addr:street":"1St Ave",
    "iso:country":"US",
    "sg:address":"1841 1st Ave",
    "sg:city":"New York",
    "sg:classifiers":[
        {
            "category":"Deli",
            "type":"Food & Drink"
        },
        {
            "category":"Food & Beverages",
            "subcategory":"Bakery",
            "type":"Retail Goods"
        }
    ],
    "sg:phone":"+1 212 996 0656",
    "sg:postcode":"10128",
    "sg:province":"NY",
    "sg:tags":[
        "sandwich"
    ],
    "wof:name":"Pam Deli Grocery",
    "wof:placetype":"venue"
},
  "geometry": {"coordinates":[-73.945279,40.782756],"type":"Point"}
}