{
  "type": "Feature",
  "properties": {
    "addr:full":"589 5th Ave New York NY 10017",
    "addr:housenumber":"589",
    "addr:postcode":"10017",
    "addr:street":"5Th Ave",
    "iso:country":"US",
    "sg:address":"589 5th Ave",
    "sg:city":"New York",
    "sg:classifiers":[
        {
            "category":"Communications",
            "type":"Services"
        }
    ],
    "sg:phone":"+1 212 308 7348",
    "sg:postcode":"10017",
    "sg:province":"NY",
    "wof:name":"Dattel Communications Systems",
    "wof:placetype":"venue"
},
  "geometry": {"coordinates":[-73.979024,40.756032],"type":"Point"}
}