{
  "type": "Feature",
  "properties": {
    "iso:country":"US",
    "sg:address":"354 Degraw St",
    "sg:city":"Brooklyn",
    "sg:classifiers":[
        {
            "category":"Shopping",
            "subcategory":"Clothing, Apparel, & Fashions",
            "type":"Retail Goods"
        }
    ],
    "sg:postcode":"11231",
    "sg:province":"NY",
    "sg:tags":[
        "children's",
        "clothing"
    ],
    "sg:website":"btweenbklyn.com",
    "wof:name":"b'tween",
    "wof:placetype":"venue"
},
  "geometry": {"coordinates":[-73.993308,40.682845],"type":"Point"}
}