{
  "type": "Feature",
  "properties": {
    "addr:full":"455 Kings Hwy Brooklyn NY 11223",
    "addr:housenumber":"455",
    "addr:postcode":"11223",
    "addr:street":"Kings Hwy",
    "iso:country":"US",
    "sg:address":"455 Kings Hwy",
    "sg:city":"Brooklyn",
    "sg:classifiers":[
        {
            "category":"Shopping",
            "subcategory":"Clothing, Apparel, & Fashions",
            "type":"Retail Goods"
        }
    ],
    "sg:phone":"+1   ",
    "sg:postcode":"11223",
    "sg:province":"NY",
    "sg:tags":[
        "family"
    ],
    "wof:name":"Damas Corp",
    "wof:placetype":"venue"
},
  "geometry": {"coordinates":[-73.972178,40.604195],"type":"Point"}
}