{
  "type": "Feature",
  "properties": {
    "iso:country":"US",
    "sg:address":"7 Maple Crest Ln",
    "sg:city":"Fulton",
    "sg:classifiers":[
        {
            "category":"Real Estate",
            "subcategory":"Architect",
            "type":"Services"
        }
    ],
    "sg:phone":"+1   ",
    "sg:postcode":"13069",
    "sg:province":"NY",
    "sg:tags":[
        "architectural"
    ],
    "wof:name":"Thomas Arctander Architects",
    "wof:placetype":"venue"
},
  "geometry": {"coordinates":[-76.40141,43.323541],"type":"Point"}
}