{
  "type": "Feature",
  "properties": {
    "addr:full":"1503 129th Street Flushing NY 11356",
    "addr:housenumber":"1503",
    "addr:postcode":"11356",
    "addr:street":"129Th Street",
    "iso:country":"US",
    "sg:address":"1503 129th Street",
    "sg:city":"Flushing",
    "sg:classifiers":[
        {
            "category":"Banks & Credit Unions",
            "subcategory":"Financial Services",
            "type":"Services"
        }
    ],
    "sg:phone":"+1 718 460 4435",
    "sg:postcode":"11356",
    "sg:province":"NY",
    "sg:tags":[
        "broker",
        "mortgage"
    ],
    "wof:name":"Chalenger USA",
    "wof:placetype":"venue"
},
  "geometry": {"coordinates":[-73.83928899999999,40.784554],"type":"Point"}
}