{
  "type": "Feature",
  "properties": {
    "iso:country":"US",
    "sg:address":"76 South St",
    "sg:city":"Oyster Bay",
    "sg:classifiers":[
        {
            "category":"Restaurant",
            "type":"Food & Drink"
        }
    ],
    "sg:phone":"+1   ",
    "sg:postcode":"11771",
    "sg:province":"NY",
    "sg:tags":[
        "grocery",
        "eating"
    ],
    "wof:name":"Taste Of Mexico",
    "wof:placetype":"venue"
},
  "geometry": {"coordinates":[-73.526668,40.874697],"type":"Point"}
}