{
  "type": "Feature",
  "properties": {
    "addr:full":"3935 Dewey Ave Rochester NY 14616",
    "addr:housenumber":"3935",
    "addr:postcode":"14616",
    "addr:street":"Dewey Ave",
    "iso:country":"US",
    "sg:address":"3935 Dewey Ave",
    "sg:city":"Rochester",
    "sg:classifiers":[
        {
            "category":"Restaurant",
            "type":"Food & Drink"
        }
    ],
    "sg:phone":"+1   ",
    "sg:postcode":"14616",
    "sg:province":"NY",
    "sg:tags":[
        "family"
    ],
    "wof:name":"Friendlys",
    "wof:placetype":"venue"
},
  "geometry": {"coordinates":[-77.64691500000001,43.243129],"type":"Point"}
}