{
  "type": "Feature",
  "properties": {
    "addr:full":"9801 4th Ave Brooklyn NY 11209",
    "addr:housenumber":"9801",
    "addr:postcode":"11209",
    "addr:street":"4Th Ave",
    "iso:country":"US",
    "sg:address":"9801 4th Ave",
    "sg:city":"Brooklyn",
    "sg:classifiers":[
        {
            "category":"Sports & Exercise",
            "subcategory":"Gym",
            "type":"Entertainment"
        }
    ],
    "sg:phone":"+1 718 680 7975",
    "sg:postcode":"11209",
    "sg:province":"NY",
    "sg:tags":[
        "club",
        "gymnasium",
        "program",
        "health",
        "fitness",
        "studio",
        "physical"
    ],
    "sg:website":"http://www.curves.com",
    "wof:name":"Curves",
    "wof:placetype":"venue"
},
  "geometry": {"coordinates":[-74.032639,40.613991],"type":"Point"}
}