{
  "type": "Feature",
  "properties": {
    "addr:full":"14 King St Croton On Hudson NY 10520",
    "addr:housenumber":"14",
    "addr:postcode":"10520",
    "addr:street":"King St",
    "iso:country":"US",
    "sg:address":"14 King St",
    "sg:city":"Croton On Hudson",
    "sg:classifiers":[
        {
            "category":"Real Estate",
            "subcategory":"Architect",
            "type":"Services"
        }
    ],
    "sg:phone":"+1   ",
    "sg:postcode":"10520",
    "sg:province":"NY",
    "sg:tags":[
        "architectural"
    ],
    "wof:name":"Barry Donaldson & Assoc",
    "wof:placetype":"venue"
},
  "geometry": {"coordinates":[-73.882299,41.213663],"type":"Point"}
}