{
  "type": "Feature",
  "properties": {
    "addr:full":"251 Post Ave Ste 1 Westbury NY 11590",
    "addr:housenumber":"251",
    "addr:postcode":"11590",
    "addr:street":"Post Ave Ste 1",
    "iso:country":"US",
    "sg:address":"251 Post Ave Ste 1",
    "sg:city":"Westbury",
    "sg:classifiers":[
        {
            "category":"Professional",
            "subcategory":"Lawyer & Legal Services",
            "type":"Services"
        }
    ],
    "sg:phone":"+1 516 802 3691",
    "sg:postcode":"11590",
    "sg:province":"NY",
    "wof:name":"Law Office Of Tara A Maher",
    "wof:placetype":"venue"
},
  "geometry": {"coordinates":[-73.588072,40.757966],"type":"Point"}
}