{
  "type": "Feature",
  "properties": {
    "iso:country":"US",
    "sg:address":"13533 Lefferts Blvd",
    "sg:city":"South Ozone Park",
    "sg:classifiers":[
        {
            "category":"Professional",
            "subcategory":"Computer Services",
            "type":"Services"
        }
    ],
    "sg:phone":"+1 718 322 5253",
    "sg:postcode":"11420",
    "sg:province":"NY",
    "sg:tags":[
        "stereo",
        "installation"
    ],
    "wof:name":"Show Time Customs",
    "wof:placetype":"venue"
},
  "geometry": {"coordinates":[-73.82071000000001,40.670467],"type":"Point"}
}