{
  "type": "Feature",
  "properties": {
    "iso:country":"US",
    "sg:address":"168 7th St",
    "sg:city":"Brooklyn",
    "sg:classifiers":[
        {
            "category":"Shopping",
            "subcategory":"Pets & Pet Supplies",
            "type":"Retail Goods"
        }
    ],
    "sg:phone":"+1 718 832 4806",
    "sg:postcode":"11215",
    "sg:province":"NY",
    "sg:tags":[
        "training"
    ],
    "sg:website":"www.semperfidony.com",
    "wof:name":"Semper Fido",
    "wof:placetype":"venue"
},
  "geometry": {"coordinates":[-73.991175,40.672975],"type":"Point"}
}