{
  "type": "Feature",
  "properties": {
    "iso:country":"US",
    "sg:address":"12 Dorset Pl",
    "sg:city":"Queensbury",
    "sg:classifiers":[
        {
            "category":"Real Estate",
            "subcategory":"Real Estate Operator",
            "type":"Services"
        }
    ],
    "sg:phone":"+1 518 798 9766",
    "sg:postcode":"12804",
    "sg:province":"NY",
    "sg:tags":[
        "apartment"
    ],
    "wof:name":"Stratford Apartments",
    "wof:placetype":"venue"
},
  "geometry": {"coordinates":[-73.712767,43.336668],"type":"Point"}
}