{
  "type": "Feature",
  "properties": {
    "addr:full":"46 Deepdale Dr Great Neck NY 11021",
    "addr:housenumber":"46",
    "addr:postcode":"11021",
    "addr:street":"Deepdale Dr",
    "iso:country":"US",
    "sg:address":"46 Deepdale Dr",
    "sg:city":"Great Neck",
    "sg:classifiers":[
        {
            "category":"Professional",
            "subcategory":"Lawyer & Legal Services",
            "type":"Services"
        }
    ],
    "sg:phone":"+1   ",
    "sg:postcode":"11021",
    "sg:province":"NY",
    "sg:tags":[
        "law",
        "at"
    ],
    "wof:name":"Barry J Brman Cunsellor At Law",
    "wof:placetype":"venue"
},
  "geometry": {"coordinates":[-73.73783299999999,40.789196],"type":"Point"}
}