{
  "type": "Feature",
  "properties": {
    "addr:full":"6538 Baptist Way East Syracuse NY 13057",
    "addr:housenumber":"6538",
    "addr:postcode":"13057",
    "addr:street":"Baptist Way",
    "iso:country":"US",
    "sg:address":"6538 Baptist Way",
    "sg:city":"East Syracuse",
    "sg:classifiers":[
        {
            "category":"Organizations",
            "subcategory":"Religious Organization",
            "type":"Services"
        },
        {
            "category":"Professional",
            "subcategory":"Business Services",
            "type":"Services"
        }
    ],
    "sg:phone":"+1 315 433 1001",
    "sg:postcode":"13057",
    "sg:province":"NY",
    "sg:website":"www.bcnysbc.org",
    "wof:name":"Baptist Convention Of New York",
    "wof:placetype":"venue"
},
  "geometry": {"coordinates":[-76.087006,43.089519],"type":"Point"}
}