{
  "type": "Feature",
  "properties": {
    "addr:full":"10 Hooper Rd Endicott NY 13760",
    "addr:housenumber":"10",
    "addr:postcode":"13760",
    "addr:street":"Hooper Rd",
    "iso:country":"US",
    "sg:address":"10 Hooper Rd",
    "sg:city":"Endicott",
    "sg:classifiers":[
        {
            "category":"Food & Beverages",
            "subcategory":"Dairy",
            "type":"Retail Goods"
        }
    ],
    "sg:phone":"+1   ",
    "sg:postcode":"13760",
    "sg:province":"NY",
    "sg:tags":[
        "product"
    ],
    "wof:name":"Ice Cream City",
    "wof:placetype":"venue"
},
  "geometry": {"coordinates":[-76.017505,42.108407],"type":"Point"}
}