{
  "type": "Feature",
  "properties": {
    "iso:country":"US",
    "sg:address":"10 Century Hill Dr",
    "sg:city":"Latham",
    "sg:classifiers":[
        {
            "category":"Professional",
            "subcategory":"Advertising",
            "type":"Services"
        }
    ],
    "sg:phone":"+1 518 786 6488",
    "sg:postcode":"12110",
    "sg:province":"NY",
    "sg:tags":[
        "counselor"
    ],
    "wof:name":"Masto Public Relations",
    "wof:placetype":"venue"
},
  "geometry": {"coordinates":[-73.758439,42.772108],"type":"Point"}
}