{
  "type": "Feature",
  "properties": {
    "addr:full":"873 Liberty Ave Brooklyn NY 11208",
    "addr:housenumber":"873",
    "addr:postcode":"11208",
    "addr:street":"Liberty Ave",
    "iso:country":"US",
    "sg:address":"873 Liberty Ave",
    "sg:city":"Brooklyn",
    "sg:classifiers":[
        {
            "category":"Freight",
            "type":"Transportation"
        }
    ],
    "sg:phone":"+1 718 647 0711",
    "sg:postcode":"11208",
    "sg:province":"NY",
    "sg:tags":[
        "broker",
        "trucking"
    ],
    "wof:name":"Tes Auto Repair & Sales",
    "wof:placetype":"venue"
},
  "geometry": {"coordinates":[-73.877149,40.677311],"type":"Point"}
}