{
  "type": "Feature",
  "properties": {
    "addr:full":"233 Lehrer Ave Elmont NY 11003",
    "addr:housenumber":"233",
    "addr:postcode":"11003",
    "addr:street":"Lehrer Ave",
    "iso:country":"US",
    "sg:address":"233 Lehrer Ave",
    "sg:city":"Elmont",
    "sg:classifiers":[
        {
            "category":"Building & Trades",
            "subcategory":"Construction",
            "type":"Services"
        }
    ],
    "sg:phone":"+1 516 775 4261",
    "sg:postcode":"11003",
    "sg:province":"NY",
    "sg:tags":[
        "residential",
        "remodeling"
    ],
    "wof:name":"Mpv Construction Corp",
    "wof:placetype":"venue"
},
  "geometry": {"coordinates":[-73.696684,40.703592],"type":"Point"}
}