{
  "type": "Feature",
  "properties": {
    "addr:full":"403 Triangle Rd Hammond NY 13646",
    "addr:housenumber":"403",
    "addr:postcode":"13646",
    "addr:street":"Triangle Rd",
    "iso:country":"US",
    "sg:address":"403 Triangle Rd",
    "sg:city":"Hammond",
    "sg:classifiers":[
        {
            "category":"Retail",
            "subcategory":"Auto Repair",
            "type":"Services"
        },
        {
            "category":"Wholesale",
            "subcategory":"Scrap",
            "type":"Manufacturing & Wholesale Goods"
        }
    ],
    "sg:phone":"+1 315 324 6234",
    "sg:postcode":"13646",
    "sg:province":"NY",
    "sg:tags":[
        "repairing",
        "automobile",
        "material"
    ],
    "wof:name":"Stewart's Auto Works",
    "wof:placetype":"venue"
},
  "geometry": {"coordinates":[-75.71498800000001,44.41947],"type":"Point"}
}