{
  "type": "Feature",
  "properties": {
    "addr:full":"340 W 17 St New York NY 10011",
    "addr:housenumber":"340",
    "addr:postcode":"10011",
    "addr:street":"W 17 St",
    "iso:country":"US",
    "sg:address":"340 W 17 St",
    "sg:city":"New York",
    "sg:classifiers":[
        {
            "category":"Health Services",
            "subcategory":"Doctor",
            "type":"Services"
        }
    ],
    "sg:phone":"+1 212 243 4300",
    "sg:postcode":"10011",
    "sg:province":"NY",
    "sg:tags":[
        "medical"
    ],
    "wof:name":"J A Sonnabend MD PC",
    "wof:placetype":"venue"
},
  "geometry": {"coordinates":[-74.00312700000001,40.74231],"type":"Point"}
}