{
  "type": "Feature",
  "properties": {
    "addr:full":"26 Vineyard Ave Highland NY 12528",
    "addr:housenumber":"26",
    "addr:postcode":"12528",
    "addr:street":"Vineyard Ave",
    "iso:country":"US",
    "sg:address":"26 Vineyard Ave",
    "sg:city":"Highland",
    "sg:classifiers":[
        {
            "category":"Personal",
            "subcategory":"Beauty Salon",
            "type":"Services"
        }
    ],
    "sg:phone":"+1   ",
    "sg:postcode":"12528",
    "sg:province":"NY",
    "sg:tags":[
        "shop"
    ],
    "wof:name":"Stephanies Salon",
    "wof:placetype":"venue"
},
  "geometry": {"coordinates":[-73.96126599999999,41.720496],"type":"Point"}
}