{
  "type": "Feature",
  "properties": {
    "iso:country":"US",
    "sg:address":"84 Business Park Dr Ste 302",
    "sg:city":"Armonk",
    "sg:classifiers":[
        {
            "category":"Professional",
            "subcategory":"Lawyer & Legal Services",
            "type":"Services"
        }
    ],
    "sg:phone":"+1 914 730 3400",
    "sg:postcode":"10504",
    "sg:province":"NY",
    "sg:website":"www.harriton-furrer.com",
    "wof:name":"Harriton & Furrer LLP",
    "wof:placetype":"venue"
},
  "geometry": {"coordinates":[-73.708601,41.118796],"type":"Point"}
}