{
  "type": "Feature",
  "properties": {
    "iso:country":"US",
    "sg:address":"1251 Co Rd 6",
    "sg:city":"Hammond",
    "sg:classifiers":[
        {
            "category":"Shopping",
            "subcategory":"Crafts & Fabrics",
            "type":"Retail Goods"
        }
    ],
    "sg:phone":"+1 315 324 5462",
    "sg:postcode":"13646",
    "sg:province":"NY",
    "sg:tags":[
        "shop"
    ],
    "wof:name":"Phoenix Fabrics",
    "wof:placetype":"venue"
},
  "geometry": {"coordinates":[-75.731875,44.450203],"type":"Point"}
}