{
  "type": "Feature",
  "properties": {
    "addr:full":"401 W 53rd St Ste 5c Manhattan NY 10019",
    "addr:housenumber":"401",
    "addr:postcode":"10019",
    "addr:street":"W 53Rd St Ste 5C",
    "iso:country":"US",
    "sg:address":"401 W 53rd St Ste 5c",
    "sg:city":"Manhattan",
    "sg:classifiers":[
        {
            "category":"Personal",
            "type":"Services"
        }
    ],
    "sg:phone":"+1 646 216 8388",
    "sg:postcode":"10019",
    "sg:province":"NY",
    "sg:tags":[
        "planning",
        "wedding"
    ],
    "sg:website":"ckyoccasions.com",
    "wof:name":"CKY Occasions",
    "wof:placetype":"venue"
},
  "geometry": {"coordinates":[-73.988276,40.764972],"type":"Point"}
}