{
  "type": "Feature",
  "properties": {
    "addr:full":"5469 Sheridan Dr Buffalo NY 14221",
    "addr:housenumber":"5469",
    "addr:postcode":"14221",
    "addr:street":"Sheridan Dr",
    "iso:country":"US",
    "sg:address":"5469 Sheridan Dr",
    "sg:city":"Buffalo",
    "sg:classifiers":[
        {
            "category":"Restaurant",
            "type":"Food & Drink"
        }
    ],
    "sg:phone":"+1 716 204 0700",
    "sg:postcode":"14221",
    "sg:province":"NY",
    "sg:website":"www.subway.com",
    "wof:name":"Subway Sandwiches & Salads",
    "wof:placetype":"venue"
},
  "geometry": {"coordinates":[-78.72558600000001,42.978014],"type":"Point"}
}