{
  "type": "Feature",
  "properties": {
    "iso:country":"US",
    "sg:address":"127 Smithtown Blvd Ste 13",
    "sg:city":"Nesconset",
    "sg:classifiers":[
        {
            "category":"Shopping",
            "subcategory":"Jewelry",
            "type":"Retail Goods"
        }
    ],
    "sg:phone":"+1 631 361 7260",
    "sg:postcode":"11767",
    "sg:province":"NY",
    "wof:name":"Prima-Donna",
    "wof:placetype":"venue"
},
  "geometry": {"coordinates":[-73.164597,40.8391],"type":"Point"}
}