{
  "type": "Feature",
  "properties": {
    "addr:full":"27 Liberty Ter Buffalo NY 14215",
    "addr:housenumber":"27",
    "addr:postcode":"14215",
    "addr:street":"Liberty Ter",
    "iso:country":"US",
    "sg:address":"27 Liberty Ter",
    "sg:city":"Buffalo",
    "sg:classifiers":[
        {
            "category":"Building & Trades",
            "subcategory":"Construction",
            "type":"Services"
        }
    ],
    "sg:phone":"+1 716 832 5398",
    "sg:postcode":"14215",
    "sg:province":"NY",
    "sg:tags":[
        "system",
        "contractor",
        "air conditioning"
    ],
    "wof:name":"Ml Heating & Cooling",
    "wof:placetype":"venue"
},
  "geometry": {"coordinates":[-78.788044,42.945656],"type":"Point"}
}