{
  "type": "Feature",
  "properties": {
    "addr:full":"1371 Eastern Pkwy Brooklyn NY 11233",
    "addr:housenumber":"1371",
    "addr:postcode":"11233",
    "addr:street":"Eastern Pkwy",
    "iso:country":"US",
    "sg:address":"1371 Eastern Pkwy",
    "sg:city":"Brooklyn",
    "sg:classifiers":[
        {
            "category":"Professional",
            "type":"Services"
        }
    ],
    "sg:phone":"+1 718 771 7820",
    "sg:postcode":"11233",
    "sg:province":"NY",
    "sg:tags":[
        "establishment"
    ],
    "wof:name":"Ralph Eastern Assoc",
    "wof:placetype":"venue"
},
  "geometry": {"coordinates":[-73.92463499999999,40.668566],"type":"Point"}
}