{
  "type": "Feature",
  "properties": {
    "addr:full":"4740 41st St Apt 3E Sunnyside NY 11104",
    "addr:housenumber":"4740",
    "addr:postcode":"11104",
    "addr:street":"41St St Apt 3E",
    "iso:country":"US",
    "sg:address":"4740 41st St Apt 3E",
    "sg:city":"Sunnyside",
    "sg:classifiers":[
        {
            "category":"Professional",
            "subcategory":"Secretarial Services",
            "type":"Services"
        }
    ],
    "sg:phone":"+1 718 784 3836",
    "sg:postcode":"11104",
    "sg:province":"NY",
    "sg:tags":[
        "answering",
        "telephone"
    ],
    "wof:name":"Yalcmin Ans",
    "wof:placetype":"venue"
},
  "geometry": {"coordinates":[-73.92332500000001,40.743778],"type":"Point"}
}