{
  "type": "Feature",
  "properties": {
    "iso:country":"US",
    "sg:address":"55 Fieldston Ter",
    "sg:city":"Rochester",
    "sg:classifiers":[
        {
            "category":"Organizations",
            "subcategory":"Religious Organization",
            "type":"Services"
        }
    ],
    "sg:phone":"+1 585 654 7993",
    "sg:postcode":"14610",
    "sg:province":"NY",
    "sg:tags":[
        "clergy"
    ],
    "wof:name":"Glenda Prins",
    "wof:placetype":"venue"
},
  "geometry": {"coordinates":[-77.53668500000001,43.150595],"type":"Point"}
}