{
  "type": "Feature",
  "properties": {
    "addr:full":"319 Route 211 E Middletown NY 10940",
    "addr:housenumber":"319",
    "addr:postcode":"10940",
    "addr:street":"Route 211 E",
    "iso:country":"US",
    "sg:address":"319 Route 211 E",
    "sg:city":"Middletown",
    "sg:classifiers":[
        {
            "category":"Banks & Credit Unions",
            "subcategory":"Investment Brokerage",
            "type":"Services"
        },
        {
            "category":"Shopping",
            "subcategory":"Computers & Home Electronics",
            "type":"Retail Goods"
        }
    ],
    "sg:phone":"+1 845 343 5516",
    "sg:postcode":"10940",
    "sg:province":"NY",
    "sg:tags":[
        "dvd",
        "video",
        "tape",
        "sale",
        "dvds-rental"
    ],
    "sg:website":"http://www.blockbuster.com",
    "wof:name":"Blockbuster Video",
    "wof:placetype":"venue"
},
  "geometry": {"coordinates":[-74.398653,41.454734],"type":"Point"}
}