{
  "type": "Feature",
  "properties": {
    "iso:country":"US",
    "sg:address":"24 Vernon Pl",
    "sg:city":"Mt Vernon",
    "sg:classifiers":[
        {
            "category":"Organizations",
            "subcategory":"Religious Organization",
            "type":"Services"
        }
    ],
    "sg:phone":"+1 914 699 1953",
    "sg:postcode":"10552",
    "sg:province":"NY",
    "sg:website":"www.colorblindmusic.com",
    "wof:name":"Colorblind Music Ministries",
    "wof:placetype":"venue"
},
  "geometry": {"coordinates":[-73.82875199999999,40.923288],"type":"Point"}
}