{
  "type": "Feature",
  "properties": {
    "addr:full":"1269 Fillmore Ave Buffalo NY 14211",
    "addr:housenumber":"1269",
    "addr:postcode":"14211",
    "addr:street":"Fillmore Ave",
    "iso:country":"US",
    "sg:address":"1269 Fillmore Ave",
    "sg:city":"Buffalo",
    "sg:classifiers":[
        {
            "category":"Restaurant",
            "type":"Food & Drink"
        }
    ],
    "sg:phone":"+1 716 896 8887",
    "sg:postcode":"14211",
    "sg:province":"NY",
    "wof:name":"Lee's Barbecue",
    "wof:placetype":"venue"
},
  "geometry": {"coordinates":[-78.839302,42.908001],"type":"Point"}
}