{
  "type": "Feature",
  "properties": {
    "iso:country":"US",
    "sg:address":"2082 Middle Country Rd",
    "sg:city":"Centereach",
    "sg:classifiers":[
        {
            "category":"Restaurant",
            "type":"Food & Drink"
        }
    ],
    "sg:menulink":"http://www.allmenus.com/ny/brookhaven/73761-pizza-hut/menu/",
    "sg:phone":"+1 631 981 3434",
    "sg:postcode":"11720",
    "sg:province":"NY",
    "sg:tags":[
        "american",
        "pizza"
    ],
    "wof:name":"Pizza Hut",
    "wof:placetype":"venue"
},
  "geometry": {"coordinates":[-73.084613,40.858414],"type":"Point"}
}