{
  "type": "Feature",
  "properties": {
    "addr:full":"79 Central Park N New York NY 10026",
    "addr:housenumber":"79",
    "addr:postcode":"10026",
    "addr:street":"Central Park N",
    "iso:country":"US",
    "sg:address":"79 Central Park N",
    "sg:city":"New York",
    "sg:classifiers":[
        {
            "category":"Shopping",
            "subcategory":"Clothing, Apparel, & Fashions",
            "type":"Retail Goods"
        }
    ],
    "sg:phone":"+1 212 499 9111",
    "sg:postcode":"10026",
    "sg:province":"NY",
    "wof:name":"Leeper Kids",
    "wof:placetype":"venue"
},
  "geometry": {"coordinates":[-73.950699,40.797354],"type":"Point"}
}