{
  "type": "Feature",
  "properties": {
    "addr:full":"4101 Bronxwood Ave Bronx NY 10466",
    "addr:housenumber":"4101",
    "addr:postcode":"10466",
    "addr:street":"Bronxwood Ave",
    "iso:country":"US",
    "sg:address":"4101 Bronxwood Ave",
    "sg:city":"Bronx",
    "sg:classifiers":[
        {
            "category":"Organizations",
            "subcategory":"Religious Organization",
            "type":"Services"
        }
    ],
    "sg:phone":"+1 718 231 8357",
    "sg:postcode":"10466",
    "sg:province":"NY",
    "sg:tags":[
        "clergy"
    ],
    "wof:name":"Mary Wells",
    "wof:placetype":"venue"
},
  "geometry": {"coordinates":[-73.852766,40.889506],"type":"Point"}
}