{
  "type": "Feature",
  "properties": {
    "iso:country":"US",
    "sg:address":"1450 53rd St",
    "sg:city":"Brooklyn",
    "sg:classifiers":[
        {
            "category":"Organizations",
            "subcategory":"Religious Organization",
            "type":"Services"
        }
    ],
    "sg:phone":"+1 718 435 5663",
    "sg:postcode":"11219",
    "sg:province":"NY",
    "sg:tags":[
        "clergy"
    ],
    "wof:name":"Bernard Glatzer",
    "wof:placetype":"venue"
},
  "geometry": {"coordinates":[-73.990944,40.630746],"type":"Point"}
}