{
  "type": "Feature",
  "properties": {
    "iso:country":"US",
    "sg:address":"77 Windsor Pl Ste 13",
    "sg:city":"Central Islip",
    "sg:classifiers":[
        {
            "category":"Building & Trades",
            "subcategory":"Construction",
            "type":"Services"
        }
    ],
    "sg:phone":"+1 631 582 2770",
    "sg:postcode":"11722",
    "sg:province":"NY",
    "sg:tags":[
        "painter"
    ],
    "sg:website":"www.tomcopainting.com",
    "wof:name":"Tomco Painting Inc",
    "wof:placetype":"venue"
},
  "geometry": {"coordinates":[-73.17800099999999,40.793598],"type":"Point"}
}