{
  "type": "Feature",
  "properties": {
    "iso:country":"US",
    "sg:address":"8721 18th Ave",
    "sg:city":"Brooklyn",
    "sg:classifiers":[
        {
            "category":"Building & Trades",
            "subcategory":"Plumbing",
            "type":"Services"
        }
    ],
    "sg:phone":"+1 718 621 7007",
    "sg:postcode":"11214",
    "sg:province":"NY",
    "sg:tags":[
        "heating",
        "contractor"
    ],
    "wof:name":"Petcol Mechanical Svc",
    "wof:placetype":"venue"
},
  "geometry": {"coordinates":[-74.005983,40.604004],"type":"Point"}
}