{
  "type": "Feature",
  "properties": {
    "iso:country":"US",
    "sg:address":"11 Alice St",
    "sg:city":"Binghamton",
    "sg:classifiers":[
        {
            "category":"Shopping",
            "subcategory":"Discount & Variety Stores",
            "type":"Retail Goods"
        }
    ],
    "sg:phone":"+1 607 771 4277",
    "sg:postcode":"13901",
    "sg:province":"NY",
    "sg:tags":[
        "outlet"
    ],
    "wof:name":"Binghamton Knitting Co Inc",
    "wof:placetype":"venue"
},
  "geometry": {"coordinates":[-75.855797,42.1646],"type":"Point"}
}