{
  "type": "Feature",
  "properties": {
    "iso:country":"US",
    "sg:address":"24 State Hwy 17K",
    "sg:city":"Newburgh",
    "sg:classifiers":[
        {
            "category":"Insurance",
            "subcategory":"Insurance Agent",
            "type":"Services"
        }
    ],
    "sg:phone":"+1 845 565 8000",
    "sg:postcode":"12550",
    "sg:province":"NY",
    "sg:website":"www.statefarm.com",
    "wof:name":"State Farm Insurance",
    "wof:placetype":"venue"
},
  "geometry": {"coordinates":[-74.05390800000001,41.503261],"type":"Point"}
}