{
  "type": "Feature",
  "properties": {
    "iso:country":"US",
    "sg:address":"366 E Main St",
    "sg:city":"Middletown",
    "sg:classifiers":[
        {
            "category":"Retail",
            "subcategory":"Auto Repair",
            "type":"Services"
        }
    ],
    "sg:phone":"+1 845 343 6066",
    "sg:postcode":"10940",
    "sg:province":"NY",
    "sg:tags":[
        "body",
        "repairing",
        "painting",
        "automobile"
    ],
    "wof:name":"Gailie Collision Custom",
    "wof:placetype":"venue"
},
  "geometry": {"coordinates":[-74.398188,41.445095],"type":"Point"}
}