{
  "type": "Feature",
  "properties": {
    "iso:country":"US",
    "sg:address":"1196 Co Rte 6",
    "sg:city":"Germantown",
    "sg:classifiers":[
        {
            "category":"Building & Trades",
            "subcategory":"Landscaping Services",
            "type":"Services"
        }
    ],
    "sg:phone":"+1 518 537 4271",
    "sg:postcode":"12526",
    "sg:province":"NY",
    "sg:tags":[
        "landscape",
        "contractor"
    ],
    "wof:name":"Three Seasons Lawn Care",
    "wof:placetype":"venue"
},
  "geometry": {"coordinates":[-73.84045399999999,42.087846],"type":"Point"}
}