{
  "type": "Feature",
  "properties": {
    "addr:full":"1446 Dewey Ave Rochester NY 14615",
    "addr:housenumber":"1446",
    "addr:postcode":"14615",
    "addr:street":"Dewey Ave",
    "iso:country":"US",
    "sg:address":"1446 Dewey Ave",
    "sg:city":"Rochester",
    "sg:classifiers":[
        {
            "category":"Personal",
            "subcategory":"Beauty Salon",
            "type":"Services"
        }
    ],
    "sg:phone":"+1 585 278 1847",
    "sg:postcode":"14615",
    "sg:province":"NY",
    "wof:name":"Childrens Gallery",
    "wof:placetype":"venue"
},
  "geometry": {"coordinates":[-77.638875,43.193083],"type":"Point"}
}