{
  "type": "Feature",
  "properties": {
    "iso:country":"US",
    "sg:address":"20 E 30 St",
    "sg:city":"New York",
    "sg:classifiers":[
        {
            "category":"Real Estate",
            "subcategory":"Real Estate Operator",
            "type":"Services"
        }
    ],
    "sg:phone":"+1 212 889 6838",
    "sg:postcode":"10016",
    "sg:province":"NY",
    "sg:tags":[
        "building"
    ],
    "wof:name":"Allan R Dovman",
    "wof:placetype":"venue"
},
  "geometry": {"coordinates":[-73.985821,40.745732],"type":"Point"}
}