{
  "type": "Feature",
  "properties": {
    "addr:full":"28 Bill Horton Way Wappingers Falls NY 12590",
    "addr:housenumber":"28",
    "addr:postcode":"12590",
    "addr:street":"Bill Horton Way",
    "iso:country":"US",
    "sg:address":"28 Bill Horton Way",
    "sg:city":"Wappingers Falls",
    "sg:classifiers":[
        {
            "category":"Building & Trades",
            "subcategory":"Landscaping Services",
            "type":"Services"
        }
    ],
    "sg:phone":"+1 845 297 4247",
    "sg:postcode":"12590",
    "sg:province":"NY",
    "sg:tags":[
        "landscape",
        "contractor"
    ],
    "wof:name":"Red Cedar Landscaping Inc",
    "wof:placetype":"venue"
},
  "geometry": {"coordinates":[-73.888711,41.620696],"type":"Point"}
}