{
  "type": "Feature",
  "properties": {
    "addr:full":"77 Pomeroy St Cortland NY 13045",
    "addr:housenumber":"77",
    "addr:postcode":"13045",
    "addr:street":"Pomeroy St",
    "iso:country":"US",
    "sg:address":"77 Pomeroy St",
    "sg:city":"Cortland",
    "sg:classifiers":[
        {
            "category":"Wholesale",
            "subcategory":"Electrical",
            "type":"Manufacturing & Wholesale Goods"
        }
    ],
    "sg:phone":"+1 607 753 7563",
    "sg:postcode":"13045",
    "sg:province":"NY",
    "sg:tags":[
        "equipment",
        "electric",
        "supply"
    ],
    "wof:name":"Skyline Electric Supply",
    "wof:placetype":"venue"
},
  "geometry": {"coordinates":[-76.16671599999999,42.599039],"type":"Point"}
}