{
  "type": "Feature",
  "properties": {
    "addr:full":"7508 37th Avenue Jackson Heights NY 11372",
    "addr:housenumber":"7508",
    "addr:postcode":"11372",
    "addr:street":"37Th Avenue",
    "iso:country":"US",
    "sg:address":"7508 37th Avenue",
    "sg:city":"Jackson Heights",
    "sg:classifiers":[
        {
            "category":"Shopping",
            "subcategory":"Optician",
            "type":"Retail Goods"
        }
    ],
    "sg:phone":"+1 718 476 1458",
    "sg:postcode":"11372",
    "sg:province":"NY",
    "sg:tags":[
        "eyewear"
    ],
    "wof:name":"Olivos Opticians",
    "wof:placetype":"venue"
},
  "geometry": {"coordinates":[-73.890494,40.748984],"type":"Point"}
}