{
  "type": "Feature",
  "properties": {
    "addr:full":"7 Rivington St New York NY 10002",
    "addr:housenumber":"7",
    "addr:postcode":"10002",
    "addr:street":"Rivington St",
    "iso:country":"US",
    "sg:address":"7 Rivington St",
    "sg:city":"New York",
    "sg:classifiers":[
        {
            "category":"Restaurant",
            "type":"Food & Drink"
        }
    ],
    "sg:menulink":"http://www.allmenus.com/ny/new-york/272777-loreley/menu/",
    "sg:phone":"+1 212 253 7077",
    "sg:postcode":"10002",
    "sg:province":"NY",
    "sg:tags":[
        "german"
    ],
    "wof:name":"Loreley",
    "wof:placetype":"venue"
},
  "geometry": {"coordinates":[-73.99285500000001,40.721216],"type":"Point"}
}