{
  "type": "Feature",
  "properties": {
    "addr:full":"148 W 37th St New York NY 10018",
    "addr:housenumber":"148",
    "addr:postcode":"10018",
    "addr:street":"W 37Th St",
    "iso:country":"US",
    "sg:address":"148 W 37th St",
    "sg:city":"New York",
    "sg:classifiers":[
        {
            "category":"Shopping",
            "type":"Retail Goods"
        }
    ],
    "sg:phone":"+1 212 760 3300",
    "sg:postcode":"10018",
    "sg:province":"NY",
    "sg:tags":[
        "equipment",
        "telephone",
        "supply"
    ],
    "sg:website":"www.lornapsi.com",
    "wof:name":"LORNA-Psi Communication Inc",
    "wof:placetype":"venue"
},
  "geometry": {"coordinates":[-73.988761,40.752542],"type":"Point"}
}