{
  "type": "Feature",
  "properties": {
    "iso:country":"US",
    "sg:address":"1095 Genesee St",
    "sg:city":"Buffalo",
    "sg:classifiers":[
        {
            "category":"Organizations",
            "subcategory":"Community Association",
            "type":"Services"
        }
    ],
    "sg:phone":"+1 716 892 5122",
    "sg:postcode":"14211",
    "sg:province":"NY",
    "wof:name":"Afro Dog",
    "wof:placetype":"venue"
},
  "geometry": {"coordinates":[-78.83770800000001,42.902744],"type":"Point"}
}