{
  "type": "Feature",
  "properties": {
    "iso:country":"US",
    "sg:address":"533 W 218th St",
    "sg:city":"New York",
    "sg:classifiers":[
        {
            "category":"Education",
            "subcategory":"College",
            "type":"Public Place"
        }
    ],
    "sg:phone":"+1 212 942 0431",
    "sg:postcode":"10034",
    "sg:province":"NY",
    "sg:tags":[
        "academic",
        "school"
    ],
    "wof:name":"Columbia University",
    "wof:placetype":"venue"
},
  "geometry": {"coordinates":[-73.91505600000001,40.871603],"type":"Point"}
}