{
  "type": "Feature",
  "properties": {
    "addr:full":"39 Lockwood Ave Yonkers NY 10701",
    "addr:housenumber":"39",
    "addr:postcode":"10701",
    "addr:street":"Lockwood Ave",
    "iso:country":"US",
    "sg:address":"39 Lockwood Ave",
    "sg:city":"Yonkers",
    "sg:classifiers":[
        {
            "category":"Food & Beverages",
            "subcategory":"Meat & Fish",
            "type":"Retail Goods"
        }
    ],
    "sg:phone":"+1   ",
    "sg:postcode":"10701",
    "sg:province":"NY",
    "sg:tags":[
        "grocery",
        "alcoholic"
    ],
    "wof:name":"Yonkers Miasarnia",
    "wof:placetype":"venue"
},
  "geometry": {"coordinates":[-73.874431,40.947788],"type":"Point"}
}