{
  "type": "Feature",
  "properties": {
    "addr:full":"200 E 3rd St Jamestown NY 14701",
    "addr:housenumber":"200",
    "addr:postcode":"14701",
    "addr:street":"E 3Rd St",
    "iso:country":"US",
    "sg:address":"200 E 3rd St",
    "sg:city":"Jamestown",
    "sg:classifiers":[
        {
            "category":"Government",
            "subcategory":"Office",
            "type":"Public Place"
        }
    ],
    "sg:phone":"+1 716 483 7510",
    "sg:postcode":"14701",
    "sg:province":"NY",
    "wof:name":"Accessors Office",
    "wof:placetype":"venue"
},
  "geometry": {"coordinates":[-79.238907,42.096722],"type":"Point"}
}