{
  "type": "Feature",
  "properties": {
    "iso:country":"US",
    "name:eng_x_preferred":[
        "Flatbush Av - Brooklyn College"
    ],
    "wof:name":"Flatbush Av - Brooklyn College",
    "wof:placetype":"venue"
},
  "geometry": {"coordinates":[-73.947642,40.632836],"type":"Point"}
}