{
  "type": "Feature",
  "properties": {
    "iso:country":"US",
    "sg:address":"229 Neptune Ave",
    "sg:city":"Brooklyn",
    "sg:classifiers":[
        {
            "category":"Shopping",
            "subcategory":"Crafts & Fabrics",
            "type":"Retail Goods"
        }
    ],
    "sg:phone":"+1 718 332 3853",
    "sg:postcode":"11235",
    "sg:province":"NY",
    "sg:tags":[
        "shop"
    ],
    "wof:name":"Shedman Fashion",
    "wof:placetype":"venue"
},
  "geometry": {"coordinates":[-73.961032,40.581725],"type":"Point"}
}