{
  "type": "Feature",
  "properties": {
    "addr:full":"450 Meacham Ave Elmont NY 11003",
    "addr:housenumber":"450",
    "addr:postcode":"11003",
    "addr:street":"Meacham Ave",
    "iso:country":"US",
    "sg:address":"450 Meacham Ave",
    "sg:city":"Elmont",
    "sg:classifiers":[
        {
            "category":"Deli",
            "type":"Food & Drink"
        },
        {
            "category":"Food & Beverages",
            "subcategory":"Bakery",
            "type":"Retail Goods"
        }
    ],
    "sg:phone":"+1 516 328 9277",
    "sg:postcode":"11003",
    "sg:province":"NY",
    "sg:tags":[
        "sandwich"
    ],
    "wof:name":"Brc Deli",
    "wof:placetype":"venue"
},
  "geometry": {"coordinates":[-73.691029,40.697745],"type":"Point"}
}