{
  "type": "Feature",
  "properties": {
    "iso:country":"US",
    "sg:address":"5203 4th Ave",
    "sg:city":"Brooklyn",
    "sg:classifiers":[
        {
            "category":"Banks & Credit Unions",
            "subcategory":"Investment Brokerage",
            "type":"Services"
        }
    ],
    "sg:phone":"+1 718 492 7077",
    "sg:postcode":"11220",
    "sg:province":"NY",
    "sg:tags":[
        "security"
    ],
    "wof:name":"Edal General Brokerage Inc",
    "wof:placetype":"venue"
},
  "geometry": {"coordinates":[-74.014256,40.644755],"type":"Point"}
}