{
  "type": "Feature",
  "properties": {
    "addr:full":"80 Congress St Troy NY 12180",
    "addr:housenumber":"80",
    "addr:postcode":"12180",
    "addr:street":"Congress St",
    "iso:country":"US",
    "sg:address":"80 Congress St",
    "sg:city":"Troy",
    "sg:classifiers":[
        {
            "category":"Personal",
            "subcategory":"Beauty Salon",
            "type":"Services"
        }
    ],
    "sg:phone":"+1 518 273 0660",
    "sg:postcode":"12180",
    "sg:province":"NY",
    "wof:name":"Styles Upon Styles",
    "wof:placetype":"venue"
},
  "geometry": {"coordinates":[-73.69041799999999,42.728756],"type":"Point"}
}