{
  "type": "Feature",
  "properties": {
    "addr:full":"612 Rogers Ave Brooklyn NY 11225",
    "addr:housenumber":"612",
    "addr:postcode":"11225",
    "addr:street":"Rogers Ave",
    "iso:country":"US",
    "sg:address":"612 Rogers Ave",
    "sg:city":"Brooklyn",
    "sg:classifiers":[
        {
            "category":"Restaurant",
            "type":"Food & Drink"
        }
    ],
    "sg:phone":"+1 718 703 2913",
    "sg:postcode":"11225",
    "sg:province":"NY",
    "wof:name":"Good Food & Tings",
    "wof:placetype":"venue"
},
  "geometry": {"coordinates":[-73.95313299999999,40.656203],"type":"Point"}
}