{
  "type": "Feature",
  "properties": {
    "iso:country":"US",
    "sg:address":"99 Hillside Ave Ste Z",
    "sg:city":"Williston Park",
    "sg:classifiers":[
        {
            "category":"Professional",
            "subcategory":"Lawyer & Legal Services",
            "type":"Services"
        }
    ],
    "sg:phone":"+1 516 877 0436",
    "sg:postcode":"11596",
    "sg:province":"NY",
    "sg:tags":[
        "divorce",
        "law",
        "family"
    ],
    "wof:name":"Michael J Kaper",
    "wof:placetype":"venue"
},
  "geometry": {"coordinates":[-73.643204,40.757099],"type":"Point"}
}