{
  "type": "Feature",
  "properties": {
    "iso:country":"US",
    "sg:address":"2425 Grand Ave",
    "sg:city":"Bellmore",
    "sg:classifiers":[
        {
            "category":"Wholesale",
            "subcategory":"Vending Machines",
            "type":"Manufacturing & Wholesale Goods"
        }
    ],
    "sg:phone":"+1 516 785 6485",
    "sg:postcode":"11710",
    "sg:province":"NY",
    "sg:tags":[
        "equipment",
        "commercial"
    ],
    "wof:name":"A & D Vending Co",
    "wof:placetype":"venue"
},
  "geometry": {"coordinates":[-73.53936899999999,40.668036],"type":"Point"}
}