{
  "type": "Feature",
  "properties": {
    "addr:full":"35 E 84th St New York NY 10028",
    "addr:housenumber":"35",
    "addr:postcode":"10028",
    "addr:street":"E 84Th St",
    "iso:country":"US",
    "sg:address":"35 E 84th St",
    "sg:city":"New York",
    "sg:classifiers":[
        {
            "category":"Health Services",
            "subcategory":"Doctor",
            "type":"Services"
        }
    ],
    "sg:phone":"+1 212 879 0509",
    "sg:postcode":"10028",
    "sg:province":"NY",
    "sg:tags":[
        "medical"
    ],
    "wof:name":"Matthew Tolchin",
    "wof:placetype":"venue"
},
  "geometry": {"coordinates":[-73.95816499999999,40.778861],"type":"Point"}
}