{
  "type": "Feature",
  "properties": {
    "addr:full":"103 S Bedford Rd Mount Kisco NY 10549",
    "addr:housenumber":"103",
    "addr:postcode":"10549",
    "addr:street":"S Bedford Rd",
    "iso:country":"US",
    "sg:address":"103 S Bedford Rd",
    "sg:city":"Mount Kisco",
    "sg:classifiers":[
        {
            "category":"Real Estate",
            "subcategory":"Architect",
            "type":"Services"
        }
    ],
    "sg:phone":"+1 914 241 3620",
    "sg:postcode":"10549",
    "sg:province":"NY",
    "sg:tags":[
        "architectural"
    ],
    "wof:name":"Kenneth R Ndler Consulting LLC",
    "wof:placetype":"venue"
},
  "geometry": {"coordinates":[-73.71813400000001,41.198165],"type":"Point"}
}