{
  "type": "Feature",
  "properties": {
    "addr:full":"701 Seneca Pkwy Rochester NY 14613",
    "addr:housenumber":"701",
    "addr:postcode":"14613",
    "addr:street":"Seneca Pkwy",
    "iso:country":"US",
    "sg:address":"701 Seneca Pkwy",
    "sg:city":"Rochester",
    "sg:classifiers":[
        {
            "category":"Professional",
            "subcategory":"Management & Consulting",
            "type":"Services"
        }
    ],
    "sg:phone":"+1   ",
    "sg:postcode":"14613",
    "sg:province":"NY",
    "sg:tags":[
        "public",
        "relations"
    ],
    "wof:name":"Prominent Professional Images",
    "wof:placetype":"venue"
},
  "geometry": {"coordinates":[-77.645948,43.189121],"type":"Point"}
}