{
  "type": "Feature",
  "properties": {
    "iso:country":"US",
    "sg:address":"4 Pleasantview Ave",
    "sg:city":"Albany",
    "sg:classifiers":[
        {
            "category":"Government",
            "subcategory":"Jail",
            "type":"Public Place"
        }
    ],
    "sg:phone":"+1 518 485 7980",
    "sg:postcode":"12203",
    "sg:province":"NY",
    "sg:tags":[
        "finance"
    ],
    "wof:name":"Criminal Jstice Srvces-Finance",
    "wof:placetype":"venue"
},
  "geometry": {"coordinates":[-73.82317500000001,42.672868],"type":"Point"}
}