{
  "type": "Feature",
  "properties": {
    "iso:country":"US",
    "sg:address":"362 5th Avenue Lbby",
    "sg:city":"New York",
    "sg:classifiers":[
        {
            "category":"Building & Trades",
            "subcategory":"Cleaning & Sanitation",
            "type":"Services"
        }
    ],
    "sg:phone":"+1 212 947 6866",
    "sg:postcode":"10001",
    "sg:province":"NY",
    "sg:tags":[
        "carpet"
    ],
    "wof:name":"Kiwi Carpet",
    "wof:placetype":"venue"
},
  "geometry": {"coordinates":[-73.984201,40.748853],"type":"Point"}
}