{
  "type": "Feature",
  "properties": {
    "iso:country":"US",
    "sg:address":"350 Hendrickson Ave",
    "sg:city":"Lynbrook",
    "sg:classifiers":[
        {
            "category":"Wholesale",
            "subcategory":"Electrical",
            "type":"Manufacturing & Wholesale Goods"
        }
    ],
    "sg:phone":"+1 516 599 4127",
    "sg:postcode":"11563",
    "sg:province":"NY",
    "sg:tags":[
        "alarm",
        "burglar",
        "system"
    ],
    "wof:name":"Liberty Bell Alarms",
    "wof:placetype":"venue"
},
  "geometry": {"coordinates":[-73.687231,40.66417],"type":"Point"}
}