{
  "type": "Feature",
  "properties": {
    "iso:country":"US",
    "sg:address":"80 Water St",
    "sg:city":"Jamestown",
    "sg:classifiers":[
        {
            "category":"Retail",
            "subcategory":"Auto Repair",
            "type":"Services"
        }
    ],
    "sg:phone":"+1   ",
    "sg:postcode":"14701",
    "sg:province":"NY",
    "sg:tags":[
        "automotive",
        "general"
    ],
    "wof:name":"Buteras Towing",
    "wof:placetype":"venue"
},
  "geometry": {"coordinates":[-79.232589,42.092496],"type":"Point"}
}