{
  "type": "Feature",
  "properties": {
    "iso:country":"US",
    "sg:address":"869 Rte 109",
    "sg:city":"West Babylon",
    "sg:classifiers":[
        {
            "category":"Autos & Motor Vehicles",
            "subcategory":"Automobile Sales",
            "type":"Retail Goods"
        }
    ],
    "sg:phone":"+1 631 226 6777",
    "sg:postcode":"11704",
    "sg:province":"NY",
    "sg:tags":[
        "car",
        "dealer"
    ],
    "wof:name":"Romeo's Auto Sales Inc",
    "wof:placetype":"venue"
},
  "geometry": {"coordinates":[-73.389202,40.715227],"type":"Point"}
}