{
  "type": "Feature",
  "properties": {
    "addr:full":"766 E 93rd St Brooklyn NY 11236",
    "addr:housenumber":"766",
    "addr:postcode":"11236",
    "addr:street":"E 93Rd St",
    "iso:country":"US",
    "sg:address":"766 E 93rd St",
    "sg:city":"Brooklyn",
    "sg:classifiers":[
        {
            "category":"Shopping",
            "subcategory":"Computers & Home Electronics",
            "type":"Retail Goods"
        },
        {
            "category":"Communications",
            "subcategory":"Television Station",
            "type":"Services"
        }
    ],
    "sg:phone":"+1 718 346 1200",
    "sg:postcode":"11236",
    "sg:province":"NY",
    "sg:tags":[
        "satellite",
        "antenna",
        "cable",
        "tv",
        "system",
        "equipment",
        "consumer"
    ],
    "wof:name":"All Systems Satellite Distributors Of Virginia, Inc.",
    "wof:placetype":"venue"
},
  "geometry": {"coordinates":[-73.91252900000001,40.649529],"type":"Point"}
}