{
  "type": "Feature",
  "properties": {
    "iso:country":"US",
    "sg:address":"7 N Erie St",
    "sg:city":"Mayville",
    "sg:classifiers":[
        {
            "category":"Social Services",
            "type":"Services"
        }
    ],
    "sg:phone":"+1 716 753 4395",
    "sg:postcode":"14757",
    "sg:province":"NY",
    "wof:name":"Child Support Collection Unit",
    "wof:placetype":"venue"
},
  "geometry": {"coordinates":[-79.506484,42.255281],"type":"Point"}
}