{
  "type": "Feature",
  "properties": {
    "addr:full":"69 E Pine St Gloversville NY 12078",
    "addr:housenumber":"69",
    "addr:postcode":"12078",
    "addr:street":"E Pine St",
    "iso:country":"US",
    "sg:address":"69 E Pine St",
    "sg:city":"Gloversville",
    "sg:classifiers":[
        {
            "category":"Communications",
            "subcategory":"Film & Video Production",
            "type":"Services"
        }
    ],
    "sg:phone":"+1 518 773 3337",
    "sg:postcode":"12078",
    "sg:province":"NY",
    "sg:tags":[
        "taping"
    ],
    "wof:name":"Jeremy Walsh Videography",
    "wof:placetype":"venue"
},
  "geometry": {"coordinates":[-74.34425899999999,43.044726],"type":"Point"}
}