{
  "type": "Feature",
  "properties": {
    "addr:full":"401 Mill St Rome NY 13440",
    "addr:housenumber":"401",
    "addr:postcode":"13440",
    "addr:street":"Mill St",
    "iso:country":"US",
    "sg:address":"401 Mill St",
    "sg:city":"Rome",
    "sg:classifiers":[
        {
            "category":"Manufacturing",
            "subcategory":"Tools & Machinery",
            "type":"Manufacturing & Wholesale Goods"
        }
    ],
    "sg:phone":"+1 315 337 7840",
    "sg:postcode":"13440",
    "sg:province":"NY",
    "sg:tags":[
        "mold",
        "special"
    ],
    "wof:name":"Hubbard Tool & Die Co",
    "wof:placetype":"venue"
},
  "geometry": {"coordinates":[-75.44926700000001,43.204273],"type":"Point"}
}