{
  "type": "Feature",
  "properties": {
    "addr:full":"16 W 45th St Fl 2 New York NY 10036",
    "addr:housenumber":"16;2",
    "addr:postcode":"10036",
    "addr:street":"W 45Th St",
    "iso:country":"US",
    "sg:address":"16 W 45th St Fl 2",
    "sg:city":"New York",
    "sg:classifiers":[
        {
            "category":"Banks & Credit Unions",
            "subcategory":"Investment Brokerage",
            "type":"Services"
        }
    ],
    "sg:phone":"+1 212 382 3240",
    "sg:postcode":"10036",
    "sg:province":"NY",
    "sg:tags":[
        "investing"
    ],
    "wof:name":"GDR Privee",
    "wof:placetype":"venue"
},
  "geometry": {"coordinates":[-73.980602,40.75563],"type":"Point"}
}