{
  "type": "Feature",
  "properties": {
    "iso:country":"US",
    "sg:address":"599 3rd Ave Exd",
    "sg:city":"Rensselaer",
    "sg:classifiers":[
        {
            "category":"Autos & Motor Vehicles",
            "subcategory":"Automobile Sales",
            "type":"Retail Goods"
        }
    ],
    "sg:phone":"+1 518 283 1108",
    "sg:postcode":"12144",
    "sg:province":"NY",
    "sg:tags":[
        "car",
        "dealer"
    ],
    "wof:name":"World Class Motors",
    "wof:placetype":"venue"
},
  "geometry": {"coordinates":[-73.700288,42.644231],"type":"Point"}
}