{
  "type": "Feature",
  "properties": {
    "addr:full":"4017 State St Schenectady NY 12304",
    "addr:housenumber":"4017",
    "addr:postcode":"12304",
    "addr:street":"State St",
    "iso:country":"US",
    "sg:address":"4017 State St",
    "sg:city":"Schenectady",
    "sg:classifiers":[
        {
            "category":"Sports & Exercise",
            "subcategory":"Gym",
            "type":"Entertainment"
        }
    ],
    "sg:phone":"+1 518 377 9337",
    "sg:postcode":"12304",
    "sg:province":"NY",
    "sg:tags":[
        "club",
        "health",
        "studio",
        "gymnasium"
    ],
    "wof:name":"Curves",
    "wof:placetype":"venue"
},
  "geometry": {"coordinates":[-73.88777899999999,42.766053],"type":"Point"}
}