{
  "type": "Feature",
  "properties": {
    "addr:full":"38 W Main St Tarrytown NY 10591",
    "addr:housenumber":"38",
    "addr:postcode":"10591",
    "addr:street":"W Main St",
    "iso:country":"US",
    "sg:address":"38 W Main St",
    "sg:city":"Tarrytown",
    "sg:classifiers":[
        {
            "category":"Shopping",
            "subcategory":"Used Merchandise",
            "type":"Retail Goods"
        }
    ],
    "sg:phone":"+1 914 631 3368",
    "sg:postcode":"10591",
    "sg:province":"NY",
    "sg:tags":[
        "antique"
    ],
    "wof:name":"Pretty Funny",
    "wof:placetype":"venue"
},
  "geometry": {"coordinates":[-73.85948,41.076417],"type":"Point"}
}