{
  "type": "Feature",
  "properties": {
    "iso:country":"US",
    "sg:address":"95 Old Country Rd",
    "sg:city":"Carle Place",
    "sg:classifiers":[
        {
            "category":"Shopping",
            "subcategory":"Pharmacy",
            "type":"Retail Goods"
        }
    ],
    "sg:phone":"+1 516 739 1978",
    "sg:postcode":"11514",
    "sg:province":"NY",
    "sg:tags":[
        "drugstore"
    ],
    "sg:website":"www.stopandshop.com",
    "wof:name":"Stop&Shop Pharmacy",
    "wof:placetype":"venue"
},
  "geometry": {"coordinates":[-73.61992600000001,40.742627],"type":"Point"}
}