{
  "type": "Feature",
  "properties": {
    "addr:full":"1300 Niagara St Buffalo NY 14213",
    "addr:housenumber":"1300",
    "addr:postcode":"14213",
    "addr:street":"Niagara St",
    "iso:country":"US",
    "sg:address":"1300 Niagara St",
    "sg:city":"Buffalo",
    "sg:classifiers":[
        {
            "category":"Professional",
            "subcategory":"Employment Agencies",
            "type":"Services"
        }
    ],
    "sg:phone":"+1 716 838 4261",
    "sg:postcode":"14213",
    "sg:province":"NY",
    "sg:website":"www.durhamstaffing.com",
    "wof:name":"Durham Staffing Inc",
    "wof:placetype":"venue"
},
  "geometry": {"coordinates":[-78.899089,42.919441],"type":"Point"}
}