{
  "type": "Feature",
  "properties": {
    "addr:full":"1672 Victory Blvd Staten Island NY 10314",
    "addr:housenumber":"1672",
    "addr:postcode":"10314",
    "addr:street":"Victory Blvd",
    "iso:country":"US",
    "sg:address":"1672 Victory Blvd",
    "sg:city":"Staten Island",
    "sg:classifiers":[
        {
            "category":"Professional",
            "subcategory":"Employment Agencies",
            "type":"Services"
        }
    ],
    "sg:phone":"+1 718 720 7242",
    "sg:postcode":"10314",
    "sg:province":"NY",
    "wof:name":"RN Staffing Solutions LLC",
    "wof:placetype":"venue"
},
  "geometry": {"coordinates":[-74.119789,40.613154],"type":"Point"}
}