{
  "type": "Feature",
  "properties": {
    "addr:full":"7303 Yellowstone Boulevard Forest Hills NY 11375",
    "addr:housenumber":"7303",
    "addr:postcode":"11375",
    "addr:street":"Yellowstone Boulevard",
    "iso:country":"US",
    "sg:address":"7303 Yellowstone Boulevard",
    "sg:city":"Forest Hills",
    "sg:classifiers":[
        {
            "category":"Restaurant",
            "type":"Food & Drink"
        }
    ],
    "sg:phone":"+1 718 268 8899",
    "sg:postcode":"11375",
    "sg:province":"NY",
    "wof:name":"Panda Restaurant",
    "wof:placetype":"venue"
},
  "geometry": {"coordinates":[-73.856922,40.71754],"type":"Point"}
}