{
  "type": "Feature",
  "properties": {
    "addr:full":"83 Marlborough Rd Brooklyn NY 11226",
    "addr:housenumber":"83",
    "addr:postcode":"11226",
    "addr:street":"Marlborough Rd",
    "iso:country":"US",
    "sg:address":"83 Marlborough Rd",
    "sg:city":"Brooklyn",
    "sg:classifiers":[
        {
            "category":"Education",
            "subcategory":"School",
            "type":"Public Place"
        }
    ],
    "sg:phone":"+1 718 284 3110",
    "sg:postcode":"11226",
    "sg:province":"NY",
    "wof:name":"The Children's Center For Early Learning Inc",
    "wof:placetype":"venue"
},
  "geometry": {"coordinates":[-73.96530199999999,40.646801],"type":"Point"}
}