{
  "type": "Feature",
  "properties": {
    "addr:full":"3511 Queens Boulevard Long Island City NY 11101",
    "addr:housenumber":"3511",
    "addr:postcode":"11101",
    "addr:street":"Queens Boulevard",
    "iso:country":"US",
    "sg:address":"3511 Queens Boulevard",
    "sg:city":"Long Island City",
    "sg:classifiers":[
        {
            "category":"Professional",
            "subcategory":"Computer Services",
            "type":"Services"
        }
    ],
    "sg:phone":"+1 718 729 9800",
    "sg:postcode":"11101",
    "sg:province":"NY",
    "sg:tags":[
        "stereo",
        "installation"
    ],
    "wof:name":"Sound City Auto",
    "wof:placetype":"venue"
},
  "geometry": {"coordinates":[-73.929785,40.744602],"type":"Point"}
}