{
  "type": "Feature",
  "properties": {
    "iso:country":"US",
    "sg:address":"3310 State Hwy 352",
    "sg:city":"Corning",
    "sg:classifiers":[
        {
            "category":"Wholesale",
            "subcategory":"Construction Materials",
            "type":"Manufacturing & Wholesale Goods"
        }
    ],
    "sg:phone":"+1 607 562 5347",
    "sg:postcode":"14814",
    "sg:province":"NY",
    "sg:tags":[
        "sand",
        "gravel"
    ],
    "sg:website":"www.portersconcrete.com",
    "wof:name":"Porters Concrete Svc",
    "wof:placetype":"venue"
},
  "geometry": {"coordinates":[-76.958326,42.129537],"type":"Point"}
}