{
  "type": "Feature",
  "properties": {
    "addr:full":"3417 Steinway St Astoria NY 11105",
    "addr:housenumber":"3417",
    "addr:postcode":"11105",
    "addr:street":"Steinway St",
    "iso:country":"US",
    "sg:address":"3417 Steinway St",
    "sg:city":"Astoria",
    "sg:classifiers":[
        {
            "category":"Shopping",
            "subcategory":"Bridal",
            "type":"Retail Goods"
        }
    ],
    "sg:phone":"+1 718 433 4171",
    "sg:postcode":"11105",
    "sg:province":"NY",
    "wof:name":"Yours Only Bridal",
    "wof:placetype":"venue"
},
  "geometry": {"coordinates":[-73.921255,40.756171],"type":"Point"}
}