{
  "type": "Feature",
  "properties": {
    "iso:country":"US",
    "sg:address":"2035 Lakeville Rd",
    "sg:city":"New Hyde Park",
    "sg:classifiers":[
        {
            "category":"Health Services",
            "subcategory":"Doctor",
            "type":"Services"
        }
    ],
    "sg:phone":"+1 516 437 1633",
    "sg:postcode":"11040",
    "sg:province":"NY",
    "sg:tags":[
        "dentist"
    ],
    "wof:name":"Nassau Queens Endodontics",
    "wof:placetype":"venue"
},
  "geometry": {"coordinates":[-73.700716,40.75159],"type":"Point"}
}