{
  "type": "Feature",
  "properties": {
    "iso:country":"US",
    "sg:address":"816 Hicksville Rd",
    "sg:city":"Massapequa",
    "sg:classifiers":[
        {
            "category":"Shopping",
            "subcategory":"Clothing, Apparel, & Fashions",
            "type":"Retail Goods"
        }
    ],
    "sg:phone":"+1   ",
    "sg:postcode":"11758",
    "sg:province":"NY",
    "sg:tags":[
        "store"
    ],
    "wof:name":"Mandee",
    "wof:placetype":"venue"
},
  "geometry": {"coordinates":[-73.477457,40.690491],"type":"Point"}
}