{
  "type": "Feature",
  "properties": {
    "iso:country":"US",
    "sg:address":"405 Court St",
    "sg:city":"Binghamton",
    "sg:classifiers":[
        {
            "category":"Retail",
            "subcategory":"Auto Repair",
            "type":"Services"
        }
    ],
    "sg:phone":"+1 607 772 9057",
    "sg:postcode":"13904",
    "sg:province":"NY",
    "sg:tags":[
        "repairing",
        "automobile"
    ],
    "wof:name":"Marv's Auto Repair Shop",
    "wof:placetype":"venue"
},
  "geometry": {"coordinates":[-75.88388399999999,42.104393],"type":"Point"}
}