{
  "type": "Feature",
  "properties": {
    "addr:full":"57 W 57 St New York NY 10019",
    "addr:housenumber":"57",
    "addr:postcode":"10019",
    "addr:street":"W 57 St",
    "iso:country":"US",
    "sg:address":"57 W 57 St",
    "sg:city":"New York",
    "sg:classifiers":[
        {
            "category":"Health Services",
            "subcategory":"Medical Lab",
            "type":"Services"
        }
    ],
    "sg:phone":"+1 212 751 5338",
    "sg:postcode":"10019",
    "sg:province":"NY",
    "sg:tags":[
        "laboratory"
    ],
    "wof:name":"Ghighi Dental Studio Inc",
    "wof:placetype":"venue"
},
  "geometry": {"coordinates":[-73.975762,40.763613],"type":"Point"}
}