{
  "type": "Feature",
  "properties": {
    "iso:country":"US",
    "sg:address":"501 East 75th Street",
    "sg:city":"New York",
    "sg:classifiers":[
        {
            "category":"Coffee & Tea",
            "type":"Food & Drink"
        }
    ],
    "sg:postcode":"10021",
    "sg:province":"NY",
    "sg:website":"www.salontea.com",
    "wof:name":"Tracy Stern Salontea Teabar",
    "wof:placetype":"venue"
},
  "geometry": {"coordinates":[-73.952298,40.768801],"type":"Point"}
}