{
  "type": "Feature",
  "properties": {
    "addr:full":"350 Broadway Rm 309 New York NY 10013",
    "addr:housenumber":"350;309",
    "addr:postcode":"10013",
    "addr:street":"Broadway Rm",
    "iso:country":"US",
    "sg:address":"350 Broadway Rm 309",
    "sg:city":"New York",
    "sg:classifiers":[
        {
            "category":"Professional",
            "subcategory":"Lawyer & Legal Services",
            "type":"Services"
        }
    ],
    "sg:phone":"+1 212 226 5700",
    "sg:postcode":"10013",
    "sg:province":"NY",
    "wof:name":"Fisher Robert M Lwyr",
    "wof:placetype":"venue"
},
  "geometry": {"coordinates":[-74.003899,40.7169],"type":"Point"}
}