{
  "type": "Feature",
  "properties": {
    "addr:full":"577 Burnside Ave Inwood NY 11096",
    "addr:housenumber":"577",
    "addr:postcode":"11096",
    "addr:street":"Burnside Ave",
    "iso:country":"US",
    "sg:address":"577 Burnside Ave",
    "sg:city":"Inwood",
    "sg:classifiers":[
        {
            "category":"Social Services",
            "type":"Services"
        }
    ],
    "sg:phone":"+1 516 371 0500",
    "sg:postcode":"11096",
    "sg:province":"NY",
    "sg:tags":[
        "youth",
        "organization",
        "center"
    ],
    "wof:name":"D & A Cellular",
    "wof:placetype":"venue"
},
  "geometry": {"coordinates":[-73.742408,40.622895],"type":"Point"}
}