{
  "type": "Feature",
  "properties": {
    "addr:full":"134 W 29th St New York NY 10001",
    "addr:housenumber":"134",
    "addr:postcode":"10001",
    "addr:street":"W 29Th St",
    "iso:country":"US",
    "sg:address":"134 W 29th St",
    "sg:city":"New York",
    "sg:classifiers":[
        {
            "category":"Wholesale",
            "subcategory":"Apparel",
            "type":"Manufacturing & Wholesale Goods"
        }
    ],
    "sg:phone":"+1 212 695 6684",
    "sg:postcode":"10001",
    "sg:province":"NY",
    "sg:tags":[
        "clothing"
    ],
    "wof:name":"Neelam Fashions Inc",
    "wof:placetype":"venue"
},
  "geometry": {"coordinates":[-73.992199,40.747374],"type":"Point"}
}