{
  "type": "Feature",
  "properties": {
    "addr:full":"221 Meadowbrook Duanesburg NY 12056",
    "addr:housenumber":"221",
    "addr:postcode":"12056",
    "addr:street":"Meadowbrook Duanesburg",
    "iso:country":"US",
    "sg:address":"221 Meadowbrook",
    "sg:city":"Duanesburg",
    "sg:classifiers":[
        {
            "category":"Building & Trades",
            "subcategory":"Construction",
            "type":"Services"
        }
    ],
    "sg:phone":"+1 518 356 3976",
    "sg:postcode":"12056",
    "sg:province":"NY",
    "sg:tags":[
        "new",
        "home"
    ],
    "wof:name":"Viscusi Builders Ltd",
    "wof:placetype":"venue"
},
  "geometry": {"coordinates":[-74.041281,42.767538],"type":"Point"}
}