{
  "type": "Feature",
  "properties": {
    "addr:full":"31 W 47 St New York NY 10036",
    "addr:housenumber":"31",
    "addr:postcode":"10036",
    "addr:street":"W 47 St",
    "iso:country":"US",
    "sg:address":"31 W 47 St",
    "sg:city":"New York",
    "sg:classifiers":[
        {
            "category":"Restaurant",
            "type":"Food & Drink"
        }
    ],
    "sg:phone":"+1 212 395 0745",
    "sg:postcode":"10036",
    "sg:province":"NY",
    "wof:name":"4 Jays Cafe",
    "wof:placetype":"venue"
},
  "geometry": {"coordinates":[-73.981009,40.757668],"type":"Point"}
}