{
  "type": "Feature",
  "properties": {
    "iso:country":"US",
    "sg:address":"4012 104th St",
    "sg:city":"Corona",
    "sg:classifiers":[
        {
            "category":"Restaurant",
            "type":"Food & Drink"
        }
    ],
    "sg:phone":"+1 718 205 8683",
    "sg:postcode":"11368",
    "sg:province":"NY",
    "sg:tags":[
        "greek"
    ],
    "wof:name":"Corona Gyro Inc",
    "wof:placetype":"venue"
},
  "geometry": {"coordinates":[-73.861571,40.749247],"type":"Point"}
}