{
  "type": "Feature",
  "properties": {
    "addr:full":"2209 Avenue M Brooklyn NY 11210",
    "addr:housenumber":"2209",
    "addr:postcode":"11210",
    "addr:street":"Avenue M",
    "iso:country":"US",
    "sg:address":"2209 Avenue M",
    "sg:city":"Brooklyn",
    "sg:classifiers":[
        {
            "category":"Real Estate",
            "subcategory":"Real Estate Services",
            "type":"Services"
        }
    ],
    "sg:phone":"+1 718 421 6900",
    "sg:postcode":"11210",
    "sg:province":"NY",
    "sg:tags":[
        "management",
        "property"
    ],
    "wof:name":"Sova Management LLC",
    "wof:placetype":"venue"
},
  "geometry": {"coordinates":[-73.95300400000001,40.618914],"type":"Point"}
}