{
  "type": "Feature",
  "properties": {
    "iso:country":"US",
    "sg:address":"67 Scudder Ave",
    "sg:city":"Copiague",
    "sg:classifiers":[
        {
            "category":"Organizations",
            "subcategory":"Religious Organization",
            "type":"Services"
        }
    ],
    "sg:phone":"+1 631 842 5846",
    "sg:postcode":"11726",
    "sg:province":"NY",
    "wof:name":"Covenant Christian Fellowship",
    "wof:placetype":"venue"
},
  "geometry": {"coordinates":[-73.39384800000001,40.678355],"type":"Point"}
}