{
  "type": "Feature",
  "properties": {
    "iso:country":"US",
    "sg:address":"3600 White Plains Rd",
    "sg:city":"Bronx",
    "sg:classifiers":[
        {
            "category":"Food & Beverages",
            "subcategory":"Meat & Fish",
            "type":"Retail Goods"
        }
    ],
    "sg:phone":"+1 718 994 2628",
    "sg:postcode":"10467",
    "sg:province":"NY",
    "wof:name":"Fante Meat Market Inc",
    "wof:placetype":"venue"
},
  "geometry": {"coordinates":[-73.86492,40.879793],"type":"Point"}
}