{
  "type": "Feature",
  "properties": {
    "iso:country":"US",
    "sg:address":"65 Leroy St",
    "sg:city":"Binghamton",
    "sg:classifiers":[
        {
            "category":"Retail",
            "subcategory":"Portrait Studio",
            "type":"Services"
        }
    ],
    "sg:phone":"+1 607 723 0237",
    "sg:postcode":"13905",
    "sg:province":"NY",
    "sg:tags":[
        "photographer"
    ],
    "wof:name":"Eastman Portrait Studio",
    "wof:placetype":"venue"
},
  "geometry": {"coordinates":[-75.926715,42.095734],"type":"Point"}
}