{
  "type": "Feature",
  "properties": {
    "addr:full":"73 E Lovell St Mahopac NY 10541",
    "addr:housenumber":"73",
    "addr:postcode":"10541",
    "addr:street":"E Lovell St",
    "iso:country":"US",
    "sg:address":"73 E Lovell St",
    "sg:city":"Mahopac",
    "sg:classifiers":[
        {
            "category":"Building & Trades",
            "subcategory":"Construction",
            "type":"Services"
        }
    ],
    "sg:phone":"+1 845 628 0510",
    "sg:postcode":"10541",
    "sg:province":"NY",
    "sg:tags":[
        "house"
    ],
    "wof:name":"Fierro General Cont Corp",
    "wof:placetype":"venue"
},
  "geometry": {"coordinates":[-73.718057,41.350204],"type":"Point"}
}