{
  "type": "Feature",
  "properties": {
    "iso:country":"US",
    "sg:address":"18675 US Hwy 11",
    "sg:city":"Watertown",
    "sg:classifiers":[
        {
            "category":"Autos & Motor Vehicles",
            "subcategory":"Automobile Sales",
            "type":"Retail Goods"
        }
    ],
    "sg:phone":"+1 315 788 8012",
    "sg:postcode":"13601",
    "sg:province":"NY",
    "sg:tags":[
        "car",
        "dealer"
    ],
    "wof:name":"Saturn",
    "wof:placetype":"venue"
},
  "geometry": {"coordinates":[-75.923711,43.938546],"type":"Point"}
}