{
  "type": "Feature",
  "properties": {
    "addr:full":"60 12th St Brooklyn NY 11215",
    "addr:housenumber":"60",
    "addr:postcode":"11215",
    "addr:street":"12Th St",
    "iso:country":"US",
    "sg:address":"60 12th St",
    "sg:city":"Brooklyn",
    "sg:classifiers":[
        {
            "category":"Home & Garden",
            "subcategory":"Building Materials",
            "type":"Retail Goods"
        },
        {
            "category":"Building & Trades",
            "subcategory":"Construction",
            "type":"Services"
        }
    ],
    "sg:phone":"+1 718 788 8118",
    "sg:postcode":"11215",
    "sg:province":"NY",
    "sg:tags":[
        "bathroom",
        "top",
        "counter",
        "cabinet",
        "planning",
        "fixtures",
        "accessory",
        "remodeling",
        "kitchen"
    ],
    "wof:name":"Sun Global Group Inc",
    "wof:placetype":"venue"
},
  "geometry": {"coordinates":[-73.995925,40.671271],"type":"Point"}
}