{
  "type": "Feature",
  "properties": {
    "addr:full":"1573 Bergen St Brooklyn NY 11213",
    "addr:housenumber":"1573",
    "addr:postcode":"11213",
    "addr:street":"Bergen St",
    "iso:country":"US",
    "sg:address":"1573 Bergen St",
    "sg:city":"Brooklyn",
    "sg:classifiers":[
        {
            "category":"Arts & Performance",
            "subcategory":"Theater",
            "type":"Entertainment"
        }
    ],
    "sg:phone":"+1 718 789 5316",
    "sg:postcode":"11213",
    "sg:province":"NY",
    "sg:tags":[
        "bureau",
        "tapes-sound-dealers"
    ],
    "wof:name":"King Pin Entertainment, Inc.",
    "wof:placetype":"venue"
},
  "geometry": {"coordinates":[-73.931282,40.675079],"type":"Point"}
}