{
  "type": "Feature",
  "properties": {
    "addr:full":"75 S Liberty Dr Stony Point NY 10980",
    "addr:housenumber":"75",
    "addr:postcode":"10980",
    "addr:street":"S Liberty Dr",
    "iso:country":"US",
    "sg:address":"75 S Liberty Dr",
    "sg:city":"Stony Point",
    "sg:classifiers":[
        {
            "category":"Restaurant",
            "type":"Food & Drink"
        }
    ],
    "sg:phone":"+1 845 786 7635",
    "sg:postcode":"10980",
    "sg:province":"NY",
    "sg:tags":[
        "delicatessen"
    ],
    "wof:name":"B's Nest Deli",
    "wof:placetype":"venue"
},
  "geometry": {"coordinates":[-73.98446800000001,41.222983],"type":"Point"}
}