{
  "type": "Feature",
  "properties": {
    "addr:full":"145 W 57th Street New York NY 10019",
    "addr:housenumber":"145",
    "addr:postcode":"10019",
    "addr:street":"W 57Th Street",
    "iso:country":"US",
    "sg:address":"145 W 57th Street",
    "sg:city":"New York",
    "sg:classifiers":[
        {
            "category":"Health Services",
            "subcategory":"Doctor",
            "type":"Services"
        }
    ],
    "sg:phone":"+1 212 977 8787",
    "sg:postcode":"10019",
    "sg:province":"NY",
    "wof:name":"Park Sonada MD",
    "wof:placetype":"venue"
},
  "geometry": {"coordinates":[-73.978466,40.764881],"type":"Point"}
}