{
  "type": "Feature",
  "properties": {
    "addr:full":"100 Inip Dr Inwood NY 11096",
    "addr:housenumber":"100",
    "addr:postcode":"11096",
    "addr:street":"Inip Dr",
    "iso:country":"US",
    "sg:address":"100 Inip Dr",
    "sg:city":"Inwood",
    "sg:classifiers":[
        {
            "category":"Wholesale",
            "subcategory":"Apparel",
            "type":"Manufacturing & Wholesale Goods"
        },
        {
            "category":"Freight",
            "type":"Transportation"
        }
    ],
    "sg:phone":"+1 516 239 8111",
    "sg:postcode":"11096",
    "sg:province":"NY",
    "sg:tags":[
        "clothing",
        "general"
    ],
    "sg:website":"www.benelias.com",
    "wof:name":"Ben Elias Industries Corp",
    "wof:placetype":"venue"
},
  "geometry": {"coordinates":[-73.747619,40.626901],"type":"Point"}
}