{
  "type": "Feature",
  "properties": {
    "addr:full":"241 W 30 St New York NY 10001",
    "addr:housenumber":"241",
    "addr:postcode":"10001",
    "addr:street":"W 30 St",
    "iso:country":"US",
    "sg:address":"241 W 30 St",
    "sg:city":"New York",
    "sg:classifiers":[
        {
            "category":"Building & Trades",
            "subcategory":"Electrical",
            "type":"Services"
        },
        {
            "category":"Professional",
            "subcategory":"Business Services",
            "type":"Services"
        }
    ],
    "sg:phone":"+1 212 643 0300",
    "sg:postcode":"10001",
    "sg:province":"NY",
    "sg:tags":[
        "installation",
        "answering",
        "datum",
        "telephone",
        "long",
        "sales",
        "paging"
    ],
    "sg:website":"www.eratel.com",
    "wof:name":"ERA Telecommunications Inc",
    "wof:placetype":"venue"
},
  "geometry": {"coordinates":[-73.99438499999999,40.749246],"type":"Point"}
}