{
  "type": "Feature",
  "properties": {
    "addr:full":"114 W 47th Street 24th Floor New York NY 10036",
    "addr:housenumber":"114;24th floor",
    "addr:postcode":"10036",
    "addr:street":"W 47Th Street",
    "iso:country":"US",
    "sg:address":"114 W 47th Street 24th Floor",
    "sg:city":"New York",
    "sg:classifiers":[
        {
            "category":"Professional",
            "subcategory":"Management & Consulting",
            "type":"Services"
        }
    ],
    "sg:postcode":"10036",
    "sg:province":"NY",
    "sg:website":"http://www.medialinkllc.com/",
    "wof:name":"MediaLink",
    "wof:placetype":"venue"
},
  "geometry": {"coordinates":[-73.98436599999999,40.758972],"type":"Point"}
}