{
  "type": "Feature",
  "properties": {
    "addr:full":"545 Madison Ave New York NY 10022",
    "addr:housenumber":"545",
    "addr:postcode":"10022",
    "addr:street":"Madison Ave",
    "iso:country":"US",
    "sg:address":"545 Madison Ave",
    "sg:city":"New York",
    "sg:classifiers":[
        {
            "category":"Banks & Credit Unions",
            "subcategory":"Investment Brokerage",
            "type":"Services"
        }
    ],
    "sg:phone":"+1 212 980 5230",
    "sg:postcode":"10022",
    "sg:province":"NY",
    "sg:tags":[
        "counselor"
    ],
    "wof:name":"Inverness Counsel (de Corp)",
    "wof:placetype":"venue"
},
  "geometry": {"coordinates":[-73.97350299999999,40.760483],"type":"Point"}
}