{
  "type": "Feature",
  "properties": {
    "addr:full":"63745 Route 25 Southold NY 11971",
    "addr:housenumber":"63745",
    "addr:postcode":"11971",
    "addr:street":"Route 25",
    "iso:country":"US",
    "sg:address":"63745 Route 25",
    "sg:city":"Southold",
    "sg:classifiers":[
        {
            "category":"Building & Trades",
            "subcategory":"Landscaping Services",
            "type":"Services"
        }
    ],
    "sg:phone":"+1 631 765 1963",
    "sg:postcode":"11971",
    "sg:province":"NY",
    "sg:tags":[
        "tree"
    ],
    "wof:name":"Island Tree Co",
    "wof:placetype":"venue"
},
  "geometry": {"coordinates":[-72.398133,41.078633],"type":"Point"}
}