{
  "type": "Feature",
  "properties": {
    "addr:full":"1353 Newbridge Rd North Bellmore NY 11710",
    "addr:housenumber":"1353",
    "addr:postcode":"11710",
    "addr:street":"Newbridge Rd",
    "iso:country":"US",
    "sg:address":"1353 Newbridge Rd",
    "sg:city":"North Bellmore",
    "sg:classifiers":[
        {
            "category":"Retail",
            "subcategory":"Auto Repair",
            "type":"Services"
        }
    ],
    "sg:phone":"+1 516 781 0487",
    "sg:postcode":"11710",
    "sg:province":"NY",
    "sg:tags":[
        "body",
        "shop"
    ],
    "wof:name":"Newbridge Auto Body Inc",
    "wof:placetype":"venue"
},
  "geometry": {"coordinates":[-73.5411,40.686798],"type":"Point"}
}