{
  "type": "Feature",
  "properties": {
    "addr:full":"296 E Main St Patchogue NY 11772",
    "addr:housenumber":"296",
    "addr:postcode":"11772",
    "addr:street":"E Main St",
    "iso:country":"US",
    "sg:address":"296 E Main St",
    "sg:city":"Patchogue",
    "sg:classifiers":[
        {
            "category":"Professional",
            "subcategory":"Accounting & Tax Preparation",
            "type":"Services"
        }
    ],
    "sg:phone":"+1   ",
    "sg:postcode":"11772",
    "sg:province":"NY",
    "sg:tags":[
        "return"
    ],
    "wof:name":"International Taxes",
    "wof:placetype":"venue"
},
  "geometry": {"coordinates":[-73.00916599999999,40.765786],"type":"Point"}
}