{
  "type": "Feature",
  "properties": {
    "addr:full":"19 Center St Palatine Bridge NY 13452",
    "addr:housenumber":"19",
    "addr:postcode":"13452",
    "addr:street":"Center St",
    "iso:country":"US",
    "sg:address":"19 Center St",
    "sg:city":"Palatine Bridge",
    "sg:classifiers":[
        {
            "category":"Building & Trades",
            "subcategory":"Construction",
            "type":"Services"
        }
    ],
    "sg:phone":"+1 518 673 2281",
    "sg:postcode":"13452",
    "sg:province":"NY",
    "sg:tags":[
        "home",
        "improvement"
    ],
    "wof:name":"Casler Construction Co",
    "wof:placetype":"venue"
},
  "geometry": {"coordinates":[-74.575086,42.913371],"type":"Point"}
}