{
  "type": "Feature",
  "properties": {
    "iso:country":"US",
    "sg:address":"19 Broad St Ste 24",
    "sg:city":"Waterford",
    "sg:classifiers":[
        {
            "category":"Wholesale",
            "subcategory":"Groceries",
            "type":"Manufacturing & Wholesale Goods"
        }
    ],
    "sg:phone":"+1 518 961 2552",
    "sg:postcode":"12188",
    "sg:province":"NY",
    "sg:tags":[
        "food",
        "products-wholesale"
    ],
    "sg:website":"http://www.hudson-neva.com",
    "wof:name":"Gustav Karlsson Co Inc",
    "wof:placetype":"venue"
},
  "geometry": {"coordinates":[-73.676765,42.789644],"type":"Point"}
}