{
  "type": "Feature",
  "properties": {
    "iso:country":"US",
    "sg:address":"140 Eastern Blvd",
    "sg:city":"Canandaigua",
    "sg:classifiers":[
        {
            "category":"Fast Food",
            "type":"Food & Drink"
        },
        {
            "category":"Restaurant",
            "type":"Food & Drink"
        },
        {
            "category":"Food & Beverages",
            "subcategory":"Groceries & Convenience Stores",
            "type":"Retail Goods"
        }
    ],
    "sg:phone":"+1 585 396 9356",
    "sg:postcode":"14424",
    "sg:province":"NY",
    "sg:tags":[
        "shop",
        "american",
        "sandwich"
    ],
    "sg:website":"http://www.arbys.com",
    "wof:name":"Arby's",
    "wof:placetype":"venue"
},
  "geometry": {"coordinates":[-77.26363000000001,42.8784],"type":"Point"}
}