{
  "type": "Feature",
  "properties": {
    "iso:country":"US",
    "sg:address":"6590 Cayuga Lake Rd",
    "sg:city":"Ovid",
    "sg:classifiers":[
        {
            "category":"Travel",
            "subcategory":"Campground",
            "type":"Entertainment"
        }
    ],
    "sg:phone":"+1 607 869 9787",
    "sg:postcode":"14521",
    "sg:province":"NY",
    "wof:name":"Sned-Acres Family Campground",
    "wof:placetype":"venue"
},
  "geometry": {"coordinates":[-76.75811899999999,42.707206],"type":"Point"}
}