{
  "type": "Feature",
  "properties": {
    "iso:country":"US",
    "sg:address":"16 Provost Dr",
    "sg:city":"Suffern",
    "sg:classifiers":[
        {
            "category":"Building & Trades",
            "subcategory":"Landscaping Services",
            "type":"Services"
        }
    ],
    "sg:phone":"+1 845 369 1909",
    "sg:postcode":"10901",
    "sg:province":"NY",
    "wof:name":"Coloritos Lawn Care",
    "wof:placetype":"venue"
},
  "geometry": {"coordinates":[-74.12184600000001,41.101475],"type":"Point"}
}