{
  "type": "Feature",
  "properties": {
    "addr:full":"7 Meadow Ave W Bronxville NY 10708",
    "addr:housenumber":"7",
    "addr:postcode":"10708",
    "addr:street":"Meadow Ave W",
    "iso:country":"US",
    "sg:address":"7 Meadow Ave W",
    "sg:city":"Bronxville",
    "sg:classifiers":[
        {
            "category":"Building & Trades",
            "subcategory":"Construction",
            "type":"Services"
        }
    ],
    "sg:phone":"+1 914 961 6470",
    "sg:postcode":"10708",
    "sg:province":"NY",
    "sg:tags":[
        "specializing",
        "residential",
        "general",
        "contractor"
    ],
    "wof:name":"Westchester Construction II",
    "wof:placetype":"venue"
},
  "geometry": {"coordinates":[-73.84614999999999,40.943885],"type":"Point"}
}