{
  "type": "Feature",
  "properties": {
    "iso:country":"US",
    "sg:address":"104 Rockaway Ave",
    "sg:city":"Valley Stream",
    "sg:classifiers":[
        {
            "category":"Food & Beverages",
            "subcategory":"Groceries & Convenience Stores",
            "type":"Retail Goods"
        }
    ],
    "sg:phone":"+1 516 568 1112",
    "sg:postcode":"11580",
    "sg:province":"NY",
    "wof:name":"Valley Hut",
    "wof:placetype":"venue"
},
  "geometry": {"coordinates":[-73.69883299999999,40.663304],"type":"Point"}
}