{
  "type": "Feature",
  "properties": {
    "addr:full":"83 Orchard St New York NY 10002",
    "addr:housenumber":"83",
    "addr:postcode":"10002",
    "addr:street":"Orchard St",
    "iso:country":"US",
    "sg:address":"83 Orchard St",
    "sg:city":"New York",
    "sg:classifiers":[
        {
            "category":"Shopping",
            "subcategory":"Clothing, Apparel, & Fashions",
            "type":"Retail Goods"
        }
    ],
    "sg:phone":"+1 212 680 5630",
    "sg:postcode":"10002",
    "sg:province":"NY",
    "sg:tags":[
        "clothing",
        "women's"
    ],
    "sg:website":"www.kaightnyc.com",
    "wof:name":"Kaight",
    "wof:placetype":"venue"
},
  "geometry": {"coordinates":[-73.990358,40.717841],"type":"Point"}
}