{
  "type": "Feature",
  "properties": {
    "addr:full":"1219 Lexington Ave New York NY 10028",
    "addr:housenumber":"1219",
    "addr:postcode":"10028",
    "addr:street":"Lexington Ave",
    "iso:country":"US",
    "sg:address":"1219 Lexington Ave",
    "sg:city":"New York",
    "sg:classifiers":[
        {
            "category":"Retail",
            "subcategory":"Laundry & Dry Cleaning",
            "type":"Services"
        }
    ],
    "sg:phone":"+1 212 288 0432",
    "sg:postcode":"10028",
    "sg:province":"NY",
    "sg:tags":[
        "cleaner"
    ],
    "wof:name":"Art Cleaners & Tailors",
    "wof:placetype":"venue"
},
  "geometry": {"coordinates":[-73.957397,40.777302],"type":"Point"}
}