{
  "type": "Feature",
  "properties": {
    "addr:full":"109 Maple Ave Rye NY 10580",
    "addr:housenumber":"109",
    "addr:postcode":"10580",
    "addr:street":"Maple Ave",
    "iso:country":"US",
    "sg:address":"109 Maple Ave",
    "sg:city":"Rye",
    "sg:classifiers":[
        {
            "category":"Utilities",
            "subcategory":"Electric",
            "type":"Services"
        },
        {
            "category":"Manufacturing",
            "subcategory":"Electronics",
            "type":"Manufacturing & Wholesale Goods"
        },
        {
            "category":"Building & Trades",
            "subcategory":"Electrical",
            "type":"Services"
        }
    ],
    "sg:phone":"+1 914 939 2891",
    "sg:postcode":"10580",
    "sg:province":"NY",
    "sg:tags":[
        "industrial",
        "electrician",
        "contractors-commercial",
        "equipment-testing"
    ],
    "wof:name":"Pinto Electric Co Inc",
    "wof:placetype":"venue"
},
  "geometry": {"coordinates":[-73.696721,40.980144],"type":"Point"}
}