{
  "type": "Feature",
  "properties": {
    "addr:full":"11 Nagle Ave New York NY 10040",
    "addr:housenumber":"11",
    "addr:postcode":"10040",
    "addr:street":"Nagle Ave",
    "iso:country":"US",
    "sg:address":"11 Nagle Ave",
    "sg:city":"New York",
    "sg:classifiers":[
        {
            "category":"Restaurant",
            "type":"Food & Drink"
        }
    ],
    "sg:menulink":"http://www.allmenus.com/ny/new-york/47998-5-star-que-ricuras/menu/",
    "sg:phone":"+1 212 304 1872",
    "sg:postcode":"10040",
    "sg:province":"NY",
    "sg:tags":[
        "dominican"
    ],
    "wof:name":"5 Star Que Ricuras",
    "wof:placetype":"venue"
},
  "geometry": {"coordinates":[-73.93102,40.859319],"type":"Point"}
}