{
  "type": "Feature",
  "properties": {
    "iso:country":"US",
    "sg:address":"5562 Bear Rd Ste C1",
    "sg:city":"Syracuse",
    "sg:classifiers":[
        {
            "category":"Real Estate",
            "subcategory":"Real Estate Operator",
            "type":"Services"
        }
    ],
    "sg:phone":"+1 315 458 4257",
    "sg:postcode":"13212",
    "sg:province":"NY",
    "sg:tags":[
        "apartment"
    ],
    "wof:name":"Allen Meadows Apts",
    "wof:placetype":"venue"
},
  "geometry": {"coordinates":[-76.133769,43.1444],"type":"Point"}
}