{
  "type": "Feature",
  "properties": {
    "addr:full":"3461 Lafayette Rd Jamesville NY 13078",
    "addr:housenumber":"3461",
    "addr:postcode":"13078",
    "iso:country":"US",
    "sg:address":"3461 Lafayette Rd",
    "sg:city":"Jamesville",
    "sg:classifiers":[
        {
            "category":"Home & Garden",
            "subcategory":"Garden Supply",
            "type":"Retail Goods"
        }
    ],
    "sg:phone":"+1   ",
    "sg:postcode":"13078",
    "sg:province":"NY",
    "wof:name":"Tanglewood Gardens LLC",
    "wof:placetype":"venue"
},
  "geometry": {"coordinates":[-76.096281,42.937388],"type":"Point"}
}