{
  "type": "Feature",
  "properties": {
    "iso:country":"US",
    "sg:address":"15 Vine St",
    "sg:city":"Keeseville",
    "sg:classifiers":[
        {
            "category":"Professional",
            "subcategory":"Management & Consulting",
            "type":"Services"
        }
    ],
    "sg:phone":"+1 518 834 9006",
    "sg:postcode":"12944",
    "sg:province":"NY",
    "sg:tags":[
        "consultant",
        "business"
    ],
    "wof:name":"Upstate Records Management LLC",
    "wof:placetype":"venue"
},
  "geometry": {"coordinates":[-73.478819,44.503515],"type":"Point"}
}