{
  "type": "Feature",
  "properties": {
    "addr:full":"5414 Arlington Ave Bronx NY 10471",
    "addr:housenumber":"5414",
    "addr:postcode":"10471",
    "addr:street":"Arlington Ave",
    "iso:country":"US",
    "sg:address":"5414 Arlington Ave",
    "sg:city":"Bronx",
    "sg:classifiers":[
        {
            "category":"Real Estate",
            "subcategory":"Real Estate Operator",
            "type":"Services"
        }
    ],
    "sg:phone":"+1 718 796 8222",
    "sg:postcode":"10471",
    "sg:province":"NY",
    "sg:tags":[
        "building",
        "apartment"
    ],
    "wof:name":"River Dale Park Maint Offc",
    "wof:placetype":"venue"
},
  "geometry": {"coordinates":[-73.90737799999999,40.903179],"type":"Point"}
}