{
  "type": "Feature",
  "properties": {
    "addr:full":"155 W Dominick St Rome NY 13440",
    "addr:housenumber":"155",
    "addr:postcode":"13440",
    "addr:street":"W Dominick St",
    "iso:country":"US",
    "sg:address":"155 W Dominick St",
    "sg:city":"Rome",
    "sg:classifiers":[
        {
            "category":"Community Center",
            "type":"Public Place"
        }
    ],
    "sg:phone":"+1 315 337 1200",
    "sg:postcode":"13440",
    "sg:province":"NY",
    "sg:tags":[
        "medical"
    ],
    "wof:name":"Rome Memorial Hospital",
    "wof:placetype":"venue"
},
  "geometry": {"coordinates":[-75.458842,43.211374],"type":"Point"}
}