{
  "type": "Feature",
  "properties": {
    "addr:full":"1886 7th Ave New York NY 10026",
    "addr:housenumber":"1886",
    "addr:postcode":"10026",
    "addr:street":"7Th Ave",
    "iso:country":"US",
    "sg:address":"1886 7th Ave",
    "sg:city":"New York",
    "sg:classifiers":[
        {
            "category":"Building & Trades",
            "subcategory":"Cleaning & Sanitation",
            "type":"Services"
        }
    ],
    "sg:phone":"+1 212 222 5687",
    "sg:postcode":"10026",
    "sg:province":"NY",
    "sg:tags":[
        "butler",
        "maid"
    ],
    "wof:name":"Maids Of Manhattan",
    "wof:placetype":"venue"
},
  "geometry": {"coordinates":[-73.953205,40.802364],"type":"Point"}
}