{
  "type": "Feature",
  "properties": {
    "iso:country":"US",
    "sg:address":"24 Horizon Farms Dr",
    "sg:city":"Warwick",
    "sg:classifiers":[
        {
            "category":"Health Services",
            "subcategory":"Health Practitioner",
            "type":"Services"
        }
    ],
    "sg:phone":"+1 845 258 4322",
    "sg:postcode":"10990",
    "sg:province":"NY",
    "sg:tags":[
        "therapist",
        "physical"
    ],
    "wof:name":"Patricia A Storjohann",
    "wof:placetype":"venue"
},
  "geometry": {"coordinates":[-74.46207099999999,41.280814],"type":"Point"}
}