{
  "type": "Feature",
  "properties": {
    "addr:full":"230 Bloomingburg Rd Middletown NY 10940",
    "addr:housenumber":"230",
    "addr:postcode":"10940",
    "addr:street":"Bloomingburg Rd",
    "iso:country":"US",
    "sg:address":"230 Bloomingburg Rd",
    "sg:city":"Middletown",
    "sg:classifiers":[
        {
            "category":"Home & Garden",
            "subcategory":"Furniture",
            "type":"Retail Goods"
        }
    ],
    "sg:phone":"+1   ",
    "sg:postcode":"10940",
    "sg:province":"NY",
    "sg:tags":[
        "household"
    ],
    "wof:name":"Bruce Stevens Furniture Co",
    "wof:placetype":"venue"
},
  "geometry": {"coordinates":[-74.41281499999999,41.513265],"type":"Point"}
}