{
  "type": "Feature",
  "properties": {
    "addr:full":"2370 Grand Concourse Bronx NY 10458",
    "addr:housenumber":"2370",
    "addr:postcode":"10458",
    "addr:street":"Grand Concourse",
    "iso:country":"US",
    "sg:address":"2370 Grand Concourse",
    "sg:city":"Bronx",
    "sg:classifiers":[
        {
            "category":"Bagels",
            "type":"Food & Drink"
        },
        {
            "category":"Coffee & Tea",
            "type":"Food & Drink"
        },
        {
            "category":"Food & Beverages",
            "subcategory":"Bakery",
            "type":"Retail Goods"
        },
        {
            "category":"Bakery",
            "type":"Food & Drink"
        },
        {
            "category":"Donuts",
            "type":"Food & Drink"
        }
    ],
    "sg:menulink":"http://www.allmenus.com/ny/bronx/138221-dunkin-donuts/menu/",
    "sg:phone":"+1 718 940 8055",
    "sg:postcode":"10458",
    "sg:province":"NY",
    "sg:tags":[
        "coffee",
        "tea",
        "american",
        "bagel",
        "bakery",
        "pastry"
    ],
    "wof:name":"Dunkin' Donuts",
    "wof:placetype":"venue"
},
  "geometry": {"coordinates":[-73.89872699999999,40.859173],"type":"Point"}
}