{
  "type": "Feature",
  "properties": {
    "iso:country":"US",
    "sg:address":"167 Birchwood Dr",
    "sg:city":"Rochester",
    "sg:classifiers":[
        {
            "category":"Building & Trades",
            "subcategory":"Construction",
            "type":"Services"
        }
    ],
    "sg:phone":"+1 585 309 3086",
    "sg:postcode":"14622",
    "sg:province":"NY",
    "sg:tags":[
        "home",
        "improvement"
    ],
    "wof:name":"Sharp Construction & Remodel",
    "wof:placetype":"venue"
},
  "geometry": {"coordinates":[-77.551248,43.225935],"type":"Point"}
}