{
  "type": "Feature",
  "properties": {
    "iso:country":"US",
    "sg:address":"590 Madison Ave",
    "sg:city":"New York",
    "sg:classifiers":[
        {
            "category":"Banks & Credit Unions",
            "subcategory":"Investment Brokerage",
            "type":"Services"
        }
    ],
    "sg:phone":"+1 212 752 1600",
    "sg:postcode":"10022",
    "sg:province":"NY",
    "sg:tags":[
        "consultant",
        "planning",
        "financial"
    ],
    "wof:name":"Harbourton Enterprises",
    "wof:placetype":"venue"
},
  "geometry": {"coordinates":[-73.97276100000001,40.761718],"type":"Point"}
}