{
  "type": "Feature",
  "properties": {
    "addr:full":"6278 Northern Blvd East Norwich NY 11732",
    "addr:housenumber":"6278",
    "addr:postcode":"11732",
    "addr:street":"Northern Blvd East",
    "iso:country":"US",
    "sg:address":"6278 Northern Blvd",
    "sg:city":"East Norwich",
    "sg:classifiers":[
        {
            "category":"Retail",
            "subcategory":"Car Wash",
            "type":"Services"
        },
        {
            "category":"Retail",
            "subcategory":"Auto Repair",
            "type":"Services"
        }
    ],
    "sg:phone":"+1 516 624 9605",
    "sg:postcode":"11732",
    "sg:province":"NY",
    "sg:tags":[
        "body",
        "automobile",
        "detail",
        "clean"
    ],
    "wof:name":"Pro-Buff Detailing",
    "wof:placetype":"venue"
},
  "geometry": {"coordinates":[-73.533631,40.842213],"type":"Point"}
}