{
  "type": "Feature",
  "properties": {
    "addr:full":"4 River Rd New York NY 10044",
    "addr:housenumber":"4",
    "addr:postcode":"10044",
    "addr:street":"River Rd",
    "iso:country":"US",
    "sg:address":"4 River Rd",
    "sg:city":"New York",
    "sg:classifiers":[
        {
            "category":"Personal",
            "subcategory":"Beauty Salon",
            "type":"Services"
        }
    ],
    "sg:phone":"+1 212 935 2056",
    "sg:postcode":"10044",
    "sg:province":"NY",
    "wof:name":"Freemantle Beauty",
    "wof:placetype":"venue"
},
  "geometry": {"coordinates":[-73.946144,40.765854],"type":"Point"}
}