{
  "type": "Feature",
  "properties": {
    "iso:country":"US",
    "sg:address":"347 W 36 St",
    "sg:city":"New York",
    "sg:classifiers":[
        {
            "category":"Manufacturing",
            "subcategory":"Motor Vehicles & Parts",
            "type":"Manufacturing & Wholesale Goods"
        }
    ],
    "sg:phone":"+1 212 643 2918",
    "sg:postcode":"10018",
    "sg:province":"NY",
    "sg:tags":[
        "shoulder",
        "pad"
    ],
    "wof:name":"Interpads",
    "wof:placetype":"venue"
},
  "geometry": {"coordinates":[-73.99431199999999,40.754183],"type":"Point"}
}