{
  "type": "Feature",
  "properties": {
    "addr:full":"26 Main St Fultonville NY 12072",
    "addr:housenumber":"26",
    "addr:postcode":"12072",
    "addr:street":"Main St",
    "iso:country":"US",
    "sg:address":"26 Main St",
    "sg:city":"Fultonville",
    "sg:classifiers":[
        {
            "category":"Government",
            "subcategory":"Post Office",
            "type":"Public Place"
        }
    ],
    "sg:phone":"+1 518 853 3631",
    "sg:postcode":"12072",
    "sg:province":"NY",
    "wof:name":"US Post Office",
    "wof:placetype":"venue"
},
  "geometry": {"coordinates":[-74.370853,42.947379],"type":"Point"}
}