{
  "type": "Feature",
  "properties": {
    "addr:full":"100 Manetto Hill Rd Plainview NY 11803",
    "addr:housenumber":"100",
    "addr:postcode":"11803",
    "addr:street":"Manetto Hill Rd",
    "iso:country":"US",
    "sg:address":"100 Manetto Hill Rd",
    "sg:city":"Plainview",
    "sg:classifiers":[
        {
            "category":"Health Services",
            "subcategory":"Doctor",
            "type":"Services"
        }
    ],
    "sg:phone":"+1 516 433 3232",
    "sg:postcode":"11803",
    "sg:province":"NY",
    "sg:tags":[
        "physician",
        "surgeon"
    ],
    "wof:name":"Donald P Orofino MD",
    "wof:placetype":"venue"
},
  "geometry": {"coordinates":[-73.470185,40.780615],"type":"Point"}
}