{
  "type": "Feature",
  "properties": {
    "addr:full":"459 Merrick Rd Lynbrook NY 11563",
    "addr:housenumber":"459",
    "addr:postcode":"11563",
    "addr:street":"Merrick Rd",
    "iso:country":"US",
    "sg:address":"459 Merrick Rd",
    "sg:city":"Lynbrook",
    "sg:classifiers":[
        {
            "category":"Food & Beverages",
            "subcategory":"Groceries & Convenience Stores",
            "type":"Retail Goods"
        }
    ],
    "sg:phone":"+1   ",
    "sg:postcode":"11563",
    "sg:province":"NY",
    "wof:name":"Blossoms Corner",
    "wof:placetype":"venue"
},
  "geometry": {"coordinates":[-73.676558,40.658451],"type":"Point"}
}