{
  "type": "Feature",
  "properties": {
    "addr:full":"726 Exchange St Ste 516 Buffalo NY 14210",
    "addr:housenumber":"726",
    "addr:postcode":"14210",
    "addr:street":"Exchange St Ste 516",
    "iso:country":"US",
    "sg:address":"726 Exchange St Ste 516",
    "sg:city":"Buffalo",
    "sg:classifiers":[
        {
            "category":"Professional",
            "subcategory":"Lawyer & Legal Services",
            "type":"Services"
        }
    ],
    "sg:phone":"+1 716 856 1700",
    "sg:postcode":"14210",
    "sg:province":"NY",
    "wof:name":"Cannon Heyman & Weiss Llp",
    "wof:placetype":"venue"
},
  "geometry": {"coordinates":[-78.84963,42.874844],"type":"Point"}
}