{
  "type": "Feature",
  "properties": {
    "addr:full":"42 Lido Blvd Point Lookout NY 11569",
    "addr:housenumber":"42",
    "addr:postcode":"11569",
    "addr:street":"Lido Blvd",
    "iso:country":"US",
    "sg:address":"42 Lido Blvd",
    "sg:city":"Point Lookout",
    "sg:classifiers":[
        {
            "category":"Building & Trades",
            "subcategory":"Electrical",
            "type":"Services"
        }
    ],
    "sg:phone":"+1 516 431 2348",
    "sg:postcode":"11569",
    "sg:province":"NY",
    "sg:tags":[
        "electrical",
        "contractor"
    ],
    "wof:name":"Futuristic Home Incorporated",
    "wof:placetype":"venue"
},
  "geometry": {"coordinates":[-73.581457,40.592091],"type":"Point"}
}