{
  "type": "Feature",
  "properties": {
    "addr:full":"164 Sheedy Rd Vestal NY 13850",
    "addr:housenumber":"164",
    "addr:postcode":"13850",
    "addr:street":"Sheedy Rd",
    "iso:country":"US",
    "sg:address":"164 Sheedy Rd",
    "sg:city":"Vestal",
    "sg:classifiers":[
        {
            "category":"Shopping",
            "subcategory":"Clothing, Apparel, & Fashions",
            "type":"Retail Goods"
        }
    ],
    "sg:phone":"+1   ",
    "sg:postcode":"13850",
    "sg:province":"NY",
    "wof:name":"Coras Boutique",
    "wof:placetype":"venue"
},
  "geometry": {"coordinates":[-76.016693,42.054928],"type":"Point"}
}