{
  "type": "Feature",
  "properties": {
    "addr:full":"7321 15th Ave Brooklyn NY 11228",
    "addr:housenumber":"7321",
    "addr:postcode":"11228",
    "addr:street":"15Th Ave",
    "iso:country":"US",
    "sg:address":"7321 15th Ave",
    "sg:city":"Brooklyn",
    "sg:classifiers":[
        {
            "category":"Government",
            "subcategory":"Office",
            "type":"Public Place"
        }
    ],
    "sg:phone":"+1 516 640 8710",
    "sg:postcode":"11228",
    "sg:province":"NY",
    "sg:tags":[
        "township",
        "government-city",
        "village"
    ],
    "wof:name":"Nyc Dept Of Education",
    "wof:placetype":"venue"
},
  "geometry": {"coordinates":[-74.001919,40.618684],"type":"Point"}
}