{
  "type": "Feature",
  "properties": {
    "addr:full":"388 Robyn Pl East Meadow NY 11554",
    "addr:housenumber":"388",
    "addr:postcode":"11554",
    "addr:street":"Robyn Pl",
    "iso:country":"US",
    "sg:address":"388 Robyn Pl",
    "sg:city":"East Meadow",
    "sg:classifiers":[
        {
            "category":"Professional",
            "subcategory":"Management & Consulting",
            "type":"Services"
        }
    ],
    "sg:phone":"+1 516 781 4343",
    "sg:postcode":"11554",
    "sg:province":"NY",
    "sg:tags":[
        "consultant",
        "business"
    ],
    "wof:name":"Infocex Co",
    "wof:placetype":"venue"
},
  "geometry": {"coordinates":[-73.547543,40.713197],"type":"Point"}
}