{
  "type": "Feature",
  "properties": {
    "addr:full":"6314 Westerly Ter Jamesville NY 13078",
    "addr:housenumber":"6314",
    "addr:postcode":"13078",
    "addr:street":"Westerly Ter Jamesville",
    "iso:country":"US",
    "sg:address":"6314 Westerly Ter",
    "sg:city":"Jamesville",
    "sg:classifiers":[
        {
            "category":"Social Services",
            "type":"Services"
        }
    ],
    "sg:phone":"+1 315 446 4858",
    "sg:postcode":"13078",
    "sg:province":"NY",
    "sg:tags":[
        "worker"
    ],
    "wof:name":"Gerda Vandyck-Bothe",
    "wof:placetype":"venue"
},
  "geometry": {"coordinates":[-76.08337299999999,43.024377],"type":"Point"}
}