{
  "type": "Feature",
  "properties": {
    "iso:country":"US",
    "sg:address":"4502 18th Ave",
    "sg:city":"Brooklyn",
    "sg:classifiers":[
        {
            "category":"Utilities",
            "subcategory":"Mobile Phone",
            "type":"Services"
        }
    ],
    "sg:phone":"+1 718 851 0101",
    "sg:postcode":"11204",
    "sg:province":"NY",
    "sg:tags":[
        "telephone",
        "cellular"
    ],
    "wof:name":"Brooklyn Wireless Mailing",
    "wof:placetype":"venue"
},
  "geometry": {"coordinates":[-73.979063,40.62993],"type":"Point"}
}