{
  "type": "Feature",
  "properties": {
    "iso:country":"US",
    "sg:address":"2480 Poersch Ct",
    "sg:city":"Niskayuna",
    "sg:classifiers":[
        {
            "category":"Personal",
            "type":"Services"
        }
    ],
    "sg:phone":"+1 518 382 8372",
    "sg:postcode":"12309",
    "sg:province":"NY",
    "sg:tags":[
        "electrolysis"
    ],
    "wof:name":"Niskayuna Electrolysis",
    "wof:placetype":"venue"
},
  "geometry": {"coordinates":[-73.88561300000001,42.812069],"type":"Point"}
}