{
  "type": "Feature",
  "properties": {
    "addr:full":"18 Parkway Dr Syosset NY 11791",
    "addr:housenumber":"18",
    "addr:postcode":"11791",
    "addr:street":"Parkway Dr",
    "iso:country":"US",
    "sg:address":"18 Parkway Dr",
    "sg:city":"Syosset",
    "sg:classifiers":[
        {
            "category":"Building & Trades",
            "subcategory":"Construction",
            "type":"Services"
        }
    ],
    "sg:phone":"+1 516 933 1040",
    "sg:postcode":"11791",
    "sg:province":"NY",
    "sg:tags":[
        "hanging",
        "contractor"
    ],
    "wof:name":"Linas Contracting",
    "wof:placetype":"venue"
},
  "geometry": {"coordinates":[-73.50166299999999,40.790025],"type":"Point"}
}