{
  "type": "Feature",
  "properties": {
    "iso:country":"US",
    "sg:address":"150 E 58th St Bsmt",
    "sg:city":"New York",
    "sg:classifiers":[
        {
            "category":"Building & Trades",
            "subcategory":"Locksmith",
            "type":"Services"
        }
    ],
    "sg:phone":"+1 212 492 9583",
    "sg:postcode":"10155",
    "sg:province":"NY",
    "sg:tags":[
        "key"
    ],
    "wof:name":"24 Hour A Emerg Locksmith",
    "wof:placetype":"venue"
},
  "geometry": {"coordinates":[-73.968102,40.761101],"type":"Point"}
}