{
  "type": "Feature",
  "properties": {
    "iso:country":"US",
    "sg:address":"1 Regatta Pl",
    "sg:city":"Troy",
    "sg:classifiers":[
        {
            "category":"Building & Trades",
            "subcategory":"Construction",
            "type":"Services"
        }
    ],
    "sg:phone":"+1 518 273 3371",
    "sg:postcode":"12180",
    "sg:province":"NY",
    "wof:name":"L & L Blacktop Inc",
    "wof:placetype":"venue"
},
  "geometry": {"coordinates":[-73.683633,42.753046],"type":"Point"}
}