{
  "type": "Feature",
  "properties": {
    "addr:full":"243 Prospect Park W Brooklyn NY 11215",
    "addr:housenumber":"243",
    "addr:postcode":"11215",
    "addr:street":"Prospect Park W",
    "iso:country":"US",
    "sg:address":"243 Prospect Park W",
    "sg:city":"Brooklyn",
    "sg:classifiers":[
        {
            "category":"Health Services",
            "subcategory":"Nursing And Care Facility",
            "type":"Services"
        }
    ],
    "sg:phone":"+1 718 832 1075",
    "sg:postcode":"11215",
    "sg:province":"NY",
    "sg:tags":[
        "disabled",
        "home",
        "for",
        "developmentally",
        "child"
    ],
    "wof:name":"Mercy Home For Children Inc",
    "wof:placetype":"venue"
},
  "geometry": {"coordinates":[-73.98142199999999,40.659126],"type":"Point"}
}