{
  "type": "Feature",
  "properties": {
    "addr:full":"1839 N Railroad Avenue Staten Island NY 10306",
    "addr:housenumber":"1839",
    "addr:postcode":"10306",
    "addr:street":"N Railroad Avenue",
    "iso:country":"US",
    "sg:address":"1839 N Railroad Avenue",
    "sg:city":"Staten Island",
    "sg:classifiers":[
        {
            "category":"Health Services",
            "subcategory":"Dentist",
            "type":"Services"
        }
    ],
    "sg:phone":"+1 718 979 2121",
    "sg:postcode":"10306",
    "sg:province":"NY",
    "wof:name":"Pannone Anthony DDS",
    "wof:placetype":"venue"
},
  "geometry": {"coordinates":[-74.126779,40.56489],"type":"Point"}
}