{
  "type": "Feature",
  "properties": {
    "addr:full":"52 Woodville Rd Shoreham NY 11786",
    "addr:housenumber":"52",
    "addr:postcode":"11786",
    "addr:street":"Woodville Rd",
    "iso:country":"US",
    "sg:address":"52 Woodville Rd",
    "sg:city":"Shoreham",
    "sg:classifiers":[
        {
            "category":"Real Estate",
            "subcategory":"Real Estate Agent",
            "type":"Services"
        }
    ],
    "sg:phone":"+1 631 821 4272",
    "sg:postcode":"11786",
    "sg:province":"NY",
    "wof:name":"Projects Properties Inc",
    "wof:placetype":"venue"
},
  "geometry": {"coordinates":[-72.906971,40.956218],"type":"Point"}
}