{
  "type": "Feature",
  "properties": {
    "iso:country":"US",
    "sg:address":"1 N Liberty Ave",
    "sg:city":"Endicott",
    "sg:classifiers":[
        {
            "category":"Building & Trades",
            "subcategory":"Plumbing",
            "type":"Services"
        }
    ],
    "sg:phone":"+1 607 785 3435",
    "sg:postcode":"13760",
    "sg:province":"NY",
    "sg:tags":[
        "plumber",
        "industrial",
        "contractors-commercial"
    ],
    "wof:name":"Clark Mechanical Plumbing & Heating",
    "wof:placetype":"venue"
},
  "geometry": {"coordinates":[-76.064148,42.099461],"type":"Point"}
}