{
  "type": "Feature",
  "properties": {
    "addr:full":"382 State Hwy 59 Monsey NY 10952",
    "addr:housenumber":"382",
    "addr:postcode":"10952",
    "addr:street":"State Hwy 59",
    "iso:country":"US",
    "sg:address":"382 State Hwy 59",
    "sg:city":"Monsey",
    "sg:classifiers":[
        {
            "category":"Manufacturing",
            "subcategory":"Textiles",
            "type":"Manufacturing & Wholesale Goods"
        }
    ],
    "sg:phone":"+1   ",
    "sg:postcode":"10952",
    "sg:province":"NY",
    "sg:tags":[
        "linen",
        "fabric",
        "mfg"
    ],
    "wof:name":"La Viano Fine Linen USA Inc",
    "wof:placetype":"venue"
},
  "geometry": {"coordinates":[-74.094004,41.11059],"type":"Point"}
}