{
  "type": "Feature",
  "properties": {
    "iso:country":"US",
    "sg:address":"128 W 62 St",
    "sg:city":"New York",
    "sg:classifiers":[
        {
            "category":"Museum",
            "type":"Entertainment"
        }
    ],
    "sg:phone":"+1   ",
    "sg:postcode":"10023",
    "sg:province":"NY",
    "sg:tags":[
        "gallery"
    ],
    "wof:name":"Neustadt Museum Tiffany Art",
    "wof:placetype":"venue"
},
  "geometry": {"coordinates":[-73.985675,40.771901],"type":"Point"}
}