{
  "type": "Feature",
  "properties": {
    "addr:full":"145 S William St Newburgh NY 12550",
    "addr:housenumber":"145",
    "addr:postcode":"12550",
    "addr:street":"S William St",
    "iso:country":"US",
    "sg:address":"145 S William St",
    "sg:city":"Newburgh",
    "sg:classifiers":[
        {
            "category":"Building & Trades",
            "subcategory":"Plumbing",
            "type":"Services"
        }
    ],
    "sg:phone":"+1 845 297 6600",
    "sg:postcode":"12550",
    "sg:province":"NY",
    "wof:name":"Wolfe Plumbing Heating & Air Conditioning Inc",
    "wof:placetype":"venue"
},
  "geometry": {"coordinates":[-74.014099,41.496201],"type":"Point"}
}