{
  "type": "Feature",
  "properties": {
    "iso:country":"US",
    "sg:address":"1165 Ulster Ave",
    "sg:city":"Kingston",
    "sg:classifiers":[
        {
            "category":"Shopping",
            "subcategory":"Bicycles & Sporting Goods",
            "type":"Retail Goods"
        }
    ],
    "sg:phone":"+1 845 336 0630",
    "sg:postcode":"12401",
    "sg:province":"NY",
    "wof:name":"Sports Authority",
    "wof:placetype":"venue"
},
  "geometry": {"coordinates":[-73.989898,41.964178],"type":"Point"}
}