{
  "type": "Feature",
  "properties": {
    "addr:full":"1812 Richmond Ave Staten Island NY 10314",
    "addr:housenumber":"1812",
    "addr:postcode":"10314",
    "addr:street":"Richmond Ave",
    "iso:country":"US",
    "sg:address":"1812 Richmond Ave",
    "sg:city":"Staten Island",
    "sg:classifiers":[
        {
            "category":"Health Services",
            "subcategory":"Doctor",
            "type":"Services"
        }
    ],
    "sg:phone":"+1 718 761 0124",
    "sg:postcode":"10314",
    "sg:province":"NY",
    "sg:tags":[
        "medical"
    ],
    "wof:name":"Mary Hanna MD",
    "wof:placetype":"venue"
},
  "geometry": {"coordinates":[-74.16333299999999,40.601817],"type":"Point"}
}