{
  "type": "Feature",
  "properties": {
    "iso:country":"US",
    "sg:address":"4 Mina Pl",
    "sg:city":"Kings Park",
    "sg:classifiers":[
        {
            "category":"Manufacturing",
            "subcategory":"Printing",
            "type":"Manufacturing & Wholesale Goods"
        }
    ],
    "sg:phone":"+1   ",
    "sg:postcode":"11754",
    "sg:province":"NY",
    "sg:tags":[
        "lithographic",
        "commercial"
    ],
    "wof:name":"P J Graphics Inc",
    "wof:placetype":"venue"
},
  "geometry": {"coordinates":[-73.229995,40.885253],"type":"Point"}
}