{
  "type": "Feature",
  "properties": {
    "addr:full":"34 Prospect St White Plains NY 10607",
    "addr:housenumber":"34",
    "addr:postcode":"10607",
    "addr:street":"Prospect St",
    "iso:country":"US",
    "sg:address":"34 Prospect St",
    "sg:city":"White Plains",
    "sg:classifiers":[
        {
            "category":"Building & Trades",
            "subcategory":"Landscaping Services",
            "type":"Services"
        }
    ],
    "sg:phone":"+1 914 946 7628",
    "sg:postcode":"10607",
    "sg:province":"NY",
    "sg:tags":[
        "landscape"
    ],
    "wof:name":"Lorenzo Dimarino Landscaping",
    "wof:placetype":"venue"
},
  "geometry": {"coordinates":[-73.785996,41.034972],"type":"Point"}
}