{
  "type": "Feature",
  "properties": {
    "addr:full":"14 Woodland St Blue Point NY 11715",
    "addr:housenumber":"14",
    "addr:postcode":"11715",
    "addr:street":"Woodland St",
    "iso:country":"US",
    "sg:address":"14 Woodland St",
    "sg:city":"Blue Point",
    "sg:classifiers":[
        {
            "category":"Real Estate",
            "subcategory":"Real Estate Agent",
            "type":"Services"
        }
    ],
    "sg:phone":"+1 631 363 2198",
    "sg:postcode":"11715",
    "sg:province":"NY",
    "wof:name":"J&C Property Management Team I",
    "wof:placetype":"venue"
},
  "geometry": {"coordinates":[-73.034995,40.747064],"type":"Point"}
}