{
  "type": "Feature",
  "properties": {
    "iso:country":"US",
    "sg:address":"570 Franklin Ave",
    "sg:city":"Massapequa",
    "sg:classifiers":[
        {
            "category":"Real Estate",
            "subcategory":"Real Estate Agent",
            "type":"Services"
        }
    ],
    "sg:phone":"+1 516 799 3116",
    "sg:postcode":"11758",
    "sg:province":"NY",
    "wof:name":"Cobblestone Real Estate",
    "wof:placetype":"venue"
},
  "geometry": {"coordinates":[-73.46984,40.681959],"type":"Point"}
}