{
  "type": "Feature",
  "properties": {
    "iso:country":"US",
    "sg:address":"3970 Big Tree Rd",
    "sg:city":"Hamburg",
    "sg:classifiers":[
        {
            "category":"Manufacturing",
            "subcategory":"Printing",
            "type":"Manufacturing & Wholesale Goods"
        }
    ],
    "sg:phone":"+1   ",
    "sg:postcode":"14075",
    "sg:province":"NY",
    "sg:tags":[
        "print",
        "lithographic",
        "typesetting"
    ],
    "sg:website":"www.gatewayprints.com",
    "wof:name":"Gateway Printing & Graphics",
    "wof:placetype":"venue"
},
  "geometry": {"coordinates":[-78.835213,42.772076],"type":"Point"}
}