{
  "type": "Feature",
  "properties": {
    "addr:full":"13 W Main St Tarrytown NY 10591",
    "addr:housenumber":"13",
    "addr:postcode":"10591",
    "addr:street":"W Main St",
    "iso:country":"US",
    "sg:address":"13 W Main St",
    "sg:city":"Tarrytown",
    "sg:classifiers":[
        {
            "category":"Shopping",
            "subcategory":"Used Merchandise",
            "type":"Retail Goods"
        }
    ],
    "sg:phone":"+1   ",
    "sg:postcode":"10591",
    "sg:province":"NY",
    "wof:name":"Curio Shop",
    "wof:placetype":"venue"
},
  "geometry": {"coordinates":[-73.858559,41.076355],"type":"Point"}
}