{
  "type": "Feature",
  "properties": {
    "addr:full":"1736 State Hwy 9j Castletn On Hdsn NY 12033",
    "addr:housenumber":"1736",
    "addr:postcode":"12033",
    "addr:street":"State Hwy 9J",
    "iso:country":"US",
    "sg:address":"1736 State Hwy 9j",
    "sg:city":"Castletn On Hdsn",
    "sg:classifiers":[
        {
            "category":"Bars & Pubs",
            "type":"Food & Drink"
        }
    ],
    "sg:phone":"+1 518 477 2412",
    "sg:postcode":"12033",
    "sg:province":"NY",
    "wof:name":"Hillcrest Inn",
    "wof:placetype":"venue"
},
  "geometry": {"coordinates":[-73.743933,42.561986],"type":"Point"}
}