{
  "type": "Feature",
  "properties": {
    "iso:country":"US",
    "sg:address":"45 Samsondale Ave",
    "sg:city":"West Haverstraw",
    "sg:classifiers":[
        {
            "category":"Shopping",
            "type":"Retail Goods"
        }
    ],
    "sg:phone":"+1 845 429 9003",
    "sg:postcode":"10993",
    "sg:province":"NY",
    "sg:tags":[
        "pet",
        "shop",
        "center"
    ],
    "wof:name":"Animart Pet Center Inc",
    "wof:placetype":"venue"
},
  "geometry": {"coordinates":[-73.98047099999999,41.207504],"type":"Point"}
}