{
  "type": "Feature",
  "properties": {
    "iso:country":"US",
    "sg:address":"188 Ballard Rd",
    "sg:city":"Gansevoort",
    "sg:classifiers":[
        {
            "category":"Building & Trades",
            "subcategory":"Construction",
            "type":"Services"
        }
    ],
    "sg:phone":"+1 518 581 9360",
    "sg:postcode":"12831",
    "sg:province":"NY",
    "sg:tags":[
        "contractor",
        "specialty",
        "mfg"
    ],
    "wof:name":"Signworks",
    "wof:placetype":"venue"
},
  "geometry": {"coordinates":[-73.707857,43.165953],"type":"Point"}
}