{
  "type": "Feature",
  "properties": {
    "iso:country":"US",
    "sg:address":"172 S Main St",
    "sg:city":"Northville",
    "sg:classifiers":[
        {
            "category":"Food & Beverages",
            "subcategory":"Liquor & Beverages",
            "type":"Retail Goods"
        }
    ],
    "sg:phone":"+1 518 863 4121",
    "sg:postcode":"12134",
    "sg:province":"NY",
    "sg:tags":[
        "store"
    ],
    "wof:name":"Northville Liquor Store",
    "wof:placetype":"venue"
},
  "geometry": {"coordinates":[-74.171379,43.224771],"type":"Point"}
}