{
  "type": "Feature",
  "properties": {
    "iso:country":"US",
    "sg:address":"516 W 36 St",
    "sg:city":"New York",
    "sg:classifiers":[
        {
            "category":"Professional",
            "subcategory":"Business Services",
            "type":"Services"
        }
    ],
    "sg:phone":"+1 212 564 7957",
    "sg:postcode":"10018",
    "sg:province":"NY",
    "sg:tags":[
        "slitting",
        "cutting"
    ],
    "wof:name":"Arista Cutting Contractors",
    "wof:placetype":"venue"
},
  "geometry": {"coordinates":[-73.998955,40.755953],"type":"Point"}
}