{
  "type": "Feature",
  "properties": {
    "iso:country":"US",
    "sg:address":"16 Waller Ave",
    "sg:city":"Ossining",
    "sg:classifiers":[
        {
            "category":"Organizations",
            "subcategory":"Professional Association",
            "type":"Services"
        }
    ],
    "sg:phone":"+1   ",
    "sg:postcode":"10562",
    "sg:province":"NY",
    "sg:tags":[
        "business"
    ],
    "wof:name":"Portuguese Club of Ossining",
    "wof:placetype":"venue"
},
  "geometry": {"coordinates":[-73.863517,41.15914],"type":"Point"}
}