{
  "type": "Feature",
  "properties": {
    "addr:full":"6 Commercial St Hicksville NY 11801",
    "addr:housenumber":"6",
    "addr:postcode":"11801",
    "addr:street":"Commercial St",
    "iso:country":"US",
    "sg:address":"6 Commercial St",
    "sg:city":"Hicksville",
    "sg:classifiers":[
        {
            "category":"Professional",
            "type":"Services"
        }
    ],
    "sg:phone":"+1 516 433 4954",
    "sg:postcode":"11801",
    "sg:province":"NY",
    "sg:tags":[
        "establishment"
    ],
    "wof:name":"G T Copa",
    "wof:placetype":"venue"
},
  "geometry": {"coordinates":[-73.50896899999999,40.760657],"type":"Point"}
}