{
  "type": "Feature",
  "properties": {
    "addr:full":"1365 E 2nd St Jamestown NY 14701",
    "addr:housenumber":"1365",
    "addr:postcode":"14701",
    "addr:street":"E 2Nd St",
    "iso:country":"US",
    "sg:address":"1365 E 2nd St",
    "sg:city":"Jamestown",
    "sg:classifiers":[
        {
            "category":"Wholesale",
            "subcategory":"Electrical",
            "type":"Manufacturing & Wholesale Goods"
        }
    ],
    "sg:phone":"+1 716 664 6200",
    "sg:postcode":"14701",
    "sg:province":"NY",
    "sg:tags":[
        "communication",
        "radio",
        "system"
    ],
    "wof:name":"Eagle Radio Technologies",
    "wof:placetype":"venue"
},
  "geometry": {"coordinates":[-79.210235,42.113441],"type":"Point"}
}