{
  "type": "Feature",
  "properties": {
    "iso:country":"US",
    "sg:address":"41 Perry Street",
    "sg:city":"New York",
    "sg:classifiers":[
        {
            "category":"Shopping",
            "subcategory":"Clothing, Apparel, & Fashions",
            "type":"Retail Goods"
        }
    ],
    "sg:phone":"+1 212 675 1994",
    "sg:postcode":"10014",
    "sg:province":"NY",
    "sg:tags":[
        "accessory",
        "clothing",
        "women's"
    ],
    "wof:name":"Geminola",
    "wof:placetype":"venue"
},
  "geometry": {"coordinates":[-74.002852,40.735598],"type":"Point"}
}