{
  "type": "Feature",
  "properties": {
    "addr:full":"333 Mamaroneck Ave White Plains NY 10605",
    "addr:housenumber":"333",
    "addr:postcode":"10605",
    "addr:street":"Mamaroneck Ave",
    "iso:country":"US",
    "sg:address":"333 Mamaroneck Ave",
    "sg:city":"White Plains",
    "sg:classifiers":[
        {
            "category":"Education",
            "subcategory":"Special Training",
            "type":"Public Place"
        }
    ],
    "sg:phone":"+1 914 949 3172",
    "sg:postcode":"10605",
    "sg:province":"NY",
    "sg:tags":[
        "reading",
        "instruction",
        "improvement"
    ],
    "wof:name":"KWIK Learning",
    "wof:placetype":"venue"
},
  "geometry": {"coordinates":[-73.763448,41.025235],"type":"Point"}
}