{
  "type": "Feature",
  "properties": {
    "iso:country":"US",
    "sg:address":"301 Valley Dr",
    "sg:city":"Syracuse",
    "sg:classifiers":[
        {
            "category":"Social Services",
            "subcategory":"Child Care",
            "type":"Services"
        }
    ],
    "sg:phone":"+1 315 468 1632",
    "sg:postcode":"13207",
    "sg:province":"NY",
    "sg:tags":[
        "kindergarten",
        "academic",
        "school"
    ],
    "wof:name":"Parkside Children's Ctr",
    "wof:placetype":"venue"
},
  "geometry": {"coordinates":[-76.15957899999999,43.015311],"type":"Point"}
}