{
  "type": "Feature",
  "properties": {
    "addr:full":"Carlton Avenue and Park Place Brooklyn NY 11238",
    "addr:postcode":"11238",
    "addr:street":"Carlton Avenue And Park Place",
    "iso:country":"US",
    "sg:address":"Carlton Avenue and Park Place",
    "sg:city":"Brooklyn",
    "sg:classifiers":[
        {
            "category":"Communications",
            "subcategory":"Film & Video Production",
            "type":"Services"
        }
    ],
    "sg:postcode":"11238",
    "sg:province":"NY",
    "sg:tags":[
        "video/film"
    ],
    "wof:name":"Oookic Productions",
    "wof:placetype":"venue"
},
  "geometry": {"coordinates":[-73.972347,40.677447],"type":"Point"}
}