{
  "type": "Feature",
  "properties": {
    "addr:full":"149 Hester St New York NY 10002",
    "addr:housenumber":"149",
    "addr:postcode":"10002",
    "addr:street":"Hester St",
    "iso:country":"US",
    "sg:address":"149 Hester St",
    "sg:city":"New York",
    "sg:classifiers":[
        {
            "category":"Health Services",
            "subcategory":"Doctor",
            "type":"Services"
        }
    ],
    "sg:phone":"+1   ",
    "sg:postcode":"10002",
    "sg:province":"NY",
    "wof:name":"Chort Wong Dr",
    "wof:placetype":"venue"
},
  "geometry": {"coordinates":[-73.99442500000001,40.716966],"type":"Point"}
}