{
  "type": "Feature",
  "properties": {
    "iso:country":"US",
    "sg:address":"324 Butler Rd",
    "sg:city":"Poland",
    "sg:classifiers":[
        {
            "category":"Insurance",
            "subcategory":"Hazard Insurance",
            "type":"Services"
        }
    ],
    "sg:phone":"+1 315 269 4686",
    "sg:postcode":"13431",
    "sg:province":"NY",
    "wof:name":"Noreaster Insurance",
    "wof:placetype":"venue"
},
  "geometry": {"coordinates":[-75.05677799999999,43.154319],"type":"Point"}
}