{
  "type": "Feature",
  "properties": {
    "addr:full":"1388 Briggs Rd Penn Yan NY 14527",
    "addr:housenumber":"1388",
    "addr:postcode":"14527",
    "addr:street":"Briggs Rd",
    "iso:country":"US",
    "sg:address":"1388 Briggs Rd",
    "sg:city":"Penn Yan",
    "sg:phone":"+1 315 536 6948",
    "sg:postcode":"14527",
    "sg:province":"NY",
    "sg:tags":[
        "farm",
        "field",
        "corn",
        "crop"
    ],
    "wof:name":"Curell Farms",
    "wof:placetype":"venue"
},
  "geometry": {"coordinates":[-77.113843,42.697407],"type":"Point"}
}