{
  "type": "Feature",
  "properties": {
    "iso:country":"US",
    "sg:address":"52 Mariaville Rd",
    "sg:city":"Schenectady",
    "sg:classifiers":[
        {
            "category":"Real Estate",
            "subcategory":"Real Estate Agent",
            "type":"Services"
        }
    ],
    "sg:phone":"+1 518 372 7306",
    "sg:postcode":"12306",
    "sg:province":"NY",
    "wof:name":"R & M Associates",
    "wof:placetype":"venue"
},
  "geometry": {"coordinates":[-73.99482999999999,42.793537],"type":"Point"}
}