{
  "type": "Feature",
  "properties": {
    "iso:country":"US",
    "sg:address":"102 Leroy St",
    "sg:city":"Binghamton",
    "sg:classifiers":[
        {
            "category":"Building & Trades",
            "subcategory":"Construction",
            "type":"Services"
        }
    ],
    "sg:phone":"+1 607 772 6778",
    "sg:postcode":"13905",
    "sg:province":"NY",
    "sg:tags":[
        "hanging",
        "contractor"
    ],
    "wof:name":"Butchs Painting",
    "wof:placetype":"venue"
},
  "geometry": {"coordinates":[-75.93009600000001,42.095646],"type":"Point"}
}