{
  "type": "Feature",
  "properties": {
    "addr:full":"5217 20th Avenue Brooklyn NY 11204",
    "addr:housenumber":"5217",
    "addr:postcode":"11204",
    "addr:street":"20Th Avenue",
    "iso:country":"US",
    "sg:address":"5217 20th Avenue",
    "sg:city":"Brooklyn",
    "sg:classifiers":[
        {
            "category":"Real Estate",
            "subcategory":"Real Estate Services",
            "type":"Services"
        }
    ],
    "sg:phone":"+1 718 331 4414",
    "sg:postcode":"11204",
    "sg:province":"NY",
    "sg:tags":[
        "management",
        "property"
    ],
    "wof:name":"552 Associates",
    "wof:placetype":"venue"
},
  "geometry": {"coordinates":[-73.97847400000001,40.623449],"type":"Point"}
}