{
  "type": "Feature",
  "properties": {
    "addr:full":"450 E 20th St New York NY 10009",
    "addr:housenumber":"450",
    "addr:postcode":"10009",
    "addr:street":"E 20Th St",
    "iso:country":"US",
    "sg:address":"450 E 20th St",
    "sg:city":"New York",
    "sg:classifiers":[
        {
            "category":"Wholesale",
            "subcategory":"Durable Goods & Equipment",
            "type":"Manufacturing & Wholesale Goods"
        }
    ],
    "sg:phone":"+1 516 938 7771",
    "sg:postcode":"10009",
    "sg:province":"NY",
    "sg:tags":[
        "representative",
        "manufacturer"
    ],
    "wof:name":"Leicht Apparel",
    "wof:placetype":"venue"
},
  "geometry": {"coordinates":[-73.978101,40.73416],"type":"Point"}
}