{
  "type": "Feature",
  "properties": {
    "iso:country":"US",
    "sg:address":"1196 Ave of the Americas",
    "sg:city":"New York",
    "sg:classifiers":[
        {
            "category":"Manufacturing",
            "subcategory":"Jewelry",
            "type":"Manufacturing & Wholesale Goods"
        }
    ],
    "sg:phone":"+1   ",
    "sg:postcode":"10036",
    "sg:province":"NY",
    "sg:tags":[
        "material",
        "mfg"
    ],
    "wof:name":"Eddies Diamonds",
    "wof:placetype":"venue"
},
  "geometry": {"coordinates":[-73.982039,40.757421],"type":"Point"}
}