{
  "type": "Feature",
  "properties": {
    "iso:country":"US",
    "sg:address":"1680 59th St",
    "sg:city":"Brooklyn",
    "sg:classifiers":[
        {
            "category":"Organizations",
            "subcategory":"Religious Organization",
            "type":"Services"
        }
    ],
    "sg:phone":"+1 718 236 1666",
    "sg:postcode":"11204",
    "sg:province":"NY",
    "sg:tags":[
        "clergy"
    ],
    "wof:name":"Y Israel",
    "wof:placetype":"venue"
},
  "geometry": {"coordinates":[-73.990056,40.624791],"type":"Point"}
}