{
  "type": "Feature",
  "properties": {
    "addr:full":"327 Pontoon Bridge Rd Massena NY 13662",
    "addr:housenumber":"327",
    "addr:postcode":"13662",
    "addr:street":"Pontoon Bridge Rd",
    "iso:country":"US",
    "sg:address":"327 Pontoon Bridge Rd",
    "sg:city":"Massena",
    "sg:classifiers":[
        {
            "category":"Retail",
            "subcategory":"Auto Repair",
            "type":"Services"
        }
    ],
    "sg:phone":"+1 315 769 6331",
    "sg:postcode":"13662",
    "sg:province":"NY",
    "sg:tags":[
        "repairing",
        "automobile"
    ],
    "wof:name":"Page Automotive",
    "wof:placetype":"venue"
},
  "geometry": {"coordinates":[-74.903946,44.949259],"type":"Point"}
}