{
  "type": "Feature",
  "properties": {
    "iso:country":"US",
    "sg:address":"1 Center St",
    "sg:city":"Cuba",
    "sg:classifiers":[
        {
            "category":"Shopping",
            "subcategory":"Clothing, Apparel, & Fashions",
            "type":"Retail Goods"
        }
    ],
    "sg:phone":"+1 585 968 0858",
    "sg:postcode":"14727",
    "sg:province":"NY",
    "wof:name":"Western New York & Pa Rr",
    "wof:placetype":"venue"
},
  "geometry": {"coordinates":[-78.27909099999999,42.221916],"type":"Point"}
}