{
  "type": "Feature",
  "properties": {
    "iso:country":"US",
    "sg:address":"1620 Westchester Ave",
    "sg:city":"Bronx",
    "sg:classifiers":[
        {
            "category":"Banks & Credit Unions",
            "subcategory":"Bank",
            "type":"Services"
        },
        {
            "category":"Banks & Credit Unions",
            "subcategory":"Financial Services",
            "type":"Services"
        }
    ],
    "sg:phone":"+1 800 900 9000",
    "sg:postcode":"10472",
    "sg:province":"NY",
    "sg:tags":[
        "commercial",
        "loan",
        "internet",
        "saving",
        "banking"
    ],
    "sg:website":"http://www.bofa.com",
    "wof:name":"Bank Of America",
    "wof:placetype":"venue"
},
  "geometry": {"coordinates":[-73.874588,40.82951],"type":"Point"}
}