{
  "type": "Feature",
  "properties": {
    "addr:full":"279 S Broadway Hicksville NY 11801",
    "addr:housenumber":"279",
    "addr:postcode":"11801",
    "addr:street":"S Broadway",
    "iso:country":"US",
    "sg:address":"279 S Broadway",
    "sg:city":"Hicksville",
    "sg:classifiers":[
        {
            "category":"Fast Food",
            "type":"Food & Drink"
        },
        {
            "category":"Restaurant",
            "type":"Food & Drink"
        }
    ],
    "sg:phone":"+1 516 935 0209",
    "sg:postcode":"11801",
    "sg:province":"NY",
    "sg:tags":[
        "mexican"
    ],
    "sg:website":"www.tacobell.com",
    "wof:name":"Taco Bell",
    "wof:placetype":"venue"
},
  "geometry": {"coordinates":[-73.516982,40.762394],"type":"Point"}
}