{
  "type": "Feature",
  "properties": {
    "iso:country":"US",
    "sg:address":"9 Lent Ave",
    "sg:city":"Le Roy",
    "sg:classifiers":[
        {
            "category":"Manufacturing",
            "subcategory":"Furniture",
            "type":"Manufacturing & Wholesale Goods"
        }
    ],
    "sg:phone":"+1   ",
    "sg:postcode":"14482",
    "sg:province":"NY",
    "sg:tags":[
        "mfg"
    ],
    "wof:name":"Icon Design LLC",
    "wof:placetype":"venue"
},
  "geometry": {"coordinates":[-77.997704,42.980167],"type":"Point"}
}