{
  "type": "Feature",
  "properties": {
    "iso:country":"US",
    "sg:address":"261 Adelphi St",
    "sg:city":"Brooklyn",
    "sg:classifiers":[
        {
            "category":"Real Estate",
            "subcategory":"Real Estate Agent",
            "type":"Services"
        }
    ],
    "sg:phone":"+1 718 624 6084",
    "sg:postcode":"11205",
    "sg:province":"NY",
    "wof:name":"Century 21",
    "wof:placetype":"venue"
},
  "geometry": {"coordinates":[-73.971197,40.689743],"type":"Point"}
}