{
  "type": "Feature",
  "properties": {
    "iso:country":"US",
    "sg:address":"1360 55th St",
    "sg:city":"Brooklyn",
    "sg:classifiers":[
        {
            "category":"Organizations",
            "subcategory":"Religious Organization",
            "type":"Services"
        }
    ],
    "sg:phone":"+1 718 436 8084",
    "sg:postcode":"11219",
    "sg:province":"NY",
    "sg:tags":[
        "clergy"
    ],
    "wof:name":"Efraim Stein",
    "wof:placetype":"venue"
},
  "geometry": {"coordinates":[-73.99441,40.631036],"type":"Point"}
}