{
  "type": "Feature",
  "properties": {
    "addr:full":"67 Universe Dr Levittown NY 11756",
    "addr:housenumber":"67",
    "addr:postcode":"11756",
    "addr:street":"Universe Dr",
    "iso:country":"US",
    "sg:address":"67 Universe Dr",
    "sg:city":"Levittown",
    "sg:classifiers":[
        {
            "category":"Freight",
            "type":"Transportation"
        }
    ],
    "sg:phone":"+1 516 735 3175",
    "sg:postcode":"11756",
    "sg:province":"NY",
    "sg:tags":[
        "operator",
        "mover",
        "local",
        "trucking"
    ],
    "wof:name":"J Johnson Jr Moving",
    "wof:placetype":"venue"
},
  "geometry": {"coordinates":[-73.49835400000001,40.732821],"type":"Point"}
}