{
  "type": "Feature",
  "properties": {
    "addr:full":"2060 Oneil Rd Macedon NY 14502",
    "addr:housenumber":"2060",
    "addr:postcode":"14502",
    "addr:street":"Oneil Rd",
    "iso:country":"US",
    "sg:address":"2060 Oneil Rd",
    "sg:city":"Macedon",
    "sg:classifiers":[
        {
            "category":"Wholesale",
            "subcategory":"Chemicals & Plastics",
            "type":"Manufacturing & Wholesale Goods"
        }
    ],
    "sg:phone":"+1 716 329 7994",
    "sg:postcode":"14502",
    "sg:province":"NY",
    "sg:tags":[
        "distributor",
        "bottled",
        "gas"
    ],
    "wof:name":"Liss America LLC",
    "wof:placetype":"venue"
},
  "geometry": {"coordinates":[-77.29084899999999,43.075685],"type":"Point"}
}