{
  "type": "Feature",
  "properties": {
    "addr:full":"107 Van Buren St Brooklyn NY 11221",
    "addr:housenumber":"107",
    "addr:postcode":"11221",
    "addr:street":"Van Buren St",
    "iso:country":"US",
    "sg:address":"107 Van Buren St",
    "sg:city":"Brooklyn",
    "sg:classifiers":[
        {
            "category":"Social Services",
            "subcategory":"Child Care",
            "type":"Services"
        }
    ],
    "sg:phone":"+1 718 453 4879",
    "sg:postcode":"11221",
    "sg:province":"NY",
    "sg:tags":[
        "day"
    ],
    "wof:name":"Serani's Daycare",
    "wof:placetype":"venue"
},
  "geometry": {"coordinates":[-73.941479,40.690398],"type":"Point"}
}