{
  "type": "Feature",
  "properties": {
    "iso:country":"US",
    "sg:address":"18 Summit Ave",
    "sg:city":"Larchmont",
    "sg:classifiers":[
        {
            "category":"Professional",
            "subcategory":"Business Services",
            "type":"Services"
        }
    ],
    "sg:phone":"+1 914 834 0449",
    "sg:postcode":"10538",
    "sg:province":"NY",
    "sg:tags":[
        "commercial",
        "designers-industrial"
    ],
    "wof:name":"Summit Design Associates",
    "wof:placetype":"venue"
},
  "geometry": {"coordinates":[-73.75517600000001,40.932227],"type":"Point"}
}