{
  "type": "Feature",
  "properties": {
    "iso:country":"US",
    "sg:address":"783 Iradell Rd",
    "sg:city":"Trumansburg",
    "sg:phone":"+1 607 387 6156",
    "sg:postcode":"14886",
    "sg:province":"NY",
    "sg:tags":[
        "wheat",
        "farm",
        "cash",
        "crop",
        "field",
        "grain"
    ],
    "wof:name":"Fieldstone Farms",
    "wof:placetype":"venue"
},
  "geometry": {"coordinates":[-76.673051,42.478677],"type":"Point"}
}