{
  "type": "Feature",
  "properties": {
    "addr:full":"300 High Point Rd Hartsdale NY 10530",
    "addr:housenumber":"300",
    "addr:postcode":"10530",
    "addr:street":"High Point Rd",
    "iso:country":"US",
    "sg:address":"300 High Point Rd",
    "sg:city":"Hartsdale",
    "sg:classifiers":[
        {
            "category":"Building & Trades",
            "subcategory":"Construction",
            "type":"Services"
        }
    ],
    "sg:phone":"+1 914 949 6181",
    "sg:postcode":"10530",
    "sg:province":"NY",
    "sg:tags":[
        "concrete",
        "contractor"
    ],
    "wof:name":"A & A Concrete & Construction",
    "wof:placetype":"venue"
},
  "geometry": {"coordinates":[-73.820674,41.013272],"type":"Point"}
}