{
  "type": "Feature",
  "properties": {
    "addr:full":"158 Grand St New York NY 10013",
    "addr:housenumber":"158",
    "addr:postcode":"10013",
    "addr:street":"Grand St",
    "iso:country":"US",
    "sg:address":"158 Grand St",
    "sg:city":"New York",
    "sg:classifiers":[
        {
            "category":"Real Estate",
            "subcategory":"Real Estate Agent",
            "type":"Services"
        }
    ],
    "sg:phone":"+1 212 226 0452",
    "sg:postcode":"10013",
    "sg:province":"NY",
    "wof:name":"158 Grand Realty Co",
    "wof:placetype":"venue"
},
  "geometry": {"coordinates":[-73.998728,40.720004],"type":"Point"}
}