{
  "type": "Feature",
  "properties": {
    "addr:full":"350 Motor Pkwy Hauppauge NY 11788",
    "addr:housenumber":"350",
    "addr:postcode":"11788",
    "addr:street":"Motor Pkwy",
    "iso:country":"US",
    "sg:address":"350 Motor Pkwy",
    "sg:city":"Hauppauge",
    "sg:classifiers":[
        {
            "category":"Professional",
            "subcategory":"Accounting & Tax Preparation",
            "type":"Services"
        }
    ],
    "sg:phone":"+1 631 951 4066",
    "sg:postcode":"11788",
    "sg:province":"NY",
    "sg:tags":[
        "physician",
        "hospital",
        "billing"
    ],
    "wof:name":"Armanti Assocs Inc",
    "wof:placetype":"venue"
},
  "geometry": {"coordinates":[-73.24091300000001,40.807634],"type":"Point"}
}