{
  "type": "Feature",
  "properties": {
    "iso:country":"US",
    "sg:address":"4 W 47th St",
    "sg:city":"New York",
    "sg:classifiers":[
        {
            "category":"Shopping",
            "subcategory":"Jewelry",
            "type":"Retail Goods"
        }
    ],
    "sg:phone":"+1 212 382 0366",
    "sg:postcode":"10036",
    "sg:province":"NY",
    "wof:name":"Ekstra Rodin Natalia",
    "wof:placetype":"venue"
},
  "geometry": {"coordinates":[-73.978808,40.756745],"type":"Point"}
}