{
  "type": "Feature",
  "properties": {
    "addr:full":"70 Cedar Hill Ave Nyack NY 10960",
    "addr:housenumber":"70",
    "addr:postcode":"10960",
    "addr:street":"Cedar Hill Ave",
    "iso:country":"US",
    "sg:address":"70 Cedar Hill Ave",
    "sg:city":"Nyack",
    "sg:phone":"+1 845 727 1200",
    "sg:postcode":"10960",
    "sg:province":"NY",
    "sg:tags":[
        "equipment",
        "supply"
    ],
    "sg:website":"www.pso2go.com",
    "wof:name":"Beacon Digital Svc",
    "wof:placetype":"venue"
},
  "geometry": {"coordinates":[-73.921396,41.08789],"type":"Point"}
}