{
  "type": "Feature",
  "properties": {
    "addr:full":"10 Terminal Dr Latham NY 12110",
    "addr:housenumber":"10",
    "addr:postcode":"12110",
    "addr:street":"Terminal Dr",
    "iso:country":"US",
    "sg:address":"10 Terminal Dr",
    "sg:city":"Latham",
    "sg:classifiers":[
        {
            "category":"Building & Trades",
            "subcategory":"Construction",
            "type":"Services"
        }
    ],
    "sg:phone":"+1 518 218 0246",
    "sg:postcode":"12110",
    "sg:province":"NY",
    "sg:tags":[
        "hazardous",
        "waste",
        "removal"
    ],
    "wof:name":"Onyx Environmental Inc",
    "wof:placetype":"venue"
},
  "geometry": {"coordinates":[-73.795708,42.732581],"type":"Point"}
}