{
  "type": "Feature",
  "properties": {
    "iso:country":"US",
    "sg:address":"3 Oconnor Ct",
    "sg:city":"Montrose",
    "sg:classifiers":[
        {
            "category":"Wholesale",
            "subcategory":"Machinery & Supplies",
            "type":"Manufacturing & Wholesale Goods"
        }
    ],
    "sg:phone":"+1 914 737 2378",
    "sg:postcode":"10548",
    "sg:province":"NY",
    "sg:tags":[
        "industrial"
    ],
    "wof:name":"Pelican Sales Inc",
    "wof:placetype":"venue"
},
  "geometry": {"coordinates":[-73.937174,41.238154],"type":"Point"}
}