{
  "type": "Feature",
  "properties": {
    "addr:full":"144 Decatur St Brooklyn NY 11233",
    "addr:housenumber":"144",
    "addr:postcode":"11233",
    "addr:street":"Decatur St",
    "iso:country":"US",
    "sg:address":"144 Decatur St",
    "sg:city":"Brooklyn",
    "sg:classifiers":[
        {
            "category":"Shopping",
            "subcategory":"Catalog Store",
            "type":"Retail Goods"
        }
    ],
    "sg:phone":"+1   ",
    "sg:postcode":"11233",
    "sg:province":"NY",
    "sg:tags":[
        "house",
        "mail"
    ],
    "wof:name":"Marchesandaga",
    "wof:placetype":"venue"
},
  "geometry": {"coordinates":[-73.934765,40.681215],"type":"Point"}
}