{
  "type": "Feature",
  "properties": {
    "iso:country":"US",
    "sg:address":"321 Woodmere Blvd",
    "sg:city":"Woodmere",
    "sg:classifiers":[
        {
            "category":"Education",
            "subcategory":"School",
            "type":"Public Place"
        }
    ],
    "sg:phone":"+1 516 295 6280",
    "sg:postcode":"11598",
    "sg:province":"NY",
    "sg:tags":[
        "high",
        "middle",
        "elementary"
    ],
    "wof:name":"Hebrew Academy For Special Children",
    "wof:placetype":"venue"
},
  "geometry": {"coordinates":[-73.714705,40.634259],"type":"Point"}
}