{
  "type": "Feature",
  "properties": {
    "addr:full":"65 Channel Dr Port Washington NY 11050",
    "addr:housenumber":"65",
    "addr:postcode":"11050",
    "addr:street":"Channel Dr",
    "iso:country":"US",
    "sg:address":"65 Channel Dr",
    "sg:city":"Port Washington",
    "sg:classifiers":[
        {
            "category":"Professional",
            "type":"Services"
        }
    ],
    "sg:phone":"+1 516 767 2518",
    "sg:postcode":"11050",
    "sg:province":"NY",
    "sg:tags":[
        "establishment"
    ],
    "wof:name":"Oswald-Ortec",
    "wof:placetype":"venue"
},
  "geometry": {"coordinates":[-73.701623,40.84175],"type":"Point"}
}