{
  "type": "Feature",
  "properties": {
    "iso:country":"US",
    "name:eng_x_preferred":[
        "36 St"
    ],
    "wof:name":"36 St Station",
    "wof:placetype":"venue"
},
  "geometry": {"coordinates":[-73.928781,40.752039],"type":"Point"}
}