{
  "type": "Feature",
  "properties": {
    "iso:country":"US",
    "sg:address":"1289 Union Ave",
    "sg:city":"Newburgh",
    "sg:phone":"+1 845 564 4754",
    "sg:postcode":"12550",
    "sg:province":"NY",
    "sg:tags":[
        "equipment",
        "supply"
    ],
    "sg:website":"www.cafeinternationale.com",
    "wof:name":"Cafe Internationale",
    "wof:placetype":"venue"
},
  "geometry": {"coordinates":[-74.07633199999999,41.545438],"type":"Point"}
}