{
  "type": "Feature",
  "properties": {
    "addr:full":"316 New York Ave Ogdensburg NY 13669",
    "addr:housenumber":"316",
    "addr:postcode":"13669",
    "addr:street":"New York Ave",
    "iso:country":"US",
    "sg:address":"316 New York Ave",
    "sg:city":"Ogdensburg",
    "sg:classifiers":[
        {
            "category":"Health Services",
            "subcategory":"Chiropractor",
            "type":"Services"
        }
    ],
    "sg:phone":"+1 315 394 2225",
    "sg:postcode":"13669",
    "sg:province":"NY",
    "sg:tags":[
        "physician",
        "surgeon"
    ],
    "wof:name":"Springstead, Scott Dc",
    "wof:placetype":"venue"
},
  "geometry": {"coordinates":[-75.49741,44.691442],"type":"Point"}
}