{
  "type": "Feature",
  "properties": {
    "iso:country":"US",
    "sg:address":"971 Southern Boulevard",
    "sg:city":"Bronx",
    "sg:classifiers":[
        {
            "category":"Shopping",
            "subcategory":"Mobile Phones",
            "type":"Retail Goods"
        }
    ],
    "sg:phone":"+1 718 328 2656",
    "sg:postcode":"10459",
    "sg:province":"NY",
    "sg:website":"www.t-mobile.com",
    "wof:name":"T Mobile",
    "wof:placetype":"venue"
},
  "geometry": {"coordinates":[-73.891859,40.822132],"type":"Point"}
}