{
  "type": "Feature",
  "properties": {
    "iso:country":"US",
    "sg:address":"61 Holly St",
    "sg:city":"Yonkers",
    "sg:classifiers":[
        {
            "category":"Travel",
            "subcategory":"Travel Agent",
            "type":"Entertainment"
        }
    ],
    "sg:phone":"+1   ",
    "sg:postcode":"10704",
    "sg:province":"NY",
    "sg:tags":[
        "operator",
        "tour"
    ],
    "wof:name":"Cruises & Tours By Marylen",
    "wof:placetype":"venue"
},
  "geometry": {"coordinates":[-73.871928,40.921204],"type":"Point"}
}