{
  "type": "Feature",
  "properties": {
    "iso:country":"US",
    "sg:address":"85 E Main St",
    "sg:city":"Bay Shore",
    "sg:classifiers":[
        {
            "category":"Shopping",
            "subcategory":"Pharmacy",
            "type":"Retail Goods"
        }
    ],
    "sg:phone":"+1   ",
    "sg:postcode":"11706",
    "sg:province":"NY",
    "wof:name":"Shore Drugs",
    "wof:placetype":"venue"
},
  "geometry": {"coordinates":[-73.245062,40.723522],"type":"Point"}
}