{
  "type": "Feature",
  "properties": {
    "iso:country":"US",
    "sg:address":"234 S Highland Ave",
    "sg:city":"Ossining",
    "sg:classifiers":[
        {
            "category":"Food & Beverages",
            "subcategory":"Liquor & Beverages",
            "type":"Retail Goods"
        }
    ],
    "sg:phone":"+1 914 762 2322",
    "sg:postcode":"10562",
    "sg:province":"NY",
    "wof:name":"Old Country Wine & Liquor",
    "wof:placetype":"venue"
},
  "geometry": {"coordinates":[-73.860997,41.145132],"type":"Point"}
}