{
  "type": "Feature",
  "properties": {
    "addr:full":"404 Utica Avenue Brooklyn NY 11213",
    "addr:housenumber":"404",
    "addr:postcode":"11213",
    "addr:street":"Utica Avenue",
    "iso:country":"US",
    "sg:address":"404 Utica Avenue",
    "sg:city":"Brooklyn",
    "sg:classifiers":[
        {
            "category":"Home & Garden",
            "subcategory":"Carpets & Floor Coverings",
            "type":"Retail Goods"
        }
    ],
    "sg:phone":"+1 718 773 6998",
    "sg:postcode":"11213",
    "sg:province":"NY",
    "sg:tags":[
        "flooring"
    ],
    "wof:name":"Derwyn Carpet & Tiles",
    "wof:placetype":"venue"
},
  "geometry": {"coordinates":[-73.93159799999999,40.665279],"type":"Point"}
}