{
  "type": "Feature",
  "properties": {
    "iso:country":"US",
    "sg:address":"5 W 4th St",
    "sg:city":"Jamestown",
    "sg:classifiers":[
        {
            "category":"Personal",
            "subcategory":"Beauty Salon",
            "type":"Services"
        }
    ],
    "sg:phone":"+1 716 487 9820",
    "sg:postcode":"14701",
    "sg:province":"NY",
    "wof:name":"Nouveau",
    "wof:placetype":"venue"
},
  "geometry": {"coordinates":[-79.242198,42.097113],"type":"Point"}
}