{
  "type": "Feature",
  "properties": {
    "iso:country":"US",
    "sg:address":"1 Deborah Lee Dr",
    "sg:city":"Apalachin",
    "sg:classifiers":[
        {
            "category":"Manufacturing",
            "subcategory":"Printing",
            "type":"Manufacturing & Wholesale Goods"
        }
    ],
    "sg:phone":"+1 607 625 5848",
    "sg:postcode":"13732",
    "sg:province":"NY",
    "sg:tags":[
        "screen"
    ],
    "wof:name":"Youngblood Screen Printing",
    "wof:placetype":"venue"
},
  "geometry": {"coordinates":[-76.11413,42.064047],"type":"Point"}
}