{
  "type": "Feature",
  "properties": {
    "addr:full":"8280 Kanona Rd Avoca NY 14809",
    "addr:housenumber":"8280",
    "addr:postcode":"14809",
    "addr:street":"Kanona Rd",
    "iso:country":"US",
    "sg:address":"8280 Kanona Rd",
    "sg:city":"Avoca",
    "sg:classifiers":[
        {
            "category":"Retail",
            "subcategory":"Auto Repair",
            "type":"Services"
        }
    ],
    "sg:phone":"+1 607 566 3787",
    "sg:postcode":"14809",
    "sg:province":"NY",
    "sg:tags":[
        "truck"
    ],
    "wof:name":"Wilbri Inc",
    "wof:placetype":"venue"
},
  "geometry": {"coordinates":[-77.404263,42.401984],"type":"Point"}
}