{
  "type": "Feature",
  "properties": {
    "iso:country":"US",
    "sg:address":"444 Central Park W",
    "sg:city":"New York",
    "sg:classifiers":[
        {
            "category":"Health Services",
            "subcategory":"Doctor",
            "type":"Services"
        }
    ],
    "sg:phone":"+1 212 665 5900",
    "sg:postcode":"10025",
    "sg:province":"NY",
    "wof:name":"Aaron Harry MD",
    "wof:placetype":"venue"
},
  "geometry": {"coordinates":[-73.96080000000001,40.797001],"type":"Point"}
}