{
  "type": "Feature",
  "properties": {
    "addr:full":"26 Heritage Pl S Nesconset NY 11767",
    "addr:housenumber":"26",
    "addr:postcode":"11767",
    "addr:street":"Heritage Pl S Nesconset",
    "iso:country":"US",
    "sg:address":"26 Heritage Pl S",
    "sg:city":"Nesconset",
    "sg:classifiers":[
        {
            "category":"Building & Trades",
            "subcategory":"Construction",
            "type":"Services"
        }
    ],
    "sg:phone":"+1 631 265 0265",
    "sg:postcode":"11767",
    "sg:province":"NY",
    "sg:tags":[
        "wallcoverings-installation",
        "wallpaper",
        "painting",
        "contractor"
    ],
    "wof:name":"Powerhouse Painting",
    "wof:placetype":"venue"
},
  "geometry": {"coordinates":[-73.14679,40.840839],"type":"Point"}
}