{
  "type": "Feature",
  "properties": {
    "addr:full":"145 Commack Rd Ste Ll10 Commack NY 11725",
    "addr:housenumber":"145",
    "addr:postcode":"11725",
    "addr:street":"Commack Rd Ste Ll10",
    "iso:country":"US",
    "sg:address":"145 Commack Rd Ste Ll10",
    "sg:city":"Commack",
    "sg:classifiers":[
        {
            "category":"Personal",
            "type":"Services"
        },
        {
            "category":"Professional",
            "subcategory":"Business Services",
            "type":"Services"
        }
    ],
    "sg:phone":"+1 516 777 7295",
    "sg:postcode":"11725",
    "sg:province":"NY",
    "sg:tags":[
        "auction",
        "estates-sales",
        "liquidation",
        "appraisal",
        "auctioneer"
    ],
    "sg:website":"http://www.americanassetsonline.com",
    "wof:name":"American Auctions Liquidations Appraisals Inc",
    "wof:placetype":"venue"
},
  "geometry": {"coordinates":[-73.29396800000001,40.839199],"type":"Point"}
}