{
  "type": "Feature",
  "properties": {
    "addr:full":"165 Montague St Brooklyn NY 11201",
    "addr:housenumber":"165",
    "addr:postcode":"11201",
    "addr:street":"Montague St",
    "iso:country":"US",
    "sg:address":"165 Montague St",
    "sg:city":"Brooklyn",
    "sg:classifiers":[
        {
            "category":"Communications",
            "subcategory":"Radio Station",
            "type":"Services"
        }
    ],
    "sg:phone":"+1 718 647 4830",
    "sg:postcode":"11201",
    "sg:province":"NY",
    "wof:name":"2 Am Development Inc",
    "wof:placetype":"venue"
},
  "geometry": {"coordinates":[-73.992771,40.694523],"type":"Point"}
}