{
  "type": "Feature",
  "properties": {
    "addr:full":"101 Cordell Rd Schenectady NY 12304",
    "addr:housenumber":"101",
    "addr:postcode":"12304",
    "addr:street":"Cordell Rd",
    "iso:country":"US",
    "sg:address":"101 Cordell Rd",
    "sg:city":"Schenectady",
    "sg:classifiers":[
        {
            "category":"Banks & Credit Unions",
            "subcategory":"Bank",
            "type":"Services"
        }
    ],
    "sg:phone":"+1 518 346 3381",
    "sg:postcode":"12304",
    "sg:province":"NY",
    "sg:tags":[
        "loan",
        "real estate"
    ],
    "wof:name":"First Alternative",
    "wof:placetype":"venue"
},
  "geometry": {"coordinates":[-73.89810199999999,42.759963],"type":"Point"}
}