{
  "type": "Feature",
  "properties": {
    "addr:full":"23 Westlake Dr Valhalla NY 10595",
    "addr:housenumber":"23",
    "addr:postcode":"10595",
    "addr:street":"Westlake Dr",
    "iso:country":"US",
    "sg:address":"23 Westlake Dr",
    "sg:city":"Valhalla",
    "sg:classifiers":[
        {
            "category":"Professional",
            "subcategory":"Lawyer & Legal Services",
            "type":"Services"
        }
    ],
    "sg:phone":"+1   ",
    "sg:postcode":"10595",
    "sg:province":"NY",
    "wof:name":"Phillip A Grimaldi Jr",
    "wof:placetype":"venue"
},
  "geometry": {"coordinates":[-73.774771,41.082885],"type":"Point"}
}