{
  "type": "Feature",
  "properties": {
    "iso:country":"US",
    "sg:address":"30 Old Riverhead Rd",
    "sg:city":"Westhampton Beach",
    "sg:classifiers":[
        {
            "category":"Retail",
            "subcategory":"Auto Repair",
            "type":"Services"
        }
    ],
    "sg:phone":"+1   ",
    "sg:postcode":"11978",
    "sg:province":"NY",
    "sg:tags":[
        "general",
        "supply"
    ],
    "wof:name":"Angelos Auto Works Inc",
    "wof:placetype":"venue"
},
  "geometry": {"coordinates":[-72.64684800000001,40.823664],"type":"Point"}
}