{
  "type": "Feature",
  "properties": {
    "addr:full":"22 Charles Colman Blvd Pawling NY 12564",
    "addr:housenumber":"22",
    "addr:postcode":"12564",
    "addr:street":"Charles Colman Blvd",
    "iso:country":"US",
    "sg:address":"22 Charles Colman Blvd",
    "sg:city":"Pawling",
    "sg:classifiers":[
        {
            "category":"Shopping",
            "subcategory":"Books",
            "type":"Retail Goods"
        }
    ],
    "sg:phone":"+1   ",
    "sg:postcode":"12564",
    "sg:province":"NY",
    "wof:name":"Book Cove",
    "wof:placetype":"venue"
},
  "geometry": {"coordinates":[-73.601321,41.563552],"type":"Point"}
}