{
  "type": "Feature",
  "properties": {
    "iso:country":"US",
    "sg:address":"125 E Terrace Ave",
    "sg:city":"Lakewood",
    "sg:classifiers":[
        {
            "category":"Health Services",
            "subcategory":"Doctor",
            "type":"Services"
        },
        {
            "category":"Health Services",
            "subcategory":"Hospital",
            "type":"Services"
        }
    ],
    "sg:phone":"+1 716 763 9675",
    "sg:postcode":"14750",
    "sg:province":"NY",
    "sg:tags":[
        "consultant",
        "medical",
        "practice",
        "nursing",
        "home"
    ],
    "wof:name":"Three Circles",
    "wof:placetype":"venue"
},
  "geometry": {"coordinates":[-79.315735,42.104323],"type":"Point"}
}