{
  "type": "Feature",
  "properties": {
    "iso:country":"US",
    "sg:address":"118 Ivy St",
    "sg:city":"Jamestown",
    "sg:classifiers":[
        {
            "category":"Shopping",
            "subcategory":"Bicycles & Sporting Goods",
            "type":"Retail Goods"
        }
    ],
    "sg:phone":"+1   ",
    "sg:postcode":"14701",
    "sg:province":"NY",
    "wof:name":"Bc & T TEC Scuba",
    "wof:placetype":"venue"
},
  "geometry": {"coordinates":[-79.231092,42.079725],"type":"Point"}
}