{
  "type": "Feature",
  "properties": {
    "addr:full":"25 Slocum Ave Tappan NY 10983",
    "addr:housenumber":"25",
    "addr:postcode":"10983",
    "addr:street":"Slocum Ave",
    "iso:country":"US",
    "sg:address":"25 Slocum Ave",
    "sg:city":"Tappan",
    "sg:classifiers":[
        {
            "category":"Professional",
            "type":"Services"
        }
    ],
    "sg:phone":"+1   ",
    "sg:postcode":"10983",
    "sg:province":"NY",
    "wof:name":"Take Care",
    "wof:placetype":"venue"
},
  "geometry": {"coordinates":[-73.93749099999999,41.0216],"type":"Point"}
}