{
  "type": "Feature",
  "properties": {
    "iso:country":"US",
    "sg:address":"236 Mennella Rd",
    "sg:city":"Poughquag",
    "sg:classifiers":[
        {
            "category":"Professional",
            "subcategory":"Computer Services",
            "type":"Services"
        }
    ],
    "sg:phone":"+1 845 724 3039",
    "sg:postcode":"12570",
    "sg:province":"NY",
    "sg:tags":[
        "design",
        "system",
        "programing",
        "custom"
    ],
    "wof:name":"Enzus Inc",
    "wof:placetype":"venue"
},
  "geometry": {"coordinates":[-73.66448099999999,41.640893],"type":"Point"}
}