{
  "type": "Feature",
  "properties": {
    "iso:country":"US",
    "sg:address":"201 Beach 116th St",
    "sg:city":"Rockaway Park",
    "sg:classifiers":[
        {
            "category":"Deli",
            "type":"Food & Drink"
        }
    ],
    "sg:postcode":"11694",
    "sg:province":"NY",
    "wof:name":"Rockaway Park Deli and Grocery",
    "wof:placetype":"venue"
},
  "geometry": {"coordinates":[-73.837284,40.579783],"type":"Point"}
}