{
  "type": "Feature",
  "properties": {
    "addr:full":"868 E 180th Street Bronx NY 10460",
    "addr:housenumber":"868",
    "addr:postcode":"10460",
    "addr:street":"E 180Th Street",
    "iso:country":"US",
    "sg:address":"868 E 180th Street",
    "sg:city":"Bronx",
    "sg:classifiers":[
        {
            "category":"Shopping",
            "subcategory":"Florist",
            "type":"Retail Goods"
        }
    ],
    "sg:phone":"+1 718 220 8309",
    "sg:postcode":"10460",
    "sg:province":"NY",
    "wof:name":"Lupitas Flower Shop",
    "wof:placetype":"venue"
},
  "geometry": {"coordinates":[-73.883194,40.845236],"type":"Point"}
}