{
  "type": "Feature",
  "properties": {
    "addr:full":"318 E 106th St New York NY 10029",
    "addr:housenumber":"318",
    "addr:postcode":"10029",
    "addr:street":"E 106Th St",
    "iso:country":"US",
    "sg:address":"318 E 106th St",
    "sg:city":"New York",
    "sg:classifiers":[
        {
            "category":"Food & Beverages",
            "subcategory":"Groceries & Convenience Stores",
            "type":"Retail Goods"
        }
    ],
    "sg:phone":"+1   ",
    "sg:postcode":"10029",
    "sg:province":"NY",
    "wof:name":"318 Supermarket",
    "wof:placetype":"venue"
},
  "geometry": {"coordinates":[-73.942435,40.790624],"type":"Point"}
}