{
  "type": "Feature",
  "properties": {
    "addr:full":"81 State St Binghamton NY 13901",
    "addr:housenumber":"81",
    "addr:postcode":"13901",
    "addr:street":"State St",
    "iso:country":"US",
    "sg:address":"81 State St",
    "sg:city":"Binghamton",
    "sg:classifiers":[
        {
            "category":"Shopping",
            "subcategory":"Clothing, Apparel, & Fashions",
            "type":"Retail Goods"
        }
    ],
    "sg:phone":"+1 607 722 1745",
    "sg:postcode":"13901",
    "sg:province":"NY",
    "wof:name":"Boomerang Clothing Co",
    "wof:placetype":"venue"
},
  "geometry": {"coordinates":[-75.912582,42.097662],"type":"Point"}
}