{
  "type": "Feature",
  "properties": {
    "addr:full":"1309 Avenue U Brooklyn NY 11229",
    "addr:housenumber":"1309",
    "addr:postcode":"11229",
    "addr:street":"Avenue U",
    "iso:country":"US",
    "sg:address":"1309 Avenue U",
    "sg:city":"Brooklyn",
    "sg:classifiers":[
        {
            "category":"Insurance",
            "subcategory":"Health Insurance",
            "type":"Services"
        }
    ],
    "sg:phone":"+1 718 645 2222",
    "sg:postcode":"11229",
    "sg:province":"NY",
    "sg:tags":[
        "market"
    ],
    "wof:name":"Wealth of Health Nutrition Center",
    "wof:placetype":"venue"
},
  "geometry": {"coordinates":[-73.95787,40.598786],"type":"Point"}
}