{
  "type": "Feature",
  "properties": {
    "iso:country":"US",
    "sg:address":"83 Thomas St",
    "sg:city":"Brentwood",
    "sg:classifiers":[
        {
            "category":"Building & Trades",
            "subcategory":"Construction",
            "type":"Services"
        }
    ],
    "sg:phone":"+1 631 231 9352",
    "sg:postcode":"11717",
    "sg:province":"NY",
    "sg:tags":[
        "general",
        "contractor"
    ],
    "wof:name":"RDC Construction",
    "wof:placetype":"venue"
},
  "geometry": {"coordinates":[-73.26227,40.805784],"type":"Point"}
}