{
  "type": "Feature",
  "properties": {
    "addr:full":"1083 Sheepshead Bay Rd Brooklyn NY 11229",
    "addr:housenumber":"1083",
    "addr:postcode":"11229",
    "addr:street":"Sheepshead Bay Rd",
    "iso:country":"US",
    "sg:address":"1083 Sheepshead Bay Rd",
    "sg:city":"Brooklyn",
    "sg:classifiers":[
        {
            "category":"Real Estate",
            "subcategory":"Real Estate Agent",
            "type":"Services"
        }
    ],
    "sg:phone":"+1 718 891 3103",
    "sg:postcode":"11229",
    "sg:province":"NY",
    "wof:name":"1083 87 Realty Corp",
    "wof:placetype":"venue"
},
  "geometry": {"coordinates":[-73.95778199999999,40.592383],"type":"Point"}
}