{
  "type": "Feature",
  "properties": {
    "iso:country":"US",
    "sg:address":"30 Kingsley Rd",
    "sg:city":"Huntington",
    "sg:classifiers":[
        {
            "category":"Wholesale",
            "subcategory":"Non-durable Goods",
            "type":"Manufacturing & Wholesale Goods"
        }
    ],
    "sg:phone":"+1 631 367 9574",
    "sg:postcode":"11743",
    "sg:province":"NY",
    "wof:name":"R O L Sales",
    "wof:placetype":"venue"
},
  "geometry": {"coordinates":[-73.44099199999999,40.820167],"type":"Point"}
}