{
  "type": "Feature",
  "properties": {
    "addr:full":"427 Bedford Rd Pleasantville NY 10570",
    "addr:housenumber":"427",
    "addr:postcode":"10570",
    "addr:street":"Bedford Rd",
    "iso:country":"US",
    "sg:address":"427 Bedford Rd",
    "sg:city":"Pleasantville",
    "sg:classifiers":[
        {
            "category":"Banks & Credit Unions",
            "subcategory":"Investment Brokerage",
            "type":"Services"
        }
    ],
    "sg:phone":"+1 914 747 0810",
    "sg:postcode":"10570",
    "sg:province":"NY",
    "sg:tags":[
        "investing",
        "consultant",
        "planning",
        "financial"
    ],
    "sg:website":"www.ameripriseadvisors.com",
    "wof:name":"Ameriprise Financial Advisors",
    "wof:placetype":"venue"
},
  "geometry": {"coordinates":[-73.790233,41.134557],"type":"Point"}
}