{
  "type": "Feature",
  "properties": {
    "addr:full":"554 Seneca Avenue Ridgewood NY 11385",
    "addr:housenumber":"554",
    "addr:postcode":"11385",
    "addr:street":"Seneca Avenue",
    "iso:country":"US",
    "sg:address":"554 Seneca Avenue",
    "sg:city":"Ridgewood",
    "sg:classifiers":[
        {
            "category":"Personal",
            "subcategory":"Barber",
            "type":"Services"
        }
    ],
    "sg:phone":"+1 718 418 0739",
    "sg:postcode":"11385",
    "sg:province":"NY",
    "wof:name":"Seneca Barbershop",
    "wof:placetype":"venue"
},
  "geometry": {"coordinates":[-73.911349,40.704954],"type":"Point"}
}