{
  "type": "Feature",
  "properties": {
    "iso:country":"US",
    "sg:address":"3300 Chambers Rd",
    "sg:city":"Horseheads",
    "sg:classifiers":[
        {
            "category":"Shopping",
            "subcategory":"Optical Goods",
            "type":"Retail Goods"
        },
        {
            "category":"Shopping",
            "subcategory":"Optician",
            "type":"Retail Goods"
        },
        {
            "category":"Health Services",
            "subcategory":"Optometrist",
            "type":"Services"
        },
        {
            "category":"Personal",
            "subcategory":"Shoe Repair & Shine",
            "type":"Services"
        }
    ],
    "sg:phone":"+1 607 739 2677",
    "sg:postcode":"14845",
    "sg:province":"NY",
    "sg:tags":[
        "eyeglass",
        "sunglass"
    ],
    "sg:website":"http://",
    "wof:name":"Sears Optical",
    "wof:placetype":"venue"
},
  "geometry": {"coordinates":[-76.878197,42.159519],"type":"Point"}
}