{
  "type": "Feature",
  "properties": {
    "iso:country":"US",
    "sg:address":"24 Irving Ave",
    "sg:city":"Granville",
    "sg:classifiers":[
        {
            "category":"Food & Beverages",
            "subcategory":"Groceries & Convenience Stores",
            "type":"Retail Goods"
        }
    ],
    "sg:phone":"+1   ",
    "sg:postcode":"12832",
    "sg:province":"NY",
    "wof:name":"Supleys Grocery",
    "wof:placetype":"venue"
},
  "geometry": {"coordinates":[-73.269091,43.403732],"type":"Point"}
}