{
  "type": "Feature",
  "properties": {
    "iso:country":"US",
    "sg:address":"1023 65th St",
    "sg:city":"Brooklyn",
    "sg:classifiers":[
        {
            "category":"Building & Trades",
            "subcategory":"Construction",
            "type":"Services"
        }
    ],
    "sg:phone":"+1 718 680 0628",
    "sg:postcode":"11219",
    "sg:province":"NY",
    "sg:tags":[
        "contractor"
    ],
    "wof:name":"Avarino Tile & Marble Inc",
    "wof:placetype":"venue"
},
  "geometry": {"coordinates":[-74.006254,40.629001],"type":"Point"}
}