{
  "type": "Feature",
  "properties": {
    "addr:full":"222 Riverside Ave Buffalo NY 14207",
    "addr:housenumber":"222",
    "addr:postcode":"14207",
    "addr:street":"Riverside Ave",
    "iso:country":"US",
    "sg:address":"222 Riverside Ave",
    "sg:city":"Buffalo",
    "sg:classifiers":[
        {
            "category":"Personal",
            "type":"Services"
        },
        {
            "category":"Professional",
            "subcategory":"Art Services",
            "type":"Services"
        }
    ],
    "sg:phone":"+1 716 874 0854",
    "sg:postcode":"14207",
    "sg:province":"NY",
    "sg:tags":[
        "photography",
        "videography",
        "wedding"
    ],
    "wof:name":"Wendy Mitchell Photography",
    "wof:placetype":"venue"
},
  "geometry": {"coordinates":[-78.901325,42.952729],"type":"Point"}
}