{
  "type": "Feature",
  "properties": {
    "iso:country":"US",
    "sg:address":"190 Kelsey Rd",
    "sg:city":"Candor",
    "sg:classifiers":[
        {
            "category":"Professional",
            "subcategory":"Detective & Security Services",
            "type":"Services"
        }
    ],
    "sg:phone":"+1 607 659 5836",
    "sg:postcode":"13743",
    "sg:province":"NY",
    "sg:tags":[
        "information",
        "bureau"
    ],
    "wof:name":"Dragonfly Bereavement Serices",
    "wof:placetype":"venue"
},
  "geometry": {"coordinates":[-76.321303,42.200193],"type":"Point"}
}