{
  "type": "Feature",
  "properties": {
    "addr:full":"315 7th Ave New York NY 10001",
    "addr:housenumber":"315",
    "addr:postcode":"10001",
    "addr:street":"7Th Ave",
    "iso:country":"US",
    "sg:address":"315 7th Ave",
    "sg:city":"New York",
    "sg:classifiers":[
        {
            "category":"Shopping",
            "subcategory":"Mobile Phones",
            "type":"Retail Goods"
        }
    ],
    "sg:phone":"+1 212 675 0306",
    "sg:postcode":"10001",
    "sg:province":"NY",
    "sg:website":"www.t-mobile.com",
    "wof:name":"T-Mobile",
    "wof:placetype":"venue"
},
  "geometry": {"coordinates":[-73.993267,40.747093],"type":"Point"}
}