{
  "type": "Feature",
  "properties": {
    "addr:full":"350 7th Ave New York NY 10001",
    "addr:housenumber":"350",
    "addr:postcode":"10001",
    "addr:street":"7Th Ave",
    "iso:country":"US",
    "sg:address":"350 7th Ave",
    "sg:city":"New York",
    "sg:classifiers":[
        {
            "category":"Restaurant",
            "type":"Food & Drink"
        }
    ],
    "sg:phone":"+1 212 967 1919",
    "sg:postcode":"10001",
    "sg:province":"NY",
    "sg:tags":[
        "new",
        "american"
    ],
    "sg:website":"www.sevenbarandgrill.com",
    "wof:name":"Seven Bar and Grill",
    "wof:placetype":"venue"
},
  "geometry": {"coordinates":[-73.993103,40.748232],"type":"Point"}
}