{
  "type": "Feature",
  "properties": {
    "iso:country":"US",
    "sg:address":"4 Rocket Ct",
    "sg:city":"Selden",
    "sg:classifiers":[
        {
            "category":"Professional",
            "subcategory":"Management & Consulting",
            "type":"Services"
        }
    ],
    "sg:phone":"+1   ",
    "sg:postcode":"11784",
    "sg:province":"NY",
    "sg:tags":[
        "public",
        "relations"
    ],
    "wof:name":"Concepts For Promotions",
    "wof:placetype":"venue"
},
  "geometry": {"coordinates":[-73.056704,40.885407],"type":"Point"}
}