{
  "type": "Feature",
  "properties": {
    "iso:country":"US",
    "sg:address":"20 Candee St",
    "sg:city":"Phoenix",
    "sg:classifiers":[
        {
            "category":"Wholesale",
            "subcategory":"Construction Materials",
            "type":"Manufacturing & Wholesale Goods"
        }
    ],
    "sg:phone":"+1 315 695 2026",
    "sg:postcode":"13135",
    "sg:province":"NY",
    "sg:tags":[
        "molding"
    ],
    "wof:name":"Oneida Rostone Corp",
    "wof:placetype":"venue"
},
  "geometry": {"coordinates":[-76.29421499999999,43.232705],"type":"Point"}
}