{
  "type": "Feature",
  "properties": {
    "addr:full":"233 Mott Street New York NY 10012",
    "addr:housenumber":"233",
    "addr:postcode":"10012",
    "addr:street":"Mott Street",
    "iso:country":"US",
    "sg:address":"233 Mott Street",
    "sg:city":"New York",
    "sg:classifiers":[
        {
            "category":"Place Of Worship",
            "subcategory":"Church",
            "type":"Public Place"
        }
    ],
    "sg:phone":"+1 212 226 3984",
    "sg:postcode":"10012",
    "sg:province":"NY",
    "sg:website":"www.oldsaintpatricks.com",
    "wof:name":"Old St.Patrick's Cathedral",
    "wof:placetype":"venue"
},
  "geometry": {"coordinates":[-73.995239,40.722645],"type":"Point"}
}