{
  "type": "Feature",
  "properties": {
    "iso:country":"US",
    "sg:address":"4929 Culver Rd",
    "sg:city":"Rochester",
    "sg:classifiers":[
        {
            "category":"Banks & Credit Unions",
            "subcategory":"Investment Brokerage",
            "type":"Services"
        }
    ],
    "sg:phone":"+1 585 467 5622",
    "sg:postcode":"14622",
    "sg:province":"NY",
    "sg:tags":[
        "advisory"
    ],
    "wof:name":"Bayview Investments",
    "wof:placetype":"venue"
},
  "geometry": {"coordinates":[-77.53724,43.23451],"type":"Point"}
}