{
  "type": "Feature",
  "properties": {
    "addr:full":"1140 Franklin Ave Ste 201 Garden City NY 11530",
    "addr:housenumber":"1140",
    "addr:postcode":"11530",
    "addr:street":"Franklin Ave Ste 201",
    "iso:country":"US",
    "sg:address":"1140 Franklin Ave Ste 201",
    "sg:city":"Garden City",
    "sg:classifiers":[
        {
            "category":"Professional",
            "subcategory":"Lawyer & Legal Services",
            "type":"Services"
        }
    ],
    "sg:phone":"+1 516 742 6600",
    "sg:postcode":"11530",
    "sg:province":"NY",
    "wof:name":"Carney & MacKay",
    "wof:placetype":"venue"
},
  "geometry": {"coordinates":[-73.637024,40.732244],"type":"Point"}
}