{
  "type": "Feature",
  "properties": {
    "iso:country":"US",
    "sg:address":"299 Starr Ridge Rd",
    "sg:city":"Brewster",
    "sg:classifiers":[
        {
            "category":"Building & Trades",
            "subcategory":"Construction",
            "type":"Services"
        }
    ],
    "sg:phone":"+1 845 278 5748",
    "sg:postcode":"10509",
    "sg:province":"NY",
    "sg:tags":[
        "contractor"
    ],
    "wof:name":"Masterworks Masonry",
    "wof:placetype":"venue"
},
  "geometry": {"coordinates":[-73.59473699999999,41.378273],"type":"Point"}
}