{
  "type": "Feature",
  "properties": {
    "iso:country":"US",
    "sg:address":"1000 East Ave",
    "sg:city":"Rochester",
    "sg:classifiers":[
        {
            "category":"Food & Beverages",
            "subcategory":"Groceries & Convenience Stores",
            "type":"Retail Goods"
        }
    ],
    "sg:phone":"+1 585 342 5464",
    "sg:postcode":"14607",
    "sg:province":"NY",
    "sg:tags":[
        "notion"
    ],
    "wof:name":"Mj Threads",
    "wof:placetype":"venue"
},
  "geometry": {"coordinates":[-77.576905,43.150742],"type":"Point"}
}