{
  "type": "Feature",
  "properties": {
    "iso:country":"US",
    "sg:address":"712 W Main St",
    "sg:city":"Watertown",
    "sg:classifiers":[
        {
            "category":"Retail",
            "subcategory":"Auto Repair",
            "type":"Services"
        }
    ],
    "sg:phone":"+1 315 782 5132",
    "sg:postcode":"13601",
    "sg:province":"NY",
    "sg:tags":[
        "repairing",
        "automobile"
    ],
    "wof:name":"Parson's Service Ctr",
    "wof:placetype":"venue"
},
  "geometry": {"coordinates":[-75.91798199999999,43.984312],"type":"Point"}
}