{
  "type": "Feature",
  "properties": {
    "iso:country":"US",
    "sg:address":"303 Moonlawn Rd",
    "sg:city":"Troy",
    "sg:classifiers":[
        {
            "category":"Real Estate",
            "subcategory":"Real Estate Agent",
            "type":"Services"
        }
    ],
    "sg:phone":"+1 518 279 1487",
    "sg:postcode":"12180",
    "sg:province":"NY",
    "wof:name":"H J Hannan Realty Inc",
    "wof:placetype":"venue"
},
  "geometry": {"coordinates":[-73.590969,42.754072],"type":"Point"}
}