{
  "type": "Feature",
  "properties": {
    "addr:full":"300 W 39th St New York NY 10018",
    "addr:housenumber":"300",
    "addr:postcode":"10018",
    "addr:street":"W 39Th St",
    "iso:country":"US",
    "sg:address":"300 W 39th St",
    "sg:city":"New York",
    "sg:classifiers":[
        {
            "category":"Building & Trades",
            "subcategory":"Construction",
            "type":"Services"
        }
    ],
    "sg:phone":"+1 212 931 6844",
    "sg:postcode":"10018",
    "sg:province":"NY",
    "sg:tags":[
        "contractor"
    ],
    "wof:name":"A Pappajohn Company",
    "wof:placetype":"venue"
},
  "geometry": {"coordinates":[-73.99121700000001,40.755327],"type":"Point"}
}