{
  "type": "Feature",
  "properties": {
    "iso:country":"US",
    "sg:address":"Cochecton Tpke",
    "sg:city":"Newburgh",
    "sg:classifiers":[
        {
            "category":"Education",
            "subcategory":"School",
            "type":"Public Place"
        }
    ],
    "sg:phone":"+1 845 564 1551",
    "sg:postcode":"12550",
    "sg:province":"NY",
    "sg:tags":[
        "high",
        "middle",
        "elementary"
    ],
    "wof:name":"Vly Central Schools E Coldenham Elementary School",
    "wof:placetype":"venue"
},
  "geometry": {"coordinates":[-74.0299,41.5131],"type":"Point"}
}