{
  "type": "Feature",
  "properties": {
    "iso:country":"US",
    "sg:address":"1625 Poplar St",
    "sg:city":"Bronx",
    "sg:classifiers":[
        {
            "category":"Health Services",
            "subcategory":"Doctor",
            "type":"Services"
        }
    ],
    "sg:phone":"+1 718 405 8440",
    "sg:postcode":"10461",
    "sg:province":"NY",
    "sg:tags":[
        "medical"
    ],
    "wof:name":"Shalom Buchbinder MD PC",
    "wof:placetype":"venue"
},
  "geometry": {"coordinates":[-73.84673600000001,40.845596],"type":"Point"}
}