{
  "type": "Feature",
  "properties": {
    "addr:full":"38 Longs Ave Tonawanda NY 14150",
    "addr:housenumber":"38",
    "addr:postcode":"14150",
    "addr:street":"Longs Ave",
    "iso:country":"US",
    "sg:address":"38 Longs Ave",
    "sg:city":"Tonawanda",
    "sg:classifiers":[
        {
            "category":"Freight",
            "type":"Transportation"
        }
    ],
    "sg:phone":"+1   ",
    "sg:postcode":"14150",
    "sg:province":"NY",
    "sg:tags":[
        "operator",
        "local",
        "trucking"
    ],
    "wof:name":"Al Moving",
    "wof:placetype":"venue"
},
  "geometry": {"coordinates":[-78.872058,43.020411],"type":"Point"}
}