{
  "type": "Feature",
  "properties": {
    "addr:full":"120 US Hwy 9w Haverstraw NY 10927",
    "addr:housenumber":"120",
    "addr:postcode":"10927",
    "addr:street":"Us Hwy 9W",
    "iso:country":"US",
    "sg:address":"120 US Hwy 9w",
    "sg:city":"Haverstraw",
    "sg:classifiers":[
        {
            "category":"Building & Trades",
            "subcategory":"Construction",
            "type":"Services"
        }
    ],
    "sg:phone":"+1 845 429 0039",
    "sg:postcode":"10927",
    "sg:province":"NY",
    "sg:tags":[
        "house",
        "company"
    ],
    "wof:name":"R & R Construction",
    "wof:placetype":"venue"
},
  "geometry": {"coordinates":[-73.96106899999999,41.188076],"type":"Point"}
}