{
  "type": "Feature",
  "properties": {
    "iso:country":"US",
    "sg:address":"421 Great East Neck Rd",
    "sg:city":"West Babylon",
    "sg:classifiers":[
        {
            "category":"Real Estate",
            "subcategory":"Real Estate Operator",
            "type":"Services"
        }
    ],
    "sg:phone":"+1 631 321 1616",
    "sg:postcode":"11704",
    "sg:province":"NY",
    "sg:tags":[
        "building",
        "nonresidential"
    ],
    "wof:name":"Party Palace",
    "wof:placetype":"venue"
},
  "geometry": {"coordinates":[-73.342957,40.702625],"type":"Point"}
}