{
  "type": "Feature",
  "properties": {
    "iso:country":"US",
    "sg:address":"5012 Snyder Ave",
    "sg:city":"Brooklyn",
    "sg:classifiers":[
        {
            "category":"Building & Trades",
            "subcategory":"Construction",
            "type":"Services"
        }
    ],
    "sg:phone":"+1 718 495 9338",
    "sg:postcode":"11203",
    "sg:province":"NY",
    "sg:tags":[
        "house"
    ],
    "wof:name":"Utica Woodcraft",
    "wof:placetype":"venue"
},
  "geometry": {"coordinates":[-73.92928499999999,40.65009],"type":"Point"}
}