{
  "type": "Feature",
  "properties": {
    "addr:full":"4064 Nesconset Hwy East Setauket NY 11733",
    "addr:housenumber":"4064",
    "addr:postcode":"11733",
    "addr:street":"Nesconset Hwy East",
    "iso:country":"US",
    "sg:address":"4064 Nesconset Hwy",
    "sg:city":"East Setauket",
    "sg:classifiers":[
        {
            "category":"Food & Beverages",
            "subcategory":"Liquor & Beverages",
            "type":"Retail Goods"
        }
    ],
    "sg:phone":"+1 631 331 3096",
    "sg:postcode":"11733",
    "sg:province":"NY",
    "sg:tags":[
        "beer",
        "spirit",
        "wine"
    ],
    "sg:website":"www.bottleblowoutwineandliquor.com/",
    "wof:name":"Bottle Blow Out Wine & Liquor",
    "wof:placetype":"venue"
},
  "geometry": {"coordinates":[-73.047881,40.905939],"type":"Point"}
}