{
  "type": "Feature",
  "properties": {
    "addr:full":"50 Lake St Hamburg NY 14075",
    "addr:housenumber":"50",
    "addr:postcode":"14075",
    "addr:street":"Lake St",
    "iso:country":"US",
    "sg:address":"50 Lake St",
    "sg:city":"Hamburg",
    "sg:classifiers":[
        {
            "category":"Recreation",
            "type":"Entertainment"
        }
    ],
    "sg:phone":"+1 716 549 6819",
    "sg:postcode":"14075",
    "sg:province":"NY",
    "sg:tags":[
        "martial",
        "arts",
        "instruction"
    ],
    "wof:name":"Ninjutsu",
    "wof:placetype":"venue"
},
  "geometry": {"coordinates":[-78.83915399999999,42.717918],"type":"Point"}
}