{
  "type": "Feature",
  "properties": {
    "addr:full":"111 E 22 St New York NY 10010",
    "addr:housenumber":"111;22",
    "addr:postcode":"10010",
    "addr:street":"E;St",
    "iso:country":"US",
    "sg:address":"111 E 22 St",
    "sg:city":"New York",
    "sg:classifiers":[
        {
            "category":"Professional",
            "type":"Services"
        }
    ],
    "sg:phone":"+1 212 460 5867",
    "sg:postcode":"10010",
    "sg:province":"NY",
    "sg:tags":[
        "establishment"
    ],
    "wof:name":"Kashmir",
    "wof:placetype":"venue"
},
  "geometry": {"coordinates":[-73.98563300000001,40.739148],"type":"Point"}
}