{
  "type": "Feature",
  "properties": {
    "addr:full":"537 W 24th Street New York NY 10011",
    "addr:housenumber":"537",
    "addr:postcode":"10011",
    "addr:street":"W 24Th Street",
    "iso:country":"US",
    "sg:address":"537 W 24th Street",
    "sg:city":"New York",
    "sg:classifiers":[
        {
            "category":"Arts & Performance",
            "subcategory":"Art Gallery",
            "type":"Entertainment"
        }
    ],
    "sg:phone":"+1 212 925 3500",
    "sg:postcode":"10011",
    "sg:province":"NY",
    "wof:name":"Cowles Charles Gallery",
    "wof:placetype":"venue"
},
  "geometry": {"coordinates":[-74.006033,40.749215],"type":"Point"}
}