{
  "type": "Feature",
  "properties": {
    "addr:full":"200 Ontario St Buffalo NY 14207",
    "addr:housenumber":"200",
    "addr:postcode":"14207",
    "addr:street":"Ontario St",
    "iso:country":"US",
    "sg:address":"200 Ontario St",
    "sg:city":"Buffalo",
    "sg:classifiers":[
        {
            "category":"Health Services",
            "subcategory":"Doctor",
            "type":"Services"
        }
    ],
    "sg:phone":"+1 716 876 1233",
    "sg:postcode":"14207",
    "sg:province":"NY",
    "sg:tags":[
        "surgeon",
        "oral",
        "dentist"
    ],
    "wof:name":"Mc Lanahan Robert T DDS",
    "wof:placetype":"venue"
},
  "geometry": {"coordinates":[-78.903999,42.949402],"type":"Point"}
}