{
  "type": "Feature",
  "properties": {
    "addr:full":"866 Eastern Pkwy Brooklyn NY 11213",
    "addr:housenumber":"866",
    "addr:postcode":"11213",
    "addr:street":"Eastern Pkwy",
    "iso:country":"US",
    "sg:address":"866 Eastern Pkwy",
    "sg:city":"Brooklyn",
    "sg:classifiers":[
        {
            "category":"Professional",
            "type":"Services"
        }
    ],
    "sg:phone":"+1 718 756 6600",
    "sg:postcode":"11213",
    "sg:province":"NY",
    "sg:tags":[
        "establishment"
    ],
    "wof:name":"Conci Urge",
    "wof:placetype":"venue"
},
  "geometry": {"coordinates":[-73.94147700000001,40.669323],"type":"Point"}
}