{
  "type": "Feature",
  "properties": {
    "addr:full":"1 Fairmont Ave Medford NY 11763",
    "addr:housenumber":"1",
    "addr:postcode":"11763",
    "addr:street":"Fairmont Ave",
    "iso:country":"US",
    "sg:address":"1 Fairmont Ave",
    "sg:city":"Medford",
    "sg:classifiers":[
        {
            "category":"Building & Trades",
            "subcategory":"Landscaping Services",
            "type":"Services"
        }
    ],
    "sg:phone":"+1 631 732 2617",
    "sg:postcode":"11763",
    "sg:province":"NY",
    "sg:tags":[
        "landscape",
        "contractor"
    ],
    "wof:name":"Shamrock Landscaping Turf Mgmt",
    "wof:placetype":"venue"
},
  "geometry": {"coordinates":[-73.00505099999999,40.836051],"type":"Point"}
}