{
  "type": "Feature",
  "properties": {
    "addr:full":"1757 Dr Martin L King Jr Blvd Bronx NY 10453",
    "addr:housenumber":"1757",
    "addr:postcode":"10453",
    "addr:street":"Dr Martin L King Jr Blvd",
    "iso:country":"US",
    "sg:address":"1757 Dr Martin L King Jr Blvd",
    "sg:city":"Bronx",
    "sg:classifiers":[
        {
            "category":"Shopping",
            "subcategory":"Shoes",
            "type":"Retail Goods"
        }
    ],
    "sg:phone":"+1 347 202 5330",
    "sg:postcode":"10453",
    "sg:province":"NY",
    "sg:tags":[
        "store"
    ],
    "wof:name":"Sneeker Empire",
    "wof:placetype":"venue"
},
  "geometry": {"coordinates":[-73.91644700000001,40.85011],"type":"Point"}
}