{
  "type": "Feature",
  "properties": {
    "addr:full":"1280 Allerton Avenue Bronx NY 10469",
    "addr:housenumber":"1280",
    "addr:postcode":"10469",
    "addr:street":"Allerton Avenue",
    "iso:country":"US",
    "sg:address":"1280 Allerton Avenue",
    "sg:city":"Bronx",
    "sg:classifiers":[
        {
            "category":"Autos & Motor Vehicles",
            "subcategory":"Fuel & Gas Station",
            "type":"Retail Goods"
        }
    ],
    "sg:phone":"+1 718 882 3432",
    "sg:postcode":"10469",
    "sg:province":"NY",
    "wof:name":"Don-Glo Auto Svce Ctr of the Bronx",
    "wof:placetype":"venue"
},
  "geometry": {"coordinates":[-73.849411,40.865261],"type":"Point"}
}