{
  "type": "Feature",
  "properties": {
    "addr:full":"9522 4th Ave Brooklyn NY 11209",
    "addr:housenumber":"9522",
    "addr:postcode":"11209",
    "addr:street":"4Th Ave",
    "iso:country":"US",
    "sg:address":"9522 4th Ave",
    "sg:city":"Brooklyn",
    "sg:classifiers":[
        {
            "category":"Bars & Pubs",
            "type":"Food & Drink"
        }
    ],
    "sg:menulink":"http://www.allmenus.com/ny/brooklyn/54682-fuel/menu/",
    "sg:phone":"+1 718 491 8686",
    "sg:postcode":"11209",
    "sg:province":"NY",
    "sg:tags":[
        "smoothy",
        "juice",
        "american",
        "sandwich",
        "wrap"
    ],
    "wof:name":"Fuel Energy Food and Juice Bar",
    "wof:placetype":"venue"
},
  "geometry": {"coordinates":[-74.031468,40.615482],"type":"Point"}
}