{
  "type": "Feature",
  "properties": {
    "addr:full":"25 Memorial Dr Chappaqua NY 10514",
    "addr:housenumber":"25",
    "addr:postcode":"10514",
    "addr:street":"Memorial Dr",
    "iso:country":"US",
    "sg:address":"25 Memorial Dr",
    "sg:city":"Chappaqua",
    "sg:classifiers":[
        {
            "category":"Professional",
            "subcategory":"Engineering",
            "type":"Services"
        }
    ],
    "sg:phone":"+1 914 238 3555",
    "sg:postcode":"10514",
    "sg:province":"NY",
    "sg:tags":[
        "engineer"
    ],
    "wof:name":"Campbell Engineering",
    "wof:placetype":"venue"
},
  "geometry": {"coordinates":[-73.764348,41.159262],"type":"Point"}
}