{
  "type": "Feature",
  "properties": {
    "addr:full":"1639 Westchester Ave Bronx NY 10472",
    "addr:housenumber":"1639",
    "addr:postcode":"10472",
    "addr:street":"Westchester Ave",
    "iso:country":"US",
    "sg:address":"1639 Westchester Ave",
    "sg:city":"Bronx",
    "sg:classifiers":[
        {
            "category":"Home & Garden",
            "subcategory":"Carpets & Floor Coverings",
            "type":"Retail Goods"
        }
    ],
    "sg:phone":"+1 718 328 3797",
    "sg:postcode":"10472",
    "sg:province":"NY",
    "sg:tags":[
        "installs",
        "carpeting"
    ],
    "wof:name":"Alex Carpet",
    "wof:placetype":"venue"
},
  "geometry": {"coordinates":[-73.87454700000001,40.829522],"type":"Point"}
}