{
  "type": "Feature",
  "properties": {
    "addr:full":"181 Springville Rd Hampton Bays NY 11946",
    "addr:housenumber":"181",
    "addr:postcode":"11946",
    "addr:street":"Springville Rd",
    "iso:country":"US",
    "sg:address":"181 Springville Rd",
    "sg:city":"Hampton Bays",
    "sg:classifiers":[
        {
            "category":"Retail",
            "subcategory":"Repair Shop",
            "type":"Services"
        }
    ],
    "sg:phone":"+1 631 728 7379",
    "sg:postcode":"11946",
    "sg:province":"NY",
    "sg:tags":[
        "ironwork"
    ],
    "wof:name":"Visions In Steel",
    "wof:placetype":"venue"
},
  "geometry": {"coordinates":[-72.525277,40.859879],"type":"Point"}
}