{
  "type": "Feature",
  "properties": {
    "iso:country":"US",
    "sg:address":"342 E 71 St",
    "sg:city":"New York",
    "sg:classifiers":[
        {
            "category":"Retail",
            "subcategory":"Laundry & Dry Cleaning",
            "type":"Services"
        }
    ],
    "sg:phone":"+1 212 628 9001",
    "sg:postcode":"10021",
    "sg:province":"NY",
    "wof:name":"LA Mode First Cleaners",
    "wof:placetype":"venue"
},
  "geometry": {"coordinates":[-73.956903,40.767261],"type":"Point"}
}