{
  "type": "Feature",
  "properties": {
    "iso:country":"US",
    "sg:address":"2704 Jerome Avenue",
    "sg:city":"Bronx",
    "sg:classifiers":[
        {
            "category":"Retail",
            "subcategory":"Car Wash",
            "type":"Services"
        }
    ],
    "sg:phone":"+1 718 933 6977",
    "sg:postcode":"10468",
    "sg:province":"NY",
    "wof:name":"Kingsbridge Car Wash",
    "wof:placetype":"venue"
},
  "geometry": {"coordinates":[-73.89645,40.868382],"type":"Point"}
}