{
  "type": "Feature",
  "properties": {
    "addr:full":"70 Bolton St Lindenhurst NY 11757",
    "addr:housenumber":"70",
    "addr:postcode":"11757",
    "addr:street":"Bolton St",
    "iso:country":"US",
    "sg:address":"70 Bolton St",
    "sg:city":"Lindenhurst",
    "sg:classifiers":[
        {
            "category":"Manufacturing",
            "subcategory":"Printing",
            "type":"Manufacturing & Wholesale Goods"
        }
    ],
    "sg:phone":"+1 718 237 0264",
    "sg:postcode":"11757",
    "sg:province":"NY",
    "sg:tags":[
        "book"
    ],
    "wof:name":"Quite Specific Media Group",
    "wof:placetype":"venue"
},
  "geometry": {"coordinates":[-73.394105,40.71071],"type":"Point"}
}