{
  "type": "Feature",
  "properties": {
    "addr:full":"14 Rosecliff Rd Staten Island NY 10303",
    "addr:housenumber":"14",
    "addr:postcode":"10303",
    "addr:street":"Rosecliff Rd",
    "iso:country":"US",
    "sg:address":"14 Rosecliff Rd",
    "sg:city":"Staten Island",
    "sg:classifiers":[
        {
            "category":"Wholesale",
            "subcategory":"Machinery & Supplies",
            "type":"Manufacturing & Wholesale Goods"
        }
    ],
    "sg:phone":"+1 718 983 1973",
    "sg:postcode":"10303",
    "sg:province":"NY",
    "sg:tags":[
        "equipment",
        "establishment"
    ],
    "wof:name":"B B D D Inc",
    "wof:placetype":"venue"
},
  "geometry": {"coordinates":[-74.163585,40.625271],"type":"Point"}
}