{
  "type": "Feature",
  "properties": {
    "addr:full":"4932 Saunders Settlement Rd Lockport NY 14094",
    "addr:housenumber":"4932",
    "addr:postcode":"14094",
    "addr:street":"Saunders Settlement Rd",
    "iso:country":"US",
    "sg:address":"4932 Saunders Settlement Rd",
    "sg:city":"Lockport",
    "sg:classifiers":[
        {
            "category":"Building & Trades",
            "subcategory":"Landscaping Services",
            "type":"Services"
        }
    ],
    "sg:phone":"+1 716 434 4395",
    "sg:postcode":"14094",
    "sg:province":"NY",
    "sg:tags":[
        "landscape",
        "contractor"
    ],
    "wof:name":"Create-A-Scape",
    "wof:placetype":"venue"
},
  "geometry": {"coordinates":[-78.757789,43.149191],"type":"Point"}
}