{
  "type": "Feature",
  "properties": {
    "addr:full":"327 Broadway Kingston NY 12401",
    "addr:housenumber":"327",
    "addr:postcode":"12401",
    "addr:street":"Broadway",
    "iso:country":"US",
    "sg:address":"327 Broadway",
    "sg:city":"Kingston",
    "sg:classifiers":[
        {
            "category":"Autos & Motor Vehicles",
            "subcategory":"Fuel & Gas Station",
            "type":"Retail Goods"
        }
    ],
    "sg:phone":"+1   ",
    "sg:postcode":"12401",
    "sg:province":"NY",
    "sg:tags":[
        "station",
        "gasoline"
    ],
    "wof:name":"Mobil",
    "wof:placetype":"venue"
},
  "geometry": {"coordinates":[-73.992287,41.925575],"type":"Point"}
}