{
  "type": "Feature",
  "properties": {
    "iso:country":"US",
    "sg:address":"415 W 1st St",
    "sg:city":"Elmira",
    "sg:classifiers":[
        {
            "category":"Retail",
            "subcategory":"Laundry & Dry Cleaning",
            "type":"Services"
        }
    ],
    "sg:phone":"+1 607 733 9083",
    "sg:postcode":"14901",
    "sg:province":"NY",
    "sg:tags":[
        "hanging"
    ],
    "wof:name":"Earls Painting",
    "wof:placetype":"venue"
},
  "geometry": {"coordinates":[-76.815938,42.088541],"type":"Point"}
}