{
  "type": "Feature",
  "properties": {
    "iso:country":"US",
    "sg:address":"124 Pavement Rd",
    "sg:city":"Lancaster",
    "sg:classifiers":[
        {
            "category":"Retail",
            "subcategory":"Animal Services",
            "type":"Services"
        }
    ],
    "sg:phone":"+1 716 681 8842",
    "sg:postcode":"14086",
    "sg:province":"NY",
    "wof:name":"Paws & Claws Dog Grooming",
    "wof:placetype":"venue"
},
  "geometry": {"coordinates":[-78.62289699999999,42.900981],"type":"Point"}
}