{
  "type": "Feature",
  "properties": {
    "iso:country":"US",
    "sg:address":"90 Farrell St",
    "sg:city":"Long Beach",
    "sg:classifiers":[
        {
            "category":"Building & Trades",
            "subcategory":"Electrical",
            "type":"Services"
        }
    ],
    "sg:phone":"+1 516 432 2206",
    "sg:postcode":"11561",
    "sg:province":"NY",
    "sg:tags":[
        "electrical",
        "contractor"
    ],
    "wof:name":"El Electric Co",
    "wof:placetype":"venue"
},
  "geometry": {"coordinates":[-73.640969,40.592899],"type":"Point"}
}