{
  "type": "Feature",
  "properties": {
    "addr:full":"41 Webster Ave Goshen NY 10924",
    "addr:housenumber":"41",
    "addr:postcode":"10924",
    "addr:street":"Webster Ave",
    "iso:country":"US",
    "sg:address":"41 Webster Ave",
    "sg:city":"Goshen",
    "sg:classifiers":[
        {
            "category":"Government",
            "subcategory":"Office",
            "type":"Public Place"
        }
    ],
    "sg:phone":"+1 845 294 6477",
    "sg:postcode":"10924",
    "sg:province":"NY",
    "sg:tags":[
        "village"
    ],
    "wof:name":"Goshen Town Justice",
    "wof:placetype":"venue"
},
  "geometry": {"coordinates":[-74.323376,41.402677],"type":"Point"}
}