{
  "type": "Feature",
  "properties": {
    "iso:country":"US",
    "sg:address":"10 Stonegate Ln",
    "sg:city":"Glen Head",
    "sg:classifiers":[
        {
            "category":"Home & Garden",
            "subcategory":"Furniture",
            "type":"Retail Goods"
        }
    ],
    "sg:phone":"+1 516 621 0445",
    "sg:postcode":"11545",
    "sg:province":"NY",
    "sg:tags":[
        "store"
    ],
    "wof:name":"Design Institute America",
    "wof:placetype":"venue"
},
  "geometry": {"coordinates":[-73.605797,40.822399],"type":"Point"}
}