{
  "type": "Feature",
  "properties": {
    "addr:full":"2334 Lockport Rd Sanborn NY 14132",
    "addr:housenumber":"2334",
    "addr:postcode":"14132",
    "addr:street":"Lockport Rd",
    "iso:country":"US",
    "sg:address":"2334 Lockport Rd",
    "sg:city":"Sanborn",
    "sg:classifiers":[
        {
            "category":"Organizations",
            "subcategory":"Religious Organization",
            "type":"Services"
        }
    ],
    "sg:phone":"+1   ",
    "sg:postcode":"14132",
    "sg:province":"NY",
    "wof:name":"Wheatfield Christian Academy",
    "wof:placetype":"venue"
},
  "geometry": {"coordinates":[-78.92155200000001,43.121321],"type":"Point"}
}