{
  "type": "Feature",
  "properties": {
    "iso:country":"US",
    "sg:address":"450 Woodward Ave",
    "sg:city":"Buffalo",
    "sg:classifiers":[
        {
            "category":"Government",
            "subcategory":"Office",
            "type":"Public Place"
        }
    ],
    "sg:phone":"+1 716 875 6710",
    "sg:postcode":"14214",
    "sg:province":"NY",
    "sg:tags":[
        "city",
        "program"
    ],
    "sg:website":"www.tonawanda.ny.us",
    "wof:name":"Tonawanda Sanitation Dept",
    "wof:placetype":"venue"
},
  "geometry": {"coordinates":[-78.849074,42.941748],"type":"Point"}
}