{
  "type": "Feature",
  "properties": {
    "addr:full":"114 Lilac Dr Horseheads NY 14845",
    "addr:housenumber":"114",
    "addr:postcode":"14845",
    "addr:street":"Lilac Dr",
    "iso:country":"US",
    "sg:address":"114 Lilac Dr",
    "sg:city":"Horseheads",
    "sg:classifiers":[
        {
            "category":"Education",
            "subcategory":"Dance Studio",
            "type":"Public Place"
        }
    ],
    "sg:phone":"+1   ",
    "sg:postcode":"14845",
    "sg:province":"NY",
    "wof:name":"Donna Brooks Dance Academy",
    "wof:placetype":"venue"
},
  "geometry": {"coordinates":[-76.846253,42.175503],"type":"Point"}
}