{
  "type": "Feature",
  "properties": {
    "addr:full":"2514 Hoffman Street Bronx NY 10458",
    "addr:housenumber":"2514",
    "addr:postcode":"10458",
    "addr:street":"Hoffman Street",
    "iso:country":"US",
    "sg:address":"2514 Hoffman Street",
    "sg:city":"Bronx",
    "sg:classifiers":[
        {
            "category":"Autos & Motor Vehicles",
            "subcategory":"Auto Supplies",
            "type":"Retail Goods"
        }
    ],
    "sg:phone":"+1 718 364 5070",
    "sg:postcode":"10458",
    "sg:province":"NY",
    "sg:tags":[
        "glass"
    ],
    "wof:name":"The Hoffman Auto Glass Sound & Security",
    "wof:placetype":"venue"
},
  "geometry": {"coordinates":[-73.886302,40.858293],"type":"Point"}
}