{
  "type": "Feature",
  "properties": {
    "addr:full":"50 Valley Ln E Valley Stream NY 11581",
    "addr:housenumber":"50",
    "addr:postcode":"11581",
    "addr:street":"Valley Ln E",
    "iso:country":"US",
    "sg:address":"50 Valley Ln E",
    "sg:city":"Valley Stream",
    "sg:classifiers":[
        {
            "category":"Wholesale",
            "subcategory":"Groceries",
            "type":"Manufacturing & Wholesale Goods"
        }
    ],
    "sg:phone":"+1 516 295 4311",
    "sg:postcode":"11581",
    "sg:province":"NY",
    "sg:tags":[
        "frozen",
        "packaged"
    ],
    "wof:name":"RSR Inc",
    "wof:placetype":"venue"
},
  "geometry": {"coordinates":[-73.719396,40.646516],"type":"Point"}
}