{
  "type": "Feature",
  "properties": {
    "addr:full":"607 Jefferson Rd Rochester NY 14623",
    "addr:housenumber":"607",
    "addr:postcode":"14623",
    "addr:street":"Jefferson Rd",
    "iso:country":"US",
    "sg:address":"607 Jefferson Rd",
    "sg:city":"Rochester",
    "sg:classifiers":[
        {
            "category":"Food & Beverages",
            "subcategory":"Bakery",
            "type":"Retail Goods"
        }
    ],
    "sg:phone":"+1 585 427 0670",
    "sg:postcode":"14623",
    "sg:province":"NY",
    "sg:tags":[
        "doughnut"
    ],
    "sg:website":"www.timhortons.com",
    "wof:name":"Tim Hortons",
    "wof:placetype":"venue"
},
  "geometry": {"coordinates":[-77.62558799999999,43.087017],"type":"Point"}
}