{
  "type": "Feature",
  "properties": {
    "addr:full":"3256 62nd St Woodside NY 11377",
    "addr:housenumber":"3256",
    "addr:postcode":"11377",
    "addr:street":"62Nd St",
    "iso:country":"US",
    "sg:address":"3256 62nd St",
    "sg:city":"Woodside",
    "sg:classifiers":[
        {
            "category":"Retail",
            "subcategory":"Auto Repair",
            "type":"Services"
        }
    ],
    "sg:phone":"+1 718 932 3846",
    "sg:postcode":"11377",
    "sg:province":"NY",
    "sg:tags":[
        "body",
        "shop"
    ],
    "wof:name":"Kim's 62 Street Auto Inc",
    "wof:placetype":"venue"
},
  "geometry": {"coordinates":[-73.900497,40.754101],"type":"Point"}
}