{
  "type": "Feature",
  "properties": {
    "iso:country":"US",
    "sg:address":"3600 Jerome Ave",
    "sg:city":"Bronx",
    "sg:classifiers":[
        {
            "category":"Professional",
            "subcategory":"Employment Agencies",
            "type":"Services"
        }
    ],
    "sg:phone":"+1 718 933 0360",
    "sg:postcode":"10467",
    "sg:province":"NY",
    "sg:tags":[
        "opportunity"
    ],
    "wof:name":"Federation Employment Guidance",
    "wof:placetype":"venue"
},
  "geometry": {"coordinates":[-73.877983,40.886999],"type":"Point"}
}