{
  "type": "Feature",
  "properties": {
    "addr:full":"38 Pvt Rd 20 Olivebridge NY 12461",
    "addr:housenumber":"38;20",
    "addr:postcode":"12461",
    "addr:street":"Pvt Rd",
    "iso:country":"US",
    "sg:address":"38 Pvt Rd 20",
    "sg:city":"Olivebridge",
    "sg:classifiers":[
        {
            "category":"Home & Garden",
            "subcategory":"Building Materials",
            "type":"Retail Goods"
        }
    ],
    "sg:phone":"+1   ",
    "sg:postcode":"12461",
    "sg:province":"NY",
    "wof:name":"Krumville Lumber",
    "wof:placetype":"venue"
},
  "geometry": {"coordinates":[-74.253535,41.900169],"type":"Point"}
}