{
  "type": "Feature",
  "properties": {
    "addr:full":"226 W 29th St New York NY 10001",
    "addr:housenumber":"226",
    "addr:postcode":"10001",
    "addr:street":"W 29Th St",
    "iso:country":"US",
    "sg:address":"226 W 29th St",
    "sg:city":"New York",
    "sg:classifiers":[
        {
            "category":"Personal",
            "type":"Services"
        }
    ],
    "sg:phone":"+1 212 492 9625",
    "sg:postcode":"10001",
    "sg:province":"NY",
    "sg:tags":[
        "towing"
    ],
    "wof:name":"A 7 Day 24 Hour A Towing",
    "wof:placetype":"venue"
},
  "geometry": {"coordinates":[-73.99400300000001,40.748402],"type":"Point"}
}