{
  "type": "Feature",
  "properties": {
    "addr:full":"528 Main St Poughkeepsie NY 12601",
    "addr:housenumber":"528",
    "addr:postcode":"12601",
    "addr:street":"Main St",
    "iso:country":"US",
    "sg:address":"528 Main St",
    "sg:city":"Poughkeepsie",
    "sg:classifiers":[
        {
            "category":"Restaurant",
            "type":"Food & Drink"
        }
    ],
    "sg:phone":"+1 845 485 3455",
    "sg:postcode":"12601",
    "sg:province":"NY",
    "wof:name":"LA Cocina De LA Tia",
    "wof:placetype":"venue"
},
  "geometry": {"coordinates":[-73.91762199999999,41.70058],"type":"Point"}
}