{
  "type": "Feature",
  "properties": {
    "addr:full":"17 Cumberland St Brooklyn NY 11205",
    "addr:housenumber":"17",
    "addr:postcode":"11205",
    "addr:street":"Cumberland St",
    "iso:country":"US",
    "sg:address":"17 Cumberland St",
    "sg:city":"Brooklyn",
    "sg:classifiers":[
        {
            "category":"Autos & Motor Vehicles",
            "subcategory":"Automobile Sales",
            "type":"Retail Goods"
        },
        {
            "category":"Airline",
            "type":"Transportation"
        }
    ],
    "sg:phone":"+1 212 882 1184",
    "sg:postcode":"11205",
    "sg:province":"NY",
    "sg:tags":[
        "shuttle",
        "airport",
        "limo"
    ],
    "wof:name":"New York City Limo",
    "wof:placetype":"venue"
},
  "geometry": {"coordinates":[-73.97457900000001,40.697525],"type":"Point"}
}