{
  "type": "Feature",
  "properties": {
    "iso:country":"US",
    "sg:address":"6311 Inducon Dr E",
    "sg:city":"Sanborn",
    "sg:classifiers":[
        {
            "category":"Manufacturing",
            "subcategory":"Metals",
            "type":"Manufacturing & Wholesale Goods"
        }
    ],
    "sg:phone":"+1   ",
    "sg:postcode":"14132",
    "sg:province":"NY",
    "sg:tags":[
        "mfg",
        "metalwork",
        "structural"
    ],
    "wof:name":"Metal Products International",
    "wof:placetype":"venue"
},
  "geometry": {"coordinates":[-78.91713900000001,43.119029],"type":"Point"}
}