{
  "type": "Feature",
  "properties": {
    "addr:full":"14075 Ash Ave Flushing NY 11355",
    "addr:housenumber":"14075",
    "addr:postcode":"11355",
    "addr:street":"Ash Ave",
    "iso:country":"US",
    "sg:address":"14075 Ash Ave",
    "sg:city":"Flushing",
    "sg:classifiers":[
        {
            "category":"Personal",
            "subcategory":"Barber",
            "type":"Services"
        }
    ],
    "sg:phone":"+1 718 762 4845",
    "sg:postcode":"11355",
    "sg:province":"NY",
    "wof:name":"Mainstream Barber Shop",
    "wof:placetype":"venue"
},
  "geometry": {"coordinates":[-73.823097,40.7556],"type":"Point"}
}