{
  "type": "Feature",
  "properties": {
    "addr:full":"6050 69th Ave Ridgewood NY 11385",
    "addr:housenumber":"6050",
    "addr:postcode":"11385",
    "addr:street":"69Th Ave",
    "iso:country":"US",
    "sg:address":"6050 69th Ave",
    "sg:city":"Ridgewood",
    "sg:classifiers":[
        {
            "category":"Health Services",
            "subcategory":"Doctor",
            "type":"Services"
        }
    ],
    "sg:phone":"+1 718 381 3456",
    "sg:postcode":"11385",
    "sg:province":"NY",
    "wof:name":"Kozikowski Gregory",
    "wof:placetype":"venue"
},
  "geometry": {"coordinates":[-73.897329,40.702587],"type":"Point"}
}