{
  "type": "Feature",
  "properties": {
    "addr:full":"489 Chestnut St Fredonia NY 14063",
    "addr:housenumber":"489",
    "addr:postcode":"14063",
    "addr:street":"Chestnut St",
    "iso:country":"US",
    "sg:address":"489 Chestnut St",
    "sg:city":"Fredonia",
    "sg:classifiers":[
        {
            "category":"Professional",
            "subcategory":"Business Services",
            "type":"Services"
        }
    ],
    "sg:phone":"+1 716 679 1815",
    "sg:postcode":"14063",
    "sg:province":"NY",
    "sg:tags":[
        "consultant",
        "coach"
    ],
    "sg:website":"http://www.fitzgeraldtech.com",
    "wof:name":"Fitzgerald Consulting Service",
    "wof:placetype":"venue"
},
  "geometry": {"coordinates":[-79.353684,42.449265],"type":"Point"}
}