{
  "type": "Feature",
  "properties": {
    "iso:country":"US",
    "sg:address":"5 John R Albanese Pl",
    "sg:city":"Eastchester",
    "sg:classifiers":[
        {
            "category":"Restaurant",
            "type":"Food & Drink"
        }
    ],
    "sg:phone":"+1 914 779 4646",
    "sg:postcode":"10709",
    "sg:province":"NY",
    "sg:tags":[
        "style",
        "family",
        "italian"
    ],
    "wof:name":"Ciao!",
    "wof:placetype":"venue"
},
  "geometry": {"coordinates":[-73.818792,40.949913],"type":"Point"}
}