{
  "type": "Feature",
  "properties": {
    "iso:country":"US",
    "sg:address":"700 Fenimore Rd",
    "sg:city":"Mamaroneck",
    "sg:classifiers":[
        {
            "category":"Wholesale",
            "subcategory":"Electrical",
            "type":"Manufacturing & Wholesale Goods"
        }
    ],
    "sg:phone":"+1 914 698 4800",
    "sg:postcode":"10543",
    "sg:province":"NY",
    "sg:tags":[
        "equipment",
        "electronic",
        "supply"
    ],
    "wof:name":"Tech Material Corp",
    "wof:placetype":"venue"
},
  "geometry": {"coordinates":[-73.744749,40.95148],"type":"Point"}
}