{
  "type": "Feature",
  "properties": {
    "addr:full":"445 E 14 St New York NY 10009",
    "addr:housenumber":"445;14",
    "addr:postcode":"10009",
    "addr:street":"E;St",
    "iso:country":"US",
    "sg:address":"445 E 14 St",
    "sg:city":"New York",
    "sg:classifiers":[
        {
            "category":"Organizations",
            "subcategory":"Religious Organization",
            "type":"Services"
        }
    ],
    "sg:phone":"+1 718 624 8614",
    "sg:postcode":"10009",
    "sg:province":"NY",
    "sg:tags":[
        "center",
        "for",
        "activity"
    ],
    "wof:name":"Iskon of Manhatten Inc",
    "wof:placetype":"venue"
},
  "geometry": {"coordinates":[-73.98106,40.730923],"type":"Point"}
}