{
  "type": "Feature",
  "properties": {
    "addr:full":"230 Ford St Ogdensburg NY 13669",
    "addr:housenumber":"230",
    "addr:postcode":"13669",
    "addr:street":"Ford St",
    "iso:country":"US",
    "sg:address":"230 Ford St",
    "sg:city":"Ogdensburg",
    "sg:classifiers":[
        {
            "category":"Health Services",
            "subcategory":"Doctor",
            "type":"Services"
        }
    ],
    "sg:phone":"+1 315 393 9132",
    "sg:postcode":"13669",
    "sg:province":"NY",
    "sg:tags":[
        "physician",
        "family",
        "practice",
        "surgeons",
        "medicine",
        "surgeon"
    ],
    "wof:name":"Lars Thompson Md",
    "wof:placetype":"venue"
},
  "geometry": {"coordinates":[-75.493713,44.697212],"type":"Point"}
}