{
  "type": "Feature",
  "properties": {
    "iso:country":"US",
    "sg:address":"4947 State Hwy 31",
    "sg:city":"Clay",
    "sg:classifiers":[
        {
            "category":"Social Services",
            "subcategory":"Child Care",
            "type":"Services"
        }
    ],
    "sg:phone":"+1 315 699 2250",
    "sg:postcode":"13041",
    "sg:province":"NY",
    "sg:tags":[
        "kindergarten",
        "academic",
        "school"
    ],
    "wof:name":"Clay Community Nursery School",
    "wof:placetype":"venue"
},
  "geometry": {"coordinates":[-76.175044,43.186025],"type":"Point"}
}