{
  "type": "Feature",
  "properties": {
    "iso:country":"US",
    "sg:address":"6372 Knickerbocker Rd",
    "sg:city":"Ontario",
    "sg:classifiers":[
        {
            "category":"Building & Trades",
            "subcategory":"Construction",
            "type":"Services"
        }
    ],
    "sg:phone":"+1 315 524 4099",
    "sg:postcode":"14519",
    "sg:province":"NY",
    "sg:tags":[
        "grading",
        "demolition",
        "contractor"
    ],
    "wof:name":"Empire Wrecking Company Inc",
    "wof:placetype":"venue"
},
  "geometry": {"coordinates":[-77.286269,43.230397],"type":"Point"}
}