{
  "type": "Feature",
  "properties": {
    "iso:country":"US",
    "sg:address":"725 W Clinton St",
    "sg:city":"Ithaca",
    "sg:classifiers":[
        {
            "category":"Professional",
            "subcategory":"Research",
            "type":"Services"
        }
    ],
    "sg:phone":"+1 607 277 8498",
    "sg:postcode":"14850",
    "sg:province":"NY",
    "sg:tags":[
        "development",
        "electronic"
    ],
    "wof:name":"D L Instruments",
    "wof:placetype":"venue"
},
  "geometry": {"coordinates":[-76.51564500000001,42.436284],"type":"Point"}
}