{
  "type": "Feature",
  "properties": {
    "addr:full":"170 Saw Mill River Rd Yonkers NY 10701",
    "addr:housenumber":"170",
    "addr:postcode":"10701",
    "addr:street":"Saw Mill River Rd",
    "iso:country":"US",
    "sg:address":"170 Saw Mill River Rd",
    "sg:city":"Yonkers",
    "sg:classifiers":[
        {
            "category":"Home & Garden",
            "subcategory":"Furniture",
            "type":"Retail Goods"
        }
    ],
    "sg:phone":"+1 914 378 1805",
    "sg:postcode":"10701",
    "sg:province":"NY",
    "wof:name":"Big's Bedrooms Outlet",
    "wof:placetype":"venue"
},
  "geometry": {"coordinates":[-73.880888,40.942396],"type":"Point"}
}