{
  "type": "Feature",
  "properties": {
    "iso:country":"US",
    "sg:address":"11 Stella Ct",
    "sg:city":"Stony Point",
    "sg:classifiers":[
        {
            "category":"Professional",
            "subcategory":"Business Services",
            "type":"Services"
        }
    ],
    "sg:phone":"+1 845 942 0944",
    "sg:postcode":"10980",
    "sg:province":"NY",
    "sg:tags":[
        "painter",
        "sign"
    ],
    "wof:name":"Signs & Designs By Robert",
    "wof:placetype":"venue"
},
  "geometry": {"coordinates":[-74.054074,41.227834],"type":"Point"}
}