{
  "type": "Feature",
  "properties": {
    "addr:full":"49 Old Country Rd Westbury NY 11590",
    "addr:housenumber":"49",
    "addr:postcode":"11590",
    "addr:street":"Old Country Rd",
    "iso:country":"US",
    "sg:address":"49 Old Country Rd",
    "sg:city":"Westbury",
    "sg:classifiers":[
        {
            "category":"Shopping",
            "subcategory":"Mobile Phones",
            "type":"Retail Goods"
        }
    ],
    "sg:phone":"+1 516 937 2900",
    "sg:postcode":"11590",
    "sg:province":"NY",
    "wof:name":"Verizon Wireless",
    "wof:placetype":"venue"
},
  "geometry": {"coordinates":[-73.601303,40.745602],"type":"Point"}
}