{
  "type": "Feature",
  "properties": {
    "addr:full":"824 Saratoga Ave Brooklyn NY 11212",
    "addr:housenumber":"824",
    "addr:postcode":"11212",
    "addr:street":"Saratoga Ave",
    "iso:country":"US",
    "sg:address":"824 Saratoga Ave",
    "sg:city":"Brooklyn",
    "sg:classifiers":[
        {
            "category":"Home & Garden",
            "subcategory":"Carpets & Floor Coverings",
            "type":"Retail Goods"
        }
    ],
    "sg:phone":"+1 917 299 5285",
    "sg:postcode":"11212",
    "sg:province":"NY",
    "sg:tags":[
        "flooring"
    ],
    "sg:website":"barryflooring.com",
    "wof:name":"Barry Flooring Corp",
    "wof:placetype":"venue"
},
  "geometry": {"coordinates":[-73.915514,40.660434],"type":"Point"}
}