{
  "type": "Feature",
  "properties": {
    "addr:full":"12 Fawn Meadows Ct Getzville NY 14068",
    "addr:housenumber":"12",
    "addr:postcode":"14068",
    "addr:street":"Fawn Meadows Ct",
    "iso:country":"US",
    "sg:address":"12 Fawn Meadows Ct",
    "sg:city":"Getzville",
    "sg:classifiers":[
        {
            "category":"Real Estate",
            "subcategory":"Real Estate Operator",
            "type":"Services"
        }
    ],
    "sg:phone":"+1 716 688 2572",
    "sg:postcode":"14068",
    "sg:province":"NY",
    "sg:tags":[
        "property",
        "lessor"
    ],
    "wof:name":"Tom Shanahan",
    "wof:placetype":"venue"
},
  "geometry": {"coordinates":[-78.738446,43.040041],"type":"Point"}
}