{
  "type": "Feature",
  "properties": {
    "iso:country":"US",
    "sg:address":"20 Elm St",
    "sg:city":"Potsdam",
    "sg:classifiers":[
        {
            "category":"Insurance",
            "subcategory":"Insurance Agent",
            "type":"Services"
        }
    ],
    "sg:phone":"+1 315 265 2140",
    "sg:postcode":"13676",
    "sg:province":"NY",
    "wof:name":"William Hayman Agency",
    "wof:placetype":"venue"
},
  "geometry": {"coordinates":[-74.986634,44.669899],"type":"Point"}
}