{
  "type": "Feature",
  "properties": {
    "addr:full":"20897 Cagwin Rd Watertown NY 13601",
    "addr:postcode":"20897;13601",
    "addr:street":"Cagwin Rd",
    "iso:country":"US",
    "sg:address":"20897 Cagwin Rd",
    "sg:city":"Watertown",
    "sg:classifiers":[
        {
            "category":"Health Services",
            "subcategory":"Doctor",
            "type":"Services"
        }
    ],
    "sg:phone":"+1 315 583 6288",
    "sg:postcode":"13601",
    "sg:province":"NY",
    "sg:tags":[
        "medicine",
        "physician",
        "practice",
        "surgeons",
        "family"
    ],
    "wof:name":"Paul S Curtis Md Pc",
    "wof:placetype":"venue"
},
  "geometry": {"coordinates":[-75.954594,43.900337],"type":"Point"}
}