{
  "type": "Feature",
  "properties": {
    "iso:country":"US",
    "sg:address":"7 Foster Xing",
    "sg:city":"East Quogue",
    "sg:classifiers":[
        {
            "category":"Building & Trades",
            "subcategory":"Construction",
            "type":"Services"
        }
    ],
    "sg:phone":"+1 631 653 8659",
    "sg:postcode":"11942",
    "sg:province":"NY",
    "sg:tags":[
        "contractor"
    ],
    "wof:name":"Red Rain Restorations",
    "wof:placetype":"venue"
},
  "geometry": {"coordinates":[-72.57512199999999,40.842841],"type":"Point"}
}