{
  "type": "Feature",
  "properties": {
    "addr:full":"70 Town Office Rd Troy NY 12180",
    "addr:housenumber":"70",
    "addr:postcode":"12180",
    "addr:street":"Town Office Rd",
    "iso:country":"US",
    "sg:address":"70 Town Office Rd",
    "sg:city":"Troy",
    "sg:classifiers":[
        {
            "category":"Wholesale",
            "subcategory":"Chemicals & Plastics",
            "type":"Manufacturing & Wholesale Goods"
        }
    ],
    "sg:phone":"+1 518 279 1090",
    "sg:postcode":"12180",
    "sg:province":"NY",
    "wof:name":"Promised Land Farm",
    "wof:placetype":"venue"
},
  "geometry": {"coordinates":[-73.607373,42.741458],"type":"Point"}
}