{
  "type": "Feature",
  "properties": {
    "iso:country":"US",
    "sg:address":"13540 78th Dr",
    "sg:city":"Flushing",
    "sg:classifiers":[
        {
            "category":"Health Services",
            "subcategory":"Doctor",
            "type":"Services"
        }
    ],
    "sg:phone":"+1 718 380 8500",
    "sg:postcode":"11367",
    "sg:province":"NY",
    "wof:name":"Bennett Leslie G MD",
    "wof:placetype":"venue"
},
  "geometry": {"coordinates":[-73.8246,40.717999],"type":"Point"}
}