{
  "type": "Feature",
  "properties": {
    "addr:full":"996 Main St Clifton Park NY 12065",
    "addr:housenumber":"996",
    "addr:postcode":"12065",
    "addr:street":"Main St",
    "iso:country":"US",
    "sg:address":"996 Main St",
    "sg:city":"Clifton Park",
    "sg:classifiers":[
        {
            "category":"Organizations",
            "subcategory":"Religious Organization",
            "type":"Services"
        }
    ],
    "sg:phone":"+1 518 877 3314",
    "sg:postcode":"12065",
    "sg:province":"NY",
    "wof:name":"Grace Chapel of Clifton Park",
    "wof:placetype":"venue"
},
  "geometry": {"coordinates":[-73.82271799999999,42.908032],"type":"Point"}
}