{
  "type": "Feature",
  "properties": {
    "iso:country":"US",
    "sg:address":"426 Ontario Ave",
    "sg:city":"Syracuse",
    "sg:classifiers":[
        {
            "category":"Building & Trades",
            "subcategory":"Construction",
            "type":"Services"
        }
    ],
    "sg:phone":"+1 315 468 2780",
    "sg:postcode":"13209",
    "sg:province":"NY",
    "wof:name":"Solvay Construction",
    "wof:placetype":"venue"
},
  "geometry": {"coordinates":[-76.253991,43.100807],"type":"Point"}
}