{
  "type": "Feature",
  "properties": {
    "addr:full":"120 Larchmont Ave Larchmont NY 10538",
    "addr:housenumber":"120",
    "addr:postcode":"10538",
    "addr:street":"Larchmont Ave",
    "iso:country":"US",
    "sg:address":"120 Larchmont Ave",
    "sg:city":"Larchmont",
    "sg:classifiers":[
        {
            "category":"Government",
            "subcategory":"Office",
            "type":"Public Place"
        }
    ],
    "sg:phone":"+1 914 834 6202",
    "sg:postcode":"10538",
    "sg:province":"NY",
    "sg:tags":[
        "village"
    ],
    "wof:name":"Larchmont Taxes",
    "wof:placetype":"venue"
},
  "geometry": {"coordinates":[-73.751412,40.927568],"type":"Point"}
}