{
  "type": "Feature",
  "properties": {
    "addr:full":"541 3rd Avenue New York NY 10016",
    "addr:housenumber":"541",
    "addr:postcode":"10016",
    "addr:street":"3Rd Avenue",
    "iso:country":"US",
    "sg:address":"541 3rd Avenue",
    "sg:city":"New York",
    "sg:classifiers":[
        {
            "category":"Personal",
            "subcategory":"Shoe Repair & Shine",
            "type":"Services"
        }
    ],
    "sg:phone":"+1 212 684 7564",
    "sg:postcode":"10016",
    "sg:province":"NY",
    "wof:name":"Andrea's Shoe Repair",
    "wof:placetype":"venue"
},
  "geometry": {"coordinates":[-73.97745,40.746847],"type":"Point"}
}