{
  "type": "Feature",
  "properties": {
    "addr:full":"689 N Clinton St Syracuse NY 13204",
    "addr:housenumber":"689",
    "addr:postcode":"13204",
    "addr:street":"N Clinton St",
    "iso:country":"US",
    "sg:address":"689 N Clinton St",
    "sg:city":"Syracuse",
    "sg:classifiers":[
        {
            "category":"Shopping",
            "subcategory":"Musical Instruments",
            "type":"Retail Goods"
        }
    ],
    "sg:phone":"+1 315 701 0457",
    "sg:postcode":"13204",
    "sg:province":"NY",
    "sg:tags":[
        "music",
        "dealer"
    ],
    "wof:name":"VIP Music Distr",
    "wof:placetype":"venue"
},
  "geometry": {"coordinates":[-76.15680399999999,43.059456],"type":"Point"}
}