{
  "type": "Feature",
  "properties": {
    "addr:full":"109 Newbridge Rd Hicksville NY 11801",
    "addr:housenumber":"109",
    "addr:postcode":"11801",
    "addr:street":"Newbridge Rd",
    "iso:country":"US",
    "sg:address":"109 Newbridge Rd",
    "sg:city":"Hicksville",
    "sg:classifiers":[
        {
            "category":"Professional",
            "type":"Services"
        }
    ],
    "sg:phone":"+1 516 529 7777",
    "sg:postcode":"11801",
    "sg:province":"NY",
    "sg:tags":[
        "establishment"
    ],
    "wof:name":"Blutter & Blutter",
    "wof:placetype":"venue"
},
  "geometry": {"coordinates":[-73.527148,40.765077],"type":"Point"}
}