{
  "type": "Feature",
  "properties": {
    "iso:country":"US",
    "sg:address":"190 Ward St",
    "sg:city":"Montgomery",
    "sg:classifiers":[
        {
            "category":"Autos & Motor Vehicles",
            "subcategory":"Fuel & Gas Station",
            "type":"Retail Goods"
        }
    ],
    "sg:phone":"+1 845 457 9559",
    "sg:postcode":"12549",
    "sg:province":"NY",
    "wof:name":"Kaufmans Exxon",
    "wof:placetype":"venue"
},
  "geometry": {"coordinates":[-74.23066799999999,41.525987],"type":"Point"}
}