{
  "type": "Feature",
  "properties": {
    "addr:full":"1170 Port Washington Blvd Port Washington NY 11050",
    "addr:housenumber":"1170",
    "addr:postcode":"11050",
    "addr:street":"Port Washington Blvd",
    "iso:country":"US",
    "sg:address":"1170 Port Washington Blvd",
    "sg:city":"Port Washington",
    "sg:classifiers":[
        {
            "category":"Health Services",
            "subcategory":"Chiropractor",
            "type":"Services"
        }
    ],
    "sg:phone":"+1 516 944 0410",
    "sg:postcode":"11050",
    "sg:province":"NY",
    "wof:name":"Yoram Amiran DC",
    "wof:placetype":"venue"
},
  "geometry": {"coordinates":[-73.68515499999999,40.833133],"type":"Point"}
}