{
  "type": "Feature",
  "properties": {
    "iso:country":"US",
    "sg:address":"12 W 23rd St Frnt",
    "sg:city":"New York",
    "sg:classifiers":[
        {
            "category":"Retail",
            "subcategory":"Auto Repair",
            "type":"Services"
        }
    ],
    "sg:phone":"+1 646 452 0370",
    "sg:postcode":"10010",
    "sg:province":"NY",
    "wof:name":"Added Auto Repair",
    "wof:placetype":"venue"
},
  "geometry": {"coordinates":[-73.989502,40.7416],"type":"Point"}
}