{
  "type": "Feature",
  "properties": {
    "addr:full":"173 Woodhull Ave Riverhead NY 11901",
    "addr:housenumber":"173",
    "addr:postcode":"11901",
    "addr:street":"Woodhull Ave",
    "iso:country":"US",
    "sg:address":"173 Woodhull Ave",
    "sg:city":"Riverhead",
    "sg:classifiers":[
        {
            "category":"Professional",
            "type":"Services"
        }
    ],
    "sg:phone":"+1 631 727 1199",
    "sg:postcode":"11901",
    "sg:province":"NY",
    "sg:tags":[
        "establishment"
    ],
    "wof:name":"Ohana Enterprises",
    "wof:placetype":"venue"
},
  "geometry": {"coordinates":[-72.664225,40.91425],"type":"Point"}
}