{
  "type": "Feature",
  "properties": {
    "addr:full":"3314 Ditmars Blvd Astoria NY 11105",
    "addr:housenumber":"3314",
    "addr:postcode":"11105",
    "addr:street":"Ditmars Blvd",
    "iso:country":"US",
    "sg:address":"3314 Ditmars Blvd",
    "sg:city":"Astoria",
    "sg:classifiers":[
        {
            "category":"Food & Beverages",
            "subcategory":"Meat & Fish",
            "type":"Retail Goods"
        }
    ],
    "sg:phone":"+1 718 728 3810",
    "sg:postcode":"11105",
    "sg:province":"NY",
    "sg:tags":[
        "shop"
    ],
    "wof:name":"K & T 2 Quality Meats Inc",
    "wof:placetype":"venue"
},
  "geometry": {"coordinates":[-73.909599,40.775299],"type":"Point"}
}