{
  "type": "Feature",
  "properties": {
    "addr:full":"502 Park Ave New York NY 10022",
    "addr:housenumber":"502",
    "addr:postcode":"10022",
    "addr:street":"Park Ave",
    "iso:country":"US",
    "sg:address":"502 Park Ave",
    "sg:city":"New York",
    "sg:classifiers":[
        {
            "category":"Freight",
            "type":"Transportation"
        }
    ],
    "sg:phone":"+1 212 486 8125",
    "sg:postcode":"10022",
    "sg:province":"NY",
    "sg:tags":[
        "shipping",
        "agent"
    ],
    "wof:name":"AOCS Inc",
    "wof:placetype":"venue"
},
  "geometry": {"coordinates":[-73.969337,40.763546],"type":"Point"}
}