{
  "type": "Feature",
  "properties": {
    "iso:country":"US",
    "sg:address":"161 8th Ave",
    "sg:city":"Troy",
    "sg:classifiers":[
        {
            "category":"Home & Garden",
            "subcategory":"Carpets & Floor Coverings",
            "type":"Retail Goods"
        }
    ],
    "sg:phone":"+1   ",
    "sg:postcode":"12180",
    "sg:province":"NY",
    "wof:name":"North Country Carpet",
    "wof:placetype":"venue"
},
  "geometry": {"coordinates":[-73.67724800000001,42.756551],"type":"Point"}
}