{
  "type": "Feature",
  "properties": {
    "iso:country":"US",
    "sg:address":"11 Hastings Dr",
    "sg:city":"Beacon",
    "sg:classifiers":[
        {
            "category":"Health Services",
            "subcategory":"Doctor",
            "type":"Services"
        },
        {
            "category":"Health Services",
            "subcategory":"Clinic",
            "type":"Services"
        },
        {
            "category":"Health Services",
            "subcategory":"Hospital",
            "type":"Services"
        }
    ],
    "sg:phone":"+1 845 838 3816",
    "sg:postcode":"12508",
    "sg:province":"NY",
    "sg:tags":[
        "counseling",
        "mental"
    ],
    "wof:name":"St Francis Hospital",
    "wof:placetype":"venue"
},
  "geometry": {"coordinates":[-73.958504,41.509399],"type":"Point"}
}