{
  "type": "Feature",
  "properties": {
    "addr:full":"19 Wood Ln Levittown NY 11756",
    "addr:housenumber":"19",
    "addr:postcode":"11756",
    "addr:street":"Wood Ln",
    "iso:country":"US",
    "sg:address":"19 Wood Ln",
    "sg:city":"Levittown",
    "sg:classifiers":[
        {
            "category":"Travel",
            "subcategory":"Travel Agent",
            "type":"Entertainment"
        }
    ],
    "sg:phone":"+1 516 579 5966",
    "sg:postcode":"11756",
    "sg:province":"NY",
    "sg:tags":[
        "agency",
        "bureau"
    ],
    "wof:name":"Travel Friends",
    "wof:placetype":"venue"
},
  "geometry": {"coordinates":[-73.509652,40.713157],"type":"Point"}
}