{
  "type": "Feature",
  "properties": {
    "iso:country":"US",
    "sg:address":"163 Ludlow St",
    "sg:city":"New York",
    "sg:classifiers":[
        {
            "category":"Building & Trades",
            "subcategory":"Construction",
            "type":"Services"
        }
    ],
    "sg:phone":"+1 212 505 7365",
    "sg:postcode":"10002",
    "sg:province":"NY",
    "sg:tags":[
        "carpentry",
        "contractor"
    ],
    "wof:name":"Superior Service Co",
    "wof:placetype":"venue"
},
  "geometry": {"coordinates":[-73.98724199999999,40.722401],"type":"Point"}
}