{
  "type": "Feature",
  "properties": {
    "iso:country":"US",
    "sg:address":"26531 Three Mile Point Rd",
    "sg:city":"Chaumont",
    "sg:classifiers":[
        {
            "category":"Building & Trades",
            "subcategory":"Construction",
            "type":"Services"
        }
    ],
    "sg:phone":"+1 315 649 2790",
    "sg:postcode":"13622",
    "sg:province":"NY",
    "sg:tags":[
        "general",
        "contractor"
    ],
    "wof:name":"Charles Valentine Construction",
    "wof:placetype":"venue"
},
  "geometry": {"coordinates":[-76.176749,44.064008],"type":"Point"}
}