{
  "type": "Feature",
  "properties": {
    "addr:full":"296 Smith St Brooklyn NY 11231",
    "addr:housenumber":"296",
    "addr:postcode":"11231",
    "addr:street":"Smith St",
    "iso:country":"US",
    "sg:address":"296 Smith St",
    "sg:city":"Brooklyn",
    "sg:classifiers":[
        {
            "category":"Manufacturing",
            "subcategory":"Apparel",
            "type":"Manufacturing & Wholesale Goods"
        }
    ],
    "sg:phone":"+1 718 855 0311",
    "sg:postcode":"11231",
    "sg:province":"NY",
    "sg:tags":[
        "clothing"
    ],
    "wof:name":"Frida's Closet",
    "wof:placetype":"venue"
},
  "geometry": {"coordinates":[-73.993723,40.682168],"type":"Point"}
}