{
  "type": "Feature",
  "properties": {
    "iso:country":"US",
    "sg:address":"94 Columbia St",
    "sg:city":"Cohoes",
    "sg:classifiers":[
        {
            "category":"Food & Beverages",
            "subcategory":"Groceries & Convenience Stores",
            "type":"Retail Goods"
        }
    ],
    "sg:phone":"+1 518 235 9821",
    "sg:postcode":"12047",
    "sg:province":"NY",
    "sg:website":"www.stewartsicecream.com",
    "wof:name":"Stewart's Shop",
    "wof:placetype":"venue"
},
  "geometry": {"coordinates":[-73.703361,42.769734],"type":"Point"}
}