{
  "type": "Feature",
  "properties": {
    "addr:full":"336 78th Street Brooklyn NY 11209",
    "addr:housenumber":"336",
    "addr:postcode":"11209",
    "addr:street":"78Th Street",
    "iso:country":"US",
    "sg:address":"336 78th Street",
    "sg:city":"Brooklyn",
    "sg:classifiers":[
        {
            "category":"Health Services",
            "subcategory":"Doctor",
            "type":"Services"
        }
    ],
    "sg:phone":"+1 718 745 6693",
    "sg:postcode":"11209",
    "sg:province":"NY",
    "wof:name":"Khoury Nidal MD",
    "wof:placetype":"venue"
},
  "geometry": {"coordinates":[-74.027224,40.628831],"type":"Point"}
}