{
  "type": "Feature",
  "properties": {
    "addr:full":"9528 Ave L Brooklyn NY 11236",
    "addr:housenumber":"9528",
    "addr:postcode":"11236",
    "addr:street":"Ave L",
    "iso:country":"US",
    "sg:address":"9528 Ave L",
    "sg:city":"Brooklyn",
    "sg:classifiers":[
        {
            "category":"Restaurant",
            "type":"Food & Drink"
        }
    ],
    "sg:phone":"+1 718 251 0050",
    "sg:postcode":"11236",
    "sg:province":"NY",
    "wof:name":"Family Garden Chinese Rstrnt",
    "wof:placetype":"venue"
},
  "geometry": {"coordinates":[-73.89613199999999,40.638006],"type":"Point"}
}