{
  "type": "Feature",
  "properties": {
    "iso:country":"US",
    "sg:address":"5 Westminster Dr",
    "sg:city":"White Plains",
    "sg:classifiers":[
        {
            "category":"Building & Trades",
            "subcategory":"Construction",
            "type":"Services"
        }
    ],
    "sg:phone":"+1 914 682 9575",
    "sg:postcode":"10604",
    "sg:province":"NY",
    "sg:tags":[
        "hanging",
        "contractor"
    ],
    "wof:name":"Valencia Painting Inc",
    "wof:placetype":"venue"
},
  "geometry": {"coordinates":[-73.760604,41.046188],"type":"Point"}
}