{
  "type": "Feature",
  "properties": {
    "iso:country":"US",
    "sg:address":"46-09 Queens Blvd",
    "sg:city":"Sunnyside",
    "sg:classifiers":[
        {
            "category":"Coffee & Tea",
            "type":"Food & Drink"
        }
    ],
    "sg:phone":"+1 718 472 5215",
    "sg:postcode":"11104",
    "sg:province":"NY",
    "sg:website":"www.starbucks.com",
    "wof:name":"Starbucks",
    "wof:placetype":"venue"
},
  "geometry": {"coordinates":[-73.918504,40.743312],"type":"Point"}
}