{
  "type": "Feature",
  "properties": {
    "addr:full":"34 Ivy Way Lancaster NY 14086",
    "addr:housenumber":"34",
    "addr:postcode":"14086",
    "addr:street":"Ivy Way",
    "iso:country":"US",
    "sg:address":"34 Ivy Way",
    "sg:city":"Lancaster",
    "sg:classifiers":[
        {
            "category":"Real Estate",
            "subcategory":"Real Estate Services",
            "type":"Services"
        },
        {
            "category":"Building & Trades",
            "subcategory":"Cleaning & Sanitation",
            "type":"Services"
        }
    ],
    "sg:phone":"+1 716 681 0514",
    "sg:postcode":"14086",
    "sg:province":"NY",
    "sg:tags":[
        "maintenance",
        "cleaners-interior"
    ],
    "wof:name":"Atp Service",
    "wof:placetype":"venue"
},
  "geometry": {"coordinates":[-78.65844,42.896519],"type":"Point"}
}