{
  "type": "Feature",
  "properties": {
    "addr:full":"34 Church St Malverne NY 11565",
    "addr:housenumber":"34",
    "addr:postcode":"11565",
    "addr:street":"Church St",
    "iso:country":"US",
    "sg:address":"34 Church St",
    "sg:city":"Malverne",
    "sg:classifiers":[
        {
            "category":"Personal",
            "subcategory":"Barber",
            "type":"Services"
        }
    ],
    "sg:phone":"+1 516 596 0469",
    "sg:postcode":"11565",
    "sg:province":"NY",
    "sg:tags":[
        "shop"
    ],
    "wof:name":"Delphi Barber Shop",
    "wof:placetype":"venue"
},
  "geometry": {"coordinates":[-73.66860200000001,40.674999],"type":"Point"}
}