{
  "type": "Feature",
  "properties": {
    "addr:full":"233 Grand Blvd Westbury NY 11590",
    "addr:housenumber":"233",
    "addr:postcode":"11590",
    "addr:street":"Grand Blvd",
    "iso:country":"US",
    "sg:address":"233 Grand Blvd",
    "sg:city":"Westbury",
    "sg:classifiers":[
        {
            "category":"Building & Trades",
            "subcategory":"Plumbing",
            "type":"Services"
        }
    ],
    "sg:phone":"+1 516 997 5656",
    "sg:postcode":"11590",
    "sg:province":"NY",
    "sg:tags":[
        "conditioning",
        "air",
        "heating",
        "contractor"
    ],
    "sg:website":"www.countyfair.com",
    "wof:name":"County Fair Air Conditioning",
    "wof:placetype":"venue"
},
  "geometry": {"coordinates":[-73.575557,40.756939],"type":"Point"}
}