{
  "type": "Feature",
  "properties": {
    "addr:full":"298 Red Maple Dr S Wantagh NY 11793",
    "addr:housenumber":"298",
    "addr:postcode":"11793",
    "addr:street":"Red Maple Dr S",
    "iso:country":"US",
    "sg:address":"298 Red Maple Dr S",
    "sg:city":"Wantagh",
    "sg:classifiers":[
        {
            "category":"Banks & Credit Unions",
            "subcategory":"Financial Services",
            "type":"Services"
        }
    ],
    "sg:phone":"+1 516 796 5754",
    "sg:postcode":"11793",
    "sg:province":"NY",
    "sg:tags":[
        "investor"
    ],
    "sg:website":"www.wallstreetonlinesite.com",
    "wof:name":"Variable Annuity Co",
    "wof:placetype":"venue"
},
  "geometry": {"coordinates":[-73.497102,40.706835],"type":"Point"}
}