{
  "type": "Feature",
  "properties": {
    "iso:country":"US",
    "sg:address":"3258 Abbott Rd",
    "sg:city":"Orchard Park",
    "sg:classifiers":[
        {
            "category":"Autos & Motor Vehicles",
            "subcategory":"Automobile Sales",
            "type":"Retail Goods"
        }
    ],
    "sg:phone":"+1   ",
    "sg:postcode":"14127",
    "sg:province":"NY",
    "sg:tags":[
        "used"
    ],
    "wof:name":"Wayne C Taneff",
    "wof:placetype":"venue"
},
  "geometry": {"coordinates":[-78.794797,42.796281],"type":"Point"}
}