{
  "type": "Feature",
  "properties": {
    "addr:full":"67 Oakdale-Bohemia Rd Oakdale NY 11769",
    "addr:housenumber":"67",
    "addr:postcode":"11769",
    "addr:street":"Oakdale-Bohemia Rd",
    "iso:country":"US",
    "sg:address":"67 Oakdale-Bohemia Rd",
    "sg:city":"Oakdale",
    "sg:classifiers":[
        {
            "category":"Organizations",
            "subcategory":"Religious Organization",
            "type":"Services"
        }
    ],
    "sg:phone":"+1 631 563 1663",
    "sg:postcode":"11769",
    "sg:province":"NY",
    "sg:tags":[
        "synagogue"
    ],
    "sg:website":"www.bnai-israel.org",
    "wof:name":"B'Nai Israel Reform Temple",
    "wof:placetype":"venue"
},
  "geometry": {"coordinates":[-73.12723200000001,40.74816],"type":"Point"}
}