{
  "type": "Feature",
  "properties": {
    "iso:country":"US",
    "sg:address":"9676 State Hwy 19",
    "sg:city":"Houghton",
    "sg:classifiers":[
        {
            "category":"Food & Beverages",
            "subcategory":"Groceries & Convenience Stores",
            "type":"Retail Goods"
        }
    ],
    "sg:phone":"+1   ",
    "sg:postcode":"14744",
    "sg:province":"NY",
    "wof:name":"Houghton Mini Mart",
    "wof:placetype":"venue"
},
  "geometry": {"coordinates":[-78.157758,42.422534],"type":"Point"}
}