{
  "type": "Feature",
  "properties": {
    "iso:country":"US",
    "sg:address":"1306 Gowans Rd",
    "sg:city":"Angola",
    "sg:classifiers":[
        {
            "category":"Restaurant",
            "type":"Food & Drink"
        }
    ],
    "sg:phone":"+1   ",
    "sg:postcode":"14006",
    "sg:province":"NY",
    "sg:tags":[
        "eating"
    ],
    "wof:name":"Evangola Pizzaria",
    "wof:placetype":"venue"
},
  "geometry": {"coordinates":[-79.018299,42.641628],"type":"Point"}
}