{
  "type": "Feature",
  "properties": {
    "addr:full":"1624 Voorhies Ave Brooklyn NY 11235",
    "addr:housenumber":"1624",
    "addr:postcode":"11235",
    "addr:street":"Voorhies Ave",
    "iso:country":"US",
    "sg:address":"1624 Voorhies Ave",
    "sg:city":"Brooklyn",
    "sg:classifiers":[
        {
            "category":"Professional",
            "subcategory":"Lawyer & Legal Services",
            "type":"Services"
        }
    ],
    "sg:phone":"+1 718 646 7360",
    "sg:postcode":"11235",
    "sg:province":"NY",
    "sg:tags":[
        "attorney"
    ],
    "wof:name":"Gursoy & Schneider PC",
    "wof:placetype":"venue"
},
  "geometry": {"coordinates":[-73.952083,40.585831],"type":"Point"}
}