{
  "type": "Feature",
  "properties": {
    "addr:full":"300 Maspeth Ave Brooklyn NY 11211",
    "addr:housenumber":"300",
    "addr:postcode":"11211",
    "addr:street":"Maspeth Ave",
    "iso:country":"US",
    "sg:address":"300 Maspeth Ave",
    "sg:city":"Brooklyn",
    "sg:classifiers":[
        {
            "category":"Freight",
            "type":"Transportation"
        }
    ],
    "sg:phone":"+1   ",
    "sg:postcode":"11211",
    "sg:province":"NY",
    "sg:tags":[
        "delivery",
        "local"
    ],
    "wof:name":"Fedex",
    "wof:placetype":"venue"
},
  "geometry": {"coordinates":[-73.932878,40.717496],"type":"Point"}
}