{
  "type": "Feature",
  "properties": {
    "addr:full":"2116 S Park Ave Buffalo NY 14220",
    "addr:housenumber":"2116",
    "addr:postcode":"14220",
    "addr:street":"S Park Ave",
    "iso:country":"US",
    "sg:address":"2116 S Park Ave",
    "sg:city":"Buffalo",
    "sg:classifiers":[
        {
            "category":"Retail",
            "subcategory":"Auto Repair",
            "type":"Services"
        }
    ],
    "sg:phone":"+1 716 825 6459",
    "sg:postcode":"14220",
    "sg:province":"NY",
    "sg:tags":[
        "repairing",
        "automobile"
    ],
    "wof:name":"Steve Stack's Auto Repair Svce",
    "wof:placetype":"venue"
},
  "geometry": {"coordinates":[-78.823898,42.841099],"type":"Point"}
}