{
  "type": "Feature",
  "properties": {
    "iso:country":"US",
    "sg:address":"209 Willowood Dr",
    "sg:city":"Rochester",
    "sg:classifiers":[
        {
            "category":"Professional",
            "subcategory":"Management & Consulting",
            "type":"Services"
        }
    ],
    "sg:phone":"+1   ",
    "sg:postcode":"14612",
    "sg:province":"NY",
    "sg:tags":[
        "retail",
        "direct",
        "sales"
    ],
    "wof:name":"Party Lite Lisa Grasta",
    "wof:placetype":"venue"
},
  "geometry": {"coordinates":[-77.691278,43.246152],"type":"Point"}
}