{
  "type": "Feature",
  "properties": {
    "addr:full":"36 Allegro St Staten Island NY 10312",
    "addr:housenumber":"36",
    "addr:postcode":"10312",
    "addr:street":"Allegro St",
    "iso:country":"US",
    "sg:address":"36 Allegro St",
    "sg:city":"Staten Island",
    "sg:classifiers":[
        {
            "category":"Banks & Credit Unions",
            "subcategory":"Bank",
            "type":"Services"
        }
    ],
    "sg:phone":"+1 718 356 7410",
    "sg:postcode":"10312",
    "sg:province":"NY",
    "sg:tags":[
        "loan",
        "real estate"
    ],
    "wof:name":"Yonkers Savings & Loan Assn",
    "wof:placetype":"venue"
},
  "geometry": {"coordinates":[-74.176244,40.527745],"type":"Point"}
}