{
  "type": "Feature",
  "properties": {
    "iso:country":"US",
    "sg:address":"4301 Bronx Blvd",
    "sg:city":"Bronx",
    "sg:classifiers":[
        {
            "category":"Building & Trades",
            "subcategory":"Construction",
            "type":"Services"
        }
    ],
    "sg:phone":"+1 718 881 9162",
    "sg:postcode":"10466",
    "sg:province":"NY",
    "sg:tags":[
        "company"
    ],
    "wof:name":"Red Hook Construction",
    "wof:placetype":"venue"
},
  "geometry": {"coordinates":[-73.85865099999999,40.898564],"type":"Point"}
}