{
  "type": "Feature",
  "properties": {
    "iso:country":"US",
    "sg:address":"62 4th St",
    "sg:city":"Brooklyn",
    "sg:classifiers":[
        {
            "category":"Sports & Exercise",
            "subcategory":"Gym",
            "type":"Entertainment"
        }
    ],
    "sg:phone":"+1 917 541 8902",
    "sg:postcode":"11231",
    "sg:province":"NY",
    "sg:tags":[
        "club",
        "health",
        "studio",
        "gymnasium"
    ],
    "wof:name":"Brooklyn Fencing Ctr",
    "wof:placetype":"venue"
},
  "geometry": {"coordinates":[-73.99251,40.676345],"type":"Point"}
}