{
  "type": "Feature",
  "properties": {
    "iso:country":"US",
    "sg:address":"260 6th St",
    "sg:city":"Verplanck",
    "sg:classifiers":[
        {
            "category":"Professional",
            "type":"Services"
        }
    ],
    "sg:phone":"+1 914 737 4503",
    "sg:postcode":"10596",
    "sg:province":"NY",
    "sg:tags":[
        "establishment"
    ],
    "wof:name":"Harvey Hutter & Co",
    "wof:placetype":"venue"
},
  "geometry": {"coordinates":[-73.96435099999999,41.255184],"type":"Point"}
}