{
  "type": "Feature",
  "properties": {
    "addr:full":"196 Mc Clellan St Bronx NY 10456",
    "addr:housenumber":"196",
    "addr:postcode":"10456",
    "addr:street":"Mc Clellan St",
    "iso:country":"US",
    "sg:address":"196 Mc Clellan St",
    "sg:city":"Bronx",
    "sg:classifiers":[
        {
            "category":"Restaurant",
            "type":"Food & Drink"
        }
    ],
    "sg:phone":"+1 718 681 3240",
    "sg:postcode":"10456",
    "sg:province":"NY",
    "wof:name":"Papaye Restaurant",
    "wof:placetype":"venue"
},
  "geometry": {"coordinates":[-73.918064,40.832728],"type":"Point"}
}