{
  "type": "Feature",
  "properties": {
    "iso:country":"US",
    "sg:address":"291 Reed Rd",
    "sg:city":"Clyde",
    "sg:classifiers":[
        {
            "category":"Organizations",
            "subcategory":"Religious Organization",
            "type":"Services"
        }
    ],
    "sg:phone":"+1 315 946 0553",
    "sg:postcode":"14433",
    "sg:province":"NY",
    "sg:tags":[
        "church"
    ],
    "wof:name":"Clyde Mapleview Church",
    "wof:placetype":"venue"
},
  "geometry": {"coordinates":[-76.938282,43.014469],"type":"Point"}
}