{
  "type": "Feature",
  "properties": {
    "iso:country":"US",
    "sg:address":"339 Iradell Rd",
    "sg:city":"Ithaca",
    "sg:classifiers":[
        {
            "category":"Autos & Motor Vehicles",
            "subcategory":"Automobile Sales",
            "type":"Retail Goods"
        }
    ],
    "sg:phone":"+1 607 387 7199",
    "sg:postcode":"14850",
    "sg:province":"NY",
    "sg:tags":[
        "car",
        "used",
        "dealer"
    ],
    "wof:name":"Countryside Automotive",
    "wof:placetype":"venue"
},
  "geometry": {"coordinates":[-76.608503,42.481156],"type":"Point"}
}