{
  "type": "Feature",
  "properties": {
    "iso:country":"US",
    "sg:address":"1805 Deer Park Ave",
    "sg:city":"Deer Park",
    "sg:classifiers":[
        {
            "category":"Restaurant",
            "type":"Food & Drink"
        }
    ],
    "sg:phone":"+1 631 254 0453",
    "sg:postcode":"11729",
    "sg:province":"NY",
    "wof:name":"Aladdin Sweets & Cafe",
    "wof:placetype":"venue"
},
  "geometry": {"coordinates":[-73.32794699999999,40.758612],"type":"Point"}
}