{
  "type": "Feature",
  "properties": {
    "addr:full":"58 Richmond Blvd Ronkonkoma NY 11779",
    "addr:housenumber":"58",
    "addr:postcode":"11779",
    "addr:street":"Richmond Blvd",
    "iso:country":"US",
    "sg:address":"58 Richmond Blvd",
    "sg:city":"Ronkonkoma",
    "sg:classifiers":[
        {
            "category":"Real Estate",
            "subcategory":"Real Estate Agent",
            "type":"Services"
        }
    ],
    "sg:phone":"+1 631 471 3344",
    "sg:postcode":"11779",
    "sg:province":"NY",
    "sg:tags":[
        "appraiser"
    ],
    "wof:name":"Market Vision Appraisal Svc",
    "wof:placetype":"venue"
},
  "geometry": {"coordinates":[-73.14909900000001,40.822807],"type":"Point"}
}