{
  "type": "Feature",
  "properties": {
    "addr:full":"110 E Seneca St Sherrill NY 13461",
    "addr:housenumber":"110",
    "addr:postcode":"13461",
    "addr:street":"E Seneca St",
    "iso:country":"US",
    "sg:address":"110 E Seneca St",
    "sg:city":"Sherrill",
    "sg:classifiers":[
        {
            "category":"Utilities",
            "subcategory":"Electric",
            "type":"Services"
        }
    ],
    "sg:phone":"+1   ",
    "sg:postcode":"13461",
    "sg:province":"NY",
    "sg:tags":[
        "plant",
        "power"
    ],
    "wof:name":"Sterling Powers Partners LP",
    "wof:placetype":"venue"
},
  "geometry": {"coordinates":[-75.598071,43.076697],"type":"Point"}
}