{
  "type": "Feature",
  "properties": {
    "addr:full":"65 William St Lyons NY 14489",
    "addr:housenumber":"65",
    "addr:postcode":"14489",
    "addr:street":"William St",
    "iso:country":"US",
    "sg:address":"65 William St",
    "sg:city":"Lyons",
    "sg:classifiers":[
        {
            "category":"Cinema",
            "subcategory":"Movie Theater",
            "type":"Entertainment"
        }
    ],
    "sg:phone":"+1 315 946 4604",
    "sg:postcode":"14489",
    "sg:province":"NY",
    "wof:name":"Ohmann Theaters",
    "wof:placetype":"venue"
},
  "geometry": {"coordinates":[-76.99244299999999,43.063365],"type":"Point"}
}