{
  "type": "Feature",
  "properties": {
    "iso:country":"US",
    "sg:address":"1115 E 87th St",
    "sg:city":"Brooklyn",
    "sg:classifiers":[
        {
            "category":"Organizations",
            "subcategory":"Religious Organization",
            "type":"Services"
        }
    ],
    "sg:phone":"+1 718 763 2244",
    "sg:postcode":"11236",
    "sg:province":"NY",
    "sg:tags":[
        "synagogue"
    ],
    "wof:name":"Remsen Heights Jewish Ctr",
    "wof:placetype":"venue"
},
  "geometry": {"coordinates":[-73.90347199999999,40.634592],"type":"Point"}
}