{
  "type": "Feature",
  "properties": {
    "addr:full":"494 Main St Northport NY 11768",
    "addr:housenumber":"494",
    "addr:postcode":"11768",
    "addr:street":"Main St",
    "iso:country":"US",
    "sg:address":"494 Main St",
    "sg:city":"Northport",
    "sg:classifiers":[
        {
            "category":"Real Estate",
            "subcategory":"Real Estate Agent",
            "type":"Services"
        }
    ],
    "sg:phone":"+1 631 754 3332",
    "sg:postcode":"11768",
    "sg:province":"NY",
    "wof:name":"Dawn's Horizon Realty, Inc",
    "wof:placetype":"venue"
},
  "geometry": {"coordinates":[-73.33622699999999,40.900799],"type":"Point"}
}