{
  "type": "Feature",
  "properties": {
    "iso:country":"US",
    "sg:address":"169 Main St",
    "sg:city":"Dansville",
    "sg:classifiers":[
        {
            "category":"Shopping",
            "subcategory":"Gifts & Souvenirs",
            "type":"Retail Goods"
        }
    ],
    "sg:phone":"+1   ",
    "sg:postcode":"14437",
    "sg:province":"NY",
    "wof:name":"Village Flowers & Gifts",
    "wof:placetype":"venue"
},
  "geometry": {"coordinates":[-77.69587900000001,42.560768],"type":"Point"}
}