{
  "type": "Feature",
  "properties": {
    "addr:full":"1106 Waverly Ave Holtsville NY 11742",
    "addr:housenumber":"1106",
    "addr:postcode":"11742",
    "addr:street":"Waverly Ave",
    "iso:country":"US",
    "sg:address":"1106 Waverly Ave",
    "sg:city":"Holtsville",
    "sg:classifiers":[
        {
            "category":"Food & Beverages",
            "subcategory":"Groceries & Convenience Stores",
            "type":"Retail Goods"
        }
    ],
    "sg:phone":"+1 631 475 6730",
    "sg:postcode":"11742",
    "sg:province":"NY",
    "sg:website":"www.expressmart.com",
    "wof:name":"Express Mart",
    "wof:placetype":"venue"
},
  "geometry": {"coordinates":[-73.045799,40.8223],"type":"Point"}
}