{
  "type": "Feature",
  "properties": {
    "addr:full":"347 Troutman St Brooklyn NY 11237",
    "addr:housenumber":"347",
    "addr:postcode":"11237",
    "addr:street":"Troutman St",
    "iso:country":"US",
    "sg:address":"347 Troutman St",
    "sg:city":"Brooklyn",
    "sg:classifiers":[
        {
            "category":"Wholesale",
            "subcategory":"Apparel",
            "type":"Manufacturing & Wholesale Goods"
        }
    ],
    "sg:phone":"+1 718 386 3808",
    "sg:postcode":"11237",
    "sg:province":"NY",
    "wof:name":"G C Finishing",
    "wof:placetype":"venue"
},
  "geometry": {"coordinates":[-73.92322900000001,40.706209],"type":"Point"}
}