{
  "type": "Feature",
  "properties": {
    "addr:full":"1040 State Hwy 45 Pomona NY 10970",
    "addr:housenumber":"1040",
    "addr:postcode":"10970",
    "addr:street":"State Hwy 45",
    "iso:country":"US",
    "sg:address":"1040 State Hwy 45",
    "sg:city":"Pomona",
    "sg:classifiers":[
        {
            "category":"Wholesale",
            "subcategory":"Plants",
            "type":"Manufacturing & Wholesale Goods"
        }
    ],
    "sg:phone":"+1 845 354 8500",
    "sg:postcode":"10970",
    "sg:province":"NY",
    "sg:tags":[
        "nursery",
        "stock"
    ],
    "wof:name":"Down To Earth Plants & Pdts",
    "wof:placetype":"venue"
},
  "geometry": {"coordinates":[-74.03604900000001,41.186209],"type":"Point"}
}