{
  "type": "Feature",
  "properties": {
    "addr:full":"1992 Commerce St Yorktown Heights NY 10598",
    "addr:housenumber":"1992",
    "addr:postcode":"10598",
    "addr:street":"Commerce St",
    "iso:country":"US",
    "sg:address":"1992 Commerce St",
    "sg:city":"Yorktown Heights",
    "sg:classifiers":[
        {
            "category":"Professional",
            "subcategory":"Business Services",
            "type":"Services"
        }
    ],
    "sg:phone":"+1 914 962 0605",
    "sg:postcode":"10598",
    "sg:province":"NY",
    "wof:name":"Mail Boxes Etc",
    "wof:placetype":"venue"
},
  "geometry": {"coordinates":[-73.782155,41.276096],"type":"Point"}
}