{
  "type": "Feature",
  "properties": {
    "iso:country":"US",
    "sg:address":"16 Liberty St",
    "sg:city":"Troy",
    "sg:classifiers":[
        {
            "category":"Organizations",
            "subcategory":"Community Association",
            "type":"Services"
        }
    ],
    "sg:phone":"+1   ",
    "sg:postcode":"12180",
    "sg:province":"NY",
    "wof:name":"CRAB Garrison 1954",
    "wof:placetype":"venue"
},
  "geometry": {"coordinates":[-73.688902,42.725161],"type":"Point"}
}