{
  "type": "Feature",
  "properties": {
    "addr:full":"111 Pine Hill Rd Port Jefferson NY 11777",
    "addr:housenumber":"111",
    "addr:postcode":"11777",
    "addr:street":"Pine Hill Rd",
    "iso:country":"US",
    "sg:address":"111 Pine Hill Rd",
    "sg:city":"Port Jefferson",
    "sg:classifiers":[
        {
            "category":"Banks & Credit Unions",
            "subcategory":"Investment Brokerage",
            "type":"Services"
        }
    ],
    "sg:phone":"+1 631 473 2558",
    "sg:postcode":"11777",
    "sg:province":"NY",
    "sg:website":"www.edwardjones.com",
    "wof:name":"Edward Jones",
    "wof:placetype":"venue"
},
  "geometry": {"coordinates":[-73.04405800000001,40.941609],"type":"Point"}
}