{
  "type": "Feature",
  "properties": {
    "iso:country":"US",
    "sg:address":"4557 E Lake Rd",
    "sg:city":"Wilson",
    "sg:classifiers":[
        {
            "category":"Organizations",
            "subcategory":"Religious Organization",
            "type":"Services"
        }
    ],
    "sg:phone":"+1 716 751 9376",
    "sg:postcode":"14172",
    "sg:province":"NY",
    "sg:tags":[
        "clergy"
    ],
    "wof:name":"John Wetherwax",
    "wof:placetype":"venue"
},
  "geometry": {"coordinates":[-78.798204,43.322859],"type":"Point"}
}