{
  "type": "Feature",
  "properties": {
    "iso:country":"US",
    "sg:address":"2610 Pine Ave",
    "sg:city":"Niagara Falls",
    "sg:classifiers":[
        {
            "category":"Wholesale",
            "subcategory":"Fruits & Vegetables",
            "type":"Manufacturing & Wholesale Goods"
        }
    ],
    "sg:phone":"+1 716 282 6086",
    "sg:postcode":"14301",
    "sg:province":"NY",
    "wof:name":"Grana Produce",
    "wof:placetype":"venue"
},
  "geometry": {"coordinates":[-79.030186,43.0952],"type":"Point"}
}