{
  "type": "Feature",
  "properties": {
    "addr:full":"1233 Abbott Rd Buffalo NY 14218",
    "addr:housenumber":"1233",
    "addr:postcode":"14218",
    "addr:street":"Abbott Rd",
    "iso:country":"US",
    "sg:address":"1233 Abbott Rd",
    "sg:city":"Buffalo",
    "sg:classifiers":[
        {
            "category":"Shopping",
            "subcategory":"Discount & Variety Stores",
            "type":"Retail Goods"
        }
    ],
    "sg:phone":"+1   ",
    "sg:postcode":"14218",
    "sg:province":"NY",
    "wof:name":"Dollar General",
    "wof:placetype":"venue"
},
  "geometry": {"coordinates":[-78.805301,42.830798],"type":"Point"}
}