{
  "type": "Feature",
  "properties": {
    "iso:country":"US",
    "sg:address":"320 Park Ave",
    "sg:city":"Lockport",
    "sg:classifiers":[
        {
            "category":"Home & Garden",
            "subcategory":"Furniture",
            "type":"Retail Goods"
        }
    ],
    "sg:phone":"+1   ",
    "sg:postcode":"14094",
    "sg:province":"NY",
    "sg:website":"www.pieslockportfurniture.com",
    "wof:name":"Pies Lockport Furn Galleries",
    "wof:placetype":"venue"
},
  "geometry": {"coordinates":[-78.708692,43.168532],"type":"Point"}
}