{
  "type": "Feature",
  "properties": {
    "addr:full":"1827 Pitkin Ave Brooklyn NY 11212",
    "addr:housenumber":"1827",
    "addr:postcode":"11212",
    "addr:street":"Pitkin Ave",
    "iso:country":"US",
    "sg:address":"1827 Pitkin Ave",
    "sg:city":"Brooklyn",
    "sg:classifiers":[
        {
            "category":"Autos & Motor Vehicles",
            "subcategory":"Auto Supplies",
            "type":"Retail Goods"
        }
    ],
    "sg:phone":"+1 718 342 0700",
    "sg:postcode":"11212",
    "sg:province":"NY",
    "sg:tags":[
        "automobile",
        "parts",
        "accessory"
    ],
    "wof:name":"Brooklyn Auto Parts Co Inc",
    "wof:placetype":"venue"
},
  "geometry": {"coordinates":[-73.90557,40.67051],"type":"Point"}
}