{
  "type": "Feature",
  "properties": {
    "addr:full":"3556 Bedford Ave Brooklyn NY 11210",
    "addr:housenumber":"3556",
    "addr:postcode":"11210",
    "addr:street":"Bedford Ave",
    "iso:country":"US",
    "sg:address":"3556 Bedford Ave",
    "sg:city":"Brooklyn",
    "sg:classifiers":[
        {
            "category":"Professional",
            "type":"Services"
        }
    ],
    "sg:phone":"+1 718 244 2214",
    "sg:postcode":"11210",
    "sg:province":"NY",
    "sg:tags":[
        "establishment"
    ],
    "wof:name":"National Jewish Girl Scout",
    "wof:placetype":"venue"
},
  "geometry": {"coordinates":[-73.94954,40.615125],"type":"Point"}
}