{
  "type": "Feature",
  "properties": {
    "addr:full":"406 Main St Port Jefferson NY 11777",
    "addr:housenumber":"406",
    "addr:postcode":"11777",
    "addr:street":"Main St",
    "iso:country":"US",
    "sg:address":"406 Main St",
    "sg:city":"Port Jefferson",
    "sg:classifiers":[
        {
            "category":"Building & Trades",
            "subcategory":"Construction",
            "type":"Services"
        }
    ],
    "sg:phone":"+1 631 928 4533",
    "sg:postcode":"11777",
    "sg:province":"NY",
    "sg:tags":[
        "contractor"
    ],
    "wof:name":"Christine Ashley",
    "wof:placetype":"venue"
},
  "geometry": {"coordinates":[-73.067487,40.94399],"type":"Point"}
}