{
  "type": "Feature",
  "properties": {
    "addr:full":"421 S Broadway Hicksville NY 11801",
    "addr:housenumber":"421",
    "addr:postcode":"11801",
    "addr:street":"S Broadway",
    "iso:country":"US",
    "sg:address":"421 S Broadway",
    "sg:city":"Hicksville",
    "sg:classifiers":[
        {
            "category":"Banks & Credit Unions",
            "subcategory":"Bank",
            "type":"Services"
        }
    ],
    "sg:phone":"+1 516 681 5200",
    "sg:postcode":"11801",
    "sg:province":"NY",
    "wof:name":"Habib Amer Bank",
    "wof:placetype":"venue"
},
  "geometry": {"coordinates":[-73.51279700000001,40.758916],"type":"Point"}
}