{
  "type": "Feature",
  "properties": {
    "addr:full":"12 E 41st St New York NY 10017",
    "addr:housenumber":"12",
    "addr:postcode":"10017",
    "addr:street":"E 41St St",
    "iso:country":"US",
    "sg:address":"12 E 41st St",
    "sg:city":"New York",
    "sg:classifiers":[
        {
            "category":"Health Services",
            "subcategory":"Clinic",
            "type":"Services"
        },
        {
            "category":"Organizations",
            "subcategory":"Professional Association",
            "type":"Services"
        }
    ],
    "sg:phone":"+1 212 684 4670",
    "sg:postcode":"10017",
    "sg:province":"NY",
    "sg:tags":[
        "medical",
        "group"
    ],
    "sg:website":"www.nycms.org",
    "wof:name":"New York County Medical Soc",
    "wof:placetype":"venue"
},
  "geometry": {"coordinates":[-73.980272,40.752334],"type":"Point"}
}