{
  "type": "Feature",
  "properties": {
    "addr:full":"36 E 72nd St New York NY 10021",
    "addr:housenumber":"36",
    "addr:postcode":"10021",
    "addr:street":"E 72Nd St",
    "iso:country":"US",
    "sg:address":"36 E 72nd St",
    "sg:city":"New York",
    "sg:classifiers":[
        {
            "category":"Professional",
            "subcategory":"Lawyer & Legal Services",
            "type":"Services"
        }
    ],
    "sg:phone":"+1 212 517 7880",
    "sg:postcode":"10021",
    "sg:province":"NY",
    "wof:name":"Johnston Lowell Atty",
    "wof:placetype":"venue"
},
  "geometry": {"coordinates":[-73.96530199999999,40.771599],"type":"Point"}
}