{
  "type": "Feature",
  "properties": {
    "iso:country":"US",
    "sg:address":"271 Madison Ave",
    "sg:city":"New York",
    "sg:classifiers":[
        {
            "category":"Real Estate",
            "subcategory":"Real Estate Agent",
            "type":"Services"
        }
    ],
    "sg:phone":"+1 212 687 9300",
    "sg:postcode":"10016",
    "sg:province":"NY",
    "wof:name":"Robert P Corso & Co",
    "wof:placetype":"venue"
},
  "geometry": {"coordinates":[-73.980352,40.751132],"type":"Point"}
}