{
  "type": "Feature",
  "properties": {
    "addr:full":"2502 86th St Fl 4 Brooklyn NY 11214",
    "addr:housenumber":"2502;4",
    "addr:postcode":"11214",
    "addr:street":"86Th St",
    "iso:country":"US",
    "sg:address":"2502 86th St Fl 4",
    "sg:city":"Brooklyn",
    "sg:classifiers":[
        {
            "category":"Insurance",
            "subcategory":"Insurance Agent",
            "type":"Services"
        },
        {
            "category":"Banks & Credit Unions",
            "subcategory":"Financial Services",
            "type":"Services"
        },
        {
            "category":"Professional",
            "subcategory":"Management & Consulting",
            "type":"Services"
        }
    ],
    "sg:phone":"+1 718 946 2479",
    "sg:postcode":"11214",
    "sg:province":"NY",
    "sg:tags":[
        "financing",
        "consultant",
        "planning",
        "adjuster",
        "counseling",
        "debt"
    ],
    "wof:name":"Nationalrelief.Com",
    "wof:placetype":"venue"
},
  "geometry": {"coordinates":[-73.98712999999999,40.59788],"type":"Point"}
}