{
  "type": "Feature",
  "properties": {
    "addr:full":"5554 Main St Buffalo NY 14221",
    "addr:housenumber":"5554",
    "addr:postcode":"14221",
    "addr:street":"Main St",
    "iso:country":"US",
    "sg:address":"5554 Main St",
    "sg:city":"Buffalo",
    "sg:classifiers":[
        {
            "category":"Banks & Credit Unions",
            "subcategory":"Bank",
            "type":"Services"
        }
    ],
    "sg:phone":"+1 716 632 3741",
    "sg:postcode":"14221",
    "sg:province":"NY",
    "sg:tags":[
        "state",
        "commercial"
    ],
    "wof:name":"Hsbc Bank USA National Assn",
    "wof:placetype":"venue"
},
  "geometry": {"coordinates":[-78.746466,42.96261],"type":"Point"}
}