{
  "type": "Feature",
  "properties": {
    "addr:full":"418 Main Ave Apt 2 Wynantskill NY 12198",
    "addr:housenumber":"418;2",
    "addr:postcode":"12198",
    "addr:street":"Main Ave Apt",
    "iso:country":"US",
    "sg:address":"418 Main Ave Apt 2",
    "sg:city":"Wynantskill",
    "sg:classifiers":[
        {
            "category":"Building & Trades",
            "subcategory":"Construction",
            "type":"Services"
        }
    ],
    "sg:phone":"+1 518 283 8619",
    "sg:postcode":"12198",
    "sg:province":"NY",
    "sg:tags":[
        "painting",
        "contractor"
    ],
    "wof:name":"P W Fortin Enterior/Exterior",
    "wof:placetype":"venue"
},
  "geometry": {"coordinates":[-73.632948,42.693004],"type":"Point"}
}