{
  "type": "Feature",
  "properties": {
    "iso:country":"US",
    "sg:address":"62 S Main St",
    "sg:city":"Sayville",
    "sg:classifiers":[
        {
            "category":"Shopping",
            "subcategory":"Discount & Variety Stores",
            "type":"Retail Goods"
        }
    ],
    "sg:phone":"+1   ",
    "sg:postcode":"11782",
    "sg:province":"NY",
    "wof:name":"Fire Flies",
    "wof:placetype":"venue"
},
  "geometry": {"coordinates":[-73.08148199999999,40.73614],"type":"Point"}
}