{
  "type": "Feature",
  "properties": {
    "addr:full":"103 Applegate Dr Central Islip NY 11722",
    "addr:housenumber":"103",
    "addr:postcode":"11722",
    "addr:street":"Applegate Dr",
    "iso:country":"US",
    "sg:address":"103 Applegate Dr",
    "sg:city":"Central Islip",
    "sg:classifiers":[
        {
            "category":"Building & Trades",
            "subcategory":"Construction",
            "type":"Services"
        }
    ],
    "sg:phone":"+1 718 444 2383",
    "sg:postcode":"11722",
    "sg:province":"NY",
    "sg:tags":[
        "floor",
        "laying",
        "contractor"
    ],
    "wof:name":"Eastern Carpet & Mat",
    "wof:placetype":"venue"
},
  "geometry": {"coordinates":[-73.214521,40.795969],"type":"Point"}
}