{
  "type": "Feature",
  "properties": {
    "addr:full":"799 Broadway Ste 606 New York NY 10003",
    "addr:housenumber":"799;606",
    "addr:postcode":"10003",
    "addr:street":"Broadway Ste",
    "iso:country":"US",
    "sg:address":"799 Broadway Ste 606",
    "sg:city":"New York",
    "sg:classifiers":[
        {
            "category":"Real Estate",
            "subcategory":"Architect",
            "type":"Services"
        }
    ],
    "sg:phone":"+1 212 614 6690",
    "sg:postcode":"10003",
    "sg:province":"NY",
    "sg:website":"www.robertbischoff.com",
    "wof:name":"Robert Bischoff Architect",
    "wof:placetype":"venue"
},
  "geometry": {"coordinates":[-73.99140199999999,40.732101],"type":"Point"}
}