{
  "type": "Feature",
  "properties": {
    "iso:country":"US",
    "sg:address":"789 Beardsley Hollow Rd",
    "sg:city":"Alpine",
    "sg:classifiers":[
        {
            "category":"Professional",
            "subcategory":"Computer Services",
            "type":"Services"
        }
    ],
    "sg:phone":"+1 607 594 2850",
    "sg:postcode":"14805",
    "sg:province":"NY",
    "sg:tags":[
        "repair"
    ],
    "wof:name":"Art Matrix-Light Link Internet",
    "wof:placetype":"venue"
},
  "geometry": {"coordinates":[-76.77829699999999,42.297401],"type":"Point"}
}