{
  "type": "Feature",
  "properties": {
    "addr:full":"3035 Lasalle Ave Bronx NY 10461",
    "addr:housenumber":"3035",
    "addr:postcode":"10461",
    "addr:street":"Lasalle Ave",
    "iso:country":"US",
    "sg:address":"3035 Lasalle Ave",
    "sg:city":"Bronx",
    "sg:classifiers":[
        {
            "category":"Wholesale",
            "subcategory":"Scrap",
            "type":"Manufacturing & Wholesale Goods"
        }
    ],
    "sg:phone":"+1 718 792 7616",
    "sg:postcode":"10461",
    "sg:province":"NY",
    "sg:tags":[
        "waste"
    ],
    "wof:name":"Industrial Ecology Svc",
    "wof:placetype":"venue"
},
  "geometry": {"coordinates":[-73.827787,40.839951],"type":"Point"}
}