{
  "type": "Feature",
  "properties": {
    "iso:country":"US",
    "sg:address":"12 Berry Ln",
    "sg:city":"Pawling",
    "sg:classifiers":[
        {
            "category":"Professional",
            "subcategory":"Business Services",
            "type":"Services"
        }
    ],
    "sg:phone":"+1 845 855 1274",
    "sg:postcode":"12564",
    "sg:province":"NY",
    "sg:tags":[
        "organizing",
        "services-household"
    ],
    "wof:name":"Risk Management Services Of New York, Inc.",
    "wof:placetype":"venue"
},
  "geometry": {"coordinates":[-73.548169,41.598763],"type":"Point"}
}