{
  "type": "Feature",
  "properties": {
    "iso:country":"US",
    "sg:address":"1345 Co Rd 14",
    "sg:city":"Rensselaer Falls",
    "sg:classifiers":[
        {
            "category":"Insurance",
            "subcategory":"Insurance Agent",
            "type":"Services"
        }
    ],
    "sg:phone":"+1 315 344 7300",
    "sg:postcode":"13680",
    "sg:province":"NY",
    "wof:name":"Norton Insurance",
    "wof:placetype":"venue"
},
  "geometry": {"coordinates":[-75.313441,44.59137],"type":"Point"}
}