{
  "type": "Feature",
  "properties": {
    "addr:full":"2921 Erie Blvd E Syracuse NY 13224",
    "addr:housenumber":"2921",
    "addr:postcode":"13224",
    "addr:street":"Erie Blvd E",
    "iso:country":"US",
    "sg:address":"2921 Erie Blvd E",
    "sg:city":"Syracuse",
    "sg:classifiers":[
        {
            "category":"Shopping",
            "subcategory":"Optical Goods",
            "type":"Retail Goods"
        }
    ],
    "sg:phone":"+1   ",
    "sg:postcode":"13224",
    "sg:province":"NY",
    "wof:name":"South Shore Optometrist",
    "wof:placetype":"venue"
},
  "geometry": {"coordinates":[-76.08404,43.055683],"type":"Point"}
}