{
  "type": "Feature",
  "properties": {
    "iso:country":"US",
    "sg:address":"6636 Revere Dr",
    "sg:city":"Derby",
    "sg:classifiers":[
        {
            "category":"Manufacturing",
            "subcategory":"Metals",
            "type":"Manufacturing & Wholesale Goods"
        }
    ],
    "sg:phone":"+1   ",
    "sg:postcode":"14047",
    "sg:province":"NY",
    "wof:name":"Jeremiah Enterprises",
    "wof:placetype":"venue"
},
  "geometry": {"coordinates":[-78.975122,42.706209],"type":"Point"}
}