{
  "type": "Feature",
  "properties": {
    "iso:country":"US",
    "sg:address":"30 Gates Ave",
    "sg:city":"Plainview",
    "sg:classifiers":[
        {
            "category":"Professional",
            "subcategory":"Accounting & Tax Preparation",
            "type":"Services"
        }
    ],
    "sg:phone":"+1 516 872 8293",
    "sg:postcode":"11803",
    "sg:province":"NY",
    "sg:tags":[
        "accountant"
    ],
    "wof:name":"Scott Ruthizer CPA",
    "wof:placetype":"venue"
},
  "geometry": {"coordinates":[-73.48713499999999,40.764424],"type":"Point"}
}