{
  "type": "Feature",
  "properties": {
    "addr:full":"11235 Flanagan Rd Fillmore NY 14735",
    "addr:housenumber":"11235",
    "addr:postcode":"14735",
    "addr:street":"Flanagan Rd",
    "iso:country":"US",
    "sg:address":"11235 Flanagan Rd",
    "sg:city":"Fillmore",
    "sg:classifiers":[
        {
            "category":"Building & Trades",
            "subcategory":"Plumbing",
            "type":"Services"
        }
    ],
    "sg:phone":"+1 585 567 4540",
    "sg:postcode":"14735",
    "sg:province":"NY",
    "sg:tags":[
        "contractor"
    ],
    "wof:name":"J B Services",
    "wof:placetype":"venue"
},
  "geometry": {"coordinates":[-78.167359,42.490188],"type":"Point"}
}