{
  "type": "Feature",
  "properties": {
    "addr:full":"271 Ludington St Buffalo NY 14206",
    "addr:housenumber":"271",
    "addr:postcode":"14206",
    "addr:street":"Ludington St",
    "iso:country":"US",
    "sg:address":"271 Ludington St",
    "sg:city":"Buffalo",
    "sg:classifiers":[
        {
            "category":"Food & Beverages",
            "subcategory":"Groceries & Convenience Stores",
            "type":"Retail Goods"
        }
    ],
    "sg:phone":"+1 716 897 3711",
    "sg:postcode":"14206",
    "sg:province":"NY",
    "sg:tags":[
        "grocer"
    ],
    "wof:name":"Tele Food Delivery In",
    "wof:placetype":"venue"
},
  "geometry": {"coordinates":[-78.804001,42.887402],"type":"Point"}
}