{
  "type": "Feature",
  "properties": {
    "iso:country":"US",
    "sg:address":"1570 E Delavan Ave",
    "sg:city":"Buffalo",
    "sg:classifiers":[
        {
            "category":"Autos & Motor Vehicles",
            "subcategory":"Fuel & Gas Station",
            "type":"Retail Goods"
        }
    ],
    "sg:phone":"+1 716 897 3591",
    "sg:postcode":"14215",
    "sg:province":"NY",
    "wof:name":"Seitz Svce Sta Inc",
    "wof:placetype":"venue"
},
  "geometry": {"coordinates":[-78.798203,42.922699],"type":"Point"}
}