{
  "type": "Feature",
  "properties": {
    "addr:full":"19 Cadman Plz W Brooklyn NY 11201",
    "addr:housenumber":"19",
    "addr:postcode":"11201",
    "addr:street":"Cadman Plz W",
    "iso:country":"US",
    "sg:address":"19 Cadman Plz W",
    "sg:city":"Brooklyn",
    "sg:classifiers":[
        {
            "category":"Building & Trades",
            "subcategory":"Locksmith",
            "type":"Services"
        }
    ],
    "sg:phone":"+1 347 225 9730",
    "sg:postcode":"11201",
    "sg:province":"NY",
    "sg:tags":[
        "key"
    ],
    "wof:name":"OLD FULTON TOWING ALL DAY 24 HRS",
    "wof:placetype":"venue"
},
  "geometry": {"coordinates":[-73.993582,40.702771],"type":"Point"}
}