{
  "type": "Feature",
  "properties": {
    "addr:full":"186 Exchange St Ste 110 Buffalo NY 14204",
    "addr:housenumber":"186",
    "addr:postcode":"14204",
    "addr:street":"Exchange St Ste 110",
    "iso:country":"US",
    "sg:address":"186 Exchange St Ste 110",
    "sg:city":"Buffalo",
    "sg:classifiers":[
        {
            "category":"Government",
            "subcategory":"Office",
            "type":"Public Place"
        }
    ],
    "sg:phone":"+1 716 551 4141",
    "sg:postcode":"14204",
    "sg:province":"NY",
    "sg:tags":[
        "government-united",
        "state"
    ],
    "sg:website":"http://www.rrb.gov",
    "wof:name":"Railroad Retirement Board, United States",
    "wof:placetype":"venue"
},
  "geometry": {"coordinates":[-78.869642,42.878029],"type":"Point"}
}