{
  "type": "Feature",
  "properties": {
    "iso:country":"US",
    "sg:address":"8126 Transit Rd",
    "sg:city":"Buffalo",
    "sg:classifiers":[
        {
            "category":"Restaurant",
            "type":"Food & Drink"
        }
    ],
    "sg:menulink":"http://www.allmenus.com/ny/clarence/142607-subway/menu/",
    "sg:phone":"+1 716 688 2758",
    "sg:postcode":"14221",
    "sg:province":"NY",
    "sg:tags":[
        "american",
        "sandwich"
    ],
    "wof:name":"Subway",
    "wof:placetype":"venue"
},
  "geometry": {"coordinates":[-78.69694200000001,42.989147],"type":"Point"}
}