{
  "type": "Feature",
  "properties": {
    "addr:full":"1573 Coney Island Ave Brooklyn NY 11230",
    "addr:housenumber":"1573",
    "addr:postcode":"11230",
    "addr:street":"Coney Island Ave",
    "iso:country":"US",
    "sg:address":"1573 Coney Island Ave",
    "sg:city":"Brooklyn",
    "sg:classifiers":[
        {
            "category":"Shopping",
            "type":"Retail Goods"
        }
    ],
    "sg:phone":"+1 718 253 2351",
    "sg:postcode":"11230",
    "sg:province":"NY",
    "sg:tags":[
        "picture",
        "frame"
    ],
    "wof:name":"Get The Picture",
    "wof:placetype":"venue"
},
  "geometry": {"coordinates":[-73.963937,40.618854],"type":"Point"}
}