{
  "type": "Feature",
  "properties": {
    "addr:full":"85 N 5th St Brooklyn NY 11211",
    "addr:housenumber":"85",
    "addr:postcode":"11211",
    "addr:street":"N 5Th St",
    "iso:country":"US",
    "sg:address":"85 N 5th St",
    "sg:city":"Brooklyn",
    "sg:classifiers":[
        {
            "category":"Professional",
            "subcategory":"Management & Consulting",
            "type":"Services"
        }
    ],
    "sg:phone":"+1 718 388 1704",
    "sg:postcode":"11211",
    "sg:province":"NY",
    "sg:tags":[
        "logistics"
    ],
    "wof:name":"Aim Worldwide Logistics Inc",
    "wof:placetype":"venue"
},
  "geometry": {"coordinates":[-73.96075500000001,40.718085],"type":"Point"}
}