{
  "type": "Feature",
  "properties": {
    "addr:full":"309 5th Avenue Rm 407 New York NY 10016",
    "addr:housenumber":"309;407",
    "addr:postcode":"10016",
    "addr:street":"5Th Avenue Rm",
    "iso:country":"US",
    "sg:address":"309 5th Avenue Rm 407",
    "sg:city":"New York",
    "sg:classifiers":[
        {
            "category":"Building & Trades",
            "subcategory":"Locksmith",
            "type":"Services"
        }
    ],
    "sg:phone":"+1 914 771 6100",
    "sg:postcode":"10016",
    "sg:province":"NY",
    "sg:tags":[
        "key"
    ],
    "wof:name":"Hauptman Home Products",
    "wof:placetype":"venue"
},
  "geometry": {"coordinates":[-73.98582,40.746883],"type":"Point"}
}