{
  "type": "Feature",
  "properties": {
    "iso:country":"US",
    "sg:address":"1235 Western Ave",
    "sg:city":"Albany",
    "sg:classifiers":[
        {
            "category":"Shopping",
            "type":"Retail Goods"
        }
    ],
    "sg:phone":"+1 518 438 1040",
    "sg:postcode":"12203",
    "sg:province":"NY",
    "sg:tags":[
        "pet",
        "food",
        "supply"
    ],
    "sg:website":"www.petsuppliesplus.com",
    "wof:name":"Pet Supplies Plus Inc",
    "wof:placetype":"venue"
},
  "geometry": {"coordinates":[-73.82652899999999,42.67754],"type":"Point"}
}