{
  "type": "Feature",
  "properties": {
    "addr:full":"35 N Dansville St Cohocton NY 14826",
    "addr:housenumber":"35",
    "addr:postcode":"14826",
    "addr:street":"N Dansville St",
    "iso:country":"US",
    "sg:address":"35 N Dansville St",
    "sg:city":"Cohocton",
    "sg:classifiers":[
        {
            "category":"Autos & Motor Vehicles",
            "subcategory":"Automobile Sales",
            "type":"Retail Goods"
        }
    ],
    "sg:phone":"+1   ",
    "sg:postcode":"14826",
    "sg:province":"NY",
    "sg:tags":[
        "repair",
        "used",
        "truck",
        "general"
    ],
    "wof:name":"B & B Enterprises",
    "wof:placetype":"venue"
},
  "geometry": {"coordinates":[-77.507801,42.502923],"type":"Point"}
}