{
  "type": "Feature",
  "properties": {
    "iso:country":"US",
    "sg:address":"20 Medford Ave",
    "sg:city":"Patchogue",
    "sg:classifiers":[
        {
            "category":"Professional",
            "subcategory":"Lawyer & Legal Services",
            "type":"Services"
        }
    ],
    "sg:phone":"+1 631 447 5880",
    "sg:postcode":"11772",
    "sg:province":"NY",
    "sg:tags":[
        "attorney"
    ],
    "wof:name":"Craig Augi",
    "wof:placetype":"venue"
},
  "geometry": {"coordinates":[-73.00717,40.76786],"type":"Point"}
}