{
  "type": "Feature",
  "properties": {
    "addr:full":"3500 Main St Buffalo NY 14226",
    "addr:housenumber":"3500",
    "addr:postcode":"14226",
    "addr:street":"Main St",
    "iso:country":"US",
    "sg:address":"3500 Main St",
    "sg:city":"Buffalo",
    "sg:classifiers":[
        {
            "category":"Shopping",
            "subcategory":"Music",
            "type":"Retail Goods"
        }
    ],
    "sg:phone":"+1 716 837 2090",
    "sg:postcode":"14226",
    "sg:province":"NY",
    "sg:tags":[
        "compact",
        "record",
        "disc",
        "tape",
        "dvd's"
    ],
    "sg:website":"www.amherstrecords.com",
    "wof:name":"Record Theatre",
    "wof:placetype":"venue"
},
  "geometry": {"coordinates":[-78.81759599999999,42.958],"type":"Point"}
}