{
  "type": "Feature",
  "properties": {
    "addr:full":"1446 1st Avenue New York NY 10021",
    "addr:housenumber":"1446",
    "addr:postcode":"10021",
    "addr:street":"1St Avenue",
    "iso:country":"US",
    "sg:address":"1446 1st Avenue",
    "sg:city":"New York",
    "sg:classifiers":[
        {
            "category":"Restaurant",
            "type":"Food & Drink"
        }
    ],
    "sg:phone":"+1 212 772 1734",
    "sg:postcode":"10021",
    "sg:province":"NY",
    "wof:name":"Citibar",
    "wof:placetype":"venue"
},
  "geometry": {"coordinates":[-73.954491,40.769813],"type":"Point"}
}