{
  "type": "Feature",
  "properties": {
    "addr:full":"169 Birch Rd Kings Park NY 11754",
    "addr:housenumber":"169",
    "addr:postcode":"11754",
    "addr:street":"Birch Rd",
    "iso:country":"US",
    "sg:address":"169 Birch Rd",
    "sg:city":"Kings Park",
    "sg:classifiers":[
        {
            "category":"Real Estate",
            "subcategory":"Real Estate Agent",
            "type":"Services"
        }
    ],
    "sg:phone":"+1 631 265 7942",
    "sg:postcode":"11754",
    "sg:province":"NY",
    "wof:name":"Squillacioti Haller Rlty Corp",
    "wof:placetype":"venue"
},
  "geometry": {"coordinates":[-73.22197,40.888625],"type":"Point"}
}