{
  "type": "Feature",
  "properties": {
    "addr:full":"131 Akron St Lindenhurst NY 11757",
    "addr:housenumber":"131",
    "addr:postcode":"11757",
    "addr:street":"Akron St",
    "iso:country":"US",
    "sg:address":"131 Akron St",
    "sg:city":"Lindenhurst",
    "sg:classifiers":[
        {
            "category":"Wholesale",
            "subcategory":"Electrical",
            "type":"Manufacturing & Wholesale Goods"
        }
    ],
    "sg:phone":"+1 631 226 2424",
    "sg:postcode":"11757",
    "sg:province":"NY",
    "sg:tags":[
        "electric",
        "motor"
    ],
    "sg:website":"www.brucelectric.com",
    "wof:name":"Bruce Electric Equipment Corp",
    "wof:placetype":"venue"
},
  "geometry": {"coordinates":[-73.385925,40.684145],"type":"Point"}
}