{
  "type": "Feature",
  "properties": {
    "addr:full":"116 Water St Albany NY 12207",
    "addr:housenumber":"116",
    "addr:postcode":"12207",
    "addr:street":"Water St",
    "iso:country":"US",
    "sg:address":"116 Water St",
    "sg:city":"Albany",
    "sg:classifiers":[
        {
            "category":"Retail",
            "subcategory":"Car Wash",
            "type":"Services"
        }
    ],
    "sg:phone":"+1 518 462 7078",
    "sg:postcode":"12207",
    "sg:province":"NY",
    "sg:tags":[
        "automobile",
        "detail",
        "clean"
    ],
    "wof:name":"Marmatt Auto Detailing Inc",
    "wof:placetype":"venue"
},
  "geometry": {"coordinates":[-73.744647,42.655764],"type":"Point"}
}