{
  "type": "Feature",
  "properties": {
    "addr:full":"6000 W Genesee St Camillus NY 13031",
    "addr:housenumber":"6000",
    "addr:postcode":"13031",
    "addr:street":"W Genesee St",
    "iso:country":"US",
    "sg:address":"6000 W Genesee St",
    "sg:city":"Camillus",
    "sg:classifiers":[
        {
            "category":"Insurance",
            "subcategory":"Insurance Agent",
            "type":"Services"
        }
    ],
    "sg:phone":"+1 315 468 4741",
    "sg:postcode":"13031",
    "sg:province":"NY",
    "sg:website":"www.modern-woodmen.org",
    "wof:name":"Modern Woodmen Of America",
    "wof:placetype":"venue"
},
  "geometry": {"coordinates":[-76.30259599999999,43.03821],"type":"Point"}
}