{
  "type": "Feature",
  "properties": {
    "addr:full":"205 Montague St Brooklyn NY 11201",
    "addr:housenumber":"205",
    "addr:postcode":"11201",
    "addr:street":"Montague St",
    "iso:country":"US",
    "sg:address":"205 Montague St",
    "sg:city":"Brooklyn",
    "sg:classifiers":[
        {
            "category":"Banks & Credit Unions",
            "subcategory":"Bank",
            "type":"Services"
        }
    ],
    "sg:phone":"+1 718 643 9265",
    "sg:postcode":"11201",
    "sg:province":"NY",
    "sg:tags":[
        "national"
    ],
    "wof:name":"Fleet",
    "wof:placetype":"venue"
},
  "geometry": {"coordinates":[-73.99152599999999,40.694203],"type":"Point"}
}