{
  "type": "Feature",
  "properties": {
    "addr:full":"14 N Broadway Tarrytown NY 10591",
    "addr:housenumber":"14",
    "addr:postcode":"10591",
    "addr:street":"N Broadway",
    "iso:country":"US",
    "sg:address":"14 N Broadway",
    "sg:city":"Tarrytown",
    "sg:classifiers":[
        {
            "category":"Education",
            "subcategory":"Junior College",
            "type":"Public Place"
        }
    ],
    "sg:phone":"+1 914 631 4432",
    "sg:postcode":"10591",
    "sg:province":"NY",
    "sg:tags":[
        "technical",
        "institute"
    ],
    "wof:name":"Ny School Of Esthetics Inc",
    "wof:placetype":"venue"
},
  "geometry": {"coordinates":[-73.857653,41.079956],"type":"Point"}
}