{
  "type": "Feature",
  "properties": {
    "iso:country":"US",
    "sg:address":"1 Circle Dr",
    "sg:city":"Valley Stream",
    "sg:classifiers":[
        {
            "category":"Restaurant",
            "type":"Food & Drink"
        }
    ],
    "sg:phone":"+1 516 791 9200",
    "sg:postcode":"11580",
    "sg:province":"NY",
    "wof:name":"Big Apple Buffet",
    "wof:placetype":"venue"
},
  "geometry": {"coordinates":[-73.705101,40.6726],"type":"Point"}
}