{
  "type": "Feature",
  "properties": {
    "addr:full":"5655 S Park Ave Hamburg NY 14075",
    "addr:housenumber":"5655",
    "addr:postcode":"14075",
    "addr:street":"S Park Ave",
    "iso:country":"US",
    "sg:address":"5655 S Park Ave",
    "sg:city":"Hamburg",
    "sg:classifiers":[
        {
            "category":"Shopping",
            "subcategory":"Computers & Home Electronics",
            "type":"Retail Goods"
        }
    ],
    "sg:phone":"+1 716 646 8577",
    "sg:postcode":"14075",
    "sg:province":"NY",
    "sg:tags":[
        "software"
    ],
    "wof:name":"Magneforce Software Systems",
    "wof:placetype":"venue"
},
  "geometry": {"coordinates":[-78.825102,42.743695],"type":"Point"}
}