{
  "type": "Feature",
  "properties": {
    "addr:full":"1788 Penfield Rd Lowr Penfield NY 14526",
    "addr:housenumber":"1788",
    "addr:postcode":"14526",
    "addr:street":"Penfield Rd",
    "iso:country":"US",
    "sg:address":"1788 Penfield Rd Lowr",
    "sg:city":"Penfield",
    "sg:classifiers":[
        {
            "category":"Professional",
            "subcategory":"Detective & Security Services",
            "type":"Services"
        }
    ],
    "sg:phone":"+1 585 586 3056",
    "sg:postcode":"14526",
    "sg:province":"NY",
    "sg:tags":[
        "information",
        "bureau"
    ],
    "wof:name":"Grace Community Services",
    "wof:placetype":"venue"
},
  "geometry": {"coordinates":[-77.479721,43.129002],"type":"Point"}
}