{
  "type": "Feature",
  "properties": {
    "iso:country":"US",
    "sg:address":"111 Livingston Street",
    "sg:city":"Brooklyn",
    "sg:classifiers":[
        {
            "category":"Banks & Credit Unions",
            "subcategory":"Bank",
            "type":"Services"
        }
    ],
    "sg:phone":"+1 718 802 1212",
    "sg:postcode":"11201",
    "sg:province":"NY",
    "wof:name":"Community Capital Bank",
    "wof:placetype":"venue"
},
  "geometry": {"coordinates":[-73.98953899999999,40.691079],"type":"Point"}
}