{
  "type": "Feature",
  "properties": {
    "addr:full":"895 Huguenot Ave Staten Island NY 10312",
    "addr:housenumber":"895",
    "addr:postcode":"10312",
    "addr:street":"Huguenot Ave",
    "iso:country":"US",
    "sg:address":"895 Huguenot Ave",
    "sg:city":"Staten Island",
    "sg:classifiers":[
        {
            "category":"Restaurant",
            "type":"Food & Drink"
        }
    ],
    "sg:menulink":"http://www.allmenus.com/ny/staten-island/54638-john-johns/menu/",
    "sg:phone":"+1 718 356 6800",
    "sg:postcode":"10312",
    "sg:province":"NY",
    "sg:tags":[
        "american",
        "pizza"
    ],
    "wof:name":"John John's",
    "wof:placetype":"venue"
},
  "geometry": {"coordinates":[-74.19255099999999,40.533248],"type":"Point"}
}