{
  "type": "Feature",
  "properties": {
    "addr:full":"2177 Albemarle Road Brooklyn NY 11226",
    "addr:housenumber":"2177",
    "addr:postcode":"11226",
    "addr:street":"Albemarle Road",
    "iso:country":"US",
    "sg:address":"2177 Albemarle Road",
    "sg:city":"Brooklyn",
    "sg:classifiers":[
        {
            "category":"Shopping",
            "subcategory":"Florist",
            "type":"Retail Goods"
        }
    ],
    "sg:phone":"+1 718 940 1002",
    "sg:postcode":"11226",
    "sg:province":"NY",
    "wof:name":"Flowers by A B",
    "wof:placetype":"venue"
},
  "geometry": {"coordinates":[-73.957534,40.647806],"type":"Point"}
}