{
  "type": "Feature",
  "properties": {
    "addr:full":"250 W 57th St Ste 2217 New York NY 10107",
    "addr:housenumber":"250",
    "addr:postcode":"10107",
    "addr:street":"W 57Th St Ste 2217",
    "iso:country":"US",
    "sg:address":"250 W 57th St Ste 2217",
    "sg:city":"New York",
    "sg:classifiers":[
        {
            "category":"Banks & Credit Unions",
            "subcategory":"Investment Brokerage",
            "type":"Services"
        }
    ],
    "sg:phone":"+1 212 888 3200",
    "sg:postcode":"10107",
    "sg:province":"NY",
    "sg:tags":[
        "investing"
    ],
    "wof:name":"Providence Capital Incorporated",
    "wof:placetype":"venue"
},
  "geometry": {"coordinates":[-73.982212,40.766279],"type":"Point"}
}