{
  "type": "Feature",
  "properties": {
    "addr:full":"6 Garden St Great Neck NY 11021",
    "addr:housenumber":"6",
    "addr:postcode":"11021",
    "addr:street":"Garden St",
    "iso:country":"US",
    "sg:address":"6 Garden St",
    "sg:city":"Great Neck",
    "sg:classifiers":[
        {
            "category":"Professional",
            "subcategory":"Lawyer & Legal Services",
            "type":"Services"
        }
    ],
    "sg:phone":"+1 516 829 8800",
    "sg:postcode":"11021",
    "sg:province":"NY",
    "sg:tags":[
        "attorney"
    ],
    "wof:name":"Cary M Hirshon Law Office",
    "wof:placetype":"venue"
},
  "geometry": {"coordinates":[-73.717502,40.78814],"type":"Point"}
}