{
  "type": "Feature",
  "properties": {
    "addr:full":"473 State St Rochester NY 14608",
    "addr:housenumber":"473",
    "addr:postcode":"14608",
    "addr:street":"State St",
    "iso:country":"US",
    "sg:address":"473 State St",
    "sg:city":"Rochester",
    "sg:classifiers":[
        {
            "category":"Retail",
            "subcategory":"Repair Shop",
            "type":"Services"
        }
    ],
    "sg:phone":"+1   ",
    "sg:postcode":"14608",
    "sg:province":"NY",
    "wof:name":"Acme Safe & Lock",
    "wof:placetype":"venue"
},
  "geometry": {"coordinates":[-77.62320699999999,43.164561],"type":"Point"}
}