{
  "type": "Feature",
  "properties": {
    "addr:full":"650 Stewart Ave Garden City NY 11530",
    "addr:housenumber":"650",
    "addr:postcode":"11530",
    "addr:street":"Stewart Ave",
    "iso:country":"US",
    "sg:address":"650 Stewart Ave",
    "sg:city":"Garden City",
    "sg:classifiers":[
        {
            "category":"Shopping",
            "subcategory":"Department Store",
            "type":"Retail Goods"
        }
    ],
    "sg:phone":"+1 516 683 4777",
    "sg:postcode":"11530",
    "sg:province":"NY",
    "sg:website":"www.burlingtoncoatfactory.com",
    "wof:name":"Burlington Coat Factory",
    "wof:placetype":"venue"
},
  "geometry": {"coordinates":[-73.610901,40.7318],"type":"Point"}
}