{
  "type": "Feature",
  "properties": {
    "addr:full":"1019 Montauk Hwy Shirley NY 11967",
    "addr:housenumber":"1019",
    "addr:postcode":"11967",
    "addr:street":"Montauk Hwy",
    "iso:country":"US",
    "sg:address":"1019 Montauk Hwy",
    "sg:city":"Shirley",
    "sg:classifiers":[
        {
            "category":"Home & Garden",
            "subcategory":"Hardware",
            "type":"Retail Goods"
        }
    ],
    "sg:phone":"+1 631 281 7686",
    "sg:postcode":"11967",
    "sg:province":"NY",
    "sg:website":"www.sears.com",
    "wof:name":"Sears Hardware Store",
    "wof:placetype":"venue"
},
  "geometry": {"coordinates":[-72.858268,40.802862],"type":"Point"}
}