{
  "type": "Feature",
  "properties": {
    "iso:country":"US",
    "sg:address":"1500 Route 9D",
    "sg:city":"Wappingers Falls",
    "sg:classifiers":[
        {
            "category":"Bars & Pubs",
            "subcategory":"Nightclub",
            "type":"Food & Drink"
        }
    ],
    "sg:phone":"+1 845 838 0094",
    "sg:postcode":"12590",
    "sg:province":"NY",
    "sg:tags":[
        "nightlife"
    ],
    "wof:name":"Dutchess Stadium",
    "wof:placetype":"venue"
},
  "geometry": {"coordinates":[-73.90922500000001,41.572515],"type":"Point"}
}