{
  "type": "Feature",
  "properties": {
    "addr:full":"600 W 218th St New York NY 10034",
    "addr:housenumber":"600",
    "addr:postcode":"10034",
    "addr:street":"W 218Th St",
    "iso:country":"US",
    "sg:address":"600 W 218th St",
    "sg:city":"New York",
    "sg:classifiers":[
        {
            "category":"Professional",
            "type":"Services"
        }
    ],
    "sg:phone":"+1   ",
    "sg:postcode":"10034",
    "sg:province":"NY",
    "wof:name":"Infamy Inc",
    "wof:placetype":"venue"
},
  "geometry": {"coordinates":[-73.918459,40.873022],"type":"Point"}
}