{
  "type": "Feature",
  "properties": {
    "iso:country":"US",
    "sg:address":"11 Stanton St",
    "sg:city":"New York",
    "sg:classifiers":[
        {
            "category":"Professional",
            "subcategory":"Business Services",
            "type":"Services"
        }
    ],
    "sg:phone":"+1 917 523 7527",
    "sg:postcode":"10002",
    "sg:province":"NY",
    "sg:tags":[
        "recording",
        "studio"
    ],
    "wof:name":"Applerock Studios",
    "wof:placetype":"venue"
},
  "geometry": {"coordinates":[-73.992221,40.72254],"type":"Point"}
}