{
  "type": "Feature",
  "properties": {
    "iso:country":"US",
    "sg:address":"1992 Deer Park Ave",
    "sg:city":"Deer Park",
    "sg:classifiers":[
        {
            "category":"Health Services",
            "subcategory":"Doctor",
            "type":"Services"
        }
    ],
    "sg:phone":"+1 631 667 0004",
    "sg:postcode":"11729",
    "sg:province":"NY",
    "sg:tags":[
        "dentist"
    ],
    "wof:name":"Kenneth A Paticoff DDS",
    "wof:placetype":"venue"
},
  "geometry": {"coordinates":[-73.33148799999999,40.766926],"type":"Point"}
}