{
  "type": "Feature",
  "properties": {
    "addr:full":"6 Hooker Ave Poughkeepsie NY 12601",
    "addr:housenumber":"6",
    "addr:postcode":"12601",
    "addr:street":"Hooker Ave",
    "iso:country":"US",
    "sg:address":"6 Hooker Ave",
    "sg:city":"Poughkeepsie",
    "sg:classifiers":[
        {
            "category":"Restaurant",
            "type":"Food & Drink"
        }
    ],
    "sg:phone":"+1 845 485 9886",
    "sg:postcode":"12601",
    "sg:province":"NY",
    "sg:tags":[
        "out"
    ],
    "wof:name":"Sam's Food Mart Inc",
    "wof:placetype":"venue"
},
  "geometry": {"coordinates":[-73.92403400000001,41.697743],"type":"Point"}
}