{
  "type": "Feature",
  "properties": {
    "addr:full":"3023 3rd Ave Bronx NY 10455",
    "addr:housenumber":"3023",
    "addr:postcode":"10455",
    "addr:street":"3Rd Ave",
    "iso:country":"US",
    "sg:address":"3023 3rd Ave",
    "sg:city":"Bronx",
    "sg:classifiers":[
        {
            "category":"Shopping",
            "type":"Retail Goods"
        }
    ],
    "sg:phone":"+1   ",
    "sg:postcode":"10455",
    "sg:province":"NY",
    "sg:tags":[
        "merchandise"
    ],
    "wof:name":"Petmaster 2 I N C",
    "wof:placetype":"venue"
},
  "geometry": {"coordinates":[-73.913157,40.820122],"type":"Point"}
}