{
  "type": "Feature",
  "properties": {
    "addr:full":"225 Erie St E Blauvelt NY 10913",
    "addr:housenumber":"225",
    "addr:postcode":"10913",
    "addr:street":"Erie St",
    "iso:country":"US",
    "sg:address":"225 Erie St E",
    "sg:city":"Blauvelt",
    "sg:classifiers":[
        {
            "category":"Building & Trades",
            "subcategory":"Plumbing",
            "type":"Services"
        }
    ],
    "sg:phone":"+1 845 359 6157",
    "sg:postcode":"10913",
    "sg:province":"NY",
    "sg:tags":[
        "conditioning",
        "air",
        "system",
        "contractor"
    ],
    "wof:name":"Arctic Air Heating & Cooling",
    "wof:placetype":"venue"
},
  "geometry": {"coordinates":[-73.94770200000001,41.063769],"type":"Point"}
}