{
  "type": "Feature",
  "properties": {
    "addr:full":"4403 Austin Blvd Island Park NY 11558",
    "addr:housenumber":"4403",
    "addr:postcode":"11558",
    "addr:street":"Austin Blvd;Park",
    "iso:country":"US",
    "sg:address":"4403 Austin Blvd",
    "sg:city":"Island Park",
    "sg:classifiers":[
        {
            "category":"Shopping",
            "subcategory":"Antiques",
            "type":"Retail Goods"
        }
    ],
    "sg:phone":"+1 516 992 0981",
    "sg:postcode":"11558",
    "sg:province":"NY",
    "wof:name":"Kotler Galleries & a",
    "wof:placetype":"venue"
},
  "geometry": {"coordinates":[-73.652418,40.601971],"type":"Point"}
}