{
  "type": "Feature",
  "properties": {
    "iso:country":"US",
    "sg:address":"7112 13th Ave",
    "sg:city":"Brooklyn",
    "sg:classifiers":[
        {
            "category":"Restaurant",
            "type":"Food & Drink"
        }
    ],
    "sg:menulink":"http://www.allmenus.com/ny/brooklyn/51615-krispy-pizza/menu/",
    "sg:phone":"+1 718 745 9618",
    "sg:postcode":"11228",
    "sg:province":"NY",
    "sg:tags":[
        "american",
        "pizza"
    ],
    "wof:name":"Krispy Pizza",
    "wof:placetype":"venue"
},
  "geometry": {"coordinates":[-74.005218,40.622366],"type":"Point"}
}