{
  "type": "Feature",
  "properties": {
    "iso:country":"US",
    "sg:address":"99 Aberfoyle Rd",
    "sg:city":"New Rochelle",
    "sg:classifiers":[
        {
            "category":"Wholesale",
            "subcategory":"Stationery",
            "type":"Manufacturing & Wholesale Goods"
        }
    ],
    "sg:phone":"+1 914 637 0036",
    "sg:postcode":"10804",
    "sg:province":"NY",
    "sg:tags":[
        "supply"
    ],
    "wof:name":"Forms In Space Inc",
    "wof:placetype":"venue"
},
  "geometry": {"coordinates":[-73.79302199999999,40.934795],"type":"Point"}
}