{
  "type": "Feature",
  "properties": {
    "iso:country":"US",
    "sg:address":"493 Franklin St",
    "sg:city":"Buffalo",
    "sg:classifiers":[
        {
            "category":"Real Estate",
            "subcategory":"Real Estate Agent",
            "type":"Services"
        }
    ],
    "sg:phone":"+1 716 881 2400",
    "sg:postcode":"14202",
    "sg:province":"NY",
    "wof:name":"Prestige Properties-West Ny",
    "wof:placetype":"venue"
},
  "geometry": {"coordinates":[-78.871622,42.901182],"type":"Point"}
}