{
  "type": "Feature",
  "properties": {
    "iso:country":"US",
    "sg:address":"140 E 29th St",
    "sg:city":"New York",
    "sg:classifiers":[
        {
            "category":"Wholesale",
            "subcategory":"Chemicals & Plastics",
            "type":"Manufacturing & Wholesale Goods"
        }
    ],
    "sg:phone":"+1 212 545 9470",
    "sg:postcode":"10016",
    "sg:province":"NY",
    "wof:name":"Mjr Chemical Corp",
    "wof:placetype":"venue"
},
  "geometry": {"coordinates":[-73.980592,40.742604],"type":"Point"}
}