{
  "type": "Feature",
  "properties": {
    "addr:full":"521 E Pine St Olean NY 14760",
    "addr:housenumber":"521",
    "addr:postcode":"14760",
    "addr:street":"E Pine St",
    "iso:country":"US",
    "sg:address":"521 E Pine St",
    "sg:city":"Olean",
    "sg:classifiers":[
        {
            "category":"Building & Trades",
            "subcategory":"Electrical",
            "type":"Services"
        }
    ],
    "sg:phone":"+1 716 372 6972",
    "sg:postcode":"14760",
    "sg:province":"NY",
    "sg:tags":[
        "electric",
        "contractor"
    ],
    "wof:name":"Ellman Electric",
    "wof:placetype":"venue"
},
  "geometry": {"coordinates":[-78.432914,42.096784],"type":"Point"}
}