{
  "type": "Feature",
  "properties": {
    "addr:full":"1776 2nd Ave New York NY 10128",
    "addr:housenumber":"1776",
    "addr:postcode":"10128",
    "addr:street":"2Nd Ave",
    "iso:country":"US",
    "sg:address":"1776 2nd Ave",
    "sg:city":"New York",
    "sg:classifiers":[
        {
            "category":"Restaurant",
            "type":"Food & Drink"
        }
    ],
    "sg:menulink":"http://www.allmenus.com/ny/new-york/53230-subway/menu/",
    "sg:phone":"+1 212 600 0949",
    "sg:postcode":"10128",
    "sg:province":"NY",
    "sg:tags":[
        "american",
        "sandwich"
    ],
    "wof:name":"Subway",
    "wof:placetype":"venue"
},
  "geometry": {"coordinates":[-73.948341,40.781959],"type":"Point"}
}