{
  "type": "Feature",
  "properties": {
    "addr:full":"400 E Sandford Blvd Mount Vernon NY 10550",
    "addr:housenumber":"400",
    "addr:postcode":"10550",
    "addr:street":"E Sandford Blvd",
    "iso:country":"US",
    "sg:address":"400 E Sandford Blvd",
    "sg:city":"Mount Vernon",
    "sg:classifiers":[
        {
            "category":"Restaurant",
            "type":"Food & Drink"
        }
    ],
    "sg:phone":"+1 914 664 8988",
    "sg:postcode":"10550",
    "sg:province":"NY",
    "sg:tags":[
        "eating"
    ],
    "wof:name":"Great Wall Chinese Restaurant",
    "wof:placetype":"venue"
},
  "geometry": {"coordinates":[-73.819988,40.901548],"type":"Point"}
}