{
  "type": "Feature",
  "properties": {
    "iso:country":"US",
    "sg:address":"2465 Broadway",
    "sg:city":"New York",
    "sg:classifiers":[
        {
            "category":"Food & Beverages",
            "subcategory":"Groceries & Convenience Stores",
            "type":"Retail Goods"
        }
    ],
    "sg:phone":"+1 212 874 8204",
    "sg:postcode":"10025",
    "sg:province":"NY",
    "sg:tags":[
        "grocer"
    ],
    "wof:name":"Key Food Supermarket",
    "wof:placetype":"venue"
},
  "geometry": {"coordinates":[-73.973755,40.792066],"type":"Point"}
}