{
  "type": "Feature",
  "properties": {
    "iso:country":"US",
    "sg:address":"47 Pitt St",
    "sg:city":"New York",
    "sg:classifiers":[
        {
            "category":"Food & Beverages",
            "subcategory":"Groceries & Convenience Stores",
            "type":"Retail Goods"
        }
    ],
    "sg:phone":"+1 212 533 4785",
    "sg:postcode":"10002",
    "sg:province":"NY",
    "wof:name":"Ramon A Reyes",
    "wof:placetype":"venue"
},
  "geometry": {"coordinates":[-73.98339799999999,40.716499],"type":"Point"}
}