{
  "type": "Feature",
  "properties": {
    "addr:full":"193 Hollybrook Rd Brockport NY 14420",
    "addr:housenumber":"193",
    "addr:postcode":"14420",
    "addr:street":"Hollybrook Rd",
    "iso:country":"US",
    "sg:address":"193 Hollybrook Rd",
    "sg:city":"Brockport",
    "sg:classifiers":[
        {
            "category":"Building & Trades",
            "subcategory":"Construction",
            "type":"Services"
        }
    ],
    "sg:phone":"+1 585 395 9333",
    "sg:postcode":"14420",
    "sg:province":"NY",
    "sg:tags":[
        "house"
    ],
    "wof:name":"Lomonaco Construction",
    "wof:placetype":"venue"
},
  "geometry": {"coordinates":[-77.932672,43.205044],"type":"Point"}
}