{
  "type": "Feature",
  "properties": {
    "iso:country":"US",
    "sg:address":"8 Lake Ave",
    "sg:city":"Tuckahoe",
    "sg:classifiers":[
        {
            "category":"Building & Trades",
            "subcategory":"Plumbing",
            "type":"Services"
        }
    ],
    "sg:phone":"+1 914 771 8187",
    "sg:postcode":"10707",
    "sg:province":"NY",
    "sg:tags":[
        "contractor"
    ],
    "wof:name":"BC Plumbing & Heating Inc",
    "wof:placetype":"venue"
},
  "geometry": {"coordinates":[-73.831323,40.948876],"type":"Point"}
}