{
  "type": "Feature",
  "properties": {
    "addr:full":"307 Vanderbilt St Brooklyn NY 11218",
    "addr:housenumber":"307",
    "addr:postcode":"11218",
    "addr:street":"Vanderbilt St",
    "iso:country":"US",
    "sg:address":"307 Vanderbilt St",
    "sg:city":"Brooklyn",
    "sg:classifiers":[
        {
            "category":"Restaurant",
            "type":"Food & Drink"
        }
    ],
    "sg:phone":"+1 718 851 4616",
    "sg:postcode":"11218",
    "sg:province":"NY",
    "sg:tags":[
        "delicatessen"
    ],
    "wof:name":"JPN Vanderbilt Delicatessan",
    "wof:placetype":"venue"
},
  "geometry": {"coordinates":[-73.978381,40.652728],"type":"Point"}
}