{
  "type": "Feature",
  "properties": {
    "iso:country":"US",
    "sg:address":"46 Albion Cross Rd",
    "sg:city":"Parish",
    "sg:classifiers":[
        {
            "category":"Shopping",
            "subcategory":"Bicycles & Sporting Goods",
            "type":"Retail Goods"
        }
    ],
    "sg:phone":"+1 315 298 6176",
    "sg:postcode":"13131",
    "sg:province":"NY",
    "sg:tags":[
        "apparel",
        "bowling",
        "accessory"
    ],
    "wof:name":"General Sales & Svc",
    "wof:placetype":"venue"
},
  "geometry": {"coordinates":[-76.08126,43.461878],"type":"Point"}
}