{
  "type": "Feature",
  "properties": {
    "addr:full":"314 Hoosick St Troy NY 12180",
    "addr:housenumber":"314",
    "addr:postcode":"12180",
    "addr:street":"Hoosick St",
    "iso:country":"US",
    "sg:address":"314 Hoosick St",
    "sg:city":"Troy",
    "sg:classifiers":[
        {
            "category":"Professional",
            "subcategory":"Lawyer & Legal Services",
            "type":"Services"
        }
    ],
    "sg:phone":"+1 518 271 9664",
    "sg:postcode":"12180",
    "sg:province":"NY",
    "sg:tags":[
        "attorney",
        "plan"
    ],
    "wof:name":"Stanton D King",
    "wof:placetype":"venue"
},
  "geometry": {"coordinates":[-73.666267,42.737741],"type":"Point"}
}