{
  "type": "Feature",
  "properties": {
    "addr:full":"1602 Bronxdale Ave Bronx NY 10462",
    "addr:housenumber":"1602",
    "addr:postcode":"10462",
    "addr:street":"Bronxdale Ave",
    "iso:country":"US",
    "sg:address":"1602 Bronxdale Ave",
    "sg:city":"Bronx",
    "sg:classifiers":[
        {
            "category":"Autos & Motor Vehicles",
            "subcategory":"Fuel & Gas Station",
            "type":"Retail Goods"
        },
        {
            "category":"Autos & Motor Vehicles",
            "subcategory":"Auto Supplies",
            "type":"Retail Goods"
        },
        {
            "category":"Retail",
            "subcategory":"Repair Shop",
            "type":"Services"
        },
        {
            "category":"Building & Trades",
            "subcategory":"Plumbing",
            "type":"Services"
        },
        {
            "category":"Retail",
            "subcategory":"Auto Repair",
            "type":"Services"
        }
    ],
    "sg:phone":"+1 347 949 8966",
    "sg:postcode":"10462",
    "sg:province":"NY",
    "sg:tags":[
        "radiators-repairing",
        "alternator",
        "classic",
        "generators-automotive",
        "brake",
        "restoration-antique",
        "automobile",
        "lube",
        "equipment-service",
        "repair-automobile",
        "wheel",
        "rebuilding",
        "oil",
        "electric",
        "radiator",
        "exchange",
        "automotive",
        "emission",
        "diagnostic",
        "servicing-automotive",
        "axle",
        "alignment-frame",
        "injection",
        "air conditioning",
        "tune",
        "repairing",
        "installation",
        "transmission",
        "clutch",
        "sale",
        "engine",
        "truck",
        "customizing",
        "referral"
    ],
    "sg:website":"http://www.yext.com/p/superpages/jerry-son-auto-service-bronx-new-york.html",
    "wof:name":"Jerry & Son Auto Service",
    "wof:placetype":"venue"
},
  "geometry": {"coordinates":[-73.857018,40.84359],"type":"Point"}
}