{
  "type": "Feature",
  "properties": {
    "addr:full":"26 Dorothy Dix Dr Middletown NY 10940",
    "addr:housenumber":"26",
    "addr:postcode":"10940",
    "addr:street":"Dorothy Dix Dr",
    "iso:country":"US",
    "sg:address":"26 Dorothy Dix Dr",
    "sg:city":"Middletown",
    "sg:classifiers":[
        {
            "category":"Banks & Credit Unions",
            "subcategory":"Bank",
            "type":"Services"
        }
    ],
    "sg:phone":"+1 845 561 3941",
    "sg:postcode":"10940",
    "sg:province":"NY",
    "sg:tags":[
        "federal"
    ],
    "wof:name":"Hudson Heritage Federal Credit",
    "wof:placetype":"venue"
},
  "geometry": {"coordinates":[-74.439424,41.448882],"type":"Point"}
}