{
  "type": "Feature",
  "properties": {
    "addr:full":"33 Grand St Kingston NY 12401",
    "addr:housenumber":"33",
    "addr:postcode":"12401",
    "addr:street":"Grand St",
    "iso:country":"US",
    "sg:address":"33 Grand St",
    "sg:city":"Kingston",
    "sg:classifiers":[
        {
            "category":"Health Services",
            "subcategory":"Medical Lab",
            "type":"Services"
        }
    ],
    "sg:phone":"+1 845 331 6400",
    "sg:postcode":"12401",
    "sg:province":"NY",
    "sg:tags":[
        "laboratory"
    ],
    "wof:name":"Kingston Universal Community",
    "wof:placetype":"venue"
},
  "geometry": {"coordinates":[-73.99960400000001,41.928642],"type":"Point"}
}