{
  "type": "Feature",
  "properties": {
    "addr:full":"124 97th St Brooklyn NY 11209",
    "addr:housenumber":"124",
    "addr:postcode":"11209",
    "addr:street":"97Th St",
    "iso:country":"US",
    "sg:address":"124 97th St",
    "sg:city":"Brooklyn",
    "sg:classifiers":[
        {
            "category":"Professional",
            "subcategory":"Business Services",
            "type":"Services"
        }
    ],
    "sg:phone":"+1 718 491 3590",
    "sg:postcode":"11209",
    "sg:province":"NY",
    "sg:tags":[
        "appraiser"
    ],
    "wof:name":"Trust Appraisals",
    "wof:placetype":"venue"
},
  "geometry": {"coordinates":[-74.035696,40.61575],"type":"Point"}
}