{
  "type": "Feature",
  "properties": {
    "addr:full":"90 Walnut Ln Manhasset NY 11030",
    "addr:housenumber":"90",
    "addr:postcode":"11030",
    "addr:street":"Walnut Ln",
    "iso:country":"US",
    "sg:address":"90 Walnut Ln",
    "sg:city":"Manhasset",
    "sg:classifiers":[
        {
            "category":"Health Services",
            "subcategory":"Doctor",
            "type":"Services"
        }
    ],
    "sg:phone":"+1 516 627 5714",
    "sg:postcode":"11030",
    "sg:province":"NY",
    "wof:name":"Vallarino Ramon MD PC",
    "wof:placetype":"venue"
},
  "geometry": {"coordinates":[-73.67600299999999,40.805199],"type":"Point"}
}