{
  "type": "Feature",
  "properties": {
    "iso:country":"US",
    "sg:address":"1800 Old Walt Whitman Rd",
    "sg:city":"Melville",
    "sg:classifiers":[
        {
            "category":"Professional",
            "type":"Services"
        }
    ],
    "sg:phone":"+1 631 249 2485",
    "sg:postcode":"11747",
    "sg:province":"NY",
    "sg:tags":[
        "establishment"
    ],
    "wof:name":"CFM",
    "wof:placetype":"venue"
},
  "geometry": {"coordinates":[-73.42788,40.770357],"type":"Point"}
}