{
  "type": "Feature",
  "properties": {
    "addr:full":"114 Nagle Ave New York NY 10040",
    "addr:housenumber":"114",
    "addr:postcode":"10040",
    "addr:street":"Nagle Ave",
    "iso:country":"US",
    "sg:address":"114 Nagle Ave",
    "sg:city":"New York",
    "sg:classifiers":[
        {
            "category":"Retail",
            "subcategory":"Photofinishing",
            "type":"Services"
        }
    ],
    "sg:phone":"+1   ",
    "sg:postcode":"10040",
    "sg:province":"NY",
    "sg:tags":[
        "laboratory"
    ],
    "wof:name":"Imagenes Photo Lab Inc",
    "wof:placetype":"venue"
},
  "geometry": {"coordinates":[-73.926919,40.860832],"type":"Point"}
}