{
  "type": "Feature",
  "properties": {
    "addr:full":"27 Bluff Point Rd Northport NY 11768",
    "addr:housenumber":"27",
    "addr:postcode":"11768",
    "addr:street":"Bluff Point Rd",
    "iso:country":"US",
    "sg:address":"27 Bluff Point Rd",
    "sg:city":"Northport",
    "sg:classifiers":[
        {
            "category":"Retail",
            "subcategory":"Car Wash",
            "type":"Services"
        }
    ],
    "sg:phone":"+1   ",
    "sg:postcode":"11768",
    "sg:province":"NY",
    "sg:tags":[
        "carwash"
    ],
    "wof:name":"Classque Car Wash of Northport",
    "wof:placetype":"venue"
},
  "geometry": {"coordinates":[-73.35618599999999,40.909591],"type":"Point"}
}