{
  "type": "Feature",
  "properties": {
    "addr:full":"1432 Montauk Hwy Patchogue NY 11772",
    "addr:housenumber":"1432",
    "addr:postcode":"11772",
    "addr:street":"Montauk Hwy",
    "iso:country":"US",
    "sg:address":"1432 Montauk Hwy",
    "sg:city":"Patchogue",
    "sg:classifiers":[
        {
            "category":"Real Estate",
            "subcategory":"Real Estate Agent",
            "type":"Services"
        }
    ],
    "sg:phone":"+1 631 286 2200",
    "sg:postcode":"11772",
    "sg:province":"NY",
    "wof:name":"Mark Neuman",
    "wof:placetype":"venue"
},
  "geometry": {"coordinates":[-72.957621,40.771548],"type":"Point"}
}