{
  "type": "Feature",
  "properties": {
    "addr:full":"64 Fulton St 2nd Fl Corner of Gold St New York NY 10038",
    "addr:housenumber":"64",
    "addr:postcode":"10038",
    "addr:street":"Fulton St;Corner Of Gold St",
    "iso:country":"US",
    "sg:address":"64 Fulton St 2nd Fl Corner of Gold St",
    "sg:city":"New York",
    "sg:classifiers":[
        {
            "category":"Shopping",
            "subcategory":"Comic Books",
            "type":"Retail Goods"
        }
    ],
    "sg:phone":"+1 212 302 8192",
    "sg:postcode":"10038",
    "sg:province":"NY",
    "sg:website":"www.midtowncomics.com/",
    "wof:name":"Midtown Comics Downtown",
    "wof:placetype":"venue"
},
  "geometry": {"coordinates":[-74.00536099999999,40.708721],"type":"Point"}
}