{
  "type": "Feature",
  "properties": {
    "iso:country":"US",
    "sg:address":"34 Pryer Manor Rd",
    "sg:city":"Larchmont",
    "sg:classifiers":[
        {
            "category":"Health Services",
            "subcategory":"Doctor",
            "type":"Services"
        }
    ],
    "sg:phone":"+1 914 576 1166",
    "sg:postcode":"10538",
    "sg:province":"NY",
    "sg:tags":[
        "physician",
        "surgeon"
    ],
    "wof:name":"Arthur E Gillman MD",
    "wof:placetype":"venue"
},
  "geometry": {"coordinates":[-73.76104599999999,40.919892],"type":"Point"}
}