{
  "type": "Feature",
  "properties": {
    "addr:full":"50 Charles Lindbergh Blvd Uniondale NY 11553",
    "addr:housenumber":"50",
    "addr:postcode":"11553",
    "addr:street":"Charles Lindbergh Blvd",
    "iso:country":"US",
    "sg:address":"50 Charles Lindbergh Blvd",
    "sg:city":"Uniondale",
    "sg:classifiers":[
        {
            "category":"Professional",
            "subcategory":"Computer Services",
            "type":"Services"
        }
    ],
    "sg:phone":"+1 516 390 4627",
    "sg:postcode":"11553",
    "sg:province":"NY",
    "sg:tags":[
        "repair"
    ],
    "sg:website":"www.onsglobal.com",
    "wof:name":"Omega Network Systems",
    "wof:placetype":"venue"
},
  "geometry": {"coordinates":[-73.604641,40.726002],"type":"Point"}
}