{
  "type": "Feature",
  "properties": {
    "iso:country":"US",
    "sg:address":"200 W Main St",
    "sg:city":"Patchogue",
    "sg:classifiers":[
        {
            "category":"Wholesale",
            "subcategory":"Home Furnishings",
            "type":"Manufacturing & Wholesale Goods"
        }
    ],
    "sg:phone":"+1 631 758 3089",
    "sg:postcode":"11772",
    "sg:province":"NY",
    "wof:name":"Linken Carpet",
    "wof:placetype":"venue"
},
  "geometry": {"coordinates":[-73.01985500000001,40.765955],"type":"Point"}
}