{
  "type": "Feature",
  "properties": {
    "addr:full":"30 Saint Andrews Ct Glen Cove NY 11568",
    "addr:housenumber":"30",
    "addr:postcode":"11568",
    "addr:street":"Saint Andrews Ct",
    "iso:country":"US",
    "sg:address":"30 Saint Andrews Ct",
    "sg:city":"Glen Cove",
    "sg:classifiers":[
        {
            "category":"Shopping",
            "subcategory":"Bicycles & Sporting Goods",
            "type":"Retail Goods"
        }
    ],
    "sg:phone":"+1   ",
    "sg:postcode":"11568",
    "sg:province":"NY",
    "wof:name":"Andrew Pohalski Pro Shop",
    "wof:placetype":"venue"
},
  "geometry": {"coordinates":[-73.581692,40.7775],"type":"Point"}
}