{
  "type": "Feature",
  "properties": {
    "iso:country":"US",
    "sg:address":"98 Jackson Ave",
    "sg:city":"Syosset",
    "sg:classifiers":[
        {
            "category":"Restaurant",
            "type":"Food & Drink"
        }
    ],
    "sg:phone":"+1 516 364 1769",
    "sg:postcode":"11791",
    "sg:province":"NY",
    "wof:name":"Sweet Water",
    "wof:placetype":"venue"
},
  "geometry": {"coordinates":[-73.502363,40.823502],"type":"Point"}
}