{
  "type": "Feature",
  "properties": {
    "addr:full":"3770 Carman Rd Schenectady NY 12303",
    "addr:housenumber":"3770",
    "addr:postcode":"12303",
    "addr:street":"Carman Rd",
    "iso:country":"US",
    "sg:address":"3770 Carman Rd",
    "sg:city":"Schenectady",
    "sg:classifiers":[
        {
            "category":"Restaurant",
            "type":"Food & Drink"
        }
    ],
    "sg:menulink":"http://www.allmenus.com/ny/guilderland/61366-peking-house/menu/",
    "sg:phone":"+1 518 355 1688",
    "sg:postcode":"12303",
    "sg:province":"NY",
    "sg:tags":[
        "asian",
        "chinese"
    ],
    "wof:name":"Peking House",
    "wof:placetype":"venue"
},
  "geometry": {"coordinates":[-73.937112,42.725465],"type":"Point"}
}