{
  "type": "Feature",
  "properties": {
    "iso:country":"US",
    "sg:address":"12 Old Albany Post Rd",
    "sg:city":"Garrison",
    "sg:classifiers":[
        {
            "category":"Building & Trades",
            "subcategory":"Construction",
            "type":"Services"
        }
    ],
    "sg:phone":"+1 914 646 4658",
    "sg:postcode":"10524",
    "sg:province":"NY",
    "sg:tags":[
        "excavation",
        "contractor"
    ],
    "wof:name":"Removal Corp",
    "wof:placetype":"venue"
},
  "geometry": {"coordinates":[-73.90411,41.341308],"type":"Point"}
}