{
  "type": "Feature",
  "properties": {
    "addr:full":"301 E 57th St New York NY 10022",
    "addr:housenumber":"301",
    "addr:postcode":"10022",
    "addr:street":"E 57Th St",
    "iso:country":"US",
    "sg:address":"301 E 57th St",
    "sg:city":"New York",
    "sg:classifiers":[
        {
            "category":"Retail",
            "subcategory":"Auto Repair",
            "type":"Services"
        }
    ],
    "sg:phone":"+1 646 237 1128",
    "sg:postcode":"10022",
    "sg:province":"NY",
    "sg:tags":[
        "wrecker"
    ],
    "wof:name":"ABCA Tow 24 Hr",
    "wof:placetype":"venue"
},
  "geometry": {"coordinates":[-73.96450299999999,40.758973],"type":"Point"}
}