{
  "type": "Feature",
  "properties": {
    "addr:full":"129 E 80th St New York NY 10021",
    "addr:housenumber":"129",
    "addr:postcode":"10021",
    "addr:street":"E 80Th St",
    "iso:country":"US",
    "sg:address":"129 E 80th St",
    "sg:city":"New York",
    "sg:classifiers":[
        {
            "category":"Personal",
            "subcategory":"Skin Care",
            "type":"Services"
        }
    ],
    "sg:phone":"+1 212 794 2961",
    "sg:postcode":"10021",
    "sg:province":"NY",
    "wof:name":"Facial Dynamics",
    "wof:placetype":"venue"
},
  "geometry": {"coordinates":[-73.959,40.775902],"type":"Point"}
}