{
  "type": "Feature",
  "properties": {
    "iso:country":"US",
    "sg:address":"279 W 117th Street Apt 3G",
    "sg:city":"New York",
    "sg:classifiers":[
        {
            "category":"Professional",
            "subcategory":"Lawyer & Legal Services",
            "type":"Services"
        }
    ],
    "sg:phone":"+1 212 865 7978",
    "sg:postcode":"10026",
    "sg:province":"NY",
    "wof:name":"Colombus Law Group",
    "wof:placetype":"venue"
},
  "geometry": {"coordinates":[-73.95409100000001,40.80477],"type":"Point"}
}