{
  "type": "Feature",
  "properties": {
    "addr:full":"773 Burke Ave Bronx NY 10467",
    "addr:housenumber":"773",
    "addr:postcode":"10467",
    "addr:street":"Burke Ave",
    "iso:country":"US",
    "sg:address":"773 Burke Ave",
    "sg:city":"Bronx",
    "sg:classifiers":[
        {
            "category":"Utilities",
            "subcategory":"Cable",
            "type":"Services"
        }
    ],
    "sg:phone":"+1 718 231 1047",
    "sg:postcode":"10467",
    "sg:province":"NY",
    "sg:tags":[
        "television"
    ],
    "wof:name":"Top Quality Communications",
    "wof:placetype":"venue"
},
  "geometry": {"coordinates":[-73.863381,40.871451],"type":"Point"}
}