{
  "type": "Feature",
  "properties": {
    "addr:full":"1365 Culver Rd Rochester NY 14609",
    "addr:housenumber":"1365",
    "addr:postcode":"14609",
    "addr:street":"Culver Rd",
    "iso:country":"US",
    "sg:address":"1365 Culver Rd",
    "sg:city":"Rochester",
    "sg:classifiers":[
        {
            "category":"Personal",
            "subcategory":"Beauty Salon",
            "type":"Services"
        }
    ],
    "sg:phone":"+1 585 654 8700",
    "sg:postcode":"14609",
    "sg:province":"NY",
    "sg:tags":[
        "shop",
        "equipment",
        "establishment"
    ],
    "wof:name":"Donald's Beauty & Wig Salon",
    "wof:placetype":"venue"
},
  "geometry": {"coordinates":[-77.560543,43.170346],"type":"Point"}
}