{
  "type": "Feature",
  "properties": {
    "addr:full":"345 Kear St Yorktown Heights NY 10598",
    "addr:housenumber":"345",
    "addr:postcode":"10598",
    "addr:street":"Kear St",
    "iso:country":"US",
    "sg:address":"345 Kear St",
    "sg:city":"Yorktown Heights",
    "sg:classifiers":[
        {
            "category":"Health Services",
            "subcategory":"Health Practitioner",
            "type":"Services"
        }
    ],
    "sg:phone":"+1 914 962 2002",
    "sg:postcode":"10598",
    "sg:province":"NY",
    "sg:tags":[
        "psychologist"
    ],
    "wof:name":"Northern Westchester Ctr",
    "wof:placetype":"venue"
},
  "geometry": {"coordinates":[-73.781312,41.270763],"type":"Point"}
}