{
  "type": "Feature",
  "properties": {
    "addr:full":"1045 Grant Ave Bronx NY 10456",
    "addr:housenumber":"1045",
    "addr:postcode":"10456",
    "addr:street":"Grant Ave",
    "iso:country":"US",
    "sg:address":"1045 Grant Ave",
    "sg:city":"Bronx",
    "sg:classifiers":[
        {
            "category":"Food & Beverages",
            "subcategory":"Groceries & Convenience Stores",
            "type":"Retail Goods"
        }
    ],
    "sg:phone":"+1 718 410 7654",
    "sg:postcode":"10456",
    "sg:province":"NY",
    "sg:tags":[
        "grocer"
    ],
    "wof:name":"Aleman Grocery",
    "wof:placetype":"venue"
},
  "geometry": {"coordinates":[-73.916697,40.830785],"type":"Point"}
}