{
  "type": "Feature",
  "properties": {
    "iso:country":"US",
    "sg:address":"515 W 36 St",
    "sg:city":"New York",
    "sg:classifiers":[
        {
            "category":"Building & Trades",
            "subcategory":"Construction",
            "type":"Services"
        }
    ],
    "sg:phone":"+1 212 695 1252",
    "sg:postcode":"10018",
    "sg:province":"NY",
    "sg:tags":[
        "acoustical",
        "contractor"
    ],
    "wof:name":"National Acoustics Inc",
    "wof:placetype":"venue"
},
  "geometry": {"coordinates":[-74.00105499999999,40.757067],"type":"Point"}
}