{
  "type": "Feature",
  "properties": {
    "addr:full":"12 W 11 St New York NY 10011",
    "addr:housenumber":"12",
    "addr:postcode":"10011",
    "addr:street":"W 11 St",
    "iso:country":"US",
    "sg:address":"12 W 11 St",
    "sg:city":"New York",
    "sg:classifiers":[
        {
            "category":"Organizations",
            "subcategory":"Professional Association",
            "type":"Services"
        }
    ],
    "sg:phone":"+1 212 260 5580",
    "sg:postcode":"10011",
    "sg:province":"NY",
    "wof:name":"Annie Tinker Assn For Women",
    "wof:placetype":"venue"
},
  "geometry": {"coordinates":[-73.99805600000001,40.735184],"type":"Point"}
}