{
  "type": "Feature",
  "properties": {
    "iso:country":"US",
    "sg:address":"1011 Fort Salonga Rd",
    "sg:city":"Northport",
    "sg:classifiers":[
        {
            "category":"Autos & Motor Vehicles",
            "subcategory":"Fuel & Gas Station",
            "type":"Retail Goods"
        },
        {
            "category":"Retail",
            "subcategory":"Auto Repair",
            "type":"Services"
        }
    ],
    "sg:phone":"+1 631 757 9863",
    "sg:postcode":"11768",
    "sg:province":"NY",
    "sg:tags":[
        "oil",
        "general"
    ],
    "wof:name":"Salonga Service Ltd",
    "wof:placetype":"venue"
},
  "geometry": {"coordinates":[-73.317848,40.905775],"type":"Point"}
}