{
  "type": "Feature",
  "properties": {
    "iso:country":"US",
    "sg:address":"40 Nassau Ave",
    "sg:city":"Islip",
    "sg:classifiers":[
        {
            "category":"Real Estate",
            "subcategory":"Real Estate Agent",
            "type":"Services"
        }
    ],
    "sg:phone":"+1 718 648 6800",
    "sg:postcode":"11751",
    "sg:province":"NY",
    "wof:name":"Glenn A Gabberty Apraisals",
    "wof:placetype":"venue"
},
  "geometry": {"coordinates":[-73.210855,40.730727],"type":"Point"}
}