{
  "type": "Feature",
  "properties": {
    "addr:full":"684 Nesconset Hwy Smithtown NY 11787",
    "addr:housenumber":"684",
    "addr:postcode":"11787",
    "addr:street":"Nesconset Hwy",
    "iso:country":"US",
    "sg:address":"684 Nesconset Hwy",
    "sg:city":"Smithtown",
    "sg:classifiers":[
        {
            "category":"Health Services",
            "subcategory":"Doctor",
            "type":"Services"
        }
    ],
    "sg:phone":"+1   ",
    "sg:postcode":"11787",
    "sg:province":"NY",
    "wof:name":"Lee J Montes DDS",
    "wof:placetype":"venue"
},
  "geometry": {"coordinates":[-73.171454,40.846961],"type":"Point"}
}