{
  "type": "Feature",
  "properties": {
    "addr:full":"62 E Market St Red Hook NY 12571",
    "addr:housenumber":"62",
    "addr:postcode":"12571",
    "addr:street":"E Market St",
    "iso:country":"US",
    "sg:address":"62 E Market St",
    "sg:city":"Red Hook",
    "sg:classifiers":[
        {
            "category":"Building & Trades",
            "subcategory":"Electrical",
            "type":"Services"
        }
    ],
    "sg:phone":"+1 845 758 1258",
    "sg:postcode":"12571",
    "sg:province":"NY",
    "sg:tags":[
        "electrical",
        "contractor"
    ],
    "wof:name":"Hilser Electric Inc",
    "wof:placetype":"venue"
},
  "geometry": {"coordinates":[-73.871064,41.994515],"type":"Point"}
}