{
  "type": "Feature",
  "properties": {
    "addr:full":"157 E Jericho Tpke Mineola NY 11501",
    "addr:housenumber":"157",
    "addr:postcode":"11501",
    "addr:street":"E Jericho Tpke",
    "iso:country":"US",
    "sg:address":"157 E Jericho Tpke",
    "sg:city":"Mineola",
    "sg:classifiers":[
        {
            "category":"Personal",
            "type":"Services"
        },
        {
            "category":"Retail",
            "subcategory":"Auto Repair",
            "type":"Services"
        }
    ],
    "sg:phone":"+1 516 294 3600",
    "sg:postcode":"11501",
    "sg:province":"NY",
    "sg:tags":[
        "body",
        "shop",
        "towing"
    ],
    "wof:name":"Mineola-Jericho Auto Body",
    "wof:placetype":"venue"
},
  "geometry": {"coordinates":[-73.63069900000001,40.752701],"type":"Point"}
}