{
  "type": "Feature",
  "properties": {
    "addr:full":"45 Irving Ave Croton On Hudson NY 10520",
    "addr:housenumber":"45",
    "addr:postcode":"10520",
    "addr:street":"Irving Ave",
    "iso:country":"US",
    "sg:address":"45 Irving Ave",
    "sg:city":"Croton On Hudson",
    "sg:classifiers":[
        {
            "category":"Professional",
            "subcategory":"Computer Services",
            "type":"Services"
        }
    ],
    "sg:phone":"+1 914 206 8352",
    "sg:postcode":"10520",
    "sg:province":"NY",
    "wof:name":"Computer Troubleshooters",
    "wof:placetype":"venue"
},
  "geometry": {"coordinates":[-73.881614,41.205456],"type":"Point"}
}