{
  "type": "Feature",
  "properties": {
    "addr:full":"94 N Industry Ct Deer Park NY 11729",
    "addr:housenumber":"94",
    "addr:postcode":"11729",
    "addr:street":"N Industry Ct",
    "iso:country":"US",
    "sg:address":"94 N Industry Ct",
    "sg:city":"Deer Park",
    "sg:classifiers":[
        {
            "category":"Shopping",
            "subcategory":"Catalog Store",
            "type":"Retail Goods"
        }
    ],
    "sg:phone":"+1 631 254 1208",
    "sg:postcode":"11729",
    "sg:province":"NY",
    "sg:tags":[
        "internet"
    ],
    "wof:name":"World Of America",
    "wof:placetype":"venue"
},
  "geometry": {"coordinates":[-73.29730000000001,40.766859],"type":"Point"}
}