{
  "type": "Feature",
  "properties": {
    "iso:country":"US",
    "sg:address":"7485 Morgan Rd",
    "sg:city":"Liverpool",
    "sg:classifiers":[
        {
            "category":"Organizations",
            "subcategory":"Labor Organization",
            "type":"Services"
        }
    ],
    "sg:phone":"+1 315 451 3663",
    "sg:postcode":"13090",
    "sg:province":"NY",
    "wof:name":"United Liverpool Faculty Assn",
    "wof:placetype":"venue"
},
  "geometry": {"coordinates":[-76.206035,43.131562],"type":"Point"}
}