{
  "type": "Feature",
  "properties": {
    "iso:country":"US",
    "sg:address":"867 Abbott Rd",
    "sg:city":"Buffalo",
    "sg:classifiers":[
        {
            "category":"Social Services",
            "subcategory":"Child Care",
            "type":"Services"
        }
    ],
    "sg:phone":"+1 716 826 6922",
    "sg:postcode":"14220",
    "sg:province":"NY",
    "sg:tags":[
        "day"
    ],
    "wof:name":"Rainbow Day Care Center",
    "wof:placetype":"venue"
},
  "geometry": {"coordinates":[-78.80819700000001,42.840698],"type":"Point"}
}