{
  "type": "Feature",
  "properties": {
    "addr:full":"119 N Main St Horseheads NY 14845",
    "addr:housenumber":"119",
    "addr:postcode":"14845",
    "addr:street":"N Main St",
    "iso:country":"US",
    "sg:address":"119 N Main St",
    "sg:city":"Horseheads",
    "sg:classifiers":[
        {
            "category":"Autos & Motor Vehicles",
            "subcategory":"Fuel & Gas Station",
            "type":"Retail Goods"
        }
    ],
    "sg:phone":"+1   ",
    "sg:postcode":"14845",
    "sg:province":"NY",
    "sg:tags":[
        "grocery",
        "station",
        "gasoline"
    ],
    "wof:name":"Kwik - Fill",
    "wof:placetype":"venue"
},
  "geometry": {"coordinates":[-76.822362,42.168921],"type":"Point"}
}