{
  "type": "Feature",
  "properties": {
    "iso:country":"US",
    "sg:address":"20 Petty Ln",
    "sg:city":"Medford",
    "sg:classifiers":[
        {
            "category":"Retail",
            "subcategory":"Repair Shop",
            "type":"Services"
        }
    ],
    "sg:phone":"+1   ",
    "sg:postcode":"11763",
    "sg:province":"NY",
    "sg:tags":[
        "apparel",
        "re",
        "sport"
    ],
    "wof:name":"Racquet Works Pro Shop LTD",
    "wof:placetype":"venue"
},
  "geometry": {"coordinates":[-73.016931,40.820062],"type":"Point"}
}