{
  "type": "Feature",
  "properties": {
    "addr:full":"376 3rd Ave New York NY 10016",
    "addr:housenumber":"376",
    "addr:postcode":"10016",
    "addr:street":"3Rd Ave",
    "iso:country":"US",
    "sg:address":"376 3rd Ave",
    "sg:city":"New York",
    "sg:classifiers":[
        {
            "category":"Retail",
            "subcategory":"Laundry & Dry Cleaning",
            "type":"Services"
        }
    ],
    "sg:phone":"+1 212 684 7590",
    "sg:postcode":"10016",
    "sg:province":"NY",
    "wof:name":"Vanity Fair Cleaners",
    "wof:placetype":"venue"
},
  "geometry": {"coordinates":[-73.98180499999999,40.741803],"type":"Point"}
}