{
  "type": "Feature",
  "properties": {
    "iso:country":"US",
    "sg:address":"57 Rossmore Ave",
    "sg:city":"Bronxville",
    "sg:classifiers":[
        {
            "category":"Professional",
            "type":"Services"
        }
    ],
    "sg:phone":"+1   ",
    "sg:postcode":"10708",
    "sg:province":"NY",
    "wof:name":"Bennett Terrain Inc",
    "wof:placetype":"venue"
},
  "geometry": {"coordinates":[-73.837981,40.935519],"type":"Point"}
}