{
  "type": "Feature",
  "properties": {
    "iso:country":"US",
    "sg:address":"106 Mosco St",
    "sg:city":"New York",
    "sg:classifiers":[
        {
            "category":"Restaurant",
            "type":"Food & Drink"
        }
    ],
    "sg:phone":"+1 212 693 1060",
    "sg:postcode":"10013",
    "sg:province":"NY",
    "sg:tags":[
        "chinese"
    ],
    "wof:name":"Fried Dumpling",
    "wof:placetype":"venue"
},
  "geometry": {"coordinates":[-73.999437,40.714466],"type":"Point"}
}