{
  "type": "Feature",
  "properties": {
    "addr:full":"62 W 45 St New York NY 10036",
    "addr:housenumber":"62",
    "addr:postcode":"10036",
    "addr:street":"W 45 St",
    "iso:country":"US",
    "sg:address":"62 W 45 St",
    "sg:city":"New York",
    "sg:classifiers":[
        {
            "category":"Travel",
            "subcategory":"Travel Agent",
            "type":"Entertainment"
        }
    ],
    "sg:phone":"+1 212 542 8165",
    "sg:postcode":"10036",
    "sg:province":"NY",
    "sg:tags":[
        "agency",
        "bureau"
    ],
    "wof:name":"N Y Net",
    "wof:placetype":"venue"
},
  "geometry": {"coordinates":[-73.981219,40.755851],"type":"Point"}
}