{
  "type": "Feature",
  "properties": {
    "addr:full":"115 N Main St Honeoye Falls NY 14472",
    "addr:housenumber":"115",
    "addr:postcode":"14472",
    "addr:street":"N Main St",
    "iso:country":"US",
    "sg:address":"115 N Main St",
    "sg:city":"Honeoye Falls",
    "sg:classifiers":[
        {
            "category":"Autos & Motor Vehicles",
            "subcategory":"Fuel & Gas Station",
            "type":"Retail Goods"
        }
    ],
    "sg:phone":"+1 585 624 4950",
    "sg:postcode":"14472",
    "sg:province":"NY",
    "sg:tags":[
        "station",
        "gasoline",
        "oil"
    ],
    "wof:name":"Newcomb Honeoye Falls Station",
    "wof:placetype":"venue"
},
  "geometry": {"coordinates":[-77.591391,42.964027],"type":"Point"}
}