{
  "type": "Feature",
  "properties": {
    "iso:country":"US",
    "sg:address":"114 Manor Dr",
    "sg:city":"Cornwall",
    "sg:classifiers":[
        {
            "category":"Building & Trades",
            "subcategory":"Landscaping Services",
            "type":"Services"
        }
    ],
    "sg:phone":"+1 845 534 0339",
    "sg:postcode":"12518",
    "sg:province":"NY",
    "sg:tags":[
        "waterproofing",
        "landscape",
        "contractor"
    ],
    "wof:name":"Green Acres",
    "wof:placetype":"venue"
},
  "geometry": {"coordinates":[-74.040572,41.440186],"type":"Point"}
}