{
  "type": "Feature",
  "properties": {
    "iso:country":"US",
    "sg:address":"737 Fort Salonga Rd",
    "sg:city":"Northport",
    "sg:classifiers":[
        {
            "category":"Shopping",
            "subcategory":"Optician",
            "type":"Retail Goods"
        }
    ],
    "sg:phone":"+1 631 754 2020",
    "sg:postcode":"11768",
    "sg:province":"NY",
    "sg:tags":[
        "eyewear"
    ],
    "sg:website":"www.dvretail.com",
    "wof:name":"Davis Vision",
    "wof:placetype":"venue"
},
  "geometry": {"coordinates":[-73.296097,40.9128],"type":"Point"}
}