{
  "type": "Feature",
  "properties": {
    "iso:country":"US",
    "sg:address":"184 Kent Ave",
    "sg:city":"Brooklyn",
    "sg:classifiers":[
        {
            "category":"Real Estate",
            "subcategory":"Real Estate Operator",
            "type":"Services"
        }
    ],
    "sg:phone":"+1 718 963 2400",
    "sg:postcode":"11211",
    "sg:province":"NY",
    "sg:tags":[
        "building",
        "nonresidential"
    ],
    "wof:name":"Americorp Equities",
    "wof:placetype":"venue"
},
  "geometry": {"coordinates":[-73.957933,40.724226],"type":"Point"}
}