{
  "type": "Feature",
  "properties": {
    "addr:full":"1900 Clinton Ave S Rochester NY 14618",
    "addr:housenumber":"1900",
    "addr:postcode":"14618",
    "addr:street":"Clinton Ave S",
    "iso:country":"US",
    "sg:address":"1900 Clinton Ave S",
    "sg:city":"Rochester",
    "sg:classifiers":[
        {
            "category":"Professional",
            "subcategory":"Research",
            "type":"Services"
        }
    ],
    "sg:phone":"+1   ",
    "sg:postcode":"14618",
    "sg:province":"NY",
    "sg:tags":[
        "organization",
        "noncommercial"
    ],
    "wof:name":"Pioneer Network",
    "wof:placetype":"venue"
},
  "geometry": {"coordinates":[-77.595299,43.119998],"type":"Point"}
}