{
  "type": "Feature",
  "properties": {
    "iso:country":"US",
    "sg:address":"11 Dory Ln",
    "sg:city":"Massapequa",
    "sg:classifiers":[
        {
            "category":"Shopping",
            "subcategory":"Clothing, Apparel, & Fashions",
            "type":"Retail Goods"
        }
    ],
    "sg:phone":"+1 516 797 8688",
    "sg:postcode":"11758",
    "sg:province":"NY",
    "sg:tags":[
        "apparel",
        "racing",
        "sportswear",
        "merchandise"
    ],
    "wof:name":"Magnum Sportswear Inc",
    "wof:placetype":"venue"
},
  "geometry": {"coordinates":[-73.48335400000001,40.654823],"type":"Point"}
}