{
  "type": "Feature",
  "properties": {
    "addr:full":"2916 8th Ave New York NY 10039",
    "addr:housenumber":"2916",
    "addr:postcode":"10039",
    "addr:street":"8Th Ave",
    "iso:country":"US",
    "sg:address":"2916 8th Ave",
    "sg:city":"New York",
    "sg:classifiers":[
        {
            "category":"Shopping",
            "subcategory":"Clothing, Apparel, & Fashions",
            "type":"Retail Goods"
        }
    ],
    "sg:phone":"+1   ",
    "sg:postcode":"10039",
    "sg:province":"NY",
    "wof:name":"Uptown Harlem Fashion LLC",
    "wof:placetype":"venue"
},
  "geometry": {"coordinates":[-73.937303,40.828952],"type":"Point"}
}