{
  "type": "Feature",
  "properties": {
    "addr:full":"1168 Troy Schenectady Rd Latham NY 12110",
    "addr:housenumber":"1168",
    "addr:postcode":"12110",
    "addr:street":"Troy Schenectady Rd",
    "iso:country":"US",
    "sg:address":"1168 Troy Schenectady Rd",
    "sg:city":"Latham",
    "sg:classifiers":[
        {
            "category":"Travel",
            "subcategory":"Travel Agent",
            "type":"Entertainment"
        }
    ],
    "sg:phone":"+1   ",
    "sg:postcode":"12110",
    "sg:province":"NY",
    "sg:tags":[
        "agency"
    ],
    "wof:name":"PEF Travel Corp",
    "wof:placetype":"venue"
},
  "geometry": {"coordinates":[-73.817194,42.767982],"type":"Point"}
}