{
  "type": "Feature",
  "properties": {
    "addr:full":"172 Graham Ave Brooklyn NY 11206",
    "addr:housenumber":"172",
    "addr:postcode":"11206",
    "addr:street":"Graham Ave",
    "iso:country":"US",
    "sg:address":"172 Graham Ave",
    "sg:city":"Brooklyn",
    "sg:classifiers":[
        {
            "category":"Manufacturing",
            "subcategory":"Chemicals & Compounds",
            "type":"Manufacturing & Wholesale Goods"
        },
        {
            "category":"Wholesale",
            "subcategory":"Painting Supplies",
            "type":"Manufacturing & Wholesale Goods"
        },
        {
            "category":"Manufacturing",
            "subcategory":"Building Materials",
            "type":"Manufacturing & Wholesale Goods"
        }
    ],
    "sg:phone":"+1 718 388 5151",
    "sg:postcode":"11206",
    "sg:province":"NY",
    "sg:tags":[
        "paint-wholesale",
        "equipment",
        "manufacturer",
        "painter",
        "paint"
    ],
    "wof:name":"Seldowitz & Glaubiger, Inc.",
    "wof:placetype":"venue"
},
  "geometry": {"coordinates":[-73.943242,40.70754],"type":"Point"}
}