{
  "type": "Feature",
  "properties": {
    "addr:full":"18-20 W. 21st Street Suite 804 New York NY 10010",
    "addr:housenumber":"18-20;804",
    "addr:postcode":"10010",
    "addr:street":"W. 21St Street Suite",
    "iso:country":"US",
    "sg:address":"18-20 W. 21st Street Suite 804",
    "sg:city":"New York",
    "sg:classifiers":[
        {
            "category":"Professional",
            "subcategory":"Computer Services",
            "type":"Services"
        }
    ],
    "sg:phone":"+1 617 417 3999",
    "sg:postcode":"10010",
    "sg:province":"NY",
    "sg:tags":[
        "personal-finance-education",
        "personal-finance-tools",
        "tc50"
    ],
    "sg:website":"http://www.learnvest.com",
    "wof:name":"LearnVest",
    "wof:placetype":"venue"
},
  "geometry": {"coordinates":[-73.993317,40.741297],"type":"Point"}
}