{
  "type": "Feature",
  "properties": {
    "addr:full":"1890 Eastchester Rd Bronx NY 10461",
    "addr:housenumber":"1890",
    "addr:postcode":"10461",
    "addr:street":"Eastchester Rd",
    "iso:country":"US",
    "sg:address":"1890 Eastchester Rd",
    "sg:city":"Bronx",
    "sg:classifiers":[
        {
            "category":"Shopping",
            "subcategory":"Stationery & Office Supplies",
            "type":"Retail Goods"
        }
    ],
    "sg:phone":"+1 718 409 0347",
    "sg:postcode":"10461",
    "sg:province":"NY",
    "sg:tags":[
        "stationer"
    ],
    "wof:name":"R T Convenient & Grocery",
    "wof:placetype":"venue"
},
  "geometry": {"coordinates":[-73.84322299999999,40.852728],"type":"Point"}
}