{
  "type": "Feature",
  "properties": {
    "addr:full":"355 Smith St. Brooklyn NY",
    "wof:name":"Brooklyn Social",
    "wof:placetype":"venue"
},
  "geometry": {"coordinates":[-73.99222,40.679868],"type":"Point"}
}