{
  "type": "Feature",
  "properties": {
    "iso:country":"US",
    "sg:address":"128 Parkdale Ave",
    "sg:city":"Buffalo",
    "sg:classifiers":[
        {
            "category":"Organizations",
            "subcategory":"Religious Organization",
            "type":"Services"
        }
    ],
    "sg:phone":"+1 716 883 4444",
    "sg:postcode":"14213",
    "sg:province":"NY",
    "sg:tags":[
        "church"
    ],
    "wof:name":"Iglesia De Jesucristo",
    "wof:placetype":"venue"
},
  "geometry": {"coordinates":[-78.88804500000001,42.919742],"type":"Point"}
}