{
  "type": "Feature",
  "properties": {
    "iso:country":"US",
    "sg:address":"72 Meadow Dr",
    "sg:city":"Woodmere",
    "sg:classifiers":[
        {
            "category":"Professional",
            "subcategory":"Lawyer & Legal Services",
            "type":"Services"
        }
    ],
    "sg:phone":"+1 516 295 2509",
    "sg:postcode":"11598",
    "sg:province":"NY",
    "sg:tags":[
        "attorney"
    ],
    "wof:name":"Friedman & Rogovin",
    "wof:placetype":"venue"
},
  "geometry": {"coordinates":[-73.712159,40.624458],"type":"Point"}
}