{
  "type": "Feature",
  "properties": {
    "iso:country":"US",
    "sg:address":"416 Bay Ridge Ave",
    "sg:city":"Brooklyn",
    "sg:classifiers":[
        {
            "category":"Professional",
            "subcategory":"Computer Services",
            "type":"Services"
        }
    ],
    "sg:phone":"+1 718 567 8888",
    "sg:postcode":"11220",
    "sg:province":"NY",
    "sg:tags":[
        "consultant",
        "designer"
    ],
    "sg:website":"www.decisionsdecisions-inc.com",
    "wof:name":"Decisions Decisions Inc",
    "wof:placetype":"venue"
},
  "geometry": {"coordinates":[-74.021361,40.633592],"type":"Point"}
}