{
  "type": "Feature",
  "properties": {
    "addr:full":"7 Barn Rd Lake Placid NY 12946",
    "addr:housenumber":"7",
    "addr:postcode":"12946",
    "addr:street":"Barn Rd",
    "iso:country":"US",
    "sg:address":"7 Barn Rd",
    "sg:city":"Lake Placid",
    "sg:classifiers":[
        {
            "category":"Building & Trades",
            "subcategory":"Construction",
            "type":"Services"
        }
    ],
    "sg:phone":"+1 518 523 1942",
    "sg:postcode":"12946",
    "sg:province":"NY",
    "sg:tags":[
        "general",
        "contractor"
    ],
    "wof:name":"David M Preston & Builders",
    "wof:placetype":"venue"
},
  "geometry": {"coordinates":[-74.01103500000001,44.292735],"type":"Point"}
}