{
  "type": "Feature",
  "properties": {
    "iso:country":"US",
    "sg:address":"73 S 3rd Ave",
    "sg:city":"Mt Vernon",
    "sg:classifiers":[
        {
            "category":"Shopping",
            "subcategory":"Used Merchandise",
            "type":"Retail Goods"
        }
    ],
    "sg:phone":"+1 914 667 5296",
    "sg:postcode":"10550",
    "sg:province":"NY",
    "sg:tags":[
        "antique"
    ],
    "wof:name":"Aromiel's Gemini Antique Earth",
    "wof:placetype":"venue"
},
  "geometry": {"coordinates":[-73.83572700000001,40.911243],"type":"Point"}
}