{
  "type": "Feature",
  "properties": {
    "addr:full":"126 Delancey St New York NY 10002",
    "addr:housenumber":"126",
    "addr:postcode":"10002",
    "addr:street":"Delancey St",
    "iso:country":"US",
    "sg:address":"126 Delancey St",
    "sg:city":"New York",
    "sg:classifiers":[
        {
            "category":"Home & Garden",
            "subcategory":"Furniture",
            "type":"Retail Goods"
        }
    ],
    "sg:phone":"+1 877 817 9500",
    "sg:postcode":"10002",
    "sg:province":"NY",
    "sg:tags":[
        "store"
    ],
    "wof:name":"Reliable International Furniture Inc",
    "wof:placetype":"venue"
},
  "geometry": {"coordinates":[-73.987526,40.718584],"type":"Point"}
}