{
  "type": "Feature",
  "properties": {
    "addr:full":"15 Haas St Deer Park NY 11729",
    "addr:housenumber":"15",
    "addr:postcode":"11729",
    "addr:street":"Haas St",
    "iso:country":"US",
    "sg:address":"15 Haas St",
    "sg:city":"Deer Park",
    "sg:classifiers":[
        {
            "category":"Building & Trades",
            "subcategory":"Construction",
            "type":"Services"
        }
    ],
    "sg:phone":"+1 631 595 1789",
    "sg:postcode":"11729",
    "sg:province":"NY",
    "sg:tags":[
        "house"
    ],
    "wof:name":"Serenity Home Improvements",
    "wof:placetype":"venue"
},
  "geometry": {"coordinates":[-73.322479,40.750083],"type":"Point"}
}