{
  "type": "Feature",
  "properties": {
    "addr:full":"5397 Sheridan Dr Buffalo NY 14221",
    "addr:housenumber":"5397",
    "addr:postcode":"14221",
    "addr:street":"Sheridan Dr",
    "iso:country":"US",
    "sg:address":"5397 Sheridan Dr",
    "sg:city":"Buffalo",
    "sg:classifiers":[
        {
            "category":"Shopping",
            "type":"Retail Goods"
        }
    ],
    "sg:phone":"+1 716 634 3397",
    "sg:postcode":"14221",
    "sg:province":"NY",
    "sg:tags":[
        "pet",
        "shop"
    ],
    "sg:website":"www.stevespets.com",
    "wof:name":"Steve's Wonderful World-Pets",
    "wof:placetype":"venue"
},
  "geometry": {"coordinates":[-78.73432099999999,42.978457],"type":"Point"}
}