{
  "type": "Feature",
  "properties": {
    "addr:full":"5783 Smith Rd Verona NY 13478",
    "addr:housenumber":"5783",
    "addr:postcode":"13478",
    "addr:street":"Smith Rd",
    "iso:country":"US",
    "sg:address":"5783 Smith Rd",
    "sg:city":"Verona",
    "sg:classifiers":[
        {
            "category":"Building & Trades",
            "subcategory":"Construction",
            "type":"Services"
        }
    ],
    "sg:phone":"+1 315 363 7092",
    "sg:postcode":"13478",
    "sg:province":"NY",
    "sg:tags":[
        "house"
    ],
    "wof:name":"Harris Home Improvement",
    "wof:placetype":"venue"
},
  "geometry": {"coordinates":[-75.54063499999999,43.149173],"type":"Point"}
}