{
  "type": "Feature",
  "properties": {
    "addr:full":"445 Main St Youngstown NY 14174",
    "addr:housenumber":"445",
    "addr:postcode":"14174",
    "addr:street":"Main St",
    "iso:country":"US",
    "sg:address":"445 Main St",
    "sg:city":"Youngstown",
    "sg:classifiers":[
        {
            "category":"Sports & Exercise",
            "subcategory":"Gym",
            "type":"Entertainment"
        }
    ],
    "sg:phone":"+1   ",
    "sg:postcode":"14174",
    "sg:province":"NY",
    "sg:tags":[
        "fitness",
        "physical",
        "facility"
    ],
    "wof:name":"A Quality Life",
    "wof:placetype":"venue"
},
  "geometry": {"coordinates":[-79.05005800000001,43.250131],"type":"Point"}
}