{
  "type": "Feature",
  "properties": {
    "iso:country":"US",
    "sg:address":"38 Eastview Mall Dr",
    "sg:city":"Victor",
    "sg:classifiers":[
        {
            "category":"Wholesale",
            "subcategory":"Machinery & Supplies",
            "type":"Manufacturing & Wholesale Goods"
        }
    ],
    "sg:phone":"+1 585 223 4820",
    "sg:postcode":"14564",
    "sg:province":"NY",
    "sg:tags":[
        "rubber",
        "product"
    ],
    "wof:name":"Buckeye Rubber",
    "wof:placetype":"venue"
},
  "geometry": {"coordinates":[-77.439284,43.026037],"type":"Point"}
}