{
  "type": "Feature",
  "properties": {
    "addr:full":"33 Hewitt Ave Hicksville NY 11801",
    "addr:housenumber":"33",
    "addr:postcode":"11801",
    "addr:street":"Hewitt Ave",
    "iso:country":"US",
    "sg:address":"33 Hewitt Ave",
    "sg:city":"Hicksville",
    "sg:classifiers":[
        {
            "category":"Freight",
            "type":"Transportation"
        }
    ],
    "sg:phone":"+1   ",
    "sg:postcode":"11801",
    "sg:province":"NY",
    "sg:tags":[
        "local",
        "trucking"
    ],
    "wof:name":"Brer-Four Transportation Corp",
    "wof:placetype":"venue"
},
  "geometry": {"coordinates":[-73.539252,40.759723],"type":"Point"}
}