{
  "type": "Feature",
  "properties": {
    "iso:country":"US",
    "sg:address":"3505 James St",
    "sg:city":"Syracuse",
    "sg:classifiers":[
        {
            "category":"Professional",
            "subcategory":"Accounting & Tax Preparation",
            "type":"Services"
        }
    ],
    "sg:phone":"+1 315 437 5195",
    "sg:postcode":"13206",
    "sg:province":"NY",
    "sg:tags":[
        "return",
        "filing"
    ],
    "wof:name":"Tax Experts",
    "wof:placetype":"venue"
},
  "geometry": {"coordinates":[-76.097354,43.069341],"type":"Point"}
}