{
  "type": "Feature",
  "properties": {
    "iso:country":"US",
    "sg:address":"43 Madeline Rd",
    "sg:city":"Ridge",
    "sg:classifiers":[
        {
            "category":"Building & Trades",
            "subcategory":"Landscaping Services",
            "type":"Services"
        }
    ],
    "sg:phone":"+1 631 475 7411",
    "sg:postcode":"11961",
    "sg:province":"NY",
    "sg:tags":[
        "tree"
    ],
    "wof:name":"Best Value Outdoor Land Service",
    "wof:placetype":"venue"
},
  "geometry": {"coordinates":[-72.859348,40.89761],"type":"Point"}
}