{
  "type": "Feature",
  "properties": {
    "addr:full":"2109 Nostrand Avenue Brooklyn NY 11210",
    "addr:housenumber":"2109",
    "addr:postcode":"11210",
    "addr:street":"Nostrand Avenue",
    "iso:country":"US",
    "sg:address":"2109 Nostrand Avenue",
    "sg:city":"Brooklyn",
    "sg:classifiers":[
        {
            "category":"Shopping",
            "subcategory":"Pharmacy",
            "type":"Retail Goods"
        }
    ],
    "sg:phone":"+1 718 421 3600",
    "sg:postcode":"11210",
    "sg:province":"NY",
    "sg:tags":[
        "drugstore"
    ],
    "wof:name":"Junction Pharmacy",
    "wof:placetype":"venue"
},
  "geometry": {"coordinates":[-73.947625,40.634003],"type":"Point"}
}