{
  "type": "Feature",
  "properties": {
    "addr:full":"293 State Hwy 104A Oswego NY 13126",
    "addr:housenumber":"293",
    "addr:postcode":"13126",
    "addr:street":"State Hwy 104A",
    "iso:country":"US",
    "sg:address":"293 State Hwy 104A",
    "sg:city":"Oswego",
    "sg:classifiers":[
        {
            "category":"Shopping",
            "subcategory":"Clothing, Apparel, & Fashions",
            "type":"Retail Goods"
        }
    ],
    "sg:phone":"+1   ",
    "sg:postcode":"13126",
    "sg:province":"NY",
    "wof:name":"Fashion Bug",
    "wof:placetype":"venue"
},
  "geometry": {"coordinates":[-76.593497,43.393709],"type":"Point"}
}