{
  "type": "Feature",
  "properties": {
    "addr:full":"2343 Hylan Blvd Staten Island NY 10306",
    "addr:housenumber":"2343",
    "addr:postcode":"10306",
    "addr:street":"Hylan Blvd",
    "iso:country":"US",
    "sg:address":"2343 Hylan Blvd",
    "sg:city":"Staten Island",
    "sg:classifiers":[
        {
            "category":"Professional",
            "subcategory":"Management & Consulting",
            "type":"Services"
        }
    ],
    "sg:phone":"+1 718 370 2843",
    "sg:postcode":"10306",
    "sg:province":"NY",
    "sg:tags":[
        "fuel"
    ],
    "wof:name":"Prudent Wealth Management",
    "wof:placetype":"venue"
},
  "geometry": {"coordinates":[-74.10699099999999,40.57322],"type":"Point"}
}