{
  "type": "Feature",
  "properties": {
    "addr:full":"102 S Main St Northville NY 12134",
    "addr:housenumber":"102",
    "addr:postcode":"12134",
    "addr:street":"S Main St",
    "iso:country":"US",
    "sg:address":"102 S Main St",
    "sg:city":"Northville",
    "sg:classifiers":[
        {
            "category":"Restaurant",
            "type":"Food & Drink"
        }
    ],
    "sg:phone":"+1 518 863 4464",
    "sg:postcode":"12134",
    "sg:province":"NY",
    "wof:name":"Crazy Mary's Classic Cafe",
    "wof:placetype":"venue"
},
  "geometry": {"coordinates":[-74.171848,43.225904],"type":"Point"}
}