{
  "type": "Feature",
  "properties": {
    "iso:country":"US",
    "sg:address":"7699 State Hwy 5",
    "sg:city":"St Johnsville",
    "sg:classifiers":[
        {
            "category":"Home & Garden",
            "subcategory":"Garden Supply",
            "type":"Retail Goods"
        }
    ],
    "sg:phone":"+1 518 568 7013",
    "sg:postcode":"13452",
    "sg:province":"NY",
    "sg:tags":[
        "lawn",
        "mower"
    ],
    "wof:name":"Amy's Sales & Svc",
    "wof:placetype":"venue"
},
  "geometry": {"coordinates":[-74.689655,42.998227],"type":"Point"}
}