{
  "type": "Feature",
  "properties": {
    "iso:country":"US",
    "sg:address":"7608 Oswego Rd",
    "sg:city":"Liverpool",
    "sg:classifiers":[
        {
            "category":"Communications",
            "type":"Services"
        }
    ],
    "sg:phone":"+1 315 652 2100",
    "sg:postcode":"13090",
    "sg:province":"NY",
    "sg:tags":[
        "carrier"
    ],
    "wof:name":"Wireless Plus",
    "wof:placetype":"venue"
},
  "geometry": {"coordinates":[-76.225988,43.137519],"type":"Point"}
}