{
  "type": "Feature",
  "properties": {
    "addr:full":"20 W 33 St New York NY 10001",
    "addr:housenumber":"20",
    "addr:postcode":"10001",
    "addr:street":"W 33 St",
    "iso:country":"US",
    "sg:address":"20 W 33 St",
    "sg:city":"New York",
    "sg:classifiers":[
        {
            "category":"Wholesale",
            "subcategory":"Apparel",
            "type":"Manufacturing & Wholesale Goods"
        },
        {
            "category":"Manufacturing",
            "subcategory":"Apparel",
            "type":"Manufacturing & Wholesale Goods"
        }
    ],
    "sg:phone":"+1 212 947 9807",
    "sg:postcode":"10001",
    "sg:province":"NY",
    "sg:tags":[
        "clothing",
        "mfg"
    ],
    "wof:name":"Kidstreet Accessories",
    "wof:placetype":"venue"
},
  "geometry": {"coordinates":[-73.987649,40.748723],"type":"Point"}
}