{
  "type": "Feature",
  "properties": {
    "addr:full":"313 Ave U Brooklyn NY 11223",
    "addr:housenumber":"313",
    "addr:postcode":"11223",
    "addr:street":"Ave U",
    "iso:country":"US",
    "sg:address":"313 Ave U",
    "sg:city":"Brooklyn",
    "sg:classifiers":[
        {
            "category":"Restaurant",
            "type":"Food & Drink"
        }
    ],
    "sg:phone":"+1   ",
    "sg:postcode":"11223",
    "sg:province":"NY",
    "sg:tags":[
        "drinking",
        "eating"
    ],
    "wof:name":"Fiorentinos Ristorante",
    "wof:placetype":"venue"
},
  "geometry": {"coordinates":[-73.971958,40.597179],"type":"Point"}
}