{
  "type": "Feature",
  "properties": {
    "iso:country":"US",
    "sg:address":"1111 Paterson St",
    "sg:city":"Ogdensburg",
    "sg:classifiers":[
        {
            "category":"Health Services",
            "subcategory":"Doctor",
            "type":"Services"
        }
    ],
    "sg:phone":"+1 315 393 9113",
    "sg:postcode":"13669",
    "sg:province":"NY",
    "sg:tags":[
        "physician",
        "surgeon"
    ],
    "wof:name":"Advanced Physical Therapy",
    "wof:placetype":"venue"
},
  "geometry": {"coordinates":[-75.477642,44.692152],"type":"Point"}
}