{
  "type": "Feature",
  "properties": {
    "iso:country":"US",
    "sg:address":"3649 Merrick Rd",
    "sg:city":"Seaford",
    "sg:classifiers":[
        {
            "category":"Food & Beverages",
            "subcategory":"Bakery",
            "type":"Retail Goods"
        }
    ],
    "sg:phone":"+1 516 785 5509",
    "sg:postcode":"11783",
    "sg:province":"NY",
    "sg:tags":[
        "baker"
    ],
    "wof:name":"Gerst's Cake & Cookie Shop",
    "wof:placetype":"venue"
},
  "geometry": {"coordinates":[-73.495959,40.665236],"type":"Point"}
}