{
  "type": "Feature",
  "properties": {
    "iso:country":"US",
    "sg:address":"79 Middleville Rd",
    "sg:city":"Northport",
    "sg:classifiers":[
        {
            "category":"Education",
            "subcategory":"Library",
            "type":"Public Place"
        }
    ],
    "sg:phone":"+1 631 261 4400",
    "sg:postcode":"11768",
    "sg:province":"NY",
    "wof:name":"Department Of VA Medical Libr",
    "wof:placetype":"venue"
},
  "geometry": {"coordinates":[-73.306918,40.899947],"type":"Point"}
}