{
  "type": "Feature",
  "properties": {
    "iso:country":"US",
    "sg:address":"183 Centre St",
    "sg:city":"New York",
    "sg:classifiers":[
        {
            "category":"Health Services",
            "subcategory":"Clinic",
            "type":"Services"
        }
    ],
    "sg:phone":"+1 212 966 4866",
    "sg:postcode":"10013",
    "sg:province":"NY",
    "sg:tags":[
        "medical",
        "group"
    ],
    "wof:name":"American Infertility-New York",
    "wof:placetype":"venue"
},
  "geometry": {"coordinates":[-73.99977199999999,40.71825],"type":"Point"}
}