{
  "type": "Feature",
  "properties": {
    "addr:full":"115 E 23rd St New York NY 10079",
    "addr:housenumber":"115",
    "addr:postcode":"10079",
    "addr:street":"E 23Rd St",
    "iso:country":"US",
    "sg:address":"115 E 23rd St",
    "sg:city":"New York",
    "sg:classifiers":[
        {
            "category":"Communications",
            "subcategory":"Newspaper",
            "type":"Services"
        }
    ],
    "sg:postcode":"10079",
    "sg:province":"NY",
    "sg:tags":[
        "print",
        "medium"
    ],
    "wof:name":"Psychology Today",
    "wof:placetype":"venue"
},
  "geometry": {"coordinates":[-73.985433,40.740231],"type":"Point"}
}