{
  "type": "Feature",
  "properties": {
    "iso:country":"US",
    "sg:address":"115 E 23rd St",
    "sg:city":"New York",
    "sg:classifiers":[
        {
            "category":"Communications",
            "subcategory":"Newspaper",
            "type":"Services"
        }
    ],
    "sg:postcode":"10079",
    "sg:province":"NY",
    "sg:tags":[
        "print",
        "medium"
    ],
    "wof:name":"Psychology Today",
    "wof:placetype":"venue"
},
  "geometry": {"coordinates":[-73.985433,40.740231],"type":"Point"}
}