{
  "type": "Feature",
  "properties": {
    "iso:country":"US",
    "sg:address":"1293 Middle Country Rd",
    "sg:city":"Middle Island",
    "sg:classifiers":[
        {
            "category":"Real Estate",
            "subcategory":"Real Estate Agent",
            "type":"Services"
        }
    ],
    "sg:phone":"+1 631 205 5300",
    "sg:postcode":"11953",
    "sg:province":"NY",
    "wof:name":"Coldwell Banker",
    "wof:placetype":"venue"
},
  "geometry": {"coordinates":[-72.927514,40.885682],"type":"Point"}
}