{
  "type": "Feature",
  "properties": {
    "addr:full":"2748 W Entry Rd Baldwinsville NY 13027",
    "addr:housenumber":"2748",
    "addr:postcode":"13027",
    "addr:street":"W Entry Rd",
    "iso:country":"US",
    "sg:address":"2748 W Entry Rd",
    "sg:city":"Baldwinsville",
    "sg:classifiers":[
        {
            "category":"Freight",
            "type":"Transportation"
        }
    ],
    "sg:phone":"+1   ",
    "sg:postcode":"13027",
    "sg:province":"NY",
    "sg:tags":[
        "general"
    ],
    "sg:website":"www.ainsleywarehouse.com",
    "wof:name":"Ainsley Superior Warehouse",
    "wof:placetype":"venue"
},
  "geometry": {"coordinates":[-76.30971099999999,43.179182],"type":"Point"}
}