{
  "type": "Feature",
  "properties": {
    "addr:full":"219 W 19th St New York NY 10011",
    "addr:housenumber":"219",
    "addr:postcode":"10011",
    "addr:street":"W 19Th St",
    "iso:country":"US",
    "sg:address":"219 W 19th St",
    "sg:city":"New York",
    "sg:classifiers":[
        {
            "category":"Sports & Exercise",
            "subcategory":"Gym",
            "type":"Entertainment"
        },
        {
            "category":"Education",
            "subcategory":"Dance Studio",
            "type":"Public Place"
        }
    ],
    "sg:phone":"+1 347 989 4667",
    "sg:postcode":"10011",
    "sg:province":"NY",
    "sg:tags":[
        "trainer"
    ],
    "sg:website":"www.twirlnyc.com",
    "wof:name":"TWIRL NYC",
    "wof:placetype":"venue"
},
  "geometry": {"coordinates":[-73.998361,40.742125],"type":"Point"}
}