{
  "type": "Feature",
  "properties": {
    "iso:country":"US",
    "sg:address":"153 Main St Unit 5",
    "sg:city":"Sayville",
    "sg:classifiers":[
        {
            "category":"Personal",
            "subcategory":"Beauty Salon",
            "type":"Services"
        }
    ],
    "sg:phone":"+1 631 244 0933",
    "sg:postcode":"11782",
    "sg:province":"NY",
    "sg:website":"http://www.vanitysquaresalon.com",
    "wof:name":"Vanity Square Salon Inc",
    "wof:placetype":"venue"
},
  "geometry": {"coordinates":[-73.084869,40.734692],"type":"Point"}
}