{
  "type": "Feature",
  "properties": {
    "addr:full":"1675 Grand Concourse Bronx NY 10452",
    "addr:housenumber":"1675",
    "addr:postcode":"10452",
    "addr:street":"Grand Concourse",
    "iso:country":"US",
    "sg:address":"1675 Grand Concourse",
    "sg:city":"Bronx",
    "sg:classifiers":[
        {
            "category":"Education",
            "subcategory":"Dance Studio",
            "type":"Public Place"
        }
    ],
    "sg:phone":"+1 718 299 8728",
    "sg:postcode":"10452",
    "sg:province":"NY",
    "sg:tags":[
        "instruction",
        "dancing"
    ],
    "wof:name":"Te Dance",
    "wof:placetype":"venue"
},
  "geometry": {"coordinates":[-73.91194900000001,40.843204],"type":"Point"}
}