{
  "type": "Feature",
  "properties": {
    "addr:full":"65-07 Woodhaven Blvd New York NY 11374",
    "addr:housenumber":"65-07",
    "addr:postcode":"11374",
    "addr:street":"Woodhaven Blvd",
    "iso:country":"US",
    "sg:address":"65-07 Woodhaven Blvd",
    "sg:city":"New York",
    "sg:classifiers":[
        {
            "category":"Sports & Exercise",
            "subcategory":"Gym",
            "type":"Entertainment"
        }
    ],
    "sg:phone":"+1 718 275 2100",
    "sg:postcode":"11374",
    "sg:province":"NY",
    "sg:tags":[
        "yoga"
    ],
    "sg:website":"www.hotyogaregopark.com",
    "wof:name":"Bikram Yoga Rego Park",
    "wof:placetype":"venue"
},
  "geometry": {"coordinates":[-73.871342,40.731492],"type":"Point"}
}