{
  "type": "Feature",
  "properties": {
    "addr:full":"50 Prescott St Albany NY 12205",
    "addr:housenumber":"50",
    "addr:postcode":"12205",
    "addr:street":"Prescott St",
    "iso:country":"US",
    "sg:address":"50 Prescott St",
    "sg:city":"Albany",
    "sg:classifiers":[
        {
            "category":"Organizations",
            "subcategory":"Non-profit Organization",
            "type":"Services"
        },
        {
            "category":"Real Estate",
            "subcategory":"Real Estate Operator",
            "type":"Services"
        }
    ],
    "sg:phone":"+1 518 869 7441",
    "sg:postcode":"12205",
    "sg:province":"NY",
    "sg:tags":[
        "building",
        "apartment"
    ],
    "wof:name":"Bishop Broderick Apartments",
    "wof:placetype":"venue"
},
  "geometry": {"coordinates":[-73.865173,42.745443],"type":"Point"}
}