{
  "type": "Feature",
  "properties": {
    "addr:full":"1306 Franklin Ave Mamaroneck NY 10543",
    "addr:housenumber":"1306",
    "addr:postcode":"10543",
    "addr:street":"Franklin Ave",
    "iso:country":"US",
    "sg:address":"1306 Franklin Ave",
    "sg:city":"Mamaroneck",
    "sg:classifiers":[
        {
            "category":"Building & Trades",
            "subcategory":"Plumbing",
            "type":"Services"
        }
    ],
    "sg:phone":"+1 914 698 2783",
    "sg:postcode":"10543",
    "sg:province":"NY",
    "sg:tags":[
        "contractor"
    ],
    "wof:name":"A & G Installations Inc",
    "wof:placetype":"venue"
},
  "geometry": {"coordinates":[-73.725443,40.961658],"type":"Point"}
}