{
  "type": "Feature",
  "properties": {
    "addr:full":"118 Spindle Rd Hicksville NY 11801",
    "addr:housenumber":"118",
    "addr:postcode":"11801",
    "addr:street":"Spindle Rd",
    "iso:country":"US",
    "sg:address":"118 Spindle Rd",
    "sg:city":"Hicksville",
    "sg:classifiers":[
        {
            "category":"Professional",
            "subcategory":"Detective & Security Services",
            "type":"Services"
        }
    ],
    "sg:phone":"+1 516 731 7194",
    "sg:postcode":"11801",
    "sg:province":"NY",
    "sg:tags":[
        "information",
        "bureau"
    ],
    "sg:website":"http://www.artisannewsservice.com",
    "wof:name":"Artisan News Service",
    "wof:placetype":"venue"
},
  "geometry": {"coordinates":[-73.52331100000001,40.743734],"type":"Point"}
}