{
  "type": "Feature",
  "properties": {
    "iso:country":"US",
    "sg:address":"2 Wall St Fl 8",
    "sg:city":"New York",
    "sg:classifiers":[
        {
            "category":"Professional",
            "subcategory":"Lawyer & Legal Services",
            "type":"Services"
        }
    ],
    "sg:phone":"+1 212 344 3800",
    "sg:postcode":"10005",
    "sg:province":"NY",
    "wof:name":"Christophe & Associates PC",
    "wof:placetype":"venue"
},
  "geometry": {"coordinates":[-74.158024,40.707859],"type":"Point"}
}