{
  "type": "Feature",
  "properties": {
    "addr:full":"4001 Hylan Blvd Staten Island NY 10308",
    "addr:housenumber":"4001",
    "addr:postcode":"10308",
    "addr:street":"Hylan Blvd",
    "iso:country":"US",
    "sg:address":"4001 Hylan Blvd",
    "sg:city":"Staten Island",
    "sg:classifiers":[
        {
            "category":"Professional",
            "subcategory":"Business Services",
            "type":"Services"
        }
    ],
    "sg:phone":"+1 718 608 8500",
    "sg:postcode":"10308",
    "sg:province":"NY",
    "sg:tags":[
        "appraiser"
    ],
    "wof:name":"Executive Appraisal Svc",
    "wof:placetype":"venue"
},
  "geometry": {"coordinates":[-74.14700499999999,40.541304],"type":"Point"}
}