{
  "type": "Feature",
  "properties": {
    "iso:country":"US",
    "sg:address":"111 Rockne St",
    "sg:city":"Staten Island",
    "sg:classifiers":[
        {
            "category":"Building & Trades",
            "subcategory":"Landscaping Services",
            "type":"Services"
        }
    ],
    "sg:phone":"+1 718 984 3411",
    "sg:postcode":"10314",
    "sg:province":"NY",
    "sg:tags":[
        "landscape"
    ],
    "wof:name":"Calvanico Landscaping",
    "wof:placetype":"venue"
},
  "geometry": {"coordinates":[-74.159122,40.586706],"type":"Point"}
}