{
  "type": "Feature",
  "properties": {
    "iso:country":"US",
    "sg:address":"911 S Park Ave",
    "sg:city":"Buffalo",
    "sg:classifiers":[
        {
            "category":"Autos & Motor Vehicles",
            "subcategory":"Auto Supplies",
            "type":"Retail Goods"
        }
    ],
    "sg:phone":"+1 716 823 1300",
    "sg:postcode":"14210",
    "sg:province":"NY",
    "sg:tags":[
        "tire"
    ],
    "wof:name":"Tires R Us",
    "wof:placetype":"venue"
},
  "geometry": {"coordinates":[-78.848106,42.86629],"type":"Point"}
}