{
  "type": "Feature",
  "properties": {
    "addr:full":"467 South Ave Rochester NY 14620",
    "addr:housenumber":"467",
    "addr:postcode":"14620",
    "addr:street":"South Ave",
    "iso:country":"US",
    "sg:address":"467 South Ave",
    "sg:city":"Rochester",
    "sg:classifiers":[
        {
            "category":"Personal",
            "subcategory":"Beauty Salon",
            "type":"Services"
        }
    ],
    "sg:phone":"+1 585 325 1130",
    "sg:postcode":"14620",
    "sg:province":"NY",
    "wof:name":"Hair N There",
    "wof:placetype":"venue"
},
  "geometry": {"coordinates":[-77.605644,43.146493],"type":"Point"}
}