{
  "type": "Feature",
  "properties": {
    "iso:country":"US",
    "sg:address":"139 Dixon Ave",
    "sg:city":"Amityville",
    "sg:classifiers":[
        {
            "category":"Autos & Motor Vehicles",
            "subcategory":"Auto Supplies",
            "type":"Retail Goods"
        }
    ],
    "sg:phone":"+1 631 789 3737",
    "sg:postcode":"11701",
    "sg:province":"NY",
    "sg:tags":[
        "material",
        "u"
    ],
    "wof:name":"Accurate Auto Salvage Inc",
    "wof:placetype":"venue"
},
  "geometry": {"coordinates":[-73.414523,40.684054],"type":"Point"}
}