{
  "type": "Feature",
  "properties": {
    "addr:full":"347 Freeman St Brooklyn NY 11222",
    "addr:housenumber":"347",
    "addr:postcode":"11222",
    "addr:street":"Freeman St",
    "iso:country":"US",
    "sg:address":"347 Freeman St",
    "sg:city":"Brooklyn",
    "sg:classifiers":[
        {
            "category":"Building & Trades",
            "subcategory":"Plumbing",
            "type":"Services"
        }
    ],
    "sg:phone":"+1 718 609 1430",
    "sg:postcode":"11222",
    "sg:province":"NY",
    "sg:tags":[
        "conditioning",
        "air",
        "system",
        "contractor"
    ],
    "wof:name":"Cde Air Conditioning",
    "wof:placetype":"venue"
},
  "geometry": {"coordinates":[-73.94992499999999,40.734936],"type":"Point"}
}