{
  "type": "Feature",
  "properties": {
    "iso:country":"US",
    "sg:address":"74 Mamaroneck Ave",
    "sg:city":"White Plains",
    "sg:classifiers":[
        {
            "category":"Deli",
            "type":"Food & Drink"
        }
    ],
    "sg:menulink":"http://www.allmenus.com/ny/white-plains/1714-blimpie-subs--sandwiches/menu/",
    "sg:phone":"+1 914 993 0533",
    "sg:postcode":"10601",
    "sg:province":"NY",
    "sg:tags":[
        "wrap",
        "american",
        "sandwich"
    ],
    "wof:name":"Blimpie Subs & Sandwiches",
    "wof:placetype":"venue"
},
  "geometry": {"coordinates":[-73.766006,41.030893],"type":"Point"}
}