{
  "type": "Feature",
  "properties": {
    "addr:full":"228 Jefferson St Albany NY 12210",
    "addr:housenumber":"228",
    "addr:postcode":"12210",
    "addr:street":"Jefferson St",
    "iso:country":"US",
    "sg:address":"228 Jefferson St",
    "sg:city":"Albany",
    "sg:classifiers":[
        {
            "category":"Bars & Pubs",
            "type":"Food & Drink"
        }
    ],
    "sg:phone":"+1   ",
    "sg:postcode":"12210",
    "sg:province":"NY",
    "sg:tags":[
        "drinking"
    ],
    "wof:name":"G & G Tavern",
    "wof:placetype":"venue"
},
  "geometry": {"coordinates":[-73.766913,42.651065],"type":"Point"}
}