{
  "type": "Feature",
  "properties": {
    "iso:country":"US",
    "sg:address":"220 N Peterboro St",
    "sg:city":"Canastota",
    "sg:classifiers":[
        {
            "category":"Education",
            "subcategory":"School",
            "type":"Public Place"
        }
    ],
    "sg:phone":"+1 315 697 2027",
    "sg:postcode":"13032",
    "sg:province":"NY",
    "wof:name":"Peterboro Street Primary Schl",
    "wof:placetype":"venue"
},
  "geometry": {"coordinates":[-75.750394,43.082039],"type":"Point"}
}