{
  "type": "Feature",
  "properties": {
    "addr:full":"53 Broadway Amityville NY 11701",
    "addr:housenumber":"53",
    "addr:postcode":"11701",
    "addr:street":"Broadway",
    "iso:country":"US",
    "sg:address":"53 Broadway",
    "sg:city":"Amityville",
    "sg:classifiers":[
        {
            "category":"Professional",
            "subcategory":"Lawyer & Legal Services",
            "type":"Services"
        }
    ],
    "sg:phone":"+1 631 264 0303",
    "sg:postcode":"11701",
    "sg:province":"NY",
    "sg:tags":[
        "attorney"
    ],
    "wof:name":"Van Nostrand & Martin",
    "wof:placetype":"venue"
},
  "geometry": {"coordinates":[-73.41623199999999,40.673745],"type":"Point"}
}