{
  "type": "Feature",
  "properties": {
    "iso:country":"US",
    "sg:address":"5551 Fitzgerald Rd",
    "sg:city":"Trumansburg",
    "sg:classifiers":[
        {
            "category":"Retail",
            "subcategory":"Auto Repair",
            "type":"Services"
        }
    ],
    "sg:phone":"+1   ",
    "sg:postcode":"14886",
    "sg:province":"NY",
    "sg:tags":[
        "general"
    ],
    "wof:name":"New 2 U Automotive",
    "wof:placetype":"venue"
},
  "geometry": {"coordinates":[-76.746602,42.441491],"type":"Point"}
}