{
  "type": "Feature",
  "properties": {
    "addr:full":"228 Lewis Ave Brooklyn NY 11221",
    "addr:housenumber":"228",
    "addr:postcode":"11221",
    "addr:street":"Lewis Ave",
    "iso:country":"US",
    "sg:address":"228 Lewis Ave",
    "sg:city":"Brooklyn",
    "sg:classifiers":[
        {
            "category":"Food & Beverages",
            "subcategory":"Groceries & Convenience Stores",
            "type":"Retail Goods"
        }
    ],
    "sg:phone":"+1 718 443 1645",
    "sg:postcode":"11221",
    "sg:province":"NY",
    "sg:tags":[
        "product"
    ],
    "wof:name":"Edward Food Corp",
    "wof:placetype":"venue"
},
  "geometry": {"coordinates":[-73.93631999999999,40.689354],"type":"Point"}
}