{
  "type": "Feature",
  "properties": {
    "addr:full":"748 Hudson River Rd Mechanicville NY 12118",
    "addr:housenumber":"748",
    "addr:postcode":"12118",
    "addr:street":"Hudson River Rd",
    "iso:country":"US",
    "sg:address":"748 Hudson River Rd",
    "sg:city":"Mechanicville",
    "sg:classifiers":[
        {
            "category":"Building & Trades",
            "subcategory":"Construction",
            "type":"Services"
        }
    ],
    "sg:phone":"+1 518 664 9484",
    "sg:postcode":"12118",
    "sg:province":"NY",
    "sg:tags":[
        "excavating",
        "contractor"
    ],
    "wof:name":"Troy Top Soil Co",
    "wof:placetype":"venue"
},
  "geometry": {"coordinates":[-73.67645,42.851308],"type":"Point"}
}