{
  "type": "Feature",
  "properties": {
    "iso:country":"US",
    "sg:address":"41 Lake St",
    "sg:city":"Owego",
    "sg:classifiers":[
        {
            "category":"Shopping",
            "type":"Retail Goods"
        }
    ],
    "sg:phone":"+1 607 687 2876",
    "sg:postcode":"13827",
    "sg:province":"NY",
    "sg:tags":[
        "craft",
        "instruction",
        "merchandise"
    ],
    "sg:website":"http://www.gallery41.com",
    "wof:name":"Gallery 41",
    "wof:placetype":"venue"
},
  "geometry": {"coordinates":[-76.261105,42.103068],"type":"Point"}
}