{
  "type": "Feature",
  "properties": {
    "addr:full":"18 E Montauk Hwy Hampton Bays NY 11946",
    "addr:housenumber":"18",
    "addr:postcode":"11946",
    "addr:street":"E Montauk Hwy",
    "iso:country":"US",
    "sg:address":"18 E Montauk Hwy",
    "sg:city":"Hampton Bays",
    "sg:classifiers":[
        {
            "category":"Banks & Credit Unions",
            "subcategory":"Bank",
            "type":"Services"
        }
    ],
    "sg:phone":"+1 631 728 3597",
    "sg:postcode":"11946",
    "sg:province":"NY",
    "sg:website":"www.hudsoncitysavingsbank.com",
    "wof:name":"Hudson City Savings Bank",
    "wof:placetype":"venue"
},
  "geometry": {"coordinates":[-72.52244,40.878441],"type":"Point"}
}