{
  "type": "Feature",
  "properties": {
    "addr:full":"1353 Baldwin Rd Yorktown Heights NY 10598",
    "addr:housenumber":"1353",
    "addr:postcode":"10598",
    "addr:street":"Baldwin Rd",
    "iso:country":"US",
    "sg:address":"1353 Baldwin Rd",
    "sg:city":"Yorktown Heights",
    "sg:classifiers":[
        {
            "category":"Building & Trades",
            "subcategory":"Construction",
            "type":"Services"
        }
    ],
    "sg:phone":"+1 914 245 7389",
    "sg:postcode":"10598",
    "sg:province":"NY",
    "sg:tags":[
        "house"
    ],
    "wof:name":"A & B Lab Installations Inc",
    "wof:placetype":"venue"
},
  "geometry": {"coordinates":[-73.81076,41.259063],"type":"Point"}
}