{
  "type": "Feature",
  "properties": {
    "addr:full":"102 Fairview Blvd Hempstead NY 11550",
    "addr:housenumber":"102",
    "addr:postcode":"11550",
    "addr:street":"Fairview Blvd",
    "iso:country":"US",
    "sg:address":"102 Fairview Blvd",
    "sg:city":"Hempstead",
    "sg:classifiers":[
        {
            "category":"Banks & Credit Unions",
            "subcategory":"Bank",
            "type":"Services"
        }
    ],
    "sg:phone":"+1 516 248 8050",
    "sg:postcode":"11550",
    "sg:province":"NY",
    "sg:tags":[
        "loan",
        "real estate"
    ],
    "wof:name":"Capital Growth Group Corp",
    "wof:placetype":"venue"
},
  "geometry": {"coordinates":[-73.60866,40.715697],"type":"Point"}
}