{
  "type": "Feature",
  "properties": {
    "addr:full":"920 E 7th St Brooklyn NY 11230",
    "addr:housenumber":"920",
    "addr:postcode":"11230",
    "addr:street":"E 7Th St",
    "iso:country":"US",
    "sg:address":"920 E 7th St",
    "sg:city":"Brooklyn",
    "sg:classifiers":[
        {
            "category":"Wholesale",
            "subcategory":"Stationery",
            "type":"Manufacturing & Wholesale Goods"
        }
    ],
    "sg:phone":"+1 718 788 0014",
    "sg:postcode":"11230",
    "sg:province":"NY",
    "sg:tags":[
        "computer",
        "supply"
    ],
    "wof:name":"Microtel International Inc",
    "wof:placetype":"venue"
},
  "geometry": {"coordinates":[-73.969978,40.628664],"type":"Point"}
}