{
  "type": "Feature",
  "properties": {
    "addr:full":"381 West Ave Lockport NY 14094",
    "addr:housenumber":"381",
    "addr:postcode":"14094",
    "addr:street":"West Ave",
    "iso:country":"US",
    "sg:address":"381 West Ave",
    "sg:city":"Lockport",
    "sg:classifiers":[
        {
            "category":"Retail",
            "subcategory":"Auto Repair",
            "type":"Services"
        }
    ],
    "sg:phone":"+1 716 433 2005",
    "sg:postcode":"14094",
    "sg:province":"NY",
    "sg:tags":[
        "transmission"
    ],
    "wof:name":"Lockport Transmissions",
    "wof:placetype":"venue"
},
  "geometry": {"coordinates":[-78.70824,43.167155],"type":"Point"}
}