{
  "type": "Feature",
  "properties": {
    "iso:country":"US",
    "sg:address":"938 S Broadway",
    "sg:city":"Hicksville",
    "sg:classifiers":[
        {
            "category":"Restaurant",
            "type":"Food & Drink"
        }
    ],
    "sg:phone":"+1 516 932 3780",
    "sg:postcode":"11801",
    "sg:province":"NY",
    "sg:tags":[
        "grill",
        "style",
        "bar",
        "american",
        "family"
    ],
    "sg:website":"http://www.applebees.com",
    "wof:name":"Applebee's",
    "wof:placetype":"venue"
},
  "geometry": {"coordinates":[-73.53395999999999,40.771623],"type":"Point"}
}