{
  "type": "Feature",
  "properties": {
    "addr:full":"46 E 61 St New York NY 10065",
    "addr:housenumber":"46;61",
    "addr:postcode":"10065",
    "addr:street":"E;St",
    "iso:country":"US",
    "sg:address":"46 E 61 St",
    "sg:city":"New York",
    "sg:classifiers":[
        {
            "category":"Shopping",
            "subcategory":"Clothing, Apparel, & Fashions",
            "type":"Retail Goods"
        }
    ],
    "sg:phone":"+1   ",
    "sg:postcode":"10065",
    "sg:province":"NY",
    "sg:tags":[
        "woven",
        "fabric"
    ],
    "wof:name":"Lora Piana USA  LLC",
    "wof:placetype":"venue"
},
  "geometry": {"coordinates":[-73.969211,40.764256],"type":"Point"}
}