{
  "type": "Feature",
  "properties": {
    "addr:full":"140 Main St Farmingdale NY 11735",
    "addr:housenumber":"140",
    "addr:postcode":"11735",
    "addr:street":"Main St",
    "iso:country":"US",
    "sg:address":"140 Main St",
    "sg:city":"Farmingdale",
    "sg:classifiers":[
        {
            "category":"Building & Trades",
            "subcategory":"Electrical",
            "type":"Services"
        }
    ],
    "sg:phone":"+1 631 577 1998",
    "sg:postcode":"11735",
    "sg:province":"NY",
    "wof:name":"Phase One Cable Inc",
    "wof:placetype":"venue"
},
  "geometry": {"coordinates":[-73.44598000000001,40.733042],"type":"Point"}
}