{
  "type": "Feature",
  "properties": {
    "iso:country":"US",
    "sg:address":"37-55 90th Street",
    "sg:city":"Queens",
    "sg:classifiers":[
        {
            "category":"Food & Beverages",
            "subcategory":"Liquor & Beverages",
            "type":"Retail Goods"
        }
    ],
    "sg:phone":"+1 718 429 7233",
    "sg:postcode":"11372",
    "sg:province":"NY",
    "sg:tags":[
        "beer",
        "spirit",
        "wine"
    ],
    "wof:name":"SM Wine & Liquors, Inc.",
    "wof:placetype":"venue"
},
  "geometry": {"coordinates":[-73.877729,40.755344],"type":"Point"}
}