{
  "type": "Feature",
  "properties": {
    "addr:full":"2566 Balltown Rd Schenectady NY 12309",
    "addr:housenumber":"2566",
    "addr:postcode":"12309",
    "addr:street":"Balltown Rd",
    "iso:country":"US",
    "sg:address":"2566 Balltown Rd",
    "sg:city":"Schenectady",
    "sg:classifiers":[
        {
            "category":"Social Services",
            "subcategory":"Child Care",
            "type":"Services"
        }
    ],
    "sg:phone":"+1 518 346 7751",
    "sg:postcode":"12309",
    "sg:province":"NY",
    "wof:name":"Kid's Time",
    "wof:placetype":"venue"
},
  "geometry": {"coordinates":[-73.891695,42.834468],"type":"Point"}
}