{
  "type": "Feature",
  "properties": {
    "addr:full":"2754 N Jerusalem Rd North Bellmore NY 11710",
    "addr:housenumber":"2754",
    "addr:postcode":"11710",
    "addr:street":"N Jerusalem Rd",
    "iso:country":"US",
    "sg:address":"2754 N Jerusalem Rd",
    "sg:city":"North Bellmore",
    "sg:classifiers":[
        {
            "category":"Restaurant",
            "type":"Food & Drink"
        }
    ],
    "sg:phone":"+1 516 679 4805",
    "sg:postcode":"11710",
    "sg:province":"NY",
    "sg:tags":[
        "italian"
    ],
    "sg:website":"www.elisasrestaurant.com/",
    "wof:name":"Elisa's Restaurant",
    "wof:placetype":"venue"
},
  "geometry": {"coordinates":[-73.532501,40.7062],"type":"Point"}
}