{
  "type": "Feature",
  "properties": {
    "addr:full":"145 West Rd Cortland NY 13045",
    "addr:housenumber":"145",
    "addr:postcode":"13045",
    "addr:street":"West Rd",
    "iso:country":"US",
    "sg:address":"145 West Rd",
    "sg:city":"Cortland",
    "sg:classifiers":[
        {
            "category":"Restaurant",
            "type":"Food & Drink"
        }
    ],
    "sg:phone":"+1   ",
    "sg:postcode":"13045",
    "sg:province":"NY",
    "sg:tags":[
        "eating"
    ],
    "wof:name":"Friendlys",
    "wof:placetype":"venue"
},
  "geometry": {"coordinates":[-76.21543,42.577785],"type":"Point"}
}