{
  "type": "Feature",
  "properties": {
    "addr:full":"710 Park Ave New York NY 10021",
    "addr:housenumber":"710",
    "addr:postcode":"10021",
    "addr:street":"Park Ave",
    "iso:country":"US",
    "sg:address":"710 Park Ave",
    "sg:city":"New York",
    "sg:classifiers":[
        {
            "category":"Health Services",
            "subcategory":"Doctor",
            "type":"Services"
        }
    ],
    "sg:phone":"+1 212 861 4715",
    "sg:postcode":"10021",
    "sg:province":"NY",
    "sg:tags":[
        "physician",
        "surgeon"
    ],
    "wof:name":"Robert Burger MD",
    "wof:placetype":"venue"
},
  "geometry": {"coordinates":[-73.965238,40.769169],"type":"Point"}
}