{
  "type": "Feature",
  "properties": {
    "addr:full":"691 9th Ave Manhattan NY 10036",
    "addr:housenumber":"691",
    "addr:postcode":"10036",
    "addr:street":"9Th Ave",
    "iso:country":"US",
    "sg:address":"691 9th Ave",
    "sg:city":"Manhattan",
    "sg:classifiers":[
        {
            "category":"Restaurant",
            "type":"Food & Drink"
        }
    ],
    "sg:phone":"+1 212 974 0300",
    "sg:postcode":"10036",
    "sg:province":"NY",
    "sg:tags":[
        "mediterranean"
    ],
    "sg:website":"balkanikany.com/",
    "wof:name":"Balkanika",
    "wof:placetype":"venue"
},
  "geometry": {"coordinates":[-73.990358,40.762056],"type":"Point"}
}