{
  "type": "Feature",
  "properties": {
    "addr:full":"655 3rd Avenue New York NY 10017",
    "addr:housenumber":"655",
    "addr:postcode":"10017",
    "addr:street":"3Rd Avenue",
    "iso:country":"US",
    "sg:address":"655 3rd Avenue",
    "sg:city":"New York",
    "sg:classifiers":[
        {
            "category":"Professional",
            "subcategory":"Accounting & Tax Preparation",
            "type":"Services"
        }
    ],
    "sg:phone":"+1 212 867 9630",
    "sg:postcode":"10017",
    "sg:province":"NY",
    "sg:tags":[
        "accountant"
    ],
    "wof:name":"Zalbe Ira M CPA",
    "wof:placetype":"venue"
},
  "geometry": {"coordinates":[-73.974397,40.750773],"type":"Point"}
}