{
  "type": "Feature",
  "properties": {
    "addr:full":"5 W 37th St New York NY 10018",
    "addr:housenumber":"5",
    "addr:postcode":"10018",
    "addr:street":"W 37Th St",
    "iso:country":"US",
    "sg:address":"5 W 37th St",
    "sg:city":"New York",
    "sg:classifiers":[
        {
            "category":"Professional",
            "subcategory":"Lawyer & Legal Services",
            "type":"Services"
        }
    ],
    "sg:phone":"+1 212 302 2001",
    "sg:postcode":"10018",
    "sg:province":"NY",
    "sg:tags":[
        "attorney"
    ],
    "wof:name":"Clifford Olshaker Law Office",
    "wof:placetype":"venue"
},
  "geometry": {"coordinates":[-73.986262,40.75171],"type":"Point"}
}