{
  "type": "Feature",
  "properties": {
    "iso:country":"US",
    "sg:address":"785 Walt Whitman Rd",
    "sg:city":"Melville",
    "sg:classifiers":[
        {
            "category":"Professional",
            "type":"Services"
        }
    ],
    "sg:phone":"+1 631 271 2776",
    "sg:postcode":"11747",
    "sg:province":"NY",
    "wof:name":"Express Mailing Svc",
    "wof:placetype":"venue"
},
  "geometry": {"coordinates":[-73.41234300000001,40.801342],"type":"Point"}
}