{
  "type": "Feature",
  "properties": {
    "addr:full":"243 E Main St Port Jervis NY 12771",
    "addr:housenumber":"243",
    "addr:postcode":"12771",
    "addr:street":"E Main St",
    "iso:country":"US",
    "sg:address":"243 E Main St",
    "sg:city":"Port Jervis",
    "sg:classifiers":[
        {
            "category":"Real Estate",
            "subcategory":"Real Estate Agent",
            "type":"Services"
        }
    ],
    "sg:phone":"+1 845 856 4492",
    "sg:postcode":"12771",
    "sg:province":"NY",
    "wof:name":"Era Meloi Realty",
    "wof:placetype":"venue"
},
  "geometry": {"coordinates":[-74.68573600000001,41.361867],"type":"Point"}
}