{
  "type": "Feature",
  "properties": {
    "iso:country":"US",
    "sg:address":"32 Mapes Rd",
    "sg:city":"Barryville",
    "sg:classifiers":[
        {
            "category":"Building & Trades",
            "subcategory":"Electrical",
            "type":"Services"
        }
    ],
    "sg:phone":"+1 845 557 6385",
    "sg:postcode":"12719",
    "sg:province":"NY",
    "sg:tags":[
        "electrician"
    ],
    "wof:name":"Pine Electric",
    "wof:placetype":"venue"
},
  "geometry": {"coordinates":[-74.876052,41.462441],"type":"Point"}
}