{
  "type": "Feature",
  "properties": {
    "addr:full":"8 River St Hoosick Falls NY 12090",
    "addr:housenumber":"8",
    "addr:postcode":"12090",
    "addr:street":"River St",
    "iso:country":"US",
    "sg:address":"8 River St",
    "sg:city":"Hoosick Falls",
    "sg:classifiers":[
        {
            "category":"Professional",
            "subcategory":"Business Services",
            "type":"Services"
        }
    ],
    "sg:phone":"+1   ",
    "sg:postcode":"12090",
    "sg:province":"NY",
    "wof:name":"Markers Octagon Realty",
    "wof:placetype":"venue"
},
  "geometry": {"coordinates":[-73.35226299999999,42.896626],"type":"Point"}
}