{
  "type": "Feature",
  "properties": {
    "iso:country":"US",
    "sg:address":"81 W Notre Dame St",
    "sg:city":"Glens Falls",
    "sg:classifiers":[
        {
            "category":"Retail",
            "subcategory":"Portrait Studio",
            "type":"Services"
        }
    ],
    "sg:phone":"+1 518 743 8891",
    "sg:postcode":"12801",
    "sg:province":"NY",
    "sg:tags":[
        "photographer"
    ],
    "wof:name":"James Appleyard Photography",
    "wof:placetype":"venue"
},
  "geometry": {"coordinates":[-73.654605,43.311454],"type":"Point"}
}