{
  "type": "Feature",
  "properties": {
    "addr:full":"176 Koenig Rd Tonawanda NY 14150",
    "addr:housenumber":"176",
    "addr:postcode":"14150",
    "addr:street":"Koenig Rd",
    "iso:country":"US",
    "sg:address":"176 Koenig Rd",
    "sg:city":"Tonawanda",
    "sg:classifiers":[
        {
            "category":"Shopping",
            "subcategory":"Used Merchandise",
            "type":"Retail Goods"
        }
    ],
    "sg:phone":"+1   ",
    "sg:postcode":"14150",
    "sg:province":"NY",
    "sg:tags":[
        "antique"
    ],
    "wof:name":"Mary Janes Antiques",
    "wof:placetype":"venue"
},
  "geometry": {"coordinates":[-78.82277000000001,43.001447],"type":"Point"}
}