{
  "type": "Feature",
  "properties": {
    "iso:country":"US",
    "sg:address":"7 Chatham Sq",
    "sg:city":"New York",
    "sg:classifiers":[
        {
            "category":"Health Services",
            "subcategory":"Doctor",
            "type":"Services"
        }
    ],
    "sg:phone":"+1 212 619 1141",
    "sg:postcode":"10038",
    "sg:province":"NY",
    "sg:tags":[
        "dentist"
    ],
    "wof:name":"Blount Nup & Chuang",
    "wof:placetype":"venue"
},
  "geometry": {"coordinates":[-73.997956,40.713794],"type":"Point"}
}