{
  "type": "Feature",
  "properties": {
    "addr:full":"150 Bridgeville Rd Monticello NY 12701",
    "addr:housenumber":"150",
    "addr:postcode":"12701",
    "addr:street":"Bridgeville Rd",
    "iso:country":"US",
    "sg:address":"150 Bridgeville Rd",
    "sg:city":"Monticello",
    "sg:classifiers":[
        {
            "category":"Building & Trades",
            "subcategory":"Equipment Rental",
            "type":"Services"
        }
    ],
    "sg:phone":"+1 845 794 0100",
    "sg:postcode":"12701",
    "sg:province":"NY",
    "sg:tags":[
        "store"
    ],
    "wof:name":"Rental Ctr of Monticello Inc",
    "wof:placetype":"venue"
},
  "geometry": {"coordinates":[-74.62769900000001,41.636548],"type":"Point"}
}