{
  "type": "Feature",
  "properties": {
    "iso:country":"US",
    "sg:address":"85 Elizabeth St",
    "sg:city":"New York",
    "sg:classifiers":[
        {
            "category":"Food & Beverages",
            "subcategory":"Specialty",
            "type":"Retail Goods"
        }
    ],
    "sg:phone":"+1 212 925 7105",
    "sg:postcode":"10013",
    "sg:province":"NY",
    "sg:tags":[
        "herb"
    ],
    "wof:name":"Elizabeth Herb Medicine Inc",
    "wof:placetype":"venue"
},
  "geometry": {"coordinates":[-73.99597199999999,40.718334],"type":"Point"}
}