{
  "type": "Feature",
  "properties": {
    "addr:full":"647 E 14 St New York NY 10009",
    "addr:housenumber":"647;14",
    "addr:postcode":"10009",
    "addr:street":"E",
    "iso:country":"US",
    "sg:address":"647 E 14 St",
    "sg:city":"New York",
    "sg:classifiers":[
        {
            "category":"Building & Trades",
            "subcategory":"Construction",
            "type":"Services"
        }
    ],
    "sg:phone":"+1 212 673 7770",
    "sg:postcode":"10009",
    "sg:province":"NY",
    "sg:tags":[
        "hanging",
        "contractor"
    ],
    "wof:name":"Onesource Facility Services",
    "wof:placetype":"venue"
},
  "geometry": {"coordinates":[-73.97648,40.728988],"type":"Point"}
}