{
  "type": "Feature",
  "properties": {
    "addr:full":"101 Gertrude St North Syracuse NY 13212",
    "addr:housenumber":"101",
    "addr:postcode":"13212",
    "addr:street":"Gertrude St",
    "iso:country":"US",
    "sg:address":"101 Gertrude St",
    "sg:city":"North Syracuse",
    "sg:classifiers":[
        {
            "category":"Manufacturing",
            "subcategory":"Signs",
            "type":"Manufacturing & Wholesale Goods"
        }
    ],
    "sg:phone":"+1 315 452 0308",
    "sg:postcode":"13212",
    "sg:province":"NY",
    "sg:tags":[
        "mfg"
    ],
    "wof:name":"North Syracuse Sign Co",
    "wof:placetype":"venue"
},
  "geometry": {"coordinates":[-76.12244099999999,43.138605],"type":"Point"}
}