{
  "type": "Feature",
  "properties": {
    "iso:country":"US",
    "sg:address":"3120 Bainbridge Ave Frnt 7 7 Frnt",
    "sg:city":"Bronx",
    "sg:phone":"+1 718 547 4655",
    "sg:postcode":"10467",
    "sg:province":"NY",
    "wof:name":"Uneeda Check Cashing Inc",
    "wof:placetype":"venue"
},
  "geometry": {"coordinates":[-73.87932499999999,40.874211],"type":"Point"}
}