{
  "type": "Feature",
  "properties": {
    "iso:country":"US",
    "sg:address":"30 Artist Dr",
    "sg:city":"Middle Island",
    "sg:classifiers":[
        {
            "category":"Travel",
            "subcategory":"Travel Agent",
            "type":"Entertainment"
        }
    ],
    "sg:phone":"+1   ",
    "sg:postcode":"11953",
    "sg:province":"NY",
    "sg:tags":[
        "operator",
        "tour"
    ],
    "wof:name":"Long Island Wine Tours",
    "wof:placetype":"venue"
},
  "geometry": {"coordinates":[-72.937173,40.887475],"type":"Point"}
}