{
  "type": "Feature",
  "properties": {
    "iso:country":"US",
    "sg:address":"43 Mason Ln",
    "sg:city":"Troy",
    "sg:classifiers":[
        {
            "category":"Government",
            "subcategory":"Fire Station",
            "type":"Public Place"
        }
    ],
    "sg:phone":"+1 518 663 9981",
    "sg:postcode":"12180",
    "sg:province":"NY",
    "sg:tags":[
        "department",
        "protection"
    ],
    "wof:name":"Raymertown Volunteer Fire Co",
    "wof:placetype":"venue"
},
  "geometry": {"coordinates":[-73.538038,42.812016],"type":"Point"}
}