{
  "type": "Feature",
  "properties": {
    "iso:country":"US",
    "sg:address":"8816 Niagara Falls Blvd",
    "sg:city":"Niagara Falls",
    "sg:classifiers":[
        {
            "category":"Real Estate",
            "subcategory":"Real Estate Operator",
            "type":"Services"
        }
    ],
    "sg:phone":"+1 716 297 4706",
    "sg:postcode":"14304",
    "sg:province":"NY",
    "wof:name":"Rose Garden Apartments",
    "wof:placetype":"venue"
},
  "geometry": {"coordinates":[-78.961259,43.092383],"type":"Point"}
}