{
  "type": "Feature",
  "properties": {
    "addr:full":"193 Calebs Path Central Islip NY 11722",
    "addr:housenumber":"193",
    "addr:postcode":"11722",
    "addr:street":"Calebs Path",
    "iso:country":"US",
    "sg:address":"193 Calebs Path",
    "sg:city":"Central Islip",
    "sg:classifiers":[
        {
            "category":"Food & Beverages",
            "subcategory":"Groceries & Convenience Stores",
            "type":"Retail Goods"
        }
    ],
    "sg:phone":"+1   ",
    "sg:postcode":"11722",
    "sg:province":"NY",
    "sg:website":"www.7-eleven.com",
    "wof:name":"7-Eleven",
    "wof:placetype":"venue"
},
  "geometry": {"coordinates":[-73.228685,40.80036],"type":"Point"}
}