{
  "type": "Feature",
  "properties": {
    "iso:country":"US",
    "sg:address":"2365 Crotona Ave",
    "sg:city":"Bronx",
    "sg:classifiers":[
        {
            "category":"Professional",
            "subcategory":"Business Services",
            "type":"Services"
        }
    ],
    "sg:phone":"+1 718 733 8815",
    "sg:postcode":"10458",
    "sg:province":"NY",
    "sg:tags":[
        "communications",
        "retail",
        "music",
        "cellular"
    ],
    "wof:name":"Deep Within Music",
    "wof:placetype":"venue"
},
  "geometry": {"coordinates":[-73.884261,40.852463],"type":"Point"}
}