{
  "type": "Feature",
  "properties": {
    "iso:country":"US",
    "sg:address":"206 Huston St",
    "sg:city":"Schenectady",
    "sg:classifiers":[
        {
            "category":"Shopping",
            "subcategory":"Computers & Home Electronics",
            "type":"Retail Goods"
        }
    ],
    "sg:phone":"+1   ",
    "sg:postcode":"12302",
    "sg:province":"NY",
    "wof:name":"Hunter Electronics",
    "wof:placetype":"venue"
},
  "geometry": {"coordinates":[-73.964009,42.831897],"type":"Point"}
}