{
  "type": "Feature",
  "properties": {
    "addr:full":"975 Jerusalem Ave Uniondale NY 11553",
    "addr:housenumber":"975",
    "addr:postcode":"11553",
    "addr:street":"Jerusalem Ave",
    "iso:country":"US",
    "sg:address":"975 Jerusalem Ave",
    "sg:city":"Uniondale",
    "sg:classifiers":[
        {
            "category":"Education",
            "subcategory":"School",
            "type":"Public Place"
        }
    ],
    "sg:phone":"+1 516 486 3505",
    "sg:postcode":"11553",
    "sg:province":"NY",
    "sg:tags":[
        "high",
        "middle",
        "elementary"
    ],
    "wof:name":"Uniondale School District",
    "wof:placetype":"venue"
},
  "geometry": {"coordinates":[-73.582787,40.695899],"type":"Point"}
}