{
  "type": "Feature",
  "properties": {
    "addr:full":"32 Fostertown Rd Newburgh NY 12550",
    "addr:housenumber":"32",
    "addr:postcode":"12550",
    "addr:street":"Fostertown Rd",
    "iso:country":"US",
    "sg:address":"32 Fostertown Rd",
    "sg:city":"Newburgh",
    "sg:classifiers":[
        {
            "category":"Professional",
            "subcategory":"Accounting & Tax Preparation",
            "type":"Services"
        }
    ],
    "sg:phone":"+1 845 565 5400",
    "sg:postcode":"12550",
    "sg:province":"NY",
    "sg:tags":[
        "accountant"
    ],
    "sg:website":"www.stanleymarksllp.com",
    "wof:name":"Marks Stanley & Co",
    "wof:placetype":"venue"
},
  "geometry": {"coordinates":[-74.015297,41.535301],"type":"Point"}
}