{
  "type": "Feature",
  "properties": {
    "addr:full":"621 Aero Dr Buffalo NY 14225",
    "addr:housenumber":"621",
    "addr:postcode":"14225",
    "addr:street":"Aero Dr",
    "iso:country":"US",
    "sg:address":"621 Aero Dr",
    "sg:city":"Buffalo",
    "sg:classifiers":[
        {
            "category":"Building & Trades",
            "subcategory":"Construction",
            "type":"Services"
        }
    ],
    "sg:phone":"+1 716 634 2221",
    "sg:postcode":"14225",
    "sg:province":"NY",
    "sg:tags":[
        "bridges",
        "street",
        "paving",
        "highway",
        "contractor"
    ],
    "wof:name":"Omer Construction Co Inc",
    "wof:placetype":"venue"
},
  "geometry": {"coordinates":[-78.717714,42.940854],"type":"Point"}
}