{
  "type": "Feature",
  "properties": {
    "addr:full":"333 Union Ave Lynbrook NY 11563",
    "addr:housenumber":"333",
    "addr:postcode":"11563",
    "addr:street":"Union Ave",
    "iso:country":"US",
    "sg:address":"333 Union Ave",
    "sg:city":"Lynbrook",
    "sg:classifiers":[
        {
            "category":"Organizations",
            "subcategory":"Non-profit Organization",
            "type":"Services"
        }
    ],
    "sg:phone":"+1 516 593 1929",
    "sg:postcode":"11563",
    "sg:province":"NY",
    "wof:name":"Lynbrook Teachers Assn",
    "wof:placetype":"venue"
},
  "geometry": {"coordinates":[-73.681151,40.644766],"type":"Point"}
}