{
  "type": "Feature",
  "properties": {
    "addr:full":"52 W 56th St New York NY 10019",
    "addr:housenumber":"52",
    "addr:postcode":"10019",
    "addr:street":"W 56Th St",
    "iso:country":"US",
    "sg:address":"52 W 56th St",
    "sg:city":"New York",
    "sg:classifiers":[
        {
            "category":"Shopping",
            "subcategory":"Florist",
            "type":"Retail Goods"
        }
    ],
    "sg:phone":"+1 212 582 3680",
    "sg:postcode":"10019",
    "sg:province":"NY",
    "wof:name":"Sheilds & Warendorff",
    "wof:placetype":"venue"
},
  "geometry": {"coordinates":[-73.976856,40.763278],"type":"Point"}
}