{
  "type": "Feature",
  "properties": {
    "iso:country":"US",
    "sg:address":"792 E 2nd St",
    "sg:city":"Jamestown",
    "sg:classifiers":[
        {
            "category":"Taxi",
            "type":"Transportation"
        }
    ],
    "sg:phone":"+1   ",
    "sg:postcode":"14701",
    "sg:province":"NY",
    "sg:tags":[
        "taxicab"
    ],
    "wof:name":"Rainbow Cab",
    "wof:placetype":"venue"
},
  "geometry": {"coordinates":[-79.228301,42.102051],"type":"Point"}
}