{
  "type": "Feature",
  "properties": {
    "addr:full":"257 W Kingsbridge Rd Bronx NY 10463",
    "addr:housenumber":"257",
    "addr:postcode":"10463",
    "addr:street":"W Kingsbridge Rd",
    "iso:country":"US",
    "sg:address":"257 W Kingsbridge Rd",
    "sg:city":"Bronx",
    "sg:classifiers":[
        {
            "category":"Real Estate",
            "subcategory":"Real Estate Agent",
            "type":"Services"
        }
    ],
    "sg:phone":"+1 718 543 6801",
    "sg:postcode":"10463",
    "sg:province":"NY",
    "wof:name":"Exclusive Realty & Brokerage",
    "wof:placetype":"venue"
},
  "geometry": {"coordinates":[-73.90550399999999,40.87309],"type":"Point"}
}