{
  "type": "Feature",
  "properties": {
    "addr:full":"1158 Fairport Rd Fairport NY 14450",
    "addr:housenumber":"1158",
    "addr:postcode":"14450",
    "addr:street":"Fairport Rd",
    "iso:country":"US",
    "sg:address":"1158 Fairport Rd",
    "sg:city":"Fairport",
    "sg:classifiers":[
        {
            "category":"Shopping",
            "subcategory":"Clothing, Apparel, & Fashions",
            "type":"Retail Goods"
        }
    ],
    "sg:phone":"+1 585 586 0430",
    "sg:postcode":"14450",
    "sg:province":"NY",
    "sg:tags":[
        "tailor"
    ],
    "wof:name":"Tailored To AT",
    "wof:placetype":"venue"
},
  "geometry": {"coordinates":[-77.466981,43.102333],"type":"Point"}
}