{
  "type": "Feature",
  "properties": {
    "iso:country":"US",
    "sg:address":"101 Pondfield Rd",
    "sg:city":"Bronxville",
    "sg:classifiers":[
        {
            "category":"Shopping",
            "subcategory":"Shoes",
            "type":"Retail Goods"
        }
    ],
    "sg:phone":"+1 914 793 1403",
    "sg:postcode":"10708",
    "sg:province":"NY",
    "wof:name":"Plaza Bootery",
    "wof:placetype":"venue"
},
  "geometry": {"coordinates":[-73.83273199999999,40.939316],"type":"Point"}
}