{
  "type": "Feature",
  "properties": {
    "addr:full":"660 Fox St Bronx NY 10455",
    "addr:housenumber":"660",
    "addr:postcode":"10455",
    "addr:street":"Fox St",
    "iso:country":"US",
    "sg:address":"660 Fox St",
    "sg:city":"Bronx",
    "sg:classifiers":[
        {
            "category":"Social Services",
            "type":"Services"
        }
    ],
    "sg:phone":"+1 718 585 1093",
    "sg:postcode":"10455",
    "sg:province":"NY",
    "sg:tags":[
        "youth",
        "organization",
        "center"
    ],
    "wof:name":"Pathways For Youth",
    "wof:placetype":"venue"
},
  "geometry": {"coordinates":[-73.900676,40.813855],"type":"Point"}
}