{
  "type": "Feature",
  "properties": {
    "iso:country":"US",
    "sg:address":"52 E 53rd Street",
    "sg:city":"New York",
    "sg:classifiers":[
        {
            "category":"Wholesale",
            "subcategory":"Stationery",
            "type":"Manufacturing & Wholesale Goods"
        }
    ],
    "sg:phone":"+1 212 223 0633",
    "sg:postcode":"10022",
    "sg:province":"NY",
    "sg:tags":[
        "card"
    ],
    "wof:name":"American Greeting Card Shop",
    "wof:placetype":"venue"
},
  "geometry": {"coordinates":[-73.973748,40.759409],"type":"Point"}
}