{
  "type": "Feature",
  "properties": {
    "addr:full":"111 3 Ave New York NY 10003",
    "addr:housenumber":"111",
    "addr:postcode":"10003",
    "addr:street":"3 Ave",
    "iso:country":"US",
    "sg:address":"111 3 Ave",
    "sg:city":"New York",
    "sg:classifiers":[
        {
            "category":"Retail",
            "subcategory":"Auto Repair",
            "type":"Services"
        }
    ],
    "sg:phone":"+1 212 348 7264",
    "sg:postcode":"10003",
    "sg:province":"NY",
    "sg:tags":[
        "repairing",
        "automobile"
    ],
    "wof:name":"City Wide Auto Repair Shop",
    "wof:placetype":"venue"
},
  "geometry": {"coordinates":[-73.989634,40.729761],"type":"Point"}
}