{
  "type": "Feature",
  "properties": {
    "iso:country":"US",
    "sg:address":"55 Pondfield Rd",
    "sg:city":"Bronxville",
    "sg:classifiers":[
        {
            "category":"Professional",
            "subcategory":"Lawyer & Legal Services",
            "type":"Services"
        }
    ],
    "sg:phone":"+1   ",
    "sg:postcode":"10708",
    "sg:province":"NY",
    "wof:name":"Stanley Tomkiel III",
    "wof:placetype":"venue"
},
  "geometry": {"coordinates":[-73.83364899999999,40.940878],"type":"Point"}
}