{
  "type": "Feature",
  "properties": {
    "addr:full":"70 Country Village Ln New Hyde Park NY 11040",
    "addr:housenumber":"70",
    "addr:postcode":"11040",
    "addr:street":"Country Village Ln",
    "iso:country":"US",
    "sg:address":"70 Country Village Ln",
    "sg:city":"New Hyde Park",
    "sg:classifiers":[
        {
            "category":"Communications",
            "subcategory":"Film & Video Production",
            "type":"Services"
        }
    ],
    "sg:phone":"+1   ",
    "sg:postcode":"11040",
    "sg:province":"NY",
    "sg:tags":[
        "motion"
    ],
    "wof:name":"Wershba Productions",
    "wof:placetype":"venue"
},
  "geometry": {"coordinates":[-73.68266,40.756788],"type":"Point"}
}