{
  "type": "Feature",
  "properties": {
    "addr:full":"1880 Central Park Ave Yonkers NY 10710",
    "addr:housenumber":"1880",
    "addr:postcode":"10710",
    "addr:street":"Central Park Ave",
    "iso:country":"US",
    "sg:address":"1880 Central Park Ave",
    "sg:city":"Yonkers",
    "sg:classifiers":[
        {
            "category":"Home & Garden",
            "subcategory":"Furniture",
            "type":"Retail Goods"
        }
    ],
    "sg:phone":"+1 914 779 1000",
    "sg:postcode":"10710",
    "sg:province":"NY",
    "sg:tags":[
        "equipment",
        "kitchen",
        "cabinet"
    ],
    "wof:name":"Quaker Maid Kitchens",
    "wof:placetype":"venue"
},
  "geometry": {"coordinates":[-73.83893500000001,40.964542],"type":"Point"}
}