{
  "type": "Feature",
  "properties": {
    "iso:country":"US",
    "sg:address":"310 Lake Ave",
    "sg:city":"Blasdell",
    "sg:classifiers":[
        {
            "category":"Freight",
            "type":"Transportation"
        }
    ],
    "sg:phone":"+1 716 828 1650",
    "sg:postcode":"14219",
    "sg:province":"NY",
    "sg:tags":[
        "trucking"
    ],
    "wof:name":"Spearhead Transportation Svc",
    "wof:placetype":"venue"
},
  "geometry": {"coordinates":[-78.841323,42.797836],"type":"Point"}
}