{
  "type": "Feature",
  "properties": {
    "addr:full":"460 Brielle Ave Staten Island NY 10314",
    "addr:housenumber":"460",
    "addr:postcode":"10314",
    "addr:street":"Brielle Ave",
    "iso:country":"US",
    "sg:address":"460 Brielle Ave",
    "sg:city":"Staten Island",
    "sg:classifiers":[
        {
            "category":"Social Services",
            "type":"Services"
        }
    ],
    "sg:phone":"+1 718 980 5043",
    "sg:postcode":"10314",
    "sg:province":"NY",
    "sg:tags":[
        "youth",
        "organization",
        "center"
    ],
    "sg:website":"www.scouting.org",
    "wof:name":"Boy Scouts Of America",
    "wof:placetype":"venue"
},
  "geometry": {"coordinates":[-74.138497,40.589314],"type":"Point"}
}