{
  "type": "Feature",
  "properties": {
    "addr:full":"Limelight Marketplace 656 Ave of the Americas Manhattan NY 10011",
    "addr:housenumber":"656",
    "addr:postcode":"10011",
    "addr:street":"Ave Of The Americas",
    "iso:country":"US",
    "sg:address":"Limelight Marketplace 656 Ave of the Americas",
    "sg:city":"Manhattan",
    "sg:classifiers":[
        {
            "category":"Food & Beverages",
            "subcategory":"Candy",
            "type":"Retail Goods"
        }
    ],
    "sg:postcode":"10011",
    "sg:province":"NY",
    "sg:tags":[
        "dessert"
    ],
    "wof:name":"Mariebelle Cacao Bar & Cafe",
    "wof:placetype":"venue"
},
  "geometry": {"coordinates":[-73.993768,40.741265],"type":"Point"}
}