{
  "type": "Feature",
  "properties": {
    "addr:full":"209 E 49th St New York NY 10017",
    "addr:housenumber":"209",
    "addr:postcode":"10017",
    "addr:street":"E 49Th St",
    "iso:country":"US",
    "sg:address":"209 E 49th St",
    "sg:city":"New York",
    "sg:classifiers":[
        {
            "category":"Restaurant",
            "type":"Food & Drink"
        }
    ],
    "sg:phone":"+1 212 751 4545",
    "sg:postcode":"10017",
    "sg:province":"NY",
    "sg:tags":[
        "american",
        "latin",
        "mexican"
    ],
    "sg:website":"www.modernmexican.com",
    "wof:name":"Pampano",
    "wof:placetype":"venue"
},
  "geometry": {"coordinates":[-73.97069999999999,40.754998],"type":"Point"}
}