{
  "type": "Feature",
  "properties": {
    "addr:full":"35 Harwood Ct Scarsdale NY 10583",
    "addr:housenumber":"35",
    "addr:postcode":"10583",
    "addr:street":"Harwood Ct",
    "iso:country":"US",
    "sg:address":"35 Harwood Ct",
    "sg:city":"Scarsdale",
    "sg:classifiers":[
        {
            "category":"Shopping",
            "subcategory":"Jewelry",
            "type":"Retail Goods"
        }
    ],
    "sg:phone":"+1 914 472 5788",
    "sg:postcode":"10583",
    "sg:province":"NY",
    "sg:tags":[
        "jeweler"
    ],
    "wof:name":"Pazzam Jewelry Designs LTD",
    "wof:placetype":"venue"
},
  "geometry": {"coordinates":[-73.807288,40.988963],"type":"Point"}
}