{
  "type": "Feature",
  "properties": {
    "addr:full":"86 Emjay Blvd Brentwood NY 11717",
    "addr:housenumber":"86",
    "addr:postcode":"11717",
    "addr:street":"Emjay Blvd",
    "iso:country":"US",
    "sg:address":"86 Emjay Blvd",
    "sg:city":"Brentwood",
    "sg:classifiers":[
        {
            "category":"Manufacturing",
            "subcategory":"Paper Products",
            "type":"Manufacturing & Wholesale Goods"
        }
    ],
    "sg:phone":"+1 631 273 1700",
    "sg:postcode":"11717",
    "sg:province":"NY",
    "sg:tags":[
        "converter"
    ],
    "sg:website":"www.ajmpack.com",
    "wof:name":"AJM Packaging",
    "wof:placetype":"venue"
},
  "geometry": {"coordinates":[-73.27477,40.777888],"type":"Point"}
}