{
  "type": "Feature",
  "properties": {
    "addr:full":"1829 Maple Rd Buffalo NY 14221",
    "addr:housenumber":"1829",
    "addr:postcode":"14221",
    "addr:street":"Maple Rd",
    "iso:country":"US",
    "sg:address":"1829 Maple Rd",
    "sg:city":"Buffalo",
    "sg:classifiers":[
        {
            "category":"Professional",
            "subcategory":"Computer Services",
            "type":"Services"
        }
    ],
    "sg:phone":"+1 716 626 6363",
    "sg:postcode":"14221",
    "sg:province":"NY",
    "sg:tags":[
        "isp",
        "provider",
        "internet"
    ],
    "sg:website":"http://www.shopusa.com",
    "wof:name":"Shopusa Inc",
    "wof:placetype":"venue"
},
  "geometry": {"coordinates":[-78.719234,42.991037],"type":"Point"}
}