{
  "type": "Feature",
  "properties": {
    "addr:full":"14 Beach Rd Great Neck NY 11023",
    "addr:housenumber":"14",
    "addr:postcode":"11023",
    "addr:street":"Beach Rd",
    "iso:country":"US",
    "sg:address":"14 Beach Rd",
    "sg:city":"Great Neck",
    "sg:classifiers":[
        {
            "category":"Professional",
            "type":"Services"
        }
    ],
    "sg:phone":"+1   ",
    "sg:postcode":"11023",
    "sg:province":"NY",
    "wof:name":"Continental Processing Inc",
    "wof:placetype":"venue"
},
  "geometry": {"coordinates":[-73.737889,40.803512],"type":"Point"}
}