{
  "type": "Feature",
  "properties": {
    "addr:full":"1599 E Gun Hill Rd Bronx NY 10469",
    "addr:housenumber":"1599",
    "addr:postcode":"10469",
    "addr:street":"E Gun Hill Rd",
    "iso:country":"US",
    "sg:address":"1599 E Gun Hill Rd",
    "sg:city":"Bronx",
    "sg:classifiers":[
        {
            "category":"Professional",
            "subcategory":"Lawyer & Legal Services",
            "type":"Services"
        }
    ],
    "sg:phone":"+1 718 379 3500",
    "sg:postcode":"10469",
    "sg:province":"NY",
    "sg:website":"www.maduedozie.com",
    "wof:name":"Madu Edozie & Madu PC",
    "wof:placetype":"venue"
},
  "geometry": {"coordinates":[-73.838876,40.866899],"type":"Point"}
}