{
  "type": "Feature",
  "properties": {
    "addr:full":"1502 8th Ave Brooklyn NY 11215",
    "addr:housenumber":"1502",
    "addr:postcode":"11215",
    "addr:street":"8Th Ave",
    "iso:country":"US",
    "sg:address":"1502 8th Ave",
    "sg:city":"Brooklyn",
    "sg:classifiers":[
        {
            "category":"Personal",
            "type":"Services"
        }
    ],
    "sg:phone":"+1 718 768 7611",
    "sg:postcode":"11215",
    "sg:province":"NY",
    "sg:tags":[
        "sewing",
        "alteration"
    ],
    "wof:name":"Jack's Custom Tailoring & Alteration",
    "wof:placetype":"venue"
},
  "geometry": {"coordinates":[-73.9823,40.6619],"type":"Point"}
}