{
  "type": "Feature",
  "properties": {
    "iso:country":"US",
    "sg:address":"517 Uniondale Ave",
    "sg:city":"Uniondale",
    "sg:classifiers":[
        {
            "category":"Organizations",
            "subcategory":"Religious Organization",
            "type":"Services"
        }
    ],
    "sg:phone":"+1 516 214 6317",
    "sg:postcode":"11553",
    "sg:province":"NY",
    "wof:name":"Casa De Oracion",
    "wof:placetype":"venue"
},
  "geometry": {"coordinates":[-73.59273899999999,40.702311],"type":"Point"}
}