{
  "type": "Feature",
  "properties": {
    "iso:country":"US",
    "sg:address":"3000 Ocean Pkwy",
    "sg:city":"Brooklyn",
    "sg:classifiers":[
        {
            "category":"Health Services",
            "subcategory":"Podiatrist",
            "type":"Services"
        }
    ],
    "sg:phone":"+1 718 265 2600",
    "sg:postcode":"11235",
    "sg:province":"NY",
    "wof:name":"Bruce R Greenbaum DPM",
    "wof:placetype":"venue"
},
  "geometry": {"coordinates":[-73.968486,40.57702],"type":"Point"}
}