{
  "type": "Feature",
  "properties": {
    "addr:full":"92 Wahl Ave Inwood NY 11096",
    "addr:housenumber":"92",
    "addr:postcode":"11096",
    "addr:street":"Wahl Ave",
    "iso:country":"US",
    "sg:address":"92 Wahl Ave",
    "sg:city":"Inwood",
    "sg:classifiers":[
        {
            "category":"Retail",
            "subcategory":"Funeral Services",
            "type":"Services"
        }
    ],
    "sg:phone":"+1 718 471 2828",
    "sg:postcode":"11096",
    "sg:province":"NY",
    "sg:tags":[
        "director"
    ],
    "wof:name":"Gaffney's Jeremian C Funeral",
    "wof:placetype":"venue"
},
  "geometry": {"coordinates":[-73.74444200000001,40.618669],"type":"Point"}
}