{
  "type": "Feature",
  "properties": {
    "addr:full":"1206 Kings Hwy Brooklyn NY 11229",
    "addr:housenumber":"1206",
    "addr:postcode":"11229",
    "addr:street":"Kings Hwy",
    "iso:country":"US",
    "sg:address":"1206 Kings Hwy",
    "sg:city":"Brooklyn",
    "sg:classifiers":[
        {
            "category":"Health Services",
            "subcategory":"Dentist",
            "type":"Services"
        }
    ],
    "sg:phone":"+1 718 998 5111",
    "sg:postcode":"11229",
    "sg:province":"NY",
    "sg:website":"www.rightdentist.com",
    "wof:name":"Trachtenberg Michelle Dr DDS",
    "wof:placetype":"venue"
},
  "geometry": {"coordinates":[-73.960649,40.607671],"type":"Point"}
}