{
  "type": "Feature",
  "properties": {
    "addr:full":"431 Bridge St Newark Valley NY 13811",
    "addr:housenumber":"431",
    "addr:postcode":"13811",
    "addr:street":"Bridge St",
    "iso:country":"US",
    "sg:address":"431 Bridge St",
    "sg:city":"Newark Valley",
    "sg:classifiers":[
        {
            "category":"Farming",
            "subcategory":"Dairy Farm",
            "type":"Manufacturing & Wholesale Goods"
        }
    ],
    "sg:phone":"+1 607 642 8169",
    "sg:postcode":"13811",
    "sg:province":"NY",
    "wof:name":"Dairy Farmers of America",
    "wof:placetype":"venue"
},
  "geometry": {"coordinates":[-76.19767299999999,42.213642],"type":"Point"}
}