{
  "type": "Feature",
  "properties": {
    "addr:full":"3890 Merrick Rd Seaford NY 11783",
    "addr:housenumber":"3890",
    "addr:postcode":"11783",
    "addr:street":"Merrick Rd",
    "iso:country":"US",
    "sg:address":"3890 Merrick Rd",
    "sg:city":"Seaford",
    "sg:classifiers":[
        {
            "category":"Banks & Credit Unions",
            "subcategory":"Bank",
            "type":"Services"
        },
        {
            "category":"Banks & Credit Unions",
            "subcategory":"Financial Services",
            "type":"Services"
        }
    ],
    "sg:phone":"+1 516 783 0426",
    "sg:postcode":"11783",
    "sg:province":"NY",
    "sg:tags":[
        "saving",
        "loan",
        "commercial"
    ],
    "sg:website":"https://www.chase.com/",
    "wof:name":"CHASE Bank",
    "wof:placetype":"venue"
},
  "geometry": {"coordinates":[-73.487285,40.666059],"type":"Point"}
}