{
  "type": "Feature",
  "properties": {
    "iso:country":"US",
    "sg:address":"199 Newtown Rd",
    "sg:city":"Plainview",
    "sg:classifiers":[
        {
            "category":"Freight",
            "type":"Transportation"
        }
    ],
    "sg:phone":"+1   ",
    "sg:postcode":"11803",
    "sg:province":"NY",
    "sg:tags":[
        "carrier"
    ],
    "wof:name":"Tropical Express USA Inc",
    "wof:placetype":"venue"
},
  "geometry": {"coordinates":[-73.45164800000001,40.784731],"type":"Point"}
}