{
  "type": "Feature",
  "properties": {
    "addr:full":"165 10th Street Staten Island NY 10306",
    "addr:housenumber":"165",
    "addr:postcode":"10306",
    "addr:street":"10Th Street",
    "iso:country":"US",
    "sg:address":"165 10th Street",
    "sg:city":"Staten Island",
    "sg:classifiers":[
        {
            "category":"Building & Trades",
            "subcategory":"Pest Control",
            "type":"Services"
        }
    ],
    "sg:phone":"+1 718 667 9526",
    "sg:postcode":"10306",
    "sg:province":"NY",
    "sg:website":"www.tandtpestcontrol.com",
    "wof:name":"T and T Pest Control",
    "wof:placetype":"venue"
},
  "geometry": {"coordinates":[-74.11743199999999,40.569026],"type":"Point"}
}