{
  "type": "Feature",
  "properties": {
    "addr:full":"19 Buffalo St Hamburg NY 14075",
    "addr:housenumber":"19",
    "addr:postcode":"14075",
    "addr:street":"Buffalo St",
    "iso:country":"US",
    "sg:address":"19 Buffalo St",
    "sg:city":"Hamburg",
    "sg:classifiers":[
        {
            "category":"Shopping",
            "subcategory":"Jewelry",
            "type":"Retail Goods"
        }
    ],
    "sg:phone":"+1   ",
    "sg:postcode":"14075",
    "sg:province":"NY",
    "wof:name":"Silver Renaissance Jewelry",
    "wof:placetype":"venue"
},
  "geometry": {"coordinates":[-78.829255,42.716975],"type":"Point"}
}