{
  "type": "Feature",
  "properties": {
    "addr:full":"9402 Main St Dansville NY 14437",
    "addr:housenumber":"9402",
    "addr:postcode":"14437",
    "addr:street":"Main St",
    "iso:country":"US",
    "sg:address":"9402 Main St",
    "sg:city":"Dansville",
    "sg:classifiers":[
        {
            "category":"Autos & Motor Vehicles",
            "subcategory":"Auto Supplies",
            "type":"Retail Goods"
        },
        {
            "category":"Wholesale",
            "subcategory":"Electrical",
            "type":"Manufacturing & Wholesale Goods"
        },
        {
            "category":"Wholesale",
            "subcategory":"Auto Parts",
            "type":"Manufacturing & Wholesale Goods"
        }
    ],
    "sg:phone":"+1 585 335 6200",
    "sg:postcode":"14437",
    "sg:province":"NY",
    "sg:tags":[
        "battery",
        "automobile",
        "accessory",
        "equipment",
        "truck",
        "engines-supplies"
    ],
    "sg:website":"http://ad.doubleclick.net/clk;221862232;45455595;j?http://www.carquest.com/carquest/store_locator.html",
    "wof:name":"CARQUEST Auto Parts",
    "wof:placetype":"venue"
},
  "geometry": {"coordinates":[-77.683903,42.549637],"type":"Point"}
}