{
  "type": "Feature",
  "properties": {
    "addr:full":"4709 Crossroads Park Dr Liverpool NY 13088",
    "addr:housenumber":"4709",
    "addr:postcode":"13088",
    "addr:street":"Crossroads Park Dr",
    "iso:country":"US",
    "sg:address":"4709 Crossroads Park Dr",
    "sg:city":"Liverpool",
    "sg:classifiers":[
        {
            "category":"Health Services",
            "subcategory":"Health Practitioner",
            "type":"Services"
        }
    ],
    "sg:phone":"+1 315 461 0456",
    "sg:postcode":"13088",
    "sg:province":"NY",
    "sg:tags":[
        "occupational",
        "safety"
    ],
    "sg:website":"www.hinseminars.com",
    "wof:name":"Healthcare Information Network",
    "wof:placetype":"venue"
},
  "geometry": {"coordinates":[-76.189183,43.121431],"type":"Point"}
}