{
  "type": "Feature",
  "properties": {
    "iso:country":"US",
    "sg:address":"1 Candlelight Ct",
    "sg:city":"Clifton Park",
    "sg:classifiers":[
        {
            "category":"Building & Trades",
            "subcategory":"Construction",
            "type":"Services"
        }
    ],
    "sg:phone":"+1 518 373 9939",
    "sg:postcode":"12065",
    "sg:province":"NY",
    "sg:tags":[
        "contractor"
    ],
    "wof:name":"Puckett & Sons Contractor",
    "wof:placetype":"venue"
},
  "geometry": {"coordinates":[-73.768833,42.852393],"type":"Point"}
}