{
  "type": "Feature",
  "properties": {
    "iso:country":"US",
    "sg:address":"89 Wolfs Ln",
    "sg:city":"Pelham",
    "sg:classifiers":[
        {
            "category":"Organizations",
            "subcategory":"Professional Association",
            "type":"Services"
        }
    ],
    "sg:phone":"+1 914 738 7380",
    "sg:postcode":"10803",
    "sg:province":"NY",
    "sg:tags":[
        "business",
        "trade"
    ],
    "wof:name":"Pelham Chamber Of Commerce Inc",
    "wof:placetype":"venue"
},
  "geometry": {"coordinates":[-73.811027,40.908865],"type":"Point"}
}