{
  "type": "Feature",
  "properties": {
    "addr:full":"1335 Lexington Ave New York NY 10128",
    "addr:housenumber":"1335",
    "addr:postcode":"10128",
    "addr:street":"Lexington Ave",
    "iso:country":"US",
    "sg:address":"1335 Lexington Ave",
    "sg:city":"New York",
    "sg:classifiers":[
        {
            "category":"Retail",
            "subcategory":"Repair Shop",
            "type":"Services"
        }
    ],
    "sg:phone":"+1 212 518 2079",
    "sg:postcode":"10128",
    "sg:province":"NY",
    "sg:tags":[
        "lock",
        "locksmith"
    ],
    "wof:name":"Emergency Locksmith",
    "wof:placetype":"venue"
},
  "geometry": {"coordinates":[-73.95440499999999,40.780854],"type":"Point"}
}