{
  "type": "Feature",
  "properties": {
    "addr:full":"1279 State Hwy 311 Patterson NY 12563",
    "addr:housenumber":"1279",
    "addr:postcode":"12563",
    "addr:street":"State Hwy 311",
    "iso:country":"US",
    "sg:address":"1279 State Hwy 311",
    "sg:city":"Patterson",
    "sg:classifiers":[
        {
            "category":"Building & Trades",
            "subcategory":"Cleaning & Sanitation",
            "type":"Services"
        }
    ],
    "sg:phone":"+1 845 878 3909",
    "sg:postcode":"12563",
    "sg:province":"NY",
    "sg:tags":[
        "polishing",
        "waxing",
        "floor"
    ],
    "wof:name":"Surfacesys",
    "wof:placetype":"venue"
},
  "geometry": {"coordinates":[-73.64392599999999,41.474225],"type":"Point"}
}