{
  "type": "Feature",
  "properties": {
    "iso:country":"US",
    "sg:address":"2545 Natta Blvd",
    "sg:city":"Bellmore",
    "sg:classifiers":[
        {
            "category":"Shopping",
            "subcategory":"Computers & Home Electronics",
            "type":"Retail Goods"
        }
    ],
    "sg:phone":"+1 516 343 4046",
    "sg:postcode":"11710",
    "sg:province":"NY",
    "sg:tags":[
        "theater",
        "consumer",
        "system"
    ],
    "wof:name":"Long Island Spy Supply Company",
    "wof:placetype":"venue"
},
  "geometry": {"coordinates":[-73.535242,40.67492],"type":"Point"}
}