{
  "type": "Feature",
  "properties": {
    "addr:full":"392 Main St Catskill NY 12414",
    "addr:housenumber":"392",
    "addr:postcode":"12414",
    "addr:street":"Main St",
    "iso:country":"US",
    "sg:address":"392 Main St",
    "sg:city":"Catskill",
    "sg:classifiers":[
        {
            "category":"Shopping",
            "subcategory":"Gifts & Souvenirs",
            "type":"Retail Goods"
        }
    ],
    "sg:phone":"+1   ",
    "sg:postcode":"12414",
    "sg:province":"NY",
    "wof:name":"Partytime Variety",
    "wof:placetype":"venue"
},
  "geometry": {"coordinates":[-73.86554599999999,42.21937],"type":"Point"}
}