{
  "type": "Feature",
  "properties": {
    "iso:country":"US",
    "sg:address":"2171 White Plains Rd",
    "sg:city":"Bronx",
    "sg:classifiers":[
        {
            "category":"Shopping",
            "subcategory":"Computers & Home Electronics",
            "type":"Retail Goods"
        }
    ],
    "sg:phone":"+1 718 319 9676",
    "sg:postcode":"10462",
    "sg:province":"NY",
    "sg:tags":[
        "game",
        "video"
    ],
    "wof:name":"Game Station Inc",
    "wof:placetype":"venue"
},
  "geometry": {"coordinates":[-73.86774200000001,40.855523],"type":"Point"}
}