{
  "type": "Feature",
  "properties": {
    "addr:full":"1633 Broadway New York NY 10019",
    "addr:housenumber":"1633",
    "addr:postcode":"10019",
    "addr:street":"Broadway",
    "iso:country":"US",
    "sg:address":"1633 Broadway",
    "sg:city":"New York",
    "sg:classifiers":[
        {
            "category":"Cinema",
            "subcategory":"Movie Theater",
            "type":"Entertainment"
        }
    ],
    "sg:phone":"+1 212 489 4943",
    "sg:postcode":"10019",
    "sg:province":"NY",
    "sg:tags":[
        "motion",
        "picture"
    ],
    "wof:name":"Civita Colonia Artistica",
    "wof:placetype":"venue"
},
  "geometry": {"coordinates":[-73.98400100000001,40.761501],"type":"Point"}
}