{
  "type": "Feature",
  "properties": {
    "addr:full":"6 Grey Bark Ln Apalachin NY 13732",
    "addr:housenumber":"6",
    "addr:postcode":"13732",
    "addr:street":"Grey Bark Ln",
    "iso:country":"US",
    "sg:address":"6 Grey Bark Ln",
    "sg:city":"Apalachin",
    "sg:classifiers":[
        {
            "category":"Health Services",
            "subcategory":"Doctor",
            "type":"Services"
        }
    ],
    "sg:phone":"+1   ",
    "sg:postcode":"13732",
    "sg:province":"NY",
    "wof:name":"Mike Sostowski",
    "wof:placetype":"venue"
},
  "geometry": {"coordinates":[-76.11241800000001,42.04808],"type":"Point"}
}