{
  "type": "Feature",
  "properties": {
    "addr:full":"143 Broadway Monticello NY 12701",
    "addr:housenumber":"143",
    "addr:postcode":"12701",
    "addr:street":"Broadway",
    "iso:country":"US",
    "sg:address":"143 Broadway",
    "sg:city":"Monticello",
    "sg:classifiers":[
        {
            "category":"Shopping",
            "subcategory":"Discount & Variety Stores",
            "type":"Retail Goods"
        },
        {
            "category":"Shopping",
            "subcategory":"Department Store",
            "type":"Retail Goods"
        }
    ],
    "sg:phone":"+1 845 794 2863",
    "sg:postcode":"12701",
    "sg:province":"NY",
    "wof:name":"Family Dollar Stores",
    "wof:placetype":"venue"
},
  "geometry": {"coordinates":[-74.68122700000001,41.65342],"type":"Point"}
}