{
  "type": "Feature",
  "properties": {
    "iso:country":"US",
    "sg:address":"52 Lewis Ln",
    "sg:city":"Bloomingburg",
    "sg:classifiers":[
        {
            "category":"Building & Trades",
            "subcategory":"Construction",
            "type":"Services"
        }
    ],
    "sg:phone":"+1 845 733 5006",
    "sg:postcode":"12721",
    "sg:province":"NY",
    "sg:tags":[
        "excavating",
        "contractor"
    ],
    "wof:name":"Anderson Family Trucking",
    "wof:placetype":"venue"
},
  "geometry": {"coordinates":[-74.418595,41.59116],"type":"Point"}
}