{
  "type": "Feature",
  "properties": {
    "addr:full":"481 State Hwy 306 Monsey NY 10952",
    "addr:housenumber":"481",
    "addr:postcode":"10952",
    "addr:street":"State Hwy 306",
    "iso:country":"US",
    "sg:address":"481 State Hwy 306",
    "sg:city":"Monsey",
    "sg:classifiers":[
        {
            "category":"Retail",
            "subcategory":"Veterinary Services",
            "type":"Services"
        }
    ],
    "sg:phone":"+1 845 354 6602",
    "sg:postcode":"10952",
    "sg:province":"NY",
    "sg:tags":[
        "hospital",
        "for",
        "animal",
        "specialty"
    ],
    "wof:name":"All Creatures Great and Small",
    "wof:placetype":"venue"
},
  "geometry": {"coordinates":[-74.070116,41.157755],"type":"Point"}
}