{
  "type": "Feature",
  "properties": {
    "addr:full":"15 Grant Pl Lake Peekskill NY 10537",
    "addr:housenumber":"15",
    "addr:postcode":"10537",
    "addr:street":"Grant Pl",
    "iso:country":"US",
    "sg:address":"15 Grant Pl",
    "sg:city":"Lake Peekskill",
    "sg:classifiers":[
        {
            "category":"Building & Trades",
            "subcategory":"Plumbing",
            "type":"Services"
        }
    ],
    "sg:phone":"+1 845 528 2226",
    "sg:postcode":"10537",
    "sg:province":"NY",
    "sg:tags":[
        "plumbing",
        "contractor"
    ],
    "wof:name":"All Pro Rooter",
    "wof:placetype":"venue"
},
  "geometry": {"coordinates":[-73.876801,41.3379],"type":"Point"}
}