{
  "type": "Feature",
  "properties": {
    "addr:full":"230 Park Ave Rm 2525 New York NY 10169",
    "addr:housenumber":"230;2525",
    "addr:postcode":"10169",
    "addr:street":"Park Ave Rm",
    "iso:country":"US",
    "sg:address":"230 Park Ave Rm 2525",
    "sg:city":"New York",
    "sg:classifiers":[
        {
            "category":"Professional",
            "subcategory":"Lawyer & Legal Services",
            "type":"Services"
        }
    ],
    "sg:phone":"+1 212 867 9120",
    "sg:postcode":"10169",
    "sg:province":"NY",
    "sg:website":"www.bischoflegal.com",
    "wof:name":"Law Offices Of George L Bischof",
    "wof:placetype":"venue"
},
  "geometry": {"coordinates":[-73.976218,40.754628],"type":"Point"}
}