{
  "type": "Feature",
  "properties": {
    "addr:full":"814 Jamaica Avenue Brooklyn NY 11208",
    "addr:housenumber":"814",
    "addr:postcode":"11208",
    "addr:street":"Jamaica Avenue",
    "iso:country":"US",
    "sg:address":"814 Jamaica Avenue",
    "sg:city":"Brooklyn",
    "sg:classifiers":[
        {
            "category":"Food & Beverages",
            "subcategory":"Groceries & Convenience Stores",
            "type":"Retail Goods"
        }
    ],
    "sg:phone":"+1 718 348 6253",
    "sg:postcode":"11208",
    "sg:province":"NY",
    "wof:name":"Western Beef Supermarket",
    "wof:placetype":"venue"
},
  "geometry": {"coordinates":[-73.87546,40.688544],"type":"Point"}
}