{
  "type": "Feature",
  "properties": {
    "iso:country":"US",
    "sg:address":"1451 Nostrand Ave",
    "sg:city":"Brooklyn",
    "sg:classifiers":[
        {
            "category":"Real Estate",
            "subcategory":"Real Estate Agent",
            "type":"Services"
        }
    ],
    "sg:phone":"+1 718 284 7910",
    "sg:postcode":"11226",
    "sg:province":"NY",
    "wof:name":"Fletcher Real Estate",
    "wof:placetype":"venue"
},
  "geometry": {"coordinates":[-73.949669,40.651697],"type":"Point"}
}