{
  "type": "Feature",
  "properties": {
    "iso:country":"US",
    "sg:address":"8 Comsewogue Ct",
    "sg:city":"Port Jefferson Station",
    "sg:classifiers":[
        {
            "category":"Building & Trades",
            "subcategory":"Construction",
            "type":"Services"
        }
    ],
    "sg:phone":"+1 631 476 0403",
    "sg:postcode":"11776",
    "sg:province":"NY",
    "sg:tags":[
        "house"
    ],
    "wof:name":"L Milanesi Const Inc",
    "wof:placetype":"venue"
},
  "geometry": {"coordinates":[-73.012748,40.905137],"type":"Point"}
}