{
  "type": "Feature",
  "properties": {
    "addr:full":"126 Murray Ave Yonkers NY 10704",
    "addr:housenumber":"126",
    "addr:postcode":"10704",
    "addr:street":"Murray Ave",
    "iso:country":"US",
    "sg:address":"126 Murray Ave",
    "sg:city":"Yonkers",
    "sg:classifiers":[
        {
            "category":"Professional",
            "subcategory":"Management & Consulting",
            "type":"Services"
        }
    ],
    "sg:phone":"+1 914 965 8302",
    "sg:postcode":"10704",
    "sg:province":"NY",
    "sg:tags":[
        "party",
        "planning",
        "event"
    ],
    "wof:name":"Hostess Helpers Of Westchester",
    "wof:placetype":"venue"
},
  "geometry": {"coordinates":[-73.85893,40.930928],"type":"Point"}
}