{
  "type": "Feature",
  "properties": {
    "iso:country":"US",
    "sg:address":"201 Orchard St",
    "sg:city":"Walden",
    "sg:classifiers":[
        {
            "category":"Manufacturing",
            "subcategory":"Retail Goods",
            "type":"Manufacturing & Wholesale Goods"
        }
    ],
    "sg:phone":"+1 845 778 3195",
    "sg:postcode":"12586",
    "sg:province":"NY",
    "sg:tags":[
        "aerosol"
    ],
    "wof:name":"Chemi-Coatings Inc",
    "wof:placetype":"venue"
},
  "geometry": {"coordinates":[-74.194039,41.559919],"type":"Point"}
}