{
  "type": "Feature",
  "properties": {
    "addr:full":"460 Hudson St New York NY 10014",
    "addr:housenumber":"460",
    "addr:postcode":"10014",
    "addr:street":"Hudson St",
    "iso:country":"US",
    "sg:address":"460 Hudson St",
    "sg:city":"New York",
    "sg:classifiers":[
        {
            "category":"Personal",
            "subcategory":"Shoe Repair & Shine",
            "type":"Services"
        }
    ],
    "sg:phone":"+1 646 486 2680",
    "sg:postcode":"10014",
    "sg:province":"NY",
    "sg:tags":[
        "repairing",
        "watch",
        "boot"
    ],
    "wof:name":"David Shoe Repair Store",
    "wof:placetype":"venue"
},
  "geometry": {"coordinates":[-74.00649300000001,40.731451],"type":"Point"}
}