{
  "type": "Feature",
  "properties": {
    "addr:full":"333 Jericho Tpke Huntington Sta NY 11746",
    "addr:housenumber":"333",
    "addr:postcode":"11746",
    "addr:street":"Jericho Tpke",
    "iso:country":"US",
    "sg:address":"333 Jericho Tpke",
    "sg:city":"Huntington Sta",
    "sg:classifiers":[
        {
            "category":"Manufacturing",
            "subcategory":"Printing",
            "type":"Manufacturing & Wholesale Goods"
        }
    ],
    "sg:phone":"+1 631 547 0004",
    "sg:postcode":"11746",
    "sg:province":"NY",
    "sg:tags":[
        "printer"
    ],
    "wof:name":"Alpha Graphics",
    "wof:placetype":"venue"
},
  "geometry": {"coordinates":[-73.398757,40.829568],"type":"Point"}
}