{
  "type": "Feature",
  "properties": {
    "addr:full":"141 Hunter Ave Albany NY 12206",
    "addr:housenumber":"141",
    "addr:postcode":"12206",
    "addr:street":"Hunter Ave",
    "iso:country":"US",
    "sg:address":"141 Hunter Ave",
    "sg:city":"Albany",
    "sg:classifiers":[
        {
            "category":"Retail",
            "subcategory":"Auto Repair",
            "type":"Services"
        }
    ],
    "sg:phone":"+1 518 459 7023",
    "sg:postcode":"12206",
    "sg:province":"NY",
    "sg:tags":[
        "body",
        "automobile",
        "painting"
    ],
    "wof:name":"Empire State Auto",
    "wof:placetype":"venue"
},
  "geometry": {"coordinates":[-73.784638,42.676489],"type":"Point"}
}