{
  "type": "Feature",
  "properties": {
    "addr:full":"985 Co Rte 57 Phoenix NY 13135",
    "addr:housenumber":"985",
    "addr:postcode":"13135",
    "addr:street":"Co Rte 57",
    "iso:country":"US",
    "sg:address":"985 Co Rte 57",
    "sg:city":"Phoenix",
    "sg:classifiers":[
        {
            "category":"Building & Trades",
            "subcategory":"Construction",
            "type":"Services"
        }
    ],
    "sg:phone":"+1 315 695 4994",
    "sg:postcode":"13135",
    "sg:province":"NY",
    "sg:tags":[
        "contractor"
    ],
    "wof:name":"Shoe Roofing Inc",
    "wof:placetype":"venue"
},
  "geometry": {"coordinates":[-76.329094,43.252562],"type":"Point"}
}