{
  "type": "Feature",
  "properties": {
    "addr:full":"2 W Searsville Rd Montgomery NY 12549",
    "addr:housenumber":"2",
    "addr:postcode":"12549",
    "addr:street":"W Searsville Rd",
    "iso:country":"US",
    "sg:address":"2 W Searsville Rd",
    "sg:city":"Montgomery",
    "sg:classifiers":[
        {
            "category":"Building & Trades",
            "subcategory":"Landscaping Services",
            "type":"Services"
        }
    ],
    "sg:phone":"+1 845 457 3550",
    "sg:postcode":"12549",
    "sg:province":"NY",
    "sg:tags":[
        "landscape"
    ],
    "wof:name":"Doug Sternemann Lawn Maint",
    "wof:placetype":"venue"
},
  "geometry": {"coordinates":[-74.257903,41.557722],"type":"Point"}
}