{
  "type": "Feature",
  "properties": {
    "addr:full":"1640 Hempstead Tpke East Meadow NY 11554",
    "addr:housenumber":"1640",
    "addr:postcode":"11554",
    "addr:street":"Hempstead Tpke",
    "iso:country":"US",
    "sg:address":"1640 Hempstead Tpke",
    "sg:city":"East Meadow",
    "sg:classifiers":[
        {
            "category":"Health Services",
            "subcategory":"Dentist",
            "type":"Services"
        }
    ],
    "sg:phone":"+1 516 794 7700",
    "sg:postcode":"11554",
    "sg:province":"NY",
    "wof:name":"D",
    "wof:placetype":"venue"
},
  "geometry": {"coordinates":[-73.573303,40.7234],"type":"Point"}
}