{
  "type": "Feature",
  "properties": {
    "addr:full":"6805 State Hwy 80 Cooperstown NY 13326",
    "addr:housenumber":"6805",
    "addr:postcode":"13326",
    "addr:street":"State Hwy 80",
    "iso:country":"US",
    "sg:address":"6805 State Hwy 80",
    "sg:city":"Cooperstown",
    "sg:classifiers":[
        {
            "category":"Travel",
            "subcategory":"Hotels & Motels",
            "type":"Entertainment"
        }
    ],
    "sg:phone":"+1 607 547 9740",
    "sg:postcode":"13326",
    "sg:province":"NY",
    "sg:website":"www.lakeviewmotelny.com",
    "wof:name":"Lake View Motel",
    "wof:placetype":"venue"
},
  "geometry": {"coordinates":[-74.901433,42.765766],"type":"Point"}
}