{
  "type": "Feature",
  "properties": {
    "iso:country":"US",
    "sg:address":"323 Ashford Ave",
    "sg:city":"Dobbs Ferry",
    "sg:classifiers":[
        {
            "category":"Sports & Exercise",
            "subcategory":"Race Track",
            "type":"Entertainment"
        }
    ],
    "sg:phone":"+1   ",
    "sg:postcode":"10522",
    "sg:province":"NY",
    "sg:tags":[
        "operation",
        "racing",
        "or"
    ],
    "wof:name":"Raceway Construction Service",
    "wof:placetype":"venue"
},
  "geometry": {"coordinates":[-73.853368,41.014394],"type":"Point"}
}