{
  "type": "Feature",
  "properties": {
    "addr:full":"200 Lexington Ave New York NY 10016",
    "addr:housenumber":"200",
    "addr:postcode":"10016",
    "addr:street":"Lexington Ave",
    "iso:country":"US",
    "sg:address":"200 Lexington Ave",
    "sg:city":"New York",
    "sg:classifiers":[
        {
            "category":"Manufacturing",
            "subcategory":"Furniture",
            "type":"Manufacturing & Wholesale Goods"
        }
    ],
    "sg:phone":"+1   ",
    "sg:postcode":"10016",
    "sg:province":"NY",
    "sg:tags":[
        "wood",
        "mfg"
    ],
    "wof:name":"Boyce Products LTD",
    "wof:placetype":"venue"
},
  "geometry": {"coordinates":[-73.98030900000001,40.745708],"type":"Point"}
}