{
  "type": "Feature",
  "properties": {
    "addr:full":"3758 E Tremont Ave Bronx NY 10465",
    "addr:housenumber":"3758",
    "addr:postcode":"10465",
    "addr:street":"E Tremont Ave",
    "iso:country":"US",
    "sg:address":"3758 E Tremont Ave",
    "sg:city":"Bronx",
    "sg:classifiers":[
        {
            "category":"Bars & Pubs",
            "type":"Food & Drink"
        }
    ],
    "sg:phone":"+1 718 822 9600",
    "sg:postcode":"10465",
    "sg:province":"NY",
    "wof:name":"Randall Pub",
    "wof:placetype":"venue"
},
  "geometry": {"coordinates":[-73.821254,40.825797],"type":"Point"}
}