{
  "type": "Feature",
  "properties": {
    "addr:full":"79 Whig St Newark Valley NY 13811",
    "addr:housenumber":"79",
    "addr:postcode":"13811",
    "addr:street":"Whig St",
    "iso:country":"US",
    "sg:address":"79 Whig St",
    "sg:city":"Newark Valley",
    "sg:classifiers":[
        {
            "category":"Education",
            "subcategory":"School",
            "type":"Public Place"
        }
    ],
    "sg:phone":"+1 607 642 3221",
    "sg:postcode":"13811",
    "sg:province":"NY",
    "sg:tags":[
        "district"
    ],
    "wof:name":"Newark Valley Central Schl Adm",
    "wof:placetype":"venue"
},
  "geometry": {"coordinates":[-76.18524499999999,42.228514],"type":"Point"}
}