{
  "type": "Feature",
  "properties": {
    "iso:country":"US",
    "sg:address":"760 Broadway",
    "sg:city":"Brooklyn",
    "sg:classifiers":[
        {
            "category":"Health Services",
            "subcategory":"Clinic",
            "type":"Services"
        }
    ],
    "sg:phone":"+1 718 963 8000",
    "sg:postcode":"11206",
    "sg:province":"NY",
    "sg:tags":[
        "medical"
    ],
    "wof:name":"Jose Orsini, M.D.",
    "wof:placetype":"venue"
},
  "geometry": {"coordinates":[-73.94279400000001,40.699474],"type":"Point"}
}