{
  "type": "Feature",
  "properties": {
    "iso:country":"US",
    "sg:address":"705 Shenandoah Ave",
    "sg:city":"Peekskill",
    "sg:classifiers":[
        {
            "category":"Organizations",
            "subcategory":"Religious Organization",
            "type":"Services"
        }
    ],
    "sg:phone":"+1 914 737 8249",
    "sg:postcode":"10566",
    "sg:province":"NY",
    "sg:tags":[
        "church"
    ],
    "wof:name":"St Peter & Paul Catholic",
    "wof:placetype":"venue"
},
  "geometry": {"coordinates":[-73.92706699999999,41.275353],"type":"Point"}
}