{
  "type": "Feature",
  "properties": {
    "addr:full":"863 Central Ave Woodmere NY 11598",
    "addr:housenumber":"863",
    "addr:postcode":"11598",
    "addr:street":"Central Ave",
    "iso:country":"US",
    "sg:address":"863 Central Ave",
    "sg:city":"Woodmere",
    "sg:classifiers":[
        {
            "category":"Health Services",
            "subcategory":"Doctor",
            "type":"Services"
        }
    ],
    "sg:phone":"+1 516 569 4709",
    "sg:postcode":"11598",
    "sg:province":"NY",
    "sg:tags":[
        "physician",
        "surgeon"
    ],
    "wof:name":"Levine & Overby",
    "wof:placetype":"venue"
},
  "geometry": {"coordinates":[-73.713365,40.629332],"type":"Point"}
}