{
  "type": "Feature",
  "properties": {
    "addr:full":"2 Purdy Ave Rye NY 10580",
    "addr:housenumber":"2",
    "addr:postcode":"10580",
    "addr:street":"Purdy Ave",
    "iso:country":"US",
    "sg:address":"2 Purdy Ave",
    "sg:city":"Rye",
    "sg:classifiers":[
        {
            "category":"Professional",
            "subcategory":"Art Services",
            "type":"Services"
        }
    ],
    "sg:phone":"+1 914 967 8956",
    "sg:postcode":"10580",
    "sg:province":"NY",
    "sg:tags":[
        "artist"
    ],
    "wof:name":"Paolo Gallery",
    "wof:placetype":"venue"
},
  "geometry": {"coordinates":[-73.68369199999999,40.984572],"type":"Point"}
}