{
  "type": "Feature",
  "properties": {
    "iso:country":"US",
    "sg:address":"3 Fieldhouse Ave",
    "sg:city":"East Setauket",
    "sg:classifiers":[
        {
            "category":"Food & Beverages",
            "subcategory":"Groceries & Convenience Stores",
            "type":"Retail Goods"
        }
    ],
    "sg:phone":"+1   ",
    "sg:postcode":"11733",
    "sg:province":"NY",
    "wof:name":"Islandwide Food Svc",
    "wof:placetype":"venue"
},
  "geometry": {"coordinates":[-73.093467,40.899583],"type":"Point"}
}