{
  "type": "Feature",
  "properties": {
    "iso:country":"US",
    "sg:address":"5406 Beverley Rd",
    "sg:city":"Brooklyn",
    "sg:classifiers":[
        {
            "category":"Building & Trades",
            "subcategory":"Plumbing",
            "type":"Services"
        }
    ],
    "sg:phone":"+1 718 451 3413",
    "sg:postcode":"11203",
    "sg:province":"NY",
    "sg:tags":[
        "boiler",
        "cleaning"
    ],
    "wof:name":"ANT General Contracting",
    "wof:placetype":"venue"
},
  "geometry": {"coordinates":[-73.92502500000001,40.646542],"type":"Point"}
}