{
  "type": "Feature",
  "properties": {
    "addr:full":"50 E 77th St New York NY 10021",
    "addr:housenumber":"50",
    "addr:postcode":"10021",
    "addr:street":"E 77Th St",
    "iso:country":"US",
    "sg:address":"50 E 77th St",
    "sg:city":"New York",
    "sg:classifiers":[
        {
            "category":"Real Estate",
            "subcategory":"Real Estate Operator",
            "type":"Services"
        }
    ],
    "sg:phone":"+1 212 861 4239",
    "sg:postcode":"10021",
    "sg:province":"NY",
    "sg:tags":[
        "apartment"
    ],
    "wof:name":"Carlyle House Inc",
    "wof:placetype":"venue"
},
  "geometry": {"coordinates":[-73.963097,40.775002],"type":"Point"}
}