{
  "type": "Feature",
  "properties": {
    "addr:full":"2340 Brighton Henrietta Town Line Rd Rochester NY 14623",
    "addr:housenumber":"2340",
    "addr:postcode":"14623",
    "addr:street":"Brighton Henrietta Town Line Rd",
    "iso:country":"US",
    "sg:address":"2340 Brighton Henrietta Town Line Rd",
    "sg:city":"Rochester",
    "sg:classifiers":[
        {
            "category":"Manufacturing",
            "subcategory":"Signs",
            "type":"Manufacturing & Wholesale Goods"
        }
    ],
    "sg:phone":"+1 585 427 9050",
    "sg:postcode":"14623",
    "sg:province":"NY",
    "sg:website":"www.totalidentity.com",
    "wof:name":"Pride Signs",
    "wof:placetype":"venue"
},
  "geometry": {"coordinates":[-77.619654,43.094521],"type":"Point"}
}