{
  "type": "Feature",
  "properties": {
    "addr:full":"39 Leroy St Binghamton NY 13905",
    "addr:housenumber":"39",
    "addr:postcode":"13905",
    "addr:street":"Leroy St",
    "iso:country":"US",
    "sg:address":"39 Leroy St",
    "sg:city":"Binghamton",
    "sg:classifiers":[
        {
            "category":"Health Services",
            "subcategory":"Doctor",
            "type":"Services"
        }
    ],
    "sg:phone":"+1 607 722 5145",
    "sg:postcode":"13905",
    "sg:province":"NY",
    "sg:tags":[
        "dentist"
    ],
    "wof:name":"Scott Farrell DDS",
    "wof:placetype":"venue"
},
  "geometry": {"coordinates":[-75.92352,42.095496],"type":"Point"}
}