{
  "type": "Feature",
  "properties": {
    "addr:full":"21 Main St Milton NY 12547",
    "addr:housenumber":"21",
    "addr:postcode":"12547",
    "addr:street":"Main St",
    "iso:country":"US",
    "sg:address":"21 Main St",
    "sg:city":"Milton",
    "sg:classifiers":[
        {
            "category":"Government",
            "subcategory":"Fire Station",
            "type":"Public Place"
        }
    ],
    "sg:phone":"+1 845 795 2355",
    "sg:postcode":"12547",
    "sg:province":"NY",
    "sg:tags":[
        "department"
    ],
    "wof:name":"Milton Fire District",
    "wof:placetype":"venue"
},
  "geometry": {"coordinates":[-73.959744,41.656982],"type":"Point"}
}