{
  "type": "Feature",
  "properties": {
    "addr:full":"346 Central Ave Lawrence NY 11559",
    "addr:housenumber":"346",
    "addr:postcode":"11559",
    "addr:street":"Central Ave",
    "iso:country":"US",
    "sg:address":"346 Central Ave",
    "sg:city":"Lawrence",
    "sg:classifiers":[
        {
            "category":"Shopping",
            "subcategory":"Used Merchandise",
            "type":"Retail Goods"
        }
    ],
    "sg:phone":"+1 516 569 3980",
    "sg:postcode":"11559",
    "sg:province":"NY",
    "sg:tags":[
        "shop",
        "thrift"
    ],
    "wof:name":"Horizon Thrift Shop",
    "wof:placetype":"venue"
},
  "geometry": {"coordinates":[-73.73074099999999,40.617045],"type":"Point"}
}