{
  "type": "Feature",
  "properties": {
    "addr:full":"2159 Knapp St Brooklyn NY 11229",
    "addr:housenumber":"2159",
    "addr:postcode":"11229",
    "addr:street":"Knapp St",
    "iso:country":"US",
    "sg:address":"2159 Knapp St",
    "sg:city":"Brooklyn",
    "sg:classifiers":[
        {
            "category":"Restaurant",
            "type":"Food & Drink"
        }
    ],
    "sg:phone":"+1 718 743 0537",
    "sg:postcode":"11229",
    "sg:province":"NY",
    "wof:name":"Knapp St. Pizza",
    "wof:placetype":"venue"
},
  "geometry": {"coordinates":[-73.93396300000001,40.599637],"type":"Point"}
}