{
  "type": "Feature",
  "properties": {
    "addr:full":"411 5th Ave New York NY 10016",
    "addr:housenumber":"411",
    "addr:postcode":"10016",
    "addr:street":"5Th Ave",
    "iso:country":"US",
    "sg:address":"411 5th Ave",
    "sg:city":"New York",
    "sg:classifiers":[
        {
            "category":"Professional",
            "type":"Services"
        },
        {
            "category":"Professional",
            "subcategory":"Computer Services",
            "type":"Services"
        }
    ],
    "sg:phone":"+1 212 686 9022",
    "sg:postcode":"10016",
    "sg:province":"NY",
    "sg:tags":[
        "financial",
        "for",
        "datum",
        "system",
        "macroeconomic",
        "t",
        "provides",
        "establishment"
    ],
    "wof:name":"Ecowin Inc",
    "wof:placetype":"venue"
},
  "geometry": {"coordinates":[-73.98272299999999,40.750959],"type":"Point"}
}