{
  "type": "Feature",
  "properties": {
    "addr:full":"627 Plymouth Ave Syracuse NY 13211",
    "addr:housenumber":"627",
    "addr:postcode":"13211",
    "addr:street":"Plymouth Ave",
    "iso:country":"US",
    "sg:address":"627 Plymouth Ave",
    "sg:city":"Syracuse",
    "sg:classifiers":[
        {
            "category":"Home & Garden",
            "subcategory":"Building Materials",
            "type":"Retail Goods"
        }
    ],
    "sg:phone":"+1 315 454 5566",
    "sg:postcode":"13211",
    "sg:province":"NY",
    "sg:tags":[
        "windows"
    ],
    "wof:name":"Lantry Enterprises",
    "wof:placetype":"venue"
},
  "geometry": {"coordinates":[-76.135733,43.105173],"type":"Point"}
}