{
  "type": "Feature",
  "properties": {
    "iso:country":"US",
    "sg:address":"83 Chamberlain St",
    "sg:city":"Wellsville",
    "sg:classifiers":[
        {
            "category":"Organizations",
            "subcategory":"Religious Organization",
            "type":"Services"
        }
    ],
    "sg:phone":"+1 585 593 5069",
    "sg:postcode":"14895",
    "sg:province":"NY",
    "sg:tags":[
        "church"
    ],
    "wof:name":"Presbyterian Church-Wellsville",
    "wof:placetype":"venue"
},
  "geometry": {"coordinates":[-77.955963,42.121456],"type":"Point"}
}