{
  "type": "Feature",
  "properties": {
    "addr:full":"25 Horton Dr Huntington Sta NY 11746",
    "addr:housenumber":"25",
    "addr:postcode":"11746",
    "addr:street":"Horton Dr",
    "iso:country":"US",
    "sg:address":"25 Horton Dr",
    "sg:city":"Huntington Sta",
    "sg:classifiers":[
        {
            "category":"Shopping",
            "type":"Retail Goods"
        }
    ],
    "sg:phone":"+1 631 549 0551",
    "sg:postcode":"11746",
    "sg:province":"NY",
    "sg:tags":[
        "equipment",
        "telephone",
        "supply"
    ],
    "wof:name":"All Action Communication Inc",
    "wof:placetype":"venue"
},
  "geometry": {"coordinates":[-73.404301,40.816821],"type":"Point"}
}