{
  "type": "Feature",
  "properties": {
    "addr:full":"8846 7th Ave Brooklyn NY 11228",
    "addr:housenumber":"8846",
    "addr:postcode":"11228",
    "addr:street":"7Th Ave",
    "iso:country":"US",
    "sg:address":"8846 7th Ave",
    "sg:city":"Brooklyn",
    "sg:classifiers":[
        {
            "category":"Health Services",
            "subcategory":"Doctor",
            "type":"Services"
        }
    ],
    "sg:phone":"+1 718 745 9300",
    "sg:postcode":"11228",
    "sg:province":"NY",
    "wof:name":"Abhary Sayedeh F MD",
    "wof:placetype":"venue"
},
  "geometry": {"coordinates":[-74.02179700000001,40.617199],"type":"Point"}
}