{
  "type": "Feature",
  "properties": {
    "addr:full":"1322 Jerome Ave Bronx NY 10452",
    "addr:housenumber":"1322",
    "addr:postcode":"10452",
    "addr:street":"Jerome Ave",
    "iso:country":"US",
    "sg:address":"1322 Jerome Ave",
    "sg:city":"Bronx",
    "sg:classifiers":[
        {
            "category":"Insurance",
            "subcategory":"Insurance Agent",
            "type":"Services"
        }
    ],
    "sg:phone":"+1 718 588 2121",
    "sg:postcode":"10452",
    "sg:province":"NY",
    "wof:name":"Jerome Auto Driving School",
    "wof:placetype":"venue"
},
  "geometry": {"coordinates":[-73.91866397130001,40.8385569177],"type":"Point"}
}