{
  "type": "Feature",
  "properties": {
    "iso:country":"US",
    "sg:address":"811 Jericho Tpke",
    "sg:city":"Smithtown",
    "sg:classifiers":[
        {
            "category":"Professional",
            "subcategory":"Lawyer & Legal Services",
            "type":"Services"
        }
    ],
    "sg:phone":"+1 631 265 9882",
    "sg:postcode":"11787",
    "sg:province":"NY",
    "sg:tags":[
        "attorney"
    ],
    "wof:name":"Raymond M Smolenski PC",
    "wof:placetype":"venue"
},
  "geometry": {"coordinates":[-73.234983,40.847174],"type":"Point"}
}