{
  "type": "Feature",
  "properties": {
    "iso:country":"US",
    "sg:address":"96 Orchard St Ste Mgmt",
    "sg:city":"New York",
    "sg:classifiers":[
        {
            "category":"Shopping",
            "subcategory":"Jewelry",
            "type":"Retail Goods"
        }
    ],
    "sg:phone":"+1 212 387 0824",
    "sg:postcode":"10002",
    "sg:province":"NY",
    "wof:name":"Design Works",
    "wof:placetype":"venue"
},
  "geometry": {"coordinates":[-73.989988,40.718194],"type":"Point"}
}