{
  "type": "Feature",
  "properties": {
    "addr:full":"570 Bloomingdale Rd Staten Island NY 10309",
    "addr:housenumber":"570",
    "addr:postcode":"10309",
    "addr:street":"Bloomingdale Rd",
    "iso:country":"US",
    "sg:address":"570 Bloomingdale Rd",
    "sg:city":"Staten Island",
    "sg:classifiers":[
        {
            "category":"Health Services",
            "subcategory":"Doctor",
            "type":"Services"
        }
    ],
    "sg:phone":"+1 718 356 5310",
    "sg:postcode":"10309",
    "sg:province":"NY",
    "sg:tags":[
        "dentist"
    ],
    "wof:name":"Bloomingdale Dental",
    "wof:placetype":"venue"
},
  "geometry": {"coordinates":[-74.21776800000001,40.538983],"type":"Point"}
}