{
  "type": "Feature",
  "properties": {
    "iso:country":"US",
    "sg:address":"1330 Gerling St",
    "sg:city":"Schenectady",
    "sg:classifiers":[
        {
            "category":"Shopping",
            "subcategory":"Pharmacy",
            "type":"Retail Goods"
        }
    ],
    "sg:phone":"+1 518 346 3121",
    "sg:postcode":"12308",
    "sg:province":"NY",
    "wof:name":"CVS Pharmacy",
    "wof:placetype":"venue"
},
  "geometry": {"coordinates":[-73.907309,42.822377],"type":"Point"}
}