{
  "type": "Feature",
  "properties": {
    "iso:country":"US",
    "sg:address":"2255 N Triphammer Rd",
    "sg:city":"Ithaca",
    "sg:classifiers":[
        {
            "category":"Personal",
            "subcategory":"Beauty Salon",
            "type":"Services"
        }
    ],
    "sg:phone":"+1 607 257 0241",
    "sg:postcode":"14850",
    "sg:province":"NY",
    "wof:name":"Scizzor Wizards",
    "wof:placetype":"venue"
},
  "geometry": {"coordinates":[-76.481892,42.478135],"type":"Point"}
}