{
  "type": "Feature",
  "properties": {
    "addr:full":"124 Greenwich Ave New York NY 10011",
    "addr:housenumber":"124",
    "addr:postcode":"10011",
    "addr:street":"Greenwich Ave",
    "iso:country":"US",
    "sg:address":"124 Greenwich Ave",
    "sg:city":"New York",
    "sg:classifiers":[
        {
            "category":"Retail",
            "subcategory":"Repair Shop",
            "type":"Services"
        }
    ],
    "sg:phone":"+1 646 237 9669",
    "sg:postcode":"10011",
    "sg:province":"NY",
    "sg:tags":[
        "lock",
        "locksmith"
    ],
    "wof:name":"Accurate 24 Hours Emergency",
    "wof:placetype":"venue"
},
  "geometry": {"coordinates":[-74.001768,40.737674],"type":"Point"}
}