{
  "type": "Feature",
  "properties": {
    "addr:full":"9432 State Hwy 49 Marcy NY 13403",
    "addr:housenumber":"9432",
    "addr:postcode":"13403",
    "addr:street":"State Hwy 49",
    "iso:country":"US",
    "sg:address":"9432 State Hwy 49",
    "sg:city":"Marcy",
    "sg:phone":"+1 315 735 6153",
    "sg:postcode":"13403",
    "sg:province":"NY",
    "sg:tags":[
        "bulk",
        "gas"
    ],
    "wof:name":"Messer GT & S",
    "wof:placetype":"venue"
},
  "geometry": {"coordinates":[-75.263735,43.135743],"type":"Point"}
}