{
  "type": "Feature",
  "properties": {
    "addr:full":"68 S Howells Point Rd Bellport NY 11713",
    "addr:housenumber":"68",
    "addr:postcode":"11713",
    "addr:street":"S Howells Point Rd",
    "iso:country":"US",
    "sg:address":"68 S Howells Point Rd",
    "sg:city":"Bellport",
    "sg:classifiers":[
        {
            "category":"Building & Trades",
            "subcategory":"Plumbing",
            "type":"Services"
        }
    ],
    "sg:phone":"+1 631 475 2123",
    "sg:postcode":"11713",
    "sg:province":"NY",
    "sg:tags":[
        "water",
        "drainage"
    ],
    "wof:name":"Artco Construction Inc",
    "wof:placetype":"venue"
},
  "geometry": {"coordinates":[-72.94949200000001,40.743917],"type":"Point"}
}