{
  "type": "Feature",
  "properties": {
    "iso:country":"US",
    "sg:address":"1756 E 172nd St",
    "sg:city":"Bronx",
    "sg:classifiers":[
        {
            "category":"Organizations",
            "subcategory":"Religious Organization",
            "type":"Services"
        }
    ],
    "sg:phone":"+1 718 597 9600",
    "sg:postcode":"10472",
    "sg:province":"NY",
    "wof:name":"Lukumi Church of Orishas",
    "wof:placetype":"venue"
},
  "geometry": {"coordinates":[-73.869095,40.832503],"type":"Point"}
}