{
  "type": "Feature",
  "properties": {
    "addr:full":"916 Old Liverpool Rd Liverpool NY 13088",
    "addr:housenumber":"916",
    "addr:postcode":"13088",
    "addr:street":"Old Liverpool Rd",
    "iso:country":"US",
    "sg:address":"916 Old Liverpool Rd",
    "sg:city":"Liverpool",
    "sg:classifiers":[
        {
            "category":"Banks & Credit Unions",
            "subcategory":"Investment Brokerage",
            "type":"Services"
        }
    ],
    "sg:phone":"+1 315 453 8001",
    "sg:postcode":"13088",
    "sg:province":"NY",
    "sg:tags":[
        "security"
    ],
    "wof:name":"Edward Jones 03254",
    "wof:placetype":"venue"
},
  "geometry": {"coordinates":[-76.197796,43.097982],"type":"Point"}
}