{
  "type": "Feature",
  "properties": {
    "addr:full":"70 Linden Oaks Rochester NY 14625",
    "addr:housenumber":"70",
    "addr:postcode":"14625",
    "addr:street":"Linden Oaks",
    "iso:country":"US",
    "sg:address":"70 Linden Oaks",
    "sg:city":"Rochester",
    "sg:classifiers":[
        {
            "category":"Professional",
            "subcategory":"Lawyer & Legal Services",
            "type":"Services"
        }
    ],
    "sg:phone":"+1 585 383 5357",
    "sg:postcode":"14625",
    "sg:province":"NY",
    "sg:tags":[
        "attorney"
    ],
    "wof:name":"Thomas M Glavin",
    "wof:placetype":"venue"
},
  "geometry": {"coordinates":[-77.520443,43.125986],"type":"Point"}
}