{
  "type": "Feature",
  "properties": {
    "addr:full":"590 Amsterdam Ave New York NY 10024",
    "addr:housenumber":"590",
    "addr:postcode":"10024",
    "addr:street":"Amsterdam Ave",
    "iso:country":"US",
    "sg:address":"590 Amsterdam Ave",
    "sg:city":"New York",
    "sg:classifiers":[
        {
            "category":"Retail",
            "subcategory":"Repair Shop",
            "type":"Services"
        }
    ],
    "sg:phone":"+1 212 492 9821",
    "sg:postcode":"10024",
    "sg:province":"NY",
    "sg:tags":[
        "lock",
        "locksmith"
    ],
    "wof:name":"7 24 Anyplace Emrgncy Locksmth",
    "wof:placetype":"venue"
},
  "geometry": {"coordinates":[-73.97387999999999,40.789276],"type":"Point"}
}