{
  "type": "Feature",
  "properties": {
    "addr:full":"100 Parkway Dr S Unit 2 Hauppauge NY 11788",
    "addr:housenumber":"100;2",
    "addr:postcode":"11788",
    "addr:street":"Parkway Dr S Unit",
    "iso:country":"US",
    "sg:address":"100 Parkway Dr S Unit 2",
    "sg:city":"Hauppauge",
    "sg:classifiers":[
        {
            "category":"Sports & Exercise",
            "subcategory":"Gym",
            "type":"Entertainment"
        },
        {
            "category":"Arena",
            "subcategory":"Sports Club",
            "type":"Entertainment"
        }
    ],
    "sg:phone":"+1 631 864 3424",
    "sg:postcode":"11788",
    "sg:province":"NY",
    "sg:tags":[
        "health",
        "gymnasium"
    ],
    "wof:name":"Sports & Fitness Ventures",
    "wof:placetype":"venue"
},
  "geometry": {"coordinates":[-73.25967799999999,40.823515],"type":"Point"}
}