{
  "type": "Feature",
  "properties": {
    "iso:country":"US",
    "sg:address":"310 E Kingsbridge Rd",
    "sg:city":"Bronx",
    "sg:classifiers":[
        {
            "category":"Education",
            "subcategory":"Library",
            "type":"Public Place"
        }
    ],
    "sg:phone":"+1 718 579 4222",
    "sg:postcode":"10458",
    "sg:province":"NY",
    "sg:website":"www.nypl.org",
    "wof:name":"New York Public Library",
    "wof:placetype":"venue"
},
  "geometry": {"coordinates":[-73.89377399999999,40.865219],"type":"Point"}
}