{
  "type": "Feature",
  "properties": {
    "iso:country":"US",
    "sg:address":"461 Eldert Ln",
    "sg:city":"Brooklyn",
    "sg:classifiers":[
        {
            "category":"Professional",
            "subcategory":"Advertising",
            "type":"Services"
        }
    ],
    "sg:phone":"+1 718 647 0333",
    "sg:postcode":"11208",
    "sg:province":"NY",
    "sg:tags":[
        "distribution"
    ],
    "wof:name":"Natt Distributing Svc",
    "wof:placetype":"venue"
},
  "geometry": {"coordinates":[-73.86544600000001,40.679861],"type":"Point"}
}