{
  "type": "Feature",
  "properties": {
    "iso:country":"US",
    "sg:address":"718 E 187th St",
    "sg:city":"Bronx",
    "sg:classifiers":[
        {
            "category":"Restaurant",
            "type":"Food & Drink"
        }
    ],
    "sg:phone":"+1 718 220 0209",
    "sg:postcode":"10458",
    "sg:province":"NY",
    "sg:tags":[
        "shop",
        "coffee"
    ],
    "wof:name":"Two Star Coffee Shop",
    "wof:placetype":"venue"
},
  "geometry": {"coordinates":[-73.88418799999999,40.854045],"type":"Point"}
}