{
  "type": "Feature",
  "properties": {
    "addr:full":"222 Mansion Ave Staten Island NY 10308",
    "addr:housenumber":"222",
    "addr:postcode":"10308",
    "addr:street":"Mansion Ave",
    "iso:country":"US",
    "sg:address":"222 Mansion Ave",
    "sg:city":"Staten Island",
    "sg:classifiers":[
        {
            "category":"Autos & Motor Vehicles",
            "subcategory":"Boat Sales",
            "type":"Retail Goods"
        }
    ],
    "sg:phone":"+1   ",
    "sg:postcode":"10308",
    "sg:province":"NY",
    "sg:tags":[
        "operator",
        "marina",
        "used",
        "new"
    ],
    "wof:name":"Staten Island Boat Sales Inc",
    "wof:placetype":"venue"
},
  "geometry": {"coordinates":[-74.142109,40.542995],"type":"Point"}
}