{
  "type": "Feature",
  "properties": {
    "iso:country":"US",
    "sg:address":"9 Brightonwood Rd",
    "sg:city":"Glenmont",
    "sg:classifiers":[
        {
            "category":"Professional",
            "subcategory":"Management & Consulting",
            "type":"Services"
        }
    ],
    "sg:phone":"+1 518 475 9605",
    "sg:postcode":"12077",
    "sg:province":"NY",
    "sg:tags":[
        "consultant"
    ],
    "wof:name":"Goldenlane Assoc Inc",
    "wof:placetype":"venue"
},
  "geometry": {"coordinates":[-73.808921,42.600745],"type":"Point"}
}