{
  "type": "Feature",
  "properties": {
    "addr:full":"528 Morris Ave Bronx NY 10451",
    "addr:housenumber":"528",
    "addr:postcode":"10451",
    "addr:street":"Morris Ave",
    "iso:country":"US",
    "sg:address":"528 Morris Ave",
    "sg:city":"Bronx",
    "sg:classifiers":[
        {
            "category":"Food & Beverages",
            "subcategory":"Groceries & Convenience Stores",
            "type":"Retail Goods"
        }
    ],
    "sg:phone":"+1   ",
    "sg:postcode":"10451",
    "sg:province":"NY",
    "wof:name":"D G Grocery Corp",
    "wof:placetype":"venue"
},
  "geometry": {"coordinates":[-73.92276699999999,40.817592],"type":"Point"}
}