{
  "type": "Feature",
  "properties": {
    "iso:country":"US",
    "sg:address":"567 E 105th St",
    "sg:city":"Brooklyn",
    "sg:classifiers":[
        {
            "category":"Health Services",
            "subcategory":"Clinic",
            "type":"Services"
        }
    ],
    "sg:phone":"+1 718 307 3000",
    "sg:postcode":"11236",
    "sg:province":"NY",
    "sg:tags":[
        "hospital",
        "group",
        "medical"
    ],
    "sg:website":"www.siuh.edu",
    "wof:name":"Staten Island University Hospital",
    "wof:placetype":"venue"
},
  "geometry": {"coordinates":[-73.898499,40.650902],"type":"Point"}
}