{
  "type": "Feature",
  "properties": {
    "iso:country":"US",
    "sg:address":"5885 Big Tree Rd",
    "sg:city":"Lakeville",
    "sg:classifiers":[
        {
            "category":"Building & Trades",
            "subcategory":"Construction",
            "type":"Services"
        }
    ],
    "sg:phone":"+1 585 346 3169",
    "sg:postcode":"14480",
    "sg:province":"NY",
    "sg:tags":[
        "painter"
    ],
    "wof:name":"BSR Painting",
    "wof:placetype":"venue"
},
  "geometry": {"coordinates":[-77.701598,42.835428],"type":"Point"}
}