{
  "type": "Feature",
  "properties": {
    "addr:full":"18194 Minkler Rd Adams Center NY 13606",
    "addr:postcode":"18194;13606",
    "addr:street":"Minkler Rd",
    "iso:country":"US",
    "sg:address":"18194 Minkler Rd",
    "sg:city":"Adams Center",
    "sg:classifiers":[
        {
            "category":"Organizations",
            "subcategory":"Religious Organization",
            "type":"Services"
        }
    ],
    "sg:phone":"+1 315 583 5072",
    "sg:postcode":"13606",
    "sg:province":"NY",
    "sg:tags":[
        "clergy"
    ],
    "wof:name":"Walter E Giles",
    "wof:placetype":"venue"
},
  "geometry": {"coordinates":[-76.00749,43.854816],"type":"Point"}
}