{
  "type": "Feature",
  "properties": {
    "iso:country":"US",
    "sg:address":"3656 Lyell Rd",
    "sg:city":"Rochester",
    "sg:classifiers":[
        {
            "category":"Building & Trades",
            "subcategory":"Construction",
            "type":"Services"
        }
    ],
    "sg:phone":"+1 585 429 9808",
    "sg:postcode":"14606",
    "sg:province":"NY",
    "sg:tags":[
        "house",
        "co"
    ],
    "wof:name":"Mingoea Defeo Inc",
    "wof:placetype":"venue"
},
  "geometry": {"coordinates":[-77.72728499999999,43.164571],"type":"Point"}
}