{
  "type": "Feature",
  "properties": {
    "iso:country":"US",
    "sg:address":"514 Park Blvd",
    "sg:city":"Massapequa Park",
    "sg:classifiers":[
        {
            "category":"Restaurant",
            "type":"Food & Drink"
        }
    ],
    "sg:phone":"+1   ",
    "sg:postcode":"11762",
    "sg:province":"NY",
    "sg:tags":[
        "eating"
    ],
    "wof:name":"Baniellos",
    "wof:placetype":"venue"
},
  "geometry": {"coordinates":[-73.456357,40.677313],"type":"Point"}
}