{
  "type": "Feature",
  "properties": {
    "addr:full":"1175 E Broadway Hewlett NY 11557",
    "addr:housenumber":"1175",
    "addr:postcode":"11557",
    "addr:street":"E Broadway",
    "iso:country":"US",
    "sg:address":"1175 E Broadway",
    "sg:city":"Hewlett",
    "sg:classifiers":[
        {
            "category":"Professional",
            "subcategory":"Lawyer & Legal Services",
            "type":"Services"
        }
    ],
    "sg:phone":"+1 516 569 3067",
    "sg:postcode":"11557",
    "sg:province":"NY",
    "sg:tags":[
        "attorney"
    ],
    "wof:name":"Ruth Becker",
    "wof:placetype":"venue"
},
  "geometry": {"coordinates":[-73.701582,40.634375],"type":"Point"}
}