{
  "type": "Feature",
  "properties": {
    "iso:country":"US",
    "sg:address":"8269 River Rd",
    "sg:city":"Rome",
    "sg:classifiers":[
        {
            "category":"Wholesale",
            "subcategory":"Meat",
            "type":"Manufacturing & Wholesale Goods"
        }
    ],
    "sg:phone":"+1 315 337 1911",
    "sg:postcode":"13440",
    "sg:province":"NY",
    "wof:name":"Gold Medal Packing Inc",
    "wof:placetype":"venue"
},
  "geometry": {"coordinates":[-75.33938999999999,43.190037],"type":"Point"}
}