{
  "type": "Feature",
  "properties": {
    "iso:country":"US",
    "sg:address":"212 Elmwood Ave Suite 1E",
    "sg:city":"Gloversville",
    "sg:classifiers":[
        {
            "category":"Professional",
            "subcategory":"Engineering",
            "type":"Services"
        },
        {
            "category":"Real Estate",
            "subcategory":"Architect",
            "type":"Services"
        }
    ],
    "sg:phone":"+1 518 725 0006",
    "sg:postcode":"12078",
    "sg:province":"NY",
    "sg:tags":[
        "consulting",
        "architectural",
        "engineer"
    ],
    "sg:website":"http://www.h-p-engineering.com",
    "wof:name":"H+P Engineering, P.C.",
    "wof:placetype":"venue"
},
  "geometry": {"coordinates":[-74.320182,43.061519],"type":"Point"}
}