{
  "type": "Feature",
  "properties": {
    "iso:country":"US",
    "sg:address":"3124 Church Ave",
    "sg:city":"Brooklyn",
    "sg:classifiers":[
        {
            "category":"Social Services",
            "subcategory":"Child Care",
            "type":"Services"
        }
    ],
    "sg:phone":"+1 718 287 0037",
    "sg:postcode":"11226",
    "sg:province":"NY",
    "sg:tags":[
        "day"
    ],
    "wof:name":"Precious Moments Day Care",
    "wof:placetype":"venue"
},
  "geometry": {"coordinates":[-73.9478,40.650799],"type":"Point"}
}