{
  "type": "Feature",
  "properties": {
    "addr:full":"2417 Hollers Ave Bronx NY 10475",
    "addr:housenumber":"2417",
    "addr:postcode":"10475",
    "addr:street":"Hollers Ave",
    "iso:country":"US",
    "sg:address":"2417 Hollers Ave",
    "sg:city":"Bronx",
    "sg:classifiers":[
        {
            "category":"Shopping",
            "subcategory":"Bicycles & Sporting Goods",
            "type":"Retail Goods"
        }
    ],
    "sg:phone":"+1 718 882 0238",
    "sg:postcode":"10475",
    "sg:province":"NY",
    "sg:tags":[
        "apparel",
        "equipment",
        "accessory",
        "bowling"
    ],
    "wof:name":"Rock N Robin Pro Shop",
    "wof:placetype":"venue"
},
  "geometry": {"coordinates":[-73.822805,40.885885],"type":"Point"}
}