{
  "type": "Feature",
  "properties": {
    "addr:full":"433 Broome St Ground Floor Manhattan NY 10013",
    "addr:housenumber":"433",
    "addr:postcode":"10013",
    "addr:street":"Broome St",
    "iso:country":"US",
    "sg:address":"433 Broome St Ground Floor",
    "sg:city":"Manhattan",
    "sg:classifiers":[
        {
            "category":"Coffee & Tea",
            "type":"Food & Drink"
        }
    ],
    "sg:phone":"+1 212 933 4853",
    "sg:postcode":"10013",
    "sg:province":"NY",
    "sg:website":"harneysoho.blogspot.com",
    "wof:name":"Harney & Sons SoHo",
    "wof:placetype":"venue"
},
  "geometry": {"coordinates":[-73.99947299999999,40.72133],"type":"Point"}
}