{
  "type": "Feature",
  "properties": {
    "iso:country":"US",
    "sg:address":"1113 Jericho Turnpike",
    "sg:city":"New Hyde Park",
    "sg:classifiers":[
        {
            "category":"Restaurant",
            "type":"Food & Drink"
        }
    ],
    "sg:phone":"+1 516 488 1366",
    "sg:postcode":"11040",
    "sg:province":"NY",
    "sg:tags":[
        "italian",
        "pizza"
    ],
    "wof:name":"Gino's Pizza of New Hyde Park",
    "wof:placetype":"venue"
},
  "geometry": {"coordinates":[-73.68463,40.732733],"type":"Point"}
}