{
  "type": "Feature",
  "properties": {
    "iso:country":"US",
    "sg:address":"30 Brickyard Rd",
    "sg:city":"Troy",
    "sg:classifiers":[
        {
            "category":"Communications",
            "subcategory":"Film & Video Production",
            "type":"Services"
        }
    ],
    "sg:phone":"+1 518 235 3921",
    "sg:postcode":"12182",
    "sg:province":"NY",
    "sg:tags":[
        "repair",
        "equipment-installation"
    ],
    "wof:name":"Msh Visual Planners",
    "wof:placetype":"venue"
},
  "geometry": {"coordinates":[-73.653417,42.790986],"type":"Point"}
}