{
  "type": "Feature",
  "properties": {
    "iso:country":"US",
    "sg:address":"322 W Franklin St",
    "sg:city":"Endicott",
    "sg:classifiers":[
        {
            "category":"Professional",
            "subcategory":"Accounting & Tax Preparation",
            "type":"Services"
        }
    ],
    "sg:phone":"+1 607 754 0880",
    "sg:postcode":"13760",
    "sg:province":"NY",
    "sg:tags":[
        "accountant"
    ],
    "wof:name":"Michael S Ricciardi CPA",
    "wof:placetype":"venue"
},
  "geometry": {"coordinates":[-76.07084,42.100583],"type":"Point"}
}