{
  "type": "Feature",
  "properties": {
    "iso:country":"US",
    "sg:address":"5500 Main St",
    "sg:city":"Buffalo",
    "sg:classifiers":[
        {
            "category":"Professional",
            "subcategory":"Engineering",
            "type":"Services"
        }
    ],
    "sg:phone":"+1 716 634 7644",
    "sg:postcode":"14221",
    "sg:province":"NY",
    "wof:name":"OBrien & Gere Engineers",
    "wof:placetype":"venue"
},
  "geometry": {"coordinates":[-78.747851,42.962356],"type":"Point"}
}