{
  "type": "Feature",
  "properties": {
    "iso:country":"US",
    "sg:address":"48 Quintree Ln",
    "sg:city":"Melville",
    "sg:classifiers":[
        {
            "category":"Professional",
            "subcategory":"Accounting & Tax Preparation",
            "type":"Services"
        }
    ],
    "sg:phone":"+1 631 385 4465",
    "sg:postcode":"11747",
    "sg:province":"NY",
    "sg:tags":[
        "accountant"
    ],
    "wof:name":"Ivy M Davis CPA",
    "wof:placetype":"venue"
},
  "geometry": {"coordinates":[-73.390996,40.802421],"type":"Point"}
}