{
  "type": "Feature",
  "properties": {
    "iso:country":"US",
    "sg:address":"884 Busti-Sugar Grove Rd",
    "sg:city":"Jamestown",
    "sg:classifiers":[
        {
            "category":"Retail",
            "subcategory":"Veterinary Services",
            "type":"Services"
        }
    ],
    "sg:phone":"+1 716 484 0610",
    "sg:postcode":"14701",
    "sg:province":"NY",
    "sg:tags":[
        "veterinarian"
    ],
    "wof:name":"Busti Veterinary Hospital",
    "wof:placetype":"venue"
},
  "geometry": {"coordinates":[-79.284038,42.03752],"type":"Point"}
}