{
  "type": "Feature",
  "properties": {
    "iso:country":"US",
    "sg:address":"21 Lansing Rd S",
    "sg:city":"Schenectady",
    "sg:classifiers":[
        {
            "category":"Professional",
            "type":"Services"
        }
    ],
    "sg:phone":"+1 518 370 2664",
    "sg:postcode":"12304",
    "sg:province":"NY",
    "sg:tags":[
        "establishment"
    ],
    "wof:name":"Islamic Center",
    "wof:placetype":"venue"
},
  "geometry": {"coordinates":[-73.884039,42.759227],"type":"Point"}
}