{
  "type": "Feature",
  "properties": {
    "iso:country":"US",
    "sg:address":"8411 Wright Rd",
    "sg:city":"Hammondsport",
    "sg:classifiers":[
        {
            "category":"Farming",
            "subcategory":"Farm",
            "type":"Manufacturing & Wholesale Goods"
        }
    ],
    "sg:phone":"+1 607 868 7116",
    "sg:postcode":"14840",
    "sg:province":"NY",
    "wof:name":"Medrek Farms Barn",
    "wof:placetype":"venue"
},
  "geometry": {"coordinates":[-77.21584199999999,42.469373],"type":"Point"}
}