{
  "type": "Feature",
  "properties": {
    "iso:country":"US",
    "sg:address":"270 W 39 St",
    "sg:city":"New York",
    "sg:classifiers":[
        {
            "category":"Wholesale",
            "subcategory":"Apparel",
            "type":"Manufacturing & Wholesale Goods"
        }
    ],
    "sg:phone":"+1 212 575 5915",
    "sg:postcode":"10018",
    "sg:province":"NY",
    "sg:tags":[
        "synthetic",
        "converter",
        "textile",
        "jobber",
        "fab",
        "converting",
        "woven",
        "cotton"
    ],
    "wof:name":"Jamie Textiles Inc",
    "wof:placetype":"venue"
},
  "geometry": {"coordinates":[-73.98967500000001,40.754407],"type":"Point"}
}