{
  "type": "Feature",
  "properties": {
    "addr:full":"3233 Knapp Rd Vestal NY 13850",
    "addr:housenumber":"3233",
    "addr:postcode":"13850",
    "addr:street":"Knapp Rd",
    "iso:country":"US",
    "sg:address":"3233 Knapp Rd",
    "sg:city":"Vestal",
    "sg:classifiers":[
        {
            "category":"Professional",
            "type":"Services"
        }
    ],
    "sg:phone":"+1   ",
    "sg:postcode":"13850",
    "sg:province":"NY",
    "wof:name":"Fasten Inc",
    "wof:placetype":"venue"
},
  "geometry": {"coordinates":[-75.994456,42.085969],"type":"Point"}
}