{
  "type": "Feature",
  "properties": {
    "addr:full":"138 E 39 St New York NY 10016",
    "addr:housenumber":"138;39",
    "addr:postcode":"10016",
    "addr:street":"E;St",
    "iso:country":"US",
    "sg:address":"138 E 39 St",
    "sg:city":"New York",
    "sg:classifiers":[
        {
            "category":"Organizations",
            "subcategory":"Religious Organization",
            "type":"Services"
        }
    ],
    "sg:phone":"+1 212 689 7810",
    "sg:postcode":"10016",
    "sg:province":"NY",
    "sg:tags":[
        "church"
    ],
    "sg:website":"www.armenianprelacy.org",
    "wof:name":"Armenian Apostolic Chr-Distofc",
    "wof:placetype":"venue"
},
  "geometry": {"coordinates":[-73.975982,40.748859],"type":"Point"}
}