{
  "type": "Feature",
  "properties": {
    "iso:country":"US",
    "sg:address":"15 Henry St",
    "sg:city":"Binghamton",
    "sg:classifiers":[
        {
            "category":"Government",
            "subcategory":"Police Station",
            "type":"Public Place"
        }
    ],
    "sg:phone":"+1 607 773 2723",
    "sg:postcode":"13901",
    "sg:province":"NY",
    "sg:tags":[
        "protection"
    ],
    "wof:name":"Marshals Service United States",
    "wof:placetype":"venue"
},
  "geometry": {"coordinates":[-75.91206099999999,42.100508],"type":"Point"}
}