{
  "type": "Feature",
  "properties": {
    "addr:full":"212 Williamsburg St E Brooklyn NY 11211",
    "addr:housenumber":"212",
    "addr:postcode":"11211",
    "addr:street":"Williamsburg St E",
    "iso:country":"US",
    "sg:address":"212 Williamsburg St E",
    "sg:city":"Brooklyn",
    "sg:classifiers":[
        {
            "category":"Government",
            "subcategory":"Police Station",
            "type":"Public Place"
        }
    ],
    "sg:phone":"+1 718 963 4168",
    "sg:postcode":"11211",
    "sg:province":"NY",
    "sg:tags":[
        "department"
    ],
    "wof:name":"New York Police Station",
    "wof:placetype":"venue"
},
  "geometry": {"coordinates":[-73.95806399999999,40.705882],"type":"Point"}
}