{
  "type": "Feature",
  "properties": {
    "addr:full":"5613 Fort Hamilton Pkwy Brooklyn NY 11219",
    "addr:housenumber":"5613",
    "addr:postcode":"11219",
    "addr:street":"Fort Hamilton Pkwy",
    "iso:country":"US",
    "sg:address":"5613 Fort Hamilton Pkwy",
    "sg:city":"Brooklyn",
    "sg:classifiers":[
        {
            "category":"Community Center",
            "type":"Public Place"
        }
    ],
    "sg:phone":"+1 718 854 3190",
    "sg:postcode":"11219",
    "sg:province":"NY",
    "sg:tags":[
        "medical"
    ],
    "wof:name":"Wic Program-Maimonides Medical Center",
    "wof:placetype":"venue"
},
  "geometry": {"coordinates":[-74.00309799999999,40.634602],"type":"Point"}
}