{
  "type": "Feature",
  "properties": {
    "addr:full":"1571 Broadway Brooklyn NY 11207",
    "addr:housenumber":"1571",
    "addr:postcode":"11207",
    "addr:street":"Broadway",
    "iso:country":"US",
    "sg:address":"1571 Broadway",
    "sg:city":"Brooklyn",
    "sg:classifiers":[
        {
            "category":"Restaurant",
            "type":"Food & Drink"
        }
    ],
    "sg:menulink":"http://www.allmenus.com/ny/brooklyn/47186-delicias-coffee-shop/menu/",
    "sg:phone":"+1 718 573 7765",
    "sg:postcode":"11207",
    "sg:province":"NY",
    "sg:tags":[
        "american"
    ],
    "wof:name":"Delicias Coffee Shop",
    "wof:placetype":"venue"
},
  "geometry": {"coordinates":[-73.915526,40.685738],"type":"Point"}
}