{
  "type": "Feature",
  "properties": {
    "iso:country":"US",
    "sg:address":"66 New St",
    "sg:city":"Pine Bush",
    "sg:classifiers":[
        {
            "category":"Restaurant",
            "type":"Food & Drink"
        }
    ],
    "sg:phone":"+1 845 744 8315",
    "sg:postcode":"12566",
    "sg:province":"NY",
    "wof:name":"North Street Grill",
    "wof:placetype":"venue"
},
  "geometry": {"coordinates":[-74.29970400000001,41.609787],"type":"Point"}
}