{
  "type": "Feature",
  "properties": {
    "iso:country":"US",
    "sg:address":"3 Neptune Rd Ste 825",
    "sg:city":"Poughkeepsie",
    "sg:classifiers":[
        {
            "category":"Professional",
            "subcategory":"Employment Agencies",
            "type":"Services"
        },
        {
            "category":"Arts & Performance",
            "subcategory":"Theater",
            "type":"Entertainment"
        }
    ],
    "sg:phone":"+1 845 462 5852",
    "sg:postcode":"12601",
    "sg:province":"NY",
    "sg:tags":[
        "modeling",
        "talent",
        "theatrical"
    ],
    "wof:name":"Kids On Tv Scouting & Casting",
    "wof:placetype":"venue"
},
  "geometry": {"coordinates":[-73.92345400000001,41.643396],"type":"Point"}
}