{
  "type": "Feature",
  "properties": {
    "iso:country":"US",
    "sg:address":"76 Green Way Dr",
    "sg:city":"Irvington",
    "sg:classifiers":[
        {
            "category":"Professional",
            "subcategory":"Lawyer & Legal Services",
            "type":"Services"
        }
    ],
    "sg:phone":"+1 914 591 3278",
    "sg:postcode":"10533",
    "sg:province":"NY",
    "sg:tags":[
        "attorney"
    ],
    "wof:name":"Alayne Katz",
    "wof:placetype":"venue"
},
  "geometry": {"coordinates":[-73.86071099999999,41.037865],"type":"Point"}
}