{
  "type": "Feature",
  "properties": {
    "addr:full":"201 Mill St Rome NY 13440",
    "addr:housenumber":"201",
    "addr:postcode":"13440",
    "addr:street":"Mill St",
    "iso:country":"US",
    "sg:address":"201 Mill St",
    "sg:city":"Rome",
    "sg:classifiers":[
        {
            "category":"Shopping",
            "subcategory":"Music",
            "type":"Retail Goods"
        }
    ],
    "sg:phone":"+1   ",
    "sg:postcode":"13440",
    "sg:province":"NY",
    "wof:name":"Rome Ddso Record Room",
    "wof:placetype":"venue"
},
  "geometry": {"coordinates":[-75.44872100000001,43.203041],"type":"Point"}
}