{
  "type": "Feature",
  "properties": {
    "iso:country":"US",
    "sg:address":"451 Clarkson Ave",
    "sg:city":"Brooklyn",
    "sg:classifiers":[
        {
            "category":"Health Services",
            "subcategory":"Doctor",
            "type":"Services"
        }
    ],
    "sg:phone":"+1 718 270 3825",
    "sg:postcode":"11203",
    "sg:province":"NY",
    "sg:tags":[
        "aids"
    ],
    "wof:name":"Brooklyn Pediatric Aids Netwrk",
    "wof:placetype":"venue"
},
  "geometry": {"coordinates":[-73.94356999999999,40.655887],"type":"Point"}
}