{
  "type": "Feature",
  "properties": {
    "iso:country":"US",
    "sg:address":"2 Grovewood Ln",
    "sg:city":"Rochester",
    "sg:classifiers":[
        {
            "category":"Shopping",
            "subcategory":"Discount & Variety Stores",
            "type":"Retail Goods"
        }
    ],
    "sg:phone":"+1 585 429 6520",
    "sg:postcode":"14624",
    "sg:province":"NY",
    "sg:tags":[
        "merchandise",
        "general"
    ],
    "wof:name":"Red Bud Sales",
    "wof:placetype":"venue"
},
  "geometry": {"coordinates":[-77.72114999999999,43.109909],"type":"Point"}
}