{
  "type": "Feature",
  "properties": {
    "iso:country":"US",
    "sg:address":"10 Meadow Sweet Rd",
    "sg:city":"Cortlandt Manor",
    "sg:classifiers":[
        {
            "category":"Professional",
            "subcategory":"Secretarial Services",
            "type":"Services"
        }
    ],
    "sg:phone":"+1 914 788 8712",
    "sg:postcode":"10567",
    "sg:province":"NY",
    "sg:tags":[
        "transcription",
        "medical"
    ],
    "wof:name":"Phoenix Med Com Corp",
    "wof:placetype":"venue"
},
  "geometry": {"coordinates":[-73.854871,41.277992],"type":"Point"}
}