{
  "type": "Feature",
  "properties": {
    "addr:full":"1588 2nd Ave New York NY 10028",
    "addr:housenumber":"1588",
    "addr:postcode":"10028",
    "addr:street":"2Nd Ave",
    "iso:country":"US",
    "sg:address":"1588 2nd Ave",
    "sg:city":"New York",
    "sg:classifiers":[
        {
            "category":"Restaurant",
            "type":"Food & Drink"
        }
    ],
    "sg:phone":"+1 212 396 3339",
    "sg:postcode":"10028",
    "sg:province":"NY",
    "sg:tags":[
        "chinese"
    ],
    "sg:website":"wajealsichuanchilihousenyc.com",
    "wof:name":"Wa Jeal Sichuan Chili House",
    "wof:placetype":"venue"
},
  "geometry": {"coordinates":[-73.953157,40.775352],"type":"Point"}
}