{
  "type": "Feature",
  "properties": {
    "addr:full":"321 E 73 St New York NY 10021",
    "addr:housenumber":"321;73",
    "addr:postcode":"10021",
    "addr:street":"E;St",
    "iso:country":"US",
    "sg:address":"321 E 73 St",
    "sg:city":"New York",
    "sg:classifiers":[
        {
            "category":"Organizations",
            "subcategory":"Non-profit Organization",
            "type":"Services"
        }
    ],
    "sg:phone":"+1 212 265 1919",
    "sg:postcode":"10021",
    "sg:province":"NY",
    "wof:name":"American Fund For Czechoslovak",
    "wof:placetype":"venue"
},
  "geometry": {"coordinates":[-73.955831,40.768754],"type":"Point"}
}