{
  "type": "Feature",
  "properties": {
    "addr:full":"862 Foote Ave Jamestown NY 14701",
    "addr:housenumber":"862",
    "addr:postcode":"14701",
    "addr:street":"Foote Ave",
    "iso:country":"US",
    "sg:address":"862 Foote Ave",
    "sg:city":"Jamestown",
    "sg:classifiers":[
        {
            "category":"Health Services",
            "subcategory":"Clinic",
            "type":"Services"
        }
    ],
    "sg:phone":"+1 716 664 2464",
    "sg:postcode":"14701",
    "sg:province":"NY",
    "sg:tags":[
        "specialty",
        "outpatient"
    ],
    "wof:name":"Resource Center The",
    "wof:placetype":"venue"
},
  "geometry": {"coordinates":[-79.22678000000001,42.077834],"type":"Point"}
}