{
  "type": "Feature",
  "properties": {
    "iso:country":"US",
    "sg:address":"275 Sickles Ave",
    "sg:city":"New Rochelle",
    "sg:classifiers":[
        {
            "category":"Building & Trades",
            "subcategory":"Landscaping Services",
            "type":"Services"
        }
    ],
    "sg:phone":"+1 914 636 3167",
    "sg:postcode":"10801",
    "sg:province":"NY",
    "sg:tags":[
        "landscape"
    ],
    "wof:name":"Acocella Angelo & Sons Ldscpg",
    "wof:placetype":"venue"
},
  "geometry": {"coordinates":[-73.794415,40.914091],"type":"Point"}
}