{
  "type": "Feature",
  "properties": {
    "iso:country":"US",
    "sg:address":"10 Emerson Rd",
    "sg:city":"Hampton Bays",
    "sg:classifiers":[
        {
            "category":"Building & Trades",
            "subcategory":"Construction",
            "type":"Services"
        }
    ],
    "sg:phone":"+1 631 728 2563",
    "sg:postcode":"11951",
    "sg:province":"NY",
    "sg:tags":[
        "general",
        "contractor"
    ],
    "wof:name":"3-D Building & Home Imprvmt",
    "wof:placetype":"venue"
},
  "geometry": {"coordinates":[-72.864113,40.758037],"type":"Point"}
}