{
  "type": "Feature",
  "properties": {
    "addr:full":"124 York St Auburn NY 13021",
    "addr:housenumber":"124",
    "addr:postcode":"13021",
    "addr:street":"York St",
    "iso:country":"US",
    "sg:address":"124 York St",
    "sg:city":"Auburn",
    "sg:classifiers":[
        {
            "category":"Building & Trades",
            "subcategory":"Plumbing",
            "type":"Services"
        }
    ],
    "sg:phone":"+1 315 252 8753",
    "sg:postcode":"13021",
    "sg:province":"NY",
    "sg:tags":[
        "plumbing",
        "air",
        "warm",
        "heating",
        "contractor"
    ],
    "wof:name":"Hares & Weeks Inc",
    "wof:placetype":"venue"
},
  "geometry": {"coordinates":[-76.579701,42.950055],"type":"Point"}
}