{
  "type": "Feature",
  "properties": {
    "iso:country":"US",
    "sg:address":"131 W 35th St",
    "sg:city":"New York",
    "sg:classifiers":[
        {
            "category":"Professional",
            "subcategory":"Computer Services",
            "type":"Services"
        }
    ],
    "sg:phone":"+1 212 249 9888",
    "sg:postcode":"10001",
    "sg:province":"NY",
    "sg:tags":[
        "repair"
    ],
    "sg:website":"www.sherlockdaterecovery.com",
    "wof:name":"ATOMIC BYTES",
    "wof:placetype":"venue"
},
  "geometry": {"coordinates":[-73.988428,40.751112],"type":"Point"}
}