{
  "type": "Feature",
  "properties": {
    "iso:country":"US",
    "sg:address":"711 3rd Ave",
    "sg:city":"New York",
    "sg:classifiers":[
        {
            "category":"Organizations",
            "subcategory":"Non-profit Organization",
            "type":"Services"
        }
    ],
    "sg:phone":"+1 212 687 6200",
    "sg:postcode":"10017",
    "sg:province":"NY",
    "sg:tags":[
        "service/non-profit",
        "community"
    ],
    "sg:website":"www.jdc.org/",
    "wof:name":"Joint Distribution Committee",
    "wof:placetype":"venue"
},
  "geometry": {"coordinates":[-73.97305,40.75228],"type":"Point"}
}