{
  "type": "Feature",
  "properties": {
    "addr:full":"646 9 Ave New York NY 10036",
    "addr:housenumber":"646",
    "addr:postcode":"10036",
    "addr:street":"9 Ave",
    "iso:country":"US",
    "sg:address":"646 9 Ave",
    "sg:city":"New York",
    "sg:classifiers":[
        {
            "category":"Retail",
            "subcategory":"Repair Shop",
            "type":"Services"
        }
    ],
    "sg:phone":"+1 212 819 0035",
    "sg:postcode":"10036",
    "sg:province":"NY",
    "sg:tags":[
        "lock",
        "locksmith"
    ],
    "wof:name":"Cosmic Door Equipment Co",
    "wof:placetype":"venue"
},
  "geometry": {"coordinates":[-73.992633,40.75843],"type":"Point"}
}