{
  "type": "Feature",
  "properties": {
    "iso:country":"US",
    "sg:address":"16725 Rockaway Blvd",
    "sg:city":"Jamaica",
    "sg:classifiers":[
        {
            "category":"Transit Center",
            "subcategory":"Freight",
            "type":"Transportation"
        }
    ],
    "sg:phone":"+1 718 656 1237",
    "sg:postcode":"11434",
    "sg:province":"NY",
    "sg:tags":[
        "air",
        "cargo",
        "express",
        "package"
    ],
    "sg:website":"http://www.czechairlinescargo.com",
    "wof:name":"Air Mark",
    "wof:placetype":"venue"
},
  "geometry": {"coordinates":[-73.77512400000001,40.660151],"type":"Point"}
}