{
  "type": "Feature",
  "properties": {
    "iso:country":"US",
    "sg:address":"122 E 57th St",
    "sg:city":"New York",
    "sg:classifiers":[
        {
            "category":"Wholesale",
            "subcategory":"Drugs",
            "type":"Manufacturing & Wholesale Goods"
        }
    ],
    "sg:phone":"+1 917 838 6037",
    "sg:postcode":"10022",
    "sg:province":"NY",
    "sg:tags":[
        "aid",
        "product",
        "health",
        "beauty"
    ],
    "wof:name":"Allstate Beauty",
    "wof:placetype":"venue"
},
  "geometry": {"coordinates":[-73.97013099999999,40.761398],"type":"Point"}
}