{
  "type": "Feature",
  "properties": {
    "addr:full":"4051 194th St 20 Flushing NY 11358",
    "addr:housenumber":"4051;20",
    "addr:postcode":"11358",
    "addr:street":"194Th St",
    "iso:country":"US",
    "sg:address":"4051 194th St 20",
    "sg:city":"Flushing",
    "sg:classifiers":[
        {
            "category":"Personal",
            "subcategory":"Beauty Salon",
            "type":"Services"
        }
    ],
    "sg:phone":"+1 718 423 1205",
    "sg:postcode":"11358",
    "sg:province":"NY",
    "wof:name":"Hair Character",
    "wof:placetype":"venue"
},
  "geometry": {"coordinates":[-73.787952,40.760384],"type":"Point"}
}