{
  "type": "Feature",
  "properties": {
    "addr:full":"131 E Manlius St East Syracuse NY 13057",
    "addr:housenumber":"131",
    "addr:postcode":"13057",
    "addr:street":"E Manlius St",
    "iso:country":"US",
    "sg:address":"131 E Manlius St",
    "sg:city":"East Syracuse",
    "sg:classifiers":[
        {
            "category":"Shopping",
            "subcategory":"Department Store",
            "type":"Retail Goods"
        }
    ],
    "sg:phone":"+1 315 437 8942",
    "sg:postcode":"13057",
    "sg:province":"NY",
    "sg:website":"www.sacksstore.com",
    "wof:name":"Sack's Department Store",
    "wof:placetype":"venue"
},
  "geometry": {"coordinates":[-76.06917300000001,43.063973],"type":"Point"}
}