{
  "type": "Feature",
  "properties": {
    "iso:country":"US",
    "sg:address":"6300 E Port Bay Rd",
    "sg:city":"Wolcott",
    "sg:classifiers":[
        {
            "category":"Shopping",
            "subcategory":"Bicycles & Sporting Goods",
            "type":"Retail Goods"
        }
    ],
    "sg:phone":"+1 315 594 6621",
    "sg:postcode":"14590",
    "sg:province":"NY",
    "wof:name":"Stewart's Collectors Shop",
    "wof:placetype":"venue"
},
  "geometry": {"coordinates":[-76.80911399999999,43.227367],"type":"Point"}
}