{
  "type": "Feature",
  "properties": {
    "iso:country":"US",
    "sg:address":"217 Nabinger Hill Rd",
    "sg:city":"Nineveh",
    "sg:classifiers":[
        {
            "category":"Wholesale",
            "subcategory":"Durable Goods & Equipment",
            "type":"Manufacturing & Wholesale Goods"
        }
    ],
    "sg:phone":"+1 607 693 2302",
    "sg:postcode":"13813",
    "sg:province":"NY",
    "wof:name":"Walnut Acres Inc",
    "wof:placetype":"venue"
},
  "geometry": {"coordinates":[-75.58372900000001,42.169475],"type":"Point"}
}