{
  "type": "Feature",
  "properties": {
    "iso:country":"US",
    "sg:address":"140 W 57 St",
    "sg:city":"New York",
    "sg:classifiers":[
        {
            "category":"Professional",
            "subcategory":"Employment Agencies",
            "type":"Services"
        }
    ],
    "sg:phone":"+1 212 586 7672",
    "sg:postcode":"10019",
    "sg:province":"NY",
    "sg:tags":[
        "consultant",
        "search",
        "executive"
    ],
    "wof:name":"Next Search Group",
    "wof:placetype":"venue"
},
  "geometry": {"coordinates":[-73.978838,40.764768],"type":"Point"}
}