{
  "type": "Feature",
  "properties": {
    "iso:country":"US",
    "sg:address":"1955 1st Avenue Apt 342",
    "sg:city":"New York",
    "sg:classifiers":[
        {
            "category":"Building & Trades",
            "subcategory":"Construction",
            "type":"Services"
        }
    ],
    "sg:phone":"+1 212 931 0325",
    "sg:postcode":"10029",
    "sg:province":"NY",
    "sg:tags":[
        "interior",
        "design"
    ],
    "wof:name":"Fusion Design Studio",
    "wof:placetype":"venue"
},
  "geometry": {"coordinates":[-73.942714,40.785979],"type":"Point"}
}