{
  "type": "Feature",
  "properties": {
    "addr:full":"302 Walnut Ave Bronx NY 10454",
    "addr:housenumber":"302",
    "addr:postcode":"10454",
    "addr:street":"Walnut Ave",
    "iso:country":"US",
    "sg:address":"302 Walnut Ave",
    "sg:city":"Bronx",
    "sg:classifiers":[
        {
            "category":"Local Transit",
            "type":"Transportation"
        }
    ],
    "sg:phone":"+1 718 292 1010",
    "sg:postcode":"10454",
    "sg:province":"NY",
    "sg:tags":[
        "limousine"
    ],
    "wof:name":"Delroy Limousine Svc",
    "wof:placetype":"venue"
},
  "geometry": {"coordinates":[-73.906673,40.804469],"type":"Point"}
}