{
  "type": "Feature",
  "properties": {
    "iso:country":"US",
    "sg:address":"87 Fulton St",
    "sg:city":"White Plains",
    "sg:classifiers":[
        {
            "category":"Autos & Motor Vehicles",
            "subcategory":"Fuel & Gas Station",
            "type":"Retail Goods"
        }
    ],
    "sg:phone":"+1 914 428 7185",
    "sg:postcode":"10606",
    "sg:province":"NY",
    "sg:tags":[
        "oil"
    ],
    "wof:name":"Proper Service Ctr",
    "wof:placetype":"venue"
},
  "geometry": {"coordinates":[-73.784949,41.035078],"type":"Point"}
}