{
  "type": "Feature",
  "properties": {
    "iso:country":"US",
    "sg:address":"824 Pre Emption Rd",
    "sg:city":"Geneva",
    "sg:classifiers":[
        {
            "category":"Social Services",
            "subcategory":"Adult Care",
            "type":"Services"
        }
    ],
    "sg:phone":"+1 315 789 7704",
    "sg:postcode":"14456",
    "sg:province":"NY",
    "sg:tags":[
        "residential"
    ],
    "wof:name":"Ontario County A R C",
    "wof:placetype":"venue"
},
  "geometry": {"coordinates":[-77.01102,42.861432],"type":"Point"}
}