{
  "type": "Feature",
  "properties": {
    "addr:full":"3565 Hylan Blvd Staten Island NY 10308",
    "addr:housenumber":"3565",
    "addr:postcode":"10308",
    "addr:street":"Hylan Blvd",
    "iso:country":"US",
    "sg:address":"3565 Hylan Blvd",
    "sg:city":"Staten Island",
    "sg:classifiers":[
        {
            "category":"Social Services",
            "subcategory":"Adult Care",
            "type":"Services"
        }
    ],
    "sg:phone":"+1 718 979 3600",
    "sg:postcode":"10308",
    "sg:province":"NY",
    "sg:tags":[
        "home"
    ],
    "wof:name":"Hylan Manor Center Inc",
    "wof:placetype":"venue"
},
  "geometry": {"coordinates":[-74.135214,40.551141],"type":"Point"}
}