{
  "type": "Feature",
  "properties": {
    "iso:country":"US",
    "sg:address":"616 Livonia Ave",
    "sg:city":"Brooklyn",
    "sg:classifiers":[
        {
            "category":"Restaurant",
            "type":"Food & Drink"
        }
    ],
    "sg:phone":"+1   ",
    "sg:postcode":"11207",
    "sg:province":"NY",
    "sg:tags":[
        "eating"
    ],
    "wof:name":"Leslies Restaurant",
    "wof:placetype":"venue"
},
  "geometry": {"coordinates":[-73.894497,40.664582],"type":"Point"}
}