{
  "type": "Feature",
  "properties": {
    "addr:full":"3180 Latta Rd Ste 600 Rochester NY 14612",
    "addr:housenumber":"3180",
    "addr:postcode":"14612",
    "addr:street":"Latta Rd Ste 600",
    "iso:country":"US",
    "sg:address":"3180 Latta Rd Ste 600",
    "sg:city":"Rochester",
    "sg:classifiers":[
        {
            "category":"Manufacturing",
            "subcategory":"Buildings",
            "type":"Manufacturing & Wholesale Goods"
        },
        {
            "category":"Home & Garden",
            "subcategory":"Building Materials",
            "type":"Retail Goods"
        },
        {
            "category":"Building & Trades",
            "subcategory":"Construction",
            "type":"Services"
        }
    ],
    "sg:phone":"+1 585 720 0990",
    "sg:postcode":"14612",
    "sg:province":"NY",
    "sg:tags":[
        "roofing",
        "altering",
        "consultant",
        "builder",
        "improvement",
        "siding",
        "contractor",
        "remodeling"
    ],
    "sg:website":"http://www.nypatriot.com",
    "wof:name":"Patriot Construction",
    "wof:placetype":"venue"
},
  "geometry": {"coordinates":[-77.69771900000001,43.253004],"type":"Point"}
}