{
  "type": "Feature",
  "properties": {
    "iso:country":"US",
    "sg:address":"51 Old Rte 9",
    "sg:city":"Wappingers Falls",
    "sg:classifiers":[
        {
            "category":"Professional",
            "subcategory":"Management & Consulting",
            "type":"Services"
        }
    ],
    "sg:phone":"+1 845 297 2719",
    "sg:postcode":"12590",
    "sg:province":"NY",
    "sg:tags":[
        "consultant",
        "security",
        "system"
    ],
    "wof:name":"Custom Monitoring",
    "wof:placetype":"venue"
},
  "geometry": {"coordinates":[-73.909503,41.586772],"type":"Point"}
}