{
  "type": "Feature",
  "properties": {
    "iso:country":"US",
    "sg:address":"73 Grand St",
    "sg:city":"New York",
    "sg:classifiers":[
        {
            "category":"Health Services",
            "subcategory":"Chiropractor",
            "type":"Services"
        }
    ],
    "sg:phone":"+1 212 899 5433",
    "sg:postcode":"10013",
    "sg:province":"NY",
    "wof:name":"Robert Marchese DC",
    "wof:placetype":"venue"
},
  "geometry": {"coordinates":[-74.00232099999999,40.721605],"type":"Point"}
}