{
  "type": "Feature",
  "properties": {
    "iso:country":"US",
    "sg:address":"1745 Armory Dr",
    "sg:city":"Utica",
    "sg:classifiers":[
        {
            "category":"Government",
            "subcategory":"Office",
            "type":"Public Place"
        }
    ],
    "sg:phone":"+1 315 724 1489",
    "sg:postcode":"13501",
    "sg:province":"NY",
    "sg:tags":[
        "aviation",
        "support",
        "army"
    ],
    "wof:name":"Oms 6",
    "wof:placetype":"venue"
},
  "geometry": {"coordinates":[-75.209417,43.078572],"type":"Point"}
}