{
  "type": "Feature",
  "properties": {
    "addr:full":"561 Waite Rd Rexford NY 12148",
    "addr:housenumber":"561",
    "addr:postcode":"12148",
    "addr:street":"Waite Rd",
    "iso:country":"US",
    "sg:address":"561 Waite Rd",
    "sg:city":"Rexford",
    "sg:classifiers":[
        {
            "category":"Freight",
            "type":"Transportation"
        }
    ],
    "sg:phone":"+1   ",
    "sg:postcode":"12148",
    "sg:province":"NY",
    "sg:tags":[
        "operator",
        "local",
        "trucking"
    ],
    "wof:name":"Vanauken Trucking Inc",
    "wof:placetype":"venue"
},
  "geometry": {"coordinates":[-73.843507,42.861142],"type":"Point"}
}