{
  "type": "Feature",
  "properties": {
    "addr:full":"3424 Boston Rd Bronx NY 10469",
    "addr:housenumber":"3424",
    "addr:postcode":"10469",
    "addr:street":"Boston Rd",
    "iso:country":"US",
    "sg:address":"3424 Boston Rd",
    "sg:city":"Bronx",
    "sg:classifiers":[
        {
            "category":"Personal",
            "subcategory":"Beauty Salon",
            "type":"Services"
        },
        {
            "category":"Shopping",
            "subcategory":"Clothing, Apparel, & Fashions",
            "type":"Retail Goods"
        }
    ],
    "sg:phone":"+1 718 654 9309",
    "sg:postcode":"10469",
    "sg:province":"NY",
    "wof:name":"Wig Fashions",
    "wof:placetype":"venue"
},
  "geometry": {"coordinates":[-73.849141,40.876039],"type":"Point"}
}