{
  "type": "Feature",
  "properties": {
    "addr:full":"43 Main St Canton NY 13617",
    "addr:housenumber":"43",
    "addr:postcode":"13617",
    "addr:street":"Main St",
    "iso:country":"US",
    "sg:address":"43 Main St",
    "sg:city":"Canton",
    "sg:classifiers":[
        {
            "category":"Restaurant",
            "type":"Food & Drink"
        }
    ],
    "sg:phone":"+1 315 386 3778",
    "sg:postcode":"13617",
    "sg:province":"NY",
    "wof:name":"A-1 Oriental Kitchen",
    "wof:placetype":"venue"
},
  "geometry": {"coordinates":[-74.708033,44.901868],"type":"Point"}
}