{
  "type": "Feature",
  "properties": {
    "addr:full":"216 Kings Hwy Brooklyn NY 11223",
    "addr:housenumber":"216",
    "addr:postcode":"11223",
    "addr:street":"Kings Hwy",
    "iso:country":"US",
    "sg:address":"216 Kings Hwy",
    "sg:city":"Brooklyn",
    "sg:classifiers":[
        {
            "category":"Food & Beverages",
            "subcategory":"Groceries & Convenience Stores",
            "type":"Retail Goods"
        }
    ],
    "sg:phone":"+1 718 266 9370",
    "sg:postcode":"11223",
    "sg:province":"NY",
    "sg:tags":[
        "grocer"
    ],
    "wof:name":"Kings Hwy Mini-Mart",
    "wof:placetype":"venue"
},
  "geometry": {"coordinates":[-73.98282,40.605355],"type":"Point"}
}