{
  "type": "Feature",
  "properties": {
    "addr:full":"101 Broad St Plattsburgh NY 12901",
    "addr:housenumber":"101",
    "addr:postcode":"12901",
    "addr:street":"Broad St",
    "iso:country":"US",
    "sg:address":"101 Broad St",
    "sg:city":"Plattsburgh",
    "sg:classifiers":[
        {
            "category":"Social Services",
            "subcategory":"Child Care",
            "type":"Services"
        }
    ],
    "sg:phone":"+1 518 564 2273",
    "sg:postcode":"12901",
    "sg:province":"NY",
    "sg:tags":[
        "day"
    ],
    "wof:name":"Suny Plttsburgh Child Care Ctr",
    "wof:placetype":"venue"
},
  "geometry": {"coordinates":[-73.46396300000001,44.694581],"type":"Point"}
}