{
  "type": "Feature",
  "properties": {
    "iso:country":"US",
    "sg:address":"45 Palo Alto Dr",
    "sg:city":"Hampton Bays",
    "sg:classifiers":[
        {
            "category":"Real Estate",
            "subcategory":"Real Estate Agent",
            "type":"Services"
        }
    ],
    "sg:phone":"+1 631 728 2827",
    "sg:postcode":"11946",
    "sg:province":"NY",
    "wof:name":"Hampton Bays Online",
    "wof:placetype":"venue"
},
  "geometry": {"coordinates":[-72.50292399999999,40.86812],"type":"Point"}
}