{
  "type": "Feature",
  "properties": {
    "addr:full":"1145 Boston Rd Bronx NY 10456",
    "addr:housenumber":"1145",
    "addr:postcode":"10456",
    "addr:street":"Boston Rd",
    "iso:country":"US",
    "sg:address":"1145 Boston Rd",
    "sg:city":"Bronx",
    "sg:classifiers":[
        {
            "category":"Food & Beverages",
            "subcategory":"Groceries & Convenience Stores",
            "type":"Retail Goods"
        }
    ],
    "sg:phone":"+1 718 589 6358",
    "sg:postcode":"10456",
    "sg:province":"NY",
    "sg:tags":[
        "grocer"
    ],
    "wof:name":"Perez Deli Groceries",
    "wof:placetype":"venue"
},
  "geometry": {"coordinates":[-73.902748,40.829167],"type":"Point"}
}