{
  "type": "Feature",
  "properties": {
    "addr:full":"7 Pine Pl Lindenhurst NY 11757",
    "addr:housenumber":"7",
    "addr:postcode":"11757",
    "addr:street":"Pine Pl",
    "iso:country":"US",
    "sg:address":"7 Pine Pl",
    "sg:city":"Lindenhurst",
    "sg:classifiers":[
        {
            "category":"Organizations",
            "subcategory":"Community Association",
            "type":"Services"
        }
    ],
    "sg:phone":"+1 631 957 1100",
    "sg:postcode":"11757",
    "sg:province":"NY",
    "sg:tags":[
        "club"
    ],
    "wof:name":"Long Island Parrot Society",
    "wof:placetype":"venue"
},
  "geometry": {"coordinates":[-73.350094,40.672813],"type":"Point"}
}