{
  "type": "Feature",
  "properties": {
    "addr:full":"53 N Park Ave Rockville Centre NY 11570",
    "addr:housenumber":"53",
    "addr:postcode":"11570",
    "addr:street":"N Park Ave",
    "iso:country":"US",
    "sg:address":"53 N Park Ave",
    "sg:city":"Rockville Centre",
    "sg:classifiers":[
        {
            "category":"Banks & Credit Unions",
            "subcategory":"Investment Brokerage",
            "type":"Services"
        },
        {
            "category":"Professional",
            "subcategory":"Management & Consulting",
            "type":"Services"
        }
    ],
    "sg:phone":"+1 516 872 4900",
    "sg:postcode":"11570",
    "sg:province":"NY",
    "sg:tags":[
        "business"
    ],
    "wof:name":"Bonnie Management Company Inc",
    "wof:placetype":"venue"
},
  "geometry": {"coordinates":[-73.64501799999999,40.658286],"type":"Point"}
}