{
  "type": "Feature",
  "properties": {
    "iso:country":"US",
    "sg:address":"379 N Bedford Rd",
    "sg:city":"Mount Kisco",
    "sg:classifiers":[
        {
            "category":"Autos & Motor Vehicles",
            "subcategory":"Auto Supplies",
            "type":"Retail Goods"
        }
    ],
    "sg:phone":"+1 914 666 4970",
    "sg:postcode":"10549",
    "sg:province":"NY",
    "sg:tags":[
        "glass"
    ],
    "wof:name":"Diamond Triumph Glass",
    "wof:placetype":"venue"
},
  "geometry": {"coordinates":[-73.717022,41.219893],"type":"Point"}
}