{
  "type": "Feature",
  "properties": {
    "iso:country":"US",
    "sg:address":"347 5th Ave",
    "sg:city":"Brooklyn",
    "sg:classifiers":[
        {
            "category":"Shopping",
            "subcategory":"Shoes",
            "type":"Retail Goods"
        }
    ],
    "sg:phone":"+1 718 369 2417",
    "sg:postcode":"11215",
    "sg:province":"NY",
    "sg:tags":[
        "store"
    ],
    "wof:name":"Wonderland NYC Inc",
    "wof:placetype":"venue"
},
  "geometry": {"coordinates":[-73.983842,40.671831],"type":"Point"}
}