{
  "type": "Feature",
  "properties": {
    "addr:full":"15 W. 45th St New York NY 10036",
    "addr:housenumber":"15",
    "addr:postcode":"10036",
    "addr:street":"W. 45Th St",
    "iso:country":"US",
    "sg:address":"15 W. 45th St",
    "sg:city":"New York",
    "sg:classifiers":[
        {
            "category":"Bagels",
            "subcategory":"None",
            "type":"Food & Drink"
        }
    ],
    "sg:phone":"+1 212 764 1566",
    "sg:postcode":"10036",
    "sg:province":"NY",
    "wof:name":"Mom's Bagels and Tables Inc.",
    "wof:placetype":"venue"
},
  "geometry": {"coordinates":[-73.980321,40.755763],"type":"Point"}
}