{
  "type": "Feature",
  "properties": {
    "iso:country":"US",
    "sg:address":"82 Montague St",
    "sg:city":"Brooklyn",
    "sg:classifiers":[
        {
            "category":"Retail",
            "subcategory":"Portrait Studio",
            "type":"Services"
        }
    ],
    "sg:phone":"+1 718 237 6070",
    "sg:postcode":"11201",
    "sg:province":"NY",
    "sg:tags":[
        "laboratory",
        "photofinishing",
        "photo"
    ],
    "wof:name":"Cincinnati Photo Inc",
    "wof:placetype":"venue"
},
  "geometry": {"coordinates":[-73.996971,40.695549],"type":"Point"}
}