{
  "type": "Feature",
  "properties": {
    "addr:full":"181 W Merrick Rd Valley Stream NY 11580",
    "addr:housenumber":"181",
    "addr:postcode":"11580",
    "addr:street":"W Merrick Rd",
    "iso:country":"US",
    "sg:address":"181 W Merrick Rd",
    "sg:city":"Valley Stream",
    "sg:classifiers":[
        {
            "category":"Restaurant",
            "type":"Food & Drink"
        }
    ],
    "sg:phone":"+1 516 561 9411",
    "sg:postcode":"11580",
    "sg:province":"NY",
    "sg:website":"www.burgerking.com",
    "wof:name":"Burger King",
    "wof:placetype":"venue"
},
  "geometry": {"coordinates":[-73.7024,40.665798],"type":"Point"}
}