{
  "type": "Feature",
  "properties": {
    "addr:full":"1770 Central Ave Albany NY 12205",
    "addr:housenumber":"1770",
    "addr:postcode":"12205",
    "addr:street":"Central Ave",
    "iso:country":"US",
    "sg:address":"1770 Central Ave",
    "sg:city":"Albany",
    "sg:classifiers":[
        {
            "category":"Coffee & Tea",
            "type":"Food & Drink"
        },
        {
            "category":"Bagels",
            "type":"Food & Drink"
        }
    ],
    "sg:menulink":"http://www.allmenus.com/ny/colonie/62881-brueggers/menu/",
    "sg:phone":"+1 518 464 0363",
    "sg:postcode":"12205",
    "sg:province":"NY",
    "sg:tags":[
        "wrap",
        "soup",
        "american",
        "sandwich",
        "salad"
    ],
    "wof:name":"Bruegger's",
    "wof:placetype":"venue"
},
  "geometry": {"coordinates":[-73.84647699999999,42.728526],"type":"Point"}
}