{
  "type": "Feature",
  "properties": {
    "addr:full":"3215 Far Reach Dr Baldwinsville NY 13027",
    "addr:housenumber":"3215",
    "addr:postcode":"13027",
    "addr:street":"Far Reach Dr",
    "iso:country":"US",
    "sg:address":"3215 Far Reach Dr",
    "sg:city":"Baldwinsville",
    "sg:classifiers":[
        {
            "category":"Shopping",
            "subcategory":"Catalog Store",
            "type":"Retail Goods"
        }
    ],
    "sg:phone":"+1   ",
    "sg:postcode":"13027",
    "sg:province":"NY",
    "sg:tags":[
        "mail",
        "house"
    ],
    "wof:name":"S D Dupen Enterprises",
    "wof:placetype":"venue"
},
  "geometry": {"coordinates":[-76.289806,43.20351],"type":"Point"}
}