{
  "type": "Feature",
  "properties": {
    "iso:country":"US",
    "sg:address":"369 Browns Rd",
    "sg:city":"Walden",
    "sg:classifiers":[
        {
            "category":"Building & Trades",
            "subcategory":"Construction",
            "type":"Services"
        }
    ],
    "sg:phone":"+1 845 567 9855",
    "sg:postcode":"12586",
    "sg:province":"NY",
    "sg:tags":[
        "general",
        "contractor"
    ],
    "wof:name":"Dennis Wayne Contracting",
    "wof:placetype":"venue"
},
  "geometry": {"coordinates":[-74.145366,41.527937],"type":"Point"}
}