{
  "type": "Feature",
  "properties": {
    "addr:full":"226 Turk Rd Geneva NY 14456",
    "addr:housenumber":"226",
    "addr:postcode":"14456",
    "addr:street":"Turk Rd",
    "iso:country":"US",
    "sg:address":"226 Turk Rd",
    "sg:city":"Geneva",
    "sg:classifiers":[
        {
            "category":"Recreation",
            "type":"Entertainment"
        }
    ],
    "sg:phone":"+1 315 781 2180",
    "sg:postcode":"14456",
    "sg:province":"NY",
    "sg:tags":[
        "club",
        "country"
    ],
    "wof:name":"Seneca Lake Country Club",
    "wof:placetype":"venue"
},
  "geometry": {"coordinates":[-76.98021799999999,42.822191],"type":"Point"}
}