{
  "type": "Feature",
  "properties": {
    "addr:full":"88 Lexington Avenue Brooklyn NY 11238",
    "addr:housenumber":"88",
    "addr:postcode":"11238",
    "addr:street":"Lexington Avenue",
    "iso:country":"US",
    "sg:address":"88 Lexington Avenue",
    "sg:city":"Brooklyn",
    "sg:classifiers":[
        {
            "category":"Real Estate",
            "subcategory":"Architect",
            "type":"Services"
        }
    ],
    "sg:phone":"+1 718 230 4468",
    "sg:postcode":"11238",
    "sg:province":"NY",
    "wof:name":"Rmf Bryant Architects",
    "wof:placetype":"venue"
},
  "geometry": {"coordinates":[-73.95863900000001,40.686775],"type":"Point"}
}