{
  "type": "Feature",
  "properties": {
    "addr:full":"141 E 55th St New York NY 10022",
    "addr:housenumber":"141",
    "addr:postcode":"10022",
    "addr:street":"E 55Th St",
    "iso:country":"US",
    "sg:address":"141 E 55th St",
    "sg:city":"New York",
    "sg:classifiers":[
        {
            "category":"Health Services",
            "subcategory":"Health Practitioner",
            "type":"Services"
        },
        {
            "category":"Health Services",
            "subcategory":"Chiropractor",
            "type":"Services"
        }
    ],
    "sg:phone":"+1 212 355 5136",
    "sg:postcode":"10022",
    "sg:province":"NY",
    "sg:tags":[
        "nutritionist"
    ],
    "sg:website":"www.drshockey.com",
    "wof:name":"New Century Midtown East Chiropractors Dr. Edmund Shockey",
    "wof:placetype":"venue"
},
  "geometry": {"coordinates":[-73.969842,40.759684],"type":"Point"}
}