{
  "type": "Feature",
  "properties": {
    "iso:country":"US",
    "sg:address":"148 Hamilton St",
    "sg:city":"Geneva",
    "sg:classifiers":[
        {
            "category":"Insurance",
            "subcategory":"Insurance Agent",
            "type":"Services"
        }
    ],
    "sg:phone":"+1 315 789 9252",
    "sg:postcode":"14456",
    "sg:province":"NY",
    "wof:name":"Morley Financial Services",
    "wof:placetype":"venue"
},
  "geometry": {"coordinates":[-76.98840800000001,42.860172],"type":"Point"}
}