{
  "type": "Feature",
  "properties": {
    "addr:full":"9 Lake Ave Center Moriches NY 11934",
    "addr:housenumber":"9",
    "addr:postcode":"11934",
    "addr:street":"Lake Ave Center",
    "iso:country":"US",
    "sg:address":"9 Lake Ave",
    "sg:city":"Center Moriches",
    "sg:classifiers":[
        {
            "category":"Professional",
            "subcategory":"Computer Services",
            "type":"Services"
        }
    ],
    "sg:phone":"+1 631 874 2510",
    "sg:postcode":"11934",
    "sg:province":"NY",
    "sg:tags":[
        "repair"
    ],
    "wof:name":"Friendly Computers",
    "wof:placetype":"venue"
},
  "geometry": {"coordinates":[-72.79787899999999,40.798839],"type":"Point"}
}