{
  "type": "Feature",
  "properties": {
    "addr:full":"18 Carlton Rd Monsey NY 10952",
    "addr:housenumber":"18",
    "addr:postcode":"10952",
    "addr:street":"Carlton Rd",
    "iso:country":"US",
    "sg:address":"18 Carlton Rd",
    "sg:city":"Monsey",
    "sg:classifiers":[
        {
            "category":"Professional",
            "subcategory":"Printing & Photocopies",
            "type":"Services"
        }
    ],
    "sg:phone":"+1 212 584 9528",
    "sg:postcode":"10952",
    "sg:province":"NY",
    "sg:tags":[
        "lithographer"
    ],
    "wof:name":"Lamesa Printing Co",
    "wof:placetype":"venue"
},
  "geometry": {"coordinates":[-74.071983,41.123009],"type":"Point"}
}