{
  "type": "Feature",
  "properties": {
    "addr:full":"116 Spruce St Cedarhurst NY 11516",
    "addr:housenumber":"116",
    "addr:postcode":"11516",
    "addr:street":"Spruce St",
    "iso:country":"US",
    "sg:address":"116 Spruce St",
    "sg:city":"Cedarhurst",
    "sg:classifiers":[
        {
            "category":"Professional",
            "subcategory":"Lawyer & Legal Services",
            "type":"Services"
        }
    ],
    "sg:phone":"+1 516 374 3023",
    "sg:postcode":"11516",
    "sg:province":"NY",
    "sg:tags":[
        "attorney"
    ],
    "wof:name":"Glinkenhouse Floumanhaft Queen",
    "wof:placetype":"venue"
},
  "geometry": {"coordinates":[-73.72548399999999,40.621304],"type":"Point"}
}