{
  "type": "Feature",
  "properties": {
    "addr:full":"1906 Willis Ave Merrick NY 11566",
    "addr:housenumber":"1906",
    "addr:postcode":"11566",
    "addr:street":"Willis Ave",
    "iso:country":"US",
    "sg:address":"1906 Willis Ave",
    "sg:city":"Merrick",
    "sg:classifiers":[
        {
            "category":"Building & Trades",
            "subcategory":"Pest Control",
            "type":"Services"
        }
    ],
    "sg:phone":"+1   ",
    "sg:postcode":"11566",
    "sg:province":"NY",
    "wof:name":"Sentry Exterminating Company",
    "wof:placetype":"venue"
},
  "geometry": {"coordinates":[-73.560018,40.671205],"type":"Point"}
}