{
  "type": "Feature",
  "properties": {
    "addr:full":"776 Summa Ave Westbury NY 11590",
    "addr:housenumber":"776",
    "addr:postcode":"11590",
    "addr:street":"Summa Ave",
    "iso:country":"US",
    "sg:address":"776 Summa Ave",
    "sg:city":"Westbury",
    "sg:classifiers":[
        {
            "category":"Organizations",
            "subcategory":"Religious Organization",
            "type":"Services"
        }
    ],
    "sg:phone":"+1 516 334 2479",
    "sg:postcode":"11590",
    "sg:province":"NY",
    "wof:name":"Dar-Ul Tabligh",
    "wof:placetype":"venue"
},
  "geometry": {"coordinates":[-73.55716099999999,40.758682],"type":"Point"}
}