{
  "type": "Feature",
  "properties": {
    "addr:full":"3184 Grand Concourse Bronx NY 10458",
    "addr:housenumber":"3184",
    "addr:postcode":"10458",
    "addr:street":"Grand Concourse",
    "iso:country":"US",
    "sg:address":"3184 Grand Concourse",
    "sg:city":"Bronx",
    "sg:classifiers":[
        {
            "category":"Health Services",
            "subcategory":"Doctor",
            "type":"Services"
        }
    ],
    "sg:phone":"+1 718 584 7100",
    "sg:postcode":"10458",
    "sg:province":"NY",
    "sg:tags":[
        "physician",
        "surgeon"
    ],
    "wof:name":"Patel Medical Assoc",
    "wof:placetype":"venue"
},
  "geometry": {"coordinates":[-73.885413,40.876885],"type":"Point"}
}