{
  "type": "Feature",
  "properties": {
    "addr:full":"99 John Street Suite 224 New York NY 10038",
    "addr:housenumber":"99;224",
    "addr:postcode":"10038",
    "addr:street":"John Street Suite",
    "iso:country":"US",
    "sg:address":"99 John Street Suite 224",
    "sg:city":"New York",
    "sg:classifiers":[
        {
            "category":"Professional",
            "subcategory":"Computer Services",
            "type":"Services"
        }
    ],
    "sg:phone":"+1 315 569 4259",
    "sg:postcode":"10038",
    "sg:province":"NY",
    "sg:tags":[
        "twitter",
        "bingo",
        "tweet",
        "game",
        "prizes"
    ],
    "sg:website":"http://www.twibingo.com",
    "wof:name":"Twibingo",
    "wof:placetype":"venue"
},
  "geometry": {"coordinates":[-74.006531,40.708227],"type":"Point"}
}