{
  "type": "Feature",
  "properties": {
    "iso:country":"US",
    "sg:address":"1009 Colesville Rd",
    "sg:city":"Binghamton",
    "sg:classifiers":[
        {
            "category":"Building & Trades",
            "subcategory":"Landscaping Services",
            "type":"Services"
        }
    ],
    "sg:phone":"+1 607 722 7070",
    "sg:postcode":"13904",
    "sg:province":"NY",
    "sg:tags":[
        "fuel",
        "dealer"
    ],
    "wof:name":"All Pro Tree Service",
    "wof:placetype":"venue"
},
  "geometry": {"coordinates":[-75.760062,42.136382],"type":"Point"}
}