{
  "type": "Feature",
  "properties": {
    "addr:full":"420 W Merrick Rd Valley Stream NY 11580",
    "addr:housenumber":"420",
    "addr:postcode":"11580",
    "addr:street":"W Merrick Rd",
    "iso:country":"US",
    "sg:address":"420 W Merrick Rd",
    "sg:city":"Valley Stream",
    "sg:classifiers":[
        {
            "category":"Freight",
            "type":"Transportation"
        }
    ],
    "sg:phone":"+1 516 825 0866",
    "sg:postcode":"11580",
    "sg:province":"NY",
    "sg:tags":[
        "broker",
        "customs"
    ],
    "wof:name":"Jemm Custom Brokers Inc",
    "wof:placetype":"venue"
},
  "geometry": {"coordinates":[-73.71291600000001,40.668554],"type":"Point"}
}