{
  "type": "Feature",
  "properties": {
    "addr:full":"572 E 169th St Bronx NY 10456",
    "addr:housenumber":"572",
    "addr:postcode":"10456",
    "addr:street":"E 169Th St",
    "iso:country":"US",
    "sg:address":"572 E 169th St",
    "sg:city":"Bronx",
    "sg:classifiers":[
        {
            "category":"Retail",
            "subcategory":"Repair Shop",
            "type":"Services"
        }
    ],
    "sg:phone":"+1 718 414 2113",
    "sg:postcode":"10456",
    "sg:province":"NY",
    "sg:tags":[
        "lock",
        "locksmith"
    ],
    "wof:name":"USA Locksmiths",
    "wof:placetype":"venue"
},
  "geometry": {"coordinates":[-73.90211600000001,40.831744],"type":"Point"}
}