{
  "type": "Feature",
  "properties": {
    "iso:country":"US",
    "sg:address":"400 Lincoln Pl",
    "sg:city":"Brooklyn",
    "sg:classifiers":[
        {
            "category":"Government",
            "subcategory":"Office",
            "type":"Public Place"
        }
    ],
    "sg:phone":"+1 718 789 8506",
    "sg:postcode":"11238",
    "sg:province":"NY",
    "sg:tags":[
        "village"
    ],
    "wof:name":"New York City Algebra Project",
    "wof:placetype":"venue"
},
  "geometry": {"coordinates":[-73.965873,40.673546],"type":"Point"}
}