{
  "type": "Feature",
  "properties": {
    "addr:full":"4051 State Hwy 28 Milford NY 13807",
    "addr:housenumber":"4051",
    "addr:postcode":"13807",
    "addr:street":"State Hwy 28",
    "iso:country":"US",
    "sg:address":"4051 State Hwy 28",
    "sg:city":"Milford",
    "sg:classifiers":[
        {
            "category":"Manufacturing",
            "subcategory":"Apparel",
            "type":"Manufacturing & Wholesale Goods"
        },
        {
            "category":"Wholesale",
            "subcategory":"Non-durable Goods",
            "type":"Manufacturing & Wholesale Goods"
        }
    ],
    "sg:phone":"+1 607 286 9759",
    "sg:postcode":"13807",
    "sg:province":"NY",
    "sg:tags":[
        "product",
        "canvas",
        "mfg"
    ],
    "wof:name":"Krieg's Boat Shop",
    "wof:placetype":"venue"
},
  "geometry": {"coordinates":[-74.956193,42.607324],"type":"Point"}
}