{
  "type": "Feature",
  "properties": {
    "addr:full":"121 University Pl New York NY 10003",
    "addr:housenumber":"121",
    "addr:postcode":"10003",
    "addr:street":"University Pl",
    "iso:country":"US",
    "sg:address":"121 University Pl",
    "sg:city":"New York",
    "sg:classifiers":[
        {
            "category":"Building & Trades",
            "subcategory":"Locksmith",
            "type":"Services"
        }
    ],
    "sg:phone":"+1 212 620 9002",
    "sg:postcode":"10003",
    "sg:province":"NY",
    "sg:tags":[
        "key"
    ],
    "wof:name":"Citi Security & Hardware Inc",
    "wof:placetype":"venue"
},
  "geometry": {"coordinates":[-73.992203,40.734501],"type":"Point"}
}