{
  "type": "Feature",
  "properties": {
    "addr:full":"235 Merrick St Clayton NY 13624",
    "addr:housenumber":"235",
    "addr:postcode":"13624",
    "addr:street":"Merrick St",
    "iso:country":"US",
    "sg:address":"235 Merrick St",
    "sg:city":"Clayton",
    "sg:classifiers":[
        {
            "category":"Shopping",
            "subcategory":"Computers & Home Electronics",
            "type":"Retail Goods"
        }
    ],
    "sg:phone":"+1 315 686 4615",
    "sg:postcode":"13624",
    "sg:province":"NY",
    "sg:tags":[
        "equipment",
        "dealer"
    ],
    "wof:name":"Computer Creation On-Line",
    "wof:placetype":"venue"
},
  "geometry": {"coordinates":[-76.086624,44.24276],"type":"Point"}
}