{
  "type": "Feature",
  "properties": {
    "iso:country":"US",
    "sg:address":"29 Rapp Rd",
    "sg:city":"Albany",
    "sg:classifiers":[
        {
            "category":"Health Services",
            "subcategory":"Medical Lab",
            "type":"Services"
        }
    ],
    "sg:phone":"+1 845 794 5840",
    "sg:postcode":"12203",
    "sg:province":"NY",
    "sg:tags":[
        "laboratory"
    ],
    "wof:name":"Sullivan Diagnostic Treatment",
    "wof:placetype":"venue"
},
  "geometry": {"coordinates":[-73.850994,42.697926],"type":"Point"}
}