{
  "type": "Feature",
  "properties": {
    "addr:full":"148 W 24th St Fl 6 New York NY 10011",
    "addr:housenumber":"148;6",
    "addr:postcode":"10011",
    "addr:street":"W 24Th St",
    "iso:country":"US",
    "sg:address":"148 W 24th St Fl 6",
    "sg:city":"New York",
    "sg:classifiers":[
        {
            "category":"Banks & Credit Unions",
            "subcategory":"Bank",
            "type":"Services"
        }
    ],
    "sg:phone":"+1 212 827 0298",
    "sg:postcode":"10011",
    "sg:province":"NY",
    "wof:name":"Maple Grove Services",
    "wof:placetype":"venue"
},
  "geometry": {"coordinates":[-73.99378,40.744015],"type":"Point"}
}