{
  "type": "Feature",
  "properties": {
    "addr:full":"877 E Main St Riverhead NY 11901",
    "addr:housenumber":"877",
    "addr:postcode":"11901",
    "addr:street":"E Main St",
    "iso:country":"US",
    "sg:address":"877 E Main St",
    "sg:city":"Riverhead",
    "sg:classifiers":[
        {
            "category":"Banks & Credit Unions",
            "subcategory":"Investment Brokerage",
            "type":"Services"
        }
    ],
    "sg:phone":"+1 631 284 8200",
    "sg:postcode":"11901",
    "sg:province":"NY",
    "sg:tags":[
        "security"
    ],
    "wof:name":"Merrill Lynch",
    "wof:placetype":"venue"
},
  "geometry": {"coordinates":[-72.651589,40.923424],"type":"Point"}
}