{
  "type": "Feature",
  "properties": {
    "addr:full":"1620 Ditmas Ave Brooklyn NY 11226",
    "addr:housenumber":"1620",
    "addr:postcode":"11226",
    "addr:street":"Ditmas Ave",
    "iso:country":"US",
    "sg:address":"1620 Ditmas Ave",
    "sg:city":"Brooklyn",
    "sg:classifiers":[
        {
            "category":"Professional",
            "subcategory":"Computer Services",
            "type":"Services"
        }
    ],
    "sg:phone":"+1   ",
    "sg:postcode":"11226",
    "sg:province":"NY",
    "sg:tags":[
        "electronic",
        "datum",
        "recovery"
    ],
    "wof:name":"Data Recovery Service Inc",
    "wof:placetype":"venue"
},
  "geometry": {"coordinates":[-73.961978,40.637781],"type":"Point"}
}