{
  "type": "Feature",
  "properties": {
    "iso:country":"US",
    "sg:address":"128 N Carll Ave",
    "sg:city":"Babylon",
    "sg:classifiers":[
        {
            "category":"Retail",
            "subcategory":"Repair Shop",
            "type":"Services"
        }
    ],
    "sg:phone":"+1 631 223 0455",
    "sg:postcode":"11702",
    "sg:province":"NY",
    "sg:tags":[
        "lock",
        "locksmith"
    ],
    "wof:name":"24 Hour Emergency Locksmith",
    "wof:placetype":"venue"
},
  "geometry": {"coordinates":[-73.325941,40.70082],"type":"Point"}
}