{
  "type": "Feature",
  "properties": {
    "iso:country":"US",
    "sg:address":"120 13th St",
    "sg:city":"Niagara Falls",
    "sg:classifiers":[
        {
            "category":"Local Transit",
            "type":"Transportation"
        }
    ],
    "sg:phone":"+1 716 285 9357",
    "sg:postcode":"14303",
    "sg:province":"NY",
    "sg:tags":[
        "bus",
        "line"
    ],
    "wof:name":"Niagara Falls Coach Lines",
    "wof:placetype":"venue"
},
  "geometry": {"coordinates":[-79.045846,43.083826],"type":"Point"}
}