{
  "type": "Feature",
  "properties": {
    "addr:full":"50 Dann St Buffalo NY 14207",
    "addr:housenumber":"50",
    "addr:postcode":"14207",
    "addr:street":"Dann St",
    "iso:country":"US",
    "sg:address":"50 Dann St",
    "sg:city":"Buffalo",
    "sg:classifiers":[
        {
            "category":"Recreation",
            "type":"Entertainment"
        }
    ],
    "sg:phone":"+1   ",
    "sg:postcode":"14207",
    "sg:province":"NY",
    "sg:tags":[
        "a",
        "operates",
        "field",
        "as",
        "complex",
        "baseball"
    ],
    "wof:name":"Lou Gehrig Youth Baseball",
    "wof:placetype":"venue"
},
  "geometry": {"coordinates":[-78.90366,42.93512],"type":"Point"}
}