{
  "type": "Feature",
  "properties": {
    "addr:full":"506 Malcolm X Blvd New York NY 10037",
    "addr:housenumber":"506",
    "addr:postcode":"10037",
    "addr:street":"Malcolm X Blvd",
    "iso:country":"US",
    "sg:address":"506 Malcolm X Blvd",
    "sg:city":"New York",
    "sg:classifiers":[
        {
            "category":"Health Services",
            "subcategory":"Doctor",
            "type":"Services"
        }
    ],
    "sg:phone":"+1 212 939 1000",
    "sg:postcode":"10037",
    "sg:province":"NY",
    "sg:tags":[
        "physician",
        "surgeon"
    ],
    "wof:name":"Luis Marcos MD",
    "wof:placetype":"venue"
},
  "geometry": {"coordinates":[-73.939909,40.815404],"type":"Point"}
}