{
  "type": "Feature",
  "properties": {
    "iso:country":"US",
    "sg:address":"10621 Doyle Rd",
    "sg:city":"Utica",
    "sg:classifiers":[
        {
            "category":"Shopping",
            "subcategory":"Computers & Home Electronics",
            "type":"Retail Goods"
        }
    ],
    "sg:phone":"+1   ",
    "sg:postcode":"13502",
    "sg:province":"NY",
    "wof:name":"User Friendly Software Systems",
    "wof:placetype":"venue"
},
  "geometry": {"coordinates":[-75.203073,43.163463],"type":"Point"}
}