{
  "type": "Feature",
  "properties": {
    "addr:full":"246 W End Ave New York NY 10023",
    "addr:housenumber":"246",
    "addr:postcode":"10023",
    "addr:street":"W End Ave",
    "iso:country":"US",
    "sg:address":"246 W End Ave",
    "sg:city":"New York",
    "sg:classifiers":[
        {
            "category":"Health Services",
            "subcategory":"Doctor",
            "type":"Services"
        }
    ],
    "sg:phone":"+1 212 595 2229",
    "sg:postcode":"10023",
    "sg:province":"NY",
    "sg:tags":[
        "medical"
    ],
    "wof:name":"Shanoks Medical Clinic",
    "wof:placetype":"venue"
},
  "geometry": {"coordinates":[-73.984476,40.779807],"type":"Point"}
}