{
  "type": "Feature",
  "properties": {
    "addr:full":"212 Front St Owego NY 13827",
    "addr:housenumber":"212",
    "addr:postcode":"13827",
    "addr:street":"Front St",
    "iso:country":"US",
    "sg:address":"212 Front St",
    "sg:city":"Owego",
    "sg:classifiers":[
        {
            "category":"Professional",
            "subcategory":"Lawyer & Legal Services",
            "type":"Services"
        }
    ],
    "sg:phone":"+1 607 687 1350",
    "sg:postcode":"13827",
    "sg:province":"NY",
    "sg:tags":[
        "attorney"
    ],
    "wof:name":"Dixon Schumacher PC",
    "wof:placetype":"venue"
},
  "geometry": {"coordinates":[-76.25706700000001,42.104169],"type":"Point"}
}