{
  "type": "Feature",
  "properties": {
    "iso:country":"US",
    "sg:address":"119 W 22 St",
    "sg:city":"New York",
    "sg:classifiers":[
        {
            "category":"Shopping",
            "type":"Retail Goods"
        }
    ],
    "sg:phone":"+1 212 633 0110",
    "sg:postcode":"10011",
    "sg:province":"NY",
    "sg:tags":[
        "art",
        "gallery",
        "dealer"
    ],
    "wof:name":"Gary Tatintsian Gallery Inc",
    "wof:placetype":"venue"
},
  "geometry": {"coordinates":[-73.995698,40.743276],"type":"Point"}
}