{
  "type": "Feature",
  "properties": {
    "addr:full":"Van Duzer & Beach St Staten Island NY 10304",
    "addr:postcode":"10304",
    "addr:street":"Van;St",
    "iso:country":"US",
    "sg:address":"Van Duzer & Beach St",
    "sg:city":"Staten Island",
    "sg:classifiers":[
        {
            "category":"Food & Beverages",
            "subcategory":"Groceries & Convenience Stores",
            "type":"Retail Goods"
        }
    ],
    "sg:postcode":"10304",
    "sg:province":"NY",
    "wof:name":"Country Store Deli and Grocery",
    "wof:placetype":"venue"
},
  "geometry": {"coordinates":[-74.079723,40.628953],"type":"Point"}
}