{
  "type": "Feature",
  "properties": {
    "iso:country":"US",
    "sg:address":"325 W 52nd St",
    "sg:city":"New York",
    "sg:classifiers":[
        {
            "category":"Real Estate",
            "subcategory":"Real Estate Agent",
            "type":"Services"
        }
    ],
    "sg:phone":"+1 212 246 5586",
    "sg:postcode":"10019",
    "sg:province":"NY",
    "sg:tags":[
        "cooperative"
    ],
    "wof:name":"325 W 52nd Street Co-Op",
    "wof:placetype":"venue"
},
  "geometry": {"coordinates":[-73.98746800000001,40.76451],"type":"Point"}
}