{
  "type": "Feature",
  "properties": {
    "addr:full":"2050 82nd St Brooklyn NY 11214",
    "addr:housenumber":"2050",
    "addr:postcode":"11214",
    "addr:street":"82Nd St",
    "iso:country":"US",
    "sg:address":"2050 82nd St",
    "sg:city":"Brooklyn",
    "sg:classifiers":[
        {
            "category":"Home & Garden",
            "subcategory":"Building Materials",
            "type":"Retail Goods"
        },
        {
            "category":"Building & Trades",
            "subcategory":"Construction",
            "type":"Services"
        }
    ],
    "sg:phone":"+1 718 259 2672",
    "sg:postcode":"11214",
    "sg:province":"NY",
    "sg:tags":[
        "concrete",
        "staining",
        "contractor"
    ],
    "wof:name":"Fontana Contracting",
    "wof:placetype":"venue"
},
  "geometry": {"coordinates":[-73.994759,40.606192],"type":"Point"}
}