{
  "type": "Feature",
  "properties": {
    "iso:country":"US",
    "sg:address":"141 Beard St",
    "sg:city":"Brooklyn",
    "sg:classifiers":[
        {
            "category":"Freight",
            "type":"Transportation"
        }
    ],
    "sg:phone":"+1   ",
    "sg:postcode":"11231",
    "sg:province":"NY",
    "sg:tags":[
        "operator",
        "trucking",
        "local",
        "general"
    ],
    "wof:name":"WEb Trucking Corp",
    "wof:placetype":"venue"
},
  "geometry": {"coordinates":[-74.014482,40.67425],"type":"Point"}
}