{
  "type": "Feature",
  "properties": {
    "addr:full":"333 E 34 St New York NY 10016",
    "addr:housenumber":"333;34",
    "addr:postcode":"10016",
    "addr:street":"E;St",
    "iso:country":"US",
    "sg:address":"333 E 34 St",
    "sg:city":"New York",
    "sg:classifiers":[
        {
            "category":"Health Services",
            "subcategory":"Doctor",
            "type":"Services"
        }
    ],
    "sg:phone":"+1 212 532 5446",
    "sg:postcode":"10016",
    "sg:province":"NY",
    "wof:name":"Thomas Kay Dr",
    "wof:placetype":"venue"
},
  "geometry": {"coordinates":[-73.97355,40.743888],"type":"Point"}
}