{
  "type": "Feature",
  "properties": {
    "addr:full":"24 E 36th St New York NY 10016",
    "addr:housenumber":"24",
    "addr:postcode":"10016",
    "addr:street":"E 36Th St",
    "iso:country":"US",
    "sg:address":"24 E 36th St",
    "sg:city":"New York",
    "sg:classifiers":[
        {
            "category":"Personal",
            "subcategory":"Hair Removal",
            "type":"Services"
        }
    ],
    "sg:phone":"+1 212 213 3003",
    "sg:postcode":"10016",
    "sg:province":"NY",
    "sg:tags":[
        "laser"
    ],
    "sg:website":"serenemax.com",
    "wof:name":"Serene Max",
    "wof:placetype":"venue"
},
  "geometry": {"coordinates":[-73.981876,40.74895],"type":"Point"}
}