{
  "type": "Feature",
  "properties": {
    "iso:country":"US",
    "sg:address":"172 Pike St",
    "sg:city":"Port Jervis",
    "sg:classifiers":[
        {
            "category":"Restaurant",
            "type":"Food & Drink"
        }
    ],
    "sg:phone":"+1 845 858 9956",
    "sg:postcode":"12771",
    "sg:province":"NY",
    "wof:name":"Woolz Wings N Things",
    "wof:placetype":"venue"
},
  "geometry": {"coordinates":[-74.689097,41.377875],"type":"Point"}
}