{
  "type": "Feature",
  "properties": {
    "addr:full":"6215 8th Ave Brooklyn NY 11220",
    "addr:housenumber":"6215",
    "addr:postcode":"11220",
    "addr:street":"8Th Ave",
    "iso:country":"US",
    "sg:address":"6215 8th Ave",
    "sg:city":"Brooklyn",
    "sg:classifiers":[
        {
            "category":"Building & Trades",
            "subcategory":"Construction",
            "type":"Services"
        }
    ],
    "sg:phone":"+1 718 833 9833",
    "sg:postcode":"11220",
    "sg:province":"NY",
    "sg:tags":[
        "contractor"
    ],
    "wof:name":"Siteline Design & Construction",
    "wof:placetype":"venue"
},
  "geometry": {"coordinates":[-74.071877,40.634103],"type":"Point"}
}