{
  "type": "Feature",
  "properties": {
    "addr:full":"1 Hunts Pt Bronx NY 10451",
    "addr:housenumber":"1",
    "addr:postcode":"10451",
    "addr:street":"Hunts Pt",
    "iso:country":"US",
    "sg:address":"1 Hunts Pt",
    "sg:city":"Bronx",
    "sg:classifiers":[
        {
            "category":"Food & Beverages",
            "subcategory":"Meat & Fish",
            "type":"Retail Goods"
        }
    ],
    "sg:phone":"+1 718 842 6767",
    "sg:postcode":"10451",
    "sg:province":"NY",
    "sg:tags":[
        "shop"
    ],
    "sg:website":"www.austinmeat.com",
    "wof:name":"Austin Meat Co",
    "wof:placetype":"venue"
},
  "geometry": {"coordinates":[-73.916566,40.845047],"type":"Point"}
}