{
  "type": "Feature",
  "properties": {
    "addr:full":"5137 Pulver Rd Dundee NY 14837",
    "addr:housenumber":"5137",
    "addr:postcode":"14837",
    "addr:street":"Pulver Rd",
    "iso:country":"US",
    "sg:address":"5137 Pulver Rd",
    "sg:city":"Dundee",
    "sg:classifiers":[
        {
            "category":"Building & Trades",
            "subcategory":"Construction",
            "type":"Services"
        }
    ],
    "sg:phone":"+1 607 243 7127",
    "sg:postcode":"14837",
    "sg:province":"NY",
    "sg:tags":[
        "painter"
    ],
    "wof:name":"Kennedy Painting",
    "wof:placetype":"venue"
},
  "geometry": {"coordinates":[-77.015528,42.483765],"type":"Point"}
}