{
  "type": "Feature",
  "properties": {
    "iso:country":"US",
    "sg:address":"34 Sherwood Ln",
    "sg:city":"Burnt Hills",
    "sg:classifiers":[
        {
            "category":"Building & Trades",
            "subcategory":"Construction",
            "type":"Services"
        }
    ],
    "sg:phone":"+1 518 399 6277",
    "sg:postcode":"12027",
    "sg:province":"NY",
    "sg:tags":[
        "home",
        "family"
    ],
    "wof:name":"Building Connection Inc",
    "wof:placetype":"venue"
},
  "geometry": {"coordinates":[-73.902452,42.910596],"type":"Point"}
}