{
  "type": "Feature",
  "properties": {
    "addr:full":"1000 President St Brooklyn NY 11225",
    "addr:housenumber":"1000",
    "addr:postcode":"11225",
    "addr:street":"President St",
    "iso:country":"US",
    "sg:address":"1000 President St",
    "sg:city":"Brooklyn",
    "sg:classifiers":[
        {
            "category":"Building & Trades",
            "subcategory":"Construction",
            "type":"Services"
        }
    ],
    "sg:phone":"+1 718 778 1280",
    "sg:postcode":"11225",
    "sg:province":"NY",
    "sg:tags":[
        "general",
        "contractor"
    ],
    "wof:name":"K & T Constr Corp",
    "wof:placetype":"venue"
},
  "geometry": {"coordinates":[-73.96109,40.669463],"type":"Point"}
}