{
  "type": "Feature",
  "properties": {
    "addr:full":"4915 Nesconset Hwy Port Jeffrsn Sta NY 11776",
    "addr:postcode":"4915;11776",
    "addr:street":"Nesconset Hwy Port Jeffrsn Sta",
    "iso:country":"US",
    "sg:address":"4915 Nesconset Hwy",
    "sg:city":"Port Jeffrsn Sta",
    "sg:classifiers":[
        {
            "category":"Wholesale",
            "subcategory":"Electrical",
            "type":"Manufacturing & Wholesale Goods"
        }
    ],
    "sg:phone":"+1 631 473 3493",
    "sg:postcode":"11776",
    "sg:province":"NY",
    "sg:tags":[
        "electric",
        "motor"
    ],
    "wof:name":"Ramp Motors Truck",
    "wof:placetype":"venue"
},
  "geometry": {"coordinates":[-73.048856,40.923801],"type":"Point"}
}