{
  "type": "Feature",
  "properties": {
    "iso:country":"US",
    "sg:address":"1 M And T Plz",
    "sg:city":"Buffalo",
    "sg:classifiers":[
        {
            "category":"Banks & Credit Unions",
            "subcategory":"Financial Services",
            "type":"Services"
        },
        {
            "category":"Professional",
            "subcategory":"Business Services",
            "type":"Services"
        }
    ],
    "sg:phone":"+1 716 842 5445",
    "sg:postcode":"14203",
    "sg:province":"NY",
    "sg:tags":[
        "holding"
    ],
    "wof:name":"First Empire State Holding Company",
    "wof:placetype":"venue"
},
  "geometry": {"coordinates":[-78.8741,42.883762],"type":"Point"}
}