{
  "type": "Feature",
  "properties": {
    "addr:full":"36 Fish Rd Ithaca NY 14850",
    "addr:housenumber":"36",
    "addr:postcode":"14850",
    "addr:street":"Fish Rd",
    "iso:country":"US",
    "sg:address":"36 Fish Rd",
    "sg:city":"Ithaca",
    "sg:phone":"+1 607 272 8035",
    "sg:postcode":"14850",
    "sg:province":"NY",
    "sg:tags":[
        "farm",
        "field",
        "crop"
    ],
    "wof:name":"Laue Farms",
    "wof:placetype":"venue"
},
  "geometry": {"coordinates":[-76.63429600000001,42.442314],"type":"Point"}
}