{
  "type": "Feature",
  "properties": {
    "iso:country":"US",
    "sg:address":"1766 Black River Blvd N",
    "sg:city":"Rome",
    "sg:classifiers":[
        {
            "category":"Shopping",
            "subcategory":"Clothing, Apparel, & Fashions",
            "type":"Retail Goods"
        }
    ],
    "sg:phone":"+1 315 334 4329",
    "sg:postcode":"13440",
    "sg:province":"NY",
    "wof:name":"Label Shopper",
    "wof:placetype":"venue"
},
  "geometry": {"coordinates":[-75.436018,43.2377],"type":"Point"}
}