{
  "type": "Feature",
  "properties": {
    "iso:country":"US",
    "sg:address":"550 Bedford Rd",
    "sg:city":"Bedford Hills",
    "sg:classifiers":[
        {
            "category":"Personal",
            "type":"Services"
        }
    ],
    "sg:phone":"+1 914 242 8800",
    "sg:postcode":"10507",
    "sg:province":"NY",
    "sg:tags":[
        "gym",
        "therapist",
        "massage"
    ],
    "wof:name":"Breathing & Relaxation Center",
    "wof:placetype":"venue"
},
  "geometry": {"coordinates":[-73.710503,41.229],"type":"Point"}
}