{
  "type": "Feature",
  "properties": {
    "addr:full":"4515 5th Ave Brooklyn NY 11220",
    "addr:housenumber":"4515",
    "addr:postcode":"11220",
    "addr:street":"5Th Ave",
    "iso:country":"US",
    "sg:address":"4515 5th Ave",
    "sg:city":"Brooklyn",
    "sg:classifiers":[
        {
            "category":"Personal",
            "subcategory":"Shoe Repair & Shine",
            "type":"Services"
        }
    ],
    "sg:phone":"+1 718 854 2836",
    "sg:postcode":"11220",
    "sg:province":"NY",
    "sg:tags":[
        "repairing",
        "boot"
    ],
    "wof:name":"Frank's Shoe Svce",
    "wof:placetype":"venue"
},
  "geometry": {"coordinates":[-74.007599,40.647499],"type":"Point"}
}