{
  "type": "Feature",
  "properties": {
    "iso:country":"US",
    "sg:address":"70 Crowley Ave",
    "sg:city":"Buffalo",
    "sg:classifiers":[
        {
            "category":"Organizations",
            "subcategory":"Membership Organization",
            "type":"Services"
        }
    ],
    "sg:phone":"+1 716 873 8083",
    "sg:postcode":"14207",
    "sg:province":"NY",
    "sg:tags":[
        "athletic"
    ],
    "wof:name":"River Rock Baseball League",
    "wof:placetype":"venue"
},
  "geometry": {"coordinates":[-78.90791,42.952808],"type":"Point"}
}