{
  "type": "Feature",
  "properties": {
    "iso:country":"US",
    "sg:address":"7 Hickory Ln",
    "sg:city":"Rochester",
    "sg:classifiers":[
        {
            "category":"Professional",
            "subcategory":"Lawyer & Legal Services",
            "type":"Services"
        }
    ],
    "sg:phone":"+1 585 461 5937",
    "sg:postcode":"14625",
    "sg:province":"NY",
    "sg:tags":[
        "attorney"
    ],
    "wof:name":"Norman M Spindelman",
    "wof:placetype":"venue"
},
  "geometry": {"coordinates":[-77.495195,43.146551],"type":"Point"}
}