{
  "type": "Feature",
  "properties": {
    "addr:full":"167 Main St Westhampton Bch NY 11978",
    "addr:housenumber":"167",
    "addr:postcode":"11978",
    "addr:street":"Main St",
    "iso:country":"US",
    "sg:address":"167 Main St",
    "sg:city":"Westhampton Bch",
    "sg:classifiers":[
        {
            "category":"Shopping",
            "subcategory":"Clothing, Apparel, & Fashions",
            "type":"Retail Goods"
        }
    ],
    "sg:phone":"+1 631 288 7000",
    "sg:postcode":"11978",
    "sg:province":"NY",
    "sg:tags":[
        "item",
        "boutique"
    ],
    "wof:name":"Jimmy's",
    "wof:placetype":"venue"
},
  "geometry": {"coordinates":[-72.641148,40.81002],"type":"Point"}
}