{
  "type": "Feature",
  "properties": {
    "addr:full":"421 W 17 St New York NY 10011",
    "addr:housenumber":"421",
    "addr:postcode":"10011",
    "addr:street":"W 17 St",
    "iso:country":"US",
    "sg:address":"421 W 17 St",
    "sg:city":"New York",
    "sg:classifiers":[
        {
            "category":"Government",
            "subcategory":"Office",
            "type":"Public Place"
        }
    ],
    "sg:phone":"+1 212 255 5005",
    "sg:postcode":"10011",
    "sg:province":"NY",
    "sg:tags":[
        "village"
    ],
    "wof:name":"New York City Housing",
    "wof:placetype":"venue"
},
  "geometry": {"coordinates":[-74.00633500000001,40.743881],"type":"Point"}
}