{
  "type": "Feature",
  "properties": {
    "addr:full":"265 W 231st St Bronx NY 10463",
    "addr:housenumber":"265",
    "addr:postcode":"10463",
    "addr:street":"W 231St St",
    "iso:country":"US",
    "sg:address":"265 W 231st St",
    "sg:city":"Bronx",
    "sg:classifiers":[
        {
            "category":"Insurance",
            "subcategory":"Insurance Agent",
            "type":"Services"
        }
    ],
    "sg:phone":"+1 718 884 0120",
    "sg:postcode":"10463",
    "sg:province":"NY",
    "wof:name":"Carl J Hockemeyer",
    "wof:placetype":"venue"
},
  "geometry": {"coordinates":[-73.907191,40.880163],"type":"Point"}
}