{
  "type": "Feature",
  "properties": {
    "addr:full":"1202 Imperial Dr Webster NY 14580",
    "addr:housenumber":"1202",
    "addr:postcode":"14580",
    "addr:street":"Imperial Dr",
    "iso:country":"US",
    "sg:address":"1202 Imperial Dr",
    "sg:city":"Webster",
    "sg:classifiers":[
        {
            "category":"Building & Trades",
            "subcategory":"Construction",
            "type":"Services"
        }
    ],
    "sg:phone":"+1 585 872 4551",
    "sg:postcode":"14580",
    "sg:province":"NY",
    "sg:tags":[
        "house"
    ],
    "wof:name":"Rus-Len Development Corp",
    "wof:placetype":"venue"
},
  "geometry": {"coordinates":[-77.435036,43.238345],"type":"Point"}
}