{
  "type": "Feature",
  "properties": {
    "addr:full":"4649 Vrooman Dr Lewiston NY 14092",
    "addr:housenumber":"4649",
    "addr:postcode":"14092",
    "addr:street":"Vrooman Dr",
    "iso:country":"US",
    "sg:address":"4649 Vrooman Dr",
    "sg:city":"Lewiston",
    "sg:classifiers":[
        {
            "category":"Restaurant",
            "type":"Food & Drink"
        }
    ],
    "sg:phone":"+1 716 282 0644",
    "sg:postcode":"14092",
    "sg:province":"NY",
    "wof:name":"Market Side Restaurant",
    "wof:placetype":"venue"
},
  "geometry": {"coordinates":[-79.03974599999999,43.187588],"type":"Point"}
}