{
  "type": "Feature",
  "properties": {
    "addr:full":"6706 11th Ave Brooklyn NY 11219",
    "addr:housenumber":"6706",
    "addr:postcode":"11219",
    "addr:street":"11Th Ave",
    "iso:country":"US",
    "sg:address":"6706 11th Ave",
    "sg:city":"Brooklyn",
    "sg:classifiers":[
        {
            "category":"Retail",
            "subcategory":"Laundry & Dry Cleaning",
            "type":"Services"
        }
    ],
    "sg:phone":"+1 718 680 9191",
    "sg:postcode":"11219",
    "sg:province":"NY",
    "sg:tags":[
        "cleaner",
        "plant",
        "drycleaning"
    ],
    "wof:name":"Alexis French Cleaners",
    "wof:placetype":"venue"
},
  "geometry": {"coordinates":[-74.007401,40.627399],"type":"Point"}
}