{
  "type": "Feature",
  "properties": {
    "iso:country":"US",
    "sg:address":"9 Ludlow St",
    "sg:city":"Yonkers",
    "sg:classifiers":[
        {
            "category":"Taxi",
            "type":"Transportation"
        }
    ],
    "sg:phone":"+1 914 968 2800",
    "sg:postcode":"10705",
    "sg:province":"NY",
    "sg:tags":[
        "taxicab"
    ],
    "wof:name":"Valentine Car Svc",
    "wof:placetype":"venue"
},
  "geometry": {"coordinates":[-73.897133,40.923742],"type":"Point"}
}