{
  "type": "Feature",
  "properties": {
    "addr:full":"393 5th Ave Brooklyn NY 11215",
    "addr:housenumber":"393",
    "addr:postcode":"11215",
    "addr:street":"5Th Ave",
    "iso:country":"US",
    "sg:address":"393 5th Ave",
    "sg:city":"Brooklyn",
    "sg:classifiers":[
        {
            "category":"Shopping",
            "subcategory":"Gifts & Souvenirs",
            "type":"Retail Goods"
        }
    ],
    "sg:phone":"+1 718 768 5208",
    "sg:postcode":"11215",
    "sg:province":"NY",
    "sg:tags":[
        "shop"
    ],
    "wof:name":"Vineyard Baskets",
    "wof:placetype":"venue"
},
  "geometry": {"coordinates":[-73.985001,40.670707],"type":"Point"}
}