{
  "type": "Feature",
  "properties": {
    "addr:full":"Mudd Building, Columbia University 500 W 120th St Manhattan NY 10027",
    "addr:housenumber":"500",
    "addr:postcode":"10027",
    "addr:street":"W 120Th St",
    "iso:country":"US",
    "sg:address":"Mudd Building, Columbia University 500 W 120th St",
    "sg:city":"Manhattan",
    "sg:classifiers":[
        {
            "category":"Restaurant",
            "type":"Food & Drink"
        }
    ],
    "sg:postcode":"10027",
    "sg:province":"NY",
    "wof:name":"Carleton Lounge",
    "wof:placetype":"venue"
},
  "geometry": {"coordinates":[-73.960133,40.809457],"type":"Point"}
}