{
  "type": "Feature",
  "properties": {
    "iso:country":"US",
    "sg:address":"91 Golden Pheasant Dr",
    "sg:city":"Getzville",
    "sg:classifiers":[
        {
            "category":"Personal",
            "type":"Services"
        }
    ],
    "sg:phone":"+1 716 688 1271",
    "sg:postcode":"14068",
    "sg:province":"NY",
    "wof:name":"Sun Capsule Plus",
    "wof:placetype":"venue"
},
  "geometry": {"coordinates":[-78.748554,43.029714],"type":"Point"}
}