{
  "type": "Feature",
  "properties": {
    "addr:full":"90 E Shore Rd Manhasset NY 11023",
    "addr:housenumber":"90",
    "addr:postcode":"11023",
    "addr:street":"E Shore Rd",
    "iso:country":"US",
    "sg:address":"90 E Shore Rd",
    "sg:city":"Manhasset",
    "sg:classifiers":[
        {
            "category":"Restaurant",
            "type":"Food & Drink"
        }
    ],
    "sg:phone":"+1 516 365 3805",
    "sg:postcode":"11023",
    "sg:province":"NY",
    "wof:name":"Amazon Cafe",
    "wof:placetype":"venue"
},
  "geometry": {"coordinates":[-73.707551,40.789594],"type":"Point"}
}