{
  "type": "Feature",
  "properties": {
    "addr:full":"66 Overlook Ter New York NY 10040",
    "addr:housenumber":"66",
    "addr:postcode":"10040",
    "addr:street":"Overlook Ter",
    "iso:country":"US",
    "sg:address":"66 Overlook Ter",
    "sg:city":"New York",
    "sg:classifiers":[
        {
            "category":"Recreation",
            "type":"Entertainment"
        }
    ],
    "sg:phone":"+1   ",
    "sg:postcode":"10040",
    "sg:province":"NY",
    "wof:name":"Tai CHI For Everyone",
    "wof:placetype":"venue"
},
  "geometry": {"coordinates":[-73.934724,40.85689],"type":"Point"}
}