{
  "type": "Feature",
  "properties": {
    "addr:full":"1539 E 13th St Brooklyn NY 11230",
    "addr:housenumber":"1539",
    "addr:postcode":"11230",
    "addr:street":"E 13Th St",
    "iso:country":"US",
    "sg:address":"1539 E 13th St",
    "sg:city":"Brooklyn",
    "sg:classifiers":[
        {
            "category":"Communications",
            "subcategory":"Newspaper",
            "type":"Services"
        }
    ],
    "sg:phone":"+1 718 336 8544",
    "sg:postcode":"11230",
    "sg:province":"NY",
    "sg:tags":[
        "print",
        "medium"
    ],
    "sg:website":"www.kashrusmagazine.com",
    "wof:name":"Kashrus Magazine",
    "wof:placetype":"venue"
},
  "geometry": {"coordinates":[-73.960503,40.6115],"type":"Point"}
}