{
  "type": "Feature",
  "properties": {
    "iso:country":"US",
    "sg:address":"610 Fordsbush Rd",
    "sg:city":"Fort Plain",
    "sg:classifiers":[
        {
            "category":"Real Estate",
            "subcategory":"Developer",
            "type":"Services"
        }
    ],
    "sg:phone":"+1 518 568 7767",
    "sg:postcode":"13339",
    "sg:province":"NY",
    "sg:tags":[
        "cemetery"
    ],
    "wof:name":"Mt Hope Cemetery Assoc Mr",
    "wof:placetype":"venue"
},
  "geometry": {"coordinates":[-74.741846,42.960949],"type":"Point"}
}