{
  "type": "Feature",
  "properties": {
    "addr:full":"121 Dwight Park Cir Syracuse NY 13209",
    "addr:housenumber":"121",
    "addr:postcode":"13209",
    "addr:street":"Dwight Park Cir",
    "iso:country":"US",
    "sg:address":"121 Dwight Park Cir",
    "sg:city":"Syracuse",
    "sg:classifiers":[
        {
            "category":"Wholesale",
            "subcategory":"Non-durable Goods",
            "type":"Manufacturing & Wholesale Goods"
        }
    ],
    "sg:phone":"+1 315 457 5277",
    "sg:postcode":"13209",
    "sg:province":"NY",
    "sg:tags":[
        "candle",
        "equipment"
    ],
    "wof:name":"TVG Glass",
    "wof:placetype":"venue"
},
  "geometry": {"coordinates":[-76.253462,43.111843],"type":"Point"}
}