{
  "type": "Feature",
  "properties": {
    "addr:full":"123 E Tremont Avenue Bronx NY 10453",
    "addr:housenumber":"123",
    "addr:postcode":"10453",
    "addr:street":"E Tremont Avenue",
    "iso:country":"US",
    "sg:address":"123 E Tremont Avenue",
    "sg:city":"Bronx",
    "sg:classifiers":[
        {
            "category":"Restaurant",
            "type":"Food & Drink"
        }
    ],
    "sg:phone":"+1 718 716 6800",
    "sg:postcode":"10453",
    "sg:province":"NY",
    "wof:name":"Golden Dragon Restaurant",
    "wof:placetype":"venue"
},
  "geometry": {"coordinates":[-73.907287,40.85077],"type":"Point"}
}