{
  "type": "Feature",
  "properties": {
    "addr:full":"108-110 W 107th St New York NY 10025",
    "addr:housenumber":"108-110",
    "addr:postcode":"10025",
    "addr:street":"W 107Th St",
    "iso:country":"US",
    "sg:address":"108-110 W 107th St",
    "sg:city":"New York",
    "sg:classifiers":[
        {
            "category":"Retail",
            "subcategory":"Storage",
            "type":"Services"
        }
    ],
    "sg:phone":"+1 212 786 7243",
    "sg:postcode":"10025",
    "sg:province":"NY",
    "sg:tags":[
        "self"
    ],
    "sg:website":"www.manhattanministorage.com/",
    "wof:name":"Manhattan Mini Storage",
    "wof:placetype":"venue"
},
  "geometry": {"coordinates":[-73.96345100000001,40.800116],"type":"Point"}
}