{
  "type": "Feature",
  "properties": {
    "addr:full":"400 Park Ave New York NY 10022",
    "addr:housenumber":"400",
    "addr:postcode":"10022",
    "addr:street":"Park Ave",
    "iso:country":"US",
    "sg:address":"400 Park Ave",
    "sg:city":"New York",
    "sg:classifiers":[
        {
            "category":"Real Estate",
            "subcategory":"Real Estate Operator",
            "type":"Services"
        }
    ],
    "sg:phone":"+1 212 355 2700",
    "sg:postcode":"10022",
    "sg:province":"NY",
    "sg:tags":[
        "building",
        "nonresidential"
    ],
    "wof:name":"E S C O Properties",
    "wof:placetype":"venue"
},
  "geometry": {"coordinates":[-73.97169599999999,40.760312],"type":"Point"}
}