{
  "type": "Feature",
  "properties": {
    "addr:full":"199 Orange Tpke Sloatsburg NY 10974",
    "addr:housenumber":"199",
    "addr:postcode":"10974",
    "addr:street":"Orange Tpke",
    "iso:country":"US",
    "sg:address":"199 Orange Tpke",
    "sg:city":"Sloatsburg",
    "sg:classifiers":[
        {
            "category":"Building & Trades",
            "subcategory":"Landscaping Services",
            "type":"Services"
        }
    ],
    "sg:phone":"+1 845 753 5226",
    "sg:postcode":"10974",
    "sg:province":"NY",
    "sg:tags":[
        "landscape",
        "contractor"
    ],
    "wof:name":"Artistic Gardens Inc",
    "wof:placetype":"venue"
},
  "geometry": {"coordinates":[-74.190979,41.170038],"type":"Point"}
}