{
  "type": "Feature",
  "properties": {
    "iso:country":"US",
    "sg:address":"6 Susan Dr",
    "sg:city":"Poughquag",
    "sg:classifiers":[
        {
            "category":"Building & Trades",
            "subcategory":"Construction",
            "type":"Services"
        }
    ],
    "sg:phone":"+1 845 724 4100",
    "sg:postcode":"12570",
    "sg:province":"NY",
    "sg:tags":[
        "general",
        "contractor"
    ],
    "wof:name":"Sips Builder Inc",
    "wof:placetype":"venue"
},
  "geometry": {"coordinates":[-73.653655,41.63879],"type":"Point"}
}