{
  "type": "Feature",
  "properties": {
    "iso:country":"US",
    "sg:address":"1138 E 85th St",
    "sg:city":"Brooklyn",
    "sg:classifiers":[
        {
            "category":"Communications",
            "type":"Services"
        }
    ],
    "sg:phone":"+1 718 451 9200",
    "sg:postcode":"11236",
    "sg:province":"NY",
    "sg:tags":[
        "communication"
    ],
    "wof:name":"Nuchoice Communications Inc",
    "wof:placetype":"venue"
},
  "geometry": {"coordinates":[-73.904735,40.633532],"type":"Point"}
}