{
  "type": "Feature",
  "properties": {
    "iso:country":"US",
    "sg:address":"3082 Bernard Rd",
    "sg:city":"Cassadaga",
    "sg:classifiers":[
        {
            "category":"Freight",
            "type":"Transportation"
        }
    ],
    "sg:phone":"+1   ",
    "sg:postcode":"14718",
    "sg:province":"NY",
    "sg:tags":[
        "operator",
        "local",
        "trucking"
    ],
    "wof:name":"Lil Bit Trucking",
    "wof:placetype":"venue"
},
  "geometry": {"coordinates":[-79.263925,42.326472],"type":"Point"}
}