{
  "type": "Feature",
  "properties": {
    "addr:full":"434 Fishkill Ave Beacon NY 12508",
    "addr:housenumber":"434",
    "addr:postcode":"12508",
    "addr:street":"Fishkill Ave",
    "iso:country":"US",
    "sg:address":"434 Fishkill Ave",
    "sg:city":"Beacon",
    "sg:classifiers":[
        {
            "category":"Retail",
            "subcategory":"Self-service Laundry",
            "type":"Services"
        }
    ],
    "sg:phone":"+1 845 831 6779",
    "sg:postcode":"12508",
    "sg:province":"NY",
    "wof:name":"Margaret's Laundry Mat",
    "wof:placetype":"venue"
},
  "geometry": {"coordinates":[-73.94844999999999,41.514486],"type":"Point"}
}