{
  "type": "Feature",
  "properties": {
    "addr:full":"1145 Rte 35 South Salem NY 10590",
    "addr:housenumber":"1145",
    "addr:postcode":"10590",
    "addr:street":"Rte 35 South",
    "iso:country":"US",
    "sg:address":"1145 Rte 35",
    "sg:city":"South Salem",
    "sg:classifiers":[
        {
            "category":"Retail",
            "subcategory":"Animal Services",
            "type":"Services"
        }
    ],
    "sg:phone":"+1 914 763 6311",
    "sg:postcode":"10590",
    "sg:province":"NY",
    "sg:tags":[
        "breeder",
        "horse"
    ],
    "wof:name":"Davenport Inc",
    "wof:placetype":"venue"
},
  "geometry": {"coordinates":[-73.58096399999999,41.275424],"type":"Point"}
}