{
  "type": "Feature",
  "properties": {
    "addr:full":"242 Drexel Ave Westbury NY 11590",
    "addr:housenumber":"242",
    "addr:postcode":"11590",
    "addr:street":"Drexel Ave",
    "iso:country":"US",
    "sg:address":"242 Drexel Ave",
    "sg:city":"Westbury",
    "sg:classifiers":[
        {
            "category":"Professional",
            "subcategory":"Lawyer & Legal Services",
            "type":"Services"
        }
    ],
    "sg:phone":"+1 516 876 0800",
    "sg:postcode":"11590",
    "sg:province":"NY",
    "sg:tags":[
        "attorney"
    ],
    "wof:name":"Druckman & Sinel Llp",
    "wof:placetype":"venue"
},
  "geometry": {"coordinates":[-73.58910400000001,40.757801],"type":"Point"}
}