{
  "type": "Feature",
  "properties": {
    "iso:country":"US",
    "sg:address":"400 Route 211 E Ste 9",
    "sg:city":"Middletown",
    "sg:classifiers":[
        {
            "category":"Restaurant",
            "type":"Food & Drink"
        }
    ],
    "sg:phone":"+1 845 343 6888",
    "sg:postcode":"10940",
    "sg:province":"NY",
    "sg:tags":[
        "buffet"
    ],
    "wof:name":"New King Buffet",
    "wof:placetype":"venue"
},
  "geometry": {"coordinates":[-74.38732899999999,41.455688],"type":"Point"}
}