{
  "type": "Feature",
  "properties": {
    "iso:country":"US",
    "sg:address":"832 Washington Ave",
    "sg:city":"Brooklyn",
    "sg:classifiers":[
        {
            "category":"Banks & Credit Unions",
            "subcategory":"Bank",
            "type":"Services"
        }
    ],
    "sg:phone":"+1 718 622 8883",
    "sg:postcode":"11238",
    "sg:province":"NY",
    "sg:tags":[
        "cashing",
        "check"
    ],
    "wof:name":"Pay-O-Matic",
    "wof:placetype":"venue"
},
  "geometry": {"coordinates":[-73.962946,40.673306],"type":"Point"}
}