{
  "type": "Feature",
  "properties": {
    "addr:full":"25309 139th Ave Rosedale NY 11422",
    "addr:housenumber":"25309",
    "addr:postcode":"11422",
    "addr:street":"139Th Ave",
    "iso:country":"US",
    "sg:address":"25309 139th Ave",
    "sg:city":"Rosedale",
    "sg:classifiers":[
        {
            "category":"Wholesale",
            "subcategory":"Computers",
            "type":"Manufacturing & Wholesale Goods"
        }
    ],
    "sg:phone":"+1 800 631 7581",
    "sg:postcode":"11422",
    "sg:province":"NY",
    "wof:name":"Microfax Computers",
    "wof:placetype":"venue"
},
  "geometry": {"coordinates":[-73.729623,40.661873],"type":"Point"}
}