{
  "type": "Feature",
  "properties": {
    "iso:country":"US",
    "sg:address":"841 Tilden St",
    "sg:city":"Bronx",
    "sg:classifiers":[
        {
            "category":"Building & Trades",
            "subcategory":"Construction",
            "type":"Services"
        }
    ],
    "sg:phone":"+1 718 828 9100",
    "sg:postcode":"10467",
    "sg:province":"NY",
    "sg:tags":[
        "waterproofing",
        "contractor"
    ],
    "wof:name":"Ag Waterproofing Corp",
    "wof:placetype":"venue"
},
  "geometry": {"coordinates":[-73.860336,40.876934],"type":"Point"}
}