{
  "type": "Feature",
  "properties": {
    "iso:country":"US",
    "sg:address":"238 6th Ave",
    "sg:city":"Brooklyn",
    "sg:classifiers":[
        {
            "category":"Professional",
            "subcategory":"Computer Services",
            "type":"Services"
        }
    ],
    "sg:phone":"+1 718 499 3979",
    "sg:postcode":"11215",
    "sg:province":"NY",
    "sg:tags":[
        "design",
        "system"
    ],
    "wof:name":"Idvector Inc",
    "wof:placetype":"venue"
},
  "geometry": {"coordinates":[-73.979437,40.673565],"type":"Point"}
}