{
  "type": "Feature",
  "properties": {
    "addr:full":"514 Middle Country Rd Middle Island NY 11953",
    "addr:housenumber":"514",
    "addr:postcode":"11953",
    "addr:street":"Middle Country Rd Middle Island",
    "iso:country":"US",
    "sg:address":"514 Middle Country Rd",
    "sg:city":"Middle Island",
    "sg:classifiers":[
        {
            "category":"Organizations",
            "subcategory":"Non-profit Organization",
            "type":"Services"
        },
        {
            "category":"Health Services",
            "subcategory":"Hospital",
            "type":"Services"
        }
    ],
    "sg:phone":"+1 631 924 3741",
    "sg:postcode":"11953",
    "sg:province":"NY",
    "sg:tags":[
        "information",
        "treatment",
        "alcoholism",
        "specialty"
    ],
    "wof:name":"Family Recovery Ctr",
    "wof:placetype":"venue"
},
  "geometry": {"coordinates":[-72.959013,40.879508],"type":"Point"}
}