{
  "type": "Feature",
  "properties": {
    "iso:country":"US",
    "sg:address":"5 Washington Ave",
    "sg:city":"Bay Shore",
    "sg:classifiers":[
        {
            "category":"Building & Trades",
            "subcategory":"Plumbing",
            "type":"Services"
        }
    ],
    "sg:phone":"+1 631 586 9560",
    "sg:postcode":"11706",
    "sg:province":"NY",
    "sg:tags":[
        "engineering",
        "contractor"
    ],
    "wof:name":"Marchia Mj Inc",
    "wof:placetype":"venue"
},
  "geometry": {"coordinates":[-73.29001100000001,40.767403],"type":"Point"}
}