{
  "type": "Feature",
  "properties": {
    "addr:full":"28 Pen Web Park Webster NY 14580",
    "addr:housenumber":"28",
    "addr:postcode":"14580",
    "addr:street":"Pen Web Park",
    "iso:country":"US",
    "sg:address":"28 Pen Web Park",
    "sg:city":"Webster",
    "sg:classifiers":[
        {
            "category":"Building & Trades",
            "subcategory":"Construction",
            "type":"Services"
        }
    ],
    "sg:phone":"+1 585 671 0474",
    "sg:postcode":"14580",
    "sg:province":"NY",
    "sg:tags":[
        "home",
        "builder"
    ],
    "wof:name":"Pen-Web Corp",
    "wof:placetype":"venue"
},
  "geometry": {"coordinates":[-77.499503,43.187478],"type":"Point"}
}