{
  "type": "Feature",
  "properties": {
    "iso:country":"US",
    "sg:address":"34 Vineyard Rd",
    "sg:city":"Huntington",
    "sg:classifiers":[
        {
            "category":"Building & Trades",
            "subcategory":"Construction",
            "type":"Services"
        }
    ],
    "sg:phone":"+1 631 271 5086",
    "sg:postcode":"11743",
    "sg:province":"NY",
    "sg:tags":[
        "hanging",
        "contractor"
    ],
    "wof:name":"Kmr Painting & Decorating",
    "wof:placetype":"venue"
},
  "geometry": {"coordinates":[-73.40498599999999,40.882026],"type":"Point"}
}