{
  "type": "Feature",
  "properties": {
    "iso:country":"US",
    "sg:address":"900 Merchants Concourse",
    "sg:city":"Westbury",
    "sg:classifiers":[
        {
            "category":"Professional",
            "subcategory":"Computer Services",
            "type":"Services"
        }
    ],
    "sg:phone":"+1 516 561 1342",
    "sg:postcode":"11590",
    "sg:province":"NY",
    "sg:tags":[
        "repair"
    ],
    "sg:website":"www.tekki.com",
    "wof:name":"Tekki Corp",
    "wof:placetype":"venue"
},
  "geometry": {"coordinates":[-73.577904,40.749802],"type":"Point"}
}