{
  "type": "Feature",
  "properties": {
    "iso:country":"US",
    "sg:address":"135 Margaret St",
    "sg:city":"Plattsburgh",
    "sg:classifiers":[
        {
            "category":"Government",
            "subcategory":"Office",
            "type":"Public Place"
        }
    ],
    "sg:phone":"+1 518 565 4800",
    "sg:postcode":"12901",
    "sg:province":"NY",
    "sg:tags":[
        "program",
        "administrative"
    ],
    "wof:name":"Jtpa",
    "wof:placetype":"venue"
},
  "geometry": {"coordinates":[-73.453147,44.699247],"type":"Point"}
}