{
  "type": "Feature",
  "properties": {
    "addr:full":"6 Enterprise Dr East Setauket NY 11733",
    "addr:housenumber":"6",
    "addr:postcode":"11733",
    "addr:street":"Enterprise Dr East",
    "iso:country":"US",
    "sg:address":"6 Enterprise Dr",
    "sg:city":"East Setauket",
    "sg:classifiers":[
        {
            "category":"Building & Trades",
            "subcategory":"Construction",
            "type":"Services"
        }
    ],
    "sg:phone":"+1 631 331 1665",
    "sg:postcode":"11733",
    "sg:province":"NY",
    "sg:tags":[
        "concrete",
        "contractor"
    ],
    "wof:name":"Extreme Concrete Designs",
    "wof:placetype":"venue"
},
  "geometry": {"coordinates":[-73.082988,40.935163],"type":"Point"}
}