{
  "type": "Feature",
  "properties": {
    "addr:full":"1100 Jefferson Rd Rochester NY 14623",
    "addr:housenumber":"1100",
    "addr:postcode":"14623",
    "addr:street":"Jefferson Rd",
    "iso:country":"US",
    "sg:address":"1100 Jefferson Rd",
    "sg:city":"Rochester",
    "sg:classifiers":[
        {
            "category":"Manufacturing",
            "subcategory":"Wood Products",
            "type":"Manufacturing & Wholesale Goods"
        }
    ],
    "sg:phone":"+1   ",
    "sg:postcode":"14623",
    "sg:province":"NY",
    "sg:tags":[
        "tool",
        "woodworking",
        "accessory"
    ],
    "sg:website":"www.woodcraft.com",
    "wof:name":"Woodcraft",
    "wof:placetype":"venue"
},
  "geometry": {"coordinates":[-77.607185,43.08728],"type":"Point"}
}