{
  "type": "Feature",
  "properties": {
    "iso:country":"US",
    "sg:address":"124 Lexington Avenue",
    "sg:city":"New York",
    "sg:classifiers":[
        {
            "category":"Restaurant",
            "type":"Food & Drink"
        }
    ],
    "sg:phone":"+1 212 683 6207",
    "sg:postcode":"10016",
    "sg:province":"NY",
    "wof:name":"Niamatkada",
    "wof:placetype":"venue"
},
  "geometry": {"coordinates":[-73.98237,40.742782],"type":"Point"}
}