{
  "type": "Feature",
  "properties": {
    "iso:country":"US",
    "sg:address":"109 Williams Rd",
    "sg:city":"East Rochester",
    "sg:classifiers":[
        {
            "category":"Shopping",
            "subcategory":"Stationery & Office Supplies",
            "type":"Retail Goods"
        }
    ],
    "sg:phone":"+1   ",
    "sg:postcode":"14467",
    "sg:province":"NY",
    "wof:name":"Gen Co Enterprise",
    "wof:placetype":"venue"
},
  "geometry": {"coordinates":[-77.602581,43.022825],"type":"Point"}
}