{
  "type": "Feature",
  "properties": {
    "iso:country":"US",
    "sg:address":"732 Jerusalem Ave",
    "sg:city":"Uniondale",
    "sg:classifiers":[
        {
            "category":"Building & Trades",
            "subcategory":"Landscaping Services",
            "type":"Services"
        }
    ],
    "sg:phone":"+1 516 410 4771",
    "sg:postcode":"11553",
    "sg:province":"NY",
    "sg:tags":[
        "landscape",
        "contractor"
    ],
    "wof:name":"Edgard Landscaping",
    "wof:placetype":"venue"
},
  "geometry": {"coordinates":[-73.590366,40.699642],"type":"Point"}
}