{
  "type": "Feature",
  "properties": {
    "iso:country":"US",
    "sg:address":"357 S Middletown Rd",
    "sg:city":"Nanuet",
    "sg:classifiers":[
        {
            "category":"Health Services",
            "subcategory":"Hospital",
            "type":"Services"
        }
    ],
    "sg:phone":"+1 845 623 9193",
    "sg:postcode":"10954",
    "sg:province":"NY",
    "sg:tags":[
        "mental"
    ],
    "wof:name":"Nanuet House",
    "wof:placetype":"venue"
},
  "geometry": {"coordinates":[-74.01479500000001,41.080235],"type":"Point"}
}