{
  "type": "Feature",
  "properties": {
    "addr:full":"13 E 6th Rd Far Rockaway NY 11693",
    "addr:housenumber":"13",
    "addr:postcode":"11693",
    "addr:street":"E 6Th Rd",
    "iso:country":"US",
    "sg:address":"13 E 6th Rd",
    "sg:city":"Far Rockaway",
    "sg:classifiers":[
        {
            "category":"Professional",
            "subcategory":"Management & Consulting",
            "type":"Services"
        }
    ],
    "sg:phone":"+1   ",
    "sg:postcode":"11693",
    "sg:province":"NY",
    "sg:tags":[
        "promotion"
    ],
    "wof:name":"Able Associates",
    "wof:placetype":"venue"
},
  "geometry": {"coordinates":[-73.81801400000001,40.609314],"type":"Point"}
}