{
  "type": "Feature",
  "properties": {
    "addr:full":"33 E 20th St New York NY 10003",
    "addr:housenumber":"33",
    "addr:postcode":"10003",
    "addr:street":"E 20Th St",
    "iso:country":"US",
    "sg:address":"33 E 20th St",
    "sg:city":"New York",
    "sg:classifiers":[
        {
            "category":"Real Estate",
            "subcategory":"Real Estate Services",
            "type":"Services"
        }
    ],
    "sg:phone":"+1 212 583 1358",
    "sg:postcode":"10003",
    "sg:province":"NY",
    "sg:tags":[
        "management",
        "property"
    ],
    "wof:name":"Yorkshire House Assocs",
    "wof:placetype":"venue"
},
  "geometry": {"coordinates":[-73.98894900000001,40.738846],"type":"Point"}
}