{
  "type": "Feature",
  "properties": {
    "addr:full":"592 Hangar Rd Rome NY 13441",
    "addr:housenumber":"592",
    "addr:postcode":"13441",
    "addr:street":"Hangar Rd",
    "iso:country":"US",
    "sg:address":"592 Hangar Rd",
    "sg:city":"Rome",
    "sg:classifiers":[
        {
            "category":"Autos & Motor Vehicles",
            "subcategory":"Automobile Sales",
            "type":"Retail Goods"
        },
        {
            "category":"Retail",
            "subcategory":"Auto Rental",
            "type":"Services"
        }
    ],
    "sg:phone":"+1 315 334 4562",
    "sg:postcode":"13441",
    "sg:province":"NY",
    "sg:tags":[
        "car",
        "leasing",
        "truck"
    ],
    "sg:website":"http://budget.com/IYP_tl",
    "wof:name":"Budget Rent A Car",
    "wof:placetype":"venue"
},
  "geometry": {"coordinates":[-75.407747,43.225202],"type":"Point"}
}