{
  "type": "Feature",
  "properties": {
    "iso:country":"US",
    "sg:address":"102 Sears Ave",
    "sg:city":"Elmsford",
    "sg:classifiers":[
        {
            "category":"Local Transit",
            "type":"Transportation"
        }
    ],
    "sg:phone":"+1   ",
    "sg:postcode":"10523",
    "sg:province":"NY",
    "sg:tags":[
        "passenger"
    ],
    "wof:name":"Tri State Transportation",
    "wof:placetype":"venue"
},
  "geometry": {"coordinates":[-73.811685,41.062024],"type":"Point"}
}