{
  "type": "Feature",
  "properties": {
    "addr:full":"244 W Main St Goshen NY 10924",
    "addr:housenumber":"244",
    "addr:postcode":"10924",
    "addr:street":"W Main St",
    "iso:country":"US",
    "sg:address":"244 W Main St",
    "sg:city":"Goshen",
    "sg:classifiers":[
        {
            "category":"Personal",
            "subcategory":"Beauty Salon",
            "type":"Services"
        }
    ],
    "sg:phone":"+1 845 294 9211",
    "sg:postcode":"10924",
    "sg:province":"NY",
    "wof:name":"Martha & Co",
    "wof:placetype":"venue"
},
  "geometry": {"coordinates":[-74.330049,41.400729],"type":"Point"}
}