{
  "type": "Feature",
  "properties": {
    "addr:full":"151 E Melcourt Dr Buffalo NY 14225",
    "addr:housenumber":"151",
    "addr:postcode":"14225",
    "addr:street":"E Melcourt Dr",
    "iso:country":"US",
    "sg:address":"151 E Melcourt Dr",
    "sg:city":"Buffalo",
    "sg:classifiers":[
        {
            "category":"Building & Trades",
            "subcategory":"Construction",
            "type":"Services"
        }
    ],
    "sg:phone":"+1 716 891 8468",
    "sg:postcode":"14225",
    "sg:province":"NY",
    "sg:tags":[
        "handyman"
    ],
    "wof:name":"Lyric Contracting",
    "wof:placetype":"venue"
},
  "geometry": {"coordinates":[-78.76720299999999,42.921598],"type":"Point"}
}