{
  "type": "Feature",
  "properties": {
    "iso:country":"US",
    "sg:address":"7 Madison Ave",
    "sg:city":"Larchmont",
    "sg:classifiers":[
        {
            "category":"Restaurant",
            "type":"Food & Drink"
        }
    ],
    "sg:phone":"+1 914 833 9416",
    "sg:postcode":"10538",
    "sg:province":"NY",
    "wof:name":"LA Villetta Ristorante",
    "wof:placetype":"venue"
},
  "geometry": {"coordinates":[-73.763638,40.932838],"type":"Point"}
}