{
  "type": "Feature",
  "properties": {
    "addr:full":"1455 Weaver St Scarsdale NY 10583",
    "addr:housenumber":"1455",
    "addr:postcode":"10583",
    "addr:street":"Weaver St",
    "iso:country":"US",
    "sg:address":"1455 Weaver St",
    "sg:city":"Scarsdale",
    "sg:classifiers":[
        {
            "category":"Autos & Motor Vehicles",
            "subcategory":"Fuel & Gas Station",
            "type":"Retail Goods"
        }
    ],
    "sg:phone":"+1 914 472 6356",
    "sg:postcode":"10583",
    "sg:province":"NY",
    "sg:tags":[
        "oil"
    ],
    "wof:name":"Shell",
    "wof:placetype":"venue"
},
  "geometry": {"coordinates":[-73.77545499999999,40.97667],"type":"Point"}
}