{
  "type": "Feature",
  "properties": {
    "iso:country":"US",
    "sg:address":"10 Genesee St E",
    "sg:city":"Scottsville",
    "sg:classifiers":[
        {
            "category":"Organizations",
            "subcategory":"Religious Organization",
            "type":"Services"
        }
    ],
    "sg:phone":"+1 585 889 9540",
    "sg:postcode":"14546",
    "sg:province":"NY",
    "sg:tags":[
        "clergy"
    ],
    "wof:name":"Ronald Sallade",
    "wof:placetype":"venue"
},
  "geometry": {"coordinates":[-77.743801,43.022109],"type":"Point"}
}