{
  "type": "Feature",
  "properties": {
    "iso:country":"US",
    "sg:address":"405 Jewell Dr",
    "sg:city":"Liverpool",
    "sg:classifiers":[
        {
            "category":"Building & Trades",
            "subcategory":"Electrical",
            "type":"Services"
        }
    ],
    "sg:phone":"+1 315 451 4965",
    "sg:postcode":"13088",
    "sg:province":"NY",
    "sg:tags":[
        "electrical",
        "contractor"
    ],
    "wof:name":"Carmine Carapella",
    "wof:placetype":"venue"
},
  "geometry": {"coordinates":[-76.17230499999999,43.114504],"type":"Point"}
}