{
  "type": "Feature",
  "properties": {
    "addr:full":"866 United Nations Plaza New York NY 10017",
    "addr:housenumber":"866",
    "addr:postcode":"10017",
    "addr:street":"United Nations Plaza",
    "iso:country":"US",
    "sg:address":"866 United Nations Plaza",
    "sg:city":"New York",
    "sg:classifiers":[
        {
            "category":"Professional",
            "subcategory":"Lawyer & Legal Services",
            "type":"Services"
        }
    ],
    "sg:phone":"+1 212 661 8770",
    "sg:postcode":"10017",
    "sg:province":"NY",
    "wof:name":"Fersko Ray",
    "wof:placetype":"venue"
},
  "geometry": {"coordinates":[-73.96686699999999,40.752413],"type":"Point"}
}