{
  "type": "Feature",
  "properties": {
    "iso:country":"US",
    "sg:address":"980 Church St",
    "sg:city":"Baldwin",
    "sg:classifiers":[
        {
            "category":"Home & Garden",
            "subcategory":"Furniture",
            "type":"Retail Goods"
        }
    ],
    "sg:phone":"+1 516 223 3621",
    "sg:postcode":"11510",
    "sg:province":"NY",
    "sg:tags":[
        "mattress"
    ],
    "wof:name":"Money Matters Inc",
    "wof:placetype":"venue"
},
  "geometry": {"coordinates":[-73.60550600000001,40.641342],"type":"Point"}
}