{
  "type": "Feature",
  "properties": {
    "iso:country":"US",
    "sg:address":"60 W 57th St",
    "sg:city":"New York",
    "sg:classifiers":[
        {
            "category":"Shopping",
            "subcategory":"Department Store",
            "type":"Retail Goods"
        }
    ],
    "sg:phone":"+1 212 957 1487",
    "sg:postcode":"10019",
    "sg:province":"NY",
    "wof:name":"Momart Discount Store Ltd",
    "wof:placetype":"venue"
},
  "geometry": {"coordinates":[-73.976501,40.764198],"type":"Point"}
}