{
  "type": "Feature",
  "properties": {
    "addr:full":"960 W Jericho Tpke Smithtown NY 11787",
    "addr:housenumber":"960",
    "addr:postcode":"11787",
    "addr:street":"W Jericho Tpke",
    "iso:country":"US",
    "sg:address":"960 W Jericho Tpke",
    "sg:city":"Smithtown",
    "sg:classifiers":[
        {
            "category":"Real Estate",
            "subcategory":"Real Estate Agent",
            "type":"Services"
        }
    ],
    "sg:phone":"+1 631 724 8500",
    "sg:postcode":"11787",
    "sg:province":"NY",
    "wof:name":"Century 21",
    "wof:placetype":"venue"
},
  "geometry": {"coordinates":[-73.250441,40.847708],"type":"Point"}
}