{
  "type": "Feature",
  "properties": {
    "iso:country":"US",
    "sg:address":"2001 College Ave",
    "sg:city":"Elmira",
    "sg:classifiers":[
        {
            "category":"Restaurant",
            "type":"Food & Drink"
        }
    ],
    "sg:phone":"+1 607 732 5085",
    "sg:postcode":"14901",
    "sg:province":"NY",
    "wof:name":"KFC",
    "wof:placetype":"venue"
},
  "geometry": {"coordinates":[-76.82277999999999,42.117878],"type":"Point"}
}