{
  "type": "Feature",
  "properties": {
    "addr:full":"977 Allerton Avenue Bronx NY 10469",
    "addr:housenumber":"977",
    "addr:postcode":"10469",
    "addr:street":"Allerton Avenue",
    "iso:country":"US",
    "sg:address":"977 Allerton Avenue",
    "sg:city":"Bronx",
    "sg:classifiers":[
        {
            "category":"Real Estate",
            "subcategory":"Real Estate Services",
            "type":"Services"
        }
    ],
    "sg:phone":"+1 718 882 1200",
    "sg:postcode":"10469",
    "sg:province":"NY",
    "wof:name":"Vataj Realty",
    "wof:placetype":"venue"
},
  "geometry": {"coordinates":[-73.859298,40.865615],"type":"Point"}
}