{
  "type": "Feature",
  "properties": {
    "iso:country":"US",
    "sg:address":"210 N Franklin St",
    "sg:city":"Watkins Glen",
    "sg:classifiers":[
        {
            "category":"Manufacturing",
            "subcategory":"Printing",
            "type":"Manufacturing & Wholesale Goods"
        }
    ],
    "sg:phone":"+1   ",
    "sg:postcode":"14891",
    "sg:province":"NY",
    "sg:tags":[
        "newspaper",
        "offset"
    ],
    "wof:name":"Daily News The",
    "wof:placetype":"venue"
},
  "geometry": {"coordinates":[-76.874022,42.38175],"type":"Point"}
}