{
  "type": "Feature",
  "properties": {
    "iso:country":"US",
    "sg:address":"1428 E Gun Hill Rd",
    "sg:city":"Bronx",
    "sg:classifiers":[
        {
            "category":"Professional",
            "subcategory":"Lawyer & Legal Services",
            "type":"Services"
        }
    ],
    "sg:phone":"+1 718 882 2681",
    "sg:postcode":"10469",
    "sg:province":"NY",
    "sg:tags":[
        "attorney"
    ],
    "wof:name":"Rodman & Campbell PC",
    "wof:placetype":"venue"
},
  "geometry": {"coordinates":[-73.844994,40.869827],"type":"Point"}
}