{
  "type": "Feature",
  "properties": {
    "iso:country":"US",
    "sg:address":"350 W 51st St Near 9th Ave",
    "sg:city":"New York",
    "sg:classifiers":[
        {
            "category":"Coffee & Tea",
            "type":"Food & Drink"
        }
    ],
    "sg:phone":"+1 646 330 5515",
    "sg:postcode":"10019",
    "sg:province":"NY",
    "sg:website":"www.bkoffie.com/",
    "wof:name":"B. Koffie",
    "wof:placetype":"venue"
},
  "geometry": {"coordinates":[-73.987616,40.763601],"type":"Point"}
}