{
  "type": "Feature",
  "properties": {
    "iso:country":"US",
    "sg:address":"118 Cayuga St",
    "sg:city":"Fulton",
    "sg:classifiers":[
        {
            "category":"Personal",
            "type":"Services"
        }
    ],
    "sg:phone":"+1   ",
    "sg:postcode":"13069",
    "sg:province":"NY",
    "wof:name":"Radison Sun Studio",
    "wof:placetype":"venue"
},
  "geometry": {"coordinates":[-76.416405,43.324158],"type":"Point"}
}