{
  "type": "Feature",
  "properties": {
    "addr:full":"674 Old Liverpool Rd Liverpool NY 13088",
    "addr:housenumber":"674",
    "addr:postcode":"13088",
    "addr:street":"Old Liverpool Rd",
    "iso:country":"US",
    "sg:address":"674 Old Liverpool Rd",
    "sg:city":"Liverpool",
    "sg:classifiers":[
        {
            "category":"Building & Trades",
            "subcategory":"Cleaning & Sanitation",
            "type":"Services"
        }
    ],
    "sg:phone":"+1 315 451 9298",
    "sg:postcode":"13088",
    "sg:province":"NY",
    "sg:tags":[
        "janitor"
    ],
    "wof:name":"Clean Town",
    "wof:placetype":"venue"
},
  "geometry": {"coordinates":[-76.194793,43.093579],"type":"Point"}
}