{
  "type": "Feature",
  "properties": {
    "addr:full":"862 Huguenot Avenue Staten Island NY 10312",
    "addr:housenumber":"862",
    "addr:postcode":"10312",
    "addr:street":"Huguenot Avenue",
    "iso:country":"US",
    "sg:address":"862 Huguenot Avenue",
    "sg:city":"Staten Island",
    "sg:classifiers":[
        {
            "category":"Restaurant",
            "type":"Food & Drink"
        }
    ],
    "sg:phone":"+1 718 605 0620",
    "sg:postcode":"10312",
    "sg:province":"NY",
    "sg:tags":[
        "pizza"
    ],
    "wof:name":"Ciro Pizza Cafe",
    "wof:placetype":"venue"
},
  "geometry": {"coordinates":[-74.192527,40.533317],"type":"Point"}
}