{
  "type": "Feature",
  "properties": {
    "addr:full":"405 E Main St Unit A Bay Shore NY 11706",
    "addr:housenumber":"405",
    "addr:postcode":"11706",
    "addr:street":"E Main St Unit A",
    "iso:country":"US",
    "sg:address":"405 E Main St Unit A",
    "sg:city":"Bay Shore",
    "sg:classifiers":[
        {
            "category":"Real Estate",
            "subcategory":"Real Estate Operator",
            "type":"Services"
        }
    ],
    "sg:phone":"+1 631 666 7860",
    "sg:postcode":"11706",
    "sg:province":"NY",
    "sg:tags":[
        "apartment"
    ],
    "wof:name":"Hedges the",
    "wof:placetype":"venue"
},
  "geometry": {"coordinates":[-73.233857,40.727474],"type":"Point"}
}