{
  "type": "Feature",
  "properties": {
    "iso:country":"US",
    "sg:address":"3541 Long Beach Rd",
    "sg:city":"Oceanside",
    "sg:classifiers":[
        {
            "category":"Shopping",
            "subcategory":"Clothing, Apparel, & Fashions",
            "type":"Retail Goods"
        }
    ],
    "sg:phone":"+1 516 596 0100",
    "sg:postcode":"11572",
    "sg:province":"NY",
    "sg:tags":[
        "shoe",
        "store"
    ],
    "sg:website":"www.incrediblefeets.com",
    "wof:name":"Incredible Feets",
    "wof:placetype":"venue"
},
  "geometry": {"coordinates":[-73.639397,40.6245],"type":"Point"}
}