{
  "type": "Feature",
  "properties": {
    "iso:country":"US",
    "sg:address":"2001 4th Ave",
    "sg:city":"Troy",
    "sg:classifiers":[
        {
            "category":"Health Services",
            "subcategory":"Doctor",
            "type":"Services"
        }
    ],
    "sg:phone":"+1 518 274 9126",
    "sg:postcode":"12189",
    "sg:province":"NY",
    "sg:tags":[
        "medical"
    ],
    "wof:name":"James M Cioffi",
    "wof:placetype":"venue"
},
  "geometry": {"coordinates":[-73.703529,42.732928],"type":"Point"}
}