{
  "type": "Feature",
  "properties": {
    "addr:full":"940 Homestead Ave Maybrook NY 12543",
    "addr:housenumber":"940",
    "addr:postcode":"12543",
    "addr:street":"Homestead Ave",
    "iso:country":"US",
    "sg:address":"940 Homestead Ave",
    "sg:city":"Maybrook",
    "sg:classifiers":[
        {
            "category":"Restaurant",
            "type":"Food & Drink"
        }
    ],
    "sg:phone":"+1 845 427 5067",
    "sg:postcode":"12543",
    "sg:province":"NY",
    "wof:name":"Maybrook Diner",
    "wof:placetype":"venue"
},
  "geometry": {"coordinates":[-74.20790100000001,41.496899],"type":"Point"}
}