{
  "type": "Feature",
  "properties": {
    "addr:full":"4307 National St Corona NY 11368",
    "addr:housenumber":"4307",
    "addr:postcode":"11368",
    "addr:street":"National St",
    "iso:country":"US",
    "sg:address":"4307 National St",
    "sg:city":"Corona",
    "sg:classifiers":[
        {
            "category":"Personal",
            "subcategory":"Barber",
            "type":"Services"
        }
    ],
    "sg:phone":"+1 718 429 5843",
    "sg:postcode":"11368",
    "sg:province":"NY",
    "wof:name":"Leo's Barber Shop",
    "wof:placetype":"venue"
},
  "geometry": {"coordinates":[-73.86370100000001,40.746399],"type":"Point"}
}