{
  "type": "Feature",
  "properties": {
    "iso:country":"US",
    "sg:address":"710 Rockaway Ave",
    "sg:city":"Brooklyn",
    "sg:classifiers":[
        {
            "category":"Shopping",
            "subcategory":"Pharmacy",
            "type":"Retail Goods"
        }
    ],
    "sg:phone":"+1 718 498 2277",
    "sg:postcode":"11212",
    "sg:province":"NY",
    "wof:name":"Rockway Rx Inc",
    "wof:placetype":"venue"
},
  "geometry": {"coordinates":[-73.908524,40.661014],"type":"Point"}
}