{
  "type": "Feature",
  "properties": {
    "addr:full":"149 8th Ave New York NY 10011",
    "addr:housenumber":"149",
    "addr:postcode":"10011",
    "addr:street":"8Th Ave",
    "iso:country":"US",
    "sg:address":"149 8th Ave",
    "sg:city":"New York",
    "sg:classifiers":[
        {
            "category":"Restaurant",
            "type":"Food & Drink"
        }
    ],
    "sg:phone":"+1 212 620 4015",
    "sg:postcode":"10011",
    "sg:province":"NY",
    "sg:tags":[
        "mexican"
    ],
    "sg:website":"www.chipotle.com/",
    "wof:name":"Chipotle",
    "wof:placetype":"venue"
},
  "geometry": {"coordinates":[-74.0011004917,40.7420322531],"type":"Point"}
}