{
  "type": "Feature",
  "properties": {
    "addr:full":"164 W 25th St New York NY 10001",
    "addr:housenumber":"164",
    "addr:postcode":"10001",
    "addr:street":"W 25Th St",
    "iso:country":"US",
    "sg:address":"164 W 25th St",
    "sg:city":"New York",
    "sg:classifiers":[
        {
            "category":"Shopping",
            "subcategory":"Florist",
            "type":"Retail Goods"
        }
    ],
    "sg:phone":"+1 212 679 3229",
    "sg:postcode":"10001",
    "sg:province":"NY",
    "wof:name":"Design Fusion",
    "wof:placetype":"venue"
},
  "geometry": {"coordinates":[-73.99431199999999,40.745131],"type":"Point"}
}