{
  "type": "Feature",
  "properties": {
    "iso:country":"US",
    "sg:address":"194 Harman Street",
    "sg:city":"Brooklyn",
    "sg:classifiers":[
        {
            "category":"Education",
            "subcategory":"School",
            "type":"Public Place"
        }
    ],
    "sg:phone":"+1 718 573 0781",
    "sg:postcode":"11237",
    "sg:province":"NY",
    "sg:tags":[
        "high",
        "middle",
        "elementary"
    ],
    "wof:name":"N Y City of",
    "wof:placetype":"venue"
},
  "geometry": {"coordinates":[-73.920637,40.698209],"type":"Point"}
}