{
  "type": "Feature",
  "properties": {
    "iso:country":"US",
    "sg:address":"546 S Glenora Rd",
    "sg:city":"Dundee",
    "sg:classifiers":[
        {
            "category":"Travel",
            "subcategory":"Hotels & Motels",
            "type":"Entertainment"
        }
    ],
    "sg:phone":"+1 607 243 7414",
    "sg:postcode":"14837",
    "sg:province":"NY",
    "sg:tags":[
        "breakfast",
        "accommodation",
        "bed"
    ],
    "wof:name":"Tree Farm Bed & Breakfast",
    "wof:placetype":"venue"
},
  "geometry": {"coordinates":[-76.94168999999999,42.484064],"type":"Point"}
}