{
  "type": "Feature",
  "properties": {
    "addr:full":"34 May St Webster NY 14580",
    "addr:housenumber":"34",
    "addr:postcode":"14580",
    "addr:street":"May St",
    "iso:country":"US",
    "sg:address":"34 May St",
    "sg:city":"Webster",
    "sg:classifiers":[
        {
            "category":"Professional",
            "subcategory":"Art Services",
            "type":"Services"
        }
    ],
    "sg:phone":"+1 585 872 9222",
    "sg:postcode":"14580",
    "sg:province":"NY",
    "sg:tags":[
        "graphic",
        "arts",
        "designer",
        "design",
        "related"
    ],
    "sg:website":"www.forwardbranding.com",
    "wof:name":"Forward Branding & Identity",
    "wof:placetype":"venue"
},
  "geometry": {"coordinates":[-77.428932,43.217051],"type":"Point"}
}