{
  "type": "Feature",
  "properties": {
    "iso:country":"US",
    "sg:address":"242 Waverly Ave",
    "sg:city":"Patchogue",
    "sg:classifiers":[
        {
            "category":"Organizations",
            "subcategory":"Labor Organization",
            "type":"Services"
        }
    ],
    "sg:phone":"+1 631 654 1108",
    "sg:postcode":"11772",
    "sg:province":"NY",
    "sg:website":"www.cwa1108.org",
    "wof:name":"CWA Local",
    "wof:placetype":"venue"
},
  "geometry": {"coordinates":[-73.02813399999999,40.773497],"type":"Point"}
}