{
  "type": "Feature",
  "properties": {
    "addr:full":"78 Center St Ellenville NY 12428",
    "addr:housenumber":"78",
    "addr:postcode":"12428",
    "addr:street":"Center St",
    "iso:country":"US",
    "sg:address":"78 Center St",
    "sg:city":"Ellenville",
    "sg:classifiers":[
        {
            "category":"Taxi",
            "type":"Transportation"
        }
    ],
    "sg:phone":"+1   ",
    "sg:postcode":"12428",
    "sg:province":"NY",
    "sg:tags":[
        "taxicab"
    ],
    "wof:name":"C J Cabs",
    "wof:placetype":"venue"
},
  "geometry": {"coordinates":[-74.39491099999999,41.716473],"type":"Point"}
}