{
  "type": "Feature",
  "properties": {
    "iso:country":"US",
    "sg:address":"935 2nd Ave",
    "sg:city":"New York",
    "sg:classifiers":[
        {
            "category":"Personal",
            "type":"Services"
        }
    ],
    "sg:phone":"+1 212 812 2656",
    "sg:postcode":"10022",
    "sg:province":"NY",
    "sg:tags":[
        "towing"
    ],
    "wof:name":"A Towing",
    "wof:placetype":"venue"
},
  "geometry": {"coordinates":[-73.968903,40.754601],"type":"Point"}
}