{
  "type": "Feature",
  "properties": {
    "iso:country":"US",
    "sg:address":"178 Phillips Rd",
    "sg:city":"Webster",
    "sg:classifiers":[
        {
            "category":"Building & Trades",
            "subcategory":"Electrical",
            "type":"Services"
        }
    ],
    "sg:phone":"+1 585 872 0027",
    "sg:postcode":"14580",
    "sg:province":"NY",
    "sg:tags":[
        "electric",
        "industrial",
        "contractors-commercial",
        "contractor"
    ],
    "sg:website":"http://www.allanelectricinc.com",
    "wof:name":"Allan Electric",
    "wof:placetype":"venue"
},
  "geometry": {"coordinates":[-77.41999800000001,43.261764],"type":"Point"}
}