{
  "type": "Feature",
  "properties": {
    "iso:country":"US",
    "sg:address":"9 Devitt Rd",
    "sg:city":"Waterford",
    "sg:classifiers":[
        {
            "category":"Freight",
            "type":"Transportation"
        }
    ],
    "sg:phone":"+1   ",
    "sg:postcode":"12188",
    "sg:province":"NY",
    "sg:tags":[
        "local",
        "trucking"
    ],
    "wof:name":"C R Trucking",
    "wof:placetype":"venue"
},
  "geometry": {"coordinates":[-73.69889499999999,42.821417],"type":"Point"}
}