{
  "type": "Feature",
  "properties": {
    "iso:country":"US",
    "sg:address":"26 W 17th St Ste 503",
    "sg:city":"New York",
    "sg:classifiers":[
        {
            "category":"Building & Trades",
            "subcategory":"Construction",
            "type":"Services"
        }
    ],
    "sg:phone":"+1 212 253 5349",
    "sg:postcode":"10011",
    "sg:province":"NY",
    "sg:tags":[
        "contractor"
    ],
    "wof:name":"Blue Source LIc",
    "wof:placetype":"venue"
},
  "geometry": {"coordinates":[-73.993082,40.738125],"type":"Point"}
}