{
  "type": "Feature",
  "properties": {
    "addr:full":"380 S 2nd St Brooklyn NY 11211",
    "addr:housenumber":"380",
    "addr:postcode":"11211",
    "addr:street":"S 2Nd St",
    "iso:country":"US",
    "sg:address":"380 S 2nd St",
    "sg:city":"Brooklyn",
    "sg:classifiers":[
        {
            "category":"Food & Beverages",
            "subcategory":"Groceries & Convenience Stores",
            "type":"Retail Goods"
        }
    ],
    "sg:phone":"+1 718 302 9679",
    "sg:postcode":"11211",
    "sg:province":"NY",
    "sg:tags":[
        "shop",
        "grocer",
        "meat"
    ],
    "wof:name":"Choco Meat Market",
    "wof:placetype":"venue"
},
  "geometry": {"coordinates":[-73.9534,40.710201],"type":"Point"}
}