{
  "type": "Feature",
  "properties": {
    "iso:country":"US",
    "sg:address":"11783 Broadway St",
    "sg:city":"Alden",
    "sg:classifiers":[
        {
            "category":"Freight",
            "type":"Transportation"
        }
    ],
    "sg:phone":"+1   ",
    "sg:postcode":"14004",
    "sg:province":"NY",
    "sg:tags":[
        "arrangement"
    ],
    "wof:name":"Mercer Transportation",
    "wof:placetype":"venue"
},
  "geometry": {"coordinates":[-78.548931,42.892591],"type":"Point"}
}