{
  "type": "Feature",
  "properties": {
    "addr:full":"1961 Route 6 Carmel NY 10512",
    "addr:housenumber":"1961",
    "addr:postcode":"10512",
    "addr:street":"Route 6",
    "iso:country":"US",
    "sg:address":"1961 Route 6",
    "sg:city":"Carmel",
    "sg:classifiers":[
        {
            "category":"Health Services",
            "subcategory":"Clinic",
            "type":"Services"
        },
        {
            "category":"Personal",
            "type":"Services"
        },
        {
            "category":"Health Services",
            "subcategory":"Health Practitioner",
            "type":"Services"
        }
    ],
    "sg:phone":"+1 845 225 4707",
    "sg:postcode":"10512",
    "sg:province":"NY",
    "sg:tags":[
        "counseling",
        "addiction",
        "abuse",
        "mental",
        "drug"
    ],
    "wof:name":"Therapy & Medication Treatment",
    "wof:placetype":"venue"
},
  "geometry": {"coordinates":[-73.663308,41.411907],"type":"Point"}
}