{
  "type": "Feature",
  "properties": {
    "iso:country":"US",
    "sg:address":"131 W Sunrise Hwy",
    "sg:city":"Lindenhurst",
    "sg:classifiers":[
        {
            "category":"Restaurant",
            "type":"Food & Drink"
        }
    ],
    "sg:phone":"+1   ",
    "sg:postcode":"11757",
    "sg:province":"NY",
    "sg:tags":[
        "eating"
    ],
    "wof:name":"Hing Hing Chinese Takeout",
    "wof:placetype":"venue"
},
  "geometry": {"coordinates":[-73.389993,40.69523],"type":"Point"}
}