{
  "type": "Feature",
  "properties": {
    "iso:country":"US",
    "sg:address":"95 Cantiague Rock Rd",
    "sg:city":"Westbury",
    "sg:classifiers":[
        {
            "category":"Wholesale",
            "subcategory":"Stationery",
            "type":"Manufacturing & Wholesale Goods"
        }
    ],
    "sg:phone":"+1 516 938 8006",
    "sg:postcode":"11590",
    "sg:province":"NY",
    "sg:tags":[
        "paper"
    ],
    "wof:name":"International Paper",
    "wof:placetype":"venue"
},
  "geometry": {"coordinates":[-73.55082,40.767358],"type":"Point"}
}