{
  "type": "Feature",
  "properties": {
    "addr:full":"535 Piermont Ave Piermont NY 10968",
    "addr:housenumber":"535",
    "addr:postcode":"10968",
    "addr:street":"Piermont Ave",
    "iso:country":"US",
    "sg:address":"535 Piermont Ave",
    "sg:city":"Piermont",
    "sg:classifiers":[
        {
            "category":"Shopping",
            "subcategory":"Hobbies, Toys, & Games",
            "type":"Retail Goods"
        },
        {
            "category":"Shopping",
            "subcategory":"Clothing, Apparel, & Fashions",
            "type":"Retail Goods"
        }
    ],
    "sg:phone":"+1 845 359 1669",
    "sg:postcode":"10968",
    "sg:province":"NY",
    "sg:tags":[
        "wear"
    ],
    "wof:name":"Buttercup & Friends Inc",
    "wof:placetype":"venue"
},
  "geometry": {"coordinates":[-73.917146,41.042739],"type":"Point"}
}