{
  "type": "Feature",
  "properties": {
    "iso:country":"US",
    "sg:address":"18 Clover Ln",
    "sg:city":"Northport",
    "sg:classifiers":[
        {
            "category":"Building & Trades",
            "subcategory":"Construction",
            "type":"Services"
        }
    ],
    "sg:phone":"+1 631 754 0444",
    "sg:postcode":"11768",
    "sg:province":"NY",
    "sg:tags":[
        "contractor"
    ],
    "wof:name":"Alfred Its Lasda",
    "wof:placetype":"venue"
},
  "geometry": {"coordinates":[-73.3494,40.876795],"type":"Point"}
}