{
  "type": "Feature",
  "properties": {
    "addr:full":"1956 Meservey Hill Rd Wellsville NY 14895",
    "addr:housenumber":"1956",
    "addr:postcode":"14895",
    "addr:street":"Meservey Hill Rd",
    "iso:country":"US",
    "sg:address":"1956 Meservey Hill Rd",
    "sg:city":"Wellsville",
    "sg:classifiers":[
        {
            "category":"Farming",
            "subcategory":"Dairy Farm",
            "type":"Manufacturing & Wholesale Goods"
        }
    ],
    "sg:phone":"+1 585 593 5045",
    "sg:postcode":"14895",
    "sg:province":"NY",
    "sg:tags":[
        "field",
        "corn",
        "grain",
        "cash",
        "crop"
    ],
    "wof:name":"G Link",
    "wof:placetype":"venue"
},
  "geometry": {"coordinates":[-77.963688,42.083592],"type":"Point"}
}