{
  "type": "Feature",
  "properties": {
    "addr:full":"1926 Lincoln Ave Holbrook NY 11741",
    "addr:housenumber":"1926",
    "addr:postcode":"11741",
    "addr:street":"Lincoln Ave",
    "iso:country":"US",
    "sg:address":"1926 Lincoln Ave",
    "sg:city":"Holbrook",
    "sg:classifiers":[
        {
            "category":"Home & Garden",
            "subcategory":"Building Materials",
            "type":"Retail Goods"
        },
        {
            "category":"Manufacturing",
            "subcategory":"Building Materials",
            "type":"Manufacturing & Wholesale Goods"
        },
        {
            "category":"Home & Garden",
            "subcategory":"Furniture",
            "type":"Retail Goods"
        }
    ],
    "sg:phone":"+1 631 738 0259",
    "sg:postcode":"11741",
    "sg:province":"NY",
    "sg:tags":[
        "cabinet",
        "accessory",
        "window",
        "doors",
        "frames",
        "equipment-household",
        "kitchen"
    ],
    "wof:name":"Doors Plus Inc",
    "wof:placetype":"venue"
},
  "geometry": {"coordinates":[-73.086388,40.807624],"type":"Point"}
}