{
  "type": "Feature",
  "properties": {
    "iso:country":"US",
    "sg:address":"32 E 1st St",
    "sg:city":"Mt Vernon",
    "sg:classifiers":[
        {
            "category":"Organizations",
            "subcategory":"Religious Organization",
            "type":"Services"
        }
    ],
    "sg:phone":"+1 914 665 3532",
    "sg:postcode":"10550",
    "sg:province":"NY",
    "sg:tags":[
        "church"
    ],
    "wof:name":"Power In The Word Ministry",
    "wof:placetype":"venue"
},
  "geometry": {"coordinates":[-73.835618,40.911867],"type":"Point"}
}