{
  "type": "Feature",
  "properties": {
    "iso:country":"US",
    "sg:address":"579 74th St",
    "sg:city":"Brooklyn",
    "sg:classifiers":[
        {
            "category":"Professional",
            "subcategory":"Lawyer & Legal Services",
            "type":"Services"
        }
    ],
    "sg:phone":"+1 718 491 9270",
    "sg:postcode":"11209",
    "sg:province":"NY",
    "wof:name":"McPherson Maryjane Atty",
    "wof:placetype":"venue"
},
  "geometry": {"coordinates":[-74.01979799999999,40.629299],"type":"Point"}
}