{
  "type": "Feature",
  "properties": {
    "addr:full":"322 Rutledge St Brooklyn NY 11211",
    "addr:housenumber":"322",
    "addr:postcode":"11211",
    "addr:street":"Rutledge St",
    "iso:country":"US",
    "sg:address":"322 Rutledge St",
    "sg:city":"Brooklyn",
    "sg:classifiers":[
        {
            "category":"Professional",
            "subcategory":"Art Services",
            "type":"Services"
        }
    ],
    "sg:phone":"+1 718 302 8076",
    "sg:postcode":"11211",
    "sg:province":"NY",
    "sg:tags":[
        "graphic",
        "designer"
    ],
    "wof:name":"Dream Design LTD",
    "wof:placetype":"venue"
},
  "geometry": {"coordinates":[-73.951716,40.70528],"type":"Point"}
}