{
  "type": "Feature",
  "properties": {
    "iso:country":"US",
    "sg:address":"1627 3rd Ave",
    "sg:city":"Watervliet",
    "sg:classifiers":[
        {
            "category":"Organizations",
            "subcategory":"Community Association",
            "type":"Services"
        }
    ],
    "sg:phone":"+1 518 273 9713",
    "sg:postcode":"12189",
    "sg:province":"NY",
    "sg:tags":[
        "club"
    ],
    "wof:name":"Simonian Avakian Vets Post",
    "wof:placetype":"venue"
},
  "geometry": {"coordinates":[-73.70295299999999,42.729081],"type":"Point"}
}