{
  "type": "Feature",
  "properties": {
    "addr:full":"12 Pell Street Bsmt New York NY 10013",
    "addr:housenumber":"12",
    "addr:postcode":"10013",
    "addr:street":"Pell Street",
    "iso:country":"US",
    "sg:address":"12 Pell Street Bsmt",
    "sg:city":"New York",
    "sg:classifiers":[
        {
            "category":"Personal",
            "subcategory":"Beauty Salon",
            "type":"Services"
        }
    ],
    "sg:phone":"+1 212 528 1381",
    "sg:postcode":"10013",
    "sg:province":"NY",
    "sg:tags":[
        "hair"
    ],
    "wof:name":"Lee Lee Beauty & Hair Salon",
    "wof:placetype":"venue"
},
  "geometry": {"coordinates":[-73.997665,40.714864],"type":"Point"}
}