{
  "type": "Feature",
  "properties": {
    "addr:full":"30 Rockefeller Plz New York NY 10112",
    "addr:housenumber":"30",
    "addr:postcode":"10112",
    "addr:street":"Rockefeller Plz",
    "iso:country":"US",
    "sg:address":"30 Rockefeller Plz",
    "sg:city":"New York",
    "sg:classifiers":[
        {
            "category":"Restaurant",
            "type":"Food & Drink"
        }
    ],
    "sg:menulink":"http://www.allmenus.com/ny/new-york/57094-two-boots-rock-center/menu/",
    "sg:phone":"+1 212 332 8800",
    "sg:postcode":"10112",
    "sg:province":"NY",
    "sg:tags":[
        "american",
        "pizza"
    ],
    "wof:name":"Two Boots Rock Center",
    "wof:placetype":"venue"
},
  "geometry": {"coordinates":[-73.97890700000001,40.758454],"type":"Point"}
}