{
  "type": "Feature",
  "properties": {
    "addr:full":"18 Rowe Ave Lynbrook NY 11563",
    "addr:housenumber":"18",
    "addr:postcode":"11563",
    "addr:street":"Rowe Ave",
    "iso:country":"US",
    "sg:address":"18 Rowe Ave",
    "sg:city":"Lynbrook",
    "sg:classifiers":[
        {
            "category":"Shopping",
            "type":"Retail Goods"
        }
    ],
    "sg:phone":"+1 516 599 0849",
    "sg:postcode":"11563",
    "sg:province":"NY",
    "sg:tags":[
        "candle",
        "merchandise"
    ],
    "sg:website":"www.anniesvictorianattic.com",
    "wof:name":"Annie's Victorian Attic",
    "wof:placetype":"venue"
},
  "geometry": {"coordinates":[-73.68016,40.644821],"type":"Point"}
}