{
  "type": "Feature",
  "properties": {
    "addr:full":"898 Park Ave New York NY 10021",
    "addr:housenumber":"898",
    "addr:postcode":"10021",
    "addr:street":"Park Ave",
    "iso:country":"US",
    "sg:address":"898 Park Ave",
    "sg:city":"New York",
    "sg:classifiers":[
        {
            "category":"Health Services",
            "subcategory":"Doctor",
            "type":"Services"
        }
    ],
    "sg:phone":"+1 212 517 5060",
    "sg:postcode":"10021",
    "sg:province":"NY",
    "wof:name":"Jacobson Michael W MD",
    "wof:placetype":"venue"
},
  "geometry": {"coordinates":[-73.96060199999999,40.7757],"type":"Point"}
}