{
  "type": "Feature",
  "properties": {
    "addr:full":"152 Juniper Dr Ballston Spa NY 12020",
    "addr:housenumber":"152",
    "addr:postcode":"12020",
    "addr:street":"Juniper Dr",
    "iso:country":"US",
    "sg:address":"152 Juniper Dr",
    "sg:city":"Ballston Spa",
    "sg:classifiers":[
        {
            "category":"Building & Trades",
            "subcategory":"Construction",
            "type":"Services"
        }
    ],
    "sg:phone":"+1 518 884 8256",
    "sg:postcode":"12020",
    "sg:province":"NY",
    "wof:name":"Pavement Cornell Maintenance",
    "wof:placetype":"venue"
},
  "geometry": {"coordinates":[-73.853887,43.025852],"type":"Point"}
}