{
  "type": "Feature",
  "properties": {
    "iso:country":"US",
    "sg:address":"23 Elizabeth Dr",
    "sg:city":"Chester",
    "sg:classifiers":[
        {
            "category":"Professional",
            "subcategory":"Testing Lab",
            "type":"Services"
        }
    ],
    "sg:phone":"+1 845 469 4087",
    "sg:postcode":"10918",
    "sg:province":"NY",
    "sg:tags":[
        "laboratory"
    ],
    "wof:name":"Steris Isomedix",
    "wof:placetype":"venue"
},
  "geometry": {"coordinates":[-74.289843,41.350422],"type":"Point"}
}