{
  "type": "Feature",
  "properties": {
    "iso:country":"US",
    "sg:address":"169 Cordell Rd",
    "sg:city":"Schenectady",
    "sg:classifiers":[
        {
            "category":"Education",
            "subcategory":"College",
            "type":"Public Place"
        }
    ],
    "sg:phone":"+1 518 382 9304",
    "sg:postcode":"12303",
    "sg:province":"NY",
    "sg:tags":[
        "academic",
        "school"
    ],
    "wof:name":"College Works Lawn & Landscape",
    "wof:placetype":"venue"
},
  "geometry": {"coordinates":[-73.90700200000001,42.753851],"type":"Point"}
}