{
  "type": "Feature",
  "properties": {
    "iso:country":"US",
    "sg:address":"168 E Main St",
    "sg:city":"Port Jervis",
    "sg:classifiers":[
        {
            "category":"Government",
            "subcategory":"Office",
            "type":"Public Place"
        }
    ],
    "sg:phone":"+1 845 858 1468",
    "sg:postcode":"12771",
    "sg:province":"NY",
    "sg:tags":[
        "executive"
    ],
    "wof:name":"Nursing Port Jervis Office",
    "wof:placetype":"venue"
},
  "geometry": {"coordinates":[-74.682807,41.366929],"type":"Point"}
}