{
  "type": "Feature",
  "properties": {
    "addr:full":"337 Court St Brooklyn NY 11231",
    "addr:housenumber":"337",
    "addr:postcode":"11231",
    "addr:street":"Court St",
    "iso:country":"US",
    "sg:address":"337 Court St",
    "sg:city":"Brooklyn",
    "sg:classifiers":[
        {
            "category":"Health Services",
            "subcategory":"Chiropractor",
            "type":"Services"
        }
    ],
    "sg:phone":"+1 718 797 9579",
    "sg:postcode":"11231",
    "sg:province":"NY",
    "wof:name":"Court Chiropractic",
    "wof:placetype":"venue"
},
  "geometry": {"coordinates":[-73.99561300000001,40.682635],"type":"Point"}
}