{
  "type": "Feature",
  "properties": {
    "iso:country":"US",
    "sg:address":"68 Beekman Ave",
    "sg:city":"Sleepy Hollow",
    "sg:classifiers":[
        {
            "category":"Local Transit",
            "type":"Transportation"
        }
    ],
    "sg:phone":"+1 914 631 2277",
    "sg:postcode":"10591",
    "sg:province":"NY",
    "sg:tags":[
        "limousine"
    ],
    "wof:name":"All County Express Car Limo Sv",
    "wof:placetype":"venue"
},
  "geometry": {"coordinates":[-73.861065,41.084582],"type":"Point"}
}