{
  "type": "Feature",
  "properties": {
    "addr:full":"7610 34th Avenue Jackson Heights NY 11372",
    "addr:housenumber":"7610",
    "addr:postcode":"11372",
    "addr:street":"34Th Avenue",
    "iso:country":"US",
    "sg:address":"7610 34th Avenue",
    "sg:city":"Jackson Heights",
    "sg:classifiers":[
        {
            "category":"Health Services",
            "subcategory":"Doctor",
            "type":"Services"
        }
    ],
    "sg:phone":"+1 718 424 4545",
    "sg:postcode":"11372",
    "sg:province":"NY",
    "wof:name":"Santos Zenaida E MD",
    "wof:placetype":"venue"
},
  "geometry": {"coordinates":[-73.890519,40.753091],"type":"Point"}
}