{
  "type": "Feature",
  "properties": {
    "addr:full":"1122 Coney Island Ave Brooklyn NY 11230",
    "addr:housenumber":"1122",
    "addr:postcode":"11230",
    "addr:street":"Coney Island Ave",
    "iso:country":"US",
    "sg:address":"1122 Coney Island Ave",
    "sg:city":"Brooklyn",
    "sg:classifiers":[
        {
            "category":"Shopping",
            "subcategory":"Jewelry",
            "type":"Retail Goods"
        }
    ],
    "sg:phone":"+1 347 221 1913",
    "sg:postcode":"11230",
    "sg:province":"NY",
    "wof:name":"Parkway Jewelers",
    "wof:placetype":"venue"
},
  "geometry": {"coordinates":[-73.96643,40.630177],"type":"Point"}
}