{
  "type": "Feature",
  "properties": {
    "addr:full":"6597 Joy Rd East Syracuse NY 13057",
    "addr:housenumber":"6597",
    "addr:postcode":"13057",
    "addr:street":"Joy Rd",
    "iso:country":"US",
    "sg:address":"6597 Joy Rd",
    "sg:city":"East Syracuse",
    "sg:classifiers":[
        {
            "category":"Building & Trades",
            "subcategory":"Equipment Rental",
            "type":"Services"
        }
    ],
    "sg:phone":"+1 315 437 8423",
    "sg:postcode":"13057",
    "sg:province":"NY",
    "sg:tags":[
        "toilet"
    ],
    "sg:website":"www.syr-sl.com",
    "wof:name":"Syracuse Safety Lites Inc",
    "wof:placetype":"venue"
},
  "geometry": {"coordinates":[-76.083365,43.096175],"type":"Point"}
}