{
  "type": "Feature",
  "properties": {
    "addr:full":"292 Deems Ave Staten Island NY 10314",
    "addr:housenumber":"292",
    "addr:postcode":"10314",
    "addr:street":"Deems Ave",
    "iso:country":"US",
    "sg:address":"292 Deems Ave",
    "sg:city":"Staten Island",
    "sg:classifiers":[
        {
            "category":"Building & Trades",
            "subcategory":"Cleaning & Sanitation",
            "type":"Services"
        }
    ],
    "sg:phone":"+1 718 273 4085",
    "sg:postcode":"10314",
    "sg:province":"NY",
    "wof:name":"Aqua Blast Pressure Cleaning",
    "wof:placetype":"venue"
},
  "geometry": {"coordinates":[-74.132644,40.616249],"type":"Point"}
}