{
  "type": "Feature",
  "properties": {
    "addr:full":"3875 S Park Ave Buffalo NY 14219",
    "addr:housenumber":"3875",
    "addr:postcode":"14219",
    "addr:street":"S Park Ave",
    "iso:country":"US",
    "sg:address":"3875 S Park Ave",
    "sg:city":"Buffalo",
    "sg:classifiers":[
        {
            "category":"Professional",
            "subcategory":"Business Services",
            "type":"Services"
        }
    ],
    "sg:phone":"+1   ",
    "sg:postcode":"14219",
    "sg:province":"NY",
    "wof:name":"Americas Instant Sign",
    "wof:placetype":"venue"
},
  "geometry": {"coordinates":[-78.823933,42.793121],"type":"Point"}
}