{
  "type": "Feature",
  "properties": {
    "iso:country":"US",
    "sg:address":"27 Lyncrest Dr",
    "sg:city":"Monsey",
    "sg:classifiers":[
        {
            "category":"Structure",
            "subcategory":"Office Building",
            "type":"Public Place"
        }
    ],
    "sg:phone":"+1 845 362 1198",
    "sg:postcode":"10952",
    "sg:province":"NY",
    "sg:tags":[
        "park"
    ],
    "wof:name":"Davidson Properties",
    "wof:placetype":"venue"
},
  "geometry": {"coordinates":[-74.08136,41.139568],"type":"Point"}
}