{
  "type": "Feature",
  "properties": {
    "iso:country":"US",
    "sg:address":"1309 Nostrand Ave",
    "sg:city":"Brooklyn",
    "sg:classifiers":[
        {
            "category":"Restaurant",
            "type":"Food & Drink"
        }
    ],
    "sg:phone":"+1 718 287 8340",
    "sg:postcode":"11226",
    "sg:province":"NY",
    "wof:name":"Flavor Time Restaurant",
    "wof:placetype":"venue"
},
  "geometry": {"coordinates":[-73.94989099999999,40.654599],"type":"Point"}
}