{
  "type": "Feature",
  "properties": {
    "addr:full":"388 Croton Ave Cortlandt Manor NY 10567",
    "addr:housenumber":"388",
    "addr:postcode":"10567",
    "addr:street":"Croton Ave Cortlandt",
    "iso:country":"US",
    "sg:address":"388 Croton Ave",
    "sg:city":"Cortlandt Manor",
    "sg:classifiers":[
        {
            "category":"Professional",
            "subcategory":"Management & Consulting",
            "type":"Services"
        }
    ],
    "sg:phone":"+1 914 788 0072",
    "sg:postcode":"10567",
    "sg:province":"NY",
    "sg:tags":[
        "public",
        "relations"
    ],
    "wof:name":"Geneive Brown Associates",
    "wof:placetype":"venue"
},
  "geometry": {"coordinates":[-73.855428,41.274881],"type":"Point"}
}