{
  "type": "Feature",
  "properties": {
    "addr:full":"415 Clinton St Hempstead NY 11550",
    "addr:housenumber":"415",
    "addr:postcode":"11550",
    "addr:street":"Clinton St",
    "iso:country":"US",
    "sg:address":"415 Clinton St",
    "sg:city":"Hempstead",
    "sg:classifiers":[
        {
            "category":"Home & Garden",
            "subcategory":"Household Appliances",
            "type":"Retail Goods"
        }
    ],
    "sg:phone":"+1 516 483 3777",
    "sg:postcode":"11550",
    "sg:province":"NY",
    "sg:tags":[
        "repair"
    ],
    "wof:name":"Nassau & Suffolk",
    "wof:placetype":"venue"
},
  "geometry": {"coordinates":[-73.620903,40.7187],"type":"Point"}
}