{
  "type": "Feature",
  "properties": {
    "addr:full":"525 E 5th St New York NY 10009",
    "addr:housenumber":"525",
    "addr:postcode":"10009",
    "addr:street":"E 5Th St",
    "iso:country":"US",
    "sg:address":"525 E 5th St",
    "sg:city":"New York",
    "sg:classifiers":[
        {
            "category":"Building & Trades",
            "subcategory":"Locksmith",
            "type":"Services"
        }
    ],
    "sg:phone":"+1 212 584 7238",
    "sg:postcode":"10009",
    "sg:province":"NY",
    "sg:tags":[
        "key"
    ],
    "wof:name":"AA Locksmith",
    "wof:placetype":"venue"
},
  "geometry": {"coordinates":[-73.98380299999999,40.724602],"type":"Point"}
}