{
  "type": "Feature",
  "properties": {
    "addr:full":"1 Manor Ln Lawrence NY 11559",
    "addr:housenumber":"1",
    "addr:postcode":"11559",
    "addr:street":"Manor Ln",
    "iso:country":"US",
    "sg:address":"1 Manor Ln",
    "sg:city":"Lawrence",
    "sg:classifiers":[
        {
            "category":"Building & Trades",
            "subcategory":"Construction",
            "type":"Services"
        }
    ],
    "sg:phone":"+1 516 371 2040",
    "sg:postcode":"11559",
    "sg:province":"NY",
    "sg:tags":[
        "general",
        "contractor"
    ],
    "wof:name":"BTA Building & Development",
    "wof:placetype":"venue"
},
  "geometry": {"coordinates":[-73.731684,40.610786],"type":"Point"}
}