{
  "type": "Feature",
  "properties": {
    "addr:full":"213 Avenue of the Americ New York NY 10014",
    "addr:housenumber":"213",
    "addr:postcode":"10014",
    "addr:street":"Avenue Of The",
    "iso:country":"US",
    "sg:address":"213 Avenue of the Americ",
    "sg:city":"New York",
    "sg:classifiers":[
        {
            "category":"Building & Trades",
            "subcategory":"Plumbing",
            "type":"Services"
        }
    ],
    "sg:phone":"+1 646 509 2045",
    "sg:postcode":"10014",
    "sg:province":"NY",
    "wof:name":"0 # 0 # 0 & 0 24 Hour Emergency Plumbing",
    "wof:placetype":"venue"
},
  "geometry": {"coordinates":[-74.003338,40.727232],"type":"Point"}
}