{
  "type": "Feature",
  "properties": {
    "iso:country":"US",
    "sg:address":"2116 Hickory Hill Rd",
    "sg:city":"Fonda",
    "sg:classifiers":[
        {
            "category":"Manufacturing",
            "subcategory":"Retail Goods",
            "type":"Manufacturing & Wholesale Goods"
        }
    ],
    "sg:phone":"+1   ",
    "sg:postcode":"12068",
    "sg:province":"NY",
    "sg:tags":[
        "product",
        "mfg"
    ],
    "wof:name":"Kountry Kandles",
    "wof:placetype":"venue"
},
  "geometry": {"coordinates":[-74.42565399999999,42.946915],"type":"Point"}
}