{
  "type": "Feature",
  "properties": {
    "addr:full":"3612 Union St Unit 220 Queens NY 11354",
    "addr:housenumber":"3612;220",
    "addr:postcode":"11354",
    "addr:street":"Union St Unit",
    "iso:country":"US",
    "sg:address":"3612 Union St Unit 220",
    "sg:city":"Queens",
    "sg:classifiers":[
        {
            "category":"Building & Trades",
            "subcategory":"Cleaning & Sanitation",
            "type":"Services"
        }
    ],
    "sg:phone":"+1 201 256 3334",
    "sg:postcode":"11354",
    "sg:province":"NY",
    "sg:tags":[
        "carpet"
    ],
    "wof:name":"Chinese & Oriental Rug Cleaning",
    "wof:placetype":"venue"
},
  "geometry": {"coordinates":[-73.828299,40.763342],"type":"Point"}
}