{
  "type": "Feature",
  "properties": {
    "addr:full":"1277 5th Ave Troy NY 12180",
    "addr:housenumber":"1277",
    "addr:postcode":"12180",
    "addr:street":"5Th Ave",
    "iso:country":"US",
    "sg:address":"1277 5th Ave",
    "sg:city":"Troy",
    "sg:classifiers":[
        {
            "category":"Building & Trades",
            "subcategory":"Construction",
            "type":"Services"
        }
    ],
    "sg:phone":"+1 518 274 6871",
    "sg:postcode":"12180",
    "sg:province":"NY",
    "sg:tags":[
        "painter"
    ],
    "wof:name":"Frank J Ryan & Sons Inc",
    "wof:placetype":"venue"
},
  "geometry": {"coordinates":[-73.68943400000001,42.723697],"type":"Point"}
}