{
  "type": "Feature",
  "properties": {
    "iso:country":"US",
    "sg:address":"177 Wales Ave",
    "sg:city":"Tonawanda",
    "sg:classifiers":[
        {
            "category":"Manufacturing",
            "subcategory":"Glass & Minerals",
            "type":"Manufacturing & Wholesale Goods"
        }
    ],
    "sg:phone":"+1 716 692 1761",
    "sg:postcode":"14150",
    "sg:province":"NY",
    "sg:tags":[
        "refractory"
    ],
    "wof:name":"Harbison Walker Refractories",
    "wof:placetype":"venue"
},
  "geometry": {"coordinates":[-78.859503,43.017714],"type":"Point"}
}