{
  "type": "Feature",
  "properties": {
    "iso:country":"US",
    "sg:address":"611 Broadway",
    "sg:city":"New York",
    "sg:classifiers":[
        {
            "category":"Professional",
            "subcategory":"Art Services",
            "type":"Services"
        }
    ],
    "sg:phone":"+1 212 473 4710",
    "sg:postcode":"10012",
    "sg:province":"NY",
    "sg:tags":[
        "commercial",
        "graphic",
        "design",
        "designer"
    ],
    "wof:name":"Flyleaf",
    "wof:placetype":"venue"
},
  "geometry": {"coordinates":[-73.99594999999999,40.726498],"type":"Point"}
}