{
  "type": "Feature",
  "properties": {
    "iso:country":"US",
    "sg:address":"284 President St",
    "sg:city":"Brooklyn",
    "sg:classifiers":[
        {
            "category":"Travel",
            "subcategory":"Bed & Breakfast",
            "type":"Entertainment"
        }
    ],
    "sg:phone":"+1 917 992 5052",
    "sg:postcode":"11231",
    "sg:province":"NY",
    "sg:website":"carrollgardenshouse.com/",
    "wof:name":"Carroll Gardens House",
    "wof:placetype":"venue"
},
  "geometry": {"coordinates":[-73.995107,40.681534],"type":"Point"}
}