{
  "type": "Feature",
  "properties": {
    "addr:full":"2117 Stannards Rd Wellsville NY 14895",
    "addr:housenumber":"2117",
    "addr:postcode":"14895",
    "addr:street":"Stannards Rd",
    "iso:country":"US",
    "sg:address":"2117 Stannards Rd",
    "sg:city":"Wellsville",
    "sg:classifiers":[
        {
            "category":"Real Estate",
            "subcategory":"Real Estate Operator",
            "type":"Services"
        }
    ],
    "sg:phone":"+1 585 593 3906",
    "sg:postcode":"14895",
    "sg:province":"NY",
    "sg:tags":[
        "building",
        "mobile",
        "park",
        "commercial",
        "operates",
        "farm",
        "home"
    ],
    "wof:name":"Babbitt-Howe Beulah",
    "wof:placetype":"venue"
},
  "geometry": {"coordinates":[-77.922467,42.091026],"type":"Point"}
}