{
  "type": "Feature",
  "properties": {
    "addr:full":"1846 US Hwy 9 Lake Katrine NY 12449",
    "addr:housenumber":"1846",
    "addr:postcode":"12449",
    "addr:street":"Us Hwy 9",
    "iso:country":"US",
    "sg:address":"1846 US Hwy 9",
    "sg:city":"Lake Katrine",
    "sg:classifiers":[
        {
            "category":"Wholesale",
            "subcategory":"Groceries",
            "type":"Manufacturing & Wholesale Goods"
        }
    ],
    "sg:phone":"+1 845 336 3339",
    "sg:postcode":"12449",
    "sg:province":"NY",
    "sg:tags":[
        "pet",
        "food"
    ],
    "wof:name":"Pet Club Inc",
    "wof:placetype":"venue"
},
  "geometry": {"coordinates":[-73.98635400000001,41.991673],"type":"Point"}
}