{
  "type": "Feature",
  "properties": {
    "iso:country":"US",
    "sg:address":"3896 Illona Ln",
    "sg:city":"Seaford",
    "sg:classifiers":[
        {
            "category":"Travel",
            "subcategory":"Travel Agent",
            "type":"Entertainment"
        }
    ],
    "sg:phone":"+1   ",
    "sg:postcode":"11783",
    "sg:province":"NY",
    "sg:tags":[
        "agency"
    ],
    "wof:name":"Uei Freight Services Intl",
    "wof:placetype":"venue"
},
  "geometry": {"coordinates":[-73.489332,40.656954],"type":"Point"}
}