{
  "type": "Feature",
  "properties": {
    "addr:full":"9035 Sutphin Boulevard Jamaica NY 11435",
    "addr:housenumber":"9035",
    "addr:postcode":"11435",
    "addr:street":"Sutphin Boulevard",
    "iso:country":"US",
    "sg:address":"9035 Sutphin Boulevard",
    "sg:city":"Jamaica",
    "sg:classifiers":[
        {
            "category":"Shopping",
            "subcategory":"Pawn Shop",
            "type":"Retail Goods"
        }
    ],
    "sg:phone":"+1 718 526 7300",
    "sg:postcode":"11435",
    "sg:province":"NY",
    "wof:name":"Sutphin Trading Depot",
    "wof:placetype":"venue"
},
  "geometry": {"coordinates":[-73.80790500000001,40.702182],"type":"Point"}
}