{
  "type": "Feature",
  "properties": {
    "iso:country":"US",
    "sg:address":"1021 Portion Rd",
    "sg:city":"Ronkonkoma",
    "sg:classifiers":[
        {
            "category":"Food & Beverages",
            "subcategory":"Groceries & Convenience Stores",
            "type":"Retail Goods"
        }
    ],
    "sg:phone":"+1 631 451 1004",
    "sg:postcode":"11779",
    "sg:province":"NY",
    "wof:name":"American Arcade Mini Mart",
    "wof:placetype":"venue"
},
  "geometry": {"coordinates":[-73.068218,40.8353],"type":"Point"}
}