{
  "type": "Feature",
  "properties": {
    "addr:full":"198 Jericho Tpke Mineola NY 11501",
    "addr:housenumber":"198",
    "addr:postcode":"11501",
    "addr:street":"Jericho Tpke",
    "iso:country":"US",
    "sg:address":"198 Jericho Tpke",
    "sg:city":"Mineola",
    "sg:classifiers":[
        {
            "category":"Insurance",
            "subcategory":"Insurance Agent",
            "type":"Services"
        }
    ],
    "sg:phone":"+1 516 739 2300",
    "sg:postcode":"11501",
    "sg:province":"NY",
    "sg:website":"www.karisinsurance.com",
    "wof:name":"Karis & Karis Agency",
    "wof:placetype":"venue"
},
  "geometry": {"coordinates":[-73.64191099999999,40.749087],"type":"Point"}
}