{
  "type": "Feature",
  "properties": {
    "iso:country":"US",
    "sg:address":"561 S Drury Ln",
    "sg:city":"Rock Tavern",
    "sg:classifiers":[
        {
            "category":"Autos & Motor Vehicles",
            "subcategory":"Auto Supplies",
            "type":"Retail Goods"
        },
        {
            "category":"Manufacturing",
            "subcategory":"Tools & Machinery",
            "type":"Manufacturing & Wholesale Goods"
        }
    ],
    "sg:phone":"+1 845 567 0700",
    "sg:postcode":"12575",
    "sg:province":"NY",
    "sg:tags":[
        "alternator",
        "automotive",
        "parts",
        "generator",
        "rebuilding"
    ],
    "wof:name":"Auto Electric Store Inc",
    "wof:placetype":"venue"
},
  "geometry": {"coordinates":[-74.13049599999999,41.514809],"type":"Point"}
}