{
  "type": "Feature",
  "properties": {
    "addr:full":"3985 Tonawanda Creek Rd East Amherst NY 14051",
    "addr:housenumber":"3985",
    "addr:postcode":"14051",
    "addr:street":"Tonawanda Creek Rd",
    "iso:country":"US",
    "sg:address":"3985 Tonawanda Creek Rd",
    "sg:city":"East Amherst",
    "sg:classifiers":[
        {
            "category":"Professional",
            "subcategory":"Research",
            "type":"Services"
        }
    ],
    "sg:phone":"+1 716 689 6232",
    "sg:postcode":"14051",
    "sg:province":"NY",
    "sg:tags":[
        "environmental",
        "ecological"
    ],
    "wof:name":"Layhaunts-Group",
    "wof:placetype":"venue"
},
  "geometry": {"coordinates":[-78.697042,43.084964],"type":"Point"}
}