{
  "type": "Feature",
  "properties": {
    "addr:full":"16 Taft Pl Albertson NY 11507",
    "addr:housenumber":"16",
    "addr:postcode":"11507",
    "addr:street":"Taft Pl",
    "iso:country":"US",
    "sg:address":"16 Taft Pl",
    "sg:city":"Albertson",
    "sg:classifiers":[
        {
            "category":"Building & Trades",
            "subcategory":"Electrical",
            "type":"Services"
        }
    ],
    "sg:phone":"+1 718 229 9076",
    "sg:postcode":"11507",
    "sg:province":"NY",
    "sg:tags":[
        "electrician"
    ],
    "sg:website":"www.taftelectric.com",
    "wof:name":"Taft Electric Co",
    "wof:placetype":"venue"
},
  "geometry": {"coordinates":[-73.64949799999999,40.769699],"type":"Point"}
}