{
  "type": "Feature",
  "properties": {
    "iso:country":"US",
    "sg:address":"73 W Main St",
    "sg:city":"Macedon",
    "sg:classifiers":[
        {
            "category":"Shopping",
            "subcategory":"Computers & Home Electronics",
            "type":"Retail Goods"
        }
    ],
    "sg:phone":"+1 315 986 1200",
    "sg:postcode":"14502",
    "sg:province":"NY",
    "sg:tags":[
        "equipment",
        "satellite",
        "system"
    ],
    "wof:name":"Wireless Worldwide Inc",
    "wof:placetype":"venue"
},
  "geometry": {"coordinates":[-77.29916299999999,43.069155],"type":"Point"}
}