{
  "type": "Feature",
  "properties": {
    "iso:country":"US",
    "sg:address":"217 E 51st St",
    "sg:city":"New York",
    "sg:classifiers":[
        {
            "category":"Park",
            "type":"Public Place"
        }
    ],
    "sg:phone":"+1 212 838 0528",
    "sg:postcode":"10022",
    "sg:province":"NY",
    "wof:name":"Greenacre Park",
    "wof:placetype":"venue"
},
  "geometry": {"coordinates":[-73.969803,40.756401],"type":"Point"}
}