{
  "type": "Feature",
  "properties": {
    "iso:country":"US",
    "sg:address":"130 Garth Rd",
    "sg:city":"Scarsdale",
    "sg:classifiers":[
        {
            "category":"Wholesale",
            "subcategory":"Chemicals & Plastics",
            "type":"Manufacturing & Wholesale Goods"
        }
    ],
    "sg:phone":"+1 914 645 4499",
    "sg:postcode":"10583",
    "sg:province":"NY",
    "sg:tags":[
        "container"
    ],
    "wof:name":"Caccia Inc",
    "wof:placetype":"venue"
},
  "geometry": {"coordinates":[-73.811074,40.984309],"type":"Point"}
}