{
  "type": "Feature",
  "properties": {
    "addr:full":"252 Hedgegarth Dr Rochester NY 14617",
    "addr:housenumber":"252",
    "addr:postcode":"14617",
    "addr:street":"Hedgegarth Dr",
    "iso:country":"US",
    "sg:address":"252 Hedgegarth Dr",
    "sg:city":"Rochester",
    "sg:classifiers":[
        {
            "category":"Professional",
            "type":"Services"
        }
    ],
    "sg:phone":"+1 585 266 8290",
    "sg:postcode":"14617",
    "sg:province":"NY",
    "sg:tags":[
        "establishment"
    ],
    "wof:name":"Micropump Inc",
    "wof:placetype":"venue"
},
  "geometry": {"coordinates":[-77.590542,43.212141],"type":"Point"}
}