{
  "type": "Feature",
  "properties": {
    "iso:country":"US",
    "sg:address":"46 Garth Rd",
    "sg:city":"Scarsdale",
    "sg:classifiers":[
        {
            "category":"Shopping",
            "subcategory":"Bicycles & Sporting Goods",
            "type":"Retail Goods"
        }
    ],
    "sg:phone":"+1   ",
    "sg:postcode":"10583",
    "sg:province":"NY",
    "wof:name":"Sierra Cycles",
    "wof:placetype":"venue"
},
  "geometry": {"coordinates":[-73.809961,40.987838],"type":"Point"}
}