{
  "type": "Feature",
  "properties": {
    "addr:full":"13984 State Rte 370 Red Creek NY 13143",
    "addr:housenumber":"13984",
    "addr:postcode":"13143",
    "addr:street":"State Rte 370",
    "iso:country":"US",
    "sg:address":"13984 State Rte 370",
    "sg:city":"Red Creek",
    "sg:classifiers":[
        {
            "category":"Manufacturing",
            "subcategory":"Lumber",
            "type":"Manufacturing & Wholesale Goods"
        }
    ],
    "sg:phone":"+1   ",
    "sg:postcode":"13143",
    "sg:province":"NY",
    "sg:tags":[
        "logging"
    ],
    "wof:name":"Bailey Logging & Firewood",
    "wof:placetype":"venue"
},
  "geometry": {"coordinates":[-76.723176,43.20911],"type":"Point"}
}