{
  "type": "Feature",
  "properties": {
    "iso:country":"US",
    "sg:address":"200 Boundary Ave",
    "sg:city":"Massapequa",
    "sg:classifiers":[
        {
            "category":"Health Services",
            "subcategory":"Doctor",
            "type":"Services"
        }
    ],
    "sg:phone":"+1 516 454 6219",
    "sg:postcode":"11758",
    "sg:province":"NY",
    "sg:tags":[
        "medical"
    ],
    "wof:name":"Steven Pelaez MD",
    "wof:placetype":"venue"
},
  "geometry": {"coordinates":[-73.462857,40.71726],"type":"Point"}
}