{
  "type": "Feature",
  "properties": {
    "addr:full":"60-62 East 11th Street Fourth Floor New York NY 10003",
    "addr:housenumber":"60-62",
    "addr:postcode":"10003",
    "addr:street":"East 11Th Street;Floor",
    "iso:country":"US",
    "sg:address":"60-62 East 11th Street Fourth Floor",
    "sg:city":"New York",
    "sg:classifiers":[
        {
            "category":"Professional",
            "subcategory":"Computer Services",
            "type":"Services"
        }
    ],
    "sg:phone":"+1 212 731 2033",
    "sg:postcode":"10003",
    "sg:province":"NY",
    "sg:tags":[
        "marketing",
        "social-media",
        "lead-generation",
        "demand-generation",
        "direct-mail",
        "direct-marketing",
        "agency"
    ],
    "sg:website":"http://www.entermarketing.com",
    "wof:name":"enter:marketing",
    "wof:placetype":"venue"
},
  "geometry": {"coordinates":[-73.99190400000001,40.732705],"type":"Point"}
}