{
  "type": "Feature",
  "properties": {
    "addr:full":"2657 Co Rd 46 Fort Edward NY 12828",
    "addr:housenumber":"2657;46",
    "addr:postcode":"12828",
    "addr:street":"Co Rd",
    "iso:country":"US",
    "sg:address":"2657 Co Rd 46",
    "sg:city":"Fort Edward",
    "sg:classifiers":[
        {
            "category":"Farming",
            "subcategory":"Dairy Farm",
            "type":"Manufacturing & Wholesale Goods"
        }
    ],
    "sg:phone":"+1 518 747 9135",
    "sg:postcode":"12828",
    "sg:province":"NY",
    "wof:name":"Wicks Farm",
    "wof:placetype":"venue"
},
  "geometry": {"coordinates":[-73.53903099999999,43.247451],"type":"Point"}
}