{
  "type": "Feature",
  "properties": {
    "addr:full":"2116 Williamsbridge Rd Bronx NY 10461",
    "addr:housenumber":"2116",
    "addr:postcode":"10461",
    "addr:street":"Williamsbridge Rd",
    "iso:country":"US",
    "sg:address":"2116 Williamsbridge Rd",
    "sg:city":"Bronx",
    "sg:classifiers":[
        {
            "category":"Real Estate",
            "subcategory":"Real Estate Agent",
            "type":"Services"
        }
    ],
    "sg:phone":"+1 718 794 9447",
    "sg:postcode":"10461",
    "sg:province":"NY",
    "sg:tags":[
        "appraiser"
    ],
    "wof:name":"M & J Appraisal Svc",
    "wof:placetype":"venue"
},
  "geometry": {"coordinates":[-73.855934,40.856721],"type":"Point"}
}