{
  "type": "Feature",
  "properties": {
    "iso:country":"US",
    "sg:address":"1 Meadow Way",
    "sg:city":"Lawrence",
    "sg:classifiers":[
        {
            "category":"Professional",
            "subcategory":"Management & Consulting",
            "type":"Services"
        }
    ],
    "sg:phone":"+1 212 355 1122",
    "sg:postcode":"11559",
    "sg:province":"NY",
    "sg:tags":[
        "business"
    ],
    "wof:name":"Worth Enterprises LLC",
    "wof:placetype":"venue"
},
  "geometry": {"coordinates":[-73.71767,40.609728],"type":"Point"}
}