{
  "type": "Feature",
  "properties": {
    "iso:country":"US",
    "sg:address":"26 Middleville Rd",
    "sg:city":"Northport",
    "sg:classifiers":[
        {
            "category":"Building & Trades",
            "subcategory":"Construction",
            "type":"Services"
        }
    ],
    "sg:phone":"+1 631 261 4770",
    "sg:postcode":"11768",
    "sg:province":"NY",
    "sg:tags":[
        "house"
    ],
    "wof:name":"Patrick Smith Const",
    "wof:placetype":"venue"
},
  "geometry": {"coordinates":[-73.319665,40.898309],"type":"Point"}
}