{
  "type": "Feature",
  "properties": {
    "addr:full":"316A Sunrise Hwy Rockville Centre NY 11570",
    "addr:housenumber":"316a",
    "addr:postcode":"11570",
    "addr:street":"Sunrise Hwy",
    "iso:country":"US",
    "sg:address":"316A Sunrise Hwy",
    "sg:city":"Rockville Centre",
    "sg:classifiers":[
        {
            "category":"Sports & Exercise",
            "subcategory":"Bicycle Rental",
            "type":"Entertainment"
        }
    ],
    "sg:phone":"+1 516 594 4567",
    "sg:postcode":"11570",
    "sg:province":"NY",
    "sg:tags":[
        "wear"
    ],
    "wof:name":"National Jeans Co",
    "wof:placetype":"venue"
},
  "geometry": {"coordinates":[-73.643097,40.657101],"type":"Point"}
}