{
  "type": "Feature",
  "properties": {
    "addr:full":"263 Watchogue Rd Staten Island NY 10314",
    "addr:housenumber":"263",
    "addr:postcode":"10314",
    "addr:street":"Watchogue Rd",
    "iso:country":"US",
    "sg:address":"263 Watchogue Rd",
    "sg:city":"Staten Island",
    "sg:classifiers":[
        {
            "category":"Professional",
            "subcategory":"Management & Consulting",
            "type":"Services"
        }
    ],
    "sg:phone":"+1   ",
    "sg:postcode":"10314",
    "sg:province":"NY",
    "sg:tags":[
        "business"
    ],
    "wof:name":"J&B Consultants",
    "wof:placetype":"venue"
},
  "geometry": {"coordinates":[-74.137866,40.616099],"type":"Point"}
}