{
  "type": "Feature",
  "properties": {
    "addr:full":"472 Bergen St Brooklyn NY 11217",
    "addr:housenumber":"472",
    "addr:postcode":"11217",
    "addr:street":"Bergen St",
    "iso:country":"US",
    "sg:address":"472 Bergen St",
    "sg:city":"Brooklyn",
    "sg:classifiers":[
        {
            "category":"Professional",
            "subcategory":"Employment Agencies",
            "type":"Services"
        }
    ],
    "sg:phone":"+1 718 399 8660",
    "sg:postcode":"11217",
    "sg:province":"NY",
    "sg:tags":[
        "help",
        "contractor"
    ],
    "wof:name":"Tradesource",
    "wof:placetype":"venue"
},
  "geometry": {"coordinates":[-73.976297,40.681238],"type":"Point"}
}