{
  "type": "Feature",
  "properties": {
    "iso:country":"US",
    "sg:address":"243 Washington Ave",
    "sg:city":"Patchogue",
    "sg:classifiers":[
        {
            "category":"Organizations",
            "subcategory":"Religious Organization",
            "type":"Services"
        }
    ],
    "sg:phone":"+1 631 289 5786",
    "sg:postcode":"11772",
    "sg:province":"NY",
    "sg:tags":[
        "clergy"
    ],
    "wof:name":"Evensen Dennis",
    "wof:placetype":"venue"
},
  "geometry": {"coordinates":[-72.999674,40.778261],"type":"Point"}
}