{
  "type": "Feature",
  "properties": {
    "addr:full":"132 E 45th St New York NY 10017",
    "addr:housenumber":"132",
    "addr:postcode":"10017",
    "addr:street":"E 45Th St",
    "iso:country":"US",
    "sg:address":"132 E 45th St",
    "sg:city":"New York",
    "sg:classifiers":[
        {
            "category":"Manufacturing",
            "subcategory":"Textiles",
            "type":"Manufacturing & Wholesale Goods"
        }
    ],
    "sg:phone":"+1 212 370 4375",
    "sg:postcode":"10017",
    "sg:province":"NY",
    "wof:name":"Gerry Nichol Decorative Txtls",
    "wof:placetype":"venue"
},
  "geometry": {"coordinates":[-73.973213,40.752699],"type":"Point"}
}