{
  "type": "Feature",
  "properties": {
    "addr:full":"249 Albourne Ave Staten Island NY 10309",
    "addr:housenumber":"249",
    "addr:postcode":"10309",
    "addr:street":"Albourne Ave",
    "iso:country":"US",
    "sg:address":"249 Albourne Ave",
    "sg:city":"Staten Island",
    "sg:classifiers":[
        {
            "category":"Professional",
            "subcategory":"Engineering",
            "type":"Services"
        }
    ],
    "sg:phone":"+1 718 984 9355",
    "sg:postcode":"10309",
    "sg:province":"NY",
    "wof:name":"George Weir Consulting Svcs",
    "wof:placetype":"venue"
},
  "geometry": {"coordinates":[-74.199944,40.530321],"type":"Point"}
}