{
  "type": "Feature",
  "properties": {
    "addr:full":"110 Bryant Ave Roslyn NY 11576",
    "addr:housenumber":"110",
    "addr:postcode":"11576",
    "addr:street":"Bryant Ave",
    "iso:country":"US",
    "sg:address":"110 Bryant Ave",
    "sg:city":"Roslyn",
    "sg:classifiers":[
        {
            "category":"Organizations",
            "subcategory":"Religious Organization",
            "type":"Services"
        }
    ],
    "sg:phone":"+1 516 621 2757",
    "sg:postcode":"11576",
    "sg:province":"NY",
    "wof:name":"St Mary's Church Campaign Ofc",
    "wof:placetype":"venue"
},
  "geometry": {"coordinates":[-73.646202,40.806599],"type":"Point"}
}