{
  "type": "Feature",
  "properties": {
    "addr:full":"676 Riverside Dr New York NY 10031",
    "addr:housenumber":"676",
    "addr:postcode":"10031",
    "addr:street":"Riverside Dr",
    "iso:country":"US",
    "sg:address":"676 Riverside Dr",
    "sg:city":"New York",
    "sg:classifiers":[
        {
            "category":"Professional",
            "subcategory":"Business Services",
            "type":"Services"
        }
    ],
    "sg:phone":"+1 212 690 5767",
    "sg:postcode":"10031",
    "sg:province":"NY",
    "sg:tags":[
        "painter",
        "sign"
    ],
    "wof:name":"Nixon's Neon Signs",
    "wof:placetype":"venue"
},
  "geometry": {"coordinates":[-73.95224399999999,40.826542],"type":"Point"}
}