{
  "type": "Feature",
  "properties": {
    "iso:country":"US",
    "sg:address":"66 Wilmington Dr",
    "sg:city":"Melville",
    "sg:classifiers":[
        {
            "category":"Health Services",
            "subcategory":"Doctor",
            "type":"Services"
        }
    ],
    "sg:phone":"+1 631 643 9529",
    "sg:postcode":"11747",
    "sg:province":"NY",
    "sg:tags":[
        "physician",
        "surgeon"
    ],
    "wof:name":"Rudolph Calabrese Phd",
    "wof:placetype":"venue"
},
  "geometry": {"coordinates":[-73.38343,40.774181],"type":"Point"}
}