{
  "type": "Feature",
  "properties": {
    "addr:full":"105 Tuckahoe Rd Yonkers NY 10710",
    "addr:housenumber":"105",
    "addr:postcode":"10710",
    "addr:street":"Tuckahoe Rd",
    "iso:country":"US",
    "sg:address":"105 Tuckahoe Rd",
    "sg:city":"Yonkers",
    "sg:classifiers":[
        {
            "category":"Building & Trades",
            "subcategory":"Electrical",
            "type":"Services"
        }
    ],
    "sg:phone":"+1 914 476 7676",
    "sg:postcode":"10710",
    "sg:province":"NY",
    "sg:tags":[
        "electrical",
        "contractor"
    ],
    "wof:name":"L B Electric",
    "wof:placetype":"venue"
},
  "geometry": {"coordinates":[-73.86621599999999,40.955552],"type":"Point"}
}