{
  "type": "Feature",
  "properties": {
    "addr:full":"172 E Bayberry Rd Islip NY 11751",
    "addr:housenumber":"172",
    "addr:postcode":"11751",
    "addr:street":"E Bayberry Rd",
    "iso:country":"US",
    "sg:address":"172 E Bayberry Rd",
    "sg:city":"Islip",
    "sg:classifiers":[
        {
            "category":"Shopping",
            "subcategory":"Clothing, Apparel, & Fashions",
            "type":"Retail Goods"
        }
    ],
    "sg:phone":"+1   ",
    "sg:postcode":"11751",
    "sg:province":"NY",
    "sg:tags":[
        "wear"
    ],
    "wof:name":"Kids Chic",
    "wof:placetype":"venue"
},
  "geometry": {"coordinates":[-73.22054900000001,40.708346],"type":"Point"}
}