{
  "type": "Feature",
  "properties": {
    "addr:full":"1408 Webster Ave Bronx NY 10456",
    "addr:housenumber":"1408",
    "addr:postcode":"10456",
    "addr:street":"Webster Ave",
    "iso:country":"US",
    "sg:address":"1408 Webster Ave",
    "sg:city":"Bronx",
    "sg:classifiers":[
        {
            "category":"Recreation",
            "type":"Entertainment"
        }
    ],
    "sg:phone":"+1 718 410 7390",
    "sg:postcode":"10456",
    "sg:province":"NY",
    "sg:tags":[
        "information",
        "activity"
    ],
    "wof:name":"Kids World",
    "wof:placetype":"venue"
},
  "geometry": {"coordinates":[-73.906971,40.836726],"type":"Point"}
}