{
  "type": "Feature",
  "properties": {
    "iso:country":"US",
    "sg:address":"79 Lake Ave",
    "sg:city":"Lake Luzerne",
    "sg:classifiers":[
        {
            "category":"Organizations",
            "subcategory":"Professional Association",
            "type":"Services"
        }
    ],
    "sg:phone":"+1 518 696 3500",
    "sg:postcode":"12846",
    "sg:province":"NY",
    "sg:tags":[
        "business",
        "trade"
    ],
    "sg:website":"www.lakeluzernechamber.org",
    "wof:name":"Lake Luzerne Chamber-Commerce",
    "wof:placetype":"venue"
},
  "geometry": {"coordinates":[-73.834997,43.3128],"type":"Point"}
}