{
  "type": "Feature",
  "properties": {
    "iso:country":"US",
    "sg:address":"690 Cleveland St",
    "sg:city":"Brooklyn",
    "sg:classifiers":[
        {
            "category":"Building & Trades",
            "subcategory":"Cleaning & Sanitation",
            "type":"Services"
        }
    ],
    "sg:phone":"+1 347 880 9947",
    "sg:postcode":"11208",
    "sg:province":"NY",
    "sg:tags":[
        "cleaning-industrial"
    ],
    "sg:website":"http://indigblue.vpweb.com",
    "wof:name":"INDGO BLUE",
    "wof:placetype":"venue"
},
  "geometry": {"coordinates":[-73.882403,40.666583],"type":"Point"}
}