{
  "type": "Feature",
  "properties": {
    "addr:full":"407 W 13th St Ste 3 New York NY 10014",
    "addr:housenumber":"407",
    "addr:postcode":"10014",
    "addr:street":"W 13Th St Ste 3",
    "iso:country":"US",
    "sg:address":"407 W 13th St Ste 3",
    "sg:city":"New York",
    "sg:classifiers":[
        {
            "category":"Health Services",
            "subcategory":"Health Practitioner",
            "type":"Services"
        }
    ],
    "sg:phone":"+1 212 924 4920",
    "sg:postcode":"10014",
    "sg:province":"NY",
    "sg:tags":[
        "therapy",
        "physical"
    ],
    "sg:website":"www.fusion-pt.com",
    "wof:name":"Fusion Physical Therapy & Sports Wellness PC",
    "wof:placetype":"venue"
},
  "geometry": {"coordinates":[-74.006096,40.740365],"type":"Point"}
}