{
  "type": "Feature",
  "properties": {
    "addr:full":"900 Broadway Amityville NY 11701",
    "addr:housenumber":"900",
    "addr:postcode":"11701",
    "addr:street":"Broadway",
    "iso:country":"US",
    "sg:address":"900 Broadway",
    "sg:city":"Amityville",
    "sg:classifiers":[
        {
            "category":"Restaurant",
            "type":"Food & Drink"
        }
    ],
    "sg:phone":"+1   ",
    "sg:postcode":"11701",
    "sg:province":"NY",
    "sg:tags":[
        "eating"
    ],
    "wof:name":"McDonalds",
    "wof:placetype":"venue"
},
  "geometry": {"coordinates":[-73.42775,40.705332],"type":"Point"}
}