{
  "type": "Feature",
  "properties": {
    "iso:country":"US",
    "sg:address":"77 Main St",
    "sg:city":"New Canaan",
    "sg:classifiers":[
        {
            "category":"Government",
            "subcategory":"Office",
            "type":"Public Place"
        }
    ],
    "sg:phone":"+1 203 972 2361",
    "sg:postcode":"06840",
    "sg:province":"NY",
    "sg:tags":[
        "village"
    ],
    "wof:name":"New Canaan Engineering Dept",
    "wof:placetype":"venue"
},
  "geometry": {"coordinates":[-73.492357,41.147205],"type":"Point"}
}