{
  "type": "Feature",
  "properties": {
    "addr:full":"636 Wellwood Ave Lindenhurst NY 11757",
    "addr:housenumber":"636",
    "addr:postcode":"11757",
    "addr:street":"Wellwood Ave",
    "iso:country":"US",
    "sg:address":"636 Wellwood Ave",
    "sg:city":"Lindenhurst",
    "sg:classifiers":[
        {
            "category":"Restaurant",
            "type":"Food & Drink"
        }
    ],
    "sg:phone":"+1 631 226 3590",
    "sg:postcode":"11757",
    "sg:province":"NY",
    "wof:name":"New Foo Lou Chinese Kitchen",
    "wof:placetype":"venue"
},
  "geometry": {"coordinates":[-73.383663,40.700298],"type":"Point"}
}