{
  "type": "Feature",
  "properties": {
    "addr:full":"1558 W Henrietta Rd Avon NY 14414",
    "addr:housenumber":"1558",
    "addr:postcode":"14414",
    "addr:street":"W Henrietta Rd",
    "iso:country":"US",
    "sg:address":"1558 W Henrietta Rd",
    "sg:city":"Avon",
    "sg:classifiers":[
        {
            "category":"Autos & Motor Vehicles",
            "subcategory":"Automobile Sales",
            "type":"Retail Goods"
        }
    ],
    "sg:phone":"+1 585 226 2929",
    "sg:postcode":"14414",
    "sg:province":"NY",
    "sg:tags":[
        "car",
        "dealer"
    ],
    "wof:name":"First Choice Auto Sales",
    "wof:placetype":"venue"
},
  "geometry": {"coordinates":[-77.705309,42.915464],"type":"Point"}
}