{
  "type": "Feature",
  "properties": {
    "iso:country":"US",
    "sg:address":"1085 Eggert Rd",
    "sg:city":"Buffalo",
    "sg:classifiers":[
        {
            "category":"Education",
            "subcategory":"School",
            "type":"Public Place"
        }
    ],
    "sg:phone":"+1 716 836 6903",
    "sg:postcode":"14226",
    "sg:province":"NY",
    "sg:website":"www.kadimah.org",
    "wof:name":"Kadimah School of Buffalo",
    "wof:placetype":"venue"
},
  "geometry": {"coordinates":[-78.803849,42.957948],"type":"Point"}
}