{
  "type": "Feature",
  "properties": {
    "addr:full":"1185 McDonald Ave Brooklyn NY 11230",
    "addr:housenumber":"1185",
    "addr:postcode":"11230",
    "addr:street":"Mcdonald Ave",
    "iso:country":"US",
    "sg:address":"1185 McDonald Ave",
    "sg:city":"Brooklyn",
    "sg:classifiers":[
        {
            "category":"Shopping",
            "subcategory":"Clothing, Apparel, & Fashions",
            "type":"Retail Goods"
        }
    ],
    "sg:phone":"+1 718 377 8871",
    "sg:postcode":"11230",
    "sg:province":"NY",
    "sg:tags":[
        "salvage",
        "surplus",
        "merchandise"
    ],
    "wof:name":"Weissman Salvage & Surplus",
    "wof:placetype":"venue"
},
  "geometry": {"coordinates":[-73.97595800000001,40.625277],"type":"Point"}
}