{
  "type": "Feature",
  "properties": {
    "iso:country":"US",
    "sg:address":"9 Carver Ter",
    "sg:city":"Yonkers",
    "sg:classifiers":[
        {
            "category":"Building & Trades",
            "subcategory":"Construction",
            "type":"Services"
        }
    ],
    "sg:phone":"+1 914 324 1368",
    "sg:postcode":"10710",
    "sg:province":"NY",
    "sg:tags":[
        "roofing",
        "contractor"
    ],
    "wof:name":"City Line Roofing Corp",
    "wof:placetype":"venue"
},
  "geometry": {"coordinates":[-73.83570400000001,40.955798],"type":"Point"}
}