{
  "type": "Feature",
  "properties": {
    "addr:full":"722 Middle Country Rd Selden NY 11784",
    "addr:housenumber":"722",
    "addr:postcode":"11784",
    "addr:street":"Middle Country Rd",
    "iso:country":"US",
    "sg:address":"722 Middle Country Rd",
    "sg:city":"Selden",
    "sg:classifiers":[
        {
            "category":"Manufacturing",
            "subcategory":"Signs",
            "type":"Manufacturing & Wholesale Goods"
        },
        {
            "category":"Professional",
            "subcategory":"Business Services",
            "type":"Services"
        }
    ],
    "sg:phone":"+1 631 732 9606",
    "sg:postcode":"11784",
    "sg:province":"NY",
    "sg:tags":[
        "repairing",
        "specialty",
        "mfg"
    ],
    "wof:name":"Sign Department The",
    "wof:placetype":"venue"
},
  "geometry": {"coordinates":[-73.036494,40.866295],"type":"Point"}
}