{
  "type": "Feature",
  "properties": {
    "addr:full":"1389 Madison Ave New York NY 10128",
    "addr:housenumber":"1389",
    "addr:postcode":"10128",
    "addr:street":"Madison Ave",
    "iso:country":"US",
    "sg:address":"1389 Madison Ave",
    "sg:city":"New York",
    "sg:classifiers":[
        {
            "category":"Restaurant",
            "type":"Food & Drink"
        }
    ],
    "sg:phone":"+1 212 987 1700",
    "sg:postcode":"10128",
    "sg:province":"NY",
    "sg:tags":[
        "french"
    ],
    "sg:website":"www.champignoncatering.com",
    "wof:name":"Champignon on Madison",
    "wof:placetype":"venue"
},
  "geometry": {"coordinates":[-73.953953,40.787535],"type":"Point"}
}