{
  "type": "Feature",
  "properties": {
    "addr:full":"140 E 38th St New York NY 10016",
    "addr:housenumber":"140",
    "addr:postcode":"10016",
    "addr:street":"E 38Th St",
    "iso:country":"US",
    "sg:address":"140 E 38th St",
    "sg:city":"New York",
    "sg:classifiers":[
        {
            "category":"Health Services",
            "subcategory":"Doctor",
            "type":"Services"
        }
    ],
    "sg:phone":"+1 212 889 1938",
    "sg:postcode":"10016",
    "sg:province":"NY",
    "sg:tags":[
        "clinic",
        "medical"
    ],
    "wof:name":"AA Midtown Medical Eye Center",
    "wof:placetype":"venue"
},
  "geometry": {"coordinates":[-73.976365,40.748202],"type":"Point"}
}