{
  "type": "Feature",
  "properties": {
    "addr:full":"200 Madison Ave New York NY 10016",
    "addr:housenumber":"200",
    "addr:postcode":"10016",
    "addr:street":"Madison Ave",
    "iso:country":"US",
    "sg:address":"200 Madison Ave",
    "sg:city":"New York",
    "sg:classifiers":[
        {
            "category":"Professional",
            "subcategory":"Lawyer & Legal Services",
            "type":"Services"
        }
    ],
    "sg:phone":"+1 212 252 0300",
    "sg:postcode":"10016",
    "sg:province":"NY",
    "sg:tags":[
        "attorney"
    ],
    "wof:name":"Kagan Lubic Lepper Lewis Colbe",
    "wof:placetype":"venue"
},
  "geometry": {"coordinates":[-73.982024,40.74905],"type":"Point"}
}