{
  "type": "Feature",
  "properties": {
    "iso:country":"US",
    "sg:address":"464 New York Ave Ste 100",
    "sg:city":"Huntington",
    "sg:classifiers":[
        {
            "category":"Professional",
            "subcategory":"Lawyer & Legal Services",
            "type":"Services"
        }
    ],
    "sg:phone":"+1 631 673 4998",
    "sg:postcode":"11743",
    "sg:province":"NY",
    "wof:name":"Randazzo Sheryl L Atty",
    "wof:placetype":"venue"
},
  "geometry": {"coordinates":[-73.42365599999999,40.866538],"type":"Point"}
}