{
  "type": "Feature",
  "properties": {
    "iso:country":"US",
    "sg:address":"440 9th Ave",
    "sg:city":"New York",
    "sg:classifiers":[
        {
            "category":"Real Estate",
            "subcategory":"Real Estate Services",
            "type":"Services"
        }
    ],
    "sg:phone":"+1 212 594 0566",
    "sg:postcode":"10001",
    "sg:province":"NY",
    "sg:tags":[
        "management",
        "property"
    ],
    "wof:name":"Murray Hill Property Management Inc",
    "wof:placetype":"venue"
},
  "geometry": {"coordinates":[-73.996002,40.7537],"type":"Point"}
}