{
  "type": "Feature",
  "properties": {
    "addr:full":"637 Nostrand Ave Brooklyn NY 11216",
    "addr:housenumber":"637",
    "addr:postcode":"11216",
    "addr:street":"Nostrand Ave",
    "iso:country":"US",
    "sg:address":"637 Nostrand Ave",
    "sg:city":"Brooklyn",
    "sg:classifiers":[
        {
            "category":"Deli",
            "type":"Food & Drink"
        },
        {
            "category":"Food & Beverages",
            "subcategory":"Bakery",
            "type":"Retail Goods"
        }
    ],
    "sg:phone":"+1 718 484 3711",
    "sg:postcode":"11216",
    "sg:province":"NY",
    "sg:tags":[
        "sandwich"
    ],
    "wof:name":"Us American Deli Corporation",
    "wof:placetype":"venue"
},
  "geometry": {"coordinates":[-73.949787,40.675324],"type":"Point"}
}