{
  "type": "Feature",
  "properties": {
    "iso:country":"US",
    "sg:address":"1918 Pine Ave",
    "sg:city":"Niagara Falls",
    "sg:classifiers":[
        {
            "category":"Wholesale",
            "subcategory":"Non-durable Goods",
            "type":"Manufacturing & Wholesale Goods"
        }
    ],
    "sg:phone":"+1 716 285 7332",
    "sg:postcode":"14301",
    "sg:province":"NY",
    "wof:name":"Raul Mercier Fine Art",
    "wof:placetype":"venue"
},
  "geometry": {"coordinates":[-79.038505,43.095168],"type":"Point"}
}