{
  "type": "Feature",
  "properties": {
    "iso:country":"US",
    "sg:address":"212 Center St",
    "sg:city":"Ithaca",
    "sg:classifiers":[
        {
            "category":"Shopping",
            "subcategory":"Used Merchandise",
            "type":"Retail Goods"
        }
    ],
    "sg:phone":"+1   ",
    "sg:postcode":"14850",
    "sg:province":"NY",
    "wof:name":"Significant Elements",
    "wof:placetype":"venue"
},
  "geometry": {"coordinates":[-76.502618,42.435629],"type":"Point"}
}