{
  "type": "Feature",
  "properties": {
    "iso:country":"US",
    "sg:address":"199 Quay Rd",
    "sg:city":"Delanson",
    "sg:classifiers":[
        {
            "category":"Building & Trades",
            "subcategory":"Construction",
            "type":"Services"
        }
    ],
    "sg:phone":"+1 518 475 5641",
    "sg:postcode":"12053",
    "sg:province":"NY",
    "sg:tags":[
        "maintenance",
        "contractor"
    ],
    "wof:name":"R H Maintenance & Vessel Entry",
    "wof:placetype":"venue"
},
  "geometry": {"coordinates":[-74.10254999999999,42.713174],"type":"Point"}
}