{
  "type": "Feature",
  "properties": {
    "iso:country":"US",
    "sg:address":"801 New Hague Rd",
    "sg:city":"Hague",
    "sg:classifiers":[
        {
            "category":"Professional",
            "subcategory":"Lawyer & Legal Services",
            "type":"Services"
        }
    ],
    "sg:phone":"+1 518 585 2749",
    "sg:postcode":"12836",
    "sg:province":"NY",
    "sg:tags":[
        "attorney"
    ],
    "wof:name":"Heather Knott Law Offices",
    "wof:placetype":"venue"
},
  "geometry": {"coordinates":[-73.49990699999999,43.788785],"type":"Point"}
}