{
  "type": "Feature",
  "properties": {
    "iso:country":"US",
    "sg:address":"29 N Bayles Ave",
    "sg:city":"Port Washington",
    "sg:classifiers":[
        {
            "category":"Manufacturing",
            "subcategory":"Retail Goods",
            "type":"Manufacturing & Wholesale Goods"
        }
    ],
    "sg:phone":"+1   ",
    "sg:postcode":"11050",
    "sg:province":"NY",
    "sg:tags":[
        "lead",
        "mfg"
    ],
    "wof:name":"Chroma Design Inc",
    "wof:placetype":"venue"
},
  "geometry": {"coordinates":[-73.687484,40.83332],"type":"Point"}
}