{
  "type": "Feature",
  "properties": {
    "iso:country":"US",
    "sg:address":"157 N Cayuga St",
    "sg:city":"Union Springs",
    "sg:classifiers":[
        {
            "category":"Autos & Motor Vehicles",
            "subcategory":"Auto Supplies",
            "type":"Retail Goods"
        }
    ],
    "sg:phone":"+1 315 889 7458",
    "sg:postcode":"13160",
    "sg:province":"NY",
    "sg:tags":[
        "automobile",
        "parts"
    ],
    "wof:name":"Union Spring Parts Plus",
    "wof:placetype":"venue"
},
  "geometry": {"coordinates":[-76.691244,42.847161],"type":"Point"}
}