{
  "type": "Feature",
  "properties": {
    "addr:full":"99 Gold Street Brooklyn NY 11201",
    "addr:housenumber":"99",
    "addr:postcode":"11201",
    "addr:street":"Gold Street",
    "iso:country":"US",
    "sg:address":"99 Gold Street",
    "sg:city":"Brooklyn",
    "sg:classifiers":[
        {
            "category":"Communications",
            "subcategory":"Newspaper",
            "type":"Services"
        }
    ],
    "sg:phone":"+1 718 643 1484",
    "sg:postcode":"11201",
    "sg:province":"NY",
    "sg:tags":[
        "magazine"
    ],
    "wof:name":"Ninety Nine Gold Assoc",
    "wof:placetype":"venue"
},
  "geometry": {"coordinates":[-73.982692,40.701637],"type":"Point"}
}