{
  "type": "Feature",
  "properties": {
    "iso:country":"US",
    "sg:address":"1370 Buffalo Rd",
    "sg:city":"Rochester",
    "sg:classifiers":[
        {
            "category":"Restaurant",
            "type":"Food & Drink"
        }
    ],
    "sg:phone":"+1   ",
    "sg:postcode":"14624",
    "sg:province":"NY",
    "sg:tags":[
        "grill",
        "bar"
    ],
    "wof:name":"Townsends Infield Sports Bar",
    "wof:placetype":"venue"
},
  "geometry": {"coordinates":[-77.680536,43.150022],"type":"Point"}
}