{
  "type": "Feature",
  "properties": {
    "addr:full":"1305 Middle Country Rd Selden NY 11784",
    "addr:housenumber":"1305",
    "addr:postcode":"11784",
    "addr:street":"Middle Country Rd",
    "iso:country":"US",
    "sg:address":"1305 Middle Country Rd",
    "sg:city":"Selden",
    "sg:classifiers":[
        {
            "category":"Professional",
            "type":"Services"
        }
    ],
    "sg:phone":"+1 631 696 2226",
    "sg:postcode":"11784",
    "sg:province":"NY",
    "sg:tags":[
        "establishment"
    ],
    "wof:name":"Vital Group Inc",
    "wof:placetype":"venue"
},
  "geometry": {"coordinates":[-73.05911399999999,40.862094],"type":"Point"}
}