{
  "type": "Feature",
  "properties": {
    "iso:country":"US",
    "sg:address":"929 N Sanford Rd",
    "sg:city":"Afton",
    "sg:classifiers":[
        {
            "category":"Building & Trades",
            "subcategory":"Construction",
            "type":"Services"
        }
    ],
    "sg:phone":"+1 607 467 4412",
    "sg:postcode":"13754",
    "sg:province":"NY",
    "sg:tags":[
        "carpentry",
        "contractor"
    ],
    "wof:name":"Steven & Debra Eisenberg",
    "wof:placetype":"venue"
},
  "geometry": {"coordinates":[-75.45269399999999,42.155671],"type":"Point"}
}