{
  "type": "Feature",
  "properties": {
    "addr:full":"1003 Northern Blvd Manhasset NY 11030",
    "addr:housenumber":"1003",
    "addr:postcode":"11030",
    "addr:street":"Northern Blvd",
    "iso:country":"US",
    "sg:address":"1003 Northern Blvd",
    "sg:city":"Manhasset",
    "sg:classifiers":[
        {
            "category":"Wholesale",
            "subcategory":"Non-durable Goods",
            "type":"Manufacturing & Wholesale Goods"
        }
    ],
    "sg:phone":"+1 516 869 5447",
    "sg:postcode":"11030",
    "sg:province":"NY",
    "sg:tags":[
        "interior"
    ],
    "wof:name":"Sinamex",
    "wof:placetype":"venue"
},
  "geometry": {"coordinates":[-73.70728200000001,40.785433],"type":"Point"}
}