{
  "type": "Feature",
  "properties": {
    "iso:country":"US",
    "sg:address":"493 7th Ave",
    "sg:city":"Brooklyn",
    "sg:classifiers":[
        {
            "category":"Shopping",
            "type":"Retail Goods"
        }
    ],
    "sg:phone":"+1 718 840 5840",
    "sg:postcode":"11215",
    "sg:province":"NY",
    "sg:website":"myspace.com/brooklynmonsterfactory",
    "wof:name":"Brooklyn Monster Factory",
    "wof:placetype":"venue"
},
  "geometry": {"coordinates":[-73.985707,40.661505],"type":"Point"}
}