{
  "type": "Feature",
  "properties": {
    "addr:full":"20 Iron Mountain Rd Warwick NY 10990",
    "addr:housenumber":"20",
    "addr:postcode":"10990",
    "addr:street":"Iron Mountain Rd",
    "iso:country":"US",
    "sg:address":"20 Iron Mountain Rd",
    "sg:city":"Warwick",
    "sg:classifiers":[
        {
            "category":"Education",
            "subcategory":"School",
            "type":"Public Place"
        }
    ],
    "sg:phone":"+1 845 986 9959",
    "sg:postcode":"10990",
    "sg:province":"NY",
    "wof:name":"Woodland Hollow Learning Ctr",
    "wof:placetype":"venue"
},
  "geometry": {"coordinates":[-74.413684,41.234615],"type":"Point"}
}