{
  "type": "Feature",
  "properties": {
    "iso:country":"US",
    "sg:address":"1355 61st St",
    "sg:city":"Brooklyn",
    "sg:classifiers":[
        {
            "category":"Shopping",
            "subcategory":"Clothing, Apparel, & Fashions",
            "type":"Retail Goods"
        }
    ],
    "sg:phone":"+1 718 436 8693",
    "sg:postcode":"11219",
    "sg:province":"NY",
    "wof:name":"Nielle Sing Fashions",
    "wof:placetype":"venue"
},
  "geometry": {"coordinates":[-73.99782399999999,40.627724],"type":"Point"}
}