{
  "type": "Feature",
  "properties": {
    "addr:full":"35 West St Spring Valley NY 10977",
    "addr:housenumber":"35",
    "addr:postcode":"10977",
    "addr:street":"West St",
    "iso:country":"US",
    "sg:address":"35 West St",
    "sg:city":"Spring Valley",
    "sg:classifiers":[
        {
            "category":"Wholesale",
            "subcategory":"Stationery",
            "type":"Manufacturing & Wholesale Goods"
        }
    ],
    "sg:phone":"+1 845 425 8008",
    "sg:postcode":"10977",
    "sg:province":"NY",
    "sg:tags":[
        "packaging",
        "material"
    ],
    "wof:name":"A & S Packing Supplies Co Inc",
    "wof:placetype":"venue"
},
  "geometry": {"coordinates":[-74.05013099999999,41.111179],"type":"Point"}
}