{
  "type": "Feature",
  "properties": {
    "iso:country":"US",
    "sg:address":"85 Pondfield Rd W",
    "sg:city":"Bronxville",
    "sg:classifiers":[
        {
            "category":"Professional",
            "subcategory":"Lawyer & Legal Services",
            "type":"Services"
        }
    ],
    "sg:phone":"+1 212 267 3330",
    "sg:postcode":"10708",
    "sg:province":"NY",
    "wof:name":"Meagher & Meagher Law Offices",
    "wof:placetype":"venue"
},
  "geometry": {"coordinates":[-73.841443,40.944115],"type":"Point"}
}