{
  "type": "Feature",
  "properties": {
    "iso:country":"US",
    "sg:address":"4771 Summerhurst Dr",
    "sg:city":"Liverpool",
    "sg:classifiers":[
        {
            "category":"Shopping",
            "subcategory":"Catalog Store",
            "type":"Retail Goods"
        }
    ],
    "sg:phone":"+1 315 457 9063",
    "sg:postcode":"13088",
    "sg:province":"NY",
    "sg:tags":[
        "e"
    ],
    "wof:name":"Nomrom Enterprises",
    "wof:placetype":"venue"
},
  "geometry": {"coordinates":[-76.186244,43.139564],"type":"Point"}
}