{
  "type": "Feature",
  "properties": {
    "iso:country":"US",
    "sg:address":"672 S Gannon Ave",
    "sg:city":"Staten Island",
    "sg:classifiers":[
        {
            "category":"Building & Trades",
            "subcategory":"Construction",
            "type":"Services"
        }
    ],
    "sg:phone":"+1 718 477 2510",
    "sg:postcode":"10314",
    "sg:province":"NY",
    "sg:tags":[
        "general",
        "contractor"
    ],
    "wof:name":"Diamond Construction USA",
    "wof:placetype":"venue"
},
  "geometry": {"coordinates":[-74.145174,40.607222],"type":"Point"}
}