{
  "type": "Feature",
  "properties": {
    "addr:full":"1032 Northern Blvd Roslyn NY 11576",
    "addr:housenumber":"1032",
    "addr:postcode":"11576",
    "addr:street":"Northern Blvd",
    "iso:country":"US",
    "sg:address":"1032 Northern Blvd",
    "sg:city":"Roslyn",
    "sg:classifiers":[
        {
            "category":"Professional",
            "subcategory":"Accounting & Tax Preparation",
            "type":"Services"
        }
    ],
    "sg:phone":"+1 516 621 9040",
    "sg:postcode":"11576",
    "sg:province":"NY",
    "sg:tags":[
        "accountant"
    ],
    "wof:name":"Patestas Simeon S CPA",
    "wof:placetype":"venue"
},
  "geometry": {"coordinates":[-73.667,40.797501],"type":"Point"}
}