{
  "type": "Feature",
  "properties": {
    "addr:full":"12693 Upton Rd Red Creek NY 13143",
    "addr:housenumber":"12693",
    "addr:postcode":"13143",
    "addr:street":"Upton Rd",
    "iso:country":"US",
    "sg:address":"12693 Upton Rd",
    "sg:city":"Red Creek",
    "sg:classifiers":[
        {
            "category":"Personal",
            "subcategory":"Barber",
            "type":"Services"
        }
    ],
    "sg:phone":"+1 315 754 8803",
    "sg:postcode":"13143",
    "sg:province":"NY",
    "wof:name":"Gabrielle's Hair Design",
    "wof:placetype":"venue"
},
  "geometry": {"coordinates":[-76.686583,43.234551],"type":"Point"}
}