{
  "type": "Feature",
  "properties": {
    "iso:country":"US",
    "sg:address":"75 Main St",
    "sg:city":"Champlain",
    "sg:classifiers":[
        {
            "category":"Professional",
            "type":"Services"
        }
    ],
    "sg:phone":"+1 518 298 8147",
    "sg:postcode":"12919",
    "sg:province":"NY",
    "sg:tags":[
        "establishment"
    ],
    "wof:name":"Harry Dog",
    "wof:placetype":"venue"
},
  "geometry": {"coordinates":[-73.448115,44.986841],"type":"Point"}
}