{
  "type": "Feature",
  "properties": {
    "addr:full":"46 N 6th St Brooklyn NY 11211",
    "addr:housenumber":"46",
    "addr:postcode":"11211",
    "addr:street":"N 6Th St",
    "iso:country":"US",
    "sg:address":"46 N 6th St",
    "sg:city":"Brooklyn",
    "sg:classifiers":[
        {
            "category":"Shopping",
            "subcategory":"Clothing, Apparel, & Fashions",
            "type":"Retail Goods"
        }
    ],
    "sg:phone":"+1 718 388 5188",
    "sg:postcode":"11211",
    "sg:province":"NY",
    "wof:name":"Noisette",
    "wof:placetype":"venue"
},
  "geometry": {"coordinates":[-73.96182399999999,40.719271],"type":"Point"}
}