{
  "type": "Feature",
  "properties": {
    "iso:country":"US",
    "sg:address":"5 Davis Dr",
    "sg:city":"Oneonta",
    "sg:classifiers":[
        {
            "category":"Insurance",
            "subcategory":"Insurance Agent",
            "type":"Services"
        }
    ],
    "sg:phone":"+1 607 432 3047",
    "sg:postcode":"13820",
    "sg:province":"NY",
    "sg:tags":[
        "real estate"
    ],
    "wof:name":"Bailey Calvert I",
    "wof:placetype":"venue"
},
  "geometry": {"coordinates":[-75.09069100000001,42.461028],"type":"Point"}
}