{
  "type": "Feature",
  "properties": {
    "iso:country":"US",
    "sg:address":"707 Kings Rd",
    "sg:city":"Schenectady",
    "sg:classifiers":[
        {
            "category":"Manufacturing",
            "subcategory":"Building Materials",
            "type":"Manufacturing & Wholesale Goods"
        },
        {
            "category":"Building & Trades",
            "subcategory":"Construction",
            "type":"Services"
        }
    ],
    "sg:phone":"+1 518 372 5330",
    "sg:postcode":"12304",
    "sg:province":"NY",
    "sg:tags":[
        "builder",
        "stair",
        "mfg"
    ],
    "wof:name":"Bob's Carpentry",
    "wof:placetype":"venue"
},
  "geometry": {"coordinates":[-73.913402,42.770732],"type":"Point"}
}