{
  "type": "Feature",
  "properties": {
    "iso:country":"US",
    "sg:address":"19 Birchwood Ln",
    "sg:city":"Hicksville",
    "sg:classifiers":[
        {
            "category":"Social Services",
            "subcategory":"Child Care",
            "type":"Services"
        }
    ],
    "sg:phone":"+1   ",
    "sg:postcode":"11801",
    "sg:province":"NY",
    "sg:tags":[
        "day"
    ],
    "wof:name":"Children of The World Daycare",
    "wof:placetype":"venue"
},
  "geometry": {"coordinates":[-73.507007,40.751574],"type":"Point"}
}