{
  "type": "Feature",
  "properties": {
    "addr:full":"709 Harry L Dr Johnson City NY 13790",
    "addr:housenumber":"709",
    "addr:postcode":"13790",
    "addr:street":"Harry L Dr",
    "iso:country":"US",
    "sg:address":"709 Harry L Dr",
    "sg:city":"Johnson City",
    "sg:classifiers":[
        {
            "category":"Deli",
            "type":"Food & Drink"
        }
    ],
    "sg:menulink":"http://www.allmenus.com/ny/union/126414-blimpie-subs--sandwiches/menu/",
    "sg:phone":"+1 607 798 6297",
    "sg:postcode":"13790",
    "sg:province":"NY",
    "sg:tags":[
        "wrap",
        "american",
        "sandwich"
    ],
    "wof:name":"Blimpie Subs & Sandwiches",
    "wof:placetype":"venue"
},
  "geometry": {"coordinates":[-75.976465,42.124919],"type":"Point"}
}