{
  "type": "Feature",
  "properties": {
    "addr:full":"19 S Main St Jamestown NY 14701",
    "addr:housenumber":"19",
    "addr:postcode":"14701",
    "addr:street":"S Main St",
    "iso:country":"US",
    "sg:address":"19 S Main St",
    "sg:city":"Jamestown",
    "sg:classifiers":[
        {
            "category":"Shopping",
            "subcategory":"Pharmacy",
            "type":"Retail Goods"
        }
    ],
    "sg:phone":"+1 716 488 0778",
    "sg:postcode":"14701",
    "sg:province":"NY",
    "wof:name":"CVS Pharmacy",
    "wof:placetype":"venue"
},
  "geometry": {"coordinates":[-79.23576199999999,42.090522],"type":"Point"}
}