{
  "type": "Feature",
  "properties": {
    "iso:country":"US",
    "sg:address":"45 Victory Boulevard",
    "sg:city":"Staten Island",
    "sg:classifiers":[
        {
            "category":"Wholesale",
            "subcategory":"Stationery",
            "type":"Manufacturing & Wholesale Goods"
        },
        {
            "category":"Shopping",
            "subcategory":"Pharmacy",
            "type":"Retail Goods"
        }
    ],
    "sg:phone":"+1 718 727 0430",
    "sg:postcode":"10301",
    "sg:province":"NY",
    "sg:tags":[
        "drugstore",
        "card"
    ],
    "wof:name":"Liggett Rexall Drg",
    "wof:placetype":"venue"
},
  "geometry": {"coordinates":[-74.077263,40.637766],"type":"Point"}
}