{
  "type": "Feature",
  "properties": {
    "iso:country":"US",
    "sg:address":"11 Trescott St",
    "sg:city":"Dix Hills",
    "sg:classifiers":[
        {
            "category":"Professional",
            "subcategory":"Accounting & Tax Preparation",
            "type":"Services"
        }
    ],
    "sg:phone":"+1 631 242 5036",
    "sg:postcode":"11746",
    "sg:province":"NY",
    "sg:tags":[
        "bookkeeping",
        "general"
    ],
    "wof:name":"Cis Account",
    "wof:placetype":"venue"
},
  "geometry": {"coordinates":[-73.34488399999999,40.776644],"type":"Point"}
}