{
  "type": "Feature",
  "properties": {
    "iso:country":"US",
    "sg:address":"1285 State Hwy 318",
    "sg:city":"Waterloo",
    "sg:classifiers":[
        {
            "category":"Autos & Motor Vehicles",
            "subcategory":"Auto Supplies",
            "type":"Retail Goods"
        }
    ],
    "sg:phone":"+1 315 539 1168",
    "sg:postcode":"13165",
    "sg:province":"NY",
    "sg:tags":[
        "automotive",
        "truck",
        "tire",
        "general"
    ],
    "wof:name":"Tallmadge Tire Svc of Geneva",
    "wof:placetype":"venue"
},
  "geometry": {"coordinates":[-76.882012,42.955954],"type":"Point"}
}