{
  "type": "Feature",
  "properties": {
    "addr:full":"810 Allerton Ave Bronx NY 10467",
    "addr:housenumber":"810",
    "addr:postcode":"10467",
    "addr:street":"Allerton Ave",
    "iso:country":"US",
    "sg:address":"810 Allerton Ave",
    "sg:city":"Bronx",
    "sg:classifiers":[
        {
            "category":"Real Estate",
            "subcategory":"Real Estate Agent",
            "type":"Services"
        }
    ],
    "sg:phone":"+1 718 328 3897",
    "sg:postcode":"10467",
    "sg:province":"NY",
    "wof:name":"Lebron Mortgages",
    "wof:placetype":"venue"
},
  "geometry": {"coordinates":[-73.862899,40.865443],"type":"Point"}
}