{
  "type": "Feature",
  "properties": {
    "iso:country":"US",
    "sg:address":"90 Broad St",
    "sg:city":"New York",
    "sg:classifiers":[
        {
            "category":"Banks & Credit Unions",
            "subcategory":"Investment Brokerage",
            "type":"Services"
        }
    ],
    "sg:phone":"+1 212 248 3707",
    "sg:postcode":"10004",
    "sg:province":"NY",
    "sg:tags":[
        "investing"
    ],
    "wof:name":"Voorhis H M Baird",
    "wof:placetype":"venue"
},
  "geometry": {"coordinates":[-74.01159699999999,40.703999],"type":"Point"}
}