{
  "type": "Feature",
  "properties": {
    "iso:country":"US",
    "sg:address":"149 Fish and Game Club Rd",
    "sg:city":"Canajoharie",
    "sg:classifiers":[
        {
            "category":"Farming",
            "subcategory":"Fish & Marine Products",
            "type":"Manufacturing & Wholesale Goods"
        }
    ],
    "sg:phone":"+1 518 673 2389",
    "sg:postcode":"13317",
    "sg:province":"NY",
    "sg:tags":[
        "preserves",
        "fishing",
        "hunting"
    ],
    "wof:name":"Canajoharie Forest Fish & Game",
    "wof:placetype":"venue"
},
  "geometry": {"coordinates":[-74.531656,42.855368],"type":"Point"}
}