{
  "type": "Feature",
  "properties": {
    "iso:country":"US",
    "sg:address":"15 Rolling Brook Dr",
    "sg:city":"Clifton Park",
    "sg:classifiers":[
        {
            "category":"Professional",
            "subcategory":"Computer Services",
            "type":"Services"
        }
    ],
    "sg:phone":"+1 518 371 2301",
    "sg:postcode":"12065",
    "sg:province":"NY",
    "sg:tags":[
        "wholesale",
        "consulting",
        "provides"
    ],
    "wof:name":"Phoenix Distribution & Service",
    "wof:placetype":"venue"
},
  "geometry": {"coordinates":[-73.78908,42.881791],"type":"Point"}
}