{
  "type": "Feature",
  "properties": {
    "iso:country":"US",
    "sg:address":"1956 Rush Mendon Rd",
    "sg:city":"Rush",
    "sg:classifiers":[
        {
            "category":"Building & Trades",
            "subcategory":"Construction",
            "type":"Services"
        }
    ],
    "sg:phone":"+1 585 533 2164",
    "sg:postcode":"14543",
    "sg:province":"NY",
    "sg:tags":[
        "house"
    ],
    "wof:name":"Schneider Construction",
    "wof:placetype":"venue"
},
  "geometry": {"coordinates":[-77.64281699999999,42.995907],"type":"Point"}
}