{
  "type": "Feature",
  "properties": {
    "addr:full":"2 Lafayette St New York NY 10007",
    "addr:housenumber":"2",
    "addr:postcode":"10007",
    "addr:street":"Lafayette St",
    "iso:country":"US",
    "sg:address":"2 Lafayette St",
    "sg:city":"New York",
    "sg:classifiers":[
        {
            "category":"Government",
            "subcategory":"Office",
            "type":"Public Place"
        }
    ],
    "sg:phone":"+1 212 212 4421",
    "sg:postcode":"10007",
    "sg:province":"NY",
    "sg:tags":[
        "village"
    ],
    "wof:name":"New York Conflicts-Interest",
    "wof:placetype":"venue"
},
  "geometry": {"coordinates":[-74.003404,40.714151],"type":"Point"}
}