{
  "type": "Feature",
  "properties": {
    "addr:full":"9321 3rd Ave Brooklyn NY 11209",
    "addr:housenumber":"9321",
    "addr:postcode":"11209",
    "addr:street":"3Rd Ave",
    "iso:country":"US",
    "sg:address":"9321 3rd Ave",
    "sg:city":"Brooklyn",
    "sg:classifiers":[
        {
            "category":"Autos & Motor Vehicles",
            "subcategory":"Fuel & Gas Station",
            "type":"Retail Goods"
        }
    ],
    "sg:phone":"+1 718 833 0267",
    "sg:postcode":"11209",
    "sg:province":"NY",
    "sg:tags":[
        "oil"
    ],
    "wof:name":"F & S Auto Svce Ltd",
    "wof:placetype":"venue"
},
  "geometry": {"coordinates":[-74.033096,40.618099],"type":"Point"}
}