{
  "type": "Feature",
  "properties": {
    "addr:full":"280 Jerusalem Ave Hempstead NY 11550",
    "addr:housenumber":"280",
    "addr:postcode":"11550",
    "addr:street":"Jerusalem Ave",
    "iso:country":"US",
    "sg:address":"280 Jerusalem Ave",
    "sg:city":"Hempstead",
    "sg:classifiers":[
        {
            "category":"Organizations",
            "subcategory":"Religious Organization",
            "type":"Services"
        }
    ],
    "sg:phone":"+1 516 292 7647",
    "sg:postcode":"11550",
    "sg:province":"NY",
    "sg:tags":[
        "church"
    ],
    "wof:name":"God's Miracle Temple",
    "wof:placetype":"venue"
},
  "geometry": {"coordinates":[-73.60719,40.702329],"type":"Point"}
}