{
  "type": "Feature",
  "properties": {
    "addr:full":"460 Nichols Rd Hauppauge NY 11788",
    "addr:housenumber":"460",
    "addr:postcode":"11788",
    "addr:street":"Nichols Rd",
    "iso:country":"US",
    "sg:address":"460 Nichols Rd",
    "sg:city":"Hauppauge",
    "sg:classifiers":[
        {
            "category":"Building & Trades",
            "subcategory":"Construction",
            "type":"Services"
        }
    ],
    "sg:phone":"+1 631 979 6404",
    "sg:postcode":"11788",
    "sg:province":"NY",
    "sg:tags":[
        "tile",
        "dealer"
    ],
    "wof:name":"Ceramica Tile & Marble",
    "wof:placetype":"venue"
},
  "geometry": {"coordinates":[-73.14801,40.826517],"type":"Point"}
}