{
  "type": "Feature",
  "properties": {
    "addr:full":"465 Endo Blvd Garden City NY 11530",
    "addr:housenumber":"465",
    "addr:postcode":"11530",
    "addr:street":"Endo Blvd",
    "iso:country":"US",
    "sg:address":"465 Endo Blvd",
    "sg:city":"Garden City",
    "sg:classifiers":[
        {
            "category":"Food & Beverages",
            "subcategory":"Liquor & Beverages",
            "type":"Retail Goods"
        }
    ],
    "sg:phone":"+1 516 222 2449",
    "sg:postcode":"11530",
    "sg:province":"NY",
    "sg:tags":[
        "beer",
        "spirit",
        "wine"
    ],
    "wof:name":"E Vineyard Inc",
    "wof:placetype":"venue"
},
  "geometry": {"coordinates":[-73.59200199999999,40.73468],"type":"Point"}
}