{
  "type": "Feature",
  "properties": {
    "iso:country":"US",
    "sg:address":"2 Long Bow Rd",
    "sg:city":"Wading River",
    "sg:classifiers":[
        {
            "category":"Building & Trades",
            "subcategory":"Construction",
            "type":"Services"
        }
    ],
    "sg:phone":"+1 631 737 4296",
    "sg:postcode":"11792",
    "sg:province":"NY",
    "sg:tags":[
        "fence",
        "contractor"
    ],
    "wof:name":"Sunrise Custom Fence Inc",
    "wof:placetype":"venue"
},
  "geometry": {"coordinates":[-72.861592,40.946852],"type":"Point"}
}