{
  "type": "Feature",
  "properties": {
    "addr:full":"9902 63rd Rd Rego Park NY 11374",
    "addr:housenumber":"9902",
    "addr:postcode":"11374",
    "addr:street":"63Rd Rd",
    "iso:country":"US",
    "sg:address":"9902 63rd Rd",
    "sg:city":"Rego Park",
    "sg:classifiers":[
        {
            "category":"Home & Garden",
            "subcategory":"Hardware",
            "type":"Retail Goods"
        }
    ],
    "sg:phone":"+1 718 275 8427",
    "sg:postcode":"11374",
    "sg:province":"NY",
    "sg:tags":[
        "store"
    ],
    "wof:name":"Dagim Hardware",
    "wof:placetype":"venue"
},
  "geometry": {"coordinates":[-73.85659800000001,40.732399],"type":"Point"}
}