{
  "type": "Feature",
  "properties": {
    "addr:full":"160 North 4th Street between Bedford and Driggs Brooklyn NY 11211",
    "addr:housenumber":"160",
    "addr:postcode":"11211",
    "addr:street":"North 4Th Street",
    "iso:country":"US",
    "sg:address":"160 North 4th Street between Bedford and Driggs",
    "sg:city":"Brooklyn",
    "sg:classifiers":[
        {
            "category":"Bars & Pubs",
            "subcategory":"Nightclub",
            "type":"Food & Drink"
        }
    ],
    "sg:postcode":"11211",
    "sg:province":"NY",
    "sg:tags":[
        "nightlife"
    ],
    "wof:name":"Funhouse",
    "wof:placetype":"venue"
},
  "geometry": {"coordinates":[-73.959,40.715698],"type":"Point"}
}