{
  "type": "Feature",
  "properties": {
    "iso:country":"US",
    "sg:address":"431 Boston Post Rd",
    "sg:city":"Port Chester",
    "sg:classifiers":[
        {
            "category":"Shopping",
            "subcategory":"Jewelry",
            "type":"Retail Goods"
        }
    ],
    "sg:phone":"+1   ",
    "sg:postcode":"10573",
    "sg:province":"NY",
    "sg:tags":[
        "watch"
    ],
    "wof:name":"Mgs Watch & Jewelery Center",
    "wof:placetype":"venue"
},
  "geometry": {"coordinates":[-73.67462500000001,40.993881],"type":"Point"}
}