{
  "type": "Feature",
  "properties": {
    "iso:country":"US",
    "sg:address":"452 Franklin St",
    "sg:city":"Buffalo",
    "sg:classifiers":[
        {
            "category":"Education",
            "subcategory":"Music School",
            "type":"Public Place"
        }
    ],
    "sg:phone":"+1 716 886 5902",
    "sg:postcode":"14202",
    "sg:province":"NY",
    "sg:tags":[
        "instrument",
        "teacher",
        "musical"
    ],
    "wof:name":"Mc Clellan Music House",
    "wof:placetype":"venue"
},
  "geometry": {"coordinates":[-78.872597,42.897999],"type":"Point"}
}