{
  "type": "Feature",
  "properties": {
    "iso:country":"US",
    "sg:address":"2740 Co Rd 67",
    "sg:city":"Freehold",
    "sg:classifiers":[
        {
            "category":"Travel",
            "subcategory":"Hotels & Motels",
            "type":"Entertainment"
        }
    ],
    "sg:phone":"+1   ",
    "sg:postcode":"12431",
    "sg:province":"NY",
    "sg:tags":[
        "course",
        "american",
        "golf",
        "bar"
    ],
    "wof:name":"Pleasant View",
    "wof:placetype":"venue"
},
  "geometry": {"coordinates":[-74.010104,42.354894],"type":"Point"}
}