{
  "type": "Feature",
  "properties": {
    "addr:full":"295 Connecticut St Buffalo NY 14213",
    "addr:housenumber":"295",
    "addr:postcode":"14213",
    "addr:street":"Connecticut St",
    "iso:country":"US",
    "sg:address":"295 Connecticut St",
    "sg:city":"Buffalo",
    "sg:classifiers":[
        {
            "category":"Education",
            "subcategory":"University",
            "type":"Public Place"
        }
    ],
    "sg:phone":"+1 716 881 2820",
    "sg:postcode":"14213",
    "sg:province":"NY",
    "sg:tags":[
        "college"
    ],
    "wof:name":"D'Youville College",
    "wof:placetype":"venue"
},
  "geometry": {"coordinates":[-78.889522,42.904756],"type":"Point"}
}