{
  "type": "Feature",
  "properties": {
    "addr:full":"80 Evergreen Ave Brooklyn NY 11206",
    "addr:housenumber":"80",
    "addr:postcode":"11206",
    "addr:street":"Evergreen Ave",
    "iso:country":"US",
    "sg:address":"80 Evergreen Ave",
    "sg:city":"Brooklyn",
    "sg:classifiers":[
        {
            "category":"Wholesale",
            "subcategory":"Toys & Hobbies",
            "type":"Manufacturing & Wholesale Goods"
        }
    ],
    "sg:phone":"+1 718 366 1814",
    "sg:postcode":"11206",
    "sg:province":"NY",
    "wof:name":"Kisswiss Inc",
    "wof:placetype":"venue"
},
  "geometry": {"coordinates":[-73.9329,40.700173],"type":"Point"}
}