{
  "type": "Feature",
  "properties": {
    "addr:full":"4 Roxbury Ave Breezy Point NY 11697",
    "addr:housenumber":"4",
    "addr:postcode":"11697",
    "addr:street":"Roxbury Ave",
    "iso:country":"US",
    "sg:address":"4 Roxbury Ave",
    "sg:city":"Breezy Point",
    "sg:classifiers":[
        {
            "category":"Restaurant",
            "type":"Food & Drink"
        }
    ],
    "sg:phone":"+1 718 945 4522",
    "sg:postcode":"11697",
    "sg:province":"NY",
    "sg:tags":[
        "eating"
    ],
    "wof:name":"Roxbury Barn II",
    "wof:placetype":"venue"
},
  "geometry": {"coordinates":[-73.886703,40.567001],"type":"Point"}
}