{
  "type": "Feature",
  "properties": {
    "iso:country":"US",
    "sg:address":"1002 Cleveland Ave",
    "sg:city":"Utica",
    "sg:classifiers":[
        {
            "category":"Building & Trades",
            "subcategory":"Plumbing",
            "type":"Services"
        }
    ],
    "sg:phone":"+1 315 733 1339",
    "sg:postcode":"13502",
    "sg:province":"NY",
    "sg:tags":[
        "plumbing",
        "heating",
        "contractor"
    ],
    "wof:name":"Richard T Borek",
    "wof:placetype":"venue"
},
  "geometry": {"coordinates":[-75.252092,43.100126],"type":"Point"}
}