{
  "type": "Feature",
  "properties": {
    "addr:full":"388 Nostrand Ave Brooklyn NY 11216",
    "addr:housenumber":"388",
    "addr:postcode":"11216",
    "addr:street":"Nostrand Ave",
    "iso:country":"US",
    "sg:address":"388 Nostrand Ave",
    "sg:city":"Brooklyn",
    "sg:classifiers":[
        {
            "category":"Food & Beverages",
            "subcategory":"Groceries & Convenience Stores",
            "type":"Retail Goods"
        }
    ],
    "sg:phone":"+1 718 789 8769",
    "sg:postcode":"11216",
    "sg:province":"NY",
    "sg:tags":[
        "grocer"
    ],
    "wof:name":"Aldaylam Deli Supermarket",
    "wof:placetype":"venue"
},
  "geometry": {"coordinates":[-73.95088199999999,40.686932],"type":"Point"}
}