{
  "type": "Feature",
  "properties": {
    "iso:country":"US",
    "sg:address":"88 Belmeade Rd",
    "sg:city":"Rochester",
    "sg:classifiers":[
        {
            "category":"Manufacturing",
            "subcategory":"Tools & Machinery",
            "type":"Manufacturing & Wholesale Goods"
        }
    ],
    "sg:phone":"+1   ",
    "sg:postcode":"14617",
    "sg:province":"NY",
    "sg:tags":[
        "analytical",
        "instrument",
        "mfg"
    ],
    "wof:name":"Rfm Assoc",
    "wof:placetype":"venue"
},
  "geometry": {"coordinates":[-77.596892,43.212737],"type":"Point"}
}