{
  "type": "Feature",
  "properties": {
    "iso:country":"US",
    "sg:address":"1344 University Ave",
    "sg:city":"Rochester",
    "sg:classifiers":[
        {
            "category":"Freight",
            "type":"Transportation"
        }
    ],
    "sg:phone":"+1   ",
    "sg:postcode":"14607",
    "sg:province":"NY",
    "sg:tags":[
        "logistics"
    ],
    "wof:name":"Tri-Star Logistics Inc",
    "wof:placetype":"venue"
},
  "geometry": {"coordinates":[-77.56564299999999,43.150187],"type":"Point"}
}