{
  "type": "Feature",
  "properties": {
    "addr:full":"571 Jericho Tpke Syosset NY 11791",
    "addr:housenumber":"571",
    "addr:postcode":"11791",
    "addr:street":"Jericho Tpke",
    "iso:country":"US",
    "sg:address":"571 Jericho Tpke",
    "sg:city":"Syosset",
    "sg:classifiers":[
        {
            "category":"Restaurant",
            "type":"Food & Drink"
        }
    ],
    "sg:menulink":"http://www.allmenus.com/ny/syosset/189202-mcdonalds/menu/",
    "sg:postcode":"11791",
    "sg:province":"NY",
    "sg:tags":[
        "burger",
        "american"
    ],
    "wof:name":"McDonald's",
    "wof:placetype":"venue"
},
  "geometry": {"coordinates":[-73.495898,40.810999],"type":"Point"}
}