{
  "type": "Feature",
  "properties": {
    "iso:country":"US",
    "sg:address":"4256 Jockey St",
    "sg:city":"Ballston Lake",
    "sg:classifiers":[
        {
            "category":"Retail",
            "subcategory":"Portrait Studio",
            "type":"Services"
        }
    ],
    "sg:phone":"+1   ",
    "sg:postcode":"12019",
    "sg:province":"NY",
    "sg:tags":[
        "laboratory",
        "photofinishing",
        "photo"
    ],
    "wof:name":"Photos By John",
    "wof:placetype":"venue"
},
  "geometry": {"coordinates":[-73.975526,42.968982],"type":"Point"}
}