{
  "type": "Feature",
  "properties": {
    "iso:country":"US",
    "sg:address":"4335 42nd St",
    "sg:city":"Sunnyside",
    "sg:classifiers":[
        {
            "category":"Real Estate",
            "subcategory":"Real Estate Services",
            "type":"Services"
        },
        {
            "category":"Real Estate",
            "subcategory":"Real Estate Agent",
            "type":"Services"
        }
    ],
    "sg:phone":"+1 718 472 0582",
    "sg:postcode":"11104",
    "sg:province":"NY",
    "sg:tags":[
        "buyer",
        "broker"
    ],
    "wof:name":"Nathan Katz Realty",
    "wof:placetype":"venue"
},
  "geometry": {"coordinates":[-73.922398,40.743679],"type":"Point"}
}