{
  "type": "Feature",
  "properties": {
    "addr:full":"5345 Transit Rd Buffalo NY 14221",
    "addr:housenumber":"5345",
    "addr:postcode":"14221",
    "addr:street":"Transit Rd",
    "iso:country":"US",
    "sg:address":"5345 Transit Rd",
    "sg:city":"Buffalo",
    "sg:classifiers":[
        {
            "category":"Restaurant",
            "type":"Food & Drink"
        }
    ],
    "sg:menulink":"http://www.allmenus.com/ny/clarence/170113-burger-king/menu/",
    "sg:phone":"+1 716 688 5595",
    "sg:postcode":"14221",
    "sg:province":"NY",
    "sg:tags":[
        "burger",
        "american"
    ],
    "wof:name":"Burger King",
    "wof:placetype":"venue"
},
  "geometry": {"coordinates":[-78.696713,42.991916],"type":"Point"}
}