{
  "type": "Feature",
  "properties": {
    "addr:full":"287 5th Ave Brooklyn NY 11215",
    "addr:housenumber":"287",
    "addr:postcode":"11215",
    "addr:street":"5Th Ave",
    "iso:country":"US",
    "sg:address":"287 5th Ave",
    "sg:city":"Brooklyn",
    "sg:classifiers":[
        {
            "category":"Shopping",
            "subcategory":"Computers & Home Electronics",
            "type":"Retail Goods"
        }
    ],
    "sg:phone":"+1   ",
    "sg:postcode":"11215",
    "sg:province":"NY",
    "wof:name":"Skys Limit Computer",
    "wof:placetype":"venue"
},
  "geometry": {"coordinates":[-73.98254799999999,40.673626],"type":"Point"}
}