{
  "type": "Feature",
  "properties": {
    "iso:country":"US",
    "sg:address":"85 Central Ave",
    "sg:city":"Lancaster",
    "sg:classifiers":[
        {
            "category":"Real Estate",
            "subcategory":"Surveying",
            "type":"Services"
        }
    ],
    "sg:phone":"+1   ",
    "sg:postcode":"14086",
    "sg:province":"NY",
    "sg:tags":[
        "civil",
        "engineering"
    ],
    "wof:name":"Delaplante James H III",
    "wof:placetype":"venue"
},
  "geometry": {"coordinates":[-78.67045899999999,42.90325],"type":"Point"}
}