{
  "type": "Feature",
  "properties": {
    "addr:full":"606 W 47 St New York NY 10036",
    "addr:housenumber":"606",
    "addr:postcode":"10036",
    "addr:street":"W 47 St",
    "iso:country":"US",
    "sg:address":"606 W 47 St",
    "sg:city":"New York",
    "sg:classifiers":[
        {
            "category":"Professional",
            "subcategory":"Management & Consulting",
            "type":"Services"
        }
    ],
    "sg:phone":"+1 212 432 8524",
    "sg:postcode":"10036",
    "sg:province":"NY",
    "sg:tags":[
        "marketing",
        "consultant"
    ],
    "wof:name":"Nifro Marketing",
    "wof:placetype":"venue"
},
  "geometry": {"coordinates":[-73.99812300000001,40.764803],"type":"Point"}
}