{
  "type": "Feature",
  "properties": {
    "addr:full":"15 E 32 St New York NY 10016",
    "addr:housenumber":"15;32",
    "addr:postcode":"10016",
    "addr:street":"E;St",
    "iso:country":"US",
    "sg:address":"15 E 32 St",
    "sg:city":"New York",
    "sg:classifiers":[
        {
            "category":"Retail",
            "subcategory":"Portrait Studio",
            "type":"Services"
        }
    ],
    "sg:phone":"+1 212 696 1872",
    "sg:postcode":"10016",
    "sg:province":"NY",
    "sg:tags":[
        "photography"
    ],
    "wof:name":"John Lawton Photography",
    "wof:placetype":"venue"
},
  "geometry": {"coordinates":[-73.984567,40.746936],"type":"Point"}
}