{
  "type": "Feature",
  "properties": {
    "iso:country":"US",
    "sg:address":"7 Ivy Hill Ct",
    "sg:city":"Huntington",
    "sg:classifiers":[
        {
            "category":"Manufacturing",
            "subcategory":"Metals",
            "type":"Manufacturing & Wholesale Goods"
        }
    ],
    "sg:phone":"+1 631 549 4489",
    "sg:postcode":"11743",
    "sg:province":"NY",
    "sg:tags":[
        "mfg",
        "metalwork",
        "center",
        "structural"
    ],
    "wof:name":"Architectural Metal Design",
    "wof:placetype":"venue"
},
  "geometry": {"coordinates":[-73.37242999999999,40.836471],"type":"Point"}
}