{
  "type": "Feature",
  "properties": {
    "addr:full":"77 Quaker Ridge Rd New Rochelle NY 10804",
    "addr:housenumber":"77",
    "addr:postcode":"10804",
    "addr:street":"Quaker Ridge Rd",
    "iso:country":"US",
    "sg:address":"77 Quaker Ridge Rd",
    "sg:city":"New Rochelle",
    "sg:classifiers":[
        {
            "category":"Personal",
            "subcategory":"Tanning Parlor",
            "type":"Services"
        }
    ],
    "sg:phone":"+1 914 636 7457",
    "sg:postcode":"10804",
    "sg:province":"NY",
    "sg:tags":[
        "salon"
    ],
    "wof:name":"Hollywood Tans",
    "wof:placetype":"venue"
},
  "geometry": {"coordinates":[-73.79281400000001,40.948728],"type":"Point"}
}