{
  "type": "Feature",
  "properties": {
    "addr:full":"805 W Beech St Long Beach NY 11561",
    "addr:housenumber":"805",
    "addr:postcode":"11561",
    "addr:street":"W Beech St",
    "iso:country":"US",
    "sg:address":"805 W Beech St",
    "sg:city":"Long Beach",
    "sg:classifiers":[
        {
            "category":"Shopping",
            "subcategory":"Pets & Pet Supplies",
            "type":"Retail Goods"
        }
    ],
    "sg:phone":"+1 516 897 7078",
    "sg:postcode":"11561",
    "sg:province":"NY",
    "sg:tags":[
        "store"
    ],
    "sg:website":"www.barkingbeauties.net",
    "wof:name":"Barking Beauties Inc",
    "wof:placetype":"venue"
},
  "geometry": {"coordinates":[-73.689796,40.585899],"type":"Point"}
}