{
  "type": "Feature",
  "properties": {
    "addr:full":"25 Shadowmoor Dr Fairport NY 14450",
    "addr:housenumber":"25",
    "addr:postcode":"14450",
    "addr:street":"Shadowmoor Dr",
    "iso:country":"US",
    "sg:address":"25 Shadowmoor Dr",
    "sg:city":"Fairport",
    "sg:classifiers":[
        {
            "category":"Professional",
            "subcategory":"Computer Services",
            "type":"Services"
        }
    ],
    "sg:phone":"+1 585 377 6046",
    "sg:postcode":"14450",
    "sg:province":"NY",
    "sg:tags":[
        "design",
        "electrical",
        "system",
        "contractor"
    ],
    "wof:name":"Salmon S Assoc",
    "wof:placetype":"venue"
},
  "geometry": {"coordinates":[-77.47354900000001,43.093451],"type":"Point"}
}