{
  "type": "Feature",
  "properties": {
    "addr:full":"29 Essex St New York NY 10002",
    "addr:housenumber":"29",
    "addr:postcode":"10002",
    "addr:street":"Essex St",
    "iso:country":"US",
    "sg:address":"29 Essex St",
    "sg:city":"New York",
    "sg:classifiers":[
        {
            "category":"Autos & Motor Vehicles",
            "subcategory":"Automobile Sales",
            "type":"Retail Goods"
        },
        {
            "category":"Taxi",
            "type":"Transportation"
        }
    ],
    "sg:phone":"+1 212 228 3301",
    "sg:postcode":"10002",
    "sg:province":"NY",
    "sg:tags":[
        "limo"
    ],
    "sg:website":"delanceynyc.com",
    "wof:name":"Delancey Car Services",
    "wof:placetype":"venue"
},
  "geometry": {"coordinates":[-73.98967399999999,40.715674],"type":"Point"}
}