{
  "type": "Feature",
  "properties": {
    "iso:country":"US",
    "sg:address":"329 Broadway",
    "sg:city":"Newburgh",
    "sg:classifiers":[
        {
            "category":"Shopping",
            "subcategory":"Tobacco",
            "type":"Retail Goods"
        }
    ],
    "sg:phone":"+1   ",
    "sg:postcode":"12550",
    "sg:province":"NY",
    "sg:tags":[
        "product"
    ],
    "wof:name":"Thrifty Beverage",
    "wof:placetype":"venue"
},
  "geometry": {"coordinates":[-74.02244399999999,41.500685],"type":"Point"}
}