{
  "type": "Feature",
  "properties": {
    "iso:country":"US",
    "sg:address":"647 Lafayette Ave",
    "sg:city":"Buffalo",
    "sg:classifiers":[
        {
            "category":"Building & Trades",
            "subcategory":"Construction",
            "type":"Services"
        }
    ],
    "sg:phone":"+1 716 881 1790",
    "sg:postcode":"14222",
    "sg:province":"NY",
    "sg:tags":[
        "painting",
        "contractor"
    ],
    "wof:name":"Santoro Painting",
    "wof:placetype":"venue"
},
  "geometry": {"coordinates":[-78.871021,42.920412],"type":"Point"}
}