{
  "type": "Feature",
  "properties": {
    "iso:country":"US",
    "sg:address":"138 Henry St",
    "sg:city":"Binghamton",
    "sg:classifiers":[
        {
            "category":"Food & Beverages",
            "subcategory":"Liquor & Beverages",
            "type":"Retail Goods"
        }
    ],
    "sg:phone":"+1 607 724 8168",
    "sg:postcode":"13901",
    "sg:province":"NY",
    "wof:name":"C & A Evans Liquor & Wine",
    "wof:placetype":"venue"
},
  "geometry": {"coordinates":[-75.903064,42.102592],"type":"Point"}
}