{
  "type": "Feature",
  "properties": {
    "addr:full":"19 Bayview Ave Manhasset NY 11030",
    "addr:housenumber":"19",
    "addr:postcode":"11030",
    "addr:street":"Bayview Ave",
    "iso:country":"US",
    "sg:address":"19 Bayview Ave",
    "sg:city":"Manhasset",
    "sg:classifiers":[
        {
            "category":"Personal",
            "subcategory":"Beauty Salon",
            "type":"Services"
        }
    ],
    "sg:phone":"+1 516 627 8822",
    "sg:postcode":"11030",
    "sg:province":"NY",
    "sg:tags":[
        "nail"
    ],
    "wof:name":"Cocoa Nail Salon",
    "wof:placetype":"venue"
},
  "geometry": {"coordinates":[-73.700401,40.797699],"type":"Point"}
}