{
  "type": "Feature",
  "properties": {
    "iso:country":"US",
    "sg:address":"45 Main St",
    "sg:city":"Hornell",
    "sg:classifiers":[
        {
            "category":"Restaurant",
            "type":"Food & Drink"
        }
    ],
    "sg:menulink":"http://www.allmenus.com/ny/hornell/169919-burger-king/menu/",
    "sg:phone":"+1 607 324 0961",
    "sg:postcode":"14843",
    "sg:province":"NY",
    "sg:tags":[
        "burger",
        "american"
    ],
    "wof:name":"Burger King",
    "wof:placetype":"venue"
},
  "geometry": {"coordinates":[-77.66246599999999,42.327806],"type":"Point"}
}