{
  "type": "Feature",
  "properties": {
    "iso:country":"US",
    "sg:address":"410 Jericho Tpke",
    "sg:city":"Jericho",
    "sg:classifiers":[
        {
            "category":"Banks & Credit Unions",
            "subcategory":"Investment Brokerage",
            "type":"Services"
        }
    ],
    "sg:phone":"+1 516 932 0216",
    "sg:postcode":"11753",
    "sg:province":"NY",
    "sg:tags":[
        "advisory",
        "financial"
    ],
    "wof:name":"Adomaites Associates LTD",
    "wof:placetype":"venue"
},
  "geometry": {"coordinates":[-73.53632500000001,40.79396],"type":"Point"}
}