{
  "type": "Feature",
  "properties": {
    "addr:full":"410 W Main St Huntington NY 11743",
    "addr:housenumber":"410",
    "addr:postcode":"11743",
    "addr:street":"W Main St",
    "iso:country":"US",
    "sg:address":"410 W Main St",
    "sg:city":"Huntington",
    "sg:classifiers":[
        {
            "category":"Retail",
            "subcategory":"Laundry & Dry Cleaning",
            "type":"Services"
        }
    ],
    "sg:phone":"+1 631 425 1919",
    "sg:postcode":"11743",
    "sg:province":"NY",
    "sg:website":"jimdandycleaners.com",
    "wof:name":"Jim Dandy Cleaners",
    "wof:placetype":"venue"
},
  "geometry": {"coordinates":[-73.43371500000001,40.86922],"type":"Point"}
}