{
  "type": "Feature",
  "properties": {
    "addr:full":"98 2nd St Deposit NY 13754",
    "addr:housenumber":"98",
    "addr:postcode":"13754",
    "addr:street":"2Nd St",
    "iso:country":"US",
    "sg:address":"98 2nd St",
    "sg:city":"Deposit",
    "sg:classifiers":[
        {
            "category":"Organizations",
            "subcategory":"Religious Organization",
            "type":"Services"
        }
    ],
    "sg:phone":"+1 607 467 2291",
    "sg:postcode":"13754",
    "sg:province":"NY",
    "sg:tags":[
        "church"
    ],
    "wof:name":"St Joseph's Rectory",
    "wof:placetype":"venue"
},
  "geometry": {"coordinates":[-75.425442,42.061748],"type":"Point"}
}