{
  "type": "Feature",
  "properties": {
    "addr:full":"55 Benkard Ave Newburgh NY 12550",
    "addr:housenumber":"55",
    "addr:postcode":"12550",
    "addr:street":"Benkard Ave",
    "iso:country":"US",
    "sg:address":"55 Benkard Ave",
    "sg:city":"Newburgh",
    "sg:classifiers":[
        {
            "category":"Arts & Performance",
            "subcategory":"Theater",
            "type":"Entertainment"
        }
    ],
    "sg:phone":"+1 845 562 5936",
    "sg:postcode":"12550",
    "sg:province":"NY",
    "sg:tags":[
        "live",
        "music"
    ],
    "wof:name":"Mad Squad",
    "wof:placetype":"venue"
},
  "geometry": {"coordinates":[-74.013299,41.495295],"type":"Point"}
}