{
  "type": "Feature",
  "properties": {
    "addr:full":"2418 E 4th St Brooklyn NY 11223",
    "addr:housenumber":"2418",
    "addr:postcode":"11223",
    "addr:street":"E 4Th St",
    "iso:country":"US",
    "sg:address":"2418 E 4th St",
    "sg:city":"Brooklyn",
    "sg:classifiers":[
        {
            "category":"Building & Trades",
            "subcategory":"Construction",
            "type":"Services"
        }
    ],
    "sg:phone":"+1 718 336 7030",
    "sg:postcode":"11223",
    "sg:province":"NY",
    "sg:tags":[
        "house"
    ],
    "wof:name":"Alex K Construction Corp",
    "wof:placetype":"venue"
},
  "geometry": {"coordinates":[-73.966669,40.591485],"type":"Point"}
}