{
  "type": "Feature",
  "properties": {
    "addr:full":"114 Kenmare St New York NY 10012",
    "addr:housenumber":"114",
    "addr:postcode":"10012",
    "addr:street":"Kenmare St",
    "iso:country":"US",
    "sg:address":"114 Kenmare St",
    "sg:city":"New York",
    "sg:classifiers":[
        {
            "category":"Restaurant",
            "type":"Food & Drink"
        }
    ],
    "sg:phone":"+1 646 613 7100",
    "sg:postcode":"10012",
    "sg:province":"NY",
    "sg:tags":[
        "mexican"
    ],
    "sg:website":"www.esquinanyc.com",
    "wof:name":"La Esquina Corner Deli",
    "wof:placetype":"venue"
},
  "geometry": {"coordinates":[-73.997641,40.721502],"type":"Point"}
}