{
  "type": "Feature",
  "properties": {
    "addr:full":"37 Surrey Cir Shirley NY 11967",
    "addr:housenumber":"37",
    "addr:postcode":"11967",
    "addr:street":"Surrey Cir",
    "iso:country":"US",
    "sg:address":"37 Surrey Cir",
    "sg:city":"Shirley",
    "sg:classifiers":[
        {
            "category":"Professional",
            "type":"Services"
        }
    ],
    "sg:phone":"+1 631 395 0931",
    "sg:postcode":"11967",
    "sg:province":"NY",
    "sg:tags":[
        "establishment"
    ],
    "wof:name":"A Q Enterprises",
    "wof:placetype":"venue"
},
  "geometry": {"coordinates":[-72.86628899999999,40.796823],"type":"Point"}
}