{
  "type": "Feature",
  "properties": {
    "iso:country":"US",
    "sg:address":"58 State Hwy 59",
    "sg:city":"Nanuet",
    "sg:classifiers":[
        {
            "category":"Utilities",
            "subcategory":"Electric",
            "type":"Services"
        }
    ],
    "sg:phone":"+1 845 627 3232",
    "sg:postcode":"10954",
    "sg:province":"NY",
    "sg:tags":[
        "company"
    ],
    "wof:name":"Rockland Electric Co",
    "wof:placetype":"venue"
},
  "geometry": {"coordinates":[-74.01030799999999,41.096592],"type":"Point"}
}