{
  "type": "Feature",
  "properties": {
    "addr:full":"121 W 20th St New York NY 10011",
    "addr:housenumber":"121",
    "addr:postcode":"10011",
    "addr:street":"W 20Th St",
    "iso:country":"US",
    "sg:address":"121 W 20th St",
    "sg:city":"New York",
    "sg:classifiers":[
        {
            "category":"Professional",
            "type":"Services"
        }
    ],
    "sg:phone":"+1 212 242 1473",
    "sg:postcode":"10011",
    "sg:province":"NY",
    "sg:tags":[
        "establishment"
    ],
    "wof:name":"Franklin Trust",
    "wof:placetype":"venue"
},
  "geometry": {"coordinates":[-73.996531,40.742049],"type":"Point"}
}