{
  "type": "Feature",
  "properties": {
    "addr:full":"18 43rd St Astoria NY 11105",
    "addr:housenumber":"18",
    "addr:postcode":"11105",
    "addr:street":"43Rd St",
    "iso:country":"US",
    "sg:address":"18 43rd St",
    "sg:city":"Astoria",
    "sg:classifiers":[
        {
            "category":"Retail",
            "subcategory":"Repair Shop",
            "type":"Services"
        }
    ],
    "sg:phone":"+1   ",
    "sg:postcode":"11105",
    "sg:province":"NY",
    "sg:tags":[
        "technical",
        "support"
    ],
    "wof:name":"Metropolitan Facilities Svc",
    "wof:placetype":"venue"
},
  "geometry": {"coordinates":[-73.90034799999999,40.774231],"type":"Point"}
}