{
  "type": "Feature",
  "properties": {
    "addr:full":"5 Block Blvd Massapequa Park NY 11762",
    "addr:housenumber":"5",
    "addr:postcode":"11762",
    "addr:street":"Block Blvd",
    "iso:country":"US",
    "sg:address":"5 Block Blvd",
    "sg:city":"Massapequa Park",
    "sg:classifiers":[
        {
            "category":"Health Services",
            "subcategory":"Doctor",
            "type":"Services"
        }
    ],
    "sg:phone":"+1 516 798 0401",
    "sg:postcode":"11762",
    "sg:province":"NY",
    "sg:tags":[
        "dentist"
    ],
    "wof:name":"Allan Mohr DDS",
    "wof:placetype":"venue"
},
  "geometry": {"coordinates":[-73.44494,40.667238],"type":"Point"}
}