{
  "type": "Feature",
  "properties": {
    "iso:country":"US",
    "sg:address":"4611 18th Ave",
    "sg:city":"Brooklyn",
    "sg:classifiers":[
        {
            "category":"Real Estate",
            "subcategory":"Real Estate Agent",
            "type":"Services"
        }
    ],
    "sg:phone":"+1 718 930 7422",
    "sg:postcode":"11204",
    "sg:province":"NY",
    "wof:name":"Hatzlucha Management LLC",
    "wof:placetype":"venue"
},
  "geometry": {"coordinates":[-73.97975599999999,40.629429],"type":"Point"}
}