{
  "type": "Feature",
  "properties": {
    "addr:full":"5109 Ave D Brooklyn NY 11203",
    "addr:housenumber":"5109",
    "addr:postcode":"11203",
    "addr:street":"Ave D",
    "iso:country":"US",
    "sg:address":"5109 Ave D",
    "sg:city":"Brooklyn",
    "sg:classifiers":[
        {
            "category":"Real Estate",
            "subcategory":"Architect",
            "type":"Services"
        }
    ],
    "sg:phone":"+1 718 251 1000",
    "sg:postcode":"11203",
    "sg:province":"NY",
    "wof:name":"Arch Auto Parts",
    "wof:placetype":"venue"
},
  "geometry": {"coordinates":[-73.92748,40.642323],"type":"Point"}
}