{
  "type": "Feature",
  "properties": {
    "addr:full":"230 Park Ave New York NY 10169",
    "addr:housenumber":"230",
    "addr:postcode":"10169",
    "addr:street":"Park Ave",
    "iso:country":"US",
    "sg:address":"230 Park Ave",
    "sg:city":"New York",
    "sg:classifiers":[
        {
            "category":"Banks & Credit Unions",
            "subcategory":"Investment Brokerage",
            "type":"Services"
        }
    ],
    "sg:phone":"+1 212 286 3500",
    "sg:postcode":"10169",
    "sg:province":"NY",
    "sg:tags":[
        "advisory",
        "financial"
    ],
    "wof:name":"Criterion Research Group LLC",
    "wof:placetype":"venue"
},
  "geometry": {"coordinates":[-73.97599099999999,40.754508],"type":"Point"}
}