{
  "type": "Feature",
  "properties": {
    "iso:country":"US",
    "sg:address":"756 Pre Emption Rd",
    "sg:city":"Geneva",
    "sg:classifiers":[
        {
            "category":"Organizations",
            "subcategory":"Non-profit Organization",
            "type":"Services"
        }
    ],
    "sg:phone":"+1 315 789 9821",
    "sg:postcode":"14456",
    "sg:province":"NY",
    "sg:website":"www.flvns.org",
    "wof:name":"Finger Lakes Visiting Nurse",
    "wof:placetype":"venue"
},
  "geometry": {"coordinates":[-77.01108600000001,42.865706],"type":"Point"}
}