{
  "type": "Feature",
  "properties": {
    "addr:full":"350 5th Ave New York NY 10001",
    "addr:housenumber":"350",
    "addr:postcode":"10001",
    "addr:street":"5Th Ave",
    "iso:country":"US",
    "sg:address":"350 5th Ave",
    "sg:city":"New York",
    "sg:classifiers":[
        {
            "category":"Professional",
            "subcategory":"Lawyer & Legal Services",
            "type":"Services"
        }
    ],
    "sg:phone":"+1 212 244 4187",
    "sg:postcode":"10001",
    "sg:province":"NY",
    "sg:tags":[
        "litigation",
        "personal",
        "injury"
    ],
    "wof:name":"Weingrad & Weingrad",
    "wof:placetype":"venue"
},
  "geometry": {"coordinates":[-73.984959,40.74807],"type":"Point"}
}