{
  "type": "Feature",
  "properties": {
    "iso:country":"US",
    "sg:address":"4801 W Genesee St",
    "sg:city":"Syracuse",
    "sg:classifiers":[
        {
            "category":"Organizations",
            "subcategory":"Religious Organization",
            "type":"Services"
        }
    ],
    "sg:phone":"+1 315 487 8521",
    "sg:postcode":"13219",
    "sg:province":"NY",
    "wof:name":"Fairmount Community Church",
    "wof:placetype":"venue"
},
  "geometry": {"coordinates":[-76.249971,43.043786],"type":"Point"}
}