{
  "type": "Feature",
  "properties": {
    "iso:country":"US",
    "sg:address":"23707 129th Ave",
    "sg:city":"Rosedale",
    "sg:classifiers":[
        {
            "category":"Real Estate",
            "subcategory":"Real Estate Services",
            "type":"Services"
        },
        {
            "category":"Real Estate",
            "subcategory":"Real Estate Agent",
            "type":"Services"
        }
    ],
    "sg:phone":"+1 718 525 3100",
    "sg:postcode":"11422",
    "sg:province":"NY",
    "sg:tags":[
        "buyer",
        "property",
        "management",
        "broker"
    ],
    "wof:name":"Our Place Realty",
    "wof:placetype":"venue"
},
  "geometry": {"coordinates":[-73.73018999999999,40.680372],"type":"Point"}
}