{
  "type": "Feature",
  "properties": {
    "iso:country":"US",
    "sg:address":"305 Main St",
    "sg:city":"Goshen",
    "sg:classifiers":[
        {
            "category":"Health Services",
            "subcategory":"Doctor",
            "type":"Services"
        }
    ],
    "sg:phone":"+1 845 294 4241",
    "sg:postcode":"10924",
    "sg:province":"NY",
    "wof:name":"Rosenfeld David",
    "wof:placetype":"venue"
},
  "geometry": {"coordinates":[-74.31613,41.407443],"type":"Point"}
}