{
  "type": "Feature",
  "properties": {
    "addr:full":"516 W 36 St New York NY 10018",
    "addr:housenumber":"516",
    "addr:postcode":"10018",
    "addr:street":"W 36 St",
    "iso:country":"US",
    "sg:address":"516 W 36 St",
    "sg:city":"New York",
    "sg:classifiers":[
        {
            "category":"Manufacturing",
            "subcategory":"Printing",
            "type":"Manufacturing & Wholesale Goods"
        }
    ],
    "sg:phone":"+1 212 947 6036",
    "sg:postcode":"10018",
    "sg:province":"NY",
    "sg:tags":[
        "printer"
    ],
    "wof:name":"Communigraphic Services",
    "wof:placetype":"venue"
},
  "geometry": {"coordinates":[-73.998955,40.755953],"type":"Point"}
}