{
  "type": "Feature",
  "properties": {
    "addr:full":"310 Walton Ave Bronx NY 10451",
    "addr:housenumber":"310",
    "addr:postcode":"10451",
    "addr:street":"Walton Ave",
    "iso:country":"US",
    "sg:address":"310 Walton Ave",
    "sg:city":"Bronx",
    "sg:classifiers":[
        {
            "category":"Retail",
            "subcategory":"Portrait Studio",
            "type":"Services"
        },
        {
            "category":"Professional",
            "subcategory":"Art Services",
            "type":"Services"
        }
    ],
    "sg:phone":"+1 646 670 4942",
    "sg:postcode":"10451",
    "sg:province":"NY",
    "sg:tags":[
        "photographer",
        "photography",
        "store"
    ],
    "wof:name":"Memories Photo Studio",
    "wof:placetype":"venue"
},
  "geometry": {"coordinates":[-73.929642,40.814992],"type":"Point"}
}