{
  "type": "Feature",
  "properties": {
    "iso:country":"US",
    "sg:address":"7824 Anadale Ln",
    "sg:city":"Liverpool",
    "sg:classifiers":[
        {
            "category":"Professional",
            "type":"Services"
        }
    ],
    "sg:phone":"+1   ",
    "sg:postcode":"13090",
    "sg:province":"NY",
    "wof:name":"Abbtech",
    "wof:placetype":"venue"
},
  "geometry": {"coordinates":[-76.18266300000001,43.149242],"type":"Point"}
}