{
  "type": "Feature",
  "properties": {
    "addr:full":"81 Burdick Hill Rd Ithaca NY 14850",
    "addr:housenumber":"81",
    "addr:postcode":"14850",
    "addr:street":"Burdick Hill Rd",
    "iso:country":"US",
    "sg:address":"81 Burdick Hill Rd",
    "sg:city":"Ithaca",
    "sg:classifiers":[
        {
            "category":"Organizations",
            "subcategory":"Community Association",
            "type":"Services"
        }
    ],
    "sg:phone":"+1   ",
    "sg:postcode":"14850",
    "sg:province":"NY",
    "wof:name":"New York Federation of Mu",
    "wof:placetype":"venue"
},
  "geometry": {"coordinates":[-76.494288,42.49817],"type":"Point"}
}