{
  "type": "Feature",
  "properties": {
    "iso:country":"US",
    "sg:address":"506 6th Ave",
    "sg:city":"Brooklyn",
    "sg:classifiers":[
        {
            "category":"Health Services",
            "subcategory":"Doctor",
            "type":"Services"
        },
        {
            "category":"Health Services",
            "subcategory":"Hospital",
            "type":"Services"
        }
    ],
    "sg:phone":"+1 718 369 8000",
    "sg:postcode":"11215",
    "sg:province":"NY",
    "sg:tags":[
        "cardiologist"
    ],
    "sg:website":"www.nym.org",
    "wof:name":"New York Methodist Hospital",
    "wof:placetype":"venue"
},
  "geometry": {"coordinates":[-73.98606700000001,40.665718],"type":"Point"}
}