{
  "type": "Feature",
  "properties": {
    "addr:full":"54 Newel St Brooklyn NY 11222",
    "addr:housenumber":"54",
    "addr:postcode":"11222",
    "addr:street":"Newel St",
    "iso:country":"US",
    "sg:address":"54 Newel St",
    "sg:city":"Brooklyn",
    "sg:classifiers":[
        {
            "category":"Professional",
            "subcategory":"Advertising",
            "type":"Services"
        }
    ],
    "sg:phone":"+1 718 609 0094",
    "sg:postcode":"11222",
    "sg:province":"NY",
    "wof:name":"PROCKSTARS.COM",
    "wof:placetype":"venue"
},
  "geometry": {"coordinates":[-73.94669,40.723368],"type":"Point"}
}