{
  "type": "Feature",
  "properties": {
    "addr:full":"57 Stuyvesant Rd Pittsford NY 14534",
    "addr:housenumber":"57",
    "addr:postcode":"14534",
    "addr:street":"Stuyvesant Rd",
    "iso:country":"US",
    "sg:address":"57 Stuyvesant Rd",
    "sg:city":"Pittsford",
    "sg:classifiers":[
        {
            "category":"Arts & Performance",
            "subcategory":"Theater",
            "type":"Entertainment"
        }
    ],
    "sg:phone":"+1 585 381 2090",
    "sg:postcode":"14534",
    "sg:province":"NY",
    "sg:tags":[
        "live",
        "music"
    ],
    "wof:name":"All Around Sound",
    "wof:placetype":"venue"
},
  "geometry": {"coordinates":[-77.509175,43.063361],"type":"Point"}
}