{
  "type": "Feature",
  "properties": {
    "addr:full":"310 Northern Lights Plz Syracuse NY 13212",
    "addr:housenumber":"310",
    "addr:postcode":"13212",
    "addr:street":"Northern Lights Plz",
    "iso:country":"US",
    "sg:address":"310 Northern Lights Plz",
    "sg:city":"Syracuse",
    "sg:classifiers":[
        {
            "category":"Shopping",
            "type":"Retail Goods"
        }
    ],
    "sg:phone":"+1 315 454 3949",
    "sg:postcode":"13212",
    "sg:province":"NY",
    "sg:tags":[
        "pet",
        "shop"
    ],
    "wof:name":"PETCO",
    "wof:placetype":"venue"
},
  "geometry": {"coordinates":[-76.14299800000001,43.11042],"type":"Point"}
}