{
  "type": "Feature",
  "properties": {
    "iso:country":"US",
    "sg:address":"1 Monarch Dr",
    "sg:city":"Fairport",
    "sg:classifiers":[
        {
            "category":"Building & Trades",
            "subcategory":"Cleaning & Sanitation",
            "type":"Services"
        }
    ],
    "sg:phone":"+1 585 388 8800",
    "sg:postcode":"14450",
    "sg:province":"NY",
    "sg:tags":[
        "house"
    ],
    "wof:name":"A & F Cleaning",
    "wof:placetype":"venue"
},
  "geometry": {"coordinates":[-77.39375,43.069641],"type":"Point"}
}