{
  "type": "Feature",
  "properties": {
    "iso:country":"US",
    "sg:address":"41 Greene St",
    "sg:city":"New York",
    "sg:classifiers":[
        {
            "category":"Professional",
            "type":"Services"
        }
    ],
    "sg:phone":"+1   ",
    "sg:postcode":"10013",
    "sg:province":"NY",
    "wof:name":"Artist",
    "wof:placetype":"venue"
},
  "geometry": {"coordinates":[-74.001688,40.722257],"type":"Point"}
}