{
  "type": "Feature",
  "properties": {
    "addr:full":"130 W 57 St New York NY 10019",
    "addr:housenumber":"130",
    "addr:postcode":"10019",
    "addr:street":"W 57 St",
    "iso:country":"US",
    "sg:address":"130 W 57 St",
    "sg:city":"New York",
    "sg:classifiers":[
        {
            "category":"Shopping",
            "subcategory":"Clothing, Apparel, & Fashions",
            "type":"Retail Goods"
        }
    ],
    "sg:phone":"+1   ",
    "sg:postcode":"10019",
    "sg:province":"NY",
    "wof:name":"Loutie For Men",
    "wof:placetype":"venue"
},
  "geometry": {"coordinates":[-73.97899700000001,40.764856],"type":"Point"}
}