{
  "type": "Feature",
  "properties": {
    "addr:full":"2432 Grand Concourse Bronx NY 10458",
    "addr:housenumber":"2432",
    "addr:postcode":"10458",
    "addr:street":"Grand Concourse",
    "iso:country":"US",
    "sg:address":"2432 Grand Concourse",
    "sg:city":"Bronx",
    "sg:classifiers":[
        {
            "category":"Government",
            "subcategory":"Office",
            "type":"Public Place"
        }
    ],
    "sg:phone":"+1 718 367 2450",
    "sg:postcode":"10458",
    "sg:province":"NY",
    "sg:tags":[
        "administrative",
        "program",
        "health"
    ],
    "wof:name":"Health New York Department",
    "wof:placetype":"venue"
},
  "geometry": {"coordinates":[-73.89779,40.861],"type":"Point"}
}