{
  "type": "Feature",
  "properties": {
    "addr:full":"14 Hoefler Ave Ilion NY 13357",
    "addr:housenumber":"14",
    "addr:postcode":"13357",
    "addr:street":"Hoefler Ave",
    "iso:country":"US",
    "sg:address":"14 Hoefler Ave",
    "sg:city":"Ilion",
    "sg:classifiers":[
        {
            "category":"Manufacturing",
            "subcategory":"Metals",
            "type":"Manufacturing & Wholesale Goods"
        }
    ],
    "sg:phone":"+1 315 895 3200",
    "sg:postcode":"13357",
    "sg:province":"NY",
    "sg:tags":[
        "firearm"
    ],
    "sg:website":"www.remington.com",
    "wof:name":"Remington Arms Co",
    "wof:placetype":"venue"
},
  "geometry": {"coordinates":[-75.032347,43.012985],"type":"Point"}
}