{
  "type": "Feature",
  "properties": {
    "iso:country":"US",
    "sg:address":"111 Cherry Valley Ave",
    "sg:city":"Garden City",
    "sg:classifiers":[
        {
            "category":"Organizations",
            "subcategory":"Community Association",
            "type":"Services"
        }
    ],
    "sg:phone":"+1   ",
    "sg:postcode":"11530",
    "sg:province":"NY",
    "wof:name":"Womans Club of Garden City",
    "wof:placetype":"venue"
},
  "geometry": {"coordinates":[-73.642349,40.725819],"type":"Point"}
}