{
  "type": "Feature",
  "properties": {
    "iso:country":"US",
    "sg:address":"4109 13th Ave",
    "sg:city":"Brooklyn",
    "sg:classifiers":[
        {
            "category":"Food & Beverages",
            "subcategory":"Liquor & Beverages",
            "type":"Retail Goods"
        }
    ],
    "sg:phone":"+1 718 435 5577",
    "sg:postcode":"11219",
    "sg:province":"NY",
    "sg:tags":[
        "beer",
        "spirit",
        "wine"
    ],
    "wof:name":"H & H Wine & Liquors Co",
    "wof:placetype":"venue"
},
  "geometry": {"coordinates":[-73.987602,40.639198],"type":"Point"}
}