{
  "type": "Feature",
  "properties": {
    "addr:full":"Fulton Stall Market Fulton and South Streets New York NY 10038",
    "addr:postcode":"10038",
    "addr:street":"Streets",
    "iso:country":"US",
    "sg:address":"Fulton Stall Market Fulton and South Streets",
    "sg:city":"New York",
    "sg:classifiers":[
        {
            "category":"Coffee & Tea",
            "type":"Food & Drink"
        }
    ],
    "sg:postcode":"10038",
    "sg:province":"NY",
    "wof:name":"Yummy Coffee",
    "wof:placetype":"venue"
},
  "geometry": {"coordinates":[-74.00318900000001,40.706261],"type":"Point"}
}