{
  "type": "Feature",
  "properties": {
    "iso:country":"US",
    "sg:address":"492 Metropolitan Ave",
    "sg:city":"Brooklyn",
    "sg:classifiers":[
        {
            "category":"Manufacturing",
            "subcategory":"Rubber & Plastics",
            "type":"Manufacturing & Wholesale Goods"
        }
    ],
    "sg:phone":"+1   ",
    "sg:postcode":"11211",
    "sg:province":"NY",
    "sg:tags":[
        "to",
        "toy",
        "mfg"
    ],
    "wof:name":"Flowering Bears",
    "wof:placetype":"venue"
},
  "geometry": {"coordinates":[-73.952386,40.713998],"type":"Point"}
}