{
  "type": "Feature",
  "properties": {
    "iso:country":"US",
    "sg:address":"300 Executive Blvd",
    "sg:city":"Elmsford",
    "sg:classifiers":[
        {
            "category":"Sports & Exercise",
            "subcategory":"Sports Center",
            "type":"Entertainment"
        },
        {
            "category":"Wholesale",
            "subcategory":"Construction Materials",
            "type":"Manufacturing & Wholesale Goods"
        },
        {
            "category":"Manufacturing",
            "subcategory":"Textiles",
            "type":"Manufacturing & Wholesale Goods"
        },
        {
            "category":"Community Center",
            "type":"Public Place"
        }
    ],
    "sg:phone":"+1 914 345 3370",
    "sg:postcode":"10523",
    "sg:province":"NY",
    "sg:tags":[
        "recreation",
        "wool",
        "cage",
        "waste-cotton",
        "batting"
    ],
    "wof:name":"Frozen Ropes",
    "wof:placetype":"venue"
},
  "geometry": {"coordinates":[-73.807591,41.070323],"type":"Point"}
}