{
  "type": "Feature",
  "properties": {
    "iso:country":"US",
    "sg:address":"432 Main St.",
    "sg:city":"Armonk",
    "sg:classifiers":[
        {
            "category":"Education",
            "subcategory":"Special Training",
            "type":"Public Place"
        }
    ],
    "sg:phone":"+1 914 219 5777",
    "sg:postcode":"10504",
    "sg:province":"NY",
    "sg:tags":[
        "educational",
        "tutoring"
    ],
    "wof:name":"E. Nopi Learning Center",
    "wof:placetype":"venue"
},
  "geometry": {"coordinates":[-73.713611,41.127693],"type":"Point"}
}