{
  "type": "Feature",
  "properties": {
    "iso:country":"US",
    "sg:address":"525 Warren St",
    "sg:city":"Hudson",
    "sg:classifiers":[
        {
            "category":"Shopping",
            "subcategory":"Used Merchandise",
            "type":"Retail Goods"
        }
    ],
    "sg:phone":"+1 518 828 1081",
    "sg:postcode":"12534",
    "sg:province":"NY",
    "sg:tags":[
        "durable"
    ],
    "wof:name":"Watnot Shop",
    "wof:placetype":"venue"
},
  "geometry": {"coordinates":[-73.786288,42.24916],"type":"Point"}
}