{
  "type": "Feature",
  "properties": {
    "iso:country":"US",
    "sg:address":"200 West End Avenue",
    "sg:city":"Manhattan",
    "sg:classifiers":[
        {
            "category":"Real Estate",
            "subcategory":"Real Estate Operator",
            "type":"Services"
        }
    ],
    "sg:postcode":"10023",
    "sg:province":"NY",
    "sg:tags":[
        "apartment"
    ],
    "wof:name":"200 West End Avenue",
    "wof:placetype":"venue"
},
  "geometry": {"coordinates":[-73.98538600000001,40.777977],"type":"Point"}
}