{
  "type": "Feature",
  "properties": {
    "iso:country":"US",
    "sg:address":"405 Park Ave",
    "sg:city":"New York",
    "sg:classifiers":[
        {
            "category":"Organizations",
            "subcategory":"Religious Organization",
            "type":"Services"
        }
    ],
    "sg:phone":"+1 917 368 8138",
    "sg:postcode":"10022",
    "sg:province":"NY",
    "sg:tags":[
        "church"
    ],
    "wof:name":"International Federation",
    "wof:placetype":"venue"
},
  "geometry": {"coordinates":[-73.97167399999999,40.760197],"type":"Point"}
}