{
  "type": "Feature",
  "properties": {
    "addr:full":"1178 Wantagh Ave Wantagh NY 11793",
    "addr:housenumber":"1178",
    "addr:postcode":"11793",
    "addr:street":"Wantagh Ave",
    "iso:country":"US",
    "sg:address":"1178 Wantagh Ave",
    "sg:city":"Wantagh",
    "sg:classifiers":[
        {
            "category":"Retail",
            "subcategory":"Photofinishing",
            "type":"Services"
        },
        {
            "category":"Retail",
            "subcategory":"Portrait Studio",
            "type":"Services"
        },
        {
            "category":"Shopping",
            "subcategory":"Pharmacy",
            "type":"Retail Goods"
        }
    ],
    "sg:phone":"+1 516 783 5621",
    "sg:postcode":"11793",
    "sg:province":"NY",
    "sg:tags":[
        "supply",
        "photo",
        "photography",
        "aid",
        "finishing",
        "drugstore",
        "store",
        "first"
    ],
    "sg:website":"www.cvs.com",
    "wof:name":"CVS pharmacy",
    "wof:placetype":"venue"
},
  "geometry": {"coordinates":[-73.50776500000001,40.694054],"type":"Point"}
}