{
  "type": "Feature",
  "properties": {
    "iso:country":"US",
    "sg:address":"33 Thomas St",
    "sg:city":"New York",
    "sg:classifiers":[
        {
            "category":"Banks & Credit Unions",
            "subcategory":"Bank",
            "type":"Services"
        }
    ],
    "sg:phone":"+1 212 267 1870",
    "sg:postcode":"10007",
    "sg:province":"NY",
    "wof:name":"Chase Manhattan Bank",
    "wof:placetype":"venue"
},
  "geometry": {"coordinates":[-74.00667300000001,40.716532],"type":"Point"}
}