{
  "type": "Feature",
  "properties": {
    "iso:country":"US",
    "sg:address":"2226 Boston Post Rd",
    "sg:city":"Larchmont",
    "sg:classifiers":[
        {
            "category":"Building & Trades",
            "subcategory":"Construction",
            "type":"Services"
        }
    ],
    "sg:phone":"+1 914 834 2571",
    "sg:postcode":"10538",
    "sg:province":"NY",
    "sg:tags":[
        "tile-contractors"
    ],
    "wof:name":"Georges Tiles Inc",
    "wof:placetype":"venue"
},
  "geometry": {"coordinates":[-73.755379,40.925629],"type":"Point"}
}