{
  "type": "Feature",
  "properties": {
    "iso:country":"US",
    "sg:address":"20 W 20th Street",
    "sg:city":"New York",
    "sg:classifiers":[
        {
            "category":"Education",
            "subcategory":"Special Training",
            "type":"Public Place"
        }
    ],
    "sg:phone":"+1 212 352 2037",
    "sg:postcode":"10011",
    "sg:province":"NY",
    "sg:tags":[
        "school",
        "specialty"
    ],
    "wof:name":"Pierre Finkelstein Institute of Decorative Painting",
    "wof:placetype":"venue"
},
  "geometry": {"coordinates":[-73.99975499999999,40.741089],"type":"Point"}
}