{
  "type": "Feature",
  "properties": {
    "addr:full":"5907 Roosevelt Ave Woodside NY 11377",
    "addr:housenumber":"5907",
    "addr:postcode":"11377",
    "addr:street":"Roosevelt Ave",
    "iso:country":"US",
    "sg:address":"5907 Roosevelt Ave",
    "sg:city":"Woodside",
    "sg:classifiers":[
        {
            "category":"Food & Beverages",
            "subcategory":"Meat & Fish",
            "type":"Retail Goods"
        }
    ],
    "sg:phone":"+1 718 457 7343",
    "sg:postcode":"11377",
    "sg:province":"NY",
    "sg:tags":[
        "shop"
    ],
    "wof:name":"C & J Prime Meat Market",
    "wof:placetype":"venue"
},
  "geometry": {"coordinates":[-73.905602,40.745499],"type":"Point"}
}