{
  "type": "Feature",
  "properties": {
    "addr:full":"11 Bernard Way Saranac Lake NY 12901",
    "addr:housenumber":"11",
    "addr:postcode":"12901",
    "addr:street":"Bernard Way",
    "iso:country":"US",
    "sg:address":"11 Bernard Way",
    "sg:city":"Saranac Lake",
    "sg:classifiers":[
        {
            "category":"Government",
            "subcategory":"Office",
            "type":"Public Place"
        }
    ],
    "sg:phone":"+1 518 891 0015",
    "sg:postcode":"12901",
    "sg:province":"NY",
    "wof:name":"New York Vocational & Ed Svc",
    "wof:placetype":"venue"
},
  "geometry": {"coordinates":[-73.445325,44.672836],"type":"Point"}
}