{
  "type": "Feature",
  "properties": {
    "addr:full":"115 Brown Station Rd Olivebridge NY 12461",
    "addr:housenumber":"115",
    "addr:postcode":"12461",
    "addr:street":"Brown Station Rd",
    "iso:country":"US",
    "sg:address":"115 Brown Station Rd",
    "sg:city":"Olivebridge",
    "sg:classifiers":[
        {
            "category":"Government",
            "subcategory":"Fire Station",
            "type":"Public Place"
        }
    ],
    "sg:phone":"+1 845 657 8271",
    "sg:postcode":"12461",
    "sg:province":"NY",
    "sg:tags":[
        "protection"
    ],
    "wof:name":"Zone 3 Convention Committee",
    "wof:placetype":"venue"
},
  "geometry": {"coordinates":[-74.195286,41.945245],"type":"Point"}
}