{
  "type": "Feature",
  "properties": {
    "addr:full":"64 S Main St Moravia NY 13118",
    "addr:housenumber":"64",
    "addr:postcode":"13118",
    "addr:street":"S Main St",
    "iso:country":"US",
    "sg:address":"64 S Main St",
    "sg:city":"Moravia",
    "sg:classifiers":[
        {
            "category":"Organizations",
            "subcategory":"Community Association",
            "type":"Services"
        }
    ],
    "sg:phone":"+1   ",
    "sg:postcode":"13118",
    "sg:province":"NY",
    "wof:name":"Masonic Club",
    "wof:placetype":"venue"
},
  "geometry": {"coordinates":[-76.420832,42.705105],"type":"Point"}
}