{
  "type": "Feature",
  "properties": {
    "addr:full":"95 Public Sq Watertown NY 13601",
    "addr:housenumber":"95",
    "addr:postcode":"13601",
    "addr:street":"Public Sq",
    "iso:country":"US",
    "sg:address":"95 Public Sq",
    "sg:city":"Watertown",
    "sg:classifiers":[
        {
            "category":"Taxi",
            "type":"Transportation"
        }
    ],
    "sg:phone":"+1 315 782 2121",
    "sg:postcode":"13601",
    "sg:province":"NY",
    "sg:tags":[
        "taxicab"
    ],
    "wof:name":"Yellow Cab",
    "wof:placetype":"venue"
},
  "geometry": {"coordinates":[-75.90992199999999,43.974841],"type":"Point"}
}