{
  "type": "Feature",
  "properties": {
    "addr:full":"683 Knickerbocker Ave Brooklyn NY 11221",
    "addr:housenumber":"683",
    "addr:postcode":"11221",
    "addr:street":"Knickerbocker Ave",
    "iso:country":"US",
    "sg:address":"683 Knickerbocker Ave",
    "sg:city":"Brooklyn",
    "sg:classifiers":[
        {
            "category":"Personal",
            "type":"Services"
        }
    ],
    "sg:phone":"+1 347 413 6882",
    "sg:postcode":"11221",
    "sg:province":"NY",
    "sg:tags":[
        "party",
        "planning",
        "event"
    ],
    "wof:name":"Isamar Party Supply",
    "wof:placetype":"venue"
},
  "geometry": {"coordinates":[-73.911058,40.694828],"type":"Point"}
}