{
  "type": "Feature",
  "properties": {
    "iso:country":"US",
    "sg:address":"175 W 12 St",
    "sg:city":"New York",
    "sg:classifiers":[
        {
            "category":"Real Estate",
            "subcategory":"Real Estate Operator",
            "type":"Services"
        }
    ],
    "sg:phone":"+1 212 929 3686",
    "sg:postcode":"10011",
    "sg:province":"NY",
    "sg:tags":[
        "condominium"
    ],
    "wof:name":"175 West 12 St Condo",
    "wof:placetype":"venue"
},
  "geometry": {"coordinates":[-73.99898399999999,40.736391],"type":"Point"}
}