{
  "type": "Feature",
  "properties": {
    "iso:country":"US",
    "sg:address":"5064 State Hwy 12",
    "sg:city":"Norwich",
    "sg:classifiers":[
        {
            "category":"Retail",
            "subcategory":"Auto Rental",
            "type":"Services"
        }
    ],
    "sg:phone":"+1 607 334 6412",
    "sg:postcode":"13815",
    "sg:province":"NY",
    "sg:tags":[
        "passenger",
        "car"
    ],
    "wof:name":"Goldens Rental LLC",
    "wof:placetype":"venue"
},
  "geometry": {"coordinates":[-75.528542,42.557809],"type":"Point"}
}