{
  "type": "Feature",
  "properties": {
    "iso:country":"US",
    "sg:address":"2617 Ocean Ave",
    "sg:city":"Seaford",
    "sg:classifiers":[
        {
            "category":"Building & Trades",
            "subcategory":"Construction",
            "type":"Services"
        }
    ],
    "sg:phone":"+1 516 785 2881",
    "sg:postcode":"11783",
    "sg:province":"NY",
    "sg:tags":[
        "house"
    ],
    "wof:name":"Clarke Contracting",
    "wof:placetype":"venue"
},
  "geometry": {"coordinates":[-73.49770599999999,40.657448],"type":"Point"}
}