{
  "type": "Feature",
  "properties": {
    "addr:full":"960 Morris Park Ave Bronx NY 10462",
    "addr:housenumber":"960",
    "addr:postcode":"10462",
    "addr:street":"Morris Park Ave",
    "iso:country":"US",
    "sg:address":"960 Morris Park Ave",
    "sg:city":"Bronx",
    "sg:classifiers":[
        {
            "category":"Health Services",
            "subcategory":"Doctor",
            "type":"Services"
        }
    ],
    "sg:phone":"+1 212 764 5464",
    "sg:postcode":"10462",
    "sg:province":"NY",
    "sg:tags":[
        "dentist"
    ],
    "wof:name":"212-Smiling",
    "wof:placetype":"venue"
},
  "geometry": {"coordinates":[-73.857377,40.847468],"type":"Point"}
}