{
  "type": "Feature",
  "properties": {
    "addr:full":"613 Johnson Ave Bohemia NY 11716",
    "addr:housenumber":"613",
    "addr:postcode":"11716",
    "addr:street":"Johnson Ave",
    "iso:country":"US",
    "sg:address":"613 Johnson Ave",
    "sg:city":"Bohemia",
    "sg:classifiers":[
        {
            "category":"Utilities",
            "subcategory":"Mobile Phone",
            "type":"Services"
        }
    ],
    "sg:phone":"+1   ",
    "sg:postcode":"11716",
    "sg:province":"NY",
    "sg:tags":[
        "communication",
        "radiotelephone"
    ],
    "sg:website":"www.arinc.com",
    "wof:name":"Aeronautical Radio Inc",
    "wof:placetype":"venue"
},
  "geometry": {"coordinates":[-73.09683,40.780355],"type":"Point"}
}