{
  "type": "Feature",
  "properties": {
    "addr:full":"735 Mace Ave Bronx NY 10467",
    "addr:housenumber":"735",
    "addr:postcode":"10467",
    "addr:street":"Mace Ave",
    "iso:country":"US",
    "sg:address":"735 Mace Ave",
    "sg:city":"Bronx",
    "sg:classifiers":[
        {
            "category":"Professional",
            "subcategory":"Management & Consulting",
            "type":"Services"
        }
    ],
    "sg:phone":"+1 718 652 5556",
    "sg:postcode":"10467",
    "sg:province":"NY",
    "wof:name":"Trc Inc",
    "wof:placetype":"venue"
},
  "geometry": {"coordinates":[-73.866412,40.863195],"type":"Point"}
}