{
  "type": "Feature",
  "properties": {
    "addr:full":"27 Main St Chester NY 10918",
    "addr:housenumber":"27",
    "addr:postcode":"10918",
    "addr:street":"Main St",
    "iso:country":"US",
    "sg:address":"27 Main St",
    "sg:city":"Chester",
    "sg:classifiers":[
        {
            "category":"Manufacturing",
            "subcategory":"Printing",
            "type":"Manufacturing & Wholesale Goods"
        }
    ],
    "sg:phone":"+1 845 469 5606",
    "sg:postcode":"10918",
    "sg:province":"NY",
    "sg:tags":[
        "printer"
    ],
    "wof:name":"Avalon Blueprint",
    "wof:placetype":"venue"
},
  "geometry": {"coordinates":[-74.271832,41.362254],"type":"Point"}
}