{
  "type": "Feature",
  "properties": {
    "addr:full":"1402 Augustina Ave Far Rockaway NY 11691",
    "addr:housenumber":"1402",
    "addr:postcode":"11691",
    "addr:street":"Augustina Ave",
    "iso:country":"US",
    "sg:address":"1402 Augustina Ave",
    "sg:city":"Far Rockaway",
    "sg:classifiers":[
        {
            "category":"Retail",
            "subcategory":"Auto Repair",
            "type":"Services"
        }
    ],
    "sg:phone":"+1 718 471 7059",
    "sg:postcode":"11691",
    "sg:province":"NY",
    "wof:name":"Arties Collision Corp",
    "wof:placetype":"venue"
},
  "geometry": {"coordinates":[-73.75140399999999,40.606899],"type":"Point"}
}