{
  "type": "Feature",
  "properties": {
    "iso:country":"US",
    "sg:address":"7 Anita Dr",
    "sg:city":"Sayville",
    "sg:classifiers":[
        {
            "category":"Cinema",
            "subcategory":"Movie Theater",
            "type":"Entertainment"
        }
    ],
    "sg:phone":"+1 631 669 2626",
    "sg:postcode":"11782",
    "sg:province":"NY",
    "sg:tags":[
        "motion",
        "picture"
    ],
    "wof:name":"West Islip Twin Cinema",
    "wof:placetype":"venue"
},
  "geometry": {"coordinates":[-73.090132,40.724408],"type":"Point"}
}