{
  "type": "Feature",
  "properties": {
    "iso:country":"US",
    "sg:address":"415 E 203rd St",
    "sg:city":"Bronx",
    "sg:classifiers":[
        {
            "category":"Government",
            "subcategory":"Office",
            "type":"Public Place"
        }
    ],
    "sg:phone":"+1 718 652 2192",
    "sg:postcode":"10467",
    "sg:province":"NY",
    "sg:tags":[
        "environmental",
        "protection"
    ],
    "wof:name":"Envirnmntal Cnsrvation NY Dept",
    "wof:placetype":"venue"
},
  "geometry": {"coordinates":[-73.877331,40.870594],"type":"Point"}
}