{
  "type": "Feature",
  "properties": {
    "iso:country":"US",
    "sg:address":"7302 Victor Mendon Rd",
    "sg:city":"Victor",
    "sg:classifiers":[
        {
            "category":"Building & Trades",
            "subcategory":"Construction",
            "type":"Services"
        }
    ],
    "sg:phone":"+1 585 924 8444",
    "sg:postcode":"14564",
    "sg:province":"NY",
    "sg:tags":[
        "house"
    ],
    "wof:name":"Jeffers Home Remodeling",
    "wof:placetype":"venue"
},
  "geometry": {"coordinates":[-77.43162700000001,42.995784],"type":"Point"}
}