{
  "type": "Feature",
  "properties": {
    "iso:country":"US",
    "sg:address":"12330 Upton Rd",
    "sg:city":"Red Creek",
    "sg:classifiers":[
        {
            "category":"Autos & Motor Vehicles",
            "subcategory":"Auto Supplies",
            "type":"Retail Goods"
        }
    ],
    "sg:phone":"+1   ",
    "sg:postcode":"13143",
    "sg:province":"NY",
    "wof:name":"Bakers Auto Parts",
    "wof:placetype":"venue"
},
  "geometry": {"coordinates":[-76.676315,43.208116],"type":"Point"}
}