{
  "type": "Feature",
  "properties": {
    "iso:country":"US",
    "sg:address":"3 Crescendoe Rd",
    "sg:city":"Johnstown",
    "sg:classifiers":[
        {
            "category":"Building & Trades",
            "subcategory":"Construction",
            "type":"Services"
        }
    ],
    "sg:phone":"+1 518 736 1159",
    "sg:postcode":"12095",
    "sg:province":"NY",
    "sg:tags":[
        "contractor"
    ],
    "wof:name":"Frenyea Siding",
    "wof:placetype":"venue"
},
  "geometry": {"coordinates":[-74.370693,43.012827],"type":"Point"}
}