{
  "type": "Feature",
  "properties": {
    "iso:country":"US",
    "sg:address":"226 E 54th St",
    "sg:city":"New York",
    "sg:classifiers":[
        {
            "category":"Building & Trades",
            "subcategory":"Cleaning & Sanitation",
            "type":"Services"
        },
        {
            "category":"Social Services",
            "subcategory":"Child Care",
            "type":"Services"
        },
        {
            "category":"Health Services",
            "subcategory":"Health Practitioner",
            "type":"Services"
        }
    ],
    "sg:phone":"+1 212 444 1313",
    "sg:postcode":"10022",
    "sg:province":"NY",
    "sg:tags":[
        "home",
        "day"
    ],
    "sg:website":"www.penelopespeople.com",
    "wof:name":"Penelope's People",
    "wof:placetype":"venue"
},
  "geometry": {"coordinates":[-73.967929,40.757782],"type":"Point"}
}