{
  "type": "Feature",
  "properties": {
    "iso:country":"US",
    "sg:address":"954 Quaker Rd",
    "sg:city":"Scottsville",
    "sg:classifiers":[
        {
            "category":"Professional",
            "subcategory":"Advertising",
            "type":"Services"
        }
    ],
    "sg:phone":"+1 585 889 5280",
    "sg:postcode":"14546",
    "sg:province":"NY",
    "sg:tags":[
        "mail",
        "direct"
    ],
    "wof:name":"Winross Direct",
    "wof:placetype":"venue"
},
  "geometry": {"coordinates":[-77.766879,43.006193],"type":"Point"}
}