{
  "type": "Feature",
  "properties": {
    "addr:full":"2000 Empire Blvd Ste 220 Webster NY 14580",
    "addr:housenumber":"2000",
    "addr:postcode":"14580",
    "addr:street":"Empire Blvd Ste 220",
    "iso:country":"US",
    "sg:address":"2000 Empire Blvd Ste 220",
    "sg:city":"Webster",
    "sg:phone":"+1 585 216 1080",
    "sg:postcode":"14580",
    "sg:province":"NY",
    "sg:website":"http://www.advancedhearingcenters.com",
    "wof:name":"Advanced Hearing Centers",
    "wof:placetype":"venue"
},
  "geometry": {"coordinates":[-77.501671,43.19408],"type":"Point"}
}