{
  "type": "Feature",
  "properties": {
    "iso:country":"US",
    "sg:address":"371 High St",
    "sg:city":"Victor",
    "sg:classifiers":[
        {
            "category":"Building & Trades",
            "subcategory":"Construction",
            "type":"Services"
        }
    ],
    "sg:phone":"+1 585 924 3278",
    "sg:postcode":"14564",
    "sg:province":"NY",
    "sg:tags":[
        "carpentry",
        "contractor"
    ],
    "wof:name":"Ken Spinelli Carpentry Inc",
    "wof:placetype":"venue"
},
  "geometry": {"coordinates":[-77.43364099999999,43.022648],"type":"Point"}
}