{
  "type": "Feature",
  "properties": {
    "iso:country":"US",
    "sg:address":"168 Ludlow St",
    "sg:city":"New York",
    "sg:classifiers":[
        {
            "category":"Professional",
            "type":"Services"
        }
    ],
    "sg:phone":"+1 646 654 1358",
    "sg:postcode":"10002",
    "sg:province":"NY",
    "sg:tags":[
        "establishment"
    ],
    "wof:name":"Lee & Co",
    "wof:placetype":"venue"
},
  "geometry": {"coordinates":[-73.987166,40.722182],"type":"Point"}
}