{
  "type": "Feature",
  "properties": {
    "iso:country":"US",
    "sg:address":"11 Commercial St",
    "sg:city":"Hicksville",
    "sg:classifiers":[
        {
            "category":"Shopping",
            "subcategory":"Bicycles & Sporting Goods",
            "type":"Retail Goods"
        }
    ],
    "sg:phone":"+1 516 933 2697",
    "sg:postcode":"11801",
    "sg:province":"NY",
    "sg:tags":[
        "equipment",
        "archery",
        "supply"
    ],
    "wof:name":"C & B Archery",
    "wof:placetype":"venue"
},
  "geometry": {"coordinates":[-73.50882799999999,40.760526],"type":"Point"}
}