{
  "type": "Feature",
  "properties": {
    "iso:country":"US",
    "sg:address":"39 Hammond Ln",
    "sg:city":"Plattsburgh",
    "sg:classifiers":[
        {
            "category":"Real Estate",
            "subcategory":"Real Estate Agent",
            "type":"Services"
        }
    ],
    "sg:phone":"+1 518 563 2031",
    "sg:postcode":"12901",
    "sg:province":"NY",
    "wof:name":"Welcome Home Realty",
    "wof:placetype":"venue"
},
  "geometry": {"coordinates":[-73.499949,44.694915],"type":"Point"}
}