{
  "type": "Feature",
  "properties": {
    "iso:country":"US",
    "sg:address":"261 Liberty St",
    "sg:city":"Newburgh",
    "sg:classifiers":[
        {
            "category":"Real Estate",
            "subcategory":"Real Estate Services",
            "type":"Services"
        },
        {
            "category":"Real Estate",
            "subcategory":"Real Estate Agent",
            "type":"Services"
        }
    ],
    "sg:phone":"+1 845 565 1290",
    "sg:postcode":"12550",
    "sg:province":"NY",
    "sg:tags":[
        "buyer",
        "property",
        "management",
        "broker"
    ],
    "sg:website":"www.sierra-properties.com",
    "wof:name":"Sierra Properties Inc",
    "wof:placetype":"venue"
},
  "geometry": {"coordinates":[-74.010696,41.505299],"type":"Point"}
}