{
  "type": "Feature",
  "properties": {
    "iso:country":"US",
    "sg:address":"1845 Emerson St",
    "sg:city":"Rochester",
    "sg:classifiers":[
        {
            "category":"Government",
            "subcategory":"Office",
            "type":"Public Place"
        }
    ],
    "sg:phone":"+1 585 277 1645",
    "sg:postcode":"14606",
    "sg:province":"NY",
    "wof:name":"Monroe County Tranfer Stn",
    "wof:placetype":"venue"
},
  "geometry": {"coordinates":[-77.67747,43.173894],"type":"Point"}
}