{
  "type": "Feature",
  "properties": {
    "iso:country":"US",
    "sg:address":"667 Madison Ave Fl 24",
    "sg:city":"New York",
    "sg:classifiers":[
        {
            "category":"Arts & Performance",
            "subcategory":"Art Gallery",
            "type":"Entertainment"
        }
    ],
    "sg:phone":"+1 212 813 9797",
    "sg:postcode":"10065",
    "sg:province":"NY",
    "wof:name":"Gotham Hospitality",
    "wof:placetype":"venue"
},
  "geometry": {"coordinates":[-73.97031,40.764508],"type":"Point"}
}