{
  "type": "Feature",
  "properties": {
    "iso:country":"US",
    "sg:address":"325 Route 100",
    "sg:city":"Somers",
    "sg:classifiers":[
        {
            "category":"Professional",
            "subcategory":"Accounting & Tax Preparation",
            "type":"Services"
        }
    ],
    "sg:phone":"+1 866 871 1040",
    "sg:postcode":"10589",
    "sg:province":"NY",
    "sg:tags":[
        "return",
        "preparation-business"
    ],
    "sg:website":"http://www.libertytax.com/",
    "wof:name":"Liberty Tax Service",
    "wof:placetype":"venue"
},
  "geometry": {"coordinates":[-73.694447,41.309677],"type":"Point"}
}