{
  "type": "Feature",
  "properties": {
    "iso:country":"US",
    "sg:address":"225 W 116th St",
    "sg:city":"New York",
    "sg:classifiers":[
        {
            "category":"Restaurant",
            "type":"Food & Drink"
        }
    ],
    "sg:menulink":"http://www.allmenus.com/ny/new-york/49097-sokhna-restaurant/menu/",
    "sg:phone":"+1 212 864 0081",
    "sg:postcode":"10026",
    "sg:province":"NY",
    "sg:tags":[
        "american"
    ],
    "wof:name":"Sokhna Restaurant",
    "wof:placetype":"venue"
},
  "geometry": {"coordinates":[-73.95394899999999,40.803824],"type":"Point"}
}