{
  "type": "Feature",
  "properties": {
    "iso:country":"US",
    "sg:address":"500 Balltown Rd",
    "sg:city":"Schenectady",
    "sg:classifiers":[
        {
            "category":"Government",
            "subcategory":"Office",
            "type":"Public Place"
        }
    ],
    "sg:phone":"+1 518 370 7400",
    "sg:postcode":"12304",
    "sg:province":"NY",
    "sg:tags":[
        "state",
        "resource"
    ],
    "wof:name":"Capital District DSO",
    "wof:placetype":"venue"
},
  "geometry": {"coordinates":[-73.89350399999999,42.777591],"type":"Point"}
}