{
  "type": "Feature",
  "properties": {
    "addr:full":"2071 Clinton St Buffalo NY 14206",
    "addr:housenumber":"2071",
    "addr:postcode":"14206",
    "addr:street":"Clinton St",
    "iso:country":"US",
    "sg:address":"2071 Clinton St",
    "sg:city":"Buffalo",
    "sg:classifiers":[
        {
            "category":"Sports & Exercise",
            "subcategory":"Bowling",
            "type":"Entertainment"
        }
    ],
    "sg:phone":"+1 716 822 5132",
    "sg:postcode":"14206",
    "sg:province":"NY",
    "sg:tags":[
        "alley",
        "pin",
        "ten"
    ],
    "sg:website":"www.townedgebowling.com",
    "wof:name":"Town Edge Bowling Center Inc",
    "wof:placetype":"venue"
},
  "geometry": {"coordinates":[-78.79969800000001,42.871799],"type":"Point"}
}