{
  "type": "Feature",
  "properties": {
    "addr:full":"6919 New Utrecht Avenue Brooklyn NY 11228",
    "addr:housenumber":"6919",
    "addr:postcode":"11228",
    "addr:street":"New Utrecht Avenue",
    "iso:country":"US",
    "sg:address":"6919 New Utrecht Avenue",
    "sg:city":"Brooklyn",
    "sg:classifiers":[
        {
            "category":"Bakery",
            "type":"Food & Drink"
        }
    ],
    "sg:phone":"+1 718 256 2626",
    "sg:postcode":"11228",
    "sg:province":"NY",
    "wof:name":"A & D Bakery",
    "wof:placetype":"venue"
},
  "geometry": {"coordinates":[-73.998643,40.619813],"type":"Point"}
}