{
  "type": "Feature",
  "properties": {
    "iso:country":"US",
    "sg:address":"57 W 38th St",
    "sg:city":"New York",
    "sg:classifiers":[
        {
            "category":"Wholesale",
            "subcategory":"Apparel",
            "type":"Manufacturing & Wholesale Goods"
        }
    ],
    "sg:phone":"+1   ",
    "sg:postcode":"10018",
    "sg:province":"NY",
    "sg:tags":[
        "clothing",
        "mfg"
    ],
    "wof:name":"Miss Milan Fashion LTD",
    "wof:placetype":"venue"
},
  "geometry": {"coordinates":[-73.984515,40.751607],"type":"Point"}
}