{
  "type": "Feature",
  "properties": {
    "iso:country":"US",
    "sg:address":"6419 Myrtle Avenue",
    "sg:city":"Glendale",
    "sg:classifiers":[
        {
            "category":"Professional",
            "subcategory":"Accounting & Tax Preparation",
            "type":"Services"
        }
    ],
    "sg:phone":"+1 718 366 1200",
    "sg:postcode":"11385",
    "sg:province":"NY",
    "sg:tags":[
        "accountant"
    ],
    "wof:name":"Bonventre & Kratz",
    "wof:placetype":"venue"
},
  "geometry": {"coordinates":[-73.891615,40.701127],"type":"Point"}
}