{
  "type": "Feature",
  "properties": {
    "addr:full":"62 Marine St Farmingdale NY 11735",
    "addr:housenumber":"62",
    "addr:postcode":"11735",
    "addr:street":"Marine St",
    "iso:country":"US",
    "sg:address":"62 Marine St",
    "sg:city":"Farmingdale",
    "sg:classifiers":[
        {
            "category":"Wholesale",
            "subcategory":"Auto Parts",
            "type":"Manufacturing & Wholesale Goods"
        }
    ],
    "sg:phone":"+1 631 845 9366",
    "sg:postcode":"11735",
    "sg:province":"NY",
    "sg:tags":[
        "used"
    ],
    "wof:name":"Baires Driveline",
    "wof:placetype":"venue"
},
  "geometry": {"coordinates":[-73.42083100000001,40.714611],"type":"Point"}
}