{
  "type": "Feature",
  "properties": {
    "iso:country":"US",
    "sg:address":"164 Lake Rd",
    "sg:city":"Dryden",
    "sg:classifiers":[
        {
            "category":"Home & Garden",
            "subcategory":"Household Appliances",
            "type":"Retail Goods"
        },
        {
            "category":"Building & Trades",
            "subcategory":"Construction",
            "type":"Services"
        }
    ],
    "sg:phone":"+1 607 844 5358",
    "sg:postcode":"13053",
    "sg:province":"NY",
    "sg:tags":[
        "major",
        "dishwashing",
        "system",
        "machine",
        "contractor",
        "air conditioning"
    ],
    "wof:name":"R E Shipe Contracting",
    "wof:placetype":"venue"
},
  "geometry": {"coordinates":[-76.28658299999999,42.474331],"type":"Point"}
}