{
  "type": "Feature",
  "properties": {
    "iso:country":"US",
    "sg:address":"527 Halstead Ave",
    "sg:city":"Mamaroneck",
    "sg:classifiers":[
        {
            "category":"Professional",
            "subcategory":"Accounting & Tax Preparation",
            "type":"Services"
        }
    ],
    "sg:phone":"+1 914 670 0670",
    "sg:postcode":"10543",
    "sg:province":"NY",
    "sg:tags":[
        "bookkeeping",
        "general"
    ],
    "wof:name":"Vincent Ferrari",
    "wof:placetype":"venue"
},
  "geometry": {"coordinates":[-73.731495,40.95681],"type":"Point"}
}