{
  "type": "Feature",
  "properties": {
    "iso:country":"US",
    "sg:address":"101 Cox Rd",
    "sg:city":"Newfield",
    "sg:classifiers":[
        {
            "category":"Retail",
            "subcategory":"Veterinary Services",
            "type":"Services"
        }
    ],
    "sg:phone":"+1 607 564 9226",
    "sg:postcode":"14867",
    "sg:province":"NY",
    "sg:tags":[
        "veterinarian"
    ],
    "wof:name":"Somerset Equine Practice",
    "wof:placetype":"venue"
},
  "geometry": {"coordinates":[-76.610603,42.3456],"type":"Point"}
}