{
  "type": "Feature",
  "properties": {
    "iso:country":"US",
    "sg:address":"180 Clover Hills Dr",
    "sg:city":"Rochester",
    "sg:classifiers":[
        {
            "category":"Wholesale",
            "subcategory":"Machinery & Supplies",
            "type":"Manufacturing & Wholesale Goods"
        }
    ],
    "sg:phone":"+1 585 244 0630",
    "sg:postcode":"14618",
    "sg:province":"NY",
    "sg:tags":[
        "equipment",
        "laminating"
    ],
    "wof:name":"Newmark Associates",
    "wof:placetype":"venue"
},
  "geometry": {"coordinates":[-77.552639,43.104834],"type":"Point"}
}