{
  "type": "Feature",
  "properties": {
    "addr:full":"52 Cedar St Dobbs Ferry NY 10522",
    "addr:housenumber":"52",
    "addr:postcode":"10522",
    "addr:street":"Cedar St",
    "iso:country":"US",
    "sg:address":"52 Cedar St",
    "sg:city":"Dobbs Ferry",
    "sg:classifiers":[
        {
            "category":"Professional",
            "subcategory":"Lawyer & Legal Services",
            "type":"Services"
        }
    ],
    "sg:phone":"+1 914 693 6363",
    "sg:postcode":"10522",
    "sg:province":"NY",
    "sg:tags":[
        "attorney"
    ],
    "wof:name":"Elizabeth M Enochs",
    "wof:placetype":"venue"
},
  "geometry": {"coordinates":[-73.870941,41.015157],"type":"Point"}
}