{
  "type": "Feature",
  "properties": {
    "iso:country":"US",
    "sg:address":"17 Hemlock St",
    "sg:city":"Latham",
    "sg:classifiers":[
        {
            "category":"Wholesale",
            "subcategory":"Construction Materials",
            "type":"Manufacturing & Wholesale Goods"
        }
    ],
    "sg:phone":"+1 518 785 3100",
    "sg:postcode":"12110",
    "sg:province":"NY",
    "wof:name":"Jim Waters of Connecticut",
    "wof:placetype":"venue"
},
  "geometry": {"coordinates":[-73.793497,42.738965],"type":"Point"}
}