{
  "type": "Feature",
  "properties": {
    "addr:full":"2660 Park Ave Bronx NY 10451",
    "addr:housenumber":"2660",
    "addr:postcode":"10451",
    "addr:street":"Park Ave",
    "iso:country":"US",
    "sg:address":"2660 Park Ave",
    "sg:city":"Bronx",
    "sg:classifiers":[
        {
            "category":"Wholesale",
            "subcategory":"Machinery & Supplies",
            "type":"Manufacturing & Wholesale Goods"
        }
    ],
    "sg:phone":"+1 718 665 0570",
    "sg:postcode":"10451",
    "sg:province":"NY",
    "sg:tags":[
        "equipment",
        "welding"
    ],
    "sg:website":"www.indyweldsupply.com",
    "wof:name":"Independent Welding Supply",
    "wof:placetype":"venue"
},
  "geometry": {"coordinates":[-73.92786099999999,40.814054],"type":"Point"}
}