{
  "type": "Feature",
  "properties": {
    "addr:full":"810 7th Ave New York NY 10019",
    "addr:housenumber":"810",
    "addr:postcode":"10019",
    "addr:street":"7Th Ave",
    "iso:country":"US",
    "sg:address":"810 7th Ave",
    "sg:city":"New York",
    "sg:classifiers":[
        {
            "category":"Restaurant",
            "type":"Food & Drink"
        }
    ],
    "sg:phone":"+1 212 767 1717",
    "sg:postcode":"10019",
    "sg:province":"NY",
    "wof:name":"Martini's",
    "wof:placetype":"venue"
},
  "geometry": {"coordinates":[-73.982101,40.762699],"type":"Point"}
}