{
  "type": "Feature",
  "properties": {
    "iso:country":"US",
    "sg:address":"1389 Hempstead Tpke",
    "sg:city":"Elmont",
    "sg:classifiers":[
        {
            "category":"Wholesale",
            "subcategory":"Electrical",
            "type":"Manufacturing & Wholesale Goods"
        }
    ],
    "sg:phone":"+1 516 837 8493",
    "sg:postcode":"11003",
    "sg:province":"NY",
    "sg:tags":[
        "control",
        "security",
        "system"
    ],
    "wof:name":"Beacon Security",
    "wof:placetype":"venue"
},
  "geometry": {"coordinates":[-73.692004,40.707809],"type":"Point"}
}