{
  "type": "Feature",
  "properties": {
    "iso:country":"US",
    "sg:address":"3041 Kingsbridge Ave",
    "sg:city":"Bronx",
    "sg:classifiers":[
        {
            "category":"Social Services",
            "subcategory":"Child Care",
            "type":"Services"
        }
    ],
    "sg:phone":"+1 718 549 1525",
    "sg:postcode":"10463",
    "sg:province":"NY",
    "sg:tags":[
        "day"
    ],
    "wof:name":"Spuyten Dyvil Prschlpre-School",
    "wof:placetype":"venue"
},
  "geometry": {"coordinates":[-73.906781,40.87959],"type":"Point"}
}