{
  "type": "Feature",
  "properties": {
    "iso:country":"US",
    "sg:address":"6 Orchard Dr",
    "sg:city":"Woodbury",
    "sg:classifiers":[
        {
            "category":"Building & Trades",
            "subcategory":"Equipment Rental",
            "type":"Services"
        }
    ],
    "sg:phone":"+1   ",
    "sg:postcode":"11797",
    "sg:province":"NY",
    "wof:name":"Brae Leasing Ltd",
    "wof:placetype":"venue"
},
  "geometry": {"coordinates":[-73.456667,40.810783],"type":"Point"}
}