{
  "type": "Feature",
  "properties": {
    "iso:country":"US",
    "sg:address":"160 Marion St",
    "sg:city":"Sayville",
    "sg:classifiers":[
        {
            "category":"Building & Trades",
            "subcategory":"Construction",
            "type":"Services"
        }
    ],
    "sg:phone":"+1 631 589 1008",
    "sg:postcode":"11782",
    "sg:province":"NY",
    "sg:tags":[
        "house"
    ],
    "wof:name":"Dennis Demetres",
    "wof:placetype":"venue"
},
  "geometry": {"coordinates":[-73.094767,40.749597],"type":"Point"}
}