{
  "type": "Feature",
  "properties": {
    "addr:full":"258 Wythe Avenue Brooklyn NY 11211",
    "addr:housenumber":"258",
    "addr:postcode":"11211",
    "addr:street":"Wythe Avenue",
    "iso:country":"US",
    "sg:address":"258 Wythe Avenue",
    "sg:city":"Brooklyn",
    "sg:classifiers":[
        {
            "category":"Arts & Performance",
            "subcategory":"Music",
            "type":"Entertainment"
        },
        {
            "category":"Restaurant",
            "type":"Food & Drink"
        }
    ],
    "sg:phone":"+1 718 218 6934",
    "sg:postcode":"11211",
    "sg:province":"NY",
    "sg:tags":[
        "venue",
        "french"
    ],
    "sg:website":"www.zebuloncafeconcert.com",
    "wof:name":"Zebulon",
    "wof:placetype":"venue"
},
  "geometry": {"coordinates":[-73.96379899999999,40.716599],"type":"Point"}
}