{
  "type": "Feature",
  "properties": {
    "addr:full":"119 Manhattan Ave Hawthorne NY 10532",
    "addr:housenumber":"119",
    "addr:postcode":"10532",
    "addr:street":"Manhattan Ave",
    "iso:country":"US",
    "sg:address":"119 Manhattan Ave",
    "sg:city":"Hawthorne",
    "sg:classifiers":[
        {
            "category":"Autos & Motor Vehicles",
            "subcategory":"Automobile Sales",
            "type":"Retail Goods"
        }
    ],
    "sg:phone":"+1   ",
    "sg:postcode":"10532",
    "sg:province":"NY",
    "wof:name":"Celebrity Motors Inc",
    "wof:placetype":"venue"
},
  "geometry": {"coordinates":[-73.787323,41.096344],"type":"Point"}
}