{
  "type": "Feature",
  "properties": {
    "addr:full":"8 High St Victor NY 14564",
    "addr:housenumber":"8",
    "addr:postcode":"14564",
    "addr:street":"High St",
    "iso:country":"US",
    "sg:address":"8 High St",
    "sg:city":"Victor",
    "sg:classifiers":[
        {
            "category":"Shopping",
            "subcategory":"Beauty & Cosmetics",
            "type":"Retail Goods"
        }
    ],
    "sg:phone":"+1   ",
    "sg:postcode":"14564",
    "sg:province":"NY",
    "sg:tags":[
        "merchandise"
    ],
    "wof:name":"Merle Norman Cosmetics",
    "wof:placetype":"venue"
},
  "geometry": {"coordinates":[-77.41587800000001,42.988147],"type":"Point"}
}