{
  "type": "Feature",
  "properties": {
    "addr:full":"34 N Main St New Berlin NY 13411",
    "addr:housenumber":"34",
    "addr:postcode":"13411",
    "addr:street":"N Main St",
    "iso:country":"US",
    "sg:address":"34 N Main St",
    "sg:city":"New Berlin",
    "sg:classifiers":[
        {
            "category":"Organizations",
            "subcategory":"Non-profit Organization",
            "type":"Services"
        }
    ],
    "sg:phone":"+1 607 847 6105",
    "sg:postcode":"13411",
    "sg:province":"NY",
    "sg:tags":[
        "handicapped"
    ],
    "wof:name":"Broome Developmental Svc",
    "wof:placetype":"venue"
},
  "geometry": {"coordinates":[-75.332323,42.627239],"type":"Point"}
}