{
  "type": "Feature",
  "properties": {
    "iso:country":"US",
    "sg:address":"270 Atlantic Ave",
    "sg:city":"Brooklyn",
    "sg:classifiers":[
        {
            "category":"Retail",
            "subcategory":"Auto Rental",
            "type":"Services"
        }
    ],
    "sg:phone":"+1 718 858 0889",
    "sg:postcode":"11201",
    "sg:province":"NY",
    "sg:tags":[
        "renting",
        "truck",
        "leasing"
    ],
    "wof:name":"U-Haul Co",
    "wof:placetype":"venue"
},
  "geometry": {"coordinates":[-73.98972999999999,40.688791],"type":"Point"}
}