{
  "type": "Feature",
  "properties": {
    "addr:full":"6 Balter Rd New City NY 10956",
    "addr:housenumber":"6",
    "addr:postcode":"10956",
    "addr:street":"Balter Rd",
    "iso:country":"US",
    "sg:address":"6 Balter Rd",
    "sg:city":"New City",
    "sg:classifiers":[
        {
            "category":"Building & Trades",
            "subcategory":"Construction",
            "type":"Services"
        }
    ],
    "sg:phone":"+1 845 353 3909",
    "sg:postcode":"10956",
    "sg:province":"NY",
    "sg:tags":[
        "general",
        "contractor"
    ],
    "wof:name":"Prime Paving Inc",
    "wof:placetype":"venue"
},
  "geometry": {"coordinates":[-74.017945,41.157011],"type":"Point"}
}