{
  "type": "Feature",
  "properties": {
    "addr:full":"40 W 72nd Street New York NY 10023",
    "addr:housenumber":"40",
    "addr:postcode":"10023",
    "addr:street":"W 72Nd Street",
    "iso:country":"US",
    "sg:address":"40 W 72nd Street",
    "sg:city":"New York",
    "sg:classifiers":[
        {
            "category":"Health Services",
            "subcategory":"Dentist",
            "type":"Services"
        }
    ],
    "sg:phone":"+1 212 362 3720",
    "sg:postcode":"10023",
    "sg:province":"NY",
    "wof:name":"Periodontics & Implant Dentistry",
    "wof:placetype":"venue"
},
  "geometry": {"coordinates":[-73.977068,40.77667],"type":"Point"}
}