{
  "type": "Feature",
  "properties": {
    "iso:country":"US",
    "sg:address":"785 State Route 17M Ste 9",
    "sg:city":"Monroe",
    "sg:classifiers":[
        {
            "category":"Personal",
            "subcategory":"Day Spa",
            "type":"Services"
        }
    ],
    "sg:phone":"+1 845 774 2559",
    "sg:postcode":"10950",
    "sg:province":"NY",
    "wof:name":"Life Plex",
    "wof:placetype":"venue"
},
  "geometry": {"coordinates":[-74.192188,41.33316],"type":"Point"}
}