{
  "type": "Feature",
  "properties": {
    "iso:country":"US",
    "sg:address":"29 York Dr",
    "sg:city":"Great Neck",
    "sg:classifiers":[
        {
            "category":"Building & Trades",
            "subcategory":"Electrical",
            "type":"Services"
        }
    ],
    "sg:phone":"+1 516 482 3400",
    "sg:postcode":"11021",
    "sg:province":"NY",
    "sg:tags":[
        "electrical",
        "electric",
        "contractor"
    ],
    "wof:name":"Ohm's Electrical Corp",
    "wof:placetype":"venue"
},
  "geometry": {"coordinates":[-73.709637,40.789708],"type":"Point"}
}