{
  "type": "Feature",
  "properties": {
    "addr:full":"3033 Express Dr N Islandia NY 11749",
    "addr:housenumber":"3033",
    "addr:postcode":"11749",
    "addr:street":"Express Dr N Islandia",
    "iso:country":"US",
    "sg:address":"3033 Express Dr N",
    "sg:city":"Islandia",
    "sg:classifiers":[
        {
            "category":"Shopping",
            "subcategory":"Computers & Home Electronics",
            "type":"Retail Goods"
        }
    ],
    "sg:phone":"+1 631 348 3700",
    "sg:postcode":"11749",
    "sg:province":"NY",
    "sg:tags":[
        "equipment",
        "electronic",
        "supply"
    ],
    "wof:name":"FAI Electronics Corp",
    "wof:placetype":"venue"
},
  "geometry": {"coordinates":[-73.15075,40.810742],"type":"Point"}
}