{
  "type": "Feature",
  "properties": {
    "addr:full":"27130 77th Ave New Hyde Park NY 11040",
    "addr:housenumber":"27130",
    "addr:postcode":"11040",
    "addr:street":"77Th Ave",
    "iso:country":"US",
    "sg:address":"27130 77th Ave",
    "sg:city":"New Hyde Park",
    "sg:classifiers":[
        {
            "category":"Health Services",
            "subcategory":"Chiropractor",
            "type":"Services"
        }
    ],
    "sg:phone":"+1 516 222 2225",
    "sg:postcode":"11040",
    "sg:province":"NY",
    "wof:name":"Lindel Ralph E Chirprctr",
    "wof:placetype":"venue"
},
  "geometry": {"coordinates":[-73.70369700000001,40.7533],"type":"Point"}
}