{
  "type": "Feature",
  "properties": {
    "iso:country":"US",
    "sg:address":"600 5th Ave",
    "sg:city":"New York",
    "sg:classifiers":[
        {
            "category":"Insurance",
            "subcategory":"Hazard Insurance",
            "type":"Services"
        }
    ],
    "sg:phone":"+1 212 332 8080",
    "sg:postcode":"10020",
    "sg:province":"NY",
    "sg:tags":[
        "casualty"
    ],
    "wof:name":"Jabawwat Inc",
    "wof:placetype":"venue"
},
  "geometry": {"coordinates":[-73.97783699999999,40.757739],"type":"Point"}
}