{
  "type": "Feature",
  "properties": {
    "addr:full":"28 W Carl St Hicksville NY 11801",
    "addr:housenumber":"28",
    "addr:postcode":"11801",
    "addr:street":"W Carl St",
    "iso:country":"US",
    "sg:address":"28 W Carl St",
    "sg:city":"Hicksville",
    "sg:classifiers":[
        {
            "category":"Recreation",
            "type":"Entertainment"
        }
    ],
    "sg:phone":"+1 516 733 8412",
    "sg:postcode":"11801",
    "sg:province":"NY",
    "sg:tags":[
        "hall",
        "auditorium"
    ],
    "wof:name":"Hicksville Community Ctr",
    "wof:placetype":"venue"
},
  "geometry": {"coordinates":[-73.521552,40.764424],"type":"Point"}
}