{
  "type": "Feature",
  "properties": {
    "addr:full":"9 Sycamore Ln Suffern NY 10901",
    "addr:housenumber":"9",
    "addr:postcode":"10901",
    "addr:street":"Sycamore Ln",
    "iso:country":"US",
    "sg:address":"9 Sycamore Ln",
    "sg:city":"Suffern",
    "sg:classifiers":[
        {
            "category":"Professional",
            "subcategory":"Accounting & Tax Preparation",
            "type":"Services"
        }
    ],
    "sg:phone":"+1   ",
    "sg:postcode":"10901",
    "sg:province":"NY",
    "wof:name":"Cindy Fleisher CPA",
    "wof:placetype":"venue"
},
  "geometry": {"coordinates":[-74.08599599999999,41.136294],"type":"Point"}
}