{
  "type": "Feature",
  "properties": {
    "addr:full":"30 S 6th Ave Mount Vernon NY 10550",
    "addr:housenumber":"30",
    "addr:postcode":"10550",
    "addr:street":"S 6Th Ave",
    "iso:country":"US",
    "sg:address":"30 S 6th Ave",
    "sg:city":"Mount Vernon",
    "sg:classifiers":[
        {
            "category":"Wholesale",
            "subcategory":"Machinery & Supplies",
            "type":"Manufacturing & Wholesale Goods"
        }
    ],
    "sg:phone":"+1 914 668 3800",
    "sg:postcode":"10550",
    "sg:province":"NY",
    "sg:tags":[
        "distributor",
        "fluid",
        "power"
    ],
    "wof:name":"Db Hydraulic Equipment",
    "wof:placetype":"venue"
},
  "geometry": {"coordinates":[-73.83827599999999,40.909386],"type":"Point"}
}