{
  "type": "Feature",
  "properties": {
    "addr:full":"7406 Metropolitan Avenue Middle Village NY 11379",
    "addr:housenumber":"7406",
    "addr:postcode":"11379",
    "addr:street":"Metropolitan Avenue",
    "iso:country":"US",
    "sg:address":"7406 Metropolitan Avenue",
    "sg:city":"Middle Village",
    "sg:classifiers":[
        {
            "category":"Professional",
            "subcategory":"Lawyer & Legal Services",
            "type":"Services"
        }
    ],
    "sg:phone":"+1 718 894 4600",
    "sg:postcode":"11379",
    "sg:province":"NY",
    "wof:name":"Colonna & Urso Llp",
    "wof:placetype":"venue"
},
  "geometry": {"coordinates":[-73.878264,40.712832],"type":"Point"}
}