{
  "type": "Feature",
  "properties": {
    "iso:country":"US",
    "sg:address":"244 Canal St",
    "sg:city":"New York",
    "sg:classifiers":[
        {
            "category":"Wholesale",
            "subcategory":"Jewelry",
            "type":"Manufacturing & Wholesale Goods"
        }
    ],
    "sg:phone":"+1 212 343 0494",
    "sg:postcode":"10013",
    "sg:province":"NY",
    "sg:tags":[
        "platinum",
        "silver",
        "gold"
    ],
    "wof:name":"Jewelry Specialties",
    "wof:placetype":"venue"
},
  "geometry": {"coordinates":[-74.000409,40.71821],"type":"Point"}
}