{
  "type": "Feature",
  "properties": {
    "iso:country":"US",
    "sg:address":"275 Glen Ave",
    "sg:city":"Dover Plains",
    "sg:classifiers":[
        {
            "category":"Building & Trades",
            "subcategory":"Construction",
            "type":"Services"
        }
    ],
    "sg:phone":"+1 845 877 9312",
    "sg:postcode":"12522",
    "sg:province":"NY",
    "sg:tags":[
        "house",
        "co"
    ],
    "wof:name":"Amenia Construction Corp",
    "wof:placetype":"venue"
},
  "geometry": {"coordinates":[-73.583888,41.761511],"type":"Point"}
}