{
  "type": "Feature",
  "properties": {
    "iso:country":"US",
    "sg:address":"779 Co Rd 5",
    "sg:city":"Otego",
    "sg:classifiers":[
        {
            "category":"Wholesale",
            "subcategory":"Construction Materials",
            "type":"Manufacturing & Wholesale Goods"
        }
    ],
    "sg:phone":"+1 607 988 2746",
    "sg:postcode":"13825",
    "sg:province":"NY",
    "sg:tags":[
        "fence"
    ],
    "wof:name":"Invisible Fence Of CNY",
    "wof:placetype":"venue"
},
  "geometry": {"coordinates":[-75.23518199999999,42.425163],"type":"Point"}
}