{
  "type": "Feature",
  "properties": {
    "addr:full":"2911 Densmore Rd Albion NY 14411",
    "addr:housenumber":"2911",
    "addr:postcode":"14411",
    "addr:street":"Densmore Rd",
    "iso:country":"US",
    "sg:address":"2911 Densmore Rd",
    "sg:city":"Albion",
    "sg:phone":"+1 585 589 9557",
    "sg:postcode":"14411",
    "sg:province":"NY",
    "sg:tags":[
        "wheat",
        "farm",
        "corn",
        "tree",
        "fruit",
        "or"
    ],
    "wof:name":"Kast Farms Inc",
    "wof:placetype":"venue"
},
  "geometry": {"coordinates":[-78.135469,43.288554],"type":"Point"}
}