{
  "type": "Feature",
  "properties": {
    "addr:full":"132 Clarke St Brentwood NY 11717",
    "addr:housenumber":"132",
    "addr:postcode":"11717",
    "addr:street":"Clarke St",
    "iso:country":"US",
    "sg:address":"132 Clarke St",
    "sg:city":"Brentwood",
    "sg:classifiers":[
        {
            "category":"Personal",
            "subcategory":"Beauty Salon",
            "type":"Services"
        }
    ],
    "sg:phone":"+1 631 231 0310",
    "sg:postcode":"11717",
    "sg:province":"NY",
    "wof:name":"Grace & Lucy's Beauty Salon",
    "wof:placetype":"venue"
},
  "geometry": {"coordinates":[-73.249966,40.798912],"type":"Point"}
}