{
  "type": "Feature",
  "properties": {
    "addr:full":"4 Madison Ave W Rensselaer NY 12144",
    "addr:housenumber":"4",
    "addr:postcode":"12144",
    "addr:street":"Madison Ave W",
    "iso:country":"US",
    "sg:address":"4 Madison Ave W",
    "sg:city":"Rensselaer",
    "sg:classifiers":[
        {
            "category":"Government",
            "subcategory":"Fire Station",
            "type":"Public Place"
        }
    ],
    "sg:phone":"+1 518 479 1201",
    "sg:postcode":"12144",
    "sg:province":"NY",
    "sg:tags":[
        "department"
    ],
    "wof:name":"Clinton Heights Fire Dept",
    "wof:placetype":"venue"
},
  "geometry": {"coordinates":[-73.72942399999999,42.616074],"type":"Point"}
}