{
  "type": "Feature",
  "properties": {
    "addr:full":"19 W 8 St New York NY 10011",
    "addr:housenumber":"19;8",
    "addr:postcode":"10011",
    "addr:street":"W",
    "iso:country":"US",
    "sg:address":"19 W 8 St",
    "sg:city":"New York",
    "sg:classifiers":[
        {
            "category":"Shopping",
            "subcategory":"Clothing, Apparel, & Fashions",
            "type":"Retail Goods"
        }
    ],
    "sg:phone":"+1   ",
    "sg:postcode":"10011",
    "sg:province":"NY",
    "sg:tags":[
        "family",
        "store"
    ],
    "wof:name":"Image Urban Ltd",
    "wof:placetype":"venue"
},
  "geometry": {"coordinates":[-73.99736300000001,40.732684],"type":"Point"}
}