{
  "type": "Feature",
  "properties": {
    "iso:country":"US",
    "sg:address":"2709 Coney Island Ave",
    "sg:city":"Brooklyn",
    "sg:classifiers":[
        {
            "category":"Autos & Motor Vehicles",
            "subcategory":"Automobile Sales",
            "type":"Retail Goods"
        }
    ],
    "sg:phone":"+1 718 648 8822",
    "sg:postcode":"11235",
    "sg:province":"NY",
    "sg:tags":[
        "car"
    ],
    "sg:website":"www.grandprixmotors.net",
    "wof:name":"Grand Prix Motors",
    "wof:placetype":"venue"
},
  "geometry": {"coordinates":[-73.96022499999999,40.590576],"type":"Point"}
}