{
  "type": "Feature",
  "properties": {
    "addr:full":"116 Suffolk Street New York NY 10002",
    "addr:housenumber":"116",
    "addr:postcode":"10002",
    "addr:street":"Suffolk Street",
    "iso:country":"US",
    "sg:address":"116 Suffolk Street",
    "sg:city":"New York",
    "sg:classifiers":[
        {
            "category":"Bars & Pubs",
            "subcategory":"Nightclub",
            "type":"Food & Drink"
        }
    ],
    "sg:phone":"+1 212 475 7088",
    "sg:postcode":"10002",
    "sg:province":"NY",
    "sg:tags":[
        "nightlife"
    ],
    "wof:name":"Rothko",
    "wof:placetype":"venue"
},
  "geometry": {"coordinates":[-73.985901,40.719002],"type":"Point"}
}