{
  "type": "Feature",
  "properties": {
    "addr:full":"39 William St Auburn NY 13021",
    "addr:housenumber":"39",
    "addr:postcode":"13021",
    "addr:street":"William St",
    "iso:country":"US",
    "sg:address":"39 William St",
    "sg:city":"Auburn",
    "sg:classifiers":[
        {
            "category":"Health Services",
            "subcategory":"Doctor",
            "type":"Services"
        }
    ],
    "sg:phone":"+1 315 253 9776",
    "sg:postcode":"13021",
    "sg:province":"NY",
    "sg:tags":[
        "physician",
        "surgeon"
    ],
    "wof:name":"Patrick J Buttarazzi MD",
    "wof:placetype":"venue"
},
  "geometry": {"coordinates":[-76.568073,42.929911],"type":"Point"}
}