{
  "type": "Feature",
  "properties": {
    "addr:full":"8 Wickford Way Fairport NY 14450",
    "addr:housenumber":"8",
    "addr:postcode":"14450",
    "addr:street":"Wickford Way",
    "iso:country":"US",
    "sg:address":"8 Wickford Way",
    "sg:city":"Fairport",
    "sg:classifiers":[
        {
            "category":"Organizations",
            "subcategory":"Religious Organization",
            "type":"Services"
        }
    ],
    "sg:phone":"+1 585 385 6039",
    "sg:postcode":"14450",
    "sg:province":"NY",
    "sg:tags":[
        "clergy"
    ],
    "wof:name":"John J Philipps",
    "wof:placetype":"venue"
},
  "geometry": {"coordinates":[-77.477833,43.076084],"type":"Point"}
}