{
  "type": "Feature",
  "properties": {
    "iso:country":"US",
    "sg:address":"198 S Franklin St",
    "sg:city":"Nyack",
    "sg:classifiers":[
        {
            "category":"Wholesale",
            "subcategory":"Machinery & Supplies",
            "type":"Manufacturing & Wholesale Goods"
        }
    ],
    "sg:phone":"+1 845 353 1395",
    "sg:postcode":"10960",
    "sg:province":"NY",
    "sg:tags":[
        "machine",
        "tool"
    ],
    "sg:website":"www.nyrock.net",
    "wof:name":"Nyrock Machine Tools Inc",
    "wof:placetype":"venue"
},
  "geometry": {"coordinates":[-73.92187699999999,41.084173],"type":"Point"}
}