{
  "type": "Feature",
  "properties": {
    "addr:full":"1590 E 233rd St Bronx NY 10466",
    "addr:housenumber":"1590",
    "addr:postcode":"10466",
    "addr:street":"E 233Rd St",
    "iso:country":"US",
    "sg:address":"1590 E 233rd St",
    "sg:city":"Bronx",
    "sg:classifiers":[
        {
            "category":"Building & Trades",
            "subcategory":"Construction",
            "type":"Services"
        }
    ],
    "sg:phone":"+1 718 324 3700",
    "sg:postcode":"10466",
    "sg:province":"NY",
    "sg:tags":[
        "masonry",
        "waterproofing",
        "contractor"
    ],
    "wof:name":"Grenadier",
    "wof:placetype":"venue"
},
  "geometry": {"coordinates":[-73.82923099999999,40.888955],"type":"Point"}
}