{
  "type": "Feature",
  "properties": {
    "addr:full":"70 4th Ave Brooklyn NY 11217",
    "addr:housenumber":"70",
    "addr:postcode":"11217",
    "addr:street":"4Th Ave",
    "iso:country":"US",
    "sg:address":"70 4th Ave",
    "sg:city":"Brooklyn",
    "sg:classifiers":[
        {
            "category":"Retail",
            "subcategory":"Repair Shop",
            "type":"Services"
        }
    ],
    "sg:phone":"+1 718 956 7780",
    "sg:postcode":"11217",
    "sg:province":"NY",
    "sg:tags":[
        "lock",
        "locksmith"
    ],
    "wof:name":"24 Hour 7 Day Emerg Locksmith",
    "wof:placetype":"venue"
},
  "geometry": {"coordinates":[-73.980034,40.681854],"type":"Point"}
}