{
  "type": "Feature",
  "properties": {
    "addr:full":"1053 Evergreen Ave Bronx NY 10472",
    "addr:housenumber":"1053",
    "addr:postcode":"10472",
    "addr:street":"Evergreen Ave",
    "iso:country":"US",
    "sg:address":"1053 Evergreen Ave",
    "sg:city":"Bronx",
    "sg:classifiers":[
        {
            "category":"Real Estate",
            "subcategory":"Real Estate Agent",
            "type":"Services"
        }
    ],
    "sg:phone":"+1 718 991 4433",
    "sg:postcode":"10472",
    "sg:province":"NY",
    "wof:name":"Select Realty Corp",
    "wof:placetype":"venue"
},
  "geometry": {"coordinates":[-73.880301,40.824631],"type":"Point"}
}