{
  "type": "Feature",
  "properties": {
    "addr:full":"486 S Mountain Rd Gardiner NY 12525",
    "addr:housenumber":"486",
    "addr:postcode":"12525",
    "addr:street":"S Mountain Rd",
    "iso:country":"US",
    "sg:address":"486 S Mountain Rd",
    "sg:city":"Gardiner",
    "sg:classifiers":[
        {
            "category":"Freight",
            "type":"Transportation"
        }
    ],
    "sg:phone":"+1   ",
    "sg:postcode":"12525",
    "sg:province":"NY",
    "sg:tags":[
        "operator",
        "local",
        "trucking"
    ],
    "wof:name":"J T Marks Trucking Inc",
    "wof:placetype":"venue"
},
  "geometry": {"coordinates":[-74.23586,41.684581],"type":"Point"}
}