{
  "type": "Feature",
  "properties": {
    "addr:full":"6011 Johnson Rd Sinclairville NY 14775",
    "addr:housenumber":"6011",
    "addr:postcode":"14775",
    "addr:street":"Johnson Rd",
    "iso:country":"US",
    "sg:address":"6011 Johnson Rd",
    "sg:city":"Sinclairville",
    "sg:classifiers":[
        {
            "category":"Organizations",
            "subcategory":"Non-profit Organization",
            "type":"Services"
        }
    ],
    "sg:phone":"+1 716 962 3767",
    "sg:postcode":"14775",
    "sg:province":"NY",
    "sg:tags":[
        "disability"
    ],
    "wof:name":"Human Service Seminars",
    "wof:placetype":"venue"
},
  "geometry": {"coordinates":[-79.67359399999999,42.238495],"type":"Point"}
}