{
  "type": "Feature",
  "properties": {
    "addr:full":"15 Valerie Ct Sayville NY 11782",
    "addr:housenumber":"15",
    "addr:postcode":"11782",
    "addr:street":"Valerie Ct",
    "iso:country":"US",
    "sg:address":"15 Valerie Ct",
    "sg:city":"Sayville",
    "sg:classifiers":[
        {
            "category":"Building & Trades",
            "subcategory":"Construction",
            "type":"Services"
        }
    ],
    "sg:phone":"+1 631 567 2869",
    "sg:postcode":"11782",
    "sg:province":"NY",
    "sg:tags":[
        "house",
        "contractor"
    ],
    "wof:name":"Paul Grace Contracting",
    "wof:placetype":"venue"
},
  "geometry": {"coordinates":[-73.079375,40.752887],"type":"Point"}
}