{
  "type": "Feature",
  "properties": {
    "iso:country":"US",
    "sg:address":"5732 Main St",
    "sg:city":"Williamsville",
    "sg:classifiers":[
        {
            "category":"Manufacturing",
            "subcategory":"Printing",
            "type":"Manufacturing & Wholesale Goods"
        }
    ],
    "sg:phone":"+1 716 633 7514",
    "sg:postcode":"14221",
    "sg:province":"NY",
    "sg:tags":[
        "printer",
        "form"
    ],
    "wof:name":"Printing Post",
    "wof:placetype":"venue"
},
  "geometry": {"coordinates":[-78.738235,42.963986],"type":"Point"}
}