{
  "type": "Feature",
  "properties": {
    "addr:full":"97 Mountain Ave New Rochelle NY 10804",
    "addr:housenumber":"97",
    "addr:postcode":"10804",
    "addr:street":"Mountain Ave",
    "iso:country":"US",
    "sg:address":"97 Mountain Ave",
    "sg:city":"New Rochelle",
    "sg:classifiers":[
        {
            "category":"Social Services",
            "type":"Services"
        }
    ],
    "sg:phone":"+1 914 834 1371",
    "sg:postcode":"10804",
    "sg:province":"NY",
    "sg:tags":[
        "counselor",
        "marriage",
        "family"
    ],
    "wof:name":"Amy K Schindler",
    "wof:placetype":"venue"
},
  "geometry": {"coordinates":[-73.77027099999999,40.935855],"type":"Point"}
}