{
  "type": "Feature",
  "properties": {
    "addr:full":"3957 Keily Dr Seaford NY 11783",
    "addr:housenumber":"3957",
    "addr:postcode":"11783",
    "addr:street":"Keily Dr",
    "iso:country":"US",
    "sg:address":"3957 Keily Dr",
    "sg:city":"Seaford",
    "sg:classifiers":[
        {
            "category":"Arts & Performance",
            "subcategory":"Theater",
            "type":"Entertainment"
        }
    ],
    "sg:phone":"+1 516 785 1844",
    "sg:postcode":"11783",
    "sg:province":"NY",
    "sg:tags":[
        "entertainer"
    ],
    "wof:name":"Bill White Productions",
    "wof:placetype":"venue"
},
  "geometry": {"coordinates":[-73.486065,40.686499],"type":"Point"}
}