{
  "type": "Feature",
  "properties": {
    "addr:full":"25 Pixley Industrial Pkwy Rochester NY 14624",
    "addr:housenumber":"25",
    "addr:postcode":"14624",
    "addr:street":"Pixley Industrial Pkwy",
    "iso:country":"US",
    "sg:address":"25 Pixley Industrial Pkwy",
    "sg:city":"Rochester",
    "sg:classifiers":[
        {
            "category":"Professional",
            "subcategory":"Management & Consulting",
            "type":"Services"
        }
    ],
    "sg:phone":"+1 585 247 3355",
    "sg:postcode":"14624",
    "sg:province":"NY",
    "sg:tags":[
        "food"
    ],
    "wof:name":"Kastners Statewide Food Svc",
    "wof:placetype":"venue"
},
  "geometry": {"coordinates":[-77.712182,43.141075],"type":"Point"}
}