{
  "type": "Feature",
  "properties": {
    "addr:full":"2 New St Middletown NY 10940",
    "addr:housenumber":"2",
    "addr:postcode":"10940",
    "addr:street":"New St",
    "iso:country":"US",
    "sg:address":"2 New St",
    "sg:city":"Middletown",
    "sg:classifiers":[
        {
            "category":"Manufacturing",
            "subcategory":"Toys & Sporting Goods",
            "type":"Manufacturing & Wholesale Goods"
        }
    ],
    "sg:phone":"+1   ",
    "sg:postcode":"10940",
    "sg:province":"NY",
    "sg:tags":[
        "control",
        "car",
        "remote",
        "mfg"
    ],
    "wof:name":"Custom Electric Cars",
    "wof:placetype":"venue"
},
  "geometry": {"coordinates":[-74.41025999999999,41.44751],"type":"Point"}
}