{
  "type": "Feature",
  "properties": {
    "iso:country":"US",
    "sg:address":"150 White Plains Rd",
    "sg:city":"Tarrytown",
    "sg:classifiers":[
        {
            "category":"Museum",
            "type":"Entertainment"
        }
    ],
    "sg:phone":"+1 914 631 8200",
    "sg:postcode":"10591",
    "sg:province":"NY",
    "sg:tags":[
        "business",
        "gallery",
        "association"
    ],
    "sg:website":"www.hudsonvalley.org",
    "wof:name":"Historic Hudson Valley",
    "wof:placetype":"venue"
},
  "geometry": {"coordinates":[-73.85434100000001,41.06406],"type":"Point"}
}