{
  "type": "Feature",
  "properties": {
    "iso:country":"US",
    "sg:address":"17 W 27 St",
    "sg:city":"New York",
    "sg:classifiers":[
        {
            "category":"Restaurant",
            "type":"Food & Drink"
        }
    ],
    "sg:phone":"+1 212 696 2655",
    "sg:postcode":"10001",
    "sg:province":"NY",
    "sg:tags":[
        "delicatessen"
    ],
    "wof:name":"27 Street Cafe",
    "wof:placetype":"venue"
},
  "geometry": {"coordinates":[-73.988152,40.744225],"type":"Point"}
}