{
  "type": "Feature",
  "properties": {
    "addr:full":"14 Main St Arkport NY 14807",
    "addr:housenumber":"14",
    "addr:postcode":"14807",
    "addr:street":"Main St",
    "iso:country":"US",
    "sg:address":"14 Main St",
    "sg:city":"Arkport",
    "sg:classifiers":[
        {
            "category":"Home & Garden",
            "subcategory":"Building Materials",
            "type":"Retail Goods"
        },
        {
            "category":"Building & Trades",
            "subcategory":"Construction",
            "type":"Services"
        }
    ],
    "sg:phone":"+1 607 295 7773",
    "sg:postcode":"14807",
    "sg:province":"NY",
    "sg:tags":[
        "siding",
        "contractor"
    ],
    "sg:website":"http://www.airventalum.com",
    "wof:name":"Air Vent Aluminum",
    "wof:placetype":"venue"
},
  "geometry": {"coordinates":[-77.69545599999999,42.394026],"type":"Point"}
}