{
  "type": "Feature",
  "properties": {
    "iso:country":"US",
    "sg:address":"1745 Chrisler Ave",
    "sg:city":"Schenectady",
    "sg:classifiers":[
        {
            "category":"Shopping",
            "subcategory":"Bicycles & Sporting Goods",
            "type":"Retail Goods"
        }
    ],
    "sg:phone":"+1 518 377 5959",
    "sg:postcode":"12303",
    "sg:province":"NY",
    "sg:tags":[
        "equipment",
        "playground"
    ],
    "wof:name":"Backyard Adventures",
    "wof:placetype":"venue"
},
  "geometry": {"coordinates":[-73.935018,42.788032],"type":"Point"}
}