{
  "type": "Feature",
  "properties": {
    "addr:full":"167 Forbell St Brooklyn NY 11208",
    "addr:housenumber":"167",
    "addr:postcode":"11208",
    "addr:street":"Forbell St",
    "iso:country":"US",
    "sg:address":"167 Forbell St",
    "sg:city":"Brooklyn",
    "sg:classifiers":[
        {
            "category":"Food & Beverages",
            "subcategory":"Meat & Fish",
            "type":"Retail Goods"
        }
    ],
    "sg:phone":"+1   ",
    "sg:postcode":"11208",
    "sg:province":"NY",
    "sg:tags":[
        "market"
    ],
    "wof:name":"Bari Meat Market",
    "wof:placetype":"venue"
},
  "geometry": {"coordinates":[-73.864677,40.680859],"type":"Point"}
}