{
  "type": "Feature",
  "properties": {
    "addr:full":"341 Menahan Street Brooklyn NY 11237",
    "addr:housenumber":"341",
    "addr:postcode":"11237",
    "addr:street":"Menahan Street",
    "iso:country":"US",
    "sg:address":"341 Menahan Street",
    "sg:city":"Brooklyn",
    "sg:classifiers":[
        {
            "category":"Retail",
            "subcategory":"Auto Repair",
            "type":"Services"
        }
    ],
    "sg:phone":"+1 718 366 5200",
    "sg:postcode":"11237",
    "sg:province":"NY",
    "wof:name":"Andrade Brthrs Auto Rpr",
    "wof:placetype":"venue"
},
  "geometry": {"coordinates":[-73.914292,40.701175],"type":"Point"}
}