{
  "type": "Feature",
  "properties": {
    "iso:country":"US",
    "sg:address":"7329 Eastman Rd",
    "sg:city":"Syracuse",
    "sg:classifiers":[
        {
            "category":"Building & Trades",
            "subcategory":"Landscaping Services",
            "type":"Services"
        }
    ],
    "sg:phone":"+1 315 374 7683",
    "sg:postcode":"13212",
    "sg:province":"NY",
    "sg:tags":[
        "landscape",
        "contractor"
    ],
    "wof:name":"J S Development",
    "wof:placetype":"venue"
},
  "geometry": {"coordinates":[-76.083943,43.139311],"type":"Point"}
}