{
  "type": "Feature",
  "properties": {
    "iso:country":"US",
    "sg:address":"2020 Route 301",
    "sg:city":"Carmel",
    "sg:classifiers":[
        {
            "category":"Place Of Worship",
            "subcategory":"Monastery",
            "type":"Public Place"
        }
    ],
    "sg:phone":"+1 845 225 1819",
    "sg:postcode":"10512",
    "sg:province":"NY",
    "sg:tags":[
        "convent"
    ],
    "wof:name":"Chuang Yen Monastery",
    "wof:placetype":"venue"
},
  "geometry": {"coordinates":[-73.79186,41.476827],"type":"Point"}
}