{
  "type": "Feature",
  "properties": {
    "iso:country":"US",
    "sg:address":"1675 Roosevelt Ave",
    "sg:city":"Bohemia",
    "sg:classifiers":[
        {
            "category":"Retail",
            "subcategory":"Repair Shop",
            "type":"Services"
        }
    ],
    "sg:phone":"+1 631 218 1384",
    "sg:postcode":"11716",
    "sg:province":"NY",
    "sg:tags":[
        "antique"
    ],
    "wof:name":"Luis Restoration",
    "wof:placetype":"venue"
},
  "geometry": {"coordinates":[-73.13359800000001,40.786201],"type":"Point"}
}