{
  "type": "Feature",
  "properties": {
    "iso:country":"US",
    "sg:address":"7804 13th Ave",
    "sg:city":"Brooklyn",
    "sg:classifiers":[
        {
            "category":"Insurance",
            "subcategory":"Insurance Agent",
            "type":"Services"
        }
    ],
    "sg:phone":"+1 718 833 4100",
    "sg:postcode":"11228",
    "sg:province":"NY",
    "wof:name":"Frank J Silvestsri Inc",
    "wof:placetype":"venue"
},
  "geometry": {"coordinates":[-74.00984099999999,40.618093],"type":"Point"}
}