{
  "type": "Feature",
  "properties": {
    "iso:country":"US",
    "sg:address":"64 W 116th St",
    "sg:city":"New York",
    "sg:classifiers":[
        {
            "category":"Restaurant",
            "type":"Food & Drink"
        }
    ],
    "sg:phone":"+1 212 987 3441",
    "sg:postcode":"10026",
    "sg:province":"NY",
    "wof:name":"Caribbean American Restaurant",
    "wof:placetype":"venue"
},
  "geometry": {"coordinates":[-73.94924899999999,40.801544],"type":"Point"}
}