{
  "type": "Feature",
  "properties": {
    "addr:full":"107 Gramatan Ave Mount Vernon NY 10550",
    "addr:housenumber":"107",
    "addr:postcode":"10550",
    "addr:street":"Gramatan Ave",
    "iso:country":"US",
    "sg:address":"107 Gramatan Ave",
    "sg:city":"Mount Vernon",
    "sg:classifiers":[
        {
            "category":"Food & Beverages",
            "subcategory":"Groceries & Convenience Stores",
            "type":"Retail Goods"
        }
    ],
    "sg:phone":"+1   ",
    "sg:postcode":"10550",
    "sg:province":"NY",
    "wof:name":"Bradeli",
    "wof:placetype":"venue"
},
  "geometry": {"coordinates":[-73.837253,40.91289],"type":"Point"}
}