{
  "type": "Feature",
  "properties": {
    "addr:full":"70 S Peru St Plattsburgh NY 12901",
    "addr:housenumber":"70",
    "addr:postcode":"12901",
    "addr:street":"S Peru St",
    "iso:country":"US",
    "sg:address":"70 S Peru St",
    "sg:city":"Plattsburgh",
    "sg:classifiers":[
        {
            "category":"Real Estate",
            "subcategory":"Real Estate Operator",
            "type":"Services"
        }
    ],
    "sg:phone":"+1 518 561 1506",
    "sg:postcode":"12901",
    "sg:province":"NY",
    "sg:tags":[
        "mobile",
        "home",
        "site"
    ],
    "wof:name":"Trombley Trailer Park Inc",
    "wof:placetype":"venue"
},
  "geometry": {"coordinates":[-73.45432700000001,44.681287],"type":"Point"}
}