{
  "type": "Feature",
  "properties": {
    "addr:full":"35 Thixton Dr Hewlett NY 11557",
    "addr:housenumber":"35",
    "addr:postcode":"11557",
    "addr:street":"Thixton Dr",
    "iso:country":"US",
    "sg:address":"35 Thixton Dr",
    "sg:city":"Hewlett",
    "sg:classifiers":[
        {
            "category":"Building & Trades",
            "subcategory":"Construction",
            "type":"Services"
        }
    ],
    "sg:phone":"+1 516 295 5618",
    "sg:postcode":"11557",
    "sg:province":"NY",
    "sg:tags":[
        "contractor"
    ],
    "wof:name":"Richard Schreiber",
    "wof:placetype":"venue"
},
  "geometry": {"coordinates":[-73.678055,40.630394],"type":"Point"}
}