{
  "type": "Feature",
  "properties": {
    "iso:country":"US",
    "sg:address":"285 Kenmore Ave",
    "sg:city":"Buffalo",
    "sg:classifiers":[
        {
            "category":"Wholesale",
            "subcategory":"Office Equipment",
            "type":"Manufacturing & Wholesale Goods"
        }
    ],
    "sg:phone":"+1 716 803 9000",
    "sg:postcode":"14223",
    "sg:province":"NY",
    "sg:tags":[
        "machine",
        "duplicating",
        "copying"
    ],
    "wof:name":"Central Copier Svc Inc",
    "wof:placetype":"venue"
},
  "geometry": {"coordinates":[-78.828569,42.958284],"type":"Point"}
}