{
  "type": "Feature",
  "properties": {
    "iso:country":"US",
    "sg:address":"2010 E Main St",
    "sg:city":"Endicott",
    "sg:classifiers":[
        {
            "category":"Shopping",
            "subcategory":"Crafts & Fabrics",
            "type":"Retail Goods"
        }
    ],
    "sg:phone":"+1   ",
    "sg:postcode":"13760",
    "sg:province":"NY",
    "sg:tags":[
        "sewing"
    ],
    "wof:name":"Valenta Corporation",
    "wof:placetype":"venue"
},
  "geometry": {"coordinates":[-76.038562,42.102663],"type":"Point"}
}