{
  "type": "Feature",
  "properties": {
    "addr:full":"10 Grouse Cir Queensbury NY 12804",
    "addr:housenumber":"10",
    "addr:postcode":"12804",
    "addr:street":"Grouse Cir",
    "iso:country":"US",
    "sg:address":"10 Grouse Cir",
    "sg:city":"Queensbury",
    "sg:classifiers":[
        {
            "category":"Wholesale",
            "subcategory":"Electrical",
            "type":"Manufacturing & Wholesale Goods"
        }
    ],
    "sg:phone":"+1 518 798 0714",
    "sg:postcode":"12804",
    "sg:province":"NY",
    "sg:tags":[
        "equipment",
        "electronic",
        "supply"
    ],
    "sg:website":"www.challengeelectronics.com",
    "wof:name":"Challenge Electronics Corp",
    "wof:placetype":"venue"
},
  "geometry": {"coordinates":[-73.71548300000001,43.317526],"type":"Point"}
}