{
  "type": "Feature",
  "properties": {
    "addr:full":"66 President St Brooklyn NY 11231",
    "addr:housenumber":"66",
    "addr:postcode":"11231",
    "addr:street":"President St",
    "iso:country":"US",
    "sg:address":"66 President St",
    "sg:city":"Brooklyn",
    "sg:classifiers":[
        {
            "category":"Real Estate",
            "subcategory":"Architect",
            "type":"Services"
        }
    ],
    "sg:phone":"+1   ",
    "sg:postcode":"11231",
    "sg:province":"NY",
    "sg:tags":[
        "architectural"
    ],
    "wof:name":"Building Site",
    "wof:placetype":"venue"
},
  "geometry": {"coordinates":[-74.004345,40.684014],"type":"Point"}
}