{
  "type": "Feature",
  "properties": {
    "addr:full":"60 Claremont Pl Mount Vernon NY 10553",
    "addr:housenumber":"60",
    "addr:postcode":"10553",
    "addr:street":"Claremont Pl",
    "iso:country":"US",
    "sg:address":"60 Claremont Pl",
    "sg:city":"Mount Vernon",
    "sg:classifiers":[
        {
            "category":"Manufacturing",
            "subcategory":"Chemicals & Compounds",
            "type":"Manufacturing & Wholesale Goods"
        }
    ],
    "sg:phone":"+1   ",
    "sg:postcode":"10553",
    "sg:province":"NY",
    "sg:tags":[
        "preparation",
        "toilet",
        "mfg"
    ],
    "wof:name":"Loreleye Laboratories Ltd",
    "wof:placetype":"venue"
},
  "geometry": {"coordinates":[-73.823274,40.912324],"type":"Point"}
}