{
  "type": "Feature",
  "properties": {
    "addr:full":"7119 Minoa Rd East Syracuse NY 13057",
    "addr:housenumber":"7119",
    "addr:postcode":"13057",
    "addr:street":"Minoa Rd",
    "iso:country":"US",
    "sg:address":"7119 Minoa Rd",
    "sg:city":"East Syracuse",
    "sg:classifiers":[
        {
            "category":"Restaurant",
            "type":"Food & Drink"
        }
    ],
    "sg:phone":"+1 315 656 4155",
    "sg:postcode":"13057",
    "sg:province":"NY",
    "sg:tags":[
        "eating"
    ],
    "wof:name":"Franks Country Roadhouse Inc",
    "wof:placetype":"venue"
},
  "geometry": {"coordinates":[-76.002728,43.105571],"type":"Point"}
}