{
  "type": "Feature",
  "properties": {
    "addr:full":"789 Craigville Rd Chester NY 10918",
    "addr:housenumber":"789",
    "addr:postcode":"10918",
    "addr:street":"Craigville Rd",
    "iso:country":"US",
    "sg:address":"789 Craigville Rd",
    "sg:city":"Chester",
    "sg:classifiers":[
        {
            "category":"Organizations",
            "subcategory":"Religious Organization",
            "type":"Services"
        }
    ],
    "sg:phone":"+1 845 469 4408",
    "sg:postcode":"10918",
    "sg:province":"NY",
    "sg:tags":[
        "church"
    ],
    "sg:website":"www.craigvillebiblechurch.org",
    "wof:name":"Craigville Bible Church Inc",
    "wof:placetype":"venue"
},
  "geometry": {"coordinates":[-74.238536,41.384484],"type":"Point"}
}