{
  "type": "Feature",
  "properties": {
    "iso:country":"US",
    "sg:address":"828 Burdeck St",
    "sg:city":"Schenectady",
    "sg:classifiers":[
        {
            "category":"Building & Trades",
            "subcategory":"Construction",
            "type":"Services"
        }
    ],
    "sg:phone":"+1 518 356 4890",
    "sg:postcode":"12306",
    "sg:province":"NY",
    "sg:tags":[
        "paving",
        "contractor"
    ],
    "wof:name":"Towne Construction & Paving",
    "wof:placetype":"venue"
},
  "geometry": {"coordinates":[-74.01034,42.788448],"type":"Point"}
}