{
  "type": "Feature",
  "properties": {
    "addr:full":"469 Seventh Ave Manhattan NY 10018",
    "addr:housenumber":"469",
    "addr:postcode":"10018",
    "addr:street":"Seventh Ave",
    "iso:country":"US",
    "sg:address":"469 Seventh Ave",
    "sg:city":"Manhattan",
    "sg:classifiers":[
        {
            "category":"Real Estate",
            "subcategory":"Real Estate Services",
            "type":"Services"
        },
        {
            "category":"Real Estate",
            "subcategory":"Real Estate Operator",
            "type":"Services"
        }
    ],
    "sg:phone":"+1 917 209 4300",
    "sg:postcode":"10018",
    "sg:province":"NY",
    "sg:tags":[
        "apartment"
    ],
    "sg:website":"www.meiergroupnyc.com",
    "wof:name":"The Meier Group",
    "wof:placetype":"venue"
},
  "geometry": {"coordinates":[-73.989981,40.751907],"type":"Point"}
}