{
  "type": "Feature",
  "properties": {
    "iso:country":"US",
    "sg:address":"1571 Washington St",
    "sg:city":"Watertown",
    "sg:classifiers":[
        {
            "category":"Health Services",
            "subcategory":"Doctor",
            "type":"Services"
        }
    ],
    "sg:phone":"+1 315 782 0325",
    "sg:postcode":"13601",
    "sg:province":"NY",
    "sg:tags":[
        "physician",
        "surgeon"
    ],
    "wof:name":"Gosselin Leo J Jr",
    "wof:placetype":"venue"
},
  "geometry": {"coordinates":[-75.91490899999999,43.950169],"type":"Point"}
}