{
  "type": "Feature",
  "properties": {
    "addr:full":"662 S Main St Central Square NY 13036",
    "addr:housenumber":"662",
    "addr:postcode":"13036",
    "addr:street":"S Main St",
    "iso:country":"US",
    "sg:address":"662 S Main St",
    "sg:city":"Central Square",
    "sg:classifiers":[
        {
            "category":"Professional",
            "subcategory":"Accounting & Tax Preparation",
            "type":"Services"
        }
    ],
    "sg:phone":"+1 315 676 7510",
    "sg:postcode":"13036",
    "sg:province":"NY",
    "sg:tags":[
        "return",
        "filing"
    ],
    "wof:name":"Jackson Hewitt Tax Svc",
    "wof:placetype":"venue"
},
  "geometry": {"coordinates":[-76.145293,43.284423],"type":"Point"}
}