{
  "type": "Feature",
  "properties": {
    "iso:country":"US",
    "sg:address":"12621 38th Avenue",
    "sg:city":"Corona",
    "sg:classifiers":[
        {
            "category":"Retail",
            "subcategory":"Auto Repair",
            "type":"Services"
        }
    ],
    "sg:phone":"+1 718 205 5807",
    "sg:postcode":"11368",
    "sg:province":"NY",
    "wof:name":"Alfonfo Auto Repair",
    "wof:placetype":"venue"
},
  "geometry": {"coordinates":[-73.842647,40.757466],"type":"Point"}
}