{
  "type": "Feature",
  "properties": {
    "iso:country":"US",
    "sg:address":"1702 Palmetto St",
    "sg:city":"Flushing",
    "sg:classifiers":[
        {
            "category":"Retail",
            "subcategory":"Self-service Laundry",
            "type":"Services"
        }
    ],
    "sg:phone":"+1 718 366 7077",
    "sg:postcode":"11385",
    "sg:province":"NY",
    "wof:name":"Jom Laundromat",
    "wof:placetype":"venue"
},
  "geometry": {"coordinates":[-73.907646,40.702741],"type":"Point"}
}