{
  "type": "Feature",
  "properties": {
    "addr:full":"172 Spring St New York NY 10012",
    "addr:housenumber":"172",
    "addr:postcode":"10012",
    "addr:street":"Spring St",
    "iso:country":"US",
    "sg:address":"172 Spring St",
    "sg:city":"New York",
    "sg:classifiers":[
        {
            "category":"Food & Beverages",
            "subcategory":"Groceries & Convenience Stores",
            "type":"Retail Goods"
        }
    ],
    "sg:phone":"+1 212 925 7131",
    "sg:postcode":"10012",
    "sg:province":"NY",
    "sg:website":"www.lebo.com",
    "wof:name":"Lebo",
    "wof:placetype":"venue"
},
  "geometry": {"coordinates":[-74.349001,40.724581],"type":"Point"}
}