{
  "type": "Feature",
  "properties": {
    "iso:country":"US",
    "sg:address":"2159 E 35th St",
    "sg:city":"Brooklyn",
    "sg:classifiers":[
        {
            "category":"Real Estate",
            "subcategory":"Real Estate Agent",
            "type":"Services"
        }
    ],
    "sg:phone":"+1 718 338 1537",
    "sg:postcode":"11234",
    "sg:province":"NY",
    "wof:name":"Douglas Manor Realty Corp",
    "wof:placetype":"venue"
},
  "geometry": {"coordinates":[-73.929205,40.607015],"type":"Point"}
}