{
  "type": "Feature",
  "properties": {
    "iso:country":"US",
    "sg:address":"1601 Gravesend Neck Rd Ste 12",
    "sg:city":"Brooklyn",
    "sg:classifiers":[
        {
            "category":"Real Estate",
            "subcategory":"Real Estate Services",
            "type":"Services"
        },
        {
            "category":"Real Estate",
            "subcategory":"Real Estate Agent",
            "type":"Services"
        }
    ],
    "sg:phone":"+1 718 234 9617",
    "sg:postcode":"11229",
    "sg:province":"NY",
    "sg:tags":[
        "home",
        "staging"
    ],
    "sg:website":"www.NordEastRealtyGroup.com",
    "wof:name":"Nord-East Realty Group",
    "wof:placetype":"venue"
},
  "geometry": {"coordinates":[-73.95433199999999,40.595404],"type":"Point"}
}