{
  "type": "Feature",
  "properties": {
    "addr:full":"6 Industrial Park Rd Plattsburgh NY 12944",
    "addr:housenumber":"6",
    "addr:postcode":"12944",
    "addr:street":"Industrial Park Rd",
    "iso:country":"US",
    "sg:address":"6 Industrial Park Rd",
    "sg:city":"Plattsburgh",
    "sg:classifiers":[
        {
            "category":"Manufacturing",
            "subcategory":"Metals",
            "type":"Manufacturing & Wholesale Goods"
        }
    ],
    "sg:phone":"+1   ",
    "sg:postcode":"12944",
    "sg:province":"NY",
    "sg:tags":[
        "steel",
        "frame",
        "door",
        "mfg"
    ],
    "wof:name":"Nadcor",
    "wof:placetype":"venue"
},
  "geometry": {"coordinates":[-73.489407,44.489843],"type":"Point"}
}