{
  "type": "Feature",
  "properties": {
    "addr:full":"10 Brentwood Dr Ithaca NY 14850",
    "addr:housenumber":"10",
    "addr:postcode":"14850",
    "addr:street":"Brentwood Dr",
    "iso:country":"US",
    "sg:address":"10 Brentwood Dr",
    "sg:city":"Ithaca",
    "sg:classifiers":[
        {
            "category":"Shopping",
            "subcategory":"Optical Goods",
            "type":"Retail Goods"
        }
    ],
    "sg:phone":"+1   ",
    "sg:postcode":"14850",
    "sg:province":"NY",
    "wof:name":"Glassworks Optical",
    "wof:placetype":"venue"
},
  "geometry": {"coordinates":[-76.463244,42.478704],"type":"Point"}
}