{
  "type": "Feature",
  "properties": {
    "addr:full":"408 E 82nd St New York NY 10028",
    "addr:housenumber":"408",
    "addr:postcode":"10028",
    "addr:street":"E 82Nd St",
    "iso:country":"US",
    "sg:address":"408 E 82nd St",
    "sg:city":"New York",
    "sg:classifiers":[
        {
            "category":"Education",
            "subcategory":"School",
            "type":"Public Place"
        }
    ],
    "sg:phone":"+1 212 288 1989",
    "sg:postcode":"10028",
    "sg:province":"NY",
    "wof:name":"2 B",
    "wof:placetype":"venue"
},
  "geometry": {"coordinates":[-73.949186,40.773354],"type":"Point"}
}