{
  "type": "Feature",
  "properties": {
    "iso:country":"US",
    "sg:address":"200 Broadway",
    "sg:city":"Troy",
    "sg:classifiers":[
        {
            "category":"Professional",
            "subcategory":"Management & Consulting",
            "type":"Services"
        }
    ],
    "sg:phone":"+1 518 272 9364",
    "sg:postcode":"12180",
    "sg:province":"NY",
    "sg:tags":[
        "consultant",
        "business"
    ],
    "wof:name":"Resource Advantage Inc",
    "wof:placetype":"venue"
},
  "geometry": {"coordinates":[-73.690888,42.731393],"type":"Point"}
}