{
  "type": "Feature",
  "properties": {
    "addr:full":"738 Leverett Ave Staten Island NY 10312",
    "addr:housenumber":"738",
    "addr:postcode":"10312",
    "addr:street":"Leverett Ave",
    "iso:country":"US",
    "sg:address":"738 Leverett Ave",
    "sg:city":"Staten Island",
    "sg:classifiers":[
        {
            "category":"Professional",
            "subcategory":"Accounting & Tax Preparation",
            "type":"Services"
        }
    ],
    "sg:phone":"+1 718 984 2397",
    "sg:postcode":"10312",
    "sg:province":"NY",
    "sg:tags":[
        "return",
        "filing"
    ],
    "wof:name":"Metro-Tax",
    "wof:placetype":"venue"
},
  "geometry": {"coordinates":[-74.172111,40.55434],"type":"Point"}
}