{
  "type": "Feature",
  "properties": {
    "iso:country":"US",
    "sg:address":"423 Central Park Ave",
    "sg:city":"Scarsdale",
    "sg:classifiers":[
        {
            "category":"Shopping",
            "subcategory":"Stationery & Office Supplies",
            "type":"Retail Goods"
        }
    ],
    "sg:phone":"+1   ",
    "sg:postcode":"10583",
    "sg:province":"NY",
    "wof:name":"Office Depot",
    "wof:placetype":"venue"
},
  "geometry": {"coordinates":[-73.810439,41.006995],"type":"Point"}
}