{
  "type": "Feature",
  "properties": {
    "iso:country":"US",
    "sg:address":"338 Mohawk Dr",
    "sg:city":"Fonda",
    "sg:classifiers":[
        {
            "category":"Restaurant",
            "type":"Food & Drink"
        }
    ],
    "sg:phone":"+1 518 829 7049",
    "sg:postcode":"12177",
    "sg:province":"NY",
    "sg:tags":[
        "delicatessen"
    ],
    "wof:name":"Tribes Hill Deli",
    "wof:placetype":"venue"
},
  "geometry": {"coordinates":[-74.29076000000001,42.951418],"type":"Point"}
}