{
  "type": "Feature",
  "properties": {
    "addr:full":"4 Metrotech Ctr Brooklyn NY 11201",
    "addr:housenumber":"4",
    "addr:postcode":"11201",
    "addr:street":"Metrotech Ctr",
    "iso:country":"US",
    "sg:address":"4 Metrotech Ctr",
    "sg:city":"Brooklyn",
    "sg:classifiers":[
        {
            "category":"Restaurant",
            "type":"Food & Drink"
        }
    ],
    "sg:menulink":"http://www.allmenus.com/ny/brooklyn/148200-subway/menu/",
    "sg:phone":"+1 718 596 6712",
    "sg:postcode":"11201",
    "sg:province":"NY",
    "sg:tags":[
        "american",
        "sandwich"
    ],
    "wof:name":"Subway",
    "wof:placetype":"venue"
},
  "geometry": {"coordinates":[-73.987182,40.693714],"type":"Point"}
}