{
  "type": "Feature",
  "properties": {
    "iso:country":"US",
    "sg:address":"6144 Rte 25A",
    "sg:city":"Wading River",
    "sg:classifiers":[
        {
            "category":"Health Services",
            "subcategory":"Health Practitioner",
            "type":"Services"
        }
    ],
    "sg:phone":"+1 631 929 3277",
    "sg:postcode":"11792",
    "sg:province":"NY",
    "sg:tags":[
        "therapist",
        "physical"
    ],
    "wof:name":"Sports Physical Therapy Of Ny",
    "wof:placetype":"venue"
},
  "geometry": {"coordinates":[-72.83553499999999,40.944462],"type":"Point"}
}