{
  "type": "Feature",
  "properties": {
    "addr:full":"451 E 84th St New York NY 10028",
    "addr:housenumber":"451",
    "addr:postcode":"10028",
    "addr:street":"E 84Th St",
    "iso:country":"US",
    "sg:address":"451 E 84th St",
    "sg:city":"New York",
    "sg:classifiers":[
        {
            "category":"Professional",
            "type":"Services"
        }
    ],
    "sg:phone":"+1 212 535 8242",
    "sg:postcode":"10028",
    "sg:province":"NY",
    "sg:tags":[
        "arranger",
        "music",
        "composer"
    ],
    "wof:name":"Dick Behrke Inc",
    "wof:placetype":"venue"
},
  "geometry": {"coordinates":[-73.948919,40.775162],"type":"Point"}
}