{
  "type": "Feature",
  "properties": {
    "addr:full":"3603 James St Syracuse NY 13206",
    "addr:housenumber":"3603",
    "addr:postcode":"13206",
    "addr:street":"James St",
    "iso:country":"US",
    "sg:address":"3603 James St",
    "sg:city":"Syracuse",
    "sg:classifiers":[
        {
            "category":"Personal",
            "subcategory":"Beauty Salon",
            "type":"Services"
        }
    ],
    "sg:phone":"+1 315 437 2580",
    "sg:postcode":"13206",
    "sg:province":"NY",
    "wof:name":"Scissar'd Hair & Nails",
    "wof:placetype":"venue"
},
  "geometry": {"coordinates":[-76.09613299999999,43.069328],"type":"Point"}
}