{
  "type": "Feature",
  "properties": {
    "addr:full":"90 Putnam Ave Brooklyn NY 11238",
    "addr:housenumber":"90",
    "addr:postcode":"11238",
    "addr:street":"Putnam Ave",
    "iso:country":"US",
    "sg:address":"90 Putnam Ave",
    "sg:city":"Brooklyn",
    "sg:classifiers":[
        {
            "category":"Organizations",
            "subcategory":"Religious Organization",
            "type":"Services"
        }
    ],
    "sg:phone":"+1 718 622 5447",
    "sg:postcode":"11238",
    "sg:province":"NY",
    "sg:tags":[
        "church"
    ],
    "wof:name":"Saint Peter Spiritual House",
    "wof:placetype":"venue"
},
  "geometry": {"coordinates":[-73.95846899999999,40.682956],"type":"Point"}
}