{
  "type": "Feature",
  "properties": {
    "addr:full":"7632 N State St Lowville NY 13367",
    "addr:housenumber":"7632",
    "addr:postcode":"13367",
    "addr:street":"N State St",
    "iso:country":"US",
    "sg:address":"7632 N State St",
    "sg:city":"Lowville",
    "sg:classifiers":[
        {
            "category":"Shopping",
            "type":"Retail Goods"
        }
    ],
    "sg:phone":"+1 315 376 2882",
    "sg:postcode":"13367",
    "sg:province":"NY",
    "sg:tags":[
        "art",
        "gallery",
        "dealer"
    ],
    "wof:name":"Doug Hoch Studio & Gallery",
    "wof:placetype":"venue"
},
  "geometry": {"coordinates":[-75.49241499999999,43.78676],"type":"Point"}
}