{
  "type": "Feature",
  "properties": {
    "addr:full":"54 East 13th Street Manhattan NY 10003",
    "addr:housenumber":"54",
    "addr:postcode":"10003",
    "addr:street":"East 13Th Street",
    "iso:country":"US",
    "sg:address":"54 East 13th Street",
    "sg:city":"Manhattan",
    "sg:classifiers":[
        {
            "category":"Bars & Pubs",
            "subcategory":"Lounge",
            "type":"Food & Drink"
        },
        {
            "category":"Restaurant",
            "type":"Food & Drink"
        }
    ],
    "sg:phone":"+1 212 477 1177",
    "sg:postcode":"10003",
    "sg:province":"NY",
    "sg:tags":[
        "korean",
        "karaoke"
    ],
    "sg:website":"www.nemonyc.com",
    "wof:name":"Nemo NYC",
    "wof:placetype":"venue"
},
  "geometry": {"coordinates":[-73.99154900000001,40.734202],"type":"Point"}
}