{
  "type": "Feature",
  "properties": {
    "iso:country":"US",
    "sg:address":"573 Warburton Ave",
    "sg:city":"Yonkers",
    "sg:classifiers":[
        {
            "category":"Organizations",
            "subcategory":"Membership Organization",
            "type":"Services"
        }
    ],
    "sg:phone":"+1   ",
    "sg:postcode":"10701",
    "sg:province":"NY",
    "wof:name":"Uniformed Fire Officers Assn",
    "wof:placetype":"venue"
},
  "geometry": {"coordinates":[-73.895141,40.956146],"type":"Point"}
}