{
  "type": "Feature",
  "properties": {
    "addr:full":"1230 Sheridan Ave Bronx NY 10456",
    "addr:housenumber":"1230",
    "addr:postcode":"10456",
    "addr:street":"Sheridan Ave",
    "iso:country":"US",
    "sg:address":"1230 Sheridan Ave",
    "sg:city":"Bronx",
    "sg:classifiers":[
        {
            "category":"Communications",
            "subcategory":"Radio Station",
            "type":"Services"
        }
    ],
    "sg:phone":"+1 718 878 6852",
    "sg:postcode":"10456",
    "sg:province":"NY",
    "wof:name":"Radio Alpha Y Omega",
    "wof:placetype":"venue"
},
  "geometry": {"coordinates":[-73.916006,40.834542],"type":"Point"}
}