{
  "type": "Feature",
  "properties": {
    "iso:country":"US",
    "sg:address":"24 Main St",
    "sg:city":"Highland",
    "sg:classifiers":[
        {
            "category":"Building & Trades",
            "subcategory":"Construction",
            "type":"Services"
        }
    ],
    "sg:phone":"+1 845 691 7761",
    "sg:postcode":"12528",
    "sg:province":"NY",
    "sg:tags":[
        "contractor"
    ],
    "wof:name":"William J Farrell Stoneworks",
    "wof:placetype":"venue"
},
  "geometry": {"coordinates":[-73.96445,41.71932],"type":"Point"}
}