{
  "type": "Feature",
  "properties": {
    "iso:country":"US",
    "sg:address":"2627 Hylan Boulevard",
    "sg:city":"Staten Island",
    "sg:classifiers":[
        {
            "category":"Health Services",
            "subcategory":"Dentist",
            "type":"Services"
        }
    ],
    "sg:phone":"+1 718 987 3131",
    "sg:postcode":"10306",
    "sg:province":"NY",
    "wof:name":"John M Carlo DDS",
    "wof:placetype":"venue"
},
  "geometry": {"coordinates":[-74.112432,40.567886],"type":"Point"}
}