{
  "type": "Feature",
  "properties": {
    "addr:full":"113 E 90th St New York NY 10128",
    "addr:housenumber":"113",
    "addr:postcode":"10128",
    "addr:street":"E 90Th St",
    "iso:country":"US",
    "sg:address":"113 E 90th St",
    "sg:city":"New York",
    "sg:classifiers":[
        {
            "category":"Arts & Performance",
            "subcategory":"Art Gallery",
            "type":"Entertainment"
        }
    ],
    "sg:phone":"+1 212 987 4997",
    "sg:postcode":"10128",
    "sg:province":"NY",
    "wof:name":"Stone Allan Gallery",
    "wof:placetype":"venue"
},
  "geometry": {"coordinates":[-73.954803,40.7826],"type":"Point"}
}