{
  "type": "Feature",
  "properties": {
    "addr:full":"6848 E Genesee St Fayetteville NY 13066",
    "addr:housenumber":"6848",
    "addr:postcode":"13066",
    "addr:street":"E Genesee St",
    "iso:country":"US",
    "sg:address":"6848 E Genesee St",
    "sg:city":"Fayetteville",
    "sg:classifiers":[
        {
            "category":"Insurance",
            "subcategory":"Hazard Insurance",
            "type":"Services"
        }
    ],
    "sg:phone":"+1 315 445 0491",
    "sg:postcode":"13066",
    "sg:province":"NY",
    "sg:tags":[
        "commercial",
        "business"
    ],
    "wof:name":"Impact Business Machines Inc",
    "wof:placetype":"venue"
},
  "geometry": {"coordinates":[-76.048393,43.02958],"type":"Point"}
}