{
  "type": "Feature",
  "properties": {
    "addr:full":"4802 10th Ave Brooklyn NY 11219",
    "addr:housenumber":"4802",
    "addr:postcode":"11219",
    "addr:street":"10Th Ave",
    "iso:country":"US",
    "sg:address":"4802 10th Ave",
    "sg:city":"Brooklyn",
    "sg:classifiers":[
        {
            "category":"Health Services",
            "subcategory":"Hospital",
            "type":"Services"
        }
    ],
    "sg:phone":"+1 718 283 7686",
    "sg:postcode":"11219",
    "sg:province":"NY",
    "sg:tags":[
        "general"
    ],
    "wof:name":"Cardithrcic Srgcal Assoc PC NY",
    "wof:placetype":"venue"
},
  "geometry": {"coordinates":[-73.998772,40.639074],"type":"Point"}
}