{
  "type": "Feature",
  "properties": {
    "addr:full":"460 Smith St Farmingdale NY 11735",
    "addr:housenumber":"460",
    "addr:postcode":"11735",
    "addr:street":"Smith St",
    "iso:country":"US",
    "sg:address":"460 Smith St",
    "sg:city":"Farmingdale",
    "sg:classifiers":[
        {
            "category":"Manufacturing",
            "subcategory":"Building Materials",
            "type":"Manufacturing & Wholesale Goods"
        }
    ],
    "sg:phone":"+1   ",
    "sg:postcode":"11735",
    "sg:province":"NY",
    "sg:tags":[
        "metal",
        "mfg"
    ],
    "sg:website":"www.kellywindows.com",
    "wof:name":"Kelly Window Systems Inc",
    "wof:placetype":"venue"
},
  "geometry": {"coordinates":[-73.41180799999999,40.756532],"type":"Point"}
}