{
  "type": "Feature",
  "properties": {
    "addr:full":"2245 Co Rte 2 Richland NY 13144",
    "addr:housenumber":"2245",
    "addr:postcode":"13144",
    "addr:street":"Co Rte 2",
    "iso:country":"US",
    "sg:address":"2245 Co Rte 2",
    "sg:city":"Richland",
    "sg:classifiers":[
        {
            "category":"Personal",
            "subcategory":"Beauty Salon",
            "type":"Services"
        }
    ],
    "sg:phone":"+1 315 298 5233",
    "sg:postcode":"13144",
    "sg:province":"NY",
    "wof:name":"Linda's Beauty Salon",
    "wof:placetype":"venue"
},
  "geometry": {"coordinates":[-76.022035,43.576318],"type":"Point"}
}