{
  "type": "Feature",
  "properties": {
    "addr:full":"111 Nassau St New York NY 10038",
    "addr:housenumber":"111",
    "addr:postcode":"10038",
    "addr:street":"Nassau St",
    "iso:country":"US",
    "sg:address":"111 Nassau St",
    "sg:city":"New York",
    "sg:classifiers":[
        {
            "category":"Shopping",
            "subcategory":"Optical Goods",
            "type":"Retail Goods"
        }
    ],
    "sg:phone":"+1   ",
    "sg:postcode":"10038",
    "sg:province":"NY",
    "wof:name":"Pildes Optical",
    "wof:placetype":"venue"
},
  "geometry": {"coordinates":[-74.006719,40.711104],"type":"Point"}
}