{
  "type": "Feature",
  "properties": {
    "addr:full":"718 Henderson Ave Staten Island NY 10310",
    "addr:housenumber":"718",
    "addr:postcode":"10310",
    "addr:street":"Henderson Ave",
    "iso:country":"US",
    "sg:address":"718 Henderson Ave",
    "sg:city":"Staten Island",
    "sg:classifiers":[
        {
            "category":"Wholesale",
            "subcategory":"Groceries",
            "type":"Manufacturing & Wholesale Goods"
        }
    ],
    "sg:phone":"+1 718 720 9672",
    "sg:postcode":"10310",
    "sg:province":"NY",
    "wof:name":"Rivera Grocery",
    "wof:placetype":"venue"
},
  "geometry": {"coordinates":[-74.11499499999999,40.637291],"type":"Point"}
}