{
  "type": "Feature",
  "properties": {
    "iso:country":"US",
    "sg:address":"1045 Lakeville Rd",
    "sg:city":"New Hyde Park",
    "sg:classifiers":[
        {
            "category":"Education",
            "subcategory":"Dance Studio",
            "type":"Public Place"
        }
    ],
    "sg:phone":"+1 516 775 2523",
    "sg:postcode":"11040",
    "sg:province":"NY",
    "sg:tags":[
        "instruction",
        "dancing"
    ],
    "wof:name":"Kristines School Of Dance",
    "wof:placetype":"venue"
},
  "geometry": {"coordinates":[-73.692944,40.742032],"type":"Point"}
}