{
  "type": "Feature",
  "properties": {
    "addr:full":"145 E 98th St New York NY 10029",
    "addr:housenumber":"145",
    "addr:postcode":"10029",
    "addr:street":"E 98Th St",
    "iso:country":"US",
    "sg:address":"145 E 98th St",
    "sg:city":"New York",
    "sg:classifiers":[
        {
            "category":"Home & Garden",
            "subcategory":"Furniture",
            "type":"Retail Goods"
        }
    ],
    "sg:phone":"+1 347 240 7305",
    "sg:postcode":"10029",
    "sg:province":"NY",
    "sg:tags":[
        "store"
    ],
    "wof:name":"Peoples Choice",
    "wof:placetype":"venue"
},
  "geometry": {"coordinates":[-73.94973899999999,40.787218],"type":"Point"}
}