{
  "type": "Feature",
  "properties": {
    "iso:country":"US",
    "sg:address":"141 Ulster Ave",
    "sg:city":"Saugerties",
    "sg:classifiers":[
        {
            "category":"Wholesale",
            "subcategory":"Computers",
            "type":"Manufacturing & Wholesale Goods"
        },
        {
            "category":"Shopping",
            "subcategory":"Computers & Home Electronics",
            "type":"Retail Goods"
        }
    ],
    "sg:phone":"+1 845 246 0458",
    "sg:postcode":"12477",
    "sg:province":"NY",
    "sg:tags":[
        "equipment",
        "dealer"
    ],
    "sg:website":"www.moorhuscomputers.com",
    "wof:name":"Moorhus Computers",
    "wof:placetype":"venue"
},
  "geometry": {"coordinates":[-73.960157,42.08081],"type":"Point"}
}