{
  "type": "Feature",
  "properties": {
    "addr:full":"233 Elmira Rd Ithaca NY 14850",
    "addr:housenumber":"233",
    "addr:postcode":"14850",
    "addr:street":"Elmira Rd",
    "iso:country":"US",
    "sg:address":"233 Elmira Rd",
    "sg:city":"Ithaca",
    "sg:classifiers":[
        {
            "category":"Shopping",
            "subcategory":"Gifts & Souvenirs",
            "type":"Retail Goods"
        }
    ],
    "sg:phone":"+1 607 272 3996",
    "sg:postcode":"14850",
    "sg:province":"NY",
    "sg:tags":[
        "shop",
        "greeting",
        "card"
    ],
    "wof:name":"4 Seasons Cards And Collectibles",
    "wof:placetype":"venue"
},
  "geometry": {"coordinates":[-76.505813,42.429368],"type":"Point"}
}