{
  "type": "Feature",
  "properties": {
    "addr:full":"11318 Cooper St Cato NY 13033",
    "addr:housenumber":"11318",
    "addr:postcode":"13033",
    "addr:street":"Cooper St",
    "iso:country":"US",
    "sg:address":"11318 Cooper St",
    "sg:city":"Cato",
    "sg:classifiers":[
        {
            "category":"Social Services",
            "subcategory":"Child Care",
            "type":"Services"
        }
    ],
    "sg:phone":"+1 315 626 2847",
    "sg:postcode":"13033",
    "sg:province":"NY",
    "wof:name":"Cooper Street Kids Daycare",
    "wof:placetype":"venue"
},
  "geometry": {"coordinates":[-76.62811600000001,43.144874],"type":"Point"}
}