{
  "type": "Feature",
  "properties": {
    "addr:full":"1168 Maryvale Dr Buffalo NY 14225",
    "addr:housenumber":"1168",
    "addr:postcode":"14225",
    "addr:street":"Maryvale Dr",
    "iso:country":"US",
    "sg:address":"1168 Maryvale Dr",
    "sg:city":"Buffalo",
    "sg:classifiers":[
        {
            "category":"Recreation",
            "type":"Entertainment"
        }
    ],
    "sg:phone":"+1 585 615 0057",
    "sg:postcode":"14225",
    "sg:province":"NY",
    "sg:tags":[
        "entertainers-family",
        "business"
    ],
    "wof:name":"The Crusaders Drum Corps Inc",
    "wof:placetype":"venue"
},
  "geometry": {"coordinates":[-78.74527,42.933231],"type":"Point"}
}