{
  "type": "Feature",
  "properties": {
    "addr:full":"13 Caroline St Saratoga Springs NY 12866",
    "addr:housenumber":"13",
    "addr:postcode":"12866",
    "addr:street":"Caroline St",
    "iso:country":"US",
    "sg:address":"13 Caroline St",
    "sg:city":"Saratoga Springs",
    "sg:classifiers":[
        {
            "category":"Professional",
            "type":"Services"
        }
    ],
    "sg:phone":"+1 518 581 1316",
    "sg:postcode":"12866",
    "sg:province":"NY",
    "sg:tags":[
        "establishment"
    ],
    "wof:name":"Thirteen",
    "wof:placetype":"venue"
},
  "geometry": {"coordinates":[-73.784108,43.082069],"type":"Point"}
}