{
  "type": "Feature",
  "properties": {
    "addr:full":"177 Prince St New York NY 10012",
    "addr:housenumber":"177",
    "addr:postcode":"10012",
    "addr:street":"Prince St",
    "iso:country":"US",
    "sg:address":"177 Prince St",
    "sg:city":"New York",
    "sg:classifiers":[
        {
            "category":"Social Services",
            "type":"Services"
        }
    ],
    "sg:phone":"+1 212 712 7133",
    "sg:postcode":"10012",
    "sg:province":"NY",
    "sg:tags":[
        "worker"
    ],
    "wof:name":"Nancy Goldman Csw",
    "wof:placetype":"venue"
},
  "geometry": {"coordinates":[-74.002055,40.726391],"type":"Point"}
}