{
  "type": "Feature",
  "properties": {
    "addr:full":"111 Central Park Ave Hartsdale NY 10530",
    "addr:housenumber":"111",
    "addr:postcode":"10530",
    "addr:street":"Central Park Ave",
    "iso:country":"US",
    "sg:address":"111 Central Park Ave",
    "sg:city":"Hartsdale",
    "sg:classifiers":[
        {
            "category":"Professional",
            "subcategory":"Lawyer & Legal Services",
            "type":"Services"
        }
    ],
    "sg:phone":"+1 914 761 3111",
    "sg:postcode":"10530",
    "sg:province":"NY",
    "sg:tags":[
        "attorney"
    ],
    "wof:name":"Jeffrey S Antin",
    "wof:placetype":"venue"
},
  "geometry": {"coordinates":[-73.80025000000001,41.016865],"type":"Point"}
}