{
  "type": "Feature",
  "properties": {
    "iso:country":"US",
    "sg:address":"1353 E Gun Hill Rd",
    "sg:city":"Bronx",
    "sg:classifiers":[
        {
            "category":"Banks & Credit Unions",
            "subcategory":"Bank",
            "type":"Services"
        }
    ],
    "sg:phone":"+1 718 515 5112",
    "sg:postcode":"10469",
    "sg:province":"NY",
    "sg:tags":[
        "depository",
        "banking",
        "check",
        "cashing"
    ],
    "wof:name":"Right Check Cashing",
    "wof:placetype":"venue"
},
  "geometry": {"coordinates":[-73.846107,40.870493],"type":"Point"}
}