{
  "type": "Feature",
  "properties": {
    "iso:country":"US",
    "sg:address":"278 87th St",
    "sg:city":"Brooklyn",
    "sg:classifiers":[
        {
            "category":"Bakery",
            "type":"Food & Drink"
        }
    ],
    "sg:phone":"+1 718 833 1626",
    "sg:postcode":"11209",
    "sg:province":"NY",
    "sg:website":"www.ivybakery.com",
    "wof:name":"Ivy Bakery",
    "wof:placetype":"venue"
},
  "geometry": {"coordinates":[-74.031741,40.622809],"type":"Point"}
}