{
  "type": "Feature",
  "properties": {
    "iso:country":"US",
    "sg:address":"499 Co Rd 76",
    "sg:city":"Patchogue",
    "sg:classifiers":[
        {
            "category":"Restaurant",
            "type":"Food & Drink"
        }
    ],
    "sg:phone":"+1 631 475 2070",
    "sg:postcode":"11788",
    "sg:province":"NY",
    "wof:name":"KOW Loong Kitchen",
    "wof:placetype":"venue"
},
  "geometry": {"coordinates":[-73.20289099999999,40.825482],"type":"Point"}
}