{
  "type": "Feature",
  "properties": {
    "addr:full":"588 Armstrong Ave Staten Island NY 10308",
    "addr:housenumber":"588",
    "addr:postcode":"10308",
    "addr:street":"Armstrong Ave",
    "iso:country":"US",
    "sg:address":"588 Armstrong Ave",
    "sg:city":"Staten Island",
    "sg:classifiers":[
        {
            "category":"Building & Trades",
            "subcategory":"Plumbing",
            "type":"Services"
        }
    ],
    "sg:phone":"+1 718 227 1989",
    "sg:postcode":"10308",
    "sg:province":"NY",
    "sg:tags":[
        "heating",
        "contractor"
    ],
    "wof:name":"Expert Service",
    "wof:placetype":"venue"
},
  "geometry": {"coordinates":[-74.160056,40.54833],"type":"Point"}
}