{
  "type": "Feature",
  "properties": {
    "addr:full":"50 W Main St Patchogue NY 11772",
    "addr:housenumber":"50",
    "addr:postcode":"11772",
    "addr:street":"W Main St",
    "iso:country":"US",
    "sg:address":"50 W Main St",
    "sg:city":"Patchogue",
    "sg:classifiers":[
        {
            "category":"Shopping",
            "subcategory":"Clothing, Apparel, & Fashions",
            "type":"Retail Goods"
        }
    ],
    "sg:phone":"+1   ",
    "sg:postcode":"11772",
    "sg:province":"NY",
    "sg:tags":[
        "uniform"
    ],
    "wof:name":"Uniforms N Things",
    "wof:placetype":"venue"
},
  "geometry": {"coordinates":[-73.01603900000001,40.765687],"type":"Point"}
}