{
  "type": "Feature",
  "properties": {
    "iso:country":"US",
    "sg:address":"241 Kenmore Ave",
    "sg:city":"Syracuse",
    "sg:classifiers":[
        {
            "category":"Building & Trades",
            "subcategory":"Cleaning & Sanitation",
            "type":"Services"
        }
    ],
    "sg:phone":"+1   ",
    "sg:postcode":"13205",
    "sg:province":"NY",
    "sg:tags":[
        "maintenance"
    ],
    "wof:name":"Upscale Janitorial Service",
    "wof:placetype":"venue"
},
  "geometry": {"coordinates":[-76.152,43.013805],"type":"Point"}
}