{
  "type": "Feature",
  "properties": {
    "addr:full":"16023 Rockaway Blvd Ste 6 Jamaica NY 11434",
    "addr:housenumber":"16023",
    "addr:postcode":"11434",
    "addr:street":"Rockaway Blvd Ste 6",
    "iso:country":"US",
    "sg:address":"16023 Rockaway Blvd Ste 6",
    "sg:city":"Jamaica",
    "sg:classifiers":[
        {
            "category":"Transit Center",
            "subcategory":"Freight",
            "type":"Transportation"
        }
    ],
    "sg:phone":"+1 718 977 8033",
    "sg:postcode":"11434",
    "sg:province":"NY",
    "sg:tags":[
        "air",
        "cargo",
        "express",
        "forwarding",
        "package"
    ],
    "sg:website":"http://www.timetoair.com",
    "wof:name":"Time To Air Corp",
    "wof:placetype":"venue"
},
  "geometry": {"coordinates":[-73.77512400000001,40.660151],"type":"Point"}
}