{
  "type": "Feature",
  "properties": {
    "addr:full":"1 Smith Haven Mall Lake Grove NY 11755",
    "addr:housenumber":"1",
    "addr:postcode":"11755",
    "addr:street":"Smith Haven Mall",
    "iso:country":"US",
    "sg:address":"1 Smith Haven Mall",
    "sg:city":"Lake Grove",
    "sg:classifiers":[
        {
            "category":"Shopping",
            "subcategory":"Shoes",
            "type":"Retail Goods"
        }
    ],
    "sg:phone":"+1 631 382 5051",
    "sg:postcode":"11755",
    "sg:province":"NY",
    "sg:tags":[
        "store"
    ],
    "sg:website":"www.striderite.com",
    "wof:name":"Stride Rite",
    "wof:placetype":"venue"
},
  "geometry": {"coordinates":[-73.12555399999999,40.863734],"type":"Point"}
}