{
  "type": "Feature",
  "properties": {
    "iso:country":"US",
    "sg:address":"4135 Laconia Ave",
    "sg:city":"Bronx",
    "sg:classifiers":[
        {
            "category":"Shopping",
            "subcategory":"Gifts & Souvenirs",
            "type":"Retail Goods"
        }
    ],
    "sg:phone":"+1 718 652 8961",
    "sg:postcode":"10466",
    "sg:province":"NY",
    "sg:tags":[
        "shop"
    ],
    "wof:name":"Orion Newsstand",
    "wof:placetype":"venue"
},
  "geometry": {"coordinates":[-73.84689,40.88802],"type":"Point"}
}