{
  "type": "Feature",
  "properties": {
    "addr:full":"4438 de Reimer Ave Bronx NY 10466",
    "addr:housenumber":"4438",
    "addr:postcode":"10466",
    "addr:street":"De Reimer Ave",
    "iso:country":"US",
    "sg:address":"4438 de Reimer Ave",
    "sg:city":"Bronx",
    "sg:classifiers":[
        {
            "category":"Professional",
            "type":"Services"
        }
    ],
    "sg:phone":"+1 718 653 0898",
    "sg:postcode":"10466",
    "sg:province":"NY",
    "sg:tags":[
        "establishment"
    ],
    "wof:name":"Direct Commerce Inc",
    "wof:placetype":"venue"
},
  "geometry": {"coordinates":[-73.845344,40.899904],"type":"Point"}
}