{
  "type": "Feature",
  "properties": {
    "addr:full":"13419 166th Pl Apt 7C Jamaica NY 11434",
    "addr:housenumber":"13419;7c",
    "addr:postcode":"11434",
    "addr:street":"166Th Pl Apt",
    "iso:country":"US",
    "sg:address":"13419 166th Pl Apt 7C",
    "sg:city":"Jamaica",
    "sg:classifiers":[
        {
            "category":"Real Estate",
            "subcategory":"Surveying",
            "type":"Services"
        }
    ],
    "sg:phone":"+1 718 527 6742",
    "sg:postcode":"11434",
    "sg:province":"NY",
    "sg:tags":[
        "planning",
        "land"
    ],
    "wof:name":"Urban Philanthropy Inc",
    "wof:placetype":"venue"
},
  "geometry": {"coordinates":[-73.773506,40.673036],"type":"Point"}
}