{
  "type": "Feature",
  "properties": {
    "addr:full":"631 S Mountain Rd New City NY 10956",
    "addr:housenumber":"631",
    "addr:postcode":"10956",
    "addr:street":"S Mountain Rd",
    "iso:country":"US",
    "sg:address":"631 S Mountain Rd",
    "sg:city":"New City",
    "sg:classifiers":[
        {
            "category":"Building & Trades",
            "subcategory":"Construction",
            "type":"Services"
        }
    ],
    "sg:phone":"+1 845 634 3416",
    "sg:postcode":"10956",
    "sg:province":"NY",
    "sg:tags":[
        "house"
    ],
    "wof:name":"Additions Unlimited Inc",
    "wof:placetype":"venue"
},
  "geometry": {"coordinates":[-73.974164,41.181396],"type":"Point"}
}