{
  "type": "Feature",
  "properties": {
    "addr:full":"152 W 57th Street New York NY 10019",
    "addr:housenumber":"152",
    "addr:postcode":"10019",
    "addr:street":"W 57Th Street",
    "iso:country":"US",
    "sg:address":"152 W 57th Street",
    "sg:city":"New York",
    "sg:classifiers":[
        {
            "category":"Banks & Credit Unions",
            "subcategory":"Investment Brokerage",
            "type":"Services"
        }
    ],
    "sg:phone":"+1 646 778 4699",
    "sg:postcode":"10019",
    "sg:province":"NY",
    "sg:tags":[
        "investing"
    ],
    "wof:name":"Lionston Capital Management",
    "wof:placetype":"venue"
},
  "geometry": {"coordinates":[-73.98577899999999,40.765422],"type":"Point"}
}