{
  "type": "Feature",
  "properties": {
    "iso:country":"US",
    "sg:address":"15 Prospect St",
    "sg:city":"Rouses Point",
    "sg:classifiers":[
        {
            "category":"Autos & Motor Vehicles",
            "subcategory":"Auto Supplies",
            "type":"Retail Goods"
        }
    ],
    "sg:phone":"+1 518 297 5433",
    "sg:postcode":"12979",
    "sg:province":"NY",
    "sg:tags":[
        "automobile",
        "parts"
    ],
    "wof:name":"Dave's Performance Ctr",
    "wof:placetype":"venue"
},
  "geometry": {"coordinates":[-73.382161,44.992074],"type":"Point"}
}