{
  "type": "Feature",
  "properties": {
    "iso:country":"US",
    "sg:address":"4475 Henry Hudson Pkwy W",
    "sg:city":"Bronx",
    "sg:classifiers":[
        {
            "category":"Retail",
            "subcategory":"Repair Shop",
            "type":"Services"
        }
    ],
    "sg:phone":"+1 718 884 4344",
    "sg:postcode":"10471",
    "sg:province":"NY",
    "sg:tags":[
        "lock",
        "locksmith"
    ],
    "wof:name":"Hi Tech Locksmith",
    "wof:placetype":"venue"
},
  "geometry": {"coordinates":[-73.908782,40.891781],"type":"Point"}
}