{
  "type": "Feature",
  "properties": {
    "addr:full":"31 Beechwood Ave Port Washington NY 11050",
    "addr:housenumber":"31",
    "addr:postcode":"11050",
    "addr:street":"Beechwood Ave",
    "iso:country":"US",
    "sg:address":"31 Beechwood Ave",
    "sg:city":"Port Washington",
    "sg:classifiers":[
        {
            "category":"Retail",
            "subcategory":"Auto Repair",
            "type":"Services"
        },
        {
            "category":"Wholesale",
            "subcategory":"Auto Parts",
            "type":"Manufacturing & Wholesale Goods"
        }
    ],
    "sg:phone":"+1 516 944 3149",
    "sg:postcode":"11050",
    "sg:province":"NY",
    "sg:tags":[
        "repairing",
        "automobile",
        "radiator"
    ],
    "wof:name":"Radiator Service Inc",
    "wof:placetype":"venue"
},
  "geometry": {"coordinates":[-73.684195,40.824699],"type":"Point"}
}