{
  "type": "Feature",
  "properties": {
    "iso:country":"US",
    "sg:address":"4763 Main St",
    "sg:city":"Buffalo",
    "sg:classifiers":[
        {
            "category":"Health Services",
            "subcategory":"Doctor",
            "type":"Services"
        }
    ],
    "sg:phone":"+1   ",
    "sg:postcode":"14226",
    "sg:province":"NY",
    "sg:tags":[
        "medical"
    ],
    "wof:name":"Crofts John",
    "wof:placetype":"venue"
},
  "geometry": {"coordinates":[-78.775155,42.960642],"type":"Point"}
}