{
  "type": "Feature",
  "properties": {
    "iso:country":"US",
    "sg:address":"220 E 161st St",
    "sg:city":"Bronx",
    "sg:classifiers":[
        {
            "category":"Shopping",
            "subcategory":"Shoes",
            "type":"Retail Goods"
        }
    ],
    "sg:phone":"+1 718 588 9641",
    "sg:postcode":"10451",
    "sg:province":"NY",
    "wof:name":"Fabco Shoes 48",
    "wof:placetype":"venue"
},
  "geometry": {"coordinates":[-73.92048200000001,40.826155],"type":"Point"}
}