{
  "type": "Feature",
  "properties": {
    "addr:full":"239 E 84th St Ste 1E New York NY 10028",
    "addr:housenumber":"239",
    "addr:postcode":"10028",
    "addr:street":"E 84Th St Ste 1E",
    "iso:country":"US",
    "sg:address":"239 E 84th St Ste 1E",
    "sg:city":"New York",
    "sg:classifiers":[
        {
            "category":"Real Estate",
            "subcategory":"Real Estate Services",
            "type":"Services"
        }
    ],
    "sg:phone":"+1 212 300 5472",
    "sg:postcode":"10028",
    "sg:province":"NY",
    "sg:website":"www.prozhanrealty.com",
    "wof:name":"Prozhan Realty",
    "wof:placetype":"venue"
},
  "geometry": {"coordinates":[-73.953288,40.77706],"type":"Point"}
}