{
  "type": "Feature",
  "properties": {
    "iso:country":"US",
    "sg:address":"42 Smiths Ln",
    "sg:city":"Commack",
    "sg:classifiers":[
        {
            "category":"Building & Trades",
            "subcategory":"Landscaping Services",
            "type":"Services"
        }
    ],
    "sg:phone":"+1 631 864 4218",
    "sg:postcode":"11725",
    "sg:province":"NY",
    "sg:tags":[
        "tree"
    ],
    "wof:name":"Anthony's Tree Service",
    "wof:placetype":"venue"
},
  "geometry": {"coordinates":[-73.277778,40.84098],"type":"Point"}
}