{
  "type": "Feature",
  "properties": {
    "addr:full":"727 Flushing Ave Brooklyn NY 11206",
    "addr:housenumber":"727",
    "addr:postcode":"11206",
    "addr:street":"Flushing Ave",
    "iso:country":"US",
    "sg:address":"727 Flushing Ave",
    "sg:city":"Brooklyn",
    "sg:classifiers":[
        {
            "category":"Home & Garden",
            "subcategory":"Hardware",
            "type":"Retail Goods"
        }
    ],
    "sg:phone":"+1 718 388 4424",
    "sg:postcode":"11206",
    "sg:province":"NY",
    "sg:tags":[
        "covering",
        "carpeting",
        "floor"
    ],
    "wof:name":"Aguadilla Floor Covering",
    "wof:placetype":"venue"
},
  "geometry": {"coordinates":[-73.943398,40.7006],"type":"Point"}
}