{
  "type": "Feature",
  "properties": {
    "addr:full":"782 Co Rd 52 Greenwich NY 12834",
    "addr:housenumber":"782;52",
    "addr:postcode":"12834",
    "addr:street":"Co Rd",
    "iso:country":"US",
    "sg:address":"782 Co Rd 52",
    "sg:city":"Greenwich",
    "sg:classifiers":[
        {
            "category":"Manufacturing",
            "subcategory":"Metals",
            "type":"Manufacturing & Wholesale Goods"
        }
    ],
    "sg:phone":"+1 518 692 7642",
    "sg:postcode":"12834",
    "sg:province":"NY",
    "sg:tags":[
        "production",
        "grinding"
    ],
    "wof:name":"Karlson Glass Works",
    "wof:placetype":"venue"
},
  "geometry": {"coordinates":[-73.493073,43.139229],"type":"Point"}
}