{
  "type": "Feature",
  "properties": {
    "iso:country":"US",
    "sg:address":"1389 N Shore Rd",
    "sg:city":"Hadley",
    "sg:classifiers":[
        {
            "category":"Building & Trades",
            "subcategory":"Construction",
            "type":"Services"
        }
    ],
    "sg:phone":"+1 518 696 4293",
    "sg:postcode":"12835",
    "sg:province":"NY",
    "sg:tags":[
        "house"
    ],
    "wof:name":"Sharmor",
    "wof:placetype":"venue"
},
  "geometry": {"coordinates":[-74.029403,43.28969],"type":"Point"}
}