{
  "type": "Feature",
  "properties": {
    "iso:country":"US",
    "sg:address":"2271 Kraft Rd",
    "sg:city":"Ithaca",
    "sg:classifiers":[
        {
            "category":"Travel",
            "subcategory":"Campground",
            "type":"Entertainment"
        }
    ],
    "sg:phone":"+1 607 387 9225",
    "sg:postcode":"14850",
    "sg:province":"NY",
    "sg:tags":[
        "trailer"
    ],
    "wof:name":"Spruce Row Campsite",
    "wof:placetype":"venue"
},
  "geometry": {"coordinates":[-76.578547,42.518609],"type":"Point"}
}