{
  "type": "Feature",
  "properties": {
    "iso:country":"US",
    "sg:address":"4207 Recreation Dr",
    "sg:city":"Canandaigua",
    "sg:phone":"+1 585 394 3430",
    "sg:postcode":"14424",
    "sg:province":"NY",
    "sg:website":"http://www.applebees.com",
    "wof:name":"Applebee's",
    "wof:placetype":"venue"
},
  "geometry": {"coordinates":[-77.239515,42.87322],"type":"Point"}
}