{
  "type": "Feature",
  "properties": {
    "addr:full":"1735 E 45th St Brooklyn NY 11234",
    "addr:housenumber":"1735",
    "addr:postcode":"11234",
    "addr:street":"E 45Th St",
    "iso:country":"US",
    "sg:address":"1735 E 45th St",
    "sg:city":"Brooklyn",
    "sg:classifiers":[
        {
            "category":"Health Services",
            "subcategory":"Doctor",
            "type":"Services"
        }
    ],
    "sg:phone":"+1 718 377 3334",
    "sg:postcode":"11234",
    "sg:province":"NY",
    "sg:tags":[
        "dentist"
    ],
    "wof:name":"Family Dentistry",
    "wof:placetype":"venue"
},
  "geometry": {"coordinates":[-73.931575,40.618334],"type":"Point"}
}