{
  "type": "Feature",
  "properties": {
    "iso:country":"US",
    "sg:address":"118 Lester Clark Rd",
    "sg:city":"Newburgh",
    "sg:classifiers":[
        {
            "category":"Retail",
            "subcategory":"Repair Shop",
            "type":"Services"
        }
    ],
    "sg:phone":"+1 845 568 0139",
    "sg:postcode":"12550",
    "sg:province":"NY",
    "sg:tags":[
        "related"
    ],
    "wof:name":"Mr Mailbox & Co",
    "wof:placetype":"venue"
},
  "geometry": {"coordinates":[-74.03316100000001,41.581268],"type":"Point"}
}