{
  "type": "Feature",
  "properties": {
    "addr:full":"4 E 1st St New York NY 10003",
    "addr:housenumber":"4",
    "addr:postcode":"10003",
    "addr:street":"E 1St St",
    "iso:country":"US",
    "sg:address":"4 E 1st St",
    "sg:city":"New York",
    "sg:classifiers":[
        {
            "category":"Real Estate",
            "subcategory":"Real Estate Operator",
            "type":"Services"
        }
    ],
    "sg:phone":"+1 212 228 2693",
    "sg:postcode":"10003",
    "sg:province":"NY",
    "sg:tags":[
        "apartment"
    ],
    "wof:name":"Henry Phipps Plaza West",
    "wof:placetype":"venue"
},
  "geometry": {"coordinates":[-73.992029,40.724939],"type":"Point"}
}