{
  "type": "Feature",
  "properties": {
    "iso:country":"US",
    "sg:address":"526 W 47th St",
    "sg:city":"New York",
    "sg:classifiers":[
        {
            "category":"Restaurant",
            "type":"Food & Drink"
        }
    ],
    "sg:phone":"+1 212 397 1137",
    "sg:postcode":"10036",
    "sg:province":"NY",
    "sg:tags":[
        "mexican"
    ],
    "wof:name":"La Rosita",
    "wof:placetype":"venue"
},
  "geometry": {"coordinates":[-73.99432299999999,40.763216],"type":"Point"}
}