{
  "type": "Feature",
  "properties": {
    "addr:full":"87 Croton Ave Ossining NY 10562",
    "addr:housenumber":"87",
    "addr:postcode":"10562",
    "addr:street":"Croton Ave",
    "iso:country":"US",
    "sg:address":"87 Croton Ave",
    "sg:city":"Ossining",
    "sg:classifiers":[
        {
            "category":"Restaurant",
            "type":"Food & Drink"
        }
    ],
    "sg:phone":"+1   ",
    "sg:postcode":"10562",
    "sg:province":"NY",
    "sg:tags":[
        "eating"
    ],
    "wof:name":"Sun Fresh Rest",
    "wof:placetype":"venue"
},
  "geometry": {"coordinates":[-73.85483499999999,41.166431],"type":"Point"}
}