{
  "type": "Feature",
  "properties": {
    "iso:country":"US",
    "sg:address":"7 Jay St",
    "sg:city":"Stony Point",
    "sg:classifiers":[
        {
            "category":"Insurance",
            "subcategory":"Title Insurance",
            "type":"Services"
        }
    ],
    "sg:phone":"+1 845 947 1553",
    "sg:postcode":"10980",
    "sg:province":"NY",
    "sg:tags":[
        "carrier"
    ],
    "wof:name":"Clegg Cecily",
    "wof:placetype":"venue"
},
  "geometry": {"coordinates":[-73.987894,41.229749],"type":"Point"}
}