{
  "type": "Feature",
  "properties": {
    "addr:full":"342 Hemstreet Rd Schaghticoke NY 12154",
    "addr:housenumber":"342",
    "addr:postcode":"12154",
    "addr:street":"Hemstreet Rd",
    "iso:country":"US",
    "sg:address":"342 Hemstreet Rd",
    "sg:city":"Schaghticoke",
    "sg:classifiers":[
        {
            "category":"Wholesale",
            "subcategory":"Medical Equipment & Supplies",
            "type":"Manufacturing & Wholesale Goods"
        }
    ],
    "sg:phone":"+1 518 753 0035",
    "sg:postcode":"12154",
    "sg:province":"NY",
    "wof:name":"Birchwood Medical",
    "wof:placetype":"venue"
},
  "geometry": {"coordinates":[-73.63192600000001,42.923129],"type":"Point"}
}