{
  "type": "Feature",
  "properties": {
    "iso:country":"US",
    "sg:address":"100 Emerson Pl",
    "sg:city":"Brooklyn",
    "sg:classifiers":[
        {
            "category":"Building & Trades",
            "subcategory":"Construction",
            "type":"Services"
        }
    ],
    "sg:phone":"+1 718 638 4950",
    "sg:postcode":"11205",
    "sg:province":"NY",
    "sg:tags":[
        "interior",
        "design"
    ],
    "wof:name":"Interiors By George & Martha",
    "wof:placetype":"venue"
},
  "geometry": {"coordinates":[-73.962519,40.694566],"type":"Point"}
}