{
  "type": "Feature",
  "properties": {
    "addr:full":"40 Walter Dr Nesconset NY 11767",
    "addr:housenumber":"40",
    "addr:postcode":"11767",
    "addr:street":"Walter Dr",
    "iso:country":"US",
    "sg:address":"40 Walter Dr",
    "sg:city":"Nesconset",
    "sg:classifiers":[
        {
            "category":"Building & Trades",
            "subcategory":"Landscaping Services",
            "type":"Services"
        }
    ],
    "sg:phone":"+1 631 981 0074",
    "sg:postcode":"11767",
    "sg:province":"NY",
    "sg:tags":[
        "landscape"
    ],
    "wof:name":"Nick Minerva Landscaping",
    "wof:placetype":"venue"
},
  "geometry": {"coordinates":[-73.13202699999999,40.837272],"type":"Point"}
}