{
  "type": "Feature",
  "properties": {
    "iso:country":"US",
    "sg:address":"532 Broadhollow Rd",
    "sg:city":"Melville",
    "sg:classifiers":[
        {
            "category":"Arts & Performance",
            "subcategory":"Theater",
            "type":"Entertainment"
        }
    ],
    "sg:phone":"+1 516 420 4432",
    "sg:postcode":"11747",
    "sg:province":"NY",
    "sg:tags":[
        "theatres-concert",
        "venue",
        "hall"
    ],
    "wof:name":"532 Broadhollow Assoc",
    "wof:placetype":"venue"
},
  "geometry": {"coordinates":[-73.421356,40.774532],"type":"Point"}
}