{
  "type": "Feature",
  "properties": {
    "addr:full":"3060 Review Ave Long Island City NY 11101",
    "addr:housenumber":"3060",
    "addr:postcode":"11101",
    "addr:street":"Review Ave",
    "iso:country":"US",
    "sg:address":"3060 Review Ave",
    "sg:city":"Long Island City",
    "sg:classifiers":[
        {
            "category":"Building & Trades",
            "subcategory":"Electrical",
            "type":"Services"
        }
    ],
    "sg:phone":"+1 718 706 6986",
    "sg:postcode":"11101",
    "sg:province":"NY",
    "sg:tags":[
        "electrician"
    ],
    "wof:name":"Lior Electric Corp",
    "wof:placetype":"venue"
},
  "geometry": {"coordinates":[-73.939654,40.736618],"type":"Point"}
}