{
  "type": "Feature",
  "properties": {
    "iso:country":"US",
    "sg:address":"4660 State Hwy 436",
    "sg:city":"Dansville",
    "sg:classifiers":[
        {
            "category":"Farming",
            "subcategory":"Livestock Farm",
            "type":"Manufacturing & Wholesale Goods"
        }
    ],
    "sg:phone":"+1 585 335 9670",
    "sg:postcode":"14437",
    "sg:province":"NY",
    "sg:tags":[
        "specialty",
        "animal"
    ],
    "wof:name":"American Wildlife Control",
    "wof:placetype":"venue"
},
  "geometry": {"coordinates":[-77.778801,42.560979],"type":"Point"}
}