{
  "type": "Feature",
  "properties": {
    "iso:country":"US",
    "sg:address":"109 Sutorius Dr",
    "sg:city":"Rochester",
    "sg:classifiers":[
        {
            "category":"Organizations",
            "subcategory":"Community Association",
            "type":"Services"
        }
    ],
    "sg:phone":"+1 585 865 7910",
    "sg:postcode":"14616",
    "sg:province":"NY",
    "wof:name":"Huggers Ski Club Incorporated",
    "wof:placetype":"venue"
},
  "geometry": {"coordinates":[-77.649024,43.239325],"type":"Point"}
}