{
  "type": "Feature",
  "properties": {
    "iso:country":"US",
    "sg:address":"967 Reeves Ave",
    "sg:city":"Riverhead",
    "sg:classifiers":[
        {
            "category":"Sports & Exercise",
            "subcategory":"Golf",
            "type":"Entertainment"
        }
    ],
    "sg:phone":"+1 631 208 3510",
    "sg:postcode":"11901",
    "sg:province":"NY",
    "wof:name":"Woods the",
    "wof:placetype":"venue"
},
  "geometry": {"coordinates":[-72.71520200000001,40.945202],"type":"Point"}
}