{
  "type": "Feature",
  "properties": {
    "addr:full":"676 Pelham Rd New Rochelle NY 10805",
    "addr:housenumber":"676",
    "addr:postcode":"10805",
    "addr:street":"Pelham Rd",
    "iso:country":"US",
    "sg:address":"676 Pelham Rd",
    "sg:city":"New Rochelle",
    "sg:classifiers":[
        {
            "category":"Health Services",
            "subcategory":"Nursing And Care Facility",
            "type":"Services"
        }
    ],
    "sg:phone":"+1 914 632 9600",
    "sg:postcode":"10805",
    "sg:province":"NY",
    "sg:tags":[
        "skilled"
    ],
    "sg:website":"www.dumontmasonichome.org",
    "wof:name":"Dumont Masonic Home",
    "wof:placetype":"venue"
},
  "geometry": {"coordinates":[-73.788505,40.88949],"type":"Point"}
}