{
  "type": "Feature",
  "properties": {
    "addr:full":"1006 McLean Ave Yonkers NY 10704",
    "addr:housenumber":"1006",
    "addr:postcode":"10704",
    "addr:street":"Mclean Ave",
    "iso:country":"US",
    "sg:address":"1006 McLean Ave",
    "sg:city":"Yonkers",
    "sg:classifiers":[
        {
            "category":"Shopping",
            "type":"Retail Goods"
        }
    ],
    "sg:phone":"+1 914 237 1143",
    "sg:postcode":"10704",
    "sg:province":"NY",
    "sg:tags":[
        "hearing",
        "equipment",
        "supply",
        "impaired"
    ],
    "wof:name":"Carmine's Hearing Aid Svc Inc",
    "wof:placetype":"venue"
},
  "geometry": {"coordinates":[-73.863668,40.90236],"type":"Point"}
}