{
  "type": "Feature",
  "properties": {
    "iso:country":"US",
    "sg:address":"1493 Cedar St",
    "sg:city":"Elmira",
    "sg:classifiers":[
        {
            "category":"Retail",
            "subcategory":"Repair Shop",
            "type":"Services"
        }
    ],
    "sg:phone":"+1 607 734 9813",
    "sg:postcode":"14904",
    "sg:province":"NY",
    "sg:tags":[
        "welding"
    ],
    "wof:name":"Cedar Street Manufacturing",
    "wof:placetype":"venue"
},
  "geometry": {"coordinates":[-76.800085,42.057813],"type":"Point"}
}