{
  "type": "Feature",
  "properties": {
    "addr:full":"2117 Ave Z Brooklyn NY 11235",
    "addr:postcode":"11235",
    "addr:street":"2117 Ave",
    "iso:country":"US",
    "sg:address":"2117 Ave Z",
    "sg:city":"Brooklyn",
    "sg:classifiers":[
        {
            "category":"Personal",
            "subcategory":"Beauty Salon",
            "type":"Services"
        }
    ],
    "sg:phone":"+1   ",
    "sg:postcode":"11235",
    "sg:province":"NY",
    "sg:tags":[
        "shop"
    ],
    "wof:name":"Hello Gorgeous Inc",
    "wof:placetype":"venue"
},
  "geometry": {"coordinates":[-73.947507,40.588788],"type":"Point"}
}