{
  "type": "Feature",
  "properties": {
    "iso:country":"US",
    "sg:address":"597 Willis Ave",
    "sg:city":"Williston Park",
    "sg:classifiers":[
        {
            "category":"Food & Beverages",
            "subcategory":"Specialty",
            "type":"Retail Goods"
        }
    ],
    "sg:phone":"+1 516 294 5559",
    "sg:postcode":"11596",
    "sg:province":"NY",
    "sg:tags":[
        "gourmet",
        "shop"
    ],
    "wof:name":"Madison's Gourmet Shoppe",
    "wof:placetype":"venue"
},
  "geometry": {"coordinates":[-73.646258,40.761343],"type":"Point"}
}