{
  "type": "Feature",
  "properties": {
    "iso:country":"US",
    "sg:address":"154 Christopher St",
    "sg:city":"New York",
    "sg:classifiers":[
        {
            "category":"Professional",
            "subcategory":"Research",
            "type":"Services"
        }
    ],
    "sg:phone":"+1 212 741 9110",
    "sg:postcode":"10014",
    "sg:province":"NY",
    "sg:tags":[
        "literary",
        "organization",
        "magazine",
        "for"
    ],
    "wof:name":"Clmp",
    "wof:placetype":"venue"
},
  "geometry": {"coordinates":[-74.00986899999999,40.73245],"type":"Point"}
}