{
  "type": "Feature",
  "properties": {
    "iso:country":"US",
    "sg:address":"6 Brook Rd",
    "sg:city":"Westhampton Beach",
    "sg:classifiers":[
        {
            "category":"Professional",
            "subcategory":"Management & Consulting",
            "type":"Services"
        }
    ],
    "sg:phone":"+1   ",
    "sg:postcode":"11978",
    "sg:province":"NY",
    "sg:tags":[
        "public",
        "relations"
    ],
    "wof:name":"Jason Belkin Public Relations",
    "wof:placetype":"venue"
},
  "geometry": {"coordinates":[-72.644958,40.814859],"type":"Point"}
}