{
  "type": "Feature",
  "properties": {
    "iso:country":"US",
    "sg:address":"2053 State Hwy 29",
    "sg:city":"Johnstown",
    "sg:classifiers":[
        {
            "category":"Farming",
            "subcategory":"Dairy Farm",
            "type":"Manufacturing & Wholesale Goods"
        }
    ],
    "sg:phone":"+1 518 762 8201",
    "sg:postcode":"12095",
    "sg:province":"NY",
    "wof:name":"Roger Putman",
    "wof:placetype":"venue"
},
  "geometry": {"coordinates":[-74.286952,43.032565],"type":"Point"}
}