{
  "type": "Feature",
  "properties": {
    "addr:full":"275 Livonia Ave Brooklyn NY 11212",
    "addr:housenumber":"275",
    "addr:postcode":"11212",
    "addr:street":"Livonia Ave",
    "iso:country":"US",
    "sg:address":"275 Livonia Ave",
    "sg:city":"Brooklyn",
    "sg:classifiers":[
        {
            "category":"Real Estate",
            "subcategory":"Real Estate Operator",
            "type":"Services"
        }
    ],
    "sg:phone":"+1 718 345 5485",
    "sg:postcode":"11212",
    "sg:province":"NY",
    "sg:tags":[
        "residential"
    ],
    "wof:name":"Sanders Enterprise Cmnty Dev",
    "wof:placetype":"venue"
},
  "geometry": {"coordinates":[-73.90891999999999,40.662554],"type":"Point"}
}