{
  "type": "Feature",
  "properties": {
    "addr:full":"164 Ushers Rd Round Lake NY 12151",
    "addr:housenumber":"164",
    "addr:postcode":"12151",
    "addr:street":"Ushers Rd",
    "iso:country":"US",
    "sg:address":"164 Ushers Rd",
    "sg:city":"Round Lake",
    "sg:classifiers":[
        {
            "category":"Building & Trades",
            "subcategory":"Electrical",
            "type":"Services"
        }
    ],
    "sg:phone":"+1 518 877 0301",
    "sg:postcode":"12151",
    "sg:province":"NY",
    "sg:tags":[
        "electric",
        "contractor"
    ],
    "wof:name":"Gemini Electrical Design",
    "wof:placetype":"venue"
},
  "geometry": {"coordinates":[-73.77249399999999,42.910328],"type":"Point"}
}