{
  "type": "Feature",
  "properties": {
    "addr:full":"2116 Merrick Ave N Merrick NY 11566",
    "addr:housenumber":"2116",
    "addr:postcode":"11566",
    "addr:street":"Merrick Ave N",
    "iso:country":"US",
    "sg:address":"2116 Merrick Ave N",
    "sg:city":"Merrick",
    "sg:classifiers":[
        {
            "category":"Professional",
            "subcategory":"Accounting & Tax Preparation",
            "type":"Services"
        }
    ],
    "sg:phone":"+1 516 379 8979",
    "sg:postcode":"11566",
    "sg:province":"NY",
    "sg:tags":[
        "accountant"
    ],
    "wof:name":"Leon Beltzer CPA",
    "wof:placetype":"venue"
},
  "geometry": {"coordinates":[-73.55383500000001,40.667765],"type":"Point"}
}