{
  "type": "Feature",
  "properties": {
    "addr:full":"570 Rockaway Tpke Lawrence NY 11559",
    "addr:housenumber":"570",
    "addr:postcode":"11559",
    "addr:street":"Rockaway Tpke",
    "iso:country":"US",
    "sg:address":"570 Rockaway Tpke",
    "sg:city":"Lawrence",
    "sg:classifiers":[
        {
            "category":"Sports & Exercise",
            "subcategory":"Golf",
            "type":"Entertainment"
        }
    ],
    "sg:phone":"+1 516 239 1743",
    "sg:postcode":"11559",
    "sg:province":"NY",
    "sg:tags":[
        "mini"
    ],
    "sg:website":"www.5townsminigofbattng.com",
    "wof:name":"Five Towns Mini Golf & Batting Range",
    "wof:placetype":"venue"
},
  "geometry": {"coordinates":[-73.737999,40.630798],"type":"Point"}
}