{
  "type": "Feature",
  "properties": {
    "addr:full":"1166 Burke Ave Bronx NY 10469",
    "addr:housenumber":"1166",
    "addr:postcode":"10469",
    "addr:street":"Burke Ave",
    "iso:country":"US",
    "sg:address":"1166 Burke Ave",
    "sg:city":"Bronx",
    "sg:classifiers":[
        {
            "category":"Professional",
            "type":"Services"
        }
    ],
    "sg:phone":"+1   ",
    "sg:postcode":"10469",
    "sg:province":"NY",
    "wof:name":"Bl Williams Inc",
    "wof:placetype":"venue"
},
  "geometry": {"coordinates":[-73.851848,40.871086],"type":"Point"}
}