{
  "type": "Feature",
  "properties": {
    "iso:country":"US",
    "sg:address":"330 37th St",
    "sg:city":"Brooklyn",
    "sg:classifiers":[
        {
            "category":"Personal",
            "subcategory":"Beauty Salon",
            "type":"Services"
        }
    ],
    "sg:phone":"+1 718 768 2342",
    "sg:postcode":"11232",
    "sg:province":"NY",
    "wof:name":"Ny Beauty Trading",
    "wof:placetype":"venue"
},
  "geometry": {"coordinates":[-74.005438,40.654004],"type":"Point"}
}