{
  "type": "Feature",
  "properties": {
    "iso:country":"US",
    "sg:address":"345 Park Ave S Lbby",
    "sg:city":"New York",
    "sg:classifiers":[
        {
            "category":"Real Estate",
            "subcategory":"Real Estate Services",
            "type":"Services"
        }
    ],
    "sg:phone":"+1 212 685 8595",
    "sg:postcode":"10010",
    "sg:province":"NY",
    "sg:tags":[
        "management",
        "property"
    ],
    "wof:name":"345 Park Ave So Partners",
    "wof:placetype":"venue"
},
  "geometry": {"coordinates":[-73.985298,40.741501],"type":"Point"}
}