{
  "type": "Feature",
  "properties": {
    "addr:full":"750 Thayer Rd Fairport NY 14450",
    "addr:housenumber":"750",
    "addr:postcode":"14450",
    "addr:street":"Thayer Rd",
    "iso:country":"US",
    "sg:address":"750 Thayer Rd",
    "sg:city":"Fairport",
    "sg:classifiers":[
        {
            "category":"Professional",
            "subcategory":"Business Services",
            "type":"Services"
        }
    ],
    "sg:phone":"+1 585 223 6625",
    "sg:postcode":"14450",
    "sg:province":"NY",
    "sg:tags":[
        "consultant",
        "coach"
    ],
    "wof:name":"E C Salibian",
    "wof:placetype":"venue"
},
  "geometry": {"coordinates":[-77.421707,43.041809],"type":"Point"}
}