{
  "type": "Feature",
  "properties": {
    "addr:full":"111 Mineola Ave Roslyn Heights NY 11577",
    "addr:housenumber":"111",
    "addr:postcode":"11577",
    "addr:street":"Mineola Ave",
    "iso:country":"US",
    "sg:address":"111 Mineola Ave",
    "sg:city":"Roslyn Heights",
    "sg:classifiers":[
        {
            "category":"Health Services",
            "subcategory":"Chiropractor",
            "type":"Services"
        }
    ],
    "sg:phone":"+1 516 484 0776",
    "sg:postcode":"11577",
    "sg:province":"NY",
    "wof:name":"Silverman Steven DC",
    "wof:placetype":"venue"
},
  "geometry": {"coordinates":[-73.65129899999999,40.7887],"type":"Point"}
}