{
  "type": "Feature",
  "properties": {
    "addr:full":"65 S Broadway Tarrytown NY 10591",
    "addr:housenumber":"65",
    "addr:postcode":"10591",
    "addr:street":"S Broadway",
    "iso:country":"US",
    "sg:address":"65 S Broadway",
    "sg:city":"Tarrytown",
    "sg:classifiers":[
        {
            "category":"Health Services",
            "subcategory":"Clinic",
            "type":"Services"
        }
    ],
    "sg:phone":"+1 914 631 7200",
    "sg:postcode":"10591",
    "sg:province":"NY",
    "sg:tags":[
        "home",
        "care"
    ],
    "sg:website":"www.familyhhc.com",
    "wof:name":"Family Home Health Care",
    "wof:placetype":"venue"
},
  "geometry": {"coordinates":[-73.859123,41.074389],"type":"Point"}
}