{
  "type": "Feature",
  "properties": {
    "addr:full":"1737 Coney Island Ave Brooklyn NY 11230",
    "addr:housenumber":"1737",
    "addr:postcode":"11230",
    "addr:street":"Coney Island Ave",
    "iso:country":"US",
    "sg:address":"1737 Coney Island Ave",
    "sg:city":"Brooklyn",
    "sg:classifiers":[
        {
            "category":"Professional",
            "subcategory":"Business Services",
            "type":"Services"
        }
    ],
    "sg:phone":"+1 718 339 7799",
    "sg:postcode":"11230",
    "sg:province":"NY",
    "sg:tags":[
        "messenger"
    ],
    "wof:name":"Israelite Messenger Svc",
    "wof:placetype":"venue"
},
  "geometry": {"coordinates":[-73.962806,40.612711],"type":"Point"}
}