{
  "type": "Feature",
  "properties": {
    "iso:country":"US",
    "sg:address":"770 5th Ave",
    "sg:city":"Brooklyn",
    "sg:classifiers":[
        {
            "category":"Banks & Credit Unions",
            "subcategory":"Bank",
            "type":"Services"
        }
    ],
    "sg:phone":"+1 718 788 6200",
    "sg:postcode":"11232",
    "sg:province":"NY",
    "wof:name":"770 Fifth Ave Co",
    "wof:placetype":"venue"
},
  "geometry": {"coordinates":[-73.997513,40.65741],"type":"Point"}
}