{
  "type": "Feature",
  "properties": {
    "addr:full":"302 Kingsland Ave Brooklyn NY 11222",
    "addr:housenumber":"302",
    "addr:postcode":"11222",
    "addr:street":"Kingsland Ave",
    "iso:country":"US",
    "sg:address":"302 Kingsland Ave",
    "sg:city":"Brooklyn",
    "sg:classifiers":[
        {
            "category":"Building & Trades",
            "subcategory":"Plumbing",
            "type":"Services"
        }
    ],
    "sg:phone":"+1 718 349 2902",
    "sg:postcode":"11222",
    "sg:province":"NY",
    "wof:name":"Cobra Kitchen Ventilation",
    "wof:placetype":"venue"
},
  "geometry": {"coordinates":[-73.94161,40.727224],"type":"Point"}
}