{
  "type": "Feature",
  "properties": {
    "addr:full":"104 W Main St Stony Point NY 10980",
    "addr:housenumber":"104",
    "addr:postcode":"10980",
    "addr:street":"W Main St",
    "iso:country":"US",
    "sg:address":"104 W Main St",
    "sg:city":"Stony Point",
    "sg:classifiers":[
        {
            "category":"Autos & Motor Vehicles",
            "subcategory":"Fuel & Gas Station",
            "type":"Retail Goods"
        }
    ],
    "sg:phone":"+1 845 942 2602",
    "sg:postcode":"10980",
    "sg:province":"NY",
    "sg:tags":[
        "oil"
    ],
    "wof:name":"Super Value",
    "wof:placetype":"venue"
},
  "geometry": {"coordinates":[-73.987239,41.229229],"type":"Point"}
}