{
  "type": "Feature",
  "properties": {
    "iso:country":"US",
    "sg:address":"251 Macdougal St",
    "sg:city":"Brooklyn",
    "sg:classifiers":[
        {
            "category":"Education",
            "subcategory":"School",
            "type":"Public Place"
        }
    ],
    "sg:phone":"+1 718 573 8799",
    "sg:postcode":"11233",
    "sg:province":"NY",
    "wof:name":"Public School 73",
    "wof:placetype":"venue"
},
  "geometry": {"coordinates":[-73.908918,40.680576],"type":"Point"}
}