{
  "type": "Feature",
  "properties": {
    "addr:full":"3404 Mickle Ave Bronx NY 10469",
    "addr:housenumber":"3404",
    "addr:postcode":"10469",
    "addr:street":"Mickle Ave",
    "iso:country":"US",
    "sg:address":"3404 Mickle Ave",
    "sg:city":"Bronx",
    "sg:classifiers":[
        {
            "category":"Retail",
            "subcategory":"Portrait Studio",
            "type":"Services"
        }
    ],
    "sg:phone":"+1   ",
    "sg:postcode":"10469",
    "sg:province":"NY",
    "sg:tags":[
        "photo"
    ],
    "wof:name":"Lewis Studios Inc",
    "wof:placetype":"venue"
},
  "geometry": {"coordinates":[-73.845353,40.877276],"type":"Point"}
}