{
  "type": "Feature",
  "properties": {
    "iso:country":"US",
    "sg:address":"490 S Work St",
    "sg:city":"Falconer",
    "sg:classifiers":[
        {
            "category":"Wholesale",
            "subcategory":"Machinery & Supplies",
            "type":"Manufacturing & Wholesale Goods"
        }
    ],
    "sg:phone":"+1 716 664 7368",
    "sg:postcode":"14733",
    "sg:province":"NY",
    "sg:tags":[
        "contractor"
    ],
    "wof:name":"United Rentals",
    "wof:placetype":"venue"
},
  "geometry": {"coordinates":[-79.19056999999999,42.114788],"type":"Point"}
}