{
  "type": "Feature",
  "properties": {
    "iso:country":"US",
    "sg:address":"41 Willow St",
    "sg:city":"Central Islip",
    "sg:classifiers":[
        {
            "category":"Personal",
            "subcategory":"Shoe Repair & Shine",
            "type":"Services"
        }
    ],
    "sg:phone":"+1 631 582 1118",
    "sg:postcode":"11722",
    "sg:province":"NY",
    "sg:tags":[
        "repairing",
        "boot"
    ],
    "wof:name":"Betheas Professional Shoe Care",
    "wof:placetype":"venue"
},
  "geometry": {"coordinates":[-73.18123,40.783061],"type":"Point"}
}