{
  "type": "Feature",
  "properties": {
    "addr:full":"12 British American Blvd Latham NY 12110",
    "addr:housenumber":"12",
    "addr:postcode":"12110",
    "addr:street":"British American Blvd",
    "iso:country":"US",
    "sg:address":"12 British American Blvd",
    "sg:city":"Latham",
    "sg:classifiers":[
        {
            "category":"Health Services",
            "subcategory":"Doctor",
            "type":"Services"
        }
    ],
    "sg:phone":"+1 518 289 1800",
    "sg:postcode":"12110",
    "sg:province":"NY",
    "sg:tags":[
        "physician",
        "surgeon"
    ],
    "wof:name":"Med Assoc",
    "wof:placetype":"venue"
},
  "geometry": {"coordinates":[-73.817831,42.7591],"type":"Point"}
}