{
  "type": "Feature",
  "properties": {
    "addr:full":"330 W 56th St New York NY 10019",
    "addr:housenumber":"330",
    "addr:postcode":"10019",
    "addr:street":"W 56Th St",
    "iso:country":"US",
    "sg:address":"330 W 56th St",
    "sg:city":"New York",
    "sg:classifiers":[
        {
            "category":"Real Estate",
            "subcategory":"Real Estate Operator",
            "type":"Services"
        }
    ],
    "sg:phone":"+1 212 581 4320",
    "sg:postcode":"10019",
    "sg:province":"NY",
    "sg:tags":[
        "apartment"
    ],
    "wof:name":"Apartment Resources",
    "wof:placetype":"venue"
},
  "geometry": {"coordinates":[-73.984298,40.766289],"type":"Point"}
}