{
  "type": "Feature",
  "properties": {
    "addr:full":"230 Lambert Ave Copiague NY 11726",
    "addr:housenumber":"230",
    "addr:postcode":"11726",
    "addr:street":"Lambert Ave",
    "iso:country":"US",
    "sg:address":"230 Lambert Ave",
    "sg:city":"Copiague",
    "sg:classifiers":[
        {
            "category":"Manufacturing",
            "subcategory":"Tools & Machinery",
            "type":"Manufacturing & Wholesale Goods"
        },
        {
            "category":"Retail",
            "subcategory":"Repair Shop",
            "type":"Services"
        },
        {
            "category":"Retail",
            "subcategory":"Auto Repair",
            "type":"Services"
        }
    ],
    "sg:phone":"+1 631 226 9412",
    "sg:postcode":"11726",
    "sg:province":"NY",
    "sg:tags":[
        "machine",
        "automobile",
        "machinery-rebuild"
    ],
    "wof:name":"Ryan Machine Works",
    "wof:placetype":"venue"
},
  "geometry": {"coordinates":[-73.393567,40.680036],"type":"Point"}
}