{
  "type": "Feature",
  "properties": {
    "addr:full":"1909 Curry Rd Schenectady NY 12306",
    "addr:housenumber":"1909",
    "addr:postcode":"12306",
    "addr:street":"Curry Rd",
    "iso:country":"US",
    "sg:address":"1909 Curry Rd",
    "sg:city":"Schenectady",
    "sg:classifiers":[
        {
            "category":"Deli",
            "type":"Food & Drink"
        }
    ],
    "sg:menulink":"http://www.allmenus.com/ny/rotterdam/126476-blimpie-subs--sandwiches/menu/",
    "sg:phone":"+1 518 348 0695",
    "sg:postcode":"12306",
    "sg:province":"NY",
    "sg:tags":[
        "wrap",
        "american",
        "sandwich"
    ],
    "wof:name":"Blimpie Subs & Sandwiches",
    "wof:placetype":"venue"
},
  "geometry": {"coordinates":[-73.95677000000001,42.781047],"type":"Point"}
}