{
  "type": "Feature",
  "properties": {
    "iso:country":"US",
    "sg:address":"413 Meeker Ave",
    "sg:city":"Brooklyn",
    "sg:classifiers":[
        {
            "category":"Retail",
            "subcategory":"Auto Repair",
            "type":"Services"
        }
    ],
    "sg:phone":"+1 718 388 1532",
    "sg:postcode":"11222",
    "sg:province":"NY",
    "sg:tags":[
        "repairing",
        "automobile"
    ],
    "sg:website":"www.tonysautobodyinc.com",
    "wof:name":"Tony's Auto Body Inc",
    "wof:placetype":"venue"
},
  "geometry": {"coordinates":[-73.945801,40.719601],"type":"Point"}
}