{
  "type": "Feature",
  "properties": {
    "addr:full":"52 Main St Kingston NY 12401",
    "addr:housenumber":"52",
    "addr:postcode":"12401",
    "addr:street":"Main St",
    "iso:country":"US",
    "sg:address":"52 Main St",
    "sg:city":"Kingston",
    "sg:classifiers":[
        {
            "category":"Health Services",
            "subcategory":"Doctor",
            "type":"Services"
        }
    ],
    "sg:phone":"+1 845 338 9830",
    "sg:postcode":"12401",
    "sg:province":"NY",
    "sg:tags":[
        "physician",
        "surgeon"
    ],
    "wof:name":"Joseph Mauceri MD",
    "wof:placetype":"venue"
},
  "geometry": {"coordinates":[-74.018649,41.932457],"type":"Point"}
}