{
  "type": "Feature",
  "properties": {
    "addr:full":"577 Grassmere Ter Far Rockaway NY 11691",
    "addr:housenumber":"577",
    "addr:postcode":"11691",
    "addr:street":"Grassmere Ter",
    "iso:country":"US",
    "sg:address":"577 Grassmere Ter",
    "sg:city":"Far Rockaway",
    "sg:classifiers":[
        {
            "category":"Shopping",
            "subcategory":"Computers & Home Electronics",
            "type":"Retail Goods"
        }
    ],
    "sg:phone":"+1 718 337 4064",
    "sg:postcode":"11691",
    "sg:province":"NY",
    "wof:name":"Harrison Video Services",
    "wof:placetype":"venue"
},
  "geometry": {"coordinates":[-73.75859800000001,40.600201],"type":"Point"}
}