{
  "type": "Feature",
  "properties": {
    "addr:full":"43 Marscher Pl Staten Island NY 10309",
    "addr:housenumber":"43",
    "addr:postcode":"10309",
    "addr:street":"Marscher Pl",
    "iso:country":"US",
    "sg:address":"43 Marscher Pl",
    "sg:city":"Staten Island",
    "sg:classifiers":[
        {
            "category":"Building & Trades",
            "subcategory":"Plumbing",
            "type":"Services"
        }
    ],
    "sg:phone":"+1 718 967 2605",
    "sg:postcode":"10309",
    "sg:province":"NY",
    "sg:tags":[
        "contractor"
    ],
    "wof:name":"McCann Peter Plumbing & Htg",
    "wof:placetype":"venue"
},
  "geometry": {"coordinates":[-74.196078,40.51424],"type":"Point"}
}