{
  "type": "Feature",
  "properties": {
    "addr:full":"44 Kingston Ave Port Jervis NY 12771",
    "addr:housenumber":"44",
    "addr:postcode":"12771",
    "addr:street":"Kingston Ave",
    "iso:country":"US",
    "sg:address":"44 Kingston Ave",
    "sg:city":"Port Jervis",
    "sg:classifiers":[
        {
            "category":"Taxi",
            "type":"Transportation"
        }
    ],
    "sg:phone":"+1 845 858 4994",
    "sg:postcode":"12771",
    "sg:province":"NY",
    "sg:tags":[
        "taxicab"
    ],
    "wof:name":"City Taxi",
    "wof:placetype":"venue"
},
  "geometry": {"coordinates":[-74.68212699999999,41.378349],"type":"Point"}
}