{
  "type": "Feature",
  "properties": {
    "iso:country":"US",
    "sg:address":"87 Salem Ln",
    "sg:city":"South Salem",
    "sg:classifiers":[
        {
            "category":"Professional",
            "subcategory":"Business Services",
            "type":"Services"
        }
    ],
    "sg:phone":"+1   ",
    "sg:postcode":"10590",
    "sg:province":"NY",
    "wof:name":"Display Works",
    "wof:placetype":"venue"
},
  "geometry": {"coordinates":[-73.54853900000001,41.278817],"type":"Point"}
}