{
  "type": "Feature",
  "properties": {
    "addr:full":"467 William Floyd Pkwy Shirley NY 11967",
    "addr:housenumber":"467",
    "addr:postcode":"11967",
    "addr:street":"William Floyd Pkwy",
    "iso:country":"US",
    "sg:address":"467 William Floyd Pkwy",
    "sg:city":"Shirley",
    "sg:classifiers":[
        {
            "category":"Restaurant",
            "type":"Food & Drink"
        }
    ],
    "sg:phone":"+1 631 399 4388",
    "sg:postcode":"11967",
    "sg:province":"NY",
    "wof:name":"William Floyd Diner",
    "wof:placetype":"venue"
},
  "geometry": {"coordinates":[-72.866302,40.777199],"type":"Point"}
}