{
  "type": "Feature",
  "properties": {
    "iso:country":"US",
    "sg:address":"444 W Main St",
    "sg:city":"Patchogue",
    "sg:classifiers":[
        {
            "category":"Health Services",
            "subcategory":"Doctor",
            "type":"Services"
        }
    ],
    "sg:phone":"+1 631 475 5250",
    "sg:postcode":"11772",
    "sg:province":"NY",
    "sg:tags":[
        "medical"
    ],
    "wof:name":"Kilion Daphna",
    "wof:placetype":"venue"
},
  "geometry": {"coordinates":[-73.02893400000001,40.761468],"type":"Point"}
}