{
  "type": "Feature",
  "properties": {
    "iso:country":"US",
    "sg:address":"7176 Stone Hill Rd",
    "sg:city":"Livonia",
    "sg:phone":"+1 585 346 5502",
    "sg:postcode":"14487",
    "sg:province":"NY",
    "sg:tags":[
        "farm",
        "grain",
        "cash"
    ],
    "wof:name":"Marjorie Panipinto",
    "wof:placetype":"venue"
},
  "geometry": {"coordinates":[-77.627765,42.836641],"type":"Point"}
}