{
  "type": "Feature",
  "properties": {
    "addr:full":"150 W 117th St New York NY 10026",
    "addr:housenumber":"150",
    "addr:postcode":"10026",
    "addr:street":"W 117Th St",
    "iso:country":"US",
    "sg:address":"150 W 117th St",
    "sg:city":"New York",
    "sg:classifiers":[
        {
            "category":"Professional",
            "type":"Services"
        }
    ],
    "sg:phone":"+1 212 663 3456",
    "sg:postcode":"10026",
    "sg:province":"NY",
    "sg:tags":[
        "establishment"
    ],
    "wof:name":"Get Da Picture",
    "wof:placetype":"venue"
},
  "geometry": {"coordinates":[-73.950971,40.803221],"type":"Point"}
}