{
  "type": "Feature",
  "properties": {
    "addr:full":"233 Broadway New York NY 10007",
    "addr:housenumber":"233",
    "addr:postcode":"10007",
    "addr:street":"Broadway",
    "iso:country":"US",
    "sg:address":"233 Broadway",
    "sg:city":"New York",
    "sg:classifiers":[
        {
            "category":"Professional",
            "subcategory":"Lawyer & Legal Services",
            "type":"Services"
        }
    ],
    "sg:phone":"+1 212 925 2020",
    "sg:postcode":"10007",
    "sg:province":"NY",
    "sg:tags":[
        "attorney"
    ],
    "wof:name":"Dennis P Spates Law Offices",
    "wof:placetype":"venue"
},
  "geometry": {"coordinates":[-74.00789399999999,40.712303],"type":"Point"}
}