{
  "type": "Feature",
  "properties": {
    "iso:country":"US",
    "sg:address":"156 Center St",
    "sg:city":"Massena",
    "sg:classifiers":[
        {
            "category":"Health Services",
            "subcategory":"Nursing And Care Facility",
            "type":"Services"
        },
        {
            "category":"Social Services",
            "type":"Services"
        }
    ],
    "sg:phone":"+1 315 764 9442",
    "sg:postcode":"13662",
    "sg:province":"NY",
    "sg:tags":[
        "clinic",
        "outpatient",
        "adult",
        "specialty"
    ],
    "wof:name":"Independent Living Center",
    "wof:placetype":"venue"
},
  "geometry": {"coordinates":[-74.885628,44.934178],"type":"Point"}
}