{
  "type": "Feature",
  "properties": {
    "iso:country":"US",
    "sg:address":"10 Maverick Ter",
    "sg:city":"Woodstock",
    "sg:classifiers":[
        {
            "category":"Manufacturing",
            "subcategory":"Glass & Minerals",
            "type":"Manufacturing & Wholesale Goods"
        }
    ],
    "sg:phone":"+1   ",
    "sg:postcode":"12498",
    "sg:province":"NY",
    "sg:tags":[
        "mfg"
    ],
    "wof:name":"Yoav Greenberg Glass Studio",
    "wof:placetype":"venue"
},
  "geometry": {"coordinates":[-74.115273,42.022255],"type":"Point"}
}