{
  "type": "Feature",
  "properties": {
    "iso:country":"US",
    "sg:address":"15 W 37th St 7th Floor",
    "sg:city":"New York",
    "sg:classifiers":[
        {
            "category":"Manufacturing",
            "subcategory":"Electronics",
            "type":"Manufacturing & Wholesale Goods"
        }
    ],
    "sg:phone":"+1 888 497 6552",
    "sg:postcode":"10018",
    "sg:province":"NY",
    "sg:tags":[
        "door-knob",
        "door-handle",
        "disinfect",
        "clean",
        "green",
        "hygiene",
        "health",
        "public-health",
        "d3-micro",
        "hyscent"
    ],
    "sg:website":"http://www.hyso.com",
    "wof:name":"HYSO",
    "wof:placetype":"venue"
},
  "geometry": {"coordinates":[-73.986013,40.751572],"type":"Point"}
}