{
  "type": "Feature",
  "properties": {
    "iso:country":"US",
    "sg:address":"98 Eagle Ct",
    "sg:city":"Port Jervis",
    "sg:classifiers":[
        {
            "category":"Education",
            "subcategory":"Special Training",
            "type":"Public Place"
        }
    ],
    "sg:phone":"+1   ",
    "sg:postcode":"12780",
    "sg:province":"NY",
    "wof:name":"Success Stratagies LLC",
    "wof:placetype":"venue"
},
  "geometry": {"coordinates":[-74.747406,41.432807],"type":"Point"}
}