{
  "type": "Feature",
  "properties": {
    "iso:country":"US",
    "sg:address":"620 Orchard Park Rd",
    "sg:city":"Buffalo",
    "sg:classifiers":[
        {
            "category":"Personal",
            "type":"Services"
        },
        {
            "category":"Retail",
            "subcategory":"Auto Repair",
            "type":"Services"
        }
    ],
    "sg:phone":"+1 716 674 0087",
    "sg:postcode":"14224",
    "sg:province":"NY",
    "sg:tags":[
        "body",
        "shop",
        "mover"
    ],
    "wof:name":"AA Collision & Insurance Claim Experts",
    "wof:placetype":"venue"
},
  "geometry": {"coordinates":[-78.77649700000001,42.830002],"type":"Point"}
}