{
  "type": "Feature",
  "properties": {
    "iso:country":"US",
    "sg:address":"23122 Merrick Blvd",
    "sg:city":"Springfield Gardens",
    "sg:classifiers":[
        {
            "category":"Autos & Motor Vehicles",
            "subcategory":"Auto Supplies",
            "type":"Retail Goods"
        }
    ],
    "sg:phone":"+1 718 528 5609",
    "sg:postcode":"11413",
    "sg:province":"NY",
    "sg:tags":[
        "tire"
    ],
    "wof:name":"M D Tires",
    "wof:placetype":"venue"
},
  "geometry": {"coordinates":[-73.738772,40.675354],"type":"Point"}
}