{
  "type": "Feature",
  "properties": {
    "addr:full":"127 Sterling Dr Utica NY 13502",
    "addr:housenumber":"127",
    "addr:postcode":"13502",
    "addr:street":"Sterling Dr",
    "iso:country":"US",
    "sg:address":"127 Sterling Dr",
    "sg:city":"Utica",
    "sg:classifiers":[
        {
            "category":"Building & Trades",
            "subcategory":"Construction",
            "type":"Services"
        }
    ],
    "sg:phone":"+1 315 796 7322",
    "sg:postcode":"13502",
    "sg:province":"NY",
    "sg:tags":[
        "home"
    ],
    "wof:name":"R J C Enterprises",
    "wof:placetype":"venue"
},
  "geometry": {"coordinates":[-75.129221,43.10729],"type":"Point"}
}