{
  "type": "Feature",
  "properties": {
    "addr:full":"947 Maple Dr Webster NY 14580",
    "addr:housenumber":"947",
    "addr:postcode":"14580",
    "addr:street":"Maple Dr",
    "iso:country":"US",
    "sg:address":"947 Maple Dr",
    "sg:city":"Webster",
    "sg:classifiers":[
        {
            "category":"Building & Trades",
            "subcategory":"Construction",
            "type":"Services"
        }
    ],
    "sg:phone":"+1 585 671 5468",
    "sg:postcode":"14580",
    "sg:province":"NY",
    "sg:tags":[
        "heavy"
    ],
    "wof:name":"Natures Ponds & Waterscapes",
    "wof:placetype":"venue"
},
  "geometry": {"coordinates":[-77.505971,43.210341],"type":"Point"}
}