{
  "type": "Feature",
  "properties": {
    "iso:country":"US",
    "sg:address":"268 Washington Ave",
    "sg:city":"St James",
    "sg:classifiers":[
        {
            "category":"Restaurant",
            "type":"Food & Drink"
        }
    ],
    "sg:phone":"+1 631 864 1099",
    "sg:postcode":"11780",
    "sg:province":"NY",
    "sg:tags":[
        "delicatessen"
    ],
    "wof:name":"Expressway Deli",
    "wof:placetype":"venue"
},
  "geometry": {"coordinates":[-73.158423,40.878632],"type":"Point"}
}