{
  "type": "Feature",
  "properties": {
    "addr:full":"380 Grove Ave Patchogue NY 11772",
    "addr:housenumber":"380",
    "addr:postcode":"11772",
    "addr:street":"Grove Ave",
    "iso:country":"US",
    "sg:address":"380 Grove Ave",
    "sg:city":"Patchogue",
    "sg:classifiers":[
        {
            "category":"Manufacturing",
            "subcategory":"Building Materials",
            "type":"Manufacturing & Wholesale Goods"
        }
    ],
    "sg:phone":"+1   ",
    "sg:postcode":"11772",
    "sg:province":"NY",
    "sg:tags":[
        "mfg",
        "household",
        "wood",
        "cabinet",
        "furniture"
    ],
    "wof:name":"M J S Woodworking",
    "wof:placetype":"venue"
},
  "geometry": {"coordinates":[-73.002054,40.755055],"type":"Point"}
}