{
  "type": "Feature",
  "properties": {
    "iso:country":"US",
    "sg:address":"1425 Kings Hwy",
    "sg:city":"Brooklyn",
    "sg:classifiers":[
        {
            "category":"Shopping",
            "subcategory":"Pharmacy",
            "type":"Retail Goods"
        }
    ],
    "sg:phone":"+1 718 382 7700",
    "sg:postcode":"11229",
    "sg:province":"NY",
    "sg:tags":[
        "drugstore"
    ],
    "wof:name":"Kingsway Pharmacy",
    "wof:placetype":"venue"
},
  "geometry": {"coordinates":[-73.958941,40.608504],"type":"Point"}
}