{
  "type": "Feature",
  "properties": {
    "addr:full":"1570 Lake St Elmira NY 14901",
    "addr:housenumber":"1570",
    "addr:postcode":"14901",
    "addr:street":"Lake St",
    "iso:country":"US",
    "sg:address":"1570 Lake St",
    "sg:city":"Elmira",
    "sg:classifiers":[
        {
            "category":"Recreation",
            "type":"Entertainment"
        }
    ],
    "sg:phone":"+1 607 732 0494",
    "sg:postcode":"14901",
    "sg:province":"NY",
    "sg:tags":[
        "skating",
        "rink"
    ],
    "wof:name":"Joycrest Skating Rink",
    "wof:placetype":"venue"
},
  "geometry": {"coordinates":[-76.808379,42.11695],"type":"Point"}
}