{
  "type": "Feature",
  "properties": {
    "addr:full":"58 Bowery New York NY 10013",
    "addr:housenumber":"58",
    "addr:postcode":"10013",
    "addr:street":"Bowery",
    "iso:country":"US",
    "sg:address":"58 Bowery",
    "sg:city":"New York",
    "sg:classifiers":[
        {
            "category":"Banks & Credit Unions",
            "subcategory":"Bank",
            "type":"Services"
        }
    ],
    "sg:phone":"+1 800 975 4722",
    "sg:postcode":"10013",
    "sg:province":"NY",
    "sg:website":"us.hsbc.com",
    "wof:name":"HSBC",
    "wof:placetype":"venue"
},
  "geometry": {"coordinates":[-73.996166,40.716184],"type":"Point"}
}