{
  "type": "Feature",
  "properties": {
    "addr:full":"111 Ausable St Keeseville NY 12944",
    "addr:housenumber":"111",
    "addr:postcode":"12944",
    "addr:street":"Ausable St",
    "iso:country":"US",
    "sg:address":"111 Ausable St",
    "sg:city":"Keeseville",
    "sg:classifiers":[
        {
            "category":"Government",
            "subcategory":"Office",
            "type":"Public Place"
        }
    ],
    "sg:phone":"+1 518 834 9035",
    "sg:postcode":"12944",
    "sg:province":"NY",
    "sg:tags":[
        "city"
    ],
    "wof:name":"Ausable Town Clerk",
    "wof:placetype":"venue"
},
  "geometry": {"coordinates":[-73.481931,44.505171],"type":"Point"}
}