{
  "type": "Feature",
  "properties": {
    "addr:full":"20 Manchester Rd Poughkeepsie NY 12603",
    "addr:housenumber":"20",
    "addr:postcode":"12603",
    "addr:street":"Manchester Rd",
    "iso:country":"US",
    "sg:address":"20 Manchester Rd",
    "sg:city":"Poughkeepsie",
    "sg:classifiers":[
        {
            "category":"Government",
            "subcategory":"Office",
            "type":"Public Place"
        }
    ],
    "sg:phone":"+1 845 486 2950",
    "sg:postcode":"12603",
    "sg:province":"NY",
    "sg:website":"www.lexingtonctr.org",
    "wof:name":"Lexington Center For Recovery",
    "wof:placetype":"venue"
},
  "geometry": {"coordinates":[-73.893443,41.694072],"type":"Point"}
}