{
  "type": "Feature",
  "properties": {
    "iso:country":"US",
    "sg:address":"1733 Edison Ave",
    "sg:city":"Bronx",
    "sg:classifiers":[
        {
            "category":"Local Transit",
            "type":"Transportation"
        }
    ],
    "sg:phone":"+1   ",
    "sg:postcode":"10461",
    "sg:province":"NY",
    "sg:tags":[
        "passenger"
    ],
    "wof:name":"Crosby Car Service",
    "wof:placetype":"venue"
},
  "geometry": {"coordinates":[-73.832713,40.845868],"type":"Point"}
}