{
  "type": "Feature",
  "properties": {
    "addr:full":"3217 Broadway Astoria NY 11106",
    "addr:housenumber":"3217",
    "addr:postcode":"11106",
    "addr:street":"Broadway",
    "iso:country":"US",
    "sg:address":"3217 Broadway",
    "sg:city":"Astoria",
    "sg:classifiers":[
        {
            "category":"Professional",
            "subcategory":"Lawyer & Legal Services",
            "type":"Services"
        }
    ],
    "sg:phone":"+1 718 274 0700",
    "sg:postcode":"11106",
    "sg:province":"NY",
    "sg:tags":[
        "notary"
    ],
    "wof:name":"Ralis Anthony D",
    "wof:placetype":"venue"
},
  "geometry": {"coordinates":[-73.92445499999999,40.761567],"type":"Point"}
}