{
  "type": "Feature",
  "properties": {
    "addr:full":"1228 Surf Ave Brooklyn NY 11224",
    "addr:housenumber":"1228",
    "addr:postcode":"11224",
    "addr:street":"Surf Ave",
    "iso:country":"US",
    "sg:address":"1228 Surf Ave",
    "sg:city":"Brooklyn",
    "sg:classifiers":[
        {
            "category":"Wholesale",
            "subcategory":"Machinery & Supplies",
            "type":"Manufacturing & Wholesale Goods"
        }
    ],
    "sg:phone":"+1 718 449 8384",
    "sg:postcode":"11224",
    "sg:province":"NY",
    "sg:tags":[
        "industrial"
    ],
    "wof:name":"AZ Kabul Corp",
    "wof:placetype":"venue"
},
  "geometry": {"coordinates":[-73.97963799999999,40.575537],"type":"Point"}
}