{
  "type": "Feature",
  "properties": {
    "addr:full":"975 Morris Park Ave Bronx NY 10462",
    "addr:housenumber":"975",
    "addr:postcode":"10462",
    "addr:street":"Morris Park Ave",
    "iso:country":"US",
    "sg:address":"975 Morris Park Ave",
    "sg:city":"Bronx",
    "sg:classifiers":[
        {
            "category":"Professional",
            "type":"Services"
        }
    ],
    "sg:phone":"+1 718 518 1500",
    "sg:postcode":"10462",
    "sg:province":"NY",
    "sg:tags":[
        "establishment"
    ],
    "wof:name":"Center For Family Support",
    "wof:placetype":"venue"
},
  "geometry": {"coordinates":[-73.856279,40.848093],"type":"Point"}
}