{
  "type": "Feature",
  "properties": {
    "addr:full":"1158 60th St Brooklyn NY 11219",
    "addr:housenumber":"1158",
    "addr:postcode":"11219",
    "addr:street":"60Th St",
    "iso:country":"US",
    "sg:address":"1158 60th St",
    "sg:city":"Brooklyn",
    "sg:classifiers":[
        {
            "category":"Home & Garden",
            "subcategory":"Building Materials",
            "type":"Retail Goods"
        }
    ],
    "sg:phone":"+1 718 686 6442",
    "sg:postcode":"11219",
    "sg:province":"NY",
    "sg:tags":[
        "lumber"
    ],
    "wof:name":"Brooklyn Lumber Corp",
    "wof:placetype":"venue"
},
  "geometry": {"coordinates":[-74.001784,40.630902],"type":"Point"}
}