{
  "type": "Feature",
  "properties": {
    "iso:country":"US",
    "sg:address":"2 Old Dock Rd",
    "sg:city":"Yaphank",
    "sg:classifiers":[
        {
            "category":"Professional",
            "subcategory":"Printing & Photocopies",
            "type":"Services"
        }
    ],
    "sg:phone":"+1 631 205 1200",
    "sg:postcode":"11980",
    "sg:province":"NY",
    "sg:tags":[
        "duplicating",
        "copying"
    ],
    "wof:name":"One Source Document Mgmt",
    "wof:placetype":"venue"
},
  "geometry": {"coordinates":[-72.94388499999999,40.810877],"type":"Point"}
}