{
  "type": "Feature",
  "properties": {
    "iso:country":"US",
    "sg:address":"235 Old Route 17",
    "sg:city":"Windsor",
    "sg:classifiers":[
        {
            "category":"Transit Center",
            "subcategory":"Freight",
            "type":"Transportation"
        },
        {
            "category":"Freight",
            "type":"Transportation"
        }
    ],
    "sg:phone":"+1 607 343 5350",
    "sg:postcode":"13865",
    "sg:province":"NY",
    "sg:tags":[
        "local",
        "trucking-motor",
        "trucking"
    ],
    "wof:name":"D Harrington Trucking, Inc.",
    "wof:placetype":"venue"
},
  "geometry": {"coordinates":[-75.683233,42.082388],"type":"Point"}
}