{
  "type": "Feature",
  "properties": {
    "iso:country":"US",
    "sg:address":"222 Mason St",
    "sg:city":"Morrisonville",
    "sg:classifiers":[
        {
            "category":"Building & Trades",
            "subcategory":"Plumbing",
            "type":"Services"
        }
    ],
    "sg:phone":"+1 518 561 2955",
    "sg:postcode":"12962",
    "sg:province":"NY",
    "sg:tags":[
        "conditioning",
        "air",
        "system",
        "contractor"
    ],
    "wof:name":"SRK Home Improvement",
    "wof:placetype":"venue"
},
  "geometry": {"coordinates":[-73.555621,44.649317],"type":"Point"}
}