{
  "type": "Feature",
  "properties": {
    "addr:full":"19 Charles St Malone NY 12953",
    "addr:housenumber":"19",
    "addr:postcode":"12953",
    "addr:street":"Charles St",
    "iso:country":"US",
    "sg:address":"19 Charles St",
    "sg:city":"Malone",
    "sg:classifiers":[
        {
            "category":"Building & Trades",
            "subcategory":"Construction",
            "type":"Services"
        }
    ],
    "sg:phone":"+1 518 483 2033",
    "sg:postcode":"12953",
    "sg:province":"NY",
    "sg:tags":[
        "excavation",
        "contractor"
    ],
    "wof:name":"Edward Duquette & Son Inc",
    "wof:placetype":"venue"
},
  "geometry": {"coordinates":[-74.293926,44.854786],"type":"Point"}
}