{
  "type": "Feature",
  "properties": {
    "addr:full":"569 W 207th St New York NY 10034",
    "addr:housenumber":"569",
    "addr:postcode":"10034",
    "addr:street":"W 207Th St",
    "iso:country":"US",
    "sg:address":"569 W 207th St",
    "sg:city":"New York",
    "sg:classifiers":[
        {
            "category":"Personal",
            "subcategory":"Beauty Salon",
            "type":"Services"
        }
    ],
    "sg:phone":"+1 212 942 0905",
    "sg:postcode":"10034",
    "sg:province":"NY",
    "sg:tags":[
        "shop"
    ],
    "wof:name":"Charles Unisex 2",
    "wof:placetype":"venue"
},
  "geometry": {"coordinates":[-73.920202,40.866086],"type":"Point"}
}