{
  "type": "Feature",
  "properties": {
    "addr:full":"5838 Page Place Maspeth NY 11378",
    "addr:housenumber":"5838",
    "addr:postcode":"11378",
    "addr:street":"Page Place",
    "iso:country":"US",
    "sg:address":"5838 Page Place",
    "sg:city":"Maspeth",
    "sg:classifiers":[
        {
            "category":"Shopping",
            "subcategory":"Stationery & Office Supplies",
            "type":"Retail Goods"
        }
    ],
    "sg:phone":"+1 718 803 5000",
    "sg:postcode":"11378",
    "sg:province":"NY",
    "sg:tags":[
        "equipment"
    ],
    "wof:name":"The Weeks Lerman Group",
    "wof:placetype":"venue"
},
  "geometry": {"coordinates":[-73.91792100000001,40.71866],"type":"Point"}
}