{
  "type": "Feature",
  "properties": {
    "iso:country":"US",
    "sg:address":"145 Elmwood Park W",
    "sg:city":"Tonawanda",
    "sg:classifiers":[
        {
            "category":"Utilities",
            "subcategory":"Cable",
            "type":"Services"
        }
    ],
    "sg:phone":"+1   ",
    "sg:postcode":"14150",
    "sg:province":"NY",
    "sg:tags":[
        "television"
    ],
    "wof:name":"Underdog Cable Inc",
    "wof:placetype":"venue"
},
  "geometry": {"coordinates":[-78.88295599999999,43.011224],"type":"Point"}
}