{
  "type": "Feature",
  "properties": {
    "addr:full":"3640 Johnson Ave Bronx NY 10463",
    "addr:housenumber":"3640",
    "addr:postcode":"10463",
    "addr:street":"Johnson Ave",
    "iso:country":"US",
    "sg:address":"3640 Johnson Ave",
    "sg:city":"Bronx",
    "sg:classifiers":[
        {
            "category":"Social Services",
            "type":"Services"
        }
    ],
    "sg:phone":"+1 718 884 8566",
    "sg:postcode":"10463",
    "sg:province":"NY",
    "sg:tags":[
        "referral"
    ],
    "wof:name":"Psychrefer Refferal Svc",
    "wof:placetype":"venue"
},
  "geometry": {"coordinates":[-73.909459,40.886971],"type":"Point"}
}