{
  "type": "Feature",
  "properties": {
    "iso:country":"US",
    "sg:address":"3940 Harlem Rd",
    "sg:city":"Buffalo",
    "sg:classifiers":[
        {
            "category":"Professional",
            "subcategory":"Lawyer & Legal Services",
            "type":"Services"
        }
    ],
    "sg:phone":"+1   ",
    "sg:postcode":"14226",
    "sg:province":"NY",
    "wof:name":"Janet Gunner",
    "wof:placetype":"venue"
},
  "geometry": {"coordinates":[-78.784136,42.950498],"type":"Point"}
}