{
  "type": "Feature",
  "properties": {
    "iso:country":"US",
    "sg:address":"80 Ruland Rd",
    "sg:city":"Melville",
    "sg:classifiers":[
        {
            "category":"Wholesale",
            "subcategory":"Electrical",
            "type":"Manufacturing & Wholesale Goods"
        },
        {
            "category":"Shopping",
            "subcategory":"Computers & Home Electronics",
            "type":"Retail Goods"
        }
    ],
    "sg:phone":"+1 631 501 2800",
    "sg:postcode":"11747",
    "sg:province":"NY",
    "sg:tags":[
        "equipment",
        "electronic",
        "supply"
    ],
    "sg:website":"www.partminer.com",
    "wof:name":"Part Miner Inc",
    "wof:placetype":"venue"
},
  "geometry": {"coordinates":[-73.415149,40.763027],"type":"Point"}
}