{
  "type": "Feature",
  "properties": {
    "addr:full":"575 Madison Ave New York NY 10022",
    "addr:housenumber":"575",
    "addr:postcode":"10022",
    "addr:street":"Madison Ave",
    "iso:country":"US",
    "sg:address":"575 Madison Ave",
    "sg:city":"New York",
    "sg:classifiers":[
        {
            "category":"Building & Trades",
            "subcategory":"Construction",
            "type":"Services"
        }
    ],
    "sg:phone":"+1 212 605 0221",
    "sg:postcode":"10022",
    "sg:province":"NY",
    "sg:tags":[
        "contractor"
    ],
    "wof:name":"D & D Contracting",
    "wof:placetype":"venue"
},
  "geometry": {"coordinates":[-73.97260300000001,40.761799],"type":"Point"}
}