{
  "type": "Feature",
  "properties": {
    "iso:country":"US",
    "sg:address":"7811 Karakul Ln",
    "sg:city":"Fayetteville",
    "sg:classifiers":[
        {
            "category":"Manufacturing",
            "subcategory":"Wood Products",
            "type":"Manufacturing & Wholesale Goods"
        }
    ],
    "sg:phone":"+1   ",
    "sg:postcode":"13066",
    "sg:province":"NY",
    "sg:tags":[
        "mfg"
    ],
    "wof:name":"Rifkas Treasures",
    "wof:placetype":"venue"
},
  "geometry": {"coordinates":[-75.98547600000001,43.020698],"type":"Point"}
}