{
  "type": "Feature",
  "properties": {
    "addr:full":"156 5th Avenue New York NY 10011",
    "addr:housenumber":"156",
    "addr:postcode":"10011",
    "addr:street":"5Th Avenue",
    "iso:country":"US",
    "sg:address":"156 5th Avenue",
    "sg:city":"New York",
    "sg:classifiers":[
        {
            "category":"Professional",
            "subcategory":"Computer Services",
            "type":"Services"
        }
    ],
    "sg:phone":"+1 650 961 3400",
    "sg:postcode":"10011",
    "sg:province":"NY",
    "sg:website":"http://www.ooyala.com/",
    "wof:name":"Ooyala",
    "wof:placetype":"venue"
},
  "geometry": {"coordinates":[-73.99137399999999,40.739087],"type":"Point"}
}