{
  "type": "Feature",
  "properties": {
    "addr:full":"46 Francesca Ln Staten Island NY 10303",
    "addr:housenumber":"46",
    "addr:postcode":"10303",
    "addr:street":"Francesca Ln",
    "iso:country":"US",
    "sg:address":"46 Francesca Ln",
    "sg:city":"Staten Island",
    "sg:classifiers":[
        {
            "category":"Social Services",
            "type":"Services"
        }
    ],
    "sg:phone":"+1 718 494 2858",
    "sg:postcode":"10303",
    "sg:province":"NY",
    "sg:tags":[
        "counselor",
        "marriage",
        "family"
    ],
    "wof:name":"Integrity Senior Svc",
    "wof:placetype":"venue"
},
  "geometry": {"coordinates":[-74.16104199999999,40.623157],"type":"Point"}
}