{
  "type": "Feature",
  "properties": {
    "addr:full":"354 Shore Dr Oakdale NY 11769",
    "addr:housenumber":"354",
    "addr:postcode":"11769",
    "addr:street":"Shore Dr",
    "iso:country":"US",
    "sg:address":"354 Shore Dr",
    "sg:city":"Oakdale",
    "sg:classifiers":[
        {
            "category":"Manufacturing",
            "subcategory":"Metals",
            "type":"Manufacturing & Wholesale Goods"
        }
    ],
    "sg:phone":"+1 631 567 8898",
    "sg:postcode":"11769",
    "sg:province":"NY",
    "sg:tags":[
        "manufacture",
        "installs",
        "gutter",
        "leaders"
    ],
    "wof:name":"Flo-Rite Gutter Co",
    "wof:placetype":"venue"
},
  "geometry": {"coordinates":[-73.15324200000001,40.727414],"type":"Point"}
}