{
  "type": "Feature",
  "properties": {
    "addr:full":"7031 108th Street Suite 2 Forest Hills NY 11375",
    "addr:housenumber":"7031",
    "addr:postcode":"11375",
    "addr:street":"108Th Street Suite 2",
    "iso:country":"US",
    "sg:address":"7031 108th Street Suite 2",
    "sg:city":"Forest Hills",
    "sg:classifiers":[
        {
            "category":"Health Services",
            "subcategory":"Dentist",
            "type":"Services"
        }
    ],
    "sg:phone":"+1 718 263 6602",
    "sg:postcode":"11375",
    "sg:province":"NY",
    "wof:name":"Bernstein Scott F DDS",
    "wof:placetype":"venue"
},
  "geometry": {"coordinates":[-73.844099,40.722279],"type":"Point"}
}