{
  "type": "Feature",
  "properties": {
    "iso:country":"US",
    "sg:address":"5309 4th Ave",
    "sg:city":"Brooklyn",
    "sg:classifiers":[
        {
            "category":"Food & Beverages",
            "subcategory":"Bakery",
            "type":"Retail Goods"
        }
    ],
    "sg:phone":"+1 718 439 3901",
    "sg:postcode":"11220",
    "sg:province":"NY",
    "sg:tags":[
        "bagel",
        "sandwich"
    ],
    "wof:name":"Sunset Bagel",
    "wof:placetype":"venue"
},
  "geometry": {"coordinates":[-74.014319,40.644702],"type":"Point"}
}