{
  "type": "Feature",
  "properties": {
    "iso:country":"US",
    "sg:address":"82 Woodland Ave",
    "sg:city":"Catskill",
    "sg:classifiers":[
        {
            "category":"Organizations",
            "subcategory":"Religious Organization",
            "type":"Services"
        }
    ],
    "sg:phone":"+1 518 943 5341",
    "sg:postcode":"12414",
    "sg:province":"NY",
    "sg:tags":[
        "monastery",
        "convent"
    ],
    "wof:name":"St Joseph's Villa Convent",
    "wof:placetype":"venue"
},
  "geometry": {"coordinates":[-73.858988,42.223569],"type":"Point"}
}