{
  "type": "Feature",
  "properties": {
    "iso:country":"US",
    "sg:address":"700 S Perry St",
    "sg:city":"Johnstown",
    "sg:classifiers":[
        {
            "category":"Health Services",
            "subcategory":"Doctor",
            "type":"Services"
        }
    ],
    "sg:phone":"+1 518 762 3161",
    "sg:postcode":"12095",
    "sg:province":"NY",
    "sg:tags":[
        "physician",
        "surgeon"
    ],
    "wof:name":"Kishan R Battu MD",
    "wof:placetype":"venue"
},
  "geometry": {"coordinates":[-74.370741,42.996997],"type":"Point"}
}