{
  "type": "Feature",
  "properties": {
    "iso:country":"US",
    "sg:address":"27 Columbus Ave",
    "sg:city":"New York",
    "sg:classifiers":[
        {
            "category":"Food & Beverages",
            "subcategory":"Groceries & Convenience Stores",
            "type":"Retail Goods"
        }
    ],
    "sg:phone":"+1 212 307 0115",
    "sg:postcode":"10023",
    "sg:province":"NY",
    "sg:tags":[
        "grocer"
    ],
    "wof:name":"27 Columbus Ave Deli",
    "wof:placetype":"venue"
},
  "geometry": {"coordinates":[-73.98390499999999,40.770233],"type":"Point"}
}