{
  "type": "Feature",
  "properties": {
    "iso:country":"US",
    "sg:address":"1237 Hertel Ave",
    "sg:city":"Buffalo",
    "sg:classifiers":[
        {
            "category":"Organizations",
            "subcategory":"Religious Organization",
            "type":"Services"
        }
    ],
    "sg:phone":"+1 716 875 9673",
    "sg:postcode":"14216",
    "sg:province":"NY",
    "sg:tags":[
        "clergy"
    ],
    "wof:name":"Edward L Courton",
    "wof:placetype":"venue"
},
  "geometry": {"coordinates":[-78.862295,42.947674],"type":"Point"}
}