{
  "type": "Feature",
  "properties": {
    "iso:country":"US",
    "sg:address":"29 Rupert Ave",
    "sg:city":"Staten Island",
    "sg:classifiers":[
        {
            "category":"Building & Trades",
            "subcategory":"Construction",
            "type":"Services"
        }
    ],
    "sg:phone":"+1 646 208 6424",
    "sg:postcode":"10314",
    "sg:province":"NY",
    "sg:tags":[
        "contractor"
    ],
    "wof:name":"No Limit Contracting Inc",
    "wof:placetype":"venue"
},
  "geometry": {"coordinates":[-74.132749,40.598262],"type":"Point"}
}