{
  "type": "Feature",
  "properties": {
    "iso:country":"US",
    "sg:address":"68 Central Ave",
    "sg:city":"Albany",
    "sg:classifiers":[
        {
            "category":"Food & Beverages",
            "subcategory":"Groceries & Convenience Stores",
            "type":"Retail Goods"
        }
    ],
    "sg:phone":"+1 518 432 2425",
    "sg:postcode":"12206",
    "sg:province":"NY",
    "sg:tags":[
        "grocer"
    ],
    "wof:name":"Yassah's African Grocery Store",
    "wof:placetype":"venue"
},
  "geometry": {"coordinates":[-73.76643,42.659361],"type":"Point"}
}