{
  "type": "Feature",
  "properties": {
    "iso:country":"US",
    "sg:address":"6712 Brooklawn Pkwy",
    "sg:city":"Syracuse",
    "sg:classifiers":[
        {
            "category":"Health Services",
            "subcategory":"Doctor",
            "type":"Services"
        }
    ],
    "sg:phone":"+1 315 432 8899",
    "sg:postcode":"13211",
    "sg:province":"NY",
    "sg:tags":[
        "medical"
    ],
    "wof:name":"Lax Michael B",
    "wof:placetype":"venue"
},
  "geometry": {"coordinates":[-76.096521,43.09443],"type":"Point"}
}