{
  "type": "Feature",
  "properties": {
    "addr:full":"365 Division St Amsterdam NY 12010",
    "addr:housenumber":"365",
    "addr:postcode":"12010",
    "addr:street":"Division St",
    "iso:country":"US",
    "sg:address":"365 Division St",
    "sg:city":"Amsterdam",
    "sg:classifiers":[
        {
            "category":"Health Services",
            "subcategory":"Chiropractor",
            "type":"Services"
        }
    ],
    "sg:phone":"+1 518 842 9737",
    "sg:postcode":"12010",
    "sg:province":"NY",
    "wof:name":"Amsterdam Chiropractic",
    "wof:placetype":"venue"
},
  "geometry": {"coordinates":[-74.214823,42.952377],"type":"Point"}
}