{
  "type": "Feature",
  "properties": {
    "addr:full":"624 Orwood Pl Syracuse NY 13208",
    "addr:housenumber":"624",
    "addr:postcode":"13208",
    "addr:street":"Orwood Pl",
    "iso:country":"US",
    "sg:address":"624 Orwood Pl",
    "sg:city":"Syracuse",
    "sg:classifiers":[
        {
            "category":"Wholesale",
            "subcategory":"Electrical",
            "type":"Manufacturing & Wholesale Goods"
        }
    ],
    "sg:phone":"+1 315 455 6991",
    "sg:postcode":"13208",
    "sg:province":"NY",
    "sg:tags":[
        "equipment"
    ],
    "wof:name":"Circuit Breakers Accessories",
    "wof:placetype":"venue"
},
  "geometry": {"coordinates":[-76.12388799999999,43.080807],"type":"Point"}
}