{
  "type": "Feature",
  "properties": {
    "iso:country":"US",
    "sg:address":"8838 Woodhaven Boulevard",
    "sg:city":"Woodhaven",
    "sg:classifiers":[
        {
            "category":"Health Services",
            "subcategory":"Doctor",
            "type":"Services"
        }
    ],
    "sg:phone":"+1 718 577 0500",
    "sg:postcode":"11421",
    "sg:province":"NY",
    "sg:tags":[
        "orthopedist"
    ],
    "wof:name":"Kobak Martin Dr Podiatrist",
    "wof:placetype":"venue"
},
  "geometry": {"coordinates":[-73.851297,40.691654],"type":"Point"}
}