{
  "type": "Feature",
  "properties": {
    "addr:full":"1214 North Ave New Rochelle NY 10804",
    "addr:housenumber":"1214",
    "addr:postcode":"10804",
    "addr:street":"North Ave",
    "iso:country":"US",
    "sg:address":"1214 North Ave",
    "sg:city":"New Rochelle",
    "sg:classifiers":[
        {
            "category":"Organizations",
            "subcategory":"Religious Organization",
            "type":"Services"
        }
    ],
    "sg:phone":"+1 914 632 0296",
    "sg:postcode":"10804",
    "sg:province":"NY",
    "sg:tags":[
        "clergy"
    ],
    "wof:name":"Ariel Ferrari",
    "wof:placetype":"venue"
},
  "geometry": {"coordinates":[-73.795064,40.943278],"type":"Point"}
}