{
  "type": "Feature",
  "properties": {
    "iso:country":"US",
    "sg:address":"2 Market Pl",
    "sg:city":"Yonkers",
    "sg:classifiers":[
        {
            "category":"Food & Beverages",
            "subcategory":"Meat & Fish",
            "type":"Retail Goods"
        }
    ],
    "sg:phone":"+1 914 375 1363",
    "sg:postcode":"10701",
    "sg:province":"NY",
    "sg:tags":[
        "seafood"
    ],
    "wof:name":"Pete's Seafood Spot",
    "wof:placetype":"venue"
},
  "geometry": {"coordinates":[-73.901346,40.935241],"type":"Point"}
}