{
  "type": "Feature",
  "properties": {
    "addr:full":"4905 Co Rd 26 Dundee NY 14837",
    "addr:housenumber":"4905;26",
    "addr:postcode":"14837",
    "addr:street":"Co Rd",
    "iso:country":"US",
    "sg:address":"4905 Co Rd 26",
    "sg:city":"Dundee",
    "sg:classifiers":[
        {
            "category":"Freight",
            "type":"Transportation"
        }
    ],
    "sg:phone":"+1   ",
    "sg:postcode":"14837",
    "sg:province":"NY",
    "sg:tags":[
        "general"
    ],
    "wof:name":"Between The Lakes Pest Control",
    "wof:placetype":"venue"
},
  "geometry": {"coordinates":[-77.100471,42.475445],"type":"Point"}
}