{
  "type": "Feature",
  "properties": {
    "addr:full":"45 Bedford Rd Armonk NY 10504",
    "addr:housenumber":"45",
    "addr:postcode":"10504",
    "addr:street":"Bedford Rd",
    "iso:country":"US",
    "sg:address":"45 Bedford Rd",
    "sg:city":"Armonk",
    "sg:classifiers":[
        {
            "category":"Building & Trades",
            "subcategory":"Construction",
            "type":"Services"
        }
    ],
    "sg:phone":"+1 914 273 4661",
    "sg:postcode":"10504",
    "sg:province":"NY",
    "sg:tags":[
        "utility",
        "contractor"
    ],
    "wof:name":"Bibeau Construction Co",
    "wof:placetype":"venue"
},
  "geometry": {"coordinates":[-73.70095600000001,41.124868],"type":"Point"}
}