{
  "type": "Feature",
  "properties": {
    "iso:country":"US",
    "sg:address":"6743 Transit Rd",
    "sg:city":"Buffalo",
    "sg:classifiers":[
        {
            "category":"Shopping",
            "subcategory":"Music",
            "type":"Retail Goods"
        }
    ],
    "sg:phone":"+1   ",
    "sg:postcode":"14221",
    "sg:province":"NY",
    "sg:tags":[
        "record",
        "video",
        "tape"
    ],
    "wof:name":"Media Play",
    "wof:placetype":"venue"
},
  "geometry": {"coordinates":[-78.697005,42.951195],"type":"Point"}
}