{
  "type": "Feature",
  "properties": {
    "iso:country":"US",
    "sg:address":"413 Dan Troy Dr",
    "sg:city":"Buffalo",
    "sg:classifiers":[
        {
            "category":"Health Services",
            "subcategory":"Doctor",
            "type":"Services"
        }
    ],
    "sg:phone":"+1 716 634 7274",
    "sg:postcode":"14221",
    "sg:province":"NY",
    "sg:tags":[
        "medical"
    ],
    "wof:name":"M Z Kurlan MD",
    "wof:placetype":"venue"
},
  "geometry": {"coordinates":[-78.734976,42.981273],"type":"Point"}
}