{
  "type": "Feature",
  "properties": {
    "addr:full":"27 Oakridge Dr Huntington NY 11743",
    "addr:housenumber":"27",
    "addr:postcode":"11743",
    "addr:street":"Oakridge Dr",
    "iso:country":"US",
    "sg:address":"27 Oakridge Dr",
    "sg:city":"Huntington",
    "sg:classifiers":[
        {
            "category":"Wholesale",
            "subcategory":"Apparel",
            "type":"Manufacturing & Wholesale Goods"
        }
    ],
    "sg:phone":"+1 631 367 4085",
    "sg:postcode":"11743",
    "sg:province":"NY",
    "sg:tags":[
        "handbag",
        "manufacturer",
        "representative",
        "accessory"
    ],
    "wof:name":"Phillip Snyder Associates",
    "wof:placetype":"venue"
},
  "geometry": {"coordinates":[-73.44326100000001,40.834863],"type":"Point"}
}