{
  "type": "Feature",
  "properties": {
    "iso:country":"US",
    "sg:address":"606 E 3rd St",
    "sg:city":"Brooklyn",
    "sg:classifiers":[
        {
            "category":"Building & Trades",
            "subcategory":"Construction",
            "type":"Services"
        }
    ],
    "sg:phone":"+1 718 435 1917",
    "sg:postcode":"11218",
    "sg:province":"NY",
    "sg:tags":[
        "contractor"
    ],
    "wof:name":"Aziz Contracting Co",
    "wof:placetype":"venue"
},
  "geometry": {"coordinates":[-73.976164,40.636653],"type":"Point"}
}