{
  "type": "Feature",
  "properties": {
    "iso:country":"US",
    "sg:address":"2735 Lash Rd",
    "sg:city":"Cortland",
    "sg:classifiers":[
        {
            "category":"Farming",
            "subcategory":"Dairy Farm",
            "type":"Manufacturing & Wholesale Goods"
        }
    ],
    "sg:phone":"+1 607 835 6682",
    "sg:postcode":"13045",
    "sg:province":"NY",
    "wof:name":"Vandonsel Farm",
    "wof:placetype":"venue"
},
  "geometry": {"coordinates":[-76.16148800000001,42.53935],"type":"Point"}
}