{
  "type": "Feature",
  "properties": {
    "addr:full":"774 57th St Brooklyn NY 11220",
    "addr:housenumber":"774",
    "addr:postcode":"11220",
    "addr:street":"57Th St",
    "iso:country":"US",
    "sg:address":"774 57th St",
    "sg:city":"Brooklyn",
    "sg:classifiers":[
        {
            "category":"Restaurant",
            "type":"Food & Drink"
        }
    ],
    "sg:phone":"+1   ",
    "sg:postcode":"11220",
    "sg:province":"NY",
    "sg:tags":[
        "eating"
    ],
    "wof:name":"Ho Wong Restaurant",
    "wof:placetype":"venue"
},
  "geometry": {"coordinates":[-74.009095,40.63814],"type":"Point"}
}