{
  "type": "Feature",
  "properties": {
    "addr:full":"4153 Broadway New York NY 10033",
    "addr:housenumber":"4153",
    "addr:postcode":"10033",
    "addr:street":"Broadway",
    "iso:country":"US",
    "sg:address":"4153 Broadway",
    "sg:city":"New York",
    "sg:classifiers":[
        {
            "category":"Utilities",
            "subcategory":"Mobile Phone",
            "type":"Services"
        }
    ],
    "sg:phone":"+1 212 568 6400",
    "sg:postcode":"10033",
    "sg:province":"NY",
    "sg:tags":[
        "telephone",
        "cellular"
    ],
    "wof:name":"A O Wireless",
    "wof:placetype":"venue"
},
  "geometry": {"coordinates":[-73.938413,40.846457],"type":"Point"}
}