{
  "type": "Feature",
  "properties": {
    "iso:country":"US",
    "sg:address":"131 W 33 St",
    "sg:city":"New York",
    "sg:classifiers":[
        {
            "category":"Shopping",
            "subcategory":"Clothing, Apparel, & Fashions",
            "type":"Retail Goods"
        }
    ],
    "sg:phone":"+1 212 244 3660",
    "sg:postcode":"10001",
    "sg:province":"NY",
    "sg:tags":[
        "infant",
        "wear"
    ],
    "wof:name":"Children Worldwide Fashion",
    "wof:placetype":"venue"
},
  "geometry": {"coordinates":[-73.990415,40.750026],"type":"Point"}
}