{
  "type": "Feature",
  "properties": {
    "iso:country":"US",
    "sg:address":"81 W 18 St",
    "sg:city":"New York",
    "sg:classifiers":[
        {
            "category":"Retail",
            "subcategory":"Auto Repair",
            "type":"Services"
        }
    ],
    "sg:phone":"+1 212 937 1298",
    "sg:postcode":"10011",
    "sg:province":"NY",
    "sg:tags":[
        "wrecker"
    ],
    "wof:name":"Alero Towing & Recovery",
    "wof:placetype":"venue"
},
  "geometry": {"coordinates":[-73.99299000000001,40.738819],"type":"Point"}
}