{
  "type": "Feature",
  "properties": {
    "iso:country":"US",
    "sg:address":"1424 Atlantic Ave",
    "sg:city":"Brooklyn",
    "sg:classifiers":[
        {
            "category":"Building & Trades",
            "subcategory":"Plumbing",
            "type":"Services"
        }
    ],
    "sg:phone":"+1 718 774 3022",
    "sg:postcode":"11216",
    "sg:province":"NY",
    "sg:tags":[
        "sheet",
        "work",
        "metal",
        "contractor"
    ],
    "wof:name":"Wilco Sheet Metal",
    "wof:placetype":"venue"
},
  "geometry": {"coordinates":[-73.94571000000001,40.678277],"type":"Point"}
}