{
  "type": "Feature",
  "properties": {
    "iso:country":"US",
    "sg:address":"82 Modular Ave",
    "sg:city":"Commack",
    "sg:classifiers":[
        {
            "category":"Manufacturing",
            "subcategory":"Metals",
            "type":"Manufacturing & Wholesale Goods"
        }
    ],
    "sg:phone":"+1   ",
    "sg:postcode":"11725",
    "sg:province":"NY",
    "sg:tags":[
        "fabricator",
        "sheet"
    ],
    "wof:name":"Commodity Steel Fabricators",
    "wof:placetype":"venue"
},
  "geometry": {"coordinates":[-73.272812,40.811602],"type":"Point"}
}