{
  "type": "Feature",
  "properties": {
    "iso:country":"US",
    "sg:address":"199 Jericho Tpke",
    "sg:city":"Floral Park",
    "sg:classifiers":[
        {
            "category":"Professional",
            "subcategory":"Engineering",
            "type":"Services"
        }
    ],
    "sg:phone":"+1 631 254 7164",
    "sg:postcode":"11001",
    "sg:province":"NY",
    "sg:tags":[
        "energy",
        "conservation",
        "engineer"
    ],
    "wof:name":"Honeywell",
    "wof:placetype":"venue"
},
  "geometry": {"coordinates":[-73.70343,40.728732],"type":"Point"}
}