{
  "type": "Feature",
  "properties": {
    "iso:country":"US",
    "sg:address":"8411 Elmhurst Ave",
    "sg:city":"Elmhurst",
    "sg:classifiers":[
        {
            "category":"Food & Beverages",
            "subcategory":"Groceries & Convenience Stores",
            "type":"Retail Goods"
        }
    ],
    "sg:phone":"+1 718 639 4664",
    "sg:postcode":"11373",
    "sg:province":"NY",
    "wof:name":"Ac Mini Market",
    "wof:placetype":"venue"
},
  "geometry": {"coordinates":[-73.880402,40.7425],"type":"Point"}
}