{
  "type": "Feature",
  "properties": {
    "addr:full":"121 E 84th St New York NY 10028",
    "addr:housenumber":"121",
    "addr:postcode":"10028",
    "addr:street":"E 84Th St",
    "iso:country":"US",
    "sg:address":"121 E 84th St",
    "sg:city":"New York",
    "sg:classifiers":[
        {
            "category":"Health Services",
            "subcategory":"Doctor",
            "type":"Services"
        }
    ],
    "sg:phone":"+1 212 717 9470",
    "sg:postcode":"10028",
    "sg:province":"NY",
    "wof:name":"Yaffe Ruden & Associates LLP",
    "wof:placetype":"venue"
},
  "geometry": {"coordinates":[-73.957157,40.778551],"type":"Point"}
}