{
  "type": "Feature",
  "properties": {
    "addr:full":"120 Rotterdam St Schenectady NY 12306",
    "addr:housenumber":"120",
    "addr:postcode":"12306",
    "addr:street":"Rotterdam St",
    "iso:country":"US",
    "sg:address":"120 Rotterdam St",
    "sg:city":"Schenectady",
    "sg:classifiers":[
        {
            "category":"Social Services",
            "type":"Services"
        }
    ],
    "sg:phone":"+1 518 346 6201",
    "sg:postcode":"12306",
    "sg:province":"NY",
    "wof:name":"Berkshire Farm Center & Servic",
    "wof:placetype":"venue"
},
  "geometry": {"coordinates":[-73.991342,42.793671],"type":"Point"}
}