{
  "type": "Feature",
  "properties": {
    "iso:country":"US",
    "sg:address":"7 Greenbush Ave",
    "sg:city":"East Greenbush",
    "sg:classifiers":[
        {
            "category":"Building & Trades",
            "subcategory":"Construction",
            "type":"Services"
        }
    ],
    "sg:phone":"+1 518 477 7142",
    "sg:postcode":"12061",
    "sg:province":"NY",
    "sg:tags":[
        "house"
    ],
    "wof:name":"Mw Remodelers",
    "wof:placetype":"venue"
},
  "geometry": {"coordinates":[-73.70708500000001,42.606158],"type":"Point"}
}