{
  "type": "Feature",
  "properties": {
    "addr:full":"6071 E Henrietta Rd Rush NY 14543",
    "addr:housenumber":"6071",
    "addr:postcode":"14543",
    "addr:street":"E Henrietta Rd",
    "iso:country":"US",
    "sg:address":"6071 E Henrietta Rd",
    "sg:city":"Rush",
    "sg:classifiers":[
        {
            "category":"Restaurant",
            "type":"Food & Drink"
        }
    ],
    "sg:phone":"+1 585 533 2010",
    "sg:postcode":"14543",
    "sg:province":"NY",
    "wof:name":"Rush Creekside Inn",
    "wof:placetype":"venue"
},
  "geometry": {"coordinates":[-77.645259,42.992404],"type":"Point"}
}