{
  "type": "Feature",
  "properties": {
    "addr:full":"3370 Broadway St Cheektowaga NY 14227",
    "addr:housenumber":"3370",
    "addr:postcode":"14227",
    "addr:street":"Broadway St",
    "iso:country":"US",
    "sg:address":"3370 Broadway St",
    "sg:city":"Cheektowaga",
    "sg:classifiers":[
        {
            "category":"Building & Trades",
            "subcategory":"Equipment Rental",
            "type":"Services"
        }
    ],
    "sg:phone":"+1 716 684 3460",
    "sg:postcode":"14227",
    "sg:province":"NY",
    "sg:tags":[
        "heavy",
        "construction"
    ],
    "wof:name":"Lake Steel Inc",
    "wof:placetype":"venue"
},
  "geometry": {"coordinates":[-78.73629099999999,42.904044],"type":"Point"}
}