{
  "type": "Feature",
  "properties": {
    "addr:full":"20 Jackie Cir W Rochester NY 14612",
    "addr:housenumber":"20",
    "addr:postcode":"14612",
    "addr:street":"Jackie Cir W",
    "iso:country":"US",
    "sg:address":"20 Jackie Cir W",
    "sg:city":"Rochester",
    "sg:classifiers":[
        {
            "category":"Health Services",
            "subcategory":"Doctor",
            "type":"Services"
        }
    ],
    "sg:phone":"+1 585 225 9582",
    "sg:postcode":"14612",
    "sg:province":"NY",
    "sg:tags":[
        "medical"
    ],
    "wof:name":"Gerald Eckert MD",
    "wof:placetype":"venue"
},
  "geometry": {"coordinates":[-77.67232199999999,43.255466],"type":"Point"}
}