{
  "type": "Feature",
  "properties": {
    "addr:full":"775 Tiffany St Bronx NY 10474",
    "addr:housenumber":"775",
    "addr:postcode":"10474",
    "addr:street":"Tiffany St",
    "iso:country":"US",
    "sg:address":"775 Tiffany St",
    "sg:city":"Bronx",
    "sg:classifiers":[
        {
            "category":"Retail",
            "subcategory":"Auto Repair",
            "type":"Services"
        }
    ],
    "sg:phone":"+1 718 328 7878",
    "sg:postcode":"10474",
    "sg:province":"NY",
    "wof:name":"Tiffany Auto Repair Inc",
    "wof:placetype":"venue"
},
  "geometry": {"coordinates":[-73.891879,40.815996],"type":"Point"}
}