{
  "type": "Feature",
  "properties": {
    "iso:country":"US",
    "sg:address":"195 N Bedford Rd",
    "sg:city":"Mount Kisco",
    "sg:classifiers":[
        {
            "category":"Shopping",
            "subcategory":"Jewelry",
            "type":"Retail Goods"
        }
    ],
    "sg:phone":"+1 914 244 0648",
    "sg:postcode":"10549",
    "sg:province":"NY",
    "wof:name":"Jewelry Den",
    "wof:placetype":"venue"
},
  "geometry": {"coordinates":[-73.72519699999999,41.203499],"type":"Point"}
}