{
  "type": "Feature",
  "properties": {
    "iso:country":"US",
    "sg:address":"697 Grand St",
    "sg:city":"Brooklyn",
    "sg:classifiers":[
        {
            "category":"Shopping",
            "subcategory":"Music",
            "type":"Retail Goods"
        }
    ],
    "sg:phone":"+1   ",
    "sg:postcode":"11211",
    "sg:province":"NY",
    "wof:name":"J C Music World",
    "wof:placetype":"venue"
},
  "geometry": {"coordinates":[-73.944559,40.711635],"type":"Point"}
}