{
  "type": "Feature",
  "properties": {
    "iso:country":"US",
    "sg:address":"160 W 85 St",
    "sg:city":"New York",
    "sg:classifiers":[
        {
            "category":"Shopping",
            "subcategory":"Clothing, Apparel, & Fashions",
            "type":"Retail Goods"
        }
    ],
    "sg:phone":"+1   ",
    "sg:postcode":"10024",
    "sg:province":"NY",
    "sg:tags":[
        "freelance",
        "design"
    ],
    "wof:name":"Kate Kirilcuk",
    "wof:placetype":"venue"
},
  "geometry": {"coordinates":[-73.974232,40.786203],"type":"Point"}
}