{
  "type": "Feature",
  "properties": {
    "iso:country":"US",
    "sg:address":"503 Beverly Rd",
    "sg:city":"Brooklyn",
    "sg:classifiers":[
        {
            "category":"Organizations",
            "subcategory":"Religious Organization",
            "type":"Services"
        }
    ],
    "sg:phone":"+1 718 972 8816",
    "sg:postcode":"11218",
    "sg:province":"NY",
    "sg:tags":[
        "clergy"
    ],
    "wof:name":"Irwin Feldman",
    "wof:placetype":"venue"
},
  "geometry": {"coordinates":[-73.974403,40.643346],"type":"Point"}
}