{
  "type": "Feature",
  "properties": {
    "iso:country":"US",
    "sg:address":"2295 Victory Blvd",
    "sg:city":"Staten Island",
    "sg:classifiers":[
        {
            "category":"Health Services",
            "subcategory":"Health Practitioner",
            "type":"Services"
        }
    ],
    "sg:phone":"+1   ",
    "sg:postcode":"10314",
    "sg:province":"NY",
    "wof:name":"Andrea H De Luca",
    "wof:placetype":"venue"
},
  "geometry": {"coordinates":[-74.13920899999999,40.611692],"type":"Point"}
}