{
  "type": "Feature",
  "properties": {
    "iso:country":"US",
    "sg:address":"210 Main St",
    "sg:city":"Greenport",
    "sg:classifiers":[
        {
            "category":"Shopping",
            "subcategory":"Gifts & Souvenirs",
            "type":"Retail Goods"
        }
    ],
    "sg:phone":"+1   ",
    "sg:postcode":"11944",
    "sg:province":"NY",
    "sg:tags":[
        "apparel",
        "store"
    ],
    "wof:name":"Land Shark Unlimited",
    "wof:placetype":"venue"
},
  "geometry": {"coordinates":[-72.359404,41.103399],"type":"Point"}
}