{
  "type": "Feature",
  "properties": {
    "addr:full":"1165 Myrtle Avenue Brooklyn NY 11206",
    "addr:housenumber":"1165",
    "addr:postcode":"11206",
    "addr:street":"Myrtle Avenue",
    "iso:country":"US",
    "sg:address":"1165 Myrtle Avenue",
    "sg:city":"Brooklyn",
    "sg:classifiers":[
        {
            "category":"Personal",
            "subcategory":"Nail Salon",
            "type":"Services"
        }
    ],
    "sg:phone":"+1 718 443 3115",
    "sg:postcode":"11206",
    "sg:province":"NY",
    "wof:name":"San Francisco Nails",
    "wof:placetype":"venue"
},
  "geometry": {"coordinates":[-73.934686,40.697148],"type":"Point"}
}