{
  "type": "Feature",
  "properties": {
    "iso:country":"US",
    "sg:address":"208 Hamilton Rd",
    "sg:city":"Rockville Centre",
    "sg:classifiers":[
        {
            "category":"Professional",
            "subcategory":"Lawyer & Legal Services",
            "type":"Services"
        }
    ],
    "sg:phone":"+1 516 255 5336",
    "sg:postcode":"11570",
    "sg:province":"NY",
    "wof:name":"Any Key Associates",
    "wof:placetype":"venue"
},
  "geometry": {"coordinates":[-73.63009599999999,40.668201],"type":"Point"}
}