{
  "type": "Feature",
  "properties": {
    "addr:full":"4 Freemans Bridge Rd Scotia NY 12302",
    "addr:housenumber":"4",
    "addr:postcode":"12302",
    "addr:street":"Freemans Bridge Rd",
    "iso:country":"US",
    "sg:address":"4 Freemans Bridge Rd",
    "sg:city":"Scotia",
    "sg:classifiers":[
        {
            "category":"Autos & Motor Vehicles",
            "subcategory":"Boat Sales",
            "type":"Retail Goods"
        }
    ],
    "sg:phone":"+1 518 393 0305",
    "sg:postcode":"12302",
    "sg:province":"NY",
    "sg:tags":[
        "dealer",
        "sales"
    ],
    "wof:name":"Water Edge Marina",
    "wof:placetype":"venue"
},
  "geometry": {"coordinates":[-73.93078800000001,42.830431],"type":"Point"}
}