{
  "type": "Feature",
  "properties": {
    "iso:country":"US",
    "sg:address":"144 E Maine Rd",
    "sg:city":"Johnson City",
    "sg:classifiers":[
        {
            "category":"Education",
            "subcategory":"School",
            "type":"Public Place"
        }
    ],
    "sg:phone":"+1 607 763 1249",
    "sg:postcode":"13790",
    "sg:province":"NY",
    "sg:tags":[
        "high",
        "middle",
        "elementary"
    ],
    "wof:name":"Johnson City Central School District",
    "wof:placetype":"venue"
},
  "geometry": {"coordinates":[-75.960905,42.151786],"type":"Point"}
}