{
  "type": "Feature",
  "properties": {
    "addr:full":"10433 Queens Blvd Forest Hills NY 11375",
    "addr:housenumber":"10433",
    "addr:postcode":"11375",
    "addr:street":"Queens Blvd",
    "iso:country":"US",
    "sg:address":"10433 Queens Blvd",
    "sg:city":"Forest Hills",
    "sg:classifiers":[
        {
            "category":"Retail",
            "subcategory":"Laundry & Dry Cleaning",
            "type":"Services"
        }
    ],
    "sg:phone":"+1 718 520 9082",
    "sg:postcode":"11375",
    "sg:province":"NY",
    "wof:name":"Super Seven Cleaners",
    "wof:placetype":"venue"
},
  "geometry": {"coordinates":[-73.848297,40.723701],"type":"Point"}
}