{
  "type": "Feature",
  "properties": {
    "iso:country":"US",
    "sg:address":"105 N Lewis St",
    "sg:city":"Auburn",
    "sg:classifiers":[
        {
            "category":"Manufacturing",
            "subcategory":"Textiles",
            "type":"Manufacturing & Wholesale Goods"
        }
    ],
    "sg:phone":"+1   ",
    "sg:postcode":"13021",
    "sg:province":"NY",
    "sg:tags":[
        "mfg"
    ],
    "wof:name":"Lawson & Clark Designs",
    "wof:placetype":"venue"
},
  "geometry": {"coordinates":[-76.55745,42.944304],"type":"Point"}
}