{
  "type": "Feature",
  "properties": {
    "addr:full":"1371 Church St Bohemia NY 11716",
    "addr:housenumber":"1371",
    "addr:postcode":"11716",
    "addr:street":"Church St",
    "iso:country":"US",
    "sg:address":"1371 Church St",
    "sg:city":"Bohemia",
    "sg:classifiers":[
        {
            "category":"Wholesale",
            "subcategory":"Electrical",
            "type":"Manufacturing & Wholesale Goods"
        }
    ],
    "sg:phone":"+1 631 567 0530",
    "sg:postcode":"11716",
    "sg:province":"NY",
    "sg:tags":[
        "equipment",
        "ultrasonic",
        "supply"
    ],
    "wof:name":"Sonics International & Prcsn",
    "wof:placetype":"venue"
},
  "geometry": {"coordinates":[-73.08622099999999,40.770506],"type":"Point"}
}