{
  "type": "Feature",
  "properties": {
    "addr:full":"6354 Fresh Pond Road Ridgewood NY 11385",
    "addr:housenumber":"6354",
    "addr:postcode":"11385",
    "addr:street":"Fresh Pond Road",
    "iso:country":"US",
    "sg:address":"6354 Fresh Pond Road",
    "sg:city":"Ridgewood",
    "sg:classifiers":[
        {
            "category":"Health Services",
            "subcategory":"Dentist",
            "type":"Services"
        }
    ],
    "sg:phone":"+1 718 418 5555",
    "sg:postcode":"11385",
    "sg:province":"NY",
    "wof:name":"Behmanesh Babak DDS PC",
    "wof:placetype":"venue"
},
  "geometry": {"coordinates":[-73.89972299999999,40.710868],"type":"Point"}
}