{
  "type": "Feature",
  "properties": {
    "addr:full":"4000 Jericho Tpke East Northport NY 11731",
    "addr:housenumber":"4000",
    "addr:postcode":"11731",
    "addr:street":"Jericho Tpke",
    "iso:country":"US",
    "sg:address":"4000 Jericho Tpke",
    "sg:city":"East Northport",
    "sg:classifiers":[
        {
            "category":"Shopping",
            "subcategory":"Mobile Phones",
            "type":"Retail Goods"
        }
    ],
    "sg:phone":"+1 631 499 1820",
    "sg:postcode":"11731",
    "sg:province":"NY",
    "sg:website":"www.verizonwireless.com/b2c/inde...",
    "wof:name":"Verizon Wireless",
    "wof:placetype":"venue"
},
  "geometry": {"coordinates":[-73.31476000000001,40.840174],"type":"Point"}
}