{
  "type": "Feature",
  "properties": {
    "addr:full":"916 Union Rd West Seneca NY 14224",
    "addr:housenumber":"916",
    "addr:postcode":"14224",
    "addr:street":"Union Rd",
    "iso:country":"US",
    "sg:address":"916 Union Rd",
    "sg:city":"West Seneca",
    "sg:classifiers":[
        {
            "category":"Autos & Motor Vehicles",
            "subcategory":"Fuel & Gas Station",
            "type":"Retail Goods"
        }
    ],
    "sg:phone":"+1 716 674 0140",
    "sg:postcode":"14224",
    "sg:province":"NY",
    "sg:tags":[
        "oil"
    ],
    "wof:name":"Campbell's Sunoco",
    "wof:placetype":"venue"
},
  "geometry": {"coordinates":[-78.753367,42.825485],"type":"Point"}
}