{
  "type": "Feature",
  "properties": {
    "addr:full":"353 E 78th St New York NY 10021",
    "addr:housenumber":"353",
    "addr:postcode":"10021",
    "addr:street":"E 78Th St",
    "iso:country":"US",
    "sg:address":"353 E 78th St",
    "sg:city":"New York",
    "sg:classifiers":[
        {
            "category":"Personal",
            "type":"Services"
        }
    ],
    "sg:phone":"+1 631 234 3000",
    "sg:postcode":"10021",
    "sg:province":"NY",
    "sg:tags":[
        "mover"
    ],
    "wof:name":"Liberty Moving and Storage",
    "wof:placetype":"venue"
},
  "geometry": {"coordinates":[-73.954399,40.772202],"type":"Point"}
}