{
  "type": "Feature",
  "properties": {
    "addr:full":"1623 Military Rd Niagara Falls NY 14304",
    "addr:housenumber":"1623",
    "addr:postcode":"14304",
    "addr:street":"Military Rd",
    "iso:country":"US",
    "sg:address":"1623 Military Rd",
    "sg:city":"Niagara Falls",
    "sg:classifiers":[
        {
            "category":"Manufacturing",
            "subcategory":"Tools & Machinery",
            "type":"Manufacturing & Wholesale Goods"
        }
    ],
    "sg:phone":"+1 585 202 6329",
    "sg:postcode":"14304",
    "sg:province":"NY",
    "wof:name":"Kadmea Products Inc",
    "wof:placetype":"venue"
},
  "geometry": {"coordinates":[-78.971262,43.093587],"type":"Point"}
}