{
  "type": "Feature",
  "properties": {
    "iso:country":"US",
    "sg:address":"8653 Grey Birch Dr",
    "sg:city":"Baldwinsville",
    "sg:classifiers":[
        {
            "category":"Retail",
            "subcategory":"Repair Shop",
            "type":"Services"
        }
    ],
    "sg:phone":"+1 315 451 3644",
    "sg:postcode":"13027",
    "sg:province":"NY",
    "sg:tags":[
        "facsimile"
    ],
    "wof:name":"Superior Fax Repair Co",
    "wof:placetype":"venue"
},
  "geometry": {"coordinates":[-76.29120899999999,43.187722],"type":"Point"}
}