{
  "type": "Feature",
  "properties": {
    "addr:full":"357 Ronkonkoma Ave Ronkonkoma NY 11779",
    "addr:housenumber":"357",
    "addr:postcode":"11779",
    "addr:street":"Ronkonkoma Ave",
    "iso:country":"US",
    "sg:address":"357 Ronkonkoma Ave",
    "sg:city":"Ronkonkoma",
    "sg:classifiers":[
        {
            "category":"Retail",
            "subcategory":"Auto Repair",
            "type":"Services"
        }
    ],
    "sg:phone":"+1 631 585 3433",
    "sg:postcode":"11779",
    "sg:province":"NY",
    "sg:tags":[
        "brake"
    ],
    "wof:name":"Rebuilt Manufacturing",
    "wof:placetype":"venue"
},
  "geometry": {"coordinates":[-73.111509,40.810016],"type":"Point"}
}