{
  "type": "Feature",
  "properties": {
    "iso:country":"US",
    "sg:address":"3031 Long Beach Rd",
    "sg:city":"Oceanside",
    "sg:classifiers":[
        {
            "category":"Shopping",
            "subcategory":"Clothing, Apparel, & Fashions",
            "type":"Retail Goods"
        }
    ],
    "sg:phone":"+1 516 764 0525",
    "sg:postcode":"11572",
    "sg:province":"NY",
    "sg:tags":[
        "tailor"
    ],
    "wof:name":"Nick Teh Tailor",
    "wof:placetype":"venue"
},
  "geometry": {"coordinates":[-73.639903,40.638643],"type":"Point"}
}