{
  "type": "Feature",
  "properties": {
    "addr:full":"60 Northern Dr Troy NY 12182",
    "addr:housenumber":"60",
    "addr:postcode":"12182",
    "addr:street":"Northern Dr",
    "iso:country":"US",
    "sg:address":"60 Northern Dr",
    "sg:city":"Troy",
    "sg:classifiers":[
        {
            "category":"Real Estate",
            "subcategory":"Real Estate Operator",
            "type":"Services"
        }
    ],
    "sg:phone":"+1 518 233 0329",
    "sg:postcode":"12182",
    "sg:province":"NY",
    "sg:tags":[
        "mobile",
        "home",
        "community"
    ],
    "wof:name":"Hudson River Homes Mobile Hm",
    "wof:placetype":"venue"
},
  "geometry": {"coordinates":[-73.66233800000001,42.786905],"type":"Point"}
}