{
  "type": "Feature",
  "properties": {
    "iso:country":"US",
    "sg:address":"2041 86th Street",
    "sg:city":"Brooklyn",
    "sg:classifiers":[
        {
            "category":"Shopping",
            "subcategory":"Mobile Phones",
            "type":"Retail Goods"
        }
    ],
    "sg:phone":"+1 718 266 6529",
    "sg:postcode":"11214",
    "sg:province":"NY",
    "sg:website":"www.radioshack.com",
    "wof:name":"Radioshack",
    "wof:placetype":"venue"
},
  "geometry": {"coordinates":[-73.997027,40.604006],"type":"Point"}
}