{
  "type": "Feature",
  "properties": {
    "addr:full":"119 South Ave Webster NY 14580",
    "addr:housenumber":"119",
    "addr:postcode":"14580",
    "addr:street":"South Ave",
    "iso:country":"US",
    "sg:address":"119 South Ave",
    "sg:city":"Webster",
    "sg:classifiers":[
        {
            "category":"Education",
            "subcategory":"School",
            "type":"Public Place"
        }
    ],
    "sg:phone":"+1 585 265 6500",
    "sg:postcode":"14580",
    "sg:province":"NY",
    "wof:name":"Spry Middle School",
    "wof:placetype":"venue"
},
  "geometry": {"coordinates":[-77.430396,43.208683],"type":"Point"}
}