{
  "type": "Feature",
  "properties": {
    "addr:full":"421 Warren St Hudson NY 12534",
    "addr:housenumber":"421",
    "addr:postcode":"12534",
    "addr:street":"Warren St",
    "iso:country":"US",
    "sg:address":"421 Warren St",
    "sg:city":"Hudson",
    "sg:classifiers":[
        {
            "category":"Professional",
            "type":"Services"
        }
    ],
    "sg:phone":"+1 518 828 9970",
    "sg:postcode":"12534",
    "sg:province":"NY",
    "sg:tags":[
        "establishment"
    ],
    "wof:name":"Albert Stef Studios",
    "wof:placetype":"venue"
},
  "geometry": {"coordinates":[-73.788453,42.250775],"type":"Point"}
}