{
  "type": "Feature",
  "properties": {
    "iso:country":"US",
    "sg:address":"748 Main St",
    "sg:city":"Poughkeepsie",
    "sg:classifiers":[
        {
            "category":"Shopping",
            "subcategory":"Musical Instruments",
            "type":"Retail Goods"
        }
    ],
    "sg:phone":"+1 845 452 6035",
    "sg:postcode":"12603",
    "sg:province":"NY",
    "wof:name":"New York Professional Guitar",
    "wof:placetype":"venue"
},
  "geometry": {"coordinates":[-73.90464799999999,41.696591],"type":"Point"}
}