{
  "type": "Feature",
  "properties": {
    "iso:country":"US",
    "sg:address":"1739 State Hwy 214",
    "sg:city":"Lanesville",
    "sg:classifiers":[
        {
            "category":"Education",
            "subcategory":"Special Training",
            "type":"Public Place"
        }
    ],
    "sg:phone":"+1   ",
    "sg:postcode":"12450",
    "sg:province":"NY",
    "wof:name":"Nacel Open Door Inc",
    "wof:placetype":"venue"
},
  "geometry": {"coordinates":[-74.25665499999999,42.131225],"type":"Point"}
}