{
  "type": "Feature",
  "properties": {
    "addr:full":"55 33rd St Brooklyn NY 11232",
    "addr:housenumber":"55",
    "addr:postcode":"11232",
    "addr:street":"33Rd St",
    "iso:country":"US",
    "sg:address":"55 33rd St",
    "sg:city":"Brooklyn",
    "sg:classifiers":[
        {
            "category":"Manufacturing",
            "subcategory":"Retail Goods",
            "type":"Manufacturing & Wholesale Goods"
        }
    ],
    "sg:phone":"+1   ",
    "sg:postcode":"11232",
    "sg:province":"NY",
    "sg:tags":[
        "mfg",
        "christmas",
        "foliage",
        "artificial"
    ],
    "sg:website":"www.heritagechristmas.com",
    "wof:name":"Heritage",
    "wof:placetype":"venue"
},
  "geometry": {"coordinates":[-74.005578,40.658001],"type":"Point"}
}