{
  "type": "Feature",
  "properties": {
    "addr:full":"360 Jefferson Rd Rochester NY 14623",
    "addr:housenumber":"360",
    "addr:postcode":"14623",
    "addr:street":"Jefferson Rd",
    "iso:country":"US",
    "sg:address":"360 Jefferson Rd",
    "sg:city":"Rochester",
    "sg:classifiers":[
        {
            "category":"Building & Trades",
            "subcategory":"Construction",
            "type":"Services"
        },
        {
            "category":"Home & Garden",
            "subcategory":"Carpets & Floor Coverings",
            "type":"Retail Goods"
        }
    ],
    "sg:phone":"+1 800 394 3064",
    "sg:postcode":"14623",
    "sg:province":"NY",
    "sg:tags":[
        "material",
        "tile-contractors",
        "rug",
        "flooring",
        "contractor"
    ],
    "sg:website":"http://www.filitrac.com/Click.aspx?tid=BDEDC5D5EF8BAE3541B5938870DA3DDECE60F60FEE115906&FiliAff=15016&sid=99202&utm_source=YellowPages&utm_medium=ppc&utm_campaign=national&utm_term=14623",
    "wof:name":"Rochester Linoleum & Carpet One",
    "wof:placetype":"venue"
},
  "geometry": {"coordinates":[-77.646156,43.090729],"type":"Point"}
}