{
  "type": "Feature",
  "properties": {
    "iso:country":"US",
    "sg:address":"280 Genesee St",
    "sg:city":"Utica",
    "sg:classifiers":[
        {
            "category":"Professional",
            "subcategory":"Accounting & Tax Preparation",
            "type":"Services"
        }
    ],
    "sg:phone":"+1 315 890 6740",
    "sg:postcode":"13502",
    "sg:province":"NY",
    "wof:name":"Bell Atlantic",
    "wof:placetype":"venue"
},
  "geometry": {"coordinates":[-75.23803700000001,43.098186],"type":"Point"}
}