{
  "type": "Feature",
  "properties": {
    "iso:country":"US",
    "sg:address":"452 W 1st St",
    "sg:city":"Elmira",
    "sg:classifiers":[
        {
            "category":"Manufacturing",
            "subcategory":"Furniture",
            "type":"Manufacturing & Wholesale Goods"
        }
    ],
    "sg:phone":"+1   ",
    "sg:postcode":"14901",
    "sg:province":"NY",
    "sg:tags":[
        "hardware",
        "blind",
        "drapery",
        "mfg"
    ],
    "wof:name":"Elmira Shade Works",
    "wof:placetype":"venue"
},
  "geometry": {"coordinates":[-76.817819,42.088127],"type":"Point"}
}