{
  "type": "Feature",
  "properties": {
    "addr:full":"200 E Highland Dr Rochester NY 14610",
    "addr:housenumber":"200",
    "addr:postcode":"14610",
    "addr:street":"E Highland Dr",
    "iso:country":"US",
    "sg:address":"200 E Highland Dr",
    "sg:city":"Rochester",
    "sg:classifiers":[
        {
            "category":"Professional",
            "subcategory":"Accounting & Tax Preparation",
            "type":"Services"
        }
    ],
    "sg:phone":"+1 585 697 9730",
    "sg:postcode":"14610",
    "sg:province":"NY",
    "sg:tags":[
        "billing"
    ],
    "wof:name":"Mid Town Athletic Club Billing",
    "wof:placetype":"venue"
},
  "geometry": {"coordinates":[-77.552334,43.138802],"type":"Point"}
}