{
  "type": "Feature",
  "properties": {
    "addr:full":"7703 Main St Flushing NY 11367",
    "addr:housenumber":"7703",
    "addr:postcode":"11367",
    "addr:street":"Main St",
    "iso:country":"US",
    "sg:address":"7703 Main St",
    "sg:city":"Flushing",
    "sg:classifiers":[
        {
            "category":"Organizations",
            "subcategory":"Religious Organization",
            "type":"Services"
        }
    ],
    "sg:phone":"+1 718 380 7422",
    "sg:postcode":"11367",
    "sg:province":"NY",
    "wof:name":"Chabad of Flushing Inc",
    "wof:placetype":"venue"
},
  "geometry": {"coordinates":[-73.818703,40.7211],"type":"Point"}
}