{
  "type": "Feature",
  "properties": {
    "iso:country":"US",
    "sg:address":"241 Surrey Run",
    "sg:city":"Buffalo",
    "sg:classifiers":[
        {
            "category":"Insurance",
            "subcategory":"Insurance Agent",
            "type":"Services"
        }
    ],
    "sg:phone":"+1 716 631 8014",
    "sg:postcode":"14221",
    "sg:province":"NY",
    "wof:name":"Gerald C Gentner",
    "wof:placetype":"venue"
},
  "geometry": {"coordinates":[-78.749909,42.986257],"type":"Point"}
}