{
  "type": "Feature",
  "properties": {
    "addr:full":"444 Park Avenue South  Suite 1202 New York NY 10016",
    "addr:housenumber":"444",
    "addr:postcode":"10016",
    "addr:street":"Park Avenue South Suite 1202",
    "iso:country":"US",
    "sg:address":"444 Park Avenue South  Suite 1202",
    "sg:city":"New York",
    "sg:classifiers":[
        {
            "category":"Professional",
            "subcategory":"Computer Services",
            "type":"Services"
        }
    ],
    "sg:phone":"+1 212 679 8610",
    "sg:postcode":"10016",
    "sg:province":"NY",
    "sg:website":"http://www.adventity.com/",
    "wof:name":"Adventity",
    "wof:placetype":"venue"
},
  "geometry": {"coordinates":[-73.982831,40.745147],"type":"Point"}
}