{
  "type": "Feature",
  "properties": {
    "addr:full":"6 E 43rd St New York NY 10017",
    "addr:housenumber":"6",
    "addr:postcode":"10017",
    "addr:street":"E 43Rd St",
    "iso:country":"US",
    "sg:address":"6 E 43rd St",
    "sg:city":"New York",
    "sg:classifiers":[
        {
            "category":"Banks & Credit Unions",
            "subcategory":"Financial Services",
            "type":"Services"
        }
    ],
    "sg:phone":"+1 212 634 8913",
    "sg:postcode":"10017",
    "sg:province":"NY",
    "sg:tags":[
        "patent"
    ],
    "wof:name":"Cast Iron Corporation",
    "wof:placetype":"venue"
},
  "geometry": {"coordinates":[-73.978994,40.753512],"type":"Point"}
}