{
  "type": "Feature",
  "properties": {
    "addr:full":"136 S Erie St Mayville NY 14757",
    "addr:housenumber":"136",
    "addr:postcode":"14757",
    "addr:street":"S Erie St",
    "iso:country":"US",
    "sg:address":"136 S Erie St",
    "sg:city":"Mayville",
    "sg:classifiers":[
        {
            "category":"Building & Trades",
            "subcategory":"Landscaping Services",
            "type":"Services"
        }
    ],
    "sg:phone":"+1 716 753 2787",
    "sg:postcode":"14757",
    "sg:province":"NY",
    "wof:name":"R & R Landscaping",
    "wof:placetype":"venue"
},
  "geometry": {"coordinates":[-79.49826,42.249338],"type":"Point"}
}