{
  "type": "Feature",
  "properties": {
    "addr:full":"801 E 14th Street New York NY 10009",
    "addr:housenumber":"801",
    "addr:postcode":"10009",
    "addr:street":"E 14Th Street",
    "iso:country":"US",
    "sg:address":"801 E 14th Street",
    "sg:city":"New York",
    "sg:classifiers":[
        {
            "category":"Real Estate",
            "subcategory":"Architect",
            "type":"Services"
        }
    ],
    "sg:phone":"+1 212 979 2570",
    "sg:postcode":"10009",
    "sg:province":"NY",
    "wof:name":"Shirin Construction",
    "wof:placetype":"venue"
},
  "geometry": {"coordinates":[-73.97301400000001,40.727442],"type":"Point"}
}