{
  "type": "Feature",
  "properties": {
    "addr:full":"56 Maple Ave Voorheesville NY 12186",
    "addr:housenumber":"56",
    "addr:postcode":"12186",
    "addr:street":"Maple Ave",
    "iso:country":"US",
    "sg:address":"56 Maple Ave",
    "sg:city":"Voorheesville",
    "sg:classifiers":[
        {
            "category":"Social Services",
            "type":"Services"
        }
    ],
    "sg:phone":"+1 518 765 5137",
    "sg:postcode":"12186",
    "sg:province":"NY",
    "sg:tags":[
        "organization",
        "welfare"
    ],
    "wof:name":"Community Works Of NYS",
    "wof:placetype":"venue"
},
  "geometry": {"coordinates":[-73.927995,42.650039],"type":"Point"}
}