{
  "type": "Feature",
  "properties": {
    "iso:country":"US",
    "sg:address":"11124 Flatlands Ave",
    "sg:city":"Brooklyn",
    "sg:classifiers":[
        {
            "category":"Food & Beverages",
            "subcategory":"Bakery",
            "type":"Retail Goods"
        }
    ],
    "sg:phone":"+1   ",
    "sg:postcode":"11207",
    "sg:province":"NY",
    "sg:tags":[
        "bagel"
    ],
    "wof:name":"Starret Bagels Inc",
    "wof:placetype":"venue"
},
  "geometry": {"coordinates":[-73.89005299999999,40.650953],"type":"Point"}
}