{
  "type": "Feature",
  "properties": {
    "addr:full":"83 Betwood Ln Rochester NY 14612",
    "addr:housenumber":"83",
    "addr:postcode":"14612",
    "addr:street":"Betwood Ln",
    "iso:country":"US",
    "sg:address":"83 Betwood Ln",
    "sg:city":"Rochester",
    "sg:classifiers":[
        {
            "category":"Professional",
            "type":"Services"
        }
    ],
    "sg:phone":"+1 585 225 3851",
    "sg:postcode":"14612",
    "sg:province":"NY",
    "sg:tags":[
        "information",
        "bureau"
    ],
    "wof:name":"Pa Testa Services Inc",
    "wof:placetype":"venue"
},
  "geometry": {"coordinates":[-77.701876,43.245222],"type":"Point"}
}