{
  "type": "Feature",
  "properties": {
    "addr:full":"2524 Broadway Astoria NY 11106",
    "addr:housenumber":"2524",
    "addr:postcode":"11106",
    "addr:street":"Broadway",
    "iso:country":"US",
    "sg:address":"2524 Broadway",
    "sg:city":"Astoria",
    "sg:classifiers":[
        {
            "category":"Restaurant",
            "type":"Food & Drink"
        }
    ],
    "sg:menulink":"http://www.allmenus.com/ny/queens/292110-osaka-japanese/menu/",
    "sg:phone":"+1 718 777 2662",
    "sg:postcode":"11106",
    "sg:province":"NY",
    "sg:tags":[
        "japanese"
    ],
    "wof:name":"Osaka Japanese",
    "wof:placetype":"venue"
},
  "geometry": {"coordinates":[-73.928089,40.763089],"type":"Point"}
}