{
  "type": "Feature",
  "properties": {
    "addr:full":"95 Chambers St New York NY 10007",
    "addr:housenumber":"95",
    "addr:postcode":"10007",
    "addr:street":"Chambers St",
    "iso:country":"US",
    "sg:address":"95 Chambers St",
    "sg:city":"New York",
    "sg:classifiers":[
        {
            "category":"Real Estate",
            "subcategory":"Real Estate Operator",
            "type":"Services"
        }
    ],
    "sg:phone":"+1 212 267 5567",
    "sg:postcode":"10007",
    "sg:province":"NY",
    "sg:tags":[
        "property",
        "commercial"
    ],
    "wof:name":"Rae ME Realty Inc",
    "wof:placetype":"venue"
},
  "geometry": {"coordinates":[-74.006912,40.714382],"type":"Point"}
}