{
  "type": "Feature",
  "properties": {
    "iso:country":"US",
    "sg:address":"1407 Grand Central Ave",
    "sg:city":"Elmira",
    "sg:classifiers":[
        {
            "category":"Shopping",
            "subcategory":"Computers & Home Electronics",
            "type":"Retail Goods"
        }
    ],
    "sg:phone":"+1   ",
    "sg:postcode":"14901",
    "sg:province":"NY",
    "wof:name":"D C Computer Works",
    "wof:placetype":"venue"
},
  "geometry": {"coordinates":[-76.811054,42.111953],"type":"Point"}
}