{
  "type": "Feature",
  "properties": {
    "addr:full":"104 W 29th St Fl 3 New York NY 10001",
    "addr:housenumber":"104;3",
    "addr:postcode":"10001",
    "addr:street":"W 29Th St",
    "iso:country":"US",
    "sg:address":"104 W 29th St Fl 3",
    "sg:city":"New York",
    "sg:classifiers":[
        {
            "category":"Social Services",
            "subcategory":"Child Care",
            "type":"Services"
        }
    ],
    "sg:phone":"+1 212 645 9971",
    "sg:postcode":"10001",
    "sg:province":"NY",
    "sg:tags":[
        "day"
    ],
    "wof:name":"Herbert G Birch",
    "wof:placetype":"venue"
},
  "geometry": {"coordinates":[-73.990246,40.746591],"type":"Point"}
}