{
  "type": "Feature",
  "properties": {
    "iso:country":"US",
    "sg:address":"10941 Fairchild Rd",
    "sg:city":"Remsen",
    "sg:classifiers":[
        {
            "category":"Farming",
            "subcategory":"Livestock Farm",
            "type":"Manufacturing & Wholesale Goods"
        }
    ],
    "sg:phone":"+1 315 831 5365",
    "sg:postcode":"13438",
    "sg:province":"NY",
    "sg:tags":[
        "beef",
        "feedlot",
        "cattle"
    ],
    "wof:name":"Groeslon Farms Inc",
    "wof:placetype":"venue"
},
  "geometry": {"coordinates":[-75.177065,43.342227],"type":"Point"}
}