{
  "type": "Feature",
  "properties": {
    "addr:full":"261 E 172nd St Bronx NY 10457",
    "addr:housenumber":"261",
    "addr:postcode":"10457",
    "addr:street":"E 172Nd St",
    "iso:country":"US",
    "sg:address":"261 E 172nd St",
    "sg:city":"Bronx",
    "sg:classifiers":[
        {
            "category":"Food & Beverages",
            "subcategory":"Groceries & Convenience Stores",
            "type":"Retail Goods"
        }
    ],
    "sg:phone":"+1 718 466 1942",
    "sg:postcode":"10457",
    "sg:province":"NY",
    "sg:tags":[
        "grocer"
    ],
    "wof:name":"Lisa Grocery",
    "wof:placetype":"venue"
},
  "geometry": {"coordinates":[-73.910963,40.840605],"type":"Point"}
}