{
  "type": "Feature",
  "properties": {
    "addr:full":"650 Randall Rd Ballston Spa NY 12020",
    "addr:housenumber":"650",
    "addr:postcode":"12020",
    "addr:street":"Randall Rd",
    "iso:country":"US",
    "sg:address":"650 Randall Rd",
    "sg:city":"Ballston Spa",
    "sg:classifiers":[
        {
            "category":"Professional",
            "type":"Services"
        }
    ],
    "sg:phone":"+1 518 884 9959",
    "sg:postcode":"12020",
    "sg:province":"NY",
    "sg:tags":[
        "establishment"
    ],
    "wof:name":"Redbut Development Inc",
    "wof:placetype":"venue"
},
  "geometry": {"coordinates":[-73.907833,42.977477],"type":"Point"}
}