{
  "type": "Feature",
  "properties": {
    "addr:full":"17 Tinker St Woodstock NY 12498",
    "addr:housenumber":"17",
    "addr:postcode":"12498",
    "addr:street":"Tinker St",
    "iso:country":"US",
    "sg:address":"17 Tinker St",
    "sg:city":"Woodstock",
    "sg:classifiers":[
        {
            "category":"Shopping",
            "subcategory":"Florist",
            "type":"Retail Goods"
        }
    ],
    "sg:phone":"+1 845 679 6161",
    "sg:postcode":"12498",
    "sg:province":"NY",
    "sg:tags":[
        "basket",
        "gift"
    ],
    "sg:website":"http://www.jaritas.com",
    "wof:name":"Jarita's Florist",
    "wof:placetype":"venue"
},
  "geometry": {"coordinates":[-74.119469,42.04049],"type":"Point"}
}