{
  "type": "Feature",
  "properties": {
    "addr:full":"437 Carpenter Ave Sea Cliff NY 11579",
    "addr:housenumber":"437",
    "addr:postcode":"11579",
    "addr:street":"Carpenter Ave",
    "iso:country":"US",
    "sg:address":"437 Carpenter Ave",
    "sg:city":"Sea Cliff",
    "sg:classifiers":[
        {
            "category":"Building & Trades",
            "subcategory":"Construction",
            "type":"Services"
        }
    ],
    "sg:phone":"+1 516 759 4858",
    "sg:postcode":"11579",
    "sg:province":"NY",
    "sg:tags":[
        "contractor",
        "general"
    ],
    "wof:name":"Peconic Design LLC",
    "wof:placetype":"venue"
},
  "geometry": {"coordinates":[-73.637827,40.839057],"type":"Point"}
}