{
  "type": "Feature",
  "properties": {
    "iso:country":"US",
    "sg:address":"479 State Hwy 9b",
    "sg:city":"Champlain",
    "sg:classifiers":[
        {
            "category":"Building & Trades",
            "subcategory":"Construction",
            "type":"Services"
        }
    ],
    "sg:phone":"+1 518 298 4543",
    "sg:postcode":"12919",
    "sg:province":"NY",
    "sg:tags":[
        "contractor"
    ],
    "wof:name":"Melech Masonary",
    "wof:placetype":"venue"
},
  "geometry": {"coordinates":[-73.36404400000001,44.974374],"type":"Point"}
}