{
  "type": "Feature",
  "properties": {
    "iso:country":"US",
    "sg:address":"200 Bishop McGann Dr",
    "sg:city":"Central Islip",
    "sg:classifiers":[
        {
            "category":"Real Estate",
            "subcategory":"Real Estate Operator",
            "type":"Services"
        }
    ],
    "sg:phone":"+1 631 232 9356",
    "sg:postcode":"11722",
    "sg:province":"NY",
    "sg:tags":[
        "apartment"
    ],
    "wof:name":"Bishop McGann Village",
    "wof:placetype":"venue"
},
  "geometry": {"coordinates":[-73.19940200000001,40.7789],"type":"Point"}
}