{
  "type": "Feature",
  "properties": {
    "addr:full":"4 Mill St Cazenovia NY 13035",
    "addr:housenumber":"4",
    "addr:postcode":"13035",
    "addr:street":"Mill St",
    "iso:country":"US",
    "sg:address":"4 Mill St",
    "sg:city":"Cazenovia",
    "sg:classifiers":[
        {
            "category":"Utilities",
            "subcategory":"Telephone",
            "type":"Services"
        }
    ],
    "sg:phone":"+1   ",
    "sg:postcode":"13035",
    "sg:province":"NY",
    "sg:tags":[
        "communication",
        "location"
    ],
    "wof:name":"Alltel New York Inc",
    "wof:placetype":"venue"
},
  "geometry": {"coordinates":[-75.85305099999999,42.929756],"type":"Point"}
}