{
  "type": "Feature",
  "properties": {
    "addr:full":"900 Third Avenue 17th floor New York NY 10022",
    "addr:housenumber":"900;17th floor",
    "addr:postcode":"10022",
    "addr:street":"Third Avenue",
    "iso:country":"US",
    "sg:address":"900 Third Avenue 17th floor",
    "sg:city":"New York",
    "sg:classifiers":[
        {
            "category":"Shopping",
            "subcategory":"Beauty & Cosmetics",
            "type":"Retail Goods"
        }
    ],
    "sg:phone":"+1 888 788 6277",
    "sg:postcode":"10022",
    "sg:province":"NY",
    "sg:tags":[
        "supply"
    ],
    "sg:website":"www.narscosmetics.com/",
    "wof:name":"NARS Cosmetics, Inc.",
    "wof:placetype":"venue"
},
  "geometry": {"coordinates":[-73.968909,40.758369],"type":"Point"}
}