{
  "type": "Feature",
  "properties": {
    "addr:full":"125 State St Clayton NY 13624",
    "addr:housenumber":"125",
    "addr:postcode":"13624",
    "addr:street":"State St",
    "iso:country":"US",
    "sg:address":"125 State St",
    "sg:city":"Clayton",
    "sg:classifiers":[
        {
            "category":"Health Services",
            "subcategory":"Chiropractor",
            "type":"Services"
        }
    ],
    "sg:phone":"+1 315 686 4083",
    "sg:postcode":"13624",
    "sg:province":"NY",
    "wof:name":"Atlas Chiropractic",
    "wof:placetype":"venue"
},
  "geometry": {"coordinates":[-76.07843,44.237657],"type":"Point"}
}