{
  "type": "Feature",
  "properties": {
    "addr:full":"5009 E Lake Rd Romulus NY 14541",
    "addr:housenumber":"5009",
    "addr:postcode":"14541",
    "addr:street":"E Lake Rd",
    "iso:country":"US",
    "sg:address":"5009 E Lake Rd",
    "sg:city":"Romulus",
    "sg:classifiers":[
        {
            "category":"Farming",
            "subcategory":"Farm",
            "type":"Manufacturing & Wholesale Goods"
        }
    ],
    "sg:phone":"+1 315 585 6610",
    "sg:postcode":"14541",
    "sg:province":"NY",
    "sg:tags":[
        "crop",
        "general"
    ],
    "wof:name":"Allen Light",
    "wof:placetype":"venue"
},
  "geometry": {"coordinates":[-76.927741,42.785489],"type":"Point"}
}