{
  "type": "Feature",
  "properties": {
    "addr:full":"359 Graham Avenue Brooklyn NY 11211",
    "addr:housenumber":"359",
    "addr:postcode":"11211",
    "addr:street":"Graham Avenue",
    "iso:country":"US",
    "sg:address":"359 Graham Avenue",
    "sg:city":"Brooklyn",
    "sg:classifiers":[
        {
            "category":"Food & Beverages",
            "subcategory":"Groceries & Convenience Stores",
            "type":"Retail Goods"
        }
    ],
    "sg:phone":"+1 718 388 8762",
    "sg:postcode":"11211",
    "sg:province":"NY",
    "wof:name":"359 Deli & Grocery Ltd",
    "wof:placetype":"venue"
},
  "geometry": {"coordinates":[-73.94466,40.715306],"type":"Point"}
}