{
  "type": "Feature",
  "properties": {
    "iso:country":"US",
    "sg:address":"4581 State Hwy 49",
    "sg:city":"Rome",
    "sg:classifiers":[
        {
            "category":"Shopping",
            "subcategory":"Bicycles & Sporting Goods",
            "type":"Retail Goods"
        }
    ],
    "sg:phone":"+1 315 336 3619",
    "sg:postcode":"13440",
    "sg:province":"NY",
    "wof:name":"D N Sports",
    "wof:placetype":"venue"
},
  "geometry": {"coordinates":[-75.488727,43.22647],"type":"Point"}
}