{
  "type": "Feature",
  "properties": {
    "addr:full":"74 Seminary Ave Yonkers NY 10704",
    "addr:housenumber":"74",
    "addr:postcode":"10704",
    "addr:street":"Seminary Ave",
    "iso:country":"US",
    "sg:address":"74 Seminary Ave",
    "sg:city":"Yonkers",
    "sg:classifiers":[
        {
            "category":"Insurance",
            "subcategory":"Insurance Agent",
            "type":"Services"
        }
    ],
    "sg:phone":"+1 914 965 0984",
    "sg:postcode":"10704",
    "sg:province":"NY",
    "wof:name":"Albert Lenke General Insurance",
    "wof:placetype":"venue"
},
  "geometry": {"coordinates":[-73.86515300000001,40.926708],"type":"Point"}
}