{
  "type": "Feature",
  "properties": {
    "addr:full":"3603 Avenue S Brooklyn NY 11234",
    "addr:housenumber":"3603",
    "addr:postcode":"11234",
    "addr:street":"Avenue S",
    "iso:country":"US",
    "sg:address":"3603 Avenue S",
    "sg:city":"Brooklyn",
    "sg:classifiers":[
        {
            "category":"Retail",
            "subcategory":"Pet Boarding",
            "type":"Services"
        }
    ],
    "sg:phone":"+1 718 253 7338",
    "sg:postcode":"11234",
    "sg:province":"NY",
    "sg:tags":[
        "boarding/pet",
        "sitting"
    ],
    "wof:name":"Gloria's Dog Beauty Salon",
    "wof:placetype":"venue"
},
  "geometry": {"coordinates":[-73.931315,40.609921],"type":"Point"}
}