{
  "type": "Feature",
  "properties": {
    "addr:full":"441 Wythe Ave Brooklyn NY 11211",
    "addr:housenumber":"441",
    "addr:postcode":"11211",
    "addr:street":"Wythe Ave",
    "iso:country":"US",
    "sg:address":"441 Wythe Ave",
    "sg:city":"Brooklyn",
    "sg:classifiers":[
        {
            "category":"Real Estate",
            "subcategory":"Real Estate Services",
            "type":"Services"
        }
    ],
    "sg:phone":"+1 718 388 4141",
    "sg:postcode":"11211",
    "sg:province":"NY",
    "sg:tags":[
        "management",
        "property"
    ],
    "wof:name":"Schwartz Benjamin",
    "wof:placetype":"venue"
},
  "geometry": {"coordinates":[-73.966852,40.709349],"type":"Point"}
}