{
  "type": "Feature",
  "properties": {
    "iso:country":"US",
    "sg:address":"4356 Millwood Cir",
    "sg:city":"Liverpool",
    "sg:classifiers":[
        {
            "category":"Autos & Motor Vehicles",
            "subcategory":"Motorcycle Sales",
            "type":"Retail Goods"
        }
    ],
    "sg:phone":"+1 315 622 9583",
    "sg:postcode":"13090",
    "sg:province":"NY",
    "sg:tags":[
        "scooter"
    ],
    "wof:name":"Pocket Rocket Motors",
    "wof:placetype":"venue"
},
  "geometry": {"coordinates":[-76.21135099999999,43.1455],"type":"Point"}
}