{
  "type": "Feature",
  "properties": {
    "addr:full":"1211 Madison Ave New York NY 10128",
    "addr:housenumber":"1211",
    "addr:postcode":"10128",
    "addr:street":"Madison Ave",
    "iso:country":"US",
    "sg:address":"1211 Madison Ave",
    "sg:city":"New York",
    "sg:classifiers":[
        {
            "category":"Food & Beverages",
            "subcategory":"Groceries & Convenience Stores",
            "type":"Retail Goods"
        }
    ],
    "sg:phone":"+1 212 722 0229",
    "sg:postcode":"10128",
    "sg:province":"NY",
    "sg:tags":[
        "product",
        "drugstore"
    ],
    "sg:website":"www.thefoodemporium.com",
    "wof:name":"Food Emporium",
    "wof:placetype":"venue"
},
  "geometry": {"coordinates":[-73.958099,40.782001],"type":"Point"}
}