{
  "type": "Feature",
  "properties": {
    "addr:full":"508 W 21st St New York NY 10011",
    "addr:housenumber":"508",
    "addr:postcode":"10011",
    "addr:street":"W 21St St",
    "iso:country":"US",
    "sg:address":"508 W 21st St",
    "sg:city":"New York",
    "sg:classifiers":[
        {
            "category":"Retail",
            "subcategory":"Auto Repair",
            "type":"Services"
        }
    ],
    "sg:phone":"+1 212 741 2665",
    "sg:postcode":"10011",
    "sg:province":"NY",
    "wof:name":"Jaj Auto Repair",
    "wof:placetype":"venue"
},
  "geometry": {"coordinates":[-74.00599699999999,40.746899],"type":"Point"}
}