{
  "type": "Feature",
  "properties": {
    "iso:country":"US",
    "sg:address":"999 Primrose Ln",
    "sg:city":"Valley Stream",
    "sg:classifiers":[
        {
            "category":"Building & Trades",
            "subcategory":"Construction",
            "type":"Services"
        }
    ],
    "sg:phone":"+1 516 872 0700",
    "sg:postcode":"11580",
    "sg:province":"NY",
    "sg:tags":[
        "excavating",
        "contractor"
    ],
    "wof:name":"Hard Roads Of Ny Inc",
    "wof:placetype":"venue"
},
  "geometry": {"coordinates":[-73.682349,40.682787],"type":"Point"}
}