{
  "type": "Feature",
  "properties": {
    "iso:country":"US",
    "sg:address":"3040 Veterans Memorial Hwy",
    "sg:city":"Bohemia",
    "sg:classifiers":[
        {
            "category":"Bus Charters",
            "type":"Transportation"
        }
    ],
    "sg:phone":"+1 631 585 6565",
    "sg:postcode":"11716",
    "sg:province":"NY",
    "sg:tags":[
        "rental"
    ],
    "wof:name":"Baumann & Sons Buses Inc",
    "wof:placetype":"venue"
},
  "geometry": {"coordinates":[-73.161017,40.791671],"type":"Point"}
}