{
  "type": "Feature",
  "properties": {
    "addr:full":"93 Guy Park Ave Amsterdam NY 12010",
    "addr:housenumber":"93",
    "addr:postcode":"12010",
    "addr:street":"Guy Park Ave",
    "iso:country":"US",
    "sg:address":"93 Guy Park Ave",
    "sg:city":"Amsterdam",
    "sg:classifiers":[
        {
            "category":"Health Services",
            "subcategory":"Optometrist",
            "type":"Services"
        }
    ],
    "sg:phone":"+1 518 842 9676",
    "sg:postcode":"12010",
    "sg:province":"NY",
    "wof:name":"Family Eye Care Center",
    "wof:placetype":"venue"
},
  "geometry": {"coordinates":[-74.198025,42.943994],"type":"Point"}
}