{
  "type": "Feature",
  "properties": {
    "addr:full":"1286 Grand Ave North Baldwin NY 11510",
    "addr:housenumber":"1286",
    "addr:postcode":"11510",
    "addr:street":"Grand Ave North",
    "iso:country":"US",
    "sg:address":"1286 Grand Ave",
    "sg:city":"North Baldwin",
    "sg:classifiers":[
        {
            "category":"Real Estate",
            "subcategory":"Real Estate Agent",
            "type":"Services"
        }
    ],
    "sg:phone":"+1 516 379 2212",
    "sg:postcode":"11510",
    "sg:province":"NY",
    "wof:name":"Baldwin Financial Svc Inc",
    "wof:placetype":"venue"
},
  "geometry": {"coordinates":[-73.61469,40.678904],"type":"Point"}
}