{
  "type": "Feature",
  "properties": {
    "addr:full":"1813 Little York Xing Rd Homer NY 13077",
    "addr:housenumber":"1813",
    "addr:postcode":"13077",
    "addr:street":"Little;Xing Rd",
    "iso:country":"US",
    "sg:address":"1813 Little York Xing Rd",
    "sg:city":"Homer",
    "sg:classifiers":[
        {
            "category":"Utilities",
            "subcategory":"Telephone",
            "type":"Services"
        }
    ],
    "sg:phone":"+1 607 749 2869",
    "sg:postcode":"13077",
    "sg:province":"NY",
    "sg:tags":[
        "telecommunication"
    ],
    "sg:website":"www.americantower.com",
    "wof:name":"American Tower Corp",
    "wof:placetype":"venue"
},
  "geometry": {"coordinates":[-76.15651699999999,42.69562],"type":"Point"}
}