{
  "type": "Feature",
  "properties": {
    "addr:full":"421 William St Buffalo NY 14204",
    "addr:housenumber":"421",
    "addr:postcode":"14204",
    "addr:street":"William St",
    "iso:country":"US",
    "sg:address":"421 William St",
    "sg:city":"Buffalo",
    "sg:classifiers":[
        {
            "category":"Professional",
            "subcategory":"Accounting & Tax Preparation",
            "type":"Services"
        },
        {
            "category":"Banks & Credit Unions",
            "subcategory":"Financial Services",
            "type":"Services"
        }
    ],
    "sg:phone":"+1 716 853 1264",
    "sg:postcode":"14204",
    "sg:province":"NY",
    "sg:tags":[
        "return",
        "preparation-business",
        "taxes-consultants",
        "loan",
        "reporting",
        "representative",
        "alternative",
        "bookkeeping"
    ],
    "sg:website":"http://www.hrblock.com",
    "wof:name":"H&R Block",
    "wof:placetype":"venue"
},
  "geometry": {"coordinates":[-78.855468,42.885013],"type":"Point"}
}