{
  "type": "Feature",
  "properties": {
    "iso:country":"US",
    "sg:address":"66 Mercer St",
    "sg:city":"New York",
    "sg:classifiers":[
        {
            "category":"Wholesale",
            "subcategory":"Groceries",
            "type":"Manufacturing & Wholesale Goods"
        }
    ],
    "sg:phone":"+1 212 274 1870",
    "sg:postcode":"10012",
    "sg:province":"NY",
    "sg:tags":[
        "baker"
    ],
    "wof:name":"NFP Bakery Mfg Corp",
    "wof:placetype":"venue"
},
  "geometry": {"coordinates":[-73.999624,40.723259],"type":"Point"}
}