{
  "type": "Feature",
  "properties": {
    "addr:full":"Church Street Station P.O. Box 3454 New York NY 10008",
    "addr:housenumber":"box",
    "addr:postcode":"3454;10008",
    "addr:street":"P.O.",
    "iso:country":"US",
    "sg:address":"Church Street Station P.O. Box 3454",
    "sg:city":"New York",
    "sg:classifiers":[
        {
            "category":"Professional",
            "subcategory":"Computer Services",
            "type":"Services"
        }
    ],
    "sg:phone":"+1 212 520 7000",
    "sg:postcode":"10008",
    "sg:province":"NY",
    "sg:tags":[
        "videochat",
        "chatrooms",
        "chat",
        "video",
        "socialnetworking"
    ],
    "sg:website":"http://www.paltalk.com/",
    "wof:name":"Paltalk",
    "wof:placetype":"venue"
},
  "geometry": {"coordinates":[-73.977182,40.780751],"type":"Point"}
}