{
  "type": "Feature",
  "properties": {
    "iso:country":"US",
    "sg:address":"9111 Hillview Dr",
    "sg:city":"Clarence",
    "sg:classifiers":[
        {
            "category":"Manufacturing",
            "subcategory":"Soap",
            "type":"Manufacturing & Wholesale Goods"
        }
    ],
    "sg:phone":"+1   ",
    "sg:postcode":"14031",
    "sg:province":"NY",
    "sg:tags":[
        "detergent",
        "mfg"
    ],
    "wof:name":"White Fawn Herbal Soap",
    "wof:placetype":"venue"
},
  "geometry": {"coordinates":[-78.648579,42.979843],"type":"Point"}
}