{
  "type": "Feature",
  "properties": {
    "addr:full":"36 N Main St Mechanicville NY 12118",
    "addr:housenumber":"36",
    "addr:postcode":"12118",
    "addr:street":"N Main St",
    "iso:country":"US",
    "sg:address":"36 N Main St",
    "sg:city":"Mechanicville",
    "sg:classifiers":[
        {
            "category":"Building & Trades",
            "subcategory":"Construction",
            "type":"Services"
        },
        {
            "category":"Government",
            "subcategory":"Court House",
            "type":"Public Place"
        }
    ],
    "sg:phone":"+1 518 664 7171",
    "sg:postcode":"12118",
    "sg:province":"NY",
    "sg:tags":[
        "city"
    ],
    "wof:name":"Mechanicville City Court",
    "wof:placetype":"venue"
},
  "geometry": {"coordinates":[-73.685181,42.904183],"type":"Point"}
}