{
  "type": "Feature",
  "properties": {
    "addr:full":"253 Burlington Ave Deer Park NY 11729",
    "addr:housenumber":"253",
    "addr:postcode":"11729",
    "addr:street":"Burlington Ave",
    "iso:country":"US",
    "sg:address":"253 Burlington Ave",
    "sg:city":"Deer Park",
    "sg:classifiers":[
        {
            "category":"Shopping",
            "subcategory":"Clothing, Apparel, & Fashions",
            "type":"Retail Goods"
        }
    ],
    "sg:phone":"+1   ",
    "sg:postcode":"11729",
    "sg:province":"NY",
    "sg:tags":[
        "wear"
    ],
    "wof:name":"Kidz Play",
    "wof:placetype":"venue"
},
  "geometry": {"coordinates":[-73.312617,40.780086],"type":"Point"}
}