{
  "type": "Feature",
  "properties": {
    "iso:country":"US",
    "sg:address":"144 Woodgate Dr",
    "sg:city":"Cheektowaga",
    "sg:classifiers":[
        {
            "category":"Professional",
            "subcategory":"Lawyer & Legal Services",
            "type":"Services"
        }
    ],
    "sg:phone":"+1 716 668 1144",
    "sg:postcode":"14227",
    "sg:province":"NY",
    "sg:tags":[
        "attorney"
    ],
    "wof:name":"Antonio Cardarelli",
    "wof:placetype":"venue"
},
  "geometry": {"coordinates":[-78.722708,42.87681],"type":"Point"}
}