{
  "type": "Feature",
  "properties": {
    "addr:full":"350 W 57 St New York NY 10019",
    "addr:housenumber":"350",
    "addr:postcode":"10019",
    "addr:street":"W 57 St",
    "iso:country":"US",
    "sg:address":"350 W 57 St",
    "sg:city":"New York",
    "sg:classifiers":[
        {
            "category":"Professional",
            "subcategory":"Business Services",
            "type":"Services"
        }
    ],
    "sg:phone":"+1 212 315 5266",
    "sg:postcode":"10019",
    "sg:province":"NY",
    "sg:tags":[
        "translator",
        "interpreter"
    ],
    "wof:name":"Language & Graphics",
    "wof:placetype":"venue"
},
  "geometry": {"coordinates":[-73.985716,40.767918],"type":"Point"}
}