{
  "type": "Feature",
  "properties": {
    "addr:full":"26 Welcher Ave Peekskill NY 10566",
    "addr:housenumber":"26",
    "addr:postcode":"10566",
    "addr:street":"Welcher Ave",
    "iso:country":"US",
    "sg:address":"26 Welcher Ave",
    "sg:city":"Peekskill",
    "sg:classifiers":[
        {
            "category":"Retail",
            "subcategory":"Self-service Laundry",
            "type":"Services"
        }
    ],
    "sg:phone":"+1 914 734 7468",
    "sg:postcode":"10566",
    "sg:province":"NY",
    "wof:name":"Peekskill Wash & Dry",
    "wof:placetype":"venue"
},
  "geometry": {"coordinates":[-73.934403,41.270517],"type":"Point"}
}