{
  "type": "Feature",
  "properties": {
    "addr:full":"955 Central Park Ave Scarsdale NY 10583",
    "addr:housenumber":"955",
    "addr:postcode":"10583",
    "addr:street":"Central Park Ave",
    "iso:country":"US",
    "sg:address":"955 Central Park Ave",
    "sg:city":"Scarsdale",
    "sg:classifiers":[
        {
            "category":"Home & Garden",
            "subcategory":"Home Furnishings",
            "type":"Retail Goods"
        }
    ],
    "sg:phone":"+1 914 725 1367",
    "sg:postcode":"10583",
    "sg:province":"NY",
    "sg:tags":[
        "linen"
    ],
    "wof:name":"Linens 'n Things",
    "wof:placetype":"venue"
},
  "geometry": {"coordinates":[-73.818777,40.995499],"type":"Point"}
}