{
  "type": "Feature",
  "properties": {
    "addr:full":"20 Greenwich Ave Melville NY 11747",
    "addr:housenumber":"20",
    "addr:postcode":"11747",
    "addr:street":"Greenwich Ave",
    "iso:country":"US",
    "sg:address":"20 Greenwich Ave",
    "sg:city":"Melville",
    "sg:classifiers":[
        {
            "category":"Real Estate",
            "subcategory":"Real Estate Operator",
            "type":"Services"
        }
    ],
    "sg:phone":"+1 631 427 8741",
    "sg:postcode":"11747",
    "sg:province":"NY",
    "sg:tags":[
        "property",
        "lessor"
    ],
    "wof:name":"Marie Difranco",
    "wof:placetype":"venue"
},
  "geometry": {"coordinates":[-73.40228999999999,40.810302],"type":"Point"}
}