{
  "type": "Feature",
  "properties": {
    "addr:full":"19 Farnham St Cazenovia NY 13035",
    "addr:housenumber":"19",
    "addr:postcode":"13035",
    "addr:street":"Farnham St",
    "iso:country":"US",
    "sg:address":"19 Farnham St",
    "sg:city":"Cazenovia",
    "sg:classifiers":[
        {
            "category":"Building & Trades",
            "subcategory":"Construction",
            "type":"Services"
        }
    ],
    "sg:phone":"+1 315 655 9579",
    "sg:postcode":"13035",
    "sg:province":"NY",
    "sg:tags":[
        "house"
    ],
    "wof:name":"Ralph Mietz Construction",
    "wof:placetype":"venue"
},
  "geometry": {"coordinates":[-75.85098499999999,42.930179],"type":"Point"}
}