{
  "type": "Feature",
  "properties": {
    "iso:country":"US",
    "sg:address":"59 S Lake Ave",
    "sg:city":"Bergen",
    "sg:classifiers":[
        {
            "category":"Real Estate",
            "subcategory":"Real Estate Agent",
            "type":"Services"
        }
    ],
    "sg:phone":"+1 585 494 1880",
    "sg:postcode":"14416",
    "sg:province":"NY",
    "sg:website":"www.harriswilcox.com",
    "wof:name":"Harris Wilcox Inc",
    "wof:placetype":"venue"
},
  "geometry": {"coordinates":[-77.94436899999999,43.078945],"type":"Point"}
}