{
  "type": "Feature",
  "properties": {
    "addr:full":"1300 Morris Park Ave Bronx NY 10461",
    "addr:housenumber":"1300",
    "addr:postcode":"10461",
    "addr:street":"Morris Park Ave",
    "iso:country":"US",
    "sg:address":"1300 Morris Park Ave",
    "sg:city":"Bronx",
    "sg:classifiers":[
        {
            "category":"Education",
            "subcategory":"College",
            "type":"Public Place"
        },
        {
            "category":"Health Services",
            "subcategory":"Doctor",
            "type":"Services"
        }
    ],
    "sg:phone":"+1 718 430 4031",
    "sg:postcode":"10461",
    "sg:province":"NY",
    "sg:tags":[
        "physician",
        "school",
        "surgeon"
    ],
    "wof:name":"Albert Einstein College-Med",
    "wof:placetype":"venue"
},
  "geometry": {"coordinates":[-73.843419,40.850887],"type":"Point"}
}