{
  "type": "Feature",
  "properties": {
    "addr:full":"62 E Broadway New York NY 10002",
    "addr:housenumber":"62",
    "addr:postcode":"10002",
    "addr:street":"E Broadway",
    "iso:country":"US",
    "sg:address":"62 E Broadway",
    "sg:city":"New York",
    "sg:classifiers":[
        {
            "category":"Professional",
            "subcategory":"Lawyer & Legal Services",
            "type":"Services"
        }
    ],
    "sg:phone":"+1 212 608 0988",
    "sg:postcode":"10002",
    "sg:province":"NY",
    "sg:tags":[
        "naturalization",
        "immigration"
    ],
    "wof:name":"Fudong Travel & Immigration",
    "wof:placetype":"venue"
},
  "geometry": {"coordinates":[-73.996201,40.713591],"type":"Point"}
}