{
  "type": "Feature",
  "properties": {
    "addr:full":"129 Lexington Ave Manhattan NY 10016",
    "addr:housenumber":"129",
    "addr:postcode":"10016",
    "addr:street":"Lexington Ave",
    "iso:country":"US",
    "sg:address":"129 Lexington Ave",
    "sg:city":"Manhattan",
    "sg:classifiers":[
        {
            "category":"Bars & Pubs",
            "type":"Food & Drink"
        }
    ],
    "sg:phone":"+1 212 686 3800",
    "sg:postcode":"10016",
    "sg:province":"NY",
    "sg:website":"www.whiskeyrebelnyc.com",
    "wof:name":"The Whiskey Rebel",
    "wof:placetype":"venue"
},
  "geometry": {"coordinates":[-73.981951,40.742899],"type":"Point"}
}