{
  "type": "Feature",
  "properties": {
    "addr:full":"1 Marian Ter Binghamton NY 13901",
    "addr:housenumber":"1",
    "addr:postcode":"13901",
    "addr:street":"Marian Ter",
    "iso:country":"US",
    "sg:address":"1 Marian Ter",
    "sg:city":"Binghamton",
    "sg:classifiers":[
        {
            "category":"Shopping",
            "subcategory":"Stationery & Office Supplies",
            "type":"Retail Goods"
        }
    ],
    "sg:phone":"+1   ",
    "sg:postcode":"13901",
    "sg:province":"NY",
    "wof:name":"Standard Register Company",
    "wof:placetype":"venue"
},
  "geometry": {"coordinates":[-75.85839199999999,42.198884],"type":"Point"}
}