{
  "type": "Feature",
  "properties": {
    "addr:full":"2517 S Salina St Syracuse NY 13205",
    "addr:housenumber":"2517",
    "addr:postcode":"13205",
    "addr:street":"S Salina St",
    "iso:country":"US",
    "sg:address":"2517 S Salina St",
    "sg:city":"Syracuse",
    "sg:classifiers":[
        {
            "category":"Organizations",
            "subcategory":"Religious Organization",
            "type":"Services"
        }
    ],
    "sg:phone":"+1   ",
    "sg:postcode":"13205",
    "sg:province":"NY",
    "sg:website":"www.syracuserpc.org",
    "wof:name":"Reformed Presbyterian Church",
    "wof:placetype":"venue"
},
  "geometry": {"coordinates":[-76.14373999999999,43.022281],"type":"Point"}
}