{
  "type": "Feature",
  "properties": {
    "addr:full":"250 W 34th St New York NY 10119",
    "addr:housenumber":"250",
    "addr:postcode":"10119",
    "addr:street":"W 34Th St",
    "iso:country":"US",
    "sg:address":"250 W 34th St",
    "sg:city":"New York",
    "sg:classifiers":[
        {
            "category":"Building & Trades",
            "subcategory":"Locksmith",
            "type":"Services"
        }
    ],
    "sg:phone":"+1 917 595 3932",
    "sg:postcode":"10119",
    "sg:province":"NY",
    "sg:tags":[
        "key"
    ],
    "wof:name":"Available Always",
    "wof:placetype":"venue"
},
  "geometry": {"coordinates":[-73.99212900000001,40.751475],"type":"Point"}
}