{
  "type": "Feature",
  "properties": {
    "addr:full":"455 Tompkins Ave Brooklyn NY 11216",
    "addr:housenumber":"455",
    "addr:postcode":"11216",
    "addr:street":"Tompkins Ave",
    "iso:country":"US",
    "sg:address":"455 Tompkins Ave",
    "sg:city":"Brooklyn",
    "sg:classifiers":[
        {
            "category":"Manufacturing",
            "subcategory":"Food",
            "type":"Manufacturing & Wholesale Goods"
        }
    ],
    "sg:phone":"+1 718 783 8331",
    "sg:postcode":"11216",
    "sg:province":"NY",
    "sg:tags":[
        "confectionery",
        "candy"
    ],
    "wof:name":"African Vender",
    "wof:placetype":"venue"
},
  "geometry": {"coordinates":[-73.943625,40.682446],"type":"Point"}
}