{
  "type": "Feature",
  "properties": {
    "addr:full":"113 Travers Blvd Buffalo NY 14228",
    "addr:housenumber":"113",
    "addr:postcode":"14228",
    "addr:street":"Travers Blvd",
    "iso:country":"US",
    "sg:address":"113 Travers Blvd",
    "sg:city":"Buffalo",
    "sg:classifiers":[
        {
            "category":"Real Estate",
            "subcategory":"Real Estate Operator",
            "type":"Services"
        }
    ],
    "sg:phone":"+1 716 691 5525",
    "sg:postcode":"14228",
    "sg:province":"NY",
    "sg:tags":[
        "building",
        "apartment"
    ],
    "wof:name":"Sutton Place Apartments",
    "wof:placetype":"venue"
},
  "geometry": {"coordinates":[-78.812956,43.039491],"type":"Point"}
}