{
  "type": "Feature",
  "properties": {
    "iso:country":"US",
    "sg:address":"4142 N Buffalo Rd",
    "sg:city":"Orchard Park",
    "sg:classifiers":[
        {
            "category":"Retail",
            "subcategory":"Auto Rental",
            "type":"Services"
        }
    ],
    "sg:phone":"+1 716 662 5900",
    "sg:postcode":"14127",
    "sg:province":"NY",
    "sg:tags":[
        "renting",
        "automobile"
    ],
    "wof:name":"MRS Auto Rental",
    "wof:placetype":"venue"
},
  "geometry": {"coordinates":[-78.74444699999999,42.769726],"type":"Point"}
}