{
  "type": "Feature",
  "properties": {
    "iso:country":"US",
    "sg:address":"598 Central Ave",
    "sg:city":"Cedarhurst",
    "sg:classifiers":[
        {
            "category":"Juice Bar",
            "subcategory":"None",
            "type":"Food & Drink"
        },
        {
            "category":"Bagels",
            "subcategory":"None",
            "type":"Food & Drink"
        }
    ],
    "sg:phone":"+1 516 374 7644",
    "sg:postcode":"11516",
    "sg:province":"NY",
    "sg:tags":[
        "smoothy"
    ],
    "sg:website":"www.KosherBagelDelight.com",
    "wof:name":"Bagel Delight - Kosher Bagels",
    "wof:placetype":"venue"
},
  "geometry": {"coordinates":[-73.72199999999999,40.622898],"type":"Point"}
}