{
  "type": "Feature",
  "properties": {
    "addr:full":"281 Greene Ave Brooklyn NY 11238",
    "addr:housenumber":"281",
    "addr:postcode":"11238",
    "addr:street":"Greene Ave",
    "iso:country":"US",
    "sg:address":"281 Greene Ave",
    "sg:city":"Brooklyn",
    "sg:classifiers":[
        {
            "category":"Education",
            "subcategory":"Dance Studio",
            "type":"Public Place"
        }
    ],
    "sg:phone":"+1 718 857 6007",
    "sg:postcode":"11238",
    "sg:province":"NY",
    "sg:tags":[
        "instruction",
        "dancing"
    ],
    "wof:name":"Wazoo Dance Machine",
    "wof:placetype":"venue"
},
  "geometry": {"coordinates":[-73.96150299999999,40.68722],"type":"Point"}
}