{
  "type": "Feature",
  "properties": {
    "iso:country":"US",
    "sg:address":"6411 Broadway",
    "sg:city":"Woodside",
    "sg:classifiers":[
        {
            "category":"Shopping",
            "subcategory":"Crafts & Fabrics",
            "type":"Retail Goods"
        }
    ],
    "sg:phone":"+1 718 458 8255",
    "sg:postcode":"11377",
    "sg:province":"NY",
    "sg:tags":[
        "art",
        "supply"
    ],
    "wof:name":"Olympia Crafting Inc",
    "wof:placetype":"venue"
},
  "geometry": {"coordinates":[-73.898172,40.749713],"type":"Point"}
}