{
  "type": "Feature",
  "properties": {
    "iso:country":"US",
    "sg:address":"187 Main St",
    "sg:city":"Altamont",
    "sg:classifiers":[
        {
            "category":"Restaurant",
            "type":"Food & Drink"
        }
    ],
    "sg:phone":"+1 518 861 8611",
    "sg:postcode":"12009",
    "sg:province":"NY",
    "wof:name":"Bamboo Garden",
    "wof:placetype":"venue"
},
  "geometry": {"coordinates":[-74.03331799999999,42.70108],"type":"Point"}
}