{
  "type": "Feature",
  "properties": {
    "iso:country":"US",
    "sg:address":"7369 Wheeler Rd",
    "sg:city":"Lockport",
    "sg:classifiers":[
        {
            "category":"Travel",
            "subcategory":"Campground",
            "type":"Entertainment"
        }
    ],
    "sg:phone":"+1 716 434 3991",
    "sg:postcode":"14094",
    "sg:province":"NY",
    "sg:tags":[
        "trailer"
    ],
    "sg:website":"www.niagaracamping.com",
    "wof:name":"Niagara County Camping Resort",
    "wof:placetype":"venue"
},
  "geometry": {"coordinates":[-78.63656,43.225355],"type":"Point"}
}