{
  "type": "Feature",
  "properties": {
    "iso:country":"US",
    "sg:address":"1700 Grand Concourse",
    "sg:city":"Bronx",
    "sg:classifiers":[
        {
            "category":"Health Services",
            "subcategory":"Doctor",
            "type":"Services"
        }
    ],
    "sg:phone":"+1 718 294 7862",
    "sg:postcode":"10457",
    "sg:province":"NY",
    "sg:tags":[
        "medical"
    ],
    "wof:name":"Bronx Cardiac Center",
    "wof:placetype":"venue"
},
  "geometry": {"coordinates":[-73.908632,40.846965],"type":"Point"}
}