{
  "type": "Feature",
  "properties": {
    "addr:full":"2522 Broadway New York NY 10025",
    "addr:housenumber":"2522",
    "addr:postcode":"10025",
    "addr:street":"Broadway",
    "iso:country":"US",
    "sg:address":"2522 Broadway",
    "sg:city":"New York",
    "sg:classifiers":[
        {
            "category":"Retail",
            "subcategory":"Photofinishing",
            "type":"Services"
        }
    ],
    "sg:phone":"+1 212 799 3172",
    "sg:postcode":"10025",
    "sg:province":"NY",
    "sg:tags":[
        "photo",
        "finishing"
    ],
    "sg:website":"www.duanereade.com",
    "wof:name":"Duane Reade",
    "wof:placetype":"venue"
},
  "geometry": {"coordinates":[-73.972251,40.793881],"type":"Point"}
}