{
  "type": "Feature",
  "properties": {
    "addr:full":"330 7th Ave Brooklyn NY 11215",
    "addr:housenumber":"330",
    "addr:postcode":"11215",
    "addr:street":"7Th Ave",
    "iso:country":"US",
    "sg:address":"330 7th Ave",
    "sg:city":"Brooklyn",
    "sg:classifiers":[
        {
            "category":"Health Services",
            "subcategory":"Optometrist",
            "type":"Services"
        },
        {
            "category":"Shopping",
            "subcategory":"Optician",
            "type":"Retail Goods"
        }
    ],
    "sg:phone":"+1 718 832 3513",
    "sg:postcode":"11215",
    "sg:province":"NY",
    "sg:tags":[
        "eyewear"
    ],
    "wof:name":"Urban Vision",
    "wof:placetype":"venue"
},
  "geometry": {"coordinates":[-73.98159800000001,40.667099],"type":"Point"}
}