{
  "type": "Feature",
  "properties": {
    "addr:full":"350 1 Ave New York NY 10010",
    "addr:housenumber":"350",
    "addr:postcode":"10010",
    "addr:street":"1 Ave",
    "iso:country":"US",
    "sg:address":"350 1 Ave",
    "sg:city":"New York",
    "sg:classifiers":[
        {
            "category":"Health Services",
            "subcategory":"Doctor",
            "type":"Services"
        }
    ],
    "sg:phone":"+1 212 420 4344",
    "sg:postcode":"10010",
    "sg:province":"NY",
    "sg:tags":[
        "medical",
        "hospital",
        "general"
    ],
    "wof:name":"Surgery",
    "wof:placetype":"venue"
},
  "geometry": {"coordinates":[-73.979557,40.735417],"type":"Point"}
}