{
  "type": "Feature",
  "properties": {
    "addr:full":"160 Allens Creek Rd Rochester NY 14618",
    "addr:housenumber":"160",
    "addr:postcode":"14618",
    "addr:street":"Allens Creek Rd",
    "iso:country":"US",
    "sg:address":"160 Allens Creek Rd",
    "sg:city":"Rochester",
    "sg:classifiers":[
        {
            "category":"Social Services",
            "type":"Services"
        }
    ],
    "sg:phone":"+1   ",
    "sg:postcode":"14618",
    "sg:province":"NY",
    "wof:name":"Iker Chas Csw",
    "wof:placetype":"venue"
},
  "geometry": {"coordinates":[-77.548457,43.116752],"type":"Point"}
}