{
  "type": "Feature",
  "properties": {
    "addr:full":"138 Wheeler Rd Central Islip NY 11722",
    "addr:housenumber":"138",
    "addr:postcode":"11722",
    "addr:street":"Wheeler Rd",
    "iso:country":"US",
    "sg:address":"138 Wheeler Rd",
    "sg:city":"Central Islip",
    "sg:classifiers":[
        {
            "category":"Retail",
            "subcategory":"Self-service Laundry",
            "type":"Services"
        }
    ],
    "sg:phone":"+1 631 232 0708",
    "sg:postcode":"11722",
    "sg:province":"NY",
    "wof:name":"Dirt Busters Laundry Inc",
    "wof:placetype":"venue"
},
  "geometry": {"coordinates":[-73.21272,40.802893],"type":"Point"}
}