{
  "type": "Feature",
  "properties": {
    "addr:full":"104 Mohawk Ave Schenectady NY 12302",
    "addr:housenumber":"104",
    "addr:postcode":"12302",
    "addr:street":"Mohawk Ave",
    "iso:country":"US",
    "sg:address":"104 Mohawk Ave",
    "sg:city":"Schenectady",
    "sg:classifiers":[
        {
            "category":"Shopping",
            "subcategory":"Musical Instruments",
            "type":"Retail Goods"
        },
        {
            "category":"Manufacturing",
            "subcategory":"Musical Instruments",
            "type":"Manufacturing & Wholesale Goods"
        }
    ],
    "sg:phone":"+1 518 388 8488",
    "sg:postcode":"12302",
    "sg:province":"NY",
    "sg:tags":[
        "guitar",
        "instruments-rental",
        "amplifier"
    ],
    "wof:name":"The Rhythm Section",
    "wof:placetype":"venue"
},
  "geometry": {"coordinates":[-73.961911,42.825322],"type":"Point"}
}