{
  "type": "Feature",
  "properties": {
    "addr:full":"174 Church St Arkville NY 12414",
    "addr:housenumber":"174",
    "addr:postcode":"12414",
    "addr:street":"Church St",
    "iso:country":"US",
    "sg:address":"174 Church St",
    "sg:city":"Arkville",
    "sg:classifiers":[
        {
            "category":"Building & Trades",
            "subcategory":"Construction",
            "type":"Services"
        }
    ],
    "sg:phone":"+1 845 586 1382",
    "sg:postcode":"12414",
    "sg:province":"NY",
    "sg:tags":[
        "excavating",
        "contractor"
    ],
    "wof:name":"Jeremy Owen Excavating",
    "wof:placetype":"venue"
},
  "geometry": {"coordinates":[-73.86705600000001,42.2203],"type":"Point"}
}