{
  "type": "Feature",
  "properties": {
    "addr:full":"2816 201st St Bayside NY 11360",
    "addr:housenumber":"2816",
    "addr:postcode":"11360",
    "addr:street":"201St St",
    "iso:country":"US",
    "sg:address":"2816 201st St",
    "sg:city":"Bayside",
    "sg:classifiers":[
        {
            "category":"Transit Center",
            "subcategory":"Freight",
            "type":"Transportation"
        },
        {
            "category":"Freight",
            "type":"Transportation"
        }
    ],
    "sg:phone":"+1 718 352 5353",
    "sg:postcode":"11360",
    "sg:province":"NY",
    "sg:tags":[
        "local",
        "trucking-motor",
        "trucking"
    ],
    "wof:name":"M&G Express Inc",
    "wof:placetype":"venue"
},
  "geometry": {"coordinates":[-73.793217,40.78632],"type":"Point"}
}