{
  "type": "Feature",
  "properties": {
    "addr:full":"33 Seneca St Geneva NY 14456",
    "addr:housenumber":"33",
    "addr:postcode":"14456",
    "addr:street":"Seneca St",
    "iso:country":"US",
    "sg:address":"33 Seneca St",
    "sg:city":"Geneva",
    "sg:classifiers":[
        {
            "category":"Social Services",
            "type":"Services"
        }
    ],
    "sg:phone":"+1   ",
    "sg:postcode":"14456",
    "sg:province":"NY",
    "wof:name":"Darlene Trytek",
    "wof:placetype":"venue"
},
  "geometry": {"coordinates":[-76.982676,42.866606],"type":"Point"}
}