{
  "type": "Feature",
  "properties": {
    "addr:full":"15 Bank St Staten Island NY 10301",
    "addr:housenumber":"15",
    "addr:postcode":"10301",
    "addr:street":"Bank St",
    "iso:country":"US",
    "sg:address":"15 Bank St",
    "sg:city":"Staten Island",
    "sg:classifiers":[
        {
            "category":"Wholesale",
            "subcategory":"Computers",
            "type":"Manufacturing & Wholesale Goods"
        }
    ],
    "sg:phone":"+1 718 556 1200",
    "sg:postcode":"10301",
    "sg:province":"NY",
    "sg:tags":[
        "printer",
        "laser"
    ],
    "wof:name":"Business Letters Inc",
    "wof:placetype":"venue"
},
  "geometry": {"coordinates":[-74.08918300000001,40.647188],"type":"Point"}
}