{
  "type": "Feature",
  "properties": {
    "iso:country":"US",
    "sg:address":"3283 Broadway Rd",
    "sg:city":"Alexander",
    "sg:classifiers":[
        {
            "category":"Government",
            "subcategory":"Fire Station",
            "type":"Public Place"
        }
    ],
    "sg:phone":"+1 585 591 2411",
    "sg:postcode":"14005",
    "sg:province":"NY",
    "sg:tags":[
        "protection"
    ],
    "wof:name":"Alexander Fire Department",
    "wof:placetype":"venue"
},
  "geometry": {"coordinates":[-78.258967,42.904985],"type":"Point"}
}