{
  "type": "Feature",
  "properties": {
    "addr:full":"12 Milner Ave Albany NY 12203",
    "addr:housenumber":"12",
    "addr:postcode":"12203",
    "addr:street":"Milner Ave",
    "iso:country":"US",
    "sg:address":"12 Milner Ave",
    "sg:city":"Albany",
    "sg:classifiers":[
        {
            "category":"Recreation",
            "type":"Entertainment"
        }
    ],
    "sg:phone":"+1 518 459 6320",
    "sg:postcode":"12203",
    "sg:province":"NY",
    "sg:tags":[
        "club",
        "membership"
    ],
    "wof:name":"Westland Hills Inc",
    "wof:placetype":"venue"
},
  "geometry": {"coordinates":[-73.80735799999999,42.667772],"type":"Point"}
}