{
  "type": "Feature",
  "properties": {
    "iso:country":"US",
    "sg:address":"606 New Hempstead Rd",
    "sg:city":"Spring Valley",
    "sg:classifiers":[
        {
            "category":"Building & Trades",
            "subcategory":"Landscaping Services",
            "type":"Services"
        }
    ],
    "sg:phone":"+1 845 362 0719",
    "sg:postcode":"10977",
    "sg:province":"NY",
    "sg:tags":[
        "landscape",
        "contractor"
    ],
    "wof:name":"Earthworks Landscape Constr",
    "wof:placetype":"venue"
},
  "geometry": {"coordinates":[-74.04194699999999,41.15022],"type":"Point"}
}