{
  "type": "Feature",
  "properties": {
    "iso:country":"US",
    "sg:address":"334 Oxhead Rd",
    "sg:city":"Stony Brook",
    "sg:classifiers":[
        {
            "category":"Wholesale",
            "subcategory":"Medical Equipment & Supplies",
            "type":"Manufacturing & Wholesale Goods"
        },
        {
            "category":"Retail",
            "subcategory":"Repair Shop",
            "type":"Services"
        }
    ],
    "sg:phone":"+1 631 689 6587",
    "sg:postcode":"11790",
    "sg:province":"NY",
    "sg:tags":[
        "x",
        "apparatus"
    ],
    "wof:name":"J C Medical Equipment Co Inc",
    "wof:placetype":"venue"
},
  "geometry": {"coordinates":[-73.111974,40.890533],"type":"Point"}
}