{
  "type": "Feature",
  "properties": {
    "iso:country":"US",
    "sg:address":"6 John Calvin Dr",
    "sg:city":"Blauvelt",
    "sg:classifiers":[
        {
            "category":"Arts & Performance",
            "subcategory":"Theater",
            "type":"Entertainment"
        }
    ],
    "sg:phone":"+1 845 359 4640",
    "sg:postcode":"10913",
    "sg:province":"NY",
    "sg:tags":[
        "group"
    ],
    "wof:name":"New Jersey Colonial",
    "wof:placetype":"venue"
},
  "geometry": {"coordinates":[-73.96161600000001,41.077525],"type":"Point"}
}