{
  "type": "Feature",
  "properties": {
    "addr:full":"2 Nassau Rd Great Neck NY 11021",
    "addr:housenumber":"2",
    "addr:postcode":"11021",
    "addr:street":"Nassau Rd",
    "iso:country":"US",
    "sg:address":"2 Nassau Rd",
    "sg:city":"Great Neck",
    "sg:classifiers":[
        {
            "category":"Wholesale",
            "subcategory":"Medical Equipment & Supplies",
            "type":"Manufacturing & Wholesale Goods"
        }
    ],
    "sg:phone":"+1 516 428 3242",
    "sg:postcode":"11021",
    "sg:province":"NY",
    "sg:tags":[
        "physician",
        "surgeon"
    ],
    "wof:name":"Integrated Health Enterprises",
    "wof:placetype":"venue"
},
  "geometry": {"coordinates":[-73.736665,40.77459],"type":"Point"}
}