{
  "type": "Feature",
  "properties": {
    "iso:country":"US",
    "sg:address":"210 W 89 St",
    "sg:city":"New York",
    "sg:classifiers":[
        {
            "category":"Professional",
            "type":"Services"
        }
    ],
    "sg:phone":"+1 212 787 1195",
    "sg:postcode":"10024",
    "sg:province":"NY",
    "sg:tags":[
        "establishment"
    ],
    "wof:name":"Coagulation Sciences LLC",
    "wof:placetype":"venue"
},
  "geometry": {"coordinates":[-73.974839,40.790023],"type":"Point"}
}