{
  "type": "Feature",
  "properties": {
    "iso:country":"US",
    "sg:address":"20 Hawley St Ste 100E",
    "sg:city":"Binghamton",
    "sg:phone":"+1 607 723 7058",
    "sg:postcode":"13901",
    "sg:province":"NY",
    "wof:name":"Eastern Temporaries",
    "wof:placetype":"venue"
},
  "geometry": {"coordinates":[-75.913696,42.09724],"type":"Point"}
}