{
  "type": "Feature",
  "properties": {
    "iso:country":"US",
    "sg:address":"2823 Girts Rd",
    "sg:city":"Jamestown",
    "sg:classifiers":[
        {
            "category":"Manufacturing",
            "subcategory":"Chemicals & Compounds",
            "type":"Manufacturing & Wholesale Goods"
        }
    ],
    "sg:phone":"+1   ",
    "sg:postcode":"14701",
    "sg:province":"NY",
    "sg:tags":[
        "distribution",
        "kit",
        "medical",
        "for",
        "diagnostics"
    ],
    "wof:name":"Trinity Biotech Distribution",
    "wof:placetype":"venue"
},
  "geometry": {"coordinates":[-79.249769,42.150335],"type":"Point"}
}