{
  "type": "Feature",
  "properties": {
    "iso:country":"US",
    "sg:address":"19 Meadow Glen Rd",
    "sg:city":"Kings Park",
    "sg:classifiers":[
        {
            "category":"Building & Trades",
            "subcategory":"Plumbing",
            "type":"Services"
        }
    ],
    "sg:phone":"+1 631 544 6244",
    "sg:postcode":"11754",
    "sg:province":"NY",
    "wof:name":"Hubbard Plumbing",
    "wof:placetype":"venue"
},
  "geometry": {"coordinates":[-73.28130299999999,40.884399],"type":"Point"}
}