{
  "type": "Feature",
  "properties": {
    "iso:country":"US",
    "sg:address":"100 Broad Hollow Rd",
    "sg:city":"Farmingdale",
    "sg:classifiers":[
        {
            "category":"Banks & Credit Unions",
            "subcategory":"Bank",
            "type":"Services"
        }
    ],
    "sg:phone":"+1 631 753 2655",
    "sg:postcode":"11735",
    "sg:province":"NY",
    "sg:tags":[
        "broker",
        "mortgage"
    ],
    "sg:website":"www.edenmortgage.com",
    "wof:name":"Eden Mortgage Corp",
    "wof:placetype":"venue"
},
  "geometry": {"coordinates":[-73.427324,40.715019],"type":"Point"}
}