{
  "type": "Feature",
  "properties": {
    "addr:full":"4502 14th Ave Brooklyn NY 11219",
    "addr:housenumber":"4502",
    "addr:postcode":"11219",
    "addr:street":"14Th Ave",
    "iso:country":"US",
    "sg:address":"4502 14th Ave",
    "sg:city":"Brooklyn",
    "sg:classifiers":[
        {
            "category":"Organizations",
            "subcategory":"Religious Organization",
            "type":"Services"
        }
    ],
    "sg:phone":"+1   ",
    "sg:postcode":"11219",
    "sg:province":"NY",
    "sg:tags":[
        "synagogue"
    ],
    "wof:name":"First Congregation Anshe Sfard",
    "wof:placetype":"venue"
},
  "geometry": {"coordinates":[-73.98821599999999,40.635432],"type":"Point"}
}