{
  "type": "Feature",
  "properties": {
    "iso:country":"US",
    "sg:address":"953 Ogden Ave",
    "sg:city":"Bronx",
    "sg:classifiers":[
        {
            "category":"Retail",
            "subcategory":"Repair Shop",
            "type":"Services"
        }
    ],
    "sg:phone":"+1 718 414 2144",
    "sg:postcode":"10452",
    "sg:province":"NY",
    "sg:tags":[
        "lock",
        "locksmith"
    ],
    "wof:name":"USA Locksmiths",
    "wof:placetype":"venue"
},
  "geometry": {"coordinates":[-73.929903,40.832099],"type":"Point"}
}