{
  "type": "Feature",
  "properties": {
    "addr:full":"42 Broadway New York NY 10004",
    "addr:housenumber":"42",
    "addr:postcode":"10004",
    "addr:street":"Broadway",
    "iso:country":"US",
    "sg:address":"42 Broadway",
    "sg:city":"New York",
    "sg:classifiers":[
        {
            "category":"Marine",
            "type":"Transportation"
        }
    ],
    "sg:phone":"+1   ",
    "sg:postcode":"10004",
    "sg:province":"NY",
    "sg:tags":[
        "ship",
        "registry"
    ],
    "wof:name":"Vanuatu Maritime Services Ltd",
    "wof:placetype":"venue"
},
  "geometry": {"coordinates":[-74.01284800000001,40.706086],"type":"Point"}
}