{
  "type": "Feature",
  "properties": {
    "iso:country":"US",
    "sg:address":"165 Mamaroneck Ave",
    "sg:city":"White Plains",
    "sg:classifiers":[
        {
            "category":"Shopping",
            "subcategory":"Clothing, Apparel, & Fashions",
            "type":"Retail Goods"
        }
    ],
    "sg:phone":"+1   ",
    "sg:postcode":"10601",
    "sg:province":"NY",
    "sg:tags":[
        "gown",
        "bridal",
        "dress",
        "shoes",
        "cocktail"
    ],
    "wof:name":"Follia Bridal Boutique",
    "wof:placetype":"venue"
},
  "geometry": {"coordinates":[-73.764647,41.027928],"type":"Point"}
}