{
  "type": "Feature",
  "properties": {
    "iso:country":"US",
    "sg:address":"2202 W Old State Rd",
    "sg:city":"Altamont",
    "sg:classifiers":[
        {
            "category":"Building & Trades",
            "subcategory":"Construction",
            "type":"Services"
        }
    ],
    "sg:phone":"+1 518 356 3612",
    "sg:postcode":"12009",
    "sg:province":"NY",
    "sg:tags":[
        "general",
        "contractor"
    ],
    "wof:name":"O'Connell Construction Corp",
    "wof:placetype":"venue"
},
  "geometry": {"coordinates":[-73.99304600000001,42.74553],"type":"Point"}
}