{
  "type": "Feature",
  "properties": {
    "addr:full":"495 South Ave Rochester NY 14620",
    "addr:housenumber":"495",
    "addr:postcode":"14620",
    "addr:street":"South Ave",
    "iso:country":"US",
    "sg:address":"495 South Ave",
    "sg:city":"Rochester",
    "sg:classifiers":[
        {
            "category":"Food & Beverages",
            "subcategory":"Groceries & Convenience Stores",
            "type":"Retail Goods"
        }
    ],
    "sg:phone":"+1 585 232 7980",
    "sg:postcode":"14620",
    "sg:province":"NY",
    "sg:tags":[
        "grocer"
    ],
    "wof:name":"Daily Grocery",
    "wof:placetype":"venue"
},
  "geometry": {"coordinates":[-77.605768,43.147123],"type":"Point"}
}