{
  "type": "Feature",
  "properties": {
    "iso:country":"US",
    "sg:address":"130 7th Ave South",
    "sg:city":"New York",
    "sg:classifiers":[
        {
            "category":"Bars & Pubs",
            "type":"Food & Drink"
        }
    ],
    "sg:postcode":"10014",
    "sg:province":"NY",
    "sg:tags":[
        "tapa"
    ],
    "wof:name":"Tierra",
    "wof:placetype":"venue"
},
  "geometry": {"coordinates":[-74.002392,40.734384],"type":"Point"}
}