{
  "type": "Feature",
  "properties": {
    "iso:country":"US",
    "sg:address":"303 E 91 St",
    "sg:city":"New York",
    "sg:classifiers":[
        {
            "category":"Health Services",
            "subcategory":"Clinic",
            "type":"Services"
        }
    ],
    "sg:phone":"+1 212 410 6258",
    "sg:postcode":"10128",
    "sg:province":"NY",
    "sg:tags":[
        "holistic",
        "practitioner"
    ],
    "wof:name":"Beautiful Morning",
    "wof:placetype":"venue"
},
  "geometry": {"coordinates":[-73.94704900000001,40.780149],"type":"Point"}
}