{
  "type": "Feature",
  "properties": {
    "addr:full":"114 The Village Grn Buffalo NY 14221",
    "addr:housenumber":"114",
    "addr:postcode":"14221",
    "addr:street":"The Village Grn",
    "iso:country":"US",
    "sg:address":"114 The Village Grn",
    "sg:city":"Buffalo",
    "sg:classifiers":[
        {
            "category":"Professional",
            "subcategory":"Management & Consulting",
            "type":"Services"
        }
    ],
    "sg:phone":"+1 716 632 8070",
    "sg:postcode":"14221",
    "sg:province":"NY",
    "sg:tags":[
        "counselor",
        "public",
        "relations"
    ],
    "wof:name":"Reszka & Associates",
    "wof:placetype":"venue"
},
  "geometry": {"coordinates":[-78.74887699999999,42.983306],"type":"Point"}
}