{
  "type": "Feature",
  "properties": {
    "addr:full":"SW corner of 14th St & 8th Ave New York NY 10079",
    "addr:postcode":"10079",
    "addr:street":"Sw;14Th St & 8Th Ave",
    "iso:country":"US",
    "sg:address":"SW corner of 14th St & 8th Ave",
    "sg:city":"New York",
    "sg:classifiers":[
        {
            "category":"Coffee & Tea",
            "type":"Food & Drink"
        }
    ],
    "sg:postcode":"10079",
    "sg:province":"NY",
    "wof:name":"Coffee Cart on 14th St and 8th Ave",
    "wof:placetype":"venue"
},
  "geometry": {"coordinates":[-74.00252,40.73974],"type":"Point"}
}