{
  "type": "Feature",
  "properties": {
    "addr:full":"349 Walnut St Yonkers NY 10701",
    "addr:housenumber":"349",
    "addr:postcode":"10701",
    "addr:street":"Walnut St",
    "iso:country":"US",
    "sg:address":"349 Walnut St",
    "sg:city":"Yonkers",
    "sg:classifiers":[
        {
            "category":"Home & Garden",
            "subcategory":"Building Materials",
            "type":"Retail Goods"
        }
    ],
    "sg:phone":"+1 914 963 4796",
    "sg:postcode":"10701",
    "sg:province":"NY",
    "sg:tags":[
        "contractor",
        "painting",
        "hanging"
    ],
    "wof:name":"Nyahay Paint & Wallpaper",
    "wof:placetype":"venue"
},
  "geometry": {"coordinates":[-73.886972,40.933754],"type":"Point"}
}