{
  "type": "Feature",
  "properties": {
    "iso:country":"US",
    "sg:address":"80 Greenwood Ln",
    "sg:city":"White Plains",
    "sg:classifiers":[
        {
            "category":"Professional",
            "subcategory":"Art Services",
            "type":"Services"
        }
    ],
    "sg:phone":"+1 914 391 9222",
    "sg:postcode":"10607",
    "sg:province":"NY",
    "sg:tags":[
        "graphic",
        "designer"
    ],
    "wof:name":"Westchester Design Group Inc",
    "wof:placetype":"venue"
},
  "geometry": {"coordinates":[-73.818456,41.043146],"type":"Point"}
}