{
  "type": "Feature",
  "properties": {
    "iso:country":"US",
    "sg:address":"2196 4th St",
    "sg:city":"East Meadow",
    "sg:classifiers":[
        {
            "category":"Manufacturing",
            "subcategory":"Printing",
            "type":"Manufacturing & Wholesale Goods"
        }
    ],
    "sg:phone":"+1   ",
    "sg:postcode":"11554",
    "sg:province":"NY",
    "sg:tags":[
        "publishing"
    ],
    "wof:name":"Research Press Inc",
    "wof:placetype":"venue"
},
  "geometry": {"coordinates":[-73.555733,40.722724],"type":"Point"}
}