{
  "type": "Feature",
  "properties": {
    "addr:full":"1407 60th St Brooklyn NY 11219",
    "addr:housenumber":"1407",
    "addr:postcode":"11219",
    "addr:street":"60Th St",
    "iso:country":"US",
    "sg:address":"1407 60th St",
    "sg:city":"Brooklyn",
    "sg:classifiers":[
        {
            "category":"Building & Trades",
            "subcategory":"Construction",
            "type":"Services"
        }
    ],
    "sg:phone":"+1 718 851 3222",
    "sg:postcode":"11219",
    "sg:province":"NY",
    "sg:tags":[
        "general",
        "contractor"
    ],
    "wof:name":"Shir Development Corp",
    "wof:placetype":"venue"
},
  "geometry": {"coordinates":[-73.994202,40.626323],"type":"Point"}
}