{
  "type": "Feature",
  "properties": {
    "iso:country":"US",
    "sg:address":"157 Johnsontown Rd",
    "sg:city":"Sloatsburg",
    "sg:classifiers":[
        {
            "category":"Building & Trades",
            "subcategory":"Electrical",
            "type":"Services"
        }
    ],
    "sg:phone":"+1 845 753 2844",
    "sg:postcode":"10974",
    "sg:province":"NY",
    "sg:tags":[
        "electrical",
        "electric",
        "contractor"
    ],
    "wof:name":"Roland Zimmerman Elec Cntrctrs",
    "wof:placetype":"venue"
},
  "geometry": {"coordinates":[-74.18383900000001,41.164041],"type":"Point"}
}