{
  "type": "Feature",
  "properties": {
    "iso:country":"US",
    "sg:address":"7242 Oswego Rd",
    "sg:city":"Liverpool",
    "sg:classifiers":[
        {
            "category":"Health Services",
            "subcategory":"Dentist",
            "type":"Services"
        }
    ],
    "sg:phone":"+1 315 451 7151",
    "sg:postcode":"13090",
    "sg:province":"NY",
    "sg:tags":[
        "implant",
        "dentistry",
        "dentists-periodontists",
        "dentists-implantology"
    ],
    "sg:website":"http://www.oralhealthny.com",
    "wof:name":"Albert John G DMD",
    "wof:placetype":"venue"
},
  "geometry": {"coordinates":[-76.215012,43.11972],"type":"Point"}
}