{
  "type": "Feature",
  "properties": {
    "iso:country":"US",
    "sg:address":"1920 Park St",
    "sg:city":"Syracuse",
    "sg:classifiers":[
        {
            "category":"Personal",
            "subcategory":"Beauty Salon",
            "type":"Services"
        }
    ],
    "sg:phone":"+1   ",
    "sg:postcode":"13208",
    "sg:province":"NY",
    "sg:tags":[
        "shop"
    ],
    "wof:name":"Ken & Nikki Nails",
    "wof:placetype":"venue"
},
  "geometry": {"coordinates":[-76.16437999999999,43.070996],"type":"Point"}
}