{
  "type": "Feature",
  "properties": {
    "addr:full":"35 W 31st St New York NY 10001",
    "addr:housenumber":"35",
    "addr:postcode":"10001",
    "addr:street":"W 31St St",
    "iso:country":"US",
    "sg:address":"35 W 31st St",
    "sg:city":"New York",
    "sg:classifiers":[
        {
            "category":"Food & Beverages",
            "subcategory":"Groceries & Convenience Stores",
            "type":"Retail Goods"
        }
    ],
    "sg:phone":"+1 212 594 2371",
    "sg:postcode":"10001",
    "sg:province":"NY",
    "sg:website":"www.westernunion.com",
    "wof:name":"Siri Convenience Store",
    "wof:placetype":"venue"
},
  "geometry": {"coordinates":[-73.987537,40.747378],"type":"Point"}
}