{
  "type": "Feature",
  "properties": {
    "iso:country":"US",
    "sg:address":"450 Newton St",
    "sg:city":"Westbury",
    "sg:classifiers":[
        {
            "category":"Professional",
            "type":"Services"
        }
    ],
    "sg:phone":"+1 516 997 6264",
    "sg:postcode":"11590",
    "sg:province":"NY",
    "sg:tags":[
        "establishment"
    ],
    "wof:name":"Sound Take Corp",
    "wof:placetype":"venue"
},
  "geometry": {"coordinates":[-73.585342,40.758887],"type":"Point"}
}