{
  "type": "Feature",
  "properties": {
    "iso:country":"US",
    "sg:address":"178 Main St",
    "sg:city":"Beacon",
    "sg:classifiers":[
        {
            "category":"Shopping",
            "subcategory":"Bicycles & Sporting Goods",
            "type":"Retail Goods"
        },
        {
            "category":"Sports & Exercise",
            "subcategory":"Bicycle Rental",
            "type":"Entertainment"
        }
    ],
    "sg:phone":"+1 845 765 0366",
    "sg:postcode":"12508",
    "sg:province":"NY",
    "sg:tags":[
        "bike"
    ],
    "sg:website":"www.beaconbikeshop.com",
    "wof:name":"Beacon Cycles",
    "wof:placetype":"venue"
},
  "geometry": {"coordinates":[-73.975103,41.507979],"type":"Point"}
}