{
  "type": "Feature",
  "properties": {
    "addr:full":"77 Sheather Rd Mount Kisco NY 10549",
    "addr:housenumber":"77",
    "addr:postcode":"10549",
    "addr:street":"Sheather Rd",
    "iso:country":"US",
    "sg:address":"77 Sheather Rd",
    "sg:city":"Mount Kisco",
    "sg:classifiers":[
        {
            "category":"Building & Trades",
            "subcategory":"Landscaping Services",
            "type":"Services"
        }
    ],
    "sg:phone":"+1 914 666 7028",
    "sg:postcode":"10549",
    "sg:province":"NY",
    "wof:name":"Luppino Ldscpg & Masnry LLC",
    "wof:placetype":"venue"
},
  "geometry": {"coordinates":[-73.719301,41.155927],"type":"Point"}
}