{
  "type": "Feature",
  "properties": {
    "iso:country":"US",
    "sg:address":"240 Maple St",
    "sg:city":"Islip",
    "sg:classifiers":[
        {
            "category":"Building & Trades",
            "subcategory":"Construction",
            "type":"Services"
        }
    ],
    "sg:phone":"+1 631 859 0899",
    "sg:postcode":"11751",
    "sg:province":"NY",
    "sg:tags":[
        "general",
        "contractor"
    ],
    "wof:name":"Renovator Construction",
    "wof:placetype":"venue"
},
  "geometry": {"coordinates":[-73.21186299999999,40.721352],"type":"Point"}
}