{
  "type": "Feature",
  "properties": {
    "iso:country":"US",
    "sg:address":"10 Rockefeller Plz Ste 620",
    "sg:city":"New York",
    "sg:classifiers":[
        {
            "category":"Education",
            "subcategory":"University",
            "type":"Public Place"
        }
    ],
    "sg:phone":"+1 212 218 7929",
    "sg:postcode":"10020",
    "sg:province":"NY",
    "sg:tags":[
        "college"
    ],
    "wof:name":"University of Chicago",
    "wof:placetype":"venue"
},
  "geometry": {"coordinates":[-73.979202,40.757999],"type":"Point"}
}