{
  "type": "Feature",
  "properties": {
    "addr:full":"92 Orange Ave Suffern NY 10901",
    "addr:housenumber":"92",
    "addr:postcode":"10901",
    "addr:street":"Orange Ave",
    "iso:country":"US",
    "sg:address":"92 Orange Ave",
    "sg:city":"Suffern",
    "sg:classifiers":[
        {
            "category":"Real Estate",
            "subcategory":"Real Estate Agent",
            "type":"Services"
        }
    ],
    "sg:phone":"+1 845 369 9210",
    "sg:postcode":"10901",
    "sg:province":"NY",
    "sg:tags":[
        "management"
    ],
    "wof:name":"Kiplou Realty Inc",
    "wof:placetype":"venue"
},
  "geometry": {"coordinates":[-74.154636,41.116734],"type":"Point"}
}