{
  "type": "Feature",
  "properties": {
    "iso:country":"US",
    "sg:address":"50 Virginia Rd",
    "sg:city":"White Plains",
    "sg:classifiers":[
        {
            "category":"Wholesale",
            "subcategory":"Office Equipment",
            "type":"Manufacturing & Wholesale Goods"
        }
    ],
    "sg:phone":"+1 914 949 8192",
    "sg:postcode":"10603",
    "sg:province":"NY",
    "sg:tags":[
        "machine",
        "mailing"
    ],
    "wof:name":"Carrington Co",
    "wof:placetype":"venue"
},
  "geometry": {"coordinates":[-73.774782,41.062794],"type":"Point"}
}