{
  "type": "Feature",
  "properties": {
    "addr:full":"4023 15th Ave Brooklyn NY 11218",
    "addr:housenumber":"4023",
    "addr:postcode":"11218",
    "addr:street":"15Th Ave",
    "iso:country":"US",
    "sg:address":"4023 15th Ave",
    "sg:city":"Brooklyn",
    "sg:classifiers":[
        {
            "category":"Professional",
            "subcategory":"Business Services",
            "type":"Services"
        }
    ],
    "sg:phone":"+1 718 854 4700",
    "sg:postcode":"11218",
    "sg:province":"NY",
    "sg:tags":[
        "messenger"
    ],
    "wof:name":"Munkacs Car Svc LTD",
    "wof:placetype":"venue"
},
  "geometry": {"coordinates":[-73.982893,40.636925],"type":"Point"}
}