{
  "type": "Feature",
  "properties": {
    "addr:full":"30 E 40th St New York NY 10016",
    "addr:housenumber":"30",
    "addr:postcode":"10016",
    "addr:street":"E 40Th St",
    "iso:country":"US",
    "sg:address":"30 E 40th St",
    "sg:city":"New York",
    "sg:classifiers":[
        {
            "category":"Health Services",
            "subcategory":"Health Practitioner",
            "type":"Services"
        }
    ],
    "sg:phone":"+1 212 541 5503",
    "sg:postcode":"10016",
    "sg:province":"NY",
    "sg:tags":[
        "acupuncture"
    ],
    "wof:name":"Fh Acupuncture P C",
    "wof:placetype":"venue"
},
  "geometry": {"coordinates":[-73.980108,40.751333],"type":"Point"}
}