{
  "type": "Feature",
  "properties": {
    "addr:full":"1219 Hawleyton Rd Binghamton NY 13903",
    "addr:housenumber":"1219",
    "addr:postcode":"13903",
    "addr:street":"Hawleyton Rd",
    "iso:country":"US",
    "sg:address":"1219 Hawleyton Rd",
    "sg:city":"Binghamton",
    "sg:classifiers":[
        {
            "category":"Personal",
            "subcategory":"Beauty Salon",
            "type":"Services"
        }
    ],
    "sg:phone":"+1 607 669 4247",
    "sg:postcode":"13903",
    "sg:province":"NY",
    "wof:name":"Studio 1219 Salon",
    "wof:placetype":"venue"
},
  "geometry": {"coordinates":[-75.92067400000001,42.032346],"type":"Point"}
}