{
  "type": "Feature",
  "properties": {
    "addr:full":"44 Lake Rd Ballston Lake NY 12019",
    "addr:housenumber":"44",
    "addr:postcode":"12019",
    "addr:street":"Lake Rd",
    "iso:country":"US",
    "sg:address":"44 Lake Rd",
    "sg:city":"Ballston Lake",
    "sg:classifiers":[
        {
            "category":"Building & Trades",
            "subcategory":"Construction",
            "type":"Services"
        }
    ],
    "sg:phone":"+1 518 399 4294",
    "sg:postcode":"12019",
    "sg:province":"NY",
    "sg:tags":[
        "excavation",
        "contractor"
    ],
    "wof:name":"Dig N Dump Excavation Co",
    "wof:placetype":"venue"
},
  "geometry": {"coordinates":[-73.854445,42.932402],"type":"Point"}
}