{
  "type": "Feature",
  "properties": {
    "addr:full":"2353 Central Park Ave Yonkers NY 10710",
    "addr:housenumber":"2353",
    "addr:postcode":"10710",
    "addr:street":"Central Park Ave",
    "iso:country":"US",
    "sg:address":"2353 Central Park Ave",
    "sg:city":"Yonkers",
    "sg:classifiers":[
        {
            "category":"Food & Beverages",
            "subcategory":"Specialty",
            "type":"Retail Goods"
        }
    ],
    "sg:phone":"+1 914 779 5232",
    "sg:postcode":"10710",
    "sg:province":"NY",
    "sg:tags":[
        "vitamin"
    ],
    "sg:website":"www.vitaminshoppe.com",
    "wof:name":"Vitamin Shoppe",
    "wof:placetype":"venue"
},
  "geometry": {"coordinates":[-73.830662,40.978914],"type":"Point"}
}