{
  "type": "Feature",
  "properties": {
    "addr:full":"330 W 38th St New York NY 10018",
    "addr:housenumber":"330",
    "addr:postcode":"10018",
    "addr:street":"W 38Th St",
    "iso:country":"US",
    "sg:address":"330 W 38th St",
    "sg:city":"New York",
    "sg:classifiers":[
        {
            "category":"Professional",
            "subcategory":"Lawyer & Legal Services",
            "type":"Services"
        }
    ],
    "sg:phone":"+1 212 265 7200",
    "sg:postcode":"10018",
    "sg:province":"NY",
    "sg:tags":[
        "attorney"
    ],
    "wof:name":"Gary S Mayerson & Assoc",
    "wof:placetype":"venue"
},
  "geometry": {"coordinates":[-73.993847,40.755475],"type":"Point"}
}