{
  "type": "Feature",
  "properties": {
    "iso:country":"US",
    "sg:address":"250 E 88th St",
    "sg:city":"Brooklyn",
    "sg:classifiers":[
        {
            "category":"Autos & Motor Vehicles",
            "subcategory":"Automobile Sales",
            "type":"Retail Goods"
        }
    ],
    "sg:phone":"+1   ",
    "sg:postcode":"11236",
    "sg:province":"NY",
    "sg:tags":[
        "used"
    ],
    "wof:name":"Affordable Auto Sales",
    "wof:placetype":"venue"
},
  "geometry": {"coordinates":[-73.91687,40.647811],"type":"Point"}
}