{
  "type": "Feature",
  "properties": {
    "addr:full":"226 Webb St Clayton NY 13624",
    "addr:housenumber":"226",
    "addr:postcode":"13624",
    "addr:street":"Webb St",
    "iso:country":"US",
    "sg:address":"226 Webb St",
    "sg:city":"Clayton",
    "sg:classifiers":[
        {
            "category":"Restaurant",
            "type":"Food & Drink"
        }
    ],
    "sg:phone":"+1 315 686 1110",
    "sg:postcode":"13624",
    "sg:province":"NY",
    "wof:name":"O'Briens",
    "wof:placetype":"venue"
},
  "geometry": {"coordinates":[-76.08569199999999,44.243071],"type":"Point"}
}