{
  "type": "Feature",
  "properties": {
    "iso:country":"US",
    "sg:address":"30 Portsmouth Ave",
    "sg:city":"Staten Island",
    "sg:classifiers":[
        {
            "category":"Building & Trades",
            "subcategory":"Construction",
            "type":"Services"
        }
    ],
    "sg:phone":"+1 718 447 8908",
    "sg:postcode":"10301",
    "sg:province":"NY",
    "sg:tags":[
        "general",
        "contractor"
    ],
    "wof:name":"Well Built Development Corp",
    "wof:placetype":"venue"
},
  "geometry": {"coordinates":[-74.105346,40.604284],"type":"Point"}
}