{
  "type": "Feature",
  "properties": {
    "iso:country":"US",
    "sg:address":"203 Lafayette St",
    "sg:city":"New York",
    "sg:classifiers":[
        {
            "category":"Professional",
            "subcategory":"Management & Consulting",
            "type":"Services"
        }
    ],
    "sg:phone":"+1 212 334 1836",
    "sg:postcode":"10012",
    "sg:province":"NY",
    "sg:tags":[
        "marketing",
        "consultant"
    ],
    "wof:name":"Carovan Marketing Corp",
    "wof:placetype":"venue"
},
  "geometry": {"coordinates":[-73.997962,40.721125],"type":"Point"}
}