{
  "type": "Feature",
  "properties": {
    "addr:full":"11 Knolls Cres Bronx NY 10463",
    "addr:housenumber":"11",
    "addr:postcode":"10463",
    "addr:street":"Knolls Cres",
    "iso:country":"US",
    "sg:address":"11 Knolls Cres",
    "sg:city":"Bronx",
    "sg:classifiers":[
        {
            "category":"Retail",
            "subcategory":"Repair Shop",
            "type":"Services"
        }
    ],
    "sg:phone":"+1 718 535 9254",
    "sg:postcode":"10463",
    "sg:province":"NY",
    "sg:tags":[
        "lock",
        "locksmith"
    ],
    "wof:name":"USA Locksmiths",
    "wof:placetype":"venue"
},
  "geometry": {"coordinates":[-73.918048,40.87854],"type":"Point"}
}