{
  "type": "Feature",
  "properties": {
    "addr:full":"1414 E 89th St Brooklyn NY 11236",
    "addr:housenumber":"1414",
    "addr:postcode":"11236",
    "addr:street":"E 89Th St",
    "iso:country":"US",
    "sg:address":"1414 E 89th St",
    "sg:city":"Brooklyn",
    "sg:classifiers":[
        {
            "category":"Real Estate",
            "subcategory":"Real Estate Agent",
            "type":"Services"
        }
    ],
    "sg:phone":"+1 718 763 8112",
    "sg:postcode":"11236",
    "sg:province":"NY",
    "wof:name":"Tikva Realty Corp",
    "wof:placetype":"venue"
},
  "geometry": {"coordinates":[-73.896028,40.630074],"type":"Point"}
}