{
  "type": "Feature",
  "properties": {
    "addr:full":"991 Straight Path West Babylon NY 11704",
    "addr:housenumber":"991",
    "addr:postcode":"11704",
    "addr:street":"Straight Path",
    "iso:country":"US",
    "sg:address":"991 Straight Path",
    "sg:city":"West Babylon",
    "sg:classifiers":[
        {
            "category":"Personal",
            "subcategory":"Beauty Salon",
            "type":"Services"
        }
    ],
    "sg:phone":"+1 631 884 3099",
    "sg:postcode":"11704",
    "sg:province":"NY",
    "wof:name":"Fashion Nail",
    "wof:placetype":"venue"
},
  "geometry": {"coordinates":[-73.376813,40.722982],"type":"Point"}
}