{
  "type": "Feature",
  "properties": {
    "iso:country":"US",
    "sg:address":"47 S Plank Rd",
    "sg:city":"Newburgh",
    "sg:classifiers":[
        {
            "category":"Personal",
            "subcategory":"Barber",
            "type":"Services"
        }
    ],
    "sg:phone":"+1 845 565 5650",
    "sg:postcode":"12550",
    "sg:province":"NY",
    "wof:name":"Johnny's Barber Shop",
    "wof:placetype":"venue"
},
  "geometry": {"coordinates":[-74.01701,41.514719],"type":"Point"}
}