{
  "type": "Feature",
  "properties": {
    "addr:full":"132 E 23rd St New York NY 10010",
    "addr:housenumber":"132",
    "addr:postcode":"10010",
    "addr:street":"E 23Rd St",
    "iso:country":"US",
    "sg:address":"132 E 23rd St",
    "sg:city":"New York",
    "sg:classifiers":[
        {
            "category":"Personal",
            "subcategory":"Tanning Parlor",
            "type":"Services"
        }
    ],
    "sg:phone":"+1 212 254 0280",
    "sg:postcode":"10010",
    "sg:province":"NY",
    "sg:website":"beachbum23st.com",
    "wof:name":"Beach Bum Tanning & Airbrush Salon",
    "wof:placetype":"venue"
},
  "geometry": {"coordinates":[-73.985062,40.739473],"type":"Point"}
}