{
  "type": "Feature",
  "properties": {
    "iso:country":"US",
    "sg:address":"31699 Co Rd 6",
    "sg:city":"Cape Vincent",
    "sg:classifiers":[
        {
            "category":"Building & Trades",
            "subcategory":"Landscaping Services",
            "type":"Services"
        }
    ],
    "sg:phone":"+1 315 654 4576",
    "sg:postcode":"13618",
    "sg:province":"NY",
    "sg:tags":[
        "landscape",
        "contractor"
    ],
    "wof:name":"Shimp Paving & Landscaping",
    "wof:placetype":"venue"
},
  "geometry": {"coordinates":[-76.367519,44.105891],"type":"Point"}
}