{
  "type": "Feature",
  "properties": {
    "addr:full":"2975 Brighton Henrietta Town Line Rd Ste 110 Rochester NY 14623",
    "addr:housenumber":"2975",
    "addr:postcode":"14623",
    "addr:street":"Brighton Henrietta Town Line Rd Ste 110",
    "iso:country":"US",
    "sg:address":"2975 Brighton Henrietta Town Line Rd Ste 110",
    "sg:city":"Rochester",
    "sg:classifiers":[
        {
            "category":"Real Estate",
            "subcategory":"Real Estate Services",
            "type":"Services"
        },
        {
            "category":"Shopping Center",
            "type":"Public Place"
        }
    ],
    "sg:phone":"+1 585 427 7530",
    "sg:postcode":"14623",
    "sg:province":"NY",
    "sg:tags":[
        "mall",
        "management"
    ],
    "wof:name":"Southtown Plaza Assoc",
    "wof:placetype":"venue"
},
  "geometry": {"coordinates":[-77.600587,43.095216],"type":"Point"}
}