{
  "type": "Feature",
  "properties": {
    "addr:full":"58 Quail Hollow Ln East Amherst NY 14051",
    "addr:housenumber":"58",
    "addr:postcode":"14051",
    "addr:street":"Quail Hollow Ln",
    "iso:country":"US",
    "sg:address":"58 Quail Hollow Ln",
    "sg:city":"East Amherst",
    "sg:classifiers":[
        {
            "category":"Professional",
            "subcategory":"Research",
            "type":"Services"
        }
    ],
    "sg:phone":"+1 716 639 0832",
    "sg:postcode":"14051",
    "sg:province":"NY",
    "sg:tags":[
        "environmental",
        "ecological"
    ],
    "wof:name":"Environmental Documents Inc",
    "wof:placetype":"venue"
},
  "geometry": {"coordinates":[-78.712397,43.016445],"type":"Point"}
}