{
  "type": "Feature",
  "properties": {
    "addr:full":"495 Granny Rd Medford NY 11763",
    "addr:housenumber":"495",
    "addr:postcode":"11763",
    "addr:street":"Granny Rd",
    "iso:country":"US",
    "sg:address":"495 Granny Rd",
    "sg:city":"Medford",
    "sg:classifiers":[
        {
            "category":"Food & Beverages",
            "subcategory":"Groceries & Convenience Stores",
            "type":"Retail Goods"
        }
    ],
    "sg:phone":"+1   ",
    "sg:postcode":"11763",
    "sg:province":"NY",
    "wof:name":"Fjp Deli Corp",
    "wof:placetype":"venue"
},
  "geometry": {"coordinates":[-72.97599700000001,40.849703],"type":"Point"}
}