{
  "type": "Feature",
  "properties": {
    "addr:full":"42 Queechy Lake Dr Canaan NY 12029",
    "addr:housenumber":"42",
    "addr:postcode":"12029",
    "addr:street":"Queechy Lake Dr",
    "iso:country":"US",
    "sg:address":"42 Queechy Lake Dr",
    "sg:city":"Canaan",
    "sg:classifiers":[
        {
            "category":"Restaurant",
            "type":"Food & Drink"
        }
    ],
    "sg:phone":"+1 518 781 0199",
    "sg:postcode":"12029",
    "sg:province":"NY",
    "sg:tags":[
        "grill",
        "bar"
    ],
    "wof:name":"Backwater Grille",
    "wof:placetype":"venue"
},
  "geometry": {"coordinates":[-73.42221600000001,42.404164],"type":"Point"}
}