{
  "type": "Feature",
  "properties": {
    "addr:full":"112 S Main St Northville NY 12134",
    "addr:housenumber":"112",
    "addr:postcode":"12134",
    "addr:street":"S Main St",
    "iso:country":"US",
    "sg:address":"112 S Main St",
    "sg:city":"Northville",
    "sg:classifiers":[
        {
            "category":"Shopping",
            "subcategory":"Discount & Variety Stores",
            "type":"Retail Goods"
        }
    ],
    "sg:phone":"+1 518 863 6321",
    "sg:postcode":"12134",
    "sg:province":"NY",
    "sg:tags":[
        "merchandise",
        "general"
    ],
    "wof:name":"Plug's Plus Auto Supply",
    "wof:placetype":"venue"
},
  "geometry": {"coordinates":[-74.171806,43.225787],"type":"Point"}
}