{
  "type": "Feature",
  "properties": {
    "addr:full":"41 North Ln Orchard Park NY 14127",
    "addr:housenumber":"41",
    "addr:postcode":"14127",
    "addr:street":"North Ln",
    "iso:country":"US",
    "sg:address":"41 North Ln",
    "sg:city":"Orchard Park",
    "sg:classifiers":[
        {
            "category":"Professional",
            "type":"Services"
        }
    ],
    "sg:phone":"+1   ",
    "sg:postcode":"14127",
    "sg:province":"NY",
    "wof:name":"Habasit Belting Inc",
    "wof:placetype":"venue"
},
  "geometry": {"coordinates":[-78.738286,42.749461],"type":"Point"}
}