{
  "type": "Feature",
  "properties": {
    "addr:full":"3914 Merrick Rd Seaford NY 11783",
    "addr:housenumber":"3914",
    "addr:postcode":"11783",
    "addr:street":"Merrick Rd",
    "iso:country":"US",
    "sg:address":"3914 Merrick Rd",
    "sg:city":"Seaford",
    "sg:classifiers":[
        {
            "category":"Home & Garden",
            "subcategory":"Building Materials",
            "type":"Retail Goods"
        }
    ],
    "sg:phone":"+1 516 785 0900",
    "sg:postcode":"11783",
    "sg:province":"NY",
    "sg:tags":[
        "glass",
        "window",
        "plate"
    ],
    "wof:name":"Mr Glass South Shore",
    "wof:placetype":"venue"
},
  "geometry": {"coordinates":[-73.485861,40.666171],"type":"Point"}
}