{
  "type": "Feature",
  "properties": {
    "addr:full":"526 86th St Brooklyn NY 11209",
    "addr:housenumber":"526",
    "addr:postcode":"11209",
    "addr:street":"86Th St",
    "iso:country":"US",
    "sg:address":"526 86th St",
    "sg:city":"Brooklyn",
    "sg:classifiers":[
        {
            "category":"Shopping",
            "subcategory":"Clothing, Apparel, & Fashions",
            "type":"Retail Goods"
        }
    ],
    "sg:phone":"+1 718 238 0560",
    "sg:postcode":"11209",
    "sg:province":"NY",
    "sg:tags":[
        "apparel",
        "maternity",
        "women's"
    ],
    "sg:website":"http://www.motherhood.com",
    "wof:name":"Motherhood Maternity",
    "wof:placetype":"venue"
},
  "geometry": {"coordinates":[-74.025429,40.621009],"type":"Point"}
}