{
  "type": "Feature",
  "properties": {
    "addr:full":"128 W Railroad Ave Garnerville NY 10923",
    "addr:housenumber":"128",
    "addr:postcode":"10923",
    "addr:street":"W Railroad Ave",
    "iso:country":"US",
    "sg:address":"128 W Railroad Ave",
    "sg:city":"Garnerville",
    "sg:classifiers":[
        {
            "category":"Organizations",
            "subcategory":"Religious Organization",
            "type":"Services"
        }
    ],
    "sg:phone":"+1 845 947 1218",
    "sg:postcode":"10923",
    "sg:province":"NY",
    "sg:tags":[
        "church"
    ],
    "wof:name":"Christian Church Of Rockland",
    "wof:placetype":"venue"
},
  "geometry": {"coordinates":[-73.993635,41.208289],"type":"Point"}
}