{
  "type": "Feature",
  "properties": {
    "iso:country":"US",
    "sg:address":"261 E 78th St 2nd Fl",
    "sg:city":"New York",
    "sg:classifiers":[
        {
            "category":"Health Services",
            "subcategory":"Health Practitioner",
            "type":"Services"
        }
    ],
    "sg:phone":"+1 212 472 5820",
    "sg:postcode":"10075",
    "sg:province":"NY",
    "sg:tags":[
        "therapy",
        "physical"
    ],
    "sg:website":"www.equilibriumpt.com",
    "wof:name":"Equilibrium Physical Therapy",
    "wof:placetype":"venue"
},
  "geometry": {"coordinates":[-73.955889,40.773055],"type":"Point"}
}