{
  "type": "Feature",
  "properties": {
    "iso:country":"US",
    "sg:address":"261 W 231st St",
    "sg:city":"Bronx",
    "sg:classifiers":[
        {
            "category":"Retail",
            "subcategory":"Repair Shop",
            "type":"Services"
        }
    ],
    "sg:phone":"+1 718 685 5947",
    "sg:postcode":"10463",
    "sg:province":"NY",
    "sg:tags":[
        "lock",
        "locksmith"
    ],
    "wof:name":"Locksmith Emergency",
    "wof:placetype":"venue"
},
  "geometry": {"coordinates":[-73.90730600000001,40.880247],"type":"Point"}
}