{
  "type": "Feature",
  "properties": {
    "addr:full":"2002 Story Ave Bronx NY 10473",
    "addr:housenumber":"2002",
    "addr:postcode":"10473",
    "addr:street":"Story Ave",
    "iso:country":"US",
    "sg:address":"2002 Story Ave",
    "sg:city":"Bronx",
    "sg:classifiers":[
        {
            "category":"Social Services",
            "subcategory":"Child Care",
            "type":"Services"
        }
    ],
    "sg:phone":"+1 718 597 2620",
    "sg:postcode":"10473",
    "sg:province":"NY",
    "wof:name":"Children's Happy Face",
    "wof:placetype":"venue"
},
  "geometry": {"coordinates":[-73.85262299999999,40.824962],"type":"Point"}
}