{
  "type": "Feature",
  "properties": {
    "iso:country":"US",
    "sg:address":"7803 3rd Ave",
    "sg:city":"Brooklyn",
    "sg:classifiers":[
        {
            "category":"Cafe",
            "type":"Food & Drink"
        }
    ],
    "sg:menulink":"http://www.allmenus.com/ny/brooklyn/54706-mythai-cafe/menu/",
    "sg:phone":"+1 718 833 1700",
    "sg:postcode":"11209",
    "sg:province":"NY",
    "sg:tags":[
        "asian",
        "chinese"
    ],
    "wof:name":"MyThai Cafe",
    "wof:placetype":"venue"
},
  "geometry": {"coordinates":[-74.02870799999999,40.629163],"type":"Point"}
}