{
  "type": "Feature",
  "properties": {
    "addr:full":"1258 Ridge Rd E Rochester NY 14621",
    "addr:housenumber":"1258",
    "addr:postcode":"14621",
    "addr:street":"Ridge Rd E",
    "iso:country":"US",
    "sg:address":"1258 Ridge Rd E",
    "sg:city":"Rochester",
    "sg:classifiers":[
        {
            "category":"Manufacturing",
            "subcategory":"Printing",
            "type":"Manufacturing & Wholesale Goods"
        }
    ],
    "sg:phone":"+1 585 266 4911",
    "sg:postcode":"14621",
    "sg:province":"NY",
    "sg:tags":[
        "printer",
        "offset"
    ],
    "wof:name":"East Ridge Quick Print",
    "wof:placetype":"venue"
},
  "geometry": {"coordinates":[-77.58958699999999,43.197196],"type":"Point"}
}