{
  "type": "Feature",
  "properties": {
    "iso:country":"US",
    "sg:address":"6 South St",
    "sg:city":"Stamford",
    "sg:classifiers":[
        {
            "category":"Wholesale",
            "subcategory":"Farm Supplies",
            "type":"Manufacturing & Wholesale Goods"
        }
    ],
    "sg:phone":"+1 607 652 7225",
    "sg:postcode":"12167",
    "sg:province":"NY",
    "wof:name":"Stamford Farmers Co-Op",
    "wof:placetype":"venue"
},
  "geometry": {"coordinates":[-74.621004,42.40903],"type":"Point"}
}