{
  "type": "Feature",
  "properties": {
    "iso:country":"US",
    "sg:address":"57 W 38th St",
    "sg:city":"New York",
    "sg:classifiers":[
        {
            "category":"Organizations",
            "subcategory":"Political Organization",
            "type":"Services"
        }
    ],
    "sg:phone":"+1   ",
    "sg:postcode":"10018",
    "sg:province":"NY",
    "sg:tags":[
        "profit"
    ],
    "wof:name":"Pan-Asian Amrcn Ldrship Caucus",
    "wof:placetype":"venue"
},
  "geometry": {"coordinates":[-73.984515,40.751607],"type":"Point"}
}