{
  "type": "Feature",
  "properties": {
    "addr:full":"84 Rose Ave Westbury NY 11590",
    "addr:housenumber":"84",
    "addr:postcode":"11590",
    "addr:street":"Rose Ave",
    "iso:country":"US",
    "sg:address":"84 Rose Ave",
    "sg:city":"Westbury",
    "sg:classifiers":[
        {
            "category":"Health Services",
            "subcategory":"Dentist",
            "type":"Services"
        }
    ],
    "sg:phone":"+1 516 876 9000",
    "sg:postcode":"11590",
    "sg:province":"NY",
    "wof:name":"Carle Place Dental Health Facility",
    "wof:placetype":"venue"
},
  "geometry": {"coordinates":[-73.61599699999999,40.758999],"type":"Point"}
}