{
  "type": "Feature",
  "properties": {
    "iso:country":"US",
    "sg:address":"79 Middleville Rd",
    "sg:city":"Northport",
    "sg:classifiers":[
        {
            "category":"Professional",
            "type":"Services"
        }
    ],
    "sg:phone":"+1 631 754 6103",
    "sg:postcode":"11768",
    "sg:province":"NY",
    "sg:tags":[
        "establishment"
    ],
    "wof:name":"Shingles Prevention Resea",
    "wof:placetype":"venue"
},
  "geometry": {"coordinates":[-73.306918,40.899947],"type":"Point"}
}