{
  "type": "Feature",
  "properties": {
    "addr:full":"2910 Exterior St Bronx NY 10463",
    "addr:housenumber":"2910",
    "addr:postcode":"10463",
    "addr:street":"Exterior St",
    "iso:country":"US",
    "sg:address":"2910 Exterior St",
    "sg:city":"Bronx",
    "sg:classifiers":[
        {
            "category":"Education",
            "subcategory":"School",
            "type":"Public Place"
        }
    ],
    "sg:phone":"+1 718 561 7842",
    "sg:postcode":"10463",
    "sg:province":"NY",
    "wof:name":"Marie Smith Urban Street Acad",
    "wof:placetype":"venue"
},
  "geometry": {"coordinates":[-73.906437,40.874906],"type":"Point"}
}