{
  "type": "Feature",
  "properties": {
    "addr:full":"400 N Main St Southampton NY 11968",
    "addr:housenumber":"400",
    "addr:postcode":"11968",
    "addr:street":"N Main St",
    "iso:country":"US",
    "sg:address":"400 N Main St",
    "sg:city":"Southampton",
    "sg:classifiers":[
        {
            "category":"Building & Trades",
            "subcategory":"Construction",
            "type":"Services"
        }
    ],
    "sg:phone":"+1 631 287 2178",
    "sg:postcode":"11968",
    "sg:province":"NY",
    "sg:tags":[
        "roofing",
        "contractor"
    ],
    "wof:name":"Peconic Sheet Metal",
    "wof:placetype":"venue"
},
  "geometry": {"coordinates":[-72.39180899999999,40.90117],"type":"Point"}
}