{
  "type": "Feature",
  "properties": {
    "iso:country":"US",
    "sg:address":"532 Larkfield Rd",
    "sg:city":"East Northport",
    "sg:classifiers":[
        {
            "category":"Food & Beverages",
            "subcategory":"Bakery",
            "type":"Retail Goods"
        }
    ],
    "sg:phone":"+1 631 486 4454",
    "sg:postcode":"11731",
    "sg:province":"NY",
    "sg:tags":[
        "sandwich"
    ],
    "wof:name":"Tropical Smoothie Cafe",
    "wof:placetype":"venue"
},
  "geometry": {"coordinates":[-73.32001,40.861279],"type":"Point"}
}