{
  "type": "Feature",
  "properties": {
    "addr:full":"732 Central Ave Woodmere NY 11598",
    "addr:housenumber":"732",
    "addr:postcode":"11598",
    "addr:street":"Central Ave",
    "iso:country":"US",
    "sg:address":"732 Central Ave",
    "sg:city":"Woodmere",
    "sg:classifiers":[
        {
            "category":"Professional",
            "subcategory":"Accounting & Tax Preparation",
            "type":"Services"
        }
    ],
    "sg:phone":"+1 516 569 2500",
    "sg:postcode":"11598",
    "sg:province":"NY",
    "wof:name":"Erdherim Accounting",
    "wof:placetype":"venue"
},
  "geometry": {"coordinates":[-73.716509,40.626934],"type":"Point"}
}