{
  "type": "Feature",
  "properties": {
    "iso:country":"US",
    "sg:address":"2395 Havens Corners Rd",
    "sg:city":"Penn Yan",
    "sg:classifiers":[
        {
            "category":"Organizations",
            "subcategory":"Religious Organization",
            "type":"Services"
        }
    ],
    "sg:phone":"+1 315 536 9819",
    "sg:postcode":"14527",
    "sg:province":"NY",
    "sg:tags":[
        "church"
    ],
    "wof:name":"Benton Methodist Church",
    "wof:placetype":"venue"
},
  "geometry": {"coordinates":[-77.065877,42.717416],"type":"Point"}
}