{
  "type": "Feature",
  "properties": {
    "addr:full":"483 State Hwy 7 Afton NY 13730",
    "addr:housenumber":"483",
    "addr:postcode":"13730",
    "addr:street":"State Hwy 7",
    "iso:country":"US",
    "sg:address":"483 State Hwy 7",
    "sg:city":"Afton",
    "sg:classifiers":[
        {
            "category":"Farming",
            "subcategory":"Dairy Farm",
            "type":"Manufacturing & Wholesale Goods"
        }
    ],
    "sg:phone":"+1 607 639 2946",
    "sg:postcode":"13730",
    "sg:province":"NY",
    "wof:name":"Plaesant Hill Farm",
    "wof:placetype":"venue"
},
  "geometry": {"coordinates":[-75.577682,42.21254],"type":"Point"}
}