{
  "type": "Feature",
  "properties": {
    "iso:country":"US",
    "sg:address":"225 Glenwood Ave",
    "sg:city":"Syracuse",
    "sg:classifiers":[
        {
            "category":"Organizations",
            "subcategory":"Religious Organization",
            "type":"Services"
        }
    ],
    "sg:phone":"+1 315 478 4876",
    "sg:postcode":"13207",
    "sg:province":"NY",
    "sg:tags":[
        "clergy"
    ],
    "wof:name":"B M Matthews",
    "wof:placetype":"venue"
},
  "geometry": {"coordinates":[-76.164947,43.019737],"type":"Point"}
}