{
  "type": "Feature",
  "properties": {
    "addr:full":"8614 18th Ave Brooklyn NY 11214",
    "addr:housenumber":"8614",
    "addr:postcode":"11214",
    "addr:street":"18Th Ave",
    "iso:country":"US",
    "sg:address":"8614 18th Ave",
    "sg:city":"Brooklyn",
    "sg:classifiers":[
        {
            "category":"Personal",
            "subcategory":"Beauty Salon",
            "type":"Services"
        }
    ],
    "sg:phone":"+1   ",
    "sg:postcode":"11214",
    "sg:province":"NY",
    "sg:tags":[
        "shop"
    ],
    "wof:name":"Malina Galleria",
    "wof:placetype":"venue"
},
  "geometry": {"coordinates":[-74.004273,40.605878],"type":"Point"}
}