{
  "type": "Feature",
  "properties": {
    "iso:country":"US",
    "sg:address":"35 E Main St",
    "sg:city":"Brocton",
    "sg:classifiers":[
        {
            "category":"Organizations",
            "subcategory":"Religious Organization",
            "type":"Services"
        }
    ],
    "sg:phone":"+1 716 792 4533",
    "sg:postcode":"14716",
    "sg:province":"NY",
    "wof:name":"Rhodes Jacqueline Pastor",
    "wof:placetype":"venue"
},
  "geometry": {"coordinates":[-79.439196,42.389139],"type":"Point"}
}