{
  "type": "Feature",
  "properties": {
    "addr:full":"260 Western Tpke Altamont NY 12009",
    "addr:housenumber":"260",
    "addr:postcode":"12009",
    "addr:street":"Western Tpke",
    "iso:country":"US",
    "sg:address":"260 Western Tpke",
    "sg:city":"Altamont",
    "sg:classifiers":[
        {
            "category":"Building & Trades",
            "subcategory":"Landscaping Services",
            "type":"Services"
        }
    ],
    "sg:phone":"+1 518 356 9605",
    "sg:postcode":"12009",
    "sg:province":"NY",
    "sg:tags":[
        "landscape",
        "contractor"
    ],
    "wof:name":"Rocky's Lawn Reconstruction",
    "wof:placetype":"venue"
},
  "geometry": {"coordinates":[-74.03913900000001,42.747371],"type":"Point"}
}