{
  "type": "Feature",
  "properties": {
    "iso:country":"US",
    "sg:address":"49 Country Club Rd",
    "sg:city":"Westport",
    "sg:classifiers":[
        {
            "category":"Organizations",
            "subcategory":"Community Association",
            "type":"Services"
        }
    ],
    "sg:phone":"+1 518 962 4470",
    "sg:postcode":"12986",
    "sg:province":"NY",
    "sg:tags":[
        "club"
    ],
    "wof:name":"Westport Country Club",
    "wof:placetype":"venue"
},
  "geometry": {"coordinates":[-74.485356,44.188866],"type":"Point"}
}