{
  "type": "Feature",
  "properties": {
    "iso:country":"US",
    "sg:address":"58 Oswego River Rd",
    "sg:city":"Phoenix",
    "sg:classifiers":[
        {
            "category":"Home & Garden",
            "subcategory":"Building Materials",
            "type":"Retail Goods"
        },
        {
            "category":"Building & Trades",
            "subcategory":"Construction",
            "type":"Services"
        }
    ],
    "sg:phone":"+1 315 695 6983",
    "sg:postcode":"13135",
    "sg:province":"NY",
    "sg:tags":[
        "concrete-stamped",
        "decorative",
        "installation",
        "windows-repair",
        "contractor",
        "siding",
        "replacement"
    ],
    "sg:website":"http://caplesconstruction.net",
    "wof:name":"Caples Construction Inc",
    "wof:placetype":"venue"
},
  "geometry": {"coordinates":[-76.31416299999999,43.23531],"type":"Point"}
}