{
  "type": "Feature",
  "properties": {
    "addr:full":"1615 E 4th St Brooklyn NY 11230",
    "addr:housenumber":"1615",
    "addr:postcode":"11230",
    "addr:street":"E 4Th St",
    "iso:country":"US",
    "sg:address":"1615 E 4th St",
    "sg:city":"Brooklyn",
    "sg:classifiers":[
        {
            "category":"Wholesale",
            "subcategory":"Apparel",
            "type":"Manufacturing & Wholesale Goods"
        }
    ],
    "sg:phone":"+1 718 645 3875",
    "sg:postcode":"11230",
    "sg:province":"NY",
    "sg:tags":[
        "clothing"
    ],
    "wof:name":"Royal International Corp",
    "wof:placetype":"venue"
},
  "geometry": {"coordinates":[-73.96995099999999,40.609549],"type":"Point"}
}