{
  "type": "Feature",
  "properties": {
    "addr:full":"454 Sawyer Ave Tonawanda NY 14150",
    "addr:housenumber":"454",
    "addr:postcode":"14150",
    "addr:street":"Sawyer Ave",
    "iso:country":"US",
    "sg:address":"454 Sawyer Ave",
    "sg:city":"Tonawanda",
    "sg:classifiers":[
        {
            "category":"Freight",
            "type":"Transportation"
        }
    ],
    "sg:phone":"+1   ",
    "sg:postcode":"14150",
    "sg:province":"NY",
    "sg:tags":[
        "operator",
        "trucking"
    ],
    "wof:name":"Central Transport Intl Inc",
    "wof:placetype":"venue"
},
  "geometry": {"coordinates":[-78.911973,42.97876],"type":"Point"}
}