{
  "type": "Feature",
  "properties": {
    "iso:country":"US",
    "sg:address":"303 E 188th St",
    "sg:city":"Bronx",
    "sg:classifiers":[
        {
            "category":"Real Estate",
            "subcategory":"Real Estate Agent",
            "type":"Services"
        }
    ],
    "sg:phone":"+1 718 584 5882",
    "sg:postcode":"10458",
    "sg:province":"NY",
    "sg:tags":[
        "authorities",
        "housing"
    ],
    "wof:name":"Fordham Bedford Housing Corp",
    "wof:placetype":"venue"
},
  "geometry": {"coordinates":[-73.89464599999999,40.860637],"type":"Point"}
}