{
  "type": "Feature",
  "properties": {
    "iso:country":"US",
    "sg:address":"732 Malta Ave Exd",
    "sg:city":"Ballston Spa",
    "sg:classifiers":[
        {
            "category":"Wholesale",
            "subcategory":"Plants",
            "type":"Manufacturing & Wholesale Goods"
        }
    ],
    "sg:phone":"+1 518 584 2760",
    "sg:postcode":"12020",
    "sg:province":"NY",
    "sg:tags":[
        "supply"
    ],
    "wof:name":"Elegant Designs By Lucretia",
    "wof:placetype":"venue"
},
  "geometry": {"coordinates":[-73.78267099999999,43.012326],"type":"Point"}
}