{
  "type": "Feature",
  "properties": {
    "iso:country":"US",
    "sg:address":"500 Halstead Ave",
    "sg:city":"Mamaroneck",
    "sg:classifiers":[
        {
            "category":"Building & Trades",
            "subcategory":"Construction",
            "type":"Services"
        }
    ],
    "sg:phone":"+1 914 381 6900",
    "sg:postcode":"10543",
    "sg:province":"NY",
    "sg:tags":[
        "general",
        "contractor"
    ],
    "wof:name":"Remodeling Consultants",
    "wof:placetype":"venue"
},
  "geometry": {"coordinates":[-73.731461,40.956969],"type":"Point"}
}