{
  "type": "Feature",
  "properties": {
    "addr:full":"3515 Oneida St Chadwicks NY 13319",
    "addr:housenumber":"3515",
    "addr:postcode":"13319",
    "addr:street":"Oneida St",
    "iso:country":"US",
    "sg:address":"3515 Oneida St",
    "sg:city":"Chadwicks",
    "sg:classifiers":[
        {
            "category":"Building & Trades",
            "subcategory":"Construction",
            "type":"Services"
        }
    ],
    "sg:phone":"+1 315 737 4417",
    "sg:postcode":"13319",
    "sg:province":"NY",
    "sg:tags":[
        "contractor"
    ],
    "wof:name":"Charles Tibbitts Masonry Cnstr",
    "wof:placetype":"venue"
},
  "geometry": {"coordinates":[-75.275547,43.034142],"type":"Point"}
}