{
  "type": "Feature",
  "properties": {
    "addr:full":"209 7th Ave New York NY 10011",
    "addr:housenumber":"209",
    "addr:postcode":"10011",
    "addr:street":"7Th Ave",
    "iso:country":"US",
    "sg:address":"209 7th Ave",
    "sg:city":"New York",
    "sg:classifiers":[
        {
            "category":"Restaurant",
            "type":"Food & Drink"
        }
    ],
    "sg:menulink":"http://www.allmenus.com/ny/new-york/7400-restivo-ristorante/menu/",
    "sg:phone":"+1 212 366 4133",
    "sg:postcode":"10011",
    "sg:province":"NY",
    "sg:tags":[
        "italian"
    ],
    "wof:name":"Restivo Ristorante",
    "wof:placetype":"venue"
},
  "geometry": {"coordinates":[-73.99568600000001,40.743399],"type":"Point"}
}