{
  "type": "Feature",
  "properties": {
    "addr:full":"11 Eagle Chase Woodbury NY 11797",
    "addr:housenumber":"11",
    "addr:postcode":"11797",
    "addr:street":"Eagle Chase",
    "iso:country":"US",
    "sg:address":"11 Eagle Chase",
    "sg:city":"Woodbury",
    "sg:classifiers":[
        {
            "category":"Real Estate",
            "subcategory":"Real Estate Services",
            "type":"Services"
        },
        {
            "category":"Banks & Credit Unions",
            "subcategory":"Financial Services",
            "type":"Services"
        }
    ],
    "sg:phone":"+1 800 506 9494",
    "sg:postcode":"11797",
    "sg:province":"NY",
    "sg:tags":[
        "loan",
        "processing"
    ],
    "wof:name":"M G Capital Co",
    "wof:placetype":"venue"
},
  "geometry": {"coordinates":[-73.473237,40.799665],"type":"Point"}
}