{
  "type": "Feature",
  "properties": {
    "addr:full":"925 Park Ave New York NY 10028",
    "addr:housenumber":"925",
    "addr:postcode":"10028",
    "addr:street":"Park Ave",
    "iso:country":"US",
    "sg:address":"925 Park Ave",
    "sg:city":"New York",
    "sg:classifiers":[
        {
            "category":"Real Estate",
            "subcategory":"Real Estate Operator",
            "type":"Services"
        }
    ],
    "sg:phone":"+1 212 650 9064",
    "sg:postcode":"10028",
    "sg:province":"NY",
    "sg:tags":[
        "apartment"
    ],
    "wof:name":"Nine-Twenty-Five Park Ave",
    "wof:placetype":"venue"
},
  "geometry": {"coordinates":[-73.959576,40.776764],"type":"Point"}
}