{
  "type": "Feature",
  "properties": {
    "iso:country":"US",
    "sg:address":"2116 Central Ave",
    "sg:city":"Schenectady",
    "sg:classifiers":[
        {
            "category":"Banks & Credit Unions",
            "subcategory":"Investment Brokerage",
            "type":"Services"
        }
    ],
    "sg:phone":"+1 518 782 9155",
    "sg:postcode":"12304",
    "sg:province":"NY",
    "sg:tags":[
        "advisory",
        "financial"
    ],
    "wof:name":"Royal Alliance Assoc Inc",
    "wof:placetype":"venue"
},
  "geometry": {"coordinates":[-73.881981,42.760665],"type":"Point"}
}