{
  "type": "Feature",
  "properties": {
    "addr:full":"51 Callingham Rd Pittsford NY 14534",
    "addr:housenumber":"51",
    "addr:postcode":"14534",
    "addr:street":"Callingham Rd",
    "iso:country":"US",
    "sg:address":"51 Callingham Rd",
    "sg:city":"Pittsford",
    "sg:classifiers":[
        {
            "category":"Professional",
            "subcategory":"Accounting & Tax Preparation",
            "type":"Services"
        }
    ],
    "sg:phone":"+1 585 586 8070",
    "sg:postcode":"14534",
    "sg:province":"NY",
    "sg:tags":[
        "accountant"
    ],
    "wof:name":"William A Jenny CPA",
    "wof:placetype":"venue"
},
  "geometry": {"coordinates":[-77.49524599999999,43.105622],"type":"Point"}
}