{
  "type": "Feature",
  "properties": {
    "addr:full":"4 Grand Blvd Brentwood NY 11717",
    "addr:housenumber":"4",
    "addr:postcode":"11717",
    "addr:street":"Grand Blvd",
    "iso:country":"US",
    "sg:address":"4 Grand Blvd",
    "sg:city":"Brentwood",
    "sg:classifiers":[
        {
            "category":"Manufacturing",
            "subcategory":"Metals",
            "type":"Manufacturing & Wholesale Goods"
        }
    ],
    "sg:phone":"+1 631 231 5223",
    "sg:postcode":"11717",
    "sg:province":"NY",
    "sg:tags":[
        "coating",
        "powder"
    ],
    "wof:name":"Applause Powder Coating Inc",
    "wof:placetype":"venue"
},
  "geometry": {"coordinates":[-73.226264,40.783814],"type":"Point"}
}