{
  "type": "Feature",
  "properties": {
    "iso:country":"US",
    "sg:address":"706 60th St",
    "sg:city":"Brooklyn",
    "sg:classifiers":[
        {
            "category":"Wholesale",
            "subcategory":"Computers",
            "type":"Manufacturing & Wholesale Goods"
        }
    ],
    "sg:phone":"+1 718 439 3109",
    "sg:postcode":"11220",
    "sg:province":"NY",
    "sg:website":"www.ca-ny.com",
    "wof:name":"Computech Inc",
    "wof:placetype":"venue"
},
  "geometry": {"coordinates":[-74.00970599999999,40.635516],"type":"Point"}
}