{
  "type": "Feature",
  "properties": {
    "iso:country":"US",
    "sg:address":"21 Vanderventer Ave",
    "sg:city":"Port Washington",
    "sg:classifiers":[
        {
            "category":"Freight",
            "type":"Transportation"
        }
    ],
    "sg:phone":"+1 516 883 8400",
    "sg:postcode":"11050",
    "sg:province":"NY",
    "sg:tags":[
        "trucking"
    ],
    "sg:website":"www.picpack.com",
    "wof:name":"Westbury Transport Inc",
    "wof:placetype":"venue"
},
  "geometry": {"coordinates":[-73.684849,40.828647],"type":"Point"}
}