{
  "type": "Feature",
  "properties": {
    "addr:full":"303 Bradley Ave Staten Island NY 10314",
    "addr:housenumber":"303",
    "addr:postcode":"10314",
    "addr:street":"Bradley Ave",
    "iso:country":"US",
    "sg:address":"303 Bradley Ave",
    "sg:city":"Staten Island",
    "sg:classifiers":[
        {
            "category":"Manufacturing",
            "subcategory":"Tools & Machinery",
            "type":"Manufacturing & Wholesale Goods"
        }
    ],
    "sg:phone":"+1   ",
    "sg:postcode":"10314",
    "sg:province":"NY",
    "sg:tags":[
        "medical",
        "software"
    ],
    "wof:name":"MD Reports",
    "wof:placetype":"venue"
},
  "geometry": {"coordinates":[-74.13164,40.60549],"type":"Point"}
}