{
  "type": "Feature",
  "properties": {
    "iso:country":"US",
    "sg:address":"151 W Merrick Rd",
    "sg:city":"Freeport",
    "sg:classifiers":[
        {
            "category":"Health Services",
            "subcategory":"Doctor",
            "type":"Services"
        }
    ],
    "sg:phone":"+1 516 608 6777",
    "sg:postcode":"11520",
    "sg:province":"NY",
    "sg:tags":[
        "physician",
        "surgeon"
    ],
    "wof:name":"Marc A Charles MD",
    "wof:placetype":"venue"
},
  "geometry": {"coordinates":[-73.587214,40.652907],"type":"Point"}
}