{
  "type": "Feature",
  "properties": {
    "addr:full":"6223 18th Ave Brooklyn NY 11204",
    "addr:housenumber":"6223",
    "addr:postcode":"11204",
    "addr:street":"18Th Ave",
    "iso:country":"US",
    "sg:address":"6223 18th Ave",
    "sg:city":"Brooklyn",
    "sg:classifiers":[
        {
            "category":"Wholesale",
            "subcategory":"Apparel",
            "type":"Manufacturing & Wholesale Goods"
        }
    ],
    "sg:phone":"+1 718 232 6303",
    "sg:postcode":"11204",
    "sg:province":"NY",
    "sg:tags":[
        "clothing"
    ],
    "wof:name":"Shouela Stores Inc",
    "wof:placetype":"venue"
},
  "geometry": {"coordinates":[-73.98883600000001,40.620385],"type":"Point"}
}