{
  "type": "Feature",
  "properties": {
    "iso:country":"US",
    "sg:address":"71 Oakwood Ave",
    "sg:city":"Farmingdale",
    "sg:classifiers":[
        {
            "category":"Home & Garden",
            "subcategory":"Carpets & Floor Coverings",
            "type":"Retail Goods"
        }
    ],
    "sg:phone":"+1 516 454 0639",
    "sg:postcode":"11735",
    "sg:province":"NY",
    "sg:tags":[
        "hardwood",
        "flooring",
        "contractor"
    ],
    "wof:name":"Quereau Hardwood Floors",
    "wof:placetype":"venue"
},
  "geometry": {"coordinates":[-73.44051399999999,40.713348],"type":"Point"}
}