{
  "type": "Feature",
  "properties": {
    "addr:full":"1068 Elmwood Ave Buffalo NY 14222",
    "addr:housenumber":"1068",
    "addr:postcode":"14222",
    "addr:street":"Elmwood Ave",
    "iso:country":"US",
    "sg:address":"1068 Elmwood Ave",
    "sg:city":"Buffalo",
    "sg:classifiers":[
        {
            "category":"Real Estate",
            "subcategory":"Surveying",
            "type":"Services"
        }
    ],
    "sg:phone":"+1 716 881 0707",
    "sg:postcode":"14222",
    "sg:province":"NY",
    "sg:tags":[
        "planning",
        "land"
    ],
    "wof:name":"Elmwood Village Association, T",
    "wof:placetype":"venue"
},
  "geometry": {"coordinates":[-78.87703,42.926131],"type":"Point"}
}