{
  "type": "Feature",
  "properties": {
    "addr:full":"5959 Sheridan Dr Buffalo NY 14221",
    "addr:housenumber":"5959",
    "addr:postcode":"14221",
    "addr:street":"Sheridan Dr",
    "iso:country":"US",
    "sg:address":"5959 Sheridan Dr",
    "sg:city":"Buffalo",
    "sg:classifiers":[
        {
            "category":"Recreation",
            "type":"Entertainment"
        }
    ],
    "sg:phone":"+1 716 632 8600",
    "sg:postcode":"14221",
    "sg:province":"NY",
    "sg:tags":[
        "club",
        "membership",
        "tennis",
        "court"
    ],
    "wof:name":"Amherst Hills Tennis Club",
    "wof:placetype":"venue"
},
  "geometry": {"coordinates":[-78.710707,42.97785],"type":"Point"}
}