{
  "type": "Feature",
  "properties": {
    "addr:full":"620 Fulton Ave Hempstead NY 11550",
    "addr:housenumber":"620",
    "addr:postcode":"11550",
    "addr:street":"Fulton Ave",
    "iso:country":"US",
    "sg:address":"620 Fulton Ave",
    "sg:city":"Hempstead",
    "sg:classifiers":[
        {
            "category":"Retail",
            "subcategory":"Laundry & Dry Cleaning",
            "type":"Services"
        }
    ],
    "sg:phone":"+1   ",
    "sg:postcode":"11550",
    "sg:province":"NY",
    "sg:tags":[
        "power"
    ],
    "wof:name":"A & B Laundromat",
    "wof:placetype":"venue"
},
  "geometry": {"coordinates":[-73.609956,40.711886],"type":"Point"}
}