{
  "type": "Feature",
  "properties": {
    "iso:country":"US",
    "sg:address":"3140 Downing Street",
    "sg:city":"Flushing",
    "sg:classifiers":[
        {
            "category":"Shopping",
            "subcategory":"Beauty & Cosmetics",
            "type":"Retail Goods"
        }
    ],
    "sg:phone":"+1 718 445 7676",
    "sg:postcode":"11354",
    "sg:province":"NY",
    "sg:tags":[
        "supply"
    ],
    "sg:website":"www.interfashionusa.com",
    "wof:name":"Interfashion USA",
    "wof:placetype":"venue"
},
  "geometry": {"coordinates":[-73.835994,40.768536],"type":"Point"}
}