{
  "type": "Feature",
  "properties": {
    "addr:full":"230 E 25 St New York NY 10010",
    "addr:housenumber":"230;25",
    "addr:postcode":"10010",
    "addr:street":"E;St",
    "iso:country":"US",
    "sg:address":"230 E 25 St",
    "sg:city":"New York",
    "sg:classifiers":[
        {
            "category":"Retail",
            "subcategory":"Laundry & Dry Cleaning",
            "type":"Services"
        }
    ],
    "sg:phone":"+1   ",
    "sg:postcode":"10010",
    "sg:province":"NY",
    "sg:tags":[
        "garment",
        "agent"
    ],
    "wof:name":"Barrys Cleaner",
    "wof:placetype":"venue"
},
  "geometry": {"coordinates":[-73.980524,40.739392],"type":"Point"}
}