{
  "type": "Feature",
  "properties": {
    "addr:full":"26 Watersida Plaza New York NY 10010",
    "addr:housenumber":"26",
    "addr:postcode":"10010",
    "addr:street":"Watersida Plaza",
    "iso:country":"US",
    "sg:address":"26 Watersida Plaza",
    "sg:city":"New York",
    "sg:classifiers":[
        {
            "category":"Autos & Motor Vehicles",
            "subcategory":"Automobile Sales",
            "type":"Retail Goods"
        }
    ],
    "sg:phone":"+1 718 258 8600",
    "sg:postcode":"10010",
    "sg:province":"NY",
    "sg:tags":[
        "limo"
    ],
    "sg:website":"www.genesislimousine.com/",
    "wof:name":"Genesis Intl Limousine",
    "wof:placetype":"venue"
},
  "geometry": {"coordinates":[-73.973662,40.73697],"type":"Point"}
}