{
  "type": "Feature",
  "properties": {
    "iso:country":"US",
    "sg:address":"666 W End Ave",
    "sg:city":"New York",
    "sg:classifiers":[
        {
            "category":"Building & Trades",
            "subcategory":"Plumbing",
            "type":"Services"
        }
    ],
    "sg:phone":"+1 212 889 0668",
    "sg:postcode":"10025",
    "sg:province":"NY",
    "wof:name":"A ABC Genl Contractors Upper East Side",
    "wof:placetype":"venue"
},
  "geometry": {"coordinates":[-73.9748,40.792999],"type":"Point"}
}