{
  "type": "Feature",
  "properties": {
    "iso:country":"US",
    "sg:address":"50 Main St",
    "sg:city":"Westhampton Bch",
    "sg:classifiers":[
        {
            "category":"Building & Trades",
            "subcategory":"Construction",
            "type":"Services"
        }
    ],
    "sg:phone":"+1 631 288 9895",
    "sg:postcode":"11978",
    "sg:province":"NY",
    "sg:tags":[
        "restoration",
        "cleaning",
        "patio",
        "deck"
    ],
    "wof:name":"Magiclean House Washing",
    "wof:placetype":"venue"
},
  "geometry": {"coordinates":[-72.64502299999999,40.809003],"type":"Point"}
}