{
  "type": "Feature",
  "properties": {
    "iso:country":"US",
    "sg:address":"35 Main St",
    "sg:city":"Canton",
    "sg:classifiers":[
        {
            "category":"Bars & Pubs",
            "type":"Food & Drink"
        }
    ],
    "sg:phone":"+1   ",
    "sg:postcode":"13617",
    "sg:province":"NY",
    "sg:tags":[
        "drinking"
    ],
    "wof:name":"Daves 2",
    "wof:placetype":"venue"
},
  "geometry": {"coordinates":[-75.172253,44.595492],"type":"Point"}
}