{
  "type": "Feature",
  "properties": {
    "iso:country":"US",
    "sg:address":"2 Kisco Ave",
    "sg:city":"Mt Kisco",
    "sg:classifiers":[
        {
            "category":"Restaurant",
            "type":"Food & Drink"
        }
    ],
    "sg:phone":"+1 914 666 7445",
    "sg:postcode":"10549",
    "sg:province":"NY",
    "sg:website":"www.pigcafe.com",
    "wof:name":"Flying Pig Inc",
    "wof:placetype":"venue"
},
  "geometry": {"coordinates":[-73.72887799999999,41.210177],"type":"Point"}
}