{
  "type": "Feature",
  "properties": {
    "addr:full":"48 Parkville Ave Brooklyn NY 11230",
    "addr:housenumber":"48",
    "addr:postcode":"11230",
    "addr:street":"Parkville Ave",
    "iso:country":"US",
    "sg:address":"48 Parkville Ave",
    "sg:city":"Brooklyn",
    "sg:classifiers":[
        {
            "category":"Professional",
            "subcategory":"Business Services",
            "type":"Services"
        }
    ],
    "sg:phone":"+1 917 892 0377",
    "sg:postcode":"11230",
    "sg:province":"NY",
    "wof:name":"David Sebbag Company",
    "wof:placetype":"venue"
},
  "geometry": {"coordinates":[-73.97505700000001,40.628968],"type":"Point"}
}