{
  "type": "Feature",
  "properties": {
    "addr:full":"10 N 11th St Wyandanch NY 11798",
    "addr:housenumber":"10",
    "addr:postcode":"11798",
    "addr:street":"N 11Th St",
    "iso:country":"US",
    "sg:address":"10 N 11th St",
    "sg:city":"Wyandanch",
    "sg:classifiers":[
        {
            "category":"Building & Trades",
            "subcategory":"Construction",
            "type":"Services"
        }
    ],
    "sg:phone":"+1 631 643 0310",
    "sg:postcode":"11798",
    "sg:province":"NY",
    "sg:tags":[
        "house"
    ],
    "wof:name":"Dawson Home Improvement Contg",
    "wof:placetype":"venue"
},
  "geometry": {"coordinates":[-73.359489,40.759134],"type":"Point"}
}