{
  "type": "Feature",
  "properties": {
    "addr:full":"189 E 3rd St New York NY 10009",
    "addr:housenumber":"189",
    "addr:postcode":"10009",
    "addr:street":"E 3Rd St",
    "iso:country":"US",
    "sg:address":"189 E 3rd St",
    "sg:city":"New York",
    "sg:classifiers":[
        {
            "category":"Bars & Pubs",
            "subcategory":"Lounge",
            "type":"Food & Drink"
        }
    ],
    "sg:menulink":"http://www.allmenus.com/ny/new-york/251967-le-caire-mediterranean-lounge/menu/",
    "sg:phone":"+1 212 777 7447",
    "sg:postcode":"10009",
    "sg:province":"NY",
    "sg:tags":[
        "mediterranean"
    ],
    "wof:name":"Le Caire Mediterranean Lounge",
    "wof:placetype":"venue"
},
  "geometry": {"coordinates":[-73.98351599999999,40.723134],"type":"Point"}
}