{
  "type": "Feature",
  "properties": {
    "iso:country":"US",
    "sg:address":"3137 Cedarvale Rd",
    "sg:city":"Nedrow",
    "sg:classifiers":[
        {
            "category":"Building & Trades",
            "subcategory":"Equipment Rental",
            "type":"Services"
        }
    ],
    "sg:phone":"+1   ",
    "sg:postcode":"13120",
    "sg:province":"NY",
    "wof:name":"Earth Quake Audio",
    "wof:placetype":"venue"
},
  "geometry": {"coordinates":[-76.21368699999999,42.930292],"type":"Point"}
}