{
  "type": "Feature",
  "properties": {
    "iso:country":"US",
    "sg:address":"36 Bridge St",
    "sg:city":"Slingerlands",
    "sg:classifiers":[
        {
            "category":"Professional",
            "subcategory":"Computer Services",
            "type":"Services"
        }
    ],
    "sg:phone":"+1   ",
    "sg:postcode":"12159",
    "sg:province":"NY",
    "sg:tags":[
        "programing",
        "custom"
    ],
    "wof:name":"Ux Computing Inc",
    "wof:placetype":"venue"
},
  "geometry": {"coordinates":[-73.85793700000001,42.628313],"type":"Point"}
}