{
  "type": "Feature",
  "properties": {
    "addr:full":"534 Delaware Ave Buffalo NY 14202",
    "addr:housenumber":"534",
    "addr:postcode":"14202",
    "addr:street":"Delaware Ave",
    "iso:country":"US",
    "sg:address":"534 Delaware Ave",
    "sg:city":"Buffalo",
    "sg:classifiers":[
        {
            "category":"Professional",
            "subcategory":"Lawyer & Legal Services",
            "type":"Services"
        }
    ],
    "sg:phone":"+1 716 332 7193",
    "sg:postcode":"14202",
    "sg:province":"NY",
    "wof:name":"O'Connor Gail R atty",
    "wof:placetype":"venue"
},
  "geometry": {"coordinates":[-78.87428199999999,42.898942],"type":"Point"}
}