{
  "type": "Feature",
  "properties": {
    "addr:full":"3 E 44th St New York NY 10017",
    "addr:housenumber":"3",
    "addr:postcode":"10017",
    "addr:street":"E 44Th St",
    "iso:country":"US",
    "sg:address":"3 E 44th St",
    "sg:city":"New York",
    "sg:classifiers":[
        {
            "category":"Health Services",
            "subcategory":"Chiropractor",
            "type":"Services"
        }
    ],
    "sg:phone":"+1 212 867 7477",
    "sg:postcode":"10017",
    "sg:province":"NY",
    "wof:name":"Maryanne Shiozawa Dc PC",
    "wof:placetype":"venue"
},
  "geometry": {"coordinates":[-73.978376,40.754211],"type":"Point"}
}