{
  "type": "Feature",
  "properties": {
    "addr:full":"875 Eggert Dr North Tonawanda NY 14120",
    "addr:housenumber":"875",
    "addr:postcode":"14120",
    "addr:street":"Eggert Dr",
    "iso:country":"US",
    "sg:address":"875 Eggert Dr",
    "sg:city":"North Tonawanda",
    "sg:classifiers":[
        {
            "category":"Organizations",
            "subcategory":"Religious Organization",
            "type":"Services"
        }
    ],
    "sg:phone":"+1 716 692 6862",
    "sg:postcode":"14120",
    "sg:province":"NY",
    "wof:name":"St Matthew Luthern Church",
    "wof:placetype":"venue"
},
  "geometry": {"coordinates":[-78.868202,43.047473],"type":"Point"}
}