{
  "type": "Feature",
  "properties": {
    "iso:country":"US",
    "sg:address":"753 Waterman Dr",
    "sg:city":"Watertown",
    "sg:classifiers":[
        {
            "category":"Government",
            "subcategory":"Office",
            "type":"Public Place"
        }
    ],
    "sg:phone":"+1 315 788 1441",
    "sg:postcode":"13601",
    "sg:province":"NY",
    "sg:tags":[
        "executive"
    ],
    "wof:name":"County of Jefferson",
    "wof:placetype":"venue"
},
  "geometry": {"coordinates":[-75.93013999999999,43.973292],"type":"Point"}
}