{
  "type": "Feature",
  "properties": {
    "iso:country":"US",
    "sg:address":"133 Lyndhurst Rd",
    "sg:city":"Buffalo",
    "sg:classifiers":[
        {
            "category":"Building & Trades",
            "subcategory":"Construction",
            "type":"Services"
        }
    ],
    "sg:phone":"+1 716 632 8104",
    "sg:postcode":"14221",
    "sg:province":"NY",
    "sg:tags":[
        "hanging",
        "contractor"
    ],
    "wof:name":"Ryan Painting & Decorat",
    "wof:placetype":"venue"
},
  "geometry": {"coordinates":[-78.728543,42.962416],"type":"Point"}
}