{
  "type": "Feature",
  "properties": {
    "iso:country":"US",
    "sg:address":"13817 90th Ave",
    "sg:city":"Jamaica",
    "sg:classifiers":[
        {
            "category":"Retail",
            "subcategory":"Auto Repair",
            "type":"Services"
        }
    ],
    "sg:phone":"+1 718 298 6320",
    "sg:postcode":"11435",
    "sg:province":"NY",
    "sg:tags":[
        "recap",
        "retread",
        "tire"
    ],
    "wof:name":"Joanies Flat Fix",
    "wof:placetype":"venue"
},
  "geometry": {"coordinates":[-73.80728499999999,40.703201],"type":"Point"}
}