{
  "type": "Feature",
  "properties": {
    "addr:full":"126 W 55th St New York NY 10019",
    "addr:housenumber":"126",
    "addr:postcode":"10019",
    "addr:street":"W 55Th St",
    "iso:country":"US",
    "sg:address":"126 W 55th St",
    "sg:city":"New York",
    "sg:classifiers":[
        {
            "category":"Retail",
            "subcategory":"Auto Rental",
            "type":"Services"
        }
    ],
    "sg:phone":"+1 212 486 5925",
    "sg:postcode":"10019",
    "sg:province":"NY",
    "sg:tags":[
        "car"
    ],
    "sg:website":"www.hertz.com",
    "wof:name":"Hertz Rental Car",
    "wof:placetype":"venue"
},
  "geometry": {"coordinates":[-73.979052,40.763431],"type":"Point"}
}