{
  "type": "Feature",
  "properties": {
    "addr:full":"45 Orchard Beach Blvd Port Washington NY 11050",
    "addr:housenumber":"45",
    "addr:postcode":"11050",
    "addr:street":"Orchard Beach Blvd",
    "iso:country":"US",
    "sg:address":"45 Orchard Beach Blvd",
    "sg:city":"Port Washington",
    "sg:classifiers":[
        {
            "category":"Restaurant",
            "type":"Food & Drink"
        }
    ],
    "sg:menulink":"http://www.allmenus.com/ny/port-washington/37161-di-maggios/menu/",
    "sg:phone":"+1 516 944 5900",
    "sg:postcode":"11050",
    "sg:province":"NY",
    "sg:tags":[
        "seafood",
        "american"
    ],
    "wof:name":"Di Maggio's",
    "wof:placetype":"venue"
},
  "geometry": {"coordinates":[-73.719041,40.838119],"type":"Point"}
}