{
  "type": "Feature",
  "properties": {
    "iso:country":"US",
    "sg:address":"606 W 29th St",
    "sg:city":"New York",
    "sg:classifiers":[
        {
            "category":"Retail",
            "subcategory":"Auto Repair",
            "type":"Services"
        }
    ],
    "sg:phone":"+1 646 237 9382",
    "sg:postcode":"10001",
    "sg:province":"NY",
    "sg:tags":[
        "wrecker"
    ],
    "wof:name":"Emergency Anytime Towing",
    "wof:placetype":"venue"
},
  "geometry": {"coordinates":[-74.00711800000001,40.753732],"type":"Point"}
}