{
  "type": "Feature",
  "properties": {
    "addr:full":"310 Giffords Ln Staten Island NY 10308",
    "addr:housenumber":"310",
    "addr:postcode":"10308",
    "addr:street":"Giffords Ln",
    "iso:country":"US",
    "sg:address":"310 Giffords Ln",
    "sg:city":"Staten Island",
    "sg:classifiers":[
        {
            "category":"Real Estate",
            "subcategory":"Real Estate Operator",
            "type":"Services"
        }
    ],
    "sg:phone":"+1 718 984 9544",
    "sg:postcode":"10308",
    "sg:province":"NY",
    "sg:tags":[
        "building",
        "apartment"
    ],
    "wof:name":"Sac Enterprises Inc",
    "wof:placetype":"venue"
},
  "geometry": {"coordinates":[-74.153879,40.559016],"type":"Point"}
}