{
  "type": "Feature",
  "properties": {
    "iso:country":"US",
    "sg:address":"76 3rd Ave",
    "sg:city":"New York",
    "sg:classifiers":[
        {
            "category":"Restaurant",
            "type":"Food & Drink"
        }
    ],
    "sg:phone":"+1 212 505 1668",
    "sg:postcode":"10003",
    "sg:province":"NY",
    "sg:tags":[
        "chinese"
    ],
    "sg:website":"www.yummyhouse.com",
    "wof:name":"Yummy House",
    "wof:placetype":"venue"
},
  "geometry": {"coordinates":[-73.988342,40.731756],"type":"Point"}
}