{
  "type": "Feature",
  "properties": {
    "iso:country":"US",
    "sg:address":"31 Taylor Ave",
    "sg:city":"Greenlawn",
    "sg:classifiers":[
        {
            "category":"Building & Trades",
            "subcategory":"Cleaning & Sanitation",
            "type":"Services"
        }
    ],
    "sg:phone":"+1 631 261 1327",
    "sg:postcode":"11740",
    "sg:province":"NY",
    "sg:tags":[
        "fireplace",
        "chimney"
    ],
    "wof:name":"North Shore Chimney Sweeps",
    "wof:placetype":"venue"
},
  "geometry": {"coordinates":[-73.35910800000001,40.871057],"type":"Point"}
}