{
  "type": "Feature",
  "properties": {
    "iso:country":"US",
    "sg:address":"2208 Sunrise Hwy",
    "sg:city":"Merrick",
    "sg:classifiers":[
        {
            "category":"Home & Garden",
            "subcategory":"Household Appliances",
            "type":"Retail Goods"
        }
    ],
    "sg:phone":"+1 516 378 9694",
    "sg:postcode":"11566",
    "sg:province":"NY",
    "sg:website":"www.dialabrand.com",
    "wof:name":"Dial A Brand Inc",
    "wof:placetype":"venue"
},
  "geometry": {"coordinates":[-73.545675,40.664446],"type":"Point"}
}