{
  "type": "Feature",
  "properties": {
    "addr:full":"688 Old Medford Ave Medford NY 11763",
    "addr:housenumber":"688",
    "addr:postcode":"11763",
    "addr:street":"Old Medford Ave",
    "iso:country":"US",
    "sg:address":"688 Old Medford Ave",
    "sg:city":"Medford",
    "sg:classifiers":[
        {
            "category":"Building & Trades",
            "subcategory":"Construction",
            "type":"Services"
        }
    ],
    "sg:phone":"+1 631 289 7234",
    "sg:postcode":"11763",
    "sg:province":"NY",
    "sg:tags":[
        "residential"
    ],
    "wof:name":"LGC Contracting",
    "wof:placetype":"venue"
},
  "geometry": {"coordinates":[-73.010137,40.79466],"type":"Point"}
}