{
  "type": "Feature",
  "properties": {
    "addr:full":"120 Macdougal St New York NY 10012",
    "addr:housenumber":"120",
    "addr:postcode":"10012",
    "addr:street":"Macdougal St",
    "iso:country":"US",
    "sg:address":"120 Macdougal St",
    "sg:city":"New York",
    "sg:classifiers":[
        {
            "category":"Restaurant",
            "type":"Food & Drink"
        }
    ],
    "sg:menulink":"http://www.allmenus.com/ny/new-york/2297-bombay-kitchen/menu/",
    "sg:phone":"+1 212 228 3164",
    "sg:postcode":"10012",
    "sg:province":"NY",
    "sg:tags":[
        "indian",
        "asian"
    ],
    "wof:name":"Bombay Kitchen",
    "wof:placetype":"venue"
},
  "geometry": {"coordinates":[-74.00035800000001,40.729789],"type":"Point"}
}