{
  "type": "Feature",
  "properties": {
    "iso:country":"US",
    "sg:address":"217 Ridge Rd W",
    "sg:city":"Rochester",
    "sg:classifiers":[
        {
            "category":"Shopping",
            "subcategory":"Florist",
            "type":"Retail Goods"
        }
    ],
    "sg:phone":"+1 585 254 8055",
    "sg:postcode":"14615",
    "sg:province":"NY",
    "wof:name":"Fabulous Flowers & Gift Basket",
    "wof:placetype":"venue"
},
  "geometry": {"coordinates":[-77.634704,43.198252],"type":"Point"}
}