{
  "type": "Feature",
  "properties": {
    "iso:country":"US",
    "sg:address":"100 E Main St",
    "sg:city":"Cambridge",
    "sg:classifiers":[
        {
            "category":"Health Services",
            "subcategory":"Health Practitioner",
            "type":"Services"
        }
    ],
    "sg:phone":"+1 518 677 8346",
    "sg:postcode":"12816",
    "sg:province":"NY",
    "sg:tags":[
        "psychologist"
    ],
    "wof:name":"Main Street Counseling",
    "wof:placetype":"venue"
},
  "geometry": {"coordinates":[-73.369366,43.026994],"type":"Point"}
}