{
  "type": "Feature",
  "properties": {
    "addr:full":"4517 13th Ave Brooklyn NY 11219",
    "addr:housenumber":"4517",
    "addr:postcode":"11219",
    "addr:street":"13Th Ave",
    "iso:country":"US",
    "sg:address":"4517 13th Ave",
    "sg:city":"Brooklyn",
    "sg:classifiers":[
        {
            "category":"Shopping",
            "subcategory":"Clothing, Apparel, & Fashions",
            "type":"Retail Goods"
        }
    ],
    "sg:phone":"+1   ",
    "sg:postcode":"11219",
    "sg:province":"NY",
    "wof:name":"Beauty Fashion Wigs",
    "wof:placetype":"venue"
},
  "geometry": {"coordinates":[-73.990241,40.63675],"type":"Point"}
}