{
  "type": "Feature",
  "properties": {
    "addr:full":"119 N Ocean Ave Patchogue NY 11772",
    "addr:housenumber":"119",
    "addr:postcode":"11772",
    "addr:street":"N Ocean Ave",
    "iso:country":"US",
    "sg:address":"119 N Ocean Ave",
    "sg:city":"Patchogue",
    "sg:classifiers":[
        {
            "category":"Shopping",
            "type":"Retail Goods"
        }
    ],
    "sg:phone":"+1   ",
    "sg:postcode":"11772",
    "sg:province":"NY",
    "sg:tags":[
        "aids",
        "hearing"
    ],
    "wof:name":"Audio Center Hearing Aids",
    "wof:placetype":"venue"
},
  "geometry": {"coordinates":[-73.01500299999999,40.768029],"type":"Point"}
}