{
  "type": "Feature",
  "properties": {
    "addr:full":"12 Asthalter Rd Liberty NY 12754",
    "addr:housenumber":"12",
    "addr:postcode":"12754",
    "addr:street":"Asthalter Rd",
    "iso:country":"US",
    "sg:address":"12 Asthalter Rd",
    "sg:city":"Liberty",
    "sg:classifiers":[
        {
            "category":"Building & Trades",
            "subcategory":"Construction",
            "type":"Services"
        }
    ],
    "sg:phone":"+1 845 292 4611",
    "sg:postcode":"12754",
    "sg:province":"NY",
    "sg:tags":[
        "steel",
        "erection",
        "metal",
        "fabrication",
        "structural"
    ],
    "wof:name":"Liberty Iron Works",
    "wof:placetype":"venue"
},
  "geometry": {"coordinates":[-74.73351099999999,41.804522],"type":"Point"}
}