{
  "type": "Feature",
  "properties": {
    "iso:country":"US",
    "sg:address":"1457 E 87th St",
    "sg:city":"Brooklyn",
    "sg:classifiers":[
        {
            "category":"Building & Trades",
            "subcategory":"Locksmith",
            "type":"Services"
        }
    ],
    "sg:phone":"+1 718 773 8369",
    "sg:postcode":"11236",
    "sg:province":"NY",
    "sg:tags":[
        "key"
    ],
    "wof:name":"Emmons Alan",
    "wof:placetype":"venue"
},
  "geometry": {"coordinates":[-73.89846900000001,40.630335],"type":"Point"}
}