{
  "type": "Feature",
  "properties": {
    "iso:country":"US",
    "sg:address":"127 Bayberry Ln",
    "sg:city":"Rochester",
    "sg:classifiers":[
        {
            "category":"Building & Trades",
            "subcategory":"Construction",
            "type":"Services"
        }
    ],
    "sg:phone":"+1 585 865 8679",
    "sg:postcode":"14616",
    "sg:province":"NY",
    "sg:tags":[
        "contractor"
    ],
    "wof:name":"Delgado Tile & Marble",
    "wof:placetype":"venue"
},
  "geometry": {"coordinates":[-77.641738,43.22843],"type":"Point"}
}