{
  "type": "Feature",
  "properties": {
    "addr:full":"1278 72nd St Brooklyn NY 11228",
    "addr:housenumber":"1278",
    "addr:postcode":"11228",
    "addr:street":"72Nd St",
    "iso:country":"US",
    "sg:address":"1278 72nd St",
    "sg:city":"Brooklyn",
    "sg:classifiers":[
        {
            "category":"Health Services",
            "subcategory":"Dentist",
            "type":"Services"
        }
    ],
    "sg:phone":"+1 718 680 4100",
    "sg:postcode":"11228",
    "sg:province":"NY",
    "wof:name":"De Santo Frank X DMD",
    "wof:placetype":"venue"
},
  "geometry": {"coordinates":[-74.005898,40.622002],"type":"Point"}
}