{
  "type": "Feature",
  "properties": {
    "addr:full":"127 Rutledge St Brooklyn NY 11211",
    "addr:housenumber":"127",
    "addr:postcode":"11211",
    "addr:street":"Rutledge St",
    "iso:country":"US",
    "sg:address":"127 Rutledge St",
    "sg:city":"Brooklyn",
    "sg:classifiers":[
        {
            "category":"Real Estate",
            "subcategory":"Real Estate Agent",
            "type":"Services"
        }
    ],
    "sg:phone":"+1 718 243 2889",
    "sg:postcode":"11211",
    "sg:province":"NY",
    "sg:tags":[
        "management"
    ],
    "wof:name":"Plaza Management U S A Inc",
    "wof:placetype":"venue"
},
  "geometry": {"coordinates":[-73.956564,40.702428],"type":"Point"}
}