{
  "type": "Feature",
  "properties": {
    "iso:country":"US",
    "sg:address":"4790 Black Oak Dr",
    "sg:city":"Liverpool",
    "sg:classifiers":[
        {
            "category":"Manufacturing",
            "subcategory":"Toys & Sporting Goods",
            "type":"Manufacturing & Wholesale Goods"
        }
    ],
    "sg:phone":"+1   ",
    "sg:postcode":"13088",
    "sg:province":"NY",
    "sg:tags":[
        "mfg"
    ],
    "wof:name":"Vintage Wraps",
    "wof:placetype":"venue"
},
  "geometry": {"coordinates":[-76.185997,43.133549],"type":"Point"}
}