{
  "type": "Feature",
  "properties": {
    "iso:country":"US",
    "sg:address":"537 E 137th Street",
    "sg:city":"Bronx",
    "sg:classifiers":[
        {
            "category":"Restaurant",
            "type":"Food & Drink"
        }
    ],
    "sg:phone":"+1 718 665 3372",
    "sg:postcode":"10454",
    "sg:province":"NY",
    "wof:name":"Chinatown Express Restaurant",
    "wof:placetype":"venue"
},
  "geometry": {"coordinates":[-73.91831000000001,40.806394],"type":"Point"}
}