{
  "type": "Feature",
  "properties": {
    "addr:full":"309 Rutland Rd Brooklyn NY 11225",
    "addr:housenumber":"309",
    "addr:postcode":"11225",
    "addr:street":"Rutland Rd",
    "iso:country":"US",
    "sg:address":"309 Rutland Rd",
    "sg:city":"Brooklyn",
    "sg:classifiers":[
        {
            "category":"Shopping",
            "subcategory":"Hobbies, Toys, & Games",
            "type":"Retail Goods"
        }
    ],
    "sg:phone":"+1   ",
    "sg:postcode":"11225",
    "sg:province":"NY",
    "wof:name":"Expression In Ceramics",
    "wof:placetype":"venue"
},
  "geometry": {"coordinates":[-73.947793,40.659645],"type":"Point"}
}