{
  "type": "Feature",
  "properties": {
    "iso:country":"US",
    "sg:address":"395 Woodcleft Ave",
    "sg:city":"Freeport",
    "sg:classifiers":[
        {
            "category":"Professional",
            "subcategory":"Management & Consulting",
            "type":"Services"
        },
        {
            "category":"Communications",
            "type":"Services"
        }
    ],
    "sg:phone":"+1 516 998 4955",
    "sg:postcode":"11520",
    "sg:province":"NY",
    "sg:tags":[
        "science",
        "consultant",
        "academic"
    ],
    "wof:name":"Infinity Communications Consultants",
    "wof:placetype":"venue"
},
  "geometry": {"coordinates":[-73.581108,40.629017],"type":"Point"}
}