{
  "type": "Feature",
  "properties": {
    "iso:country":"US",
    "sg:address":"1431 Rockaway Pkwy",
    "sg:city":"Brooklyn",
    "sg:classifiers":[
        {
            "category":"Food & Beverages",
            "subcategory":"Groceries & Convenience Stores",
            "type":"Retail Goods"
        }
    ],
    "sg:phone":"+1   ",
    "sg:postcode":"11236",
    "sg:province":"NY",
    "wof:name":"A & Y Candy & Grocery",
    "wof:placetype":"venue"
},
  "geometry": {"coordinates":[-73.90138,40.644297],"type":"Point"}
}