{
  "type": "Feature",
  "properties": {
    "addr:full":"110 Wartburg Dr Copiague NY 11754",
    "addr:housenumber":"110",
    "addr:postcode":"11754",
    "addr:street":"Wartburg Dr",
    "iso:country":"US",
    "sg:address":"110 Wartburg Dr",
    "sg:city":"Copiague",
    "sg:classifiers":[
        {
            "category":"Building & Trades",
            "subcategory":"Construction",
            "type":"Services"
        }
    ],
    "sg:phone":"+1 631 842 1119",
    "sg:postcode":"11754",
    "sg:province":"NY",
    "sg:tags":[
        "maker",
        "cabinet"
    ],
    "wof:name":"Longo Commercial Cbnts",
    "wof:placetype":"venue"
},
  "geometry": {"coordinates":[-73.260249,40.879224],"type":"Point"}
}