{
  "type": "Feature",
  "properties": {
    "addr:full":"108 Franklin Pl Woodmere NY 11598",
    "addr:housenumber":"108",
    "addr:postcode":"11598",
    "addr:street":"Franklin Pl",
    "iso:country":"US",
    "sg:address":"108 Franklin Pl",
    "sg:city":"Woodmere",
    "sg:classifiers":[
        {
            "category":"Utilities",
            "subcategory":"Telephone",
            "type":"Services"
        }
    ],
    "sg:phone":"+1   ",
    "sg:postcode":"11598",
    "sg:province":"NY",
    "sg:tags":[
        "communications"
    ],
    "wof:name":"Nynex Voice Messaging Service",
    "wof:placetype":"venue"
},
  "geometry": {"coordinates":[-73.708333,40.632935],"type":"Point"}
}