{
  "type": "Feature",
  "properties": {
    "iso:country":"US",
    "sg:address":"4401 Victory Blvd",
    "sg:city":"Staten Island",
    "sg:classifiers":[
        {
            "category":"Utilities",
            "subcategory":"Electric",
            "type":"Services"
        }
    ],
    "sg:phone":"+1   ",
    "sg:postcode":"10314",
    "sg:province":"NY",
    "wof:name":"NRG Energy Inc",
    "wof:placetype":"venue"
},
  "geometry": {"coordinates":[-74.198928,40.587085],"type":"Point"}
}