{
  "type": "Feature",
  "properties": {
    "addr:full":"186 W 134th St #1 Manhattan NY 10030",
    "addr:housenumber":"186",
    "addr:postcode":"10030",
    "addr:street":"W 134Th St # 1",
    "iso:country":"US",
    "sg:address":"186 W 134th St #1",
    "sg:city":"Manhattan",
    "sg:classifiers":[
        {
            "category":"Shopping",
            "subcategory":"Bicycles & Sporting Goods",
            "type":"Retail Goods"
        }
    ],
    "sg:phone":"+1 888 600 1248",
    "sg:postcode":"10030",
    "sg:province":"NY",
    "sg:tags":[
        "bike"
    ],
    "wof:name":"Bike Doctor NYC",
    "wof:placetype":"venue"
},
  "geometry": {"coordinates":[-73.943541,40.814099],"type":"Point"}
}