{
  "type": "Feature",
  "properties": {
    "addr:full":"33 W 125th Street New York NY 10027",
    "addr:housenumber":"33",
    "addr:postcode":"10027",
    "addr:street":"W 125Th Street",
    "iso:country":"US",
    "sg:address":"33 W 125th Street",
    "sg:city":"New York",
    "sg:classifiers":[
        {
            "category":"Health Services",
            "subcategory":"Dentist",
            "type":"Services"
        }
    ],
    "sg:phone":"+1 212 289 9539",
    "sg:postcode":"10027",
    "sg:province":"NY",
    "wof:name":"Posovsky Stephen DDS",
    "wof:placetype":"venue"
},
  "geometry": {"coordinates":[-73.943533,40.806825],"type":"Point"}
}