{
  "type": "Feature",
  "properties": {
    "iso:country":"US",
    "sg:address":"182 Martine Ave",
    "sg:city":"White Plains",
    "sg:classifiers":[
        {
            "category":"Shopping",
            "subcategory":"Luggage & Leather Goods",
            "type":"Retail Goods"
        }
    ],
    "sg:phone":"+1   ",
    "sg:postcode":"10601",
    "sg:province":"NY",
    "wof:name":"Lins Luggage",
    "wof:placetype":"venue"
},
  "geometry": {"coordinates":[-73.76710199999999,41.031116],"type":"Point"}
}