{
  "type": "Feature",
  "properties": {
    "iso:country":"US",
    "sg:address":"1880 Clinton St",
    "sg:city":"Buffalo",
    "sg:classifiers":[
        {
            "category":"Food & Beverages",
            "subcategory":"Groceries & Convenience Stores",
            "type":"Retail Goods"
        }
    ],
    "sg:phone":"+1 716 828 1160",
    "sg:postcode":"14206",
    "sg:province":"NY",
    "sg:tags":[
        "grocer"
    ],
    "wof:name":"Clinton Main Market",
    "wof:placetype":"venue"
},
  "geometry": {"coordinates":[-78.807198,42.8717],"type":"Point"}
}