{
  "type": "Feature",
  "properties": {
    "addr:full":"282 Hempstead Tpke West Hempstead NY 11552",
    "addr:housenumber":"282",
    "addr:postcode":"11552",
    "addr:street":"Hempstead Tpke West",
    "iso:country":"US",
    "sg:address":"282 Hempstead Tpke",
    "sg:city":"West Hempstead",
    "sg:classifiers":[
        {
            "category":"Food & Beverages",
            "subcategory":"Groceries & Convenience Stores",
            "type":"Retail Goods"
        }
    ],
    "sg:phone":"+1 516 538 5139",
    "sg:postcode":"11552",
    "sg:province":"NY",
    "wof:name":"El Salvador Deli",
    "wof:placetype":"venue"
},
  "geometry": {"coordinates":[-73.64875600000001,40.705187],"type":"Point"}
}