{
  "type": "Feature",
  "properties": {
    "addr:full":"2692 Dewey Ave Rochester NY 14616",
    "addr:housenumber":"2692",
    "addr:postcode":"14616",
    "addr:street":"Dewey Ave",
    "iso:country":"US",
    "sg:address":"2692 Dewey Ave",
    "sg:city":"Rochester",
    "sg:classifiers":[
        {
            "category":"Retail",
            "subcategory":"Funeral Services",
            "type":"Services"
        }
    ],
    "sg:phone":"+1 585 663 7000",
    "sg:postcode":"14616",
    "sg:province":"NY",
    "sg:tags":[
        "director"
    ],
    "wof:name":"Abbey Memorial Chapels",
    "wof:placetype":"venue"
},
  "geometry": {"coordinates":[-77.64121400000001,43.218691],"type":"Point"}
}