{
  "type": "Feature",
  "properties": {
    "iso:country":"US",
    "sg:address":"324 3rd St",
    "sg:city":"Youngstown",
    "sg:classifiers":[
        {
            "category":"Building & Trades",
            "subcategory":"Landscaping Services",
            "type":"Services"
        }
    ],
    "sg:phone":"+1 716 745 7911",
    "sg:postcode":"14174",
    "sg:province":"NY",
    "sg:tags":[
        "landscape",
        "contractor"
    ],
    "wof:name":"A Sunrise Services",
    "wof:placetype":"venue"
},
  "geometry": {"coordinates":[-79.046786,43.252582],"type":"Point"}
}