{
  "type": "Feature",
  "properties": {
    "addr:full":"2610 Riverfront Ctr Amsterdam NY 12010",
    "addr:housenumber":"2610",
    "addr:postcode":"12010",
    "addr:street":"Riverfront Ctr",
    "iso:country":"US",
    "sg:address":"2610 Riverfront Ctr",
    "sg:city":"Amsterdam",
    "sg:classifiers":[
        {
            "category":"Organizations",
            "subcategory":"Non-profit Organization",
            "type":"Services"
        }
    ],
    "sg:phone":"+1 518 627 0379",
    "sg:postcode":"12010",
    "sg:province":"NY",
    "sg:tags":[
        "charity",
        "foundations-educational",
        "philanthropic",
        "research"
    ],
    "wof:name":"Liberty Day Treatment",
    "wof:placetype":"venue"
},
  "geometry": {"coordinates":[-74.19048600000001,42.936993],"type":"Point"}
}