{
  "type": "Feature",
  "properties": {
    "iso:country":"US",
    "sg:address":"36 US Hwy 6",
    "sg:city":"Port Jervis",
    "sg:classifiers":[
        {
            "category":"Autos & Motor Vehicles",
            "subcategory":"Recreational Vehicle Sales",
            "type":"Retail Goods"
        }
    ],
    "sg:phone":"+1 845 856 9700",
    "sg:postcode":"12771",
    "sg:province":"NY",
    "wof:name":"84 Rv Rayewood Trailer Sales",
    "wof:placetype":"venue"
},
  "geometry": {"coordinates":[-74.694802,41.374062],"type":"Point"}
}