{
  "type": "Feature",
  "properties": {
    "addr:full":"1 Rockefeller Plz Ste 2223 New York NY 10020",
    "addr:housenumber":"1",
    "addr:postcode":"2223;10020",
    "addr:street":"Rockefeller Plz Ste",
    "iso:country":"US",
    "sg:address":"1 Rockefeller Plz Ste 2223",
    "sg:city":"New York",
    "sg:classifiers":[
        {
            "category":"Health Services",
            "subcategory":"Dentist",
            "type":"Services"
        }
    ],
    "sg:phone":"+1 212 581 2442",
    "sg:postcode":"10020",
    "sg:province":"NY",
    "sg:website":"www.llmdental.com/",
    "wof:name":"LLM Dental Associates, PC",
    "wof:placetype":"venue"
},
  "geometry": {"coordinates":[-73.97864800000001,40.758713],"type":"Point"}
}