{
  "type": "Feature",
  "properties": {
    "iso:country":"US",
    "sg:address":"195 Madison St",
    "sg:city":"Cortland",
    "sg:classifiers":[
        {
            "category":"Local Transit",
            "type":"Transportation"
        }
    ],
    "sg:phone":"+1 607 753 9180",
    "sg:postcode":"13045",
    "sg:province":"NY",
    "sg:tags":[
        "limousine"
    ],
    "sg:website":"www.elslimo.com",
    "wof:name":"Executive Limo & Sedan",
    "wof:placetype":"venue"
},
  "geometry": {"coordinates":[-76.199561,42.603276],"type":"Point"}
}