{
  "type": "Feature",
  "properties": {
    "addr:full":"305 E 86th St Ofc Mgmt New York NY 10028",
    "addr:housenumber":"305",
    "addr:postcode":"10028",
    "addr:street":"E 86Th St",
    "iso:country":"US",
    "sg:address":"305 E 86th St Ofc Mgmt",
    "sg:city":"New York",
    "sg:classifiers":[
        {
            "category":"Real Estate",
            "subcategory":"Real Estate Services",
            "type":"Services"
        }
    ],
    "sg:phone":"+1 212 289 4259",
    "sg:postcode":"10028",
    "sg:province":"NY",
    "sg:tags":[
        "management",
        "property"
    ],
    "wof:name":"Yorkshire Towers",
    "wof:placetype":"venue"
},
  "geometry": {"coordinates":[-73.95155200000001,40.777965],"type":"Point"}
}