{
  "type": "Feature",
  "properties": {
    "addr:full":"84 New Dorp Plz Staten Island NY 10306",
    "addr:housenumber":"84",
    "addr:postcode":"10306",
    "addr:street":"New Dorp Plz",
    "iso:country":"US",
    "sg:address":"84 New Dorp Plz",
    "sg:city":"Staten Island",
    "sg:classifiers":[
        {
            "category":"Social Services",
            "type":"Services"
        }
    ],
    "sg:phone":"+1 718 987 6911",
    "sg:postcode":"10306",
    "sg:province":"NY",
    "sg:tags":[
        "organization",
        "welfare"
    ],
    "sg:website":"www.msdc.org",
    "wof:name":"American Foundation For Dsbld",
    "wof:placetype":"venue"
},
  "geometry": {"coordinates":[-74.118377,40.572384],"type":"Point"}
}