{
  "type": "Feature",
  "properties": {
    "iso:country":"US",
    "sg:address":"71-02 Myrtle Ave",
    "sg:city":"Queens",
    "sg:classifiers":[
        {
            "category":"Deli",
            "type":"Food & Drink"
        }
    ],
    "sg:phone":"+1 718 821 6364",
    "sg:postcode":"11385",
    "sg:province":"NY",
    "sg:website":"www.i8at.com/deli-licious",
    "wof:name":"DeliLicious Delicatessen",
    "wof:placetype":"venue"
},
  "geometry": {"coordinates":[-73.879795,40.701741],"type":"Point"}
}