{
  "type": "Feature",
  "properties": {
    "addr:full":"916 Ave T Brooklyn NY 11222",
    "addr:housenumber":"916",
    "addr:postcode":"11222",
    "addr:street":"Ave T",
    "iso:country":"US",
    "sg:address":"916 Ave T",
    "sg:city":"Brooklyn",
    "sg:classifiers":[
        {
            "category":"Shopping",
            "type":"Retail Goods"
        }
    ],
    "sg:phone":"+1 718 934 2033",
    "sg:postcode":"11222",
    "sg:province":"NY",
    "sg:website":"www.powersellernyc.com",
    "wof:name":"PowersellerNYC",
    "wof:placetype":"venue"
},
  "geometry": {"coordinates":[-73.96189800000001,40.600273],"type":"Point"}
}