{
  "type": "Feature",
  "properties": {
    "iso:country":"US",
    "sg:address":"377 Oak St",
    "sg:city":"Garden City",
    "sg:classifiers":[
        {
            "category":"Banks & Credit Unions",
            "subcategory":"Investment Brokerage",
            "type":"Services"
        }
    ],
    "sg:phone":"+1 516 222 1506",
    "sg:postcode":"11530",
    "sg:province":"NY",
    "sg:tags":[
        "security"
    ],
    "wof:name":"Tjm Investments LLC",
    "wof:placetype":"venue"
},
  "geometry": {"coordinates":[-73.608835,40.727307],"type":"Point"}
}