{
  "type": "Feature",
  "properties": {
    "iso:country":"US",
    "sg:address":"1217 Penora St",
    "sg:city":"Depew",
    "sg:classifiers":[
        {
            "category":"Banks & Credit Unions",
            "subcategory":"Investment Brokerage",
            "type":"Services"
        }
    ],
    "sg:phone":"+1 716 681 6536",
    "sg:postcode":"14043",
    "sg:province":"NY",
    "wof:name":"Everlong Capital Management",
    "wof:placetype":"venue"
},
  "geometry": {"coordinates":[-78.68771599999999,42.891063],"type":"Point"}
}