{
  "type": "Feature",
  "properties": {
    "iso:country":"US",
    "sg:address":"3 Holland Rd",
    "sg:city":"Monroe",
    "sg:classifiers":[
        {
            "category":"Manufacturing",
            "subcategory":"Motor Vehicles & Parts",
            "type":"Manufacturing & Wholesale Goods"
        }
    ],
    "sg:phone":"+1   ",
    "sg:postcode":"10950",
    "sg:province":"NY",
    "sg:tags":[
        "jacket",
        "imprinting",
        "clothing",
        "embroidery"
    ],
    "wof:name":"M J Associates",
    "wof:placetype":"venue"
},
  "geometry": {"coordinates":[-74.194996,41.30993],"type":"Point"}
}