{
  "type": "Feature",
  "properties": {
    "iso:country":"US",
    "sg:address":"728 Hillcrest Pl",
    "sg:city":"Valley Stream",
    "sg:classifiers":[
        {
            "category":"Professional",
            "subcategory":"Lawyer & Legal Services",
            "type":"Services"
        }
    ],
    "sg:phone":"+1   ",
    "sg:postcode":"11581",
    "sg:province":"NY",
    "wof:name":"Mark Virag",
    "wof:placetype":"venue"
},
  "geometry": {"coordinates":[-73.72825400000001,40.647176],"type":"Point"}
}