{
  "type": "Feature",
  "properties": {
    "iso:country":"US",
    "sg:address":"181 Oakside Dr",
    "sg:city":"Smithtown",
    "sg:classifiers":[
        {
            "category":"Wholesale",
            "subcategory":"Hardware",
            "type":"Manufacturing & Wholesale Goods"
        }
    ],
    "sg:phone":"+1   ",
    "sg:postcode":"11787",
    "sg:province":"NY",
    "sg:tags":[
        "mfg"
    ],
    "wof:name":"HVAC Filtration Specialists",
    "wof:placetype":"venue"
},
  "geometry": {"coordinates":[-73.208431,40.880429],"type":"Point"}
}