{
  "type": "Feature",
  "properties": {
    "addr:full":"8 Prospect Ave Garden City NY 11530",
    "addr:housenumber":"8",
    "addr:postcode":"11530",
    "addr:street":"Prospect Ave",
    "iso:country":"US",
    "sg:address":"8 Prospect Ave",
    "sg:city":"Garden City",
    "sg:classifiers":[
        {
            "category":"Health Services",
            "subcategory":"Doctor",
            "type":"Services"
        },
        {
            "category":"Health Services",
            "subcategory":"Clinic",
            "type":"Services"
        }
    ],
    "sg:phone":"+1 516 877 0807",
    "sg:postcode":"11530",
    "sg:province":"NY",
    "sg:tags":[
        "counseling",
        "mental"
    ],
    "wof:name":"Feindler Eva L PHD",
    "wof:placetype":"venue"
},
  "geometry": {"coordinates":[-73.62159699999999,40.7201],"type":"Point"}
}