{
  "type": "Feature",
  "properties": {
    "addr:full":"215 East Ave Lockport NY 14094",
    "addr:housenumber":"215",
    "addr:postcode":"14094",
    "addr:street":"East Ave",
    "iso:country":"US",
    "sg:address":"215 East Ave",
    "sg:city":"Lockport",
    "sg:classifiers":[
        {
            "category":"Health Services",
            "subcategory":"Optometrist",
            "type":"Services"
        }
    ],
    "sg:phone":"+1 716 434 2874",
    "sg:postcode":"14094",
    "sg:province":"NY",
    "sg:tags":[
        "medical"
    ],
    "wof:name":"East Avenue Vision Center",
    "wof:placetype":"venue"
},
  "geometry": {"coordinates":[-78.680723,43.1732],"type":"Point"}
}