{
  "type": "Feature",
  "properties": {
    "addr:full":"200 Davis Ave Waterford NY 12188",
    "addr:housenumber":"200",
    "addr:postcode":"12188",
    "addr:street":"Davis Ave",
    "iso:country":"US",
    "sg:address":"200 Davis Ave",
    "sg:city":"Waterford",
    "sg:classifiers":[
        {
            "category":"Freight",
            "type":"Transportation"
        }
    ],
    "sg:phone":"+1   ",
    "sg:postcode":"12188",
    "sg:province":"NY",
    "sg:tags":[
        "water"
    ],
    "wof:name":"New York State Thruway Auth",
    "wof:placetype":"venue"
},
  "geometry": {"coordinates":[-73.689611,42.792569],"type":"Point"}
}