{
  "type": "Feature",
  "properties": {
    "addr:full":"985 Central Park Ave Yonkers NY 10704",
    "addr:housenumber":"985",
    "addr:postcode":"10704",
    "addr:street":"Central Park Ave",
    "iso:country":"US",
    "sg:address":"985 Central Park Ave",
    "sg:city":"Yonkers",
    "sg:classifiers":[
        {
            "category":"Manufacturing",
            "subcategory":"Glass & Minerals",
            "type":"Manufacturing & Wholesale Goods"
        },
        {
            "category":"Retail",
            "subcategory":"Auto Repair",
            "type":"Services"
        }
    ],
    "sg:phone":"+1 914 376 5602",
    "sg:postcode":"10704",
    "sg:province":"NY",
    "sg:tags":[
        "plate",
        "window",
        "windshield",
        "glass-auto"
    ],
    "wof:name":"SAFELITE AUTO GLASS",
    "wof:placetype":"venue"
},
  "geometry": {"coordinates":[-73.856426,40.935491],"type":"Point"}
}