{
  "type": "Feature",
  "properties": {
    "iso:country":"US",
    "sg:address":"75 Fir Dr",
    "sg:city":"Roslyn",
    "sg:classifiers":[
        {
            "category":"Professional",
            "subcategory":"Lawyer & Legal Services",
            "type":"Services"
        }
    ],
    "sg:phone":"+1   ",
    "sg:postcode":"11576",
    "sg:province":"NY",
    "wof:name":"Ivan M Dochter",
    "wof:placetype":"venue"
},
  "geometry": {"coordinates":[-73.63140799999999,40.804504],"type":"Point"}
}