{
  "type": "Feature",
  "properties": {
    "addr:full":"1997 Bathgate Ave Bronx NY 10457",
    "addr:housenumber":"1997",
    "addr:postcode":"10457",
    "addr:street":"Bathgate Ave",
    "iso:country":"US",
    "sg:address":"1997 Bathgate Ave",
    "sg:city":"Bronx",
    "sg:classifiers":[
        {
            "category":"Social Services",
            "subcategory":"Job Training",
            "type":"Services"
        }
    ],
    "sg:phone":"+1 718 583 3220",
    "sg:postcode":"10457",
    "sg:province":"NY",
    "wof:name":"NAPA Auto Parts",
    "wof:placetype":"venue"
},
  "geometry": {"coordinates":[-73.896174,40.848578],"type":"Point"}
}