{
  "type": "Feature",
  "properties": {
    "iso:country":"US",
    "sg:address":"501 W 113th St Frnt",
    "sg:city":"New York",
    "sg:classifiers":[
        {
            "category":"Health Services",
            "subcategory":"Optometrist",
            "type":"Services"
        }
    ],
    "sg:phone":"+1 212 662 0399",
    "sg:postcode":"10025",
    "sg:province":"NY",
    "sg:tags":[
        "ophthalmologist"
    ],
    "wof:name":"Bickoff Corey",
    "wof:placetype":"venue"
},
  "geometry": {"coordinates":[-73.962402,40.804901],"type":"Point"}
}