{
  "type": "Feature",
  "properties": {
    "addr:full":"495 3rd Ave Brooklyn NY 11215",
    "addr:housenumber":"495",
    "addr:postcode":"11215",
    "addr:street":"3Rd Ave",
    "iso:country":"US",
    "sg:address":"495 3rd Ave",
    "sg:city":"Brooklyn",
    "sg:classifiers":[
        {
            "category":"Arts & Performance",
            "subcategory":"Dance",
            "type":"Entertainment"
        },
        {
            "category":"Recreation",
            "type":"Entertainment"
        },
        {
            "category":"Arts & Performance",
            "subcategory":"Theater",
            "type":"Entertainment"
        }
    ],
    "sg:phone":"+1 718 499 5402",
    "sg:postcode":"11215",
    "sg:province":"NY",
    "sg:tags":[
        "school",
        "instruction",
        "camps-recreational",
        "theatre",
        "dancing"
    ],
    "sg:website":"www.brooklyndanceproject.com/",
    "wof:name":"Brooklyn Dance Project",
    "wof:placetype":"venue"
},
  "geometry": {"coordinates":[-73.992042,40.670226],"type":"Point"}
}