{
  "type": "Feature",
  "properties": {
    "iso:country":"US",
    "sg:address":"1495 E 96th St",
    "sg:city":"Brooklyn",
    "sg:classifiers":[
        {
            "category":"Professional",
            "type":"Services"
        }
    ],
    "sg:phone":"+1 718 444 8722",
    "sg:postcode":"11236",
    "sg:province":"NY",
    "sg:tags":[
        "processing",
        "data"
    ],
    "wof:name":"Rapidtrade International",
    "wof:placetype":"venue"
},
  "geometry": {"coordinates":[-73.89393800000001,40.636402],"type":"Point"}
}