{
  "type": "Feature",
  "properties": {
    "addr:full":"351 52nd St Brooklyn NY 11220",
    "addr:housenumber":"351",
    "addr:postcode":"11220",
    "addr:street":"52Nd St",
    "iso:country":"US",
    "sg:address":"351 52nd St",
    "sg:city":"Brooklyn",
    "sg:classifiers":[
        {
            "category":"Travel",
            "subcategory":"Travel Agent",
            "type":"Entertainment"
        }
    ],
    "sg:phone":"+1 718 522 4225",
    "sg:postcode":"11220",
    "sg:province":"NY",
    "sg:tags":[
        "agency",
        "bureau"
    ],
    "wof:name":"Dream Travel",
    "wof:placetype":"venue"
},
  "geometry": {"coordinates":[-74.014388,40.645953],"type":"Point"}
}