{
  "type": "Feature",
  "properties": {
    "iso:country":"US",
    "sg:address":"1013 Atlantic Avenue",
    "sg:city":"Brooklyn",
    "sg:classifiers":[
        {
            "category":"Retail",
            "subcategory":"Auto Repair",
            "type":"Services"
        }
    ],
    "sg:phone":"+1 718 783 8658",
    "sg:postcode":"11238",
    "sg:province":"NY",
    "wof:name":"Gp Petro Auto Repair",
    "wof:placetype":"venue"
},
  "geometry": {"coordinates":[-73.960162,40.680298],"type":"Point"}
}