{
  "type": "Feature",
  "properties": {
    "addr:full":"8 W Main St Little Falls NY 13365",
    "addr:housenumber":"8",
    "addr:postcode":"13365",
    "addr:street":"W Main St",
    "iso:country":"US",
    "sg:address":"8 W Main St",
    "sg:city":"Little Falls",
    "sg:classifiers":[
        {
            "category":"Real Estate",
            "subcategory":"Real Estate Agent",
            "type":"Services"
        }
    ],
    "sg:phone":"+1 315 823 0750",
    "sg:postcode":"13365",
    "sg:province":"NY",
    "wof:name":"Snyder Apartments",
    "wof:placetype":"venue"
},
  "geometry": {"coordinates":[-74.85988999999999,43.043173],"type":"Point"}
}