{
  "type": "Feature",
  "properties": {
    "addr:full":"1034 Lavalley Rd Mooers NY 12958",
    "addr:housenumber":"1034",
    "addr:postcode":"12958",
    "addr:street":"Lavalley Rd",
    "iso:country":"US",
    "sg:address":"1034 Lavalley Rd",
    "sg:city":"Mooers",
    "sg:classifiers":[
        {
            "category":"Autos & Motor Vehicles",
            "subcategory":"Auto Supplies",
            "type":"Retail Goods"
        }
    ],
    "sg:phone":"+1 518 236 5263",
    "sg:postcode":"12958",
    "sg:province":"NY",
    "sg:tags":[
        "automobile",
        "accessory",
        "parts",
        "accessories-wholesale",
        "part",
        "manufacturer"
    ],
    "wof:name":"Valley Ignition Distributing Co, Inc",
    "wof:placetype":"venue"
},
  "geometry": {"coordinates":[-73.534243,44.940604],"type":"Point"}
}