{
  "type": "Feature",
  "properties": {
    "iso:country":"US",
    "sg:address":"55 James E Casey Dr",
    "sg:city":"Buffalo",
    "sg:classifiers":[
        {
            "category":"Wholesale",
            "subcategory":"Machinery & Supplies",
            "type":"Manufacturing & Wholesale Goods"
        }
    ],
    "sg:phone":"+1 716 826 2636",
    "sg:postcode":"14206",
    "sg:province":"NY",
    "sg:tags":[
        "industrial",
        "special",
        "mach"
    ],
    "sg:website":"www.hanessupply.com",
    "wof:name":"Hanes Supply Inc",
    "wof:placetype":"venue"
},
  "geometry": {"coordinates":[-78.805387,42.878887],"type":"Point"}
}