{
  "type": "Feature",
  "properties": {
    "addr:full":"3509 Carman Rd Schenectady NY 12303",
    "addr:housenumber":"3509",
    "addr:postcode":"12303",
    "addr:street":"Carman Rd",
    "iso:country":"US",
    "sg:address":"3509 Carman Rd",
    "sg:city":"Schenectady",
    "sg:classifiers":[
        {
            "category":"Social Services",
            "subcategory":"Child Care",
            "type":"Services"
        }
    ],
    "sg:phone":"+1 518 355 1334",
    "sg:postcode":"12303",
    "sg:province":"NY",
    "wof:name":"Mapleleaf Daycare",
    "wof:placetype":"venue"
},
  "geometry": {"coordinates":[-73.942509,42.741122],"type":"Point"}
}