{
  "type": "Feature",
  "properties": {
    "addr:full":"6853 Erie Rd Derby NY 14047",
    "addr:housenumber":"6853",
    "addr:postcode":"14047",
    "addr:street":"Erie Rd",
    "iso:country":"US",
    "sg:address":"6853 Erie Rd",
    "sg:city":"Derby",
    "sg:classifiers":[
        {
            "category":"Restaurant",
            "type":"Food & Drink"
        }
    ],
    "sg:menulink":"http://www.allmenus.com/ny/evans/148329-subway/menu/",
    "sg:phone":"+1 716 947 7827",
    "sg:postcode":"14047",
    "sg:province":"NY",
    "sg:tags":[
        "american",
        "sandwich"
    ],
    "wof:name":"Subway",
    "wof:placetype":"venue"
},
  "geometry": {"coordinates":[-78.981319,42.700589],"type":"Point"}
}