{
  "type": "Feature",
  "properties": {
    "iso:country":"US",
    "sg:address":"2458 Johnson Rd",
    "sg:city":"Horseheads",
    "sg:classifiers":[
        {
            "category":"Building & Trades",
            "subcategory":"Construction",
            "type":"Services"
        }
    ],
    "sg:phone":"+1 607 795 1234",
    "sg:postcode":"14845",
    "sg:province":"NY",
    "sg:tags":[
        "contractor"
    ],
    "wof:name":"Roy Builders Inc",
    "wof:placetype":"venue"
},
  "geometry": {"coordinates":[-76.796204,42.216702],"type":"Point"}
}