{
  "type": "Feature",
  "properties": {
    "iso:country":"US",
    "sg:address":"15 W Main St",
    "sg:city":"Cambridge",
    "sg:classifiers":[
        {
            "category":"Manufacturing",
            "subcategory":"Tools & Machinery",
            "type":"Manufacturing & Wholesale Goods"
        }
    ],
    "sg:phone":"+1   ",
    "sg:postcode":"12816",
    "sg:province":"NY",
    "sg:tags":[
        "water",
        "pump",
        "pumping"
    ],
    "wof:name":"Subgard International LLC",
    "wof:placetype":"venue"
},
  "geometry": {"coordinates":[-73.38415000000001,43.02805],"type":"Point"}
}