{
  "type": "Feature",
  "properties": {
    "addr:full":"3709 Broadway Astoria NY 11103",
    "addr:housenumber":"3709",
    "addr:postcode":"11103",
    "addr:street":"Broadway",
    "iso:country":"US",
    "sg:address":"3709 Broadway",
    "sg:city":"Astoria",
    "sg:classifiers":[
        {
            "category":"Retail",
            "subcategory":"Laundry & Dry Cleaning",
            "type":"Services"
        }
    ],
    "sg:phone":"+1 718 545 4148",
    "sg:postcode":"11103",
    "sg:province":"NY",
    "wof:name":"Teddy's Cleaners",
    "wof:placetype":"venue"
},
  "geometry": {"coordinates":[-73.920601,40.759701],"type":"Point"}
}