{
  "type": "Feature",
  "properties": {
    "addr:full":"1308 Arden Ave Staten Island NY 10312",
    "addr:housenumber":"1308",
    "addr:postcode":"10312",
    "addr:street":"Arden Ave",
    "iso:country":"US",
    "sg:address":"1308 Arden Ave",
    "sg:city":"Staten Island",
    "sg:classifiers":[
        {
            "category":"Manufacturing",
            "subcategory":"Textiles",
            "type":"Manufacturing & Wholesale Goods"
        }
    ],
    "sg:phone":"+1   ",
    "sg:postcode":"10312",
    "sg:province":"NY",
    "sg:tags":[
        "mill",
        "knit",
        "outerwear"
    ],
    "wof:name":"Wwwwraprascalcom",
    "wof:placetype":"venue"
},
  "geometry": {"coordinates":[-74.168728,40.53937],"type":"Point"}
}