{
  "type": "Feature",
  "properties": {
    "addr:full":"214 17th St Brooklyn NY 11215",
    "addr:housenumber":"214",
    "addr:postcode":"11215",
    "addr:street":"17Th St",
    "iso:country":"US",
    "sg:address":"214 17th St",
    "sg:city":"Brooklyn",
    "sg:classifiers":[
        {
            "category":"Arts & Performance",
            "subcategory":"Theater",
            "type":"Entertainment"
        }
    ],
    "sg:phone":"+1   ",
    "sg:postcode":"11215",
    "sg:province":"NY",
    "sg:tags":[
        "theatrical"
    ],
    "wof:name":"Smatter Productions",
    "wof:placetype":"venue"
},
  "geometry": {"coordinates":[-73.99209999999999,40.664298],"type":"Point"}
}