{
  "type": "Feature",
  "properties": {
    "addr:full":"397 Plymouth Ave Buffalo NY 14213",
    "addr:housenumber":"397",
    "addr:postcode":"14213",
    "addr:street":"Plymouth Ave",
    "iso:country":"US",
    "sg:address":"397 Plymouth Ave",
    "sg:city":"Buffalo",
    "sg:classifiers":[
        {
            "category":"Social Services",
            "subcategory":"Child Care",
            "type":"Services"
        }
    ],
    "sg:phone":"+1 716 882 6724",
    "sg:postcode":"14213",
    "sg:province":"NY",
    "sg:tags":[
        "day"
    ],
    "wof:name":"Baby Bear Day Care",
    "wof:placetype":"venue"
},
  "geometry": {"coordinates":[-78.890602,42.906601],"type":"Point"}
}