{
  "type": "Feature",
  "properties": {
    "iso:country":"US",
    "sg:address":"20 W 22 St",
    "sg:city":"New York",
    "sg:classifiers":[
        {
            "category":"Retail",
            "subcategory":"Repair Shop",
            "type":"Services"
        }
    ],
    "sg:phone":"+1 212 675 8408",
    "sg:postcode":"10010",
    "sg:province":"NY",
    "sg:tags":[
        "instrument",
        "musical"
    ],
    "wof:name":"Imai Guitars",
    "wof:placetype":"venue"
},
  "geometry": {"coordinates":[-73.99287099999999,40.741914],"type":"Point"}
}