{
  "type": "Feature",
  "properties": {
    "iso:country":"US",
    "sg:address":"46 S Washington St",
    "sg:city":"Binghamton",
    "sg:classifiers":[
        {
            "category":"Restaurant",
            "type":"Food & Drink"
        }
    ],
    "sg:phone":"+1   ",
    "sg:postcode":"13903",
    "sg:province":"NY",
    "sg:tags":[
        "personal",
        "eating"
    ],
    "wof:name":"Southbridge Banquet & Catering",
    "wof:placetype":"venue"
},
  "geometry": {"coordinates":[-75.91377,42.090004],"type":"Point"}
}