{
  "type": "Feature",
  "properties": {
    "iso:country":"US",
    "sg:address":"1532 Jacob Rd",
    "sg:city":"Cortlandt Manor",
    "sg:classifiers":[
        {
            "category":"Professional",
            "subcategory":"Management & Consulting",
            "type":"Services"
        }
    ],
    "sg:phone":"+1 914 737 4500",
    "sg:postcode":"10567",
    "sg:province":"NY",
    "sg:tags":[
        "consultant"
    ],
    "wof:name":"Hunterbrook Consulting It",
    "wof:placetype":"venue"
},
  "geometry": {"coordinates":[-73.838268,41.282348],"type":"Point"}
}