{
  "type": "Feature",
  "properties": {
    "iso:country":"US",
    "sg:address":"111 South St",
    "sg:city":"Oyster Bay",
    "sg:classifiers":[
        {
            "category":"Professional",
            "subcategory":"Computer Services",
            "type":"Services"
        }
    ],
    "sg:phone":"+1 516 624 7400",
    "sg:postcode":"11771",
    "sg:province":"NY",
    "sg:tags":[
        "consultant",
        "designer"
    ],
    "sg:website":"www.lineimaging.com",
    "wof:name":"Line Imaging Systems",
    "wof:placetype":"venue"
},
  "geometry": {"coordinates":[-73.530541,40.872374],"type":"Point"}
}