{
  "type": "Feature",
  "properties": {
    "iso:country":"US",
    "sg:address":"34 Young Ave",
    "sg:city":"Pelham",
    "sg:classifiers":[
        {
            "category":"Building & Trades",
            "subcategory":"Construction",
            "type":"Services"
        }
    ],
    "sg:phone":"+1 914 712 1280",
    "sg:postcode":"10803",
    "sg:province":"NY",
    "sg:tags":[
        "hanging",
        "contractor"
    ],
    "wof:name":"P J McGoldrick Co Inc",
    "wof:placetype":"venue"
},
  "geometry": {"coordinates":[-73.803746,40.912334],"type":"Point"}
}