{
  "type": "Feature",
  "properties": {
    "iso:country":"US",
    "sg:address":"158 Roebling St",
    "sg:city":"Brooklyn",
    "sg:classifiers":[
        {
            "category":"Wholesale",
            "subcategory":"Auto Parts",
            "type":"Manufacturing & Wholesale Goods"
        }
    ],
    "sg:phone":"+1 718 387 0800",
    "sg:postcode":"11211",
    "sg:province":"NY",
    "sg:tags":[
        "automobile",
        "accessory"
    ],
    "sg:website":"www.erebunicorp.com",
    "wof:name":"Erebuni Corp",
    "wof:placetype":"venue"
},
  "geometry": {"coordinates":[-73.957823,40.714331],"type":"Point"}
}