{
  "type": "Feature",
  "properties": {
    "addr:full":"10 W 3rd St Jamestown NY 14701",
    "addr:housenumber":"10",
    "addr:postcode":"14701",
    "addr:street":"W 3Rd St",
    "iso:country":"US",
    "sg:address":"10 W 3rd St",
    "sg:city":"Jamestown",
    "sg:classifiers":[
        {
            "category":"Shopping",
            "subcategory":"Discount & Variety Stores",
            "type":"Retail Goods"
        }
    ],
    "sg:phone":"+1   ",
    "sg:postcode":"14701",
    "sg:province":"NY",
    "wof:name":"D & K",
    "wof:placetype":"venue"
},
  "geometry": {"coordinates":[-79.241629,42.096421],"type":"Point"}
}