{
  "type": "Feature",
  "properties": {
    "iso:country":"US",
    "sg:address":"250 E 87th St Apt 22A",
    "sg:city":"New York",
    "sg:classifiers":[
        {
            "category":"Real Estate",
            "subcategory":"Architect",
            "type":"Services"
        }
    ],
    "sg:phone":"+1 212 348 3881",
    "sg:postcode":"10128",
    "sg:province":"NY",
    "wof:name":"Diversity Architecture Design",
    "wof:placetype":"venue"
},
  "geometry": {"coordinates":[-73.95230100000001,40.778999],"type":"Point"}
}