{
  "type": "Feature",
  "properties": {
    "iso:country":"US",
    "sg:address":"356 Bowery",
    "sg:city":"New York",
    "sg:classifiers":[
        {
            "category":"Professional",
            "subcategory":"Business Services",
            "type":"Services"
        }
    ],
    "sg:phone":"+1 212 228 4868",
    "sg:postcode":"10012",
    "sg:province":"NY",
    "sg:tags":[
        "recording",
        "studio"
    ],
    "wof:name":"Ipecac Recording",
    "wof:placetype":"venue"
},
  "geometry": {"coordinates":[-73.991714,40.726759],"type":"Point"}
}