{
  "type": "Feature",
  "properties": {
    "iso:country":"US",
    "sg:address":"6421 W Quaker St",
    "sg:city":"Orchard Park",
    "sg:classifiers":[
        {
            "category":"Health Services",
            "subcategory":"Optometrist",
            "type":"Services"
        }
    ],
    "sg:phone":"+1 716 662 4525",
    "sg:postcode":"14127",
    "sg:province":"NY",
    "wof:name":"John M Brzezicki Jr OD",
    "wof:placetype":"venue"
},
  "geometry": {"coordinates":[-78.74611400000001,42.766679],"type":"Point"}
}