{
  "type": "Feature",
  "properties": {
    "addr:full":"3178 Nostrand Ave Brooklyn NY 11229",
    "addr:housenumber":"3178",
    "addr:postcode":"11229",
    "addr:street":"Nostrand Ave",
    "iso:country":"US",
    "sg:address":"3178 Nostrand Ave",
    "sg:city":"Brooklyn",
    "sg:classifiers":[
        {
            "category":"Professional",
            "subcategory":"Management & Consulting",
            "type":"Services"
        }
    ],
    "sg:phone":"+1 718 556 9020",
    "sg:postcode":"11229",
    "sg:province":"NY",
    "sg:tags":[
        "photo",
        "agency"
    ],
    "wof:name":"Worldwide Vsual Assgnments LLC",
    "wof:placetype":"venue"
},
  "geometry": {"coordinates":[-73.942925,40.605629],"type":"Point"}
}