{
  "type": "Feature",
  "properties": {
    "addr:full":"562 New Vernon Rd Middletown NY 10940",
    "addr:housenumber":"562",
    "addr:postcode":"10940",
    "addr:street":"New Vernon Rd",
    "iso:country":"US",
    "sg:address":"562 New Vernon Rd",
    "sg:city":"Middletown",
    "sg:classifiers":[
        {
            "category":"Shopping",
            "subcategory":"Bicycles & Sporting Goods",
            "type":"Retail Goods"
        }
    ],
    "sg:phone":"+1   ",
    "sg:postcode":"10940",
    "sg:province":"NY",
    "wof:name":"B & B Archery",
    "wof:placetype":"venue"
},
  "geometry": {"coordinates":[-74.483918,41.502342],"type":"Point"}
}