{
  "type": "Feature",
  "properties": {
    "iso:country":"US",
    "sg:address":"100 Dutch Hill Rd",
    "sg:city":"Orangeburg",
    "sg:classifiers":[
        {
            "category":"Banks & Credit Unions",
            "subcategory":"Investment Brokerage",
            "type":"Services"
        }
    ],
    "sg:phone":"+1 845 398 5809",
    "sg:postcode":"10962",
    "sg:province":"NY",
    "sg:tags":[
        "advisory"
    ],
    "wof:name":"U S B Financial Services",
    "wof:placetype":"venue"
},
  "geometry": {"coordinates":[-73.95492299999999,41.043443],"type":"Point"}
}