{
  "type": "Feature",
  "properties": {
    "addr:full":"25 Union Sq W New York NY 10003",
    "addr:housenumber":"25",
    "addr:postcode":"10003",
    "addr:street":"Union Sq W",
    "iso:country":"US",
    "sg:address":"25 Union Sq W",
    "sg:city":"New York",
    "sg:classifiers":[
        {
            "category":"Restaurant",
            "type":"Food & Drink"
        }
    ],
    "sg:phone":"+1 212 924 3388",
    "sg:postcode":"10003",
    "sg:province":"NY",
    "sg:tags":[
        "delicatessen",
        "caterer"
    ],
    "wof:name":"Atrium Deli & Grocery",
    "wof:placetype":"venue"
},
  "geometry": {"coordinates":[-73.990923,40.736313],"type":"Point"}
}