{
  "type": "Feature",
  "properties": {
    "addr:full":"722 Homer St Olean NY 14760",
    "addr:housenumber":"722",
    "addr:postcode":"14760",
    "addr:street":"Homer St",
    "iso:country":"US",
    "sg:address":"722 Homer St",
    "sg:city":"Olean",
    "sg:classifiers":[
        {
            "category":"Government",
            "subcategory":"Police Station",
            "type":"Public Place"
        }
    ],
    "sg:phone":"+1 716 373 5525",
    "sg:postcode":"14760",
    "sg:province":"NY",
    "sg:tags":[
        "protection"
    ],
    "wof:name":"Forensic Investigation Center",
    "wof:placetype":"venue"
},
  "geometry": {"coordinates":[-78.448436,42.093953],"type":"Point"}
}