{
  "type": "Feature",
  "properties": {
    "addr:full":"272 Bleecker St New York NY 10014",
    "addr:housenumber":"272",
    "addr:postcode":"10014",
    "addr:street":"Bleecker St",
    "iso:country":"US",
    "sg:address":"272 Bleecker St",
    "sg:city":"New York",
    "sg:classifiers":[
        {
            "category":"Retail",
            "subcategory":"Repair Shop",
            "type":"Services"
        }
    ],
    "sg:phone":"+1 646 278 5205",
    "sg:postcode":"10014",
    "sg:province":"NY",
    "sg:tags":[
        "lock",
        "locksmith"
    ],
    "wof:name":"A Locksmith All Day",
    "wof:placetype":"venue"
},
  "geometry": {"coordinates":[-74.003299,40.731743],"type":"Point"}
}