{
  "type": "Feature",
  "properties": {
    "iso:country":"US",
    "sg:address":"480 White Plains Rd",
    "sg:city":"Eastchester",
    "sg:classifiers":[
        {
            "category":"Travel",
            "subcategory":"Hotels & Motels",
            "type":"Entertainment"
        }
    ],
    "sg:phone":"+1 914 337 5770",
    "sg:postcode":"10709",
    "sg:province":"NY",
    "wof:name":"Tarrytown Spring Hill Suites",
    "wof:placetype":"venue"
},
  "geometry": {"coordinates":[-73.813208,40.957585],"type":"Point"}
}