{
  "type": "Feature",
  "properties": {
    "addr:full":"543 Bedford Ave Brooklyn NY 11211",
    "addr:housenumber":"543",
    "addr:postcode":"11211",
    "addr:street":"Bedford Ave",
    "iso:country":"US",
    "sg:address":"543 Bedford Ave",
    "sg:city":"Brooklyn",
    "sg:classifiers":[
        {
            "category":"Insurance",
            "subcategory":"Insurance Agent",
            "type":"Services"
        },
        {
            "category":"Insurance",
            "subcategory":"Hazard Insurance",
            "type":"Services"
        }
    ],
    "sg:phone":"+1 718 388 8323",
    "sg:postcode":"11211",
    "sg:province":"NY",
    "sg:tags":[
        "auto",
        "recreational",
        "motorcycle",
        "vehicle",
        "marine",
        "boat"
    ],
    "wof:name":"F & W PROFESSIONAL INS BROKERAGE INC",
    "wof:placetype":"venue"
},
  "geometry": {"coordinates":[-73.961853,40.7048],"type":"Point"}
}