{
  "type": "Feature",
  "properties": {
    "addr:full":"835 Franklin Ave Thornwood NY 10594",
    "addr:housenumber":"835",
    "addr:postcode":"10594",
    "addr:street":"Franklin Ave",
    "iso:country":"US",
    "sg:address":"835 Franklin Ave",
    "sg:city":"Thornwood",
    "sg:classifiers":[
        {
            "category":"Education",
            "subcategory":"Dance Studio",
            "type":"Public Place"
        }
    ],
    "sg:phone":"+1 914 747 6286",
    "sg:postcode":"10594",
    "sg:province":"NY",
    "sg:tags":[
        "instruction",
        "dancing"
    ],
    "wof:name":"Smith's Dancing School",
    "wof:placetype":"venue"
},
  "geometry": {"coordinates":[-73.78143900000001,41.12278],"type":"Point"}
}