{
  "type": "Feature",
  "properties": {
    "addr:full":"21 Hunting Hollow Ct Huntington Station NY 11746",
    "addr:housenumber":"21",
    "addr:postcode":"11746",
    "addr:street":"Hunting Hollow Ct Huntington",
    "iso:country":"US",
    "sg:address":"21 Hunting Hollow Ct",
    "sg:city":"Huntington Station",
    "sg:classifiers":[
        {
            "category":"Insurance",
            "subcategory":"Insurance Agent",
            "type":"Services"
        }
    ],
    "sg:phone":"+1 631 427 8989",
    "sg:postcode":"11746",
    "sg:province":"NY",
    "sg:tags":[
        "medical",
        "company",
        "for",
        "exam"
    ],
    "wof:name":"Crossland Medical Services PC",
    "wof:placetype":"venue"
},
  "geometry": {"coordinates":[-73.351246,40.784594],"type":"Point"}
}