{
  "type": "Feature",
  "properties": {
    "iso:country":"US",
    "sg:address":"50 Elm St",
    "sg:city":"Malone",
    "sg:classifiers":[
        {
            "category":"Professional",
            "subcategory":"Management & Consulting",
            "type":"Services"
        }
    ],
    "sg:phone":"+1 518 483 0670",
    "sg:postcode":"12953",
    "sg:province":"NY",
    "sg:tags":[
        "lobbyist"
    ],
    "wof:name":"Citizen Advocates Inc",
    "wof:placetype":"venue"
},
  "geometry": {"coordinates":[-74.290954,44.849726],"type":"Point"}
}