{
  "type": "Feature",
  "properties": {
    "addr:full":"5176 Commercial Dr Yorkville NY 13495",
    "addr:housenumber":"5176",
    "addr:postcode":"13495",
    "addr:street":"Commercial Dr",
    "iso:country":"US",
    "sg:address":"5176 Commercial Dr",
    "sg:city":"Yorkville",
    "sg:classifiers":[
        {
            "category":"Retail",
            "subcategory":"Auto Repair",
            "type":"Services"
        }
    ],
    "sg:phone":"+1 315 736 2442",
    "sg:postcode":"13495",
    "sg:province":"NY",
    "sg:tags":[
        "repairing",
        "automobile"
    ],
    "wof:name":"Tallman's Tire & Auto Svc",
    "wof:placetype":"venue"
},
  "geometry": {"coordinates":[-75.292303,43.113474],"type":"Point"}
}