{
  "type": "Feature",
  "properties": {
    "addr:full":"528 Willow Ave Cedarhurst NY 11516",
    "addr:housenumber":"528",
    "addr:postcode":"11516",
    "addr:street":"Willow Ave",
    "iso:country":"US",
    "sg:address":"528 Willow Ave",
    "sg:city":"Cedarhurst",
    "sg:classifiers":[
        {
            "category":"Education",
            "subcategory":"School",
            "type":"Public Place"
        }
    ],
    "sg:phone":"+1 516 295 3666",
    "sg:postcode":"11516",
    "sg:province":"NY",
    "wof:name":"Cahal For Children With Learning Disabilities",
    "wof:placetype":"venue"
},
  "geometry": {"coordinates":[-73.72370100000001,40.6227],"type":"Point"}
}