{
  "type": "Feature",
  "properties": {
    "addr:full":"356 W 30 St New York NY 10001",
    "addr:housenumber":"356",
    "addr:postcode":"10001",
    "addr:street":"W 30 St",
    "iso:country":"US",
    "sg:address":"356 W 30 St",
    "sg:city":"New York",
    "sg:classifiers":[
        {
            "category":"Real Estate",
            "subcategory":"Real Estate Operator",
            "type":"Services"
        }
    ],
    "sg:phone":"+1 212 586 1888",
    "sg:postcode":"10001",
    "sg:province":"NY",
    "sg:tags":[
        "building",
        "apartment"
    ],
    "wof:name":"Samuel Pompa",
    "wof:placetype":"venue"
},
  "geometry": {"coordinates":[-73.99693600000001,40.750134],"type":"Point"}
}