{
  "type": "Feature",
  "properties": {
    "iso:country":"US",
    "sg:address":"640 Middle Country Rd",
    "sg:city":"Middle Island",
    "sg:classifiers":[
        {
            "category":"Retail",
            "subcategory":"Funeral Services",
            "type":"Services"
        }
    ],
    "sg:phone":"+1 631 345 6700",
    "sg:postcode":"11953",
    "sg:province":"NY",
    "sg:tags":[
        "director"
    ],
    "wof:name":"Giove Funeral Home",
    "wof:placetype":"venue"
},
  "geometry": {"coordinates":[-72.951859,40.881228],"type":"Point"}
}