{
  "type": "Feature",
  "properties": {
    "addr:full":"334 Utica Ave Brooklyn NY 11213",
    "addr:housenumber":"334",
    "addr:postcode":"11213",
    "addr:street":"Utica Ave",
    "iso:country":"US",
    "sg:address":"334 Utica Ave",
    "sg:city":"Brooklyn",
    "sg:classifiers":[
        {
            "category":"Shopping",
            "type":"Retail Goods"
        },
        {
            "category":"Wholesale",
            "subcategory":"Durable Goods & Equipment",
            "type":"Manufacturing & Wholesale Goods"
        }
    ],
    "sg:phone":"+1 718 773 8748",
    "sg:postcode":"11213",
    "sg:province":"NY",
    "sg:tags":[
        "article",
        "religious",
        "supply"
    ],
    "wof:name":"Utica Religious Supplies",
    "wof:placetype":"venue"
},
  "geometry": {"coordinates":[-73.931422,40.666576],"type":"Point"}
}