{
  "type": "Feature",
  "properties": {
    "iso:country":"US",
    "sg:address":"6300 Thompson Rd",
    "sg:city":"Syracuse",
    "sg:classifiers":[
        {
            "category":"Restaurant",
            "type":"Food & Drink"
        }
    ],
    "sg:menulink":"http://www.allmenus.com/ny/de-witt/170083-burger-king/menu/",
    "sg:phone":"+1 315 437 8764",
    "sg:postcode":"13206",
    "sg:province":"NY",
    "sg:tags":[
        "burger",
        "american"
    ],
    "wof:name":"Burger King",
    "wof:placetype":"venue"
},
  "geometry": {"coordinates":[-76.088981,43.07649],"type":"Point"}
}