{
  "type": "Feature",
  "properties": {
    "addr:full":"72 Jericho Tpke Mineola NY 11501",
    "addr:housenumber":"72",
    "addr:postcode":"11501",
    "addr:street":"Jericho Tpke",
    "iso:country":"US",
    "sg:address":"72 Jericho Tpke",
    "sg:city":"Mineola",
    "sg:classifiers":[
        {
            "category":"Arts & Performance",
            "subcategory":"Theater",
            "type":"Entertainment"
        }
    ],
    "sg:phone":"+1 516 767 9046",
    "sg:postcode":"11501",
    "sg:province":"NY",
    "sg:tags":[
        "group"
    ],
    "wof:name":"HMS Productions LLC",
    "wof:placetype":"venue"
},
  "geometry": {"coordinates":[-73.638576,40.75009],"type":"Point"}
}