{
  "type": "Feature",
  "properties": {
    "iso:country":"US",
    "sg:address":"465 Columbus Avenue",
    "sg:city":"Valhalla",
    "sg:classifiers":[
        {
            "category":"Professional",
            "subcategory":"Computer Services",
            "type":"Services"
        }
    ],
    "sg:postcode":"10595",
    "sg:province":"NY",
    "sg:tags":[
        "shopping",
        "local-search",
        "in-store-sales",
        "retail-sales",
        "bargain",
        "research-online-buy-offline"
    ],
    "sg:website":"http://www.salelocator.com",
    "wof:name":"SaleLocator",
    "wof:placetype":"venue"
},
  "geometry": {"coordinates":[-73.77721099999999,41.102308],"type":"Point"}
}