{
  "type": "Feature",
  "properties": {
    "iso:country":"US",
    "sg:address":"67-39 Myrtle Ave",
    "sg:city":"Queens",
    "sg:classifiers":[
        {
            "category":"Restaurant",
            "type":"Food & Drink"
        }
    ],
    "sg:postcode":"11385",
    "sg:province":"NY",
    "sg:tags":[
        "pizza"
    ],
    "wof:name":"Mario's Pizza and Restaurant",
    "wof:placetype":"venue"
},
  "geometry": {"coordinates":[-73.88516300000001,40.701602],"type":"Point"}
}