{
  "type": "Feature",
  "properties": {
    "addr:full":"201 W 77th St New York NY 10024",
    "addr:housenumber":"201",
    "addr:postcode":"10024",
    "addr:street":"W 77Th St",
    "iso:country":"US",
    "sg:address":"201 W 77th St",
    "sg:city":"New York",
    "sg:classifiers":[
        {
            "category":"Building & Trades",
            "subcategory":"Locksmith",
            "type":"Services"
        }
    ],
    "sg:phone":"+1 646 224 0614",
    "sg:postcode":"10024",
    "sg:province":"NY",
    "sg:tags":[
        "key"
    ],
    "wof:name":"Emergency A Number 1 Locksmith",
    "wof:placetype":"venue"
},
  "geometry": {"coordinates":[-73.97930100000001,40.781799],"type":"Point"}
}