{
  "type": "Feature",
  "properties": {
    "iso:country":"US",
    "sg:address":"2500 Marcus Ave",
    "sg:city":"New Hyde Park",
    "sg:classifiers":[
        {
            "category":"Organizations",
            "subcategory":"Non-profit Organization",
            "type":"Services"
        }
    ],
    "sg:phone":"+1 800 933 2566",
    "sg:postcode":"11042",
    "sg:province":"NY",
    "sg:tags":[
        "service/non-profit",
        "community"
    ],
    "sg:website":"www.nybloodcenter.org",
    "wof:name":"Lake Success Donor Center",
    "wof:placetype":"venue"
},
  "geometry": {"coordinates":[-73.70026799999999,40.758996],"type":"Point"}
}