{
  "type": "Feature",
  "properties": {
    "addr:full":"1153 E Jericho Tpke Huntington NY 11743",
    "addr:housenumber":"1153",
    "addr:postcode":"11743",
    "addr:street":"E Jericho Tpke",
    "iso:country":"US",
    "sg:address":"1153 E Jericho Tpke",
    "sg:city":"Huntington",
    "sg:classifiers":[
        {
            "category":"Restaurant",
            "type":"Food & Drink"
        }
    ],
    "sg:phone":"+1 631 549 5506",
    "sg:postcode":"11743",
    "sg:province":"NY",
    "sg:tags":[
        "middle",
        "afghan",
        "eastern"
    ],
    "sg:website":"www.kabulny.com",
    "wof:name":"Kabul Afghan Cuisine",
    "wof:placetype":"venue"
},
  "geometry": {"coordinates":[-73.3647,40.8339],"type":"Point"}
}