{
  "type": "Feature",
  "properties": {
    "addr:full":"11 Walnut St Walden NY 12586",
    "addr:housenumber":"11",
    "addr:postcode":"12586",
    "addr:street":"Walnut St",
    "iso:country":"US",
    "sg:address":"11 Walnut St",
    "sg:city":"Walden",
    "sg:classifiers":[
        {
            "category":"Social Services",
            "type":"Services"
        }
    ],
    "sg:phone":"+1 845 778 1181",
    "sg:postcode":"12586",
    "sg:province":"NY",
    "sg:tags":[
        "counselor",
        "marriage",
        "family"
    ],
    "wof:name":"Walden Counseling Ctr",
    "wof:placetype":"venue"
},
  "geometry": {"coordinates":[-74.19,41.560013],"type":"Point"}
}