{
  "type": "Feature",
  "properties": {
    "addr:full":"437 5th Ave New York NY 10016",
    "addr:housenumber":"437",
    "addr:postcode":"10016",
    "addr:street":"5Th Ave",
    "iso:country":"US",
    "sg:address":"437 5th Ave",
    "sg:city":"New York",
    "sg:classifiers":[
        {
            "category":"Education",
            "subcategory":"Vocational School",
            "type":"Public Place"
        },
        {
            "category":"Personal",
            "subcategory":"Skin Care",
            "type":"Services"
        }
    ],
    "sg:phone":"+1 212 779 7800",
    "sg:postcode":"10016",
    "sg:province":"NY",
    "sg:tags":[
        "cosmetology"
    ],
    "sg:website":"www.christinevalmy.com",
    "wof:name":"Christine Valmy International School",
    "wof:placetype":"venue"
},
  "geometry": {"coordinates":[-73.982011,40.7513],"type":"Point"}
}