{
  "type": "Feature",
  "properties": {
    "addr:full":"23 N Portage St Westfield NY 14787",
    "addr:housenumber":"23",
    "addr:postcode":"14787",
    "addr:street":"N Portage St",
    "iso:country":"US",
    "sg:address":"23 N Portage St",
    "sg:city":"Westfield",
    "sg:classifiers":[
        {
            "category":"Personal",
            "subcategory":"Barber",
            "type":"Services"
        }
    ],
    "sg:phone":"+1 716 326 4004",
    "sg:postcode":"14787",
    "sg:province":"NY",
    "wof:name":"Deb's Barber Shop",
    "wof:placetype":"venue"
},
  "geometry": {"coordinates":[-79.57834099999999,42.32228],"type":"Point"}
}