{
  "type": "Feature",
  "properties": {
    "iso:country":"US",
    "sg:address":"415 Route 9W",
    "sg:city":"Glenmont",
    "sg:classifiers":[
        {
            "category":"Autos & Motor Vehicles",
            "subcategory":"Fuel & Gas Station",
            "type":"Retail Goods"
        }
    ],
    "sg:phone":"+1 518 445 2737",
    "sg:postcode":"12077",
    "sg:province":"NY",
    "sg:website":"www.prestigepetroleum.com",
    "wof:name":"Prestige Petroleum Inc",
    "wof:placetype":"venue"
},
  "geometry": {"coordinates":[-73.79222799999999,42.601663],"type":"Point"}
}