{
  "type": "Feature",
  "properties": {
    "addr:full":"25 Liberty Rd Tappan NY 10983",
    "addr:housenumber":"25",
    "addr:postcode":"10983",
    "addr:street":"Liberty Rd",
    "iso:country":"US",
    "sg:address":"25 Liberty Rd",
    "sg:city":"Tappan",
    "sg:classifiers":[
        {
            "category":"Professional",
            "subcategory":"Art Services",
            "type":"Services"
        }
    ],
    "sg:phone":"+1 845 359 3250",
    "sg:postcode":"10983",
    "sg:province":"NY",
    "sg:tags":[
        "graphic",
        "commercial",
        "designer",
        "artist"
    ],
    "wof:name":"Rpn Graphics",
    "wof:placetype":"venue"
},
  "geometry": {"coordinates":[-73.961281,41.026891],"type":"Point"}
}