{
  "type": "Feature",
  "properties": {
    "iso:country":"US",
    "sg:address":"473 W 21st Street",
    "sg:city":"New York",
    "sg:classifiers":[
        {
            "category":"Shopping",
            "subcategory":"Clothing, Apparel, & Fashions",
            "type":"Retail Goods"
        }
    ],
    "sg:phone":"+1 212 924 0221",
    "sg:postcode":"10011",
    "sg:province":"NY",
    "sg:tags":[
        "clothing",
        "women's"
    ],
    "wof:name":"Bailin Robert",
    "wof:placetype":"venue"
},
  "geometry": {"coordinates":[-74.00468600000001,40.746097],"type":"Point"}
}