{
  "type": "Feature",
  "properties": {
    "iso:country":"US",
    "sg:address":"85 Wilson Ave",
    "sg:city":"Medford",
    "sg:classifiers":[
        {
            "category":"Personal",
            "subcategory":"Beauty Salon",
            "type":"Services"
        }
    ],
    "sg:phone":"+1 631 698 2913",
    "sg:postcode":"11763",
    "sg:province":"NY",
    "wof:name":"Hair Monion",
    "wof:placetype":"venue"
},
  "geometry": {"coordinates":[-72.97492,40.866409],"type":"Point"}
}