{
  "type": "Feature",
  "properties": {
    "iso:country":"US",
    "sg:address":"1750 Flatbush Ave",
    "sg:city":"Brooklyn",
    "sg:classifiers":[
        {
            "category":"Personal",
            "subcategory":"Beauty Salon",
            "type":"Services"
        }
    ],
    "sg:phone":"+1 718 377 2073",
    "sg:postcode":"11210",
    "sg:province":"NY",
    "wof:name":"Kids & Braids",
    "wof:placetype":"venue"
},
  "geometry": {"coordinates":[-73.94309699999999,40.628635],"type":"Point"}
}