{
  "type": "Feature",
  "properties": {
    "addr:full":"995 Park Ave Rochester NY 14610",
    "addr:housenumber":"995",
    "addr:postcode":"14610",
    "addr:street":"Park Ave",
    "iso:country":"US",
    "sg:address":"995 Park Ave",
    "sg:city":"Rochester",
    "sg:classifiers":[
        {
            "category":"Organizations",
            "subcategory":"Religious Organization",
            "type":"Services"
        }
    ],
    "sg:phone":"+1 585 442 5717",
    "sg:postcode":"14610",
    "sg:province":"NY",
    "sg:tags":[
        "clergy"
    ],
    "wof:name":"John Karl Jr",
    "wof:placetype":"venue"
},
  "geometry": {"coordinates":[-77.569017,43.145862],"type":"Point"}
}