{
  "type": "Feature",
  "properties": {
    "iso:country":"US",
    "sg:address":"57 Ridge Rd",
    "sg:city":"Hartsdale",
    "sg:classifiers":[
        {
            "category":"Building & Trades",
            "subcategory":"Electrical",
            "type":"Services"
        }
    ],
    "sg:phone":"+1 914 683 1121",
    "sg:postcode":"10530",
    "sg:province":"NY",
    "sg:tags":[
        "commutator"
    ],
    "wof:name":"Synergy Corp",
    "wof:placetype":"venue"
},
  "geometry": {"coordinates":[-73.805914,41.024638],"type":"Point"}
}