{
  "type": "Feature",
  "properties": {
    "iso:country":"US",
    "sg:address":"74 Broadway",
    "sg:city":"Tivoli",
    "sg:classifiers":[
        {
            "category":"Restaurant",
            "type":"Food & Drink"
        }
    ],
    "sg:phone":"+1 845 757 5055",
    "sg:postcode":"12583",
    "sg:province":"NY",
    "wof:name":"Osaka Japanese Restaurant",
    "wof:placetype":"venue"
},
  "geometry": {"coordinates":[-73.91024400000001,42.058767],"type":"Point"}
}