{
  "type": "Feature",
  "properties": {
    "iso:country":"US",
    "sg:address":"1694 Penfield Rd",
    "sg:city":"Rochester",
    "sg:classifiers":[
        {
            "category":"Personal",
            "subcategory":"Beauty Salon",
            "type":"Services"
        }
    ],
    "sg:phone":"+1 585 586 9490",
    "sg:postcode":"14526",
    "sg:province":"NY",
    "sg:tags":[
        "shop"
    ],
    "wof:name":"Hair Designs By Rose",
    "wof:placetype":"venue"
},
  "geometry": {"coordinates":[-77.489662,43.131647],"type":"Point"}
}