{
  "type": "Feature",
  "properties": {
    "iso:country":"US",
    "sg:address":"368 North Ave",
    "sg:city":"New Rochelle",
    "sg:classifiers":[
        {
            "category":"Wholesale",
            "subcategory":"Furniture",
            "type":"Manufacturing & Wholesale Goods"
        }
    ],
    "sg:phone":"+1 914 654 8965",
    "sg:postcode":"10801",
    "sg:province":"NY",
    "wof:name":"Bedshoppecom",
    "wof:placetype":"venue"
},
  "geometry": {"coordinates":[-73.784498,40.914328],"type":"Point"}
}