{
  "type": "Feature",
  "properties": {
    "addr:full":"3921 Bell Blvd  Bayside NY 11361",
    "addr:housenumber":"3921",
    "addr:postcode":"11361",
    "addr:street":"Bell Blvd",
    "iso:country":"US",
    "sg:address":"3921 Bell Blvd ",
    "sg:city":"Bayside",
    "sg:classifiers":[
        {
            "category":"Restaurant",
            "type":"Food & Drink"
        }
    ],
    "sg:menulink":"http://www.allmenus.com/ny/queens/293291-bell-garden-chinese-restaurant/menu/",
    "sg:phone":"+1 718 279 1888",
    "sg:postcode":"11361",
    "sg:province":"NY",
    "sg:tags":[
        "chinese"
    ],
    "wof:name":"Bell Garden Chinese Restaurant",
    "wof:placetype":"venue"
},
  "geometry": {"coordinates":[-73.77158900000001,40.765101],"type":"Point"}
}