{
  "type": "Feature",
  "properties": {
    "addr:full":"10502 Northern Blvd Corona NY 11368",
    "addr:housenumber":"10502",
    "addr:postcode":"11368",
    "addr:street":"Northern Blvd",
    "iso:country":"US",
    "sg:address":"10502 Northern Blvd",
    "sg:city":"Corona",
    "sg:classifiers":[
        {
            "category":"Wholesale",
            "subcategory":"Stationery",
            "type":"Manufacturing & Wholesale Goods"
        }
    ],
    "sg:phone":"+1 718 458 0138",
    "sg:postcode":"11368",
    "sg:province":"NY",
    "sg:tags":[
        "card"
    ],
    "wof:name":"Kate's Card & Smoke Shop",
    "wof:placetype":"venue"
},
  "geometry": {"coordinates":[-73.863602,40.757599],"type":"Point"}
}