{
  "type": "Feature",
  "properties": {
    "iso:country":"US",
    "sg:address":"260 Main St",
    "sg:city":"Oneida",
    "sg:classifiers":[
        {
            "category":"Retail",
            "subcategory":"Funeral Services",
            "type":"Services"
        }
    ],
    "sg:phone":"+1 315 363 4020",
    "sg:postcode":"13421",
    "sg:province":"NY",
    "sg:tags":[
        "director"
    ],
    "wof:name":"Campbell-Dean Funeral Home Inc",
    "wof:placetype":"venue"
},
  "geometry": {"coordinates":[-75.650527,43.092484],"type":"Point"}
}