{
  "type": "Feature",
  "properties": {
    "addr:full":"5812 Mosholu Ave Bronx NY 10471",
    "addr:housenumber":"5812",
    "addr:postcode":"10471",
    "addr:street":"Mosholu Ave",
    "iso:country":"US",
    "sg:address":"5812 Mosholu Ave",
    "sg:city":"Bronx",
    "sg:classifiers":[
        {
            "category":"Shopping",
            "subcategory":"Clothing, Apparel, & Fashions",
            "type":"Retail Goods"
        }
    ],
    "sg:phone":"+1 718 549 6430",
    "sg:postcode":"10471",
    "sg:province":"NY",
    "sg:tags":[
        "tailor"
    ],
    "wof:name":"Rose Tailor",
    "wof:placetype":"venue"
},
  "geometry": {"coordinates":[-73.89712900000001,40.905095],"type":"Point"}
}