{
  "type": "Feature",
  "properties": {
    "iso:country":"US",
    "sg:address":"198 Burgoyne Ave",
    "sg:city":"Hudson Falls",
    "sg:classifiers":[
        {
            "category":"Autos & Motor Vehicles",
            "subcategory":"Auto Supplies",
            "type":"Retail Goods"
        }
    ],
    "sg:phone":"+1   ",
    "sg:postcode":"12839",
    "sg:province":"NY",
    "wof:name":"Advance Auto Parts",
    "wof:placetype":"venue"
},
  "geometry": {"coordinates":[-73.56371799999999,43.310418],"type":"Point"}
}