{
  "type": "Feature",
  "properties": {
    "addr:full":"175 Rivington Street New York NY 10002",
    "addr:housenumber":"175",
    "addr:postcode":"10002",
    "addr:street":"Rivington Street",
    "iso:country":"US",
    "sg:address":"175 Rivington Street",
    "sg:city":"New York",
    "sg:classifiers":[
        {
            "category":"Manufacturing",
            "subcategory":"Leather Goods",
            "type":"Manufacturing & Wholesale Goods"
        }
    ],
    "sg:phone":"+1 212 674 7610",
    "sg:postcode":"10002",
    "sg:province":"NY",
    "sg:website":"www.mhgstudio.com",
    "wof:name":"Mhg Studio",
    "wof:placetype":"venue"
},
  "geometry": {"coordinates":[-73.984362,40.718854],"type":"Point"}
}