{
  "type": "Feature",
  "properties": {
    "addr:full":"1125 North St Rochester NY 14621",
    "addr:housenumber":"1125",
    "addr:postcode":"14621",
    "addr:street":"North St",
    "iso:country":"US",
    "sg:address":"1125 North St",
    "sg:city":"Rochester",
    "sg:classifiers":[
        {
            "category":"Food & Beverages",
            "subcategory":"Groceries & Convenience Stores",
            "type":"Retail Goods"
        }
    ],
    "sg:phone":"+1 585 266 1230",
    "sg:postcode":"14621",
    "sg:province":"NY",
    "sg:tags":[
        "grocer"
    ],
    "wof:name":"Neighborhood Mini Mart",
    "wof:placetype":"venue"
},
  "geometry": {"coordinates":[-77.595437,43.178935],"type":"Point"}
}