{
  "type": "Feature",
  "properties": {
    "addr:full":"24 Colvin Ave Albany NY 12206",
    "addr:housenumber":"24",
    "addr:postcode":"12206",
    "addr:street":"Colvin Ave",
    "iso:country":"US",
    "sg:address":"24 Colvin Ave",
    "sg:city":"Albany",
    "sg:classifiers":[
        {
            "category":"Retail",
            "subcategory":"Repair Shop",
            "type":"Services"
        }
    ],
    "sg:phone":"+1 518 459 1611",
    "sg:postcode":"12206",
    "sg:province":"NY",
    "wof:name":"Otis Elevator Company",
    "wof:placetype":"venue"
},
  "geometry": {"coordinates":[-73.797206,42.676812],"type":"Point"}
}