{
  "type": "Feature",
  "properties": {
    "iso:country":"US",
    "sg:address":"230 Steuben St",
    "sg:city":"Montour Falls",
    "sg:classifiers":[
        {
            "category":"Health Services",
            "subcategory":"Doctor",
            "type":"Services"
        }
    ],
    "sg:phone":"+1 607 535 8618",
    "sg:postcode":"14865",
    "sg:province":"NY",
    "sg:tags":[
        "physician",
        "surgeon"
    ],
    "wof:name":"Lakeside Ob/Gyn",
    "wof:placetype":"venue"
},
  "geometry": {"coordinates":[-76.851179,42.346131],"type":"Point"}
}