{
  "type": "Feature",
  "properties": {
    "iso:country":"US",
    "sg:address":"273 Haviland Rd",
    "sg:city":"Queensbury",
    "sg:classifiers":[
        {
            "category":"Professional",
            "subcategory":"Research",
            "type":"Services"
        }
    ],
    "sg:phone":"+1 518 761 6605",
    "sg:postcode":"12804",
    "sg:province":"NY",
    "sg:tags":[
        "environmental",
        "ecological"
    ],
    "sg:website":"www.robertsenvironmental.com",
    "wof:name":"Roberts Environmental",
    "wof:placetype":"venue"
},
  "geometry": {"coordinates":[-73.651426,43.357364],"type":"Point"}
}