{
  "type": "Feature",
  "properties": {
    "addr:full":"91 US Hwy 9w West Haverstraw NY 10993",
    "addr:housenumber":"91",
    "addr:postcode":"10993",
    "addr:street":"Us Hwy 9W West",
    "iso:country":"US",
    "sg:address":"91 US Hwy 9w",
    "sg:city":"West Haverstraw",
    "sg:classifiers":[
        {
            "category":"Real Estate",
            "subcategory":"Real Estate Agent",
            "type":"Services"
        }
    ],
    "sg:phone":"+1 845 942 3798",
    "sg:postcode":"10993",
    "sg:province":"NY",
    "wof:name":"9w Plaza LLC",
    "wof:placetype":"venue"
},
  "geometry": {"coordinates":[-73.983718,41.202018],"type":"Point"}
}