{
  "type": "Feature",
  "properties": {
    "addr:full":"5657 Post Rd Bronx NY 10471",
    "addr:housenumber":"5657",
    "addr:postcode":"10471",
    "addr:street":"Post Rd",
    "iso:country":"US",
    "sg:address":"5657 Post Rd",
    "sg:city":"Bronx",
    "sg:classifiers":[
        {
            "category":"Insurance",
            "subcategory":"Insurance Agent",
            "type":"Services"
        }
    ],
    "sg:phone":"+1 718 549 8579",
    "sg:postcode":"10471",
    "sg:province":"NY",
    "sg:tags":[
        "agency",
        "advertising"
    ],
    "wof:name":"The Beck Agency",
    "wof:placetype":"venue"
},
  "geometry": {"coordinates":[-73.89752900000001,40.905249],"type":"Point"}
}