{
  "type": "Feature",
  "properties": {
    "addr:full":"265 Sunrise Hwy Rockville Centre NY 11570",
    "addr:housenumber":"265",
    "addr:postcode":"11570",
    "addr:street":"Sunrise Hwy",
    "iso:country":"US",
    "sg:address":"265 Sunrise Hwy",
    "sg:city":"Rockville Centre",
    "sg:classifiers":[
        {
            "category":"Manufacturing",
            "subcategory":"Textiles",
            "type":"Manufacturing & Wholesale Goods"
        }
    ],
    "sg:phone":"+1   ",
    "sg:postcode":"11570",
    "sg:province":"NY",
    "sg:tags":[
        "designer",
        "manufacturer",
        "intimate"
    ],
    "wof:name":"Fan-NY Sport Essentials Inc",
    "wof:placetype":"venue"
},
  "geometry": {"coordinates":[-73.645471,40.657524],"type":"Point"}
}