{
  "type": "Feature",
  "properties": {
    "iso:country":"US",
    "sg:address":"1515 46th St",
    "sg:city":"Brooklyn",
    "sg:classifiers":[
        {
            "category":"Place Of Worship",
            "subcategory":"Synagogue",
            "type":"Public Place"
        }
    ],
    "sg:phone":"+1 718 436 5082",
    "sg:postcode":"11219",
    "sg:province":"NY",
    "sg:website":"www.ptbas.org",
    "wof:name":"Progessive Temple Beth Ahavath Sholom",
    "wof:placetype":"venue"
},
  "geometry": {"coordinates":[-73.985353,40.63394],"type":"Point"}
}