{
  "type": "Feature",
  "properties": {
    "addr:full":"255 W Kingsbridge Rd Bronx NY 10463",
    "addr:housenumber":"255",
    "addr:postcode":"10463",
    "addr:street":"W Kingsbridge Rd",
    "iso:country":"US",
    "sg:address":"255 W Kingsbridge Rd",
    "sg:city":"Bronx",
    "sg:classifiers":[
        {
            "category":"Shopping",
            "subcategory":"Department Store",
            "type":"Retail Goods"
        }
    ],
    "sg:phone":"+1 718 549 5434",
    "sg:postcode":"10463",
    "sg:province":"NY",
    "sg:tags":[
        "shop"
    ],
    "wof:name":"Ramona's Discount Store",
    "wof:placetype":"venue"
},
  "geometry": {"coordinates":[-73.90556100000001,40.873127],"type":"Point"}
}