{
  "type": "Feature",
  "properties": {
    "iso:country":"US",
    "sg:address":"302 Ocean Ave",
    "sg:city":"Massapequa",
    "sg:classifiers":[
        {
            "category":"Organizations",
            "subcategory":"Religious Organization",
            "type":"Services"
        }
    ],
    "sg:phone":"+1 516 799 5158",
    "sg:postcode":"11758",
    "sg:province":"NY",
    "sg:tags":[
        "child",
        "day",
        "care"
    ],
    "wof:name":"Massapequa Reformed Church",
    "wof:placetype":"venue"
},
  "geometry": {"coordinates":[-73.47055400000001,40.668265],"type":"Point"}
}