{
  "type": "Feature",
  "properties": {
    "addr:full":"20 Carleton Ave Central Islip NY 11722",
    "addr:housenumber":"20",
    "addr:postcode":"11722",
    "addr:street":"Carleton Ave",
    "iso:country":"US",
    "sg:address":"20 Carleton Ave",
    "sg:city":"Central Islip",
    "sg:classifiers":[
        {
            "category":"Personal",
            "type":"Services"
        },
        {
            "category":"Retail",
            "subcategory":"Laundry & Dry Cleaning",
            "type":"Services"
        },
        {
            "category":"Personal",
            "subcategory":"Shoe Repair & Shine",
            "type":"Services"
        }
    ],
    "sg:phone":"+1 631 234 0747",
    "sg:postcode":"11722",
    "sg:province":"NY",
    "sg:tags":[
        "sewing",
        "alteration"
    ],
    "wof:name":"Towne Cleaners & Laundromat",
    "wof:placetype":"venue"
},
  "geometry": {"coordinates":[-73.20169799999999,40.7896],"type":"Point"}
}