{
  "type": "Feature",
  "properties": {
    "iso:country":"US",
    "sg:address":"1031 N 2nd St",
    "sg:city":"New Hyde Park",
    "sg:classifiers":[
        {
            "category":"Freight",
            "type":"Transportation"
        }
    ],
    "sg:phone":"+1   ",
    "sg:postcode":"11040",
    "sg:province":"NY",
    "sg:tags":[
        "operator",
        "local",
        "trucking"
    ],
    "wof:name":"G&H Road Service Inc",
    "wof:placetype":"venue"
},
  "geometry": {"coordinates":[-73.69844999999999,40.738971],"type":"Point"}
}