{
  "type": "Feature",
  "properties": {
    "iso:country":"US",
    "sg:address":"447 Boston Post Rd",
    "sg:city":"Port Chester",
    "sg:classifiers":[
        {
            "category":"Utilities",
            "subcategory":"Telephone",
            "type":"Services"
        }
    ],
    "sg:phone":"+1   ",
    "sg:postcode":"10573",
    "sg:province":"NY",
    "sg:tags":[
        "communications",
        "merchandise"
    ],
    "wof:name":"Sprint P C S",
    "wof:placetype":"venue"
},
  "geometry": {"coordinates":[-73.67447199999999,40.994033],"type":"Point"}
}