{
  "type": "Feature",
  "properties": {
    "addr:full":"321 W 44th St New York NY 10036",
    "addr:housenumber":"321",
    "addr:postcode":"10036",
    "addr:street":"W 44Th St",
    "iso:country":"US",
    "sg:address":"321 W 44th St",
    "sg:city":"New York",
    "sg:classifiers":[
        {
            "category":"Professional",
            "subcategory":"Management & Consulting",
            "type":"Services"
        }
    ],
    "sg:phone":"+1 212 246 5111",
    "sg:postcode":"10036",
    "sg:province":"NY",
    "wof:name":"C P S",
    "wof:placetype":"venue"
},
  "geometry": {"coordinates":[-73.991208,40.75955],"type":"Point"}
}