{
  "type": "Feature",
  "properties": {
    "iso:country":"US",
    "sg:address":"1611 Keenan Rd",
    "sg:city":"Rexville",
    "sg:classifiers":[
        {
            "category":"Home & Garden",
            "subcategory":"Home Furnishings",
            "type":"Retail Goods"
        }
    ],
    "sg:phone":"+1   ",
    "sg:postcode":"14877",
    "sg:province":"NY",
    "wof:name":"Young Sapling Pottery",
    "wof:placetype":"venue"
},
  "geometry": {"coordinates":[-77.700153,42.078139],"type":"Point"}
}