{
  "type": "Feature",
  "properties": {
    "addr:full":"98 Funston Ave Albertson NY 11507",
    "addr:housenumber":"98",
    "addr:postcode":"11507",
    "addr:street":"Funston Ave",
    "iso:country":"US",
    "sg:address":"98 Funston Ave",
    "sg:city":"Albertson",
    "sg:classifiers":[
        {
            "category":"Autos & Motor Vehicles",
            "subcategory":"Automobile Sales",
            "type":"Retail Goods"
        }
    ],
    "sg:phone":"+1   ",
    "sg:postcode":"11507",
    "sg:province":"NY",
    "wof:name":"Auto Nima Co Inc",
    "wof:placetype":"venue"
},
  "geometry": {"coordinates":[-73.649227,40.767054],"type":"Point"}
}