{
  "type": "Feature",
  "properties": {
    "iso:country":"US",
    "sg:address":"20 All Angels Hill Rd",
    "sg:city":"Wappingers Falls",
    "sg:classifiers":[
        {
            "category":"Building & Trades",
            "subcategory":"Equipment Rental",
            "type":"Services"
        }
    ],
    "sg:phone":"+1 845 463 3851",
    "sg:postcode":"12590",
    "sg:province":"NY",
    "sg:tags":[
        "heavy",
        "rent"
    ],
    "wof:name":"Albany Ladder",
    "wof:placetype":"venue"
},
  "geometry": {"coordinates":[-73.87475999999999,41.62266],"type":"Point"}
}