{
  "type": "Feature",
  "properties": {
    "addr:full":"347 W 44th St New York NY 10036",
    "addr:housenumber":"347",
    "addr:postcode":"10036",
    "addr:street":"W 44Th St",
    "iso:country":"US",
    "sg:address":"347 W 44th St",
    "sg:city":"New York",
    "sg:classifiers":[
        {
            "category":"Real Estate",
            "subcategory":"Real Estate Operator",
            "type":"Services"
        }
    ],
    "sg:phone":"+1 212 265 6500",
    "sg:postcode":"10036",
    "sg:province":"NY",
    "sg:tags":[
        "apartment",
        "management",
        "complex"
    ],
    "wof:name":"14 Bc Apartment Corporation",
    "wof:placetype":"venue"
},
  "geometry": {"coordinates":[-73.99063700000001,40.759233],"type":"Point"}
}