{
  "type": "Feature",
  "properties": {
    "iso:country":"US",
    "sg:address":"7 Mercer St",
    "sg:city":"New York",
    "sg:classifiers":[
        {
            "category":"Museum",
            "type":"Entertainment"
        }
    ],
    "sg:phone":"+1   ",
    "sg:postcode":"10013",
    "sg:province":"NY",
    "sg:tags":[
        "gallery"
    ],
    "sg:website":"www.grantgallery.com",
    "wof:name":"Grant Gallery",
    "wof:placetype":"venue"
},
  "geometry": {"coordinates":[-74.001447,40.721252],"type":"Point"}
}