{
  "type": "Feature",
  "properties": {
    "iso:country":"US",
    "sg:address":"351 Independence Plz",
    "sg:city":"Selden",
    "sg:classifiers":[
        {
            "category":"Bagels",
            "subcategory":"None",
            "type":"Food & Drink"
        }
    ],
    "sg:phone":"+1 631 736 7255",
    "sg:postcode":"11784",
    "sg:province":"NY",
    "wof:name":"Strathmore Bagels",
    "wof:placetype":"venue"
},
  "geometry": {"coordinates":[-73.05210099999999,40.863701],"type":"Point"}
}