{
  "type": "Feature",
  "properties": {
    "iso:country":"US",
    "sg:address":"804 Main St",
    "sg:city":"Center Moriches",
    "sg:classifiers":[
        {
            "category":"Personal",
            "subcategory":"Barber",
            "type":"Services"
        }
    ],
    "sg:phone":"+1 631 874 2182",
    "sg:postcode":"11934",
    "sg:province":"NY",
    "wof:name":"Instyle Barber & Beauty Shop",
    "wof:placetype":"venue"
},
  "geometry": {"coordinates":[-72.806099,40.801998],"type":"Point"}
}