{
  "type": "Feature",
  "properties": {
    "addr:full":"285 Greenwich St New York NY 10007",
    "addr:housenumber":"285",
    "addr:postcode":"10007",
    "addr:street":"Greenwich St",
    "iso:country":"US",
    "sg:address":"285 Greenwich St",
    "sg:city":"New York",
    "sg:classifiers":[
        {
            "category":"Retail",
            "subcategory":"Auto Repair",
            "type":"Services"
        }
    ],
    "sg:phone":"+1 212 993 8248",
    "sg:postcode":"10007",
    "sg:province":"NY",
    "sg:tags":[
        "towing",
        "wrecker"
    ],
    "wof:name":"A Emergency Towing 24 Hr",
    "wof:placetype":"venue"
},
  "geometry": {"coordinates":[-74.011101,40.716099],"type":"Point"}
}