{
  "type": "Feature",
  "properties": {
    "addr:full":"2870 Knight Rd Waterloo NY 13165",
    "addr:housenumber":"2870",
    "addr:postcode":"13165",
    "addr:street":"Knight Rd",
    "iso:country":"US",
    "sg:address":"2870 Knight Rd",
    "sg:city":"Waterloo",
    "sg:classifiers":[
        {
            "category":"Shopping",
            "subcategory":"Bicycles & Sporting Goods",
            "type":"Retail Goods"
        }
    ],
    "sg:phone":"+1   ",
    "sg:postcode":"13165",
    "sg:province":"NY",
    "wof:name":"Ten Point Archery",
    "wof:placetype":"venue"
},
  "geometry": {"coordinates":[-76.89524299999999,42.885229],"type":"Point"}
}