{
  "type": "Feature",
  "properties": {
    "addr:full":"396 Palmer Ave Mamaroneck NY 10543",
    "addr:housenumber":"396",
    "addr:postcode":"10543",
    "addr:street":"Palmer Ave",
    "iso:country":"US",
    "sg:address":"396 Palmer Ave",
    "sg:city":"Mamaroneck",
    "sg:classifiers":[
        {
            "category":"Shopping",
            "subcategory":"Discount & Variety Stores",
            "type":"Retail Goods"
        }
    ],
    "sg:phone":"+1   ",
    "sg:postcode":"10543",
    "sg:province":"NY",
    "sg:tags":[
        "stationery"
    ],
    "wof:name":"Labh",
    "wof:placetype":"venue"
},
  "geometry": {"coordinates":[-73.73722600000001,40.949979],"type":"Point"}
}