{
  "type": "Feature",
  "properties": {
    "addr:full":"3787 W Seneca Tpke Syracuse NY 13215",
    "addr:housenumber":"3787",
    "addr:postcode":"13215",
    "addr:street":"W Seneca Tpke",
    "iso:country":"US",
    "sg:address":"3787 W Seneca Tpke",
    "sg:city":"Syracuse",
    "sg:classifiers":[
        {
            "category":"Shopping",
            "subcategory":"Gifts & Souvenirs",
            "type":"Retail Goods"
        }
    ],
    "sg:phone":"+1 315 378 0076",
    "sg:postcode":"13215",
    "sg:province":"NY",
    "sg:tags":[
        "shop"
    ],
    "wof:name":"Kelly's Country Cupboard",
    "wof:placetype":"venue"
},
  "geometry": {"coordinates":[-76.251456,42.988972],"type":"Point"}
}