{
  "type": "Feature",
  "properties": {
    "iso:country":"US",
    "sg:address":"373 Nesconset Hwy",
    "sg:city":"Hauppauge",
    "sg:classifiers":[
        {
            "category":"Shopping",
            "subcategory":"Computers & Home Electronics",
            "type":"Retail Goods"
        }
    ],
    "sg:phone":"+1   ",
    "sg:postcode":"11788",
    "sg:province":"NY",
    "wof:name":"Lrl Computer Inc",
    "wof:placetype":"venue"
},
  "geometry": {"coordinates":[-73.175686,40.842791],"type":"Point"}
}