{
  "type": "Feature",
  "properties": {
    "iso:country":"US",
    "sg:address":"383 S Broadway",
    "sg:city":"Hicksville",
    "sg:classifiers":[
        {
            "category":"Communications",
            "subcategory":"Film & Video Production",
            "type":"Services"
        }
    ],
    "sg:phone":"+1 516 935 1492",
    "sg:postcode":"11801",
    "sg:province":"NY",
    "sg:tags":[
        "taping"
    ],
    "sg:website":"www.reeltoreelvideo.net",
    "wof:name":"Reel To Reel Video",
    "wof:placetype":"venue"
},
  "geometry": {"coordinates":[-73.51267799999999,40.758611],"type":"Point"}
}