{
  "type": "Feature",
  "properties": {
    "addr:full":"8018 5th Ave Brooklyn NY 11209",
    "addr:housenumber":"8018",
    "addr:postcode":"11209",
    "addr:street":"5Th Ave",
    "iso:country":"US",
    "sg:address":"8018 5th Ave",
    "sg:city":"Brooklyn",
    "sg:classifiers":[
        {
            "category":"Food & Beverages",
            "subcategory":"Meat & Fish",
            "type":"Retail Goods"
        }
    ],
    "sg:phone":"+1 718 491 0492",
    "sg:postcode":"11209",
    "sg:province":"NY",
    "sg:tags":[
        "seafood"
    ],
    "wof:name":"Ellen's Fish Market",
    "wof:placetype":"venue"
},
  "geometry": {"coordinates":[-74.024479,40.625205],"type":"Point"}
}