{
  "type": "Feature",
  "properties": {
    "iso:country":"US",
    "sg:address":"1577 57th St",
    "sg:city":"Brooklyn",
    "sg:classifiers":[
        {
            "category":"Autos & Motor Vehicles",
            "subcategory":"Automobile Sales",
            "type":"Retail Goods"
        }
    ],
    "sg:phone":"+1 718 972 2345",
    "sg:postcode":"11219",
    "sg:province":"NY",
    "sg:tags":[
        "car",
        "dealer"
    ],
    "wof:name":"King Hersh Auto Sales Inc",
    "wof:placetype":"venue"
},
  "geometry": {"coordinates":[-73.99142500000001,40.627645],"type":"Point"}
}