{
  "type": "Feature",
  "properties": {
    "addr:full":"3820 Fillmore Ave Brooklyn NY 11234",
    "addr:housenumber":"3820",
    "addr:postcode":"11234",
    "addr:street":"Fillmore Ave",
    "iso:country":"US",
    "sg:address":"3820 Fillmore Ave",
    "sg:city":"Brooklyn",
    "sg:classifiers":[
        {
            "category":"Home & Garden",
            "subcategory":"Household Appliances",
            "type":"Retail Goods"
        }
    ],
    "sg:phone":"+1 718 859 4732",
    "sg:postcode":"11234",
    "sg:province":"NY",
    "sg:tags":[
        "small",
        "repair"
    ],
    "wof:name":"After Hour Refrigeration Svce",
    "wof:placetype":"venue"
},
  "geometry": {"coordinates":[-73.931099,40.612598],"type":"Point"}
}