{
  "type": "Feature",
  "properties": {
    "addr:full":"1405 36th St Brooklyn NY 11218",
    "addr:housenumber":"1405",
    "addr:postcode":"11218",
    "addr:street":"36Th St",
    "iso:country":"US",
    "sg:address":"1405 36th St",
    "sg:city":"Brooklyn",
    "sg:classifiers":[
        {
            "category":"Restaurant",
            "type":"Food & Drink"
        }
    ],
    "sg:phone":"+1 212 431 1515",
    "sg:postcode":"11218",
    "sg:province":"NY",
    "sg:tags":[
        "house",
        "steak"
    ],
    "wof:name":"Bonanza Corp",
    "wof:placetype":"venue"
},
  "geometry": {"coordinates":[-73.982249,40.640907],"type":"Point"}
}