{
  "type": "Feature",
  "properties": {
    "addr:full":"64 Ryan Pl Staten Island NY 10312",
    "addr:housenumber":"64",
    "addr:postcode":"10312",
    "addr:street":"Ryan Pl",
    "iso:country":"US",
    "sg:address":"64 Ryan Pl",
    "sg:city":"Staten Island",
    "sg:classifiers":[
        {
            "category":"Professional",
            "subcategory":"Management & Consulting",
            "type":"Services"
        }
    ],
    "sg:phone":"+1   ",
    "sg:postcode":"10312",
    "sg:province":"NY",
    "wof:name":"J S Consulting",
    "wof:placetype":"venue"
},
  "geometry": {"coordinates":[-74.166977,40.527537],"type":"Point"}
}