{
  "type": "Feature",
  "properties": {
    "addr:full":"341 W 38th St Fl 9 New York NY 10018",
    "addr:housenumber":"341;9",
    "addr:postcode":"new;10018",
    "addr:street":"W 38Th St",
    "iso:country":"US",
    "sg:address":"341 W 38th St Fl 9",
    "sg:city":"New York",
    "sg:classifiers":[
        {
            "category":"Building & Trades",
            "subcategory":"Construction",
            "type":"Services"
        }
    ],
    "sg:phone":"+1 212 613 1700",
    "sg:postcode":"10018",
    "sg:province":"NY",
    "sg:tags":[
        "contractor"
    ],
    "wof:name":"Plaza Construction Corp",
    "wof:placetype":"venue"
},
  "geometry": {"coordinates":[-73.99391900000001,40.755821],"type":"Point"}
}