{
  "type": "Feature",
  "properties": {
    "addr:full":"1345 Avenue of the Americas New York NY 10105",
    "addr:housenumber":"1345",
    "addr:postcode":"10105",
    "addr:street":"Avenue Of The Americas",
    "iso:country":"US",
    "sg:address":"1345 Avenue of the Americas",
    "sg:city":"New York",
    "sg:classifiers":[
        {
            "category":"Banks & Credit Unions",
            "subcategory":"Bank",
            "type":"Services"
        }
    ],
    "sg:phone":"+1 212 757 2049",
    "sg:postcode":"10105",
    "sg:province":"NY",
    "wof:name":"BBVA Compass",
    "wof:placetype":"venue"
},
  "geometry": {"coordinates":[-73.978544,40.762748],"type":"Point"}
}