{
  "type": "Feature",
  "properties": {
    "iso:country":"US",
    "sg:address":"9 Country Rd",
    "sg:city":"Mamaroneck",
    "sg:classifiers":[
        {
            "category":"Organizations",
            "subcategory":"Professional Association",
            "type":"Services"
        }
    ],
    "sg:phone":"+1   ",
    "sg:postcode":"10543",
    "sg:province":"NY",
    "wof:name":"Laurence Greenhill Dr",
    "wof:placetype":"venue"
},
  "geometry": {"coordinates":[-73.747242,40.952439],"type":"Point"}
}