{
  "type": "Feature",
  "properties": {
    "addr:full":"1232 Virginia Ave Bronx NY 10472",
    "addr:housenumber":"1232",
    "addr:postcode":"10472",
    "addr:street":"Virginia Ave",
    "iso:country":"US",
    "sg:address":"1232 Virginia Ave",
    "sg:city":"Bronx",
    "sg:classifiers":[
        {
            "category":"Personal",
            "subcategory":"Beauty Salon",
            "type":"Services"
        }
    ],
    "sg:phone":"+1   ",
    "sg:postcode":"10472",
    "sg:province":"NY",
    "sg:tags":[
        "shop"
    ],
    "wof:name":"Charos Unisex Salon Inc",
    "wof:placetype":"venue"
},
  "geometry": {"coordinates":[-73.861116,40.832016],"type":"Point"}
}