{
  "type": "Feature",
  "properties": {
    "iso:country":"US",
    "sg:address":"1454 42nd St",
    "sg:city":"Brooklyn",
    "sg:classifiers":[
        {
            "category":"Shopping",
            "subcategory":"Clothing, Apparel, & Fashions",
            "type":"Retail Goods"
        }
    ],
    "sg:phone":"+1   ",
    "sg:postcode":"11219",
    "sg:province":"NY",
    "wof:name":"Jacks Corp",
    "wof:placetype":"venue"
},
  "geometry": {"coordinates":[-73.984601,40.63696],"type":"Point"}
}