{
  "type": "Feature",
  "properties": {
    "iso:country":"US",
    "sg:address":"1 Linden Pl",
    "sg:city":"Great Neck",
    "sg:classifiers":[
        {
            "category":"Professional",
            "subcategory":"Advertising",
            "type":"Services"
        }
    ],
    "sg:phone":"+1 516 829 2323",
    "sg:postcode":"11021",
    "sg:province":"NY",
    "sg:tags":[
        "agency"
    ],
    "wof:name":"Popofsky Advertising Inc",
    "wof:placetype":"venue"
},
  "geometry": {"coordinates":[-73.72366100000001,40.788413],"type":"Point"}
}