{
  "type": "Feature",
  "properties": {
    "addr:full":"35 Alpine Rd Yonkers NY 10710",
    "addr:housenumber":"35",
    "addr:postcode":"10710",
    "addr:street":"Alpine Rd",
    "iso:country":"US",
    "sg:address":"35 Alpine Rd",
    "sg:city":"Yonkers",
    "sg:classifiers":[
        {
            "category":"Shopping",
            "subcategory":"Hobbies, Toys, & Games",
            "type":"Retail Goods"
        }
    ],
    "sg:phone":"+1 718 229 7600",
    "sg:postcode":"10710",
    "sg:province":"NY",
    "sg:tags":[
        "hobby",
        "model",
        "shop"
    ],
    "wof:name":"Dpk Hobbies",
    "wof:placetype":"venue"
},
  "geometry": {"coordinates":[-73.82911199999999,40.966707],"type":"Point"}
}