{
  "type": "Feature",
  "properties": {
    "addr:full":"2120 Ryer Ave Bronx NY 10457",
    "addr:housenumber":"2120",
    "addr:postcode":"10457",
    "addr:street":"Ryer Ave",
    "iso:country":"US",
    "sg:address":"2120 Ryer Ave",
    "sg:city":"Bronx",
    "sg:classifiers":[
        {
            "category":"Government",
            "subcategory":"Police Station",
            "type":"Public Place"
        }
    ],
    "sg:phone":"+1 718 220 5211",
    "sg:postcode":"10457",
    "sg:province":"NY",
    "sg:tags":[
        "department"
    ],
    "wof:name":"Bronx 46th Precinct Police",
    "wof:placetype":"venue"
},
  "geometry": {"coordinates":[-73.900445,40.853535],"type":"Point"}
}