{
  "type": "Feature",
  "properties": {
    "iso:country":"US",
    "sg:address":"928 E 16th St",
    "sg:city":"Brooklyn",
    "sg:classifiers":[
        {
            "category":"Organizations",
            "subcategory":"Religious Organization",
            "type":"Services"
        }
    ],
    "sg:phone":"+1 718 338 0312",
    "sg:postcode":"11230",
    "sg:province":"NY",
    "sg:tags":[
        "clergy"
    ],
    "wof:name":"Beatrice Rosenfeld",
    "wof:placetype":"venue"
},
  "geometry": {"coordinates":[-73.960638,40.625955],"type":"Point"}
}