{
  "type": "Feature",
  "properties": {
    "addr:full":"17 Waite St Norwich NY 13815",
    "addr:housenumber":"17",
    "addr:postcode":"13815",
    "addr:street":"Waite St",
    "iso:country":"US",
    "sg:address":"17 Waite St",
    "sg:city":"Norwich",
    "sg:classifiers":[
        {
            "category":"Home & Garden",
            "subcategory":"Building Materials",
            "type":"Retail Goods"
        },
        {
            "category":"Retail",
            "subcategory":"Auto Repair",
            "type":"Services"
        }
    ],
    "sg:phone":"+1 607 336 1993",
    "sg:postcode":"13815",
    "sg:province":"NY",
    "sg:tags":[
        "plate",
        "residential",
        "commercial",
        "glass",
        "window",
        "replacement"
    ],
    "wof:name":"Chenango Glass Co",
    "wof:placetype":"venue"
},
  "geometry": {"coordinates":[-75.520476,42.539354],"type":"Point"}
}