{
  "type": "Feature",
  "properties": {
    "addr:full":"798 Grand Blvd Deer Park NY 11729",
    "addr:housenumber":"798",
    "addr:postcode":"11729",
    "addr:street":"Grand Blvd",
    "iso:country":"US",
    "sg:address":"798 Grand Blvd",
    "sg:city":"Deer Park",
    "sg:classifiers":[
        {
            "category":"Insurance",
            "subcategory":"Insurance Agent",
            "type":"Services"
        }
    ],
    "sg:phone":"+1 631 254 9400",
    "sg:postcode":"11729",
    "sg:province":"NY",
    "wof:name":"Allstate Insurance Co",
    "wof:placetype":"venue"
},
  "geometry": {"coordinates":[-73.308485,40.761469],"type":"Point"}
}