{
  "type": "Feature",
  "properties": {
    "addr:full":"109 E 157th St Bronx NY 10451",
    "addr:housenumber":"109",
    "addr:postcode":"10451",
    "addr:street":"E 157Th St",
    "iso:country":"US",
    "sg:address":"109 E 157th St",
    "sg:city":"Bronx",
    "sg:classifiers":[
        {
            "category":"Recreation",
            "type":"Entertainment"
        }
    ],
    "sg:phone":"+1 718 401 7450",
    "sg:postcode":"10451",
    "sg:province":"NY",
    "sg:tags":[
        "club",
        "baseball"
    ],
    "wof:name":"United Youth Baseball League",
    "wof:placetype":"venue"
},
  "geometry": {"coordinates":[-73.92647599999999,40.825604],"type":"Point"}
}