{
  "type": "Feature",
  "properties": {
    "iso:country":"US",
    "sg:address":"43 Division St",
    "sg:city":"Norwich",
    "sg:classifiers":[
        {
            "category":"Personal",
            "subcategory":"Barber",
            "type":"Services"
        }
    ],
    "sg:phone":"+1   ",
    "sg:postcode":"13815",
    "sg:province":"NY",
    "sg:tags":[
        "shop"
    ],
    "wof:name":"Attilios Barber Shop",
    "wof:placetype":"venue"
},
  "geometry": {"coordinates":[-75.518626,42.524658],"type":"Point"}
}