{
  "type": "Feature",
  "properties": {
    "addr:full":"406 Route 52 Carmel NY 10512",
    "addr:housenumber":"406",
    "addr:postcode":"10512",
    "addr:street":"Route 52",
    "iso:country":"US",
    "sg:address":"406 Route 52",
    "sg:city":"Carmel",
    "sg:classifiers":[
        {
            "category":"Personal",
            "type":"Services"
        }
    ],
    "sg:phone":"+1 845 225 9467",
    "sg:postcode":"10512",
    "sg:province":"NY",
    "sg:tags":[
        "sewing",
        "alteration"
    ],
    "wof:name":"La Russell's Laundry & Dry Clng Inc",
    "wof:placetype":"venue"
},
  "geometry": {"coordinates":[-73.67284100000001,41.448199],"type":"Point"}
}