{
  "type": "Feature",
  "properties": {
    "addr:full":"346 Miller Ave Brooklyn NY 11207",
    "addr:housenumber":"346",
    "addr:postcode":"11207",
    "addr:street":"Miller Ave",
    "iso:country":"US",
    "sg:address":"346 Miller Ave",
    "sg:city":"Brooklyn",
    "sg:classifiers":[
        {
            "category":"Shopping",
            "subcategory":"Jewelry",
            "type":"Retail Goods"
        }
    ],
    "sg:phone":"+1 347 221 0564",
    "sg:postcode":"11207",
    "sg:province":"NY",
    "wof:name":"E's Gold Exchange",
    "wof:placetype":"venue"
},
  "geometry": {"coordinates":[-73.891373,40.672414],"type":"Point"}
}