{
  "type": "Feature",
  "properties": {
    "addr:full":"112 W 31 St New York NY 10001",
    "addr:housenumber":"112",
    "addr:postcode":"10001",
    "addr:street":"W 31 St",
    "iso:country":"US",
    "sg:address":"112 W 31 St",
    "sg:city":"New York",
    "sg:classifiers":[
        {
            "category":"Manufacturing",
            "subcategory":"Printing",
            "type":"Manufacturing & Wholesale Goods"
        }
    ],
    "sg:phone":"+1 212 787 4021",
    "sg:postcode":"10001",
    "sg:province":"NY",
    "sg:tags":[
        "printer"
    ],
    "wof:name":"Fannin Graphics Inc",
    "wof:placetype":"venue"
},
  "geometry": {"coordinates":[-73.99177899999999,40.748887],"type":"Point"}
}