{
  "type": "Feature",
  "properties": {
    "iso:country":"US",
    "sg:address":"135 E 55 St",
    "sg:city":"New York",
    "sg:classifiers":[
        {
            "category":"Professional",
            "type":"Services"
        }
    ],
    "sg:phone":"+1 212 688 5229",
    "sg:postcode":"10022",
    "sg:province":"NY",
    "sg:tags":[
        "establishment"
    ],
    "wof:name":"Bruno Design",
    "wof:placetype":"venue"
},
  "geometry": {"coordinates":[-73.96848,40.75895],"type":"Point"}
}