{
  "type": "Feature",
  "properties": {
    "iso:country":"US",
    "sg:address":"24 Walton Ter",
    "sg:city":"Monroe",
    "sg:classifiers":[
        {
            "category":"Professional",
            "type":"Services"
        }
    ],
    "sg:phone":"+1   ",
    "sg:postcode":"10950",
    "sg:province":"NY",
    "wof:name":"Lettering By Linda",
    "wof:placetype":"venue"
},
  "geometry": {"coordinates":[-74.21707000000001,41.312944],"type":"Point"}
}