{
  "type": "Feature",
  "properties": {
    "addr:full":"81 Forest Ave Jamestown NY 14701",
    "addr:housenumber":"81",
    "addr:postcode":"14701",
    "addr:street":"Forest Ave",
    "iso:country":"US",
    "sg:address":"81 Forest Ave",
    "sg:city":"Jamestown",
    "sg:classifiers":[
        {
            "category":"Professional",
            "subcategory":"Lawyer & Legal Services",
            "type":"Services"
        }
    ],
    "sg:phone":"+1 716 484 2600",
    "sg:postcode":"14701",
    "sg:province":"NY",
    "sg:tags":[
        "attorney"
    ],
    "wof:name":"Siegel Keller & Kahn",
    "wof:placetype":"venue"
},
  "geometry": {"coordinates":[-79.240596,42.09025],"type":"Point"}
}