{
  "type": "Feature",
  "properties": {
    "addr:full":"34 Placid Ln Glenmont NY 12077",
    "addr:housenumber":"34",
    "addr:postcode":"12077",
    "addr:street":"Placid Ln",
    "iso:country":"US",
    "sg:address":"34 Placid Ln",
    "sg:city":"Glenmont",
    "sg:classifiers":[
        {
            "category":"Professional",
            "subcategory":"Research",
            "type":"Services"
        }
    ],
    "sg:phone":"+1   ",
    "sg:postcode":"12077",
    "sg:province":"NY",
    "sg:tags":[
        "organization",
        "noncommercial"
    ],
    "wof:name":"Aids Vaccine Research Inst",
    "wof:placetype":"venue"
},
  "geometry": {"coordinates":[-73.803299,42.591504],"type":"Point"}
}