{
  "type": "Feature",
  "properties": {
    "addr:full":"250 Knickerbocker Ave Bohemia NY 11716",
    "addr:housenumber":"250",
    "addr:postcode":"11716",
    "addr:street":"Knickerbocker Ave",
    "iso:country":"US",
    "sg:address":"250 Knickerbocker Ave",
    "sg:city":"Bohemia",
    "sg:classifiers":[
        {
            "category":"Manufacturing",
            "subcategory":"Building Materials",
            "type":"Manufacturing & Wholesale Goods"
        },
        {
            "category":"Manufacturing",
            "subcategory":"Tools & Machinery",
            "type":"Manufacturing & Wholesale Goods"
        }
    ],
    "sg:phone":"+1 631 563 0640",
    "sg:postcode":"11716",
    "sg:province":"NY",
    "sg:tags":[
        "industrial",
        "mfg"
    ],
    "wof:name":"De Rosa Fabrications Inc",
    "wof:placetype":"venue"
},
  "geometry": {"coordinates":[-73.087439,40.776705],"type":"Point"}
}