{
  "type": "Feature",
  "properties": {
    "addr:full":"1763 Victory Blvd Staten Island NY 10314",
    "addr:housenumber":"1763",
    "addr:postcode":"10314",
    "addr:street":"Victory Blvd",
    "iso:country":"US",
    "sg:address":"1763 Victory Blvd",
    "sg:city":"Staten Island",
    "sg:classifiers":[
        {
            "category":"Shopping",
            "type":"Retail Goods"
        }
    ],
    "sg:phone":"+1   ",
    "sg:postcode":"10314",
    "sg:province":"NY",
    "sg:tags":[
        "merchandise"
    ],
    "wof:name":"Marisch Child Wear & Gifts",
    "wof:placetype":"venue"
},
  "geometry": {"coordinates":[-74.12174400000001,40.613233],"type":"Point"}
}