{
  "type": "Feature",
  "properties": {
    "iso:country":"US",
    "sg:address":"9 George Sickles Rd",
    "sg:city":"Saugerties",
    "sg:classifiers":[
        {
            "category":"Wholesale",
            "subcategory":"Auto Parts",
            "type":"Manufacturing & Wholesale Goods"
        }
    ],
    "sg:phone":"+1 845 246 7140",
    "sg:postcode":"12477",
    "sg:province":"NY",
    "sg:tags":[
        "tire"
    ],
    "wof:name":"Pole Dancer Inc",
    "wof:placetype":"venue"
},
  "geometry": {"coordinates":[-74.023787,42.07507],"type":"Point"}
}