{
  "type": "Feature",
  "properties": {
    "addr:full":"9380 Wehrle Dr Clarence NY 14031",
    "addr:postcode":"9380;14031",
    "addr:street":"Wehrle Dr",
    "iso:country":"US",
    "sg:address":"9380 Wehrle Dr",
    "sg:city":"Clarence",
    "sg:classifiers":[
        {
            "category":"Building & Trades",
            "subcategory":"Construction",
            "type":"Services"
        }
    ],
    "sg:phone":"+1 716 759 0972",
    "sg:postcode":"14031",
    "sg:province":"NY",
    "sg:tags":[
        "wallcoverings-installation",
        "wallpaper",
        "painting",
        "contractor"
    ],
    "wof:name":"Decor Painting",
    "wof:placetype":"venue"
},
  "geometry": {"coordinates":[-78.642717,42.958772],"type":"Point"}
}