{
  "type": "Feature",
  "properties": {
    "iso:country":"US",
    "sg:address":"929 Brooker Hollow Rd",
    "sg:city":"Richmondville",
    "sg:classifiers":[
        {
            "category":"Professional",
            "subcategory":"Computer Services",
            "type":"Services"
        }
    ],
    "sg:phone":"+1 518 294 6338",
    "sg:postcode":"12149",
    "sg:province":"NY",
    "sg:tags":[
        "technical",
        "assistance",
        "support"
    ],
    "wof:name":"Robert Nied Consultancy Group",
    "wof:placetype":"venue"
},
  "geometry": {"coordinates":[-74.585047,42.626998],"type":"Point"}
}