{
  "type": "Feature",
  "properties": {
    "addr:full":"19320 US Route 11 Watertown NY 13601",
    "addr:housenumber":"19320",
    "addr:postcode":"13601",
    "addr:street":"Us Route 11",
    "iso:country":"US",
    "sg:address":"19320 US Route 11",
    "sg:city":"Watertown",
    "sg:classifiers":[
        {
            "category":"Health Services",
            "subcategory":"Doctor",
            "type":"Services"
        }
    ],
    "sg:phone":"+1 315 782 7298",
    "sg:postcode":"13601",
    "sg:province":"NY",
    "sg:tags":[
        "physician",
        "surgeon"
    ],
    "wof:name":"Ashok Seetharaman Md",
    "wof:placetype":"venue"
},
  "geometry": {"coordinates":[-75.91539,43.94644],"type":"Point"}
}