{
  "type": "Feature",
  "properties": {
    "iso:country":"US",
    "sg:address":"30 Jericho Executive Plz",
    "sg:city":"Jericho",
    "sg:classifiers":[
        {
            "category":"Professional",
            "subcategory":"Lawyer & Legal Services",
            "type":"Services"
        }
    ],
    "sg:phone":"+1 516 876 9600",
    "sg:postcode":"11753",
    "sg:province":"NY",
    "wof:name":"Rovegno & Taylor PC",
    "wof:placetype":"venue"
},
  "geometry": {"coordinates":[-73.56729900000001,40.778354],"type":"Point"}
}