{
  "type": "Feature",
  "properties": {
    "addr:full":"1030 E Tremont Ave Bronx NY 10460",
    "addr:housenumber":"1030",
    "addr:postcode":"10460",
    "addr:street":"E Tremont Ave",
    "iso:country":"US",
    "sg:address":"1030 E Tremont Ave",
    "sg:city":"Bronx",
    "sg:classifiers":[
        {
            "category":"Food & Beverages",
            "subcategory":"Groceries & Convenience Stores",
            "type":"Retail Goods"
        }
    ],
    "sg:phone":"+1 718 842 2571",
    "sg:postcode":"10460",
    "sg:province":"NY",
    "wof:name":"1030 Food Corp",
    "wof:placetype":"venue"
},
  "geometry": {"coordinates":[-73.880944,40.840231],"type":"Point"}
}