{
  "type": "Feature",
  "properties": {
    "addr:full":"14846 Hillside Ave Jamaica NY 11435",
    "addr:housenumber":"14846",
    "addr:postcode":"11435",
    "addr:street":"Hillside Ave",
    "iso:country":"US",
    "sg:address":"14846 Hillside Ave",
    "sg:city":"Jamaica",
    "sg:classifiers":[
        {
            "category":"Autos & Motor Vehicles",
            "subcategory":"Automobile Sales",
            "type":"Retail Goods"
        }
    ],
    "sg:phone":"+1 718 658 8920",
    "sg:postcode":"11435",
    "sg:province":"NY",
    "sg:tags":[
        "car",
        "used"
    ],
    "wof:name":"Carribbean Auto Sales Incorporated",
    "wof:placetype":"venue"
},
  "geometry": {"coordinates":[-73.817001,40.704048],"type":"Point"}
}