{
  "type": "Feature",
  "properties": {
    "iso:country":"US",
    "sg:address":"215 Merrick Rd",
    "sg:city":"Oceanside",
    "sg:classifiers":[
        {
            "category":"Real Estate",
            "subcategory":"Real Estate Agent",
            "type":"Services"
        }
    ],
    "sg:phone":"+1 516 678 2200",
    "sg:postcode":"11572",
    "sg:province":"NY",
    "sg:tags":[
        "notary"
    ],
    "sg:website":"www.vendomerealty.com",
    "wof:name":"Vendome Realty",
    "wof:placetype":"venue"
},
  "geometry": {"coordinates":[-73.628304,40.653801],"type":"Point"}
}