{
  "type": "Feature",
  "properties": {
    "iso:country":"US",
    "sg:address":"215 Tremont St",
    "sg:city":"Rochester",
    "sg:classifiers":[
        {
            "category":"Shopping",
            "subcategory":"Clothing, Apparel, & Fashions",
            "type":"Retail Goods"
        }
    ],
    "sg:phone":"+1 585 467 9727",
    "sg:postcode":"14608",
    "sg:province":"NY",
    "sg:tags":[
        "t"
    ],
    "sg:website":"www.avsactivewear.com",
    "wof:name":"AVS Lettering Inc",
    "wof:placetype":"venue"
},
  "geometry": {"coordinates":[-77.621494,43.147856],"type":"Point"}
}