{
  "type": "Feature",
  "properties": {
    "addr:full":"32 Chautauqua Ave Lakewood NY 14750",
    "addr:housenumber":"32",
    "addr:postcode":"14750",
    "addr:street":"Chautauqua Ave",
    "iso:country":"US",
    "sg:address":"32 Chautauqua Ave",
    "sg:city":"Lakewood",
    "sg:classifiers":[
        {
            "category":"Personal",
            "subcategory":"Beauty Salon",
            "type":"Services"
        }
    ],
    "sg:phone":"+1 716 763 4247",
    "sg:postcode":"14750",
    "sg:province":"NY",
    "wof:name":"Darling Designer Cuts",
    "wof:placetype":"venue"
},
  "geometry": {"coordinates":[-79.326213,42.104392],"type":"Point"}
}