{
  "type": "Feature",
  "properties": {
    "addr:full":"4620 Flatlands Ave Brooklyn NY 11234",
    "addr:housenumber":"4620",
    "addr:postcode":"11234",
    "addr:street":"Flatlands Ave",
    "iso:country":"US",
    "sg:address":"4620 Flatlands Ave",
    "sg:city":"Brooklyn",
    "sg:classifiers":[
        {
            "category":"Organizations",
            "subcategory":"Religious Organization",
            "type":"Services"
        }
    ],
    "sg:phone":"+1 347 221 0237",
    "sg:postcode":"11234",
    "sg:province":"NY",
    "wof:name":"LI Bethel United Church",
    "wof:placetype":"venue"
},
  "geometry": {"coordinates":[-73.931023,40.623854],"type":"Point"}
}