{
  "type": "Feature",
  "properties": {
    "iso:country":"US",
    "sg:address":"5 Chasso Ct",
    "sg:city":"Huntington Station",
    "sg:classifiers":[
        {
            "category":"Real Estate",
            "subcategory":"Real Estate Operator",
            "type":"Services"
        }
    ],
    "sg:phone":"+1 631 243 4770",
    "sg:postcode":"11746",
    "sg:province":"NY",
    "sg:tags":[
        "building",
        "nonresidential"
    ],
    "wof:name":"Safe Harbor Properties",
    "wof:placetype":"venue"
},
  "geometry": {"coordinates":[-73.31359500000001,40.79783],"type":"Point"}
}