{
  "type": "Feature",
  "properties": {
    "iso:country":"US",
    "sg:address":"3836 Richmond Ave",
    "sg:city":"Staten Island",
    "sg:classifiers":[
        {
            "category":"Banks & Credit Unions",
            "subcategory":"Bank",
            "type":"Services"
        }
    ],
    "sg:phone":"+1 718 356 9226",
    "sg:postcode":"10312",
    "sg:province":"NY",
    "sg:tags":[
        "loan",
        "real estate"
    ],
    "wof:name":"Bruce Financial Svc",
    "wof:placetype":"venue"
},
  "geometry": {"coordinates":[-74.16548899999999,40.544466],"type":"Point"}
}