{
  "type": "Feature",
  "properties": {
    "addr:full":"1195 Nostrand Ave Brooklyn NY 11225",
    "addr:housenumber":"1195",
    "addr:postcode":"11225",
    "addr:street":"Nostrand Ave",
    "iso:country":"US",
    "sg:address":"1195 Nostrand Ave",
    "sg:city":"Brooklyn",
    "sg:classifiers":[
        {
            "category":"Building & Trades",
            "subcategory":"Electrical",
            "type":"Services"
        }
    ],
    "sg:phone":"+1 718 493 0900",
    "sg:postcode":"11225",
    "sg:province":"NY",
    "sg:tags":[
        "electrical",
        "contractor"
    ],
    "wof:name":"Cracker Electric",
    "wof:placetype":"venue"
},
  "geometry": {"coordinates":[-73.950294,40.658394],"type":"Point"}
}