{
  "type": "Feature",
  "properties": {
    "iso:country":"US",
    "sg:address":"2345 Co Rd 38",
    "sg:city":"Brasher Falls",
    "sg:classifiers":[
        {
            "category":"Wholesale",
            "subcategory":"Construction Materials",
            "type":"Manufacturing & Wholesale Goods"
        }
    ],
    "sg:phone":"+1 315 769 5975",
    "sg:postcode":"13613",
    "sg:province":"NY",
    "sg:tags":[
        "contractor"
    ],
    "wof:name":"Window Shop",
    "wof:placetype":"venue"
},
  "geometry": {"coordinates":[-74.839074,44.858649],"type":"Point"}
}