{
  "type": "Feature",
  "properties": {
    "addr:full":"4876 Saunders Settlement Rd Lockport NY 14094",
    "addr:housenumber":"4876",
    "addr:postcode":"14094",
    "addr:street":"Saunders Settlement Rd",
    "iso:country":"US",
    "sg:address":"4876 Saunders Settlement Rd",
    "sg:city":"Lockport",
    "sg:classifiers":[
        {
            "category":"Wholesale",
            "subcategory":"Machinery & Supplies",
            "type":"Manufacturing & Wholesale Goods"
        }
    ],
    "sg:phone":"+1 716 434 7493",
    "sg:postcode":"14094",
    "sg:province":"NY",
    "sg:tags":[
        "contractor"
    ],
    "wof:name":"Miron B Wasik Sales & Rental",
    "wof:placetype":"venue"
},
  "geometry": {"coordinates":[-78.755284,43.149934],"type":"Point"}
}