{
  "type": "Feature",
  "properties": {
    "iso:country":"US",
    "sg:address":"261 Blaine Rd",
    "sg:city":"Canajoharie",
    "sg:classifiers":[
        {
            "category":"Farming",
            "subcategory":"Dairy Farm",
            "type":"Manufacturing & Wholesale Goods"
        }
    ],
    "sg:phone":"+1 518 673 2833",
    "sg:postcode":"13317",
    "sg:province":"NY",
    "wof:name":"Gregory P Matis",
    "wof:placetype":"venue"
},
  "geometry": {"coordinates":[-74.55315400000001,42.866524],"type":"Point"}
}