{
  "type": "Feature",
  "properties": {
    "iso:country":"US",
    "sg:address":"2775 Hamburg St",
    "sg:city":"Schenectady",
    "sg:classifiers":[
        {
            "category":"Real Estate",
            "subcategory":"Real Estate Agent",
            "type":"Services"
        }
    ],
    "sg:phone":"+1 518 357 0026",
    "sg:postcode":"12303",
    "sg:province":"NY",
    "wof:name":"J E Pirrone & Associates",
    "wof:placetype":"venue"
},
  "geometry": {"coordinates":[-73.936249,42.77293],"type":"Point"}
}