{
  "type": "Feature",
  "properties": {
    "addr:full":"2276 Steinway Street Astoria NY 11105",
    "addr:housenumber":"2276",
    "addr:postcode":"11105",
    "addr:street":"Steinway Street",
    "iso:country":"US",
    "sg:address":"2276 Steinway Street",
    "sg:city":"Astoria",
    "sg:classifiers":[
        {
            "category":"Professional",
            "subcategory":"Accounting & Tax Preparation",
            "type":"Services"
        }
    ],
    "sg:phone":"+1 718 721 7111",
    "sg:postcode":"11105",
    "sg:province":"NY",
    "sg:tags":[
        "accountant"
    ],
    "wof:name":"Kekatos Spyros Acct",
    "wof:placetype":"venue"
},
  "geometry": {"coordinates":[-73.907735,40.771476],"type":"Point"}
}