{
  "type": "Feature",
  "properties": {
    "addr:full":"40 Spruce Ct Staten Island NY 10307",
    "addr:housenumber":"40",
    "addr:postcode":"10307",
    "addr:street":"Spruce Ct",
    "iso:country":"US",
    "sg:address":"40 Spruce Ct",
    "sg:city":"Staten Island",
    "sg:classifiers":[
        {
            "category":"Social Services",
            "type":"Services"
        }
    ],
    "sg:phone":"+1 718 967 4919",
    "sg:postcode":"10307",
    "sg:province":"NY",
    "sg:tags":[
        "counselor",
        "marriage",
        "family"
    ],
    "wof:name":"Acsw Counseling Svc",
    "wof:placetype":"venue"
},
  "geometry": {"coordinates":[-74.23420299999999,40.510121],"type":"Point"}
}