{
  "type": "Feature",
  "properties": {
    "addr:full":"1 Red Lane Dr Albany NY 12211",
    "addr:housenumber":"1",
    "addr:postcode":"12211",
    "addr:street":"Red Lane Dr",
    "iso:country":"US",
    "sg:address":"1 Red Lane Dr",
    "sg:city":"Albany",
    "sg:classifiers":[
        {
            "category":"Home & Garden",
            "subcategory":"Building Materials",
            "type":"Retail Goods"
        }
    ],
    "sg:phone":"+1 518 374 0299",
    "sg:postcode":"12211",
    "sg:province":"NY",
    "sg:tags":[
        "concrete",
        "shape",
        "block"
    ],
    "sg:website":"http://www.callanan.com",
    "wof:name":"Clemente Latham Concrete",
    "wof:placetype":"venue"
},
  "geometry": {"coordinates":[-73.773392,42.700855],"type":"Point"}
}