{
  "type": "Feature",
  "properties": {
    "addr:full":"530 W 27th Street New York NY 10001",
    "addr:housenumber":"530",
    "addr:postcode":"10001",
    "addr:street":"W 27Th Street",
    "iso:country":"US",
    "sg:address":"530 W 27th Street",
    "sg:city":"New York",
    "sg:classifiers":[
        {
            "category":"Arts & Performance",
            "subcategory":"Art Gallery",
            "type":"Entertainment"
        },
        {
            "category":"Bars & Pubs",
            "subcategory":"Nightclub",
            "type":"Food & Drink"
        }
    ],
    "sg:phone":"+1 212 279 2898",
    "sg:postcode":"10001",
    "sg:province":"NY",
    "sg:tags":[
        "nightlife"
    ],
    "sg:website":"www.cosm.org/",
    "wof:name":"Cosm - Chapel of Sacred Mirrors",
    "wof:placetype":"venue"
},
  "geometry": {"coordinates":[-74.005032,40.751473],"type":"Point"}
}