{
  "type": "Feature",
  "properties": {
    "iso:country":"US",
    "sg:address":"235 Harrison Street",
    "sg:city":"Syracuse",
    "sg:classifiers":[
        {
            "category":"Professional",
            "subcategory":"Computer Services",
            "type":"Services"
        }
    ],
    "sg:postcode":"13210",
    "sg:province":"NY",
    "sg:tags":[
        "brand",
        "yourself",
        "entrepreneur",
        "personal",
        "professional",
        "branding",
        "online",
        "presence",
        "image",
        "jobs",
        "hiring",
        "employer"
    ],
    "sg:website":"http://www.brand-yourself.com/",
    "wof:name":"Brand-Yourself",
    "wof:placetype":"venue"
},
  "geometry": {"coordinates":[-76.142498,43.044373],"type":"Point"}
}