{
  "type": "Feature",
  "properties": {
    "addr:full":"12 Young Rd Katonah NY 10536",
    "addr:housenumber":"12",
    "addr:postcode":"10536",
    "addr:street":"Young Rd",
    "iso:country":"US",
    "sg:address":"12 Young Rd",
    "sg:city":"Katonah",
    "sg:classifiers":[
        {
            "category":"Insurance",
            "subcategory":"Insurance Agent",
            "type":"Services"
        }
    ],
    "sg:phone":"+1 914 232 1665",
    "sg:postcode":"10536",
    "sg:province":"NY",
    "sg:tags":[
        "processing"
    ],
    "wof:name":"Italian Claims Agency Inc",
    "wof:placetype":"venue"
},
  "geometry": {"coordinates":[-73.69951500000001,41.289099],"type":"Point"}
}