{
  "type": "Feature",
  "properties": {
    "addr:full":"10 Mark Fitzgibbons Dr Oswego NY 13126",
    "addr:housenumber":"10",
    "addr:postcode":"13126",
    "addr:street":"Mark Fitzgibbons Dr",
    "iso:country":"US",
    "sg:address":"10 Mark Fitzgibbons Dr",
    "sg:city":"Oswego",
    "sg:classifiers":[
        {
            "category":"Education",
            "subcategory":"School",
            "type":"Public Place"
        }
    ],
    "sg:phone":"+1 315 341 2300",
    "sg:postcode":"13126",
    "sg:province":"NY",
    "wof:name":"Oswego Middle School",
    "wof:placetype":"venue"
},
  "geometry": {"coordinates":[-76.507745,43.431534],"type":"Point"}
}