{
  "type": "Feature",
  "properties": {
    "addr:full":"66 Commerce Dr Farmingdale NY 11735",
    "addr:housenumber":"66",
    "addr:postcode":"11735",
    "addr:street":"Commerce Dr",
    "iso:country":"US",
    "sg:address":"66 Commerce Dr",
    "sg:city":"Farmingdale",
    "sg:classifiers":[
        {
            "category":"Wholesale",
            "subcategory":"Durable Goods & Equipment",
            "type":"Manufacturing & Wholesale Goods"
        }
    ],
    "sg:phone":"+1 631 293 4847",
    "sg:postcode":"11735",
    "sg:province":"NY",
    "sg:tags":[
        "fountain",
        "display"
    ],
    "wof:name":"JMC Sales",
    "wof:placetype":"venue"
},
  "geometry": {"coordinates":[-73.406002,40.753384],"type":"Point"}
}