{
  "type": "Feature",
  "properties": {
    "addr:full":"217 E 86 St New York NY 10028",
    "addr:housenumber":"217;86",
    "addr:postcode":"10028",
    "addr:street":"E;St",
    "iso:country":"US",
    "sg:address":"217 E 86 St",
    "sg:city":"New York",
    "sg:classifiers":[
        {
            "category":"Freight",
            "type":"Transportation"
        }
    ],
    "sg:phone":"+1 212 239 1060",
    "sg:postcode":"10028",
    "sg:province":"NY",
    "sg:tags":[
        "mover"
    ],
    "wof:name":"AAA Able Moving Co",
    "wof:placetype":"venue"
},
  "geometry": {"coordinates":[-73.951983,40.778095],"type":"Point"}
}