{
  "type": "Feature",
  "properties": {
    "iso:country":"US",
    "sg:address":"22 Fairway Dr",
    "sg:city":"Hempstead",
    "sg:classifiers":[
        {
            "category":"Wholesale",
            "subcategory":"Stationery",
            "type":"Manufacturing & Wholesale Goods"
        }
    ],
    "sg:phone":"+1 516 485 3126",
    "sg:postcode":"11550",
    "sg:province":"NY",
    "sg:tags":[
        "paper"
    ],
    "wof:name":"Mpb Paper Supply Inc",
    "wof:placetype":"venue"
},
  "geometry": {"coordinates":[-73.63825300000001,40.702265],"type":"Point"}
}