{
  "type": "Feature",
  "properties": {
    "iso:country":"US",
    "sg:address":"76 Ovid St",
    "sg:city":"Seneca Falls",
    "sg:classifiers":[
        {
            "category":"Shopping",
            "subcategory":"Gifts & Souvenirs",
            "type":"Retail Goods"
        }
    ],
    "sg:phone":"+1 315 568 2523",
    "sg:postcode":"13148",
    "sg:province":"NY",
    "sg:tags":[
        "shop"
    ],
    "wof:name":"Paradiseink",
    "wof:placetype":"venue"
},
  "geometry": {"coordinates":[-76.797489,42.905186],"type":"Point"}
}