{
  "type": "Feature",
  "properties": {
    "addr:full":"20 E 16 St New York NY 10003",
    "addr:housenumber":"20;16",
    "addr:postcode":"10003",
    "addr:street":"E",
    "iso:country":"US",
    "sg:address":"20 E 16 St",
    "sg:city":"New York",
    "sg:classifiers":[
        {
            "category":"Food & Beverages",
            "subcategory":"Groceries & Convenience Stores",
            "type":"Retail Goods"
        }
    ],
    "sg:phone":"+1   ",
    "sg:postcode":"10003",
    "sg:province":"NY",
    "wof:name":"University Market Place Inc",
    "wof:placetype":"venue"
},
  "geometry": {"coordinates":[-73.99103599999999,40.736606],"type":"Point"}
}