{
  "type": "Feature",
  "properties": {
    "addr:full":"160 N Main St Elmira NY 14901",
    "addr:housenumber":"160",
    "addr:postcode":"14901",
    "addr:street":"N Main St",
    "iso:country":"US",
    "sg:address":"160 N Main St",
    "sg:city":"Elmira",
    "sg:classifiers":[
        {
            "category":"Banks & Credit Unions",
            "subcategory":"Investment Brokerage",
            "type":"Services"
        }
    ],
    "sg:phone":"+1 607 734 3955",
    "sg:postcode":"14901",
    "sg:province":"NY",
    "sg:tags":[
        "security"
    ],
    "wof:name":"First Union",
    "wof:placetype":"venue"
},
  "geometry": {"coordinates":[-76.807671,42.088841],"type":"Point"}
}