{
  "type": "Feature",
  "properties": {
    "addr:full":"100 United Nations Plz New York NY 10017",
    "addr:housenumber":"100",
    "addr:postcode":"10017",
    "addr:street":"United Nations Plz",
    "iso:country":"US",
    "sg:address":"100 United Nations Plz",
    "sg:city":"New York",
    "sg:classifiers":[
        {
            "category":"Real Estate",
            "subcategory":"Real Estate Operator",
            "type":"Services"
        }
    ],
    "sg:phone":"+1 212 754 1740",
    "sg:postcode":"10017",
    "sg:province":"NY",
    "sg:tags":[
        "apartment"
    ],
    "wof:name":"International Foundation For Arts & Culture Inc",
    "wof:placetype":"venue"
},
  "geometry": {"coordinates":[-73.9683,40.750702],"type":"Point"}
}