{
  "type": "Feature",
  "properties": {
    "addr:full":"130 Crans Rd Middletown NY 10941",
    "addr:housenumber":"130",
    "addr:postcode":"10941",
    "addr:street":"Crans Rd",
    "iso:country":"US",
    "sg:address":"130 Crans Rd",
    "sg:city":"Middletown",
    "sg:classifiers":[
        {
            "category":"Building & Trades",
            "subcategory":"Landscaping Services",
            "type":"Services"
        }
    ],
    "sg:phone":"+1 845 361 3197",
    "sg:postcode":"10941",
    "sg:province":"NY",
    "sg:tags":[
        "design",
        "landscape",
        "maintenance"
    ],
    "wof:name":"S E T Landscape Design",
    "wof:placetype":"venue"
},
  "geometry": {"coordinates":[-74.308306,41.504526],"type":"Point"}
}