{
  "type": "Feature",
  "properties": {
    "addr:full":"111 Franklin St New York NY 10013",
    "addr:housenumber":"111",
    "addr:postcode":"10013",
    "addr:street":"Franklin St",
    "iso:country":"US",
    "sg:address":"111 Franklin St",
    "sg:city":"New York",
    "sg:classifiers":[
        {
            "category":"Education",
            "subcategory":"School",
            "type":"Public Place"
        }
    ],
    "sg:phone":"+1 212 966 0300",
    "sg:postcode":"10013",
    "sg:province":"NY",
    "sg:website":"www.nyaa.edu",
    "wof:name":"New York Academy Of Art Inc",
    "wof:placetype":"venue"
},
  "geometry": {"coordinates":[-74.006219,40.718546],"type":"Point"}
}