{
  "type": "Feature",
  "properties": {
    "iso:country":"US",
    "sg:address":"7 Odell Plz",
    "sg:city":"Yonkers",
    "sg:classifiers":[
        {
            "category":"Professional",
            "subcategory":"Management & Consulting",
            "type":"Services"
        }
    ],
    "sg:phone":"+1 914 968 0966",
    "sg:postcode":"10701",
    "sg:province":"NY",
    "sg:tags":[
        "consultant",
        "business"
    ],
    "wof:name":"New South Management Corp",
    "wof:placetype":"venue"
},
  "geometry": {"coordinates":[-73.884174,40.970159],"type":"Point"}
}