{
  "type": "Feature",
  "properties": {
    "iso:country":"US",
    "sg:address":"100 Madison St",
    "sg:city":"Syracuse",
    "sg:classifiers":[
        {
            "category":"Banks & Credit Unions",
            "subcategory":"Investment Brokerage",
            "type":"Services"
        }
    ],
    "sg:phone":"+1 315 448 3400",
    "sg:postcode":"13202",
    "sg:province":"NY",
    "sg:tags":[
        "stock",
        "bond"
    ],
    "sg:website":"www.smithbarney.com",
    "wof:name":"Smith Barney",
    "wof:placetype":"venue"
},
  "geometry": {"coordinates":[-76.148816,43.045477],"type":"Point"}
}