{
  "type": "Feature",
  "properties": {
    "addr:full":"2021 Western Ave Albany NY 12203",
    "addr:housenumber":"2021",
    "addr:postcode":"12203",
    "addr:street":"Western Ave",
    "iso:country":"US",
    "sg:address":"2021 Western Ave",
    "sg:city":"Albany",
    "sg:classifiers":[
        {
            "category":"Utilities",
            "subcategory":"Mobile Phone",
            "type":"Services"
        }
    ],
    "sg:phone":"+1 518 464 4120",
    "sg:postcode":"12203",
    "sg:province":"NY",
    "sg:tags":[
        "telephone",
        "cellular"
    ],
    "wof:name":"Thinc Wireless",
    "wof:placetype":"venue"
},
  "geometry": {"coordinates":[-73.886331,42.697029],"type":"Point"}
}