{
  "type": "Feature",
  "properties": {
    "iso:country":"US",
    "sg:address":"48 Tobey Ct",
    "sg:city":"Pittsford",
    "sg:classifiers":[
        {
            "category":"Organizations",
            "subcategory":"Non-profit Organization",
            "type":"Services"
        }
    ],
    "sg:phone":"+1 585 385 7708",
    "sg:postcode":"14534",
    "sg:province":"NY",
    "sg:tags":[
        "social"
    ],
    "wof:name":"Cornyn Foundation Inc",
    "wof:placetype":"venue"
},
  "geometry": {"coordinates":[-77.538426,43.086273],"type":"Point"}
}