{
  "type": "Feature",
  "properties": {
    "iso:country":"US",
    "sg:address":"319 William St",
    "sg:city":"Elmira",
    "sg:classifiers":[
        {
            "category":"Professional",
            "type":"Services"
        }
    ],
    "sg:phone":"+1 607 735 5690",
    "sg:postcode":"14901",
    "sg:province":"NY",
    "sg:tags":[
        "establishment"
    ],
    "wof:name":"Brainstormers",
    "wof:placetype":"venue"
},
  "geometry": {"coordinates":[-76.801873,42.093001],"type":"Point"}
}