{
  "type": "Feature",
  "properties": {
    "addr:full":"5401 6th Ave Brooklyn NY 11220",
    "addr:housenumber":"5401",
    "addr:postcode":"11220",
    "addr:street":"6Th Ave",
    "iso:country":"US",
    "sg:address":"5401 6th Ave",
    "sg:city":"Brooklyn",
    "sg:classifiers":[
        {
            "category":"Food & Beverages",
            "subcategory":"Groceries & Convenience Stores",
            "type":"Retail Goods"
        }
    ],
    "sg:phone":"+1 718 853 6155",
    "sg:postcode":"11220",
    "sg:province":"NY",
    "wof:name":"Junior Deli Grocery",
    "wof:placetype":"venue"
},
  "geometry": {"coordinates":[-74.030447,40.641441],"type":"Point"}
}