{
  "type": "Feature",
  "properties": {
    "addr:full":"130 W 57 St New York NY 10019",
    "addr:housenumber":"130",
    "addr:postcode":"10019",
    "addr:street":"W 57 St",
    "iso:country":"US",
    "sg:address":"130 W 57 St",
    "sg:city":"New York",
    "sg:classifiers":[
        {
            "category":"Banks & Credit Unions",
            "subcategory":"Bank",
            "type":"Services"
        }
    ],
    "sg:phone":"+1 212 265 1790",
    "sg:postcode":"10019",
    "sg:province":"NY",
    "sg:tags":[
        "broker",
        "mortgage"
    ],
    "wof:name":"Serfaty & Associates Capital",
    "wof:placetype":"venue"
},
  "geometry": {"coordinates":[-73.97899700000001,40.764856],"type":"Point"}
}