{
  "type": "Feature",
  "properties": {
    "iso:country":"US",
    "sg:address":"265 W 72nd St 2nd Fl",
    "sg:city":"New York",
    "sg:classifiers":[
        {
            "category":"Sports & Exercise",
            "subcategory":"Gym",
            "type":"Entertainment"
        }
    ],
    "sg:phone":"+1 212 877 4153",
    "sg:postcode":"10023",
    "sg:province":"NY",
    "sg:tags":[
        "yoga"
    ],
    "sg:website":"worldyogacenter.com",
    "wof:name":"World Yoga Center",
    "wof:placetype":"venue"
},
  "geometry": {"coordinates":[-73.98396099999999,40.77981],"type":"Point"}
}