{
  "type": "Feature",
  "properties": {
    "addr:full":"70 Fulton St Middletown NY 10940",
    "addr:housenumber":"70",
    "addr:postcode":"10940",
    "addr:street":"Fulton St",
    "iso:country":"US",
    "sg:address":"70 Fulton St",
    "sg:city":"Middletown",
    "sg:classifiers":[
        {
            "category":"Personal",
            "subcategory":"Beauty Salon",
            "type":"Services"
        }
    ],
    "sg:phone":"+1 845 343 9866",
    "sg:postcode":"10940",
    "sg:province":"NY",
    "wof:name":"Rhonda's Hair Design Of S Wind",
    "wof:placetype":"venue"
},
  "geometry": {"coordinates":[-74.421003,41.441761],"type":"Point"}
}