{
  "type": "Feature",
  "properties": {
    "iso:country":"US",
    "sg:address":"67 Exchange St",
    "sg:city":"Albany",
    "sg:classifiers":[
        {
            "category":"Professional",
            "subcategory":"Computer Services",
            "type":"Services"
        }
    ],
    "sg:phone":"+1 518 482 7202",
    "sg:postcode":"12205",
    "sg:province":"NY",
    "sg:tags":[
        "repair"
    ],
    "wof:name":"Colonie Business Machines Inc",
    "wof:placetype":"venue"
},
  "geometry": {"coordinates":[-73.784302,42.685641],"type":"Point"}
}