{
  "type": "Feature",
  "properties": {
    "addr:full":"72 S Lake Ave Bergen NY 14416",
    "addr:housenumber":"72",
    "addr:postcode":"14416",
    "addr:street":"S Lake Ave",
    "iso:country":"US",
    "sg:address":"72 S Lake Ave",
    "sg:city":"Bergen",
    "sg:classifiers":[
        {
            "category":"Wholesale",
            "subcategory":"Auto Parts",
            "type":"Manufacturing & Wholesale Goods"
        }
    ],
    "sg:phone":"+1 585 494 2050",
    "sg:postcode":"14416",
    "sg:province":"NY",
    "wof:name":"NAPA Auto Parts",
    "wof:placetype":"venue"
},
  "geometry": {"coordinates":[-77.944789,43.078024],"type":"Point"}
}