{
  "type": "Feature",
  "properties": {
    "addr:full":"106 Broadway Greenlawn NY 11740",
    "addr:housenumber":"106",
    "addr:postcode":"11740",
    "addr:street":"Broadway",
    "iso:country":"US",
    "sg:address":"106 Broadway",
    "sg:city":"Greenlawn",
    "sg:classifiers":[
        {
            "category":"Restaurant",
            "type":"Food & Drink"
        },
        {
            "category":"Shopping",
            "subcategory":"Pharmacy",
            "type":"Retail Goods"
        }
    ],
    "sg:phone":"+1 631 651 8413",
    "sg:postcode":"11740",
    "sg:province":"NY",
    "sg:tags":[
        "drugstore"
    ],
    "wof:name":"Value Drugs",
    "wof:placetype":"venue"
},
  "geometry": {"coordinates":[-73.36415100000001,40.866367],"type":"Point"}
}