{
  "type": "Feature",
  "properties": {
    "addr:full":"579 New Scotland Ave Albany NY 12208",
    "addr:housenumber":"579",
    "addr:postcode":"12208",
    "addr:street":"New Scotland Ave",
    "iso:country":"US",
    "sg:address":"579 New Scotland Ave",
    "sg:city":"Albany",
    "sg:classifiers":[
        {
            "category":"Personal",
            "subcategory":"Beauty Salon",
            "type":"Services"
        }
    ],
    "sg:phone":"+1 518 438 1849",
    "sg:postcode":"12208",
    "sg:province":"NY",
    "sg:tags":[
        "manicuring"
    ],
    "wof:name":"Vogue Nail",
    "wof:placetype":"venue"
},
  "geometry": {"coordinates":[-73.80289999999999,42.65698],"type":"Point"}
}