{
  "type": "Feature",
  "properties": {
    "addr:full":"5291 Clinton St Elma NY 14059",
    "addr:housenumber":"5291",
    "addr:postcode":"14059",
    "addr:street":"Clinton St",
    "iso:country":"US",
    "sg:address":"5291 Clinton St",
    "sg:city":"Elma",
    "sg:classifiers":[
        {
            "category":"Building & Trades",
            "subcategory":"Electrical",
            "type":"Services"
        }
    ],
    "sg:phone":"+1 716 668 3067",
    "sg:postcode":"14059",
    "sg:province":"NY",
    "sg:tags":[
        "electric",
        "contractor"
    ],
    "wof:name":"Suburban Electric",
    "wof:placetype":"venue"
},
  "geometry": {"coordinates":[-78.686218,42.859565],"type":"Point"}
}