{
  "type": "Feature",
  "properties": {
    "addr:full":"16 Sparrow Ridge Rd Carmel NY 10512",
    "addr:housenumber":"16",
    "addr:postcode":"10512",
    "addr:street":"Sparrow Ridge Rd",
    "iso:country":"US",
    "sg:address":"16 Sparrow Ridge Rd",
    "sg:city":"Carmel",
    "sg:classifiers":[
        {
            "category":"Shopping",
            "subcategory":"Gifts & Souvenirs",
            "type":"Retail Goods"
        }
    ],
    "sg:phone":"+1 212 810 7181",
    "sg:postcode":"10512",
    "sg:province":"NY",
    "sg:tags":[
        "shop"
    ],
    "wof:name":"Image Favors, Inc.",
    "wof:placetype":"venue"
},
  "geometry": {"coordinates":[-73.662888,41.440311],"type":"Point"}
}