{
  "type": "Feature",
  "properties": {
    "iso:country":"US",
    "sg:address":"79 Allen St",
    "sg:city":"Jamestown",
    "sg:classifiers":[
        {
            "category":"Restaurant",
            "type":"Food & Drink"
        }
    ],
    "sg:phone":"+1 716 488 1124",
    "sg:postcode":"14701",
    "sg:province":"NY",
    "sg:tags":[
        "caterer"
    ],
    "wof:name":"Nana's Deli",
    "wof:placetype":"venue"
},
  "geometry": {"coordinates":[-79.234174,42.091636],"type":"Point"}
}