{
  "type": "Feature",
  "properties": {
    "addr:full":"6083 State Hwy 31 Cicero NY 13039",
    "addr:housenumber":"6083",
    "addr:postcode":"13039",
    "addr:street":"State Hwy 31",
    "iso:country":"US",
    "sg:address":"6083 State Hwy 31",
    "sg:city":"Cicero",
    "sg:classifiers":[
        {
            "category":"Building & Trades",
            "subcategory":"Construction",
            "type":"Services"
        }
    ],
    "sg:phone":"+1 315 727 6450",
    "sg:postcode":"13039",
    "sg:province":"NY",
    "sg:tags":[
        "heavy"
    ],
    "wof:name":"R B X",
    "wof:placetype":"venue"
},
  "geometry": {"coordinates":[-76.105676,43.176092],"type":"Point"}
}