{
  "type": "Feature",
  "properties": {
    "addr:full":"252 W 38th St Rm 301 New York NY 10018",
    "addr:housenumber":"252;301",
    "addr:postcode":"10018",
    "addr:street":"W 38Th St Rm",
    "iso:country":"US",
    "sg:address":"252 W 38th St Rm 301",
    "sg:city":"New York",
    "sg:classifiers":[
        {
            "category":"Professional",
            "subcategory":"Lawyer & Legal Services",
            "type":"Services"
        }
    ],
    "sg:phone":"+1 212 217 0670",
    "sg:postcode":"10018",
    "sg:province":"NY",
    "wof:name":"Garbanzos Law Firm",
    "wof:placetype":"venue"
},
  "geometry": {"coordinates":[-73.990347,40.75403],"type":"Point"}
}