{
  "type": "Feature",
  "properties": {
    "iso:country":"US",
    "sg:address":"25 Peaceful Trl",
    "sg:city":"Rochester",
    "sg:classifiers":[
        {
            "category":"Manufacturing",
            "subcategory":"Printing",
            "type":"Manufacturing & Wholesale Goods"
        }
    ],
    "sg:phone":"+1   ",
    "sg:postcode":"14609",
    "sg:province":"NY",
    "sg:tags":[
        "lithographic",
        "commercial"
    ],
    "wof:name":"St Gerge Prtg Cnsltant/Brokers",
    "wof:placetype":"venue"
},
  "geometry": {"coordinates":[-77.537217,43.193258],"type":"Point"}
}