{
  "type": "Feature",
  "properties": {
    "iso:country":"US",
    "sg:address":"301 E 63 St",
    "sg:city":"New York",
    "sg:classifiers":[
        {
            "category":"Parking",
            "type":"Transportation"
        }
    ],
    "sg:phone":"+1 212 355 9054",
    "sg:postcode":"10065",
    "sg:province":"NY",
    "sg:tags":[
        "garage"
    ],
    "wof:name":"Metro Parking Corp",
    "wof:placetype":"venue"
},
  "geometry": {"coordinates":[-73.961541,40.7627],"type":"Point"}
}