{
  "type": "Feature",
  "properties": {
    "iso:country":"US",
    "sg:address":"1 Kimball St",
    "sg:city":"Amsterdam",
    "sg:classifiers":[
        {
            "category":"Social Services",
            "type":"Services"
        }
    ],
    "sg:phone":"+1 518 843 0004",
    "sg:postcode":"12010",
    "sg:province":"NY",
    "sg:tags":[
        "organization",
        "welfare"
    ],
    "wof:name":"Hispanic Outreach Svc",
    "wof:placetype":"venue"
},
  "geometry": {"coordinates":[-74.19253399999999,42.940571],"type":"Point"}
}