{
  "type": "Feature",
  "properties": {
    "iso:country":"US",
    "sg:address":"214 Cromwell Hill Rd",
    "sg:city":"Monroe",
    "sg:classifiers":[
        {
            "category":"Bagels",
            "subcategory":"None",
            "type":"Food & Drink"
        }
    ],
    "sg:phone":"+1 845 782 7158",
    "sg:postcode":"10950",
    "sg:province":"NY",
    "wof:name":"Joy O'h Properties Inc",
    "wof:placetype":"venue"
},
  "geometry": {"coordinates":[-74.21539,41.324211],"type":"Point"}
}