{
  "type": "Feature",
  "properties": {
    "addr:full":"15 Swan Street Staten Island NY 10301",
    "addr:housenumber":"15",
    "addr:postcode":"10301",
    "addr:street":"Swan Street",
    "iso:country":"US",
    "sg:address":"15 Swan Street",
    "sg:city":"Staten Island",
    "sg:classifiers":[
        {
            "category":"Building & Trades",
            "subcategory":"Construction",
            "type":"Services"
        }
    ],
    "sg:phone":"+1 718 720 5270",
    "sg:postcode":"10301",
    "sg:province":"NY",
    "sg:tags":[
        "contractor"
    ],
    "wof:name":"K E S Construction",
    "wof:placetype":"venue"
},
  "geometry": {"coordinates":[-74.076013,40.634963],"type":"Point"}
}