{
  "type": "Feature",
  "properties": {
    "addr:full":"39 Greycourt Ave Chester NY 10918",
    "addr:housenumber":"39",
    "addr:postcode":"10918",
    "addr:street":"Greycourt Ave",
    "iso:country":"US",
    "sg:address":"39 Greycourt Ave",
    "sg:city":"Chester",
    "sg:classifiers":[
        {
            "category":"Food & Beverages",
            "subcategory":"Bakery",
            "type":"Retail Goods"
        }
    ],
    "sg:phone":"+1 845 469 9096",
    "sg:postcode":"10918",
    "sg:province":"NY",
    "sg:tags":[
        "baker"
    ],
    "wof:name":"D'Amil Orlando",
    "wof:placetype":"venue"
},
  "geometry": {"coordinates":[-74.261966,41.361556],"type":"Point"}
}