{
  "type": "Feature",
  "properties": {
    "addr:full":"305 E 61 St New York NY 10065",
    "addr:housenumber":"305;61",
    "addr:postcode":"10065",
    "addr:street":"E;St",
    "iso:country":"US",
    "sg:address":"305 E 61 St",
    "sg:city":"New York",
    "sg:classifiers":[
        {
            "category":"Freight",
            "type":"Transportation"
        }
    ],
    "sg:phone":"+1   ",
    "sg:postcode":"10065",
    "sg:province":"NY",
    "sg:tags":[
        "warehouse",
        "packing",
        "storage",
        "for",
        "shipping"
    ],
    "wof:name":"Hayes Cirkers Storage Whse",
    "wof:placetype":"venue"
},
  "geometry": {"coordinates":[-73.962569,40.761601],"type":"Point"}
}