{
  "type": "Feature",
  "properties": {
    "iso:country":"US",
    "sg:address":"30 Van Buren Dr",
    "sg:city":"Monroe",
    "sg:classifiers":[
        {
            "category":"Professional",
            "subcategory":"Lawyer & Legal Services",
            "type":"Services"
        }
    ],
    "sg:phone":"+1 845 783 1551",
    "sg:postcode":"10950",
    "sg:province":"NY",
    "wof:name":"Schwartz Marvin L attorney at law",
    "wof:placetype":"venue"
},
  "geometry": {"coordinates":[-74.167239,41.337208],"type":"Point"}
}