{
  "type": "Feature",
  "properties": {
    "iso:country":"US",
    "sg:address":"276 Main St",
    "sg:city":"Huntington",
    "sg:classifiers":[
        {
            "category":"Shopping",
            "subcategory":"Clothing, Apparel, & Fashions",
            "type":"Retail Goods"
        }
    ],
    "sg:phone":"+1   ",
    "sg:postcode":"11743",
    "sg:province":"NY",
    "sg:tags":[
        "miscellaneous",
        "store",
        "accessory"
    ],
    "wof:name":"Doard",
    "wof:placetype":"venue"
},
  "geometry": {"coordinates":[-73.42715,40.871017],"type":"Point"}
}