{
  "type": "Feature",
  "properties": {
    "iso:country":"US",
    "sg:address":"717 Fulton Street",
    "sg:city":"Brooklyn",
    "sg:classifiers":[
        {
            "category":"Restaurant",
            "type":"Food & Drink"
        }
    ],
    "sg:phone":"+1 718 625 4499",
    "sg:postcode":"11217",
    "sg:province":"NY",
    "sg:tags":[
        "pizza"
    ],
    "wof:name":"S & S Brooklyn Pizza",
    "wof:placetype":"venue"
},
  "geometry": {"coordinates":[-73.976752,40.68737],"type":"Point"}
}