{
  "type": "Feature",
  "properties": {
    "addr:full":"30 Straight Path Southampton NY 11968",
    "addr:housenumber":"30",
    "addr:postcode":"11968",
    "addr:street":"Straight Path",
    "iso:country":"US",
    "sg:address":"30 Straight Path",
    "sg:city":"Southampton",
    "sg:classifiers":[
        {
            "category":"Building & Trades",
            "subcategory":"Construction",
            "type":"Services"
        }
    ],
    "sg:phone":"+1 631 283 0369",
    "sg:postcode":"11968",
    "sg:province":"NY",
    "sg:tags":[
        "nonresidential"
    ],
    "wof:name":"Douglas M Warner Building Inc",
    "wof:placetype":"venue"
},
  "geometry": {"coordinates":[-72.41188699999999,40.931981],"type":"Point"}
}