{
  "type": "Feature",
  "properties": {
    "iso:country":"US",
    "sg:address":"18 Kings Ct",
    "sg:city":"Camillus",
    "sg:classifiers":[
        {
            "category":"Organizations",
            "subcategory":"Religious Organization",
            "type":"Services"
        }
    ],
    "sg:phone":"+1 315 487 1101",
    "sg:postcode":"13031",
    "sg:province":"NY",
    "sg:tags":[
        "clergy"
    ],
    "wof:name":"Kenneth C Heuermann",
    "wof:placetype":"venue"
},
  "geometry": {"coordinates":[-76.260259,43.049909],"type":"Point"}
}