{
  "type": "Feature",
  "properties": {
    "iso:country":"US",
    "sg:address":"259 Central Ave",
    "sg:city":"Silver Creek",
    "sg:classifiers":[
        {
            "category":"Organizations",
            "subcategory":"Community Association",
            "type":"Services"
        }
    ],
    "sg:phone":"+1 716 934 7181",
    "sg:postcode":"14136",
    "sg:province":"NY",
    "sg:tags":[
        "fraternal"
    ],
    "wof:name":"Loyal Order Of Moose",
    "wof:placetype":"venue"
},
  "geometry": {"coordinates":[-79.165632,42.543888],"type":"Point"}
}