{
  "type": "Feature",
  "properties": {
    "addr:full":"1080 Long Island Ave Deer Park NY 11729",
    "addr:housenumber":"1080",
    "addr:postcode":"11729",
    "addr:street":"Long Island Ave",
    "iso:country":"US",
    "sg:address":"1080 Long Island Ave",
    "sg:city":"Deer Park",
    "sg:classifiers":[
        {
            "category":"Wholesale",
            "subcategory":"Motor Vehicles",
            "type":"Manufacturing & Wholesale Goods"
        }
    ],
    "sg:phone":"+1 631 254 0330",
    "sg:postcode":"11729",
    "sg:province":"NY",
    "sg:tags":[
        "automobile",
        "used"
    ],
    "wof:name":"Map Auto Sales Of New York",
    "wof:placetype":"venue"
},
  "geometry": {"coordinates":[-73.29529700000001,40.770143],"type":"Point"}
}