{
  "type": "Feature",
  "properties": {
    "addr:full":"114 Elbow Rd North Syracuse NY 13212",
    "addr:housenumber":"114",
    "addr:postcode":"13212",
    "addr:street":"Elbow Rd",
    "iso:country":"US",
    "sg:address":"114 Elbow Rd",
    "sg:city":"North Syracuse",
    "sg:classifiers":[
        {
            "category":"Real Estate",
            "subcategory":"Real Estate Operator",
            "type":"Services"
        }
    ],
    "sg:phone":"+1 315 454 0697",
    "sg:postcode":"13212",
    "sg:province":"NY",
    "sg:tags":[
        "senior",
        "apartment",
        "housing",
        "citizen"
    ],
    "wof:name":"Pitcher Hill Apartments",
    "wof:placetype":"venue"
},
  "geometry": {"coordinates":[-76.148578,43.115088],"type":"Point"}
}