{
  "type": "Feature",
  "properties": {
    "iso:country":"US",
    "sg:address":"1800 Northern Blvd Ste 212",
    "sg:city":"Roslyn",
    "sg:classifiers":[
        {
            "category":"Professional",
            "subcategory":"Accounting & Tax Preparation",
            "type":"Services"
        }
    ],
    "sg:phone":"+1 516 484 8941",
    "sg:postcode":"11576",
    "sg:province":"NY",
    "sg:tags":[
        "accountant"
    ],
    "wof:name":"Lionel & Belonsky Llp",
    "wof:placetype":"venue"
},
  "geometry": {"coordinates":[-73.639702,40.805801],"type":"Point"}
}