{
  "type": "Feature",
  "properties": {
    "addr:full":"2700 Bellmore Rd North Bellmore NY 11710",
    "addr:housenumber":"2700",
    "addr:postcode":"11710",
    "addr:street":"Bellmore Rd",
    "iso:country":"US",
    "sg:address":"2700 Bellmore Rd",
    "sg:city":"North Bellmore",
    "sg:classifiers":[
        {
            "category":"Food & Beverages",
            "subcategory":"Groceries & Convenience Stores",
            "type":"Retail Goods"
        }
    ],
    "sg:phone":"+1 516 785 9528",
    "sg:postcode":"11710",
    "sg:province":"NY",
    "sg:website":"www.7-eleven.com",
    "wof:name":"7-Eleven",
    "wof:placetype":"venue"
},
  "geometry": {"coordinates":[-73.53372,40.698599],"type":"Point"}
}