{
  "type": "Feature",
  "properties": {
    "iso:country":"US",
    "sg:address":"134 Morgan Ave",
    "sg:city":"Brooklyn",
    "sg:classifiers":[
        {
            "category":"Shopping",
            "subcategory":"Party Supplies",
            "type":"Retail Goods"
        }
    ],
    "sg:phone":"+1 718 821 4000",
    "sg:postcode":"11237",
    "sg:province":"NY",
    "wof:name":"Broadway Famous Party Rental",
    "wof:placetype":"venue"
},
  "geometry": {"coordinates":[-73.932503,40.708599],"type":"Point"}
}