{
  "type": "Feature",
  "properties": {
    "addr:full":"120 Hoosick St Troy NY 12180",
    "addr:housenumber":"120",
    "addr:postcode":"12180",
    "addr:street":"Hoosick St",
    "iso:country":"US",
    "sg:address":"120 Hoosick St",
    "sg:city":"Troy",
    "sg:classifiers":[
        {
            "category":"Shopping",
            "subcategory":"Tobacco",
            "type":"Retail Goods"
        }
    ],
    "sg:phone":"+1 518 272 0398",
    "sg:postcode":"12180",
    "sg:province":"NY",
    "sg:tags":[
        "cigarette",
        "cigar",
        "dealer"
    ],
    "wof:name":"Smokers Paradise Inc",
    "wof:placetype":"venue"
},
  "geometry": {"coordinates":[-73.679294,42.73943],"type":"Point"}
}