{
  "type": "Feature",
  "properties": {
    "iso:country":"US",
    "sg:address":"4620 State Hwy 9n",
    "sg:city":"Corinth",
    "sg:classifiers":[
        {
            "category":"Manufacturing",
            "subcategory":"Metals",
            "type":"Manufacturing & Wholesale Goods"
        }
    ],
    "sg:phone":"+1 518 893 0834",
    "sg:postcode":"12822",
    "sg:province":"NY",
    "wof:name":"Lyford Enterprises",
    "wof:placetype":"venue"
},
  "geometry": {"coordinates":[-73.861661,43.210218],"type":"Point"}
}