{
  "type": "Feature",
  "properties": {
    "iso:country":"US",
    "sg:address":"1063 Ridge Rd",
    "sg:city":"Lackawanna",
    "sg:classifiers":[
        {
            "category":"Home & Garden",
            "subcategory":"Building Materials",
            "type":"Retail Goods"
        },
        {
            "category":"Retail",
            "subcategory":"Auto Repair",
            "type":"Services"
        }
    ],
    "sg:phone":"+1 716 823 3422",
    "sg:postcode":"14218",
    "sg:province":"NY",
    "sg:tags":[
        "door",
        "general"
    ],
    "wof:name":"American Garage Door & Windows",
    "wof:placetype":"venue"
},
  "geometry": {"coordinates":[-78.816152,42.827337],"type":"Point"}
}