{
  "type": "Feature",
  "properties": {
    "addr:full":"410 Ocean Pkwy Brooklyn NY 11218",
    "addr:housenumber":"410",
    "addr:postcode":"11218",
    "addr:street":"Ocean Pkwy",
    "iso:country":"US",
    "sg:address":"410 Ocean Pkwy",
    "sg:city":"Brooklyn",
    "sg:classifiers":[
        {
            "category":"Freight",
            "type":"Transportation"
        }
    ],
    "sg:phone":"+1 718 287 6528",
    "sg:postcode":"11218",
    "sg:province":"NY",
    "sg:tags":[
        "trucking"
    ],
    "wof:name":"Zan USA Inc",
    "wof:placetype":"venue"
},
  "geometry": {"coordinates":[-73.97386299999999,40.640626],"type":"Point"}
}