{
  "type": "Feature",
  "properties": {
    "iso:country":"US",
    "sg:address":"107 Mott St",
    "sg:city":"New York",
    "sg:classifiers":[
        {
            "category":"Health Services",
            "subcategory":"Health Practitioner",
            "type":"Services"
        }
    ],
    "sg:phone":"+1 212 219 1465",
    "sg:postcode":"10013",
    "sg:province":"NY",
    "sg:tags":[
        "acupuncture"
    ],
    "wof:name":"Fishon Inc",
    "wof:placetype":"venue"
},
  "geometry": {"coordinates":[-73.997398,40.717701],"type":"Point"}
}