{
  "type": "Feature",
  "properties": {
    "addr:full":"15 Fluvanna Ave Jamestown NY 14701",
    "addr:housenumber":"15",
    "addr:postcode":"14701",
    "addr:street":"Fluvanna Ave",
    "iso:country":"US",
    "sg:address":"15 Fluvanna Ave",
    "sg:city":"Jamestown",
    "sg:classifiers":[
        {
            "category":"Insurance",
            "subcategory":"Hazard Insurance",
            "type":"Services"
        },
        {
            "category":"Banks & Credit Unions",
            "subcategory":"Bank",
            "type":"Services"
        }
    ],
    "sg:phone":"+1 716 483 2762",
    "sg:postcode":"14701",
    "sg:province":"NY",
    "sg:tags":[
        "commercial",
        "saving",
        "business"
    ],
    "wof:name":"Robinson Andrew S Insurance",
    "wof:placetype":"venue"
},
  "geometry": {"coordinates":[-79.24132899999999,42.111855],"type":"Point"}
}