{
  "type": "Feature",
  "properties": {
    "iso:country":"US",
    "sg:address":"55 W 2nd St",
    "sg:city":"Oswego",
    "sg:classifiers":[
        {
            "category":"Professional",
            "subcategory":"Lawyer & Legal Services",
            "type":"Services"
        }
    ],
    "sg:phone":"+1 315 342 7214",
    "sg:postcode":"13126",
    "sg:province":"NY",
    "sg:tags":[
        "attorney"
    ],
    "wof:name":"Rodak & Kirwan",
    "wof:placetype":"venue"
},
  "geometry": {"coordinates":[-76.514048,43.459347],"type":"Point"}
}