{
  "type": "Feature",
  "properties": {
    "addr:full":"949 E 174th St Bronx NY 10460",
    "addr:housenumber":"949",
    "addr:postcode":"10460",
    "addr:street":"E 174Th St",
    "iso:country":"US",
    "sg:address":"949 E 174th St",
    "sg:city":"Bronx",
    "sg:classifiers":[
        {
            "category":"Restaurant",
            "type":"Food & Drink"
        }
    ],
    "sg:phone":"+1 718 542 7147",
    "sg:postcode":"10460",
    "sg:province":"NY",
    "sg:website":"www.popeyes.com",
    "wof:name":"Popeye's Chicken & Biscuits",
    "wof:placetype":"venue"
},
  "geometry": {"coordinates":[-73.88621999999999,40.836968],"type":"Point"}
}