{
  "type": "Feature",
  "properties": {
    "iso:country":"US",
    "sg:address":"1052 New Loudon Rd",
    "sg:city":"Cohoes",
    "sg:classifiers":[
        {
            "category":"Building & Trades",
            "subcategory":"Construction",
            "type":"Services"
        }
    ],
    "sg:phone":"+1 518 785 4690",
    "sg:postcode":"12047",
    "sg:province":"NY",
    "sg:tags":[
        "maintenance",
        "contractor"
    ],
    "wof:name":"Maintenance Services",
    "wof:placetype":"venue"
},
  "geometry": {"coordinates":[-73.750058,42.776861],"type":"Point"}
}