{
  "type": "Feature",
  "properties": {
    "addr:full":"1939 E Genesee St Syracuse NY 13210",
    "addr:housenumber":"1939",
    "addr:postcode":"13210",
    "addr:street":"E Genesee St",
    "iso:country":"US",
    "sg:address":"1939 E Genesee St",
    "sg:city":"Syracuse",
    "sg:classifiers":[
        {
            "category":"Health Services",
            "subcategory":"Doctor",
            "type":"Services"
        }
    ],
    "sg:phone":"+1 315 479 7019",
    "sg:postcode":"13210",
    "sg:province":"NY",
    "sg:tags":[
        "dentist"
    ],
    "wof:name":"Alvin Holmes PC",
    "wof:placetype":"venue"
},
  "geometry": {"coordinates":[-76.120085,43.045662],"type":"Point"}
}