{
  "type": "Feature",
  "properties": {
    "iso:country":"US",
    "sg:address":"234 Tarrytown Rd",
    "sg:city":"Elmsford",
    "sg:classifiers":[
        {
            "category":"Health Services",
            "subcategory":"Clinic",
            "type":"Services"
        }
    ],
    "sg:phone":"+1 914 592 5858",
    "sg:postcode":"10523",
    "sg:province":"NY",
    "sg:tags":[
        "kidney",
        "dialysis",
        "center"
    ],
    "wof:name":"Dialysis Clinic Inc",
    "wof:placetype":"venue"
},
  "geometry": {"coordinates":[-73.80807900000001,41.048009],"type":"Point"}
}