{
  "type": "Feature",
  "properties": {
    "addr:full":"254 Bellew Ave Watertown NY 13601",
    "addr:housenumber":"254",
    "addr:postcode":"13601",
    "addr:street":"Bellew Ave",
    "iso:country":"US",
    "sg:address":"254 Bellew Ave",
    "sg:city":"Watertown",
    "sg:classifiers":[
        {
            "category":"Travel",
            "subcategory":"Travel Agent",
            "type":"Entertainment"
        }
    ],
    "sg:phone":"+1 315 782 0950",
    "sg:postcode":"13601",
    "sg:province":"NY",
    "sg:tags":[
        "agency",
        "bureau"
    ],
    "wof:name":"World of Leisure Travel Svce",
    "wof:placetype":"venue"
},
  "geometry": {"coordinates":[-75.930645,43.982186],"type":"Point"}
}