{
  "type": "Feature",
  "properties": {
    "addr:full":"10242 Hornell Rd Dansville NY 14437",
    "addr:postcode":"10242;14437",
    "addr:street":"Hornell Rd",
    "iso:country":"US",
    "sg:address":"10242 Hornell Rd",
    "sg:city":"Dansville",
    "sg:classifiers":[
        {
            "category":"Manufacturing",
            "subcategory":"Buildings",
            "type":"Manufacturing & Wholesale Goods"
        },
        {
            "category":"Building & Trades",
            "subcategory":"Construction",
            "type":"Services"
        }
    ],
    "sg:phone":"+1 585 335 8722",
    "sg:postcode":"14437",
    "sg:province":"NY",
    "sg:tags":[
        "home",
        "builder",
        "contractor"
    ],
    "wof:name":"Empire Construction",
    "wof:placetype":"venue"
},
  "geometry": {"coordinates":[-77.695373,42.536983],"type":"Point"}
}