{
  "type": "Feature",
  "properties": {
    "addr:full":"280 Madison Ave New York NY 10016",
    "addr:housenumber":"280",
    "addr:postcode":"10016",
    "addr:street":"Madison Ave",
    "iso:country":"US",
    "sg:address":"280 Madison Ave",
    "sg:city":"New York",
    "sg:classifiers":[
        {
            "category":"Restaurant",
            "type":"Food & Drink"
        }
    ],
    "sg:menulink":"http://www.allmenus.com/ny/new-york/189038-mcdonalds/menu/",
    "sg:postcode":"10016",
    "sg:province":"NY",
    "sg:tags":[
        "burger",
        "american"
    ],
    "wof:name":"McDonald's",
    "wof:placetype":"venue"
},
  "geometry": {"coordinates":[-73.980237,40.75149],"type":"Point"}
}