{
  "type": "Feature",
  "properties": {
    "addr:full":"190 W Seaman Ave Freeport NY 11520",
    "addr:housenumber":"190",
    "addr:postcode":"11520",
    "addr:street":"W Seaman Ave",
    "iso:country":"US",
    "sg:address":"190 W Seaman Ave",
    "sg:city":"Freeport",
    "sg:classifiers":[
        {
            "category":"Local Transit",
            "type":"Transportation"
        }
    ],
    "sg:phone":"+1   ",
    "sg:postcode":"11520",
    "sg:province":"NY",
    "sg:tags":[
        "passenger"
    ],
    "wof:name":"Always On Time Limo Inc",
    "wof:placetype":"venue"
},
  "geometry": {"coordinates":[-73.59608900000001,40.66451],"type":"Point"}
}