{
  "type": "Feature",
  "properties": {
    "addr:full":"1217 Avenue S Brooklyn NY 11229",
    "addr:housenumber":"1217",
    "addr:postcode":"11229",
    "addr:street":"Avenue S",
    "iso:country":"US",
    "sg:address":"1217 Avenue S",
    "sg:city":"Brooklyn",
    "sg:classifiers":[
        {
            "category":"Building & Trades",
            "subcategory":"Cleaning & Sanitation",
            "type":"Services"
        }
    ],
    "sg:phone":"+1 718 336 7500",
    "sg:postcode":"11229",
    "sg:province":"NY",
    "sg:tags":[
        "carpet"
    ],
    "wof:name":"Ari's Carpet Cleaning",
    "wof:placetype":"venue"
},
  "geometry": {"coordinates":[-73.960027,40.603301],"type":"Point"}
}