{
  "type": "Feature",
  "properties": {
    "iso:country":"US",
    "sg:address":"116 Commack Rd",
    "sg:city":"Islip",
    "sg:classifiers":[
        {
            "category":"Professional",
            "subcategory":"Art Services",
            "type":"Services"
        }
    ],
    "sg:phone":"+1 631 835 1803",
    "sg:postcode":"11751",
    "sg:province":"NY",
    "sg:tags":[
        "commercial",
        "design",
        "real estate"
    ],
    "wof:name":"Romaka Communications",
    "wof:placetype":"venue"
},
  "geometry": {"coordinates":[-73.21292699999999,40.739426],"type":"Point"}
}