{
  "type": "Feature",
  "properties": {
    "iso:country":"US",
    "sg:address":"832 State Hwy 17K",
    "sg:city":"Montgomery",
    "sg:classifiers":[
        {
            "category":"Autos & Motor Vehicles",
            "subcategory":"Auto Supplies",
            "type":"Retail Goods"
        }
    ],
    "sg:phone":"+1 845 457 9808",
    "sg:postcode":"12549",
    "sg:province":"NY",
    "sg:tags":[
        "automobile",
        "parts"
    ],
    "wof:name":"European Parts Emporium",
    "wof:placetype":"venue"
},
  "geometry": {"coordinates":[-74.17693300000001,41.524186],"type":"Point"}
}