{
  "type": "Feature",
  "properties": {
    "addr:full":"201 Montrose Rd Westbury NY 11590",
    "addr:housenumber":"201",
    "addr:postcode":"11590",
    "addr:street":"Montrose Rd",
    "iso:country":"US",
    "sg:address":"201 Montrose Rd",
    "sg:city":"Westbury",
    "sg:classifiers":[
        {
            "category":"Autos & Motor Vehicles",
            "subcategory":"Auto Supplies",
            "type":"Retail Goods"
        },
        {
            "category":"Retail",
            "subcategory":"Repair Shop",
            "type":"Services"
        },
        {
            "category":"Manufacturing",
            "subcategory":"Motor Vehicles & Parts",
            "type":"Manufacturing & Wholesale Goods"
        }
    ],
    "sg:phone":"+1 516 333 4282",
    "sg:postcode":"11590",
    "sg:province":"NY",
    "sg:tags":[
        "electric",
        "pumps-service",
        "motors-used"
    ],
    "wof:name":"Pump & Motor Shop Inc.",
    "wof:placetype":"venue"
},
  "geometry": {"coordinates":[-73.558846,40.77673],"type":"Point"}
}