{
  "type": "Feature",
  "properties": {
    "iso:country":"US",
    "sg:address":"18 Rand Pl",
    "sg:city":"Pittsford",
    "sg:classifiers":[
        {
            "category":"Professional",
            "subcategory":"Art Services",
            "type":"Services"
        }
    ],
    "sg:phone":"+1 585 249 9634",
    "sg:postcode":"14534",
    "sg:province":"NY",
    "sg:tags":[
        "graphic",
        "commercial",
        "designer",
        "artist"
    ],
    "wof:name":"Main St Cartographics",
    "wof:placetype":"venue"
},
  "geometry": {"coordinates":[-77.51515999999999,43.08802],"type":"Point"}
}