{
  "type": "Feature",
  "properties": {
    "addr:full":"40 E 94 St New York NY 10128",
    "addr:housenumber":"40;94",
    "addr:postcode":"10128",
    "addr:street":"E;St",
    "iso:country":"US",
    "sg:address":"40 E 94 St",
    "sg:city":"New York",
    "sg:classifiers":[
        {
            "category":"Parking",
            "type":"Transportation"
        }
    ],
    "sg:phone":"+1 212 722 9525",
    "sg:postcode":"10128",
    "sg:province":"NY",
    "sg:tags":[
        "garage"
    ],
    "wof:name":"Gallery Parking Corp",
    "wof:placetype":"venue"
},
  "geometry": {"coordinates":[-73.953503,40.785247],"type":"Point"}
}