{
  "type": "Feature",
  "properties": {
    "iso:country":"US",
    "sg:address":"411 Ellendale Ave",
    "sg:city":"Port Chester",
    "sg:classifiers":[
        {
            "category":"Personal",
            "subcategory":"Barber",
            "type":"Services"
        }
    ],
    "sg:phone":"+1   ",
    "sg:postcode":"10573",
    "sg:province":"NY",
    "sg:tags":[
        "shop"
    ],
    "wof:name":"Gfa Haircutting Inc",
    "wof:placetype":"venue"
},
  "geometry": {"coordinates":[-73.674494,41.002987],"type":"Point"}
}