{
  "type": "Feature",
  "properties": {
    "addr:full":"135-14 37ave Queens NY 11354",
    "addr:housenumber":"135-14",
    "addr:postcode":"11354",
    "addr:street":"37Ave",
    "iso:country":"US",
    "sg:address":"135-14 37ave",
    "sg:city":"Queens",
    "sg:classifiers":[
        {
            "category":"Personal",
            "subcategory":"Massage",
            "type":"Services"
        },
        {
            "category":"Personal",
            "subcategory":"Skin Care",
            "type":"Services"
        }
    ],
    "sg:phone":"+1 718 321 3828",
    "sg:postcode":"11354",
    "sg:province":"NY",
    "wof:name":"Y Square Beauty Studio",
    "wof:placetype":"venue"
},
  "geometry": {"coordinates":[-73.832539,40.760672],"type":"Point"}
}