{
  "type": "Feature",
  "properties": {
    "iso:country":"US",
    "sg:address":"700 Broad St",
    "sg:city":"Utica",
    "sg:classifiers":[
        {
            "category":"Wholesale",
            "subcategory":"Sporting Goods",
            "type":"Manufacturing & Wholesale Goods"
        }
    ],
    "sg:phone":"+1 315 733 3542",
    "sg:postcode":"13501",
    "sg:province":"NY",
    "sg:tags":[
        "stationery",
        "equipment",
        "recreational",
        "camping",
        "supply"
    ],
    "wof:name":"Wilcor International Inc",
    "wof:placetype":"venue"
},
  "geometry": {"coordinates":[-75.215189,43.100263],"type":"Point"}
}