{
  "type": "Feature",
  "properties": {
    "addr:full":"866 Coney Island Ave Brooklyn NY 11218",
    "addr:housenumber":"866",
    "addr:postcode":"11218",
    "addr:street":"Coney Island Ave",
    "iso:country":"US",
    "sg:address":"866 Coney Island Ave",
    "sg:city":"Brooklyn",
    "sg:classifiers":[
        {
            "category":"Taxi",
            "type":"Transportation"
        }
    ],
    "sg:phone":"+1   ",
    "sg:postcode":"11218",
    "sg:province":"NY",
    "sg:tags":[
        "taxicab"
    ],
    "wof:name":"Jillys Car Service",
    "wof:placetype":"venue"
},
  "geometry": {"coordinates":[-73.967765,40.635514],"type":"Point"}
}