{
  "type": "Feature",
  "properties": {
    "addr:full":"3 Boyle Rd Selden NY 11784",
    "addr:housenumber":"3",
    "addr:postcode":"11784",
    "addr:street":"Boyle Rd",
    "iso:country":"US",
    "sg:address":"3 Boyle Rd",
    "sg:city":"Selden",
    "sg:classifiers":[
        {
            "category":"Health Services",
            "subcategory":"Chiropractor",
            "type":"Services"
        }
    ],
    "sg:phone":"+1 631 698 6086",
    "sg:postcode":"11784",
    "sg:province":"NY",
    "wof:name":"Selden Medical Wellness",
    "wof:placetype":"venue"
},
  "geometry": {"coordinates":[-73.04969800000001,40.863998],"type":"Point"}
}