{
  "type": "Feature",
  "properties": {
    "addr:full":"1679 54th St Brooklyn NY 11204",
    "addr:housenumber":"1679",
    "addr:postcode":"11204",
    "addr:street":"54Th St",
    "iso:country":"US",
    "sg:address":"1679 54th St",
    "sg:city":"Brooklyn",
    "sg:classifiers":[
        {
            "category":"Restaurant",
            "type":"Food & Drink"
        }
    ],
    "sg:phone":"+1 718 851 1006",
    "sg:postcode":"11204",
    "sg:province":"NY",
    "sg:tags":[
        "seafood"
    ],
    "sg:website":"www.dagimfish.com",
    "wof:name":"Dagim Tahorim Co",
    "wof:placetype":"venue"
},
  "geometry": {"coordinates":[-73.98629800000001,40.627102],"type":"Point"}
}