{
  "type": "Feature",
  "properties": {
    "iso:country":"US",
    "sg:address":"110 Broad St",
    "sg:city":"Port Henry",
    "sg:classifiers":[
        {
            "category":"Government",
            "subcategory":"Office",
            "type":"Public Place"
        }
    ],
    "sg:phone":"+1 518 546 9994",
    "sg:postcode":"12974",
    "sg:province":"NY",
    "sg:tags":[
        "village"
    ],
    "wof:name":"Port Henry Village Office",
    "wof:placetype":"venue"
},
  "geometry": {"coordinates":[-73.46688399999999,44.047177],"type":"Point"}
}