{
  "type": "Feature",
  "properties": {
    "iso:country":"US",
    "sg:address":"345 Kear St",
    "sg:city":"Yorktown Heights",
    "sg:classifiers":[
        {
            "category":"Professional",
            "type":"Services"
        }
    ],
    "sg:phone":"+1 914 962 7890",
    "sg:postcode":"10598",
    "sg:province":"NY",
    "sg:tags":[
        "establishment"
    ],
    "wof:name":"Mitofsky International Inc",
    "wof:placetype":"venue"
},
  "geometry": {"coordinates":[-73.781312,41.270763],"type":"Point"}
}