{
  "type": "Feature",
  "properties": {
    "addr:full":"78 5th Ave Fl 7 New York NY 10011",
    "addr:housenumber":"78;7",
    "addr:postcode":"10011",
    "addr:street":"5Th Ave Fl",
    "iso:country":"US",
    "sg:address":"78 5th Ave Fl 7",
    "sg:city":"New York",
    "sg:classifiers":[
        {
            "category":"Shopping",
            "subcategory":"Bicycles & Sporting Goods",
            "type":"Retail Goods"
        }
    ],
    "sg:phone":"+1 212 675 0817",
    "sg:postcode":"10011",
    "sg:province":"NY",
    "wof:name":"Panther Sports & Fitness",
    "wof:placetype":"venue"
},
  "geometry": {"coordinates":[-73.99401899999999,40.735738],"type":"Point"}
}