{
  "type": "Feature",
  "properties": {
    "iso:country":"US",
    "sg:address":"371 Main St",
    "sg:city":"Massena",
    "sg:classifiers":[
        {
            "category":"Restaurant",
            "type":"Food & Drink"
        }
    ],
    "sg:menulink":"http://www.allmenus.com/ny/massena/144702-subway/menu/",
    "sg:phone":"+1 315 769 8897",
    "sg:postcode":"13662",
    "sg:province":"NY",
    "sg:tags":[
        "american",
        "sandwich"
    ],
    "wof:name":"Subway",
    "wof:placetype":"venue"
},
  "geometry": {"coordinates":[-74.88881000000001,44.920203],"type":"Point"}
}