{
  "type": "Feature",
  "properties": {
    "addr:full":"11218 Liberty Ave South Richmond Hill NY 11419",
    "addr:housenumber":"11218",
    "addr:postcode":"11419",
    "addr:street":"Liberty Ave South",
    "iso:country":"US",
    "sg:address":"11218 Liberty Ave",
    "sg:city":"South Richmond Hill",
    "sg:classifiers":[
        {
            "category":"Home & Garden",
            "subcategory":"Hardware",
            "type":"Retail Goods"
        }
    ],
    "sg:phone":"+1 718 738 1804",
    "sg:postcode":"11419",
    "sg:province":"NY",
    "sg:tags":[
        "store"
    ],
    "wof:name":"Empire Hardware & Supply",
    "wof:placetype":"venue"
},
  "geometry": {"coordinates":[-73.829498,40.685299],"type":"Point"}
}