{
  "type": "Feature",
  "properties": {
    "iso:country":"US",
    "sg:address":"130 Saratoga Rd",
    "sg:city":"S Glens Falls",
    "sg:classifiers":[
        {
            "category":"Retail",
            "subcategory":"Repair Shop",
            "type":"Services"
        }
    ],
    "sg:phone":"+1 518 798 5235",
    "sg:postcode":"12803",
    "sg:province":"NY",
    "sg:tags":[
        "television",
        "radio",
        "sales"
    ],
    "wof:name":"Action T-V Systems",
    "wof:placetype":"venue"
},
  "geometry": {"coordinates":[-73.637793,43.290206],"type":"Point"}
}