{
  "type": "Feature",
  "properties": {
    "iso:country":"US",
    "sg:address":"674 Ridge Rd",
    "sg:city":"Lackawanna",
    "sg:classifiers":[
        {
            "category":"Professional",
            "subcategory":"Lawyer & Legal Services",
            "type":"Services"
        }
    ],
    "sg:phone":"+1 716 823 2559",
    "sg:postcode":"14218",
    "sg:province":"NY",
    "sg:tags":[
        "attorney"
    ],
    "wof:name":"Edwin D Price",
    "wof:placetype":"venue"
},
  "geometry": {"coordinates":[-78.82751,42.825834],"type":"Point"}
}