{
  "type": "Feature",
  "properties": {
    "addr:full":"16405 82nd Rd Jamaica NY 11432",
    "addr:housenumber":"16405",
    "addr:postcode":"11432",
    "addr:street":"82Nd Rd",
    "iso:country":"US",
    "sg:address":"16405 82nd Rd",
    "sg:city":"Jamaica",
    "sg:classifiers":[
        {
            "category":"Health Services",
            "subcategory":"Chiropractor",
            "type":"Services"
        }
    ],
    "sg:phone":"+1 718 591 8776",
    "sg:postcode":"11432",
    "sg:province":"NY",
    "wof:name":"Schwartz Sanford DC",
    "wof:placetype":"venue"
},
  "geometry": {"coordinates":[-73.803398,40.717899],"type":"Point"}
}