{
  "type": "Feature",
  "properties": {
    "addr:full":"10528 Hinman Rd W Barneveld NY 13304",
    "addr:housenumber":"10528",
    "addr:postcode":"13304",
    "addr:street":"Hinman Rd W",
    "iso:country":"US",
    "sg:address":"10528 Hinman Rd W",
    "sg:city":"Barneveld",
    "sg:classifiers":[
        {
            "category":"Professional",
            "subcategory":"Management & Consulting",
            "type":"Services"
        }
    ],
    "sg:phone":"+1   ",
    "sg:postcode":"13304",
    "sg:province":"NY",
    "sg:tags":[
        "retail",
        "direct",
        "sales"
    ],
    "wof:name":"Rosa M Hosp",
    "wof:placetype":"venue"
},
  "geometry": {"coordinates":[-75.201511,43.240309],"type":"Point"}
}