{
  "type": "Feature",
  "properties": {
    "addr:full":"3 Manhattanville Rd Purchase NY 10577",
    "addr:housenumber":"3",
    "addr:postcode":"10577",
    "addr:street":"Manhattanville Rd",
    "iso:country":"US",
    "sg:address":"3 Manhattanville Rd",
    "sg:city":"Purchase",
    "sg:classifiers":[
        {
            "category":"Real Estate",
            "subcategory":"Real Estate Agent",
            "type":"Services"
        }
    ],
    "sg:phone":"+1 914 694 5900",
    "sg:postcode":"10577",
    "sg:province":"NY",
    "sg:tags":[
        "management"
    ],
    "wof:name":"West World Holding Inc",
    "wof:placetype":"venue"
},
  "geometry": {"coordinates":[-73.718013,41.023292],"type":"Point"}
}