{
  "type": "Feature",
  "properties": {
    "addr:full":"45 N Broadway Tarrytown NY 10591",
    "addr:housenumber":"45",
    "addr:postcode":"10591",
    "addr:street":"N Broadway",
    "iso:country":"US",
    "sg:address":"45 N Broadway",
    "sg:city":"Tarrytown",
    "sg:classifiers":[
        {
            "category":"Food & Beverages",
            "subcategory":"Groceries & Convenience Stores",
            "type":"Retail Goods"
        }
    ],
    "sg:phone":"+1   ",
    "sg:postcode":"10591",
    "sg:province":"NY",
    "wof:name":"Tarrytown Gourmet Inc",
    "wof:placetype":"venue"
},
  "geometry": {"coordinates":[-73.85778000000001,41.079616],"type":"Point"}
}