{
  "type": "Feature",
  "properties": {
    "addr:full":"149 Main St Cooperstown NY 13326",
    "addr:housenumber":"149",
    "addr:postcode":"13326",
    "addr:street":"Main St",
    "iso:country":"US",
    "sg:address":"149 Main St",
    "sg:city":"Cooperstown",
    "sg:classifiers":[
        {
            "category":"Shopping",
            "subcategory":"Clothing, Apparel, & Fashions",
            "type":"Retail Goods"
        }
    ],
    "sg:phone":"+1 607 547 8593",
    "sg:postcode":"13326",
    "sg:province":"NY",
    "sg:tags":[
        "t"
    ],
    "wof:name":"Cooperstown Shirt Co",
    "wof:placetype":"venue"
},
  "geometry": {"coordinates":[-74.92631,42.700785],"type":"Point"}
}