{
  "type": "Feature",
  "properties": {
    "addr:full":"12 Walker Rd Poughkeepsie NY 12603",
    "addr:housenumber":"12",
    "addr:postcode":"12603",
    "addr:street":"Walker Rd",
    "iso:country":"US",
    "sg:address":"12 Walker Rd",
    "sg:city":"Poughkeepsie",
    "sg:classifiers":[
        {
            "category":"Professional",
            "subcategory":"Lawyer & Legal Services",
            "type":"Services"
        }
    ],
    "sg:phone":"+1 845 462 0001",
    "sg:postcode":"12603",
    "sg:province":"NY",
    "sg:tags":[
        "attorney",
        "dwi",
        "duo",
        "divorce",
        "criminal",
        "law",
        "bankruptcy"
    ],
    "sg:website":"http://www.smandb.com",
    "wof:name":"Serino Mackay & Berube PLLC",
    "wof:placetype":"venue"
},
  "geometry": {"coordinates":[-73.870327,41.65407],"type":"Point"}
}