{
  "type": "Feature",
  "properties": {
    "addr:full":"180 Lake Flower Ave Saranac Lake NY 12983",
    "addr:housenumber":"180",
    "addr:postcode":"12983",
    "addr:street":"Lake Flower Ave",
    "iso:country":"US",
    "sg:address":"180 Lake Flower Ave",
    "sg:city":"Saranac Lake",
    "sg:classifiers":[
        {
            "category":"Autos & Motor Vehicles",
            "subcategory":"Fuel & Gas Station",
            "type":"Retail Goods"
        }
    ],
    "sg:phone":"+1 518 891 7246",
    "sg:postcode":"12983",
    "sg:province":"NY",
    "sg:tags":[
        "oil"
    ],
    "wof:name":"Hyde Mobil Convenience Store",
    "wof:placetype":"venue"
},
  "geometry": {"coordinates":[-74.116731,44.312728],"type":"Point"}
}