{
  "type": "Feature",
  "properties": {
    "iso:country":"US",
    "sg:address":"475 Jericho Tpke",
    "sg:city":"Mineola",
    "sg:classifiers":[
        {
            "category":"Shopping",
            "subcategory":"Bicycles & Sporting Goods",
            "type":"Retail Goods"
        }
    ],
    "sg:phone":"+1 516 742 5253",
    "sg:postcode":"11501",
    "sg:province":"NY",
    "sg:tags":[
        "repair",
        "lawnmowers"
    ],
    "wof:name":"Mineola Bicycle Fitnes & Mower",
    "wof:placetype":"venue"
},
  "geometry": {"coordinates":[-73.654712,40.744553],"type":"Point"}
}