{
  "type": "Feature",
  "properties": {
    "iso:country":"US",
    "sg:address":"65 Tuthill Rd",
    "sg:city":"Montauk",
    "sg:classifiers":[
        {
            "category":"Professional",
            "type":"Services"
        },
        {
            "category":"Restaurant",
            "type":"Food & Drink"
        },
        {
            "category":"Food & Beverages",
            "subcategory":"Meat & Fish",
            "type":"Retail Goods"
        }
    ],
    "sg:phone":"+1 631 668 2410",
    "sg:postcode":"11954",
    "sg:province":"NY",
    "sg:tags":[
        "style",
        "seafood-wholesale",
        "family",
        "seafood",
        "lunch",
        "caterer",
        "breakfast",
        "brunch",
        "market"
    ],
    "wof:name":"Duryea's Lobster Deck",
    "wof:placetype":"venue"
},
  "geometry": {"coordinates":[-71.95759099999999,41.051768],"type":"Point"}
}