{
  "type": "Feature",
  "properties": {
    "addr:full":"322 Latham Rd Mineola NY 11501",
    "addr:housenumber":"322",
    "addr:postcode":"11501",
    "addr:street":"Latham Rd",
    "iso:country":"US",
    "sg:address":"322 Latham Rd",
    "sg:city":"Mineola",
    "sg:classifiers":[
        {
            "category":"Building & Trades",
            "subcategory":"Construction",
            "type":"Services"
        }
    ],
    "sg:phone":"+1 516 877 2072",
    "sg:postcode":"11501",
    "sg:province":"NY",
    "sg:tags":[
        "general",
        "contractor"
    ],
    "wof:name":"Woodstar Contracting Corp",
    "wof:placetype":"venue"
},
  "geometry": {"coordinates":[-73.653643,40.745575],"type":"Point"}
}