{
  "type": "Feature",
  "properties": {
    "addr:full":"31 Colonial Ave Lancaster NY 14086",
    "addr:housenumber":"31",
    "addr:postcode":"14086",
    "addr:street":"Colonial Ave",
    "iso:country":"US",
    "sg:address":"31 Colonial Ave",
    "sg:city":"Lancaster",
    "sg:classifiers":[
        {
            "category":"Food & Beverages",
            "subcategory":"Bakery",
            "type":"Retail Goods"
        }
    ],
    "sg:phone":"+1   ",
    "sg:postcode":"14086",
    "sg:province":"NY",
    "wof:name":"Cookies Etc",
    "wof:placetype":"venue"
},
  "geometry": {"coordinates":[-78.670586,42.898032],"type":"Point"}
}