{
  "type": "Feature",
  "properties": {
    "iso:country":"US",
    "sg:address":"1115 Astor Ave",
    "sg:city":"Bronx",
    "sg:classifiers":[
        {
            "category":"Restaurant",
            "type":"Food & Drink"
        }
    ],
    "sg:phone":"+1 718 547 7557",
    "sg:postcode":"10469",
    "sg:province":"NY",
    "sg:tags":[
        "pizza"
    ],
    "sg:website":"http://www.veneziapizza.net",
    "wof:name":"Venezia Pizzeria",
    "wof:placetype":"venue"
},
  "geometry": {"coordinates":[-73.855598,40.859901],"type":"Point"}
}