{
  "type": "Feature",
  "properties": {
    "addr:full":"3379 Milton Ave Syracuse NY 13219",
    "addr:housenumber":"3379",
    "addr:postcode":"13219",
    "addr:street":"Milton Ave",
    "iso:country":"US",
    "sg:address":"3379 Milton Ave",
    "sg:city":"Syracuse",
    "sg:classifiers":[
        {
            "category":"Manufacturing",
            "subcategory":"Jewelry",
            "type":"Manufacturing & Wholesale Goods"
        },
        {
            "category":"Wholesale",
            "subcategory":"Construction Materials",
            "type":"Manufacturing & Wholesale Goods"
        },
        {
            "category":"Home & Garden",
            "subcategory":"Building Materials",
            "type":"Retail Goods"
        }
    ],
    "sg:phone":"+1 315 487 5931",
    "sg:postcode":"13219",
    "sg:province":"NY",
    "sg:tags":[
        "stone",
        "supply",
        "natural-wholesale",
        "equipment",
        "masonry",
        "manufacturer"
    ],
    "sg:website":"http://www.miltonsupply.com",
    "wof:name":"Milton Supply CO",
    "wof:placetype":"venue"
},
  "geometry": {"coordinates":[-76.24051799999999,43.051175],"type":"Point"}
}