{
  "type": "Feature",
  "properties": {
    "addr:full":"5 Greenbush Ave East Greenbush NY 12061",
    "addr:housenumber":"5",
    "addr:postcode":"12061",
    "addr:street":"Greenbush Ave",
    "iso:country":"US",
    "sg:address":"5 Greenbush Ave",
    "sg:city":"East Greenbush",
    "sg:classifiers":[
        {
            "category":"Social Services",
            "subcategory":"Child Care",
            "type":"Services"
        }
    ],
    "sg:phone":"+1 518 477 4125",
    "sg:postcode":"12061",
    "sg:province":"NY",
    "sg:tags":[
        "center"
    ],
    "wof:name":"G C C Inc",
    "wof:placetype":"venue"
},
  "geometry": {"coordinates":[-73.707599,42.606371],"type":"Point"}
}