{
  "type": "Feature",
  "properties": {
    "addr:full":"6102 7th Ave Brooklyn NY 11220",
    "addr:housenumber":"6102",
    "addr:postcode":"11220",
    "addr:street":"7Th Ave",
    "iso:country":"US",
    "sg:address":"6102 7th Ave",
    "sg:city":"Brooklyn",
    "sg:classifiers":[
        {
            "category":"Restaurant",
            "type":"Food & Drink"
        }
    ],
    "sg:phone":"+1 718 492 9088",
    "sg:postcode":"11220",
    "sg:province":"NY",
    "sg:tags":[
        "malaysian"
    ],
    "wof:name":"Belachan Restaurant",
    "wof:placetype":"venue"
},
  "geometry": {"coordinates":[-74.012368,40.636233],"type":"Point"}
}