{
  "type": "Feature",
  "properties": {
    "addr:full":"4422 3rd Ave Bronx NY 10457",
    "addr:housenumber":"4422",
    "addr:postcode":"10457",
    "addr:street":"3Rd Ave",
    "iso:country":"US",
    "sg:address":"4422 3rd Ave",
    "sg:city":"Bronx",
    "sg:classifiers":[
        {
            "category":"Health Services",
            "subcategory":"Hospital",
            "type":"Services"
        }
    ],
    "sg:phone":"+1 800 240 6147",
    "sg:postcode":"10457",
    "sg:province":"NY",
    "sg:website":"www.stbarnabashospital.org",
    "wof:name":"St. Barnabas Hospital",
    "wof:placetype":"venue"
},
  "geometry": {"coordinates":[-73.890766,40.854027],"type":"Point"}
}