{
  "type": "Feature",
  "properties": {
    "iso:country":"US",
    "sg:address":"902 Old Country Rd",
    "sg:city":"Westbury",
    "sg:classifiers":[
        {
            "category":"Retail",
            "subcategory":"Repair Shop",
            "type":"Services"
        },
        {
            "category":"Shopping",
            "subcategory":"Crafts & Fabrics",
            "type":"Retail Goods"
        },
        {
            "category":"Wholesale",
            "subcategory":"Home Furnishings",
            "type":"Manufacturing & Wholesale Goods"
        }
    ],
    "sg:phone":"+1 516 334 6330",
    "sg:postcode":"11590",
    "sg:province":"NY",
    "sg:tags":[
        "blind",
        "reupholstery",
        "store",
        "shade",
        "furniture"
    ],
    "wof:name":"Weinstein Wallpaper",
    "wof:placetype":"venue"
},
  "geometry": {"coordinates":[-73.562202,40.753799],"type":"Point"}
}