{
  "type": "Feature",
  "properties": {
    "addr:full":"7 Avis Dr Latham NY 12110",
    "addr:housenumber":"7",
    "addr:postcode":"12110",
    "addr:street":"Avis Dr",
    "iso:country":"US",
    "sg:address":"7 Avis Dr",
    "sg:city":"Latham",
    "sg:classifiers":[
        {
            "category":"Sports & Exercise",
            "subcategory":"Gym",
            "type":"Entertainment"
        }
    ],
    "sg:phone":"+1 518 786 1212",
    "sg:postcode":"12110",
    "sg:province":"NY",
    "sg:tags":[
        "spa",
        "health"
    ],
    "wof:name":"Saratoga Spa & Bath Inc",
    "wof:placetype":"venue"
},
  "geometry": {"coordinates":[-73.778915,42.746972],"type":"Point"}
}