{
  "type": "Feature",
  "properties": {
    "iso:country":"US",
    "sg:address":"6 Houston Ave",
    "sg:city":"Monroe",
    "sg:classifiers":[
        {
            "category":"Personal",
            "type":"Services"
        }
    ],
    "sg:phone":"+1 845 728 3140",
    "sg:postcode":"10950",
    "sg:province":"NY",
    "sg:tags":[
        "therapist",
        "massage"
    ],
    "wof:name":"Martin Fredericks",
    "wof:placetype":"venue"
},
  "geometry": {"coordinates":[-74.181803,41.363184],"type":"Point"}
}