{
  "type": "Feature",
  "properties": {
    "addr:full":"92 E Jericho Tpke Mineola NY 11501",
    "addr:housenumber":"92",
    "addr:postcode":"11501",
    "addr:street":"E Jericho Tpke",
    "iso:country":"US",
    "sg:address":"92 E Jericho Tpke",
    "sg:city":"Mineola",
    "sg:classifiers":[
        {
            "category":"Building & Trades",
            "subcategory":"Plumbing",
            "type":"Services"
        }
    ],
    "sg:phone":"+1 516 280 5940",
    "sg:postcode":"11501",
    "sg:province":"NY",
    "wof:name":"Mallis Plumbing Supply",
    "wof:placetype":"venue"
},
  "geometry": {"coordinates":[-73.631524,40.752557],"type":"Point"}
}