{
  "type": "Feature",
  "properties": {
    "addr:full":"366 Hempstead Ave Malverne NY 11565",
    "addr:housenumber":"366",
    "addr:postcode":"11565",
    "addr:street":"Hempstead Ave",
    "iso:country":"US",
    "sg:address":"366 Hempstead Ave",
    "sg:city":"Malverne",
    "sg:classifiers":[
        {
            "category":"Restaurant",
            "type":"Food & Drink"
        }
    ],
    "sg:phone":"+1 516 792 6336",
    "sg:postcode":"11565",
    "sg:province":"NY",
    "sg:tags":[
        "italian"
    ],
    "wof:name":"Il Villagio",
    "wof:placetype":"venue"
},
  "geometry": {"coordinates":[-73.667523,40.67779],"type":"Point"}
}