{
  "type": "Feature",
  "properties": {
    "addr:full":"938 8th Ave New York NY 10079",
    "addr:housenumber":"938",
    "addr:postcode":"10079",
    "addr:street":"8Th Ave",
    "iso:country":"US",
    "sg:address":"938 8th Ave",
    "sg:city":"New York",
    "sg:classifiers":[
        {
            "category":"Fast Food",
            "type":"Food & Drink"
        }
    ],
    "sg:phone":"+1 212 977 4785",
    "sg:postcode":"10079",
    "sg:province":"NY",
    "sg:tags":[
        "burger"
    ],
    "sg:website":"www.wendys.com",
    "wof:name":"Wendy's",
    "wof:placetype":"venue"
},
  "geometry": {"coordinates":[-74.004814,40.737537],"type":"Point"}
}