{
  "type": "Feature",
  "properties": {
    "addr:full":"2708 State Hwy 315 Deansboro NY 13328",
    "addr:housenumber":"2708",
    "addr:postcode":"13328",
    "addr:street":"State Hwy 315",
    "iso:country":"US",
    "sg:address":"2708 State Hwy 315",
    "sg:city":"Deansboro",
    "sg:classifiers":[
        {
            "category":"Retail",
            "subcategory":"Auto Repair",
            "type":"Services"
        }
    ],
    "sg:phone":"+1 315 841 8004",
    "sg:postcode":"13328",
    "sg:province":"NY",
    "sg:tags":[
        "repairing",
        "automobile"
    ],
    "wof:name":"Lindfield Transmission & Rpr",
    "wof:placetype":"venue"
},
  "geometry": {"coordinates":[-75.42633499999999,42.994375],"type":"Point"}
}