{
  "type": "Feature",
  "properties": {
    "iso:country":"US",
    "sg:address":"1651 Olean-Portville Rd",
    "sg:city":"Olean",
    "sg:classifiers":[
        {
            "category":"Autos & Motor Vehicles",
            "subcategory":"Automobile Sales",
            "type":"Retail Goods"
        }
    ],
    "sg:phone":"+1 716 373 6321",
    "sg:postcode":"14760",
    "sg:province":"NY",
    "sg:tags":[
        "car",
        "used",
        "dealer"
    ],
    "wof:name":"Denny's Cars",
    "wof:placetype":"venue"
},
  "geometry": {"coordinates":[-78.396413,42.071113],"type":"Point"}
}