{
  "type": "Feature",
  "properties": {
    "addr:full":"4861 State Hwy 52 Jeffersonville NY 12726",
    "addr:housenumber":"4861",
    "addr:postcode":"12726",
    "addr:street":"State Hwy 52",
    "iso:country":"US",
    "sg:address":"4861 State Hwy 52",
    "sg:city":"Jeffersonville",
    "sg:classifiers":[
        {
            "category":"Professional",
            "subcategory":"Lawyer & Legal Services",
            "type":"Services"
        }
    ],
    "sg:phone":"+1 845 482 4200",
    "sg:postcode":"12726",
    "sg:province":"NY",
    "sg:tags":[
        "attorney"
    ],
    "wof:name":"Levine Glass & Miller",
    "wof:placetype":"venue"
},
  "geometry": {"coordinates":[-74.98021900000001,41.658302],"type":"Point"}
}