{
  "type": "Feature",
  "properties": {
    "iso:country":"US",
    "sg:address":"2041 5 Ave",
    "sg:city":"New York",
    "sg:classifiers":[
        {
            "category":"Organizations",
            "subcategory":"Professional Association",
            "type":"Services"
        }
    ],
    "sg:phone":"+1 212 423 9930",
    "sg:postcode":"10035",
    "sg:province":"NY",
    "wof:name":"2041 Tenants Assoc",
    "wof:placetype":"venue"
},
  "geometry": {"coordinates":[-73.941771,40.807089],"type":"Point"}
}