{
  "type": "Feature",
  "properties": {
    "addr:full":"2 Bay Club Dr Flushing NY 11360",
    "addr:housenumber":"2",
    "addr:postcode":"11360",
    "addr:street":"Bay Club Dr",
    "iso:country":"US",
    "sg:address":"2 Bay Club Dr",
    "sg:city":"Flushing",
    "sg:classifiers":[
        {
            "category":"Health Services",
            "subcategory":"Doctor",
            "type":"Services"
        }
    ],
    "sg:phone":"+1 718 631 9440",
    "sg:postcode":"11360",
    "sg:province":"NY",
    "sg:tags":[
        "physician",
        "surgeon"
    ],
    "wof:name":"Marianne Frieri MD",
    "wof:placetype":"venue"
},
  "geometry": {"coordinates":[-73.781257,40.779098],"type":"Point"}
}