{
  "type": "Feature",
  "properties": {
    "addr:full":"84 Willow St Otego NY 13825",
    "addr:housenumber":"84",
    "addr:postcode":"13825",
    "addr:street":"Willow St",
    "iso:country":"US",
    "sg:address":"84 Willow St",
    "sg:city":"Otego",
    "sg:classifiers":[
        {
            "category":"Building & Trades",
            "subcategory":"Construction",
            "type":"Services"
        }
    ],
    "sg:phone":"+1 607 988 6805",
    "sg:postcode":"13825",
    "sg:province":"NY",
    "sg:tags":[
        "house"
    ],
    "wof:name":"Secor Construction",
    "wof:placetype":"venue"
},
  "geometry": {"coordinates":[-75.17977399999999,42.400537],"type":"Point"}
}