{
  "type": "Feature",
  "properties": {
    "iso:country":"US",
    "sg:address":"11 Powerhouse Rd",
    "sg:city":"Roslyn Heights",
    "sg:classifiers":[
        {
            "category":"Insurance",
            "subcategory":"Hazard Insurance",
            "type":"Services"
        }
    ],
    "sg:phone":"+1 516 484 5200",
    "sg:postcode":"11577",
    "sg:province":"NY",
    "sg:website":"www.ccpinsurance.com",
    "wof:name":"Curran Cooney Penny Agency",
    "wof:placetype":"venue"
},
  "geometry": {"coordinates":[-73.639503,40.785198],"type":"Point"}
}