{
  "type": "Feature",
  "properties": {
    "iso:country":"US",
    "sg:address":"315 Fayette St",
    "sg:city":"Manlius",
    "sg:classifiers":[
        {
            "category":"Shopping",
            "subcategory":"Jewelry",
            "type":"Retail Goods"
        }
    ],
    "sg:phone":"+1 315 682 3124",
    "sg:postcode":"13104",
    "sg:province":"NY",
    "sg:tags":[
        "jeweler"
    ],
    "sg:website":"www.manliusjewelry.com",
    "wof:name":"Manilius Jewelry & Repair",
    "wof:placetype":"venue"
},
  "geometry": {"coordinates":[-75.984309,43.005623],"type":"Point"}
}