{
  "type": "Feature",
  "properties": {
    "addr:full":"119 Higby Rd Utica NY 13501",
    "addr:housenumber":"119",
    "addr:postcode":"13501",
    "addr:street":"Higby Rd",
    "iso:country":"US",
    "sg:address":"119 Higby Rd",
    "sg:city":"Utica",
    "sg:classifiers":[
        {
            "category":"Real Estate",
            "subcategory":"Real Estate Agent",
            "type":"Services"
        }
    ],
    "sg:phone":"+1 315 724 3338",
    "sg:postcode":"13501",
    "sg:province":"NY",
    "wof:name":"Stephen A Roefaro",
    "wof:placetype":"venue"
},
  "geometry": {"coordinates":[-75.27455500000001,43.071138],"type":"Point"}
}