{
  "type": "Feature",
  "properties": {
    "iso:country":"US",
    "sg:address":"6380 Conner Rd",
    "sg:city":"East Amherst",
    "sg:classifiers":[
        {
            "category":"Building & Trades",
            "subcategory":"Construction",
            "type":"Services"
        }
    ],
    "sg:phone":"+1 716 741 4094",
    "sg:postcode":"14051",
    "sg:province":"NY",
    "sg:tags":[
        "house"
    ],
    "wof:name":"Atlas Construction",
    "wof:placetype":"venue"
},
  "geometry": {"coordinates":[-78.662813,43.03114],"type":"Point"}
}