{
  "type": "Feature",
  "properties": {
    "addr:full":"4 W 18th Street New York NY 10011",
    "addr:housenumber":"4",
    "addr:postcode":"10011",
    "addr:street":"W 18Th Street",
    "iso:country":"US",
    "sg:address":"4 W 18th Street",
    "sg:city":"New York",
    "sg:classifiers":[
        {
            "category":"Arena",
            "subcategory":"Sports Club",
            "type":"Entertainment"
        }
    ],
    "sg:phone":"+1 212 677 7228",
    "sg:postcode":"10011",
    "sg:province":"NY",
    "sg:tags":[
        "martial art"
    ],
    "wof:name":"Society For Martial Arts Instruction",
    "wof:placetype":"venue"
},
  "geometry": {"coordinates":[-73.991958,40.738673],"type":"Point"}
}