{
  "type": "Feature",
  "properties": {
    "iso:country":"US",
    "sg:address":"395 E Main St",
    "sg:city":"Ilion",
    "sg:classifiers":[
        {
            "category":"Building & Trades",
            "subcategory":"Equipment Rental",
            "type":"Services"
        }
    ],
    "sg:phone":"+1 315 866 5521",
    "sg:postcode":"13357",
    "sg:province":"NY",
    "sg:tags":[
        "yard",
        "leasing",
        "store",
        "contractors'"
    ],
    "sg:website":"http://www.backbreakacres.com",
    "wof:name":"Backbreak Acres Outdoor Power Equipment",
    "wof:placetype":"venue"
},
  "geometry": {"coordinates":[-75.023781,43.010381],"type":"Point"}
}