{
  "type": "Feature",
  "properties": {
    "addr:full":"2159 White Plains Rd Bronx NY 10462",
    "addr:housenumber":"2159",
    "addr:postcode":"10462",
    "addr:street":"White Plains Rd",
    "iso:country":"US",
    "sg:address":"2159 White Plains Rd",
    "sg:city":"Bronx",
    "sg:classifiers":[
        {
            "category":"Banks & Credit Unions",
            "subcategory":"Bank",
            "type":"Services"
        }
    ],
    "sg:phone":"+1 718 822 7502",
    "sg:postcode":"10462",
    "sg:province":"NY",
    "sg:website":"www.northforkbank.com",
    "wof:name":"CapitalOne",
    "wof:placetype":"venue"
},
  "geometry": {"coordinates":[-73.86787,40.855148],"type":"Point"}
}