{
  "type": "Feature",
  "properties": {
    "iso:country":"US",
    "sg:address":"23201 Merrick Boulevard",
    "sg:city":"Springfield Gardens",
    "sg:classifiers":[
        {
            "category":"Health Services",
            "subcategory":"Doctor",
            "type":"Services"
        }
    ],
    "sg:phone":"+1 718 525 9655",
    "sg:postcode":"11413",
    "sg:province":"NY",
    "wof:name":"Bowen-Ericksen Maria",
    "wof:placetype":"venue"
},
  "geometry": {"coordinates":[-73.737559,40.67531],"type":"Point"}
}