{
  "type": "Feature",
  "properties": {
    "addr:full":"686 Grand St Brooklyn NY 11211",
    "addr:housenumber":"686",
    "addr:postcode":"11211",
    "addr:street":"Grand St",
    "iso:country":"US",
    "sg:address":"686 Grand St",
    "sg:city":"Brooklyn",
    "sg:classifiers":[
        {
            "category":"Freight",
            "type":"Transportation"
        }
    ],
    "sg:phone":"+1   ",
    "sg:postcode":"11211",
    "sg:province":"NY",
    "sg:tags":[
        "general"
    ],
    "wof:name":"Clk Communication Inc",
    "wof:placetype":"venue"
},
  "geometry": {"coordinates":[-73.94424600000001,40.711524],"type":"Point"}
}