{
  "type": "Feature",
  "properties": {
    "iso:country":"US",
    "sg:address":"451 Fishkill Ave",
    "sg:city":"Beacon",
    "sg:classifiers":[
        {
            "category":"Social Services",
            "subcategory":"Child Care",
            "type":"Services"
        }
    ],
    "sg:phone":"+1 845 838 0275",
    "sg:postcode":"12508",
    "sg:province":"NY",
    "sg:tags":[
        "day"
    ],
    "wof:name":"NECDS",
    "wof:placetype":"venue"
},
  "geometry": {"coordinates":[-73.950423,41.513337],"type":"Point"}
}