{
  "type": "Feature",
  "properties": {
    "addr:full":"4949 Harlem Rd Amherst NY 14226",
    "addr:housenumber":"4949",
    "addr:postcode":"14226",
    "addr:street":"Harlem Rd",
    "iso:country":"US",
    "sg:address":"4949 Harlem Rd",
    "sg:city":"Amherst",
    "sg:classifiers":[
        {
            "category":"Shopping",
            "type":"Retail Goods"
        }
    ],
    "sg:phone":"+1 716 833 4488",
    "sg:postcode":"14226",
    "sg:province":"NY",
    "sg:tags":[
        "hearing",
        "equipment",
        "supply",
        "impaired"
    ],
    "wof:name":"Hearing Evaluation Svc",
    "wof:placetype":"venue"
},
  "geometry": {"coordinates":[-78.78381899999999,42.978324],"type":"Point"}
}