{
  "type": "Feature",
  "properties": {
    "addr:full":"100 16 Park New York NY 10017",
    "addr:housenumber":"16",
    "addr:postcode":"100;10017",
    "addr:street":"Park",
    "iso:country":"US",
    "sg:address":"100 16 Park",
    "sg:city":"New York",
    "sg:classifiers":[
        {
            "category":"Real Estate",
            "subcategory":"Real Estate Services",
            "type":"Services"
        }
    ],
    "sg:phone":"+1 212 722 6917",
    "sg:postcode":"10017",
    "sg:province":"NY",
    "sg:tags":[
        "management",
        "property"
    ],
    "wof:name":"Belle Maison Realty",
    "wof:placetype":"venue"
},
  "geometry": {"coordinates":[-73.97870399999999,40.750884],"type":"Point"}
}