{
  "type": "Feature",
  "properties": {
    "addr:full":"19 Cedarlawn Rd Irvington NY 10533",
    "addr:housenumber":"19",
    "addr:postcode":"ny 10533",
    "addr:street":"Cedarlawn Rd",
    "iso:country":"US",
    "sg:address":"19 Cedarlawn Rd",
    "sg:city":"Irvington",
    "sg:classifiers":[
        {
            "category":"Real Estate",
            "subcategory":"Architect",
            "type":"Services"
        }
    ],
    "sg:phone":"+1 914 591 6623",
    "sg:postcode":"10533",
    "sg:province":"NY",
    "wof:name":"Minner Arthur R Arch",
    "wof:placetype":"venue"
},
  "geometry": {"coordinates":[-73.85948399999999,41.036288],"type":"Point"}
}