{
  "type": "Feature",
  "properties": {
    "iso:country":"US",
    "sg:address":"7 Grange Pl",
    "sg:city":"Cortland",
    "sg:classifiers":[
        {
            "category":"Organizations",
            "subcategory":"Religious Organization",
            "type":"Services"
        }
    ],
    "sg:phone":"+1 607 756 4916",
    "sg:postcode":"13045",
    "sg:province":"NY",
    "sg:tags":[
        "clergy"
    ],
    "wof:name":"I Warren",
    "wof:placetype":"venue"
},
  "geometry": {"coordinates":[-76.169749,42.606667],"type":"Point"}
}