{
  "type": "Feature",
  "properties": {
    "addr:full":"10960 142nd St Jamaica NY 11435",
    "addr:housenumber":"10960",
    "addr:postcode":"11435",
    "addr:street":"142Nd St",
    "iso:country":"US",
    "sg:address":"10960 142nd St",
    "sg:city":"Jamaica",
    "sg:classifiers":[
        {
            "category":"Place Of Worship",
            "subcategory":"Church",
            "type":"Public Place"
        },
        {
            "category":"Place Of Worship",
            "type":"Public Place"
        }
    ],
    "sg:phone":"+1 718 206 4100",
    "sg:postcode":"11435",
    "sg:province":"NY",
    "sg:tags":[
        "churches-non-denominational"
    ],
    "sg:website":"http://www.joychurchjamaica.com",
    "wof:name":"Joy Church Dlcf",
    "wof:placetype":"venue"
},
  "geometry": {"coordinates":[-73.80273800000001,40.686359],"type":"Point"}
}