{
  "type": "Feature",
  "properties": {
    "iso:country":"US",
    "sg:address":"519 Allens Creek Rd",
    "sg:city":"Rochester",
    "sg:classifiers":[
        {
            "category":"Recreation",
            "subcategory":"Amusement Park",
            "type":"Entertainment"
        }
    ],
    "sg:phone":"+1 585 461 2528",
    "sg:postcode":"14618",
    "sg:province":"NY",
    "wof:name":"Creative Music Studio",
    "wof:placetype":"venue"
},
  "geometry": {"coordinates":[-77.540092,43.118311],"type":"Point"}
}