{
  "type": "Feature",
  "properties": {
    "addr:full":"252 E 167th St Bronx NY 10456",
    "addr:housenumber":"252",
    "addr:postcode":"10456",
    "addr:street":"E 167Th St",
    "iso:country":"US",
    "sg:address":"252 E 167th St",
    "sg:city":"Bronx",
    "sg:classifiers":[
        {
            "category":"Shopping",
            "type":"Retail Goods"
        }
    ],
    "sg:phone":"+1 718 681 4015",
    "sg:postcode":"10456",
    "sg:province":"NY",
    "sg:tags":[
        "wedding",
        "supply"
    ],
    "wof:name":"Concourse Jamaica Bakery",
    "wof:placetype":"venue"
},
  "geometry": {"coordinates":[-73.914185,40.833251],"type":"Point"}
}