{
  "type": "Feature",
  "properties": {
    "iso:country":"US",
    "sg:address":"450 7 Ave",
    "sg:city":"New York",
    "sg:classifiers":[
        {
            "category":"Professional",
            "type":"Services"
        }
    ],
    "sg:phone":"+1 212 594 3851",
    "sg:postcode":"10123",
    "sg:province":"NY",
    "sg:tags":[
        "establishment"
    ],
    "wof:name":"Bloom Hochberg & Co PC",
    "wof:placetype":"venue"
},
  "geometry": {"coordinates":[-73.990134,40.751659],"type":"Point"}
}