{
  "type": "Feature",
  "properties": {
    "addr:full":"2015 3 Ave New York NY 10029",
    "addr:housenumber":"2015",
    "addr:postcode":"10029",
    "addr:street":"3 Ave",
    "iso:country":"US",
    "sg:address":"2015 3 Ave",
    "sg:city":"New York",
    "sg:classifiers":[
        {
            "category":"Retail",
            "subcategory":"Auto Repair",
            "type":"Services"
        }
    ],
    "sg:phone":"+1 212 423 0054",
    "sg:postcode":"10029",
    "sg:province":"NY",
    "sg:tags":[
        "repairing",
        "automobile"
    ],
    "wof:name":"Lasta Lal Auto Svc",
    "wof:placetype":"venue"
},
  "geometry": {"coordinates":[-73.94882699999999,40.785881],"type":"Point"}
}