{
  "type": "Feature",
  "properties": {
    "iso:country":"US",
    "sg:address":"800 2nd Ave",
    "sg:city":"New York",
    "sg:classifiers":[
        {
            "category":"Health Services",
            "subcategory":"Doctor",
            "type":"Services"
        }
    ],
    "sg:phone":"+1 866 570 5996",
    "sg:postcode":"10017",
    "sg:province":"NY",
    "sg:tags":[
        "surgeon",
        "cosmetic"
    ],
    "sg:website":"www.aestheticasurgical.com",
    "wof:name":"Aesthetica Surgical",
    "wof:placetype":"venue"
},
  "geometry": {"coordinates":[-73.971999,40.749923],"type":"Point"}
}