{
  "type": "Feature",
  "properties": {
    "iso:country":"US",
    "sg:address":"234 46th St",
    "sg:city":"Brooklyn",
    "sg:classifiers":[
        {
            "category":"Shopping",
            "subcategory":"Clothing, Apparel, & Fashions",
            "type":"Retail Goods"
        }
    ],
    "sg:phone":"+1 718 439 7720",
    "sg:postcode":"11220",
    "sg:province":"NY",
    "sg:tags":[
        "designer"
    ],
    "wof:name":"Dream Fashion Inc",
    "wof:placetype":"venue"
},
  "geometry": {"coordinates":[-74.01295,40.650369],"type":"Point"}
}