{
  "type": "Feature",
  "properties": {
    "iso:country":"US",
    "sg:address":"1205 Ney Ave",
    "sg:city":"Utica",
    "sg:classifiers":[
        {
            "category":"Health Services",
            "subcategory":"Health Practitioner",
            "type":"Services"
        }
    ],
    "sg:phone":"+1   ",
    "sg:postcode":"13502",
    "sg:province":"NY",
    "wof:name":"Anne-Marie Lmt Pyrda",
    "wof:placetype":"venue"
},
  "geometry": {"coordinates":[-75.265411,43.105391],"type":"Point"}
}