{
  "type": "Feature",
  "properties": {
    "addr:full":"59 Timber Point Dr Northport NY 11768",
    "addr:housenumber":"59",
    "addr:postcode":"11768",
    "addr:street":"Timber Point Dr",
    "iso:country":"US",
    "sg:address":"59 Timber Point Dr",
    "sg:city":"Northport",
    "sg:classifiers":[
        {
            "category":"Communications",
            "subcategory":"Film & Video Production",
            "type":"Services"
        }
    ],
    "sg:phone":"+1   ",
    "sg:postcode":"11768",
    "sg:province":"NY",
    "sg:tags":[
        "motion"
    ],
    "wof:name":"Early Autumn Productions",
    "wof:placetype":"venue"
},
  "geometry": {"coordinates":[-73.309772,40.902443],"type":"Point"}
}