{
  "type": "Feature",
  "properties": {
    "iso:country":"US",
    "sg:address":"8110 Leah Ct",
    "sg:city":"Buffalo",
    "sg:classifiers":[
        {
            "category":"Building & Trades",
            "subcategory":"Construction",
            "type":"Services"
        }
    ],
    "sg:phone":"+1 716 689 3955",
    "sg:postcode":"14221",
    "sg:province":"NY",
    "sg:tags":[
        "house"
    ],
    "wof:name":"Pauly Construction",
    "wof:placetype":"venue"
},
  "geometry": {"coordinates":[-78.69093100000001,42.992239],"type":"Point"}
}