{
  "type": "Feature",
  "properties": {
    "iso:country":"US",
    "sg:address":"261 Pine Hollow Rd",
    "sg:city":"Oyster Bay",
    "sg:classifiers":[
        {
            "category":"Travel",
            "subcategory":"Travel Agent",
            "type":"Entertainment"
        }
    ],
    "sg:phone":"+1   ",
    "sg:postcode":"11771",
    "sg:province":"NY",
    "sg:tags":[
        "agency"
    ],
    "wof:name":"East Norwich Travel",
    "wof:placetype":"venue"
},
  "geometry": {"coordinates":[-73.535483,40.858947],"type":"Point"}
}