{
  "type": "Feature",
  "properties": {
    "iso:country":"US",
    "sg:address":"5 Chapman St",
    "sg:city":"Rouses Point",
    "sg:classifiers":[
        {
            "category":"Insurance",
            "subcategory":"Insurance Agent",
            "type":"Services"
        }
    ],
    "sg:phone":"+1 518 297 6602",
    "sg:postcode":"12979",
    "sg:province":"NY",
    "wof:name":"Chauvin Agency Inc",
    "wof:placetype":"venue"
},
  "geometry": {"coordinates":[-73.364659,44.992298],"type":"Point"}
}