{
  "type": "Feature",
  "properties": {
    "addr:full":"2537 US Hwy 9w Ravena NY 12143",
    "addr:housenumber":"2537",
    "addr:postcode":"12143",
    "addr:street":"Us Hwy 9W",
    "iso:country":"US",
    "sg:address":"2537 US Hwy 9w",
    "sg:city":"Ravena",
    "sg:classifiers":[
        {
            "category":"Retail",
            "subcategory":"Auto Repair",
            "type":"Services"
        }
    ],
    "sg:phone":"+1 518 756 9020",
    "sg:postcode":"12143",
    "sg:province":"NY",
    "sg:tags":[
        "wrecker"
    ],
    "wof:name":"Burns & Sons",
    "wof:placetype":"venue"
},
  "geometry": {"coordinates":[-73.817246,42.463541],"type":"Point"}
}