{
  "type": "Feature",
  "properties": {
    "iso:country":"US",
    "sg:address":"38 W 32nd St",
    "sg:city":"New York",
    "sg:classifiers":[
        {
            "category":"Education",
            "subcategory":"Special Training",
            "type":"Public Place"
        }
    ],
    "sg:phone":"+1 212 695 5470",
    "sg:postcode":"10001",
    "sg:province":"NY",
    "sg:tags":[
        "school",
        "art"
    ],
    "wof:name":"Pi Art Center",
    "wof:placetype":"venue"
},
  "geometry": {"coordinates":[-73.98742799999999,40.747929],"type":"Point"}
}