{
  "type": "Feature",
  "properties": {
    "addr:full":"21 W 45th St Fl 5L New York NY 10036",
    "addr:housenumber":"21;5l",
    "addr:postcode":"10036",
    "addr:street":"W 45Th St",
    "iso:country":"US",
    "sg:address":"21 W 45th St Fl 5L",
    "sg:city":"New York",
    "sg:classifiers":[
        {
            "category":"Shopping",
            "subcategory":"Jewelry",
            "type":"Retail Goods"
        }
    ],
    "sg:phone":"+1 212 575 0257",
    "sg:postcode":"10036",
    "sg:province":"NY",
    "wof:name":"E & I Jewelry",
    "wof:placetype":"venue"
},
  "geometry": {"coordinates":[-73.980052,40.75581],"type":"Point"}
}