{
  "type": "Feature",
  "properties": {
    "iso:country":"US",
    "sg:address":"7 Bixby Dr",
    "sg:city":"Baldwin",
    "sg:classifiers":[
        {
            "category":"Travel",
            "subcategory":"Travel Agent",
            "type":"Entertainment"
        }
    ],
    "sg:phone":"+1 516 623 5111",
    "sg:postcode":"11510",
    "sg:province":"NY",
    "sg:tags":[
        "agency",
        "bureau"
    ],
    "wof:name":"Love To Cruise",
    "wof:placetype":"venue"
},
  "geometry": {"coordinates":[-73.60858899999999,40.653196],"type":"Point"}
}