{
  "type": "Feature",
  "properties": {
    "addr:full":"Smith Haven Mall Lake Grove NY 11755",
    "addr:postcode":"11755",
    "addr:street":"Smith Haven Mall",
    "iso:country":"US",
    "sg:address":"Smith Haven Mall",
    "sg:city":"Lake Grove",
    "sg:classifiers":[
        {
            "category":"Restaurant",
            "type":"Food & Drink"
        }
    ],
    "sg:phone":"+1 631 979 1470",
    "sg:postcode":"11755",
    "sg:province":"NY",
    "wof:name":"Ruby Tuesday Restaurant",
    "wof:placetype":"venue"
},
  "geometry": {"coordinates":[-73.1147,40.851299],"type":"Point"}
}