{
  "type": "Feature",
  "properties": {
    "addr:full":"1000 Col Eileen Collins Blvd Syracuse NY 13212",
    "addr:housenumber":"1000",
    "addr:postcode":"13212",
    "addr:street":"Col Eileen Collins Blvd",
    "iso:country":"US",
    "sg:address":"1000 Col Eileen Collins Blvd",
    "sg:city":"Syracuse",
    "sg:classifiers":[
        {
            "category":"Bakery",
            "type":"Food & Drink"
        }
    ],
    "sg:menulink":"http://www.allmenus.com/ny/de-witt/108784-au-bon-pain/menu/",
    "sg:phone":"+1 315 455 7444",
    "sg:postcode":"13212",
    "sg:province":"NY",
    "sg:tags":[
        "american",
        "pastry"
    ],
    "wof:name":"Au Bon Pain",
    "wof:placetype":"venue"
},
  "geometry": {"coordinates":[-76.118197,43.113638],"type":"Point"}
}