{
  "type": "Feature",
  "properties": {
    "iso:country":"US",
    "sg:address":"3112 US Hwy 11",
    "sg:city":"Lisle",
    "sg:classifiers":[
        {
            "category":"Restaurant",
            "type":"Food & Drink"
        }
    ],
    "sg:phone":"+1 607 692 2355",
    "sg:postcode":"13797",
    "sg:province":"NY",
    "wof:name":"Vet's Spiedie Shack",
    "wof:placetype":"venue"
},
  "geometry": {"coordinates":[-75.99866,42.349249],"type":"Point"}
}