{
  "type": "Feature",
  "properties": {
    "addr:full":"255 Quaker Rd Queensbury NY 12804",
    "addr:housenumber":"255",
    "addr:postcode":"12804",
    "addr:street":"Quaker Rd",
    "iso:country":"US",
    "sg:address":"255 Quaker Rd",
    "sg:city":"Queensbury",
    "sg:classifiers":[
        {
            "category":"Restaurant",
            "type":"Food & Drink"
        }
    ],
    "sg:menulink":"http://www.allmenus.com/ny/queensbury/84903-applebees/menu/",
    "sg:phone":"+1 518 793 5420",
    "sg:postcode":"12804",
    "sg:province":"NY",
    "sg:tags":[
        "burger",
        "american",
        "sandwich",
        "soup"
    ],
    "wof:name":"Applebee's",
    "wof:placetype":"venue"
},
  "geometry": {"coordinates":[-73.650239,43.333123],"type":"Point"}
}