{
  "type": "Feature",
  "properties": {
    "iso:country":"US",
    "sg:address":"4005 Bayberry Ln",
    "sg:city":"Seaford",
    "sg:classifiers":[
        {
            "category":"Shopping",
            "subcategory":"Computers & Home Electronics",
            "type":"Retail Goods"
        }
    ],
    "sg:phone":"+1 516 349 8118",
    "sg:postcode":"11783",
    "sg:province":"NY",
    "sg:tags":[
        "consumer"
    ],
    "wof:name":"Cakawi International Ltd",
    "wof:placetype":"venue"
},
  "geometry": {"coordinates":[-73.48609399999999,40.696077],"type":"Point"}
}