{
  "type": "Feature",
  "properties": {
    "addr:full":"901 Stewart Ave Garden City NY 11530",
    "addr:housenumber":"901",
    "addr:postcode":"11530",
    "addr:street":"Stewart Ave",
    "iso:country":"US",
    "sg:address":"901 Stewart Ave",
    "sg:city":"Garden City",
    "sg:classifiers":[
        {
            "category":"Health Services",
            "subcategory":"Doctor",
            "type":"Services"
        }
    ],
    "sg:phone":"+1 516 214 6547",
    "sg:postcode":"11530",
    "sg:province":"NY",
    "sg:tags":[
        "physician",
        "surgeon"
    ],
    "wof:name":"Pediatric Ear Nose & Throat",
    "wof:placetype":"venue"
},
  "geometry": {"coordinates":[-73.59754100000001,40.734823],"type":"Point"}
}