{
  "type": "Feature",
  "properties": {
    "addr:full":"530 47th Avenue Long Island City NY 11101",
    "addr:housenumber":"530",
    "addr:postcode":"11101",
    "addr:street":"47Th Avenue",
    "iso:country":"US",
    "sg:address":"530 47th Avenue",
    "sg:city":"Long Island City",
    "sg:classifiers":[
        {
            "category":"Building & Trades",
            "subcategory":"Locksmith",
            "type":"Services"
        }
    ],
    "sg:phone":"+1 347 225 8516",
    "sg:postcode":"11101",
    "sg:province":"NY",
    "sg:tags":[
        "key"
    ],
    "wof:name":"47 Ave Locksmith 24 Hrs",
    "wof:placetype":"venue"
},
  "geometry": {"coordinates":[-73.95535,40.745804],"type":"Point"}
}