{
  "type": "Feature",
  "properties": {
    "iso:country":"US",
    "sg:address":"295 Amsterdam Ave",
    "sg:city":"New York",
    "sg:classifiers":[
        {
            "category":"Retail",
            "subcategory":"Auto Repair",
            "type":"Services"
        }
    ],
    "sg:phone":"+1 917 558 9677",
    "sg:postcode":"10023",
    "sg:province":"NY",
    "sg:tags":[
        "wrecker"
    ],
    "wof:name":"Emergency 7 Day Towing",
    "wof:placetype":"venue"
},
  "geometry": {"coordinates":[-73.980918,40.779326],"type":"Point"}
}