{
  "type": "Feature",
  "properties": {
    "addr:full":"408 8th Ave New York NY 10001",
    "addr:housenumber":"408",
    "addr:postcode":"10001",
    "addr:street":"8Th Ave",
    "iso:country":"US",
    "sg:address":"408 8th Ave",
    "sg:city":"New York",
    "sg:classifiers":[
        {
            "category":"Personal",
            "subcategory":"Massage",
            "type":"Services"
        }
    ],
    "sg:phone":"+1 212 290 2626",
    "sg:postcode":"10001",
    "sg:province":"NY",
    "wof:name":"Sun Club",
    "wof:placetype":"venue"
},
  "geometry": {"coordinates":[-73.995102,40.749901],"type":"Point"}
}