{
  "type": "Feature",
  "properties": {
    "addr:full":"24 Bond St New York NY 10012",
    "addr:housenumber":"24",
    "addr:postcode":"10012",
    "addr:street":"Bond St",
    "iso:country":"US",
    "sg:address":"24 Bond St",
    "sg:city":"New York",
    "sg:classifiers":[
        {
            "category":"Shopping",
            "subcategory":"Luggage & Leather Goods",
            "type":"Retail Goods"
        }
    ],
    "sg:phone":"+1   ",
    "sg:postcode":"10012",
    "sg:province":"NY",
    "wof:name":"Ukai of Japan",
    "wof:placetype":"venue"
},
  "geometry": {"coordinates":[-73.992169,40.7258],"type":"Point"}
}