{
  "type": "Feature",
  "properties": {
    "addr:full":"674 Thayer Rd West Point NY 10996",
    "addr:housenumber":"674",
    "addr:postcode":"10996",
    "addr:street":"Thayer Rd",
    "iso:country":"US",
    "sg:address":"674 Thayer Rd",
    "sg:city":"West Point",
    "sg:classifiers":[
        {
            "category":"Shopping",
            "subcategory":"Gifts & Souvenirs",
            "type":"Retail Goods"
        }
    ],
    "sg:phone":"+1 845 446 8681",
    "sg:postcode":"10996",
    "sg:province":"NY",
    "sg:tags":[
        "shop"
    ],
    "wof:name":"Dusa Gift Shop",
    "wof:placetype":"venue"
},
  "geometry": {"coordinates":[-73.956321,41.391494],"type":"Point"}
}