{
  "type": "Feature",
  "properties": {
    "addr:full":"345 Flatbush Ave Brooklyn NY 11238",
    "addr:housenumber":"345",
    "addr:postcode":"11238",
    "addr:street":"Flatbush Ave",
    "iso:country":"US",
    "sg:address":"345 Flatbush Ave",
    "sg:city":"Brooklyn",
    "sg:classifiers":[
        {
            "category":"Restaurant",
            "type":"Food & Drink"
        }
    ],
    "sg:phone":"+1 718 622 8700",
    "sg:postcode":"11238",
    "sg:province":"NY",
    "sg:tags":[
        "american",
        "latin"
    ],
    "wof:name":"El Gran Castillo De Jagua",
    "wof:placetype":"venue"
},
  "geometry": {"coordinates":[-73.97228,40.67724],"type":"Point"}
}