{
  "type": "Feature",
  "properties": {
    "addr:full":"17 Summersweet Dr Middle Island NY 11953",
    "addr:housenumber":"17",
    "addr:postcode":"11953",
    "addr:street":"Summersweet Dr Middle Island",
    "iso:country":"US",
    "sg:address":"17 Summersweet Dr",
    "sg:city":"Middle Island",
    "sg:classifiers":[
        {
            "category":"Building & Trades",
            "subcategory":"Landscaping Services",
            "type":"Services"
        }
    ],
    "sg:phone":"+1 631 345 0204",
    "sg:postcode":"11953",
    "sg:province":"NY",
    "wof:name":"Iken Lawncare",
    "wof:placetype":"venue"
},
  "geometry": {"coordinates":[-72.922459,40.892159],"type":"Point"}
}