{
  "type": "Feature",
  "properties": {
    "iso:country":"US",
    "sg:address":"17 Centre Dr",
    "sg:city":"Central Valley",
    "sg:classifiers":[
        {
            "category":"Food & Beverages",
            "subcategory":"Bakery",
            "type":"Retail Goods"
        }
    ],
    "sg:phone":"+1 845 782 4548",
    "sg:postcode":"10917",
    "sg:province":"NY",
    "sg:tags":[
        "sandwich"
    ],
    "wof:name":"Quiznos",
    "wof:placetype":"venue"
},
  "geometry": {"coordinates":[-74.133174,41.314511],"type":"Point"}
}