{
  "type": "Feature",
  "properties": {
    "iso:country":"US",
    "sg:address":"3984 Lockport Olcott Rd",
    "sg:city":"Lockport",
    "sg:classifiers":[
        {
            "category":"Shopping",
            "subcategory":"Discount & Variety Stores",
            "type":"Retail Goods"
        },
        {
            "category":"Shopping",
            "subcategory":"Department Store",
            "type":"Retail Goods"
        }
    ],
    "sg:phone":"+1 716 439 1886",
    "sg:postcode":"14094",
    "sg:province":"NY",
    "wof:name":"Family Dollar Stores",
    "wof:placetype":"venue"
},
  "geometry": {"coordinates":[-78.677132,43.223816],"type":"Point"}
}