{
  "type": "Feature",
  "properties": {
    "addr:full":"398 N 6th St Lindenhurst NY 11757",
    "addr:housenumber":"398",
    "addr:postcode":"11757",
    "addr:street":"N 6Th St",
    "iso:country":"US",
    "sg:address":"398 N 6th St",
    "sg:city":"Lindenhurst",
    "sg:classifiers":[
        {
            "category":"Home & Garden",
            "subcategory":"Household Appliances",
            "type":"Retail Goods"
        }
    ],
    "sg:phone":"+1 631 225 1049",
    "sg:postcode":"11757",
    "sg:province":"NY",
    "sg:tags":[
        "compactors"
    ],
    "wof:name":"F A Carting Corp",
    "wof:placetype":"venue"
},
  "geometry": {"coordinates":[-73.380354,40.689972],"type":"Point"}
}