{
  "type": "Feature",
  "properties": {
    "iso:country":"US",
    "sg:address":"12 Ridge Rd",
    "sg:city":"Glenmont",
    "sg:classifiers":[
        {
            "category":"Arts & Performance",
            "subcategory":"Theater",
            "type":"Entertainment"
        }
    ],
    "sg:phone":"+1 518 426 1244",
    "sg:postcode":"12078",
    "sg:province":"NY",
    "sg:tags":[
        "live",
        "music"
    ],
    "wof:name":"It's Your Party DJ Svc-Mike",
    "wof:placetype":"venue"
},
  "geometry": {"coordinates":[-74.343459,43.066136],"type":"Point"}
}