{
  "type": "Feature",
  "properties": {
    "iso:country":"US",
    "sg:address":"57 Railroad Pl",
    "sg:city":"Saratoga Springs",
    "sg:classifiers":[
        {
            "category":"Utilities",
            "subcategory":"Fuel Oil & Lpg",
            "type":"Services"
        }
    ],
    "sg:phone":"+1   ",
    "sg:postcode":"12866",
    "sg:province":"NY",
    "sg:tags":[
        "liquefied",
        "gas",
        "petroleum"
    ],
    "wof:name":"Paraco Gas",
    "wof:placetype":"venue"
},
  "geometry": {"coordinates":[-73.78762,43.082199],"type":"Point"}
}