{
  "type": "Feature",
  "properties": {
    "addr:full":"682 Aaron Ct Kingston NY 12401",
    "addr:housenumber":"682",
    "addr:postcode":"12401",
    "addr:street":"Aaron Ct",
    "iso:country":"US",
    "sg:address":"682 Aaron Ct",
    "sg:city":"Kingston",
    "sg:classifiers":[
        {
            "category":"Banks & Credit Unions",
            "subcategory":"Investment Brokerage",
            "type":"Services"
        }
    ],
    "sg:phone":"+1 845 331 1931",
    "sg:postcode":"12401",
    "sg:province":"NY",
    "sg:tags":[
        "security"
    ],
    "wof:name":"Lockwood Financial",
    "wof:placetype":"venue"
},
  "geometry": {"coordinates":[-74.01539200000001,41.935391],"type":"Point"}
}