{
  "type": "Feature",
  "properties": {
    "iso:country":"US",
    "sg:address":"417 Central Ave",
    "sg:city":"Dunkirk",
    "sg:classifiers":[
        {
            "category":"Home & Garden",
            "subcategory":"Building Materials",
            "type":"Retail Goods"
        }
    ],
    "sg:phone":"+1   ",
    "sg:postcode":"14048",
    "sg:province":"NY",
    "sg:tags":[
        "paint",
        "wallpaper"
    ],
    "wof:name":"Lake Shore Wallpaper & Pnt Co",
    "wof:placetype":"venue"
},
  "geometry": {"coordinates":[-79.334425,42.482793],"type":"Point"}
}