{
  "type": "Feature",
  "properties": {
    "addr:full":"750 Blue Point Rd Holtsville NY 11742",
    "addr:housenumber":"750",
    "addr:postcode":"11742",
    "addr:street":"Blue Point Rd",
    "iso:country":"US",
    "sg:address":"750 Blue Point Rd",
    "sg:city":"Holtsville",
    "sg:classifiers":[
        {
            "category":"Manufacturing",
            "subcategory":"Tools & Machinery",
            "type":"Manufacturing & Wholesale Goods"
        }
    ],
    "sg:phone":"+1   ",
    "sg:postcode":"11742",
    "sg:province":"NY",
    "sg:tags":[
        "manufacture",
        "instrument",
        "scientific"
    ],
    "sg:website":"www.bic.com",
    "wof:name":"Brookhaven Instruments Corp",
    "wof:placetype":"venue"
},
  "geometry": {"coordinates":[-73.036378,40.811421],"type":"Point"}
}