{
  "type": "Feature",
  "properties": {
    "addr:full":"65 Windsor Pl Central Islip NY 11722",
    "addr:housenumber":"65",
    "addr:postcode":"11722",
    "addr:street":"Windsor Pl",
    "iso:country":"US",
    "sg:address":"65 Windsor Pl",
    "sg:city":"Central Islip",
    "sg:classifiers":[
        {
            "category":"Building & Trades",
            "subcategory":"Construction",
            "type":"Services"
        }
    ],
    "sg:phone":"+1 631 232 0289",
    "sg:postcode":"11722",
    "sg:province":"NY",
    "sg:tags":[
        "contractor"
    ],
    "wof:name":"Quality Solid Surfaces",
    "wof:placetype":"venue"
},
  "geometry": {"coordinates":[-73.17294099999999,40.796365],"type":"Point"}
}