{
  "type": "Feature",
  "properties": {
    "addr:full":"11 Clifford St Ravena NY 12143",
    "addr:housenumber":"11",
    "addr:postcode":"12143",
    "addr:street":"Clifford St",
    "iso:country":"US",
    "sg:address":"11 Clifford St",
    "sg:city":"Ravena",
    "sg:classifiers":[
        {
            "category":"Professional",
            "type":"Services"
        }
    ],
    "sg:phone":"+1 518 756 1000",
    "sg:postcode":"12143",
    "sg:province":"NY",
    "sg:tags":[
        "caterer"
    ],
    "sg:website":"www.fresescatering.com",
    "wof:name":"Frese's Bakery & Catering",
    "wof:placetype":"venue"
},
  "geometry": {"coordinates":[-73.804788,42.473365],"type":"Point"}
}