{
  "type": "Feature",
  "properties": {
    "addr:full":"939 State Hwy 376 Wappingers Falls NY 12533",
    "addr:housenumber":"939",
    "addr:postcode":"12533",
    "addr:street":"State Hwy 376",
    "iso:country":"US",
    "sg:address":"939 State Hwy 376",
    "sg:city":"Wappingers Falls",
    "sg:classifiers":[
        {
            "category":"Shopping",
            "subcategory":"Hobbies, Toys, & Games",
            "type":"Retail Goods"
        }
    ],
    "sg:phone":"+1   ",
    "sg:postcode":"12533",
    "sg:province":"NY",
    "sg:tags":[
        "store"
    ],
    "wof:name":"Toys & More Learning Center",
    "wof:placetype":"venue"
},
  "geometry": {"coordinates":[-73.820941,41.602171],"type":"Point"}
}