{
  "type": "Feature",
  "properties": {
    "iso:country":"US",
    "sg:address":"8521 Woodbox Rd",
    "sg:city":"Manlius",
    "sg:classifiers":[
        {
            "category":"Shopping",
            "type":"Retail Goods"
        }
    ],
    "sg:phone":"+1 315 682 6360",
    "sg:postcode":"13104",
    "sg:province":"NY",
    "sg:tags":[
        "pet",
        "food",
        "supply"
    ],
    "wof:name":"Mac & Jazz",
    "wof:placetype":"venue"
},
  "geometry": {"coordinates":[-75.944228,43.003542],"type":"Point"}
}