{
  "type": "Feature",
  "properties": {
    "iso:country":"US",
    "sg:address":"553 Old Montauk Hwy",
    "sg:city":"Sayville",
    "sg:classifiers":[
        {
            "category":"Restaurant",
            "type":"Food & Drink"
        }
    ],
    "sg:phone":"+1 631 563 4144",
    "sg:postcode":"11782",
    "sg:province":"NY",
    "wof:name":"Little Black Restaurant Inc",
    "wof:placetype":"venue"
},
  "geometry": {"coordinates":[-73.066942,40.747979],"type":"Point"}
}