{
  "type": "Feature",
  "properties": {
    "addr:full":"2458 Arthur Ave Bronx NY 10458",
    "addr:housenumber":"2458",
    "addr:postcode":"10458",
    "addr:street":"Arthur Ave",
    "iso:country":"US",
    "sg:address":"2458 Arthur Ave",
    "sg:city":"Bronx",
    "sg:classifiers":[
        {
            "category":"Building & Trades",
            "subcategory":"Construction",
            "type":"Services"
        }
    ],
    "sg:phone":"+1 646 579 4549",
    "sg:postcode":"10458",
    "sg:province":"NY",
    "sg:tags":[
        "contractor"
    ],
    "wof:name":"Triboro Contracting",
    "wof:placetype":"venue"
},
  "geometry": {"coordinates":[-73.886205,40.856739],"type":"Point"}
}