{
  "type": "Feature",
  "properties": {
    "addr:full":"28 W River Rd Gansevoort NY 12831",
    "addr:housenumber":"28",
    "addr:postcode":"12831",
    "addr:street":"W River Rd",
    "iso:country":"US",
    "sg:address":"28 W River Rd",
    "sg:city":"Gansevoort",
    "sg:classifiers":[
        {
            "category":"Real Estate",
            "subcategory":"Real Estate Agent",
            "type":"Services"
        }
    ],
    "sg:phone":"+1 518 761 4615",
    "sg:postcode":"12831",
    "sg:province":"NY",
    "wof:name":"Realty USA",
    "wof:placetype":"venue"
},
  "geometry": {"coordinates":[-73.59308799999999,43.171695],"type":"Point"}
}