{
  "type": "Feature",
  "properties": {
    "iso:country":"US",
    "sg:address":"642 Broadway",
    "sg:city":"Kingston",
    "sg:classifiers":[
        {
            "category":"Wholesale",
            "subcategory":"Electrical",
            "type":"Manufacturing & Wholesale Goods"
        }
    ],
    "sg:phone":"+1 845 338 4440",
    "sg:postcode":"12401",
    "sg:province":"NY",
    "sg:tags":[
        "alarm",
        "burglar",
        "system"
    ],
    "wof:name":"Central Signal Monitoring",
    "wof:placetype":"venue"
},
  "geometry": {"coordinates":[-74.00677899999999,41.930461],"type":"Point"}
}