{
  "type": "Feature",
  "properties": {
    "iso:country":"US",
    "sg:address":"159 Liberty St",
    "sg:city":"Newburgh",
    "sg:classifiers":[
        {
            "category":"Shopping",
            "subcategory":"Books",
            "type":"Retail Goods"
        }
    ],
    "sg:phone":"+1 845 561 5522",
    "sg:postcode":"12550",
    "sg:province":"NY",
    "sg:tags":[
        "store"
    ],
    "wof:name":"Clough's Bookshop",
    "wof:placetype":"venue"
},
  "geometry": {"coordinates":[-74.01070799999999,41.500193],"type":"Point"}
}