{
  "type": "Feature",
  "properties": {
    "addr:full":"233 Madison Ave New York NY 10016",
    "addr:housenumber":"233",
    "addr:postcode":"10016",
    "addr:street":"Madison Ave",
    "iso:country":"US",
    "sg:address":"233 Madison Ave",
    "sg:city":"New York",
    "sg:classifiers":[
        {
            "category":"Government",
            "subcategory":"Office",
            "type":"Public Place"
        }
    ],
    "sg:phone":"+1 212 889 8360",
    "sg:postcode":"10016",
    "sg:province":"NY",
    "sg:tags":[
        "federal",
        "affairs"
    ],
    "wof:name":"Consulate General Of Poland",
    "wof:placetype":"venue"
},
  "geometry": {"coordinates":[-73.981123,40.750282],"type":"Point"}
}