{
  "type": "Feature",
  "properties": {
    "addr:full":"1575 Hillside Ave Ste 303 New Hyde Park NY 11040",
    "addr:housenumber":"1575;303",
    "addr:postcode":"11040",
    "addr:street":"Hillside Ave Ste;Hyde Park",
    "iso:country":"US",
    "sg:address":"1575 Hillside Ave Ste 303",
    "sg:city":"New Hyde Park",
    "sg:classifiers":[
        {
            "category":"Health Services",
            "subcategory":"Doctor",
            "type":"Services"
        }
    ],
    "sg:phone":"+1 516 437 5500",
    "sg:postcode":"11040",
    "sg:province":"NY",
    "wof:name":"Shebairo Raymond MD",
    "wof:placetype":"venue"
},
  "geometry": {"coordinates":[-73.685699,40.747898],"type":"Point"}
}