{
  "type": "Feature",
  "properties": {
    "addr:full":"1175 Plymouth Ave S Rochester NY 14611",
    "addr:housenumber":"1175",
    "addr:postcode":"14611",
    "addr:street":"Plymouth Ave S",
    "iso:country":"US",
    "sg:address":"1175 Plymouth Ave S",
    "sg:city":"Rochester",
    "sg:classifiers":[
        {
            "category":"Professional",
            "subcategory":"Management & Consulting",
            "type":"Services"
        },
        {
            "category":"Restaurant",
            "type":"Food & Drink"
        }
    ],
    "sg:phone":"+1 585 235 4450",
    "sg:postcode":"14611",
    "sg:province":"NY",
    "sg:tags":[
        "consultant",
        "energy",
        "conservation",
        "telecommunication"
    ],
    "wof:name":"Utility Solutions",
    "wof:placetype":"venue"
},
  "geometry": {"coordinates":[-77.629456,43.134808],"type":"Point"}
}