{
  "type": "Feature",
  "properties": {
    "addr:full":"358 S Broadway Hicksville NY 11801",
    "addr:housenumber":"358",
    "addr:postcode":"11801",
    "addr:street":"S Broadway",
    "iso:country":"US",
    "sg:address":"358 S Broadway",
    "sg:city":"Hicksville",
    "sg:classifiers":[
        {
            "category":"Utilities",
            "subcategory":"Mobile Phone",
            "type":"Services"
        }
    ],
    "sg:phone":"+1 516 932 6700",
    "sg:postcode":"11801",
    "sg:province":"NY",
    "sg:tags":[
        "telephone",
        "cellular"
    ],
    "wof:name":"Mobile Express Inc",
    "wof:placetype":"venue"
},
  "geometry": {"coordinates":[-73.51625,40.761594],"type":"Point"}
}