{
  "type": "Feature",
  "properties": {
    "iso:country":"US",
    "sg:address":"375 Liberty St",
    "sg:city":"Hauppauge",
    "sg:classifiers":[
        {
            "category":"Real Estate",
            "subcategory":"Real Estate Agent",
            "type":"Services"
        }
    ],
    "sg:phone":"+1 631 360 0927",
    "sg:postcode":"11788",
    "sg:province":"NY",
    "wof:name":"Granot & Holzer Realty Corp",
    "wof:placetype":"venue"
},
  "geometry": {"coordinates":[-73.16292199999999,40.820201],"type":"Point"}
}