{
  "type": "Feature",
  "properties": {
    "addr:full":"1250 Goodman St N Rochester NY 14609",
    "addr:housenumber":"1250",
    "addr:postcode":"14609",
    "addr:street":"Goodman St N",
    "iso:country":"US",
    "sg:address":"1250 Goodman St N",
    "sg:city":"Rochester",
    "sg:classifiers":[
        {
            "category":"Restaurant",
            "type":"Food & Drink"
        }
    ],
    "sg:phone":"+1   ",
    "sg:postcode":"14609",
    "sg:province":"NY",
    "sg:tags":[
        "eating"
    ],
    "wof:name":"La Martinas",
    "wof:placetype":"venue"
},
  "geometry": {"coordinates":[-77.575613,43.177052],"type":"Point"}
}