{
  "type": "Feature",
  "properties": {
    "iso:country":"US",
    "sg:address":"281 Clinton St",
    "sg:city":"Hempstead",
    "sg:classifiers":[
        {
            "category":"Organizations",
            "subcategory":"Religious Organization",
            "type":"Services"
        }
    ],
    "sg:phone":"+1   ",
    "sg:postcode":"11550",
    "sg:province":"NY",
    "wof:name":"Riches Of Christ Church Intl",
    "wof:placetype":"venue"
},
  "geometry": {"coordinates":[-73.620819,40.715193],"type":"Point"}
}