{
  "type": "Feature",
  "properties": {
    "addr:full":"105 Wolf Rd Albany NY 12205",
    "addr:housenumber":"105",
    "addr:postcode":"12205",
    "addr:street":"Wolf Rd",
    "iso:country":"US",
    "sg:address":"105 Wolf Rd",
    "sg:city":"Albany",
    "sg:classifiers":[
        {
            "category":"Social Services",
            "type":"Services"
        }
    ],
    "sg:phone":"+1 518 225 7707",
    "sg:postcode":"12205",
    "sg:province":"NY",
    "sg:tags":[
        "counselor",
        "marriage",
        "family"
    ],
    "wof:name":"Marriage & Relationships",
    "wof:placetype":"venue"
},
  "geometry": {"coordinates":[-73.809337,42.716664],"type":"Point"}
}