{
  "type": "Feature",
  "properties": {
    "addr:full":"119 E Washington St Syracuse NY 13202",
    "addr:housenumber":"119",
    "addr:postcode":"13202",
    "addr:street":"E Washington St",
    "iso:country":"US",
    "sg:address":"119 E Washington St",
    "sg:city":"Syracuse",
    "sg:classifiers":[
        {
            "category":"Parking",
            "type":"Transportation"
        }
    ],
    "sg:phone":"+1 315 424 4499",
    "sg:postcode":"13202",
    "sg:province":"NY",
    "sg:tags":[
        "garage"
    ],
    "wof:name":"M & T Bank",
    "wof:placetype":"venue"
},
  "geometry": {"coordinates":[-76.15079,43.049628],"type":"Point"}
}