{
  "type": "Feature",
  "properties": {
    "iso:country":"US",
    "sg:address":"305 State Hwy 82",
    "sg:city":"Hopewell Junction",
    "sg:classifiers":[
        {
            "category":"Building & Trades",
            "subcategory":"Electrical",
            "type":"Services"
        }
    ],
    "sg:phone":"+1 845 896 5124",
    "sg:postcode":"12533",
    "sg:province":"NY",
    "sg:tags":[
        "electrical",
        "contractor"
    ],
    "wof:name":"Palumbo Electric Corp",
    "wof:placetype":"venue"
},
  "geometry": {"coordinates":[-73.83715599999999,41.571034],"type":"Point"}
}