{
  "type": "Feature",
  "properties": {
    "addr:full":"10 Ferraro Dr Holbrook NY 11741",
    "addr:housenumber":"10",
    "addr:postcode":"11741",
    "addr:street":"Ferraro Dr",
    "iso:country":"US",
    "sg:address":"10 Ferraro Dr",
    "sg:city":"Holbrook",
    "sg:classifiers":[
        {
            "category":"Retail",
            "subcategory":"Car Wash",
            "type":"Services"
        }
    ],
    "sg:phone":"+1   ",
    "sg:postcode":"11741",
    "sg:province":"NY",
    "sg:tags":[
        "carwash"
    ],
    "wof:name":"J & S Detailing Inc",
    "wof:placetype":"venue"
},
  "geometry": {"coordinates":[-73.069759,40.779629],"type":"Point"}
}