{
  "type": "Feature",
  "properties": {
    "addr:full":"851 Forest Ave Jamestown NY 14701",
    "addr:housenumber":"851",
    "addr:postcode":"14701",
    "addr:street":"Forest Ave",
    "iso:country":"US",
    "sg:address":"851 Forest Ave",
    "sg:city":"Jamestown",
    "sg:classifiers":[
        {
            "category":"Organizations",
            "subcategory":"Religious Organization",
            "type":"Services"
        }
    ],
    "sg:phone":"+1 716 487 0830",
    "sg:postcode":"14701",
    "sg:province":"NY",
    "sg:tags":[
        "church"
    ],
    "wof:name":"Church Of Jesus Christ Of Lds",
    "wof:placetype":"venue"
},
  "geometry": {"coordinates":[-79.24477400000001,42.078306],"type":"Point"}
}