{
  "type": "Feature",
  "properties": {
    "iso:country":"US",
    "sg:address":"13 Belaire Dr",
    "sg:city":"Horseheads",
    "sg:classifiers":[
        {
            "category":"Retail",
            "subcategory":"Photofinishing",
            "type":"Services"
        }
    ],
    "sg:phone":"+1   ",
    "sg:postcode":"14845",
    "sg:province":"NY",
    "sg:tags":[
        "laboratory"
    ],
    "wof:name":"New York Pro Photo",
    "wof:placetype":"venue"
},
  "geometry": {"coordinates":[-76.866721,42.172815],"type":"Point"}
}