{
  "type": "Feature",
  "properties": {
    "addr:full":"245 E 93 St New York NY 10128",
    "addr:housenumber":"245;93",
    "addr:postcode":"10128",
    "addr:street":"E;St",
    "iso:country":"US",
    "sg:address":"245 E 93 St",
    "sg:city":"New York",
    "sg:classifiers":[
        {
            "category":"Wholesale",
            "subcategory":"Seafood",
            "type":"Manufacturing & Wholesale Goods"
        }
    ],
    "sg:phone":"+1 212 289 5299",
    "sg:postcode":"10128",
    "sg:province":"NY",
    "wof:name":"Y U Trading Corp",
    "wof:placetype":"venue"
},
  "geometry": {"coordinates":[-73.94850099999999,40.782317],"type":"Point"}
}