{
  "type": "Feature",
  "properties": {
    "iso:country":"US",
    "sg:address":"453 Main St",
    "sg:city":"New York Mills",
    "sg:classifiers":[
        {
            "category":"Retail",
            "subcategory":"Auto Repair",
            "type":"Services"
        }
    ],
    "sg:phone":"+1 315 733 7619",
    "sg:postcode":"13417",
    "sg:province":"NY",
    "sg:tags":[
        "glass",
        "coating",
        "tinting"
    ],
    "wof:name":"Glassy Business Window Tinting",
    "wof:placetype":"venue"
},
  "geometry": {"coordinates":[-75.29536299999999,43.100932],"type":"Point"}
}