{
  "type": "Feature",
  "properties": {
    "iso:country":"US",
    "sg:address":"214 Adams Way",
    "sg:city":"Sayville",
    "sg:classifiers":[
        {
            "category":"Shopping",
            "subcategory":"Books",
            "type":"Retail Goods"
        }
    ],
    "sg:phone":"+1 631 244 7423",
    "sg:postcode":"11782",
    "sg:province":"NY",
    "sg:tags":[
        "dealer"
    ],
    "wof:name":"VVA Suffolk Chapter 11",
    "wof:placetype":"venue"
},
  "geometry": {"coordinates":[-73.09532799999999,40.759126],"type":"Point"}
}