{
  "type": "Feature",
  "properties": {
    "addr:full":"51 Front St Addison NY 14801",
    "addr:housenumber":"51",
    "addr:postcode":"14801",
    "addr:street":"Front St",
    "iso:country":"US",
    "sg:address":"51 Front St",
    "sg:city":"Addison",
    "sg:classifiers":[
        {
            "category":"Shopping",
            "subcategory":"Clothing, Apparel, & Fashions",
            "type":"Retail Goods"
        }
    ],
    "sg:phone":"+1   ",
    "sg:postcode":"14801",
    "sg:province":"NY",
    "wof:name":"Crimsons Custom Designs",
    "wof:placetype":"venue"
},
  "geometry": {"coordinates":[-77.230423,42.108144],"type":"Point"}
}