{
  "type": "Feature",
  "properties": {
    "iso:country":"US",
    "sg:address":"31 Mahan St",
    "sg:city":"West Babylon",
    "sg:classifiers":[
        {
            "category":"Retail",
            "subcategory":"Repair Shop",
            "type":"Services"
        }
    ],
    "sg:phone":"+1 631 643 1911",
    "sg:postcode":"11704",
    "sg:province":"NY",
    "sg:tags":[
        "machine",
        "sewing"
    ],
    "wof:name":"Sal S Machinery",
    "wof:placetype":"venue"
},
  "geometry": {"coordinates":[-73.375339,40.734409],"type":"Point"}
}