{
  "type": "Feature",
  "properties": {
    "addr:full":"525 W 50th Street New York NY 10019",
    "addr:housenumber":"525",
    "addr:postcode":"10019",
    "addr:street":"W 50Th Street",
    "iso:country":"US",
    "sg:address":"525 W 50th Street",
    "sg:city":"New York",
    "sg:classifiers":[
        {
            "category":"Park",
            "type":"Public Place"
        }
    ],
    "sg:phone":"+1 212 969 9185",
    "sg:postcode":"10019",
    "sg:province":"NY",
    "wof:name":"Harlem Children's Zone",
    "wof:placetype":"venue"
},
  "geometry": {"coordinates":[-73.993038,40.765083],"type":"Point"}
}