{
  "type": "Feature",
  "properties": {
    "addr:full":"1343 State Hwy 96 Owego NY 13827",
    "addr:housenumber":"1343",
    "addr:postcode":"13827",
    "addr:street":"State Hwy 96",
    "iso:country":"US",
    "sg:address":"1343 State Hwy 96",
    "sg:city":"Owego",
    "sg:classifiers":[
        {
            "category":"Autos & Motor Vehicles",
            "subcategory":"Automobile Sales",
            "type":"Retail Goods"
        }
    ],
    "sg:phone":"+1   ",
    "sg:postcode":"13827",
    "sg:province":"NY",
    "sg:tags":[
        "used"
    ],
    "wof:name":"Quality Auto Trans",
    "wof:placetype":"venue"
},
  "geometry": {"coordinates":[-76.270622,42.126993],"type":"Point"}
}