{
  "type": "Feature",
  "properties": {
    "addr:full":"9233 Oswego Rd Baldwinsville NY 13027",
    "addr:housenumber":"9233",
    "addr:postcode":"13027",
    "addr:street":"Oswego Rd",
    "iso:country":"US",
    "sg:address":"9233 Oswego Rd",
    "sg:city":"Baldwinsville",
    "sg:classifiers":[
        {
            "category":"Recreation",
            "type":"Entertainment"
        }
    ],
    "sg:phone":"+1 315 695 3540",
    "sg:postcode":"13027",
    "sg:province":"NY",
    "sg:tags":[
        "stable"
    ],
    "wof:name":"Holiday Farm",
    "wof:placetype":"venue"
},
  "geometry": {"coordinates":[-76.359028,43.217177],"type":"Point"}
}