{
  "type": "Feature",
  "properties": {
    "iso:country":"US",
    "sg:address":"42 Broadway Suite 1724",
    "sg:city":"New York",
    "sg:classifiers":[
        {
            "category":"Health Services",
            "subcategory":"Clinic",
            "type":"Services"
        }
    ],
    "sg:phone":"+1 800 672 8857",
    "sg:postcode":"10004",
    "sg:province":"NY",
    "sg:tags":[
        "medical"
    ],
    "sg:website":"www.als-ny.org",
    "wof:name":"The Als Association Greater New York Chapter",
    "wof:placetype":"venue"
},
  "geometry": {"coordinates":[-74.012595,40.70596],"type":"Point"}
}