{
  "type": "Feature",
  "properties": {
    "addr:full":"169 Vincent Ave Lynbrook NY 11563",
    "addr:housenumber":"169",
    "addr:postcode":"11563",
    "addr:street":"Vincent Ave",
    "iso:country":"US",
    "sg:address":"169 Vincent Ave",
    "sg:city":"Lynbrook",
    "sg:classifiers":[
        {
            "category":"Manufacturing",
            "subcategory":"Electronics",
            "type":"Manufacturing & Wholesale Goods"
        }
    ],
    "sg:phone":"+1 516 593 3445",
    "sg:postcode":"11563",
    "sg:province":"NY",
    "sg:tags":[
        "machine",
        "shop",
        "electronic",
        "equipment",
        "supply"
    ],
    "wof:name":"Alloy Machine & Tool Co Inc",
    "wof:placetype":"venue"
},
  "geometry": {"coordinates":[-73.66703800000001,40.656501],"type":"Point"}
}