{
  "type": "Feature",
  "properties": {
    "iso:country":"US",
    "sg:address":"107 Pine St",
    "sg:city":"East Aurora",
    "sg:classifiers":[
        {
            "category":"Shopping",
            "subcategory":"Catalog Store",
            "type":"Retail Goods"
        }
    ],
    "sg:phone":"+1   ",
    "sg:postcode":"14052",
    "sg:province":"NY",
    "sg:tags":[
        "house",
        "mail"
    ],
    "wof:name":"House of Miniatures",
    "wof:placetype":"venue"
},
  "geometry": {"coordinates":[-78.60789800000001,42.772183],"type":"Point"}
}