{
  "type": "Feature",
  "properties": {
    "iso:country":"US",
    "sg:address":"22 W 27 St",
    "sg:city":"New York",
    "sg:classifiers":[
        {
            "category":"Wholesale",
            "subcategory":"Apparel",
            "type":"Manufacturing & Wholesale Goods"
        }
    ],
    "sg:phone":"+1 646 424 1440",
    "sg:postcode":"10001",
    "sg:province":"NY",
    "sg:tags":[
        "clothing"
    ],
    "wof:name":"Big Brothers Sportswear Inc",
    "wof:placetype":"venue"
},
  "geometry": {"coordinates":[-73.990673,40.745171],"type":"Point"}
}