{
  "type": "Feature",
  "properties": {
    "iso:country":"US",
    "sg:address":"1987 Stewart Ave",
    "sg:city":"New Hyde Park",
    "sg:classifiers":[
        {
            "category":"Shopping",
            "subcategory":"Clothing, Apparel, & Fashions",
            "type":"Retail Goods"
        }
    ],
    "sg:phone":"+1   ",
    "sg:postcode":"11040",
    "sg:province":"NY",
    "wof:name":"Jwl",
    "wof:placetype":"venue"
},
  "geometry": {"coordinates":[-73.701014,40.750799],"type":"Point"}
}