{
  "type": "Feature",
  "properties": {
    "addr:full":"76 Crossing Blvd Clifton Park NY 12065",
    "addr:housenumber":"76",
    "addr:postcode":"12065",
    "addr:street":"Crossing Blvd",
    "iso:country":"US",
    "sg:address":"76 Crossing Blvd",
    "sg:city":"Clifton Park",
    "sg:classifiers":[
        {
            "category":"Wholesale",
            "subcategory":"Durable Goods & Equipment",
            "type":"Manufacturing & Wholesale Goods"
        }
    ],
    "sg:phone":"+1 518 371 3192",
    "sg:postcode":"12065",
    "sg:province":"NY",
    "wof:name":"College Park Energy",
    "wof:placetype":"venue"
},
  "geometry": {"coordinates":[-73.77018,42.857997],"type":"Point"}
}