{
  "type": "Feature",
  "properties": {
    "addr:full":"813 Andrews Rd Skaneateles NY 13152",
    "addr:housenumber":"813",
    "addr:postcode":"13152",
    "addr:street":"Andrews Rd",
    "iso:country":"US",
    "sg:address":"813 Andrews Rd",
    "sg:city":"Skaneateles",
    "sg:classifiers":[
        {
            "category":"Professional",
            "type":"Services"
        }
    ],
    "sg:phone":"+1 315 685 7661",
    "sg:postcode":"13152",
    "sg:province":"NY",
    "sg:tags":[
        "establishment"
    ],
    "wof:name":"Chase Design Inc Barn",
    "wof:placetype":"venue"
},
  "geometry": {"coordinates":[-76.44535999999999,42.928907],"type":"Point"}
}