{
  "type": "Feature",
  "properties": {
    "addr:full":"3947 48th Ave Sunnyside NY 11104",
    "addr:housenumber":"3947",
    "addr:postcode":"11104",
    "addr:street":"48Th Ave",
    "iso:country":"US",
    "sg:address":"3947 48th Ave",
    "sg:city":"Sunnyside",
    "sg:phone":"+1 718 729 1921",
    "sg:postcode":"11104",
    "sg:province":"NY",
    "wof:name":"Unisex Hair Magic 39",
    "wof:placetype":"venue"
},
  "geometry": {"coordinates":[-73.92570000000001,40.740036],"type":"Point"}
}