{
  "type": "Feature",
  "properties": {
    "addr:full":"245 N Gannon Ave Staten Island NY 10314",
    "addr:housenumber":"245",
    "addr:postcode":"10314",
    "addr:street":"N Gannon Ave",
    "iso:country":"US",
    "sg:address":"245 N Gannon Ave",
    "sg:city":"Staten Island",
    "sg:classifiers":[
        {
            "category":"Health Services",
            "subcategory":"Clinic",
            "type":"Services"
        }
    ],
    "sg:phone":"+1 718 370 7720",
    "sg:postcode":"10314",
    "sg:province":"NY",
    "sg:tags":[
        "counseling",
        "mental"
    ],
    "wof:name":"Klapper Arleen Msw Csw",
    "wof:placetype":"venue"
},
  "geometry": {"coordinates":[-74.13099699999999,40.608601],"type":"Point"}
}