{
  "type": "Feature",
  "properties": {
    "iso:country":"US",
    "sg:address":"113 Rockland Plz",
    "sg:city":"Nanuet",
    "sg:classifiers":[
        {
            "category":"Retail",
            "subcategory":"Laundry & Dry Cleaning",
            "type":"Services"
        }
    ],
    "sg:phone":"+1   ",
    "sg:postcode":"10954",
    "sg:province":"NY",
    "sg:tags":[
        "drycleaning",
        "plant"
    ],
    "wof:name":"Jeul Family Cleaners Inc",
    "wof:placetype":"venue"
},
  "geometry": {"coordinates":[-74.01569499999999,41.098505],"type":"Point"}
}