{
  "type": "Feature",
  "properties": {
    "addr:full":"343 Linden St Brooklyn NY 11237",
    "addr:housenumber":"343",
    "addr:postcode":"11237",
    "addr:street":"Linden St",
    "iso:country":"US",
    "sg:address":"343 Linden St",
    "sg:city":"Brooklyn",
    "sg:classifiers":[
        {
            "category":"Shopping",
            "subcategory":"Clothing, Apparel, & Fashions",
            "type":"Retail Goods"
        }
    ],
    "sg:phone":"+1   ",
    "sg:postcode":"11237",
    "sg:province":"NY",
    "wof:name":"All Star Clothing",
    "wof:placetype":"venue"
},
  "geometry": {"coordinates":[-73.9127,40.700307],"type":"Point"}
}