{
  "type": "Feature",
  "properties": {
    "addr:full":"78 Allen Blvd Farmingdale NY 11735",
    "addr:housenumber":"78",
    "addr:postcode":"11735",
    "addr:street":"Allen Blvd",
    "iso:country":"US",
    "sg:address":"78 Allen Blvd",
    "sg:city":"Farmingdale",
    "sg:classifiers":[
        {
            "category":"Wholesale",
            "subcategory":"Groceries",
            "type":"Manufacturing & Wholesale Goods"
        }
    ],
    "sg:phone":"+1 631 420 4280",
    "sg:postcode":"11735",
    "sg:province":"NY",
    "sg:tags":[
        "beverage"
    ],
    "wof:name":"Douglas Kitchens & Baths",
    "wof:placetype":"venue"
},
  "geometry": {"coordinates":[-73.42264900000001,40.715613],"type":"Point"}
}