{
  "type": "Feature",
  "properties": {
    "addr:full":"833 Broadway New York NY 10003",
    "addr:housenumber":"833",
    "addr:postcode":"10003",
    "addr:street":"Broadway",
    "iso:country":"US",
    "sg:address":"833 Broadway",
    "sg:city":"New York",
    "sg:classifiers":[
        {
            "category":"Real Estate",
            "subcategory":"Architect",
            "type":"Services"
        }
    ],
    "sg:phone":"+1 212 228 8396",
    "sg:postcode":"10003",
    "sg:province":"NY",
    "sg:tags":[
        "designer"
    ],
    "wof:name":"Currimbhoy Design",
    "wof:placetype":"venue"
},
  "geometry": {"coordinates":[-73.991129,40.733336],"type":"Point"}
}