{
  "type": "Feature",
  "properties": {
    "addr:full":"286 Crestwood Ave Buffalo NY 14216",
    "addr:housenumber":"286",
    "addr:postcode":"14216",
    "addr:street":"Crestwood Ave",
    "iso:country":"US",
    "sg:address":"286 Crestwood Ave",
    "sg:city":"Buffalo",
    "sg:classifiers":[
        {
            "category":"Wholesale",
            "subcategory":"Jewelry",
            "type":"Manufacturing & Wholesale Goods"
        }
    ],
    "sg:phone":"+1 716 874 1937",
    "sg:postcode":"14216",
    "sg:province":"NY",
    "sg:tags":[
        "stone"
    ],
    "wof:name":"Creative Generations",
    "wof:placetype":"venue"
},
  "geometry": {"coordinates":[-78.860437,42.953592],"type":"Point"}
}