{
  "type": "Feature",
  "properties": {
    "iso:country":"US",
    "sg:address":"123 Saratoga Rd",
    "sg:city":"Schenectady",
    "sg:classifiers":[
        {
            "category":"Professional",
            "subcategory":"Accounting & Tax Preparation",
            "type":"Services"
        },
        {
            "category":"Banks & Credit Unions",
            "subcategory":"Financial Services",
            "type":"Services"
        }
    ],
    "sg:phone":"+1 518 399 1698",
    "sg:postcode":"12302",
    "sg:province":"NY",
    "sg:tags":[
        "return",
        "preparation-business",
        "taxes-consultants",
        "loan",
        "reporting",
        "representative",
        "alternative",
        "bookkeeping"
    ],
    "sg:website":"http://www.hrblock.com",
    "wof:name":"H&R Block",
    "wof:placetype":"venue"
},
  "geometry": {"coordinates":[-73.935732,42.859121],"type":"Point"}
}