{
  "type": "Feature",
  "properties": {
    "iso:country":"US",
    "sg:address":"5 Semon Rd",
    "sg:city":"Huntington",
    "sg:classifiers":[
        {
            "category":"Food & Beverages",
            "subcategory":"Liquor & Beverages",
            "type":"Retail Goods"
        }
    ],
    "sg:phone":"+1 631 271 7871",
    "sg:postcode":"11743",
    "sg:province":"NY",
    "sg:tags":[
        "beer",
        "spirit",
        "wine"
    ],
    "wof:name":"Dream Mart Wines & Liquors",
    "wof:placetype":"venue"
},
  "geometry": {"coordinates":[-73.42066,40.859033],"type":"Point"}
}