{
  "type": "Feature",
  "properties": {
    "addr:full":"838 E 223rd St Bronx NY 10466",
    "addr:housenumber":"838",
    "addr:postcode":"10466",
    "addr:street":"E 223Rd St",
    "iso:country":"US",
    "sg:address":"838 E 223rd St",
    "sg:city":"Bronx",
    "sg:classifiers":[
        {
            "category":"Building & Trades",
            "subcategory":"Construction",
            "type":"Services"
        }
    ],
    "sg:phone":"+1 718 708 4367",
    "sg:postcode":"10466",
    "sg:province":"NY",
    "sg:tags":[
        "home",
        "improvement"
    ],
    "wof:name":"Valas Home Improvement",
    "wof:placetype":"venue"
},
  "geometry": {"coordinates":[-73.856369,40.884852],"type":"Point"}
}