{
  "type": "Feature",
  "properties": {
    "addr:full":"982 Victory Blvd Staten Island NY 10301",
    "addr:housenumber":"982",
    "addr:postcode":"10301",
    "addr:street":"Victory Blvd",
    "iso:country":"US",
    "sg:address":"982 Victory Blvd",
    "sg:city":"Staten Island",
    "sg:classifiers":[
        {
            "category":"Real Estate",
            "subcategory":"Developer",
            "type":"Services"
        }
    ],
    "sg:phone":"+1 718 727 0222",
    "sg:postcode":"10301",
    "sg:province":"NY",
    "sg:tags":[
        "cemetery"
    ],
    "wof:name":"Woodland Cemetery",
    "wof:placetype":"venue"
},
  "geometry": {"coordinates":[-74.098016,40.621013],"type":"Point"}
}