{
  "type": "Feature",
  "properties": {
    "addr:full":"1705 Anthony Ave Bronx NY 10457",
    "addr:housenumber":"1705",
    "addr:postcode":"10457",
    "addr:street":"Anthony Ave",
    "iso:country":"US",
    "sg:address":"1705 Anthony Ave",
    "sg:city":"Bronx",
    "sg:classifiers":[
        {
            "category":"Professional",
            "type":"Services"
        }
    ],
    "sg:phone":"+1   ",
    "sg:postcode":"10457",
    "sg:province":"NY",
    "wof:name":"Jay Sunny International",
    "wof:placetype":"venue"
},
  "geometry": {"coordinates":[-73.90457000000001,40.843422],"type":"Point"}
}