{
  "type": "Feature",
  "properties": {
    "iso:country":"US",
    "sg:address":"107 Burmon Dr",
    "sg:city":"Orchard Park",
    "sg:classifiers":[
        {
            "category":"Professional",
            "type":"Services"
        }
    ],
    "sg:phone":"+1 716 822 9194",
    "sg:postcode":"14127",
    "sg:province":"NY",
    "sg:tags":[
        "establishment"
    ],
    "wof:name":"W J Poole & Son",
    "wof:placetype":"venue"
},
  "geometry": {"coordinates":[-78.78762,42.802308],"type":"Point"}
}