{
  "type": "Feature",
  "properties": {
    "addr:full":"623 S Broadway Yonkers NY 10705",
    "addr:housenumber":"623",
    "addr:postcode":"10705",
    "addr:street":"S Broadway",
    "iso:country":"US",
    "sg:address":"623 S Broadway",
    "sg:city":"Yonkers",
    "sg:classifiers":[
        {
            "category":"Restaurant",
            "type":"Food & Drink"
        }
    ],
    "sg:menulink":"http://www.allmenus.com/ny/yonkers/131446-ok-maguey/menu/",
    "sg:phone":"+1 914 457 7351",
    "sg:postcode":"10705",
    "sg:province":"NY",
    "sg:tags":[
        "mexican"
    ],
    "wof:name":"Ok Maguey",
    "wof:placetype":"venue"
},
  "geometry": {"coordinates":[-73.896585,40.912233],"type":"Point"}
}