{
  "type": "Feature",
  "properties": {
    "addr:full":"557 Central Ave Apt 3A Cedarhurst NY 11516",
    "addr:housenumber":"557;3a",
    "addr:postcode":"11516",
    "addr:street":"Central Ave Apt",
    "iso:country":"US",
    "sg:address":"557 Central Ave Apt 3A",
    "sg:city":"Cedarhurst",
    "sg:classifiers":[
        {
            "category":"Professional",
            "subcategory":"Accounting & Tax Preparation",
            "type":"Services"
        }
    ],
    "sg:phone":"+1 516 374 8400",
    "sg:postcode":"11516",
    "sg:province":"NY",
    "sg:tags":[
        "accountant"
    ],
    "wof:name":"Schneider Michael L CPA",
    "wof:placetype":"venue"
},
  "geometry": {"coordinates":[-73.723198,40.6222],"type":"Point"}
}