{
  "type": "Feature",
  "properties": {
    "addr:full":"30 East 76th Street 6th Floor Manhattan NY 10021",
    "addr:housenumber":"30;6th",
    "addr:postcode":"10021",
    "addr:street":"East 76Th Street;Floor",
    "iso:country":"US",
    "sg:address":"30 East 76th Street 6th Floor",
    "sg:city":"Manhattan",
    "sg:classifiers":[
        {
            "category":"Health Services",
            "subcategory":"Doctor",
            "type":"Services"
        }
    ],
    "sg:phone":"+1 212 249 3050",
    "sg:postcode":"10021",
    "sg:province":"NY",
    "sg:tags":[
        "surgeon",
        "cosmetic",
        "dermatologist"
    ],
    "wof:name":"LaserSculpt of Manhattan / Dr. Steven Victor",
    "wof:placetype":"venue"
},
  "geometry": {"coordinates":[-73.963425,40.774162],"type":"Point"}
}