{
  "type": "Feature",
  "properties": {
    "iso:country":"US",
    "sg:address":"7 Old Snake Hill Rd",
    "sg:city":"Pound Ridge",
    "sg:classifiers":[
        {
            "category":"Banks & Credit Unions",
            "subcategory":"Bank",
            "type":"Services"
        }
    ],
    "sg:phone":"+1 914 238 6084",
    "sg:postcode":"10576",
    "sg:province":"NY",
    "sg:tags":[
        "loan",
        "real estate"
    ],
    "wof:name":"New Amsterdam Mortgage",
    "wof:placetype":"venue"
},
  "geometry": {"coordinates":[-73.567392,41.182649],"type":"Point"}
}