{
  "type": "Feature",
  "properties": {
    "iso:country":"US",
    "sg:address":"468 Kennedy Rd",
    "sg:city":"Cheektowaga",
    "sg:classifiers":[
        {
            "category":"Building & Trades",
            "subcategory":"Landscaping Services",
            "type":"Services"
        }
    ],
    "sg:phone":"+1 716 893 7301",
    "sg:postcode":"14227",
    "sg:province":"NY",
    "sg:tags":[
        "landscape",
        "contractor"
    ],
    "wof:name":"Burke's Landscaping",
    "wof:placetype":"venue"
},
  "geometry": {"coordinates":[-78.776096,42.898973],"type":"Point"}
}