{
  "type": "Feature",
  "properties": {
    "iso:country":"US",
    "sg:address":"861 Fetzner Rd",
    "sg:city":"Rochester",
    "sg:classifiers":[
        {
            "category":"Restaurant",
            "type":"Food & Drink"
        }
    ],
    "sg:phone":"+1 585 227 4095",
    "sg:postcode":"14626",
    "sg:province":"NY",
    "sg:tags":[
        "eating"
    ],
    "wof:name":"Trotto's Pizzeria",
    "wof:placetype":"venue"
},
  "geometry": {"coordinates":[-77.67788299999999,43.230996],"type":"Point"}
}