{
  "type": "Feature",
  "properties": {
    "iso:country":"US",
    "sg:address":"38 Balsam Dr",
    "sg:city":"Medford",
    "sg:classifiers":[
        {
            "category":"Professional",
            "subcategory":"Computer Services",
            "type":"Services"
        }
    ],
    "sg:phone":"+1   ",
    "sg:postcode":"11763",
    "sg:province":"NY",
    "sg:tags":[
        "prepackaged",
        "book",
        "software"
    ],
    "wof:name":"Art Instruction Software",
    "wof:placetype":"venue"
},
  "geometry": {"coordinates":[-72.96784700000001,40.801169],"type":"Point"}
}