{
  "type": "Feature",
  "properties": {
    "addr:full":"16 Rosevale Ave Ronkonkoma NY 11779",
    "addr:housenumber":"16",
    "addr:postcode":"11779",
    "addr:street":"Rosevale Ave",
    "iso:country":"US",
    "sg:address":"16 Rosevale Ave",
    "sg:city":"Ronkonkoma",
    "sg:classifiers":[
        {
            "category":"Social Services",
            "type":"Services"
        }
    ],
    "sg:phone":"+1 631 588 7484",
    "sg:postcode":"11779",
    "sg:province":"NY",
    "sg:tags":[
        "shelter",
        "homeless"
    ],
    "wof:name":"Community Housing Innovations",
    "wof:placetype":"venue"
},
  "geometry": {"coordinates":[-73.118752,40.81795],"type":"Point"}
}