{
  "type": "Feature",
  "properties": {
    "iso:country":"US",
    "sg:address":"313 N Tioga St",
    "sg:city":"Ithaca",
    "sg:classifiers":[
        {
            "category":"Professional",
            "type":"Services"
        }
    ],
    "sg:phone":"+1 607 274 4800",
    "sg:postcode":"14850",
    "sg:province":"NY",
    "sg:tags":[
        "establishment"
    ],
    "wof:name":"Odyssey Networks",
    "wof:placetype":"venue"
},
  "geometry": {"coordinates":[-76.496882,42.442496],"type":"Point"}
}