{
  "type": "Feature",
  "properties": {
    "addr:full":"1840 Union St Schenectady NY 12309",
    "addr:housenumber":"1840",
    "addr:postcode":"12309",
    "addr:street":"Union St",
    "iso:country":"US",
    "sg:address":"1840 Union St",
    "sg:city":"Schenectady",
    "sg:classifiers":[
        {
            "category":"Real Estate",
            "subcategory":"Real Estate Agent",
            "type":"Services"
        }
    ],
    "sg:phone":"+1 518 370 1911",
    "sg:postcode":"12309",
    "sg:province":"NY",
    "sg:tags":[
        "agency"
    ],
    "wof:name":"Stopera Realty Inc",
    "wof:placetype":"venue"
},
  "geometry": {"coordinates":[-73.894564,42.799778],"type":"Point"}
}