{
  "type": "Feature",
  "properties": {
    "addr:full":"5727 S Park Ave Hamburg NY 14075",
    "addr:housenumber":"5727",
    "addr:postcode":"14075",
    "addr:street":"S Park Ave",
    "iso:country":"US",
    "sg:address":"5727 S Park Ave",
    "sg:city":"Hamburg",
    "sg:classifiers":[
        {
            "category":"Manufacturing",
            "subcategory":"Food",
            "type":"Manufacturing & Wholesale Goods"
        }
    ],
    "sg:phone":"+1 716 649 4590",
    "sg:postcode":"14075",
    "sg:province":"NY",
    "sg:tags":[
        "confectionery",
        "candy"
    ],
    "sg:website":"www.epkirst.com",
    "wof:name":"E P Kirst & Sons Inc",
    "wof:placetype":"venue"
},
  "geometry": {"coordinates":[-78.825447,42.735605],"type":"Point"}
}