{
  "type": "Feature",
  "properties": {
    "addr:full":"1476 E 222nd St Bronx NY 10469",
    "addr:housenumber":"1476",
    "addr:postcode":"10469",
    "addr:street":"E 222Nd St",
    "iso:country":"US",
    "sg:address":"1476 E 222nd St",
    "sg:city":"Bronx",
    "sg:classifiers":[
        {
            "category":"Wholesale",
            "subcategory":"Machinery & Supplies",
            "type":"Manufacturing & Wholesale Goods"
        }
    ],
    "sg:phone":"+1   ",
    "sg:postcode":"10469",
    "sg:province":"NY",
    "sg:tags":[
        "packing",
        "material",
        "mo",
        "for"
    ],
    "sg:website":"www.moversupply.com",
    "wof:name":"Movers Supply House Inc",
    "wof:placetype":"venue"
},
  "geometry": {"coordinates":[-73.835983,40.87599],"type":"Point"}
}