{
  "type": "Feature",
  "properties": {
    "iso:country":"US",
    "sg:address":"3 Elm Ave",
    "sg:city":"Floral Park",
    "sg:classifiers":[
        {
            "category":"Professional",
            "type":"Services"
        }
    ],
    "sg:phone":"+1   ",
    "sg:postcode":"11001",
    "sg:province":"NY",
    "wof:name":"Siteslice Inc",
    "wof:placetype":"venue"
},
  "geometry": {"coordinates":[-73.715351,40.721576],"type":"Point"}
}