{
  "type": "Feature",
  "properties": {
    "iso:country":"US",
    "sg:address":"54 Leonard St",
    "sg:city":"New York",
    "sg:classifiers":[
        {
            "category":"Professional",
            "subcategory":"Business Services",
            "type":"Services"
        }
    ],
    "sg:phone":"+1 212 334 3060",
    "sg:postcode":"10013",
    "sg:province":"NY",
    "sg:tags":[
        "translator",
        "interpreter"
    ],
    "wof:name":"New York Circle Of Translators",
    "wof:placetype":"venue"
},
  "geometry": {"coordinates":[-74.00637999999999,40.717958],"type":"Point"}
}