{
  "type": "Feature",
  "properties": {
    "addr:full":"1095 Prospect Ave Frnt 1 Bronx NY 10459",
    "addr:housenumber":"1095;1",
    "addr:postcode":"10459",
    "addr:street":"Prospect Ave Frnt",
    "iso:country":"US",
    "sg:address":"1095 Prospect Ave Frnt 1",
    "sg:city":"Bronx",
    "sg:classifiers":[
        {
            "category":"Food & Beverages",
            "subcategory":"Groceries & Convenience Stores",
            "type":"Retail Goods"
        }
    ],
    "sg:phone":"+1 718 542 5557",
    "sg:postcode":"10459",
    "sg:province":"NY",
    "wof:name":"1095 Deli Grocery",
    "wof:placetype":"venue"
},
  "geometry": {"coordinates":[-73.89916100000001,40.826022],"type":"Point"}
}