{
  "type": "Feature",
  "properties": {
    "iso:country":"US",
    "sg:address":"111 State Hwy 32",
    "sg:city":"Schuylerville",
    "sg:classifiers":[
        {
            "category":"Retail",
            "subcategory":"Auto Repair",
            "type":"Services"
        }
    ],
    "sg:phone":"+1 518 695 3904",
    "sg:postcode":"12871",
    "sg:province":"NY",
    "sg:tags":[
        "general",
        "government"
    ],
    "wof:name":"Saratoga Town Garage",
    "wof:placetype":"venue"
},
  "geometry": {"coordinates":[-73.60513,43.082568],"type":"Point"}
}