{
  "type": "Feature",
  "properties": {
    "iso:country":"US",
    "sg:address":"156 Co Rd 204",
    "sg:city":"Brockport",
    "sg:classifiers":[
        {
            "category":"Health Services",
            "subcategory":"Doctor",
            "type":"Services"
        }
    ],
    "sg:phone":"+1 585 637 2525",
    "sg:postcode":"14428",
    "sg:province":"NY",
    "sg:tags":[
        "physician",
        "medical",
        "surgeon"
    ],
    "wof:name":"Westside Surgical Associates",
    "wof:placetype":"venue"
},
  "geometry": {"coordinates":[-77.898849,43.124267],"type":"Point"}
}