{
  "type": "Feature",
  "properties": {
    "addr:full":"6401 14th Ave Brooklyn NY 11219",
    "addr:housenumber":"6401",
    "addr:postcode":"11219",
    "addr:street":"14Th Ave",
    "iso:country":"US",
    "sg:address":"6401 14th Ave",
    "sg:city":"Brooklyn",
    "sg:classifiers":[
        {
            "category":"Retail",
            "subcategory":"Self-service Laundry",
            "type":"Services"
        }
    ],
    "sg:phone":"+1   ",
    "sg:postcode":"11219",
    "sg:province":"NY",
    "sg:tags":[
        "coin"
    ],
    "wof:name":"Lucky Laundromat LI Inc",
    "wof:placetype":"venue"
},
  "geometry": {"coordinates":[-73.99932099999999,40.624656],"type":"Point"}
}