{
  "type": "Feature",
  "properties": {
    "addr:full":"6323 Knickerbocker Rd Ontario NY 14519",
    "addr:housenumber":"6323",
    "addr:postcode":"14519",
    "addr:street":"Knickerbocker Rd",
    "iso:country":"US",
    "sg:address":"6323 Knickerbocker Rd",
    "sg:city":"Ontario",
    "sg:classifiers":[
        {
            "category":"Personal",
            "subcategory":"Beauty Salon",
            "type":"Services"
        }
    ],
    "sg:phone":"+1 315 524 6791",
    "sg:postcode":"14519",
    "sg:province":"NY",
    "wof:name":"House Of Nails",
    "wof:placetype":"venue"
},
  "geometry": {"coordinates":[-77.286321,43.228521],"type":"Point"}
}