{
  "type": "Feature",
  "properties": {
    "addr:full":"175 Atlantic Ave Oceanside NY 11572",
    "addr:housenumber":"175",
    "addr:postcode":"11572",
    "addr:street":"Atlantic Ave",
    "iso:country":"US",
    "sg:address":"175 Atlantic Ave",
    "sg:city":"Oceanside",
    "sg:classifiers":[
        {
            "category":"Health Services",
            "subcategory":"Dentist",
            "type":"Services"
        }
    ],
    "sg:phone":"+1 516 536 7008",
    "sg:postcode":"11572",
    "sg:province":"NY",
    "wof:name":"Deleonardis James",
    "wof:placetype":"venue"
},
  "geometry": {"coordinates":[-73.646405,40.639981],"type":"Point"}
}