{
  "type": "Feature",
  "properties": {
    "iso:country":"US",
    "sg:address":"440 Broadway",
    "sg:city":"Newburgh",
    "sg:classifiers":[
        {
            "category":"Retail",
            "subcategory":"Auto Repair",
            "type":"Services"
        }
    ],
    "sg:phone":"+1 845 569 2278",
    "sg:postcode":"12550",
    "sg:province":"NY",
    "sg:tags":[
        "transmission"
    ],
    "wof:name":"Mitch's Transmission",
    "wof:placetype":"venue"
},
  "geometry": {"coordinates":[-74.029827,41.501353],"type":"Point"}
}