{
  "type": "Feature",
  "properties": {
    "addr:full":"4300 Hempstead Tpke Bethpage NY 11714",
    "addr:housenumber":"4300",
    "addr:postcode":"11714",
    "addr:street":"Hempstead Tpke",
    "iso:country":"US",
    "sg:address":"4300 Hempstead Tpke",
    "sg:city":"Bethpage",
    "sg:classifiers":[
        {
            "category":"Health Services",
            "subcategory":"Doctor",
            "type":"Services"
        }
    ],
    "sg:phone":"+1 516 802 8600",
    "sg:postcode":"11714",
    "sg:province":"NY",
    "sg:tags":[
        "physician",
        "surgeon"
    ],
    "wof:name":"Joel D Bregman MD",
    "wof:placetype":"venue"
},
  "geometry": {"coordinates":[-73.47811,40.725635],"type":"Point"}
}