{
  "type": "Feature",
  "properties": {
    "iso:country":"US",
    "sg:address":"8397 Rte 62",
    "sg:city":"South Dayton",
    "sg:classifiers":[
        {
            "category":"Restaurant",
            "type":"Food & Drink"
        }
    ],
    "sg:phone":"+1 716 988 3301",
    "sg:postcode":"14138",
    "sg:province":"NY",
    "wof:name":"Racers Restaurant",
    "wof:placetype":"venue"
},
  "geometry": {"coordinates":[-79.00254099999999,42.397021],"type":"Point"}
}