{
  "type": "Feature",
  "properties": {
    "addr:full":"200 W 26th St Apt 10R New York NY 10001",
    "addr:housenumber":"200",
    "addr:postcode":"10001",
    "addr:street":"W 26Th St Apt 10R",
    "iso:country":"US",
    "sg:address":"200 W 26th St Apt 10R",
    "sg:city":"New York",
    "sg:classifiers":[
        {
            "category":"Education",
            "subcategory":"University",
            "type":"Public Place"
        }
    ],
    "sg:phone":"+1 212 627 9161",
    "sg:postcode":"10001",
    "sg:province":"NY",
    "sg:tags":[
        "college"
    ],
    "wof:name":"Carr Bernadette",
    "wof:placetype":"venue"
},
  "geometry": {"coordinates":[-73.99433000000001,40.745883],"type":"Point"}
}