{
  "type": "Feature",
  "properties": {
    "iso:country":"US",
    "sg:address":"85 Berkshire Rd",
    "sg:city":"West Babylon",
    "sg:classifiers":[
        {
            "category":"Building & Trades",
            "subcategory":"Construction",
            "type":"Services"
        }
    ],
    "sg:phone":"+1 631 893 5045",
    "sg:postcode":"11704",
    "sg:province":"NY",
    "sg:tags":[
        "general",
        "contractor"
    ],
    "wof:name":"Busy Bee Constr",
    "wof:placetype":"venue"
},
  "geometry": {"coordinates":[-73.340958,40.710846],"type":"Point"}
}