{
  "type": "Feature",
  "properties": {
    "iso:country":"US",
    "sg:address":"144 N Comrie Ave",
    "sg:city":"Johnstown",
    "sg:classifiers":[
        {
            "category":"Restaurant",
            "type":"Food & Drink"
        }
    ],
    "sg:phone":"+1   ",
    "sg:postcode":"12095",
    "sg:province":"NY",
    "sg:tags":[
        "eating"
    ],
    "wof:name":"KFC",
    "wof:placetype":"venue"
},
  "geometry": {"coordinates":[-74.36019400000001,43.00947],"type":"Point"}
}