{
  "type": "Feature",
  "properties": {
    "addr:full":"745 Middle Rd Horseheads NY 14845",
    "addr:housenumber":"745",
    "addr:postcode":"14845",
    "addr:street":"Middle Rd",
    "iso:country":"US",
    "sg:address":"745 Middle Rd",
    "sg:city":"Horseheads",
    "sg:classifiers":[
        {
            "category":"Home & Garden",
            "subcategory":"Building Materials",
            "type":"Retail Goods"
        }
    ],
    "sg:phone":"+1 607 732 2669",
    "sg:postcode":"14845",
    "sg:province":"NY",
    "sg:tags":[
        "windows"
    ],
    "wof:name":"M & P Windows LLC",
    "wof:placetype":"venue"
},
  "geometry": {"coordinates":[-76.821607,42.240217],"type":"Point"}
}