{
  "type": "Feature",
  "properties": {
    "iso:country":"US",
    "sg:address":"333 W 52nd St",
    "sg:city":"New York",
    "sg:classifiers":[
        {
            "category":"Arts & Performance",
            "subcategory":"Arts Center",
            "type":"Entertainment"
        }
    ],
    "sg:phone":"+1 212 767 0744",
    "sg:postcode":"10019",
    "sg:province":"NY",
    "sg:tags":[
        "performing"
    ],
    "sg:website":"www.danceteachernetwork.com",
    "wof:name":"Dance Teacher Network",
    "wof:placetype":"venue"
},
  "geometry": {"coordinates":[-73.986042,40.764058],"type":"Point"}
}