{
  "type": "Feature",
  "properties": {
    "iso:country":"US",
    "sg:address":"3 Colonial Ave",
    "sg:city":"Warwick",
    "sg:classifiers":[
        {
            "category":"Autos & Motor Vehicles",
            "subcategory":"Fuel & Gas Station",
            "type":"Retail Goods"
        }
    ],
    "sg:phone":"+1 845 986 1313",
    "sg:postcode":"10990",
    "sg:province":"NY",
    "sg:tags":[
        "oil"
    ],
    "wof:name":"Warwick Gas & Food",
    "wof:placetype":"venue"
},
  "geometry": {"coordinates":[-74.357061,41.259779],"type":"Point"}
}