{
  "type": "Feature",
  "properties": {
    "addr:full":"3448 State Hwy 31 Baldwinsville NY 13027",
    "addr:housenumber":"3448",
    "addr:postcode":"13027",
    "addr:street":"State Hwy 31",
    "iso:country":"US",
    "sg:address":"3448 State Hwy 31",
    "sg:city":"Baldwinsville",
    "sg:classifiers":[
        {
            "category":"Health Services",
            "subcategory":"Medical Lab",
            "type":"Services"
        }
    ],
    "sg:phone":"+1 315 622 6595",
    "sg:postcode":"13027",
    "sg:province":"NY",
    "sg:tags":[
        "laboratory"
    ],
    "wof:name":"Carebest Pediatrics",
    "wof:placetype":"venue"
},
  "geometry": {"coordinates":[-76.26911,43.177667],"type":"Point"}
}