{
  "type": "Feature",
  "properties": {
    "addr:full":"1362 White Plains Rd Bronx NY 10462",
    "addr:housenumber":"1362",
    "addr:postcode":"10462",
    "addr:street":"White Plains Rd",
    "iso:country":"US",
    "sg:address":"1362 White Plains Rd",
    "sg:city":"Bronx",
    "sg:classifiers":[
        {
            "category":"Retail",
            "subcategory":"Laundry & Dry Cleaning",
            "type":"Services"
        }
    ],
    "sg:phone":"+1 718 931 6555",
    "sg:postcode":"10462",
    "sg:province":"NY",
    "sg:tags":[
        "cleaners"
    ],
    "wof:name":"Gene's Cleaners",
    "wof:placetype":"venue"
},
  "geometry": {"coordinates":[-73.863045,40.835262],"type":"Point"}
}