{
  "type": "Feature",
  "properties": {
    "addr:full":"4915 W Taft Rd Liverpool NY 13088",
    "addr:housenumber":"4915",
    "addr:postcode":"13088",
    "addr:street":"W Taft Rd",
    "iso:country":"US",
    "sg:address":"4915 W Taft Rd",
    "sg:city":"Liverpool",
    "sg:classifiers":[
        {
            "category":"Farming",
            "subcategory":"Farm & Veterinary Services",
            "type":"Manufacturing & Wholesale Goods"
        }
    ],
    "sg:phone":"+1 315 457 8762",
    "sg:postcode":"13088",
    "sg:province":"NY",
    "sg:tags":[
        "insemination"
    ],
    "wof:name":"Humane Association-Central Ny",
    "wof:placetype":"venue"
},
  "geometry": {"coordinates":[-76.17678600000001,43.1213],"type":"Point"}
}