{
  "type": "Feature",
  "properties": {
    "iso:country":"US",
    "sg:address":"2812 Avenue U",
    "sg:city":"Brooklyn",
    "sg:classifiers":[
        {
            "category":"Food & Beverages",
            "subcategory":"Liquor & Beverages",
            "type":"Retail Goods"
        }
    ],
    "sg:phone":"+1 718 648 7590",
    "sg:postcode":"11229",
    "sg:province":"NY",
    "sg:tags":[
        "beer",
        "spirit",
        "wine"
    ],
    "wof:name":"Tops Liquor Supermarket",
    "wof:placetype":"venue"
},
  "geometry": {"coordinates":[-73.943305,40.600255],"type":"Point"}
}