{
  "type": "Feature",
  "properties": {
    "addr:full":"6003 S Salina St Syracuse NY 13205",
    "addr:housenumber":"6003",
    "addr:postcode":"13205",
    "addr:street":"S Salina St",
    "iso:country":"US",
    "sg:address":"6003 S Salina St",
    "sg:city":"Syracuse",
    "sg:classifiers":[
        {
            "category":"Sports & Exercise",
            "subcategory":"Gym",
            "type":"Entertainment"
        }
    ],
    "sg:phone":"+1 315 498 5103",
    "sg:postcode":"13205",
    "sg:province":"NY",
    "sg:tags":[
        "club",
        "health",
        "studio",
        "gymnasium"
    ],
    "wof:name":"Curves",
    "wof:placetype":"venue"
},
  "geometry": {"coordinates":[-76.142905,42.982788],"type":"Point"}
}