{
  "type": "Feature",
  "properties": {
    "iso:country":"US",
    "sg:address":"79 Pike St",
    "sg:city":"Port Jervis",
    "sg:classifiers":[
        {
            "category":"Restaurant",
            "type":"Food & Drink"
        }
    ],
    "sg:phone":"+1 845 856 4010",
    "sg:postcode":"12771",
    "sg:province":"NY",
    "wof:name":"Cafe Roxanna",
    "wof:placetype":"venue"
},
  "geometry": {"coordinates":[-74.693286,41.374752],"type":"Point"}
}