{
  "type": "Feature",
  "properties": {
    "iso:country":"US",
    "sg:address":"32 Linden St",
    "sg:city":"Geneva",
    "sg:classifiers":[
        {
            "category":"Real Estate",
            "subcategory":"Real Estate Agent",
            "type":"Services"
        }
    ],
    "sg:phone":"+1 315 789 4905",
    "sg:postcode":"14456",
    "sg:province":"NY",
    "wof:name":"Cissi Wilson Real Estate",
    "wof:placetype":"venue"
},
  "geometry": {"coordinates":[-76.983487,42.867563],"type":"Point"}
}