{
  "type": "Feature",
  "properties": {
    "addr:full":"810 S 1st St Fulton NY 13069",
    "addr:housenumber":"810",
    "addr:postcode":"13069",
    "addr:street":"S 1St St",
    "iso:country":"US",
    "sg:address":"810 S 1st St",
    "sg:city":"Fulton",
    "sg:classifiers":[
        {
            "category":"Restaurant",
            "type":"Food & Drink"
        }
    ],
    "sg:phone":"+1 315 593 2009",
    "sg:postcode":"13069",
    "sg:province":"NY",
    "wof:name":"Doc's Restaurant Retreat",
    "wof:placetype":"venue"
},
  "geometry": {"coordinates":[-76.403311,43.310113],"type":"Point"}
}