{
  "type": "Feature",
  "properties": {
    "addr:full":"828 E Meadow Ave East Meadow NY 11554",
    "addr:housenumber":"828",
    "addr:postcode":"11554",
    "addr:street":"E Meadow Ave",
    "iso:country":"US",
    "sg:address":"828 E Meadow Ave",
    "sg:city":"East Meadow",
    "sg:classifiers":[
        {
            "category":"Professional",
            "subcategory":"Accounting & Tax Preparation",
            "type":"Services"
        }
    ],
    "sg:phone":"+1 516 292 6631",
    "sg:postcode":"11554",
    "sg:province":"NY",
    "sg:tags":[
        "billing"
    ],
    "wof:name":"A R Medical Billing",
    "wof:placetype":"venue"
},
  "geometry": {"coordinates":[-73.548491,40.705643],"type":"Point"}
}