{
  "type": "Feature",
  "properties": {
    "addr:full":"2034 Bear Creek Dr Ontario NY 14519",
    "addr:housenumber":"2034",
    "addr:postcode":"14519",
    "addr:street":"Bear Creek Dr",
    "iso:country":"US",
    "sg:address":"2034 Bear Creek Dr",
    "sg:city":"Ontario",
    "sg:classifiers":[
        {
            "category":"Building & Trades",
            "subcategory":"Electrical",
            "type":"Services"
        }
    ],
    "sg:phone":"+1 315 524 5720",
    "sg:postcode":"14519",
    "sg:province":"NY",
    "sg:tags":[
        "electrical",
        "contractor"
    ],
    "wof:name":"Eastside Installers",
    "wof:placetype":"venue"
},
  "geometry": {"coordinates":[-77.282241,43.259258],"type":"Point"}
}