{
  "type": "Feature",
  "properties": {
    "addr:full":"6 Kendall Dr New City NY 10956",
    "addr:housenumber":"6",
    "addr:postcode":"10956",
    "addr:street":"Kendall Dr",
    "iso:country":"US",
    "sg:address":"6 Kendall Dr",
    "sg:city":"New City",
    "sg:classifiers":[
        {
            "category":"Travel",
            "subcategory":"Campground",
            "type":"Entertainment"
        }
    ],
    "sg:phone":"+1 845 638 2515",
    "sg:postcode":"10956",
    "sg:province":"NY",
    "sg:tags":[
        "camp"
    ],
    "wof:name":"Camp Edalia Inc",
    "wof:placetype":"venue"
},
  "geometry": {"coordinates":[-73.974268,41.141952],"type":"Point"}
}