{
  "type": "Feature",
  "properties": {
    "addr:full":"4 53rd St Brooklyn NY 11232",
    "addr:housenumber":"4",
    "addr:postcode":"11232",
    "addr:street":"53Rd St",
    "iso:country":"US",
    "sg:address":"4 53rd St",
    "sg:city":"Brooklyn",
    "sg:classifiers":[
        {
            "category":"Real Estate",
            "subcategory":"Architect",
            "type":"Services"
        }
    ],
    "sg:phone":"+1 718 765 4050",
    "sg:postcode":"11232",
    "sg:province":"NY",
    "sg:tags":[
        "architectural"
    ],
    "wof:name":"Elite Woodworking",
    "wof:placetype":"venue"
},
  "geometry": {"coordinates":[-74.02143599999999,40.648923],"type":"Point"}
}