{
  "type": "Feature",
  "properties": {
    "addr:full":"4162 Lakeville Rd Geneseo NY 14454",
    "addr:postcode":"4162;14454",
    "addr:street":"Lakeville Rd",
    "iso:country":"US",
    "sg:address":"4162 Lakeville Rd",
    "sg:city":"Geneseo",
    "sg:classifiers":[
        {
            "category":"Restaurant",
            "type":"Food & Drink"
        }
    ],
    "sg:phone":"+1 585 243 0509",
    "sg:postcode":"14454",
    "sg:province":"NY",
    "sg:website":"www.mcdonalds.com",
    "wof:name":"Mc Donald's",
    "wof:placetype":"venue"
},
  "geometry": {"coordinates":[-77.7916,42.796278],"type":"Point"}
}