{
  "type": "Feature",
  "properties": {
    "addr:full":"36 Main St Le Roy NY 14482",
    "addr:housenumber":"36",
    "addr:postcode":"14482",
    "addr:street":"Main St",
    "iso:country":"US",
    "sg:address":"36 Main St",
    "sg:city":"Le Roy",
    "sg:classifiers":[
        {
            "category":"Professional",
            "subcategory":"Lawyer & Legal Services",
            "type":"Services"
        }
    ],
    "sg:phone":"+1   ",
    "sg:postcode":"14482",
    "sg:province":"NY",
    "wof:name":"Mary Kay Yanik",
    "wof:placetype":"venue"
},
  "geometry": {"coordinates":[-77.988581,42.977623],"type":"Point"}
}