{
  "type": "Feature",
  "properties": {
    "addr:full":"3385 Milton Ave Syracuse NY 13219",
    "addr:housenumber":"3385",
    "addr:postcode":"13219",
    "addr:street":"Milton Ave",
    "iso:country":"US",
    "sg:address":"3385 Milton Ave",
    "sg:city":"Syracuse",
    "sg:classifiers":[
        {
            "category":"Food & Beverages",
            "subcategory":"Groceries & Convenience Stores",
            "type":"Retail Goods"
        }
    ],
    "sg:phone":"+1   ",
    "sg:postcode":"13219",
    "sg:province":"NY",
    "sg:tags":[
        "filling",
        "station",
        "gasoline"
    ],
    "wof:name":"A Plus Mini Market",
    "wof:placetype":"venue"
},
  "geometry": {"coordinates":[-76.239244,43.051784],"type":"Point"}
}