{
  "type": "Feature",
  "properties": {
    "addr:full":"513 3rd Ave New York NY 10016",
    "addr:housenumber":"513",
    "addr:postcode":"10016",
    "addr:street":"3Rd Ave",
    "iso:country":"US",
    "sg:address":"513 3rd Ave",
    "sg:city":"New York",
    "sg:classifiers":[
        {
            "category":"Bars & Pubs",
            "type":"Food & Drink"
        },
        {
            "category":"Restaurant",
            "type":"Food & Drink"
        }
    ],
    "sg:phone":"+1 212 689 0058",
    "sg:postcode":"10016",
    "sg:province":"NY",
    "sg:tags":[
        "irish"
    ],
    "sg:website":"joshuatreebar.com",
    "wof:name":"Joshua Tree",
    "wof:placetype":"venue"
},
  "geometry": {"coordinates":[-73.977924,40.745973],"type":"Point"}
}