{
  "type": "Feature",
  "properties": {
    "addr:full":"988 Franklin Ave. Garden City NY 11530",
    "addr:housenumber":"988",
    "addr:postcode":"11530",
    "addr:street":"Franklin Ave.",
    "iso:country":"US",
    "sg:address":"988 Franklin Ave.",
    "sg:city":"Garden City",
    "sg:classifiers":[
        {
            "category":"Restaurant",
            "type":"Food & Drink"
        }
    ],
    "sg:phone":"+1 516 877 0888",
    "sg:postcode":"11530",
    "sg:province":"NY",
    "sg:tags":[
        "fusion",
        "asian"
    ],
    "sg:website":"www.jineast.com",
    "wof:name":"Jin East",
    "wof:placetype":"venue"
},
  "geometry": {"coordinates":[-73.635581,40.729429],"type":"Point"}
}