{
  "type": "Feature",
  "properties": {
    "addr:full":"21 S William St New York NY 10004",
    "addr:housenumber":"21",
    "addr:postcode":"10004",
    "addr:street":"S William St",
    "iso:country":"US",
    "sg:address":"21 S William St",
    "sg:city":"New York",
    "sg:classifiers":[
        {
            "category":"Professional",
            "type":"Services"
        }
    ],
    "sg:phone":"+1 212 509 1833",
    "sg:postcode":"10004",
    "sg:province":"NY",
    "sg:tags":[
        "establishment"
    ],
    "wof:name":"21-23 South William Street",
    "wof:placetype":"venue"
},
  "geometry": {"coordinates":[-74.011115,40.704305],"type":"Point"}
}