{
  "type": "Feature",
  "properties": {
    "iso:country":"US",
    "sg:address":"80 University Pl",
    "sg:city":"New York",
    "sg:classifiers":[
        {
            "category":"Professional",
            "subcategory":"Research",
            "type":"Services"
        },
        {
            "category":"Professional",
            "subcategory":"Management & Consulting",
            "type":"Services"
        }
    ],
    "sg:phone":"+1 212 929 6510",
    "sg:postcode":"10003",
    "sg:province":"NY",
    "sg:tags":[
        "specializing",
        "marketing",
        "analysis",
        "sampling",
        "survey",
        "market"
    ],
    "wof:name":"Blum & Weprin Associates Inc",
    "wof:placetype":"venue"
},
  "geometry": {"coordinates":[-73.992895,40.733901],"type":"Point"}
}