{
  "type": "Feature",
  "properties": {
    "iso:country":"US",
    "sg:address":"13 Taylor Sq",
    "sg:city":"White Plains",
    "sg:classifiers":[
        {
            "category":"Restaurant",
            "type":"Food & Drink"
        }
    ],
    "sg:phone":"+1 914 681 5128",
    "sg:postcode":"10604",
    "sg:province":"NY",
    "wof:name":"Great Wall Restaurant",
    "wof:placetype":"venue"
},
  "geometry": {"coordinates":[-73.75214099999999,41.042379],"type":"Point"}
}