{
  "type": "Feature",
  "properties": {
    "addr:full":"330 Durant Ave Staten Island NY 10308",
    "addr:housenumber":"330",
    "addr:postcode":"10308",
    "addr:street":"Durant Ave",
    "iso:country":"US",
    "sg:address":"330 Durant Ave",
    "sg:city":"Staten Island",
    "sg:classifiers":[
        {
            "category":"Professional",
            "subcategory":"Employment Agencies",
            "type":"Services"
        }
    ],
    "sg:phone":"+1 718 980 1479",
    "sg:postcode":"10308",
    "sg:province":"NY",
    "wof:name":"Uft Teacher Center",
    "wof:placetype":"venue"
},
  "geometry": {"coordinates":[-74.1371,40.5527],"type":"Point"}
}