{
  "type": "Feature",
  "properties": {
    "iso:country":"US",
    "sg:address":"130 Genesee St",
    "sg:city":"Avon",
    "sg:classifiers":[
        {
            "category":"Place Of Worship",
            "subcategory":"Church",
            "type":"Public Place"
        },
        {
            "category":"Place Of Worship",
            "type":"Public Place"
        }
    ],
    "sg:phone":"+1 585 226 8600",
    "sg:postcode":"14414",
    "sg:province":"NY",
    "sg:tags":[
        "churches-methodist"
    ],
    "wof:name":"Avon United Methodist Church Inc",
    "wof:placetype":"venue"
},
  "geometry": {"coordinates":[-77.746904,42.909869],"type":"Point"}
}