{
  "type": "Feature",
  "properties": {
    "addr:full":"22 Noxon Rd Poughkeepsie NY 12603",
    "addr:housenumber":"22",
    "addr:postcode":"12603",
    "addr:street":"Noxon Rd",
    "iso:country":"US",
    "sg:address":"22 Noxon Rd",
    "sg:city":"Poughkeepsie",
    "sg:classifiers":[
        {
            "category":"Freight",
            "type":"Transportation"
        }
    ],
    "sg:phone":"+1 845 485 1419",
    "sg:postcode":"12603",
    "sg:province":"NY",
    "wof:name":"JTR Transportation Corp",
    "wof:placetype":"venue"
},
  "geometry": {"coordinates":[-73.858783,41.676079],"type":"Point"}
}