{
  "type": "Feature",
  "properties": {
    "addr:full":"21 Caskey Rd Glen Spey NY 12737",
    "addr:housenumber":"21",
    "addr:postcode":"12737",
    "addr:street":"Caskey Rd",
    "iso:country":"US",
    "sg:address":"21 Caskey Rd",
    "sg:city":"Glen Spey",
    "sg:classifiers":[
        {
            "category":"Shopping",
            "type":"Retail Goods"
        }
    ],
    "sg:phone":"+1 845 858 2030",
    "sg:postcode":"12737",
    "sg:province":"NY",
    "sg:tags":[
        "coin",
        "dealer",
        "supply"
    ],
    "sg:website":"www.militarycoin.com",
    "wof:name":"Challange Coin Co",
    "wof:placetype":"venue"
},
  "geometry": {"coordinates":[-74.76147,41.432795],"type":"Point"}
}