{
  "type": "Feature",
  "properties": {
    "addr:full":"102 Madison Ave Fl 2 New York NY 10016",
    "addr:housenumber":"102;2",
    "addr:postcode":"10016",
    "addr:street":"Madison Ave Fl",
    "iso:country":"US",
    "sg:address":"102 Madison Ave Fl 2",
    "sg:city":"New York",
    "sg:classifiers":[
        {
            "category":"Building & Trades",
            "subcategory":"Construction",
            "type":"Services"
        }
    ],
    "sg:phone":"+1 212 792 0300",
    "sg:postcode":"10016",
    "sg:province":"NY",
    "sg:tags":[
        "interior",
        "design"
    ],
    "wof:name":"Hunter Roberts Interiors",
    "wof:placetype":"venue"
},
  "geometry": {"coordinates":[-73.9853,40.744795],"type":"Point"}
}