{
  "type": "Feature",
  "properties": {
    "iso:country":"US",
    "sg:address":"9 Lee St E",
    "sg:city":"Utica",
    "sg:classifiers":[
        {
            "category":"Freight",
            "type":"Transportation"
        }
    ],
    "sg:phone":"+1   ",
    "sg:postcode":"13502",
    "sg:province":"NY",
    "sg:tags":[
        "operator",
        "local",
        "courier",
        "trucking"
    ],
    "wof:name":"Corporate Express Delivery Sys",
    "wof:placetype":"venue"
},
  "geometry": {"coordinates":[-75.22240600000001,43.106452],"type":"Point"}
}