{
  "type": "Feature",
  "properties": {
    "addr:full":"408 Proctor Ave Ogdensburg NY 13669",
    "addr:housenumber":"408",
    "addr:postcode":"13669",
    "addr:street":"Proctor Ave",
    "iso:country":"US",
    "sg:address":"408 Proctor Ave",
    "sg:city":"Ogdensburg",
    "sg:classifiers":[
        {
            "category":"Organizations",
            "subcategory":"Religious Organization",
            "type":"Services"
        }
    ],
    "sg:phone":"+1 315 393 5202",
    "sg:postcode":"13669",
    "sg:province":"NY",
    "sg:tags":[
        "clergy"
    ],
    "wof:name":"Thomas T Patterson",
    "wof:placetype":"venue"
},
  "geometry": {"coordinates":[-75.45791,44.712913],"type":"Point"}
}