{
  "type": "Feature",
  "properties": {
    "addr:full":"2243 Westchester Avenue Bronx NY 10462",
    "addr:housenumber":"2243",
    "addr:postcode":"10462",
    "addr:street":"Westchester Avenue",
    "iso:country":"US",
    "sg:address":"2243 Westchester Avenue",
    "sg:city":"Bronx",
    "sg:classifiers":[
        {
            "category":"Shopping",
            "subcategory":"Jewelry",
            "type":"Retail Goods"
        }
    ],
    "sg:phone":"+1 718 239 1986",
    "sg:postcode":"10462",
    "sg:province":"NY",
    "sg:website":"www.sparkle-jewelry.com",
    "wof:name":"Sparkle Jewelry",
    "wof:placetype":"venue"
},
  "geometry": {"coordinates":[-73.850588,40.834357],"type":"Point"}
}