{
  "type": "Feature",
  "properties": {
    "addr:full":"105 Mac Dougal St New York NY 10012",
    "addr:housenumber":"105",
    "addr:postcode":"10012",
    "addr:street":"Mac Dougal St",
    "iso:country":"US",
    "sg:address":"105 Mac Dougal St",
    "sg:city":"New York",
    "sg:classifiers":[
        {
            "category":"Health Services",
            "subcategory":"Doctor",
            "type":"Services"
        }
    ],
    "sg:phone":"+1 212 995 9557",
    "sg:postcode":"10012",
    "sg:province":"NY",
    "sg:tags":[
        "physician",
        "surgeon"
    ],
    "wof:name":"Rochelle Didier MD",
    "wof:placetype":"venue"
},
  "geometry": {"coordinates":[-74.000895,40.729507],"type":"Point"}
}