{
  "type": "Feature",
  "properties": {
    "addr:full":"568 Broadway Suite 901 New York NY 10012",
    "addr:housenumber":"568;suite 901",
    "addr:postcode":"10012",
    "addr:street":"Broadway",
    "iso:country":"US",
    "sg:address":"568 Broadway Suite 901",
    "sg:city":"New York",
    "sg:classifiers":[
        {
            "category":"Professional",
            "subcategory":"Computer Services",
            "type":"Services"
        }
    ],
    "sg:phone":"+1 866 962 3621",
    "sg:postcode":"10012",
    "sg:province":"NY",
    "sg:tags":[
        "appointment",
        "times",
        "doctors",
        "dentists",
        "find"
    ],
    "sg:website":"http://www.zocdoc.com",
    "wof:name":"ZocDoc",
    "wof:placetype":"venue"
},
  "geometry": {"coordinates":[-73.99677200000001,40.725432],"type":"Point"}
}