{
  "type": "Feature",
  "properties": {
    "addr:full":"2670 N Main St Newfane NY 14108",
    "addr:housenumber":"2670",
    "addr:postcode":"14108",
    "addr:street":"N Main St",
    "iso:country":"US",
    "sg:address":"2670 N Main St",
    "sg:city":"Newfane",
    "sg:classifiers":[
        {
            "category":"Retail",
            "subcategory":"Funeral Services",
            "type":"Services"
        }
    ],
    "sg:phone":"+1 716 778 7022",
    "sg:postcode":"14108",
    "sg:province":"NY",
    "sg:tags":[
        "director"
    ],
    "wof:name":"Rutland-Corwin Funeral Home",
    "wof:placetype":"venue"
},
  "geometry": {"coordinates":[-78.709256,43.284267],"type":"Point"}
}