{
  "type": "Feature",
  "properties": {
    "addr:full":"321 South Ave Poughkeepsie NY 12601",
    "addr:housenumber":"321",
    "addr:postcode":"12601",
    "addr:street":"South Ave",
    "iso:country":"US",
    "sg:address":"321 South Ave",
    "sg:city":"Poughkeepsie",
    "sg:classifiers":[
        {
            "category":"Real Estate",
            "subcategory":"Real Estate Agent",
            "type":"Services"
        }
    ],
    "sg:phone":"+1 845 298 9191",
    "sg:postcode":"12601",
    "sg:province":"NY",
    "sg:tags":[
        "inspection"
    ],
    "wof:name":"Dutchess Pest Control Inc",
    "wof:placetype":"venue"
},
  "geometry": {"coordinates":[-73.930249,41.684195],"type":"Point"}
}