{
  "type": "Feature",
  "properties": {
    "iso:country":"US",
    "sg:address":"307 Bruckner Blvd",
    "sg:city":"Bronx",
    "sg:classifiers":[
        {
            "category":"Building & Trades",
            "subcategory":"Plumbing",
            "type":"Services"
        }
    ],
    "sg:phone":"+1 718 401 7600",
    "sg:postcode":"10454",
    "sg:province":"NY",
    "wof:name":"Enterprise Plumbing & Heating",
    "wof:placetype":"venue"
},
  "geometry": {"coordinates":[-73.91038,40.805817],"type":"Point"}
}