{
  "type": "Feature",
  "properties": {
    "iso:country":"US",
    "sg:address":"125 W End Ave",
    "sg:city":"New York",
    "sg:classifiers":[
        {
            "category":"Professional",
            "subcategory":"Business Services",
            "type":"Services"
        }
    ],
    "sg:phone":"+1 212 456 5621",
    "sg:postcode":"10023",
    "sg:province":"NY",
    "sg:tags":[
        "recording",
        "studio"
    ],
    "sg:website":"www.abcnewsvsource.com",
    "wof:name":"ABC Sound",
    "wof:placetype":"venue"
},
  "geometry": {"coordinates":[-73.987465,40.775766],"type":"Point"}
}