{
  "type": "Feature",
  "properties": {
    "addr:full":"1277 Clove Road Staten Island NY 10301",
    "addr:housenumber":"1277",
    "addr:postcode":"10301",
    "addr:street":"Clove Road",
    "iso:country":"US",
    "sg:address":"1277 Clove Road",
    "sg:city":"Staten Island",
    "sg:classifiers":[
        {
            "category":"Arts & Performance",
            "subcategory":"Art Gallery",
            "type":"Entertainment"
        }
    ],
    "sg:phone":"+1 718 448 8300",
    "sg:postcode":"10301",
    "sg:province":"NY",
    "wof:name":"Mauro Graphics Ltd",
    "wof:placetype":"venue"
},
  "geometry": {"coordinates":[-74.102964,40.615904],"type":"Point"}
}