{
  "type": "Feature",
  "properties": {
    "iso:country":"US",
    "sg:address":"4018 N Hampton Brook Dr",
    "sg:city":"Hamburg",
    "sg:classifiers":[
        {
            "category":"Wholesale",
            "subcategory":"Machinery & Supplies",
            "type":"Manufacturing & Wholesale Goods"
        }
    ],
    "sg:phone":"+1 716 649 4328",
    "sg:postcode":"14075",
    "sg:province":"NY",
    "sg:tags":[
        "industrial"
    ],
    "wof:name":"Alpha-Z Distributors",
    "wof:placetype":"venue"
},
  "geometry": {"coordinates":[-78.837771,42.707229],"type":"Point"}
}