{
  "type": "Feature",
  "properties": {
    "addr:full":"279 W 19th St Manhattan NY 10011",
    "addr:housenumber":"279",
    "addr:postcode":"10011",
    "addr:street":"W 19Th St",
    "iso:country":"US",
    "sg:address":"279 W 19th St",
    "sg:city":"Manhattan",
    "sg:classifiers":[
        {
            "category":"Building & Trades",
            "subcategory":"Cleaning & Sanitation",
            "type":"Services"
        },
        {
            "category":"Home & Garden",
            "subcategory":"Carpets & Floor Coverings",
            "type":"Retail Goods"
        }
    ],
    "sg:phone":"+1 888 669 4763",
    "sg:postcode":"10011",
    "sg:province":"NY",
    "sg:tags":[
        "flooring"
    ],
    "sg:website":"www.flat-rate-house-cleaning.com",
    "wof:name":"Flat Rate House Cleaning & Maid Service",
    "wof:placetype":"venue"
},
  "geometry": {"coordinates":[-73.999984,40.742733],"type":"Point"}
}