{
  "type": "Feature",
  "properties": {
    "addr:full":"64 S Canal St Greene NY 13778",
    "addr:housenumber":"64",
    "addr:postcode":"13778",
    "addr:street":"S Canal St",
    "iso:country":"US",
    "sg:address":"64 S Canal St",
    "sg:city":"Greene",
    "sg:classifiers":[
        {
            "category":"Manufacturing",
            "subcategory":"Tools & Machinery",
            "type":"Manufacturing & Wholesale Goods"
        }
    ],
    "sg:phone":"+1 607 656 8576",
    "sg:postcode":"13778",
    "sg:province":"NY",
    "sg:tags":[
        "construction",
        "mfg"
    ],
    "wof:name":"M J Taylor Manufacturing Inc",
    "wof:placetype":"venue"
},
  "geometry": {"coordinates":[-75.776269,42.324278],"type":"Point"}
}