{
  "type": "Feature",
  "properties": {
    "iso:country":"US",
    "sg:address":"1163 Old Country Rd",
    "sg:city":"Plainview",
    "sg:classifiers":[
        {
            "category":"Education",
            "subcategory":"Dance Studio",
            "type":"Public Place"
        }
    ],
    "sg:phone":"+1   ",
    "sg:postcode":"11803",
    "sg:province":"NY",
    "wof:name":"Dancenter",
    "wof:placetype":"venue"
},
  "geometry": {"coordinates":[-73.462519,40.776099],"type":"Point"}
}