{
  "type": "Feature",
  "properties": {
    "addr:full":"2108 Stratford Dr Westbury NY 11590",
    "addr:housenumber":"2108",
    "addr:postcode":"11590",
    "addr:street":"Stratford Dr",
    "iso:country":"US",
    "sg:address":"2108 Stratford Dr",
    "sg:city":"Westbury",
    "sg:classifiers":[
        {
            "category":"Banks & Credit Unions",
            "subcategory":"Bank",
            "type":"Services"
        }
    ],
    "sg:phone":"+1 516 997 0679",
    "sg:postcode":"11590",
    "sg:province":"NY",
    "sg:tags":[
        "personal",
        "institution"
    ],
    "wof:name":"Fal Funding Corp",
    "wof:placetype":"venue"
},
  "geometry": {"coordinates":[-73.569332,40.748586],"type":"Point"}
}