{
  "type": "Feature",
  "properties": {
    "addr:full":"46 State Hwy 214 Phoenicia NY 12464",
    "addr:housenumber":"46",
    "addr:postcode":"12464",
    "addr:street":"State Hwy 214",
    "iso:country":"US",
    "sg:address":"46 State Hwy 214",
    "sg:city":"Phoenicia",
    "sg:classifiers":[
        {
            "category":"Shopping",
            "subcategory":"Used Merchandise",
            "type":"Retail Goods"
        }
    ],
    "sg:phone":"+1   ",
    "sg:postcode":"12464",
    "sg:province":"NY",
    "wof:name":"A Country Gallery",
    "wof:placetype":"venue"
},
  "geometry": {"coordinates":[-74.316174,42.083847],"type":"Point"}
}