{
  "type": "Feature",
  "properties": {
    "addr:full":"149 Main St Oneonta NY 13820",
    "addr:housenumber":"149",
    "addr:postcode":"13820",
    "addr:street":"Main St",
    "iso:country":"US",
    "sg:address":"149 Main St",
    "sg:city":"Oneonta",
    "sg:classifiers":[
        {
            "category":"Restaurant",
            "type":"Food & Drink"
        },
        {
            "category":"Bars & Pubs",
            "type":"Food & Drink"
        }
    ],
    "sg:phone":"+1 607 432 6671",
    "sg:postcode":"13820",
    "sg:province":"NY",
    "sg:tags":[
        "drinking",
        "eating"
    ],
    "wof:name":"Novelty Lounge Inc",
    "wof:placetype":"venue"
},
  "geometry": {"coordinates":[-75.06231099999999,42.453707],"type":"Point"}
}