{
  "type": "Feature",
  "properties": {
    "addr:full":"60 Jagger Ln Southampton NY 11968",
    "addr:housenumber":"60",
    "addr:postcode":"11968",
    "addr:street":"Jagger Ln",
    "iso:country":"US",
    "sg:address":"60 Jagger Ln",
    "sg:city":"Southampton",
    "sg:classifiers":[
        {
            "category":"Banks & Credit Unions",
            "subcategory":"Bank",
            "type":"Services"
        },
        {
            "category":"Banks & Credit Unions",
            "subcategory":"Financial Services",
            "type":"Services"
        }
    ],
    "sg:phone":"+1 800 432 1000",
    "sg:postcode":"11968",
    "sg:province":"NY",
    "sg:tags":[
        "saving",
        "loan",
        "commercial",
        "banking",
        "internet"
    ],
    "sg:website":"https://www.bankofamerica.com/",
    "wof:name":"Bank of America",
    "wof:placetype":"venue"
},
  "geometry": {"coordinates":[-72.392183,40.887648],"type":"Point"}
}