{
  "type": "Feature",
  "properties": {
    "addr:full":"407 E 61 St New York NY 10065",
    "addr:housenumber":"407;61",
    "addr:postcode":"10065",
    "addr:street":"E;St",
    "iso:country":"US",
    "sg:address":"407 E 61 St",
    "sg:city":"New York",
    "sg:classifiers":[
        {
            "category":"Parking",
            "type":"Transportation"
        }
    ],
    "sg:phone":"+1 212 838 4158",
    "sg:postcode":"10065",
    "sg:province":"NY",
    "sg:tags":[
        "automobile"
    ],
    "wof:name":"Park Plaza Garage",
    "wof:placetype":"venue"
},
  "geometry": {"coordinates":[-73.958878,40.760037],"type":"Point"}
}