{
  "type": "Feature",
  "properties": {
    "addr:full":"22 Ely Rd Depew NY 14043",
    "addr:housenumber":"22",
    "addr:postcode":"14043",
    "addr:street":"Ely Rd",
    "iso:country":"US",
    "sg:address":"22 Ely Rd",
    "sg:city":"Depew",
    "sg:classifiers":[
        {
            "category":"Professional",
            "subcategory":"Management & Consulting",
            "type":"Services"
        }
    ],
    "sg:phone":"+1 716 685 1234",
    "sg:postcode":"14043",
    "sg:province":"NY",
    "sg:tags":[
        "consultant",
        "business"
    ],
    "sg:website":"www.fswiatek.com",
    "wof:name":"Frank Swiatek & Assoc",
    "wof:placetype":"venue"
},
  "geometry": {"coordinates":[-78.714915,42.894503],"type":"Point"}
}