{
  "type": "Feature",
  "properties": {
    "addr:full":"302 Glendale Ave Liverpool NY 13088",
    "addr:housenumber":"302",
    "addr:postcode":"13088",
    "addr:street":"Glendale Ave",
    "iso:country":"US",
    "sg:address":"302 Glendale Ave",
    "sg:city":"Liverpool",
    "sg:classifiers":[
        {
            "category":"Building & Trades",
            "subcategory":"Cleaning & Sanitation",
            "type":"Services"
        }
    ],
    "sg:phone":"+1 315 516 0452",
    "sg:postcode":"13088",
    "sg:province":"NY",
    "wof:name":"Jericho",
    "wof:placetype":"venue"
},
  "geometry": {"coordinates":[-76.180888,43.093202],"type":"Point"}
}