{
  "type": "Feature",
  "properties": {
    "addr:full":"300 E 39 St New York NY 10016",
    "addr:housenumber":"300;39",
    "addr:postcode":"10016",
    "addr:street":"E;St",
    "iso:country":"US",
    "sg:address":"300 E 39 St",
    "sg:city":"New York",
    "sg:classifiers":[
        {
            "category":"Building & Trades",
            "subcategory":"Construction",
            "type":"Services"
        }
    ],
    "sg:phone":"+1 212 687 8616",
    "sg:postcode":"10016",
    "sg:province":"NY",
    "sg:tags":[
        "concrete",
        "contractor"
    ],
    "wof:name":"Di Fama Concrete Inc",
    "wof:placetype":"venue"
},
  "geometry": {"coordinates":[-73.97273800000001,40.747558],"type":"Point"}
}