{
  "type": "Feature",
  "properties": {
    "iso:country":"US",
    "sg:address":"2867 Long Beach Rd",
    "sg:city":"Oceanside",
    "sg:classifiers":[
        {
            "category":"Personal",
            "subcategory":"Nail Salon",
            "type":"Services"
        }
    ],
    "sg:phone":"+1 516 255 1989",
    "sg:postcode":"11572",
    "sg:province":"NY",
    "wof:name":"Jin Zhou Tai Yuan Nail Inc",
    "wof:placetype":"venue"
},
  "geometry": {"coordinates":[-73.63972099999999,40.640788],"type":"Point"}
}