{
  "type": "Feature",
  "properties": {
    "addr:full":"94 E 7th St New York NY 10079",
    "addr:housenumber":"94",
    "addr:postcode":"10079",
    "addr:street":"E 7Th St",
    "iso:country":"US",
    "sg:address":"94 E 7th St",
    "sg:city":"New York",
    "sg:classifiers":[
        {
            "category":"Restaurant",
            "type":"Food & Drink"
        }
    ],
    "sg:phone":"+1 212 982 4140",
    "sg:postcode":"10079",
    "sg:province":"NY",
    "sg:tags":[
        "japanese"
    ],
    "wof:name":"Kyo Ya",
    "wof:placetype":"venue"
},
  "geometry": {"coordinates":[-73.985412,40.726597],"type":"Point"}
}