{
  "type": "Feature",
  "properties": {
    "addr:full":"14826 Hillside Ave Jamaica NY 11435",
    "addr:housenumber":"14826",
    "addr:postcode":"11435",
    "addr:street":"Hillside Ave",
    "iso:country":"US",
    "sg:address":"14826 Hillside Ave",
    "sg:city":"Jamaica",
    "sg:classifiers":[
        {
            "category":"Retail",
            "subcategory":"Auto Repair",
            "type":"Services"
        }
    ],
    "sg:phone":"+1 718 657 8104",
    "sg:postcode":"11435",
    "sg:province":"NY",
    "sg:tags":[
        "body",
        "shop"
    ],
    "wof:name":"Arm Auto Svce Inc",
    "wof:placetype":"venue"
},
  "geometry": {"coordinates":[-73.80819700000001,40.7061],"type":"Point"}
}