{
  "type": "Feature",
  "properties": {
    "iso:country":"US",
    "sg:address":"125 Roslyn Rd",
    "sg:city":"Roslyn Heights",
    "sg:classifiers":[
        {
            "category":"Travel",
            "subcategory":"Travel Agent",
            "type":"Entertainment"
        }
    ],
    "sg:phone":"+1   ",
    "sg:postcode":"11577",
    "sg:province":"NY",
    "sg:tags":[
        "agency",
        "tourist"
    ],
    "wof:name":"European Connection",
    "wof:placetype":"venue"
},
  "geometry": {"coordinates":[-73.639984,40.788469],"type":"Point"}
}