{
  "type": "Feature",
  "properties": {
    "iso:country":"US",
    "sg:address":"339 Terryville Rd",
    "sg:city":"Port Jefferson Station",
    "sg:classifiers":[
        {
            "category":"Shopping",
            "subcategory":"Clothing, Apparel, & Fashions",
            "type":"Retail Goods"
        }
    ],
    "sg:phone":"+1 631 473 6363",
    "sg:postcode":"11776",
    "sg:province":"NY",
    "sg:tags":[
        "dressmaker",
        "miscellaneous",
        "store",
        "accessory"
    ],
    "wof:name":"Designs On You",
    "wof:placetype":"venue"
},
  "geometry": {"coordinates":[-73.05141500000001,40.912736],"type":"Point"}
}