{
  "type": "Feature",
  "properties": {
    "addr:full":"1887 Livingston St Lima NY 14485",
    "addr:housenumber":"1887",
    "addr:postcode":"14485",
    "addr:street":"Livingston St",
    "iso:country":"US",
    "sg:address":"1887 Livingston St",
    "sg:city":"Lima",
    "sg:classifiers":[
        {
            "category":"Retail",
            "subcategory":"Repair Shop",
            "type":"Services"
        }
    ],
    "sg:phone":"+1 585 624 1060",
    "sg:postcode":"14485",
    "sg:province":"NY",
    "sg:tags":[
        "upholsterer"
    ],
    "wof:name":"John H Bailey Custom Furniture",
    "wof:placetype":"venue"
},
  "geometry": {"coordinates":[-77.61509700000001,42.90481],"type":"Point"}
}