{
  "type": "Feature",
  "properties": {
    "iso:country":"US",
    "sg:address":"11 Hawthorne Rd",
    "sg:city":"Garden City",
    "sg:classifiers":[
        {
            "category":"Professional",
            "subcategory":"Management & Consulting",
            "type":"Services"
        }
    ],
    "sg:phone":"+1 516 437 0572",
    "sg:postcode":"11530",
    "sg:province":"NY",
    "sg:tags":[
        "promotion",
        "sales"
    ],
    "wof:name":"Promotion Department Inc",
    "wof:placetype":"venue"
},
  "geometry": {"coordinates":[-73.674494,40.729724],"type":"Point"}
}