{
  "type": "Feature",
  "properties": {
    "addr:full":"7951 Cooper Ave Glendale NY 11385",
    "addr:housenumber":"7951",
    "addr:postcode":"11385",
    "addr:street":"Cooper Ave",
    "iso:country":"US",
    "sg:address":"7951 Cooper Ave",
    "sg:city":"Glendale",
    "sg:classifiers":[
        {
            "category":"Real Estate",
            "subcategory":"Real Estate Services",
            "type":"Services"
        },
        {
            "category":"Real Estate",
            "subcategory":"Real Estate Agent",
            "type":"Services"
        }
    ],
    "sg:phone":"+1 718 894 0706",
    "sg:postcode":"11385",
    "sg:province":"NY",
    "sg:tags":[
        "buyer",
        "broker"
    ],
    "wof:name":"Glen Chem Realty Corp",
    "wof:placetype":"venue"
},
  "geometry": {"coordinates":[-73.869873,40.709351],"type":"Point"}
}