{
  "type": "Feature",
  "properties": {
    "addr:full":"844 Sheldon Ave Staten Island NY 10309",
    "addr:housenumber":"844",
    "addr:postcode":"10309",
    "addr:street":"Sheldon Ave",
    "iso:country":"US",
    "sg:address":"844 Sheldon Ave",
    "sg:city":"Staten Island",
    "sg:classifiers":[
        {
            "category":"Wholesale",
            "subcategory":"Groceries",
            "type":"Manufacturing & Wholesale Goods"
        }
    ],
    "sg:phone":"+1 718 967 8302",
    "sg:postcode":"10309",
    "sg:province":"NY",
    "sg:tags":[
        "food",
        "product"
    ],
    "wof:name":"Lappo's Inc",
    "wof:placetype":"venue"
},
  "geometry": {"coordinates":[-74.205833,40.538483],"type":"Point"}
}