{
  "type": "Feature",
  "properties": {
    "iso:country":"US",
    "sg:address":"8470 Ericson Dr",
    "sg:city":"Buffalo",
    "sg:classifiers":[
        {
            "category":"Shopping",
            "type":"Retail Goods"
        }
    ],
    "sg:phone":"+1 716 633 6917",
    "sg:postcode":"14221",
    "sg:province":"NY",
    "sg:tags":[
        "stamp",
        "collector",
        "for"
    ],
    "wof:name":"CJL Stamps & Things",
    "wof:placetype":"venue"
},
  "geometry": {"coordinates":[-78.67737,42.969223],"type":"Point"}
}