{
  "type": "Feature",
  "properties": {
    "addr:full":"5191 Broadway Bronx NY 10463",
    "addr:housenumber":"5191",
    "addr:postcode":"10463",
    "addr:street":"Broadway",
    "iso:country":"US",
    "sg:address":"5191 Broadway",
    "sg:city":"Bronx",
    "sg:classifiers":[
        {
            "category":"Farming",
            "subcategory":"Fish & Marine Products",
            "type":"Manufacturing & Wholesale Goods"
        }
    ],
    "sg:phone":"+1 718 295 4400",
    "sg:postcode":"10463",
    "sg:province":"NY",
    "sg:tags":[
        "computer",
        "related"
    ],
    "wof:name":"Solution Depot",
    "wof:placetype":"venue"
},
  "geometry": {"coordinates":[-73.906098,40.877066],"type":"Point"}
}