{
  "type": "Feature",
  "properties": {
    "addr:full":"2690 Park Ave Baldwin NY 11510",
    "addr:housenumber":"2690",
    "addr:postcode":"11510",
    "addr:street":"Park Ave",
    "iso:country":"US",
    "sg:address":"2690 Park Ave",
    "sg:city":"Baldwin",
    "sg:classifiers":[
        {
            "category":"Manufacturing",
            "subcategory":"Motor Vehicles & Parts",
            "type":"Manufacturing & Wholesale Goods"
        }
    ],
    "sg:phone":"+1   ",
    "sg:postcode":"11510",
    "sg:province":"NY",
    "sg:tags":[
        "mfg"
    ],
    "wof:name":"East-West Trading Inc",
    "wof:placetype":"venue"
},
  "geometry": {"coordinates":[-73.6104,40.644571],"type":"Point"}
}