{
  "type": "Feature",
  "properties": {
    "iso:country":"US",
    "sg:address":"4375 Lower Mountain Rd",
    "sg:city":"Lockport",
    "sg:classifiers":[
        {
            "category":"Freight",
            "type":"Transportation"
        }
    ],
    "sg:phone":"+1   ",
    "sg:postcode":"14094",
    "sg:province":"NY",
    "wof:name":"Cozy Carriage Company",
    "wof:placetype":"venue"
},
  "geometry": {"coordinates":[-78.788814,43.182571],"type":"Point"}
}