{
  "type": "Feature",
  "properties": {
    "iso:country":"US",
    "sg:address":"8 Thornberry Way",
    "sg:city":"Poughkeepsie",
    "sg:classifiers":[
        {
            "category":"Health Services",
            "subcategory":"Doctor",
            "type":"Services"
        }
    ],
    "sg:phone":"+1   ",
    "sg:postcode":"12603",
    "sg:province":"NY",
    "wof:name":"Inderjitsingh G Vig",
    "wof:placetype":"venue"
},
  "geometry": {"coordinates":[-73.915555,41.659462],"type":"Point"}
}