{
  "type": "Feature",
  "properties": {
    "iso:country":"US",
    "sg:address":"1 Landmark Pl",
    "sg:city":"Syracuse",
    "sg:classifiers":[
        {
            "category":"Personal",
            "subcategory":"Beauty Salon",
            "type":"Services"
        }
    ],
    "sg:phone":"+1 315 422 3194",
    "sg:postcode":"13202",
    "sg:province":"NY",
    "sg:tags":[
        "spa",
        "day"
    ],
    "sg:website":"www.josephscarriagehouse.com",
    "wof:name":"Joseph's At The Carriage House",
    "wof:placetype":"venue"
},
  "geometry": {"coordinates":[-76.145647,43.049063],"type":"Point"}
}