{
  "type": "Feature",
  "properties": {
    "iso:country":"US",
    "sg:address":"1758 1st Ave",
    "sg:city":"New York",
    "sg:classifiers":[
        {
            "category":"Restaurant",
            "type":"Food & Drink"
        }
    ],
    "sg:phone":"+1 917 492 1790",
    "sg:postcode":"10128",
    "sg:province":"NY",
    "sg:tags":[
        "american",
        "latin"
    ],
    "wof:name":"Abuelas Cozina",
    "wof:placetype":"venue"
},
  "geometry": {"coordinates":[-73.94676,40.780173],"type":"Point"}
}