{
  "type": "Feature",
  "properties": {
    "addr:full":"640 W Hoffman Ave Lindenhurst NY 11757",
    "addr:housenumber":"640",
    "addr:postcode":"11757",
    "addr:street":"W Hoffman Ave",
    "iso:country":"US",
    "sg:address":"640 W Hoffman Ave",
    "sg:city":"Lindenhurst",
    "sg:classifiers":[
        {
            "category":"Autos & Motor Vehicles",
            "subcategory":"Auto Supplies",
            "type":"Retail Goods"
        }
    ],
    "sg:phone":"+1 631 226 0580",
    "sg:postcode":"11757",
    "sg:province":"NY",
    "sg:tags":[
        "used",
        "parts"
    ],
    "wof:name":"A Plus Auto Salvage",
    "wof:placetype":"venue"
},
  "geometry": {"coordinates":[-73.387676,40.683073],"type":"Point"}
}