{
  "type": "Feature",
  "properties": {
    "addr:full":"244 Taxter Rd Irvington NY 10533",
    "addr:housenumber":"244",
    "addr:postcode":"ny 10533",
    "addr:street":"Taxter Rd",
    "iso:country":"US",
    "sg:address":"244 Taxter Rd",
    "sg:city":"Irvington",
    "sg:classifiers":[
        {
            "category":"Professional",
            "subcategory":"Accounting & Tax Preparation",
            "type":"Services"
        }
    ],
    "sg:phone":"+1 914 591 6891",
    "sg:postcode":"10533",
    "sg:province":"NY",
    "wof:name":"Hazdala & Ward",
    "wof:placetype":"venue"
},
  "geometry": {"coordinates":[-73.839327,41.048964],"type":"Point"}
}