{
  "type": "Feature",
  "properties": {
    "iso:country":"US",
    "sg:address":"1 Hill St",
    "sg:city":"Greenwich",
    "sg:classifiers":[
        {
            "category":"Real Estate",
            "subcategory":"Real Estate Agent",
            "type":"Services"
        }
    ],
    "sg:phone":"+1 518 692 9400",
    "sg:postcode":"12834",
    "sg:province":"NY",
    "wof:name":"Reynolds Real Estate",
    "wof:placetype":"venue"
},
  "geometry": {"coordinates":[-73.49932099999999,43.090213],"type":"Point"}
}