{
  "type": "Feature",
  "properties": {
    "addr:full":"264 3rd Ave Brooklyn NY 11215",
    "addr:housenumber":"264",
    "addr:postcode":"11215",
    "addr:street":"3Rd Ave",
    "iso:country":"US",
    "sg:address":"264 3rd Ave",
    "sg:city":"Brooklyn",
    "sg:classifiers":[
        {
            "category":"Retail",
            "subcategory":"Auto Repair",
            "type":"Services"
        }
    ],
    "sg:phone":"+1   ",
    "sg:postcode":"11215",
    "sg:province":"NY",
    "sg:tags":[
        "general"
    ],
    "wof:name":"Ridge Complete Auto Inc",
    "wof:placetype":"venue"
},
  "geometry": {"coordinates":[-73.985731,40.678124],"type":"Point"}
}