{
  "type": "Feature",
  "properties": {
    "addr:full":"13 Prospect Ave Gloversville NY 12078",
    "addr:housenumber":"13",
    "addr:postcode":"12078",
    "addr:street":"Prospect Ave",
    "iso:country":"US",
    "sg:address":"13 Prospect Ave",
    "sg:city":"Gloversville",
    "sg:classifiers":[
        {
            "category":"Retail",
            "subcategory":"Funeral Services",
            "type":"Services"
        }
    ],
    "sg:phone":"+1 518 725 3616",
    "sg:postcode":"12078",
    "sg:province":"NY",
    "sg:tags":[
        "director"
    ],
    "wof:name":"John W Finocan Funeral Home",
    "wof:placetype":"venue"
},
  "geometry": {"coordinates":[-74.342174,43.05298],"type":"Point"}
}