{
  "type": "Feature",
  "properties": {
    "iso:country":"US",
    "sg:address":"27 James St",
    "sg:city":"Gloversville",
    "sg:classifiers":[
        {
            "category":"Real Estate",
            "subcategory":"Real Estate Agent",
            "type":"Services"
        }
    ],
    "sg:phone":"+1 518 725 9677",
    "sg:postcode":"12078",
    "sg:province":"NY",
    "wof:name":"Crol A Reppenhgen Apprisal Svc",
    "wof:placetype":"venue"
},
  "geometry": {"coordinates":[-74.342889,43.058252],"type":"Point"}
}