{
  "type": "Feature",
  "properties": {
    "iso:country":"US",
    "sg:address":"3967 Canyonwood Ln",
    "sg:city":"Jamesville",
    "sg:classifiers":[
        {
            "category":"Health Services",
            "subcategory":"Doctor",
            "type":"Services"
        }
    ],
    "sg:phone":"+1 315 251 0401",
    "sg:postcode":"13078",
    "sg:province":"NY",
    "sg:tags":[
        "medical"
    ],
    "wof:name":"Orthopedics East PC",
    "wof:placetype":"venue"
},
  "geometry": {"coordinates":[-76.034995,42.965524],"type":"Point"}
}