{
  "type": "Feature",
  "properties": {
    "addr:full":"134 West Ave Hilton NY 14468",
    "addr:housenumber":"134",
    "addr:postcode":"14468",
    "addr:street":"West Ave",
    "iso:country":"US",
    "sg:address":"134 West Ave",
    "sg:city":"Hilton",
    "sg:classifiers":[
        {
            "category":"Building & Trades",
            "subcategory":"Construction",
            "type":"Services"
        }
    ],
    "sg:phone":"+1 585 663 2570",
    "sg:postcode":"14468",
    "sg:province":"NY",
    "sg:tags":[
        "residential",
        "commercial",
        "remodeling",
        "contractor"
    ],
    "wof:name":"Creative Renovations",
    "wof:placetype":"venue"
},
  "geometry": {"coordinates":[-77.79471700000001,43.288152],"type":"Point"}
}