{
  "type": "Feature",
  "properties": {
    "iso:country":"US",
    "sg:address":"465 Broadway",
    "sg:city":"Kingston",
    "sg:classifiers":[
        {
            "category":"Health Services",
            "subcategory":"Clinic",
            "type":"Services"
        },
        {
            "category":"Health Services",
            "subcategory":"Doctor",
            "type":"Services"
        }
    ],
    "sg:phone":"+1 845 340 0244",
    "sg:postcode":"12401",
    "sg:province":"NY",
    "sg:tags":[
        "physician",
        "surgeon",
        "specialty",
        "outpatient"
    ],
    "wof:name":"Behavioral Healthcare of N Y",
    "wof:placetype":"venue"
},
  "geometry": {"coordinates":[-73.99848,41.927324],"type":"Point"}
}