{
  "type": "Feature",
  "properties": {
    "addr:full":"317 Browns Rd Nesconset NY 11767",
    "addr:housenumber":"317",
    "addr:postcode":"11767",
    "addr:street":"Browns Rd",
    "iso:country":"US",
    "sg:address":"317 Browns Rd",
    "sg:city":"Nesconset",
    "sg:classifiers":[
        {
            "category":"Manufacturing",
            "subcategory":"Electronics",
            "type":"Manufacturing & Wholesale Goods"
        }
    ],
    "sg:phone":"+1   ",
    "sg:postcode":"11767",
    "sg:province":"NY",
    "sg:tags":[
        "semiconductor",
        "electronic",
        "component",
        "microwave",
        "mfg"
    ],
    "wof:name":"HP",
    "wof:placetype":"venue"
},
  "geometry": {"coordinates":[-73.13054700000001,40.848996],"type":"Point"}
}