{
  "type": "Feature",
  "properties": {
    "iso:country":"US",
    "sg:address":"865 E 138th St",
    "sg:city":"Bronx",
    "sg:classifiers":[
        {
            "category":"Manufacturing",
            "subcategory":"Printing",
            "type":"Manufacturing & Wholesale Goods"
        }
    ],
    "sg:phone":"+1 718 401 6003",
    "sg:postcode":"10454",
    "sg:province":"NY",
    "sg:tags":[
        "publisher"
    ],
    "sg:website":"www.pcfcorp.com",
    "wof:name":"Publishers Circulation",
    "wof:placetype":"venue"
},
  "geometry": {"coordinates":[-73.911599,40.804459],"type":"Point"}
}