{
  "type": "Feature",
  "properties": {
    "addr:full":"3609 Dunn Dr Warners NY 13164",
    "addr:housenumber":"3609",
    "addr:postcode":"13164",
    "addr:street":"Dunn Dr",
    "iso:country":"US",
    "sg:address":"3609 Dunn Dr",
    "sg:city":"Warners",
    "sg:classifiers":[
        {
            "category":"Building & Trades",
            "subcategory":"Construction",
            "type":"Services"
        }
    ],
    "sg:phone":"+1 315 708 0089",
    "sg:postcode":"13164",
    "sg:province":"NY",
    "sg:tags":[
        "house"
    ],
    "wof:name":"Burke & Burke Homes",
    "wof:placetype":"venue"
},
  "geometry": {"coordinates":[-76.268216,43.086199],"type":"Point"}
}