{
  "type": "Feature",
  "properties": {
    "addr:full":"400 Rose Feiss Boulevard Bronx NY 10454",
    "addr:housenumber":"400",
    "addr:postcode":"10454",
    "addr:street":"Rose Feiss Boulevard",
    "iso:country":"US",
    "sg:address":"400 Rose Feiss Boulevard",
    "sg:city":"Bronx",
    "sg:classifiers":[
        {
            "category":"Food & Beverages",
            "subcategory":"Liquor & Beverages",
            "type":"Retail Goods"
        }
    ],
    "sg:phone":"+1 718 292 9700",
    "sg:postcode":"10454",
    "sg:province":"NY",
    "sg:tags":[
        "beer",
        "spirit",
        "wine"
    ],
    "wof:name":"Manhattan Beer Distributors",
    "wof:placetype":"venue"
},
  "geometry": {"coordinates":[-73.905998,40.805255],"type":"Point"}
}