{
  "type": "Feature",
  "properties": {
    "iso:country":"US",
    "sg:address":"439 State St",
    "sg:city":"Schenectady",
    "sg:classifiers":[
        {
            "category":"Shopping",
            "subcategory":"News",
            "type":"Retail Goods"
        }
    ],
    "sg:phone":"+1   ",
    "sg:postcode":"12305",
    "sg:province":"NY",
    "wof:name":"Baums Newsroom",
    "wof:placetype":"venue"
},
  "geometry": {"coordinates":[-73.941104,42.81243],"type":"Point"}
}