{
  "type": "Feature",
  "properties": {
    "addr:full":"27 Brienna Ct Staten Island NY 10309",
    "addr:housenumber":"27",
    "addr:postcode":"10309",
    "addr:street":"Brienna Ct",
    "iso:country":"US",
    "sg:address":"27 Brienna Ct",
    "sg:city":"Staten Island",
    "sg:classifiers":[
        {
            "category":"Building & Trades",
            "subcategory":"Locksmith",
            "type":"Services"
        }
    ],
    "sg:phone":"+1 718 989 6400",
    "sg:postcode":"10309",
    "sg:province":"NY",
    "sg:tags":[
        "key"
    ],
    "wof:name":"A Best Twenty Four Hr Locksmtih",
    "wof:placetype":"venue"
},
  "geometry": {"coordinates":[-74.23884700000001,40.538431],"type":"Point"}
}