{
  "type": "Feature",
  "properties": {
    "addr:full":"2276 3rd Avenue New York NY 10035",
    "addr:housenumber":"2276",
    "addr:postcode":"10035",
    "addr:street":"3Rd Avenue",
    "iso:country":"US",
    "sg:address":"2276 3rd Avenue",
    "sg:city":"New York",
    "sg:classifiers":[
        {
            "category":"Organizations",
            "subcategory":"Non-profit Organization",
            "type":"Services"
        }
    ],
    "sg:phone":"+1 917 492 1019",
    "sg:postcode":"10035",
    "sg:province":"NY",
    "sg:tags":[
        "service/non-profit",
        "community"
    ],
    "wof:name":"Palladia",
    "wof:placetype":"venue"
},
  "geometry": {"coordinates":[-73.936252,40.802859],"type":"Point"}
}