{
  "type": "Feature",
  "properties": {
    "iso:country":"US",
    "sg:address":"55 Colonial Village Rd",
    "sg:city":"Rochester",
    "sg:classifiers":[
        {
            "category":"Building & Trades",
            "subcategory":"Landscaping Services",
            "type":"Services"
        }
    ],
    "sg:phone":"+1 585 586 6810",
    "sg:postcode":"14625",
    "sg:province":"NY",
    "sg:tags":[
        "landscape",
        "contractor"
    ],
    "wof:name":"Landt's Landscape Inc",
    "wof:placetype":"venue"
},
  "geometry": {"coordinates":[-77.518824,43.134964],"type":"Point"}
}