{
  "type": "Feature",
  "properties": {
    "iso:country":"US",
    "sg:address":"369 Washington Ave",
    "sg:city":"New Hyde Park",
    "sg:classifiers":[
        {
            "category":"Retail",
            "subcategory":"Repair Shop",
            "type":"Services"
        }
    ],
    "sg:phone":"+1 516 294 5790",
    "sg:postcode":"11040",
    "sg:province":"NY",
    "sg:tags":[
        "television"
    ],
    "wof:name":"Supervision T V",
    "wof:placetype":"venue"
},
  "geometry": {"coordinates":[-73.65719799999999,40.742937],"type":"Point"}
}