{
  "type": "Feature",
  "properties": {
    "addr:full":"315 Heathcote Rd Scarsdale NY 10583",
    "addr:housenumber":"315",
    "addr:postcode":"10583",
    "addr:street":"Heathcote Rd",
    "iso:country":"US",
    "sg:address":"315 Heathcote Rd",
    "sg:city":"Scarsdale",
    "sg:classifiers":[
        {
            "category":"Banks & Credit Unions",
            "subcategory":"Bank",
            "type":"Services"
        }
    ],
    "sg:phone":"+1 914 723 2261",
    "sg:postcode":"10583",
    "sg:province":"NY",
    "sg:tags":[
        "loan",
        "real estate"
    ],
    "wof:name":"Phillibert Financial Group",
    "wof:placetype":"venue"
},
  "geometry": {"coordinates":[-73.774253,40.983477],"type":"Point"}
}