{
  "type": "Feature",
  "properties": {
    "iso:country":"US",
    "sg:address":"43 Irondequoit Mall Dr",
    "sg:city":"Rochester",
    "sg:classifiers":[
        {
            "category":"Shopping",
            "subcategory":"Clothing, Apparel, & Fashions",
            "type":"Retail Goods"
        }
    ],
    "sg:phone":"+1   ",
    "sg:postcode":"14622",
    "sg:province":"NY",
    "wof:name":"Catherines",
    "wof:placetype":"venue"
},
  "geometry": {"coordinates":[-77.573317,43.199503],"type":"Point"}
}