{
  "type": "Feature",
  "properties": {
    "addr:full":"117 McKinley St Brentwood NY 11717",
    "addr:housenumber":"117",
    "addr:postcode":"11717",
    "addr:street":"Mckinley St",
    "iso:country":"US",
    "sg:address":"117 McKinley St",
    "sg:city":"Brentwood",
    "sg:classifiers":[
        {
            "category":"Shopping",
            "type":"Retail Goods"
        }
    ],
    "sg:phone":"+1   ",
    "sg:postcode":"11717",
    "sg:province":"NY",
    "sg:tags":[
        "merchandise"
    ],
    "wof:name":"Willies Creative Workshop",
    "wof:placetype":"venue"
},
  "geometry": {"coordinates":[-73.24882100000001,40.785119],"type":"Point"}
}