{
  "type": "Feature",
  "properties": {
    "iso:country":"US",
    "sg:address":"3157 Lake Rd",
    "sg:city":"Horseheads",
    "sg:classifiers":[
        {
            "category":"Autos & Motor Vehicles",
            "subcategory":"Automobile Sales",
            "type":"Retail Goods"
        },
        {
            "category":"Retail",
            "subcategory":"Auto Repair",
            "type":"Services"
        }
    ],
    "sg:phone":"+1 607 733 5711",
    "sg:postcode":"14845",
    "sg:province":"NY",
    "sg:tags":[
        "shop",
        "repairing",
        "used",
        "car",
        "sales",
        "general",
        "automotive"
    ],
    "wof:name":"Ed's Auto Sales & Garage",
    "wof:placetype":"venue"
},
  "geometry": {"coordinates":[-76.81487799999999,42.144097],"type":"Point"}
}