{
  "type": "Feature",
  "properties": {
    "iso:country":"US",
    "sg:address":"29 Agar St",
    "sg:city":"Yonkers",
    "sg:classifiers":[
        {
            "category":"Real Estate",
            "subcategory":"Real Estate Operator",
            "type":"Services"
        }
    ],
    "sg:phone":"+1 914 965 6000",
    "sg:postcode":"10701",
    "sg:province":"NY",
    "sg:tags":[
        "manager",
        "property",
        "commercial"
    ],
    "wof:name":"2301 Jerome Ave Realty Corp",
    "wof:placetype":"venue"
},
  "geometry": {"coordinates":[-73.875057,40.949003],"type":"Point"}
}