{
  "type": "Feature",
  "properties": {
    "iso:country":"US",
    "sg:address":"2114 Jericho Tpke",
    "sg:city":"New Hyde Park",
    "sg:classifiers":[
        {
            "category":"Professional",
            "type":"Services"
        },
        {
            "category":"Deli",
            "type":"Food & Drink"
        }
    ],
    "sg:phone":"+1 516 248 1994",
    "sg:postcode":"11040",
    "sg:province":"NY",
    "sg:tags":[
        "caterer"
    ],
    "wof:name":"Deli & Otherwise Inc",
    "wof:placetype":"venue"
},
  "geometry": {"coordinates":[-73.67440000000001,40.735401],"type":"Point"}
}