{
  "type": "Feature",
  "properties": {
    "addr:full":"114 West Ave Rochester NY 14611",
    "addr:housenumber":"114",
    "addr:postcode":"14611",
    "addr:street":"West Ave",
    "iso:country":"US",
    "sg:address":"114 West Ave",
    "sg:city":"Rochester",
    "sg:classifiers":[
        {
            "category":"Manufacturing",
            "subcategory":"Tools & Machinery",
            "type":"Manufacturing & Wholesale Goods"
        }
    ],
    "sg:phone":"+1 585 328 0480",
    "sg:postcode":"14611",
    "sg:province":"NY",
    "sg:tags":[
        "machine",
        "shop"
    ],
    "sg:website":"www.tekemachine.com",
    "wof:name":"TEKE Machine Corp",
    "wof:placetype":"venue"
},
  "geometry": {"coordinates":[-77.640704,43.15006],"type":"Point"}
}