{
  "type": "Feature",
  "properties": {
    "iso:country":"US",
    "sg:address":"38 E 57th St",
    "sg:city":"New York",
    "sg:classifiers":[
        {
            "category":"Shopping",
            "subcategory":"Clothing, Apparel, & Fashions",
            "type":"Retail Goods"
        }
    ],
    "sg:phone":"+1   ",
    "sg:postcode":"10022",
    "sg:province":"NY",
    "sg:tags":[
        "costume",
        "jewelry"
    ],
    "wof:name":"Lanciani",
    "wof:placetype":"venue"
},
  "geometry": {"coordinates":[-73.970961,40.76164],"type":"Point"}
}