{
  "type": "Feature",
  "properties": {
    "addr:full":"1576 Forest Ave Staten Island NY 10302",
    "addr:housenumber":"1576",
    "addr:postcode":"10302",
    "addr:street":"Forest Ave",
    "iso:country":"US",
    "sg:address":"1576 Forest Ave",
    "sg:city":"Staten Island",
    "sg:classifiers":[
        {
            "category":"Professional",
            "subcategory":"Lawyer & Legal Services",
            "type":"Services"
        }
    ],
    "sg:phone":"+1 718 447 1300",
    "sg:postcode":"10302",
    "sg:province":"NY",
    "wof:name":"Coven Mitchell S",
    "wof:placetype":"venue"
},
  "geometry": {"coordinates":[-74.14108,40.624342],"type":"Point"}
}