{
  "type": "Feature",
  "properties": {
    "addr:full":"3279 Westchester Avenue Bronx NY 10461",
    "addr:housenumber":"3279",
    "addr:postcode":"10461",
    "addr:street":"Westchester Avenue",
    "iso:country":"US",
    "sg:address":"3279 Westchester Avenue",
    "sg:city":"Bronx",
    "sg:classifiers":[
        {
            "category":"Retail",
            "subcategory":"Laundry & Dry Cleaning",
            "type":"Services"
        }
    ],
    "sg:phone":"+1 718 823 5707",
    "sg:postcode":"10461",
    "sg:province":"NY",
    "wof:name":"Crosby Cleaners & Furriers",
    "wof:placetype":"venue"
},
  "geometry": {"coordinates":[-73.827459,40.852845],"type":"Point"}
}