{
  "type": "Feature",
  "properties": {
    "addr:full":"118 Eldridge St Manhattan NY 10002",
    "addr:housenumber":"118",
    "addr:postcode":"10002",
    "addr:street":"Eldridge St",
    "iso:country":"US",
    "sg:address":"118 Eldridge St",
    "sg:city":"Manhattan",
    "sg:classifiers":[
        {
            "category":"Restaurant",
            "type":"Food & Drink"
        }
    ],
    "sg:postcode":"10002",
    "sg:province":"NY",
    "sg:tags":[
        "chinese"
    ],
    "wof:name":"Good Taste Fuzhon Cuisine",
    "wof:placetype":"venue"
},
  "geometry": {"coordinates":[-73.99180699999999,40.718454],"type":"Point"}
}