{
  "type": "Feature",
  "properties": {
    "iso:country":"US",
    "sg:address":"432 Albany Ave",
    "sg:city":"Kingston",
    "sg:classifiers":[
        {
            "category":"Real Estate",
            "subcategory":"Real Estate Services",
            "type":"Services"
        },
        {
            "category":"Real Estate",
            "subcategory":"Real Estate Agent",
            "type":"Services"
        }
    ],
    "sg:phone":"+1 845 339 7792",
    "sg:postcode":"12401",
    "sg:province":"NY",
    "sg:tags":[
        "buyer",
        "management",
        "broker"
    ],
    "wof:name":"Mirtash Real Estate",
    "wof:placetype":"venue"
},
  "geometry": {"coordinates":[-74.000771,41.940559],"type":"Point"}
}