{
  "type": "Feature",
  "properties": {
    "addr:full":"3340 Veterans Memorial Hwy Bohemia NY 11716",
    "addr:housenumber":"3340",
    "addr:postcode":"11716",
    "addr:street":"Veterans Memorial Hwy",
    "iso:country":"US",
    "sg:address":"3340 Veterans Memorial Hwy",
    "sg:city":"Bohemia",
    "sg:classifiers":[
        {
            "category":"Professional",
            "subcategory":"Lawyer & Legal Services",
            "type":"Services"
        }
    ],
    "sg:phone":"+1 631 738 9000",
    "sg:postcode":"11716",
    "sg:province":"NY",
    "wof:name":"Peter M Puleo PC",
    "wof:placetype":"venue"
},
  "geometry": {"coordinates":[-73.1271,40.787051],"type":"Point"}
}