{
  "type": "Feature",
  "properties": {
    "addr:full":"4818 5th Ave Brooklyn NY 11220",
    "addr:housenumber":"4818",
    "addr:postcode":"11220",
    "addr:street":"5Th Ave",
    "iso:country":"US",
    "sg:address":"4818 5th Ave",
    "sg:city":"Brooklyn",
    "sg:classifiers":[
        {
            "category":"Utilities",
            "subcategory":"Mobile Phone",
            "type":"Services"
        }
    ],
    "sg:phone":"+1 718 765 1017",
    "sg:postcode":"11220",
    "sg:province":"NY",
    "sg:tags":[
        "telephone",
        "cellular"
    ],
    "wof:name":"A A Wireless Of New York",
    "wof:placetype":"venue"
},
  "geometry": {"coordinates":[-74.009714,40.645815],"type":"Point"}
}