{
  "type": "Feature",
  "properties": {
    "addr:full":"40 Eastwood Ln Roslyn NY 11581",
    "addr:housenumber":"40",
    "addr:postcode":"11581",
    "addr:street":"Eastwood Ln",
    "iso:country":"US",
    "sg:address":"40 Eastwood Ln",
    "sg:city":"Roslyn",
    "sg:classifiers":[
        {
            "category":"Professional",
            "subcategory":"Management & Consulting",
            "type":"Services"
        }
    ],
    "sg:phone":"+1 516 621 1853",
    "sg:postcode":"11581",
    "sg:province":"NY",
    "sg:tags":[
        "international",
        "consultant"
    ],
    "wof:name":"Com Trad Inc",
    "wof:placetype":"venue"
},
  "geometry": {"coordinates":[-73.719572,40.658013],"type":"Point"}
}