{
  "type": "Feature",
  "properties": {
    "iso:country":"US",
    "sg:address":"11802 Rockaway Blvd",
    "sg:city":"South Ozone Park",
    "sg:classifiers":[
        {
            "category":"Food & Beverages",
            "subcategory":"Groceries & Convenience Stores",
            "type":"Retail Goods"
        }
    ],
    "sg:phone":"+1 718 845 1230",
    "sg:postcode":"11420",
    "sg:province":"NY",
    "wof:name":"Al Prince",
    "wof:placetype":"venue"
},
  "geometry": {"coordinates":[-73.820115,40.676101],"type":"Point"}
}