{
  "type": "Feature",
  "properties": {
    "iso:country":"US",
    "sg:address":"4006 13th Avenue",
    "sg:city":"Brooklyn",
    "sg:classifiers":[
        {
            "category":"Restaurant",
            "type":"Food & Drink"
        }
    ],
    "sg:phone":"+1 718 871 5920",
    "sg:postcode":"11218",
    "sg:province":"NY",
    "wof:name":"Gino's Pizzeria",
    "wof:placetype":"venue"
},
  "geometry": {"coordinates":[-73.987206,40.639924],"type":"Point"}
}