{
  "type": "Feature",
  "properties": {
    "addr:full":"4640 Main St Buffalo NY 14226",
    "addr:housenumber":"4640",
    "addr:postcode":"14226",
    "addr:street":"Main St",
    "iso:country":"US",
    "sg:address":"4640 Main St",
    "sg:city":"Buffalo",
    "sg:classifiers":[
        {
            "category":"Organizations",
            "subcategory":"Religious Organization",
            "type":"Services"
        }
    ],
    "sg:phone":"+1 716 839 1314",
    "sg:postcode":"14226",
    "sg:province":"NY",
    "sg:tags":[
        "church"
    ],
    "wof:name":"Ascension Lutheran Church",
    "wof:placetype":"venue"
},
  "geometry": {"coordinates":[-78.779298,42.962123],"type":"Point"}
}