{
  "type": "Feature",
  "properties": {
    "iso:country":"US",
    "sg:address":"265 Macedon Center Rd",
    "sg:city":"Fairport",
    "sg:classifiers":[
        {
            "category":"Autos & Motor Vehicles",
            "subcategory":"Fuel & Gas Station",
            "type":"Retail Goods"
        }
    ],
    "sg:phone":"+1   ",
    "sg:postcode":"14450",
    "sg:province":"NY",
    "sg:tags":[
        "station",
        "gasoline"
    ],
    "wof:name":"Stop-N-Go Foods",
    "wof:placetype":"venue"
},
  "geometry": {"coordinates":[-77.429378,43.099777],"type":"Point"}
}