{
  "type": "Feature",
  "properties": {
    "addr:full":"44 Donna Ln Commack NY 11725",
    "addr:housenumber":"44",
    "addr:postcode":"11725",
    "addr:street":"Donna Ln",
    "iso:country":"US",
    "sg:address":"44 Donna Ln",
    "sg:city":"Commack",
    "sg:classifiers":[
        {
            "category":"Professional",
            "type":"Services"
        }
    ],
    "sg:phone":"+1 631 864 4611",
    "sg:postcode":"11725",
    "sg:province":"NY",
    "sg:tags":[
        "establishment"
    ],
    "wof:name":"MKL Corp",
    "wof:placetype":"venue"
},
  "geometry": {"coordinates":[-73.283418,40.819282],"type":"Point"}
}