{
  "type": "Feature",
  "properties": {
    "iso:country":"US",
    "sg:address":"11 Timothy Ct",
    "sg:city":"Monsey",
    "sg:classifiers":[
        {
            "category":"Shopping",
            "subcategory":"Gifts & Souvenirs",
            "type":"Retail Goods"
        }
    ],
    "sg:phone":"+1   ",
    "sg:postcode":"10952",
    "sg:province":"NY",
    "wof:name":"Rozs Giftware",
    "wof:placetype":"venue"
},
  "geometry": {"coordinates":[-74.069254,41.131537],"type":"Point"}
}