{
  "type": "Feature",
  "properties": {
    "addr:full":"12668 Willets Point Boulevard Corona NY 11368",
    "addr:housenumber":"12668",
    "addr:postcode":"11368",
    "addr:street":"Willets Point Boulevard",
    "iso:country":"US",
    "sg:address":"12668 Willets Point Boulevard",
    "sg:city":"Corona",
    "sg:classifiers":[
        {
            "category":"Retail",
            "subcategory":"Auto Repair",
            "type":"Services"
        }
    ],
    "sg:phone":"+1 718 457 1310",
    "sg:postcode":"11368",
    "sg:province":"NY",
    "wof:name":"Julio's Auto Repair",
    "wof:placetype":"venue"
},
  "geometry": {"coordinates":[-73.842359,40.757341],"type":"Point"}
}