{
  "type": "Feature",
  "properties": {
    "iso:country":"US",
    "sg:address":"2045 Hoover Rd",
    "sg:city":"Schenectady",
    "sg:classifiers":[
        {
            "category":"Building & Trades",
            "subcategory":"Construction",
            "type":"Services"
        }
    ],
    "sg:phone":"+1 518 346 1603",
    "sg:postcode":"12309",
    "sg:province":"NY",
    "sg:tags":[
        "house"
    ],
    "wof:name":"Face Construction",
    "wof:placetype":"venue"
},
  "geometry": {"coordinates":[-73.895426,42.8232],"type":"Point"}
}