{
  "type": "Feature",
  "properties": {
    "iso:country":"US",
    "sg:address":"1 Beekman St",
    "sg:city":"New York",
    "sg:classifiers":[
        {
            "category":"Utilities",
            "subcategory":"Telephone",
            "type":"Services"
        }
    ],
    "sg:phone":"+1   ",
    "sg:postcode":"10038",
    "sg:province":"NY",
    "sg:tags":[
        "communications"
    ],
    "wof:name":"Joshua Shaub",
    "wof:placetype":"venue"
},
  "geometry": {"coordinates":[-74.00676799999999,40.711501],"type":"Point"}
}