{
  "type": "Feature",
  "properties": {
    "addr:full":"127 Beverly Rd Brooklyn NY 11218",
    "addr:housenumber":"127",
    "addr:postcode":"11218",
    "addr:street":"Beverly Rd",
    "iso:country":"US",
    "sg:address":"127 Beverly Rd",
    "sg:city":"Brooklyn",
    "sg:classifiers":[
        {
            "category":"Building & Trades",
            "subcategory":"Construction",
            "type":"Services"
        }
    ],
    "sg:phone":"+1 718 972 3355",
    "sg:postcode":"11218",
    "sg:province":"NY",
    "sg:tags":[
        "general",
        "contractor"
    ],
    "wof:name":"Construction Park Ave",
    "wof:placetype":"venue"
},
  "geometry": {"coordinates":[-73.978387,40.642953],"type":"Point"}
}