{
  "type": "Feature",
  "properties": {
    "addr:full":"3 Alan B Shepard Jr Pl Yonkers NY 10705",
    "addr:housenumber":"3",
    "addr:postcode":"10705",
    "addr:street":"Alan B Shepard Jr Pl",
    "iso:country":"US",
    "sg:address":"3 Alan B Shepard Jr Pl",
    "sg:city":"Yonkers",
    "sg:classifiers":[
        {
            "category":"Building & Trades",
            "subcategory":"Electrical",
            "type":"Services"
        }
    ],
    "sg:phone":"+1 914 375 5555",
    "sg:postcode":"10705",
    "sg:province":"NY",
    "sg:tags":[
        "electric",
        "contractor"
    ],
    "wof:name":"Medco Electric Inc",
    "wof:placetype":"venue"
},
  "geometry": {"coordinates":[-73.883695,40.913612],"type":"Point"}
}