{
  "type": "Feature",
  "properties": {
    "iso:country":"US",
    "sg:address":"74 Riverdale Ave",
    "sg:city":"Buffalo",
    "sg:classifiers":[
        {
            "category":"Organizations",
            "subcategory":"Religious Organization",
            "type":"Services"
        }
    ],
    "sg:phone":"+1 716 877 8611",
    "sg:postcode":"14207",
    "sg:province":"NY",
    "sg:tags":[
        "church"
    ],
    "wof:name":"Calvary Chapel",
    "wof:placetype":"venue"
},
  "geometry": {"coordinates":[-78.911196,42.96065],"type":"Point"}
}