{
  "type": "Feature",
  "properties": {
    "addr:full":"880 Hawkins Ave Lake Grove NY 11755",
    "addr:housenumber":"880",
    "addr:postcode":"11755",
    "addr:street":"Hawkins Ave",
    "iso:country":"US",
    "sg:address":"880 Hawkins Ave",
    "sg:city":"Lake Grove",
    "sg:classifiers":[
        {
            "category":"Professional",
            "subcategory":"Computer Services",
            "type":"Services"
        }
    ],
    "sg:phone":"+1 212 888 8324",
    "sg:postcode":"11755",
    "sg:province":"NY",
    "sg:tags":[
        "repair"
    ],
    "wof:name":"Homebase Technologies",
    "wof:placetype":"venue"
},
  "geometry": {"coordinates":[-73.11344699999999,40.842777],"type":"Point"}
}