{
  "type": "Feature",
  "properties": {
    "iso:country":"US",
    "sg:address":"135 E 57th St",
    "sg:city":"New York",
    "sg:classifiers":[
        {
            "category":"Banks & Credit Unions",
            "subcategory":"Investment Brokerage",
            "type":"Services"
        }
    ],
    "sg:phone":"+1 212 826 3509",
    "sg:postcode":"10022",
    "sg:province":"NY",
    "sg:tags":[
        "advisory",
        "financial"
    ],
    "wof:name":"Momentum Securities",
    "wof:placetype":"venue"
},
  "geometry": {"coordinates":[-73.970253,40.761637],"type":"Point"}
}