{
  "type": "Feature",
  "properties": {
    "addr:full":"341 Bowery New York NY 10003",
    "addr:housenumber":"341",
    "addr:postcode":"10003",
    "addr:street":"Bowery",
    "iso:country":"US",
    "sg:address":"341 Bowery",
    "sg:city":"New York",
    "sg:classifiers":[
        {
            "category":"Autos & Motor Vehicles",
            "subcategory":"Auto Supplies",
            "type":"Retail Goods"
        }
    ],
    "sg:phone":"+1 212 871 0407",
    "sg:postcode":"10003",
    "sg:province":"NY",
    "sg:tags":[
        "tire"
    ],
    "wof:name":"Bowery Service",
    "wof:placetype":"venue"
},
  "geometry": {"coordinates":[-73.991997,40.7262],"type":"Point"}
}