{
  "type": "Feature",
  "properties": {
    "addr:full":"299 Broadway Ste 1405 New York NY 10007",
    "addr:housenumber":"299",
    "addr:postcode":"10007",
    "addr:street":"Broadway Ste 1405",
    "iso:country":"US",
    "sg:address":"299 Broadway Ste 1405",
    "sg:city":"New York",
    "sg:classifiers":[
        {
            "category":"Professional",
            "subcategory":"Lawyer & Legal Services",
            "type":"Services"
        }
    ],
    "sg:phone":"+1 718 596 1100",
    "sg:postcode":"10007",
    "sg:province":"NY",
    "wof:name":"Greenberg Laurence P esq",
    "wof:placetype":"venue"
},
  "geometry": {"coordinates":[-74.005532,40.715167],"type":"Point"}
}