{
  "type": "Feature",
  "properties": {
    "iso:country":"US",
    "sg:address":"173 Stock Rd",
    "sg:city":"Hannibal",
    "sg:classifiers":[
        {
            "category":"Autos & Motor Vehicles",
            "subcategory":"Automobile Sales",
            "type":"Retail Goods"
        }
    ],
    "sg:phone":"+1   ",
    "sg:postcode":"13074",
    "sg:province":"NY",
    "sg:tags":[
        "used"
    ],
    "wof:name":"First Class Auto Sales",
    "wof:placetype":"venue"
},
  "geometry": {"coordinates":[-76.542841,43.344941],"type":"Point"}
}