{
  "type": "Feature",
  "properties": {
    "iso:country":"US",
    "sg:address":"69 6th St",
    "sg:city":"Pelham",
    "sg:classifiers":[
        {
            "category":"Recreation",
            "type":"Entertainment"
        }
    ],
    "sg:phone":"+1 914 738 0440",
    "sg:postcode":"10803",
    "sg:province":"NY",
    "sg:tags":[
        "martial",
        "arts",
        "instruction"
    ],
    "wof:name":"Pelham Karate Ctr",
    "wof:placetype":"venue"
},
  "geometry": {"coordinates":[-73.806772,40.919123],"type":"Point"}
}