{
  "type": "Feature",
  "properties": {
    "addr:full":"245 Bassett Rd Buffalo NY 14221",
    "addr:housenumber":"245",
    "addr:postcode":"14221",
    "addr:street":"Bassett Rd",
    "iso:country":"US",
    "sg:address":"245 Bassett Rd",
    "sg:city":"Buffalo",
    "sg:classifiers":[
        {
            "category":"Real Estate",
            "subcategory":"Real Estate Operator",
            "type":"Services"
        }
    ],
    "sg:phone":"+1 716 688 4011",
    "sg:postcode":"14221",
    "sg:province":"NY",
    "sg:tags":[
        "living",
        "assisted",
        "facility"
    ],
    "wof:name":"Emeritus Corporation",
    "wof:placetype":"venue"
},
  "geometry": {"coordinates":[-78.729508,42.996739],"type":"Point"}
}