{
  "type": "Feature",
  "properties": {
    "addr:full":"176 Woodward Ave Flushing NY 11385",
    "addr:housenumber":"176",
    "addr:postcode":"11385",
    "addr:street":"Woodward Ave",
    "iso:country":"US",
    "sg:address":"176 Woodward Ave",
    "sg:city":"Flushing",
    "sg:classifiers":[
        {
            "category":"Retail",
            "subcategory":"Auto Repair",
            "type":"Services"
        }
    ],
    "sg:phone":"+1 718 497 9700",
    "sg:postcode":"11385",
    "sg:province":"NY",
    "sg:tags":[
        "wrecker"
    ],
    "wof:name":"Impressive Auto Collision",
    "wof:placetype":"venue"
},
  "geometry": {"coordinates":[-73.916748,40.711402],"type":"Point"}
}