{
  "type": "Feature",
  "properties": {
    "iso:country":"US",
    "sg:address":"453 Broadway",
    "sg:city":"Saratoga Springs",
    "sg:classifiers":[
        {
            "category":"Coffee & Tea",
            "type":"Food & Drink"
        },
        {
            "category":"Bagels",
            "type":"Food & Drink"
        }
    ],
    "sg:menulink":"http://www.allmenus.com/ny/saratoga-springs/114689-brueggers/menu/",
    "sg:phone":"+1 518 584 4372",
    "sg:postcode":"12866",
    "sg:province":"NY",
    "sg:tags":[
        "wrap",
        "soup",
        "american",
        "sandwich",
        "salad"
    ],
    "wof:name":"Bruegger's",
    "wof:placetype":"venue"
},
  "geometry": {"coordinates":[-73.78558,43.082813],"type":"Point"}
}