{
  "type": "Feature",
  "properties": {
    "addr:full":"146 W 29th St New York NY 10001",
    "addr:housenumber":"146",
    "addr:postcode":"10001",
    "addr:street":"W 29Th St",
    "iso:country":"US",
    "sg:address":"146 W 29th St",
    "sg:city":"New York",
    "sg:classifiers":[
        {
            "category":"Travel",
            "subcategory":"Travel Agent",
            "type":"Entertainment"
        }
    ],
    "sg:phone":"+1 212 239 0727",
    "sg:postcode":"10001",
    "sg:province":"NY",
    "sg:tags":[
        "agency",
        "bureau"
    ],
    "wof:name":"Cashmire WORLD Travel",
    "wof:placetype":"venue"
},
  "geometry": {"coordinates":[-73.991935,40.747228],"type":"Point"}
}