{
  "type": "Feature",
  "properties": {
    "addr:full":"1066 Westminster Ave Dix Hills NY 11746",
    "addr:housenumber":"1066",
    "addr:postcode":"11746",
    "addr:street":"Westminster Ave",
    "iso:country":"US",
    "sg:address":"1066 Westminster Ave",
    "sg:city":"Dix Hills",
    "sg:classifiers":[
        {
            "category":"Professional",
            "subcategory":"Business Services",
            "type":"Services"
        }
    ],
    "sg:phone":"+1 516 625 1280",
    "sg:postcode":"11746",
    "sg:province":"NY",
    "sg:tags":[
        "broker"
    ],
    "wof:name":"Prime Business Exchange Inc",
    "wof:placetype":"venue"
},
  "geometry": {"coordinates":[-73.335311,40.788909],"type":"Point"}
}