{
  "type": "Feature",
  "properties": {
    "addr:full":"1605 Pelham Pkwy N Bronx NY 10469",
    "addr:housenumber":"1605",
    "addr:postcode":"10469",
    "addr:street":"Pelham Pkwy N",
    "iso:country":"US",
    "sg:address":"1605 Pelham Pkwy N",
    "sg:city":"Bronx",
    "sg:classifiers":[
        {
            "category":"Arts & Performance",
            "subcategory":"Arts Center",
            "type":"Entertainment"
        },
        {
            "category":"Restaurant",
            "type":"Food & Drink"
        }
    ],
    "sg:postcode":"10469",
    "sg:province":"NY",
    "sg:tags":[
        "flavor",
        "performing",
        "local"
    ],
    "sg:website":"newyorkchristmashouse.com",
    "wof:name":"Garabedian House",
    "wof:placetype":"venue"
},
  "geometry": {"coordinates":[-73.839856,40.857781],"type":"Point"}
}