{
  "type": "Feature",
  "properties": {
    "iso:country":"US",
    "sg:address":"134 Cayuga Creek Rd",
    "sg:city":"Alden",
    "sg:classifiers":[
        {
            "category":"Home & Garden",
            "subcategory":"Carpets & Floor Coverings",
            "type":"Retail Goods"
        }
    ],
    "sg:phone":"+1 716 685 6666",
    "sg:postcode":"14004",
    "sg:province":"NY",
    "sg:tags":[
        "dealer",
        "rug"
    ],
    "wof:name":"Frontier Floors",
    "wof:placetype":"venue"
},
  "geometry": {"coordinates":[-78.518975,42.878748],"type":"Point"}
}