{
  "type": "Feature",
  "properties": {
    "addr:full":"217 E 7th St Brooklyn NY 11218",
    "addr:housenumber":"217",
    "addr:postcode":"11218",
    "addr:street":"E 7Th St",
    "iso:country":"US",
    "sg:address":"217 E 7th St",
    "sg:city":"Brooklyn",
    "sg:classifiers":[
        {
            "category":"Shopping",
            "subcategory":"Jewelry",
            "type":"Retail Goods"
        }
    ],
    "sg:phone":"+1 718 871 4276",
    "sg:postcode":"11218",
    "sg:province":"NY",
    "sg:tags":[
        "platinum",
        "silver",
        "gold"
    ],
    "wof:name":"Silver Services Co",
    "wof:placetype":"venue"
},
  "geometry": {"coordinates":[-73.97304,40.645557],"type":"Point"}
}