{
  "type": "Feature",
  "properties": {
    "addr:full":"72 Manhattan Ave Brooklyn NY 11206",
    "addr:housenumber":"72",
    "addr:postcode":"11206",
    "addr:street":"Manhattan Ave",
    "iso:country":"US",
    "sg:address":"72 Manhattan Ave",
    "sg:city":"Brooklyn",
    "sg:classifiers":[
        {
            "category":"Professional",
            "type":"Services"
        }
    ],
    "sg:phone":"+1 718 388 1180",
    "sg:postcode":"11206",
    "sg:province":"NY",
    "sg:tags":[
        "establishment"
    ],
    "wof:name":"Crypt Records",
    "wof:placetype":"venue"
},
  "geometry": {"coordinates":[-73.94443699999999,40.704584],"type":"Point"}
}