{
  "type": "Feature",
  "properties": {
    "iso:country":"US",
    "sg:address":"91 Gibson St",
    "sg:city":"Canandaigua",
    "sg:classifiers":[
        {
            "category":"Organizations",
            "subcategory":"Religious Organization",
            "type":"Services"
        }
    ],
    "sg:phone":"+1 585 473 0220",
    "sg:postcode":"14424",
    "sg:province":"NY",
    "sg:tags":[
        "church"
    ],
    "wof:name":"Rochester Mennonite Fellowship",
    "wof:placetype":"venue"
},
  "geometry": {"coordinates":[-77.279667,42.891595],"type":"Point"}
}