{
  "type": "Feature",
  "properties": {
    "addr:full":"1927 Holland Ave Bronx NY 10462",
    "addr:housenumber":"1927",
    "addr:postcode":"10462",
    "addr:street":"Holland Ave",
    "iso:country":"US",
    "sg:address":"1927 Holland Ave",
    "sg:city":"Bronx",
    "sg:classifiers":[
        {
            "category":"Building & Trades",
            "subcategory":"Cleaning & Sanitation",
            "type":"Services"
        }
    ],
    "sg:phone":"+1 212 518 2617",
    "sg:postcode":"10462",
    "sg:province":"NY",
    "sg:website":"www.officecleaningnyc.info",
    "wof:name":"AAA Office Cleaning",
    "wof:placetype":"venue"
},
  "geometry": {"coordinates":[-73.865492,40.848716],"type":"Point"}
}