{
  "type": "Feature",
  "properties": {
    "addr:full":"57 Stephenson Blvd New Rochelle NY 10801",
    "addr:housenumber":"57",
    "addr:postcode":"10801",
    "addr:street":"Stephenson Blvd",
    "iso:country":"US",
    "sg:address":"57 Stephenson Blvd",
    "sg:city":"New Rochelle",
    "sg:classifiers":[
        {
            "category":"Building & Trades",
            "subcategory":"Construction",
            "type":"Services"
        }
    ],
    "sg:phone":"+1 914 637 0686",
    "sg:postcode":"10801",
    "sg:province":"NY",
    "sg:tags":[
        "house"
    ],
    "wof:name":"Double Diamond Inc",
    "wof:placetype":"venue"
},
  "geometry": {"coordinates":[-73.773117,40.916404],"type":"Point"}
}