{
  "type": "Feature",
  "properties": {
    "addr:full":"33 Nassau Ave Brooklyn NY 11222",
    "addr:housenumber":"33",
    "addr:postcode":"11222",
    "addr:street":"Nassau Ave",
    "iso:country":"US",
    "sg:address":"33 Nassau Ave",
    "sg:city":"Brooklyn",
    "sg:classifiers":[
        {
            "category":"Recreation",
            "subcategory":"Playground",
            "type":"Entertainment"
        }
    ],
    "sg:phone":"+1 718 387 2071",
    "sg:postcode":"11222",
    "sg:province":"NY",
    "sg:website":"www.playspacenyc.com",
    "wof:name":"Play",
    "wof:placetype":"venue"
},
  "geometry": {"coordinates":[-73.952978,40.723132],"type":"Point"}
}