{
  "type": "Feature",
  "properties": {
    "iso:country":"US",
    "sg:address":"2857 Broadway",
    "sg:city":"Manhattan",
    "sg:classifiers":[
        {
            "category":"Restaurant",
            "type":"Food & Drink"
        }
    ],
    "sg:phone":"+1 212 222 6464",
    "sg:postcode":"10025",
    "sg:province":"NY",
    "sg:tags":[
        "vegetarian"
    ],
    "sg:website":"www.maozusa.com",
    "wof:name":"Maoz Vegetarian",
    "wof:placetype":"venue"
},
  "geometry": {"coordinates":[-73.966337,40.804865],"type":"Point"}
}