{
  "type": "Feature",
  "properties": {
    "addr:full":"Dental Arts 2102 Bay Ridge Parkway Brooklyn NY 11204",
    "addr:housenumber":"2102",
    "addr:postcode":"11204",
    "addr:street":"Bay Ridge Parkway",
    "iso:country":"US",
    "sg:address":"Dental Arts 2102 Bay Ridge Parkway",
    "sg:city":"Brooklyn",
    "sg:classifiers":[
        {
            "category":"Health Services",
            "subcategory":"Dentist",
            "type":"Services"
        }
    ],
    "sg:phone":"+1 718 259 3828",
    "sg:postcode":"11204",
    "sg:province":"NY",
    "wof:name":"Steve Slobodski, DDS",
    "wof:placetype":"venue"
},
  "geometry": {"coordinates":[-73.989493,40.609446],"type":"Point"}
}