{
  "type": "Feature",
  "properties": {
    "addr:full":"44 Douglaston Pkwy Little Neck NY 11363",
    "addr:housenumber":"44",
    "addr:postcode":"11363",
    "addr:street":"Douglaston Pkwy",
    "iso:country":"US",
    "sg:address":"44 Douglaston Pkwy",
    "sg:city":"Little Neck",
    "sg:classifiers":[
        {
            "category":"Building & Trades",
            "subcategory":"Construction",
            "type":"Services"
        }
    ],
    "sg:phone":"+1 718 428 4800",
    "sg:postcode":"11363",
    "sg:province":"NY",
    "sg:tags":[
        "general"
    ],
    "wof:name":"Future Evolution",
    "wof:placetype":"venue"
},
  "geometry": {"coordinates":[-73.74579900000001,40.766564],"type":"Point"}
}