{
  "type": "Feature",
  "properties": {
    "addr:full":"152 Jericho Tpke Huntington Sta NY 11746",
    "addr:housenumber":"152",
    "addr:postcode":"11746",
    "addr:street":"Jericho Tpke",
    "iso:country":"US",
    "sg:address":"152 Jericho Tpke",
    "sg:city":"Huntington Sta",
    "sg:classifiers":[
        {
            "category":"Mining & Drilling",
            "type":"Manufacturing & Wholesale Goods"
        }
    ],
    "sg:phone":"+1 631 271 7989",
    "sg:postcode":"11746",
    "sg:province":"NY",
    "sg:tags":[
        "stone"
    ],
    "wof:name":"Grandera Technology Inc",
    "wof:placetype":"venue"
},
  "geometry": {"coordinates":[-73.402508,40.828137],"type":"Point"}
}