{
  "type": "Feature",
  "properties": {
    "addr:full":"50 Meadow Glen Rd Northport NY 11768",
    "addr:housenumber":"50",
    "addr:postcode":"11768",
    "addr:street":"Meadow Glen Rd",
    "iso:country":"US",
    "sg:address":"50 Meadow Glen Rd",
    "sg:city":"Northport",
    "sg:classifiers":[
        {
            "category":"Organizations",
            "subcategory":"Community Association",
            "type":"Services"
        }
    ],
    "sg:phone":"+1 631 269 2500",
    "sg:postcode":"11768",
    "sg:province":"NY",
    "sg:tags":[
        "support",
        "business"
    ],
    "wof:name":"Corporate Advantage Group",
    "wof:placetype":"venue"
},
  "geometry": {"coordinates":[-73.278767,40.894315],"type":"Point"}
}