{
  "type": "Feature",
  "properties": {
    "iso:country":"US",
    "sg:address":"1600 College Ave",
    "sg:city":"Elmira",
    "sg:classifiers":[
        {
            "category":"Professional",
            "subcategory":"Employment Agencies",
            "type":"Services"
        }
    ],
    "sg:phone":"+1 607 215 7105",
    "sg:postcode":"14901",
    "sg:province":"NY",
    "sg:tags":[
        "temporary"
    ],
    "sg:website":"http://national.citysearch.com/profile/external/7816785/elmira_ny/manpower_professional.html?publisher=yellowpages&reference_id=1&placement=ypwebsitemip",
    "wof:name":"Manpower Professional",
    "wof:placetype":"venue"
},
  "geometry": {"coordinates":[-76.822225,42.116386],"type":"Point"}
}