{
  "type": "Feature",
  "properties": {
    "addr:full":"2400 Johnson Ave Bronx NY 10463",
    "addr:housenumber":"2400",
    "addr:postcode":"10463",
    "addr:street":"Johnson Ave",
    "iso:country":"US",
    "sg:address":"2400 Johnson Ave",
    "sg:city":"Bronx",
    "sg:classifiers":[
        {
            "category":"Real Estate",
            "subcategory":"Real Estate Agent",
            "type":"Services"
        }
    ],
    "sg:phone":"+1 718 796 7024",
    "sg:postcode":"10463",
    "sg:province":"NY",
    "wof:name":"Francine Gladstone Realtor",
    "wof:placetype":"venue"
},
  "geometry": {"coordinates":[-73.92004900000001,40.878807],"type":"Point"}
}