{
  "type": "Feature",
  "properties": {
    "addr:full":"133 E 29th St New York NY 10016",
    "addr:housenumber":"133",
    "addr:postcode":"10016",
    "addr:street":"E 29Th St",
    "iso:country":"US",
    "sg:address":"133 E 29th St",
    "sg:city":"New York",
    "sg:classifiers":[
        {
            "category":"Restaurant",
            "type":"Food & Drink"
        }
    ],
    "sg:phone":"+1 212 679 6571",
    "sg:postcode":"10016",
    "sg:province":"NY",
    "sg:tags":[
        "caterer"
    ],
    "wof:name":"Grammercy Park Caterers",
    "wof:placetype":"venue"
},
  "geometry": {"coordinates":[-73.980442,40.742691],"type":"Point"}
}