{
  "type": "Feature",
  "properties": {
    "iso:country":"US",
    "sg:address":"63 Flushing Avenue",
    "sg:city":"Brooklyn",
    "sg:classifiers":[
        {
            "category":"Shopping",
            "subcategory":"Stationery & Office Supplies",
            "type":"Retail Goods"
        }
    ],
    "sg:phone":"+1 718 858 8866",
    "sg:postcode":"11205",
    "sg:province":"NY",
    "sg:tags":[
        "equipment"
    ],
    "wof:name":"Pinsel Unlimited",
    "wof:placetype":"venue"
},
  "geometry": {"coordinates":[-73.975037,40.698124],"type":"Point"}
}