{
  "type": "Feature",
  "properties": {
    "addr:full":"8000 Utopia Pkwy Jamaica NY 11432",
    "addr:housenumber":"8000",
    "addr:postcode":"11432",
    "addr:street":"Utopia Pkwy",
    "iso:country":"US",
    "sg:address":"8000 Utopia Pkwy",
    "sg:city":"Jamaica",
    "sg:classifiers":[
        {
            "category":"Restaurant",
            "type":"Food & Drink"
        }
    ],
    "sg:menulink":"http://www.allmenus.com/ny/queens/115974-quiznos-sub/menu/",
    "sg:phone":"+1 718 990 1535",
    "sg:postcode":"11432",
    "sg:province":"NY",
    "sg:tags":[
        "wrap",
        "american",
        "sandwich"
    ],
    "wof:name":"Quiznos Sub",
    "wof:placetype":"venue"
},
  "geometry": {"coordinates":[-73.791764,40.725697],"type":"Point"}
}