{
  "type": "Feature",
  "properties": {
    "addr:full":"1500 Grant Blvd Syracuse NY 13208",
    "addr:housenumber":"1500",
    "addr:postcode":"13208",
    "addr:street":"Grant Blvd",
    "iso:country":"US",
    "sg:address":"1500 Grant Blvd",
    "sg:city":"Syracuse",
    "sg:classifiers":[
        {
            "category":"Health Services",
            "subcategory":"Doctor",
            "type":"Services"
        }
    ],
    "sg:phone":"+1 315 472 3414",
    "sg:postcode":"13208",
    "sg:province":"NY",
    "sg:tags":[
        "dentist"
    ],
    "wof:name":"Grant Boulevard Dental",
    "wof:placetype":"venue"
},
  "geometry": {"coordinates":[-76.137896,43.07233],"type":"Point"}
}