{
  "type": "Feature",
  "properties": {
    "iso:country":"US",
    "sg:address":"261 Lockwood Rd",
    "sg:city":"Craryville",
    "sg:classifiers":[
        {
            "category":"Real Estate",
            "subcategory":"Architect",
            "type":"Services"
        }
    ],
    "sg:phone":"+1 518 672 6664",
    "sg:postcode":"12521",
    "sg:province":"NY",
    "sg:tags":[
        "architects'",
        "specification",
        "construction",
        "builders'",
        "architectural"
    ],
    "wof:name":"Gatter Architects",
    "wof:placetype":"venue"
},
  "geometry": {"coordinates":[-73.614701,42.19564],"type":"Point"}
}