{
  "type": "Feature",
  "properties": {
    "iso:country":"US",
    "sg:address":"145 Overlook Dr",
    "sg:city":"Mastic",
    "sg:classifiers":[
        {
            "category":"Shopping",
            "subcategory":"Tobacco",
            "type":"Retail Goods"
        }
    ],
    "sg:phone":"+1   ",
    "sg:postcode":"11950",
    "sg:province":"NY",
    "sg:tags":[
        "product"
    ],
    "wof:name":"Poosepatuck Smoke Signals",
    "wof:placetype":"venue"
},
  "geometry": {"coordinates":[-72.83046299999999,40.791478],"type":"Point"}
}