{
  "type": "Feature",
  "properties": {
    "iso:country":"US",
    "sg:address":"5 Mohonk Ave",
    "sg:city":"New Paltz",
    "sg:classifiers":[
        {
            "category":"Health Services",
            "subcategory":"Chiropractor",
            "type":"Services"
        }
    ],
    "sg:phone":"+1 845 255 3175",
    "sg:postcode":"12561",
    "sg:province":"NY",
    "wof:name":"Well Within Chiroractic",
    "wof:placetype":"venue"
},
  "geometry": {"coordinates":[-74.089011,41.745418],"type":"Point"}
}