{
  "type": "Feature",
  "properties": {
    "addr:full":"6 Roberts Rd Monsey NY 10952",
    "addr:housenumber":"6",
    "addr:postcode":"10952",
    "addr:street":"Roberts Rd",
    "iso:country":"US",
    "sg:address":"6 Roberts Rd",
    "sg:city":"Monsey",
    "sg:classifiers":[
        {
            "category":"Restaurant",
            "type":"Food & Drink"
        }
    ],
    "sg:phone":"+1   ",
    "sg:postcode":"10952",
    "sg:province":"NY",
    "sg:tags":[
        "eating"
    ],
    "wof:name":"My Kitchen Decor",
    "wof:placetype":"venue"
},
  "geometry": {"coordinates":[-74.078686,41.107727],"type":"Point"}
}