{
  "type": "Feature",
  "properties": {
    "addr:full":"445 Merrick Rd Lynbrook NY 11563",
    "addr:housenumber":"445",
    "addr:postcode":"11563",
    "addr:street":"Merrick Rd",
    "iso:country":"US",
    "sg:address":"445 Merrick Rd",
    "sg:city":"Lynbrook",
    "sg:classifiers":[
        {
            "category":"Building & Trades",
            "subcategory":"Construction",
            "type":"Services"
        }
    ],
    "sg:phone":"+1 516 887 0720",
    "sg:postcode":"11563",
    "sg:province":"NY",
    "sg:tags":[
        "tile",
        "dealer"
    ],
    "wof:name":"Silver Bldg Products Co",
    "wof:placetype":"venue"
},
  "geometry": {"coordinates":[-73.677328,40.658705],"type":"Point"}
}