{
  "type": "Feature",
  "properties": {
    "addr:full":"747 Fulton St Brooklyn NY 11217",
    "addr:housenumber":"747",
    "addr:postcode":"11217",
    "addr:street":"Fulton St",
    "iso:country":"US",
    "sg:address":"747 Fulton St",
    "sg:city":"Brooklyn",
    "sg:classifiers":[
        {
            "category":"Shopping",
            "subcategory":"Used Merchandise",
            "type":"Retail Goods"
        }
    ],
    "sg:phone":"+1   ",
    "sg:postcode":"11217",
    "sg:province":"NY",
    "sg:tags":[
        "clothing"
    ],
    "wof:name":"Status Inc",
    "wof:placetype":"venue"
},
  "geometry": {"coordinates":[-73.97503399999999,40.686719],"type":"Point"}
}