{
  "type": "Feature",
  "properties": {
    "iso:country":"US",
    "sg:address":"55 Water Street Floor 49",
    "sg:city":"New York",
    "sg:classifiers":[
        {
            "category":"Professional",
            "subcategory":"Management & Consulting",
            "type":"Services"
        }
    ],
    "sg:phone":"+1 212 438 4200",
    "sg:postcode":"10041",
    "sg:province":"NY",
    "sg:website":"http://www.vistaresearch.com",
    "wof:name":"Vista Research",
    "wof:placetype":"venue"
},
  "geometry": {"coordinates":[-74.010991,40.702962],"type":"Point"}
}