{
  "type": "Feature",
  "properties": {
    "addr:full":"48 Brotherhood Plaza Dr Washingtonville NY 10992",
    "addr:housenumber":"48",
    "addr:postcode":"10992",
    "addr:street":"Brotherhood Plaza Dr",
    "iso:country":"US",
    "sg:address":"48 Brotherhood Plaza Dr",
    "sg:city":"Washingtonville",
    "sg:classifiers":[
        {
            "category":"Insurance",
            "subcategory":"Insurance Agent",
            "type":"Services"
        }
    ],
    "sg:phone":"+1 845 496 8990",
    "sg:postcode":"10992",
    "sg:province":"NY",
    "wof:name":"Liberty Mutual Insurance",
    "wof:placetype":"venue"
},
  "geometry": {"coordinates":[-74.161884,41.430091],"type":"Point"}
}