{
  "type": "Feature",
  "properties": {
    "addr:full":"75 Wells Rd Barton NY 13734",
    "addr:housenumber":"75",
    "addr:postcode":"13734",
    "addr:street":"Wells Rd",
    "iso:country":"US",
    "sg:address":"75 Wells Rd",
    "sg:city":"Barton",
    "sg:classifiers":[
        {
            "category":"Freight",
            "type":"Transportation"
        }
    ],
    "sg:phone":"+1 607 565 2938",
    "sg:postcode":"13734",
    "sg:province":"NY",
    "sg:tags":[
        "trucking"
    ],
    "wof:name":"D E Spencer Trucking Inc",
    "wof:placetype":"venue"
},
  "geometry": {"coordinates":[-76.426889,42.060077],"type":"Point"}
}