{
  "type": "Feature",
  "properties": {
    "addr:full":"1 Grand Central Pl Ste 1535 Manhattan NY 10165",
    "addr:housenumber":"1",
    "addr:postcode":"10165",
    "addr:street":"Grand Central Pl Ste 1535",
    "iso:country":"US",
    "sg:address":"1 Grand Central Pl Ste 1535",
    "sg:city":"Manhattan",
    "sg:classifiers":[
        {
            "category":"Real Estate",
            "subcategory":"Real Estate Services",
            "type":"Services"
        }
    ],
    "sg:postcode":"10165",
    "sg:province":"NY",
    "sg:tags":[
        "management",
        "property"
    ],
    "wof:name":"Javind Apartment, LLC",
    "wof:placetype":"venue"
},
  "geometry": {"coordinates":[-73.816227,40.71605],"type":"Point"}
}