{
  "type": "Feature",
  "properties": {
    "iso:country":"US",
    "sg:address":"751 Fort Salonga Rd",
    "sg:city":"Northport",
    "sg:classifiers":[
        {
            "category":"Retail",
            "subcategory":"Laundry & Dry Cleaning",
            "type":"Services"
        }
    ],
    "sg:phone":"+1 631 261 9146",
    "sg:postcode":"11768",
    "sg:province":"NY",
    "sg:website":"www.onepricedrycleaners.com",
    "wof:name":"One Price Dry Cleaners",
    "wof:placetype":"venue"
},
  "geometry": {"coordinates":[-73.295799,40.9128],"type":"Point"}
}