{
  "type": "Feature",
  "properties": {
    "iso:country":"US",
    "sg:address":"234 Hudson Ave",
    "sg:city":"Albany",
    "sg:classifiers":[
        {
            "category":"Professional",
            "type":"Services"
        }
    ],
    "sg:phone":"+1 518 472 1762",
    "sg:postcode":"12210",
    "sg:province":"NY",
    "sg:tags":[
        "establishment"
    ],
    "wof:name":"Lord & Bryant LTD",
    "wof:placetype":"venue"
},
  "geometry": {"coordinates":[-73.762479,42.651458],"type":"Point"}
}