{
  "type": "Feature",
  "properties": {
    "iso:country":"US",
    "sg:address":"5 Landview Dr",
    "sg:city":"Huntington Station",
    "sg:classifiers":[
        {
            "category":"Professional",
            "subcategory":"Management & Consulting",
            "type":"Services"
        }
    ],
    "sg:phone":"+1   ",
    "sg:postcode":"11746",
    "sg:province":"NY",
    "sg:tags":[
        "retail",
        "direct",
        "sales"
    ],
    "wof:name":"Hampton Spring Water Corp",
    "wof:placetype":"venue"
},
  "geometry": {"coordinates":[-73.35084999999999,40.806657],"type":"Point"}
}