{
  "type": "Feature",
  "properties": {
    "addr:full":"104 Grand St Croton On Hudson NY 10520",
    "addr:housenumber":"104",
    "addr:postcode":"10520",
    "addr:street":"Grand St",
    "iso:country":"US",
    "sg:address":"104 Grand St",
    "sg:city":"Croton On Hudson",
    "sg:classifiers":[
        {
            "category":"Banks & Credit Unions",
            "subcategory":"Investment Brokerage",
            "type":"Services"
        },
        {
            "category":"Professional",
            "subcategory":"Management & Consulting",
            "type":"Services"
        }
    ],
    "sg:phone":"+1 914 827 0051",
    "sg:postcode":"10520",
    "sg:province":"NY",
    "sg:tags":[
        "consultant",
        "planning",
        "financial"
    ],
    "wof:name":"Thomas G Faranda & Associates",
    "wof:placetype":"venue"
},
  "geometry": {"coordinates":[-73.888638,41.205031],"type":"Point"}
}