{
  "type": "Feature",
  "properties": {
    "addr:full":"502 Brigham Rd Dunkirk NY 14048",
    "addr:housenumber":"502",
    "addr:postcode":"14048",
    "addr:street":"Brigham Rd",
    "iso:country":"US",
    "sg:address":"502 Brigham Rd",
    "sg:city":"Dunkirk",
    "sg:classifiers":[
        {
            "category":"Building & Trades",
            "subcategory":"Construction",
            "type":"Services"
        }
    ],
    "sg:phone":"+1 716 366 0370",
    "sg:postcode":"14048",
    "sg:province":"NY",
    "sg:tags":[
        "carpentry",
        "contractor"
    ],
    "wof:name":"Maureen Carlsons Construction",
    "wof:placetype":"venue"
},
  "geometry": {"coordinates":[-79.345912,42.479497],"type":"Point"}
}