{
  "type": "Feature",
  "properties": {
    "iso:country":"US",
    "sg:address":"57 W Islip Rd",
    "sg:city":"West Islip",
    "sg:classifiers":[
        {
            "category":"Building & Trades",
            "subcategory":"Plumbing",
            "type":"Services"
        }
    ],
    "sg:phone":"+1 631 661 3642",
    "sg:postcode":"11795",
    "sg:province":"NY",
    "sg:tags":[
        "plumbing",
        "contractor"
    ],
    "wof:name":"Bryan's Plumbing",
    "wof:placetype":"venue"
},
  "geometry": {"coordinates":[-73.315665,40.689295],"type":"Point"}
}