{
  "type": "Feature",
  "properties": {
    "iso:country":"US",
    "sg:address":"39 Oak St",
    "sg:city":"Brewster",
    "sg:classifiers":[
        {
            "category":"Health Services",
            "subcategory":"Hospital",
            "type":"Services"
        }
    ],
    "sg:phone":"+1 845 278 1803",
    "sg:postcode":"10509",
    "sg:province":"NY",
    "wof:name":"Putnam Hospital Ctr Brewster",
    "wof:placetype":"venue"
},
  "geometry": {"coordinates":[-73.61591,41.39528],"type":"Point"}
}