{
  "type": "Feature",
  "properties": {
    "addr:full":"641 Lexington Ave Fl 13 New York NY 10022",
    "addr:housenumber":"641;13",
    "addr:postcode":"10022",
    "addr:street":"Lexington Ave Fl",
    "iso:country":"US",
    "sg:address":"641 Lexington Ave Fl 13",
    "sg:city":"New York",
    "sg:classifiers":[
        {
            "category":"Building & Trades",
            "subcategory":"Construction",
            "type":"Services"
        }
    ],
    "sg:phone":"+1 212 974 2210",
    "sg:postcode":"10022",
    "sg:province":"NY",
    "sg:tags":[
        "interior",
        "design"
    ],
    "wof:name":"The Bern Companies",
    "wof:placetype":"venue"
},
  "geometry": {"coordinates":[-73.969944,40.75883],"type":"Point"}
}