{
  "type": "Feature",
  "properties": {
    "addr:full":"6535 Seneca St Elma NY 14059",
    "addr:housenumber":"6535",
    "addr:postcode":"14059",
    "addr:street":"Seneca St",
    "iso:country":"US",
    "sg:address":"6535 Seneca St",
    "sg:city":"Elma",
    "sg:classifiers":[
        {
            "category":"Building & Trades",
            "subcategory":"Plumbing",
            "type":"Services"
        }
    ],
    "sg:phone":"+1 716 652 1662",
    "sg:postcode":"14059",
    "sg:province":"NY",
    "sg:tags":[
        "contractor"
    ],
    "wof:name":"Elma Plumbing & Remodeling Co",
    "wof:placetype":"venue"
},
  "geometry": {"coordinates":[-78.67391000000001,42.817232],"type":"Point"}
}