{
  "type": "Feature",
  "properties": {
    "addr:full":"99 Avenue A New York NY 10009",
    "addr:housenumber":"99",
    "addr:postcode":"10009",
    "addr:street":"Avenue A",
    "iso:country":"US",
    "sg:address":"99 Avenue A",
    "sg:city":"New York",
    "sg:classifiers":[
        {
            "category":"Retail",
            "subcategory":"Laundry & Dry Cleaning",
            "type":"Services"
        }
    ],
    "sg:phone":"+1 212 260 0697",
    "sg:postcode":"10009",
    "sg:province":"NY",
    "wof:name":"Kims Dry Cleaners",
    "wof:placetype":"venue"
},
  "geometry": {"coordinates":[-73.983825,40.725626],"type":"Point"}
}