{
  "type": "Feature",
  "properties": {
    "addr:full":"127 Center Way Corning NY 14830",
    "addr:housenumber":"127",
    "addr:postcode":"14830",
    "addr:street":"Center Way",
    "iso:country":"US",
    "sg:address":"127 Center Way",
    "sg:city":"Corning",
    "sg:classifiers":[
        {
            "category":"Social Services",
            "type":"Services"
        }
    ],
    "sg:phone":"+1 607 962 7600",
    "sg:postcode":"14830",
    "sg:province":"NY",
    "sg:tags":[
        "organization",
        "welfare"
    ],
    "sg:website":"www.corningymca.org",
    "wof:name":"YMCA",
    "wof:placetype":"venue"
},
  "geometry": {"coordinates":[-77.053226,42.150573],"type":"Point"}
}