{
  "type": "Feature",
  "properties": {
    "addr:full":"12703 111th Avenue South Ozone Park NY 11420",
    "addr:housenumber":"12703",
    "addr:postcode":"11420",
    "addr:street":"111Th Avenue",
    "iso:country":"US",
    "sg:address":"12703 111th Avenue",
    "sg:city":"South Ozone Park",
    "sg:classifiers":[
        {
            "category":"Restaurant",
            "type":"Food & Drink"
        }
    ],
    "sg:phone":"+1 718 848 5951",
    "sg:postcode":"11420",
    "sg:province":"NY",
    "wof:name":"World American Kitchen",
    "wof:placetype":"venue"
},
  "geometry": {"coordinates":[-73.81413000000001,40.682665],"type":"Point"}
}