{
  "type": "Feature",
  "properties": {
    "iso:country":"US",
    "sg:address":"210 1st Ave",
    "sg:city":"New York",
    "sg:classifiers":[
        {
            "category":"Professional",
            "type":"Services"
        }
    ],
    "sg:phone":"+1 212 982 7470",
    "sg:postcode":"10009",
    "sg:province":"NY",
    "sg:tags":[
        "caterer"
    ],
    "wof:name":"Madina Restaurant & Catering",
    "wof:placetype":"venue"
},
  "geometry": {"coordinates":[-73.98309500000001,40.730374],"type":"Point"}
}