{
  "type": "Feature",
  "properties": {
    "iso:country":"US",
    "sg:address":"1230 Ave of the Americas",
    "sg:city":"New York",
    "sg:classifiers":[
        {
            "category":"Banks & Credit Unions",
            "subcategory":"Bank",
            "type":"Services"
        }
    ],
    "sg:phone":"+1 212 883 6330",
    "sg:postcode":"10020",
    "sg:province":"NY",
    "sg:tags":[
        "international",
        "company",
        "finance"
    ],
    "wof:name":"B W Capital",
    "wof:placetype":"venue"
},
  "geometry": {"coordinates":[-73.981036,40.758843],"type":"Point"}
}