{
  "type": "Feature",
  "properties": {
    "iso:country":"US",
    "sg:address":"572 Flatbush Ave",
    "sg:city":"Brooklyn",
    "sg:classifiers":[
        {
            "category":"Professional",
            "subcategory":"Lawyer & Legal Services",
            "type":"Services"
        }
    ],
    "sg:phone":"+1 718 230 5270",
    "sg:postcode":"11225",
    "sg:province":"NY",
    "sg:tags":[
        "attorney"
    ],
    "wof:name":"Thomas Wareham & Richards",
    "wof:placetype":"venue"
},
  "geometry": {"coordinates":[-73.96066399999999,40.659951],"type":"Point"}
}