{
  "type": "Feature",
  "properties": {
    "addr:full":"75 Varick St New York NY 10013",
    "addr:housenumber":"75",
    "addr:postcode":"10013",
    "addr:street":"Varick St",
    "iso:country":"US",
    "sg:address":"75 Varick St",
    "sg:city":"New York",
    "sg:classifiers":[
        {
            "category":"Professional",
            "type":"Services"
        }
    ],
    "sg:phone":"+1 212 431 3490",
    "sg:postcode":"10013",
    "sg:province":"NY",
    "wof:name":"Management Services Of Trinity",
    "wof:placetype":"venue"
},
  "geometry": {"coordinates":[-74.006316,40.72308],"type":"Point"}
}