{
  "type": "Feature",
  "properties": {
    "addr:full":"99 White Plains Rd Tarrytown NY 10591",
    "addr:housenumber":"99",
    "addr:postcode":"10591",
    "addr:street":"White Plains Rd",
    "iso:country":"US",
    "sg:address":"99 White Plains Rd",
    "sg:city":"Tarrytown",
    "sg:classifiers":[
        {
            "category":"Manufacturing",
            "subcategory":"Printing",
            "type":"Manufacturing & Wholesale Goods"
        }
    ],
    "sg:phone":"+1   ",
    "sg:postcode":"10591",
    "sg:province":"NY",
    "sg:tags":[
        "printer",
        "commercial"
    ],
    "wof:name":"Times Publishing Group",
    "wof:placetype":"venue"
},
  "geometry": {"coordinates":[-73.86057,41.063572],"type":"Point"}
}