{
  "type": "Feature",
  "properties": {
    "iso:country":"US",
    "sg:address":"8815 Brewerton Rd",
    "sg:city":"Brewerton",
    "sg:classifiers":[
        {
            "category":"Professional",
            "type":"Services"
        }
    ],
    "sg:phone":"+1 315 699 1483",
    "sg:postcode":"13029",
    "sg:province":"NY",
    "sg:tags":[
        "establishment"
    ],
    "wof:name":"Marketing Alternatives",
    "wof:placetype":"venue"
},
  "geometry": {"coordinates":[-76.12673700000001,43.19583],"type":"Point"}
}