{
  "type": "Feature",
  "properties": {
    "addr:full":"30 Essex St Albany NY 12206",
    "addr:housenumber":"30",
    "addr:postcode":"12206",
    "addr:street":"Essex St",
    "iso:country":"US",
    "sg:address":"30 Essex St",
    "sg:city":"Albany",
    "sg:classifiers":[
        {
            "category":"Real Estate",
            "subcategory":"Architect",
            "type":"Services"
        }
    ],
    "sg:phone":"+1 518 454 9300",
    "sg:postcode":"12206",
    "sg:province":"NY",
    "wof:name":"Angerame Architects",
    "wof:placetype":"venue"
},
  "geometry": {"coordinates":[-73.780366,42.677888],"type":"Point"}
}