{
  "type": "Feature",
  "properties": {
    "addr:full":"3019 Monroe Ave Rochester NY 14618",
    "addr:housenumber":"3019",
    "addr:postcode":"14618",
    "addr:street":"Monroe Ave",
    "iso:country":"US",
    "sg:address":"3019 Monroe Ave",
    "sg:city":"Rochester",
    "sg:classifiers":[
        {
            "category":"Personal",
            "subcategory":"Beauty Salon",
            "type":"Services"
        }
    ],
    "sg:phone":"+1 585 271 4450",
    "sg:postcode":"14618",
    "sg:province":"NY",
    "wof:name":"Sorellas & Co Salon",
    "wof:placetype":"venue"
},
  "geometry": {"coordinates":[-77.537001,43.101423],"type":"Point"}
}