{
  "type": "Feature",
  "properties": {
    "addr:full":"30 E 40th St New York NY 10016",
    "addr:housenumber":"30",
    "addr:postcode":"10016",
    "addr:street":"E 40Th St",
    "iso:country":"US",
    "sg:address":"30 E 40th St",
    "sg:city":"New York",
    "sg:classifiers":[
        {
            "category":"Health Services",
            "subcategory":"Doctor",
            "type":"Services"
        }
    ],
    "sg:phone":"+1 212 684 3980",
    "sg:postcode":"10016",
    "sg:province":"NY",
    "sg:tags":[
        "medical"
    ],
    "wof:name":"Campolattaro Brian N",
    "wof:placetype":"venue"
},
  "geometry": {"coordinates":[-73.97877200000001,40.750848],"type":"Point"}
}