{
  "type": "Feature",
  "properties": {
    "addr:full":"95 Sherwood Ave Farmingdale NY 11735",
    "addr:housenumber":"95",
    "addr:postcode":"11735",
    "addr:street":"Sherwood Ave",
    "iso:country":"US",
    "sg:address":"95 Sherwood Ave",
    "sg:city":"Farmingdale",
    "sg:classifiers":[
        {
            "category":"Wholesale",
            "subcategory":"Durable Goods & Equipment",
            "type":"Manufacturing & Wholesale Goods"
        }
    ],
    "sg:phone":"+1 631 777 3550",
    "sg:postcode":"11735",
    "sg:province":"NY",
    "sg:tags":[
        "compact",
        "record",
        "disc",
        "tape"
    ],
    "sg:website":"www.wtcco.com",
    "wof:name":"World Trading Ctr",
    "wof:placetype":"venue"
},
  "geometry": {"coordinates":[-73.414604,40.745828],"type":"Point"}
}