{
  "type": "Feature",
  "properties": {
    "addr:full":"895 S Harbor Rd Southold NY 11971",
    "addr:housenumber":"895",
    "addr:postcode":"11971",
    "addr:street":"S Harbor Rd",
    "iso:country":"US",
    "sg:address":"895 S Harbor Rd",
    "sg:city":"Southold",
    "sg:classifiers":[
        {
            "category":"Professional",
            "subcategory":"Research",
            "type":"Services"
        }
    ],
    "sg:phone":"+1 631 765 4387",
    "sg:postcode":"11971",
    "sg:province":"NY",
    "sg:tags":[
        "nonphysical",
        "commercial"
    ],
    "wof:name":"Minds Over Matter",
    "wof:placetype":"venue"
},
  "geometry": {"coordinates":[-72.44111599999999,41.049411],"type":"Point"}
}