{
  "type": "Feature",
  "properties": {
    "iso:country":"US",
    "sg:address":"311 Woods Ave",
    "sg:city":"Oceanside",
    "sg:classifiers":[
        {
            "category":"Manufacturing",
            "subcategory":"Printing",
            "type":"Manufacturing & Wholesale Goods"
        }
    ],
    "sg:phone":"+1   ",
    "sg:postcode":"11572",
    "sg:province":"NY",
    "sg:tags":[
        "mail",
        "commercial",
        "direct",
        "advertising"
    ],
    "wof:name":"Furst Direct",
    "wof:placetype":"venue"
},
  "geometry": {"coordinates":[-73.642174,40.642629],"type":"Point"}
}