{
  "type": "Feature",
  "properties": {
    "addr:full":"37 Franklin St Buffalo NY 14202",
    "addr:housenumber":"37",
    "addr:postcode":"14202",
    "addr:street":"Franklin St",
    "iso:country":"US",
    "sg:address":"37 Franklin St",
    "sg:city":"Buffalo",
    "sg:classifiers":[
        {
            "category":"Insurance",
            "subcategory":"Insurance Agent",
            "type":"Services"
        }
    ],
    "sg:phone":"+1 716 632 4200",
    "sg:postcode":"14202",
    "sg:province":"NY",
    "sg:tags":[
        "broker"
    ],
    "wof:name":"Wadsworth & Associates",
    "wof:placetype":"venue"
},
  "geometry": {"coordinates":[-78.87808099999999,42.881505],"type":"Point"}
}