{
  "type": "Feature",
  "properties": {
    "iso:country":"US",
    "sg:address":"408 E 49th St",
    "sg:city":"Brooklyn",
    "sg:classifiers":[
        {
            "category":"Personal",
            "type":"Services"
        }
    ],
    "sg:phone":"+1 800 805 8584",
    "sg:postcode":"11203",
    "sg:province":"NY",
    "sg:tags":[
        "sewing",
        "alteration"
    ],
    "wof:name":"Bespoke Tailor Service",
    "wof:placetype":"venue"
},
  "geometry": {"coordinates":[-73.931588,40.651932],"type":"Point"}
}