{
  "type": "Feature",
  "properties": {
    "addr:full":"75 Richmond Ter Staten Island NY 10301",
    "addr:housenumber":"75",
    "addr:postcode":"10301",
    "addr:street":"Richmond Ter",
    "iso:country":"US",
    "sg:address":"75 Richmond Ter",
    "sg:city":"Staten Island",
    "sg:classifiers":[
        {
            "category":"Parking",
            "type":"Transportation"
        }
    ],
    "sg:phone":"+1 718 420 6719",
    "sg:postcode":"10301",
    "sg:province":"NY",
    "sg:tags":[
        "garage"
    ],
    "wof:name":"Central Parking System",
    "wof:placetype":"venue"
},
  "geometry": {"coordinates":[-74.077676,40.645416],"type":"Point"}
}