{
  "type": "Feature",
  "properties": {
    "addr:full":"1110 E 34th St Brooklyn NY 11210",
    "addr:housenumber":"1110",
    "addr:postcode":"11210",
    "addr:street":"E 34Th St",
    "iso:country":"US",
    "sg:address":"1110 E 34th St",
    "sg:city":"Brooklyn",
    "sg:classifiers":[
        {
            "category":"Organizations",
            "subcategory":"Religious Organization",
            "type":"Services"
        }
    ],
    "sg:phone":"+1 347 275 4408",
    "sg:postcode":"11210",
    "sg:province":"NY",
    "wof:name":"Bethel Born Again Church",
    "wof:placetype":"venue"
},
  "geometry": {"coordinates":[-73.94349699999999,40.6287],"type":"Point"}
}