{
  "type": "Feature",
  "properties": {
    "addr:full":"630 3rd Ave New York NY 10017",
    "addr:housenumber":"630",
    "addr:postcode":"10017",
    "addr:street":"3Rd Ave",
    "iso:country":"US",
    "sg:address":"630 3rd Ave",
    "sg:city":"New York",
    "sg:classifiers":[
        {
            "category":"Professional",
            "subcategory":"Lawyer & Legal Services",
            "type":"Services"
        }
    ],
    "sg:phone":"+1 212 949 8770",
    "sg:postcode":"10017",
    "sg:province":"NY",
    "wof:name":"Levy & Tolman",
    "wof:placetype":"venue"
},
  "geometry": {"coordinates":[-73.975098,40.749802],"type":"Point"}
}