{
  "type": "Feature",
  "properties": {
    "addr:full":"40 Saw Mill River Rd Hawthorne NY 10532",
    "addr:housenumber":"40",
    "addr:postcode":"10532",
    "addr:street":"Saw Mill River Rd",
    "iso:country":"US",
    "sg:address":"40 Saw Mill River Rd",
    "sg:city":"Hawthorne",
    "sg:classifiers":[
        {
            "category":"Recreation",
            "type":"Entertainment"
        }
    ],
    "sg:phone":"+1 914 345 5005",
    "sg:postcode":"10532",
    "sg:province":"NY",
    "sg:tags":[
        "amusement"
    ],
    "wof:name":"Fencing Academy Of Weschester",
    "wof:placetype":"venue"
},
  "geometry": {"coordinates":[-73.811564,41.094547],"type":"Point"}
}