{
  "type": "Feature",
  "properties": {
    "iso:country":"US",
    "sg:address":"10 Highland View Ave",
    "sg:city":"Rensselaer",
    "sg:classifiers":[
        {
            "category":"Retail",
            "subcategory":"Veterinary Services",
            "type":"Services"
        }
    ],
    "sg:phone":"+1 518 477 5185",
    "sg:postcode":"12144",
    "sg:province":"NY",
    "sg:tags":[
        "veterinarian"
    ],
    "wof:name":"Greenbush Veterinary Assocs",
    "wof:placetype":"venue"
},
  "geometry": {"coordinates":[-73.740415,42.615809],"type":"Point"}
}