{
  "type": "Feature",
  "properties": {
    "iso:country":"US",
    "sg:address":"1583 US Hwy 20",
    "sg:city":"Skaneateles",
    "sg:classifiers":[
        {
            "category":"Professional",
            "subcategory":"Accounting & Tax Preparation",
            "type":"Services"
        }
    ],
    "sg:phone":"+1 315 685 1577",
    "sg:postcode":"13152",
    "sg:province":"NY",
    "sg:tags":[
        "accountant"
    ],
    "wof:name":"Brian D Baker CPA",
    "wof:placetype":"venue"
},
  "geometry": {"coordinates":[-76.39600799999999,42.945272],"type":"Point"}
}