{
  "type": "Feature",
  "properties": {
    "addr:full":"10 Bruen Ct Rensselaer NY 12144",
    "addr:housenumber":"10",
    "addr:postcode":"12144",
    "addr:street":"Bruen Ct",
    "iso:country":"US",
    "sg:address":"10 Bruen Ct",
    "sg:city":"Rensselaer",
    "sg:classifiers":[
        {
            "category":"Social Services",
            "subcategory":"Adult Care",
            "type":"Services"
        }
    ],
    "sg:phone":"+1 518 472 1022",
    "sg:postcode":"12144",
    "sg:province":"NY",
    "sg:tags":[
        "home"
    ],
    "wof:name":"White House Home For Adults",
    "wof:placetype":"venue"
},
  "geometry": {"coordinates":[-73.734917,42.623545],"type":"Point"}
}