{
  "type": "Feature",
  "properties": {
    "addr:full":"520 W 43rd St New York NY 10036",
    "addr:housenumber":"520",
    "addr:postcode":"10036",
    "addr:street":"W 43Rd St",
    "iso:country":"US",
    "sg:address":"520 W 43rd St",
    "sg:city":"New York",
    "sg:classifiers":[
        {
            "category":"Professional",
            "subcategory":"Lawyer & Legal Services",
            "type":"Services"
        }
    ],
    "sg:phone":"+1 212 835 0753",
    "sg:postcode":"10036",
    "sg:province":"NY",
    "wof:name":"Dunham Robert",
    "wof:placetype":"venue"
},
  "geometry": {"coordinates":[-73.996117,40.760627],"type":"Point"}
}