{
  "type": "Feature",
  "properties": {
    "iso:country":"US",
    "sg:address":"100 Pearce Ave",
    "sg:city":"Tonawanda",
    "sg:classifiers":[
        {
            "category":"Building & Trades",
            "subcategory":"Electrical",
            "type":"Services"
        }
    ],
    "sg:phone":"+1 716 332 2441",
    "sg:postcode":"14150",
    "sg:province":"NY",
    "sg:tags":[
        "electrical",
        "general"
    ],
    "wof:name":"Santana Contracting LLC",
    "wof:placetype":"venue"
},
  "geometry": {"coordinates":[-78.895079,42.991862],"type":"Point"}
}