{
  "type": "Feature",
  "properties": {
    "addr:full":"1056 Northern Blvd Roslyn NY 11576",
    "addr:housenumber":"1056",
    "addr:postcode":"11576",
    "addr:street":"Northern Blvd",
    "iso:country":"US",
    "sg:address":"1056 Northern Blvd",
    "sg:city":"Roslyn",
    "sg:classifiers":[
        {
            "category":"Building & Trades",
            "subcategory":"Landscaping Services",
            "type":"Services"
        },
        {
            "category":"Home & Garden",
            "subcategory":"Garden Supply",
            "type":"Retail Goods"
        },
        {
            "category":"Building & Trades",
            "subcategory":"Construction",
            "type":"Services"
        }
    ],
    "sg:phone":"+1 516 627 3524",
    "sg:postcode":"11576",
    "sg:province":"NY",
    "sg:tags":[
        "designer",
        "gardening",
        "consultant",
        "contractor",
        "nursery",
        "paving",
        "landscape"
    ],
    "wof:name":"Di Stefano Tony Landscaping Corp",
    "wof:placetype":"venue"
},
  "geometry": {"coordinates":[-73.663803,40.798199],"type":"Point"}
}