{
  "type": "Feature",
  "properties": {
    "iso:country":"US",
    "sg:address":"72 Great Wood Cir",
    "sg:city":"Fairport",
    "sg:classifiers":[
        {
            "category":"Communications",
            "subcategory":"Film & Video Production",
            "type":"Services"
        }
    ],
    "sg:phone":"+1 585 425 2361",
    "sg:postcode":"14450",
    "sg:province":"NY",
    "sg:tags":[
        "audio"
    ],
    "wof:name":"Heritage Video Assoc",
    "wof:placetype":"venue"
},
  "geometry": {"coordinates":[-77.443805,43.087603],"type":"Point"}
}