{
  "type": "Feature",
  "properties": {
    "iso:country":"US",
    "sg:address":"139 Gardnertown Rd",
    "sg:city":"Newburgh",
    "sg:classifiers":[
        {
            "category":"Building & Trades",
            "subcategory":"Construction",
            "type":"Services"
        }
    ],
    "sg:phone":"+1 845 566 9306",
    "sg:postcode":"12550",
    "sg:province":"NY",
    "sg:tags":[
        "contractor"
    ],
    "wof:name":"Watt Thomas Contracting I",
    "wof:placetype":"venue"
},
  "geometry": {"coordinates":[-74.065448,41.531916],"type":"Point"}
}