{
  "type": "Feature",
  "properties": {
    "iso:country":"US",
    "sg:address":"1507 40",
    "sg:city":"New York",
    "sg:classifiers":[
        {
            "category":"Wholesale",
            "subcategory":"Fruits & Vegetables",
            "type":"Manufacturing & Wholesale Goods"
        }
    ],
    "sg:phone":"+1 718 305 7321",
    "sg:postcode":"10001",
    "sg:province":"NY",
    "sg:tags":[
        "veggie"
    ],
    "wof:name":"Kol Tuv Grocery",
    "wof:placetype":"venue"
},
  "geometry": {"coordinates":[-73.982209,40.77344],"type":"Point"}
}