{
  "type": "Feature",
  "properties": {
    "iso:country":"US",
    "sg:address":"5041 State Hwy 9n",
    "sg:city":"Corinth",
    "sg:classifiers":[
        {
            "category":"Local Transit",
            "type":"Transportation"
        }
    ],
    "sg:phone":"+1   ",
    "sg:postcode":"12822",
    "sg:province":"NY",
    "sg:tags":[
        "rental",
        "driver",
        "limousine"
    ],
    "wof:name":"Queen Lace Florist",
    "wof:placetype":"venue"
},
  "geometry": {"coordinates":[-73.837209,43.254945],"type":"Point"}
}