{
  "type": "Feature",
  "properties": {
    "addr:full":"385 Pearsall Ave Cedarhurst NY 11516",
    "addr:housenumber":"385",
    "addr:postcode":"11516",
    "addr:street":"Pearsall Ave",
    "iso:country":"US",
    "sg:address":"385 Pearsall Ave",
    "sg:city":"Cedarhurst",
    "sg:classifiers":[
        {
            "category":"Personal",
            "subcategory":"Beauty Salon",
            "type":"Services"
        }
    ],
    "sg:phone":"+1 888 566 5642",
    "sg:postcode":"11516",
    "sg:province":"NY",
    "sg:tags":[
        "spa"
    ],
    "sg:website":"www.beautedeparis.fr/lash-relong...",
    "wof:name":"Lash Relonge",
    "wof:placetype":"venue"
},
  "geometry": {"coordinates":[-73.72898499999999,40.6205],"type":"Point"}
}