{
  "type": "Feature",
  "properties": {
    "addr:full":"9712 71st Avenue Forest Hills NY 11375",
    "addr:housenumber":"9712",
    "addr:postcode":"11375",
    "addr:street":"71St Avenue",
    "iso:country":"US",
    "sg:address":"9712 71st Avenue",
    "sg:city":"Forest Hills",
    "sg:classifiers":[
        {
            "category":"Building & Trades",
            "subcategory":"Locksmith",
            "type":"Services"
        }
    ],
    "sg:phone":"+1 718 459 4170",
    "sg:postcode":"11375",
    "sg:province":"NY",
    "sg:tags":[
        "key"
    ],
    "wof:name":"24 Hour A 1 Emerg Forest Hills Locksmith Serv",
    "wof:placetype":"venue"
},
  "geometry": {"coordinates":[-73.84831200000001,40.714323],"type":"Point"}
}