{
  "type": "Feature",
  "properties": {
    "iso:country":"US",
    "sg:address":"96 Hamilton St",
    "sg:city":"Oswego",
    "sg:classifiers":[
        {
            "category":"Shopping",
            "subcategory":"Department Store",
            "type":"Retail Goods"
        }
    ],
    "sg:phone":"+1 315 343 1045",
    "sg:postcode":"13126",
    "sg:province":"NY",
    "wof:name":"Peebles Department Store",
    "wof:placetype":"venue"
},
  "geometry": {"coordinates":[-76.489845,43.452458],"type":"Point"}
}