{
  "type": "Feature",
  "properties": {
    "addr:full":"168 Mulberry Dr Farmington NY 14425",
    "addr:housenumber":"168",
    "addr:postcode":"14425",
    "addr:street":"Mulberry Dr",
    "iso:country":"US",
    "sg:address":"168 Mulberry Dr",
    "sg:city":"Farmington",
    "sg:classifiers":[
        {
            "category":"Professional",
            "type":"Services"
        },
        {
            "category":"Manufacturing",
            "subcategory":"Building Materials",
            "type":"Manufacturing & Wholesale Goods"
        }
    ],
    "sg:phone":"+1 315 986 4543",
    "sg:postcode":"14425",
    "sg:province":"NY",
    "sg:tags":[
        "establishment",
        "mfg"
    ],
    "wof:name":"Woodsong Inspired Creations",
    "wof:placetype":"venue"
},
  "geometry": {"coordinates":[-77.354545,43.030665],"type":"Point"}
}