{
  "type": "Feature",
  "properties": {
    "iso:country":"US",
    "sg:address":"2354 State Hwy 434",
    "sg:city":"Apalachin",
    "sg:classifiers":[
        {
            "category":"Government",
            "subcategory":"Office",
            "type":"Public Place"
        }
    ],
    "sg:phone":"+1 607 687 3535",
    "sg:postcode":"13732",
    "sg:province":"NY",
    "sg:tags":[
        "village"
    ],
    "wof:name":"Town Council",
    "wof:placetype":"venue"
},
  "geometry": {"coordinates":[-76.232016,42.08968],"type":"Point"}
}