{
  "type": "Feature",
  "properties": {
    "iso:country":"US",
    "sg:address":"7816 20th Ave",
    "sg:city":"Brooklyn",
    "sg:classifiers":[
        {
            "category":"Wholesale",
            "subcategory":"Groceries",
            "type":"Manufacturing & Wholesale Goods"
        }
    ],
    "sg:phone":"+1 718 259 3849",
    "sg:postcode":"11214",
    "sg:province":"NY",
    "sg:tags":[
        "grocer",
        "general"
    ],
    "wof:name":"Flores Mexican Deli & Grocery",
    "wof:placetype":"venue"
},
  "geometry": {"coordinates":[-73.994124,40.608702],"type":"Point"}
}