{
  "type": "Feature",
  "properties": {
    "addr:full":"1202 E 10th St Brooklyn NY 11230",
    "addr:housenumber":"1202",
    "addr:postcode":"11230",
    "addr:street":"E 10Th St",
    "iso:country":"US",
    "sg:address":"1202 E 10th St",
    "sg:city":"Brooklyn",
    "sg:classifiers":[
        {
            "category":"Organizations",
            "subcategory":"Religious Organization",
            "type":"Services"
        }
    ],
    "sg:phone":"+1 718 258 2273",
    "sg:postcode":"11230",
    "sg:province":"NY",
    "sg:tags":[
        "clergy"
    ],
    "wof:name":"Isaac Herschlag",
    "wof:placetype":"venue"
},
  "geometry": {"coordinates":[-73.964893,40.617519],"type":"Point"}
}