{
  "type": "Feature",
  "properties": {
    "iso:country":"US",
    "sg:address":"34 Airport Rd",
    "sg:city":"Montgomery",
    "sg:classifiers":[
        {
            "category":"Professional",
            "type":"Services"
        },
        {
            "category":"Airport",
            "type":"Transportation"
        }
    ],
    "sg:phone":"+1 845 457 1550",
    "sg:postcode":"12590",
    "sg:province":"NY",
    "sg:tags":[
        "establishment"
    ],
    "wof:name":"Flying Sportsmen Inc",
    "wof:placetype":"venue"
},
  "geometry": {"coordinates":[-73.87506999999999,41.628612],"type":"Point"}
}