{
  "type": "Feature",
  "properties": {
    "iso:country":"US",
    "sg:address":"500 W 185th St",
    "sg:city":"New York",
    "sg:classifiers":[
        {
            "category":"Manufacturing",
            "subcategory":"Printing",
            "type":"Manufacturing & Wholesale Goods"
        }
    ],
    "sg:phone":"+1   ",
    "sg:postcode":"10033",
    "sg:province":"NY",
    "sg:tags":[
        "newspaper"
    ],
    "wof:name":"Commentator",
    "wof:placetype":"venue"
},
  "geometry": {"coordinates":[-73.930019,40.850865],"type":"Point"}
}