{
  "type": "Feature",
  "properties": {
    "addr:full":"233 N Macquesten Pkwy Mount Vernon NY 10550",
    "addr:housenumber":"233",
    "addr:postcode":"10550",
    "addr:street":"N Macquesten Pkwy",
    "iso:country":"US",
    "sg:address":"233 N Macquesten Pkwy",
    "sg:city":"Mount Vernon",
    "sg:classifiers":[
        {
            "category":"Building & Trades",
            "subcategory":"Cleaning & Sanitation",
            "type":"Services"
        }
    ],
    "sg:phone":"+1   ",
    "sg:postcode":"10550",
    "sg:province":"NY",
    "sg:tags":[
        "heavy",
        "equipment",
        "truck"
    ],
    "wof:name":"Partners In Grime Inc",
    "wof:placetype":"venue"
},
  "geometry": {"coordinates":[-73.84653900000001,40.916088],"type":"Point"}
}