{
  "type": "Feature",
  "properties": {
    "iso:country":"US",
    "name:eng_x_preferred":[
        "St Lawrence Av"
    ],
    "wof:name":"St Lawrence Av",
    "wof:placetype":"venue"
},
  "geometry": {"coordinates":[-73.86761799999999,40.831509],"type":"Point"}
}