{
  "type": "Feature",
  "properties": {
    "iso:country":"US",
    "sg:address":"34-48 Steinway St",
    "sg:city":"Astoria",
    "sg:classifiers":[
        {
            "category":"Personal",
            "subcategory":"Tanning Parlor",
            "type":"Services"
        }
    ],
    "sg:phone":"+1 718 784 2665",
    "sg:postcode":"11101",
    "sg:province":"NY",
    "sg:website":"beachbumastoria1.com",
    "wof:name":"Beach Bum Tanning & Airbrush Salon",
    "wof:placetype":"venue"
},
  "geometry": {"coordinates":[-73.921504,40.755933],"type":"Point"}
}