{
  "type": "Feature",
  "properties": {
    "iso:country":"US",
    "sg:address":"773 Concourse Village E",
    "sg:city":"Bronx",
    "sg:classifiers":[
        {
            "category":"Social Services",
            "subcategory":"Adult Care",
            "type":"Services"
        }
    ],
    "sg:phone":"+1 718 293 6552",
    "sg:postcode":"10451",
    "sg:province":"NY",
    "sg:tags":[
        "organization",
        "senior",
        "citizen"
    ],
    "wof:name":"Concourse Village Adults",
    "wof:placetype":"venue"
},
  "geometry": {"coordinates":[-73.920163,40.822528],"type":"Point"}
}