{
  "type": "Feature",
  "properties": {
    "iso:country":"US",
    "sg:address":"37 Boynton Ave",
    "sg:city":"Plattsburgh",
    "sg:classifiers":[
        {
            "category":"Health Services",
            "subcategory":"Doctor",
            "type":"Services"
        }
    ],
    "sg:phone":"+1   ",
    "sg:postcode":"12901",
    "sg:province":"NY",
    "wof:name":"H Afzal DDS",
    "wof:placetype":"venue"
},
  "geometry": {"coordinates":[-73.453115,44.709118],"type":"Point"}
}