{
  "type": "Feature",
  "properties": {
    "addr:full":"16 Saw Mill River Rd Hawthorne NY 10532",
    "addr:housenumber":"16",
    "addr:postcode":"10532",
    "addr:street":"Saw Mill River Rd",
    "iso:country":"US",
    "sg:address":"16 Saw Mill River Rd",
    "sg:city":"Hawthorne",
    "sg:classifiers":[
        {
            "category":"Professional",
            "subcategory":"Advertising",
            "type":"Services"
        }
    ],
    "sg:phone":"+1 914 345 3396",
    "sg:postcode":"10532",
    "sg:province":"NY",
    "sg:website":"www.wineexpress.com",
    "wof:name":"WINEEXPRESS.COM",
    "wof:placetype":"venue"
},
  "geometry": {"coordinates":[-73.811536,41.094555],"type":"Point"}
}