{
  "type": "Feature",
  "properties": {
    "addr:full":"37 Oceanview Rd Manorville NY 11946",
    "addr:housenumber":"37",
    "addr:postcode":"11946",
    "addr:street":"Oceanview Rd",
    "iso:country":"US",
    "sg:address":"37 Oceanview Rd",
    "sg:city":"Manorville",
    "sg:classifiers":[
        {
            "category":"Building & Trades",
            "subcategory":"Electrical",
            "type":"Services"
        }
    ],
    "sg:phone":"+1 631 325 8516",
    "sg:postcode":"11946",
    "sg:province":"NY",
    "sg:tags":[
        "electric",
        "contractor"
    ],
    "wof:name":"Hobb's Electric",
    "wof:placetype":"venue"
},
  "geometry": {"coordinates":[-72.49217400000001,40.88714],"type":"Point"}
}