{
  "type": "Feature",
  "properties": {
    "addr:full":"8028 Cooper Ave Glendale NY 11385",
    "addr:housenumber":"8028",
    "addr:postcode":"11385",
    "addr:street":"Cooper Ave",
    "iso:country":"US",
    "sg:address":"8028 Cooper Ave",
    "sg:city":"Glendale",
    "sg:classifiers":[
        {
            "category":"Restaurant",
            "type":"Food & Drink"
        }
    ],
    "sg:phone":"+1 718 417 1544",
    "sg:postcode":"11385",
    "sg:province":"NY",
    "sg:tags":[
        "italian"
    ],
    "wof:name":"Pasticcio Restaurant",
    "wof:placetype":"venue"
},
  "geometry": {"coordinates":[-73.869873,40.709351],"type":"Point"}
}