{
  "type": "Feature",
  "properties": {
    "iso:country":"US",
    "sg:address":"704 N Main St",
    "sg:city":"Central Square",
    "sg:classifiers":[
        {
            "category":"Professional",
            "type":"Services"
        }
    ],
    "sg:phone":"+1 315 668 2176",
    "sg:postcode":"13036",
    "sg:province":"NY",
    "sg:tags":[
        "establishment"
    ],
    "wof:name":"Uva Echo J Central Square",
    "wof:placetype":"venue"
},
  "geometry": {"coordinates":[-76.147552,43.288783],"type":"Point"}
}