{
  "type": "Feature",
  "properties": {
    "addr:full":"9812 Lockport Rd Niagara Falls NY 14304",
    "addr:housenumber":"9812",
    "addr:postcode":"14304",
    "addr:street":"Lockport Rd",
    "iso:country":"US",
    "sg:address":"9812 Lockport Rd",
    "sg:city":"Niagara Falls",
    "sg:classifiers":[
        {
            "category":"Education",
            "subcategory":"Vocational School",
            "type":"Public Place"
        }
    ],
    "sg:phone":"+1 716 298 1599",
    "sg:postcode":"14304",
    "sg:province":"NY",
    "sg:tags":[
        "training",
        "computer"
    ],
    "wof:name":"Technology Today",
    "wof:placetype":"venue"
},
  "geometry": {"coordinates":[-78.944052,43.121438],"type":"Point"}
}