{
  "type": "Feature",
  "properties": {
    "iso:country":"US",
    "sg:address":"114 Rock Rd",
    "sg:city":"Cobleskill",
    "sg:classifiers":[
        {
            "category":"Government",
            "subcategory":"Office",
            "type":"Public Place"
        }
    ],
    "sg:phone":"+1 518 234 0952",
    "sg:postcode":"12043",
    "sg:province":"NY",
    "sg:website":"www.schohariecounty-ny.gov",
    "wof:name":"Schoharie Public Trans",
    "wof:placetype":"venue"
},
  "geometry": {"coordinates":[-74.46404099999999,42.689886],"type":"Point"}
}