{
  "type": "Feature",
  "properties": {
    "iso:country":"US",
    "sg:address":"233 Robbins Ln",
    "sg:city":"Syosset",
    "sg:classifiers":[
        {
            "category":"Real Estate",
            "subcategory":"Real Estate Agent",
            "type":"Services"
        }
    ],
    "sg:phone":"+1 516 942 3854",
    "sg:postcode":"11791",
    "sg:province":"NY",
    "wof:name":"Everlast Sign & Svc",
    "wof:placetype":"venue"
},
  "geometry": {"coordinates":[-73.52070399999999,40.799755],"type":"Point"}
}