{
  "type": "Feature",
  "properties": {
    "iso:country":"US",
    "sg:address":"333 Gros Blvd",
    "sg:city":"Herkimer",
    "sg:classifiers":[
        {
            "category":"Building & Trades",
            "subcategory":"Construction",
            "type":"Services"
        }
    ],
    "sg:phone":"+1 315 866 3199",
    "sg:postcode":"13350",
    "sg:province":"NY",
    "sg:tags":[
        "commercial",
        "contractor"
    ],
    "wof:name":"Tioga Building Co Inc",
    "wof:placetype":"venue"
},
  "geometry": {"coordinates":[-74.954521,43.030759],"type":"Point"}
}