{
  "type": "Feature",
  "properties": {
    "addr:full":"209 State Hwy 59 Nanuet NY 10954",
    "addr:housenumber":"209",
    "addr:postcode":"10954",
    "addr:street":"State Hwy 59",
    "iso:country":"US",
    "sg:address":"209 State Hwy 59",
    "sg:city":"Nanuet",
    "sg:classifiers":[
        {
            "category":"Home & Garden",
            "subcategory":"Furniture",
            "type":"Retail Goods"
        }
    ],
    "sg:phone":"+1 845 627 3080",
    "sg:postcode":"10954",
    "sg:province":"NY",
    "sg:tags":[
        "bedding",
        "bed"
    ],
    "wof:name":"Rockaway Bedding Ctr",
    "wof:placetype":"venue"
},
  "geometry": {"coordinates":[-74.003308,41.093779],"type":"Point"}
}