{
  "type": "Feature",
  "properties": {
    "iso:country":"US",
    "sg:address":"908 State St",
    "sg:city":"Ogdensburg",
    "sg:classifiers":[
        {
            "category":"Shopping",
            "subcategory":"Pharmacy",
            "type":"Retail Goods"
        }
    ],
    "sg:phone":"+1 315 393 1714",
    "sg:postcode":"13669",
    "sg:province":"NY",
    "sg:tags":[
        "laboratory",
        "first",
        "aid",
        "photofinishing",
        "supply"
    ],
    "sg:website":"http://www.riteaid.com",
    "wof:name":"Rite Aid",
    "wof:placetype":"venue"
},
  "geometry": {"coordinates":[-75.487303,44.691137],"type":"Point"}
}