{
  "type": "Feature",
  "properties": {
    "iso:country":"US",
    "sg:address":"3080 Monroe Ave",
    "sg:city":"Rochester",
    "sg:classifiers":[
        {
            "category":"Shopping",
            "subcategory":"Clothing, Apparel, & Fashions",
            "type":"Retail Goods"
        }
    ],
    "sg:phone":"+1   ",
    "sg:postcode":"14618",
    "sg:province":"NY",
    "wof:name":"Rickys Tailor Shop",
    "wof:placetype":"venue"
},
  "geometry": {"coordinates":[-77.538363,43.102894],"type":"Point"}
}