{
  "type": "Feature",
  "properties": {
    "iso:country":"US",
    "sg:address":"2232 7th Ave",
    "sg:city":"New York",
    "sg:classifiers":[
        {
            "category":"Retail",
            "subcategory":"Repair Shop",
            "type":"Services"
        }
    ],
    "sg:phone":"+1 917 558 9575",
    "sg:postcode":"10027",
    "sg:province":"NY",
    "sg:tags":[
        "lock",
        "locksmith"
    ],
    "wof:name":"1 Hour All Day Emergency",
    "wof:placetype":"venue"
},
  "geometry": {"coordinates":[-73.94534299999999,40.813105],"type":"Point"}
}