{
  "type": "Feature",
  "properties": {
    "addr:full":"99 Mountain View Ln Queensbury NY 12804",
    "addr:housenumber":"99",
    "addr:postcode":"12804",
    "addr:street":"Mountain View Ln",
    "iso:country":"US",
    "sg:address":"99 Mountain View Ln",
    "sg:city":"Queensbury",
    "sg:classifiers":[
        {
            "category":"Real Estate",
            "subcategory":"Real Estate Agent",
            "type":"Services"
        }
    ],
    "sg:phone":"+1 518 793 9229",
    "sg:postcode":"12804",
    "sg:province":"NY",
    "wof:name":"Bartley Properties",
    "wof:placetype":"venue"
},
  "geometry": {"coordinates":[-73.71671600000001,43.343807],"type":"Point"}
}