{
  "type": "Feature",
  "properties": {
    "addr:full":"2760 English Rd Rochester NY 14616",
    "addr:housenumber":"2760",
    "addr:postcode":"14616",
    "addr:street":"English Rd",
    "iso:country":"US",
    "sg:address":"2760 English Rd",
    "sg:city":"Rochester",
    "sg:classifiers":[
        {
            "category":"Building & Trades",
            "subcategory":"Construction",
            "type":"Services"
        }
    ],
    "sg:phone":"+1 585 225 2109",
    "sg:postcode":"14616",
    "sg:province":"NY",
    "sg:tags":[
        "excavation",
        "grading",
        "plowing",
        "snow"
    ],
    "wof:name":"Yonckheere Bros Trcking Grdng",
    "wof:placetype":"venue"
},
  "geometry": {"coordinates":[-77.720978,43.238889],"type":"Point"}
}