{
  "type": "Feature",
  "properties": {
    "addr:full":"253 Milton Ave Ballston Spa NY 12020",
    "addr:housenumber":"253",
    "addr:postcode":"12020",
    "addr:street":"Milton Ave",
    "iso:country":"US",
    "sg:address":"253 Milton Ave",
    "sg:city":"Ballston Spa",
    "sg:classifiers":[
        {
            "category":"Autos & Motor Vehicles",
            "subcategory":"Fuel & Gas Station",
            "type":"Retail Goods"
        }
    ],
    "sg:phone":"+1 518 884 9533",
    "sg:postcode":"12020",
    "sg:province":"NY",
    "sg:tags":[
        "oil"
    ],
    "wof:name":"M & R Getty Mart",
    "wof:placetype":"venue"
},
  "geometry": {"coordinates":[-73.84961699999999,43.008442],"type":"Point"}
}