{
  "type": "Feature",
  "properties": {
    "addr:full":"12 Koch St New Rochelle NY 10801",
    "addr:housenumber":"12",
    "addr:postcode":"10801",
    "addr:street":"Koch St",
    "iso:country":"US",
    "sg:address":"12 Koch St",
    "sg:city":"New Rochelle",
    "sg:classifiers":[
        {
            "category":"Retail",
            "subcategory":"Animal Services",
            "type":"Services"
        }
    ],
    "sg:phone":"+1 914 637 0927",
    "sg:postcode":"10801",
    "sg:province":"NY",
    "wof:name":"Path Paws Pet Grooming",
    "wof:placetype":"venue"
},
  "geometry": {"coordinates":[-73.78533,40.923616],"type":"Point"}
}