{
  "type": "Feature",
  "properties": {
    "addr:full":"65 Lock St Clyde NY 14433",
    "addr:housenumber":"65",
    "addr:postcode":"14433",
    "addr:street":"Lock St",
    "iso:country":"US",
    "sg:address":"65 Lock St",
    "sg:city":"Clyde",
    "sg:classifiers":[
        {
            "category":"Real Estate",
            "subcategory":"Real Estate Operator",
            "type":"Services"
        }
    ],
    "sg:phone":"+1 315 923 3691",
    "sg:postcode":"14433",
    "sg:province":"NY",
    "sg:tags":[
        "apartment"
    ],
    "wof:name":"Midtown Square Apartments",
    "wof:placetype":"venue"
},
  "geometry": {"coordinates":[-76.872697,43.084984],"type":"Point"}
}