{
  "type": "Feature",
  "properties": {
    "addr:full":"26 8th St Carle Place NY 11514",
    "addr:housenumber":"26",
    "addr:postcode":"11514",
    "addr:street":"8Th St",
    "iso:country":"US",
    "sg:address":"26 8th St",
    "sg:city":"Carle Place",
    "sg:classifiers":[
        {
            "category":"Professional",
            "subcategory":"Business Services",
            "type":"Services"
        }
    ],
    "sg:phone":"+1 516 338 5991",
    "sg:postcode":"11514",
    "sg:province":"NY",
    "wof:name":"Eighth Street Designs",
    "wof:placetype":"venue"
},
  "geometry": {"coordinates":[-73.61210199999999,40.754895],"type":"Point"}
}