{
  "type": "Feature",
  "properties": {
    "addr:full":"189 Berkeley St Rochester NY 14607",
    "addr:housenumber":"189",
    "addr:postcode":"14607",
    "addr:street":"Berkeley St",
    "iso:country":"US",
    "sg:address":"189 Berkeley St",
    "sg:city":"Rochester",
    "sg:classifiers":[
        {
            "category":"Building & Trades",
            "subcategory":"Plumbing",
            "type":"Services"
        }
    ],
    "sg:phone":"+1 585 943 2589",
    "sg:postcode":"14607",
    "sg:province":"NY",
    "sg:tags":[
        "contractor"
    ],
    "wof:name":"Berkeley Heating & Cooling",
    "wof:placetype":"venue"
},
  "geometry": {"coordinates":[-77.578682,43.146693],"type":"Point"}
}