{
  "type": "Feature",
  "properties": {
    "addr:full":"2085 Valentine Ave Bronx NY 10457",
    "addr:housenumber":"2085",
    "addr:postcode":"10457",
    "addr:street":"Valentine Ave",
    "iso:country":"US",
    "sg:address":"2085 Valentine Ave",
    "sg:city":"Bronx",
    "sg:classifiers":[
        {
            "category":"Food & Beverages",
            "subcategory":"Groceries & Convenience Stores",
            "type":"Retail Goods"
        }
    ],
    "sg:phone":"+1 718 933 3449",
    "sg:postcode":"10457",
    "sg:province":"NY",
    "sg:tags":[
        "grocer"
    ],
    "wof:name":"Me Too Superette Inc",
    "wof:placetype":"venue"
},
  "geometry": {"coordinates":[-73.899469,40.853851],"type":"Point"}
}