{
  "type": "Feature",
  "properties": {
    "addr:full":"531 Washington St Watertown NY 13601",
    "addr:housenumber":"531",
    "addr:postcode":"13601",
    "addr:street":"Washington St",
    "iso:country":"US",
    "sg:address":"531 Washington St",
    "sg:city":"Watertown",
    "sg:classifiers":[
        {
            "category":"Health Services",
            "subcategory":"Doctor",
            "type":"Services"
        }
    ],
    "sg:phone":"+1 315 788 4740",
    "sg:postcode":"13601",
    "sg:province":"NY",
    "sg:tags":[
        "dentist"
    ],
    "wof:name":"Bregman & Dines",
    "wof:placetype":"venue"
},
  "geometry": {"coordinates":[-75.911777,43.969402],"type":"Point"}
}