{
  "type": "Feature",
  "properties": {
    "addr:full":"216 W 100th St New York NY 10025",
    "addr:housenumber":"216",
    "addr:postcode":"10025",
    "addr:street":"W 100Th St",
    "iso:country":"US",
    "sg:address":"216 W 100th St",
    "sg:city":"New York",
    "sg:classifiers":[
        {
            "category":"Retail",
            "subcategory":"Repair Shop",
            "type":"Services"
        }
    ],
    "sg:phone":"+1 646 224 9138",
    "sg:postcode":"10025",
    "sg:province":"NY",
    "sg:tags":[
        "lock",
        "locksmith"
    ],
    "wof:name":"Locksmith Service",
    "wof:placetype":"venue"
},
  "geometry": {"coordinates":[-73.969469,40.796896],"type":"Point"}
}