{
  "type": "Feature",
  "properties": {
    "iso:country":"US",
    "sg:address":"301 E 103rd St",
    "sg:city":"New York",
    "sg:classifiers":[
        {
            "category":"Building & Trades",
            "subcategory":"Locksmith",
            "type":"Services"
        }
    ],
    "sg:phone":"+1 212 595 5952",
    "sg:postcode":"10029",
    "sg:province":"NY",
    "sg:tags":[
        "key"
    ],
    "wof:name":"Open Door Locksmith",
    "wof:placetype":"venue"
},
  "geometry": {"coordinates":[-73.943275,40.788696],"type":"Point"}
}