{
  "type": "Feature",
  "properties": {
    "addr:full":"381 Hunt St Watertown NY 13601",
    "addr:housenumber":"381",
    "addr:postcode":"13601",
    "addr:street":"Hunt St",
    "iso:country":"US",
    "sg:address":"381 Hunt St",
    "sg:city":"Watertown",
    "sg:classifiers":[
        {
            "category":"Building & Trades",
            "subcategory":"Construction",
            "type":"Services"
        }
    ],
    "sg:phone":"+1 315 782 1546",
    "sg:postcode":"13601",
    "sg:province":"NY",
    "sg:tags":[
        "contractor"
    ],
    "wof:name":"P & M Construction",
    "wof:placetype":"venue"
},
  "geometry": {"coordinates":[-75.873784,43.971962],"type":"Point"}
}