{
  "type": "Feature",
  "properties": {
    "iso:country":"US",
    "sg:address":"263 Dakota St",
    "sg:city":"Rochester",
    "sg:classifiers":[
        {
            "category":"Building & Trades",
            "subcategory":"Construction",
            "type":"Services"
        }
    ],
    "sg:phone":"+1 585 436 3529",
    "sg:postcode":"14606",
    "sg:province":"NY",
    "sg:tags":[
        "sewer",
        "installation",
        "paving",
        "asphalt",
        "contractor"
    ],
    "wof:name":"Seneca Roadways Inc",
    "wof:placetype":"venue"
},
  "geometry": {"coordinates":[-77.652821,43.161246],"type":"Point"}
}