{
  "type": "Feature",
  "properties": {
    "addr:full":"234 4th Ave New York NY 10003",
    "addr:housenumber":"234",
    "addr:postcode":"10003",
    "addr:street":"4Th Ave",
    "iso:country":"US",
    "sg:address":"234 4th Ave",
    "sg:city":"New York",
    "sg:classifiers":[
        {
            "category":"Restaurant",
            "type":"Food & Drink"
        }
    ],
    "sg:menulink":"http://www.allmenus.com/ny/new-york/4757-perbacco/menu/",
    "sg:phone":"+1 212 253 2038",
    "sg:postcode":"10003",
    "sg:province":"NY",
    "sg:tags":[
        "italian"
    ],
    "wof:name":"Perbacco",
    "wof:placetype":"venue"
},
  "geometry": {"coordinates":[-73.98994999999999,40.734909],"type":"Point"}
}