{
  "type": "Feature",
  "properties": {
    "addr:full":"1512 Ave J Brooklyn NY 11230",
    "addr:housenumber":"1512",
    "addr:postcode":"11230",
    "addr:street":"Ave J",
    "iso:country":"US",
    "sg:address":"1512 Ave J",
    "sg:city":"Brooklyn",
    "sg:classifiers":[
        {
            "category":"Shopping",
            "subcategory":"News",
            "type":"Retail Goods"
        }
    ],
    "sg:phone":"+1   ",
    "sg:postcode":"11230",
    "sg:province":"NY",
    "wof:name":"Avenue J Newstand Inc",
    "wof:placetype":"venue"
},
  "geometry": {"coordinates":[-73.960464,40.625207],"type":"Point"}
}