{
  "type": "Feature",
  "properties": {
    "iso:country":"US",
    "sg:address":"5275 Co Rd 14",
    "sg:city":"Chase Mills",
    "sg:classifiers":[
        {
            "category":"Government",
            "subcategory":"Post Office",
            "type":"Public Place"
        }
    ],
    "sg:phone":"+1 315 322 5573",
    "sg:postcode":"13621",
    "sg:province":"NY",
    "wof:name":"US Post Office",
    "wof:placetype":"venue"
},
  "geometry": {"coordinates":[-75.048141,44.879624],"type":"Point"}
}