{
  "type": "Feature",
  "properties": {
    "addr:full":"2031 State Hwy 26 Oriskany Falls NY 13425",
    "addr:housenumber":"2031",
    "addr:postcode":"13425",
    "addr:street":"State Hwy 26 Oriskany",
    "iso:country":"US",
    "sg:address":"2031 State Hwy 26",
    "sg:city":"Oriskany Falls",
    "sg:classifiers":[
        {
            "category":"Building & Trades",
            "subcategory":"Electrical",
            "type":"Services"
        }
    ],
    "sg:phone":"+1 315 821 7948",
    "sg:postcode":"13425",
    "sg:province":"NY",
    "sg:tags":[
        "electrical",
        "contractor"
    ],
    "wof:name":"Emf Electric Inc",
    "wof:placetype":"venue"
},
  "geometry": {"coordinates":[-75.485996,42.959116],"type":"Point"}
}