{
  "type": "Feature",
  "properties": {
    "iso:country":"US",
    "sg:address":"1221 Ave of the Americas",
    "sg:city":"New York",
    "sg:classifiers":[
        {
            "category":"Mining & Drilling",
            "type":"Manufacturing & Wholesale Goods"
        }
    ],
    "sg:phone":"+1 212 371 1117",
    "sg:postcode":"10020",
    "sg:province":"NY",
    "sg:tags":[
        "exploration"
    ],
    "wof:name":"Patina Oil & Gas Corp",
    "wof:placetype":"venue"
},
  "geometry": {"coordinates":[-73.980986,40.759244],"type":"Point"}
}