{
  "type": "Feature",
  "properties": {
    "addr:full":"664 Amsterdam Ave Manhattan NY 10025",
    "addr:housenumber":"664",
    "addr:postcode":"10025",
    "addr:street":"Amsterdam Ave",
    "iso:country":"US",
    "sg:address":"664 Amsterdam Ave",
    "sg:city":"Manhattan",
    "sg:classifiers":[
        {
            "category":"Shopping",
            "subcategory":"Pets & Pet Supplies",
            "type":"Retail Goods"
        },
        {
            "category":"Retail",
            "subcategory":"Pet Boarding",
            "type":"Services"
        }
    ],
    "sg:phone":"+1 212 362 5221",
    "sg:postcode":"10025",
    "sg:province":"NY",
    "sg:tags":[
        "training",
        "boarding/pet",
        "groomers",
        "sitting"
    ],
    "sg:website":"www.playgroundpups.com",
    "wof:name":"Playground Pups",
    "wof:placetype":"venue"
},
  "geometry": {"coordinates":[-73.972109,40.791697],"type":"Point"}
}