{
  "type": "Feature",
  "properties": {
    "addr:full":"170 Adelphi St Brooklyn NY 11205",
    "addr:housenumber":"170",
    "addr:postcode":"11205",
    "addr:street":"Adelphi St",
    "iso:country":"US",
    "sg:address":"170 Adelphi St",
    "sg:city":"Brooklyn",
    "sg:classifiers":[
        {
            "category":"Organizations",
            "subcategory":"Religious Organization",
            "type":"Services"
        }
    ],
    "sg:phone":"+1 718 522 1422",
    "sg:postcode":"11205",
    "sg:province":"NY",
    "wof:name":"Prison Ministry",
    "wof:placetype":"venue"
},
  "geometry": {"coordinates":[-73.971716,40.692175],"type":"Point"}
}