{
  "type": "Feature",
  "properties": {
    "addr:full":"559 Straits Corners Rd Candor NY 13743",
    "addr:housenumber":"559",
    "addr:postcode":"13743",
    "addr:street":"Straits Corners Rd",
    "iso:country":"US",
    "sg:address":"559 Straits Corners Rd",
    "sg:city":"Candor",
    "sg:classifiers":[
        {
            "category":"Retail",
            "subcategory":"Animal Services",
            "type":"Services"
        }
    ],
    "sg:phone":"+1 607 659 3367",
    "sg:postcode":"13743",
    "sg:province":"NY",
    "wof:name":"Ace High Kennels",
    "wof:placetype":"venue"
},
  "geometry": {"coordinates":[-76.377213,42.191955],"type":"Point"}
}