{
  "type": "Feature",
  "properties": {
    "addr:full":"218 39th St Brooklyn NY 11232",
    "addr:housenumber":"218",
    "addr:postcode":"11232",
    "addr:street":"39Th St",
    "iso:country":"US",
    "sg:address":"218 39th St",
    "sg:city":"Brooklyn",
    "sg:classifiers":[
        {
            "category":"Wholesale",
            "subcategory":"Machinery & Supplies",
            "type":"Manufacturing & Wholesale Goods"
        }
    ],
    "sg:phone":"+1 718 768 0275",
    "sg:postcode":"11232",
    "sg:province":"NY",
    "sg:tags":[
        "equipment",
        "welding"
    ],
    "wof:name":"Atlantic Welding Supply Corp",
    "wof:placetype":"venue"
},
  "geometry": {"coordinates":[-74.009744,40.654797],"type":"Point"}
}