{
  "type": "Feature",
  "properties": {
    "addr:full":"801 Halsey St Brooklyn NY 11233",
    "addr:housenumber":"801",
    "addr:postcode":"11233",
    "addr:street":"Halsey St",
    "iso:country":"US",
    "sg:address":"801 Halsey St",
    "sg:city":"Brooklyn",
    "sg:classifiers":[
        {
            "category":"Restaurant",
            "type":"Food & Drink"
        }
    ],
    "sg:phone":"+1 347 405 9820",
    "sg:postcode":"11233",
    "sg:province":"NY",
    "sg:tags":[
        "seafood",
        "fish",
        "chip"
    ],
    "sg:website":"www.bedstuyfishfry.com",
    "wof:name":"Bed-Stuy Fish Fry",
    "wof:placetype":"venue"
},
  "geometry": {"coordinates":[-73.920517,40.685194],"type":"Point"}
}