{
  "type": "Feature",
  "properties": {
    "iso:country":"US",
    "sg:address":"4 E Fordham Rd",
    "sg:city":"Bronx",
    "sg:classifiers":[
        {
            "category":"Shopping",
            "subcategory":"Computers & Home Electronics",
            "type":"Retail Goods"
        }
    ],
    "sg:phone":"+1   ",
    "sg:postcode":"10468",
    "sg:province":"NY",
    "sg:tags":[
        "radio",
        "television",
        "consumer",
        "store"
    ],
    "wof:name":"Audio Town Inc",
    "wof:placetype":"venue"
},
  "geometry": {"coordinates":[-73.90034199999999,40.862417],"type":"Point"}
}