{
  "type": "Feature",
  "properties": {
    "iso:country":"US",
    "sg:address":"11 W 42nd St",
    "sg:city":"New York",
    "sg:classifiers":[
        {
            "category":"Wholesale",
            "subcategory":"Apparel",
            "type":"Manufacturing & Wholesale Goods"
        }
    ],
    "sg:phone":"+1 212 201 8194",
    "sg:postcode":"10036",
    "sg:province":"NY",
    "sg:tags":[
        "designer",
        "clothing"
    ],
    "wof:name":"Michael Kors LLC",
    "wof:placetype":"venue"
},
  "geometry": {"coordinates":[-73.98383200000001,40.754769],"type":"Point"}
}