{
  "type": "Feature",
  "properties": {
    "iso:country":"US",
    "sg:address":"97 N Grove St",
    "sg:city":"East Aurora",
    "sg:classifiers":[
        {
            "category":"Professional",
            "subcategory":"Research",
            "type":"Services"
        }
    ],
    "sg:phone":"+1 716 655 1234",
    "sg:postcode":"14052",
    "sg:province":"NY",
    "sg:tags":[
        "laboratory"
    ],
    "wof:name":"Aurora Labs LLC",
    "wof:placetype":"venue"
},
  "geometry": {"coordinates":[-78.61779799999999,42.769687],"type":"Point"}
}