{
  "type": "Feature",
  "properties": {
    "iso:country":"US",
    "sg:address":"10 Jacqueline Way",
    "sg:city":"Geneseo",
    "sg:classifiers":[
        {
            "category":"Organizations",
            "subcategory":"Religious Organization",
            "type":"Services"
        }
    ],
    "sg:phone":"+1 585 243 0088",
    "sg:postcode":"14454",
    "sg:province":"NY",
    "sg:tags":[
        "monastery",
        "convent"
    ],
    "wof:name":"Sisters Of Mercy",
    "wof:placetype":"venue"
},
  "geometry": {"coordinates":[-77.799072,42.797176],"type":"Point"}
}