{
  "type": "Feature",
  "properties": {
    "addr:full":"305 E 40th St Frnt New York NY 10016",
    "addr:housenumber":"305",
    "addr:postcode":"10016",
    "addr:street":"E 40Th St",
    "iso:country":"US",
    "sg:address":"305 E 40th St Frnt",
    "sg:city":"New York",
    "sg:classifiers":[
        {
            "category":"Real Estate",
            "subcategory":"Real Estate Operator",
            "type":"Services"
        }
    ],
    "sg:phone":"+1 212 661 3417",
    "sg:postcode":"10016",
    "sg:province":"NY",
    "sg:tags":[
        "apartment"
    ],
    "wof:name":"305 East 40 St Owners",
    "wof:placetype":"venue"
},
  "geometry": {"coordinates":[-73.973,40.748501],"type":"Point"}
}