{
  "type": "Feature",
  "properties": {
    "addr:full":"1606 Crosby Ave Bronx NY 10461",
    "addr:housenumber":"1606",
    "addr:postcode":"10461",
    "addr:street":"Crosby Ave",
    "iso:country":"US",
    "sg:address":"1606 Crosby Ave",
    "sg:city":"Bronx",
    "sg:classifiers":[
        {
            "category":"Shopping",
            "subcategory":"Jewelry",
            "type":"Retail Goods"
        }
    ],
    "sg:phone":"+1 718 904 1094",
    "sg:postcode":"10461",
    "sg:province":"NY",
    "wof:name":"PELHAM BAY GOLD",
    "wof:placetype":"venue"
},
  "geometry": {"coordinates":[-73.830298,40.844118],"type":"Point"}
}