{
  "type": "Feature",
  "properties": {
    "iso:country":"US",
    "sg:address":"505 Driggs Ave",
    "sg:city":"Brooklyn",
    "sg:classifiers":[
        {
            "category":"Manufacturing",
            "subcategory":"Furniture",
            "type":"Manufacturing & Wholesale Goods"
        },
        {
            "category":"Home & Garden",
            "subcategory":"Furniture",
            "type":"Retail Goods"
        }
    ],
    "sg:phone":"+1 718 782 1727",
    "sg:postcode":"11211",
    "sg:province":"NY",
    "sg:tags":[
        "designer",
        "mfg",
        "builder",
        "custom",
        "wood",
        "pro",
        "household"
    ],
    "sg:website":"http://www.atelierviollet.com",
    "wof:name":"Atelier Viollet Corp",
    "wof:placetype":"venue"
},
  "geometry": {"coordinates":[-73.955254,40.71814],"type":"Point"}
}