{
  "type": "Feature",
  "properties": {
    "addr:full":"2452 Bronx Park E Bronx NY 10467",
    "addr:housenumber":"2452",
    "addr:postcode":"10467",
    "addr:street":"Bronx Park E",
    "iso:country":"US",
    "sg:address":"2452 Bronx Park E",
    "sg:city":"Bronx",
    "sg:classifiers":[
        {
            "category":"Health Services",
            "subcategory":"Doctor",
            "type":"Services"
        }
    ],
    "sg:phone":"+1 718 519 8600",
    "sg:postcode":"10467",
    "sg:province":"NY",
    "sg:tags":[
        "medical"
    ],
    "wof:name":"Henriquez Mario",
    "wof:placetype":"venue"
},
  "geometry": {"coordinates":[-73.870434,40.862277],"type":"Point"}
}