{
  "type": "Feature",
  "properties": {
    "iso:country":"US",
    "sg:address":"2182 State Hwy 95",
    "sg:city":"Bombay",
    "sg:classifiers":[
        {
            "category":"Autos & Motor Vehicles",
            "subcategory":"Automobile Sales",
            "type":"Retail Goods"
        }
    ],
    "sg:phone":"+1 518 358 9687",
    "sg:postcode":"12914",
    "sg:province":"NY",
    "sg:tags":[
        "car",
        "dealer"
    ],
    "wof:name":"Parker's Pit",
    "wof:placetype":"venue"
},
  "geometry": {"coordinates":[-74.61909799999999,44.937977],"type":"Point"}
}