{
  "type": "Feature",
  "properties": {
    "addr:full":"155 Ave of the Americas New York NY 10013",
    "addr:housenumber":"155",
    "addr:postcode":"10013",
    "addr:street":"Ave Of The Americas",
    "iso:country":"US",
    "sg:address":"155 Ave of the Americas",
    "sg:city":"New York",
    "sg:classifiers":[
        {
            "category":"Retail",
            "subcategory":"Repair Shop",
            "type":"Services"
        }
    ],
    "sg:phone":"+1 917 677 1105",
    "sg:postcode":"10013",
    "sg:province":"NY",
    "sg:tags":[
        "lock",
        "locksmith"
    ],
    "wof:name":"24 Hour 7 Day Emerg Locksmith",
    "wof:placetype":"venue"
},
  "geometry": {"coordinates":[-74.004257,40.725033],"type":"Point"}
}