{
  "type": "Feature",
  "properties": {
    "iso:country":"US",
    "sg:address":"630 Ridge Rd W",
    "sg:city":"Rochester",
    "sg:classifiers":[
        {
            "category":"Restaurant",
            "type":"Food & Drink"
        },
        {
            "category":"Ice Cream",
            "type":"Food & Drink"
        }
    ],
    "sg:menulink":"http://www.allmenus.com/ny/rochester/217005-abbotts-frozen-custard/menu/",
    "sg:phone":"+1 585 663 6360",
    "sg:postcode":"14615",
    "sg:province":"NY",
    "sg:tags":[
        "american",
        "ice",
        "cream"
    ],
    "wof:name":"Abbott's Frozen Custard",
    "wof:placetype":"venue"
},
  "geometry": {"coordinates":[-77.6435,43.202271],"type":"Point"}
}