{
  "type": "Feature",
  "properties": {
    "iso:country":"US",
    "sg:address":"9 Woodland Rd",
    "sg:city":"Loch Sheldrake",
    "sg:classifiers":[
        {
            "category":"Real Estate",
            "subcategory":"Real Estate Operator",
            "type":"Services"
        }
    ],
    "sg:phone":"+1 845 434 6200",
    "sg:postcode":"12759",
    "sg:province":"NY",
    "sg:tags":[
        "apartment"
    ],
    "wof:name":"Woodland Townhouses Co",
    "wof:placetype":"venue"
},
  "geometry": {"coordinates":[-74.65851000000001,41.777299],"type":"Point"}
}