{
  "type": "Feature",
  "properties": {
    "iso:country":"US",
    "sg:address":"57 Halley Dr",
    "sg:city":"Pomona",
    "sg:classifiers":[
        {
            "category":"Professional",
            "type":"Services"
        }
    ],
    "sg:phone":"+1 845 364 0183",
    "sg:postcode":"10970",
    "sg:province":"NY",
    "sg:tags":[
        "establishment"
    ],
    "wof:name":"Paws Unlimited",
    "wof:placetype":"venue"
},
  "geometry": {"coordinates":[-74.052463,41.198778],"type":"Point"}
}