{
  "type": "Feature",
  "properties": {
    "iso:country":"US",
    "sg:address":"302 Winchester St",
    "sg:city":"Rochester",
    "sg:classifiers":[
        {
            "category":"Retail",
            "subcategory":"Repair Shop",
            "type":"Services"
        }
    ],
    "sg:phone":"+1 585 663 6581",
    "sg:postcode":"14615",
    "sg:province":"NY",
    "sg:tags":[
        "repairing",
        "lawn",
        "mower"
    ],
    "wof:name":"Mastercare Small Engine Repair",
    "wof:placetype":"venue"
},
  "geometry": {"coordinates":[-77.632739,43.205762],"type":"Point"}
}