{
  "type": "Feature",
  "properties": {
    "addr:full":"5030 Broadway New York NY 10034",
    "addr:housenumber":"5030",
    "addr:postcode":"10034",
    "addr:street":"Broadway",
    "iso:country":"US",
    "sg:address":"5030 Broadway",
    "sg:city":"New York",
    "sg:classifiers":[
        {
            "category":"Insurance",
            "subcategory":"Hazard Insurance",
            "type":"Services"
        }
    ],
    "sg:phone":"+1 212 928 0100",
    "sg:postcode":"10034",
    "sg:province":"NY",
    "wof:name":"GWB Insurance Brokerage",
    "wof:placetype":"venue"
},
  "geometry": {"coordinates":[-73.91684100000001,40.869278],"type":"Point"}
}