{
  "type": "Feature",
  "properties": {
    "addr:full":"25 W Crescent Ave Hamburg NY 14075",
    "addr:housenumber":"25",
    "addr:postcode":"14075",
    "addr:street":"W Crescent Ave",
    "iso:country":"US",
    "sg:address":"25 W Crescent Ave",
    "sg:city":"Hamburg",
    "sg:classifiers":[
        {
            "category":"Education",
            "subcategory":"Special Training",
            "type":"Public Place"
        }
    ],
    "sg:phone":"+1 716 649 3200",
    "sg:postcode":"14075",
    "sg:province":"NY",
    "sg:tags":[
        "guitar",
        "instrument",
        "amplifier",
        "musical"
    ],
    "wof:name":"Bell Helen Studios",
    "wof:placetype":"venue"
},
  "geometry": {"coordinates":[-78.831018,42.712694],"type":"Point"}
}