{
  "type": "Feature",
  "properties": {
    "addr:full":"120 Concord St Brooklyn NY 11201",
    "addr:housenumber":"120",
    "addr:postcode":"11201",
    "addr:street":"Concord St",
    "iso:country":"US",
    "sg:address":"120 Concord St",
    "sg:city":"Brooklyn",
    "sg:classifiers":[
        {
            "category":"Shopping",
            "subcategory":"Stationery & Office Supplies",
            "type":"Retail Goods"
        }
    ],
    "sg:phone":"+1 718 625 1184",
    "sg:postcode":"11201",
    "sg:province":"NY",
    "sg:tags":[
        "equipment"
    ],
    "wof:name":"Sharda Enterprises Inc",
    "wof:placetype":"venue"
},
  "geometry": {"coordinates":[-73.98699999999999,40.697701],"type":"Point"}
}