{
  "type": "Feature",
  "properties": {
    "addr:full":"5611 56th Drive Maspeth NY 11378",
    "addr:housenumber":"5611",
    "addr:postcode":"11378",
    "addr:street":"56Th Drive",
    "iso:country":"US",
    "sg:address":"5611 56th Drive",
    "sg:city":"Maspeth",
    "sg:classifiers":[
        {
            "category":"Restaurant",
            "type":"Food & Drink"
        }
    ],
    "sg:phone":"+1 718 416 4266",
    "sg:postcode":"11378",
    "sg:province":"NY",
    "sg:tags":[
        "seafood"
    ],
    "wof:name":"Mts International",
    "wof:placetype":"venue"
},
  "geometry": {"coordinates":[-73.91452,40.724503],"type":"Point"}
}