{
  "type": "Feature",
  "properties": {
    "iso:country":"US",
    "sg:address":"235 E 53 St",
    "sg:city":"New York",
    "sg:classifiers":[
        {
            "category":"Restaurant",
            "type":"Food & Drink"
        }
    ],
    "sg:phone":"+1   ",
    "sg:postcode":"10022",
    "sg:province":"NY",
    "sg:tags":[
        "eating"
    ],
    "wof:name":"Atlizxo Brothers",
    "wof:placetype":"venue"
},
  "geometry": {"coordinates":[-73.967705,40.757156],"type":"Point"}
}