{
  "type": "Feature",
  "properties": {
    "addr:full":"7 Clayton Ave Cortland NY 13045",
    "addr:housenumber":"7",
    "addr:postcode":"13045",
    "addr:street":"Clayton Ave",
    "iso:country":"US",
    "sg:address":"7 Clayton Ave",
    "sg:city":"Cortland",
    "sg:classifiers":[
        {
            "category":"Health Services",
            "subcategory":"Hospital",
            "type":"Services"
        }
    ],
    "sg:phone":"+1 607 758 6100",
    "sg:postcode":"13045",
    "sg:province":"NY",
    "sg:tags":[
        "mental"
    ],
    "wof:name":"Cortland County Mental Health",
    "wof:placetype":"venue"
},
  "geometry": {"coordinates":[-76.180982,42.598016],"type":"Point"}
}