{
  "type": "Feature",
  "properties": {
    "addr:full":"123 Fort Covington St Malone NY 12953",
    "addr:housenumber":"123",
    "addr:postcode":"12953",
    "addr:street":"Fort Covington St",
    "iso:country":"US",
    "sg:address":"123 Fort Covington St",
    "sg:city":"Malone",
    "sg:classifiers":[
        {
            "category":"Professional",
            "subcategory":"Management & Consulting",
            "type":"Services"
        },
        {
            "category":"Professional",
            "subcategory":"Advertising",
            "type":"Services"
        }
    ],
    "sg:phone":"+1 518 483 0891",
    "sg:postcode":"12953",
    "sg:province":"NY",
    "sg:tags":[
        "consultant",
        "direct",
        "shipping",
        "mail"
    ],
    "wof:name":"Shipping Shop",
    "wof:placetype":"venue"
},
  "geometry": {"coordinates":[-74.306313,44.855094],"type":"Point"}
}