{
  "type": "Feature",
  "properties": {
    "iso:country":"US",
    "sg:address":"396 15th St",
    "sg:city":"Brooklyn",
    "sg:classifiers":[
        {
            "category":"Building & Trades",
            "subcategory":"Electrical",
            "type":"Services"
        }
    ],
    "sg:phone":"+1 718 369 8200",
    "sg:postcode":"11215",
    "sg:province":"NY",
    "sg:tags":[
        "electrical",
        "contractor"
    ],
    "wof:name":"Jsi Service Corp",
    "wof:placetype":"venue"
},
  "geometry": {"coordinates":[-73.983411,40.662805],"type":"Point"}
}