{
  "type": "Feature",
  "properties": {
    "iso:country":"US",
    "sg:address":"950 Gerard Ave",
    "sg:city":"Bronx",
    "sg:classifiers":[
        {
            "category":"Professional",
            "subcategory":"Detective & Security Services",
            "type":"Services"
        }
    ],
    "sg:phone":"+1 718 590 3900",
    "sg:postcode":"10452",
    "sg:province":"NY",
    "sg:tags":[
        "investigator"
    ],
    "wof:name":"Compudata Investigatives Assoc",
    "wof:placetype":"venue"
},
  "geometry": {"coordinates":[-73.923579,40.829467],"type":"Point"}
}