{
  "type": "Feature",
  "properties": {
    "iso:country":"US",
    "sg:address":"4912 Ave D",
    "sg:city":"Brooklyn",
    "sg:classifiers":[
        {
            "category":"Building & Trades",
            "subcategory":"Construction",
            "type":"Services"
        }
    ],
    "sg:phone":"+1 718 629 2580",
    "sg:postcode":"11203",
    "sg:province":"NY",
    "sg:tags":[
        "contractor"
    ],
    "wof:name":"Distinctive Dsign Masnry Cnstr",
    "wof:placetype":"venue"
},
  "geometry": {"coordinates":[-73.92944199999999,40.642052],"type":"Point"}
}