{
  "type": "Feature",
  "properties": {
    "addr:full":"2847 Dudley Ave Bronx NY 10461",
    "addr:housenumber":"2847",
    "addr:postcode":"10461",
    "addr:street":"Dudley Ave",
    "iso:country":"US",
    "sg:address":"2847 Dudley Ave",
    "sg:city":"Bronx",
    "sg:classifiers":[
        {
            "category":"Utilities",
            "subcategory":"Refuse",
            "type":"Services"
        }
    ],
    "sg:phone":"+1   ",
    "sg:postcode":"10461",
    "sg:province":"NY",
    "sg:tags":[
        "disposal"
    ],
    "wof:name":"Njc Carting Corporation",
    "wof:placetype":"venue"
},
  "geometry": {"coordinates":[-73.834602,40.84],"type":"Point"}
}