{
  "type": "Feature",
  "properties": {
    "addr:full":"161 Fort Washington Avenue New York NY 10032",
    "addr:housenumber":"161",
    "addr:postcode":"10032",
    "addr:street":"Fort Washington Avenue",
    "iso:country":"US",
    "sg:address":"161 Fort Washington Avenue",
    "sg:city":"New York",
    "sg:classifiers":[
        {
            "category":"Health Services",
            "subcategory":"Doctor",
            "type":"Services"
        }
    ],
    "sg:phone":"+1 212 305 6136",
    "sg:postcode":"10032",
    "sg:province":"NY",
    "wof:name":"Whelan Richard L MD",
    "wof:placetype":"venue"
},
  "geometry": {"coordinates":[-73.94287,40.840653],"type":"Point"}
}