{
  "type": "Feature",
  "properties": {
    "iso:country":"US",
    "sg:address":"25 William St",
    "sg:city":"Tonawanda",
    "sg:classifiers":[
        {
            "category":"Retail",
            "subcategory":"Funeral Services",
            "type":"Services"
        }
    ],
    "sg:phone":"+1 716 693 1551",
    "sg:postcode":"14150",
    "sg:province":"NY",
    "sg:tags":[
        "director"
    ],
    "wof:name":"John O Roth Funeral Home",
    "wof:placetype":"venue"
},
  "geometry": {"coordinates":[-78.876141,43.017311],"type":"Point"}
}