{
  "type": "Feature",
  "properties": {
    "iso:country":"US",
    "sg:address":"84 Moore St",
    "sg:city":"Brooklyn",
    "sg:classifiers":[
        {
            "category":"Restaurant",
            "type":"Food & Drink"
        }
    ],
    "sg:phone":"+1 718 388 5290",
    "sg:postcode":"11206",
    "sg:province":"NY",
    "wof:name":"Morena Restaurant",
    "wof:placetype":"venue"
},
  "geometry": {"coordinates":[-73.941159,40.703808],"type":"Point"}
}