{
  "type": "Feature",
  "properties": {
    "addr:full":"5 Hilltop Dr Great Neck NY 11021",
    "addr:housenumber":"5",
    "addr:postcode":"11021",
    "addr:street":"Hilltop Dr",
    "iso:country":"US",
    "sg:address":"5 Hilltop Dr",
    "sg:city":"Great Neck",
    "sg:classifiers":[
        {
            "category":"Real Estate",
            "subcategory":"Real Estate Operator",
            "type":"Services"
        }
    ],
    "sg:phone":"+1 516 482 6707",
    "sg:postcode":"11021",
    "sg:province":"NY",
    "sg:tags":[
        "building",
        "nonresidential"
    ],
    "wof:name":"Cedardale",
    "wof:placetype":"venue"
},
  "geometry": {"coordinates":[-73.734703,40.792828],"type":"Point"}
}