{
  "type": "Feature",
  "properties": {
    "addr:full":"39 N Main St Brockport NY 14420",
    "addr:housenumber":"39",
    "addr:postcode":"14420",
    "addr:street":"N Main St",
    "iso:country":"US",
    "sg:address":"39 N Main St",
    "sg:city":"Brockport",
    "sg:classifiers":[
        {
            "category":"Building & Trades",
            "subcategory":"Construction",
            "type":"Services"
        }
    ],
    "sg:phone":"+1 585 395 9209",
    "sg:postcode":"14420",
    "sg:province":"NY",
    "sg:tags":[
        "masonry",
        "contractor"
    ],
    "wof:name":"Heaster Building Restoration",
    "wof:placetype":"venue"
},
  "geometry": {"coordinates":[-77.937106,43.220106],"type":"Point"}
}