{
  "type": "Feature",
  "properties": {
    "iso:country":"US",
    "sg:address":"17 W 56 St",
    "sg:city":"New York",
    "sg:classifiers":[
        {
            "category":"Wholesale",
            "subcategory":"Machinery & Supplies",
            "type":"Manufacturing & Wholesale Goods"
        }
    ],
    "sg:phone":"+1 212 541 6660",
    "sg:postcode":"10019",
    "sg:province":"NY",
    "sg:tags":[
        "equipment",
        "skin",
        "care"
    ],
    "wof:name":"Nemectron-Belmont Inc",
    "wof:placetype":"venue"
},
  "geometry": {"coordinates":[-73.97725,40.76349],"type":"Point"}
}