{
  "type": "Feature",
  "properties": {
    "addr:full":"1975 Davidson Ave Bronx NY 10453",
    "addr:housenumber":"1975",
    "addr:postcode":"10453",
    "addr:street":"Davidson Ave",
    "iso:country":"US",
    "sg:address":"1975 Davidson Ave",
    "sg:city":"Bronx",
    "sg:classifiers":[
        {
            "category":"Freight",
            "type":"Transportation"
        }
    ],
    "sg:phone":"+1   ",
    "sg:postcode":"10453",
    "sg:province":"NY",
    "sg:tags":[
        "courier"
    ],
    "wof:name":"Transporte Centroamerican Ex",
    "wof:placetype":"venue"
},
  "geometry": {"coordinates":[-73.908637,40.853752],"type":"Point"}
}