{
  "type": "Feature",
  "properties": {
    "iso:country":"US",
    "sg:address":"2166 New York Ave",
    "sg:city":"Brooklyn",
    "sg:classifiers":[
        {
            "category":"Wholesale",
            "subcategory":"Medical Equipment & Supplies",
            "type":"Manufacturing & Wholesale Goods"
        }
    ],
    "sg:phone":"+1 718 377 4100",
    "sg:postcode":"11210",
    "sg:province":"NY",
    "sg:tags":[
        "physician",
        "surgeon"
    ],
    "wof:name":"Help In A Heartbeat",
    "wof:placetype":"venue"
},
  "geometry": {"coordinates":[-73.942542,40.618944],"type":"Point"}
}