{
  "type": "Feature",
  "properties": {
    "addr:full":"1439 1st Ave, E 75 St New York NY 10021",
    "addr:housenumber":"1439;75",
    "addr:postcode":"10021",
    "addr:street":"1St Ave E;St",
    "iso:country":"US",
    "sg:address":"1439 1st Ave, E 75 St",
    "sg:city":"New York",
    "sg:classifiers":[
        {
            "category":"Shopping",
            "subcategory":"Thrift Store",
            "type":"Retail Goods"
        }
    ],
    "sg:phone":"+1 212 288 3457",
    "sg:postcode":"10021",
    "sg:province":"NY",
    "sg:website":"www.thriffany.com/",
    "wof:name":"Thriffany Thrift Store",
    "wof:placetype":"venue"
},
  "geometry": {"coordinates":[-73.98685999999999,40.725527],"type":"Point"}
}