{
  "type": "Feature",
  "properties": {
    "addr:full":"150 Varick St New York NY 10013",
    "addr:housenumber":"150",
    "addr:postcode":"10013",
    "addr:street":"Varick St",
    "iso:country":"US",
    "sg:address":"150 Varick St",
    "sg:city":"New York",
    "sg:classifiers":[
        {
            "category":"Professional",
            "subcategory":"Art Services",
            "type":"Services"
        }
    ],
    "sg:phone":"+1 212 675 9666",
    "sg:postcode":"10013",
    "sg:province":"NY",
    "sg:tags":[
        "graphic",
        "designer"
    ],
    "wof:name":"Highrock Graphics",
    "wof:placetype":"venue"
},
  "geometry": {"coordinates":[-74.005646,40.725918],"type":"Point"}
}