{
  "type": "Feature",
  "properties": {
    "addr:full":"110 W 26th St New York NY 10001",
    "addr:housenumber":"110",
    "addr:postcode":"10001",
    "addr:street":"W 26Th St",
    "iso:country":"US",
    "sg:address":"110 W 26th St",
    "sg:city":"New York",
    "sg:classifiers":[
        {
            "category":"Real Estate",
            "subcategory":"Real Estate Operator",
            "type":"Services"
        }
    ],
    "sg:phone":"+1 212 267 7778",
    "sg:postcode":"10001",
    "sg:province":"NY",
    "sg:tags":[
        "building"
    ],
    "wof:name":"Samuel I Gindi",
    "wof:placetype":"venue"
},
  "geometry": {"coordinates":[-73.994078,40.745816],"type":"Point"}
}