{
  "type": "Feature",
  "properties": {
    "addr:full":"173 Beechwood Ave New Rochelle NY 10801",
    "addr:housenumber":"173",
    "addr:postcode":"10801",
    "addr:street":"Beechwood Ave",
    "iso:country":"US",
    "sg:address":"173 Beechwood Ave",
    "sg:city":"New Rochelle",
    "sg:classifiers":[
        {
            "category":"Manufacturing",
            "subcategory":"Apparel",
            "type":"Manufacturing & Wholesale Goods"
        }
    ],
    "sg:phone":"+1 914 636 6672",
    "sg:postcode":"10801",
    "sg:province":"NY",
    "sg:tags":[
        "boy",
        "clothing",
        "furnishing"
    ],
    "wof:name":"Imp Originals Inc",
    "wof:placetype":"venue"
},
  "geometry": {"coordinates":[-73.795295,40.90614],"type":"Point"}
}