{
  "type": "Feature",
  "properties": {
    "iso:country":"US",
    "sg:address":"560 Prospect Avenue",
    "sg:city":"Bronx",
    "sg:classifiers":[
        {
            "category":"Health Services",
            "subcategory":"Health Practitioner",
            "type":"Services"
        }
    ],
    "sg:phone":"+1 718 402 0700",
    "sg:postcode":"10455",
    "sg:province":"NY",
    "sg:tags":[
        "therapy",
        "physical"
    ],
    "wof:name":"Gerard Medical PC",
    "wof:placetype":"venue"
},
  "geometry": {"coordinates":[-73.90425399999999,40.812473],"type":"Point"}
}