{
  "type": "Feature",
  "properties": {
    "iso:country":"US",
    "sg:address":"130 Pondfield Rd W",
    "sg:city":"Bronxville",
    "sg:classifiers":[
        {
            "category":"Health Services",
            "subcategory":"Doctor",
            "type":"Services"
        }
    ],
    "sg:phone":"+1 914 771 7800",
    "sg:postcode":"10708",
    "sg:province":"NY",
    "sg:tags":[
        "physician",
        "surgeon"
    ],
    "wof:name":"Ahmed Asif MD",
    "wof:placetype":"venue"
},
  "geometry": {"coordinates":[-73.842461,40.947066],"type":"Point"}
}