{
  "type": "Feature",
  "properties": {
    "addr:full":"James St Syracuse NY 13203",
    "addr:postcode":"13203",
    "addr:street":"James St",
    "iso:country":"US",
    "sg:address":"James St",
    "sg:city":"Syracuse",
    "sg:classifiers":[
        {
            "category":"Professional",
            "subcategory":"Accounting & Tax Preparation",
            "type":"Services"
        },
        {
            "category":"Professional",
            "subcategory":"Lawyer & Legal Services",
            "type":"Services"
        }
    ],
    "sg:phone":"+1 315 849 1155",
    "sg:postcode":"13203",
    "sg:province":"NY",
    "sg:tags":[
        "attorney",
        "reporting",
        "representative",
        "taxes-consultants"
    ],
    "sg:website":"http://www.wallandassociates.net",
    "wof:name":"E Kenneth Wall PC",
    "wof:placetype":"venue"
},
  "geometry": {"coordinates":[-76.128601,43.062149],"type":"Point"}
}