{
  "type": "Feature",
  "properties": {
    "iso:country":"US",
    "name:eng_x_preferred":[
        "5 Av/59 St"
    ],
    "wof:name":"5 Av/59 St Station",
    "wof:placetype":"venue"
},
  "geometry": {"coordinates":[-73.973347,40.764811],"type":"Point"}
}