{
  "type": "Feature",
  "properties": {
    "addr:full":"300 Trade Zone Dr Ronkonkoma NY 11779",
    "addr:housenumber":"300",
    "addr:postcode":"11779",
    "addr:street":"Trade Zone Dr",
    "iso:country":"US",
    "sg:address":"300 Trade Zone Dr",
    "sg:city":"Ronkonkoma",
    "sg:classifiers":[
        {
            "category":"Manufacturing",
            "subcategory":"Textiles",
            "type":"Manufacturing & Wholesale Goods"
        }
    ],
    "sg:phone":"+1 631 467 8800",
    "sg:postcode":"11779",
    "sg:province":"NY",
    "sg:tags":[
        "a",
        "gallery",
        "mill",
        "fabric",
        "mfg"
    ],
    "wof:name":"Scalamandre Silks Inc",
    "wof:placetype":"venue"
},
  "geometry": {"coordinates":[-73.091917,40.785492],"type":"Point"}
}