{
  "type": "Feature",
  "properties": {
    "addr:full":"6910 5th Avenue Brooklyn NY 11209",
    "addr:housenumber":"6910",
    "addr:postcode":"11209",
    "addr:street":"5Th Avenue",
    "iso:country":"US",
    "sg:address":"6910 5th Avenue",
    "sg:city":"Brooklyn",
    "sg:classifiers":[
        {
            "category":"Education",
            "subcategory":"School",
            "type":"Public Place"
        }
    ],
    "sg:phone":"+1 718 833 5555",
    "sg:postcode":"11209",
    "sg:province":"NY",
    "sg:tags":[
        "high",
        "middle",
        "elementary"
    ],
    "wof:name":"C C B School Brooklyn",
    "wof:placetype":"venue"
},
  "geometry": {"coordinates":[-74.02118,40.633426],"type":"Point"}
}