{
  "type": "Feature",
  "properties": {
    "addr:full":"3505 Big Tree Rd Hamburg NY 14075",
    "addr:housenumber":"3505",
    "addr:postcode":"14075",
    "addr:street":"Big Tree Rd",
    "iso:country":"US",
    "sg:address":"3505 Big Tree Rd",
    "sg:city":"Hamburg",
    "sg:classifiers":[
        {
            "category":"Retail",
            "subcategory":"Repair Shop",
            "type":"Services"
        }
    ],
    "sg:phone":"+1 716 627 7277",
    "sg:postcode":"14075",
    "sg:province":"NY",
    "sg:tags":[
        "welding"
    ],
    "wof:name":"Southtowns Welding & Fab",
    "wof:placetype":"venue"
},
  "geometry": {"coordinates":[-78.854339,42.772034],"type":"Point"}
}