{
  "type": "Feature",
  "properties": {
    "iso:country":"US",
    "sg:address":"147 Heyward St",
    "sg:city":"Brooklyn",
    "sg:classifiers":[
        {
            "category":"Social Services",
            "type":"Services"
        }
    ],
    "sg:phone":"+1   ",
    "sg:postcode":"11206",
    "sg:province":"NY",
    "wof:name":"Jacobowitz Aaron",
    "wof:placetype":"venue"
},
  "geometry": {"coordinates":[-73.954111,40.703025],"type":"Point"}
}