{
  "type": "Feature",
  "properties": {
    "iso:country":"US",
    "sg:address":"91 Firwood Rd",
    "sg:city":"Port Washington",
    "sg:classifiers":[
        {
            "category":"Manufacturing",
            "subcategory":"Printing",
            "type":"Manufacturing & Wholesale Goods"
        }
    ],
    "sg:phone":"+1 516 944 6397",
    "sg:postcode":"11050",
    "sg:province":"NY",
    "sg:tags":[
        "newspaper",
        "publishing"
    ],
    "wof:name":"Port Washington Sentinel",
    "wof:placetype":"venue"
},
  "geometry": {"coordinates":[-73.714538,40.846122],"type":"Point"}
}