{
  "type": "Feature",
  "properties": {
    "addr:full":"143 Saw Mill River Rd Elmsford NY 10523",
    "addr:housenumber":"143",
    "addr:postcode":"10523",
    "addr:street":"Saw Mill River Rd",
    "iso:country":"US",
    "sg:address":"143 Saw Mill River Rd",
    "sg:city":"Elmsford",
    "sg:classifiers":[
        {
            "category":"Building & Trades",
            "subcategory":"Construction",
            "type":"Services"
        }
    ],
    "sg:phone":"+1 914 347 5226",
    "sg:postcode":"10523",
    "sg:province":"NY",
    "sg:tags":[
        "designer",
        "dealer",
        "pool",
        "swimming"
    ],
    "wof:name":"Aqua Leisure Pool & Spa",
    "wof:placetype":"venue"
},
  "geometry": {"coordinates":[-73.81639199999999,41.058607],"type":"Point"}
}