{
  "type": "Feature",
  "properties": {
    "iso:country":"US",
    "sg:address":"11751 State Hwy 98",
    "sg:city":"Freedom",
    "sg:classifiers":[
        {
            "category":"Manufacturing",
            "subcategory":"Motor Vehicles & Parts",
            "type":"Manufacturing & Wholesale Goods"
        }
    ],
    "sg:phone":"+1   ",
    "sg:postcode":"14065",
    "sg:province":"NY",
    "sg:tags":[
        "mfg"
    ],
    "wof:name":"Ed Carley Motor Sports",
    "wof:placetype":"venue"
},
  "geometry": {"coordinates":[-78.390423,42.505892],"type":"Point"}
}