{
  "type": "Feature",
  "properties": {
    "iso:country":"US",
    "sg:address":"5880 56th St",
    "sg:city":"Maspeth",
    "sg:classifiers":[
        {
            "category":"Manufacturing",
            "subcategory":"Furniture",
            "type":"Manufacturing & Wholesale Goods"
        },
        {
            "category":"Home & Garden",
            "subcategory":"Furniture",
            "type":"Retail Goods"
        }
    ],
    "sg:phone":"+1 718 821 9109",
    "sg:postcode":"11378",
    "sg:province":"NY",
    "sg:tags":[
        "builder",
        "designer",
        "store",
        "custom"
    ],
    "wof:name":"Woodweave Furniture Co Inc",
    "wof:placetype":"venue"
},
  "geometry": {"coordinates":[-73.91122799999999,40.71615],"type":"Point"}
}