{
  "type": "Feature",
  "properties": {
    "addr:full":"1135 Pelham Pkwy N Bronx NY 10469",
    "addr:housenumber":"1135",
    "addr:postcode":"10469",
    "addr:street":"Pelham Pkwy N",
    "iso:country":"US",
    "sg:address":"1135 Pelham Pkwy N",
    "sg:city":"Bronx",
    "sg:classifiers":[
        {
            "category":"Personal",
            "type":"Services"
        }
    ],
    "sg:phone":"+1 718 547 8919",
    "sg:postcode":"10469",
    "sg:province":"NY",
    "sg:tags":[
        "therapist",
        "massage"
    ],
    "wof:name":"CIM Pro Therapeutic Ctr",
    "wof:placetype":"venue"
},
  "geometry": {"coordinates":[-73.855322,40.858258],"type":"Point"}
}