{
  "type": "Feature",
  "properties": {
    "iso:country":"US",
    "sg:address":"781 Franklin Ave",
    "sg:city":"Brooklyn",
    "sg:classifiers":[
        {
            "category":"Personal",
            "subcategory":"Beauty Salon",
            "type":"Services"
        }
    ],
    "sg:phone":"+1 718 756 9193",
    "sg:postcode":"11238",
    "sg:province":"NY",
    "wof:name":"Total Transformation",
    "wof:placetype":"venue"
},
  "geometry": {"coordinates":[-73.95752,40.671749],"type":"Point"}
}