{
  "type": "Feature",
  "properties": {
    "addr:full":"153 Crystal Ave Buffalo NY 14220",
    "addr:housenumber":"153",
    "addr:postcode":"14220",
    "addr:street":"Crystal Ave",
    "iso:country":"US",
    "sg:address":"153 Crystal Ave",
    "sg:city":"Buffalo",
    "sg:classifiers":[
        {
            "category":"Government",
            "subcategory":"Office",
            "type":"Public Place"
        }
    ],
    "sg:phone":"+1 716 821 9662",
    "sg:postcode":"14220",
    "sg:province":"NY",
    "sg:tags":[
        "executive"
    ],
    "wof:name":"West Seneca Town of",
    "wof:placetype":"venue"
},
  "geometry": {"coordinates":[-78.82751399999999,42.845865],"type":"Point"}
}