{
  "type": "Feature",
  "properties": {
    "addr:full":"887 Crotona Park N Bronx NY 10460",
    "addr:housenumber":"887",
    "addr:postcode":"10460",
    "addr:street":"Crotona Park N",
    "iso:country":"US",
    "sg:address":"887 Crotona Park N",
    "sg:city":"Bronx",
    "sg:classifiers":[
        {
            "category":"Social Services",
            "subcategory":"Child Care",
            "type":"Services"
        }
    ],
    "sg:phone":"+1 718 617 2211",
    "sg:postcode":"10460",
    "sg:province":"NY",
    "sg:tags":[
        "day"
    ],
    "wof:name":"Tremont Montery Day Care",
    "wof:placetype":"venue"
},
  "geometry": {"coordinates":[-73.889003,40.839264],"type":"Point"}
}