{
  "type": "Feature",
  "properties": {
    "iso:country":"US",
    "sg:address":"2725 Church Ave",
    "sg:city":"Brooklyn",
    "sg:classifiers":[
        {
            "category":"Personal",
            "subcategory":"Beauty Salon",
            "type":"Services"
        }
    ],
    "sg:phone":"+1 718 287 9309",
    "sg:postcode":"11226",
    "sg:province":"NY",
    "sg:tags":[
        "shop"
    ],
    "wof:name":"Dramatic Look",
    "wof:placetype":"venue"
},
  "geometry": {"coordinates":[-73.951584,40.650779],"type":"Point"}
}