{
  "type": "Feature",
  "properties": {
    "iso:country":"US",
    "sg:address":"501 John James Audubon Pkwy",
    "sg:city":"Buffalo",
    "sg:classifiers":[
        {
            "category":"Professional",
            "subcategory":"Lawyer & Legal Services",
            "type":"Services"
        }
    ],
    "sg:phone":"+1   ",
    "sg:postcode":"14228",
    "sg:province":"NY",
    "wof:name":"Nesper Ferber & Digiacomo LLP",
    "wof:placetype":"venue"
},
  "geometry": {"coordinates":[-78.782951,43.018237],"type":"Point"}
}