{
  "type": "Feature",
  "properties": {
    "iso:country":"US",
    "sg:address":"216 Rand Hill Rd",
    "sg:city":"Morrisonville",
    "sg:classifiers":[
        {
            "category":"Autos & Motor Vehicles",
            "subcategory":"Auto Supplies",
            "type":"Retail Goods"
        },
        {
            "category":"Home & Garden",
            "subcategory":"Garden Supply",
            "type":"Retail Goods"
        }
    ],
    "sg:phone":"+1 518 561 8049",
    "sg:postcode":"12962",
    "sg:province":"NY",
    "sg:tags":[
        "lawn",
        "mower"
    ],
    "wof:name":"Colver's Small Engine Works",
    "wof:placetype":"venue"
},
  "geometry": {"coordinates":[-73.568566,44.713389],"type":"Point"}
}