{
  "type": "Feature",
  "properties": {
    "addr:full":"11 Berkshire Rd Rockville Centre NY 11570",
    "addr:housenumber":"11",
    "addr:postcode":"11570",
    "addr:street":"Berkshire Rd",
    "iso:country":"US",
    "sg:address":"11 Berkshire Rd",
    "sg:city":"Rockville Centre",
    "sg:classifiers":[
        {
            "category":"Building & Trades",
            "subcategory":"Construction",
            "type":"Services"
        }
    ],
    "sg:phone":"+1 516 678 3374",
    "sg:postcode":"11570",
    "sg:province":"NY",
    "sg:tags":[
        "window",
        "treatment",
        "mfg"
    ],
    "wof:name":"Complete Window Inc",
    "wof:placetype":"venue"
},
  "geometry": {"coordinates":[-73.63899000000001,40.677161],"type":"Point"}
}