{
  "type": "Feature",
  "properties": {
    "addr:full":"4421 4th Ave Brooklyn NY 11220",
    "addr:housenumber":"4421",
    "addr:postcode":"11220",
    "addr:street":"4Th Ave",
    "iso:country":"US",
    "sg:address":"4421 4th Ave",
    "sg:city":"Brooklyn",
    "sg:classifiers":[
        {
            "category":"Food & Beverages",
            "subcategory":"Groceries & Convenience Stores",
            "type":"Retail Goods"
        }
    ],
    "sg:phone":"+1 718 438 0300",
    "sg:postcode":"11220",
    "sg:province":"NY",
    "wof:name":"Red Moon Mini Market Incorporated",
    "wof:placetype":"venue"
},
  "geometry": {"coordinates":[-74.002786,40.649575],"type":"Point"}
}