{
  "type": "Feature",
  "properties": {
    "addr:full":"1350 Ave of the Americas New York NY 10019",
    "addr:housenumber":"1350",
    "addr:postcode":"10019",
    "addr:street":"Ave Of The Americas",
    "iso:country":"US",
    "sg:address":"1350 Ave of the Americas",
    "sg:city":"New York",
    "sg:classifiers":[
        {
            "category":"Shopping",
            "subcategory":"Clothing, Apparel, & Fashions",
            "type":"Retail Goods"
        }
    ],
    "sg:phone":"+1 212 581 6968",
    "sg:postcode":"10019",
    "sg:province":"NY",
    "sg:tags":[
        "designer"
    ],
    "wof:name":"Gitman & Co Iag",
    "wof:placetype":"venue"
},
  "geometry": {"coordinates":[-73.978268,40.762638],"type":"Point"}
}