{
  "type": "Feature",
  "properties": {
    "iso:country":"US",
    "sg:address":"99 Congress St",
    "sg:city":"Troy",
    "sg:classifiers":[
        {
            "category":"Restaurant",
            "type":"Food & Drink"
        }
    ],
    "sg:phone":"+1 518 272 2422",
    "sg:postcode":"12180",
    "sg:province":"NY",
    "sg:tags":[
        "eating"
    ],
    "wof:name":"Manory's Restaurant",
    "wof:placetype":"venue"
},
  "geometry": {"coordinates":[-73.68959,42.728661],"type":"Point"}
}