{
  "type": "Feature",
  "properties": {
    "iso:country":"US",
    "sg:address":"59 Main St",
    "sg:city":"Camden",
    "sg:classifiers":[
        {
            "category":"Home & Garden",
            "subcategory":"Hardware",
            "type":"Retail Goods"
        }
    ],
    "sg:phone":"+1 315 245 2720",
    "sg:postcode":"13316",
    "sg:province":"NY",
    "wof:name":"Carpenter's Paint & Hardware",
    "wof:placetype":"venue"
},
  "geometry": {"coordinates":[-75.747968,43.334978],"type":"Point"}
}