{
  "type": "Feature",
  "properties": {
    "iso:country":"US",
    "sg:address":"212 Dorchester Ave Ste 1A",
    "sg:city":"Syracuse",
    "sg:classifiers":[
        {
            "category":"Real Estate",
            "subcategory":"Real Estate Services",
            "type":"Services"
        },
        {
            "category":"Real Estate",
            "subcategory":"Real Estate Operator",
            "type":"Services"
        }
    ],
    "sg:phone":"+1 315 437 1398",
    "sg:postcode":"13203",
    "sg:province":"NY",
    "sg:tags":[
        "vacancy",
        "apartment",
        "rental",
        "finder",
        "listing"
    ],
    "wof:name":"Rugby Square Apartments",
    "wof:placetype":"venue"
},
  "geometry": {"coordinates":[-76.12521700000001,43.069588],"type":"Point"}
}