{
  "type": "Feature",
  "properties": {
    "addr:full":"282 Scholes St Brooklyn NY 11206",
    "addr:housenumber":"282",
    "addr:postcode":"11206",
    "addr:street":"Scholes St",
    "iso:country":"US",
    "sg:address":"282 Scholes St",
    "sg:city":"Brooklyn",
    "sg:classifiers":[
        {
            "category":"Manufacturing",
            "subcategory":"Furniture",
            "type":"Manufacturing & Wholesale Goods"
        }
    ],
    "sg:phone":"+1   ",
    "sg:postcode":"11206",
    "sg:province":"NY",
    "sg:tags":[
        "upholstered",
        "household",
        "mfg"
    ],
    "wof:name":"Mazza Classic",
    "wof:placetype":"venue"
},
  "geometry": {"coordinates":[-73.93927499999999,40.709036],"type":"Point"}
}