{
  "type": "Feature",
  "properties": {
    "iso:country":"US",
    "sg:address":"105 Duane St",
    "sg:city":"New York",
    "sg:classifiers":[
        {
            "category":"Professional",
            "subcategory":"Management & Consulting",
            "type":"Services"
        }
    ],
    "sg:phone":"+1   ",
    "sg:postcode":"10007",
    "sg:province":"NY",
    "wof:name":"Liz J Abzug Consultant Svm",
    "wof:placetype":"venue"
},
  "geometry": {"coordinates":[-74.006032,40.715522],"type":"Point"}
}