{
  "type": "Feature",
  "properties": {
    "addr:full":"1327 Croes Ave Bronx NY 10472",
    "addr:housenumber":"1327",
    "addr:postcode":"10472",
    "addr:street":"Croes Ave",
    "iso:country":"US",
    "sg:address":"1327 Croes Ave",
    "sg:city":"Bronx",
    "sg:classifiers":[
        {
            "category":"Health Services",
            "subcategory":"Medical Lab",
            "type":"Services"
        }
    ],
    "sg:phone":"+1 718 893 2516",
    "sg:postcode":"10472",
    "sg:province":"NY",
    "sg:tags":[
        "laboratory",
        "dental"
    ],
    "wof:name":"Premium Dental Lab Assoc",
    "wof:placetype":"venue"
},
  "geometry": {"coordinates":[-73.871443,40.832882],"type":"Point"}
}