{
  "type": "Feature",
  "properties": {
    "addr:full":"338 W 39 St New York NY 10018",
    "addr:housenumber":"338",
    "addr:postcode":"10018",
    "addr:street":"W 39 St",
    "iso:country":"US",
    "sg:address":"338 W 39 St",
    "sg:city":"New York",
    "sg:classifiers":[
        {
            "category":"Manufacturing",
            "subcategory":"Tools & Machinery",
            "type":"Manufacturing & Wholesale Goods"
        }
    ],
    "sg:phone":"+1 212 730 7929",
    "sg:postcode":"10018",
    "sg:province":"NY",
    "sg:tags":[
        "pattern",
        "dress"
    ],
    "wof:name":"Accurate Pattern Svc",
    "wof:placetype":"venue"
},
  "geometry": {"coordinates":[-73.99322100000001,40.755997],"type":"Point"}
}