{
  "type": "Feature",
  "properties": {
    "iso:country":"US",
    "sg:address":"5790 Strickler Rd",
    "sg:city":"Clarence",
    "sg:classifiers":[
        {
            "category":"Freight",
            "type":"Transportation"
        }
    ],
    "sg:phone":"+1 716 741 5157",
    "sg:postcode":"14031",
    "sg:province":"NY",
    "wof:name":"Schreiber Tranportation",
    "wof:placetype":"venue"
},
  "geometry": {"coordinates":[-78.607473,43.005525],"type":"Point"}
}