{
  "type": "Feature",
  "properties": {
    "addr:full":"1634 Nostrand Ave Brooklyn NY 11226",
    "addr:housenumber":"1634",
    "addr:postcode":"11226",
    "addr:street":"Nostrand Ave",
    "iso:country":"US",
    "sg:address":"1634 Nostrand Ave",
    "sg:city":"Brooklyn",
    "sg:classifiers":[
        {
            "category":"Recreation",
            "type":"Entertainment"
        }
    ],
    "sg:phone":"+1 718 469 3447",
    "sg:postcode":"11226",
    "sg:province":"NY",
    "sg:tags":[
        "club",
        "tennis",
        "sport"
    ],
    "wof:name":"Msc Billiards and Tennis",
    "wof:placetype":"venue"
},
  "geometry": {"coordinates":[-73.949203,40.646198],"type":"Point"}
}