{
  "type": "Feature",
  "properties": {
    "addr:full":"6530 Kissena Boulevard Flushing NY 11367",
    "addr:postcode":"6530;11367",
    "addr:street":"Kissena Boulevard",
    "iso:country":"US",
    "sg:address":"6530 Kissena Boulevard",
    "sg:city":"Flushing",
    "sg:classifiers":[
        {
            "category":"Education",
            "subcategory":"School",
            "type":"Public Place"
        }
    ],
    "sg:phone":"+1 718 575 2400",
    "sg:postcode":"11367",
    "sg:province":"NY",
    "wof:name":"Kaplan Educational Centers",
    "wof:placetype":"venue"
},
  "geometry": {"coordinates":[-73.814887,40.736143],"type":"Point"}
}