{
  "type": "Feature",
  "properties": {
    "addr:full":"4331 39th St Sunnyside NY 11104",
    "addr:housenumber":"4331",
    "addr:postcode":"11104",
    "addr:street":"39Th St",
    "iso:country":"US",
    "sg:address":"4331 39th St",
    "sg:city":"Sunnyside",
    "sg:classifiers":[
        {
            "category":"Building & Trades",
            "subcategory":"Locksmith",
            "type":"Services"
        }
    ],
    "sg:phone":"+1 347 342 4723",
    "sg:postcode":"11104",
    "sg:province":"NY",
    "sg:tags":[
        "key"
    ],
    "wof:name":"A Best Twenty Four Hr Locksmtih",
    "wof:placetype":"venue"
},
  "geometry": {"coordinates":[-73.92567099999999,40.745502],"type":"Point"}
}