{
  "type": "Feature",
  "properties": {
    "addr:full":"31 S Terrace Ave Mount Vernon NY 10550",
    "addr:housenumber":"31",
    "addr:postcode":"10550",
    "addr:street":"S Terrace Ave",
    "iso:country":"US",
    "sg:address":"31 S Terrace Ave",
    "sg:city":"Mount Vernon",
    "sg:classifiers":[
        {
            "category":"Professional",
            "subcategory":"Business Services",
            "type":"Services"
        }
    ],
    "sg:phone":"+1   ",
    "sg:postcode":"10550",
    "sg:province":"NY",
    "wof:name":"HBD Associates Inc",
    "wof:placetype":"venue"
},
  "geometry": {"coordinates":[-73.84909,40.910949],"type":"Point"}
}