{
  "type": "Feature",
  "properties": {
    "iso:country":"US",
    "sg:address":"4493 Miller Rd",
    "sg:city":"Dansville",
    "sg:classifiers":[
        {
            "category":"Building & Trades",
            "subcategory":"Construction",
            "type":"Services"
        }
    ],
    "sg:phone":"+1 585 335 2691",
    "sg:postcode":"14437",
    "sg:province":"NY",
    "sg:tags":[
        "land",
        "grading"
    ],
    "wof:name":"J F Gleason Trucking",
    "wof:placetype":"venue"
},
  "geometry": {"coordinates":[-77.781403,42.576256],"type":"Point"}
}