{
  "type": "Feature",
  "properties": {
    "addr:full":"52 Chambers St New York NY 10007",
    "addr:housenumber":"52",
    "addr:postcode":"10007",
    "addr:street":"Chambers St",
    "iso:country":"US",
    "sg:address":"52 Chambers St",
    "sg:city":"New York",
    "sg:classifiers":[
        {
            "category":"Education",
            "subcategory":"Special Training",
            "type":"Public Place"
        }
    ],
    "sg:phone":"+1 212 374 0560",
    "sg:postcode":"10007",
    "sg:province":"NY",
    "sg:tags":[
        "educational"
    ],
    "wof:name":"Nyc Leadership Academy Inc",
    "wof:placetype":"venue"
},
  "geometry": {"coordinates":[-74.00442099999999,40.713153],"type":"Point"}
}