{
  "type": "Feature",
  "properties": {
    "iso:country":"US",
    "sg:address":"14 Fairlawn Dr",
    "sg:city":"Horseheads",
    "sg:classifiers":[
        {
            "category":"Autos & Motor Vehicles",
            "subcategory":"Automobile Sales",
            "type":"Retail Goods"
        }
    ],
    "sg:phone":"+1 607 739 9130",
    "sg:postcode":"14845",
    "sg:province":"NY",
    "sg:tags":[
        "new",
        "car"
    ],
    "wof:name":"Campbells Auto Sales",
    "wof:placetype":"venue"
},
  "geometry": {"coordinates":[-76.78971300000001,42.188974],"type":"Point"}
}