{
  "type": "Feature",
  "properties": {
    "addr:full":"61 Broadway Rm 501 New York NY 10006",
    "addr:housenumber":"61;501",
    "addr:postcode":"10006",
    "addr:street":"Broadway Rm",
    "iso:country":"US",
    "sg:address":"61 Broadway Rm 501",
    "sg:city":"New York",
    "sg:classifiers":[
        {
            "category":"Personal",
            "type":"Services"
        }
    ],
    "sg:phone":"+1 631 666 6683",
    "sg:postcode":"10006",
    "sg:province":"NY",
    "sg:tags":[
        "mover"
    ],
    "wof:name":"M & M Movers",
    "wof:placetype":"venue"
},
  "geometry": {"coordinates":[-74.012146,40.707092],"type":"Point"}
}