{
  "type": "Feature",
  "properties": {
    "addr:full":"10619 Metropolitan Avenue Forest Hills NY 11375",
    "addr:housenumber":"10619",
    "addr:postcode":"11375",
    "addr:street":"Metropolitan Avenue",
    "iso:country":"US",
    "sg:address":"10619 Metropolitan Avenue",
    "sg:city":"Forest Hills",
    "sg:classifiers":[
        {
            "category":"Professional",
            "subcategory":"Lawyer & Legal Services",
            "type":"Services"
        }
    ],
    "sg:phone":"+1 718 263 8025",
    "sg:postcode":"11375",
    "sg:province":"NY",
    "wof:name":"Gasser & Hayes",
    "wof:placetype":"venue"
},
  "geometry": {"coordinates":[-73.846675,40.709895],"type":"Point"}
}