{
  "type": "Feature",
  "properties": {
    "addr:full":"8245 Cream Hill Rd Arkport NY 14807",
    "addr:housenumber":"8245",
    "addr:postcode":"14807",
    "addr:street":"Cream Hill Rd",
    "iso:country":"US",
    "sg:address":"8245 Cream Hill Rd",
    "sg:city":"Arkport",
    "sg:classifiers":[
        {
            "category":"Utilities",
            "subcategory":"Telephone",
            "type":"Services"
        }
    ],
    "sg:phone":"+1   ",
    "sg:postcode":"14807",
    "sg:province":"NY",
    "sg:tags":[
        "communications"
    ],
    "wof:name":"and More Treasures",
    "wof:placetype":"venue"
},
  "geometry": {"coordinates":[-77.626694,42.398314],"type":"Point"}
}