{
  "type": "Feature",
  "properties": {
    "addr:full":"43 Greenwich Ave New York NY 10014",
    "addr:housenumber":"43",
    "addr:postcode":"10014",
    "addr:street":"Greenwich Ave",
    "iso:country":"US",
    "sg:address":"43 Greenwich Ave",
    "sg:city":"New York",
    "sg:classifiers":[
        {
            "category":"Shopping",
            "subcategory":"Hobbies, Toys, & Games",
            "type":"Retail Goods"
        }
    ],
    "sg:phone":"+1   ",
    "sg:postcode":"10014",
    "sg:province":"NY",
    "wof:name":"Dragon Spirit Inc",
    "wof:placetype":"venue"
},
  "geometry": {"coordinates":[-74.000721,40.735741],"type":"Point"}
}