{
  "type": "Feature",
  "properties": {
    "addr:full":"181 Cooper Ave Tonawanda NY 14150",
    "addr:housenumber":"181",
    "addr:postcode":"14150",
    "addr:street":"Cooper Ave",
    "iso:country":"US",
    "sg:address":"181 Cooper Ave",
    "sg:city":"Tonawanda",
    "sg:classifiers":[
        {
            "category":"Freight",
            "type":"Transportation"
        }
    ],
    "sg:phone":"+1   ",
    "sg:postcode":"14150",
    "sg:province":"NY",
    "sg:tags":[
        "forwarding",
        "air"
    ],
    "wof:name":"Dhl Danzas Air and Ocean",
    "wof:placetype":"venue"
},
  "geometry": {"coordinates":[-78.908477,42.987632],"type":"Point"}
}