{
  "type": "Feature",
  "properties": {
    "addr:full":"340 S Railroad St Staten Island NY 10312",
    "addr:housenumber":"340",
    "addr:postcode":"10312",
    "addr:street":"S Railroad St",
    "iso:country":"US",
    "sg:address":"340 S Railroad St",
    "sg:city":"Staten Island",
    "sg:classifiers":[
        {
            "category":"Local Transit",
            "type":"Transportation"
        }
    ],
    "sg:phone":"+1 718 317 2939",
    "sg:postcode":"10312",
    "sg:province":"NY",
    "sg:tags":[
        "car"
    ],
    "wof:name":"Legend Executive Trnsprtn Svc",
    "wof:placetype":"venue"
},
  "geometry": {"coordinates":[-74.183582,40.538541],"type":"Point"}
}