{
  "type": "Feature",
  "properties": {
    "addr:full":"1 Blake Ave Brooklyn NY 11212",
    "addr:housenumber":"1",
    "addr:postcode":"11212",
    "addr:street":"Blake Ave",
    "iso:country":"US",
    "sg:address":"1 Blake Ave",
    "sg:city":"Brooklyn",
    "sg:classifiers":[
        {
            "category":"Retail",
            "subcategory":"Auto Repair",
            "type":"Services"
        }
    ],
    "sg:phone":"+1 800 564 1110",
    "sg:postcode":"11212",
    "sg:province":"NY",
    "sg:tags":[
        "general"
    ],
    "wof:name":"New D Auto Repair",
    "wof:placetype":"venue"
},
  "geometry": {"coordinates":[-73.92097099999999,40.663953],"type":"Point"}
}