{
  "type": "Feature",
  "properties": {
    "addr:full":"2615 Jackson Ave Long Island City NY 11101",
    "addr:housenumber":"2615",
    "addr:postcode":"11101",
    "addr:street":"Jackson Ave",
    "iso:country":"US",
    "sg:address":"2615 Jackson Ave",
    "sg:city":"Long Island City",
    "sg:classifiers":[
        {
            "category":"Retail",
            "subcategory":"Auto Repair",
            "type":"Services"
        }
    ],
    "sg:phone":"+1 718 786 7474",
    "sg:postcode":"11101",
    "sg:province":"NY",
    "wof:name":"Moe Taxi & Black Car Svce Center Inc",
    "wof:placetype":"venue"
},
  "geometry": {"coordinates":[-73.9422,40.747299],"type":"Point"}
}