{
  "type": "Feature",
  "properties": {
    "iso:country":"US",
    "sg:address":"2871 Long Beach Rd",
    "sg:city":"Oceanside",
    "sg:classifiers":[
        {
            "category":"Shopping",
            "subcategory":"Pets & Pet Supplies",
            "type":"Retail Goods"
        },
        {
            "category":"Retail",
            "subcategory":"Animal Services",
            "type":"Services"
        }
    ],
    "sg:phone":"+1 516 543 4014",
    "sg:postcode":"11572",
    "sg:province":"NY",
    "sg:tags":[
        "grooming",
        "dog",
        "cat"
    ],
    "wof:name":"Groomingbells",
    "wof:placetype":"venue"
},
  "geometry": {"coordinates":[-73.640067,40.641292],"type":"Point"}
}