{
  "type": "Feature",
  "properties": {
    "addr:full":"494 Broadway New York NY 10012",
    "addr:housenumber":"494",
    "addr:postcode":"10012",
    "addr:street":"Broadway",
    "iso:country":"US",
    "sg:address":"494 Broadway",
    "sg:city":"New York",
    "sg:classifiers":[
        {
            "category":"Professional",
            "subcategory":"Management & Consulting",
            "type":"Services"
        }
    ],
    "sg:phone":"+1 212 219 0600",
    "sg:postcode":"10012",
    "sg:province":"NY",
    "sg:tags":[
        "marketing"
    ],
    "wof:name":"Special Ops Media LLC",
    "wof:placetype":"venue"
},
  "geometry": {"coordinates":[-73.998867,40.722795],"type":"Point"}
}