{
  "type": "Feature",
  "properties": {
    "addr:full":"2681 Niagara Falls Blvd Amherst NY 14228",
    "addr:housenumber":"2681",
    "addr:postcode":"14228",
    "addr:street":"Niagara Falls Blvd",
    "iso:country":"US",
    "sg:address":"2681 Niagara Falls Blvd",
    "sg:city":"Amherst",
    "sg:classifiers":[
        {
            "category":"Freight",
            "type":"Transportation"
        }
    ],
    "sg:phone":"+1 716 691 4565",
    "sg:postcode":"14228",
    "sg:province":"NY",
    "sg:tags":[
        "commercial",
        "storage"
    ],
    "wof:name":"Storage Pros",
    "wof:placetype":"venue"
},
  "geometry": {"coordinates":[-78.822113,43.026547],"type":"Point"}
}