{
  "type": "Feature",
  "properties": {
    "iso:country":"US",
    "sg:address":"7636 164th Street",
    "sg:city":"Fresh Meadows",
    "sg:classifiers":[
        {
            "category":"Retail",
            "subcategory":"Auto Repair",
            "type":"Services"
        }
    ],
    "sg:phone":"+1 718 380 0944",
    "sg:postcode":"11366",
    "sg:province":"NY",
    "wof:name":"Brendan Service Station",
    "wof:placetype":"venue"
},
  "geometry": {"coordinates":[-73.80510099999999,40.724797],"type":"Point"}
}