{
  "type": "Feature",
  "properties": {
    "iso:country":"US",
    "sg:address":"121 Dryden Rd",
    "sg:city":"Ithaca",
    "sg:classifiers":[
        {
            "category":"Restaurant",
            "type":"Food & Drink"
        }
    ],
    "sg:phone":"+1   ",
    "sg:postcode":"14850",
    "sg:province":"NY",
    "sg:tags":[
        "greek"
    ],
    "wof:name":"Greek House Restrnt The",
    "wof:placetype":"venue"
},
  "geometry": {"coordinates":[-76.486853,42.441743],"type":"Point"}
}