{
  "type": "Feature",
  "properties": {
    "addr:full":"232 Front St Hempstead NY 11550",
    "addr:housenumber":"232",
    "addr:postcode":"11550",
    "addr:street":"Front St",
    "iso:country":"US",
    "sg:address":"232 Front St",
    "sg:city":"Hempstead",
    "sg:classifiers":[
        {
            "category":"Organizations",
            "subcategory":"Religious Organization",
            "type":"Services"
        }
    ],
    "sg:phone":"+1 516 505 0514",
    "sg:postcode":"11550",
    "sg:province":"NY",
    "wof:name":"Rehobth Fellowship Center",
    "wof:placetype":"venue"
},
  "geometry": {"coordinates":[-73.626701,40.705287],"type":"Point"}
}