{
  "type": "Feature",
  "properties": {
    "addr:full":"233 Hull Ave Clintondale NY 12515",
    "addr:housenumber":"233",
    "addr:postcode":"12515",
    "addr:street":"Hull Ave",
    "iso:country":"US",
    "sg:address":"233 Hull Ave",
    "sg:city":"Clintondale",
    "sg:classifiers":[
        {
            "category":"Professional",
            "subcategory":"Business Services",
            "type":"Services"
        }
    ],
    "sg:phone":"+1 845 883 9036",
    "sg:postcode":"12515",
    "sg:province":"NY",
    "sg:tags":[
        "recording",
        "studio"
    ],
    "wof:name":"Bacon Paul Design Studio",
    "wof:placetype":"venue"
},
  "geometry": {"coordinates":[-74.049938,41.682956],"type":"Point"}
}