{
  "type": "Feature",
  "properties": {
    "addr:full":"127 S Long St Buffalo NY 14221",
    "addr:housenumber":"127",
    "addr:postcode":"14221",
    "addr:street":"S Long St",
    "iso:country":"US",
    "sg:address":"127 S Long St",
    "sg:city":"Buffalo",
    "sg:classifiers":[
        {
            "category":"Wholesale",
            "subcategory":"Office Equipment",
            "type":"Manufacturing & Wholesale Goods"
        }
    ],
    "sg:phone":"+1 716 631 1100",
    "sg:postcode":"14221",
    "sg:province":"NY",
    "sg:tags":[
        "machine",
        "mailing"
    ],
    "wof:name":"Express Mailing Systems-Ascom",
    "wof:placetype":"venue"
},
  "geometry": {"coordinates":[-78.753264,42.957086],"type":"Point"}
}