{
  "type": "Feature",
  "properties": {
    "iso:country":"US",
    "sg:address":"81 Seigel St",
    "sg:city":"Brooklyn",
    "sg:classifiers":[
        {
            "category":"Manufacturing",
            "subcategory":"Tools & Machinery",
            "type":"Manufacturing & Wholesale Goods"
        }
    ],
    "sg:phone":"+1   ",
    "sg:postcode":"11206",
    "sg:province":"NY",
    "sg:tags":[
        "repair",
        "industrial",
        "electrical",
        "apparatus",
        "mfg"
    ],
    "wof:name":"Lewis Hydraulic",
    "wof:placetype":"venue"
},
  "geometry": {"coordinates":[-73.944113,40.704426],"type":"Point"}
}