{
  "type": "Feature",
  "properties": {
    "iso:country":"US",
    "sg:address":"4631 State Hwy 5",
    "sg:city":"Herkimer",
    "sg:classifiers":[
        {
            "category":"Wholesale",
            "subcategory":"Scrap",
            "type":"Manufacturing & Wholesale Goods"
        }
    ],
    "sg:phone":"+1 315 866 1205",
    "sg:postcode":"13350",
    "sg:province":"NY",
    "sg:tags":[
        "recycling",
        "center"
    ],
    "wof:name":"Jorose Clean Wood Waste",
    "wof:placetype":"venue"
},
  "geometry": {"coordinates":[-75.01687800000001,43.017754],"type":"Point"}
}