{
  "type": "Feature",
  "properties": {
    "addr:full":"3860 Sheridan Dr Buffalo NY 14226",
    "addr:housenumber":"3860",
    "addr:postcode":"14226",
    "addr:street":"Sheridan Dr",
    "iso:country":"US",
    "sg:address":"3860 Sheridan Dr",
    "sg:city":"Buffalo",
    "sg:classifiers":[
        {
            "category":"Sports & Exercise",
            "subcategory":"Bowling",
            "type":"Entertainment"
        }
    ],
    "sg:phone":"+1 716 839 3900",
    "sg:postcode":"14226",
    "sg:province":"NY",
    "sg:tags":[
        "center"
    ],
    "wof:name":"Game Zone",
    "wof:placetype":"venue"
},
  "geometry": {"coordinates":[-78.78715200000001,42.978859],"type":"Point"}
}