{
  "type": "Feature",
  "properties": {
    "iso:country":"US",
    "sg:address":"2 Julia Dr",
    "sg:city":"Hyde Park",
    "sg:classifiers":[
        {
            "category":"Health Services",
            "subcategory":"Doctor",
            "type":"Services"
        }
    ],
    "sg:phone":"+1   ",
    "sg:postcode":"12538",
    "sg:province":"NY",
    "wof:name":"Phillips A Williams DDS",
    "wof:placetype":"venue"
},
  "geometry": {"coordinates":[-73.89264799999999,41.794339],"type":"Point"}
}