{
  "type": "Feature",
  "properties": {
    "iso:country":"US",
    "sg:address":"47 Valley Ave",
    "sg:city":"Smithtown",
    "sg:classifiers":[
        {
            "category":"Building & Trades",
            "subcategory":"Landscaping Services",
            "type":"Services"
        }
    ],
    "sg:phone":"+1 516 997 9139",
    "sg:postcode":"11787",
    "sg:province":"NY",
    "wof:name":"Greenvalley Landscaping",
    "wof:placetype":"venue"
},
  "geometry": {"coordinates":[-73.208181,40.87543],"type":"Point"}
}