{
  "type": "Feature",
  "properties": {
    "iso:country":"US",
    "sg:address":"107 W Sunrise Hwy",
    "sg:city":"Freeport",
    "sg:classifiers":[
        {
            "category":"Building & Trades",
            "subcategory":"Construction",
            "type":"Services"
        }
    ],
    "sg:phone":"+1 516 763 5385",
    "sg:postcode":"11520",
    "sg:province":"NY",
    "sg:tags":[
        "general",
        "contractor"
    ],
    "wof:name":"Elite Builders Inc",
    "wof:placetype":"venue"
},
  "geometry": {"coordinates":[-73.591812,40.655983],"type":"Point"}
}