{
  "type": "Feature",
  "properties": {
    "iso:country":"US",
    "sg:address":"1706 Quentin St",
    "sg:city":"West Babylon",
    "sg:classifiers":[
        {
            "category":"Building & Trades",
            "subcategory":"Construction",
            "type":"Services"
        }
    ],
    "sg:phone":"+1 631 587 5365",
    "sg:postcode":"11704",
    "sg:province":"NY",
    "sg:tags":[
        "contractor"
    ],
    "wof:name":"All Island Siding Plus Inc",
    "wof:placetype":"venue"
},
  "geometry": {"coordinates":[-73.35753699999999,40.705304],"type":"Point"}
}