{
  "type": "Feature",
  "properties": {
    "addr:full":"87 Wayne Dr Rochester NY 14626",
    "addr:housenumber":"87",
    "addr:postcode":"14626",
    "addr:street":"Wayne Dr",
    "iso:country":"US",
    "sg:address":"87 Wayne Dr",
    "sg:city":"Rochester",
    "sg:classifiers":[
        {
            "category":"Food & Beverages",
            "subcategory":"Liquor & Beverages",
            "type":"Retail Goods"
        }
    ],
    "sg:phone":"+1   ",
    "sg:postcode":"14626",
    "sg:province":"NY",
    "sg:tags":[
        "alcoholic"
    ],
    "wof:name":"Latta Long Liquor Inc",
    "wof:placetype":"venue"
},
  "geometry": {"coordinates":[-77.682438,43.204301],"type":"Point"}
}