{
  "type": "Feature",
  "properties": {
    "addr:full":"104 E 107th St New York NY 10029",
    "addr:housenumber":"104",
    "addr:postcode":"10029",
    "addr:street":"E 107Th St",
    "iso:country":"US",
    "sg:address":"104 E 107th St",
    "sg:city":"New York",
    "sg:classifiers":[
        {
            "category":"Professional",
            "type":"Services"
        }
    ],
    "sg:phone":"+1 212 410 4200",
    "sg:postcode":"10029",
    "sg:province":"NY",
    "wof:name":"Edwin Gould Svc For Children",
    "wof:placetype":"venue"
},
  "geometry": {"coordinates":[-73.94592299999999,40.792912],"type":"Point"}
}