{
  "type": "Feature",
  "properties": {
    "addr:full":"111 Bedford Center Rd Bedford Hills NY 10507",
    "addr:housenumber":"111",
    "addr:postcode":"10507",
    "addr:street":"Bedford Center Rd",
    "iso:country":"US",
    "sg:address":"111 Bedford Center Rd",
    "sg:city":"Bedford Hills",
    "sg:classifiers":[
        {
            "category":"Retail",
            "subcategory":"Animal Services",
            "type":"Services"
        }
    ],
    "sg:phone":"+1 914 241 6744",
    "sg:postcode":"10507",
    "sg:province":"NY",
    "sg:tags":[
        "breeder",
        "horse"
    ],
    "wof:name":"Royal Starr Farms",
    "wof:placetype":"venue"
},
  "geometry": {"coordinates":[-73.68605700000001,41.227141],"type":"Point"}
}