{
  "type": "Feature",
  "properties": {
    "addr:full":"135 Tonawanda St Buffalo NY 14207",
    "addr:housenumber":"135",
    "addr:postcode":"14207",
    "addr:street":"Tonawanda St",
    "iso:country":"US",
    "sg:address":"135 Tonawanda St",
    "sg:city":"Buffalo",
    "sg:classifiers":[
        {
            "category":"Retail",
            "subcategory":"Auto Repair",
            "type":"Services"
        }
    ],
    "sg:phone":"+1 716 875 4461",
    "sg:postcode":"14207",
    "sg:province":"NY",
    "sg:tags":[
        "body",
        "shop"
    ],
    "wof:name":"Great Arrow Truck & Auto Repr",
    "wof:placetype":"venue"
},
  "geometry": {"coordinates":[-78.897003,42.932999],"type":"Point"}
}