{
  "type": "Feature",
  "properties": {
    "iso:country":"US",
    "sg:address":"90 Church St",
    "sg:city":"Albany",
    "sg:classifiers":[
        {
            "category":"Freight",
            "type":"Transportation"
        }
    ],
    "sg:phone":"+1 518 436 8200",
    "sg:postcode":"12202",
    "sg:province":"NY",
    "sg:tags":[
        "trucking"
    ],
    "wof:name":"Fort Edward Express Inc",
    "wof:placetype":"venue"
},
  "geometry": {"coordinates":[-73.752218,42.642469],"type":"Point"}
}