{
  "type": "Feature",
  "properties": {
    "iso:country":"US",
    "sg:address":"2151 North Ave",
    "sg:city":"Niagara Falls",
    "sg:classifiers":[
        {
            "category":"Building & Trades",
            "subcategory":"Construction",
            "type":"Services"
        }
    ],
    "sg:phone":"+1 716 284 2923",
    "sg:postcode":"14305",
    "sg:province":"NY",
    "sg:tags":[
        "house"
    ],
    "wof:name":"Rodden Homes",
    "wof:placetype":"venue"
},
  "geometry": {"coordinates":[-79.03393,43.109382],"type":"Point"}
}