{
  "type": "Feature",
  "properties": {
    "iso:country":"US",
    "sg:address":"358 Reiman St",
    "sg:city":"Buffalo",
    "sg:classifiers":[
        {
            "category":"Place Of Worship",
            "subcategory":"Church",
            "type":"Public Place"
        },
        {
            "category":"Place Of Worship",
            "type":"Public Place"
        }
    ],
    "sg:phone":"+1 716 896 4673",
    "sg:postcode":"14212",
    "sg:province":"NY",
    "sg:tags":[
        "churches-baptist-general",
        "churches-baptist"
    ],
    "wof:name":"New Hope Church, S B C",
    "wof:placetype":"venue"
},
  "geometry": {"coordinates":[-78.795818,42.895531],"type":"Point"}
}