{
  "type": "Feature",
  "properties": {
    "addr:full":"2635 Delaware Ave Buffalo NY 14216",
    "addr:housenumber":"2635",
    "addr:postcode":"14216",
    "addr:street":"Delaware Ave",
    "iso:country":"US",
    "sg:address":"2635 Delaware Ave",
    "sg:city":"Buffalo",
    "sg:classifiers":[
        {
            "category":"Education",
            "subcategory":"Special Training",
            "type":"Public Place"
        }
    ],
    "sg:phone":"+1 716 885 7493",
    "sg:postcode":"14216",
    "sg:province":"NY",
    "wof:name":"Literacy Volunteers of America",
    "wof:placetype":"venue"
},
  "geometry": {"coordinates":[-78.869156,42.955372],"type":"Point"}
}