{
  "type": "Feature",
  "properties": {
    "addr:full":"1250 Broadway New York NY 10001",
    "addr:housenumber":"1250",
    "addr:postcode":"10001",
    "addr:street":"Broadway",
    "iso:country":"US",
    "sg:address":"1250 Broadway",
    "sg:city":"New York",
    "sg:classifiers":[
        {
            "category":"Building & Trades",
            "subcategory":"Locksmith",
            "type":"Services"
        }
    ],
    "sg:phone":"+1 917 237 3969",
    "sg:postcode":"10001",
    "sg:province":"NY",
    "sg:tags":[
        "key"
    ],
    "wof:name":"Emerg A 24 Hour Locksmith",
    "wof:placetype":"venue"
},
  "geometry": {"coordinates":[-73.98809799999999,40.748199],"type":"Point"}
}