{
  "type": "Feature",
  "properties": {
    "iso:country":"US",
    "sg:address":"25 Hyatt St",
    "sg:city":"Staten Island",
    "sg:classifiers":[
        {
            "category":"Banks & Credit Unions",
            "subcategory":"Bank",
            "type":"Services"
        }
    ],
    "sg:phone":"+1 718 876 6886",
    "sg:postcode":"10301",
    "sg:province":"NY",
    "sg:tags":[
        "state",
        "commercial"
    ],
    "wof:name":"Citibank",
    "wof:placetype":"venue"
},
  "geometry": {"coordinates":[-74.076836,40.642182],"type":"Point"}
}