{
  "type": "Feature",
  "properties": {
    "iso:country":"US",
    "sg:address":"40 Wheeler Ave",
    "sg:city":"Pleasantville",
    "sg:classifiers":[
        {
            "category":"Retail",
            "subcategory":"Animal Services",
            "type":"Services"
        }
    ],
    "sg:phone":"+1 914 273 3939",
    "sg:postcode":"10570",
    "sg:province":"NY",
    "sg:tags":[
        "pet",
        "boarding/pet",
        "sitting"
    ],
    "wof:name":"Pleasant Grooming",
    "wof:placetype":"venue"
},
  "geometry": {"coordinates":[-73.792,41.134399],"type":"Point"}
}