{
  "type": "Feature",
  "properties": {
    "addr:full":"853 Broadway Ste 1401 New York NY 10003",
    "addr:housenumber":"853",
    "addr:postcode":"10003",
    "addr:street":"Broadway Ste 1401",
    "iso:country":"US",
    "sg:address":"853 Broadway Ste 1401",
    "sg:city":"New York",
    "sg:classifiers":[
        {
            "category":"Health Services",
            "subcategory":"Clinic",
            "type":"Services"
        }
    ],
    "sg:phone":"+1 212 673 6153",
    "sg:postcode":"10003",
    "sg:province":"NY",
    "sg:tags":[
        "counseling",
        "mental"
    ],
    "wof:name":"Flachner Irwin J",
    "wof:placetype":"venue"
},
  "geometry": {"coordinates":[-73.990799,40.7346],"type":"Point"}
}