{
  "type": "Feature",
  "properties": {
    "addr:full":"515 Audubon Ave New York NY 10040",
    "addr:housenumber":"515",
    "addr:postcode":"10040",
    "addr:street":"Audubon Ave",
    "iso:country":"US",
    "sg:address":"515 Audubon Ave",
    "sg:city":"New York",
    "sg:classifiers":[
        {
            "category":"Social Services",
            "subcategory":"Child Care",
            "type":"Services"
        }
    ],
    "sg:phone":"+1 212 342 9438",
    "sg:postcode":"10040",
    "sg:province":"NY",
    "sg:tags":[
        "day"
    ],
    "wof:name":"Isabella Child Care",
    "wof:placetype":"venue"
},
  "geometry": {"coordinates":[-73.928101,40.854801],"type":"Point"}
}