{
  "type": "Feature",
  "properties": {
    "iso:country":"US",
    "sg:address":"113 Barker Rd",
    "sg:city":"Dolgeville",
    "sg:classifiers":[
        {
            "category":"Retail",
            "subcategory":"Auto Repair",
            "type":"Services"
        }
    ],
    "sg:phone":"+1   ",
    "sg:postcode":"13329",
    "sg:province":"NY",
    "sg:tags":[
        "body",
        "automobile",
        "used"
    ],
    "wof:name":"Fakes Auto Enterprise Inc",
    "wof:placetype":"venue"
},
  "geometry": {"coordinates":[-74.77940700000001,43.089699],"type":"Point"}
}