{
  "type": "Feature",
  "properties": {
    "addr:full":"172 Hidden Pond Path Wading River NY 11792",
    "addr:housenumber":"172",
    "addr:postcode":"11792",
    "addr:street":"Hidden Pond Path",
    "iso:country":"US",
    "sg:address":"172 Hidden Pond Path",
    "sg:city":"Wading River",
    "sg:classifiers":[
        {
            "category":"Building & Trades",
            "subcategory":"Construction",
            "type":"Services"
        }
    ],
    "sg:phone":"+1 631 929 6868",
    "sg:postcode":"11792",
    "sg:province":"NY",
    "sg:tags":[
        "repairing",
        "remodeling",
        "contractor"
    ],
    "wof:name":"Remodeling Creative Home",
    "wof:placetype":"venue"
},
  "geometry": {"coordinates":[-72.839049,40.922486],"type":"Point"}
}