{
  "type": "Feature",
  "properties": {
    "addr:full":"4 W 47th Street Suite 36 New York NY 10036",
    "addr:housenumber":"4;36",
    "addr:postcode":"10036",
    "addr:street":"W 47Th Street Suite",
    "iso:country":"US",
    "sg:address":"4 W 47th Street Suite 36",
    "sg:city":"New York",
    "sg:classifiers":[
        {
            "category":"Shopping",
            "subcategory":"Jewelry",
            "type":"Retail Goods"
        }
    ],
    "sg:phone":"+1 212 575 0008",
    "sg:postcode":"10036",
    "sg:province":"NY",
    "wof:name":"Jewelry by Alexander",
    "wof:placetype":"venue"
},
  "geometry": {"coordinates":[-73.978607,40.756699],"type":"Point"}
}