{
  "type": "Feature",
  "properties": {
    "iso:country":"US",
    "sg:address":"1317 Harris Rd",
    "sg:city":"Webster",
    "sg:classifiers":[
        {
            "category":"Building & Trades",
            "subcategory":"Electrical",
            "type":"Services"
        }
    ],
    "sg:phone":"+1 585 872 5270",
    "sg:postcode":"14580",
    "sg:province":"NY",
    "sg:tags":[
        "electrical",
        "contractor"
    ],
    "wof:name":"Bibby Electric",
    "wof:placetype":"venue"
},
  "geometry": {"coordinates":[-77.411621,43.184242],"type":"Point"}
}