{
  "type": "Feature",
  "properties": {
    "addr:full":"15 N Main St Gloversville NY 12078",
    "addr:housenumber":"15",
    "addr:postcode":"12078",
    "addr:street":"N Main St",
    "iso:country":"US",
    "sg:address":"15 N Main St",
    "sg:city":"Gloversville",
    "sg:classifiers":[
        {
            "category":"Professional",
            "subcategory":"Employment Agencies",
            "type":"Services"
        }
    ],
    "sg:phone":"+1 518 773 8515",
    "sg:postcode":"12078",
    "sg:province":"NY",
    "sg:tags":[
        "consultant",
        "search",
        "executive"
    ],
    "wof:name":"Robert Abdella/Nolan Assoc",
    "wof:placetype":"venue"
},
  "geometry": {"coordinates":[-74.345412,43.050829],"type":"Point"}
}