{
  "type": "Feature",
  "properties": {
    "iso:country":"US",
    "sg:address":"798 Walck Rd",
    "sg:city":"North Tonawanda",
    "sg:classifiers":[
        {
            "category":"Retail",
            "subcategory":"Repair Shop",
            "type":"Services"
        }
    ],
    "sg:phone":"+1 716 693 3413",
    "sg:postcode":"14120",
    "sg:province":"NY",
    "sg:tags":[
        "refinishing",
        "furniture"
    ],
    "wof:name":"Windsor Furniture Restoration",
    "wof:placetype":"venue"
},
  "geometry": {"coordinates":[-78.85802099999999,43.04554],"type":"Point"}
}