{
  "type": "Feature",
  "properties": {
    "iso:country":"US",
    "sg:address":"4127 Hylan Blvd",
    "sg:city":"Staten Island",
    "sg:classifiers":[
        {
            "category":"Banks & Credit Unions",
            "subcategory":"Investment Brokerage",
            "type":"Services"
        }
    ],
    "sg:phone":"+1 718 984 6070",
    "sg:postcode":"10308",
    "sg:province":"NY",
    "wof:name":"J P Turner & Co LLC",
    "wof:placetype":"venue"
},
  "geometry": {"coordinates":[-74.149024,40.538715],"type":"Point"}
}