{
  "type": "Feature",
  "properties": {
    "iso:country":"US",
    "sg:address":"2305 Coney Island Ave",
    "sg:city":"Brooklyn",
    "sg:classifiers":[
        {
            "category":"Health Services",
            "subcategory":"Doctor",
            "type":"Services"
        }
    ],
    "sg:phone":"+1 718 645 2161",
    "sg:postcode":"11223",
    "sg:province":"NY",
    "sg:tags":[
        "physician",
        "surgeon"
    ],
    "wof:name":"Express Surgical Supplies",
    "wof:placetype":"venue"
},
  "geometry": {"coordinates":[-73.961341,40.601485],"type":"Point"}
}