{
  "type": "Feature",
  "properties": {
    "addr:full":"31 Graham Ave Brooklyn NY 11206",
    "addr:housenumber":"31",
    "addr:postcode":"11206",
    "addr:street":"Graham Ave",
    "iso:country":"US",
    "sg:address":"31 Graham Ave",
    "sg:city":"Brooklyn",
    "sg:classifiers":[
        {
            "category":"Shopping",
            "type":"Retail Goods"
        }
    ],
    "sg:phone":"+1 718 963 1300",
    "sg:postcode":"11206",
    "sg:province":"NY",
    "sg:tags":[
        "telephone",
        "cellular"
    ],
    "wof:name":"Wireless Source",
    "wof:placetype":"venue"
},
  "geometry": {"coordinates":[-73.94249499999999,40.703053],"type":"Point"}
}