{
  "type": "Feature",
  "properties": {
    "iso:country":"US",
    "sg:address":"426 Uniondale Ave",
    "sg:city":"Uniondale",
    "sg:classifiers":[
        {
            "category":"Food & Beverages",
            "subcategory":"Liquor & Beverages",
            "type":"Retail Goods"
        }
    ],
    "sg:phone":"+1 516 483 7570",
    "sg:postcode":"11553",
    "sg:province":"NY",
    "sg:tags":[
        "beer",
        "spirit",
        "wine"
    ],
    "wof:name":"Uniondale Liquors",
    "wof:placetype":"venue"
},
  "geometry": {"coordinates":[-73.59290300000001,40.7052],"type":"Point"}
}