{
  "type": "Feature",
  "properties": {
    "addr:full":"227 Doughty Blvd Inwood NY 11096",
    "addr:housenumber":"227",
    "addr:postcode":"11096",
    "addr:street":"Doughty Blvd",
    "iso:country":"US",
    "sg:address":"227 Doughty Blvd",
    "sg:city":"Inwood",
    "sg:classifiers":[
        {
            "category":"Wholesale",
            "subcategory":"Construction Materials",
            "type":"Manufacturing & Wholesale Goods"
        },
        {
            "category":"Building & Trades",
            "subcategory":"Construction",
            "type":"Services"
        }
    ],
    "sg:phone":"+1 516 239 8504",
    "sg:postcode":"11096",
    "sg:province":"NY",
    "sg:tags":[
        "marble",
        "contractor"
    ],
    "wof:name":"Perrella Marble & Tile Contr",
    "wof:placetype":"venue"
},
  "geometry": {"coordinates":[-73.746652,40.618601],"type":"Point"}
}