{
  "type": "Feature",
  "properties": {
    "addr:full":"227 W 231st St Bronx NY 10463",
    "addr:housenumber":"227",
    "addr:postcode":"10463",
    "addr:street":"W 231St St",
    "iso:country":"US",
    "sg:address":"227 W 231st St",
    "sg:city":"Bronx",
    "sg:classifiers":[
        {
            "category":"Personal",
            "subcategory":"Beauty Salon",
            "type":"Services"
        }
    ],
    "sg:phone":"+1 718 543 0720",
    "sg:postcode":"10463",
    "sg:province":"NY",
    "wof:name":"Touch Of Class Unisex",
    "wof:placetype":"venue"
},
  "geometry": {"coordinates":[-73.905046,40.879022],"type":"Point"}
}