{
  "type": "Feature",
  "properties": {
    "addr:full":"681 8th Avenue New York NY 10036",
    "addr:housenumber":"681",
    "addr:postcode":"10036",
    "addr:street":"8Th Avenue",
    "iso:country":"US",
    "sg:address":"681 8th Avenue",
    "sg:city":"New York",
    "sg:classifiers":[
        {
            "category":"Building & Trades",
            "subcategory":"Plumbing",
            "type":"Services"
        }
    ],
    "sg:phone":"+1 646 509 2184",
    "sg:postcode":"10036",
    "sg:province":"NY",
    "wof:name":"0 0 0 0 1 Hour Emergency Plumbing",
    "wof:placetype":"venue"
},
  "geometry": {"coordinates":[-73.98936399999999,40.75789],"type":"Point"}
}