{
  "type": "Feature",
  "properties": {
    "iso:country":"US",
    "sg:address":"209 W 87th St",
    "sg:city":"New York",
    "sg:classifiers":[
        {
            "category":"Travel",
            "subcategory":"Hotels & Motels",
            "type":"Entertainment"
        }
    ],
    "sg:phone":"+1 212 873 5222",
    "sg:postcode":"10024",
    "sg:province":"NY",
    "sg:website":"www.belnord.com/",
    "wof:name":"Belnord Hotel",
    "wof:placetype":"venue"
},
  "geometry": {"coordinates":[-73.97580000000001,40.788799],"type":"Point"}
}