{
  "type": "Feature",
  "properties": {
    "iso:country":"US",
    "sg:address":"2725 Creston Ave",
    "sg:city":"Bronx",
    "sg:classifiers":[
        {
            "category":"Freight",
            "type":"Transportation"
        }
    ],
    "sg:phone":"+1 718 933 9244",
    "sg:postcode":"10468",
    "sg:province":"NY",
    "sg:tags":[
        "mover"
    ],
    "wof:name":"GBH Vanguard",
    "wof:placetype":"venue"
},
  "geometry": {"coordinates":[-73.89289100000001,40.869799],"type":"Point"}
}