{
  "type": "Feature",
  "properties": {
    "iso:country":"US",
    "sg:address":"5 Quartz Ledge Rd",
    "sg:city":"Bedford",
    "sg:classifiers":[
        {
            "category":"Building & Trades",
            "subcategory":"Electrical",
            "type":"Services"
        }
    ],
    "sg:phone":"+1 914 949 3812",
    "sg:postcode":"10506",
    "sg:province":"NY",
    "sg:tags":[
        "electrical",
        "contractor"
    ],
    "wof:name":"Post Electric Inc",
    "wof:placetype":"venue"
},
  "geometry": {"coordinates":[-73.64921,41.162036],"type":"Point"}
}