{
  "type": "Feature",
  "properties": {
    "addr:full":"783 Madison Ave New York NY 10065",
    "addr:housenumber":"783",
    "addr:postcode":"10065",
    "addr:street":"Madison Ave",
    "iso:country":"US",
    "sg:address":"783 Madison Ave",
    "sg:city":"New York",
    "sg:classifiers":[
        {
            "category":"Banks & Credit Unions",
            "subcategory":"Investment Brokerage",
            "type":"Services"
        }
    ],
    "sg:phone":"+1 212 360 7660",
    "sg:postcode":"10065",
    "sg:province":"NY",
    "sg:tags":[
        "investing"
    ],
    "wof:name":"Ziff Brothers",
    "wof:placetype":"venue"
},
  "geometry": {"coordinates":[-73.967927,40.76822],"type":"Point"}
}