{
  "type": "Feature",
  "properties": {
    "addr:full":"240 W. 40th St. New York NY 10018",
    "addr:housenumber":"240",
    "addr:postcode":"10018",
    "addr:street":"W. 40Th St.",
    "iso:country":"US",
    "sg:address":"240 W. 40th St.",
    "sg:city":"New York",
    "sg:classifiers":[
        {
            "category":"Restaurant",
            "type":"Food & Drink"
        }
    ],
    "sg:postcode":"10018",
    "sg:province":"NY",
    "sg:tags":[
        "fusion",
        "asian"
    ],
    "wof:name":"Times Pub",
    "wof:placetype":"venue"
},
  "geometry": {"coordinates":[-73.989557,40.755177],"type":"Point"}
}