{
  "type": "Feature",
  "properties": {
    "addr:full":"3316 Amboy Rd Staten Island NY 10306",
    "addr:housenumber":"3316",
    "addr:postcode":"10306",
    "addr:street":"Amboy Rd",
    "iso:country":"US",
    "sg:address":"3316 Amboy Rd",
    "sg:city":"Staten Island",
    "sg:classifiers":[
        {
            "category":"Shopping",
            "type":"Retail Goods"
        }
    ],
    "sg:phone":"+1 718 351 0293",
    "sg:postcode":"10306",
    "sg:province":"NY",
    "sg:tags":[
        "monument"
    ],
    "wof:name":"Amboy Monuments Inc",
    "wof:placetype":"venue"
},
  "geometry": {"coordinates":[-74.134807,40.560798],"type":"Point"}
}