{
  "type": "Feature",
  "properties": {
    "iso:country":"US",
    "sg:address":"46 Diamond Rd",
    "sg:city":"Kerhonkson",
    "sg:classifiers":[
        {
            "category":"Manufacturing",
            "subcategory":"Leather Goods",
            "type":"Manufacturing & Wholesale Goods"
        }
    ],
    "sg:phone":"+1   ",
    "sg:postcode":"12446",
    "sg:province":"NY",
    "sg:tags":[
        "mfg"
    ],
    "wof:name":"Leather Works",
    "wof:placetype":"venue"
},
  "geometry": {"coordinates":[-74.343149,41.882323],"type":"Point"}
}