{
  "type": "Feature",
  "properties": {
    "iso:country":"US",
    "sg:address":"780 Boughton Hill Rd",
    "sg:city":"Victor",
    "sg:classifiers":[
        {
            "category":"Building & Trades",
            "subcategory":"Construction",
            "type":"Services"
        }
    ],
    "sg:phone":"+1 585 624 9859",
    "sg:postcode":"14472",
    "sg:province":"NY",
    "sg:tags":[
        "hanging",
        "painter",
        "contractor"
    ],
    "wof:name":"Charles Streb Painting Contrs",
    "wof:placetype":"venue"
},
  "geometry": {"coordinates":[-77.49073,42.966393],"type":"Point"}
}