{
  "type": "Feature",
  "properties": {
    "iso:country":"US",
    "sg:address":"9718 Seaview Avenue",
    "sg:city":"Brooklyn",
    "sg:classifiers":[
        {
            "category":"Restaurant",
            "type":"Food & Drink"
        }
    ],
    "sg:phone":"+1 718 209 1888",
    "sg:postcode":"11236",
    "sg:province":"NY",
    "sg:tags":[
        "chinese"
    ],
    "wof:name":"Win Hing Chinese Restaurant",
    "wof:placetype":"venue"
},
  "geometry": {"coordinates":[-73.88914200000001,40.63394],"type":"Point"}
}