{
  "type": "Feature",
  "properties": {
    "iso:country":"US",
    "sg:address":"2045 US Hwy 9",
    "sg:city":"Round Lake",
    "sg:classifiers":[
        {
            "category":"Retail",
            "subcategory":"Auto Repair",
            "type":"Services"
        }
    ],
    "sg:phone":"+1 518 877 7133",
    "sg:postcode":"12151",
    "sg:province":"NY",
    "sg:tags":[
        "body",
        "automobile",
        "painting",
        "general"
    ],
    "wof:name":"Neet Automotive Repair Inc",
    "wof:placetype":"venue"
},
  "geometry": {"coordinates":[-73.78554,42.914789],"type":"Point"}
}