{
  "type": "Feature",
  "properties": {
    "addr:full":"5626 Old Saunders Settlement Rd Lockport NY 14094",
    "addr:housenumber":"5626",
    "addr:postcode":"14094",
    "addr:street":"Old Saunders Settlement Rd",
    "iso:country":"US",
    "sg:address":"5626 Old Saunders Settlement Rd",
    "sg:city":"Lockport",
    "sg:classifiers":[
        {
            "category":"Manufacturing",
            "subcategory":"Wood Products",
            "type":"Manufacturing & Wholesale Goods"
        }
    ],
    "sg:phone":"+1 716 433 5400",
    "sg:postcode":"14094",
    "sg:province":"NY",
    "sg:tags":[
        "pallet",
        "skid"
    ],
    "wof:name":"Niagara Truss & Pallet",
    "wof:placetype":"venue"
},
  "geometry": {"coordinates":[-78.725798,43.163612],"type":"Point"}
}