{
  "type": "Feature",
  "properties": {
    "iso:country":"US",
    "sg:address":"6 Roethal Dr",
    "sg:city":"Hopewell Junction",
    "sg:classifiers":[
        {
            "category":"Building & Trades",
            "subcategory":"Equipment Rental",
            "type":"Services"
        }
    ],
    "sg:phone":"+1   ",
    "sg:postcode":"12533",
    "sg:province":"NY",
    "wof:name":"Bounce N Fun",
    "wof:placetype":"venue"
},
  "geometry": {"coordinates":[-73.83899099999999,41.540573],"type":"Point"}
}