{
  "type": "Feature",
  "properties": {
    "addr:full":"260 6th St Verplanck NY 10596",
    "addr:housenumber":"260",
    "addr:postcode":"10596",
    "addr:street":"6Th St",
    "iso:country":"US",
    "sg:address":"260 6th St",
    "sg:city":"Verplanck",
    "sg:classifiers":[
        {
            "category":"Personal",
            "subcategory":"Beauty Salon",
            "type":"Services"
        }
    ],
    "sg:phone":"+1 914 737 2065",
    "sg:postcode":"10596",
    "sg:province":"NY",
    "wof:name":"Best Salon Equipment",
    "wof:placetype":"venue"
},
  "geometry": {"coordinates":[-73.96435099999999,41.255184],"type":"Point"}
}