{
  "type": "Feature",
  "properties": {
    "iso:country":"US",
    "sg:address":"700 Middle Country Rd",
    "sg:city":"Saint James",
    "sg:classifiers":[
        {
            "category":"Autos & Motor Vehicles",
            "subcategory":"Automobile Sales",
            "type":"Retail Goods"
        },
        {
            "category":"Retail",
            "subcategory":"Auto Rental",
            "type":"Services"
        },
        {
            "category":"Retail",
            "subcategory":"Auto Repair",
            "type":"Services"
        }
    ],
    "sg:phone":"+1 631 360 3200",
    "sg:postcode":"11780",
    "sg:province":"NY",
    "sg:tags":[
        "body",
        "shop",
        "car"
    ],
    "wof:name":"Lexus of Smithtown",
    "wof:placetype":"venue"
},
  "geometry": {"coordinates":[-73.151901,40.861099],"type":"Point"}
}