{
  "type": "Feature",
  "properties": {
    "addr:full":"55 Lumber Rd Roslyn NY 11576",
    "addr:postcode":"11576",
    "addr:street":"Lumber Rd",
    "iso:country":"US",
    "sg:address":"55 Lumber Rd",
    "sg:city":"Roslyn",
    "sg:classifiers":[
        {
            "category":"Personal",
            "type":"Services"
        }
    ],
    "sg:phone":"+1 516 484 0696",
    "sg:postcode":"11576",
    "sg:province":"NY",
    "sg:tags":[
        "miscellaneous"
    ],
    "wof:name":"Personal Touch By Sharon",
    "wof:placetype":"venue"
},
  "geometry": {"coordinates":[-73.65158,40.801705],"type":"Point"}
}