{
  "type": "Feature",
  "properties": {
    "iso:country":"US",
    "sg:address":"8285 Jericho Tpke",
    "sg:city":"Woodbury",
    "sg:classifiers":[
        {
            "category":"Personal",
            "subcategory":"Beauty Salon",
            "type":"Services"
        }
    ],
    "sg:phone":"+1 516 367 3777",
    "sg:postcode":"11797",
    "sg:province":"NY",
    "wof:name":"American Beauty",
    "wof:placetype":"venue"
},
  "geometry": {"coordinates":[-73.46687799999999,40.816326],"type":"Point"}
}