{
  "type": "Feature",
  "properties": {
    "addr:full":"140 Main St East Rockaway NY 11518",
    "addr:housenumber":"140",
    "addr:postcode":"11518",
    "addr:street":"Main St East",
    "iso:country":"US",
    "sg:address":"140 Main St",
    "sg:city":"East Rockaway",
    "sg:classifiers":[
        {
            "category":"Restaurant",
            "type":"Food & Drink"
        }
    ],
    "sg:phone":"+1 516 593 2525",
    "sg:postcode":"11518",
    "sg:province":"NY",
    "wof:name":"Far Sing Restrnt",
    "wof:placetype":"venue"
},
  "geometry": {"coordinates":[-73.66619900000001,40.6418],"type":"Point"}
}