{
  "type": "Feature",
  "properties": {
    "addr:full":"1 S Stone Ave Elmsford NY 10523",
    "addr:housenumber":"1",
    "addr:postcode":"10523",
    "addr:street":"S Stone Ave",
    "iso:country":"US",
    "sg:address":"1 S Stone Ave",
    "sg:city":"Elmsford",
    "sg:classifiers":[
        {
            "category":"Health Services",
            "subcategory":"Doctor",
            "type":"Services"
        },
        {
            "category":"Health Services",
            "subcategory":"Chiropractor",
            "type":"Services"
        }
    ],
    "sg:phone":"+1 914 592 1733",
    "sg:postcode":"10523",
    "sg:province":"NY",
    "sg:tags":[
        "physician",
        "surgeon",
        "chiropractic"
    ],
    "wof:name":"Charles Coppola Dr",
    "wof:placetype":"venue"
},
  "geometry": {"coordinates":[-73.81909899999999,41.054661],"type":"Point"}
}