{
  "type": "Feature",
  "properties": {
    "addr:full":"302 101st St Brooklyn NY 11209",
    "addr:housenumber":"302",
    "addr:postcode":"11209",
    "addr:street":"101St St",
    "iso:country":"US",
    "sg:address":"302 101st St",
    "sg:city":"Brooklyn",
    "sg:classifiers":[
        {
            "category":"Personal",
            "type":"Services"
        }
    ],
    "sg:phone":"+1 718 748 9528",
    "sg:postcode":"11209",
    "sg:province":"NY",
    "sg:tags":[
        "vacancy",
        "rental",
        "listing"
    ],
    "wof:name":"Verrazano Owners, Inc",
    "wof:placetype":"venue"
},
  "geometry": {"coordinates":[-74.03450100000001,40.612462],"type":"Point"}
}