{
  "type": "Feature",
  "properties": {
    "iso:country":"US",
    "sg:address":"5 W Main St Ste 202",
    "sg:city":"Elmsford",
    "sg:classifiers":[
        {
            "category":"Professional",
            "subcategory":"Management & Consulting",
            "type":"Services"
        },
        {
            "category":"Banks & Credit Unions",
            "subcategory":"Financial Services",
            "type":"Services"
        }
    ],
    "sg:phone":"+1 914 347 8002",
    "sg:postcode":"10523",
    "sg:province":"NY",
    "sg:tags":[
        "consultant",
        "financing",
        "planning"
    ],
    "wof:name":"Coulter Creative Financial Planning",
    "wof:placetype":"venue"
},
  "geometry": {"coordinates":[-73.821472,41.055659],"type":"Point"}
}