{
  "type": "Feature",
  "properties": {
    "addr:full":"15 W 86th St New York NY 10024",
    "addr:housenumber":"15",
    "addr:postcode":"10024",
    "addr:street":"W 86Th St",
    "iso:country":"US",
    "sg:address":"15 W 86th St",
    "sg:city":"New York",
    "sg:classifiers":[
        {
            "category":"Organizations",
            "subcategory":"Religious Organization",
            "type":"Services"
        }
    ],
    "sg:phone":"+1 212 724 7000",
    "sg:postcode":"10024",
    "sg:province":"NY",
    "wof:name":"Society For the Advancement of Judaism",
    "wof:placetype":"venue"
},
  "geometry": {"coordinates":[-73.969803,40.785301],"type":"Point"}
}