{
  "type": "Feature",
  "properties": {
    "addr:full":"539 Main St Medina NY 14103",
    "addr:housenumber":"539",
    "addr:postcode":"14103",
    "addr:street":"Main St",
    "iso:country":"US",
    "sg:address":"539 Main St",
    "sg:city":"Medina",
    "sg:classifiers":[
        {
            "category":"Professional",
            "subcategory":"Lawyer & Legal Services",
            "type":"Services"
        }
    ],
    "sg:phone":"+1 585 798 5555",
    "sg:postcode":"14103",
    "sg:province":"NY",
    "sg:tags":[
        "attorney"
    ],
    "wof:name":"Lance J Mark Law Offices",
    "wof:placetype":"venue"
},
  "geometry": {"coordinates":[-78.386887,43.219127],"type":"Point"}
}