{
  "type": "Feature",
  "properties": {
    "iso:country":"US",
    "sg:address":"1120 Niagara Falls Blvd",
    "sg:city":"Tonawanda",
    "sg:classifiers":[
        {
            "category":"Travel",
            "subcategory":"Hotels & Motels",
            "type":"Entertainment"
        }
    ],
    "sg:phone":"+1 716 835 5916",
    "sg:postcode":"14150",
    "sg:province":"NY",
    "sg:tags":[
        "lodging"
    ],
    "sg:website":"http://www.daysinn.com",
    "wof:name":"Days Inn Tonawanda",
    "wof:placetype":"venue"
},
  "geometry": {"coordinates":[-78.82287700000001,42.984866],"type":"Point"}
}