{
  "type": "Feature",
  "properties": {
    "iso:country":"US",
    "sg:address":"357 Saint Lawrence Ave",
    "sg:city":"Buffalo",
    "sg:classifiers":[
        {
            "category":"Animal Shelter",
            "type":"Public Place"
        },
        {
            "category":"Shopping",
            "subcategory":"Pets & Pet Supplies",
            "type":"Retail Goods"
        }
    ],
    "sg:phone":"+1 716 839 4275",
    "sg:postcode":"14216",
    "sg:province":"NY",
    "sg:tags":[
        "store"
    ],
    "wof:name":"Greyhound Rescue Adoption Team",
    "wof:placetype":"venue"
},
  "geometry": {"coordinates":[-78.85610200000001,42.956299],"type":"Point"}
}