{
  "type": "Feature",
  "properties": {
    "iso:country":"US",
    "sg:address":"336 N Rutherford Ave",
    "sg:city":"Massapequa",
    "sg:classifiers":[
        {
            "category":"Manufacturing",
            "subcategory":"Metals",
            "type":"Manufacturing & Wholesale Goods"
        }
    ],
    "sg:phone":"+1   ",
    "sg:postcode":"11758",
    "sg:province":"NY",
    "sg:tags":[
        "tool",
        "mfg"
    ],
    "wof:name":"Snap-On Tools",
    "wof:placetype":"venue"
},
  "geometry": {"coordinates":[-73.47049800000001,40.706894],"type":"Point"}
}