{
  "type": "Feature",
  "properties": {
    "iso:country":"US",
    "sg:address":"7 Office Pkwy",
    "sg:city":"Pittsford",
    "sg:classifiers":[
        {
            "category":"Social Services",
            "type":"Services"
        }
    ],
    "sg:phone":"+1   ",
    "sg:postcode":"14534",
    "sg:province":"NY",
    "wof:name":"Ronald S Bodenheimer Dr",
    "wof:placetype":"venue"
},
  "geometry": {"coordinates":[-77.546143,43.086105],"type":"Point"}
}