{
  "type": "Feature",
  "properties": {
    "iso:country":"US",
    "sg:address":"132 Larchmont Ave",
    "sg:city":"Larchmont",
    "sg:classifiers":[
        {
            "category":"Wholesale",
            "subcategory":"Durable Goods & Equipment",
            "type":"Manufacturing & Wholesale Goods"
        }
    ],
    "sg:phone":"+1 914 834 1333",
    "sg:postcode":"10538",
    "sg:province":"NY",
    "sg:tags":[
        "importer"
    ],
    "wof:name":"Vos Vinum Importing LTD",
    "wof:placetype":"venue"
},
  "geometry": {"coordinates":[-73.752297,40.928128],"type":"Point"}
}