{
  "type": "Feature",
  "properties": {
    "addr:full":"201 W Islip Rd West Islip NY 11795",
    "addr:housenumber":"201",
    "addr:postcode":"11795",
    "addr:street":"W Islip Rd",
    "iso:country":"US",
    "sg:address":"201 W Islip Rd",
    "sg:city":"West Islip",
    "sg:phone":"+1 631 893 1996",
    "sg:postcode":"11795",
    "sg:province":"NY",
    "sg:tags":[
        "oil"
    ],
    "wof:name":"Stuyvesant Fuel Svc Corp",
    "wof:placetype":"venue"
},
  "geometry": {"coordinates":[-73.316811,40.694389],"type":"Point"}
}