{
  "type": "Feature",
  "properties": {
    "iso:country":"US",
    "sg:address":"9 Ormian Dr",
    "sg:city":"Pomona",
    "sg:classifiers":[
        {
            "category":"Retail",
            "subcategory":"Repair Shop",
            "type":"Services"
        }
    ],
    "sg:phone":"+1   ",
    "sg:postcode":"10970",
    "sg:province":"NY",
    "sg:tags":[
        "electronic"
    ],
    "wof:name":"AR Technical Services",
    "wof:placetype":"venue"
},
  "geometry": {"coordinates":[-74.053279,41.192666],"type":"Point"}
}