{
  "type": "Feature",
  "properties": {
    "addr:full":"474 Willis Ave Bronx NY 10455",
    "addr:housenumber":"474",
    "addr:postcode":"10455",
    "addr:street":"Willis Ave",
    "iso:country":"US",
    "sg:address":"474 Willis Ave",
    "sg:city":"Bronx",
    "sg:classifiers":[
        {
            "category":"Shopping",
            "subcategory":"Discount & Variety Stores",
            "type":"Retail Goods"
        }
    ],
    "sg:phone":"+1 718 402 4852",
    "sg:postcode":"10455",
    "sg:province":"NY",
    "wof:name":"Liberty Two Discount Ctr",
    "wof:placetype":"venue"
},
  "geometry": {"coordinates":[-73.91875400000001,40.814591],"type":"Point"}
}