{
  "type": "Feature",
  "properties": {
    "iso:country":"US",
    "sg:address":"620 Peat Bed Rd",
    "sg:city":"Hannibal",
    "sg:classifiers":[
        {
            "category":"Building & Trades",
            "subcategory":"Landscaping Services",
            "type":"Services"
        }
    ],
    "sg:phone":"+1 315 564 5611",
    "sg:postcode":"13074",
    "sg:province":"NY",
    "sg:tags":[
        "tree",
        "design",
        "landscape"
    ],
    "wof:name":"Arbortek Tree Service",
    "wof:placetype":"venue"
},
  "geometry": {"coordinates":[-76.557007,43.308991],"type":"Point"}
}