{
  "type": "Feature",
  "properties": {
    "iso:country":"US",
    "sg:address":"1522 Main St",
    "sg:city":"Niagara Falls",
    "sg:classifiers":[
        {
            "category":"Real Estate",
            "subcategory":"Real Estate Agent",
            "type":"Services"
        }
    ],
    "sg:phone":"+1 716 284 0068",
    "sg:postcode":"14305",
    "sg:province":"NY",
    "wof:name":"Pristine Properties",
    "wof:placetype":"venue"
},
  "geometry": {"coordinates":[-79.052488,43.103352],"type":"Point"}
}