{
  "type": "Feature",
  "properties": {
    "iso:country":"US",
    "sg:address":"511 W 33 St",
    "sg:city":"New York",
    "sg:classifiers":[
        {
            "category":"Shopping",
            "type":"Retail Goods"
        }
    ],
    "sg:phone":"+1 917 757 9744",
    "sg:postcode":"10001",
    "sg:province":"NY",
    "sg:tags":[
        "aquarium"
    ],
    "wof:name":"New York Aquairum Svc",
    "wof:placetype":"venue"
},
  "geometry": {"coordinates":[-74.002216,40.755059],"type":"Point"}
}