{
  "type": "Feature",
  "properties": {
    "addr:full":"110 Forsyth St New York NY 10002",
    "addr:housenumber":"110",
    "addr:postcode":"10002",
    "addr:street":"Forsyth St",
    "iso:country":"US",
    "sg:address":"110 Forsyth St",
    "sg:city":"New York",
    "sg:classifiers":[
        {
            "category":"Professional",
            "type":"Services"
        }
    ],
    "sg:phone":"+1 212 343 9535",
    "sg:postcode":"10002",
    "sg:province":"NY",
    "sg:tags":[
        "establishment"
    ],
    "wof:name":"110 Forsyth St HDFC",
    "wof:placetype":"venue"
},
  "geometry": {"coordinates":[-73.992161,40.719749],"type":"Point"}
}