{
  "type": "Feature",
  "properties": {
    "iso:country":"US",
    "sg:address":"1400 Utica St",
    "sg:city":"Oriskany",
    "sg:classifiers":[
        {
            "category":"Health Services",
            "subcategory":"Nursing And Care Facility",
            "type":"Services"
        }
    ],
    "sg:phone":"+1 315 736 1759",
    "sg:postcode":"13424",
    "sg:province":"NY",
    "sg:tags":[
        "home"
    ],
    "wof:name":"Enriched Living",
    "wof:placetype":"venue"
},
  "geometry": {"coordinates":[-75.338955,43.160585],"type":"Point"}
}