{
  "type": "Feature",
  "properties": {
    "iso:country":"US",
    "sg:address":"280 Mamaroneck Ave",
    "sg:city":"White Plains",
    "sg:classifiers":[
        {
            "category":"Real Estate",
            "subcategory":"Real Estate Operator",
            "type":"Services"
        }
    ],
    "sg:phone":"+1 914 946 0168",
    "sg:postcode":"10605",
    "sg:province":"NY",
    "sg:tags":[
        "building",
        "nonresidential"
    ],
    "wof:name":"Medical Arts Bldg",
    "wof:placetype":"venue"
},
  "geometry": {"coordinates":[-73.76403500000001,41.026227],"type":"Point"}
}