{
  "type": "Feature",
  "properties": {
    "addr:full":"69 Leroy St Binghamton NY 13905",
    "addr:housenumber":"69",
    "addr:postcode":"13905",
    "addr:street":"Leroy St",
    "iso:country":"US",
    "sg:address":"69 Leroy St",
    "sg:city":"Binghamton",
    "sg:classifiers":[
        {
            "category":"Food & Beverages",
            "subcategory":"Groceries & Convenience Stores",
            "type":"Retail Goods"
        }
    ],
    "sg:phone":"+1   ",
    "sg:postcode":"13905",
    "sg:province":"NY",
    "wof:name":"Cavanaughs Grocry & Delctesn",
    "wof:placetype":"venue"
},
  "geometry": {"coordinates":[-75.925843,42.095768],"type":"Point"}
}