{
  "type": "Feature",
  "properties": {
    "iso:country":"US",
    "sg:address":"150 William Street",
    "sg:city":"New York",
    "sg:classifiers":[
        {
            "category":"Professional",
            "subcategory":"Lawyer & Legal Services",
            "type":"Services"
        }
    ],
    "sg:phone":"+1 212 962 8020",
    "sg:postcode":"10038",
    "sg:province":"NY",
    "sg:tags":[
        "personal",
        "injury"
    ],
    "wof:name":"Schlesinger Stuart A",
    "wof:placetype":"venue"
},
  "geometry": {"coordinates":[-74.006094,40.709672],"type":"Point"}
}