{
  "type": "Feature",
  "properties": {
    "addr:full":"4167 Richmond Ave New York NY 10312",
    "addr:housenumber":"4167",
    "addr:postcode":"10312",
    "addr:street":"Richmond Ave",
    "iso:country":"US",
    "sg:address":"4167 Richmond Ave",
    "sg:city":"New York",
    "sg:classifiers":[
        {
            "category":"Health Services",
            "subcategory":"Dentist",
            "type":"Services"
        }
    ],
    "sg:phone":"+1 718 967 9338",
    "sg:postcode":"10312",
    "sg:province":"NY",
    "sg:website":"www.drrenzocapraro.com/",
    "wof:name":"Renzo Capraro DDS",
    "wof:placetype":"venue"
},
  "geometry": {"coordinates":[-74.158299,40.536997],"type":"Point"}
}