{
  "type": "Feature",
  "properties": {
    "addr:full":"10 Devoe St Brooklyn NY 11211",
    "addr:housenumber":"10",
    "addr:postcode":"11211",
    "addr:street":"Devoe St",
    "iso:country":"US",
    "sg:address":"10 Devoe St",
    "sg:city":"Brooklyn",
    "sg:classifiers":[
        {
            "category":"Building & Trades",
            "subcategory":"Electrical",
            "type":"Services"
        }
    ],
    "sg:phone":"+1 718 782 5390",
    "sg:postcode":"11211",
    "sg:province":"NY",
    "sg:tags":[
        "electric",
        "contractor"
    ],
    "wof:name":"Sal Simeti Electrical Corp",
    "wof:placetype":"venue"
},
  "geometry": {"coordinates":[-73.949484,40.713213],"type":"Point"}
}