{
  "type": "Feature",
  "properties": {
    "addr:full":"119 11th St Brooklyn NY 11215",
    "addr:housenumber":"119",
    "addr:postcode":"11215",
    "addr:street":"11Th St",
    "iso:country":"US",
    "sg:address":"119 11th St",
    "sg:city":"Brooklyn",
    "sg:classifiers":[
        {
            "category":"Wholesale",
            "subcategory":"Hardware",
            "type":"Manufacturing & Wholesale Goods"
        }
    ],
    "sg:phone":"+1 718 832 0787",
    "sg:postcode":"11215",
    "sg:province":"NY",
    "wof:name":"ASK Wholesale Hardware Co",
    "wof:placetype":"venue"
},
  "geometry": {"coordinates":[-73.992619,40.670727],"type":"Point"}
}