{
  "type": "Feature",
  "properties": {
    "iso:country":"US",
    "sg:address":"952 Troy Schenectady Rd",
    "sg:city":"Latham",
    "sg:classifiers":[
        {
            "category":"Home & Garden",
            "subcategory":"Garden Supply",
            "type":"Retail Goods"
        }
    ],
    "sg:phone":"+1   ",
    "sg:postcode":"12110",
    "sg:province":"NY",
    "sg:tags":[
        "pet",
        "food",
        "lawn",
        "sp",
        "ornament"
    ],
    "sg:website":"www.birdfeedershop.com",
    "wof:name":"Backyard Birds Nature Shop",
    "wof:placetype":"venue"
},
  "geometry": {"coordinates":[-73.798621,42.76314],"type":"Point"}
}