{
  "type": "Feature",
  "properties": {
    "iso:country":"US",
    "sg:address":"55 Main St",
    "sg:city":"Camden",
    "sg:classifiers":[
        {
            "category":"Professional",
            "subcategory":"Lawyer & Legal Services",
            "type":"Services"
        }
    ],
    "sg:phone":"+1 315 245 0700",
    "sg:postcode":"13316",
    "sg:province":"NY",
    "sg:tags":[
        "attorney"
    ],
    "wof:name":"Timothy A Smith Law Office",
    "wof:placetype":"venue"
},
  "geometry": {"coordinates":[-75.747975,43.335039],"type":"Point"}
}