{
  "type": "Feature",
  "properties": {
    "addr:full":"655 Sutter Ave Brooklyn NY 11207",
    "addr:housenumber":"655",
    "addr:postcode":"11207",
    "addr:street":"Sutter Ave",
    "iso:country":"US",
    "sg:address":"655 Sutter Ave",
    "sg:city":"Brooklyn",
    "sg:classifiers":[
        {
            "category":"Government",
            "subcategory":"Office",
            "type":"Public Place"
        }
    ],
    "sg:phone":"+1 718 495 4181",
    "sg:postcode":"11207",
    "sg:province":"NY",
    "sg:tags":[
        "village"
    ],
    "wof:name":"Felix Industries Inc",
    "wof:placetype":"venue"
},
  "geometry": {"coordinates":[-73.89522100000001,40.66937],"type":"Point"}
}