{
  "type": "Feature",
  "properties": {
    "iso:country":"US",
    "sg:address":"112 Wyona Ave",
    "sg:city":"Lindenhurst",
    "sg:classifiers":[
        {
            "category":"Professional",
            "subcategory":"Management & Consulting",
            "type":"Services"
        },
        {
            "category":"Banks & Credit Unions",
            "subcategory":"Financial Services",
            "type":"Services"
        }
    ],
    "sg:phone":"+1 631 957 7014",
    "sg:postcode":"11757",
    "sg:province":"NY",
    "sg:tags":[
        "consultant",
        "financing",
        "planning"
    ],
    "wof:name":"Marino, J & Associate Inc",
    "wof:placetype":"venue"
},
  "geometry": {"coordinates":[-73.357829,40.67887],"type":"Point"}
}