{
  "type": "Feature",
  "properties": {
    "addr:full":"91 E End Ave New York NY 10028",
    "addr:housenumber":"91",
    "addr:postcode":"10028",
    "addr:street":"E End Ave",
    "iso:country":"US",
    "sg:address":"91 E End Ave",
    "sg:city":"New York",
    "sg:classifiers":[
        {
            "category":"Shopping",
            "subcategory":"Shoes",
            "type":"Retail Goods"
        }
    ],
    "sg:phone":"+1   ",
    "sg:postcode":"10028",
    "sg:province":"NY",
    "wof:name":"Wohl Elliot Judith B",
    "wof:placetype":"venue"
},
  "geometry": {"coordinates":[-73.945875,40.773203],"type":"Point"}
}