{
  "type": "Feature",
  "properties": {
    "addr:full":"38 Argonne Rd E Hampton Bays NY 11946",
    "addr:housenumber":"38",
    "addr:postcode":"11946",
    "addr:street":"Argonne Rd E",
    "iso:country":"US",
    "sg:address":"38 Argonne Rd E",
    "sg:city":"Hampton Bays",
    "sg:classifiers":[
        {
            "category":"Building & Trades",
            "subcategory":"Plumbing",
            "type":"Services"
        }
    ],
    "sg:phone":"+1 631 728 7476",
    "sg:postcode":"11946",
    "sg:province":"NY",
    "sg:tags":[
        "heating",
        "contractor",
        "air",
        "system",
        "conditioning"
    ],
    "wof:name":"Forge Heating & AC Corp",
    "wof:placetype":"venue"
},
  "geometry": {"coordinates":[-72.51458100000001,40.874828],"type":"Point"}
}