{
  "type": "Feature",
  "properties": {
    "iso:country":"US",
    "sg:address":"143 S Main St",
    "sg:city":"Cortland",
    "sg:classifiers":[
        {
            "category":"Banks & Credit Unions",
            "subcategory":"Bank",
            "type":"Services"
        }
    ],
    "sg:phone":"+1 607 753 8736",
    "sg:postcode":"13045",
    "sg:province":"NY",
    "sg:tags":[
        "federal",
        "loan",
        "broker"
    ],
    "sg:website":"www.cortlandfcu.org",
    "wof:name":"Cortland Federal Credit Union",
    "wof:placetype":"venue"
},
  "geometry": {"coordinates":[-76.1801,42.596259],"type":"Point"}
}