{
  "type": "Feature",
  "properties": {
    "iso:country":"US",
    "sg:address":"44 W Main St",
    "sg:city":"Middletown",
    "sg:classifiers":[
        {
            "category":"Professional",
            "subcategory":"Management & Consulting",
            "type":"Services"
        },
        {
            "category":"Professional",
            "subcategory":"Computer Services",
            "type":"Services"
        }
    ],
    "sg:phone":"+1 845 342 3520",
    "sg:postcode":"10940",
    "sg:province":"NY",
    "sg:tags":[
        "rooms-installation",
        "facility",
        "consultant",
        "space",
        "equipment",
        "planning"
    ],
    "wof:name":"Inquirere",
    "wof:placetype":"venue"
},
  "geometry": {"coordinates":[-74.421773,41.445227],"type":"Point"}
}