{
  "type": "Feature",
  "properties": {
    "iso:country":"US",
    "sg:address":"170 Cranford Blvd",
    "sg:city":"Mastic",
    "sg:classifiers":[
        {
            "category":"Government",
            "subcategory":"Fire Station",
            "type":"Public Place"
        }
    ],
    "sg:phone":"+1 631 281 3688",
    "sg:postcode":"11950",
    "sg:province":"NY",
    "sg:tags":[
        "department"
    ],
    "wof:name":"Manorville Fire Dept",
    "wof:placetype":"venue"
},
  "geometry": {"coordinates":[-72.85307,40.830345],"type":"Point"}
}