{
  "type": "Feature",
  "properties": {
    "addr:full":"1500 Broadway Suite #304 New York NY 10036",
    "addr:housenumber":"1500;suite # 304",
    "addr:postcode":"10036",
    "addr:street":"Broadway",
    "iso:country":"US",
    "sg:address":"1500 Broadway Suite #304",
    "sg:city":"New York",
    "sg:classifiers":[
        {
            "category":"Shopping",
            "subcategory":"Beauty & Cosmetics",
            "type":"Retail Goods"
        }
    ],
    "sg:phone":"+1 212 944 6789",
    "sg:postcode":"10036",
    "sg:province":"NY",
    "sg:tags":[
        "supply"
    ],
    "sg:website":"www.sephora.com",
    "wof:name":"Sephora",
    "wof:placetype":"venue"
},
  "geometry": {"coordinates":[-73.98590299999999,40.756547],"type":"Point"}
}