{
  "type": "Feature",
  "properties": {
    "addr:full":"2366 Flatbush Ave Brooklyn NY 11234",
    "addr:housenumber":"2366",
    "addr:postcode":"11234",
    "addr:street":"Flatbush Ave",
    "iso:country":"US",
    "sg:address":"2366 Flatbush Ave",
    "sg:city":"Brooklyn",
    "sg:classifiers":[
        {
            "category":"Wholesale",
            "subcategory":"Stationery",
            "type":"Manufacturing & Wholesale Goods"
        }
    ],
    "sg:phone":"+1 718 951 0909",
    "sg:postcode":"11234",
    "sg:province":"NY",
    "sg:tags":[
        "paper",
        "m",
        "direct"
    ],
    "wof:name":"Plaza Box Store",
    "wof:placetype":"venue"
},
  "geometry": {"coordinates":[-73.925685,40.612666],"type":"Point"}
}