{
  "type": "Feature",
  "properties": {
    "addr:full":"83 East St Honeoye Falls NY 14472",
    "addr:housenumber":"83",
    "addr:postcode":"14472",
    "addr:street":"East St",
    "iso:country":"US",
    "sg:address":"83 East St",
    "sg:city":"Honeoye Falls",
    "sg:classifiers":[
        {
            "category":"Education",
            "subcategory":"School",
            "type":"Public Place"
        }
    ],
    "sg:phone":"+1 585 624 7050",
    "sg:postcode":"14472",
    "sg:province":"NY",
    "wof:name":"Honeoye Falls-Lima Senior Hs",
    "wof:placetype":"venue"
},
  "geometry": {"coordinates":[-77.579747,42.953568],"type":"Point"}
}