{
  "type": "Feature",
  "properties": {
    "addr:full":"25518 Waddingham Rd Evans Mills NY 13637",
    "addr:postcode":"25518;13637",
    "addr:street":"Waddingham Rd",
    "iso:country":"US",
    "sg:address":"25518 Waddingham Rd",
    "sg:city":"Evans Mills",
    "sg:classifiers":[
        {
            "category":"Farming",
            "subcategory":"Farm",
            "type":"Manufacturing & Wholesale Goods"
        }
    ],
    "sg:phone":"+1 315 629 4373",
    "sg:postcode":"13637",
    "sg:province":"NY",
    "sg:tags":[
        "crop",
        "general"
    ],
    "wof:name":"Meeks Aleta",
    "wof:placetype":"venue"
},
  "geometry": {"coordinates":[-75.861617,44.069853],"type":"Point"}
}