{
  "type": "Feature",
  "properties": {
    "addr:full":"7 New Lake Rd Valley Cottage NY 10989",
    "addr:housenumber":"7",
    "addr:postcode":"10989",
    "addr:street":"New Lake Rd",
    "iso:country":"US",
    "sg:address":"7 New Lake Rd",
    "sg:city":"Valley Cottage",
    "sg:classifiers":[
        {
            "category":"Real Estate",
            "subcategory":"Real Estate Agent",
            "type":"Services"
        }
    ],
    "sg:phone":"+1 845 268 2121",
    "sg:postcode":"10989",
    "sg:province":"NY",
    "sg:tags":[
        "appraiser"
    ],
    "wof:name":"Balletta Enterprises Inc",
    "wof:placetype":"venue"
},
  "geometry": {"coordinates":[-73.947388,41.117932],"type":"Point"}
}