{
  "type": "Feature",
  "properties": {
    "addr:full":"18 Ardsley Dr New City NY 10956",
    "addr:housenumber":"18",
    "addr:postcode":"10956",
    "addr:street":"Ardsley Dr",
    "iso:country":"US",
    "sg:address":"18 Ardsley Dr",
    "sg:city":"New City",
    "sg:classifiers":[
        {
            "category":"Professional",
            "subcategory":"Research",
            "type":"Services"
        }
    ],
    "sg:phone":"+1 845 639 9053",
    "sg:postcode":"10956",
    "sg:province":"NY",
    "sg:tags":[
        "market",
        "analysis"
    ],
    "wof:name":"Kardis Associates",
    "wof:placetype":"venue"
},
  "geometry": {"coordinates":[-74.001099,41.174453],"type":"Point"}
}