{
  "type": "Feature",
  "properties": {
    "addr:full":"9 School St Jay NY 12996",
    "addr:housenumber":"9",
    "addr:postcode":"12996",
    "addr:street":"School St",
    "iso:country":"US",
    "sg:address":"9 School St",
    "sg:city":"Jay",
    "sg:classifiers":[
        {
            "category":"Building & Trades",
            "subcategory":"Electrical",
            "type":"Services"
        }
    ],
    "sg:phone":"+1 518 647 5467",
    "sg:postcode":"12996",
    "sg:province":"NY",
    "sg:tags":[
        "electric",
        "contractor"
    ],
    "wof:name":"PAR Electrical Contractors Inc",
    "wof:placetype":"venue"
},
  "geometry": {"coordinates":[-73.39103799999999,44.366776],"type":"Point"}
}