{
  "type": "Feature",
  "properties": {
    "addr:full":"2 Mott St New York NY 10013",
    "addr:housenumber":"2",
    "addr:postcode":"10013",
    "addr:street":"Mott St",
    "iso:country":"US",
    "sg:address":"2 Mott St",
    "sg:city":"New York",
    "sg:classifiers":[
        {
            "category":"Professional",
            "subcategory":"Accounting & Tax Preparation",
            "type":"Services"
        }
    ],
    "sg:phone":"+1 212 732 0030",
    "sg:postcode":"10013",
    "sg:province":"NY",
    "sg:tags":[
        "accountant"
    ],
    "wof:name":"Seung Stephen K CPA",
    "wof:placetype":"venue"
},
  "geometry": {"coordinates":[-73.998643,40.71354],"type":"Point"}
}