{
  "type": "Feature",
  "properties": {
    "addr:full":"55 Broad St New York NY 10004",
    "addr:housenumber":"55",
    "addr:postcode":"10004",
    "addr:street":"Broad St",
    "iso:country":"US",
    "sg:address":"55 Broad St",
    "sg:city":"New York",
    "sg:classifiers":[
        {
            "category":"Health Services",
            "subcategory":"Clinic",
            "type":"Services"
        }
    ],
    "sg:phone":"+1 212 785 2236",
    "sg:postcode":"10004",
    "sg:province":"NY",
    "wof:name":"Arcus Group",
    "wof:placetype":"venue"
},
  "geometry": {"coordinates":[-74.011229,40.706117],"type":"Point"}
}