{
  "type": "Feature",
  "properties": {
    "iso:country":"US",
    "sg:address":"19-23 St Marks Pl",
    "sg:city":"New York",
    "sg:classifiers":[
        {
            "category":"Coffee & Tea",
            "type":"Food & Drink"
        },
        {
            "category":"Ice Cream",
            "type":"Food & Drink"
        }
    ],
    "sg:postcode":"10079",
    "sg:province":"NY",
    "sg:tags":[
        "frozen",
        "yogurt"
    ],
    "wof:name":"Caf? St Mark's",
    "wof:placetype":"venue"
},
  "geometry": {"coordinates":[-73.988637,40.729127],"type":"Point"}
}