{
  "type": "Feature",
  "properties": {
    "addr:full":"1975 Linden Blvd Elmont NY 11003",
    "addr:housenumber":"1975",
    "addr:postcode":"11003",
    "addr:street":"Linden Blvd",
    "iso:country":"US",
    "sg:address":"1975 Linden Blvd",
    "sg:city":"Elmont",
    "sg:classifiers":[
        {
            "category":"Banks & Credit Unions",
            "subcategory":"Bank",
            "type":"Services"
        }
    ],
    "sg:phone":"+1 718 341 8193",
    "sg:postcode":"11003",
    "sg:province":"NY",
    "sg:tags":[
        "loan",
        "real estate"
    ],
    "wof:name":"Ameriquest Mortgage",
    "wof:placetype":"venue"
},
  "geometry": {"coordinates":[-73.71735700000001,40.687761],"type":"Point"}
}