{
  "type": "Feature",
  "properties": {
    "addr:full":"219 W Ferry St Buffalo NY 14213",
    "addr:housenumber":"219",
    "addr:postcode":"14213",
    "addr:street":"W Ferry St",
    "iso:country":"US",
    "sg:address":"219 W Ferry St",
    "sg:city":"Buffalo",
    "sg:classifiers":[
        {
            "category":"Organizations",
            "subcategory":"Community Association",
            "type":"Services"
        }
    ],
    "sg:phone":"+1 716 881 5035",
    "sg:postcode":"14213",
    "sg:province":"NY",
    "sg:tags":[
        "military"
    ],
    "sg:website":"www.vfw.org",
    "wof:name":"Veterans Of Foreign Wars",
    "wof:placetype":"venue"
},
  "geometry": {"coordinates":[-78.89398,42.91511],"type":"Point"}
}