{
  "type": "Feature",
  "properties": {
    "addr:full":"4048 Nesconset Hwy East Setauket NY 11733",
    "addr:postcode":"4048;11733",
    "addr:street":"Nesconset Hwy East",
    "iso:country":"US",
    "sg:address":"4048 Nesconset Hwy",
    "sg:city":"East Setauket",
    "sg:classifiers":[
        {
            "category":"Cinema",
            "subcategory":"Movie Rental",
            "type":"Entertainment"
        }
    ],
    "sg:phone":"+1 631 476 6893",
    "sg:postcode":"11733",
    "sg:province":"NY",
    "sg:tags":[
        "game",
        "video"
    ],
    "sg:website":"www.gamestop.com",
    "wof:name":"Gamestop",
    "wof:placetype":"venue"
},
  "geometry": {"coordinates":[-73.08609800000001,40.895802],"type":"Point"}
}