{
  "type": "Feature",
  "properties": {
    "addr:full":"531 W State St Ithaca NY 14850",
    "addr:housenumber":"531",
    "addr:postcode":"14850",
    "addr:street":"W State St",
    "iso:country":"US",
    "sg:address":"531 W State St",
    "sg:city":"Ithaca",
    "sg:classifiers":[
        {
            "category":"Health Services",
            "subcategory":"Clinic",
            "type":"Services"
        }
    ],
    "sg:phone":"+1 607 275 0238",
    "sg:postcode":"14850",
    "sg:province":"NY",
    "sg:tags":[
        "home"
    ],
    "wof:name":"Caregivers",
    "wof:placetype":"venue"
},
  "geometry": {"coordinates":[-76.50663,42.439228],"type":"Point"}
}