{
  "type": "Feature",
  "properties": {
    "iso:country":"US",
    "sg:address":"232 3rd St Ste E105",
    "sg:city":"Brooklyn",
    "sg:classifiers":[
        {
            "category":"Building & Trades",
            "subcategory":"Construction",
            "type":"Services"
        }
    ],
    "sg:phone":"+1 718 834 1752",
    "sg:postcode":"11215",
    "sg:province":"NY",
    "sg:tags":[
        "contractor"
    ],
    "wof:name":"Hable Construction",
    "wof:placetype":"venue"
},
  "geometry": {"coordinates":[-73.988067,40.674946],"type":"Point"}
}