{
  "type": "Feature",
  "properties": {
    "addr:full":"124 Seneca Way Ithaca NY 14850",
    "addr:housenumber":"124",
    "addr:postcode":"14850",
    "addr:street":"Seneca Way",
    "iso:country":"US",
    "sg:address":"124 Seneca Way",
    "sg:city":"Ithaca",
    "sg:classifiers":[
        {
            "category":"Insurance",
            "subcategory":"Insurance Agent",
            "type":"Services"
        }
    ],
    "sg:phone":"+1 607 273 7511",
    "sg:postcode":"14850",
    "sg:province":"NY",
    "sg:tags":[
        "recreational",
        "vehicle"
    ],
    "sg:website":"http://WWW.TRUEINSURANCE.COM",
    "wof:name":"True Insurance",
    "wof:placetype":"venue"
},
  "geometry": {"coordinates":[-76.494818,42.440376],"type":"Point"}
}