{
  "type": "Feature",
  "properties": {
    "addr:full":"836 Hunts Point Ave Bronx NY 10474",
    "addr:housenumber":"836",
    "addr:postcode":"10474",
    "addr:street":"Hunts Point Ave",
    "iso:country":"US",
    "sg:address":"836 Hunts Point Ave",
    "sg:city":"Bronx",
    "sg:classifiers":[
        {
            "category":"Shopping",
            "subcategory":"Discount & Variety Stores",
            "type":"Retail Goods"
        }
    ],
    "sg:phone":"+1 718 328 1631",
    "sg:postcode":"10474",
    "sg:province":"NY",
    "wof:name":"Dollar Craze Inc",
    "wof:placetype":"venue"
},
  "geometry": {"coordinates":[-73.88821299999999,40.816967],"type":"Point"}
}