{
  "type": "Feature",
  "properties": {
    "addr:full":"1178 Broadway Ste 310 New York NY 10001",
    "addr:housenumber":"1178;310",
    "addr:postcode":"10001",
    "addr:street":"Broadway Ste",
    "iso:country":"US",
    "sg:address":"1178 Broadway Ste 310",
    "sg:city":"New York",
    "sg:classifiers":[
        {
            "category":"Professional",
            "type":"Services"
        }
    ],
    "sg:phone":"+1 646 375 5131",
    "sg:postcode":"10001",
    "sg:province":"NY",
    "wof:name":"Borders International",
    "wof:placetype":"venue"
},
  "geometry": {"coordinates":[-73.988285,40.745192],"type":"Point"}
}