{
  "type": "Feature",
  "properties": {
    "addr:full":"158 Holden St Buffalo NY 14214",
    "addr:housenumber":"158",
    "addr:postcode":"14214",
    "addr:street":"Holden St",
    "iso:country":"US",
    "sg:address":"158 Holden St",
    "sg:city":"Buffalo",
    "sg:classifiers":[
        {
            "category":"Government",
            "subcategory":"Office",
            "type":"Public Place"
        }
    ],
    "sg:phone":"+1 716 834 4525",
    "sg:postcode":"14214",
    "sg:province":"NY",
    "sg:tags":[
        "state",
        "program",
        "health"
    ],
    "wof:name":"Mental Health Office",
    "wof:placetype":"venue"
},
  "geometry": {"coordinates":[-78.83493,42.937788],"type":"Point"}
}