{
  "type": "Feature",
  "properties": {
    "iso:country":"US",
    "sg:address":"3537 Merrick Rd",
    "sg:city":"Seaford",
    "sg:classifiers":[
        {
            "category":"Personal",
            "subcategory":"Beauty Salon",
            "type":"Services"
        }
    ],
    "sg:phone":"+1 516 409 1771",
    "sg:postcode":"11783",
    "sg:province":"NY",
    "sg:tags":[
        "manicuring"
    ],
    "wof:name":"Esther's Nails",
    "wof:placetype":"venue"
},
  "geometry": {"coordinates":[-73.49961999999999,40.665181],"type":"Point"}
}