{
  "type": "Feature",
  "properties": {
    "iso:country":"US",
    "sg:address":"70 Lombardy Dr",
    "sg:city":"Shirley",
    "sg:classifiers":[
        {
            "category":"Wholesale",
            "subcategory":"Computers",
            "type":"Manufacturing & Wholesale Goods"
        }
    ],
    "sg:phone":"+1 631 399 1972",
    "sg:postcode":"11967",
    "sg:province":"NY",
    "wof:name":"Crp",
    "wof:placetype":"venue"
},
  "geometry": {"coordinates":[-72.872619,40.747317],"type":"Point"}
}