{
  "type": "Feature",
  "properties": {
    "addr:full":"98 Hack Green Rd Pound Ridge NY 10576",
    "addr:housenumber":"98",
    "addr:postcode":"10576",
    "addr:street":"Hack Green Rd",
    "iso:country":"US",
    "sg:address":"98 Hack Green Rd",
    "sg:city":"Pound Ridge",
    "sg:classifiers":[
        {
            "category":"Building & Trades",
            "subcategory":"Plumbing",
            "type":"Services"
        }
    ],
    "sg:phone":"+1 914 764 4348",
    "sg:postcode":"10576",
    "sg:province":"NY",
    "sg:tags":[
        "design",
        "irrigation",
        "installation",
        "sprinkler",
        "system"
    ],
    "wof:name":"Glenmore Landscape Service",
    "wof:placetype":"venue"
},
  "geometry": {"coordinates":[-73.524308,41.20871],"type":"Point"}
}