{
  "type": "Feature",
  "properties": {
    "addr:full":"3721 State Hwy 43 West Sand Lake NY 12196",
    "addr:housenumber":"3721",
    "addr:postcode":"12196",
    "addr:street":"State Hwy 43",
    "iso:country":"US",
    "sg:address":"3721 State Hwy 43",
    "sg:city":"West Sand Lake",
    "sg:classifiers":[
        {
            "category":"Professional",
            "type":"Services"
        }
    ],
    "sg:phone":"+1 518 674 8191",
    "sg:postcode":"12196",
    "sg:province":"NY",
    "sg:tags":[
        "establishment"
    ],
    "wof:name":"Q Brothers",
    "wof:placetype":"venue"
},
  "geometry": {"coordinates":[-73.608463,42.643398],"type":"Point"}
}