{
  "type": "Feature",
  "properties": {
    "iso:country":"US",
    "sg:address":"9773 Briggs Rd",
    "sg:city":"Remsen",
    "sg:classifiers":[
        {
            "category":"Building & Trades",
            "subcategory":"Construction",
            "type":"Services"
        }
    ],
    "sg:phone":"+1 315 831 8624",
    "sg:postcode":"13438",
    "sg:province":"NY",
    "sg:tags":[
        "industrial",
        "contractors-commercial",
        "contractor"
    ],
    "wof:name":"Northern Services",
    "wof:placetype":"venue"
},
  "geometry": {"coordinates":[-75.109672,43.333847],"type":"Point"}
}