{
  "type": "Feature",
  "properties": {
    "iso:country":"US",
    "sg:address":"353 Halstead Ave",
    "sg:city":"Harrison",
    "sg:classifiers":[
        {
            "category":"Shopping",
            "subcategory":"Stationery & Office Supplies",
            "type":"Retail Goods"
        }
    ],
    "sg:phone":"+1 914 835 2111",
    "sg:postcode":"10528",
    "sg:province":"NY",
    "sg:tags":[
        "cigarette",
        "toy"
    ],
    "wof:name":"Big Top",
    "wof:placetype":"venue"
},
  "geometry": {"coordinates":[-73.709451,40.969459],"type":"Point"}
}