{
  "type": "Feature",
  "properties": {
    "iso:country":"US",
    "sg:address":"186 Glen Cove Ave",
    "sg:city":"Glen Cove",
    "sg:classifiers":[
        {
            "category":"Professional",
            "type":"Services"
        }
    ],
    "sg:phone":"+1 516 609 0160",
    "sg:postcode":"11542",
    "sg:province":"NY",
    "sg:tags":[
        "establishment"
    ],
    "wof:name":"Krucial Keys",
    "wof:placetype":"venue"
},
  "geometry": {"coordinates":[-73.635293,40.850826],"type":"Point"}
}