{
  "type": "Feature",
  "properties": {
    "addr:full":"3299 Cambridge Ave Bronx NY 10463",
    "addr:housenumber":"3299",
    "addr:postcode":"10463",
    "addr:street":"Cambridge Ave",
    "iso:country":"US",
    "sg:address":"3299 Cambridge Ave",
    "sg:city":"Bronx",
    "sg:classifiers":[
        {
            "category":"Professional",
            "subcategory":"Business Services",
            "type":"Services"
        }
    ],
    "sg:phone":"+1 718 549 9006",
    "sg:postcode":"10463",
    "sg:province":"NY",
    "sg:tags":[
        "interior",
        "consultant",
        "design",
        "decorator"
    ],
    "wof:name":"INA Fine Decors",
    "wof:placetype":"venue"
},
  "geometry": {"coordinates":[-73.908366,40.884646],"type":"Point"}
}