{
  "type": "Feature",
  "properties": {
    "iso:country":"US",
    "sg:address":"14731 41st Ave",
    "sg:city":"Flushing",
    "sg:classifiers":[
        {
            "category":"Building & Trades",
            "subcategory":"Construction",
            "type":"Services"
        }
    ],
    "sg:phone":"+1 718 961 7788",
    "sg:postcode":"11355",
    "sg:province":"NY",
    "sg:tags":[
        "contractor"
    ],
    "wof:name":"Jin Leh Construction Inc",
    "wof:placetype":"venue"
},
  "geometry": {"coordinates":[-73.81778,40.761695],"type":"Point"}
}