{
  "type": "Feature",
  "properties": {
    "iso:country":"US",
    "sg:address":"50 Pine St",
    "sg:city":"Hudson Falls",
    "sg:classifiers":[
        {
            "category":"Social Services",
            "type":"Services"
        }
    ],
    "sg:phone":"+1 518 746 2706",
    "sg:postcode":"12839",
    "sg:province":"NY",
    "wof:name":"Park Club Day Habilitation",
    "wof:placetype":"venue"
},
  "geometry": {"coordinates":[-73.57613499999999,43.300605],"type":"Point"}
}