{
  "type": "Feature",
  "properties": {
    "addr:full":"29 Carroll Ave Ronkonkoma NY 11779",
    "addr:housenumber":"29",
    "addr:postcode":"11779",
    "addr:street":"Carroll Ave",
    "iso:country":"US",
    "sg:address":"29 Carroll Ave",
    "sg:city":"Ronkonkoma",
    "sg:classifiers":[
        {
            "category":"Home & Garden",
            "subcategory":"Carpets & Floor Coverings",
            "type":"Retail Goods"
        }
    ],
    "sg:phone":"+1 631 283 0008",
    "sg:postcode":"11779",
    "sg:province":"NY",
    "sg:tags":[
        "flooring"
    ],
    "wof:name":"Bayshore Wood Floors",
    "wof:placetype":"venue"
},
  "geometry": {"coordinates":[-73.1057,40.82504],"type":"Point"}
}