{
  "type": "Feature",
  "properties": {
    "iso:country":"US",
    "sg:address":"5 Saint Marks Pl",
    "sg:city":"New York",
    "sg:classifiers":[
        {
            "category":"Shopping",
            "subcategory":"Jewelry",
            "type":"Retail Goods"
        }
    ],
    "sg:phone":"+1 212 228 4989",
    "sg:postcode":"10003",
    "sg:province":"NY",
    "wof:name":"Na Mademoiselle Inc",
    "wof:placetype":"venue"
},
  "geometry": {"coordinates":[-73.98957799999999,40.729565],"type":"Point"}
}