{
  "type": "Feature",
  "properties": {
    "addr:full":"410 Fremont St Wayland NY 14572",
    "addr:housenumber":"410",
    "addr:postcode":"14572",
    "addr:street":"Fremont St",
    "iso:country":"US",
    "sg:address":"410 Fremont St",
    "sg:city":"Wayland",
    "sg:classifiers":[
        {
            "category":"Social Services",
            "subcategory":"Adult Care",
            "type":"Services"
        }
    ],
    "sg:phone":"+1 585 728 2096",
    "sg:postcode":"14572",
    "sg:province":"NY",
    "sg:tags":[
        "residential"
    ],
    "wof:name":"Steuben Cnty Chptr NY St Assoc",
    "wof:placetype":"venue"
},
  "geometry": {"coordinates":[-77.598373,42.56937],"type":"Point"}
}