{
  "type": "Feature",
  "properties": {
    "addr:full":"12060 Buffalo Rd Irving NY 14081",
    "addr:housenumber":"12060",
    "addr:postcode":"14081",
    "addr:street":"Buffalo Rd",
    "iso:country":"US",
    "sg:address":"12060 Buffalo Rd",
    "sg:city":"Irving",
    "sg:classifiers":[
        {
            "category":"Farming",
            "subcategory":"Vineyard",
            "type":"Manufacturing & Wholesale Goods"
        }
    ],
    "sg:phone":"+1 716 934 7498",
    "sg:postcode":"14081",
    "sg:province":"NY",
    "sg:tags":[
        "grape"
    ],
    "wof:name":"Donald Genske",
    "wof:placetype":"venue"
},
  "geometry": {"coordinates":[-79.08877,42.524184],"type":"Point"}
}