{
  "type": "Feature",
  "properties": {
    "addr:full":"6203 5th Ave Brooklyn NY 11220",
    "addr:housenumber":"6203",
    "addr:postcode":"11220",
    "addr:street":"5Th Ave",
    "iso:country":"US",
    "sg:address":"6203 5th Ave",
    "sg:city":"Brooklyn",
    "sg:classifiers":[
        {
            "category":"Food & Beverages",
            "subcategory":"Groceries & Convenience Stores",
            "type":"Retail Goods"
        }
    ],
    "sg:phone":"+1 718 492 1090",
    "sg:postcode":"11220",
    "sg:province":"NY",
    "wof:name":"Plaza Xochinilco",
    "wof:placetype":"venue"
},
  "geometry": {"coordinates":[-74.017403,40.6381],"type":"Point"}
}