{
  "type": "Feature",
  "properties": {
    "iso:country":"US",
    "sg:address":"62 S 1st St",
    "sg:city":"Fulton",
    "sg:classifiers":[
        {
            "category":"Organizations",
            "subcategory":"Religious Organization",
            "type":"Services"
        }
    ],
    "sg:phone":"+1 315 593 8442",
    "sg:postcode":"13069",
    "sg:province":"NY",
    "wof:name":"Eastern Territrl Salvtion Army",
    "wof:placetype":"venue"
},
  "geometry": {"coordinates":[-76.417581,43.323489],"type":"Point"}
}