{
  "type": "Feature",
  "properties": {
    "iso:country":"US",
    "sg:address":"1532 Clark Street Rd",
    "sg:city":"Auburn",
    "sg:classifiers":[
        {
            "category":"Retail",
            "subcategory":"Veterinary Services",
            "type":"Services"
        }
    ],
    "sg:phone":"+1 315 253 7871",
    "sg:postcode":"13021",
    "sg:province":"NY",
    "sg:tags":[
        "veterinarian"
    ],
    "wof:name":"Cayuga Veterinary Svc",
    "wof:placetype":"venue"
},
  "geometry": {"coordinates":[-76.63878,42.926578],"type":"Point"}
}