{
  "type": "Feature",
  "properties": {
    "iso:country":"US",
    "sg:address":"1341 Colonial Ct",
    "sg:city":"Mamaroneck",
    "sg:classifiers":[
        {
            "category":"Shopping",
            "type":"Retail Goods"
        }
    ],
    "sg:phone":"+1   ",
    "sg:postcode":"10543",
    "sg:province":"NY",
    "sg:tags":[
        "merchandise"
    ],
    "wof:name":"Scarsdale Hearing Center",
    "wof:placetype":"venue"
},
  "geometry": {"coordinates":[-73.715099,40.951376],"type":"Point"}
}