{
  "type": "Feature",
  "properties": {
    "addr:full":"25 South St Washingtonville NY 10992",
    "addr:housenumber":"25",
    "addr:postcode":"10992",
    "addr:street":"South St",
    "iso:country":"US",
    "sg:address":"25 South St",
    "sg:city":"Washingtonville",
    "sg:classifiers":[
        {
            "category":"Shopping",
            "subcategory":"Books",
            "type":"Retail Goods"
        }
    ],
    "sg:phone":"+1   ",
    "sg:postcode":"10992",
    "sg:province":"NY",
    "wof:name":"Inner Journey Books",
    "wof:placetype":"venue"
},
  "geometry": {"coordinates":[-74.167886,41.42179],"type":"Point"}
}