{
  "type": "Feature",
  "properties": {
    "addr:full":"10101 101st Ave Ozone Park NY 11416",
    "addr:housenumber":"10101",
    "addr:postcode":"11416",
    "addr:street":"101St Ave",
    "iso:country":"US",
    "sg:address":"10101 101st Ave",
    "sg:city":"Ozone Park",
    "sg:classifiers":[
        {
            "category":"Food & Beverages",
            "subcategory":"Groceries & Convenience Stores",
            "type":"Retail Goods"
        }
    ],
    "sg:phone":"+1 718 845 3050",
    "sg:postcode":"11416",
    "sg:province":"NY",
    "wof:name":"Italian Amer Grocry",
    "wof:placetype":"venue"
},
  "geometry": {"coordinates":[-73.841499,40.685699],"type":"Point"}
}