{
  "type": "Feature",
  "properties": {
    "addr:full":"3711 55th St Woodside NY 11377",
    "addr:housenumber":"3711",
    "addr:postcode":"11377",
    "addr:street":"55Th St",
    "iso:country":"US",
    "sg:address":"3711 55th St",
    "sg:city":"Woodside",
    "sg:classifiers":[
        {
            "category":"Manufacturing",
            "subcategory":"Tools & Machinery",
            "type":"Manufacturing & Wholesale Goods"
        },
        {
            "category":"Manufacturing",
            "subcategory":"Metals",
            "type":"Manufacturing & Wholesale Goods"
        },
        {
            "category":"Building & Trades",
            "subcategory":"Construction",
            "type":"Services"
        },
        {
            "category":"Manufacturing",
            "subcategory":"Building Materials",
            "type":"Manufacturing & Wholesale Goods"
        }
    ],
    "sg:phone":"+1 718 898 9388",
    "sg:postcode":"11377",
    "sg:province":"NY",
    "sg:tags":[
        "sheet",
        "system",
        "work",
        "heating",
        "specialty",
        "machine",
        "fabricator",
        "contractor",
        "air conditioning",
        "manufacturer"
    ],
    "wof:name":"Power Sheet Metal Inc",
    "wof:placetype":"venue"
},
  "geometry": {"coordinates":[-73.90702,40.750803],"type":"Point"}
}