{
  "type": "Feature",
  "properties": {
    "addr:full":"90 Ferndale Ave Selden NY 11784",
    "addr:housenumber":"90",
    "addr:postcode":"11784",
    "addr:street":"Ferndale Ave",
    "iso:country":"US",
    "sg:address":"90 Ferndale Ave",
    "sg:city":"Selden",
    "sg:classifiers":[
        {
            "category":"Recreation",
            "type":"Entertainment"
        }
    ],
    "sg:phone":"+1 631 944 1866",
    "sg:postcode":"11784",
    "sg:province":"NY",
    "sg:tags":[
        "martial",
        "arts",
        "instruction"
    ],
    "wof:name":"Gold Dragon Tai Chi",
    "wof:placetype":"venue"
},
  "geometry": {"coordinates":[-73.04291499999999,40.85845],"type":"Point"}
}