{
  "type": "Feature",
  "properties": {
    "iso:country":"US",
    "sg:address":"11509 Rockaway Beach Blvd",
    "sg:city":"Rockaway Park",
    "sg:classifiers":[
        {
            "category":"Restaurant",
            "type":"Food & Drink"
        }
    ],
    "sg:phone":"+1 718 318 5102",
    "sg:postcode":"11694",
    "sg:province":"NY",
    "wof:name":"Rockaway Crown",
    "wof:placetype":"venue"
},
  "geometry": {"coordinates":[-73.836502,40.579899],"type":"Point"}
}