{
  "type": "Feature",
  "properties": {
    "addr:full":"100 Motor Pkwy Hauppauge NY 11788",
    "addr:housenumber":"100",
    "addr:postcode":"11788",
    "addr:street":"Motor Pkwy",
    "iso:country":"US",
    "sg:address":"100 Motor Pkwy",
    "sg:city":"Hauppauge",
    "sg:classifiers":[
        {
            "category":"Professional",
            "subcategory":"Employment Agencies",
            "type":"Services"
        }
    ],
    "sg:phone":"+1 631 231 6711",
    "sg:postcode":"11788",
    "sg:province":"NY",
    "wof:name":"Accountemps",
    "wof:placetype":"venue"
},
  "geometry": {"coordinates":[-73.267088,40.806006],"type":"Point"}
}