{
  "type": "Feature",
  "properties": {
    "iso:country":"US",
    "sg:address":"633 Saw Mill River Rd",
    "sg:city":"Ardsley",
    "sg:classifiers":[
        {
            "category":"Health Services",
            "subcategory":"Medical Lab",
            "type":"Services"
        }
    ],
    "sg:phone":"+1 914 693 7666",
    "sg:postcode":"10502",
    "sg:province":"NY",
    "sg:tags":[
        "laboratory"
    ],
    "wof:name":"TMJ Plus Orthodontic Lab Inc",
    "wof:placetype":"venue"
},
  "geometry": {"coordinates":[-73.849558,41.009699],"type":"Point"}
}