{
  "type": "Feature",
  "properties": {
    "addr:full":"2423 Lakeshore Rd Chazy NY 12921",
    "addr:housenumber":"2423",
    "addr:postcode":"12921",
    "addr:street":"Lakeshore Rd",
    "iso:country":"US",
    "sg:address":"2423 Lakeshore Rd",
    "sg:city":"Chazy",
    "sg:classifiers":[
        {
            "category":"Travel",
            "subcategory":"Hotels & Motels",
            "type":"Entertainment"
        }
    ],
    "sg:phone":"+1 518 298 5700",
    "sg:postcode":"12921",
    "sg:province":"NY",
    "sg:tags":[
        "breakfast",
        "accommodation",
        "bed"
    ],
    "wof:name":"Grand-Vue Bed & Breakfast",
    "wof:placetype":"venue"
},
  "geometry": {"coordinates":[-73.403052,44.937935],"type":"Point"}
}