{
  "type": "Feature",
  "properties": {
    "iso:country":"US",
    "sg:address":"404 Wayne St",
    "sg:city":"Olean",
    "sg:classifiers":[
        {
            "category":"Real Estate",
            "subcategory":"Real Estate Agent",
            "type":"Services"
        }
    ],
    "sg:phone":"+1 716 372 6507",
    "sg:postcode":"14760",
    "sg:province":"NY",
    "wof:name":"Di Cerbo & Palumbo",
    "wof:placetype":"venue"
},
  "geometry": {"coordinates":[-78.43518899999999,42.085242],"type":"Point"}
}