{
  "type": "Feature",
  "properties": {
    "iso:country":"US",
    "sg:address":"25 Mc Cleary Ave",
    "sg:city":"Amsterdam",
    "sg:classifiers":[
        {
            "category":"Real Estate",
            "subcategory":"Architect",
            "type":"Services"
        }
    ],
    "sg:phone":"+1   ",
    "sg:postcode":"12010",
    "sg:province":"NY",
    "sg:tags":[
        "architectural"
    ],
    "wof:name":"Tjc Architects",
    "wof:placetype":"venue"
},
  "geometry": {"coordinates":[-74.17202399999999,42.948682],"type":"Point"}
}