{
  "type": "Feature",
  "properties": {
    "iso:country":"US",
    "sg:address":"377 Main St",
    "sg:city":"Center Moriches",
    "sg:classifiers":[
        {
            "category":"Wholesale",
            "subcategory":"Machinery & Supplies",
            "type":"Manufacturing & Wholesale Goods"
        }
    ],
    "sg:phone":"+1 631 878 9100",
    "sg:postcode":"11934",
    "sg:province":"NY",
    "sg:tags":[
        "equipment",
        "industrial"
    ],
    "wof:name":"Interroll Corporation",
    "wof:placetype":"venue"
},
  "geometry": {"coordinates":[-72.793352,40.800409],"type":"Point"}
}