{
  "type": "Feature",
  "properties": {
    "iso:country":"US",
    "sg:address":"1402 Atlantic Ave",
    "sg:city":"Brooklyn",
    "sg:classifiers":[
        {
            "category":"Autos & Motor Vehicles",
            "subcategory":"Automobile Sales",
            "type":"Retail Goods"
        }
    ],
    "sg:phone":"+1 718 453 7500",
    "sg:postcode":"11216",
    "sg:province":"NY",
    "sg:tags":[
        "limo"
    ],
    "sg:website":"www.tristanlimo.com",
    "wof:name":"Tristan's Limousine Corporation",
    "wof:placetype":"venue"
},
  "geometry": {"coordinates":[-73.94546800000001,40.677922],"type":"Point"}
}