{
  "type": "Feature",
  "properties": {
    "addr:full":"814 State Hwy 284 Westtown NY 10998",
    "addr:housenumber":"814",
    "addr:postcode":"10998",
    "addr:street":"State Hwy 284 Westtown",
    "iso:country":"US",
    "sg:address":"814 State Hwy 284",
    "sg:city":"Westtown",
    "sg:classifiers":[
        {
            "category":"Wholesale",
            "subcategory":"Non-durable Goods",
            "type":"Manufacturing & Wholesale Goods"
        }
    ],
    "sg:phone":"+1 845 726 4177",
    "sg:postcode":"10998",
    "sg:province":"NY",
    "wof:name":"Mariska Inc",
    "wof:placetype":"venue"
},
  "geometry": {"coordinates":[-74.53494499999999,41.340242],"type":"Point"}
}