{
  "type": "Feature",
  "properties": {
    "addr:full":"6747 Martin St Rome NY 13440",
    "addr:housenumber":"6747",
    "addr:postcode":"13440",
    "addr:street":"Martin St",
    "iso:country":"US",
    "sg:address":"6747 Martin St",
    "sg:city":"Rome",
    "sg:classifiers":[
        {
            "category":"Wholesale",
            "subcategory":"Hardware",
            "type":"Manufacturing & Wholesale Goods"
        }
    ],
    "sg:phone":"+1 315 336 1893",
    "sg:postcode":"13440",
    "sg:province":"NY",
    "sg:tags":[
        "fastener"
    ],
    "sg:website":"www.fastenal.com",
    "wof:name":"Fastenal Co",
    "wof:placetype":"venue"
},
  "geometry": {"coordinates":[-75.442891,43.197235],"type":"Point"}
}