{
  "type": "Feature",
  "properties": {
    "addr:full":"2738 W Entry Rd Baldwinsville NY 13027",
    "addr:housenumber":"2738",
    "addr:postcode":"13027",
    "addr:street":"W Entry Rd",
    "iso:country":"US",
    "sg:address":"2738 W Entry Rd",
    "sg:city":"Baldwinsville",
    "sg:classifiers":[
        {
            "category":"Freight",
            "type":"Transportation"
        }
    ],
    "sg:phone":"+1 315 638 3368",
    "sg:postcode":"13027",
    "sg:province":"NY",
    "sg:tags":[
        "trucking"
    ],
    "wof:name":"Pro Links Svc Inc",
    "wof:placetype":"venue"
},
  "geometry": {"coordinates":[-76.308159,43.179251],"type":"Point"}
}