{
  "type": "Feature",
  "properties": {
    "addr:full":"243 E 38th St New York NY 10016",
    "addr:housenumber":"243",
    "addr:postcode":"10016",
    "addr:street":"E 38Th St",
    "iso:country":"US",
    "sg:address":"243 E 38th St",
    "sg:city":"New York",
    "sg:classifiers":[
        {
            "category":"Professional",
            "subcategory":"Employment Agencies",
            "type":"Services"
        }
    ],
    "sg:phone":"+1 212 687 1124",
    "sg:postcode":"10016",
    "sg:province":"NY",
    "sg:tags":[
        "help",
        "supply"
    ],
    "wof:name":"Home Plus Cleaning",
    "wof:placetype":"venue"
},
  "geometry": {"coordinates":[-73.97432000000001,40.747537],"type":"Point"}
}