{
  "type": "Feature",
  "properties": {
    "addr:full":"14 Wall St New York NY 10005",
    "addr:housenumber":"14",
    "addr:postcode":"10005",
    "addr:street":"Wall St",
    "iso:country":"US",
    "sg:address":"14 Wall St",
    "sg:city":"New York",
    "sg:classifiers":[
        {
            "category":"Communications",
            "subcategory":"Radio Station",
            "type":"Services"
        }
    ],
    "sg:phone":"+1 212 566 0485",
    "sg:postcode":"10005",
    "sg:province":"NY",
    "sg:website":"www.westwoodone.com",
    "wof:name":"Westwood One",
    "wof:placetype":"venue"
},
  "geometry": {"coordinates":[-74.114774,40.707613],"type":"Point"}
}