{
  "type": "Feature",
  "properties": {
    "addr:full":"58 Craw Rd Mexico NY 13114",
    "addr:housenumber":"58",
    "addr:postcode":"13114",
    "addr:street":"Craw Rd",
    "iso:country":"US",
    "sg:address":"58 Craw Rd",
    "sg:city":"Mexico",
    "sg:classifiers":[
        {
            "category":"Taxi",
            "type":"Transportation"
        }
    ],
    "sg:phone":"+1   ",
    "sg:postcode":"13114",
    "sg:province":"NY",
    "sg:tags":[
        "taxicab"
    ],
    "wof:name":"Call-A-Cab",
    "wof:placetype":"venue"
},
  "geometry": {"coordinates":[-76.27635600000001,43.41596],"type":"Point"}
}