{
  "type": "Feature",
  "properties": {
    "addr:full":"129 Atlantic Ave Brooklyn NY 11201",
    "addr:housenumber":"129",
    "addr:postcode":"11201",
    "addr:street":"Atlantic Ave",
    "iso:country":"US",
    "sg:address":"129 Atlantic Ave",
    "sg:city":"Brooklyn",
    "sg:classifiers":[
        {
            "category":"Fast Food",
            "type":"Food & Drink"
        },
        {
            "category":"Food & Beverages",
            "subcategory":"Specialty",
            "type":"Retail Goods"
        },
        {
            "category":"Restaurant",
            "type":"Food & Drink"
        },
        {
            "category":"Ice Cream",
            "type":"Food & Drink"
        }
    ],
    "sg:phone":"+1 718 855 7774",
    "sg:postcode":"11201",
    "sg:province":"NY",
    "sg:tags":[
        "frozen",
        "dessert",
        "take",
        "british"
    ],
    "sg:website":"www.chipshopnyc.com",
    "wof:name":"The Atlantic ChipShop",
    "wof:placetype":"venue"
},
  "geometry": {"coordinates":[-73.995575,40.690723],"type":"Point"}
}