{
  "type": "Feature",
  "properties": {
    "addr:full":"1075 Grand Concourse Bronx NY 10452",
    "addr:housenumber":"1075",
    "addr:postcode":"10452",
    "addr:street":"Grand Concourse",
    "iso:country":"US",
    "sg:address":"1075 Grand Concourse",
    "sg:city":"Bronx",
    "sg:classifiers":[
        {
            "category":"Organizations",
            "subcategory":"Religious Organization",
            "type":"Services"
        }
    ],
    "sg:phone":"+1 347 758 6941",
    "sg:postcode":"10452",
    "sg:province":"NY",
    "wof:name":"Holy Tabernacle Ch",
    "wof:placetype":"venue"
},
  "geometry": {"coordinates":[-73.92048200000001,40.831582],"type":"Point"}
}