{
  "type": "Feature",
  "properties": {
    "addr:full":"985 Allerton Ave Bronx NY 10469",
    "addr:housenumber":"985",
    "addr:postcode":"10469",
    "addr:street":"Allerton Ave",
    "iso:country":"US",
    "sg:address":"985 Allerton Ave",
    "sg:city":"Bronx",
    "sg:classifiers":[
        {
            "category":"Shopping",
            "subcategory":"Clothing, Apparel, & Fashions",
            "type":"Retail Goods"
        }
    ],
    "sg:phone":"+1 718 653 1402",
    "sg:postcode":"10469",
    "sg:province":"NY",
    "sg:tags":[
        "accessory",
        "clothing",
        "women's"
    ],
    "wof:name":"Angela Fashion Inc",
    "wof:placetype":"venue"
},
  "geometry": {"coordinates":[-73.85924300000001,40.865638],"type":"Point"}
}