{
  "type": "Feature",
  "properties": {
    "addr:full":"1255 Willoughby Ave Brooklyn NY 11237",
    "addr:housenumber":"1255",
    "addr:postcode":"11237",
    "addr:street":"Willoughby Ave",
    "iso:country":"US",
    "sg:address":"1255 Willoughby Ave",
    "sg:city":"Brooklyn",
    "sg:classifiers":[
        {
            "category":"Freight",
            "type":"Transportation"
        }
    ],
    "sg:phone":"+1   ",
    "sg:postcode":"11237",
    "sg:province":"NY",
    "sg:tags":[
        "local",
        "storage",
        "trucking"
    ],
    "wof:name":"U M C",
    "wof:placetype":"venue"
},
  "geometry": {"coordinates":[-73.92180999999999,40.70526],"type":"Point"}
}