{
  "type": "Feature",
  "properties": {
    "iso:country":"US",
    "sg:address":"4762 State St",
    "sg:city":"Oneida",
    "sg:classifiers":[
        {
            "category":"Building & Trades",
            "subcategory":"Cleaning & Sanitation",
            "type":"Services"
        }
    ],
    "sg:phone":"+1 315 363 1590",
    "sg:postcode":"13421",
    "sg:province":"NY",
    "sg:tags":[
        "janitor"
    ],
    "wof:name":"Cleaning Princess",
    "wof:placetype":"venue"
},
  "geometry": {"coordinates":[-75.625309,43.094311],"type":"Point"}
}