{
  "type": "Feature",
  "properties": {
    "iso:country":"US",
    "sg:address":"4720 State Highway 30",
    "sg:city":"Amsterdam",
    "sg:classifiers":[
        {
            "category":"Professional",
            "subcategory":"Management & Consulting",
            "type":"Services"
        },
        {
            "category":"Professional",
            "subcategory":"Engineering",
            "type":"Services"
        }
    ],
    "sg:phone":"+1 518 842 6500",
    "sg:postcode":"12010",
    "sg:province":"NY",
    "sg:tags":[
        "environmental",
        "ecological",
        "engineer",
        "consultant"
    ],
    "wof:name":"Geo Enviromental Management",
    "wof:placetype":"venue"
},
  "geometry": {"coordinates":[-74.188697,42.979719],"type":"Point"}
}