{
  "type": "Feature",
  "properties": {
    "addr:full":"537 Plainview Rd Plainview NY 11803",
    "addr:housenumber":"537",
    "addr:postcode":"11803",
    "addr:street":"Plainview Rd",
    "iso:country":"US",
    "sg:address":"537 Plainview Rd",
    "sg:city":"Plainview",
    "sg:classifiers":[
        {
            "category":"Building & Trades",
            "subcategory":"Landscaping Services",
            "type":"Services"
        }
    ],
    "sg:phone":"+1 516 822 4457",
    "sg:postcode":"11803",
    "sg:province":"NY",
    "sg:tags":[
        "landscape",
        "contractor"
    ],
    "wof:name":"Michael Jacob Landscaping",
    "wof:placetype":"venue"
},
  "geometry": {"coordinates":[-73.468251,40.772177],"type":"Point"}
}