{
  "type": "Feature",
  "properties": {
    "iso:country":"US",
    "sg:address":"2886 Beverly Rd",
    "sg:city":"Oceanside",
    "sg:classifiers":[
        {
            "category":"Wholesale",
            "subcategory":"Vending Machines",
            "type":"Manufacturing & Wholesale Goods"
        }
    ],
    "sg:phone":"+1   ",
    "sg:postcode":"11572",
    "sg:province":"NY",
    "sg:tags":[
        "operator"
    ],
    "wof:name":"Echo Vending Inc",
    "wof:placetype":"venue"
},
  "geometry": {"coordinates":[-73.629672,40.639753],"type":"Point"}
}