{
  "type": "Feature",
  "properties": {
    "addr:full":"5 Regency Dr Wappingers Falls NY 12590",
    "addr:housenumber":"5",
    "addr:postcode":"12590",
    "addr:street":"Regency Dr",
    "iso:country":"US",
    "sg:address":"5 Regency Dr",
    "sg:city":"Wappingers Falls",
    "sg:classifiers":[
        {
            "category":"Autos & Motor Vehicles",
            "subcategory":"Auto Supplies",
            "type":"Retail Goods"
        }
    ],
    "sg:phone":"+1   ",
    "sg:postcode":"12590",
    "sg:province":"NY",
    "wof:name":"A & L Auto Parts",
    "wof:placetype":"venue"
},
  "geometry": {"coordinates":[-73.856138,41.580812],"type":"Point"}
}