{
  "type": "Feature",
  "properties": {
    "addr:full":"315 White Plains Rd Eastchester NY 10709",
    "addr:housenumber":"315",
    "addr:postcode":"10709",
    "addr:street":"White Plains Rd",
    "iso:country":"US",
    "sg:address":"315 White Plains Rd",
    "sg:city":"Eastchester",
    "sg:classifiers":[
        {
            "category":"Personal",
            "subcategory":"Beauty Salon",
            "type":"Services"
        }
    ],
    "sg:phone":"+1 914 961 1888",
    "sg:postcode":"10709",
    "sg:province":"NY",
    "sg:tags":[
        "shop"
    ],
    "wof:name":"Tangles",
    "wof:placetype":"venue"
},
  "geometry": {"coordinates":[-73.81759700000001,40.949973],"type":"Point"}
}