{
  "type": "Feature",
  "properties": {
    "addr:full":"715 55th St Brooklyn NY 11220",
    "addr:housenumber":"715",
    "addr:postcode":"11220",
    "addr:street":"55Th St",
    "iso:country":"US",
    "sg:address":"715 55th St",
    "sg:city":"Brooklyn",
    "sg:classifiers":[
        {
            "category":"Building & Trades",
            "subcategory":"Construction",
            "type":"Services"
        }
    ],
    "sg:phone":"+1 718 836 8331",
    "sg:postcode":"11220",
    "sg:province":"NY",
    "sg:tags":[
        "general",
        "contractor"
    ],
    "wof:name":"Aaron's Construction Co",
    "wof:placetype":"venue"
},
  "geometry": {"coordinates":[-74.00681400000001,40.638564],"type":"Point"}
}