{
  "type": "Feature",
  "properties": {
    "addr:full":"162 Grand St White Plains NY 10601",
    "addr:housenumber":"162",
    "addr:postcode":"10601",
    "addr:street":"Grand St",
    "iso:country":"US",
    "sg:address":"162 Grand St",
    "sg:city":"White Plains",
    "sg:classifiers":[
        {
            "category":"Professional",
            "subcategory":"Lawyer & Legal Services",
            "type":"Services"
        }
    ],
    "sg:phone":"+1 914 761 0640",
    "sg:postcode":"10601",
    "sg:province":"NY",
    "sg:tags":[
        "attorney"
    ],
    "wof:name":"Marino & Weiss PC",
    "wof:placetype":"venue"
},
  "geometry": {"coordinates":[-73.76788999999999,41.029218],"type":"Point"}
}