{
  "type": "Feature",
  "properties": {
    "iso:country":"US",
    "sg:address":"2242 Co Rte 16",
    "sg:city":"Watkins Glen",
    "sg:classifiers":[
        {
            "category":"Freight",
            "type":"Transportation"
        }
    ],
    "sg:phone":"+1   ",
    "sg:postcode":"14891",
    "sg:province":"NY",
    "sg:tags":[
        "household",
        "good",
        "transport"
    ],
    "wof:name":"Phils Moving Co",
    "wof:placetype":"venue"
},
  "geometry": {"coordinates":[-76.962969,42.34858],"type":"Point"}
}