{
  "type": "Feature",
  "properties": {
    "addr:full":"Van Buren Rd Schenectady NY 12302",
    "addr:postcode":"12302",
    "addr:street":"Van Buren Rd",
    "iso:country":"US",
    "sg:address":"Van Buren Rd",
    "sg:city":"Schenectady",
    "sg:classifiers":[
        {
            "category":"Real Estate",
            "subcategory":"Real Estate Operator",
            "type":"Services"
        }
    ],
    "sg:phone":"+1 518 399 0990",
    "sg:postcode":"12302",
    "sg:province":"NY",
    "sg:tags":[
        "apartment"
    ],
    "wof:name":"Indian Brook Apts",
    "wof:placetype":"venue"
},
  "geometry": {"coordinates":[-73.949501,42.860298],"type":"Point"}
}