{
  "type": "Feature",
  "properties": {
    "addr:full":"598 Tuckahoe Rd Ste 2 Yonkers NY 10710",
    "addr:housenumber":"598",
    "addr:postcode":"10710",
    "addr:street":"Tuckahoe Rd Ste 2",
    "iso:country":"US",
    "sg:address":"598 Tuckahoe Rd Ste 2",
    "sg:city":"Yonkers",
    "sg:classifiers":[
        {
            "category":"Banks & Credit Unions",
            "subcategory":"Investment Brokerage",
            "type":"Services"
        },
        {
            "category":"Insurance",
            "subcategory":"Hazard Insurance",
            "type":"Services"
        }
    ],
    "sg:phone":"+1 718 320 1300",
    "sg:postcode":"10710",
    "sg:province":"NY",
    "sg:tags":[
        "commercial",
        "agent",
        "business",
        "resume"
    ],
    "sg:website":"http://www.goodhartinsurance.com",
    "wof:name":"Goodhart National Gorman Agncy",
    "wof:placetype":"venue"
},
  "geometry": {"coordinates":[-73.84702799999999,40.953667],"type":"Point"}
}