{
  "type": "Feature",
  "properties": {
    "addr:full":"76 Saybrook St Staten Island NY 10314",
    "addr:housenumber":"76",
    "addr:postcode":"10314",
    "addr:street":"Saybrook St",
    "iso:country":"US",
    "sg:address":"76 Saybrook St",
    "sg:city":"Staten Island",
    "sg:classifiers":[
        {
            "category":"Banks & Credit Unions",
            "subcategory":"Bank",
            "type":"Services"
        }
    ],
    "sg:phone":"+1 718 761 6908",
    "sg:postcode":"10314",
    "sg:province":"NY",
    "sg:tags":[
        "broker",
        "mortgage"
    ],
    "wof:name":"Crown Financial Services Inc",
    "wof:placetype":"venue"
},
  "geometry": {"coordinates":[-74.16073299999999,40.60563],"type":"Point"}
}