{
  "type": "Feature",
  "properties": {
    "iso:country":"US",
    "sg:address":"999 Blake Ave",
    "sg:city":"Brooklyn",
    "sg:classifiers":[
        {
            "category":"Health Services",
            "subcategory":"Doctor",
            "type":"Services"
        }
    ],
    "sg:phone":"+1 718 277 4795",
    "sg:postcode":"11208",
    "sg:province":"NY",
    "wof:name":"Community Healthcare Network Dr Betty Shabazz Health Center",
    "wof:placetype":"venue"
},
  "geometry": {"coordinates":[-73.881488,40.669956],"type":"Point"}
}