{
  "type": "Feature",
  "properties": {
    "addr:full":"300 Orchard Park Rd Buffalo NY 14224",
    "addr:housenumber":"300",
    "addr:postcode":"14224",
    "addr:street":"Orchard Park Rd",
    "iso:country":"US",
    "sg:address":"300 Orchard Park Rd",
    "sg:city":"Buffalo",
    "sg:classifiers":[
        {
            "category":"Autos & Motor Vehicles",
            "subcategory":"Auto Supplies",
            "type":"Retail Goods"
        },
        {
            "category":"Retail",
            "subcategory":"Auto Repair",
            "type":"Services"
        }
    ],
    "sg:phone":"+1 716 826 2052",
    "sg:postcode":"14224",
    "sg:province":"NY",
    "sg:tags":[
        "tire"
    ],
    "sg:website":"www.goodyear.com",
    "wof:name":"Goodyear Auto Service Centers",
    "wof:placetype":"venue"
},
  "geometry": {"coordinates":[-78.788101,42.8353],"type":"Point"}
}