{
  "type": "Feature",
  "properties": {
    "addr:full":"50 W 49 St New York NY 10020",
    "addr:housenumber":"50",
    "addr:postcode":"10020",
    "addr:street":"W 49 St",
    "iso:country":"US",
    "sg:address":"50 W 49 St",
    "sg:city":"New York",
    "sg:classifiers":[
        {
            "category":"Parking",
            "type":"Transportation"
        }
    ],
    "sg:phone":"+1 212 698 8530",
    "sg:postcode":"10020",
    "sg:province":"NY",
    "sg:tags":[
        "garage"
    ],
    "wof:name":"CENTRAL Parking",
    "wof:placetype":"venue"
},
  "geometry": {"coordinates":[-73.98037100000001,40.758897],"type":"Point"}
}