{
  "type": "Feature",
  "properties": {
    "addr:full":"150 E 56th Street Apt 1C New York NY 10022",
    "addr:housenumber":"150",
    "addr:postcode":"10022",
    "addr:street":"E 56Th Street Apt 1C",
    "iso:country":"US",
    "sg:address":"150 E 56th Street Apt 1C",
    "sg:city":"New York",
    "sg:classifiers":[
        {
            "category":"Health Services",
            "subcategory":"Health Practitioner",
            "type":"Services"
        }
    ],
    "sg:phone":"+1 212 888 8877",
    "sg:postcode":"10022",
    "sg:province":"NY",
    "sg:tags":[
        "acupuncture"
    ],
    "wof:name":"Acumed Medical Care Pllc",
    "wof:placetype":"venue"
},
  "geometry": {"coordinates":[-73.96578700000001,40.757807],"type":"Point"}
}