{
  "type": "Feature",
  "properties": {
    "iso:country":"US",
    "sg:address":"85 Engineers Rd",
    "sg:city":"Hauppauge",
    "sg:classifiers":[
        {
            "category":"Shopping",
            "subcategory":"Pharmacy",
            "type":"Retail Goods"
        }
    ],
    "sg:phone":"+1 631 232 2705",
    "sg:postcode":"11788",
    "sg:province":"NY",
    "sg:tags":[
        "drugstore"
    ],
    "wof:name":"Invagen Pharmceuticals Warehouse",
    "wof:placetype":"venue"
},
  "geometry": {"coordinates":[-73.23788399999999,40.813284],"type":"Point"}
}