{
  "type": "Feature",
  "properties": {
    "iso:country":"US",
    "sg:address":"7712 State Hwy 53",
    "sg:city":"Kanona",
    "sg:classifiers":[
        {
            "category":"Building & Trades",
            "subcategory":"Construction",
            "type":"Services"
        }
    ],
    "sg:phone":"+1 607 776 9435",
    "sg:postcode":"14810",
    "sg:province":"NY",
    "sg:tags":[
        "floor",
        "laying",
        "contractor"
    ],
    "wof:name":"Central New York Wood Floors",
    "wof:placetype":"venue"
},
  "geometry": {"coordinates":[-77.362939,42.377472],"type":"Point"}
}