{
  "type": "Feature",
  "properties": {
    "addr:full":"8741 Parsons Boulevard Jamaica NY 11432",
    "addr:housenumber":"8741",
    "addr:postcode":"11432",
    "addr:street":"Parsons Boulevard",
    "iso:country":"US",
    "sg:address":"8741 Parsons Boulevard",
    "sg:city":"Jamaica",
    "sg:classifiers":[
        {
            "category":"Education",
            "subcategory":"School",
            "type":"Public Place"
        }
    ],
    "sg:phone":"+1 718 291 6264",
    "sg:postcode":"11432",
    "sg:province":"NY",
    "sg:tags":[
        "high",
        "middle",
        "elementary"
    ],
    "wof:name":"New York City Community School District 28 Region 3",
    "wof:placetype":"venue"
},
  "geometry": {"coordinates":[-73.80327200000001,40.708577],"type":"Point"}
}