{
  "type": "Feature",
  "properties": {
    "addr:full":"1267 Forest Avenue Staten Island NY 10302",
    "addr:housenumber":"1267",
    "addr:postcode":"10302",
    "addr:street":"Forest Avenue",
    "iso:country":"US",
    "sg:address":"1267 Forest Avenue",
    "sg:city":"Staten Island",
    "sg:classifiers":[
        {
            "category":"Restaurant",
            "type":"Food & Drink"
        }
    ],
    "sg:phone":"+1 718 876 7888",
    "sg:postcode":"10302",
    "sg:province":"NY",
    "wof:name":"Crown Palace",
    "wof:placetype":"venue"
},
  "geometry": {"coordinates":[-74.13197599999999,40.626345],"type":"Point"}
}