{
  "type": "Feature",
  "properties": {
    "addr:full":"211 W 40 St New York NY 10018",
    "addr:housenumber":"211",
    "addr:postcode":"10018",
    "addr:street":"W 40 St",
    "iso:country":"US",
    "sg:address":"211 W 40 St",
    "sg:city":"New York",
    "sg:classifiers":[
        {
            "category":"Professional",
            "type":"Services"
        }
    ],
    "sg:phone":"+1 212 575 9300",
    "sg:postcode":"10018",
    "sg:province":"NY",
    "sg:tags":[
        "establishment"
    ],
    "wof:name":"Gcomdata",
    "wof:placetype":"venue"
},
  "geometry": {"coordinates":[-73.99047,40.755893],"type":"Point"}
}