{
  "type": "Feature",
  "properties": {
    "iso:country":"US",
    "sg:address":"30 Pleasantview Ave",
    "sg:city":"Monticello",
    "sg:classifiers":[
        {
            "category":"Social Services",
            "subcategory":"Child Care",
            "type":"Services"
        }
    ],
    "sg:phone":"+1   ",
    "sg:postcode":"12701",
    "sg:province":"NY",
    "sg:tags":[
        "day"
    ],
    "wof:name":"MAI Day LLC",
    "wof:placetype":"venue"
},
  "geometry": {"coordinates":[-74.67259799999999,41.65362],"type":"Point"}
}