{
  "type": "Feature",
  "properties": {
    "addr:full":"42 Floyd St East Hampton NY 11937",
    "addr:housenumber":"42",
    "addr:postcode":"11937",
    "addr:street":"Floyd St",
    "iso:country":"US",
    "sg:address":"42 Floyd St",
    "sg:city":"East Hampton",
    "sg:classifiers":[
        {
            "category":"Real Estate",
            "subcategory":"Architect",
            "type":"Services"
        }
    ],
    "sg:phone":"+1 631 324 1283",
    "sg:postcode":"11937",
    "sg:province":"NY",
    "sg:tags":[
        "architectural"
    ],
    "wof:name":"Frank Lupo",
    "wof:placetype":"venue"
},
  "geometry": {"coordinates":[-72.177922,40.974864],"type":"Point"}
}