{
  "type": "Feature",
  "properties": {
    "iso:country":"US",
    "sg:address":"1 Deerleap Pl",
    "sg:city":"Saratoga Springs",
    "sg:classifiers":[
        {
            "category":"Professional",
            "subcategory":"Accounting & Tax Preparation",
            "type":"Services"
        },
        {
            "category":"Professional",
            "subcategory":"Employment Agencies",
            "type":"Services"
        }
    ],
    "sg:phone":"+1 518 581 0179",
    "sg:postcode":"12866",
    "sg:province":"NY",
    "sg:tags":[
        "consultant"
    ],
    "wof:name":"Tri County Search Svc",
    "wof:placetype":"venue"
},
  "geometry": {"coordinates":[-73.831577,43.041889],"type":"Point"}
}