{
  "type": "Feature",
  "properties": {
    "iso:country":"US",
    "sg:address":"300 E 42nd St",
    "sg:city":"New York",
    "sg:classifiers":[
        {
            "category":"Professional",
            "subcategory":"Advertising",
            "type":"Services"
        }
    ],
    "sg:phone":"+1 212 682 6602",
    "sg:postcode":"10017",
    "sg:province":"NY",
    "sg:tags":[
        "counselor"
    ],
    "wof:name":"Cannon Advertising Assoc Inc",
    "wof:placetype":"venue"
},
  "geometry": {"coordinates":[-73.970412,40.749072],"type":"Point"}
}