{
  "type": "Feature",
  "properties": {
    "addr:full":"91 Smith Ave Mount Kisco NY 10549",
    "addr:housenumber":"91",
    "addr:postcode":"10549",
    "addr:street":"Smith Ave",
    "iso:country":"US",
    "sg:address":"91 Smith Ave",
    "sg:city":"Mount Kisco",
    "sg:classifiers":[
        {
            "category":"Banks & Credit Unions",
            "subcategory":"Investment Brokerage",
            "type":"Services"
        }
    ],
    "sg:phone":"+1 914 241 4971",
    "sg:postcode":"10549",
    "sg:province":"NY",
    "sg:tags":[
        "security"
    ],
    "wof:name":"Empire Financial Svces",
    "wof:placetype":"venue"
},
  "geometry": {"coordinates":[-73.72756099999999,41.20017],"type":"Point"}
}