{
  "type": "Feature",
  "properties": {
    "iso:country":"US",
    "sg:address":"72 East Ave",
    "sg:city":"Attica",
    "sg:classifiers":[
        {
            "category":"Education",
            "subcategory":"School",
            "type":"Public Place"
        }
    ],
    "sg:phone":"+1 585 591 2515",
    "sg:postcode":"14011",
    "sg:province":"NY",
    "sg:tags":[
        "educational"
    ],
    "wof:name":"Genessee Wyoming Catholic Schl",
    "wof:placetype":"venue"
},
  "geometry": {"coordinates":[-78.27456599999999,42.865881],"type":"Point"}
}