{
  "type": "Feature",
  "properties": {
    "iso:country":"US",
    "sg:address":"2 Bayview Ave",
    "sg:city":"Bayville",
    "sg:classifiers":[
        {
            "category":"Building & Trades",
            "subcategory":"Plumbing",
            "type":"Services"
        }
    ],
    "sg:phone":"+1 516 628 2059",
    "sg:postcode":"11709",
    "sg:province":"NY",
    "sg:tags":[
        "tank",
        "septic"
    ],
    "wof:name":"D C Crane Svc Inc",
    "wof:placetype":"venue"
},
  "geometry": {"coordinates":[-73.560993,40.902756],"type":"Point"}
}