{
  "type": "Feature",
  "properties": {
    "addr:full":"625 8 Ave New York NY 10018",
    "addr:housenumber":"625",
    "addr:postcode":"10018",
    "addr:street":"8 Ave",
    "iso:country":"US",
    "sg:address":"625 8 Ave",
    "sg:city":"New York",
    "sg:classifiers":[
        {
            "category":"Local Transit",
            "type":"Transportation"
        }
    ],
    "sg:phone":"+1 212 695 0001",
    "sg:postcode":"10018",
    "sg:province":"NY",
    "sg:tags":[
        "bus",
        "line"
    ],
    "wof:name":"Grayline New York Tours Inc",
    "wof:placetype":"venue"
},
  "geometry": {"coordinates":[-73.99252799999999,40.753474],"type":"Point"}
}