{
  "type": "Feature",
  "properties": {
    "addr:full":"1240 Oakpoint Ave Bronx NY 10474",
    "addr:housenumber":"1240",
    "addr:postcode":"10474",
    "addr:street":"Oakpoint Ave",
    "iso:country":"US",
    "sg:address":"1240 Oakpoint Ave",
    "sg:city":"Bronx",
    "sg:classifiers":[
        {
            "category":"Building & Trades",
            "subcategory":"Landscaping Services",
            "type":"Services"
        }
    ],
    "sg:phone":"+1 718 542 0181",
    "sg:postcode":"10474",
    "sg:province":"NY",
    "sg:tags":[
        "tree"
    ],
    "wof:name":"Juniper Tree Inc",
    "wof:placetype":"venue"
},
  "geometry": {"coordinates":[-73.88723299999999,40.810053],"type":"Point"}
}