{
  "type": "Feature",
  "properties": {
    "iso:country":"US",
    "sg:address":"RR 112",
    "sg:city":"Coram",
    "sg:classifiers":[
        {
            "category":"Retail",
            "subcategory":"Funeral Services",
            "type":"Services"
        }
    ],
    "sg:phone":"+1 631 732 3460",
    "sg:postcode":"11727",
    "sg:province":"NY",
    "sg:tags":[
        "cemetery"
    ],
    "wof:name":"Cemetery Catholic Holy Sepulchre",
    "wof:placetype":"venue"
},
  "geometry": {"coordinates":[-73.0047,40.878101],"type":"Point"}
}