{
  "type": "Feature",
  "properties": {
    "addr:full":"225 E 202nd St Bronx NY 10458",
    "addr:housenumber":"225",
    "addr:postcode":"10458",
    "addr:street":"E 202Nd St",
    "iso:country":"US",
    "sg:address":"225 E 202nd St",
    "sg:city":"Bronx",
    "sg:classifiers":[
        {
            "category":"Professional",
            "type":"Services"
        }
    ],
    "sg:phone":"+1 718 933 3490",
    "sg:postcode":"10458",
    "sg:province":"NY",
    "wof:name":"New Day Women Svc",
    "wof:placetype":"venue"
},
  "geometry": {"coordinates":[-73.88614699999999,40.873286],"type":"Point"}
}