{
  "type": "Feature",
  "properties": {
    "addr:full":"551 S Columbus Ave Mt Vernon NY 10550",
    "addr:housenumber":"551",
    "addr:postcode":"10550",
    "addr:street":"S Columbus Ave",
    "iso:country":"US",
    "sg:address":"551 S Columbus Ave",
    "sg:city":"Mt Vernon",
    "sg:classifiers":[
        {
            "category":"Wholesale",
            "subcategory":"Hardware",
            "type":"Manufacturing & Wholesale Goods"
        }
    ],
    "sg:phone":"+1 914 668 3631",
    "sg:postcode":"10550",
    "sg:province":"NY",
    "sg:tags":[
        "equipment",
        "heating",
        "system"
    ],
    "wof:name":"Sid Harvey's Westchester Corp",
    "wof:placetype":"venue"
},
  "geometry": {"coordinates":[-73.82125000000001,40.899355],"type":"Point"}
}