{
  "type": "Feature",
  "properties": {
    "addr:full":"241 Central Park W New York NY 10024",
    "addr:housenumber":"241",
    "addr:postcode":"10024",
    "addr:street":"Central Park W",
    "iso:country":"US",
    "sg:address":"241 Central Park W",
    "sg:city":"New York",
    "sg:classifiers":[
        {
            "category":"Building & Trades",
            "subcategory":"Construction",
            "type":"Services"
        }
    ],
    "sg:phone":"+1 212 920 1533",
    "sg:postcode":"10024",
    "sg:province":"NY",
    "sg:tags":[
        "contractor"
    ],
    "wof:name":"Y C Construction Management",
    "wof:placetype":"venue"
},
  "geometry": {"coordinates":[-73.970489,40.784348],"type":"Point"}
}