{
  "type": "Feature",
  "properties": {
    "iso:country":"US",
    "sg:address":"178 Ocean Pkwy",
    "sg:city":"Brooklyn",
    "sg:classifiers":[
        {
            "category":"Real Estate",
            "subcategory":"Real Estate Operator",
            "type":"Services"
        }
    ],
    "sg:postcode":"11218",
    "sg:province":"NY",
    "sg:tags":[
        "apartment"
    ],
    "wof:name":"178 Ocean Parkway Apartments",
    "wof:placetype":"venue"
},
  "geometry": {"coordinates":[-73.97524900000001,40.645964],"type":"Point"}
}