{
  "type": "Feature",
  "properties": {
    "iso:country":"US",
    "sg:address":"16 Oswego St",
    "sg:city":"Baldwinsville",
    "sg:classifiers":[
        {
            "category":"Building & Trades",
            "subcategory":"Plumbing",
            "type":"Services"
        }
    ],
    "sg:phone":"+1 315 635 5981",
    "sg:postcode":"13027",
    "sg:province":"NY",
    "sg:tags":[
        "plumbing",
        "a",
        "heating",
        "contractor"
    ],
    "wof:name":"Farrell Plumbing & Heating Co",
    "wof:placetype":"venue"
},
  "geometry": {"coordinates":[-76.33252400000001,43.158245],"type":"Point"}
}