{
  "type": "Feature",
  "properties": {
    "iso:country":"US",
    "sg:address":"50 W 17 St",
    "sg:city":"New York",
    "sg:classifiers":[
        {
            "category":"Real Estate",
            "subcategory":"Real Estate Operator",
            "type":"Services"
        }
    ],
    "sg:phone":"+1 212 757 5830",
    "sg:postcode":"10011",
    "sg:province":"NY",
    "sg:tags":[
        "owner",
        "building",
        "apartment"
    ],
    "wof:name":"Westman Realty Co",
    "wof:placetype":"venue"
},
  "geometry": {"coordinates":[-73.99426200000001,40.738528],"type":"Point"}
}