{
  "type": "Feature",
  "properties": {
    "iso:country":"US",
    "sg:address":"180 Park Ave",
    "sg:city":"Amityville",
    "sg:classifiers":[
        {
            "category":"Personal",
            "subcategory":"Beauty Salon",
            "type":"Services"
        }
    ],
    "sg:phone":"+1 631 264 2345",
    "sg:postcode":"11701",
    "sg:province":"NY",
    "sg:tags":[
        "manicuring"
    ],
    "wof:name":"Nail Studio",
    "wof:placetype":"venue"
},
  "geometry": {"coordinates":[-73.41776,40.677718],"type":"Point"}
}