{
  "type": "Feature",
  "properties": {
    "addr:full":"135 W 20th St New York NY 10011",
    "addr:housenumber":"135",
    "addr:postcode":"10011",
    "addr:street":"W 20Th St",
    "iso:country":"US",
    "sg:address":"135 W 20th St",
    "sg:city":"New York",
    "sg:classifiers":[
        {
            "category":"Real Estate",
            "subcategory":"Real Estate Agent",
            "type":"Services"
        }
    ],
    "sg:phone":"+1 212 727 3123",
    "sg:postcode":"10011",
    "sg:province":"NY",
    "wof:name":"A & G Real Estate LLC",
    "wof:placetype":"venue"
},
  "geometry": {"coordinates":[-73.996224,40.741878],"type":"Point"}
}