{
  "type": "Feature",
  "properties": {
    "addr:full":"492 E Meadow Ave East Meadow NY 11554",
    "addr:housenumber":"492",
    "addr:postcode":"11554",
    "addr:street":"E Meadow Ave",
    "iso:country":"US",
    "sg:address":"492 E Meadow Ave",
    "sg:city":"East Meadow",
    "sg:classifiers":[
        {
            "category":"Real Estate",
            "subcategory":"Real Estate Agent",
            "type":"Services"
        }
    ],
    "sg:phone":"+1 516 485 0374",
    "sg:postcode":"11554",
    "sg:province":"NY",
    "wof:name":"Realty Network",
    "wof:placetype":"venue"
},
  "geometry": {"coordinates":[-73.55723399999999,40.712274],"type":"Point"}
}