{
  "type": "Feature",
  "properties": {
    "addr:full":"155 Montague St Brooklyn NY 11201",
    "addr:housenumber":"155",
    "addr:postcode":"11201",
    "addr:street":"Montague St",
    "iso:country":"US",
    "sg:address":"155 Montague St",
    "sg:city":"Brooklyn",
    "sg:classifiers":[
        {
            "category":"Travel",
            "subcategory":"Travel Agent",
            "type":"Entertainment"
        }
    ],
    "sg:phone":"+1   ",
    "sg:postcode":"11201",
    "sg:province":"NY",
    "sg:tags":[
        "passenger",
        "agency",
        "transportation",
        "arrangement"
    ],
    "wof:name":"Liberty Travel Inc",
    "wof:placetype":"venue"
},
  "geometry": {"coordinates":[-73.993201,40.694638],"type":"Point"}
}