{
  "type": "Feature",
  "properties": {
    "iso:country":"US",
    "sg:address":"4501 Southwestern Blvd",
    "sg:city":"Hamburg",
    "sg:classifiers":[
        {
            "category":"Professional",
            "subcategory":"Business Services",
            "type":"Services"
        }
    ],
    "sg:phone":"+1 716 646 5949",
    "sg:postcode":"14075",
    "sg:province":"NY",
    "sg:tags":[
        "embroidery"
    ],
    "wof:name":"Allstars Embroidery & Screen",
    "wof:placetype":"venue"
},
  "geometry": {"coordinates":[-78.82611199999999,42.762988],"type":"Point"}
}