{
  "type": "Feature",
  "properties": {
    "addr:full":"279 Water St New York NY 10038",
    "addr:housenumber":"279",
    "addr:postcode":"10038",
    "addr:street":"Water St",
    "iso:country":"US",
    "sg:address":"279 Water St",
    "sg:city":"New York",
    "sg:classifiers":[
        {
            "category":"Cafe",
            "type":"Food & Drink"
        },
        {
            "category":"Restaurant",
            "type":"Food & Drink"
        }
    ],
    "sg:menulink":"http://www.allmenus.com/ny/new-york/252327-bridge-cafe/menu/",
    "sg:phone":"+1 212 227 3344",
    "sg:postcode":"10038",
    "sg:province":"NY",
    "sg:tags":[
        "american",
        "steakhouse",
        "seafood",
        "chicken"
    ],
    "wof:name":"Bridge Cafe",
    "wof:placetype":"venue"
},
  "geometry": {"coordinates":[-74.000826,40.70864],"type":"Point"}
}