{
  "type": "Feature",
  "properties": {
    "addr:full":"222 W Summit St Lakewood NY 14750",
    "addr:housenumber":"222",
    "addr:postcode":"14750",
    "addr:street":"W Summit St",
    "iso:country":"US",
    "sg:address":"222 W Summit St",
    "sg:city":"Lakewood",
    "sg:classifiers":[
        {
            "category":"Health Services",
            "subcategory":"Doctor",
            "type":"Services"
        }
    ],
    "sg:phone":"+1 716 763 0003",
    "sg:postcode":"14750",
    "sg:province":"NY",
    "sg:tags":[
        "dentist"
    ],
    "wof:name":"Andrew C Kohl DDS",
    "wof:placetype":"venue"
},
  "geometry": {"coordinates":[-79.342077,42.100831],"type":"Point"}
}