{
  "type": "Feature",
  "properties": {
    "iso:country":"US",
    "sg:address":"1200 Carlls Straight Path",
    "sg:city":"Dix Hills",
    "sg:classifiers":[
        {
            "category":"Building & Trades",
            "subcategory":"Plumbing",
            "type":"Services"
        }
    ],
    "sg:phone":"+1 631 254 6434",
    "sg:postcode":"11746",
    "sg:province":"NY",
    "sg:tags":[
        "plumbing",
        "contractor"
    ],
    "wof:name":"ARA Plumbing & Heating",
    "wof:placetype":"venue"
},
  "geometry": {"coordinates":[-73.320222,40.789987],"type":"Point"}
}