{
  "type": "Feature",
  "properties": {
    "iso:country":"US",
    "sg:address":"312 Lakeside Rd",
    "sg:city":"Syracuse",
    "sg:phone":"+1 315 407 8463",
    "sg:postcode":"13209",
    "sg:province":"NY",
    "sg:website":"http://www.vineyardny.org",
    "wof:name":"The Vineyard Church",
    "wof:placetype":"venue"
},
  "geometry": {"coordinates":[-76.253168,43.105052],"type":"Point"}
}