{
  "type": "Feature",
  "properties": {
    "addr:full":"16 Frederick St Garnerville NY 10923",
    "addr:housenumber":"16",
    "addr:postcode":"10923",
    "addr:street":"Frederick St",
    "iso:country":"US",
    "sg:address":"16 Frederick St",
    "sg:city":"Garnerville",
    "sg:classifiers":[
        {
            "category":"Real Estate",
            "subcategory":"Real Estate Agent",
            "type":"Services"
        }
    ],
    "sg:phone":"+1 845 786 0051",
    "sg:postcode":"10923",
    "sg:province":"NY",
    "wof:name":"ORC Realty",
    "wof:placetype":"venue"
},
  "geometry": {"coordinates":[-74.000711,41.215056],"type":"Point"}
}