{
  "type": "Feature",
  "properties": {
    "addr:full":"3649 Erie Blvd E Syracuse NY 13214",
    "addr:housenumber":"3649",
    "addr:postcode":"13214",
    "addr:street":"Erie Blvd E",
    "iso:country":"US",
    "sg:address":"3649 Erie Blvd E",
    "sg:city":"Syracuse",
    "sg:classifiers":[
        {
            "category":"Utilities",
            "subcategory":"Mobile Phone",
            "type":"Services"
        },
        {
            "category":"Shopping",
            "subcategory":"Mobile Phones",
            "type":"Retail Goods"
        },
        {
            "category":"Utilities",
            "subcategory":"Telephone",
            "type":"Services"
        },
        {
            "category":"Professional",
            "subcategory":"Computer Services",
            "type":"Services"
        }
    ],
    "sg:phone":"+1 315 449 1948",
    "sg:postcode":"13214",
    "sg:province":"NY",
    "sg:tags":[
        "telecommunication",
        "supply",
        "communication",
        "system",
        "wireless",
        "equipment",
        "cellular"
    ],
    "sg:website":"http://clickserve.dartsearch.net/link/click?lid=43000000308049899",
    "wof:name":"T-Mobile",
    "wof:placetype":"venue"
},
  "geometry": {"coordinates":[-76.065849,43.038841],"type":"Point"}
}