{
  "type": "Feature",
  "properties": {
    "iso:country":"US",
    "sg:address":"8041 Candela Ln",
    "sg:city":"Clay",
    "sg:classifiers":[
        {
            "category":"Professional",
            "subcategory":"Accounting & Tax Preparation",
            "type":"Services"
        }
    ],
    "sg:phone":"+1   ",
    "sg:postcode":"13041",
    "sg:province":"NY",
    "sg:tags":[
        "medical",
        "billing"
    ],
    "wof:name":"American Healthcare Billing",
    "wof:placetype":"venue"
},
  "geometry": {"coordinates":[-76.134739,43.158818],"type":"Point"}
}