{
  "type": "Feature",
  "properties": {
    "addr:full":"124 N Ridge St Port Chester NY 10573",
    "addr:housenumber":"124",
    "addr:postcode":"10573",
    "addr:street":"N Ridge St",
    "iso:country":"US",
    "sg:address":"124 N Ridge St",
    "sg:city":"Port Chester",
    "sg:classifiers":[
        {
            "category":"Retail",
            "subcategory":"Self-service Laundry",
            "type":"Services"
        }
    ],
    "sg:phone":"+1   ",
    "sg:postcode":"10573",
    "sg:province":"NY",
    "sg:tags":[
        "coin"
    ],
    "wof:name":"B & G Laundry LLC",
    "wof:placetype":"venue"
},
  "geometry": {"coordinates":[-73.68138399999999,41.014562],"type":"Point"}
}