{
  "type": "Feature",
  "properties": {
    "iso:country":"US",
    "sg:address":"2300 Buffalo Rd Bldg 100C",
    "sg:city":"Rochester",
    "sg:classifiers":[
        {
            "category":"Health Services",
            "subcategory":"Doctor",
            "type":"Services"
        },
        {
            "category":"Health Services",
            "subcategory":"Clinic",
            "type":"Services"
        },
        {
            "category":"Health Services",
            "subcategory":"Health Practitioner",
            "type":"Services"
        }
    ],
    "sg:phone":"+1 585 247 0080",
    "sg:postcode":"14624",
    "sg:province":"NY",
    "sg:tags":[
        "physician",
        "surgeons",
        "therapist",
        "therapy",
        "medicine",
        "sport",
        "physical"
    ],
    "wof:name":"Genesee Valley Physical Therapy And Sports Rehab, P.C.",
    "wof:placetype":"venue"
},
  "geometry": {"coordinates":[-77.71199,43.146869],"type":"Point"}
}