{
  "type": "Feature",
  "properties": {
    "iso:country":"US",
    "sg:address":"156 E 23rd Street",
    "sg:city":"New York",
    "sg:classifiers":[
        {
            "category":"Building & Trades",
            "subcategory":"Locksmith",
            "type":"Services"
        }
    ],
    "sg:phone":"+1 212 460 8636",
    "sg:postcode":"10010",
    "sg:province":"NY",
    "sg:tags":[
        "key"
    ],
    "wof:name":"Eagle Master Signs & Awards",
    "wof:placetype":"venue"
},
  "geometry": {"coordinates":[-73.984487,40.739338],"type":"Point"}
}