{
  "type": "Feature",
  "properties": {
    "addr:full":"7005 Ave U Brooklyn NY 11234",
    "addr:housenumber":"7005",
    "addr:postcode":"11234",
    "addr:street":"Ave U",
    "iso:country":"US",
    "sg:address":"7005 Ave U",
    "sg:city":"Brooklyn",
    "sg:classifiers":[
        {
            "category":"Shopping",
            "subcategory":"Stationery & Office Supplies",
            "type":"Retail Goods"
        }
    ],
    "sg:phone":"+1   ",
    "sg:postcode":"11234",
    "sg:province":"NY",
    "sg:tags":[
        "newspaper",
        "gift"
    ],
    "wof:name":"Card Corner III Inc",
    "wof:placetype":"venue"
},
  "geometry": {"coordinates":[-73.907517,40.619872],"type":"Point"}
}