{
  "type": "Feature",
  "properties": {
    "iso:country":"US",
    "sg:address":"4456 Cole Rd",
    "sg:city":"Syracuse",
    "sg:classifiers":[
        {
            "category":"Building & Trades",
            "subcategory":"Construction",
            "type":"Services"
        }
    ],
    "sg:phone":"+1 315 469 4060",
    "sg:postcode":"13215",
    "sg:province":"NY",
    "sg:tags":[
        "general",
        "contractor"
    ],
    "wof:name":"Seaward Construction",
    "wof:placetype":"venue"
},
  "geometry": {"coordinates":[-76.199546,42.945118],"type":"Point"}
}