{
  "type": "Feature",
  "properties": {
    "addr:full":"881 Chili Ave Rochester NY 14611",
    "addr:housenumber":"881",
    "addr:postcode":"14611",
    "addr:street":"Chili Ave",
    "iso:country":"US",
    "sg:address":"881 Chili Ave",
    "sg:city":"Rochester",
    "sg:classifiers":[
        {
            "category":"Food & Beverages",
            "subcategory":"Groceries & Convenience Stores",
            "type":"Retail Goods"
        }
    ],
    "sg:phone":"+1   ",
    "sg:postcode":"14611",
    "sg:province":"NY",
    "wof:name":"Brighton Super Saver Magazine",
    "wof:placetype":"venue"
},
  "geometry": {"coordinates":[-77.66009200000001,43.142266],"type":"Point"}
}