{
  "type": "Feature",
  "properties": {
    "addr:full":"19 Union Sq W Fl 12 New York NY 10003",
    "addr:housenumber":"19;12",
    "addr:postcode":"10003",
    "addr:street":"Union Sq W Fl",
    "iso:country":"US",
    "sg:address":"19 Union Sq W Fl 12",
    "sg:city":"New York",
    "sg:classifiers":[
        {
            "category":"Real Estate",
            "subcategory":"Architect",
            "type":"Services"
        }
    ],
    "sg:phone":"+1 212 691 2440",
    "sg:postcode":"10003",
    "sg:province":"NY",
    "wof:name":"Platt Byard Dovell Architects",
    "wof:placetype":"venue"
},
  "geometry": {"coordinates":[-73.991203,40.736],"type":"Point"}
}