{
  "type": "Feature",
  "properties": {
    "addr:full":"26 Sobieski St Rochester NY 14621",
    "addr:housenumber":"26",
    "addr:postcode":"14621",
    "addr:street":"Sobieski St",
    "iso:country":"US",
    "sg:address":"26 Sobieski St",
    "sg:city":"Rochester",
    "sg:classifiers":[
        {
            "category":"Organizations",
            "subcategory":"Religious Organization",
            "type":"Services"
        }
    ],
    "sg:phone":"+1 585 544 2820",
    "sg:postcode":"14621",
    "sg:province":"NY",
    "sg:tags":[
        "church"
    ],
    "wof:name":"Ukranian Christian Pentecostal",
    "wof:placetype":"venue"
},
  "geometry": {"coordinates":[-77.59613899999999,43.184551],"type":"Point"}
}