{
  "type": "Feature",
  "properties": {
    "iso:country":"US",
    "sg:address":"25 S Pearl St",
    "sg:city":"Pearl River",
    "sg:classifiers":[
        {
            "category":"Shopping",
            "subcategory":"Clothing, Apparel, & Fashions",
            "type":"Retail Goods"
        }
    ],
    "sg:phone":"+1 845 735 1614",
    "sg:postcode":"10965",
    "sg:province":"NY",
    "sg:tags":[
        "theatrical",
        "costume"
    ],
    "wof:name":"Costume House",
    "wof:placetype":"venue"
},
  "geometry": {"coordinates":[-74.02448,41.05824],"type":"Point"}
}