{
  "type": "Feature",
  "properties": {
    "addr:full":"308 Atkins Avenue Brooklyn NY 11208",
    "addr:housenumber":"308",
    "addr:postcode":"11208",
    "addr:street":"Atkins Avenue",
    "iso:country":"US",
    "sg:address":"308 Atkins Avenue",
    "sg:city":"Brooklyn",
    "sg:classifiers":[
        {
            "category":"Organizations",
            "subcategory":"Religious Organization",
            "type":"Services"
        }
    ],
    "sg:phone":"+1 718 647 8988",
    "sg:postcode":"11208",
    "sg:province":"NY",
    "wof:name":"Ammies Chapel F B H Church",
    "wof:placetype":"venue"
},
  "geometry": {"coordinates":[-73.87855999999999,40.672152],"type":"Point"}
}