{
  "type": "Feature",
  "properties": {
    "addr:full":"1312 E Gun Hill Rd Bronx NY 10469",
    "addr:housenumber":"1312",
    "addr:postcode":"10469",
    "addr:street":"E Gun Hill Rd",
    "iso:country":"US",
    "sg:address":"1312 E Gun Hill Rd",
    "sg:city":"Bronx",
    "sg:classifiers":[
        {
            "category":"Building & Trades",
            "subcategory":"Plumbing",
            "type":"Services"
        }
    ],
    "sg:phone":"+1 718 994 0808",
    "sg:postcode":"10469",
    "sg:province":"NY",
    "sg:tags":[
        "plumbing",
        "contractor"
    ],
    "wof:name":"Plumbing Sewer Drain 24 Hrs",
    "wof:placetype":"venue"
},
  "geometry": {"coordinates":[-73.848305,40.871497],"type":"Point"}
}