{
  "type": "Feature",
  "properties": {
    "iso:country":"US",
    "sg:address":"574 Warburton Ave",
    "sg:city":"Hastings On Hdsn",
    "sg:classifiers":[
        {
            "category":"Shopping",
            "subcategory":"Optical Goods",
            "type":"Retail Goods"
        }
    ],
    "sg:phone":"+1 914 478 0550",
    "sg:postcode":"10706",
    "sg:province":"NY",
    "sg:tags":[
        "optician"
    ],
    "wof:name":"Bauer Opticians",
    "wof:placetype":"venue"
},
  "geometry": {"coordinates":[-73.881927,40.996356],"type":"Point"}
}