{
  "type": "Feature",
  "properties": {
    "iso:country":"US",
    "sg:address":"169 S Plank Rd",
    "sg:city":"Newburgh",
    "sg:classifiers":[
        {
            "category":"Retail",
            "subcategory":"Self-service Laundry",
            "type":"Services"
        }
    ],
    "sg:phone":"+1   ",
    "sg:postcode":"12550",
    "sg:province":"NY",
    "sg:tags":[
        "coin"
    ],
    "wof:name":"Duds & Suds",
    "wof:placetype":"venue"
},
  "geometry": {"coordinates":[-74.063042,41.522394],"type":"Point"}
}