{
  "type": "Feature",
  "properties": {
    "addr:full":"980 Broadway Ste 535 Thornwood NY 10594",
    "addr:housenumber":"980",
    "addr:postcode":"10594",
    "addr:street":"Broadway Ste 535",
    "iso:country":"US",
    "sg:address":"980 Broadway Ste 535",
    "sg:city":"Thornwood",
    "sg:classifiers":[
        {
            "category":"Home & Garden",
            "subcategory":"Building Materials",
            "type":"Retail Goods"
        }
    ],
    "sg:phone":"+1 914 930 5592",
    "sg:postcode":"10594",
    "sg:province":"NY",
    "sg:website":"http://newyork.citysearch.com/profile/external/653723370/thornwood_ny/big_apple_refinishing.html?publisher=yellowpages&reference_id=15&placement=ypwebsitemip",
    "wof:name":"Big Apple Refinishing",
    "wof:placetype":"venue"
},
  "geometry": {"coordinates":[-73.780145,41.12604],"type":"Point"}
}