{
  "type": "Feature",
  "properties": {
    "iso:country":"US",
    "sg:address":"2872 Rosebud Ave",
    "sg:city":"Merrick",
    "sg:classifiers":[
        {
            "category":"Professional",
            "subcategory":"Accounting & Tax Preparation",
            "type":"Services"
        }
    ],
    "sg:phone":"+1 516 868 1334",
    "sg:postcode":"11566",
    "sg:province":"NY",
    "sg:tags":[
        "accountant"
    ],
    "wof:name":"Stephen Tarnofsky CPA",
    "wof:placetype":"venue"
},
  "geometry": {"coordinates":[-73.550665,40.645433],"type":"Point"}
}