{
  "type": "Feature",
  "properties": {
    "addr:full":"1857 E 13th St Brooklyn NY 11229",
    "addr:housenumber":"1857",
    "addr:postcode":"11229",
    "addr:street":"E 13Th St",
    "iso:country":"US",
    "sg:address":"1857 E 13th St",
    "sg:city":"Brooklyn",
    "sg:classifiers":[
        {
            "category":"Organizations",
            "subcategory":"Non-profit Organization",
            "type":"Services"
        }
    ],
    "sg:phone":"+1 718 382 7054",
    "sg:postcode":"11229",
    "sg:province":"NY",
    "sg:tags":[
        "service/non-profit",
        "community"
    ],
    "wof:name":"Hasc Center",
    "wof:placetype":"venue"
},
  "geometry": {"coordinates":[-73.959198,40.604198],"type":"Point"}
}