{
  "type": "Feature",
  "properties": {
    "iso:country":"US",
    "sg:address":"3039 Grace Ave",
    "sg:city":"Bronx",
    "sg:classifiers":[
        {
            "category":"Social Services",
            "subcategory":"Child Care",
            "type":"Services"
        }
    ],
    "sg:phone":"+1   ",
    "sg:postcode":"10469",
    "sg:province":"NY",
    "sg:tags":[
        "day"
    ],
    "wof:name":"Tot N Ville LLC",
    "wof:placetype":"venue"
},
  "geometry": {"coordinates":[-73.83645,40.872745],"type":"Point"}
}