{
  "type": "Feature",
  "properties": {
    "iso:country":"US",
    "sg:address":"2888 Ridgeway Ave",
    "sg:city":"Rochester",
    "sg:classifiers":[
        {
            "category":"Restaurant",
            "type":"Food & Drink"
        }
    ],
    "sg:phone":"+1 585 225 5290",
    "sg:postcode":"14626",
    "sg:province":"NY",
    "sg:tags":[
        "banquet",
        "rooms"
    ],
    "wof:name":"Lodge On The Green Party House",
    "wof:placetype":"venue"
},
  "geometry": {"coordinates":[-77.72457199999999,43.187016],"type":"Point"}
}