{
  "type": "Feature",
  "properties": {
    "addr:full":"80 N Moore St New York NY 10013",
    "addr:housenumber":"80",
    "addr:postcode":"10013",
    "addr:street":"N Moore St",
    "iso:country":"US",
    "sg:address":"80 N Moore St",
    "sg:city":"New York",
    "sg:classifiers":[
        {
            "category":"Professional",
            "subcategory":"Management & Consulting",
            "type":"Services"
        }
    ],
    "sg:phone":"+1   ",
    "sg:postcode":"10013",
    "sg:province":"NY",
    "sg:tags":[
        "communications",
        "public",
        "relations",
        "advertising"
    ],
    "wof:name":"Halliburton Mirth Associates",
    "wof:placetype":"venue"
},
  "geometry": {"coordinates":[-74.012134,40.720238],"type":"Point"}
}