{
  "type": "Feature",
  "properties": {
    "addr:full":"21 Barclay Street New York NY 10007",
    "addr:housenumber":"21",
    "addr:postcode":"10007",
    "addr:street":"Barclay Street",
    "iso:country":"US",
    "sg:address":"21 Barclay Street",
    "sg:city":"New York",
    "sg:classifiers":[
        {
            "category":"Building & Trades",
            "subcategory":"Construction",
            "type":"Services"
        }
    ],
    "sg:phone":"+1 212 693 2169",
    "sg:postcode":"10007",
    "sg:province":"NY",
    "sg:tags":[
        "contractor"
    ],
    "wof:name":"Glenwood Management Corporation",
    "wof:placetype":"venue"
},
  "geometry": {"coordinates":[-74.008754,40.712525],"type":"Point"}
}