{
  "type": "Feature",
  "properties": {
    "addr:full":"131 Greenpoint Ave Brooklyn NY 11222",
    "addr:housenumber":"131",
    "addr:postcode":"11222",
    "addr:street":"Greenpoint Ave",
    "iso:country":"US",
    "sg:address":"131 Greenpoint Ave",
    "sg:city":"Brooklyn",
    "sg:classifiers":[
        {
            "category":"Personal",
            "subcategory":"Beauty Salon",
            "type":"Services"
        }
    ],
    "sg:phone":"+1 718 389 5903",
    "sg:postcode":"11222",
    "sg:province":"NY",
    "wof:name":"Ania Beauty Salon",
    "wof:placetype":"venue"
},
  "geometry": {"coordinates":[-73.95644900000001,40.729996],"type":"Point"}
}