{
  "type": "Feature",
  "properties": {
    "addr:full":"603 Greenwich St New York NY 10014",
    "addr:housenumber":"603",
    "addr:postcode":"10014",
    "addr:street":"Greenwich St",
    "iso:country":"US",
    "sg:address":"603 Greenwich St",
    "sg:city":"New York",
    "sg:classifiers":[
        {
            "category":"Communications",
            "subcategory":"Film & Video Production",
            "type":"Services"
        }
    ],
    "sg:phone":"+1 212 633 8700",
    "sg:postcode":"10014",
    "sg:province":"NY",
    "sg:tags":[
        "company",
        "commercial"
    ],
    "wof:name":"Schofield Films Inc",
    "wof:placetype":"venue"
},
  "geometry": {"coordinates":[-74.008201,40.73035],"type":"Point"}
}