{
  "type": "Feature",
  "properties": {
    "iso:country":"US",
    "sg:address":"152 Long Beach Rd",
    "sg:city":"Island Park",
    "sg:classifiers":[
        {
            "category":"Food & Beverages",
            "subcategory":"Groceries & Convenience Stores",
            "type":"Retail Goods"
        }
    ],
    "sg:phone":"+1   ",
    "sg:postcode":"11558",
    "sg:province":"NY",
    "wof:name":"Island Park Food Center",
    "wof:placetype":"venue"
},
  "geometry": {"coordinates":[-73.655756,40.60326],"type":"Point"}
}