{
  "type": "Feature",
  "properties": {
    "iso:country":"US",
    "sg:address":"45 Allens Creek Rd",
    "sg:city":"Rochester",
    "sg:classifiers":[
        {
            "category":"Health Services",
            "subcategory":"Doctor",
            "type":"Services"
        }
    ],
    "sg:phone":"+1 585 271 7900",
    "sg:postcode":"14618",
    "sg:province":"NY",
    "sg:tags":[
        "dentist"
    ],
    "wof:name":"E David Appelbaum PC",
    "wof:placetype":"venue"
},
  "geometry": {"coordinates":[-77.549997,43.116556],"type":"Point"}
}