{
  "type": "Feature",
  "properties": {
    "iso:country":"US",
    "sg:address":"2441 White Plains Rd",
    "sg:city":"Bronx",
    "sg:classifiers":[
        {
            "category":"Retail",
            "subcategory":"Laundry & Dry Cleaning",
            "type":"Services"
        }
    ],
    "sg:phone":"+1 718 994 7797",
    "sg:postcode":"10467",
    "sg:province":"NY",
    "sg:website":"www.laundryzone.com",
    "wof:name":"Laundry Zone",
    "wof:placetype":"venue"
},
  "geometry": {"coordinates":[-73.86751599999999,40.862452],"type":"Point"}
}