{
  "type": "Feature",
  "properties": {
    "addr:full":"608 Old Post Rd Bedford NY 10506",
    "addr:housenumber":"608",
    "addr:postcode":"10506",
    "addr:street":"Old Post Rd",
    "iso:country":"US",
    "sg:address":"608 Old Post Rd",
    "sg:city":"Bedford",
    "sg:classifiers":[
        {
            "category":"Recreation",
            "type":"Entertainment"
        }
    ],
    "sg:phone":"+1 914 234 3056",
    "sg:postcode":"10506",
    "sg:province":"NY",
    "sg:tags":[
        "hall",
        "auditorium"
    ],
    "wof:name":"Bedford Historical Hall",
    "wof:placetype":"venue"
},
  "geometry": {"coordinates":[-73.643771,41.203349],"type":"Point"}
}