{
  "type": "Feature",
  "properties": {
    "addr:full":"264 Muttontown Eastwoods Rd Syosset NY 11791",
    "addr:housenumber":"264",
    "addr:postcode":"11791",
    "addr:street":"Muttontown Eastwoods Rd",
    "iso:country":"US",
    "sg:address":"264 Muttontown Eastwoods Rd",
    "sg:city":"Syosset",
    "sg:classifiers":[
        {
            "category":"Real Estate",
            "subcategory":"Real Estate Services",
            "type":"Services"
        },
        {
            "category":"Real Estate",
            "subcategory":"Real Estate Agent",
            "type":"Services"
        }
    ],
    "sg:phone":"+1 516 921 5064",
    "sg:postcode":"11791",
    "sg:province":"NY",
    "sg:tags":[
        "buyer",
        "management",
        "broker"
    ],
    "wof:name":"Rga Realty Corp",
    "wof:placetype":"venue"
},
  "geometry": {"coordinates":[-73.51651,40.82513],"type":"Point"}
}