{
  "type": "Feature",
  "properties": {
    "iso:country":"US",
    "sg:address":"798 Lexington Ave",
    "sg:city":"New York",
    "sg:classifiers":[
        {
            "category":"Retail",
            "subcategory":"Pet Boarding",
            "type":"Services"
        }
    ],
    "sg:phone":"+1 212 838 8460",
    "sg:postcode":"10021",
    "sg:province":"NY",
    "sg:tags":[
        "boarding/pet",
        "sitting"
    ],
    "wof:name":"American Kennels",
    "wof:placetype":"venue"
},
  "geometry": {"coordinates":[-73.958702,40.768398],"type":"Point"}
}