{
  "type": "Feature",
  "properties": {
    "addr:full":"605 Hudson Street New York NY 10014",
    "addr:housenumber":"605",
    "addr:postcode":"10014",
    "addr:street":"Hudson Street",
    "iso:country":"US",
    "sg:address":"605 Hudson Street",
    "sg:city":"New York",
    "sg:classifiers":[
        {
            "category":"Shopping",
            "subcategory":"Clothing, Apparel, & Fashions",
            "type":"Retail Goods"
        },
        {
            "category":"Shopping",
            "subcategory":"Gifts & Souvenirs",
            "type":"Retail Goods"
        },
        {
            "category":"Shopping",
            "subcategory":"Shoes",
            "type":"Retail Goods"
        }
    ],
    "sg:phone":"+1 212 367 8014",
    "sg:postcode":"10014",
    "sg:province":"NY",
    "sg:tags":[
        "men's",
        "flower",
        "clothing",
        "store",
        "women's"
    ],
    "wof:name":"butik",
    "wof:placetype":"venue"
},
  "geometry": {"coordinates":[-74.005898,40.7374],"type":"Point"}
}