{
  "type": "Feature",
  "properties": {
    "iso:country":"US",
    "sg:address":"82 Grant Rd",
    "sg:city":"Williamstown",
    "sg:classifiers":[
        {
            "category":"Farming",
            "subcategory":"Nursery",
            "type":"Manufacturing & Wholesale Goods"
        }
    ],
    "sg:phone":"+1 315 964 2583",
    "sg:postcode":"13493",
    "sg:province":"NY",
    "sg:tags":[
        "farm",
        "ornamental"
    ],
    "wof:name":"Schader Farms",
    "wof:placetype":"venue"
},
  "geometry": {"coordinates":[-75.888248,43.420042],"type":"Point"}
}