{
  "type": "Feature",
  "properties": {
    "addr:full":"1069 Madison Ave New York NY 10028",
    "addr:housenumber":"1069",
    "addr:postcode":"10028",
    "addr:street":"Madison Ave",
    "iso:country":"US",
    "sg:address":"1069 Madison Ave",
    "sg:city":"New York",
    "sg:classifiers":[
        {
            "category":"Personal",
            "subcategory":"Beauty Salon",
            "type":"Services"
        }
    ],
    "sg:phone":"+1 212 861 3737",
    "sg:postcode":"10028",
    "sg:province":"NY",
    "sg:tags":[
        "nail",
        "manicuring"
    ],
    "wof:name":"Liza Nail Care Salon Inc",
    "wof:placetype":"venue"
},
  "geometry": {"coordinates":[-73.961403,40.7775],"type":"Point"}
}