{
  "type": "Feature",
  "properties": {
    "addr:full":"2526 Browncroft Blvd Rochester NY 14625",
    "addr:housenumber":"2526",
    "addr:postcode":"14625",
    "addr:street":"Browncroft Blvd",
    "iso:country":"US",
    "sg:address":"2526 Browncroft Blvd",
    "sg:city":"Rochester",
    "sg:classifiers":[
        {
            "category":"Real Estate",
            "subcategory":"Real Estate Agent",
            "type":"Services"
        }
    ],
    "sg:phone":"+1 585 383 0230",
    "sg:postcode":"14625",
    "sg:province":"NY",
    "wof:name":"Philippone Realty Inc",
    "wof:placetype":"venue"
},
  "geometry": {"coordinates":[-77.50278400000001,43.15373],"type":"Point"}
}