{
  "type": "Feature",
  "properties": {
    "iso:country":"US",
    "sg:address":"67 W 23rd St",
    "sg:city":"Manhattan",
    "sg:classifiers":[
        {
            "category":"Restaurant",
            "type":"Food & Drink"
        }
    ],
    "sg:phone":"+1 212 924 2311",
    "sg:postcode":"10010",
    "sg:province":"NY",
    "sg:tags":[
        "japanese"
    ],
    "sg:website":"inakasushinyc.com",
    "wof:name":"Inaka Sushi",
    "wof:placetype":"venue"
},
  "geometry": {"coordinates":[-73.991916,40.742843],"type":"Point"}
}