{
  "type": "Feature",
  "properties": {
    "addr:full":"2079 E 16th St Brooklyn NY 11229",
    "addr:housenumber":"2079",
    "addr:postcode":"11229",
    "addr:street":"E 16Th St",
    "iso:country":"US",
    "sg:address":"2079 E 16th St",
    "sg:city":"Brooklyn",
    "sg:classifiers":[
        {
            "category":"Retail",
            "subcategory":"Auto Repair",
            "type":"Services"
        }
    ],
    "sg:phone":"+1 718 645 1900",
    "sg:postcode":"11229",
    "sg:province":"NY",
    "wof:name":"Neck Road Car Svce",
    "wof:placetype":"venue"
},
  "geometry": {"coordinates":[-73.95549800000001,40.599701],"type":"Point"}
}