{
  "type": "Feature",
  "properties": {
    "addr:full":"151 Orinoco Dr Brightwaters NY 11718",
    "addr:housenumber":"151",
    "addr:postcode":"11718",
    "addr:street":"Orinoco Dr",
    "iso:country":"US",
    "sg:address":"151 Orinoco Dr",
    "sg:city":"Brightwaters",
    "sg:classifiers":[
        {
            "category":"Retail",
            "subcategory":"Auto Repair",
            "type":"Services"
        }
    ],
    "sg:phone":"+1 631 665 4934",
    "sg:postcode":"11718",
    "sg:province":"NY",
    "sg:tags":[
        "repairing",
        "automobile"
    ],
    "wof:name":"Wally's Automotive Repr",
    "wof:placetype":"venue"
},
  "geometry": {"coordinates":[-73.26509900000001,40.720901],"type":"Point"}
}