{
  "type": "Feature",
  "properties": {
    "iso:country":"US",
    "sg:address":"140 Prospect Pl",
    "sg:city":"Brooklyn",
    "sg:classifiers":[
        {
            "category":"Professional",
            "subcategory":"Art Services",
            "type":"Services"
        }
    ],
    "sg:phone":"+1 212 219 2556",
    "sg:postcode":"11217",
    "sg:province":"NY",
    "sg:tags":[
        "photographer"
    ],
    "wof:name":"Sean Justice Photography",
    "wof:placetype":"venue"
},
  "geometry": {"coordinates":[-73.972762,40.678454],"type":"Point"}
}