{
  "type": "Feature",
  "properties": {
    "iso:country":"US",
    "sg:address":"18 Nicholas Way",
    "sg:city":"Mahopac",
    "sg:classifiers":[
        {
            "category":"Building & Trades",
            "subcategory":"Construction",
            "type":"Services"
        }
    ],
    "sg:phone":"+1 845 628 1083",
    "sg:postcode":"10541",
    "sg:province":"NY",
    "sg:tags":[
        "carpentry",
        "contractor"
    ],
    "wof:name":"Guy Demelis",
    "wof:placetype":"venue"
},
  "geometry": {"coordinates":[-73.768399,41.397856],"type":"Point"}
}