{
  "type": "Feature",
  "properties": {
    "addr:full":"2105 Mohegan Ave Bronx NY 10460",
    "addr:housenumber":"2105",
    "addr:postcode":"10460",
    "addr:street":"Mohegan Ave",
    "iso:country":"US",
    "sg:address":"2105 Mohegan Ave",
    "sg:city":"Bronx",
    "sg:classifiers":[
        {
            "category":"Wholesale",
            "subcategory":"Machinery & Supplies",
            "type":"Manufacturing & Wholesale Goods"
        }
    ],
    "sg:phone":"+1 718 295 9533",
    "sg:postcode":"10460",
    "sg:province":"NY",
    "sg:tags":[
        "baker"
    ],
    "wof:name":"Enelia's Party & Bakery Distr",
    "wof:placetype":"venue"
},
  "geometry": {"coordinates":[-73.88294399999999,40.846207],"type":"Point"}
}