{
  "type": "Feature",
  "properties": {
    "addr:full":"200 Factory Ave Syracuse NY 13208",
    "addr:housenumber":"200",
    "addr:postcode":"13208",
    "addr:street":"Factory Ave",
    "iso:country":"US",
    "sg:address":"200 Factory Ave",
    "sg:city":"Syracuse",
    "sg:classifiers":[
        {
            "category":"Wholesale",
            "subcategory":"Construction Materials",
            "type":"Manufacturing & Wholesale Goods"
        }
    ],
    "sg:phone":"+1 315 455 7406",
    "sg:postcode":"13208",
    "sg:province":"NY",
    "sg:tags":[
        "glass"
    ],
    "wof:name":"PPF Industries Inc",
    "wof:placetype":"venue"
},
  "geometry": {"coordinates":[-76.14100500000001,43.090303],"type":"Point"}
}