{
  "type": "Feature",
  "properties": {
    "addr:full":"302 W 79 St New York NY 10024",
    "addr:housenumber":"302",
    "addr:postcode":"10024",
    "addr:street":"W 79 St",
    "iso:country":"US",
    "sg:address":"302 W 79 St",
    "sg:city":"New York",
    "sg:classifiers":[
        {
            "category":"Manufacturing",
            "subcategory":"Apparel",
            "type":"Manufacturing & Wholesale Goods"
        }
    ],
    "sg:phone":"+1 212 595 0986",
    "sg:postcode":"10024",
    "sg:province":"NY",
    "sg:tags":[
        "clothing"
    ],
    "wof:name":"Cheryl Doli Brown",
    "wof:placetype":"venue"
},
  "geometry": {"coordinates":[-73.982624,40.784915],"type":"Point"}
}