{
  "type": "Feature",
  "properties": {
    "iso:country":"US",
    "sg:address":"1650 5th Ave",
    "sg:city":"Bay Shore",
    "sg:classifiers":[
        {
            "category":"Banks & Credit Unions",
            "subcategory":"Bank",
            "type":"Services"
        }
    ],
    "sg:phone":"+1 631 231 8770",
    "sg:postcode":"11706",
    "sg:province":"NY",
    "wof:name":"Bank of New York the",
    "wof:placetype":"venue"
},
  "geometry": {"coordinates":[-73.261803,40.759899],"type":"Point"}
}