{
  "type": "Feature",
  "properties": {
    "addr:full":"9604 Roosevelt Avenue Corona NY 11368",
    "addr:housenumber":"9604",
    "addr:postcode":"11368",
    "addr:street":"Roosevelt Avenue",
    "iso:country":"US",
    "sg:address":"9604 Roosevelt Avenue",
    "sg:city":"Corona",
    "sg:classifiers":[
        {
            "category":"Wholesale",
            "subcategory":"Fruits & Vegetables",
            "type":"Manufacturing & Wholesale Goods"
        }
    ],
    "sg:phone":"+1 718 429 5159",
    "sg:postcode":"11368",
    "sg:province":"NY",
    "sg:tags":[
        "veggie"
    ],
    "wof:name":"Rele Marketing",
    "wof:placetype":"venue"
},
  "geometry": {"coordinates":[-73.869131,40.749079],"type":"Point"}
}