{
  "type": "Feature",
  "properties": {
    "addr:full":"263 7th Ave Apt 4D Brooklyn NY 11215",
    "addr:housenumber":"263",
    "addr:postcode":"11215",
    "addr:street":"7Th Ave Apt 4D",
    "iso:country":"US",
    "sg:address":"263 7th Ave Apt 4D",
    "sg:city":"Brooklyn",
    "sg:classifiers":[
        {
            "category":"Health Services",
            "subcategory":"Doctor",
            "type":"Services"
        }
    ],
    "sg:phone":"+1 718 369 8190",
    "sg:postcode":"11215",
    "sg:province":"NY",
    "wof:name":"Chan Terence MD",
    "wof:placetype":"venue"
},
  "geometry": {"coordinates":[-73.97989699999999,40.6688],"type":"Point"}
}