{
  "type": "Feature",
  "properties": {
    "addr:full":"12 E Park Ave Long Beach NY 11561",
    "addr:housenumber":"12",
    "addr:postcode":"11561",
    "addr:street":"E Park Ave",
    "iso:country":"US",
    "sg:address":"12 E Park Ave",
    "sg:city":"Long Beach",
    "sg:classifiers":[
        {
            "category":"Personal",
            "subcategory":"Beauty Salon",
            "type":"Services"
        }
    ],
    "sg:phone":"+1 516 889 7098",
    "sg:postcode":"11561",
    "sg:province":"NY",
    "sg:tags":[
        "nail",
        "shop"
    ],
    "wof:name":"Best Nails",
    "wof:placetype":"venue"
},
  "geometry": {"coordinates":[-73.663696,40.588299],"type":"Point"}
}