{
  "type": "Feature",
  "properties": {
    "addr:full":"2086 Flatbush Ave Brooklyn NY 11234",
    "addr:housenumber":"2086",
    "addr:postcode":"11234",
    "addr:street":"Flatbush Ave",
    "iso:country":"US",
    "sg:address":"2086 Flatbush Ave",
    "sg:city":"Brooklyn",
    "sg:classifiers":[
        {
            "category":"Personal",
            "subcategory":"Nail Salon",
            "type":"Services"
        }
    ],
    "sg:phone":"+1 718 692 1988",
    "sg:postcode":"11234",
    "sg:province":"NY",
    "wof:name":"N Y Fashion Nail Incorporated",
    "wof:placetype":"venue"
},
  "geometry": {"coordinates":[-73.93316299999999,40.619018],"type":"Point"}
}