{
  "type": "Feature",
  "properties": {
    "iso:country":"US",
    "sg:address":"31 N Farragut Rd",
    "sg:city":"Montauk",
    "sg:classifiers":[
        {
            "category":"Restaurant",
            "type":"Food & Drink"
        }
    ],
    "sg:phone":"+1 631 668 9354",
    "sg:postcode":"11954",
    "sg:province":"NY",
    "wof:name":"Montauk Harbor Restaurant",
    "wof:placetype":"venue"
},
  "geometry": {"coordinates":[-71.943741,41.061067],"type":"Point"}
}