{
  "type": "Feature",
  "properties": {
    "iso:country":"US",
    "sg:address":"134 W High Ter",
    "sg:city":"Rochester",
    "sg:classifiers":[
        {
            "category":"Wholesale",
            "subcategory":"Farm Supplies",
            "type":"Manufacturing & Wholesale Goods"
        },
        {
            "category":"Shopping",
            "subcategory":"Pets & Pet Supplies",
            "type":"Retail Goods"
        }
    ],
    "sg:phone":"+1 585 235 0927",
    "sg:postcode":"14619",
    "sg:province":"NY",
    "sg:tags":[
        "feed",
        "grain"
    ],
    "wof:name":"Anita Barley",
    "wof:placetype":"venue"
},
  "geometry": {"coordinates":[-77.639962,43.135738],"type":"Point"}
}