{
  "type": "Feature",
  "properties": {
    "iso:country":"US",
    "sg:address":"521 Main St",
    "sg:city":"Medina",
    "sg:classifiers":[
        {
            "category":"Personal",
            "subcategory":"Beauty Salon",
            "type":"Services"
        }
    ],
    "sg:phone":"+1 585 798 4810",
    "sg:postcode":"14103",
    "sg:province":"NY",
    "wof:name":"Vision 2000",
    "wof:placetype":"venue"
},
  "geometry": {"coordinates":[-78.386819,43.219359],"type":"Point"}
}