{
  "type": "Feature",
  "properties": {
    "addr:full":"45 E 89 St New York NY 10128",
    "addr:housenumber":"45;89",
    "addr:postcode":"10128",
    "addr:street":"E;St",
    "iso:country":"US",
    "sg:address":"45 E 89 St",
    "sg:city":"New York",
    "sg:classifiers":[
        {
            "category":"Organizations",
            "subcategory":"Religious Organization",
            "type":"Services"
        }
    ],
    "sg:phone":"+1 212 427 9279",
    "sg:postcode":"10128",
    "sg:province":"NY",
    "sg:tags":[
        "clergy"
    ],
    "wof:name":"Frances Mercer",
    "wof:placetype":"venue"
},
  "geometry": {"coordinates":[-73.955879,40.782243],"type":"Point"}
}