{
  "type": "Feature",
  "properties": {
    "addr:full":"Shubert Theatre 225 W 44th St Manhattan NY 10019",
    "addr:housenumber":"225",
    "addr:postcode":"10019",
    "addr:street":"W 44Th St",
    "iso:country":"US",
    "sg:address":"Shubert Theatre 225 W 44th St",
    "sg:city":"Manhattan",
    "sg:classifiers":[
        {
            "category":"Arts & Performance",
            "subcategory":"Arts Center",
            "type":"Entertainment"
        }
    ],
    "sg:phone":"+1 212 239 6200",
    "sg:postcode":"10019",
    "sg:province":"NY",
    "sg:tags":[
        "performing"
    ],
    "sg:website":"www.memphisthemusical.com",
    "wof:name":"MEMPHIS: \u00a0A New Musical",
    "wof:placetype":"venue"
},
  "geometry": {"coordinates":[-73.98748399999999,40.757973],"type":"Point"}
}