{
  "type": "Feature",
  "properties": {
    "addr:full":"8000 Cooper Ave New York NY 11385",
    "addr:housenumber":"8000",
    "addr:postcode":"11385",
    "addr:street":"Cooper Ave",
    "iso:country":"US",
    "sg:address":"8000 Cooper Ave",
    "sg:city":"New York",
    "sg:classifiers":[
        {
            "category":"Juice Bar",
            "subcategory":"None",
            "type":"Food & Drink"
        }
    ],
    "sg:phone":"+1 718 894 3020",
    "sg:postcode":"11385",
    "sg:province":"NY",
    "sg:tags":[
        "smoothy"
    ],
    "sg:website":"www.mixstirs.com",
    "wof:name":"MixStirs",
    "wof:placetype":"venue"
},
  "geometry": {"coordinates":[-73.870147,40.709223],"type":"Point"}
}