{
  "type": "Feature",
  "properties": {
    "addr:full":"774 E 161st Street Bronx NY 10456",
    "addr:housenumber":"774",
    "addr:postcode":"10456",
    "addr:street":"E 161St Street",
    "iso:country":"US",
    "sg:address":"774 E 161st Street",
    "sg:city":"Bronx",
    "sg:classifiers":[
        {
            "category":"Food & Beverages",
            "subcategory":"Groceries & Convenience Stores",
            "type":"Retail Goods"
        }
    ],
    "sg:phone":"+1 718 993 0833",
    "sg:postcode":"10456",
    "sg:province":"NY",
    "wof:name":"Jose's Discount",
    "wof:placetype":"venue"
},
  "geometry": {"coordinates":[-73.903947,40.821025],"type":"Point"}
}