{
  "type": "Feature",
  "properties": {
    "iso:country":"US",
    "sg:address":"589 5th Ave Rm 1003",
    "sg:city":"New York",
    "sg:classifiers":[
        {
            "category":"Shopping",
            "subcategory":"Jewelry",
            "type":"Retail Goods"
        }
    ],
    "sg:phone":"+1 212 644 3838",
    "sg:postcode":"10017",
    "sg:province":"NY",
    "wof:name":"J W Blue Group Ltd",
    "wof:placetype":"venue"
},
  "geometry": {"coordinates":[-73.978188,40.756899],"type":"Point"}
}