{
  "type": "Feature",
  "properties": {
    "iso:country":"US",
    "sg:address":"876 Bryant Ave",
    "sg:city":"New Hyde Park",
    "sg:classifiers":[
        {
            "category":"Food & Beverages",
            "subcategory":"Liquor & Beverages",
            "type":"Retail Goods"
        }
    ],
    "sg:phone":"+1   ",
    "sg:postcode":"11040",
    "sg:province":"NY",
    "sg:tags":[
        "alcoholic"
    ],
    "wof:name":"BT Liquors Inc",
    "wof:placetype":"venue"
},
  "geometry": {"coordinates":[-73.686562,40.738885],"type":"Point"}
}