{
  "type": "Feature",
  "properties": {
    "iso:country":"US",
    "sg:address":"21 W Main St",
    "sg:city":"Friendship",
    "sg:classifiers":[
        {
            "category":"Place Of Worship",
            "subcategory":"Church",
            "type":"Public Place"
        },
        {
            "category":"Place Of Worship",
            "type":"Public Place"
        }
    ],
    "sg:phone":"+1 585 973 3721",
    "sg:postcode":"14739",
    "sg:province":"NY",
    "sg:tags":[
        "churches-methodist"
    ],
    "wof:name":"1st United Methodist Church Of Friendship",
    "wof:placetype":"venue"
},
  "geometry": {"coordinates":[-78.134552,42.20763],"type":"Point"}
}