{
  "type": "Feature",
  "properties": {
    "iso:country":"US",
    "sg:address":"101 Fuller Ave",
    "sg:city":"Islip",
    "sg:classifiers":[
        {
            "category":"Restaurant",
            "type":"Food & Drink"
        }
    ],
    "sg:phone":"+1   ",
    "sg:postcode":"11751",
    "sg:province":"NY",
    "sg:tags":[
        "eating"
    ],
    "wof:name":"Joed Catering",
    "wof:placetype":"venue"
},
  "geometry": {"coordinates":[-73.21847,40.738955],"type":"Point"}
}