{
  "type": "Feature",
  "properties": {
    "iso:country":"US",
    "sg:address":"225 Railroad Ave",
    "sg:city":"Bedford Hills",
    "sg:classifiers":[
        {
            "category":"Freight",
            "type":"Transportation"
        }
    ],
    "sg:phone":"+1 914 241 8123",
    "sg:postcode":"10507",
    "sg:province":"NY",
    "sg:tags":[
        "trucking"
    ],
    "wof:name":"ARJR Trucking",
    "wof:placetype":"venue"
},
  "geometry": {"coordinates":[-73.686098,41.244302],"type":"Point"}
}