{
  "type": "Feature",
  "properties": {
    "addr:full":"94 Williams Ave Amityville NY 11701",
    "addr:housenumber":"94",
    "addr:postcode":"11701",
    "addr:street":"Williams Ave",
    "iso:country":"US",
    "sg:address":"94 Williams Ave",
    "sg:city":"Amityville",
    "sg:classifiers":[
        {
            "category":"Professional",
            "subcategory":"Computer Services",
            "type":"Services"
        }
    ],
    "sg:phone":"+1 631 789 8795",
    "sg:postcode":"11701",
    "sg:province":"NY",
    "wof:name":"Angel's Products",
    "wof:placetype":"venue"
},
  "geometry": {"coordinates":[-73.420543,40.699605],"type":"Point"}
}