{
  "type": "Feature",
  "properties": {
    "iso:country":"US",
    "sg:address":"788 Union St",
    "sg:city":"Brooklyn",
    "sg:classifiers":[
        {
            "category":"Restaurant",
            "type":"Food & Drink"
        }
    ],
    "sg:phone":"+1 718 399 9876",
    "sg:postcode":"11215",
    "sg:province":"NY",
    "wof:name":"Gingko Leaf",
    "wof:placetype":"venue"
},
  "geometry": {"coordinates":[-73.976692,40.675012],"type":"Point"}
}