{
  "type": "Feature",
  "properties": {
    "addr:full":"1000 South Ave Rochester NY 14620",
    "addr:housenumber":"1000",
    "addr:postcode":"14620",
    "addr:street":"South Ave",
    "iso:country":"US",
    "sg:address":"1000 South Ave",
    "sg:city":"Rochester",
    "sg:classifiers":[
        {
            "category":"Health Services",
            "subcategory":"Doctor",
            "type":"Services"
        }
    ],
    "sg:phone":"+1 585 244 0300",
    "sg:postcode":"14620",
    "sg:province":"NY",
    "sg:tags":[
        "physician",
        "surgeon"
    ],
    "wof:name":"Regional Kidney Svc Ctr",
    "wof:placetype":"venue"
},
  "geometry": {"coordinates":[-77.60732,43.136325],"type":"Point"}
}