{
  "type": "Feature",
  "properties": {
    "iso:country":"US",
    "sg:address":"107 Prospect St",
    "sg:city":"Attica",
    "sg:classifiers":[
        {
            "category":"Health Services",
            "subcategory":"Doctor",
            "type":"Services"
        }
    ],
    "sg:phone":"+1 585 591 6000",
    "sg:postcode":"14011",
    "sg:province":"NY",
    "sg:tags":[
        "physician",
        "surgeon"
    ],
    "wof:name":"Attica Family Care Ctr",
    "wof:placetype":"venue"
},
  "geometry": {"coordinates":[-78.277838,42.868718],"type":"Point"}
}