{
  "type": "Feature",
  "properties": {
    "addr:full":"40 Central Park S Manhattan NY 10019",
    "addr:housenumber":"40",
    "addr:postcode":"10019",
    "addr:street":"Central Park S",
    "iso:country":"US",
    "sg:address":"40 Central Park S",
    "sg:city":"Manhattan",
    "sg:classifiers":[
        {
            "category":"Food & Beverages",
            "subcategory":"Candy",
            "type":"Retail Goods"
        },
        {
            "category":"Food & Beverages",
            "subcategory":"Chocolate",
            "type":"Retail Goods"
        }
    ],
    "sg:phone":"+1 212 644 3737",
    "sg:postcode":"10019",
    "sg:province":"NY",
    "sg:tags":[
        "shop",
        "dessert",
        "chocolatiers"
    ],
    "sg:website":"www.chocolatecoveredeverything.com",
    "wof:name":"Chocolate Covered Everything",
    "wof:placetype":"venue"
},
  "geometry": {"coordinates":[-73.97488199999999,40.764915],"type":"Point"}
}