{
  "type": "Feature",
  "properties": {
    "addr:full":"107 University Pl New York NY 10003",
    "addr:housenumber":"107",
    "addr:postcode":"10003",
    "addr:street":"University Pl",
    "iso:country":"US",
    "sg:address":"107 University Pl",
    "sg:city":"New York",
    "sg:classifiers":[
        {
            "category":"Restaurant",
            "type":"Food & Drink"
        }
    ],
    "sg:phone":"+1   ",
    "sg:postcode":"10003",
    "sg:province":"NY",
    "sg:tags":[
        "eating"
    ],
    "wof:name":"News Cafe",
    "wof:placetype":"venue"
},
  "geometry": {"coordinates":[-73.992374,40.73423],"type":"Point"}
}