{
  "type": "Feature",
  "properties": {
    "addr:full":"80 Bowery New York NY 10013",
    "addr:housenumber":"80",
    "addr:postcode":"10013",
    "addr:street":"Bowery",
    "iso:country":"US",
    "sg:address":"80 Bowery",
    "sg:city":"New York",
    "sg:classifiers":[
        {
            "category":"Banks & Credit Unions",
            "subcategory":"Investment Brokerage",
            "type":"Services"
        }
    ],
    "sg:phone":"+1 212 219 8018",
    "sg:postcode":"10013",
    "sg:province":"NY",
    "sg:tags":[
        "stock",
        "bond"
    ],
    "wof:name":"Cen Tek Trading Inc",
    "wof:placetype":"venue"
},
  "geometry": {"coordinates":[-73.99583800000001,40.71656],"type":"Point"}
}