{
  "type": "Feature",
  "properties": {
    "addr:full":"15 Orchard Park Sodus NY 14551",
    "addr:housenumber":"15",
    "addr:postcode":"14551",
    "addr:street":"Orchard Park",
    "iso:country":"US",
    "sg:address":"15 Orchard Park",
    "sg:city":"Sodus",
    "sg:classifiers":[
        {
            "category":"Wholesale",
            "subcategory":"Farm Supplies",
            "type":"Manufacturing & Wholesale Goods"
        }
    ],
    "sg:phone":"+1 315 483 2228",
    "sg:postcode":"14551",
    "sg:province":"NY",
    "sg:tags":[
        "fertilizer"
    ],
    "wof:name":"GVM Inc",
    "wof:placetype":"venue"
},
  "geometry": {"coordinates":[-77.071709,43.237763],"type":"Point"}
}