{
  "type": "Feature",
  "properties": {
    "iso:country":"US",
    "sg:address":"60 Cromwell Avenue",
    "sg:city":"Staten Island",
    "sg:classifiers":[
        {
            "category":"Health Services",
            "subcategory":"Dentist",
            "type":"Services"
        }
    ],
    "sg:phone":"+1 718 987 2320",
    "sg:postcode":"10304",
    "sg:province":"NY",
    "sg:tags":[
        "orthodontist"
    ],
    "wof:name":"Sirianni Epstein M DDS",
    "wof:placetype":"venue"
},
  "geometry": {"coordinates":[-74.09929099999999,40.591712],"type":"Point"}
}