{
  "type": "Feature",
  "properties": {
    "addr:full":"2485 2 Ave New York NY 10035",
    "addr:postcode":"2485;10035",
    "addr:street":"2 Ave",
    "iso:country":"US",
    "sg:address":"2485 2 Ave",
    "sg:city":"New York",
    "sg:classifiers":[
        {
            "category":"Retail",
            "subcategory":"Auto Repair",
            "type":"Services"
        }
    ],
    "sg:phone":"+1 646 307 4483",
    "sg:postcode":"10035",
    "sg:province":"NY",
    "sg:tags":[
        "wrecker"
    ],
    "wof:name":"Advance Auto Tow NYC",
    "wof:placetype":"venue"
},
  "geometry": {"coordinates":[-73.93728,40.797678],"type":"Point"}
}