{
  "type": "Feature",
  "properties": {
    "iso:country":"US",
    "sg:address":"34 Main St",
    "sg:city":"East Hampton",
    "sg:classifiers":[
        {
            "category":"Shopping",
            "subcategory":"Music",
            "type":"Retail Goods"
        }
    ],
    "sg:phone":"+1 631 324 2660",
    "sg:postcode":"11937",
    "sg:province":"NY",
    "sg:tags":[
        "compact",
        "record",
        "disc",
        "tape"
    ],
    "wof:name":"Long Island Sound Records",
    "wof:placetype":"venue"
},
  "geometry": {"coordinates":[-72.185506,40.96321],"type":"Point"}
}