{
  "type": "Feature",
  "properties": {
    "addr:full":"415 Bedford Rd Armonk NY 10504",
    "addr:housenumber":"415",
    "addr:postcode":"10504",
    "addr:street":"Bedford Rd",
    "iso:country":"US",
    "sg:address":"415 Bedford Rd",
    "sg:city":"Armonk",
    "sg:classifiers":[
        {
            "category":"Wholesale",
            "subcategory":"Hardware",
            "type":"Manufacturing & Wholesale Goods"
        }
    ],
    "sg:phone":"+1 914 273 3076",
    "sg:postcode":"10504",
    "sg:province":"NY",
    "sg:tags":[
        "plumbing",
        "fixture",
        "supply"
    ],
    "sg:website":"www.kentsupply.com",
    "wof:name":"Kent Supply Co",
    "wof:placetype":"venue"
},
  "geometry": {"coordinates":[-73.69636199999999,41.125423],"type":"Point"}
}