{
  "type": "Feature",
  "properties": {
    "iso:country":"US",
    "sg:address":"1722 Coney Island Ave",
    "sg:city":"Brooklyn",
    "sg:classifiers":[
        {
            "category":"Retail",
            "subcategory":"Laundry & Dry Cleaning",
            "type":"Services"
        }
    ],
    "sg:phone":"+1 718 336 0175",
    "sg:postcode":"11230",
    "sg:province":"NY",
    "sg:tags":[
        "cleaners"
    ],
    "wof:name":"Elite Cleaners",
    "wof:placetype":"venue"
},
  "geometry": {"coordinates":[-73.963559,40.616031],"type":"Point"}
}