{
  "type": "Feature",
  "properties": {
    "addr:full":"221 S Fulton Ave Mount Vernon NY 10550",
    "addr:housenumber":"221",
    "addr:postcode":"10550",
    "addr:street":"S Fulton Ave",
    "iso:country":"US",
    "sg:address":"221 S Fulton Ave",
    "sg:city":"Mount Vernon",
    "sg:classifiers":[
        {
            "category":"Autos & Motor Vehicles",
            "subcategory":"Fuel & Gas Station",
            "type":"Retail Goods"
        },
        {
            "category":"Retail",
            "subcategory":"Auto Repair",
            "type":"Services"
        }
    ],
    "sg:phone":"+1 914 664 5008",
    "sg:postcode":"10550",
    "sg:province":"NY",
    "sg:tags":[
        "shop",
        "garage",
        "oil"
    ],
    "wof:name":"James Harris Transportation",
    "wof:placetype":"venue"
},
  "geometry": {"coordinates":[-73.82829099999999,40.908906],"type":"Point"}
}