{
  "type": "Feature",
  "properties": {
    "iso:country":"US",
    "sg:address":"18 Cayuga Cir",
    "sg:city":"Mayville",
    "sg:classifiers":[
        {
            "category":"Organizations",
            "subcategory":"Religious Organization",
            "type":"Services"
        }
    ],
    "sg:phone":"+1 716 753 7497",
    "sg:postcode":"14757",
    "sg:province":"NY",
    "sg:tags":[
        "clergy"
    ],
    "wof:name":"Thomas E Chambers",
    "wof:placetype":"venue"
},
  "geometry": {"coordinates":[-79.464097,42.246134],"type":"Point"}
}