{
  "type": "Feature",
  "properties": {
    "addr:full":"80 Pine St Manhattan NY 10005",
    "addr:housenumber":"80",
    "addr:postcode":"10005",
    "addr:street":"Pine St",
    "iso:country":"US",
    "sg:address":"80 Pine St",
    "sg:city":"Manhattan",
    "sg:classifiers":[
        {
            "category":"Coffee & Tea",
            "type":"Food & Drink"
        }
    ],
    "sg:phone":"+1 212 480 3970",
    "sg:postcode":"10005",
    "sg:province":"NY",
    "wof:name":"Starbucks",
    "wof:placetype":"venue"
},
  "geometry": {"coordinates":[-74.00727500000001,40.7061],"type":"Point"}
}