{
  "type": "Feature",
  "properties": {
    "addr:full":"207 Hallock Rd Stony Brook NY 11790",
    "addr:housenumber":"207",
    "addr:postcode":"11790",
    "addr:street":"Hallock Rd",
    "iso:country":"US",
    "sg:address":"207 Hallock Rd",
    "sg:city":"Stony Brook",
    "sg:classifiers":[
        {
            "category":"Health Services",
            "subcategory":"Doctor",
            "type":"Services"
        }
    ],
    "sg:phone":"+1 631 689 2300",
    "sg:postcode":"11790",
    "sg:province":"NY",
    "sg:tags":[
        "podiatrist"
    ],
    "wof:name":"Smith Peter PC",
    "wof:placetype":"venue"
},
  "geometry": {"coordinates":[-73.124397,40.885601],"type":"Point"}
}