{
  "type": "Feature",
  "properties": {
    "iso:country":"US",
    "sg:address":"61 Exchange St",
    "sg:city":"Albany",
    "sg:classifiers":[
        {
            "category":"Retail",
            "subcategory":"Laundry & Dry Cleaning",
            "type":"Services"
        }
    ],
    "sg:phone":"+1   ",
    "sg:postcode":"12205",
    "sg:province":"NY",
    "sg:tags":[
        "drycleaning",
        "plant"
    ],
    "wof:name":"Exchange Dry Cleaners",
    "wof:placetype":"venue"
},
  "geometry": {"coordinates":[-73.78474900000001,42.685939],"type":"Point"}
}