{
  "type": "Feature",
  "properties": {
    "iso:country":"US",
    "sg:address":"241 W 97th St",
    "sg:city":"New York",
    "sg:classifiers":[
        {
            "category":"Professional",
            "subcategory":"Management & Consulting",
            "type":"Services"
        }
    ],
    "sg:phone":"+1 212 865 4555",
    "sg:postcode":"10025",
    "sg:province":"NY",
    "sg:tags":[
        "business"
    ],
    "wof:name":"Global Finance Library",
    "wof:placetype":"venue"
},
  "geometry": {"coordinates":[-73.972717,40.795929],"type":"Point"}
}