{
  "type": "Feature",
  "properties": {
    "iso:country":"US",
    "sg:address":"5888 Main St",
    "sg:city":"Buffalo",
    "sg:classifiers":[
        {
            "category":"Professional",
            "subcategory":"Lawyer & Legal Services",
            "type":"Services"
        }
    ],
    "sg:phone":"+1   ",
    "sg:postcode":"14221",
    "sg:province":"NY",
    "wof:name":"Victoria L DAngelo",
    "wof:placetype":"venue"
},
  "geometry": {"coordinates":[-78.73460799999999,42.964509],"type":"Point"}
}