{
  "type": "Feature",
  "properties": {
    "addr:full":"3875 Long Beach Rd Island Park NY 11558",
    "addr:housenumber":"3875",
    "addr:postcode":"11558",
    "addr:street":"Long Beach Rd",
    "iso:country":"US",
    "sg:address":"3875 Long Beach Rd",
    "sg:city":"Island Park",
    "sg:classifiers":[
        {
            "category":"Autos & Motor Vehicles",
            "subcategory":"Boat Sales",
            "type":"Retail Goods"
        }
    ],
    "sg:phone":"+1 516 431 1865",
    "sg:postcode":"11558",
    "sg:province":"NY",
    "sg:tags":[
        "dealer",
        "sales"
    ],
    "wof:name":"K & K Outboard",
    "wof:placetype":"venue"
},
  "geometry": {"coordinates":[-73.64305299999999,40.615779],"type":"Point"}
}