{
  "type": "Feature",
  "properties": {
    "addr:full":"357 E 204th St Bronx NY 10467",
    "addr:housenumber":"357",
    "addr:postcode":"10467",
    "addr:street":"E 204Th St",
    "iso:country":"US",
    "sg:address":"357 E 204th St",
    "sg:city":"Bronx",
    "sg:classifiers":[
        {
            "category":"Bars & Pubs",
            "type":"Food & Drink"
        }
    ],
    "sg:phone":"+1 718 655 6726",
    "sg:postcode":"10467",
    "sg:province":"NY",
    "wof:name":"Mcmahon's Bar",
    "wof:placetype":"venue"
},
  "geometry": {"coordinates":[-73.877833,40.87245],"type":"Point"}
}