{
  "type": "Feature",
  "properties": {
    "addr:full":"4695 Lake Ave Rochester NY 14612",
    "addr:housenumber":"4695",
    "addr:postcode":"14612",
    "addr:street":"Lake Ave",
    "iso:country":"US",
    "sg:address":"4695 Lake Ave",
    "sg:city":"Rochester",
    "sg:classifiers":[
        {
            "category":"Bars & Pubs",
            "type":"Food & Drink"
        }
    ],
    "sg:phone":"+1 585 663 9691",
    "sg:postcode":"14612",
    "sg:province":"NY",
    "wof:name":"Windjammers",
    "wof:placetype":"venue"
},
  "geometry": {"coordinates":[-77.610118,43.256249],"type":"Point"}
}