{
  "type": "Feature",
  "properties": {
    "iso:country":"US",
    "sg:address":"351 Jay St",
    "sg:city":"Brooklyn",
    "sg:classifiers":[
        {
            "category":"Shopping",
            "type":"Retail Goods"
        },
        {
            "category":"Wholesale",
            "subcategory":"Durable Goods & Equipment",
            "type":"Manufacturing & Wholesale Goods"
        }
    ],
    "sg:phone":"+1 718 855 8078",
    "sg:postcode":"11201",
    "sg:province":"NY",
    "sg:tags":[
        "room",
        "supply",
        "material",
        "drafting",
        "craft",
        "hobby"
    ],
    "wof:name":"W C Art & Drafting Supply Co",
    "wof:placetype":"venue"
},
  "geometry": {"coordinates":[-73.987154,40.69354],"type":"Point"}
}