{
  "type": "Feature",
  "properties": {
    "iso:country":"US",
    "sg:address":"218 Applegate Rd S",
    "sg:city":"Ithaca",
    "sg:classifiers":[
        {
            "category":"Sports & Exercise",
            "subcategory":"Golf",
            "type":"Entertainment"
        }
    ],
    "sg:phone":"+1 607 273 2363",
    "sg:postcode":"14850",
    "sg:province":"NY",
    "sg:tags":[
        "course"
    ],
    "sg:website":"www.hillendale.com",
    "wof:name":"Hillendale Golf Course",
    "wof:placetype":"venue"
},
  "geometry": {"coordinates":[-76.610598,42.43542],"type":"Point"}
}