{
  "type": "Feature",
  "properties": {
    "iso:country":"US",
    "sg:address":"3565 Crompond Rd",
    "sg:city":"Cortlandt Manor",
    "sg:classifiers":[
        {
            "category":"Restaurant",
            "type":"Food & Drink"
        }
    ],
    "sg:phone":"+1   ",
    "sg:postcode":"10567",
    "sg:province":"NY",
    "sg:tags":[
        "eating"
    ],
    "wof:name":"Little Srrento Itln Rest Pizza",
    "wof:placetype":"venue"
},
  "geometry": {"coordinates":[-73.85926600000001,41.292704],"type":"Point"}
}