{
  "type": "Feature",
  "properties": {
    "iso:country":"US",
    "sg:address":"140 Jay St",
    "sg:city":"Schenectady",
    "sg:classifiers":[
        {
            "category":"Retail",
            "subcategory":"Photofinishing",
            "type":"Services"
        }
    ],
    "sg:phone":"+1 518 370 8083",
    "sg:postcode":"12305",
    "sg:province":"NY",
    "sg:tags":[
        "photo",
        "restoration",
        "retouching"
    ],
    "wof:name":"Jay Street Photo",
    "wof:placetype":"venue"
},
  "geometry": {"coordinates":[-73.94038500000001,42.813523],"type":"Point"}
}