{
  "type": "Feature",
  "properties": {
    "iso:country":"US",
    "sg:address":"12 Roberts St",
    "sg:city":"Middletown",
    "sg:classifiers":[
        {
            "category":"Professional",
            "subcategory":"Lawyer & Legal Services",
            "type":"Services"
        }
    ],
    "sg:phone":"+1   ",
    "sg:postcode":"10940",
    "sg:province":"NY",
    "wof:name":"Robert P Augello",
    "wof:placetype":"venue"
},
  "geometry": {"coordinates":[-74.41895599999999,41.447475],"type":"Point"}
}