{
  "type": "Feature",
  "properties": {
    "addr:full":"365 Jay St Brooklyn NY 11201",
    "addr:housenumber":"365",
    "addr:postcode":"11201",
    "addr:street":"Jay St",
    "iso:country":"US",
    "sg:address":"365 Jay St",
    "sg:city":"Brooklyn",
    "sg:classifiers":[
        {
            "category":"Manufacturing",
            "subcategory":"Printing",
            "type":"Manufacturing & Wholesale Goods"
        }
    ],
    "sg:phone":"+1   ",
    "sg:postcode":"11201",
    "sg:province":"NY",
    "sg:tags":[
        "lithographic",
        "commercial"
    ],
    "wof:name":"Edward Press Corp",
    "wof:placetype":"venue"
},
  "geometry": {"coordinates":[-73.987216,40.692429],"type":"Point"}
}