{
  "type": "Feature",
  "properties": {
    "iso:country":"US",
    "sg:address":"103 Morningside Ave",
    "sg:city":"New York",
    "sg:classifiers":[
        {
            "category":"Organizations",
            "subcategory":"Religious Organization",
            "type":"Services"
        }
    ],
    "sg:phone":"+1 212 222 2296",
    "sg:postcode":"10027",
    "sg:province":"NY",
    "sg:tags":[
        "church"
    ],
    "wof:name":"St Lukes Baptist Church",
    "wof:placetype":"venue"
},
  "geometry": {"coordinates":[-73.954489,40.810573],"type":"Point"}
}