{
  "type": "Feature",
  "properties": {
    "iso:country":"US",
    "sg:address":"2620 124th Street",
    "sg:city":"Flushing",
    "sg:classifiers":[
        {
            "category":"Shopping",
            "subcategory":"Shoes",
            "type":"Retail Goods"
        }
    ],
    "sg:phone":"+1 718 321 1181",
    "sg:postcode":"11354",
    "sg:province":"NY",
    "sg:tags":[
        "store"
    ],
    "wof:name":"Land Mark Footwear",
    "wof:placetype":"venue"
},
  "geometry": {"coordinates":[-73.844537,40.774008],"type":"Point"}
}