{
  "type": "Feature",
  "properties": {
    "addr:full":"152 York St Auburn NY 13021",
    "addr:housenumber":"152",
    "addr:postcode":"13021",
    "addr:street":"York St",
    "iso:country":"US",
    "sg:address":"152 York St",
    "sg:city":"Auburn",
    "sg:classifiers":[
        {
            "category":"Retail",
            "subcategory":"Auto Rental",
            "type":"Services"
        }
    ],
    "sg:phone":"+1 315 252 7164",
    "sg:postcode":"13021",
    "sg:province":"NY",
    "sg:tags":[
        "renting",
        "truck",
        "leasing"
    ],
    "wof:name":"Penske Truck Rental",
    "wof:placetype":"venue"
},
  "geometry": {"coordinates":[-76.58216299999999,42.950895],"type":"Point"}
}