{
  "type": "Feature",
  "properties": {
    "addr:full":"729 Arbuckle Ave Woodmere NY 11598",
    "addr:housenumber":"729",
    "addr:postcode":"11598",
    "addr:street":"Arbuckle Ave",
    "iso:country":"US",
    "sg:address":"729 Arbuckle Ave",
    "sg:city":"Woodmere",
    "sg:classifiers":[
        {
            "category":"Organizations",
            "subcategory":"Membership Organization",
            "type":"Services"
        }
    ],
    "sg:phone":"+1   ",
    "sg:postcode":"11598",
    "sg:province":"NY",
    "wof:name":"Strauss Association",
    "wof:placetype":"venue"
},
  "geometry": {"coordinates":[-73.73014999999999,40.637205],"type":"Point"}
}