{
  "type": "Feature",
  "properties": {
    "iso:country":"US",
    "sg:address":"21 Ryder Pl",
    "sg:city":"Lynbrook",
    "sg:classifiers":[
        {
            "category":"Communications",
            "type":"Services"
        }
    ],
    "sg:phone":"+1 516 256 0707",
    "sg:postcode":"11563",
    "sg:province":"NY",
    "sg:tags":[
        "recording",
        "rehearsal",
        "studio"
    ],
    "wof:name":"Watts Music",
    "wof:placetype":"venue"
},
  "geometry": {"coordinates":[-73.673103,40.6591],"type":"Point"}
}