{
  "type": "Feature",
  "properties": {
    "iso:country":"US",
    "sg:address":"9516 New Albion Rd",
    "sg:city":"Cattaraugus",
    "sg:classifiers":[
        {
            "category":"Farming",
            "subcategory":"Dairy Farm",
            "type":"Manufacturing & Wholesale Goods"
        }
    ],
    "sg:phone":"+1 716 938 6507",
    "sg:postcode":"14719",
    "sg:province":"NY",
    "wof:name":"Gross Farms",
    "wof:placetype":"venue"
},
  "geometry": {"coordinates":[-78.864526,42.277513],"type":"Point"}
}