{
  "type": "Feature",
  "properties": {
    "iso:country":"US",
    "sg:address":"71 Beechwood Dr",
    "sg:city":"Manorville",
    "sg:classifiers":[
        {
            "category":"Transit Center",
            "subcategory":"Freight",
            "type":"Transportation"
        }
    ],
    "sg:phone":"+1 631 942 6238",
    "sg:postcode":"11949",
    "sg:province":"NY",
    "sg:tags":[
        "air",
        "cargo",
        "express",
        "package"
    ],
    "wof:name":"Dependable Ground Delivery, Corp.",
    "wof:placetype":"venue"
},
  "geometry": {"coordinates":[-72.761088,40.852036],"type":"Point"}
}