{
  "type": "Feature",
  "properties": {
    "addr:full":"60 Covert Ave Garden City NY 11530",
    "addr:housenumber":"60",
    "addr:postcode":"11530",
    "addr:street":"Covert Ave",
    "iso:country":"US",
    "sg:address":"60 Covert Ave",
    "sg:city":"Garden City",
    "sg:classifiers":[
        {
            "category":"Deli",
            "type":"Food & Drink"
        }
    ],
    "sg:phone":"+1 516 354 3238",
    "sg:postcode":"11530",
    "sg:province":"NY",
    "wof:name":"Manor Delicatessen",
    "wof:placetype":"venue"
},
  "geometry": {"coordinates":[-73.688103,40.7229],"type":"Point"}
}