{
  "type": "Feature",
  "properties": {
    "addr:full":"141 E 55th St New York NY 10022",
    "addr:housenumber":"141",
    "addr:postcode":"10022",
    "addr:street":"E 55Th St",
    "iso:country":"US",
    "sg:address":"141 E 55th St",
    "sg:city":"New York",
    "sg:classifiers":[
        {
            "category":"Health Services",
            "subcategory":"Doctor",
            "type":"Services"
        }
    ],
    "sg:phone":"+1 212 688 7508",
    "sg:postcode":"10022",
    "sg:province":"NY",
    "wof:name":"Goldstein Robert G Dr",
    "wof:placetype":"venue"
},
  "geometry": {"coordinates":[-73.969902,40.759602],"type":"Point"}
}