{
  "type": "Feature",
  "properties": {
    "addr:full":"Brooklyn Atlantic Terminal 139 Flatbush Ave Brooklyn NY 11217",
    "addr:housenumber":"139",
    "addr:postcode":"11217",
    "addr:street":"Flatbush Ave",
    "iso:country":"US",
    "sg:address":"Brooklyn Atlantic Terminal 139 Flatbush Ave",
    "sg:city":"Brooklyn",
    "sg:classifiers":[
        {
            "category":"Shopping",
            "subcategory":"Beauty & Cosmetics",
            "type":"Retail Goods"
        }
    ],
    "sg:phone":"+1 718 622 4514",
    "sg:postcode":"11217",
    "sg:province":"NY",
    "sg:tags":[
        "supply"
    ],
    "sg:website":"www.carolsdaughter.com/home.do",
    "wof:name":"Carol's Daughter",
    "wof:placetype":"venue"
},
  "geometry": {"coordinates":[-73.977721,40.684428],"type":"Point"}
}