{
  "type": "Feature",
  "properties": {
    "iso:country":"US",
    "sg:address":"1828 Schenectady Ave",
    "sg:city":"Brooklyn",
    "sg:classifiers":[
        {
            "category":"Shopping",
            "subcategory":"Books",
            "type":"Retail Goods"
        }
    ],
    "sg:phone":"+1 718 872 7118",
    "sg:postcode":"11234",
    "sg:province":"NY",
    "sg:tags":[
        "bookstore"
    ],
    "wof:name":"Ywhy Rent Books Dot Com",
    "wof:placetype":"venue"
},
  "geometry": {"coordinates":[-73.93092300000001,40.627821],"type":"Point"}
}