{
  "type": "Feature",
  "properties": {
    "iso:country":"US",
    "sg:address":"197 Clinton St",
    "sg:city":"Binghamton",
    "sg:classifiers":[
        {
            "category":"Professional",
            "subcategory":"Management & Consulting",
            "type":"Services"
        }
    ],
    "sg:phone":"+1 607 231 8854",
    "sg:postcode":"13905",
    "sg:province":"NY",
    "sg:tags":[
        "food"
    ],
    "wof:name":"Blakeslee Food Svc",
    "wof:placetype":"venue"
},
  "geometry": {"coordinates":[-75.929373,42.106382],"type":"Point"}
}