{
  "type": "Feature",
  "properties": {
    "addr:full":"37 Steele Cir Niagara Falls NY 14304",
    "addr:housenumber":"37",
    "addr:postcode":"14304",
    "addr:street":"Steele Cir",
    "iso:country":"US",
    "sg:address":"37 Steele Cir",
    "sg:city":"Niagara Falls",
    "sg:classifiers":[
        {
            "category":"Building & Trades",
            "subcategory":"Construction",
            "type":"Services"
        }
    ],
    "sg:phone":"+1 716 298 5372",
    "sg:postcode":"14304",
    "sg:province":"NY",
    "sg:tags":[
        "general",
        "contractor"
    ],
    "wof:name":"Wildwood Acres Constr",
    "wof:placetype":"venue"
},
  "geometry": {"coordinates":[-78.943714,43.13079],"type":"Point"}
}