{
  "type": "Feature",
  "properties": {
    "addr:full":"68 Morton Ave Freeport NY 11520",
    "addr:housenumber":"68",
    "addr:postcode":"11520",
    "addr:street":"Morton Ave",
    "iso:country":"US",
    "sg:address":"68 Morton Ave",
    "sg:city":"Freeport",
    "sg:classifiers":[
        {
            "category":"Building & Trades",
            "subcategory":"Landscaping Services",
            "type":"Services"
        }
    ],
    "sg:phone":"+1 516 623 9046",
    "sg:postcode":"11520",
    "sg:province":"NY",
    "sg:tags":[
        "consultant",
        "designer",
        "gardener",
        "landscape"
    ],
    "wof:name":"Moreno Manuel",
    "wof:placetype":"venue"
},
  "geometry": {"coordinates":[-73.599565,40.645393],"type":"Point"}
}