{
  "type": "Feature",
  "properties": {
    "addr:full":"77-17 Grand Avenue Maspeth NY 11378",
    "addr:housenumber":"77-17",
    "addr:postcode":"11378",
    "addr:street":"Grand Avenue",
    "iso:country":"US",
    "sg:address":"77-17 Grand Avenue",
    "sg:city":"Maspeth",
    "sg:classifiers":[
        {
            "category":"Building & Trades",
            "subcategory":"Locksmith",
            "type":"Services"
        }
    ],
    "sg:phone":"+1 718 779 8189",
    "sg:postcode":"11378",
    "sg:province":"NY",
    "sg:tags":[
        "key"
    ],
    "wof:name":"All Day Maspeth 24 Hour Emergency Locksmith",
    "wof:placetype":"venue"
},
  "geometry": {"coordinates":[-73.899303,40.723833],"type":"Point"}
}