{
  "type": "Feature",
  "properties": {
    "addr:full":"1867 State Hwy 55 Lagrangeville NY 12540",
    "addr:housenumber":"1867",
    "addr:postcode":"12540",
    "addr:street":"State Hwy 55",
    "iso:country":"US",
    "sg:address":"1867 State Hwy 55",
    "sg:city":"Lagrangeville",
    "sg:classifiers":[
        {
            "category":"Wholesale",
            "subcategory":"Machinery & Supplies",
            "type":"Manufacturing & Wholesale Goods"
        },
        {
            "category":"Building & Trades",
            "subcategory":"Landscaping Services",
            "type":"Services"
        }
    ],
    "sg:phone":"+1 845 227 2447",
    "sg:postcode":"12540",
    "sg:province":"NY",
    "sg:tags":[
        "material",
        "landscape",
        "contractor"
    ],
    "wof:name":"Lagrange Supply Inc",
    "wof:placetype":"venue"
},
  "geometry": {"coordinates":[-73.736107,41.658788],"type":"Point"}
}