{
  "type": "Feature",
  "properties": {
    "addr:full":"415 Main St Port Washington NY 11050",
    "addr:housenumber":"415",
    "addr:postcode":"11050",
    "addr:street":"Main St",
    "iso:country":"US",
    "sg:address":"415 Main St",
    "sg:city":"Port Washington",
    "sg:classifiers":[
        {
            "category":"Restaurant",
            "type":"Food & Drink"
        }
    ],
    "sg:menulink":"http://www.allmenus.com/ny/port-washington/25999-main-415/menu/",
    "sg:phone":"+1 516 767 6246",
    "sg:postcode":"11050",
    "sg:province":"NY",
    "sg:tags":[
        "american"
    ],
    "wof:name":"Main 415",
    "wof:placetype":"venue"
},
  "geometry": {"coordinates":[-73.701916,40.828911],"type":"Point"}
}