{
  "type": "Feature",
  "properties": {
    "addr:full":"242 Harwich St Kingston NY 12401",
    "addr:housenumber":"242",
    "addr:postcode":"12401",
    "addr:street":"Harwich St",
    "iso:country":"US",
    "sg:address":"242 Harwich St",
    "sg:city":"Kingston",
    "sg:classifiers":[
        {
            "category":"Professional",
            "type":"Services"
        }
    ],
    "sg:phone":"+1   ",
    "sg:postcode":"12401",
    "sg:province":"NY",
    "wof:name":"Arlantico Salzmann Inc",
    "wof:placetype":"venue"
},
  "geometry": {"coordinates":[-74.003388,41.948457],"type":"Point"}
}