{
  "type": "Feature",
  "properties": {
    "iso:country":"US",
    "sg:address":"6891 Townline Rd",
    "sg:city":"North Tonawanda",
    "sg:classifiers":[
        {
            "category":"Home & Garden",
            "subcategory":"Building Materials",
            "type":"Retail Goods"
        }
    ],
    "sg:phone":"+1 716 876 4252",
    "sg:postcode":"14120",
    "sg:province":"NY",
    "sg:tags":[
        "plywood",
        "veneer"
    ],
    "wof:name":"Wood Shed",
    "wof:placetype":"venue"
},
  "geometry": {"coordinates":[-78.823858,43.104993],"type":"Point"}
}