{
  "type": "Feature",
  "properties": {
    "addr:full":"523 Stewart Ave Brooklyn NY 11222",
    "addr:housenumber":"523",
    "addr:postcode":"11222",
    "addr:street":"Stewart Ave",
    "iso:country":"US",
    "sg:address":"523 Stewart Ave",
    "sg:city":"Brooklyn",
    "sg:classifiers":[
        {
            "category":"Food & Beverages",
            "subcategory":"Groceries & Convenience Stores",
            "type":"Retail Goods"
        }
    ],
    "sg:phone":"+1 718 485 5672",
    "sg:postcode":"11222",
    "sg:province":"NY",
    "wof:name":"Pereg Gourmet",
    "wof:placetype":"venue"
},
  "geometry": {"coordinates":[-73.932867,40.724382],"type":"Point"}
}