{
  "type": "Feature",
  "properties": {
    "iso:country":"US",
    "sg:address":"201 Center St",
    "sg:city":"Ithaca",
    "sg:classifiers":[
        {
            "category":"Health Services",
            "subcategory":"Doctor",
            "type":"Services"
        }
    ],
    "sg:phone":"+1 607 274 3205",
    "sg:postcode":"14850",
    "sg:province":"NY",
    "sg:tags":[
        "center"
    ],
    "wof:name":"Hammond Health Center The",
    "wof:placetype":"venue"
},
  "geometry": {"coordinates":[-76.502504,42.435558],"type":"Point"}
}