{
  "type": "Feature",
  "properties": {
    "addr:full":"347 5th Ave New York NY 10016",
    "addr:housenumber":"347",
    "addr:postcode":"10016",
    "addr:street":"5Th Ave",
    "iso:country":"US",
    "sg:address":"347 5th Ave",
    "sg:city":"New York",
    "sg:classifiers":[
        {
            "category":"Real Estate",
            "subcategory":"Architect",
            "type":"Services"
        }
    ],
    "sg:phone":"+1 212 779 3450",
    "sg:postcode":"10016",
    "sg:province":"NY",
    "sg:tags":[
        "construction",
        "design",
        "architectural",
        "custom"
    ],
    "wof:name":"Arcon Ltd Inc",
    "wof:placetype":"venue"
},
  "geometry": {"coordinates":[-73.98474,40.747958],"type":"Point"}
}