{
  "type": "Feature",
  "properties": {
    "iso:country":"US",
    "sg:address":"918 Ulster Ave",
    "sg:city":"Kingston",
    "sg:classifiers":[
        {
            "category":"Personal",
            "type":"Services"
        }
    ],
    "sg:phone":"+1 845 339 4052",
    "sg:postcode":"12449",
    "sg:province":"NY",
    "sg:tags":[
        "credit",
        "debt",
        "counseling"
    ],
    "wof:name":"Credit Data Of Hudson Valley",
    "wof:placetype":"venue"
},
  "geometry": {"coordinates":[-73.994184,41.956377],"type":"Point"}
}