{
  "type": "Feature",
  "properties": {
    "iso:country":"US",
    "sg:address":"247 W 37th St",
    "sg:city":"New York",
    "sg:classifiers":[
        {
            "category":"Real Estate",
            "subcategory":"Real Estate Operator",
            "type":"Services"
        }
    ],
    "sg:phone":"+1 212 245 0610",
    "sg:postcode":"10018",
    "sg:province":"NY",
    "sg:tags":[
        "apartment"
    ],
    "wof:name":"Affirmative Marketing Dept",
    "wof:placetype":"venue"
},
  "geometry": {"coordinates":[-73.990488,40.7536],"type":"Point"}
}