{
  "type": "Feature",
  "properties": {
    "addr:full":"2085 Ennabrock Rd Bellmore NY 11710",
    "addr:housenumber":"2085",
    "addr:postcode":"11710",
    "addr:street":"Ennabrock Rd",
    "iso:country":"US",
    "sg:address":"2085 Ennabrock Rd",
    "sg:city":"Bellmore",
    "sg:classifiers":[
        {
            "category":"Professional",
            "subcategory":"Accounting & Tax Preparation",
            "type":"Services"
        }
    ],
    "sg:phone":"+1   ",
    "sg:postcode":"11710",
    "sg:province":"NY",
    "wof:name":"Maury Cooper CPA",
    "wof:placetype":"venue"
},
  "geometry": {"coordinates":[-73.549712,40.702006],"type":"Point"}
}