{
  "type": "Feature",
  "properties": {
    "iso:country":"US",
    "sg:address":"33 Leeds Blvd",
    "sg:city":"Farmingville",
    "sg:classifiers":[
        {
            "category":"Health Services",
            "subcategory":"Chiropractor",
            "type":"Services"
        }
    ],
    "sg:phone":"+1 631 696 2225",
    "sg:postcode":"11738",
    "sg:province":"NY",
    "wof:name":"Farmingville Chiropractic Grp",
    "wof:placetype":"venue"
},
  "geometry": {"coordinates":[-73.05872599999999,40.841414],"type":"Point"}
}