{
  "type": "Feature",
  "properties": {
    "addr:full":"954 Lexington Ave New York NY 10021",
    "addr:housenumber":"954",
    "addr:postcode":"10021",
    "addr:street":"Lexington Ave",
    "iso:country":"US",
    "sg:address":"954 Lexington Ave",
    "sg:city":"New York",
    "sg:classifiers":[
        {
            "category":"Organizations",
            "subcategory":"Community Association",
            "type":"Services"
        }
    ],
    "sg:phone":"+1 212 794 2231",
    "sg:postcode":"10021",
    "sg:province":"NY",
    "wof:name":"Broadway Association Inc",
    "wof:placetype":"venue"
},
  "geometry": {"coordinates":[-73.963443,40.768758],"type":"Point"}
}