{
  "type": "Feature",
  "properties": {
    "iso:country":"US",
    "sg:address":"375 S End Ave",
    "sg:city":"New York",
    "sg:classifiers":[
        {
            "category":"Real Estate",
            "subcategory":"Real Estate Agent",
            "type":"Services"
        }
    ],
    "sg:phone":"+1 212 945 1887",
    "sg:postcode":"10280",
    "sg:province":"NY",
    "wof:name":"Bing Sons Realty Corp",
    "wof:placetype":"venue"
},
  "geometry": {"coordinates":[-74.01619700000001,40.710467],"type":"Point"}
}