{
  "type": "Feature",
  "properties": {
    "addr:full":"24 Deane Pl Larchmont NY 10538",
    "addr:housenumber":"24",
    "addr:postcode":"10538",
    "addr:street":"Deane Pl",
    "iso:country":"US",
    "sg:address":"24 Deane Pl",
    "sg:city":"Larchmont",
    "sg:classifiers":[
        {
            "category":"Building & Trades",
            "subcategory":"Landscaping Services",
            "type":"Services"
        }
    ],
    "sg:phone":"+1 914 834 2467",
    "sg:postcode":"10538",
    "sg:province":"NY",
    "wof:name":"Delborgo Lawn Maintenance",
    "wof:placetype":"venue"
},
  "geometry": {"coordinates":[-73.759513,40.92286],"type":"Point"}
}