{
  "type": "Feature",
  "properties": {
    "addr:full":"2475 Harlem Rd Buffalo NY 14225",
    "addr:housenumber":"2475",
    "addr:postcode":"14225",
    "addr:street":"Harlem Rd",
    "iso:country":"US",
    "sg:address":"2475 Harlem Rd",
    "sg:city":"Buffalo",
    "sg:classifiers":[
        {
            "category":"Professional",
            "subcategory":"Lawyer & Legal Services",
            "type":"Services"
        }
    ],
    "sg:phone":"+1 716 891 5000",
    "sg:postcode":"14225",
    "sg:province":"NY",
    "wof:name":"Ciesielski Robert M Atty",
    "wof:placetype":"venue"
},
  "geometry": {"coordinates":[-78.78420300000001,42.911201],"type":"Point"}
}