{
  "type": "Feature",
  "properties": {
    "addr:full":"99 Senate St Atlantic Beach NY 11501",
    "addr:housenumber":"99",
    "addr:postcode":"11501",
    "addr:street":"Senate St",
    "iso:country":"US",
    "sg:address":"99 Senate St",
    "sg:city":"Atlantic Beach",
    "sg:classifiers":[
        {
            "category":"Food & Beverages",
            "subcategory":"Groceries & Convenience Stores",
            "type":"Retail Goods"
        }
    ],
    "sg:phone":"+1   ",
    "sg:postcode":"11501",
    "sg:province":"NY",
    "wof:name":"Plaza Market",
    "wof:placetype":"venue"
},
  "geometry": {"coordinates":[-73.62692699999999,40.745429],"type":"Point"}
}