{
  "type": "Feature",
  "properties": {
    "iso:country":"US",
    "sg:address":"3408 Turf Rd",
    "sg:city":"Oceanside",
    "sg:classifiers":[
        {
            "category":"Wholesale",
            "subcategory":"Furniture",
            "type":"Manufacturing & Wholesale Goods"
        }
    ],
    "sg:phone":"+1 516 678 5729",
    "sg:postcode":"11572",
    "sg:province":"NY",
    "wof:name":"Goldberg Associates",
    "wof:placetype":"venue"
},
  "geometry": {"coordinates":[-73.627836,40.628947],"type":"Point"}
}