{
  "type": "Feature",
  "properties": {
    "addr:full":"12 W 21st Street New York NY 10010",
    "addr:housenumber":"12",
    "addr:postcode":"10010",
    "addr:street":"W 21St Street",
    "iso:country":"US",
    "sg:address":"12 W 21st Street",
    "sg:city":"New York",
    "sg:classifiers":[
        {
            "category":"Home & Garden",
            "subcategory":"Furniture",
            "type":"Retail Goods"
        }
    ],
    "sg:phone":"+1 212 645 2524",
    "sg:postcode":"10010",
    "sg:province":"NY",
    "sg:tags":[
        "store"
    ],
    "wof:name":"North Carolina Furniture Show Room",
    "wof:placetype":"venue"
},
  "geometry": {"coordinates":[-73.99086,40.740371],"type":"Point"}
}