{
  "type": "Feature",
  "properties": {
    "iso:country":"US",
    "sg:address":"19 Chestnut Dr",
    "sg:city":"Pomona",
    "sg:classifiers":[
        {
            "category":"Professional",
            "subcategory":"Business Services",
            "type":"Services"
        }
    ],
    "sg:phone":"+1 845 354 1638",
    "sg:postcode":"10970",
    "sg:province":"NY",
    "wof:name":"Creative Enterprises",
    "wof:placetype":"venue"
},
  "geometry": {"coordinates":[-74.050113,41.192673],"type":"Point"}
}