{
  "type": "Feature",
  "properties": {
    "addr:full":"301 Central Ave Lawrence NY 11559",
    "addr:housenumber":"301",
    "addr:postcode":"11559",
    "addr:street":"Central Ave",
    "iso:country":"US",
    "sg:address":"301 Central Ave",
    "sg:city":"Lawrence",
    "sg:classifiers":[
        {
            "category":"Shopping",
            "subcategory":"Florist",
            "type":"Retail Goods"
        }
    ],
    "sg:phone":"+1 516 569 0300",
    "sg:postcode":"11559",
    "sg:province":"NY",
    "sg:website":"www.stefansflorist.com",
    "wof:name":"Stefans Florist",
    "wof:placetype":"venue"
},
  "geometry": {"coordinates":[-73.733597,40.615501],"type":"Point"}
}