{
  "type": "Feature",
  "properties": {
    "iso:country":"US",
    "sg:address":"7170 Boston State Rd",
    "sg:city":"Hamburg",
    "sg:classifiers":[
        {
            "category":"Building & Trades",
            "subcategory":"Construction",
            "type":"Services"
        }
    ],
    "sg:phone":"+1 716 648 1500",
    "sg:postcode":"14075",
    "sg:province":"NY",
    "sg:tags":[
        "home",
        "builder"
    ],
    "wof:name":"Acorn Ridge",
    "wof:placetype":"venue"
},
  "geometry": {"coordinates":[-78.778952,42.686873],"type":"Point"}
}