{
  "type": "Feature",
  "properties": {
    "addr:full":"800 Fairmount Ave Jamestown NY 14701",
    "addr:housenumber":"800",
    "addr:postcode":"14701",
    "addr:street":"Fairmount Ave",
    "iso:country":"US",
    "sg:address":"800 Fairmount Ave",
    "sg:city":"Jamestown",
    "sg:classifiers":[
        {
            "category":"Real Estate",
            "subcategory":"Real Estate Agent",
            "type":"Services"
        }
    ],
    "sg:phone":"+1 716 484 2020",
    "sg:postcode":"14701",
    "sg:province":"NY",
    "sg:tags":[
        "appraisal",
        "sales"
    ],
    "wof:name":"Re/Max",
    "wof:placetype":"venue"
},
  "geometry": {"coordinates":[-79.28419599999999,42.097362],"type":"Point"}
}