{
  "type": "Feature",
  "properties": {
    "addr:full":"502 Uniondale Ave Uniondale NY 11553",
    "addr:housenumber":"502",
    "addr:postcode":"11553",
    "addr:street":"Uniondale Ave",
    "iso:country":"US",
    "sg:address":"502 Uniondale Ave",
    "sg:city":"Uniondale",
    "sg:classifiers":[
        {
            "category":"Personal",
            "subcategory":"Beauty Salon",
            "type":"Services"
        }
    ],
    "sg:phone":"+1 516 481 0952",
    "sg:postcode":"11553",
    "sg:province":"NY",
    "wof:name":"Rosi's Beauty Salon",
    "wof:placetype":"venue"
},
  "geometry": {"coordinates":[-73.59293700000001,40.703348],"type":"Point"}
}