{
  "type": "Feature",
  "properties": {
    "addr:full":"360 2nd St East Northport NY 11731",
    "addr:housenumber":"360",
    "addr:postcode":"11731",
    "addr:street":"2Nd St",
    "iso:country":"US",
    "sg:address":"360 2nd St",
    "sg:city":"East Northport",
    "sg:classifiers":[
        {
            "category":"Insurance",
            "subcategory":"Insurance Agent",
            "type":"Services"
        }
    ],
    "sg:phone":"+1 631 368 2110",
    "sg:postcode":"11731",
    "sg:province":"NY",
    "wof:name":"Culhane & King Insurance",
    "wof:placetype":"venue"
},
  "geometry": {"coordinates":[-73.32498099999999,40.868782],"type":"Point"}
}