{
  "type": "Feature",
  "properties": {
    "addr:full":"6049 Dublin Rd Canisteo NY 14823",
    "addr:housenumber":"6049",
    "addr:postcode":"14823",
    "addr:street":"Dublin Rd",
    "iso:country":"US",
    "sg:address":"6049 Dublin Rd",
    "sg:city":"Canisteo",
    "sg:classifiers":[
        {
            "category":"Freight",
            "type":"Transportation"
        }
    ],
    "sg:phone":"+1   ",
    "sg:postcode":"14823",
    "sg:province":"NY",
    "sg:tags":[
        "operator",
        "local",
        "trucking"
    ],
    "wof:name":"J & P Emo Trucking Inc",
    "wof:placetype":"venue"
},
  "geometry": {"coordinates":[-77.493827,42.293122],"type":"Point"}
}