{
  "type": "Feature",
  "properties": {
    "addr:full":"3214 Greenpoint Ave Long Island City NY 11101",
    "addr:housenumber":"3214",
    "addr:postcode":"11101",
    "addr:street":"Greenpoint Ave",
    "iso:country":"US",
    "sg:address":"3214 Greenpoint Ave",
    "sg:city":"Long Island City",
    "sg:classifiers":[
        {
            "category":"Building & Trades",
            "subcategory":"Electrical",
            "type":"Services"
        }
    ],
    "sg:phone":"+1 718 786 6473",
    "sg:postcode":"11101",
    "sg:province":"NY",
    "sg:tags":[
        "electrician"
    ],
    "wof:name":"Nunez Electric",
    "wof:placetype":"venue"
},
  "geometry": {"coordinates":[-73.935402,40.735199],"type":"Point"}
}