{
  "type": "Feature",
  "properties": {
    "iso:country":"US",
    "sg:address":"300 W 49 St",
    "sg:city":"New York",
    "sg:classifiers":[
        {
            "category":"Shopping",
            "subcategory":"Computers & Home Electronics",
            "type":"Retail Goods"
        }
    ],
    "sg:phone":"+1 212 333 3150",
    "sg:postcode":"10019",
    "sg:province":"NY",
    "sg:tags":[
        "consumer",
        "product",
        "electronic"
    ],
    "wof:name":"Sunny Electronics",
    "wof:placetype":"venue"
},
  "geometry": {"coordinates":[-73.989401,40.762859],"type":"Point"}
}