{
  "type": "Feature",
  "properties": {
    "addr:full":"306 S Main St Syracuse NY 13212",
    "addr:housenumber":"306",
    "addr:postcode":"13212",
    "addr:street":"S Main St",
    "iso:country":"US",
    "sg:address":"306 S Main St",
    "sg:city":"Syracuse",
    "sg:classifiers":[
        {
            "category":"Shopping",
            "subcategory":"Clothing, Apparel, & Fashions",
            "type":"Retail Goods"
        }
    ],
    "sg:phone":"+1 315 458 6833",
    "sg:postcode":"13212",
    "sg:province":"NY",
    "sg:tags":[
        "shop",
        "bridal"
    ],
    "wof:name":"Rebecca's Bridal Boutique Inc",
    "wof:placetype":"venue"
},
  "geometry": {"coordinates":[-76.13117099999999,43.133026],"type":"Point"}
}