{
  "type": "Feature",
  "properties": {
    "iso:country":"US",
    "sg:address":"267 42nd St",
    "sg:city":"Brooklyn",
    "sg:classifiers":[
        {
            "category":"Shopping",
            "type":"Retail Goods"
        },
        {
            "category":"Autos & Motor Vehicles",
            "subcategory":"Auto Supplies",
            "type":"Retail Goods"
        }
    ],
    "sg:phone":"+1 718 832 7770",
    "sg:postcode":"11232",
    "sg:province":"NY",
    "sg:tags":[
        "automobile",
        "alarm",
        "merchandise"
    ],
    "wof:name":"Sunset Sound and Security",
    "wof:placetype":"venue"
},
  "geometry": {"coordinates":[-74.011087,40.653177],"type":"Point"}
}