{
  "type": "Feature",
  "properties": {
    "iso:country":"US",
    "sg:address":"74 Morton St",
    "sg:city":"Brentwood",
    "sg:classifiers":[
        {
            "category":"Shopping",
            "subcategory":"Computers & Home Electronics",
            "type":"Retail Goods"
        }
    ],
    "sg:phone":"+1   ",
    "sg:postcode":"11717",
    "sg:province":"NY",
    "wof:name":"P&S Computers",
    "wof:placetype":"venue"
},
  "geometry": {"coordinates":[-73.24796000000001,40.79495],"type":"Point"}
}