{
  "type": "Feature",
  "properties": {
    "addr:full":"2099 Nostrand Ave Brooklyn NY 11210",
    "addr:housenumber":"2099",
    "addr:postcode":"11210",
    "addr:street":"Nostrand Ave",
    "iso:country":"US",
    "sg:address":"2099 Nostrand Ave",
    "sg:city":"Brooklyn",
    "sg:classifiers":[
        {
            "category":"Restaurant",
            "type":"Food & Drink"
        }
    ],
    "sg:phone":"+1   ",
    "sg:postcode":"11210",
    "sg:province":"NY",
    "sg:tags":[
        "eating"
    ],
    "wof:name":"Kam Shing Restaurant",
    "wof:placetype":"venue"
},
  "geometry": {"coordinates":[-73.947857,40.635966],"type":"Point"}
}