{
  "type": "Feature",
  "properties": {
    "addr:full":"933 Elizabeth St Utica NY 13501",
    "addr:housenumber":"933",
    "addr:postcode":"13501",
    "addr:street":"Elizabeth St",
    "iso:country":"US",
    "sg:address":"933 Elizabeth St",
    "sg:city":"Utica",
    "sg:classifiers":[
        {
            "category":"Retail",
            "subcategory":"Funeral Services",
            "type":"Services"
        }
    ],
    "sg:phone":"+1   ",
    "sg:postcode":"13501",
    "sg:province":"NY",
    "wof:name":"Sansone Funeral Home",
    "wof:placetype":"venue"
},
  "geometry": {"coordinates":[-75.209799,43.094832],"type":"Point"}
}