{
  "type": "Feature",
  "properties": {
    "addr:full":"3315 Amboy Rd Staten Island NY 10306",
    "addr:housenumber":"3315",
    "addr:postcode":"10306",
    "addr:street":"Amboy Rd",
    "iso:country":"US",
    "sg:address":"3315 Amboy Rd",
    "sg:city":"Staten Island",
    "sg:classifiers":[
        {
            "category":"Retail",
            "subcategory":"Funeral Services",
            "type":"Services"
        }
    ],
    "sg:phone":"+1 718 351 1870",
    "sg:postcode":"10306",
    "sg:province":"NY",
    "sg:tags":[
        "cemetery"
    ],
    "wof:name":"Valhalla Burial Pk",
    "wof:placetype":"venue"
},
  "geometry": {"coordinates":[-74.135181,40.559874],"type":"Point"}
}