{
  "type": "Feature",
  "properties": {
    "addr:full":"3636 Fieldston Rd Bronx NY 10463",
    "addr:housenumber":"3636",
    "addr:postcode":"10463",
    "addr:street":"Fieldston Rd",
    "iso:country":"US",
    "sg:address":"3636 Fieldston Rd",
    "sg:city":"Bronx",
    "sg:classifiers":[
        {
            "category":"Professional",
            "subcategory":"Management & Consulting",
            "type":"Services"
        }
    ],
    "sg:phone":"+1 718 543 8900",
    "sg:postcode":"10463",
    "sg:province":"NY",
    "sg:tags":[
        "consultant",
        "business"
    ],
    "wof:name":"3636 Fieldston Owners Corp",
    "wof:placetype":"venue"
},
  "geometry": {"coordinates":[-73.906279,40.887263],"type":"Point"}
}