{
  "type": "Feature",
  "properties": {
    "addr:full":"219 Rand Hill Rd Morrisonville NY 12962",
    "addr:housenumber":"219",
    "addr:postcode":"12962",
    "addr:street":"Rand Hill Rd",
    "iso:country":"US",
    "sg:address":"219 Rand Hill Rd",
    "sg:city":"Morrisonville",
    "sg:classifiers":[
        {
            "category":"Organizations",
            "subcategory":"Community Association",
            "type":"Services"
        }
    ],
    "sg:phone":"+1 518 561 3452",
    "sg:postcode":"12962",
    "sg:province":"NY",
    "sg:tags":[
        "military"
    ],
    "wof:name":"American Legion",
    "wof:placetype":"venue"
},
  "geometry": {"coordinates":[-73.568703,44.713323],"type":"Point"}
}