{
  "type": "Feature",
  "properties": {
    "iso:country":"US",
    "sg:address":"1200 Bausch and Lomb Pl",
    "sg:city":"Rochester",
    "sg:classifiers":[
        {
            "category":"Banks & Credit Unions",
            "subcategory":"Bank",
            "type":"Services"
        }
    ],
    "sg:phone":"+1 585 238 4119",
    "sg:postcode":"14604",
    "sg:province":"NY",
    "sg:tags":[
        "national"
    ],
    "wof:name":"Key Trust Bank",
    "wof:placetype":"venue"
},
  "geometry": {"coordinates":[-77.605801,43.15416],"type":"Point"}
}