{
  "type": "Feature",
  "properties": {
    "iso:country":"US",
    "sg:address":"6895 Lake Ave",
    "sg:city":"Williamson",
    "sg:classifiers":[
        {
            "category":"Shopping",
            "subcategory":"Gifts & Souvenirs",
            "type":"Retail Goods"
        }
    ],
    "sg:phone":"+1 315 597 5751",
    "sg:postcode":"14589",
    "sg:province":"NY",
    "sg:tags":[
        "shop"
    ],
    "wof:name":"Palmyra Canal Town Florist",
    "wof:placetype":"venue"
},
  "geometry": {"coordinates":[-77.18605700000001,43.248216],"type":"Point"}
}