{
  "type": "Feature",
  "properties": {
    "iso:country":"US",
    "sg:address":"137 Varick St",
    "sg:city":"New York",
    "sg:classifiers":[
        {
            "category":"Manufacturing",
            "subcategory":"Printing",
            "type":"Manufacturing & Wholesale Goods"
        }
    ],
    "sg:phone":"+1 212 625 9925",
    "sg:postcode":"10013",
    "sg:province":"NY",
    "sg:tags":[
        "printer"
    ],
    "wof:name":"Depicture Corp",
    "wof:placetype":"venue"
},
  "geometry": {"coordinates":[-74.005658,40.726434],"type":"Point"}
}