{
  "type": "Feature",
  "properties": {
    "addr:full":"Empire State Building 350 5th Avenue Suite# 5713 New York  NY 10118",
    "addr:housenumber":"350",
    "addr:postcode":"5713;10118",
    "addr:street":"5Th Avenue Suite #",
    "iso:country":"US",
    "sg:address":"Empire State Building 350 5th Avenue Suite# 5713",
    "sg:city":"New York ",
    "sg:classifiers":[
        {
            "category":"Professional",
            "subcategory":"Computer Services",
            "type":"Services"
        }
    ],
    "sg:phone":"+1 212 379 8353",
    "sg:postcode":"10118",
    "sg:province":"NY",
    "sg:tags":[
        "offshore",
        "it-outsourcing",
        "outsource",
        "bpo",
        "software-development",
        "software-house",
        "offshore-outsourcing"
    ],
    "sg:website":"http://www.verticity.com",
    "wof:name":"Verticity",
    "wof:placetype":"venue"
},
  "geometry": {"coordinates":[-73.973968,40.762966],"type":"Point"}
}