{
  "type": "Feature",
  "properties": {
    "iso:country":"US",
    "sg:address":"84 Montgomery St",
    "sg:city":"Albany",
    "sg:classifiers":[
        {
            "category":"Manufacturing",
            "subcategory":"Food",
            "type":"Manufacturing & Wholesale Goods"
        }
    ],
    "sg:phone":"+1 518 439 7603",
    "sg:postcode":"12207",
    "sg:province":"NY",
    "sg:tags":[
        "specialty"
    ],
    "wof:name":"Adventure In Food Trading",
    "wof:placetype":"venue"
},
  "geometry": {"coordinates":[-73.747045,42.654836],"type":"Point"}
}