{
  "type": "Feature",
  "properties": {
    "addr:full":"29 Magnolia Ter Albany NY 12209",
    "addr:housenumber":"29",
    "addr:postcode":"12209",
    "addr:street":"Magnolia Ter",
    "iso:country":"US",
    "sg:address":"29 Magnolia Ter",
    "sg:city":"Albany",
    "sg:classifiers":[
        {
            "category":"Professional",
            "subcategory":"Management & Consulting",
            "type":"Services"
        }
    ],
    "sg:phone":"+1 518 229 8345",
    "sg:postcode":"12209",
    "sg:province":"NY",
    "sg:tags":[
        "consultant"
    ],
    "sg:website":"http://www.exedes.com",
    "wof:name":"Executive Decision Services",
    "wof:placetype":"venue"
},
  "geometry": {"coordinates":[-73.775448,42.644264],"type":"Point"}
}