{
  "type": "Feature",
  "properties": {
    "addr:full":"4203 35th St Long Island City NY 11101",
    "addr:housenumber":"4203",
    "addr:postcode":"11101",
    "addr:street":"35Th St",
    "iso:country":"US",
    "sg:address":"4203 35th St",
    "sg:city":"Long Island City",
    "sg:classifiers":[
        {
            "category":"Building & Trades",
            "subcategory":"Construction",
            "type":"Services"
        }
    ],
    "sg:phone":"+1 718 729 8373",
    "sg:postcode":"11101",
    "sg:province":"NY",
    "sg:tags":[
        "contractor"
    ],
    "sg:website":"www.stretchwall.com",
    "wof:name":"Stretchwall Installations",
    "wof:placetype":"venue"
},
  "geometry": {"coordinates":[-73.929344,40.746877],"type":"Point"}
}