{
  "type": "Feature",
  "properties": {
    "iso:country":"US",
    "sg:address":"208 Broadway",
    "sg:city":"Amityville",
    "sg:classifiers":[
        {
            "category":"Retail",
            "subcategory":"Repair Shop",
            "type":"Services"
        }
    ],
    "sg:phone":"+1 631 326 0265",
    "sg:postcode":"11701",
    "sg:province":"NY",
    "sg:tags":[
        "lock",
        "locksmith"
    ],
    "wof:name":"24 Hour Emergency Locksmith",
    "wof:placetype":"venue"
},
  "geometry": {"coordinates":[-73.417017,40.680408],"type":"Point"}
}