{
  "type": "Feature",
  "properties": {
    "iso:country":"US",
    "sg:address":"617 S Walnut St",
    "sg:city":"Lindenhurst",
    "sg:classifiers":[
        {
            "category":"Building & Trades",
            "subcategory":"Construction",
            "type":"Services"
        }
    ],
    "sg:phone":"+1 631 225 5075",
    "sg:postcode":"11757",
    "sg:province":"NY",
    "sg:tags":[
        "asbestos",
        "consulting",
        "contractor",
        "business",
        "removal"
    ],
    "wof:name":"Enco Environmental Services",
    "wof:placetype":"venue"
},
  "geometry": {"coordinates":[-73.36960999999999,40.673766],"type":"Point"}
}