{
  "type": "Feature",
  "properties": {
    "iso:country":"US",
    "sg:address":"757 Hopkins Rd",
    "sg:city":"Buffalo",
    "sg:classifiers":[
        {
            "category":"Organizations",
            "subcategory":"Religious Organization",
            "type":"Services"
        }
    ],
    "sg:phone":"+1 716 639 7600",
    "sg:postcode":"14221",
    "sg:province":"NY",
    "wof:name":"Jewish Discovery Center",
    "wof:placetype":"venue"
},
  "geometry": {"coordinates":[-78.739392,42.999355],"type":"Point"}
}