{
  "type": "Feature",
  "properties": {
    "addr:full":"3086 Fulton St Brooklyn NY 11208",
    "addr:housenumber":"3086",
    "addr:postcode":"11208",
    "addr:street":"Fulton St",
    "iso:country":"US",
    "sg:address":"3086 Fulton St",
    "sg:city":"Brooklyn",
    "sg:classifiers":[
        {
            "category":"Autos & Motor Vehicles",
            "subcategory":"Auto Supplies",
            "type":"Retail Goods"
        }
    ],
    "sg:phone":"+1   ",
    "sg:postcode":"11208",
    "sg:province":"NY",
    "sg:tags":[
        "repair",
        "general"
    ],
    "wof:name":"D E V",
    "wof:placetype":"venue"
},
  "geometry": {"coordinates":[-73.880213,40.681355],"type":"Point"}
}