{
  "type": "Feature",
  "properties": {
    "addr:full":"4020 State St Schenectady NY 12304",
    "addr:housenumber":"4020",
    "addr:postcode":"12304",
    "addr:street":"State St",
    "iso:country":"US",
    "sg:address":"4020 State St",
    "sg:city":"Schenectady",
    "sg:classifiers":[
        {
            "category":"Home & Garden",
            "subcategory":"Furniture",
            "type":"Retail Goods"
        }
    ],
    "sg:phone":"+1 518 346 2200",
    "sg:postcode":"12304",
    "sg:province":"NY",
    "wof:name":"Adirondack Wood Shed Inc",
    "wof:placetype":"venue"
},
  "geometry": {"coordinates":[-73.887924,42.765996],"type":"Point"}
}