{
  "type": "Feature",
  "properties": {
    "iso:country":"US",
    "sg:address":"78 McGraw St",
    "sg:city":"Shirley",
    "sg:classifiers":[
        {
            "category":"Retail",
            "subcategory":"Car Wash",
            "type":"Services"
        }
    ],
    "sg:phone":"+1 631 657 3140",
    "sg:postcode":"11967",
    "sg:province":"NY",
    "wof:name":"Kellys Auto Detailing",
    "wof:placetype":"venue"
},
  "geometry": {"coordinates":[-72.863635,40.803818],"type":"Point"}
}