{
  "type": "Feature",
  "properties": {
    "addr:full":"619 Roanoke Ave Riverhead NY 11901",
    "addr:housenumber":"619",
    "addr:postcode":"11901",
    "addr:street":"Roanoke Ave",
    "iso:country":"US",
    "sg:address":"619 Roanoke Ave",
    "sg:city":"Riverhead",
    "sg:classifiers":[
        {
            "category":"Professional",
            "subcategory":"Employment Agencies",
            "type":"Services"
        }
    ],
    "sg:phone":"+1 631 369 5980",
    "sg:postcode":"11901",
    "sg:province":"NY",
    "wof:name":"Am Pm Property Services",
    "wof:placetype":"venue"
},
  "geometry": {"coordinates":[-72.6679,40.925201],"type":"Point"}
}