{
  "type": "Feature",
  "properties": {
    "addr:full":"5104 58th Place Woodside NY 11377",
    "addr:housenumber":"5104",
    "addr:postcode":"11377",
    "addr:street":"58Th Place",
    "iso:country":"US",
    "sg:address":"5104 58th Place",
    "sg:city":"Woodside",
    "sg:classifiers":[
        {
            "category":"Retail",
            "subcategory":"Auto Repair",
            "type":"Services"
        }
    ],
    "sg:phone":"+1 718 426 0085",
    "sg:postcode":"11377",
    "sg:province":"NY",
    "wof:name":"Ram Auto Repair Inc",
    "wof:placetype":"venue"
},
  "geometry": {"coordinates":[-73.90792,40.736307],"type":"Point"}
}