{
  "type": "Feature",
  "properties": {
    "addr:full":"18455 US Hwy 11 Watertown NY 13601",
    "addr:housenumber":"18455",
    "addr:postcode":"13601",
    "addr:street":"Us Hwy 11",
    "iso:country":"US",
    "sg:address":"18455 US Hwy 11",
    "sg:city":"Watertown",
    "sg:classifiers":[
        {
            "category":"Retail",
            "subcategory":"Auto Rental",
            "type":"Services"
        }
    ],
    "sg:phone":"+1 315 788 8364",
    "sg:postcode":"13601",
    "sg:province":"NY",
    "sg:tags":[
        "renting",
        "automobile"
    ],
    "wof:name":"Thrifty Car Rental",
    "wof:placetype":"venue"
},
  "geometry": {"coordinates":[-75.934005,43.933284],"type":"Point"}
}