{
  "type": "Feature",
  "properties": {
    "addr:full":"2000 Shames Dr Westbury NY 11590",
    "addr:postcode":"11590",
    "addr:street":"Dr",
    "iso:country":"US",
    "sg:address":"2000 Shames Dr",
    "sg:city":"Westbury",
    "sg:classifiers":[
        {
            "category":"Building & Trades",
            "subcategory":"Electrical",
            "type":"Services"
        }
    ],
    "sg:phone":"+1 516 932 3999",
    "sg:postcode":"11590",
    "sg:province":"NY",
    "sg:tags":[
        "installs",
        "equipment",
        "security",
        "electrical",
        "contractor"
    ],
    "wof:name":"Intelli-Tec Security Svcs LLC",
    "wof:placetype":"venue"
},
  "geometry": {"coordinates":[-73.55692500000001,40.774232],"type":"Point"}
}