{
  "type": "Feature",
  "properties": {
    "addr:full":"144 Genesee St Auburn NY 13021",
    "addr:housenumber":"144",
    "addr:postcode":"13021",
    "addr:street":"Genesee St",
    "iso:country":"US",
    "sg:address":"144 Genesee St",
    "sg:city":"Auburn",
    "sg:classifiers":[
        {
            "category":"Health Services",
            "subcategory":"Chiropractor",
            "type":"Services"
        }
    ],
    "sg:phone":"+1 315 252 2990",
    "sg:postcode":"13021",
    "sg:province":"NY",
    "wof:name":"Homic Advanced Chiropractic",
    "wof:placetype":"venue"
},
  "geometry": {"coordinates":[-76.569774,42.929814],"type":"Point"}
}