{
  "type": "Feature",
  "properties": {
    "iso:country":"US",
    "sg:address":"106 Old Country Rd",
    "sg:city":"Mineola",
    "sg:classifiers":[
        {
            "category":"Food & Beverages",
            "subcategory":"Bakery",
            "type":"Retail Goods"
        }
    ],
    "sg:phone":"+1 516 739 0195",
    "sg:postcode":"11501",
    "sg:province":"NY",
    "sg:tags":[
        "sandwich"
    ],
    "wof:name":"Subway Sandwiches",
    "wof:placetype":"venue"
},
  "geometry": {"coordinates":[-73.629901,40.740794],"type":"Point"}
}