{
  "type": "Feature",
  "properties": {
    "iso:country":"US",
    "sg:address":"4 Chelmsford Rd",
    "sg:city":"Rochester",
    "sg:classifiers":[
        {
            "category":"Health Services",
            "subcategory":"Doctor",
            "type":"Services"
        }
    ],
    "sg:phone":"+1 585 244 5665",
    "sg:postcode":"14618",
    "sg:province":"NY",
    "sg:tags":[
        "dentist"
    ],
    "wof:name":"Charles H Meinhold DDS",
    "wof:placetype":"venue"
},
  "geometry": {"coordinates":[-77.56016700000001,43.127494],"type":"Point"}
}