{
  "type": "Feature",
  "properties": {
    "iso:country":"US",
    "sg:address":"650 Main St",
    "sg:city":"East Aurora",
    "sg:classifiers":[
        {
            "category":"Wholesale",
            "subcategory":"Groceries",
            "type":"Manufacturing & Wholesale Goods"
        }
    ],
    "sg:phone":"+1 716 805 0078",
    "sg:postcode":"14052",
    "sg:province":"NY",
    "sg:tags":[
        "baker"
    ],
    "wof:name":"Cakery",
    "wof:placetype":"venue"
},
  "geometry": {"coordinates":[-78.61044699999999,42.767949],"type":"Point"}
}