{
  "type": "Feature",
  "properties": {
    "iso:country":"US",
    "sg:address":"4686 Pinecrest Ter",
    "sg:city":"Eden",
    "sg:classifiers":[
        {
            "category":"Government",
            "subcategory":"Office",
            "type":"Public Place"
        }
    ],
    "sg:phone":"+1 716 662 3337",
    "sg:postcode":"14057",
    "sg:province":"NY",
    "sg:tags":[
        "educational",
        "program",
        "administrative"
    ],
    "wof:name":"Lions Clubs of District 20 NY",
    "wof:placetype":"venue"
},
  "geometry": {"coordinates":[-78.80735199999999,42.695922],"type":"Point"}
}