{
  "type": "Feature",
  "properties": {
    "iso:country":"US",
    "sg:address":"3595 State School Rd",
    "sg:city":"Albion",
    "sg:classifiers":[
        {
            "category":"Home & Garden",
            "subcategory":"Building Materials",
            "type":"Retail Goods"
        }
    ],
    "sg:phone":"+1 585 589 1063",
    "sg:postcode":"14411",
    "sg:province":"NY",
    "sg:tags":[
        "plumbing",
        "fixture",
        "supply"
    ],
    "wof:name":"W C Roberson Plumbing & Htg",
    "wof:placetype":"venue"
},
  "geometry": {"coordinates":[-78.21456000000001,43.242453],"type":"Point"}
}