{
  "type": "Feature",
  "properties": {
    "addr:full":"1443 York Ave New York NY 10021",
    "addr:housenumber":"1443",
    "addr:postcode":"10021",
    "addr:street":"York Ave",
    "iso:country":"US",
    "sg:address":"1443 York Ave",
    "sg:city":"New York",
    "sg:classifiers":[
        {
            "category":"Restaurant",
            "type":"Food & Drink"
        }
    ],
    "sg:phone":"+1 212 396 4600",
    "sg:postcode":"10021",
    "sg:province":"NY",
    "sg:tags":[
        "cafe"
    ],
    "wof:name":"Hello Deli",
    "wof:placetype":"venue"
},
  "geometry": {"coordinates":[-73.95168099999999,40.769714],"type":"Point"}
}