{
  "type": "Feature",
  "properties": {
    "iso:country":"US",
    "sg:address":"9 Beechwood Ave",
    "sg:city":"Port Washington",
    "sg:classifiers":[
        {
            "category":"Home & Garden",
            "subcategory":"Home Furnishings",
            "type":"Retail Goods"
        }
    ],
    "sg:phone":"+1 516 883 5573",
    "sg:postcode":"11050",
    "sg:province":"NY",
    "sg:tags":[
        "curtain",
        "made",
        "drapery"
    ],
    "wof:name":"North Shore Window Treatments",
    "wof:placetype":"venue"
},
  "geometry": {"coordinates":[-73.683024,40.824844],"type":"Point"}
}