{
  "type": "Feature",
  "properties": {
    "iso:country":"US",
    "sg:address":"418 Empire Blvd",
    "sg:city":"Rochester",
    "sg:classifiers":[
        {
            "category":"Restaurant",
            "type":"Food & Drink"
        }
    ],
    "sg:phone":"+1 585 654 5570",
    "sg:postcode":"14609",
    "sg:province":"NY",
    "sg:tags":[
        "pizza"
    ],
    "wof:name":"Pontillo's Pizza & Pasta",
    "wof:placetype":"venue"
},
  "geometry": {"coordinates":[-77.546526,43.176807],"type":"Point"}
}