{
  "type": "Feature",
  "properties": {
    "addr:full":"3165 Nostrand Ave Brooklyn NY 11229",
    "addr:housenumber":"3165",
    "addr:postcode":"11229",
    "addr:street":"Nostrand Ave",
    "iso:country":"US",
    "sg:address":"3165 Nostrand Ave",
    "sg:city":"Brooklyn",
    "sg:classifiers":[
        {
            "category":"Health Services",
            "subcategory":"Podiatrist",
            "type":"Services"
        }
    ],
    "sg:phone":"+1 718 627 1212",
    "sg:postcode":"11229",
    "sg:province":"NY",
    "wof:name":"Family Foot Care",
    "wof:placetype":"venue"
},
  "geometry": {"coordinates":[-73.942768,40.605594],"type":"Point"}
}