{
  "type": "Feature",
  "properties": {
    "iso:country":"US",
    "sg:address":"39 N Plank Rd",
    "sg:city":"Newburgh",
    "sg:classifiers":[
        {
            "category":"Utilities",
            "type":"Services"
        }
    ],
    "sg:phone":"+1 845 561 2963",
    "sg:postcode":"12550",
    "sg:province":"NY",
    "sg:tags":[
        "cleaning",
        "beach",
        "lake",
        "improvement"
    ],
    "wof:name":"Beach Improvements LLC",
    "wof:placetype":"venue"
},
  "geometry": {"coordinates":[-74.028668,41.522727],"type":"Point"}
}