{
  "type": "Feature",
  "properties": {
    "iso:country":"US",
    "sg:address":"25 Maple Ave",
    "sg:city":"Cementon",
    "sg:classifiers":[
        {
            "category":"Autos & Motor Vehicles",
            "subcategory":"Automobile Sales",
            "type":"Retail Goods"
        },
        {
            "category":"Retail",
            "subcategory":"Auto Rental",
            "type":"Services"
        }
    ],
    "sg:phone":"+1 518 943 4300",
    "sg:postcode":"12414",
    "sg:province":"NY",
    "sg:tags":[
        "car"
    ],
    "wof:name":"Lacy R C Inc-Auto Sales & Service",
    "wof:placetype":"venue"
},
  "geometry": {"coordinates":[-73.87690000000001,42.216202],"type":"Point"}
}