{
  "type": "Feature",
  "properties": {
    "addr:full":"605 Park Ave New York NY 10021",
    "addr:housenumber":"605",
    "addr:postcode":"10021",
    "addr:street":"Park Ave",
    "iso:country":"US",
    "sg:address":"605 Park Ave",
    "sg:city":"New York",
    "sg:classifiers":[
        {
            "category":"Health Services",
            "subcategory":"Doctor",
            "type":"Services"
        }
    ],
    "sg:phone":"+1 212 794 1500",
    "sg:postcode":"10021",
    "sg:province":"NY",
    "wof:name":"Meisner Jay MD",
    "wof:placetype":"venue"
},
  "geometry": {"coordinates":[-73.96729999999999,40.766102],"type":"Point"}
}