{
  "type": "Feature",
  "properties": {
    "iso:country":"US",
    "sg:address":"10 Main St",
    "sg:city":"New Paltz",
    "sg:classifiers":[
        {
            "category":"Personal",
            "subcategory":"Beauty Salon",
            "type":"Services"
        }
    ],
    "sg:phone":"+1 845 255 1622",
    "sg:postcode":"12561",
    "sg:province":"NY",
    "wof:name":"Zen Hair",
    "wof:placetype":"venue"
},
  "geometry": {"coordinates":[-74.088746,41.746793],"type":"Point"}
}