{
  "type": "Feature",
  "properties": {
    "addr:full":"1501 Broadway New York NY 10036",
    "addr:housenumber":"1501",
    "addr:postcode":"10036",
    "addr:street":"Broadway",
    "iso:country":"US",
    "sg:address":"1501 Broadway",
    "sg:city":"New York",
    "sg:classifiers":[
        {
            "category":"Organizations",
            "subcategory":"Labor Organization",
            "type":"Services"
        }
    ],
    "sg:phone":"+1 212 391 1070",
    "sg:postcode":"10036",
    "sg:province":"NY",
    "wof:name":"Society Stage Dirs Chrgraphers",
    "wof:placetype":"venue"
},
  "geometry": {"coordinates":[-73.985821,40.757258],"type":"Point"}
}