{
  "type": "Feature",
  "properties": {
    "addr:full":"1437 Blossom Rd Rochester NY 14610",
    "addr:housenumber":"1437",
    "addr:postcode":"14610",
    "addr:street":"Blossom Rd",
    "iso:country":"US",
    "sg:address":"1437 Blossom Rd",
    "sg:city":"Rochester",
    "sg:classifiers":[
        {
            "category":"Professional",
            "type":"Services"
        }
    ],
    "sg:phone":"+1 585 922 8950",
    "sg:postcode":"14610",
    "sg:province":"NY",
    "sg:tags":[
        "establishment"
    ],
    "wof:name":"Mc Cauley Ctr",
    "wof:placetype":"venue"
},
  "geometry": {"coordinates":[-77.536034,43.14918],"type":"Point"}
}