{
  "type": "Feature",
  "properties": {
    "addr:full":"402 State Hwy 163 Fort Plain NY 13339",
    "addr:housenumber":"402",
    "addr:postcode":"13339",
    "addr:street":"State Hwy 163;Plain",
    "iso:country":"US",
    "sg:address":"402 State Hwy 163",
    "sg:city":"Fort Plain",
    "sg:classifiers":[
        {
            "category":"Autos & Motor Vehicles",
            "subcategory":"Auto Supplies",
            "type":"Retail Goods"
        }
    ],
    "sg:phone":"+1 518 993 2235",
    "sg:postcode":"13339",
    "sg:province":"NY",
    "sg:tags":[
        "tire"
    ],
    "wof:name":"Hill Top Tire",
    "wof:placetype":"venue"
},
  "geometry": {"coordinates":[-74.656471,42.910967],"type":"Point"}
}