{
  "type": "Feature",
  "properties": {
    "addr:full":"205 Academy St Syracuse NY 13207",
    "addr:housenumber":"205",
    "addr:postcode":"13207",
    "addr:street":"Academy St",
    "iso:country":"US",
    "sg:address":"205 Academy St",
    "sg:city":"Syracuse",
    "sg:classifiers":[
        {
            "category":"Real Estate",
            "subcategory":"Real Estate Agent",
            "type":"Services"
        }
    ],
    "sg:phone":"+1 315 492 8249",
    "sg:postcode":"13207",
    "sg:province":"NY",
    "wof:name":"Turtlegrass Enterprises",
    "wof:placetype":"venue"
},
  "geometry": {"coordinates":[-76.150716,42.999797],"type":"Point"}
}