{
  "type": "Feature",
  "properties": {
    "iso:country":"US",
    "sg:address":"245 7th Ave Frnt 1",
    "sg:city":"New York",
    "sg:classifiers":[
        {
            "category":"Banks & Credit Unions",
            "subcategory":"Bank",
            "type":"Services"
        }
    ],
    "sg:phone":"+1 212 488 2307",
    "sg:postcode":"10001",
    "sg:province":"NY",
    "wof:name":"Chase",
    "wof:placetype":"venue"
},
  "geometry": {"coordinates":[-73.995013,40.744679],"type":"Point"}
}