{
  "type": "Feature",
  "properties": {
    "addr:full":"5416 16th Ave Brooklyn NY 11204",
    "addr:housenumber":"5416",
    "addr:postcode":"11204",
    "addr:street":"16Th Ave",
    "iso:country":"US",
    "sg:address":"5416 16th Ave",
    "sg:city":"Brooklyn",
    "sg:classifiers":[
        {
            "category":"Wholesale",
            "subcategory":"Home Furnishings",
            "type":"Manufacturing & Wholesale Goods"
        }
    ],
    "sg:phone":"+1 718 851 4455",
    "sg:postcode":"11204",
    "sg:province":"NY",
    "sg:tags":[
        "blind",
        "shade"
    ],
    "wof:name":"Cohens Window Shades & Venetian Blinds",
    "wof:placetype":"venue"
},
  "geometry": {"coordinates":[-73.98870100000001,40.628101],"type":"Point"}
}