{
  "type": "Feature",
  "properties": {
    "iso:country":"US",
    "sg:address":"884 New Lots Ave",
    "sg:city":"Brooklyn",
    "sg:classifiers":[
        {
            "category":"Autos & Motor Vehicles",
            "subcategory":"Automobile Sales",
            "type":"Retail Goods"
        }
    ],
    "sg:phone":"+1 718 257 8210",
    "sg:postcode":"11208",
    "sg:province":"NY",
    "sg:tags":[
        "car",
        "dealer"
    ],
    "wof:name":"T Cars Lover Automotive",
    "wof:placetype":"venue"
},
  "geometry": {"coordinates":[-73.87755,40.668588],"type":"Point"}
}