{
  "type": "Feature",
  "properties": {
    "iso:country":"US",
    "sg:address":"3065 Maple Ave",
    "sg:city":"Wilson",
    "sg:classifiers":[
        {
            "category":"Building & Trades",
            "subcategory":"Construction",
            "type":"Services"
        }
    ],
    "sg:phone":"+1 716 751 9603",
    "sg:postcode":"14172",
    "sg:province":"NY",
    "sg:tags":[
        "home",
        "improvement"
    ],
    "sg:website":"www.swsiding.com",
    "wof:name":"S W Siding Inc",
    "wof:placetype":"venue"
},
  "geometry": {"coordinates":[-78.874498,43.306424],"type":"Point"}
}