{
  "type": "Feature",
  "properties": {
    "iso:country":"US",
    "sg:address":"59 Montauk Hwy",
    "sg:city":"Blue Point",
    "sg:classifiers":[
        {
            "category":"Restaurant",
            "type":"Food & Drink"
        }
    ],
    "sg:menulink":"http://www.allmenus.com/ny/brookhaven/209512-thongpangchang/menu/",
    "sg:phone":"+1 631 363 0507",
    "sg:postcode":"11715",
    "sg:province":"NY",
    "sg:tags":[
        "thai",
        "asian"
    ],
    "wof:name":"Thongpangchang",
    "wof:placetype":"venue"
},
  "geometry": {"coordinates":[-73.038543,40.753389],"type":"Point"}
}