{
  "type": "Feature",
  "properties": {
    "addr:full":"457 Maple Ave Westbury NY 11590",
    "addr:housenumber":"457",
    "addr:postcode":"11590",
    "addr:street":"Maple Ave",
    "iso:country":"US",
    "sg:address":"457 Maple Ave",
    "sg:city":"Westbury",
    "sg:classifiers":[
        {
            "category":"Personal",
            "subcategory":"Beauty Salon",
            "type":"Services"
        }
    ],
    "sg:phone":"+1   ",
    "sg:postcode":"11590",
    "sg:province":"NY",
    "sg:tags":[
        "shop"
    ],
    "wof:name":"M & L Unisex Salon",
    "wof:placetype":"venue"
},
  "geometry": {"coordinates":[-73.581929,40.756516],"type":"Point"}
}