{
  "type": "Feature",
  "properties": {
    "addr:full":"2540 Merrick Rd Bellmore NY 11710",
    "addr:housenumber":"2540",
    "addr:postcode":"11710",
    "addr:street":"Merrick Rd",
    "iso:country":"US",
    "sg:address":"2540 Merrick Rd",
    "sg:city":"Bellmore",
    "sg:classifiers":[
        {
            "category":"Food & Beverages",
            "subcategory":"Groceries & Convenience Stores",
            "type":"Retail Goods"
        }
    ],
    "sg:phone":"+1   ",
    "sg:postcode":"11710",
    "sg:province":"NY",
    "sg:tags":[
        "alcoholic"
    ],
    "sg:website":"www.7-eleven.com",
    "wof:name":"7-Eleven",
    "wof:placetype":"venue"
},
  "geometry": {"coordinates":[-73.53202899999999,40.66226],"type":"Point"}
}