{
  "type": "Feature",
  "properties": {
    "iso:country":"US",
    "sg:address":"1273 North Ave",
    "sg:city":"New Rochelle",
    "sg:classifiers":[
        {
            "category":"Professional",
            "subcategory":"Business Services",
            "type":"Services"
        }
    ],
    "sg:phone":"+1 914 632 4500",
    "sg:postcode":"10804",
    "sg:province":"NY",
    "sg:tags":[
        "interior",
        "consultant",
        "design",
        "decorator"
    ],
    "wof:name":"Nancy Scheer Associates Inc",
    "wof:placetype":"venue"
},
  "geometry": {"coordinates":[-73.79533499999999,40.945724],"type":"Point"}
}