{
  "type": "Feature",
  "properties": {
    "addr:full":"228 Walker Pl West Hempstead NY 11552",
    "addr:housenumber":"228",
    "addr:postcode":"11552",
    "addr:street":"Walker Pl West",
    "iso:country":"US",
    "sg:address":"228 Walker Pl",
    "sg:city":"West Hempstead",
    "sg:classifiers":[
        {
            "category":"Health Services",
            "subcategory":"Chiropractor",
            "type":"Services"
        }
    ],
    "sg:phone":"+1   ",
    "sg:postcode":"11552",
    "sg:province":"NY",
    "wof:name":"Chiropractic Russo Slater",
    "wof:placetype":"venue"
},
  "geometry": {"coordinates":[-73.656555,40.692204],"type":"Point"}
}