{
  "type": "Feature",
  "properties": {
    "iso:country":"US",
    "sg:address":"88 Sunset Ave",
    "sg:city":"Selden",
    "sg:classifiers":[
        {
            "category":"Professional",
            "type":"Services"
        }
    ],
    "sg:phone":"+1 631 451 0300",
    "sg:postcode":"11784",
    "sg:province":"NY",
    "sg:tags":[
        "establishment"
    ],
    "wof:name":"IDR Technologies",
    "wof:placetype":"venue"
},
  "geometry": {"coordinates":[-73.037042,40.856682],"type":"Point"}
}