{
  "type": "Feature",
  "properties": {
    "addr:full":"48 E Market St Corning NY 14830",
    "addr:housenumber":"48",
    "addr:postcode":"14830",
    "addr:street":"E Market St",
    "iso:country":"US",
    "sg:address":"48 E Market St",
    "sg:city":"Corning",
    "sg:classifiers":[
        {
            "category":"Professional",
            "subcategory":"Lawyer & Legal Services",
            "type":"Services"
        }
    ],
    "sg:phone":"+1 607 936 9313",
    "sg:postcode":"14830",
    "sg:province":"NY",
    "sg:tags":[
        "attorney"
    ],
    "wof:name":"Robert E Lull",
    "wof:placetype":"venue"
},
  "geometry": {"coordinates":[-77.053039,42.142991],"type":"Point"}
}