{
  "type": "Feature",
  "properties": {
    "iso:country":"US",
    "sg:address":"963 Friends Lake Rd",
    "sg:city":"Chestertown",
    "sg:classifiers":[
        {
            "category":"Restaurant",
            "type":"Food & Drink"
        }
    ],
    "sg:menulink":"http://www.allmenus.com/ny/chester/270264-friends-lake-inn/menu/",
    "sg:phone":"+1 518 494 4751",
    "sg:postcode":"12817",
    "sg:province":"NY",
    "wof:name":"Friends Lake Inn",
    "wof:placetype":"venue"
},
  "geometry": {"coordinates":[-73.851719,43.641664],"type":"Point"}
}