{
  "type": "Feature",
  "properties": {
    "iso:country":"US",
    "sg:address":"421 Center St",
    "sg:city":"Lewiston",
    "sg:classifiers":[
        {
            "category":"Insurance",
            "subcategory":"Insurance Agent",
            "type":"Services"
        },
        {
            "category":"Insurance",
            "subcategory":"Hazard Insurance",
            "type":"Services"
        },
        {
            "category":"Insurance",
            "subcategory":"Title Insurance",
            "type":"Services"
        },
        {
            "category":"Insurance",
            "subcategory":"Life Insurance",
            "type":"Services"
        }
    ],
    "sg:phone":"+1 716 754 2701",
    "sg:postcode":"14092",
    "sg:province":"NY",
    "sg:tags":[
        "business",
        "auto",
        "commercial",
        "homeowner",
        "motorcycle",
        "renter"
    ],
    "wof:name":"Allstate Insurance Company - Joel Holka",
    "wof:placetype":"venue"
},
  "geometry": {"coordinates":[-79.04410900000001,43.172916],"type":"Point"}
}