{
  "type": "Feature",
  "properties": {
    "addr:full":"1 Conger Ave S Congers NY 10920",
    "addr:housenumber":"1",
    "addr:postcode":"10920",
    "addr:street":"Conger Ave S",
    "iso:country":"US",
    "sg:address":"1 Conger Ave S",
    "sg:city":"Congers",
    "sg:classifiers":[
        {
            "category":"Building & Trades",
            "subcategory":"Construction",
            "type":"Services"
        }
    ],
    "sg:phone":"+1 845 268 1600",
    "sg:postcode":"10920",
    "sg:province":"NY",
    "sg:tags":[
        "contractor"
    ],
    "wof:name":"Tucek Roofing & Restoration Co",
    "wof:placetype":"venue"
},
  "geometry": {"coordinates":[-73.94349,41.148095],"type":"Point"}
}