{
  "type": "Feature",
  "properties": {
    "addr:full":"201 Saint Marys Ave Staten Island NY 10305",
    "addr:housenumber":"201",
    "addr:postcode":"10305",
    "addr:street":"Saint Marys Ave",
    "iso:country":"US",
    "sg:address":"201 Saint Marys Ave",
    "sg:city":"Staten Island",
    "sg:classifiers":[
        {
            "category":"Insurance",
            "subcategory":"Insurance Agent",
            "type":"Services"
        }
    ],
    "sg:phone":"+1 718 816 0900",
    "sg:postcode":"10305",
    "sg:province":"NY",
    "wof:name":"Jma Reports",
    "wof:placetype":"venue"
},
  "geometry": {"coordinates":[-74.07361899999999,40.61377],"type":"Point"}
}