{
  "type": "Feature",
  "properties": {
    "addr:full":"1002 Grand Blvd Westbury NY 11590",
    "addr:housenumber":"1002",
    "addr:postcode":"11590",
    "addr:street":"Grand Blvd",
    "iso:country":"US",
    "sg:address":"1002 Grand Blvd",
    "sg:city":"Westbury",
    "sg:classifiers":[
        {
            "category":"Shopping",
            "subcategory":"Bicycles & Sporting Goods",
            "type":"Retail Goods"
        }
    ],
    "sg:phone":"+1   ",
    "sg:postcode":"11590",
    "sg:province":"NY",
    "wof:name":"Gds Systems",
    "wof:placetype":"venue"
},
  "geometry": {"coordinates":[-73.560025,40.751082],"type":"Point"}
}