{
  "type": "Feature",
  "properties": {
    "iso:country":"US",
    "sg:address":"1011 Yonkers Ave",
    "sg:city":"Yonkers",
    "sg:classifiers":[
        {
            "category":"Shopping",
            "subcategory":"Computers & Home Electronics",
            "type":"Retail Goods"
        }
    ],
    "sg:phone":"+1   ",
    "sg:postcode":"10704",
    "sg:province":"NY",
    "sg:tags":[
        "audio",
        "video"
    ],
    "wof:name":"Auto Systems",
    "wof:placetype":"venue"
},
  "geometry": {"coordinates":[-73.859589,40.915836],"type":"Point"}
}