{
  "type": "Feature",
  "properties": {
    "iso:country":"US",
    "sg:address":"10 W Park Pl",
    "sg:city":"Norwich",
    "sg:classifiers":[
        {
            "category":"Social Services",
            "subcategory":"Adult Care",
            "type":"Services"
        }
    ],
    "sg:phone":"+1 607 334 2910",
    "sg:postcode":"13815",
    "sg:province":"NY",
    "sg:tags":[
        "organization",
        "senior",
        "citizen"
    ],
    "wof:name":"Westside Park Senior Ctr",
    "wof:placetype":"venue"
},
  "geometry": {"coordinates":[-75.523922,42.531872],"type":"Point"}
}