{
  "type": "Feature",
  "properties": {
    "iso:country":"US",
    "sg:address":"1201 Broadway",
    "sg:city":"New York",
    "sg:classifiers":[
        {
            "category":"Real Estate",
            "subcategory":"Architect",
            "type":"Services"
        }
    ],
    "sg:phone":"+1 212 696 9062",
    "sg:postcode":"10001",
    "sg:province":"NY",
    "sg:tags":[
        "firm"
    ],
    "wof:name":"A Squared Architects",
    "wof:placetype":"venue"
},
  "geometry": {"coordinates":[-73.988758,40.74538],"type":"Point"}
}