{
  "type": "Feature",
  "properties": {
    "addr:full":"69 Denton Ave S New Hyde Park NY 11040",
    "addr:housenumber":"69",
    "addr:postcode":"11040",
    "addr:street":"Denton Ave S New",
    "iso:country":"US",
    "sg:address":"69 Denton Ave S",
    "sg:city":"New Hyde Park",
    "sg:classifiers":[
        {
            "category":"Utilities",
            "subcategory":"Fuel Oil & Lpg",
            "type":"Services"
        }
    ],
    "sg:phone":"+1   ",
    "sg:postcode":"11040",
    "sg:province":"NY",
    "sg:tags":[
        "liquefied",
        "gas",
        "petroleum"
    ],
    "wof:name":"Columbia Energy",
    "wof:placetype":"venue"
},
  "geometry": {"coordinates":[-73.671172,40.73353],"type":"Point"}
}