{
  "type": "Feature",
  "properties": {
    "iso:country":"US",
    "sg:address":"55 N Glenora Rd",
    "sg:city":"Dundee",
    "sg:classifiers":[
        {
            "category":"Building & Trades",
            "subcategory":"Construction",
            "type":"Services"
        }
    ],
    "sg:phone":"+1 607 243 7072",
    "sg:postcode":"14837",
    "sg:province":"NY",
    "sg:tags":[
        "electrical",
        "contractor"
    ],
    "wof:name":"Deep Lake Industries",
    "wof:placetype":"venue"
},
  "geometry": {"coordinates":[-76.913974,42.491292],"type":"Point"}
}