{
  "type": "Feature",
  "properties": {
    "addr:full":"1685 Elmwood Ave Buffalo NY 14207",
    "addr:housenumber":"1685",
    "addr:postcode":"14207",
    "addr:street":"Elmwood Ave",
    "iso:country":"US",
    "sg:address":"1685 Elmwood Ave",
    "sg:city":"Buffalo",
    "sg:classifiers":[
        {
            "category":"Wholesale",
            "subcategory":"Machinery & Supplies",
            "type":"Manufacturing & Wholesale Goods"
        }
    ],
    "sg:phone":"+1 716 876 9600",
    "sg:postcode":"14207",
    "sg:province":"NY",
    "sg:tags":[
        "repairing"
    ],
    "wof:name":"ATM Supply",
    "wof:placetype":"venue"
},
  "geometry": {"coordinates":[-78.878473,42.943525],"type":"Point"}
}