{
  "type": "Feature",
  "properties": {
    "iso:country":"US",
    "sg:address":"2680 Main St",
    "sg:city":"Buffalo",
    "sg:classifiers":[
        {
            "category":"Social Services",
            "subcategory":"Child Care",
            "type":"Services"
        }
    ],
    "sg:phone":"+1 716 838 9830",
    "sg:postcode":"14214",
    "sg:province":"NY",
    "sg:tags":[
        "day"
    ],
    "wof:name":"Kiddieland Child Care Ctr Inc",
    "wof:placetype":"venue"
},
  "geometry": {"coordinates":[-78.836308,42.941872],"type":"Point"}
}