{
  "type": "Feature",
  "properties": {
    "addr:full":"60 Central Ave Cortland NY 13045",
    "addr:housenumber":"60",
    "addr:postcode":"13045",
    "addr:street":"Central Ave",
    "iso:country":"US",
    "sg:address":"60 Central Ave",
    "sg:city":"Cortland",
    "sg:classifiers":[
        {
            "category":"Government",
            "subcategory":"Office",
            "type":"Public Place"
        }
    ],
    "sg:phone":"+1 607 753 5057",
    "sg:postcode":"13045",
    "sg:province":"NY",
    "sg:tags":[
        "county",
        "human"
    ],
    "wof:name":"Cortland County Retired & Seni",
    "wof:placetype":"venue"
},
  "geometry": {"coordinates":[-76.176408,42.600257],"type":"Point"}
}