{
  "type": "Feature",
  "properties": {
    "iso:country":"US",
    "sg:address":"946 Fulton St",
    "sg:city":"Brooklyn",
    "sg:classifiers":[
        {
            "category":"Professional",
            "subcategory":"Lawyer & Legal Services",
            "type":"Services"
        }
    ],
    "sg:phone":"+1 718 857 4181",
    "sg:postcode":"11238",
    "sg:province":"NY",
    "sg:tags":[
        "attorney"
    ],
    "wof:name":"Jan Alex Dash Law Office",
    "wof:placetype":"venue"
},
  "geometry": {"coordinates":[-73.963061,40.682633],"type":"Point"}
}