{
  "type": "Feature",
  "properties": {
    "addr:full":"464 Grand Ave Brooklyn NY 11238",
    "addr:housenumber":"464",
    "addr:postcode":"11238",
    "addr:street":"Grand Ave",
    "iso:country":"US",
    "sg:address":"464 Grand Ave",
    "sg:city":"Brooklyn",
    "sg:classifiers":[
        {
            "category":"Restaurant",
            "type":"Food & Drink"
        }
    ],
    "sg:phone":"+1 718 554 1966",
    "sg:postcode":"11238",
    "sg:province":"NY",
    "sg:tags":[
        "creperies"
    ],
    "sg:website":"www.magocreperie.com/",
    "wof:name":"Mago Creperie",
    "wof:placetype":"venue"
},
  "geometry": {"coordinates":[-73.96159299999999,40.682187],"type":"Point"}
}