{
  "type": "Feature",
  "properties": {
    "addr:full":"250 Mamaroneck Ave White Plains NY 10605",
    "addr:housenumber":"250",
    "addr:postcode":"10605",
    "addr:street":"Mamaroneck Ave",
    "iso:country":"US",
    "sg:address":"250 Mamaroneck Ave",
    "sg:city":"White Plains",
    "sg:classifiers":[
        {
            "category":"Professional",
            "subcategory":"Management & Consulting",
            "type":"Services"
        }
    ],
    "sg:phone":"+1 914 437 8657",
    "sg:postcode":"10605",
    "sg:province":"NY",
    "sg:tags":[
        "consultant"
    ],
    "wof:name":"Bartizan Persticax Consulting",
    "wof:placetype":"venue"
},
  "geometry": {"coordinates":[-73.76437799999999,41.02703],"type":"Point"}
}