{
  "type": "Feature",
  "properties": {
    "iso:country":"US",
    "sg:address":"1127 Wehrle Dr",
    "sg:city":"Buffalo",
    "sg:classifiers":[
        {
            "category":"Professional",
            "subcategory":"Business Services",
            "type":"Services"
        }
    ],
    "sg:phone":"+1 716 633 1234",
    "sg:postcode":"14221",
    "sg:province":"NY",
    "sg:tags":[
        "courier"
    ],
    "wof:name":"1-2-3 Delivery Inc",
    "wof:placetype":"venue"
},
  "geometry": {"coordinates":[-78.74096400000001,42.949514],"type":"Point"}
}