{
  "type": "Feature",
  "properties": {
    "addr:full":"150 W 30 St New York NY 10001",
    "addr:housenumber":"150",
    "addr:postcode":"10001",
    "addr:street":"W 30 St",
    "iso:country":"US",
    "sg:address":"150 W 30 St",
    "sg:city":"New York",
    "sg:classifiers":[
        {
            "category":"Real Estate",
            "subcategory":"Architect",
            "type":"Services"
        }
    ],
    "sg:phone":"+1 212 349 6500",
    "sg:postcode":"10001",
    "sg:province":"NY",
    "sg:website":"www.mckissack.com",
    "wof:name":"Mc Kissack & Mc Kissack",
    "wof:placetype":"venue"
},
  "geometry": {"coordinates":[-73.991399,40.747795],"type":"Point"}
}