{
  "type": "Feature",
  "properties": {
    "addr:full":"34 Nicolls Rd Wyandanch NY 11798",
    "addr:housenumber":"34",
    "addr:postcode":"11798",
    "addr:street":"Nicolls Rd",
    "iso:country":"US",
    "sg:address":"34 Nicolls Rd",
    "sg:city":"Wyandanch",
    "sg:classifiers":[
        {
            "category":"Organizations",
            "subcategory":"Religious Organization",
            "type":"Services"
        }
    ],
    "sg:phone":"+1 631 253 0636",
    "sg:postcode":"11798",
    "sg:province":"NY",
    "sg:tags":[
        "church"
    ],
    "wof:name":"Wyandanch Seventh Day Advntst",
    "wof:placetype":"venue"
},
  "geometry": {"coordinates":[-73.36733099999999,40.757723],"type":"Point"}
}