{
  "type": "Feature",
  "properties": {
    "iso:country":"US",
    "sg:address":"1001 Ave of the Americas",
    "sg:city":"New York",
    "sg:classifiers":[
        {
            "category":"Building & Trades",
            "subcategory":"Electrical",
            "type":"Services"
        }
    ],
    "sg:phone":"+1 212 302 7100",
    "sg:postcode":"10018",
    "sg:province":"NY",
    "sg:tags":[
        "alarm",
        "installation",
        "security",
        "maintenance"
    ],
    "wof:name":"Amerigard Alarm & SEC Corp",
    "wof:placetype":"venue"
},
  "geometry": {"coordinates":[-73.986047,40.752292],"type":"Point"}
}