{
  "type": "Feature",
  "properties": {
    "iso:country":"US",
    "sg:address":"1121 Erie Blvd W",
    "sg:city":"Syracuse",
    "sg:classifiers":[
        {
            "category":"Home & Garden",
            "subcategory":"Carpets & Floor Coverings",
            "type":"Retail Goods"
        }
    ],
    "sg:phone":"+1   ",
    "sg:postcode":"13204",
    "sg:province":"NY",
    "sg:tags":[
        "cleaning",
        "carpeting"
    ],
    "wof:name":"Saxenian Rug Cleaning Co",
    "wof:placetype":"venue"
},
  "geometry": {"coordinates":[-76.179806,43.050152],"type":"Point"}
}