{
  "type": "Feature",
  "properties": {
    "iso:country":"US",
    "sg:address":"23 Mitchell St",
    "sg:city":"Oswego",
    "sg:classifiers":[
        {
            "category":"Organizations",
            "subcategory":"Labor Organization",
            "type":"Services"
        }
    ],
    "sg:phone":"+1 315 343 7661",
    "sg:postcode":"13126",
    "sg:province":"NY",
    "wof:name":"Laborer's International Union",
    "wof:placetype":"venue"
},
  "geometry": {"coordinates":[-76.50071699999999,43.467018],"type":"Point"}
}