{
  "type": "Feature",
  "properties": {
    "addr:full":"3645 Olinville Ave Bronx NY 10467",
    "addr:housenumber":"3645",
    "addr:postcode":"10467",
    "addr:street":"Olinville Ave",
    "iso:country":"US",
    "sg:address":"3645 Olinville Ave",
    "sg:city":"Bronx",
    "sg:classifiers":[
        {
            "category":"Banks & Credit Unions",
            "subcategory":"Financial Services",
            "type":"Services"
        }
    ],
    "sg:phone":"+1 718 231 7834",
    "sg:postcode":"10467",
    "sg:province":"NY",
    "sg:tags":[
        "investor"
    ],
    "wof:name":"CPM Associates",
    "wof:placetype":"venue"
},
  "geometry": {"coordinates":[-73.866632,40.881057],"type":"Point"}
}