{
  "type": "Feature",
  "properties": {
    "iso:country":"US",
    "sg:address":"115 Schmitt Blvd",
    "sg:city":"Farmingdale",
    "sg:classifiers":[
        {
            "category":"Shopping",
            "type":"Retail Goods"
        }
    ],
    "sg:phone":"+1 631 777 1711",
    "sg:postcode":"11735",
    "sg:province":"NY",
    "sg:tags":[
        "art",
        "gallery",
        "dealer"
    ],
    "sg:website":"www.meisnerart.com",
    "wof:name":"Meisner Gallery",
    "wof:placetype":"venue"
},
  "geometry": {"coordinates":[-73.418998,40.748624],"type":"Point"}
}