{
  "type": "Feature",
  "properties": {
    "iso:country":"US",
    "sg:address":"240 Main St",
    "sg:city":"Oneida",
    "sg:classifiers":[
        {
            "category":"Health Services",
            "subcategory":"Clinic",
            "type":"Services"
        }
    ],
    "sg:phone":"+1 315 363 7448",
    "sg:postcode":"13421",
    "sg:province":"NY",
    "wof:name":"Elder Choice",
    "wof:placetype":"venue"
},
  "geometry": {"coordinates":[-75.650666,43.092957],"type":"Point"}
}