{
  "type": "Feature",
  "properties": {
    "iso:country":"US",
    "sg:address":"329 Lexington Ave",
    "sg:city":"Manhattan",
    "sg:classifiers":[
        {
            "category":"Bars & Pubs",
            "subcategory":"Sports Bar",
            "type":"Food & Drink"
        }
    ],
    "sg:phone":"+1 212 682 7700",
    "sg:postcode":"10016",
    "sg:province":"NY",
    "sg:website":"www.thejunctionnyc.com/",
    "wof:name":"The Junction",
    "wof:placetype":"venue"
},
  "geometry": {"coordinates":[-73.977312,40.749275],"type":"Point"}
}