{
  "type": "Feature",
  "properties": {
    "iso:country":"US",
    "sg:address":"280 Windsor Hwy",
    "sg:city":"New Windsor",
    "sg:classifiers":[
        {
            "category":"Arena",
            "subcategory":"Sports Club",
            "type":"Entertainment"
        }
    ],
    "sg:phone":"+1 845 561 9898",
    "sg:postcode":"12553",
    "sg:province":"NY",
    "sg:tags":[
        "martial art"
    ],
    "wof:name":"Hong's Karate School",
    "wof:placetype":"venue"
},
  "geometry": {"coordinates":[-74.04769899999999,41.469398],"type":"Point"}
}