{
  "type": "Feature",
  "properties": {
    "iso:country":"US",
    "sg:address":"475 Round Hill Rd",
    "sg:city":"Roslyn Heights",
    "sg:classifiers":[
        {
            "category":"Education",
            "subcategory":"School",
            "type":"Public Place"
        }
    ],
    "sg:phone":"+1 516 801 5100",
    "sg:postcode":"11577",
    "sg:province":"NY",
    "sg:tags":[
        "high",
        "middle",
        "elementary"
    ],
    "wof:name":"Roslyn School District",
    "wof:placetype":"venue"
},
  "geometry": {"coordinates":[-73.63972200000001,40.791316],"type":"Point"}
}