{
  "type": "Feature",
  "properties": {
    "iso:country":"US",
    "sg:address":"44 Steele Rd",
    "sg:city":"New Windsor",
    "sg:classifiers":[
        {
            "category":"Professional",
            "subcategory":"Accounting & Tax Preparation",
            "type":"Services"
        }
    ],
    "sg:phone":"+1   ",
    "sg:postcode":"12553",
    "sg:province":"NY",
    "wof:name":"Perregos",
    "wof:placetype":"venue"
},
  "geometry": {"coordinates":[-74.060474,41.491327],"type":"Point"}
}