{
  "type": "Feature",
  "properties": {
    "addr:full":"31 Monroe Pl Brooklyn NY 11201",
    "addr:housenumber":"31",
    "addr:postcode":"11201",
    "addr:street":"Monroe Pl",
    "iso:country":"US",
    "sg:address":"31 Monroe Pl",
    "sg:city":"Brooklyn",
    "sg:classifiers":[
        {
            "category":"Social Services",
            "type":"Services"
        }
    ],
    "sg:phone":"+1 718 797 3771",
    "sg:postcode":"11201",
    "sg:province":"NY",
    "sg:tags":[
        "counseling"
    ],
    "wof:name":"Heights Independent Counseling",
    "wof:placetype":"venue"
},
  "geometry": {"coordinates":[-73.992761,40.696318],"type":"Point"}
}