{
  "type": "Feature",
  "properties": {
    "iso:country":"US",
    "sg:address":"23 Lincoln Park Dr",
    "sg:city":"Buffalo",
    "sg:classifiers":[
        {
            "category":"Real Estate",
            "subcategory":"Real Estate Agent",
            "type":"Services"
        }
    ],
    "sg:phone":"+1 716 836 0160",
    "sg:postcode":"14223",
    "sg:province":"NY",
    "wof:name":"Pearce & Pearce Rl Est",
    "wof:placetype":"venue"
},
  "geometry": {"coordinates":[-78.831515,42.971565],"type":"Point"}
}