{
  "type": "Feature",
  "properties": {
    "iso:country":"US",
    "sg:address":"36 W Roe Blvd",
    "sg:city":"Patchogue",
    "sg:classifiers":[
        {
            "category":"Professional",
            "subcategory":"Lawyer & Legal Services",
            "type":"Services"
        }
    ],
    "sg:phone":"+1   ",
    "sg:postcode":"11772",
    "sg:province":"NY",
    "wof:name":"Sloane David A Attorney At Law",
    "wof:placetype":"venue"
},
  "geometry": {"coordinates":[-73.017065,40.77465],"type":"Point"}
}