{
  "type": "Feature",
  "properties": {
    "iso:country":"US",
    "sg:address":"68 35th St",
    "sg:city":"Brooklyn",
    "sg:classifiers":[
        {
            "category":"Building & Trades",
            "subcategory":"Construction",
            "type":"Services"
        }
    ],
    "sg:phone":"+1 718 768 2975",
    "sg:postcode":"11232",
    "sg:province":"NY",
    "sg:tags":[
        "home",
        "builder"
    ],
    "wof:name":"Mystique Home Fashions",
    "wof:placetype":"venue"
},
  "geometry": {"coordinates":[-74.00649,40.656496],"type":"Point"}
}