{
  "type": "Feature",
  "properties": {
    "iso:country":"US",
    "sg:address":"519 Hudson Ave",
    "sg:city":"Rochester",
    "sg:classifiers":[
        {
            "category":"Food & Beverages",
            "subcategory":"Groceries & Convenience Stores",
            "type":"Retail Goods"
        }
    ],
    "sg:phone":"+1 585 325 2210",
    "sg:postcode":"14605",
    "sg:province":"NY",
    "sg:tags":[
        "general"
    ],
    "wof:name":"Hartson Grocery",
    "wof:placetype":"venue"
},
  "geometry": {"coordinates":[-77.59954999999999,43.173804],"type":"Point"}
}