{
  "type": "Feature",
  "properties": {
    "addr:full":"200 Front St Vestal NY 13850",
    "addr:housenumber":"200",
    "addr:postcode":"13850",
    "addr:street":"Front St",
    "iso:country":"US",
    "sg:address":"200 Front St",
    "sg:city":"Vestal",
    "sg:classifiers":[
        {
            "category":"Social Services",
            "type":"Services"
        }
    ],
    "sg:phone":"+1 607 757 2679",
    "sg:postcode":"13850",
    "sg:province":"NY",
    "sg:tags":[
        "organization",
        "welfare"
    ],
    "wof:name":"All Women's Help Ctr",
    "wof:placetype":"venue"
},
  "geometry": {"coordinates":[-76.058933,42.083798],"type":"Point"}
}