{
  "type": "Feature",
  "properties": {
    "addr:full":"37 Brad Lane Staten Island NY 10314",
    "addr:housenumber":"37",
    "addr:postcode":"10314",
    "addr:street":"Brad Lane",
    "iso:country":"US",
    "sg:address":"37 Brad Lane",
    "sg:city":"Staten Island",
    "sg:classifiers":[
        {
            "category":"Building & Trades",
            "subcategory":"Plumbing",
            "type":"Services"
        },
        {
            "category":"Building & Trades",
            "subcategory":"Construction",
            "type":"Services"
        }
    ],
    "sg:phone":"+1 718 442 2295",
    "sg:postcode":"10314",
    "sg:province":"NY",
    "sg:tags":[
        "contractor"
    ],
    "sg:website":"www.communityii.com",
    "wof:name":"Community II Heating & Air Conditioning Corporation",
    "wof:placetype":"venue"
},
  "geometry": {"coordinates":[-74.166023,40.619436],"type":"Point"}
}