{
  "type": "Feature",
  "properties": {
    "addr:full":"732 65th St Brooklyn NY 11220",
    "addr:housenumber":"732",
    "addr:postcode":"11220",
    "addr:street":"65Th St",
    "iso:country":"US",
    "sg:address":"732 65th St",
    "sg:city":"Brooklyn",
    "sg:classifiers":[
        {
            "category":"Retail",
            "subcategory":"Auto Repair",
            "type":"Services"
        }
    ],
    "sg:phone":"+1 718 833 4338",
    "sg:postcode":"11220",
    "sg:province":"NY",
    "wof:name":"Mar-Bon Motors Inc",
    "wof:placetype":"venue"
},
  "geometry": {"coordinates":[-74.01408000000001,40.633186],"type":"Point"}
}