{
  "type": "Feature",
  "properties": {
    "addr:full":"64 W 119th St New York NY 10026",
    "addr:housenumber":"64",
    "addr:postcode":"10026",
    "addr:street":"W 119Th St",
    "iso:country":"US",
    "sg:address":"64 W 119th St",
    "sg:city":"New York",
    "sg:classifiers":[
        {
            "category":"Shopping",
            "subcategory":"Books",
            "type":"Retail Goods"
        }
    ],
    "sg:phone":"+1 212 289 6356",
    "sg:postcode":"10026",
    "sg:province":"NY",
    "sg:tags":[
        "bookstore"
    ],
    "sg:website":"www.aalbc.com",
    "wof:name":"AALBC.Com",
    "wof:placetype":"venue"
},
  "geometry": {"coordinates":[-73.947138,40.803322],"type":"Point"}
}