{
  "type": "Feature",
  "properties": {
    "iso:country":"US",
    "sg:address":"32 Kirkwood Dr",
    "sg:city":"Glen Cove",
    "sg:classifiers":[
        {
            "category":"Retail",
            "subcategory":"Repair Shop",
            "type":"Services"
        }
    ],
    "sg:phone":"+1 516 676 4789",
    "sg:postcode":"11542",
    "sg:province":"NY",
    "sg:tags":[
        "cesspool",
        "cleaning"
    ],
    "wof:name":"Imperial Cesspool Cleaning Co",
    "wof:placetype":"venue"
},
  "geometry": {"coordinates":[-73.617983,40.876126],"type":"Point"}
}