{
  "type": "Feature",
  "properties": {
    "addr:full":"21 Union Hill Dr Spencerport NY 14559",
    "addr:housenumber":"21",
    "addr:postcode":"14559",
    "addr:street":"Union Hill Dr",
    "iso:country":"US",
    "sg:address":"21 Union Hill Dr",
    "sg:city":"Spencerport",
    "sg:classifiers":[
        {
            "category":"Banks & Credit Unions",
            "subcategory":"Bank",
            "type":"Services"
        }
    ],
    "sg:phone":"+1 585 349 1580",
    "sg:postcode":"14559",
    "sg:province":"NY",
    "sg:tags":[
        "loan",
        "real estate"
    ],
    "sg:website":"www.amnetmortgage.com",
    "wof:name":"American Mortgage Network",
    "wof:placetype":"venue"
},
  "geometry": {"coordinates":[-77.80280399999999,43.181591],"type":"Point"}
}