{
  "type": "Feature",
  "properties": {
    "iso:country":"US",
    "sg:address":"3175 Orchard Park Rd",
    "sg:city":"Orchard Park",
    "sg:classifiers":[
        {
            "category":"Building & Trades",
            "subcategory":"Construction",
            "type":"Services"
        }
    ],
    "sg:phone":"+1 716 674 6501",
    "sg:postcode":"14127",
    "sg:province":"NY",
    "sg:tags":[
        "home",
        "commercial",
        "family",
        "contractor"
    ],
    "wof:name":"Project Development Cons",
    "wof:placetype":"venue"
},
  "geometry": {"coordinates":[-78.75157,42.797619],"type":"Point"}
}