{
  "type": "Feature",
  "properties": {
    "iso:country":"US",
    "sg:address":"341 Main St",
    "sg:city":"South Fallsburg",
    "sg:classifiers":[
        {
            "category":"Banks & Credit Unions",
            "subcategory":"Bank",
            "type":"Services"
        }
    ],
    "sg:phone":"+1 845 434 0985",
    "sg:postcode":"12779",
    "sg:province":"NY",
    "wof:name":"Provident Bank",
    "wof:placetype":"venue"
},
  "geometry": {"coordinates":[-74.651453,41.687318],"type":"Point"}
}