{
  "type": "Feature",
  "properties": {
    "iso:country":"US",
    "sg:address":"808 Carroll St",
    "sg:city":"Brooklyn",
    "sg:classifiers":[
        {
            "category":"Social Services",
            "type":"Services"
        }
    ],
    "sg:phone":"+1 718 857 5717",
    "sg:postcode":"11215",
    "sg:province":"NY",
    "sg:tags":[
        "worker"
    ],
    "wof:name":"Iris Lipner",
    "wof:placetype":"venue"
},
  "geometry": {"coordinates":[-73.973961,40.672211],"type":"Point"}
}