{
  "type": "Feature",
  "properties": {
    "iso:country":"US",
    "sg:address":"11 E 68 St",
    "sg:city":"New York",
    "sg:classifiers":[
        {
            "category":"Health Services",
            "subcategory":"Doctor",
            "type":"Services"
        }
    ],
    "sg:phone":"+1 212 535 0111",
    "sg:postcode":"10065",
    "sg:province":"NY",
    "sg:tags":[
        "physician",
        "surgeon"
    ],
    "wof:name":"Berney Goodman PC",
    "wof:placetype":"venue"
},
  "geometry": {"coordinates":[-73.96890399999999,40.769901],"type":"Point"}
}