{
  "type": "Feature",
  "properties": {
    "addr:full":"128 W 26th St 2nd Fl New York NY 10001",
    "addr:housenumber":"128",
    "addr:postcode":"10001",
    "addr:street":"W 26Th St",
    "iso:country":"US",
    "sg:address":"128 W 26th St 2nd Fl",
    "sg:city":"New York",
    "sg:classifiers":[
        {
            "category":"Restaurant",
            "type":"Food & Drink"
        }
    ],
    "sg:phone":"+1 212 243 2085",
    "sg:postcode":"10001",
    "sg:province":"NY",
    "sg:tags":[
        "steakhouse",
        "italian"
    ],
    "sg:website":"www.tredicinyc.com",
    "wof:name":"Tre Dici",
    "wof:placetype":"venue"
},
  "geometry": {"coordinates":[-73.99274,40.745065],"type":"Point"}
}