{
  "type": "Feature",
  "properties": {
    "addr:full":"1833 Whitney Rd E Fairport NY 14450",
    "addr:housenumber":"1833",
    "addr:postcode":"14450",
    "addr:street":"Whitney Rd E",
    "iso:country":"US",
    "sg:address":"1833 Whitney Rd E",
    "sg:city":"Fairport",
    "sg:classifiers":[
        {
            "category":"Real Estate",
            "subcategory":"Real Estate Agent",
            "type":"Services"
        }
    ],
    "sg:phone":"+1 585 223 5533",
    "sg:postcode":"14450",
    "sg:province":"NY",
    "sg:tags":[
        "inspection"
    ],
    "wof:name":"Matzan & Matzan Engineering",
    "wof:placetype":"venue"
},
  "geometry": {"coordinates":[-77.398596,43.108513],"type":"Point"}
}