{
  "type": "Feature",
  "properties": {
    "iso:country":"US",
    "sg:address":"3221 Lawndale St",
    "sg:city":"Endicott",
    "sg:classifiers":[
        {
            "category":"Manufacturing",
            "subcategory":"Tools & Machinery",
            "type":"Manufacturing & Wholesale Goods"
        }
    ],
    "sg:phone":"+1 607 748 8294",
    "sg:postcode":"13760",
    "sg:province":"NY",
    "sg:tags":[
        "a",
        "shop",
        "as",
        "job",
        "operates"
    ],
    "sg:website":"www.progressivetool.com",
    "wof:name":"Progressive Tool Co  Inc",
    "wof:placetype":"venue"
},
  "geometry": {"coordinates":[-76.022291,42.108769],"type":"Point"}
}