{
  "type": "Feature",
  "properties": {
    "iso:country":"US",
    "sg:address":"317 Madison Ave",
    "sg:city":"New York",
    "sg:classifiers":[
        {
            "category":"Wholesale",
            "subcategory":"Apparel",
            "type":"Manufacturing & Wholesale Goods"
        }
    ],
    "sg:phone":"+1 212 244 0260",
    "sg:postcode":"10017",
    "sg:province":"NY",
    "sg:tags":[
        "zipper"
    ],
    "wof:name":"Ideal Fastener Corp",
    "wof:placetype":"venue"
},
  "geometry": {"coordinates":[-73.97878300000001,40.753481],"type":"Point"}
}