{
  "type": "Feature",
  "properties": {
    "addr:full":"326 Garnsey Rd Pittsford NY 14534",
    "addr:housenumber":"326",
    "addr:postcode":"14534",
    "addr:street":"Garnsey Rd",
    "iso:country":"US",
    "sg:address":"326 Garnsey Rd",
    "sg:city":"Pittsford",
    "sg:classifiers":[
        {
            "category":"Health Services",
            "subcategory":"Nursing And Care Facility",
            "type":"Services"
        },
        {
            "category":"Health Services",
            "subcategory":"Health Practitioner",
            "type":"Services"
        }
    ],
    "sg:phone":"+1 585 425 4114",
    "sg:postcode":"14534",
    "sg:province":"NY",
    "sg:tags":[
        "home",
        "eldercare-home"
    ],
    "sg:website":"http://www.lowstresslife.com",
    "wof:name":"S B Remington Md",
    "wof:placetype":"venue"
},
  "geometry": {"coordinates":[-77.45692699999999,43.054888],"type":"Point"}
}