{
  "type": "Feature",
  "properties": {
    "addr:full":"3882 Jane Ct Seaford NY 11783",
    "addr:housenumber":"3882",
    "addr:postcode":"11783",
    "addr:street":"Jane Ct",
    "iso:country":"US",
    "sg:address":"3882 Jane Ct",
    "sg:city":"Seaford",
    "sg:classifiers":[
        {
            "category":"Professional",
            "subcategory":"Business Services",
            "type":"Services"
        }
    ],
    "sg:phone":"+1   ",
    "sg:postcode":"11783",
    "sg:province":"NY",
    "sg:tags":[
        "lithographic",
        "printing",
        "commercial"
    ],
    "wof:name":"American Tagmaster Inc",
    "wof:placetype":"venue"
},
  "geometry": {"coordinates":[-73.48911200000001,40.656258],"type":"Point"}
}