{
  "type": "Feature",
  "properties": {
    "iso:country":"US",
    "sg:address":"941 Park Ave",
    "sg:city":"New York",
    "sg:classifiers":[
        {
            "category":"Real Estate",
            "subcategory":"Real Estate Operator",
            "type":"Services"
        }
    ],
    "sg:phone":"+1 212 288 0263",
    "sg:postcode":"10028",
    "sg:province":"NY",
    "sg:tags":[
        "apartment"
    ],
    "wof:name":"Apartments & Apartment Houses",
    "wof:placetype":"venue"
},
  "geometry": {"coordinates":[-73.959273,40.776829],"type":"Point"}
}