{
  "type": "Feature",
  "properties": {
    "addr:full":"1949 Bathgate Ave Bronx NY 10457",
    "addr:housenumber":"1949",
    "addr:postcode":"10457",
    "addr:street":"Bathgate Ave",
    "iso:country":"US",
    "sg:address":"1949 Bathgate Ave",
    "sg:city":"Bronx",
    "sg:classifiers":[
        {
            "category":"Organizations",
            "subcategory":"Religious Organization",
            "type":"Services"
        }
    ],
    "sg:phone":"+1 718 731 2504",
    "sg:postcode":"10457",
    "sg:province":"NY",
    "sg:tags":[
        "church"
    ],
    "wof:name":"St Joseph's Roman Catholic Chr",
    "wof:placetype":"venue"
},
  "geometry": {"coordinates":[-73.897012,40.847047],"type":"Point"}
}