{
  "type": "Feature",
  "properties": {
    "addr:full":"837 Park Pl Brooklyn NY 11216",
    "addr:housenumber":"837",
    "addr:postcode":"11216",
    "addr:street":"Park Pl",
    "iso:country":"US",
    "sg:address":"837 Park Pl",
    "sg:city":"Brooklyn",
    "sg:classifiers":[
        {
            "category":"Real Estate",
            "subcategory":"Real Estate Operator",
            "type":"Services"
        }
    ],
    "sg:phone":"+1 718 774 6596",
    "sg:postcode":"11216",
    "sg:province":"NY",
    "sg:tags":[
        "building",
        "apartment"
    ],
    "wof:name":"Lowren Management Corp",
    "wof:placetype":"venue"
},
  "geometry": {"coordinates":[-73.947396,40.673272],"type":"Point"}
}