{
  "type": "Feature",
  "properties": {
    "addr:full":"589 Main St East Aurora NY 14052",
    "addr:housenumber":"589",
    "addr:postcode":"14052",
    "addr:street":"Main St",
    "iso:country":"US",
    "sg:address":"589 Main St",
    "sg:city":"East Aurora",
    "sg:classifiers":[
        {
            "category":"Retail",
            "subcategory":"Veterinary Services",
            "type":"Services"
        }
    ],
    "sg:phone":"+1 716 652 1120",
    "sg:postcode":"14052",
    "sg:province":"NY",
    "sg:tags":[
        "veterinarian"
    ],
    "wof:name":"East Aurora Veterinary",
    "wof:placetype":"venue"
},
  "geometry": {"coordinates":[-78.61306999999999,42.767847],"type":"Point"}
}