{
  "type": "Feature",
  "properties": {
    "iso:country":"US",
    "sg:address":"280 Thimbleberry Rd",
    "sg:city":"Ballston Spa",
    "sg:classifiers":[
        {
            "category":"Professional",
            "subcategory":"Computer Services",
            "type":"Services"
        }
    ],
    "sg:phone":"+1 518 899 5855",
    "sg:postcode":"12020",
    "sg:province":"NY",
    "sg:tags":[
        "internet"
    ],
    "wof:name":"Ward Design Solutions",
    "wof:placetype":"venue"
},
  "geometry": {"coordinates":[-73.765761,42.979731],"type":"Point"}
}