{
  "type": "Feature",
  "properties": {
    "addr:full":"2242 Merrick Rd Merrick NY 11566",
    "addr:housenumber":"2242",
    "addr:postcode":"11566",
    "addr:street":"Merrick Rd",
    "iso:country":"US",
    "sg:address":"2242 Merrick Rd",
    "sg:city":"Merrick",
    "sg:classifiers":[
        {
            "category":"Retail",
            "subcategory":"Auto Repair",
            "type":"Services"
        }
    ],
    "sg:phone":"+1 516 378 4990",
    "sg:postcode":"11566",
    "sg:province":"NY",
    "sg:tags":[
        "transmission",
        "automatic"
    ],
    "wof:name":"Dial Transmissions Inc",
    "wof:placetype":"venue"
},
  "geometry": {"coordinates":[-73.54234599999999,40.659697],"type":"Point"}
}