{
  "type": "Feature",
  "properties": {
    "addr:full":"155 Bette Rd East Meadow NY 11554",
    "addr:housenumber":"155",
    "addr:postcode":"11554",
    "addr:street":"Bette Rd",
    "iso:country":"US",
    "sg:address":"155 Bette Rd",
    "sg:city":"East Meadow",
    "sg:classifiers":[
        {
            "category":"Building & Trades",
            "subcategory":"Construction",
            "type":"Services"
        }
    ],
    "sg:phone":"+1 516 520 3175",
    "sg:postcode":"11554",
    "sg:province":"NY",
    "sg:tags":[
        "contractor"
    ],
    "wof:name":"Acme Renovations Inc",
    "wof:placetype":"venue"
},
  "geometry": {"coordinates":[-73.54749,40.729377],"type":"Point"}
}