{
  "type": "Feature",
  "properties": {
    "iso:country":"US",
    "sg:address":"445 Main St",
    "sg:city":"Schoharie",
    "sg:classifiers":[
        {
            "category":"Home & Garden",
            "subcategory":"Garden Supply",
            "type":"Retail Goods"
        }
    ],
    "sg:phone":"+1 518 295 8166",
    "sg:postcode":"12157",
    "sg:province":"NY",
    "sg:tags":[
        "equipment",
        "lawn",
        "landscaping",
        "mower"
    ],
    "wof:name":"Picture Perfect Lawn & Landscape Supply",
    "wof:placetype":"venue"
},
  "geometry": {"coordinates":[-74.30461099999999,42.674179],"type":"Point"}
}