{
  "type": "Feature",
  "properties": {
    "addr:full":"28 Harwood Ct Scarsdale NY 10583",
    "addr:housenumber":"28",
    "addr:postcode":"10583",
    "addr:street":"Harwood Ct",
    "iso:country":"US",
    "sg:address":"28 Harwood Ct",
    "sg:city":"Scarsdale",
    "sg:classifiers":[
        {
            "category":"Shopping",
            "subcategory":"Jewelry",
            "type":"Retail Goods"
        }
    ],
    "sg:phone":"+1   ",
    "sg:postcode":"10583",
    "sg:province":"NY",
    "wof:name":"Sam Pazzam Lehr",
    "wof:placetype":"venue"
},
  "geometry": {"coordinates":[-73.80726300000001,40.989127],"type":"Point"}
}