{
  "type": "Feature",
  "properties": {
    "iso:country":"US",
    "sg:address":"15 Broad St W",
    "sg:city":"Mount Vernon",
    "sg:classifiers":[
        {
            "category":"Government",
            "subcategory":"Office",
            "type":"Public Place"
        }
    ],
    "sg:phone":"+1 914 699 1153",
    "sg:postcode":"10552",
    "sg:province":"NY",
    "sg:tags":[
        "social"
    ],
    "wof:name":"Bronx Westchstr Comm Aware",
    "wof:placetype":"venue"
},
  "geometry": {"coordinates":[-73.83721300000001,40.926306],"type":"Point"}
}