{
  "type": "Feature",
  "properties": {
    "addr:full":"3072 Brighton 1st St Brooklyn NY 11235",
    "addr:housenumber":"3072",
    "addr:postcode":"11235",
    "addr:street":"Brighton 1St St",
    "iso:country":"US",
    "sg:address":"3072 Brighton 1st St",
    "sg:city":"Brooklyn",
    "sg:classifiers":[
        {
            "category":"Real Estate",
            "subcategory":"Real Estate Agent",
            "type":"Services"
        }
    ],
    "sg:phone":"+1 718 946 7341",
    "sg:postcode":"11235",
    "sg:province":"NY",
    "wof:name":"Elbe Real Estate",
    "wof:placetype":"venue"
},
  "geometry": {"coordinates":[-73.96705300000001,40.576936],"type":"Point"}
}