{
  "type": "Feature",
  "properties": {
    "addr:full":"223 Oakwood Rd Huntington NY 11743",
    "addr:housenumber":"223",
    "addr:postcode":"11743",
    "addr:street":"Oakwood Rd",
    "iso:country":"US",
    "sg:address":"223 Oakwood Rd",
    "sg:city":"Huntington",
    "sg:classifiers":[
        {
            "category":"Home & Garden",
            "subcategory":"Garden Supply",
            "type":"Retail Goods"
        }
    ],
    "sg:phone":"+1 631 470 2249",
    "sg:postcode":"11743",
    "sg:province":"NY",
    "sg:tags":[
        "nursery",
        "gardening"
    ],
    "wof:name":"Old Mill Nursey",
    "wof:placetype":"venue"
},
  "geometry": {"coordinates":[-73.43226199999999,40.852334],"type":"Point"}
}