{
  "type": "Feature",
  "properties": {
    "iso:country":"US",
    "sg:address":"2027 3 Ave",
    "sg:city":"New York",
    "sg:classifiers":[
        {
            "category":"Health Services",
            "subcategory":"Doctor",
            "type":"Services"
        }
    ],
    "sg:phone":"+1 212 828 4200",
    "sg:postcode":"10029",
    "sg:province":"NY",
    "sg:tags":[
        "dentist"
    ],
    "wof:name":"East Side Dental Assoc",
    "wof:placetype":"venue"
},
  "geometry": {"coordinates":[-73.94882699999999,40.785881],"type":"Point"}
}