{
  "type": "Feature",
  "properties": {
    "addr:full":"352 E 119th St New York NY 10035",
    "addr:housenumber":"352",
    "addr:postcode":"10035",
    "addr:street":"E 119Th St",
    "iso:country":"US",
    "sg:address":"352 E 119th St",
    "sg:city":"New York",
    "sg:classifiers":[
        {
            "category":"Health Services",
            "subcategory":"Dentist",
            "type":"Services"
        }
    ],
    "sg:phone":"+1 212 876 9085",
    "sg:postcode":"10035",
    "sg:province":"NY",
    "wof:name":"Piltser Yakov",
    "wof:placetype":"venue"
},
  "geometry": {"coordinates":[-73.935097,40.798302],"type":"Point"}
}