{
  "type": "Feature",
  "properties": {
    "addr:full":"266 Ocean Ave Amityville NY 11701",
    "addr:housenumber":"266",
    "addr:postcode":"11701",
    "addr:street":"Ocean Ave",
    "iso:country":"US",
    "sg:address":"266 Ocean Ave",
    "sg:city":"Amityville",
    "sg:classifiers":[
        {
            "category":"Autos & Motor Vehicles",
            "subcategory":"Boat Sales",
            "type":"Retail Goods"
        }
    ],
    "sg:phone":"+1 631 691 7770",
    "sg:postcode":"11701",
    "sg:province":"NY",
    "sg:tags":[
        "equipment",
        "marine",
        "supply"
    ],
    "wof:name":"Trans Marine Assoc Inc",
    "wof:placetype":"venue"
},
  "geometry": {"coordinates":[-73.415092,40.662472],"type":"Point"}
}