{
  "type": "Feature",
  "properties": {
    "addr:full":"480 W Broadway New York NY 10012",
    "addr:housenumber":"480",
    "addr:postcode":"10012",
    "addr:street":"W Broadway",
    "iso:country":"US",
    "sg:address":"480 W Broadway",
    "sg:city":"New York",
    "sg:classifiers":[
        {
            "category":"Shopping",
            "subcategory":"Shoes",
            "type":"Retail Goods"
        }
    ],
    "sg:phone":"+1 212 420 8100",
    "sg:postcode":"10012",
    "sg:province":"NY",
    "sg:tags":[
        "handbag",
        "store"
    ],
    "wof:name":"Keito",
    "wof:placetype":"venue"
},
  "geometry": {"coordinates":[-74.00009900000001,40.726501],"type":"Point"}
}