{
  "type": "Feature",
  "properties": {
    "iso:country":"US",
    "sg:address":"5010 Campuswood Dr",
    "sg:city":"East Syracuse",
    "sg:classifiers":[
        {
            "category":"Banks & Credit Unions",
            "subcategory":"Bank",
            "type":"Services"
        }
    ],
    "sg:phone":"+1 315 433 9567",
    "sg:postcode":"13057",
    "sg:province":"NY",
    "sg:tags":[
        "personal",
        "institution"
    ],
    "wof:name":"Bank One National Assn Chicago",
    "wof:placetype":"venue"
},
  "geometry": {"coordinates":[-76.073514,43.09066],"type":"Point"}
}