{
  "type": "Feature",
  "properties": {
    "iso:country":"US",
    "sg:address":"6136 1st St",
    "sg:city":"Newfane",
    "sg:classifiers":[
        {
            "category":"Building & Trades",
            "subcategory":"Construction",
            "type":"Services"
        }
    ],
    "sg:phone":"+1 716 778 5499",
    "sg:postcode":"14108",
    "sg:province":"NY",
    "sg:tags":[
        "concrete",
        "contractor"
    ],
    "wof:name":"Hy-Tech Concrete",
    "wof:placetype":"venue"
},
  "geometry": {"coordinates":[-78.70220399999999,43.279155],"type":"Point"}
}