{
  "type": "Feature",
  "properties": {
    "iso:country":"US",
    "sg:address":"148 E Montauk Hwy",
    "sg:city":"Hampton Bays",
    "sg:classifiers":[
        {
            "category":"Professional",
            "subcategory":"Business Services",
            "type":"Services"
        }
    ],
    "sg:phone":"+1 631 285 1173",
    "sg:postcode":"11946",
    "sg:province":"NY",
    "sg:tags":[
        "drafting"
    ],
    "wof:name":"Draftec Consulting Group",
    "wof:placetype":"venue"
},
  "geometry": {"coordinates":[-72.500917,40.884954],"type":"Point"}
}