{
  "type": "Feature",
  "properties": {
    "addr:full":"1195 Broadway Hewlett NY 11557",
    "addr:housenumber":"1195",
    "addr:postcode":"11557",
    "addr:street":"Broadway",
    "iso:country":"US",
    "sg:address":"1195 Broadway",
    "sg:city":"Hewlett",
    "sg:classifiers":[
        {
            "category":"Shopping",
            "subcategory":"Jewelry",
            "type":"Retail Goods"
        },
        {
            "category":"Shopping",
            "subcategory":"Pawn Shop",
            "type":"Retail Goods"
        }
    ],
    "sg:phone":"+1 516 513 0830",
    "sg:postcode":"11557",
    "sg:province":"NY",
    "sg:website":"www.nygoldcashers.com/sell-gold-...",
    "wof:name":"The Gold Standard of Hewlett",
    "wof:placetype":"venue"
},
  "geometry": {"coordinates":[-73.70287399999999,40.636323],"type":"Point"}
}