{
  "type": "Feature",
  "properties": {
    "addr:full":"59 Meadow Glen Rd Northport NY 11768",
    "addr:housenumber":"59",
    "addr:postcode":"11768",
    "addr:street":"Meadow Glen Rd",
    "iso:country":"US",
    "sg:address":"59 Meadow Glen Rd",
    "sg:city":"Northport",
    "sg:classifiers":[
        {
            "category":"Communications",
            "subcategory":"Film & Video Production",
            "type":"Services"
        },
        {
            "category":"Communications",
            "subcategory":"Television Station",
            "type":"Services"
        }
    ],
    "sg:phone":"+1 631 232 2456",
    "sg:postcode":"11768",
    "sg:province":"NY",
    "sg:tags":[
        "companies-film",
        "producer",
        "tv",
        "program",
        "radio",
        "distributor"
    ],
    "wof:name":"Talentworks Inc",
    "wof:placetype":"venue"
},
  "geometry": {"coordinates":[-73.277641,40.891224],"type":"Point"}
}