{
  "type": "Feature",
  "properties": {
    "addr:full":"2100 Boston Post Rd Larchmont NY 10538",
    "addr:housenumber":"2100",
    "addr:postcode":"10538",
    "addr:street":"Boston Post Rd",
    "iso:country":"US",
    "sg:address":"2100 Boston Post Rd",
    "sg:city":"Larchmont",
    "sg:classifiers":[
        {
            "category":"Personal",
            "subcategory":"Beauty Salon",
            "type":"Services"
        }
    ],
    "sg:phone":"+1   ",
    "sg:postcode":"10538",
    "sg:province":"NY",
    "sg:tags":[
        "specializing",
        "hair",
        "toy",
        "hairdresser",
        "sh"
    ],
    "wof:name":"Fun Cuts",
    "wof:placetype":"venue"
},
  "geometry": {"coordinates":[-73.75140399999999,40.928719],"type":"Point"}
}