{
  "type": "Feature",
  "properties": {
    "iso:country":"US",
    "sg:address":"84 Lenox Ave",
    "sg:city":"Albany",
    "sg:classifiers":[
        {
            "category":"Manufacturing",
            "subcategory":"Tools & Machinery",
            "type":"Manufacturing & Wholesale Goods"
        }
    ],
    "sg:phone":"+1   ",
    "sg:postcode":"12203",
    "sg:province":"NY",
    "sg:tags":[
        "mfg",
        "industrial",
        "general"
    ],
    "wof:name":"JD Machine Design Associates",
    "wof:placetype":"venue"
},
  "geometry": {"coordinates":[-73.803703,42.666823],"type":"Point"}
}