{
  "type": "Feature",
  "properties": {
    "addr:full":"206 Barnes Rd Norwich NY 13815",
    "addr:housenumber":"206",
    "addr:postcode":"13815",
    "addr:street":"Barnes Rd",
    "iso:country":"US",
    "sg:address":"206 Barnes Rd",
    "sg:city":"Norwich",
    "sg:classifiers":[
        {
            "category":"Building & Trades",
            "subcategory":"Construction",
            "type":"Services"
        }
    ],
    "sg:phone":"+1 607 336 2051",
    "sg:postcode":"13815",
    "sg:province":"NY",
    "sg:tags":[
        "house",
        "carpentry",
        "contractor"
    ],
    "wof:name":"Bullthistle Timber Frame Inc",
    "wof:placetype":"venue"
},
  "geometry": {"coordinates":[-75.58147599999999,42.540442],"type":"Point"}
}