{
  "type": "Feature",
  "properties": {
    "iso:country":"US",
    "sg:address":"131 Middle Island Rd",
    "sg:city":"Medford",
    "sg:classifiers":[
        {
            "category":"Manufacturing",
            "subcategory":"Tools & Machinery",
            "type":"Manufacturing & Wholesale Goods"
        }
    ],
    "sg:phone":"+1   ",
    "sg:postcode":"11763",
    "sg:province":"NY",
    "sg:tags":[
        "machine",
        "parts",
        "mfg"
    ],
    "wof:name":"Mil-TEC International Inc",
    "wof:placetype":"venue"
},
  "geometry": {"coordinates":[-72.993059,40.832532],"type":"Point"}
}