{
  "type": "Feature",
  "properties": {
    "iso:country":"US",
    "sg:address":"451 Jewett Ave",
    "sg:city":"Staten Island",
    "sg:classifiers":[
        {
            "category":"Wholesale",
            "subcategory":"Hardware",
            "type":"Manufacturing & Wholesale Goods"
        },
        {
            "category":"Retail",
            "subcategory":"Repair Shop",
            "type":"Services"
        }
    ],
    "sg:phone":"+1 718 720 5820",
    "sg:postcode":"10302",
    "sg:province":"NY",
    "sg:tags":[
        "electric",
        "supply",
        "air",
        "parts",
        "conditioning",
        "motor"
    ],
    "wof:name":"Kerber & Sons Supply Co",
    "wof:placetype":"venue"
},
  "geometry": {"coordinates":[-74.13141,40.625874],"type":"Point"}
}