{
  "type": "Feature",
  "properties": {
    "addr:full":"237 W 238th St Bronx NY 10463",
    "addr:housenumber":"237",
    "addr:postcode":"10463",
    "addr:street":"W 238Th St",
    "iso:country":"US",
    "sg:address":"237 W 238th St",
    "sg:city":"Bronx",
    "sg:classifiers":[
        {
            "category":"Shopping",
            "subcategory":"Stationery & Office Supplies",
            "type":"Retail Goods"
        }
    ],
    "sg:phone":"+1 718 601 4837",
    "sg:postcode":"10463",
    "sg:province":"NY",
    "sg:tags":[
        "stationer"
    ],
    "wof:name":"R B & J Stationery",
    "wof:placetype":"venue"
},
  "geometry": {"coordinates":[-73.900082,40.884956],"type":"Point"}
}