{
  "type": "Feature",
  "properties": {
    "addr:full":"238 Adelphi St Brooklyn NY 11205",
    "addr:housenumber":"238",
    "addr:postcode":"11205",
    "addr:street":"Adelphi St",
    "iso:country":"US",
    "sg:address":"238 Adelphi St",
    "sg:city":"Brooklyn",
    "sg:classifiers":[
        {
            "category":"Building & Trades",
            "subcategory":"Cleaning & Sanitation",
            "type":"Services"
        }
    ],
    "sg:phone":"+1 718 622 8730",
    "sg:postcode":"11205",
    "sg:province":"NY",
    "sg:tags":[
        "window"
    ],
    "wof:name":"New York Finestra Two Inc.",
    "wof:placetype":"venue"
},
  "geometry": {"coordinates":[-73.971361,40.690566],"type":"Point"}
}