{
  "type": "Feature",
  "properties": {
    "iso:country":"US",
    "sg:address":"42 Maxon St",
    "sg:city":"Brockport",
    "sg:classifiers":[
        {
            "category":"Building & Trades",
            "subcategory":"Plumbing",
            "type":"Services"
        }
    ],
    "sg:phone":"+1 585 637 8265",
    "sg:postcode":"14420",
    "sg:province":"NY",
    "sg:tags":[
        "plumbing",
        "contractor"
    ],
    "wof:name":"Giff Mosher & Son",
    "wof:placetype":"venue"
},
  "geometry": {"coordinates":[-77.944086,43.210099],"type":"Point"}
}