{
  "type": "Feature",
  "properties": {
    "addr:full":"7 Maple Brook Ln New Paltz NY 12561",
    "addr:housenumber":"7",
    "addr:postcode":"12561",
    "addr:street":"Maple Brook Ln",
    "iso:country":"US",
    "sg:address":"7 Maple Brook Ln",
    "sg:city":"New Paltz",
    "sg:classifiers":[
        {
            "category":"Banks & Credit Unions",
            "subcategory":"Investment Brokerage",
            "type":"Services"
        }
    ],
    "sg:phone":"+1 845 256 9755",
    "sg:postcode":"12561",
    "sg:province":"NY",
    "sg:tags":[
        "consultant",
        "planning",
        "financial"
    ],
    "wof:name":"Irene Berner Assoc",
    "wof:placetype":"venue"
},
  "geometry": {"coordinates":[-74.080626,41.702115],"type":"Point"}
}