{
  "type": "Feature",
  "properties": {
    "addr:full":"274 Mt Orange Rd Middletown NY 10973",
    "addr:housenumber":"274",
    "addr:postcode":"10973",
    "addr:street":"Mt Orange Rd",
    "iso:country":"US",
    "sg:address":"274 Mt Orange Rd",
    "sg:city":"Middletown",
    "sg:classifiers":[
        {
            "category":"Freight",
            "type":"Transportation"
        }
    ],
    "sg:phone":"+1   ",
    "sg:postcode":"10973",
    "sg:province":"NY",
    "sg:tags":[
        "company",
        "trucking"
    ],
    "wof:name":"Barker Trucking Inc",
    "wof:placetype":"venue"
},
  "geometry": {"coordinates":[-74.492276,41.405131],"type":"Point"}
}