{
  "type": "Feature",
  "properties": {
    "addr:full":"1616 Taylor Ave Bronx NY 10460",
    "addr:housenumber":"1616",
    "addr:postcode":"10460",
    "addr:street":"Taylor Ave",
    "iso:country":"US",
    "sg:address":"1616 Taylor Ave",
    "sg:city":"Bronx",
    "sg:classifiers":[
        {
            "category":"Building & Trades",
            "subcategory":"Plumbing",
            "type":"Services"
        },
        {
            "category":"Building & Trades",
            "subcategory":"Construction",
            "type":"Services"
        }
    ],
    "sg:phone":"+1 718 829 6900",
    "sg:postcode":"10460",
    "sg:province":"NY",
    "sg:tags":[
        "equipment",
        "systems-repairing",
        "contractor",
        "heating",
        "specialty"
    ],
    "wof:name":"Budget Plumbing Heating",
    "wof:placetype":"venue"
},
  "geometry": {"coordinates":[-73.867673,40.841303],"type":"Point"}
}