{
  "type": "Feature",
  "properties": {
    "addr:full":"4615 Livingston Ave Bronx NY 10471",
    "addr:housenumber":"4615",
    "addr:postcode":"10471",
    "addr:street":"Livingston Ave",
    "iso:country":"US",
    "sg:address":"4615 Livingston Ave",
    "sg:city":"Bronx",
    "sg:classifiers":[
        {
            "category":"Building & Trades",
            "subcategory":"Construction",
            "type":"Services"
        }
    ],
    "sg:phone":"+1 718 548 6400",
    "sg:postcode":"10471",
    "sg:province":"NY",
    "sg:tags":[
        "company"
    ],
    "wof:name":"Cibco Construction Corp",
    "wof:placetype":"venue"
},
  "geometry": {"coordinates":[-73.90348299999999,40.894311],"type":"Point"}
}