{
  "type": "Feature",
  "properties": {
    "iso:country":"US",
    "sg:address":"68 N 7th St",
    "sg:city":"Brooklyn",
    "sg:classifiers":[
        {
            "category":"Shopping",
            "subcategory":"Computers & Home Electronics",
            "type":"Retail Goods"
        }
    ],
    "sg:phone":"+1 718 963 1764",
    "sg:postcode":"11211",
    "sg:province":"NY",
    "wof:name":"Leeds Electronics",
    "wof:placetype":"venue"
},
  "geometry": {"coordinates":[-73.96118300000001,40.719981],"type":"Point"}
}