{
  "type": "Feature",
  "properties": {
    "addr:full":"2877 Carmen Rd Middleport NY 14105",
    "addr:housenumber":"2877",
    "addr:postcode":"14105",
    "addr:street":"Carmen Rd",
    "iso:country":"US",
    "sg:address":"2877 Carmen Rd",
    "sg:city":"Middleport",
    "sg:classifiers":[
        {
            "category":"Freight",
            "type":"Transportation"
        }
    ],
    "sg:phone":"+1   ",
    "sg:postcode":"14105",
    "sg:province":"NY",
    "sg:tags":[
        "operator",
        "trucking"
    ],
    "wof:name":"Upstate Express Trucking LLC",
    "wof:placetype":"venue"
},
  "geometry": {"coordinates":[-78.488783,43.26938],"type":"Point"}
}