{
  "type": "Feature",
  "properties": {
    "addr:full":"2369 60th Street Brooklyn NY 11204",
    "addr:housenumber":"2369",
    "addr:postcode":"11204",
    "addr:street":"60Th Street",
    "iso:country":"US",
    "sg:address":"2369 60th Street",
    "sg:city":"Brooklyn",
    "sg:classifiers":[
        {
            "category":"Restaurant",
            "type":"Food & Drink"
        }
    ],
    "sg:phone":"+1 718 339 9826",
    "sg:postcode":"11204",
    "sg:province":"NY",
    "wof:name":"Parkville Restrnt & Bar",
    "wof:placetype":"venue"
},
  "geometry": {"coordinates":[-73.974023,40.614162],"type":"Point"}
}