{
  "type": "Feature",
  "properties": {
    "addr:full":"1812 White Plains Rd Bronx NY 10462",
    "addr:housenumber":"1812",
    "addr:postcode":"10462",
    "addr:street":"White Plains Rd",
    "iso:country":"US",
    "sg:address":"1812 White Plains Rd",
    "sg:city":"Bronx",
    "sg:classifiers":[
        {
            "category":"Shopping",
            "subcategory":"Jewelry",
            "type":"Retail Goods"
        }
    ],
    "sg:phone":"+1 347 851 4182",
    "sg:postcode":"10462",
    "sg:province":"NY",
    "wof:name":"Jacobs Jewelers",
    "wof:placetype":"venue"
},
  "geometry": {"coordinates":[-73.86604,40.845546],"type":"Point"}
}