{
  "type": "Feature",
  "properties": {
    "addr:full":"179 Audubon Ave New York NY 10033",
    "addr:housenumber":"179",
    "addr:postcode":"10033",
    "addr:street":"Audubon Ave",
    "iso:country":"US",
    "sg:address":"179 Audubon Ave",
    "sg:city":"New York",
    "sg:classifiers":[
        {
            "category":"Restaurant",
            "type":"Food & Drink"
        }
    ],
    "sg:menulink":"http://www.allmenus.com/ny/new-york/48054-d-maritza-restaurant/menu/",
    "sg:phone":"+1 212 928 2342",
    "sg:postcode":"10033",
    "sg:province":"NY",
    "sg:tags":[
        "dominican"
    ],
    "wof:name":"D' Maritza Restaurant",
    "wof:placetype":"venue"
},
  "geometry": {"coordinates":[-73.935714,40.844117],"type":"Point"}
}