{
  "type": "Feature",
  "properties": {
    "iso:country":"US",
    "sg:address":"1312 Union Ave",
    "sg:city":"Newburgh",
    "sg:classifiers":[
        {
            "category":"Wholesale",
            "subcategory":"Electrical",
            "type":"Manufacturing & Wholesale Goods"
        }
    ],
    "sg:phone":"+1 845 566 5612",
    "sg:postcode":"12550",
    "sg:province":"NY",
    "sg:tags":[
        "communication",
        "radio",
        "system"
    ],
    "wof:name":"Bird Technologies Group",
    "wof:placetype":"venue"
},
  "geometry": {"coordinates":[-74.08176899999999,41.55411],"type":"Point"}
}