{
  "type": "Feature",
  "properties": {
    "iso:country":"US",
    "sg:address":"1008 Brown St",
    "sg:city":"Peekskill",
    "sg:classifiers":[
        {
            "category":"Arts & Performance",
            "subcategory":"Theater",
            "type":"Entertainment"
        }
    ],
    "sg:phone":"+1   ",
    "sg:postcode":"10566",
    "sg:province":"NY",
    "sg:tags":[
        "theatrical"
    ],
    "wof:name":"Paramount Ctr For Arts Box Off",
    "wof:placetype":"venue"
},
  "geometry": {"coordinates":[-73.919127,41.290035],"type":"Point"}
}