{
  "type": "Feature",
  "properties": {
    "addr:full":"9 General Heath Ave White Plains NY 10603",
    "addr:housenumber":"9",
    "addr:postcode":"10603",
    "addr:street":"General Heath Ave",
    "iso:country":"US",
    "sg:address":"9 General Heath Ave",
    "sg:city":"White Plains",
    "sg:classifiers":[
        {
            "category":"Retail",
            "subcategory":"Repair Shop",
            "type":"Services"
        }
    ],
    "sg:phone":"+1 914 684 0303",
    "sg:postcode":"10603",
    "sg:province":"NY",
    "sg:tags":[
        "machine",
        "washing"
    ],
    "wof:name":"Robert's Home Appliance Svc",
    "wof:placetype":"venue"
},
  "geometry": {"coordinates":[-73.76788999999999,41.055551],"type":"Point"}
}