{
  "type": "Feature",
  "properties": {
    "iso:country":"US",
    "sg:address":"46 Sunrise Hwy",
    "sg:city":"Lindenhurst",
    "sg:phone":"+1 631 957 1660",
    "sg:postcode":"11757",
    "sg:province":"NY",
    "wof:name":"Kirin China Restaurant",
    "wof:placetype":"venue"
},
  "geometry": {"coordinates":[-73.388226,40.695715],"type":"Point"}
}