{
  "type": "Feature",
  "properties": {
    "addr:full":"27 Indian Run East Quogue NY 11942",
    "addr:housenumber":"27",
    "addr:postcode":"11942",
    "addr:street":"Indian Run East",
    "iso:country":"US",
    "sg:address":"27 Indian Run",
    "sg:city":"East Quogue",
    "sg:classifiers":[
        {
            "category":"Building & Trades",
            "subcategory":"Construction",
            "type":"Services"
        }
    ],
    "sg:phone":"+1 631 653 4504",
    "sg:postcode":"11942",
    "sg:province":"NY",
    "sg:tags":[
        "general",
        "contractor"
    ],
    "wof:name":"Pat Mcchensey Construction",
    "wof:placetype":"venue"
},
  "geometry": {"coordinates":[-72.55167299999999,40.846227],"type":"Point"}
}