{
  "type": "Feature",
  "properties": {
    "iso:country":"US",
    "sg:address":"132 Fairview Ave",
    "sg:city":"Bayport",
    "sg:classifiers":[
        {
            "category":"Building & Trades",
            "subcategory":"Construction",
            "type":"Services"
        }
    ],
    "sg:phone":"+1 631 472 1550",
    "sg:postcode":"11705",
    "sg:province":"NY",
    "sg:tags":[
        "house"
    ],
    "wof:name":"Baratta Construction",
    "wof:placetype":"venue"
},
  "geometry": {"coordinates":[-73.046274,40.741172],"type":"Point"}
}