{
  "type": "Feature",
  "properties": {
    "iso:country":"US",
    "sg:address":"313 Hamilton St",
    "sg:city":"Geneva",
    "sg:classifiers":[
        {
            "category":"Restaurant",
            "type":"Food & Drink"
        }
    ],
    "sg:phone":"+1 315 789 5760",
    "sg:postcode":"14456",
    "sg:province":"NY",
    "wof:name":"Garcias Mexican Restaurant",
    "wof:placetype":"venue"
},
  "geometry": {"coordinates":[-76.993937,42.858867],"type":"Point"}
}