{
  "type": "Feature",
  "properties": {
    "addr:full":"35 W 34th Street New York NY 10001",
    "addr:housenumber":"35",
    "addr:postcode":"10001",
    "addr:street":"W 34Th Street",
    "iso:country":"US",
    "sg:address":"35 W 34th Street",
    "sg:city":"New York",
    "sg:classifiers":[
        {
            "category":"Shopping",
            "subcategory":"Clothing, Apparel, & Fashions",
            "type":"Retail Goods"
        }
    ],
    "sg:phone":"+1 212 244 8926",
    "sg:postcode":"10001",
    "sg:province":"NY",
    "sg:tags":[
        "clothing",
        "women's"
    ],
    "wof:name":"Ann Taylor Loft",
    "wof:placetype":"venue"
},
  "geometry": {"coordinates":[-73.98703399999999,40.749354],"type":"Point"}
}