{
  "type": "Feature",
  "properties": {
    "iso:country":"US",
    "sg:address":"10 Memorial Hwy",
    "sg:city":"New Rochelle",
    "sg:classifiers":[
        {
            "category":"Health Services",
            "subcategory":"Podiatrist",
            "type":"Services"
        }
    ],
    "sg:phone":"+1 914 632 2067",
    "sg:postcode":"10801",
    "sg:province":"NY",
    "wof:name":"Martin R Scherr DPM",
    "wof:placetype":"venue"
},
  "geometry": {"coordinates":[-73.783355,40.909826],"type":"Point"}
}