{
  "type": "Feature",
  "properties": {
    "addr:full":"8754 Bay Pkwy Brooklyn NY 11214",
    "addr:housenumber":"8754",
    "addr:postcode":"11214",
    "addr:street":"Bay Pkwy",
    "iso:country":"US",
    "sg:address":"8754 Bay Pkwy",
    "sg:city":"Brooklyn",
    "sg:classifiers":[
        {
            "category":"Health Services",
            "subcategory":"Health Practitioner",
            "type":"Services"
        }
    ],
    "sg:phone":"+1 718 232 3955",
    "sg:postcode":"11214",
    "sg:province":"NY",
    "sg:tags":[
        "therapist",
        "physical"
    ],
    "wof:name":"Quality Medical",
    "wof:placetype":"venue"
},
  "geometry": {"coordinates":[-73.99630000000001,40.599992],"type":"Point"}
}