{
  "type": "Feature",
  "properties": {
    "addr:full":"7453 Morgan Rd Liverpool NY 13090",
    "addr:housenumber":"7453",
    "addr:postcode":"13090",
    "addr:street":"Morgan Rd",
    "iso:country":"US",
    "sg:address":"7453 Morgan Rd",
    "sg:city":"Liverpool",
    "sg:classifiers":[
        {
            "category":"Professional",
            "subcategory":"Accounting & Tax Preparation",
            "type":"Services"
        }
    ],
    "sg:phone":"+1 315 701 1120",
    "sg:postcode":"13090",
    "sg:province":"NY",
    "sg:tags":[
        "accountant"
    ],
    "wof:name":"Century Small Business Sltns",
    "wof:placetype":"venue"
},
  "geometry": {"coordinates":[-76.205777,43.126799],"type":"Point"}
}