{
  "type": "Feature",
  "properties": {
    "iso:country":"US",
    "sg:address":"1055 Ave of the Americas",
    "sg:city":"New York",
    "sg:classifiers":[
        {
            "category":"Home & Garden",
            "subcategory":"Hardware",
            "type":"Retail Goods"
        }
    ],
    "sg:phone":"+1 212 398 0025",
    "sg:postcode":"10018",
    "sg:province":"NY",
    "sg:tags":[
        "wholesale"
    ],
    "wof:name":"Central Hardware & Electric",
    "wof:placetype":"venue"
},
  "geometry": {"coordinates":[-73.985371,40.753108],"type":"Point"}
}