{
  "type": "Feature",
  "properties": {
    "iso:country":"US",
    "sg:address":"3996 Walden Ave",
    "sg:city":"Lancaster",
    "sg:classifiers":[
        {
            "category":"Health Services",
            "subcategory":"Dentist",
            "type":"Services"
        }
    ],
    "sg:phone":"+1 716 683 2001",
    "sg:postcode":"14086",
    "sg:province":"NY",
    "sg:tags":[
        "dentists-cosmetic",
        "denture",
        "dentists-prosthodontists",
        "dentists-pediatric",
        "dentists-endodontists",
        "dentistry"
    ],
    "sg:website":"http://www.stonydentalcare.com",
    "wof:name":"Stony Dental Care",
    "wof:placetype":"venue"
},
  "geometry": {"coordinates":[-78.64241800000001,42.920471],"type":"Point"}
}