{
  "type": "Feature",
  "properties": {
    "iso:country":"US",
    "sg:address":"11 Space Ct",
    "sg:city":"Islandia",
    "sg:classifiers":[
        {
            "category":"Wholesale",
            "subcategory":"Durable Goods & Equipment",
            "type":"Manufacturing & Wholesale Goods"
        }
    ],
    "sg:phone":"+1 631 582 5508",
    "sg:postcode":"11749",
    "sg:province":"NY",
    "sg:tags":[
        "importer"
    ],
    "wof:name":"Best Vast Imports",
    "wof:placetype":"venue"
},
  "geometry": {"coordinates":[-73.188098,40.806588],"type":"Point"}
}