{
  "type": "Feature",
  "properties": {
    "addr:full":"8221 Henry Clay Blvd Clay NY 13041",
    "addr:housenumber":"8221",
    "addr:postcode":"13041",
    "addr:street":"Henry Clay Blvd",
    "iso:country":"US",
    "sg:address":"8221 Henry Clay Blvd",
    "sg:city":"Clay",
    "sg:classifiers":[
        {
            "category":"Building & Trades",
            "subcategory":"Landscaping Services",
            "type":"Services"
        }
    ],
    "sg:phone":"+1 315 622 0908",
    "sg:postcode":"13041",
    "sg:province":"NY",
    "sg:tags":[
        "landscape",
        "contractor"
    ],
    "wof:name":"Valley Grove Landscape",
    "wof:placetype":"venue"
},
  "geometry": {"coordinates":[-76.197986,43.171046],"type":"Point"}
}