{
  "type": "Feature",
  "properties": {
    "addr:full":"24 Westwood Dr Brockport NY 14420",
    "addr:housenumber":"24",
    "addr:postcode":"14420",
    "addr:street":"Westwood Dr",
    "iso:country":"US",
    "sg:address":"24 Westwood Dr",
    "sg:city":"Brockport",
    "sg:classifiers":[
        {
            "category":"Retail",
            "subcategory":"Repair Shop",
            "type":"Services"
        }
    ],
    "sg:phone":"+1 585 637 4790",
    "sg:postcode":"14420",
    "sg:province":"NY",
    "sg:tags":[
        "lock",
        "locksmith"
    ],
    "wof:name":"Bill's Mobile Lock Svc",
    "wof:placetype":"venue"
},
  "geometry": {"coordinates":[-77.923548,43.217584],"type":"Point"}
}