{
  "type": "Feature",
  "properties": {
    "addr:full":"2312 Loring Pl N Bronx NY 10468",
    "addr:housenumber":"2312",
    "addr:postcode":"10468",
    "addr:street":"Loring Pl N",
    "iso:country":"US",
    "sg:address":"2312 Loring Pl N",
    "sg:city":"Bronx",
    "sg:classifiers":[
        {
            "category":"Real Estate",
            "subcategory":"Real Estate Agent",
            "type":"Services"
        }
    ],
    "sg:phone":"+1 718 733 6804",
    "sg:postcode":"10468",
    "sg:province":"NY",
    "wof:name":"1678 Karyas Realty Corp",
    "wof:placetype":"venue"
},
  "geometry": {"coordinates":[-73.90858,40.860918],"type":"Point"}
}