{
  "type": "Feature",
  "properties": {
    "addr:full":"537 W State St Ithaca NY 14850",
    "addr:housenumber":"537",
    "addr:postcode":"14850",
    "addr:street":"W State St",
    "iso:country":"US",
    "sg:address":"537 W State St",
    "sg:city":"Ithaca",
    "sg:classifiers":[
        {
            "category":"Manufacturing",
            "subcategory":"Signs",
            "type":"Manufacturing & Wholesale Goods"
        }
    ],
    "sg:phone":"+1   ",
    "sg:postcode":"14850",
    "sg:province":"NY",
    "sg:tags":[
        "advertising",
        "specialty"
    ],
    "sg:website":"www.signarama.com",
    "wof:name":"Sign-A-Rama",
    "wof:placetype":"venue"
},
  "geometry": {"coordinates":[-76.50672900000001,42.439223],"type":"Point"}
}