{
  "type": "Feature",
  "properties": {
    "iso:country":"US",
    "sg:address":"22 E Mountain Rd",
    "sg:city":"Grahamsville",
    "sg:classifiers":[
        {
            "category":"Building & Trades",
            "subcategory":"Construction",
            "type":"Services"
        }
    ],
    "sg:phone":"+1 845 985 7002",
    "sg:postcode":"12740",
    "sg:province":"NY",
    "sg:tags":[
        "product",
        "asphalt"
    ],
    "wof:name":"Shortlines Coatings",
    "wof:placetype":"venue"
},
  "geometry": {"coordinates":[-74.47354199999999,41.864506],"type":"Point"}
}