{
  "type": "Feature",
  "properties": {
    "iso:country":"US",
    "sg:address":"170 Concord Rd",
    "sg:city":"Yonkers",
    "sg:classifiers":[
        {
            "category":"Organizations",
            "subcategory":"Membership Organization",
            "type":"Services"
        }
    ],
    "sg:phone":"+1   ",
    "sg:postcode":"10710",
    "sg:province":"NY",
    "wof:name":"Jewish War Vets of USA",
    "wof:placetype":"venue"
},
  "geometry": {"coordinates":[-73.838189,40.973795],"type":"Point"}
}