{
  "type": "Feature",
  "properties": {
    "iso:country":"US",
    "sg:address":"201 Main St",
    "sg:city":"Vestal",
    "sg:classifiers":[
        {
            "category":"Education",
            "subcategory":"Dance Studio",
            "type":"Public Place"
        }
    ],
    "sg:phone":"+1 607 785 2553",
    "sg:postcode":"13850",
    "sg:province":"NY",
    "sg:tags":[
        "instruction",
        "dancing"
    ],
    "wof:name":"Dance Shoppe",
    "wof:placetype":"venue"
},
  "geometry": {"coordinates":[-76.053449,42.085553],"type":"Point"}
}