{
  "type": "Feature",
  "properties": {
    "iso:country":"US",
    "sg:address":"5 Windsor Rd",
    "sg:city":"Salisbury Mills",
    "sg:classifiers":[
        {
            "category":"Building & Trades",
            "subcategory":"Landscaping Services",
            "type":"Services"
        }
    ],
    "sg:phone":"+1 845 496 6064",
    "sg:postcode":"12577",
    "sg:province":"NY",
    "sg:tags":[
        "lawn",
        "care",
        "garden",
        "maintenance",
        "grounds"
    ],
    "wof:name":"Grass Cutters Plus",
    "wof:placetype":"venue"
},
  "geometry": {"coordinates":[-74.121129,41.448112],"type":"Point"}
}