{
  "type": "Feature",
  "properties": {
    "iso:country":"US",
    "sg:address":"715 Burke Ave",
    "sg:city":"Bronx",
    "sg:classifiers":[
        {
            "category":"Utilities",
            "subcategory":"Mobile Phone",
            "type":"Services"
        }
    ],
    "sg:phone":"+1 718 654 4659",
    "sg:postcode":"10467",
    "sg:province":"NY",
    "sg:tags":[
        "telephone",
        "cellular"
    ],
    "wof:name":"Next Generation Cell Phone",
    "wof:placetype":"venue"
},
  "geometry": {"coordinates":[-73.86673999999999,40.871512],"type":"Point"}
}