{
  "type": "Feature",
  "properties": {
    "iso:country":"US",
    "sg:address":"1187 Sunrise Hwy",
    "sg:city":"Copiague",
    "sg:classifiers":[
        {
            "category":"Wholesale",
            "subcategory":"Auto Parts",
            "type":"Manufacturing & Wholesale Goods"
        }
    ],
    "sg:phone":"+1 631 842 0220",
    "sg:postcode":"11726",
    "sg:province":"NY",
    "sg:tags":[
        "supply"
    ],
    "wof:name":"NAPA Auto Parts",
    "wof:placetype":"venue"
},
  "geometry": {"coordinates":[-73.402204,40.690881],"type":"Point"}
}