{
  "type": "Feature",
  "properties": {
    "iso:country":"US",
    "sg:address":"312 Main St",
    "sg:city":"Huntington",
    "sg:classifiers":[
        {
            "category":"Wholesale",
            "subcategory":"Sporting Goods",
            "type":"Manufacturing & Wholesale Goods"
        }
    ],
    "sg:phone":"+1 631 271 4131",
    "sg:postcode":"11743",
    "sg:province":"NY",
    "wof:name":"Alesis Import Inc",
    "wof:placetype":"venue"
},
  "geometry": {"coordinates":[-73.429802,40.870804],"type":"Point"}
}