{
  "type": "Feature",
  "properties": {
    "iso:country":"US",
    "sg:address":"75 N Main St",
    "sg:city":"Wellsville",
    "sg:classifiers":[
        {
            "category":"Professional",
            "subcategory":"Computer Services",
            "type":"Services"
        }
    ],
    "sg:phone":"+1 585 593 5311",
    "sg:postcode":"14895",
    "sg:province":"NY",
    "sg:tags":[
        "repair"
    ],
    "wof:name":"Computer Solutions",
    "wof:placetype":"venue"
},
  "geometry": {"coordinates":[-77.946995,42.121167],"type":"Point"}
}