{
  "type": "Feature",
  "properties": {
    "addr:full":"7 Columbia Dr East Greenbush NY 12061",
    "addr:housenumber":"7",
    "addr:postcode":"12061",
    "addr:street":"Columbia Dr",
    "iso:country":"US",
    "sg:address":"7 Columbia Dr",
    "sg:city":"East Greenbush",
    "sg:classifiers":[
        {
            "category":"Professional",
            "subcategory":"Detective & Security Services",
            "type":"Services"
        }
    ],
    "sg:phone":"+1   ",
    "sg:postcode":"12061",
    "sg:province":"NY",
    "sg:tags":[
        "car"
    ],
    "wof:name":"Blue Line Investigative Svc",
    "wof:placetype":"venue"
},
  "geometry": {"coordinates":[-73.705675,42.610893],"type":"Point"}
}