{
  "type": "Feature",
  "properties": {
    "addr:full":"88 Pine St New York NY 10005",
    "addr:housenumber":"88",
    "addr:postcode":"10005",
    "addr:street":"Pine St",
    "iso:country":"US",
    "sg:address":"88 Pine St",
    "sg:city":"New York",
    "sg:classifiers":[
        {
            "category":"Banks & Credit Unions",
            "subcategory":"Investment Brokerage",
            "type":"Services"
        }
    ],
    "sg:phone":"+1 212 482 0047",
    "sg:postcode":"10005",
    "sg:province":"NY",
    "sg:tags":[
        "index",
        "for",
        "creator",
        "researcher",
        "o",
        "bond"
    ],
    "wof:name":"Ryan Labs Inc",
    "wof:placetype":"venue"
},
  "geometry": {"coordinates":[-74.006766,40.705624],"type":"Point"}
}