{
  "type": "Feature",
  "properties": {
    "addr:full":"10606 Queens Boulevard Forest Hills NY 11375",
    "addr:housenumber":"10606",
    "addr:postcode":"11375",
    "addr:street":"Queens Boulevard",
    "iso:country":"US",
    "sg:address":"10606 Queens Boulevard",
    "sg:city":"Forest Hills",
    "sg:classifiers":[
        {
            "category":"Professional",
            "type":"Services"
        }
    ],
    "sg:phone":"+1 212 889 5541",
    "sg:postcode":"11375",
    "sg:province":"NY",
    "sg:tags":[
        "caterer"
    ],
    "wof:name":"Galleria Custom Caterers",
    "wof:placetype":"venue"
},
  "geometry": {"coordinates":[-73.84759099999999,40.722099],"type":"Point"}
}