{
  "type": "Feature",
  "properties": {
    "iso:country":"US",
    "sg:address":"34 State St",
    "sg:city":"Pittsford",
    "sg:classifiers":[
        {
            "category":"Professional",
            "subcategory":"Management & Consulting",
            "type":"Services"
        }
    ],
    "sg:phone":"+1 585 385 0550",
    "sg:postcode":"14534",
    "sg:province":"NY",
    "sg:tags":[
        "consultant",
        "business"
    ],
    "wof:name":"Michael Piston & Assoc Inc",
    "wof:placetype":"venue"
},
  "geometry": {"coordinates":[-77.512046,43.089859],"type":"Point"}
}