{
  "type": "Feature",
  "properties": {
    "iso:country":"US",
    "sg:address":"1762 Black River Blvd N",
    "sg:city":"Rome",
    "sg:classifiers":[
        {
            "category":"Shopping",
            "subcategory":"Shoes",
            "type":"Retail Goods"
        }
    ],
    "sg:phone":"+1 315 336 8475",
    "sg:postcode":"13440",
    "sg:province":"NY",
    "wof:name":"Payless Shoe Source",
    "wof:placetype":"venue"
},
  "geometry": {"coordinates":[-75.436048,43.237838],"type":"Point"}
}