{
  "type": "Feature",
  "properties": {
    "iso:country":"US",
    "sg:address":"300 W Broadway",
    "sg:city":"New York",
    "sg:classifiers":[
        {
            "category":"Shopping",
            "subcategory":"Crafts & Fabrics",
            "type":"Retail Goods"
        }
    ],
    "sg:phone":"+1 212 343 2557",
    "sg:postcode":"10013",
    "sg:province":"NY",
    "sg:tags":[
        "art"
    ],
    "wof:name":"Scrap Yard Inc",
    "wof:placetype":"venue"
},
  "geometry": {"coordinates":[-74.004628,40.721389],"type":"Point"}
}