{
  "type": "Feature",
  "properties": {
    "addr:full":"2 Renwick St Newburgh NY 12550",
    "addr:housenumber":"2",
    "addr:postcode":"12550",
    "addr:street":"Renwick St",
    "iso:country":"US",
    "sg:address":"2 Renwick St",
    "sg:city":"Newburgh",
    "sg:classifiers":[
        {
            "category":"Building & Trades",
            "subcategory":"Construction",
            "type":"Services"
        }
    ],
    "sg:phone":"+1 845 565 9235",
    "sg:postcode":"12550",
    "sg:province":"NY",
    "sg:tags":[
        "general",
        "contractor"
    ],
    "wof:name":"Tensco Construction Co LLC",
    "wof:placetype":"venue"
},
  "geometry": {"coordinates":[-74.00850699999999,41.494261],"type":"Point"}
}