{
  "type": "Feature",
  "properties": {
    "iso:country":"US",
    "sg:address":"1114 Ave of the Americas",
    "sg:city":"New York",
    "sg:classifiers":[
        {
            "category":"Utilities",
            "subcategory":"Cable",
            "type":"Services"
        }
    ],
    "sg:phone":"+1   ",
    "sg:postcode":"10036",
    "sg:province":"NY",
    "sg:tags":[
        "television"
    ],
    "wof:name":"Cable Network Services",
    "wof:placetype":"venue"
},
  "geometry": {"coordinates":[-73.983886,40.75489],"type":"Point"}
}