{
  "type": "Feature",
  "properties": {
    "iso:country":"US",
    "sg:address":"12 Leslie Ct",
    "sg:city":"Loudonville",
    "sg:classifiers":[
        {
            "category":"Building & Trades",
            "subcategory":"Construction",
            "type":"Services"
        }
    ],
    "sg:phone":"+1 518 436 1876",
    "sg:postcode":"12211",
    "sg:province":"NY",
    "sg:tags":[
        "roofing",
        "contractor"
    ],
    "wof:name":"Rg Green Roofing",
    "wof:placetype":"venue"
},
  "geometry": {"coordinates":[-73.757186,42.692295],"type":"Point"}
}