{
  "type": "Feature",
  "properties": {
    "addr:full":"4016 State Hwy 40 Argyle NY 12809",
    "addr:housenumber":"4016",
    "addr:postcode":"12809",
    "addr:street":"State Hwy 40",
    "iso:country":"US",
    "sg:address":"4016 State Hwy 40",
    "sg:city":"Argyle",
    "sg:classifiers":[
        {
            "category":"Restaurant",
            "type":"Food & Drink"
        }
    ],
    "sg:phone":"+1 518 638 6003",
    "sg:postcode":"12809",
    "sg:province":"NY",
    "wof:name":"Auction Barn Restaurant",
    "wof:placetype":"venue"
},
  "geometry": {"coordinates":[-73.50273199999999,43.165904],"type":"Point"}
}