{
  "type": "Feature",
  "properties": {
    "iso:country":"US",
    "sg:address":"547 Sissonville Rd",
    "sg:city":"Potsdam",
    "sg:classifiers":[
        {
            "category":"Manufacturing",
            "subcategory":"Paper Products",
            "type":"Manufacturing & Wholesale Goods"
        }
    ],
    "sg:phone":"+1 315 265 4000",
    "sg:postcode":"13676",
    "sg:province":"NY",
    "sg:tags":[
        "mill",
        "mfg"
    ],
    "wof:name":"Mead Westvaco Specialty Paper",
    "wof:placetype":"venue"
},
  "geometry": {"coordinates":[-74.993394,44.713809],"type":"Point"}
}