{
  "type": "Feature",
  "properties": {
    "addr:full":"9 Cherry St Potsdam NY 13676",
    "addr:housenumber":"9",
    "addr:postcode":"13676",
    "addr:street":"Cherry St",
    "iso:country":"US",
    "sg:address":"9 Cherry St",
    "sg:city":"Potsdam",
    "sg:classifiers":[
        {
            "category":"Government",
            "subcategory":"Fire Station",
            "type":"Public Place"
        }
    ],
    "sg:phone":"+1 315 265 1570",
    "sg:postcode":"13676",
    "sg:province":"NY",
    "sg:tags":[
        "protection"
    ],
    "wof:name":"Raquette River Volunteer Fire",
    "wof:placetype":"venue"
},
  "geometry": {"coordinates":[-74.99112,44.678019],"type":"Point"}
}