{
  "type": "Feature",
  "properties": {
    "iso:country":"US",
    "sg:address":"89 Pirog Rd",
    "sg:city":"Pine Bush",
    "sg:classifiers":[
        {
            "category":"Building & Trades",
            "subcategory":"Construction",
            "type":"Services"
        }
    ],
    "sg:phone":"+1 845 744 5737",
    "sg:postcode":"12566",
    "sg:province":"NY",
    "sg:tags":[
        "house"
    ],
    "wof:name":"Pinebush Construction",
    "wof:placetype":"venue"
},
  "geometry": {"coordinates":[-74.320989,41.612104],"type":"Point"}
}