{
  "type": "Feature",
  "properties": {
    "addr:full":"90 Gibson Blvd Valley Stream NY 11581",
    "addr:housenumber":"90",
    "addr:postcode":"11581",
    "addr:street":"Gibson Blvd",
    "iso:country":"US",
    "sg:address":"90 Gibson Blvd",
    "sg:city":"Valley Stream",
    "sg:classifiers":[
        {
            "category":"Autos & Motor Vehicles",
            "subcategory":"Fuel & Gas Station",
            "type":"Retail Goods"
        }
    ],
    "sg:phone":"+1 516 791 0985",
    "sg:postcode":"11581",
    "sg:province":"NY",
    "wof:name":"Kkg Auto Inc",
    "wof:placetype":"venue"
},
  "geometry": {"coordinates":[-73.701103,40.649899],"type":"Point"}
}