{
  "type": "Feature",
  "properties": {
    "addr:full":"10 W 47 St New York NY 10036",
    "addr:housenumber":"10",
    "addr:postcode":"10036",
    "addr:street":"W 47 St",
    "iso:country":"US",
    "sg:address":"10 W 47 St",
    "sg:city":"New York",
    "sg:classifiers":[
        {
            "category":"Wholesale",
            "subcategory":"Jewelry",
            "type":"Manufacturing & Wholesale Goods"
        }
    ],
    "sg:phone":"+1 212 391 2902",
    "sg:postcode":"10036",
    "sg:province":"NY",
    "sg:tags":[
        "diamond",
        "jeweler"
    ],
    "wof:name":"Marco Kalisch Imports",
    "wof:placetype":"venue"
},
  "geometry": {"coordinates":[-73.981627,40.757842],"type":"Point"}
}