{
  "type": "Feature",
  "properties": {
    "iso:country":"US",
    "sg:address":"287 Skidmores Rd",
    "sg:city":"Deer Park",
    "sg:classifiers":[
        {
            "category":"Building & Trades",
            "subcategory":"Landscaping Services",
            "type":"Services"
        }
    ],
    "sg:phone":"+1 631 667 6548",
    "sg:postcode":"11729",
    "sg:province":"NY",
    "sg:tags":[
        "landscape",
        "contractor"
    ],
    "wof:name":"Custom Lawn Svc Inc",
    "wof:placetype":"venue"
},
  "geometry": {"coordinates":[-73.311795,40.745769],"type":"Point"}
}