{
  "type": "Feature",
  "properties": {
    "iso:country":"US",
    "sg:address":"26 Hillside Rd",
    "sg:city":"Larchmont",
    "sg:classifiers":[
        {
            "category":"Professional",
            "type":"Services"
        }
    ],
    "sg:phone":"+1   ",
    "sg:postcode":"10538",
    "sg:province":"NY",
    "wof:name":"Zeldis & Co Inc",
    "wof:placetype":"venue"
},
  "geometry": {"coordinates":[-73.76291500000001,40.937243],"type":"Point"}
}