{
  "type": "Feature",
  "properties": {
    "addr:full":"220 White Plains Rd Tarrytown NY 10591",
    "addr:housenumber":"220",
    "addr:postcode":"10591",
    "addr:street":"White Plains Rd",
    "iso:country":"US",
    "sg:address":"220 White Plains Rd",
    "sg:city":"Tarrytown",
    "sg:classifiers":[
        {
            "category":"Professional",
            "subcategory":"Management & Consulting",
            "type":"Services"
        }
    ],
    "sg:phone":"+1 914 524 8316",
    "sg:postcode":"10591",
    "sg:province":"NY",
    "sg:tags":[
        "consultant",
        "business"
    ],
    "sg:website":"www.bv.com",
    "wof:name":"Black & Veatch",
    "wof:placetype":"venue"
},
  "geometry": {"coordinates":[-73.844323,41.06326],"type":"Point"}
}