{
  "type": "Feature",
  "properties": {
    "addr:full":"151 Industrial Loop Staten Island NY 10309",
    "addr:housenumber":"151",
    "addr:postcode":"10309",
    "addr:street":"Industrial Loop",
    "iso:country":"US",
    "sg:address":"151 Industrial Loop",
    "sg:city":"Staten Island",
    "sg:classifiers":[
        {
            "category":"Wholesale",
            "subcategory":"Electrical",
            "type":"Manufacturing & Wholesale Goods"
        }
    ],
    "sg:phone":"+1 718 667 6166",
    "sg:postcode":"10309",
    "sg:province":"NY",
    "sg:tags":[
        "fire",
        "alarm",
        "system"
    ],
    "wof:name":"Rhodes Security Systems Inc",
    "wof:placetype":"venue"
},
  "geometry": {"coordinates":[-74.229783,40.545969],"type":"Point"}
}