{
  "type": "Feature",
  "properties": {
    "iso:country":"US",
    "sg:address":"3 Twinkle Rd",
    "sg:city":"Airmont",
    "sg:classifiers":[
        {
            "category":"Manufacturing",
            "subcategory":"Tools & Machinery",
            "type":"Manufacturing & Wholesale Goods"
        }
    ],
    "sg:phone":"+1 845 368 2001",
    "sg:postcode":"10901",
    "sg:province":"NY",
    "sg:tags":[
        "physician",
        "surgeon"
    ],
    "wof:name":"MIM Forms",
    "wof:placetype":"venue"
},
  "geometry": {"coordinates":[-74.103887,41.103729],"type":"Point"}
}