{
  "type": "Feature",
  "properties": {
    "iso:country":"US",
    "sg:address":"5 Lakeside Rd",
    "sg:city":"Newburgh",
    "sg:classifiers":[
        {
            "category":"Travel",
            "subcategory":"Hotels & Motels",
            "type":"Entertainment"
        }
    ],
    "sg:phone":"+1 800 424 6423",
    "sg:postcode":"12550",
    "sg:province":"NY",
    "sg:website":"http://www.comfortinn.com/hotel-newburgh-new_york-NY110?promo=yplocal",
    "wof:name":"Comfort Inn Newburgh",
    "wof:placetype":"venue"
},
  "geometry": {"coordinates":[-74.11179199999999,41.521713],"type":"Point"}
}