{
  "type": "Feature",
  "properties": {
    "addr:full":"238 Bradford St Brooklyn NY 11207",
    "addr:housenumber":"238",
    "addr:postcode":"11207",
    "addr:street":"Bradford St",
    "iso:country":"US",
    "sg:address":"238 Bradford St",
    "sg:city":"Brooklyn",
    "sg:classifiers":[
        {
            "category":"Home & Garden",
            "subcategory":"Hardware",
            "type":"Retail Goods"
        }
    ],
    "sg:phone":"+1 646 393 5547",
    "sg:postcode":"11207",
    "sg:province":"NY",
    "sg:tags":[
        "store"
    ],
    "wof:name":"Hardware Brothers",
    "wof:placetype":"venue"
},
  "geometry": {"coordinates":[-73.892563,40.673389],"type":"Point"}
}