{
  "type": "Feature",
  "properties": {
    "addr:full":"4915 Bentbrook Dr Manlius NY 13104",
    "addr:postcode":"4915;13104",
    "addr:street":"Bentbrook Dr",
    "iso:country":"US",
    "sg:address":"4915 Bentbrook Dr",
    "sg:city":"Manlius",
    "sg:classifiers":[
        {
            "category":"Wholesale",
            "subcategory":"Non-durable Goods",
            "type":"Manufacturing & Wholesale Goods"
        }
    ],
    "sg:phone":"+1 315 727 2190",
    "sg:postcode":"13104",
    "sg:province":"NY",
    "wof:name":"Pakajis LLC",
    "wof:placetype":"venue"
},
  "geometry": {"coordinates":[-75.95220500000001,43.004214],"type":"Point"}
}