{
  "type": "Feature",
  "properties": {
    "addr:full":"25 E End Ave New York NY 10028",
    "addr:housenumber":"25",
    "addr:postcode":"10028",
    "addr:street":"E End Ave",
    "iso:country":"US",
    "sg:address":"25 E End Ave",
    "sg:city":"New York",
    "sg:classifiers":[
        {
            "category":"Real Estate",
            "subcategory":"Real Estate Agent",
            "type":"Services"
        }
    ],
    "sg:phone":"+1 212 650 1718",
    "sg:postcode":"10028",
    "sg:province":"NY",
    "sg:tags":[
        "management"
    ],
    "wof:name":"Fundamental Management Corp",
    "wof:placetype":"venue"
},
  "geometry": {"coordinates":[-73.947171,40.771465],"type":"Point"}
}