{
  "type": "Feature",
  "properties": {
    "addr:full":"121 Bolivar St Staten Island NY 10314",
    "addr:housenumber":"121",
    "addr:postcode":"10314",
    "addr:street":"Bolivar St",
    "iso:country":"US",
    "sg:address":"121 Bolivar St",
    "sg:city":"Staten Island",
    "sg:classifiers":[
        {
            "category":"Building & Trades",
            "subcategory":"Construction",
            "type":"Services"
        }
    ],
    "sg:phone":"+1 718 932 6300",
    "sg:postcode":"10314",
    "sg:province":"NY",
    "sg:tags":[
        "residential",
        "general",
        "contractor"
    ],
    "wof:name":"B C M Contracting Company",
    "wof:placetype":"venue"
},
  "geometry": {"coordinates":[-74.11737599999999,40.602624],"type":"Point"}
}