{
  "type": "Feature",
  "properties": {
    "iso:country":"US",
    "sg:address":"3 Coates Ave",
    "sg:city":"Holbrook",
    "sg:classifiers":[
        {
            "category":"Banks & Credit Unions",
            "subcategory":"Bank",
            "type":"Services"
        }
    ],
    "sg:phone":"+1 631 580 0598",
    "sg:postcode":"11741",
    "sg:province":"NY",
    "sg:tags":[
        "mortgage",
        "loan",
        "broker",
        "real estate"
    ],
    "sg:website":"www.empiremortgageassociates.com",
    "wof:name":"Empire Mortgage Associates LLC",
    "wof:placetype":"venue"
},
  "geometry": {"coordinates":[-73.08145500000001,40.811792],"type":"Point"}
}