{
  "type": "Feature",
  "properties": {
    "addr:full":"2911 Southwestern Blvd Orchard Park NY 14127",
    "addr:housenumber":"2911",
    "addr:postcode":"14127",
    "addr:street":"Southwestern Blvd",
    "iso:country":"US",
    "sg:address":"2911 Southwestern Blvd",
    "sg:city":"Orchard Park",
    "sg:classifiers":[
        {
            "category":"Autos & Motor Vehicles",
            "subcategory":"Automobile Sales",
            "type":"Retail Goods"
        }
    ],
    "sg:phone":"+1   ",
    "sg:postcode":"14127",
    "sg:province":"NY",
    "sg:tags":[
        "used"
    ],
    "wof:name":"CB Cars",
    "wof:placetype":"venue"
},
  "geometry": {"coordinates":[-78.722617,42.811193],"type":"Point"}
}