{
  "type": "Feature",
  "properties": {
    "addr:full":"2674 Erie Dr Weedsport NY 13166",
    "addr:housenumber":"2674",
    "addr:postcode":"13166",
    "addr:street":"Erie Dr",
    "iso:country":"US",
    "sg:address":"2674 Erie Dr",
    "sg:city":"Weedsport",
    "sg:classifiers":[
        {
            "category":"Professional",
            "subcategory":"Accounting & Tax Preparation",
            "type":"Services"
        },
        {
            "category":"Banks & Credit Unions",
            "subcategory":"Financial Services",
            "type":"Services"
        }
    ],
    "sg:phone":"+1 315 834 9056",
    "sg:postcode":"13166",
    "sg:province":"NY",
    "sg:tags":[
        "return",
        "preparation-business",
        "taxes-consultants",
        "loan",
        "reporting",
        "representative",
        "alternative",
        "bookkeeping"
    ],
    "sg:website":"http://www.hrblock.com",
    "wof:name":"H&R Block",
    "wof:placetype":"venue"
},
  "geometry": {"coordinates":[-76.56307700000001,43.04981],"type":"Point"}
}