{
  "type": "Feature",
  "properties": {
    "iso:country":"US",
    "sg:address":"120 Mildahn Rd",
    "sg:city":"Macedon",
    "sg:classifiers":[
        {
            "category":"Building & Trades",
            "subcategory":"Construction",
            "type":"Services"
        }
    ],
    "sg:phone":"+1 585 377 5004",
    "sg:postcode":"14502",
    "sg:province":"NY",
    "sg:tags":[
        "home",
        "improvement"
    ],
    "wof:name":"CRK Construction",
    "wof:placetype":"venue"
},
  "geometry": {"coordinates":[-77.36358300000001,43.128145],"type":"Point"}
}