{
  "type": "Feature",
  "properties": {
    "iso:country":"US",
    "sg:address":"116 W 23rd St",
    "sg:city":"New York",
    "sg:classifiers":[
        {
            "category":"Professional",
            "subcategory":"Business Services",
            "type":"Services"
        }
    ],
    "sg:phone":"+1 646 375 2399",
    "sg:postcode":"10011",
    "sg:province":"NY",
    "sg:tags":[
        "networking",
        "it"
    ],
    "wof:name":"Dreamers Inc",
    "wof:placetype":"venue"
},
  "geometry": {"coordinates":[-73.99533,40.743838],"type":"Point"}
}