{
  "type": "Feature",
  "properties": {
    "addr:full":"8666 110th Street Richmond Hill NY 11418",
    "addr:housenumber":"8666",
    "addr:postcode":"11418",
    "addr:street":"110Th Street",
    "iso:country":"US",
    "sg:address":"8666 110th Street",
    "sg:city":"Richmond Hill",
    "sg:classifiers":[
        {
            "category":"Banks & Credit Unions",
            "subcategory":"Atm",
            "type":"Services"
        }
    ],
    "sg:phone":"+1 718 570 8100",
    "sg:postcode":"11418",
    "sg:province":"NY",
    "sg:tags":[
        "bankruptcy"
    ],
    "wof:name":"Law Offices of Bruce Feinstein P C",
    "wof:placetype":"venue"
},
  "geometry": {"coordinates":[-73.83812500000001,40.696505],"type":"Point"}
}