{
  "type": "Feature",
  "properties": {
    "iso:country":"US",
    "sg:address":"71 Thayer St",
    "sg:city":"New York",
    "sg:classifiers":[
        {
            "category":"Place Of Worship",
            "subcategory":"Church",
            "type":"Public Place"
        }
    ],
    "sg:phone":"+1 212 569 2239",
    "sg:postcode":"10040",
    "sg:province":"NY",
    "sg:website":"firesidepentecostalassembly.org/",
    "wof:name":"Fireside Pentecostal Assembly Inc",
    "wof:placetype":"venue"
},
  "geometry": {"coordinates":[-73.9272,40.8634],"type":"Point"}
}