{
  "type": "Feature",
  "properties": {
    "addr:full":"4008 National St Corona NY 11368",
    "addr:housenumber":"4008",
    "addr:postcode":"11368",
    "addr:street":"National St",
    "iso:country":"US",
    "sg:address":"4008 National St",
    "sg:city":"Corona",
    "sg:classifiers":[
        {
            "category":"Wholesale",
            "subcategory":"Fruits & Vegetables",
            "type":"Manufacturing & Wholesale Goods"
        }
    ],
    "sg:phone":"+1 718 397 0009",
    "sg:postcode":"11368",
    "sg:province":"NY",
    "sg:tags":[
        "veggie"
    ],
    "wof:name":"Kim's Family Farm 2",
    "wof:placetype":"venue"
},
  "geometry": {"coordinates":[-73.862999,40.7495],"type":"Point"}
}