{
  "type": "Feature",
  "properties": {
    "addr:full":"9 Fairlawn Ave Washingtonville NY 10940",
    "addr:housenumber":"9",
    "addr:postcode":"10940",
    "addr:street":"Fairlawn Ave",
    "iso:country":"US",
    "sg:address":"9 Fairlawn Ave",
    "sg:city":"Washingtonville",
    "sg:classifiers":[
        {
            "category":"Sports & Exercise",
            "subcategory":"Gym",
            "type":"Entertainment"
        }
    ],
    "sg:phone":"+1 845 496 6362",
    "sg:postcode":"10940",
    "sg:province":"NY",
    "sg:tags":[
        "club",
        "health",
        "studio",
        "gymnasium"
    ],
    "sg:website":"www.proactivehealthandfitness.com",
    "wof:name":"Village Fitness Ctr",
    "wof:placetype":"venue"
},
  "geometry": {"coordinates":[-74.403322,41.453039],"type":"Point"}
}