{
  "type": "Feature",
  "properties": {
    "addr:full":"31 Covert Ave Floral Park NY 11001",
    "addr:housenumber":"31",
    "addr:postcode":"11001",
    "addr:street":"Covert Ave",
    "iso:country":"US",
    "sg:address":"31 Covert Ave",
    "sg:city":"Floral Park",
    "sg:classifiers":[
        {
            "category":"Shopping",
            "subcategory":"Gifts & Souvenirs",
            "type":"Retail Goods"
        }
    ],
    "sg:phone":"+1 516 326 7447",
    "sg:postcode":"11001",
    "sg:province":"NY",
    "sg:tags":[
        "shop"
    ],
    "wof:name":"Personal Touch Gifts",
    "wof:placetype":"venue"
},
  "geometry": {"coordinates":[-73.689269,40.7134],"type":"Point"}
}