{
  "type": "Feature",
  "properties": {
    "addr:full":"5795 Sweetland Rd Stafford NY 14143",
    "addr:housenumber":"5795",
    "addr:postcode":"14143",
    "addr:street":"Sweetland Rd",
    "iso:country":"US",
    "sg:address":"5795 Sweetland Rd",
    "sg:city":"Stafford",
    "sg:classifiers":[
        {
            "category":"Sports & Exercise",
            "subcategory":"Golf",
            "type":"Entertainment"
        }
    ],
    "sg:phone":"+1 585 343 7059",
    "sg:postcode":"14143",
    "sg:province":"NY",
    "sg:tags":[
        "course"
    ],
    "wof:name":"Sweetland Pines Inc",
    "wof:placetype":"venue"
},
  "geometry": {"coordinates":[-78.09495,42.964286],"type":"Point"}
}