{
  "type": "Feature",
  "properties": {
    "iso:country":"US",
    "sg:address":"56 New St",
    "sg:city":"Oceanside",
    "sg:classifiers":[
        {
            "category":"Recreation",
            "subcategory":"Marina",
            "type":"Entertainment"
        }
    ],
    "sg:phone":"+1 516 763 1624",
    "sg:postcode":"11572",
    "sg:province":"NY",
    "sg:tags":[
        "yard",
        "boat"
    ],
    "wof:name":"Ace Marine Inc",
    "wof:placetype":"venue"
},
  "geometry": {"coordinates":[-73.658866,40.637117],"type":"Point"}
}