{
  "type": "Feature",
  "properties": {
    "iso:country":"US",
    "sg:address":"410 S Main St",
    "sg:city":"North Syracuse",
    "sg:classifiers":[
        {
            "category":"Retail",
            "subcategory":"Portrait Studio",
            "type":"Services"
        }
    ],
    "sg:phone":"+1 315 458 2682",
    "sg:postcode":"13212",
    "sg:province":"NY",
    "sg:tags":[
        "photographer"
    ],
    "wof:name":"Haven Studio's",
    "wof:placetype":"venue"
},
  "geometry": {"coordinates":[-76.133627,43.129871],"type":"Point"}
}