{
  "type": "Feature",
  "properties": {
    "iso:country":"US",
    "sg:address":"82 Lefferts Blvd",
    "sg:city":"Kew Gardens",
    "sg:classifiers":[
        {
            "category":"Personal",
            "subcategory":"Beauty Salon",
            "type":"Services"
        }
    ],
    "sg:phone":"+1 718 805 0707",
    "sg:postcode":"11415",
    "sg:province":"NY",
    "sg:tags":[
        "shop"
    ],
    "wof:name":"Joyce Nail Salon",
    "wof:placetype":"venue"
},
  "geometry": {"coordinates":[-73.827082,40.711393],"type":"Point"}
}