{
  "type": "Feature",
  "properties": {
    "addr:full":"1055 Saw Mill River Rd Ardsley NY 10502",
    "addr:housenumber":"1055",
    "addr:postcode":"10502",
    "addr:street":"Saw Mill River Rd",
    "iso:country":"US",
    "sg:address":"1055 Saw Mill River Rd",
    "sg:city":"Ardsley",
    "sg:classifiers":[
        {
            "category":"Health Services",
            "subcategory":"Doctor",
            "type":"Services"
        }
    ],
    "sg:phone":"+1 914 693 6677",
    "sg:postcode":"10502",
    "sg:province":"NY",
    "sg:tags":[
        "physician",
        "surgeon"
    ],
    "wof:name":"Joseph F De Feo MD",
    "wof:placetype":"venue"
},
  "geometry": {"coordinates":[-73.843761,41.0192],"type":"Point"}
}