{
  "type": "Feature",
  "properties": {
    "iso:country":"US",
    "sg:address":"16 N Church St",
    "sg:city":"Athens",
    "sg:classifiers":[
        {
            "category":"Organizations",
            "subcategory":"Religious Organization",
            "type":"Services"
        }
    ],
    "sg:phone":"+1   ",
    "sg:postcode":"12015",
    "sg:province":"NY",
    "wof:name":"First Reformed Church",
    "wof:placetype":"venue"
},
  "geometry": {"coordinates":[-73.812381,42.261844],"type":"Point"}
}