{
  "type": "Feature",
  "properties": {
    "iso:country":"US",
    "sg:address":"956 Jamaica Avenue",
    "sg:city":"Brooklyn",
    "sg:classifiers":[
        {
            "category":"Bakery",
            "type":"Food & Drink"
        }
    ],
    "sg:phone":"+1 718 647 5090",
    "sg:postcode":"11208",
    "sg:province":"NY",
    "wof:name":"Chela's Bakery",
    "wof:placetype":"venue"
},
  "geometry": {"coordinates":[-73.86975,40.690688],"type":"Point"}
}