{
  "type": "Feature",
  "properties": {
    "iso:country":"US",
    "sg:address":"70 Highview Rd",
    "sg:city":"Monsey",
    "sg:classifiers":[
        {
            "category":"Organizations",
            "subcategory":"Religious Organization",
            "type":"Services"
        }
    ],
    "sg:phone":"+1 845 357 9414",
    "sg:postcode":"10952",
    "sg:province":"NY",
    "sg:tags":[
        "church"
    ],
    "wof:name":"Congregation Hadar",
    "wof:placetype":"venue"
},
  "geometry": {"coordinates":[-74.08791600000001,41.119179],"type":"Point"}
}