{
  "type": "Feature",
  "properties": {
    "addr:full":"286 Watchogue Rd Staten Island NY 10314",
    "addr:housenumber":"286",
    "addr:postcode":"10314",
    "addr:street":"Watchogue Rd",
    "iso:country":"US",
    "sg:address":"286 Watchogue Rd",
    "sg:city":"Staten Island",
    "sg:classifiers":[
        {
            "category":"Restaurant",
            "type":"Food & Drink"
        }
    ],
    "sg:phone":"+1 718 698 3432",
    "sg:postcode":"10314",
    "sg:province":"NY",
    "sg:tags":[
        "deli",
        "delicatessen"
    ],
    "wof:name":"Silvestro's Deli",
    "wof:placetype":"venue"
},
  "geometry": {"coordinates":[-74.139,40.616299],"type":"Point"}
}