{
  "type": "Feature",
  "properties": {
    "addr:full":"3978 Main St Strykersville NY 14145",
    "addr:housenumber":"3978",
    "addr:postcode":"14145",
    "addr:street":"Main St",
    "iso:country":"US",
    "sg:address":"3978 Main St",
    "sg:city":"Strykersville",
    "sg:classifiers":[
        {
            "category":"Restaurant",
            "type":"Food & Drink"
        }
    ],
    "sg:phone":"+1 585 457 3642",
    "sg:postcode":"14145",
    "sg:province":"NY",
    "sg:tags":[
        "cafe"
    ],
    "wof:name":"Cafe Lori's Bakery",
    "wof:placetype":"venue"
},
  "geometry": {"coordinates":[-78.447689,42.694627],"type":"Point"}
}