{
  "type": "Feature",
  "properties": {
    "addr:full":"15213 Bayside Ave Flushing NY 11354",
    "addr:housenumber":"15213",
    "addr:postcode":"11354",
    "addr:street":"Bayside Ave",
    "iso:country":"US",
    "sg:address":"15213 Bayside Ave",
    "sg:city":"Flushing",
    "sg:classifiers":[
        {
            "category":"Personal",
            "subcategory":"Beauty Salon",
            "type":"Services"
        }
    ],
    "sg:phone":"+1 718 939 1455",
    "sg:postcode":"11354",
    "sg:province":"NY",
    "sg:tags":[
        "hair",
        "stylist"
    ],
    "wof:name":"Vincenza Unisex Beauty Salon",
    "wof:placetype":"venue"
},
  "geometry": {"coordinates":[-73.811862,40.771563],"type":"Point"}
}