{
  "type": "Feature",
  "properties": {
    "addr:full":"114 W 87 St New York NY 10024",
    "addr:housenumber":"114",
    "addr:postcode":"10024",
    "addr:street":"W 87 St",
    "iso:country":"US",
    "sg:address":"114 W 87 St",
    "sg:city":"New York",
    "sg:classifiers":[
        {
            "category":"Real Estate",
            "subcategory":"Real Estate Operator",
            "type":"Services"
        }
    ],
    "sg:phone":"+1 212 875 3319",
    "sg:postcode":"10024",
    "sg:province":"NY",
    "sg:tags":[
        "apt",
        "operates"
    ],
    "wof:name":"C O F Realty LP",
    "wof:placetype":"venue"
},
  "geometry": {"coordinates":[-73.974251,40.788123],"type":"Point"}
}