{
  "type": "Feature",
  "properties": {
    "addr:full":"44 W 95 St New York NY 10025",
    "addr:housenumber":"44",
    "addr:postcode":"10025",
    "addr:street":"W 95 St",
    "iso:country":"US",
    "sg:address":"44 W 95 St",
    "sg:city":"New York",
    "sg:classifiers":[
        {
            "category":"Professional",
            "subcategory":"Business Services",
            "type":"Services"
        }
    ],
    "sg:phone":"+1   ",
    "sg:postcode":"10025",
    "sg:province":"NY",
    "wof:name":"Soulraye Inc",
    "wof:placetype":"venue"
},
  "geometry": {"coordinates":[-73.967111,40.791597],"type":"Point"}
}