{
  "type": "Feature",
  "properties": {
    "addr:full":"627 Cedar Swamp Rd Glen Head NY 11545",
    "addr:housenumber":"627",
    "addr:postcode":"11545",
    "addr:street":"Cedar Swamp Rd",
    "iso:country":"US",
    "sg:address":"627 Cedar Swamp Rd",
    "sg:city":"Glen Head",
    "sg:classifiers":[
        {
            "category":"Building & Trades",
            "subcategory":"Landscaping Services",
            "type":"Services"
        }
    ],
    "sg:phone":"+1 516 922 1638",
    "sg:postcode":"11545",
    "sg:province":"NY",
    "wof:name":"Natures Trees",
    "wof:placetype":"venue"
},
  "geometry": {"coordinates":[-73.615109,40.840678],"type":"Point"}
}