{
  "type": "Feature",
  "properties": {
    "iso:country":"US",
    "sg:address":"21 Westland Dr",
    "sg:city":"Glen Cove",
    "sg:classifiers":[
        {
            "category":"Professional",
            "type":"Services"
        }
    ],
    "sg:phone":"+1   ",
    "sg:postcode":"11542",
    "sg:province":"NY",
    "wof:name":"Menar Co",
    "wof:placetype":"venue"
},
  "geometry": {"coordinates":[-73.632385,40.900428],"type":"Point"}
}