{
  "type": "Feature",
  "properties": {
    "iso:country":"US",
    "sg:address":"3388 Palmyra Rd",
    "sg:city":"Marion",
    "sg:classifiers":[
        {
            "category":"Shopping",
            "subcategory":"Bicycles & Sporting Goods",
            "type":"Retail Goods"
        }
    ],
    "sg:phone":"+1 315 926 2828",
    "sg:postcode":"14505",
    "sg:province":"NY",
    "wof:name":"Guerin-Teed Archery Inc",
    "wof:placetype":"venue"
},
  "geometry": {"coordinates":[-77.20355000000001,43.120494],"type":"Point"}
}