{
  "type": "Feature",
  "properties": {
    "addr:full":"1231 Lafayette Ave Bronx NY 10474",
    "addr:housenumber":"1231",
    "addr:postcode":"10474",
    "addr:street":"Lafayette Ave",
    "iso:country":"US",
    "sg:address":"1231 Lafayette Ave",
    "sg:city":"Bronx",
    "sg:classifiers":[
        {
            "category":"Arts & Performance",
            "subcategory":"Theater",
            "type":"Entertainment"
        }
    ],
    "sg:phone":"+1 718 860 6400",
    "sg:postcode":"10474",
    "sg:province":"NY",
    "sg:tags":[
        "dance",
        "company"
    ],
    "wof:name":"Contemporary Ballet Theatre",
    "wof:placetype":"venue"
},
  "geometry": {"coordinates":[-73.891628,40.816441],"type":"Point"}
}