{
  "type": "Feature",
  "properties": {
    "addr:full":"923 Riverview Rd Rexford NY 12148",
    "addr:housenumber":"923",
    "addr:postcode":"12148",
    "addr:street":"Riverview Rd",
    "iso:country":"US",
    "sg:address":"923 Riverview Rd",
    "sg:city":"Rexford",
    "sg:classifiers":[
        {
            "category":"Restaurant",
            "type":"Food & Drink"
        }
    ],
    "sg:phone":"+1 518 399 2651",
    "sg:postcode":"12148",
    "sg:province":"NY",
    "sg:tags":[
        "parlor",
        "ice",
        "cream"
    ],
    "wof:name":"Stewart's Shops",
    "wof:placetype":"venue"
},
  "geometry": {"coordinates":[-73.888136,42.85629],"type":"Point"}
}