{
  "type": "Feature",
  "properties": {
    "iso:country":"US",
    "sg:address":"160 Hill St",
    "sg:city":"Buffalo",
    "sg:classifiers":[
        {
            "category":"Health Services",
            "subcategory":"Doctor",
            "type":"Services"
        }
    ],
    "sg:phone":"+1   ",
    "sg:postcode":"14214",
    "sg:province":"NY",
    "sg:tags":[
        "medical"
    ],
    "wof:name":"Robert J Smolinski MD",
    "wof:placetype":"venue"
},
  "geometry": {"coordinates":[-78.83162400000001,42.939097],"type":"Point"}
}