{
  "type": "Feature",
  "properties": {
    "addr:full":"40 Salina St Baldwinsville NY 13027",
    "addr:housenumber":"40",
    "addr:postcode":"13027",
    "addr:street":"Salina St",
    "iso:country":"US",
    "sg:address":"40 Salina St",
    "sg:city":"Baldwinsville",
    "sg:classifiers":[
        {
            "category":"Shopping",
            "subcategory":"Catalog Store",
            "type":"Retail Goods"
        }
    ],
    "sg:phone":"+1   ",
    "sg:postcode":"13027",
    "sg:province":"NY",
    "sg:tags":[
        "house",
        "mail"
    ],
    "wof:name":"Aeiou",
    "wof:placetype":"venue"
},
  "geometry": {"coordinates":[-76.324192,43.157899],"type":"Point"}
}