{
  "type": "Feature",
  "properties": {
    "addr:full":"2504 Hylan Blvd Staten Island NY 10306",
    "addr:housenumber":"2504",
    "addr:postcode":"10306",
    "addr:street":"Hylan Blvd",
    "iso:country":"US",
    "sg:address":"2504 Hylan Blvd",
    "sg:city":"Staten Island",
    "sg:classifiers":[
        {
            "category":"Restaurant",
            "type":"Food & Drink"
        }
    ],
    "sg:phone":"+1 718 667 6689",
    "sg:postcode":"10306",
    "sg:province":"NY",
    "sg:tags":[
        "delicatessen"
    ],
    "wof:name":"Jasmine Food Corp",
    "wof:placetype":"venue"
},
  "geometry": {"coordinates":[-74.110224,40.569922],"type":"Point"}
}