{
  "type": "Feature",
  "properties": {
    "iso:country":"US",
    "sg:address":"4655 Metropolitan Ave",
    "sg:city":"Ridgewood",
    "sg:classifiers":[
        {
            "category":"Manufacturing",
            "subcategory":"Leather Goods",
            "type":"Manufacturing & Wholesale Goods"
        }
    ],
    "sg:phone":"+1 718 417 3133",
    "sg:postcode":"11385",
    "sg:province":"NY",
    "wof:name":"J R A Realty Co",
    "wof:placetype":"venue"
},
  "geometry": {"coordinates":[-73.921898,40.714001],"type":"Point"}
}