{
  "type": "Feature",
  "properties": {
    "addr:full":"301 E 57th St 5th Fl Manhattan NY 10022",
    "addr:housenumber":"301",
    "addr:postcode":"10022",
    "addr:street":"E 57Th St",
    "iso:country":"US",
    "sg:address":"301 E 57th St 5th Fl",
    "sg:city":"Manhattan",
    "sg:classifiers":[
        {
            "category":"Sports & Exercise",
            "subcategory":"Gym",
            "type":"Entertainment"
        },
        {
            "category":"Personal",
            "subcategory":"Day Spa",
            "type":"Services"
        }
    ],
    "sg:phone":"+1 212 777 7703",
    "sg:postcode":"10022",
    "sg:province":"NY",
    "sg:tags":[
        "trainer"
    ],
    "sg:website":"www.completebody.com/57street/",
    "wof:name":"Complete Body & Spa",
    "wof:placetype":"venue"
},
  "geometry": {"coordinates":[-73.965214,40.75929],"type":"Point"}
}