{
  "type": "Feature",
  "properties": {
    "addr:full":"101 Grumman Rd W Bethpage NY 11714",
    "addr:housenumber":"101",
    "addr:postcode":"11714",
    "addr:street":"Grumman Rd W Bethpage",
    "iso:country":"US",
    "sg:address":"101 Grumman Rd W",
    "sg:city":"Bethpage",
    "sg:classifiers":[
        {
            "category":"Government",
            "subcategory":"Police Station",
            "type":"Public Place"
        }
    ],
    "sg:phone":"+1 516 573 4000",
    "sg:postcode":"11714",
    "sg:province":"NY",
    "sg:tags":[
        "protection"
    ],
    "wof:name":"Police Aviation Bureau",
    "wof:placetype":"venue"
},
  "geometry": {"coordinates":[-73.49853899999999,40.750007],"type":"Point"}
}