{
  "type": "Feature",
  "properties": {
    "iso:country":"US",
    "sg:address":"570 Expressway Dr S",
    "sg:city":"Medford",
    "sg:classifiers":[
        {
            "category":"Banks & Credit Unions",
            "subcategory":"Investment Brokerage",
            "type":"Services"
        },
        {
            "category":"Banks & Credit Unions",
            "subcategory":"Financial Services",
            "type":"Services"
        }
    ],
    "sg:phone":"+1 631 647 2090",
    "sg:postcode":"11763",
    "sg:province":"NY",
    "sg:tags":[
        "advisory",
        "planner"
    ],
    "wof:name":"Ic Financial Group",
    "wof:placetype":"venue"
},
  "geometry": {"coordinates":[-72.985816,40.822392],"type":"Point"}
}