{
  "type": "Feature",
  "properties": {
    "iso:country":"US",
    "sg:address":"184 Fort Edward Rd",
    "sg:city":"Fort Edward",
    "sg:classifiers":[
        {
            "category":"Building & Trades",
            "subcategory":"Construction",
            "type":"Services"
        }
    ],
    "sg:phone":"+1 518 743 9468",
    "sg:postcode":"12828",
    "sg:province":"NY",
    "sg:tags":[
        "contractor"
    ],
    "wof:name":"D G Builders",
    "wof:placetype":"venue"
},
  "geometry": {"coordinates":[-73.608766,43.266027],"type":"Point"}
}