{
  "type": "Feature",
  "properties": {
    "addr:full":"318 E 6th St New York NY 10003",
    "addr:housenumber":"318",
    "addr:postcode":"10003",
    "addr:street":"E 6Th St",
    "iso:country":"US",
    "sg:address":"318 E 6th St",
    "sg:city":"New York",
    "sg:classifiers":[
        {
            "category":"Restaurant",
            "type":"Food & Drink"
        }
    ],
    "sg:menulink":"http://www.allmenus.com/ny/new-york/60265-taj-mahal/menu/",
    "sg:phone":"+1 212 529 2217",
    "sg:postcode":"10003",
    "sg:province":"NY",
    "sg:tags":[
        "indian",
        "asian"
    ],
    "wof:name":"Taj Mahal",
    "wof:placetype":"venue"
},
  "geometry": {"coordinates":[-73.987707,40.726813],"type":"Point"}
}