{
  "type": "Feature",
  "properties": {
    "iso:country":"US",
    "sg:address":"82 Carleton Ave",
    "sg:city":"Central Islip",
    "sg:classifiers":[
        {
            "category":"Education",
            "subcategory":"School",
            "type":"Public Place"
        }
    ],
    "sg:phone":"+1 631 234 6324",
    "sg:postcode":"11722",
    "sg:province":"NY",
    "sg:website":"www.ourladyofprovidence.org",
    "wof:name":"Our Lady of Providence Regional School",
    "wof:placetype":"venue"
},
  "geometry": {"coordinates":[-73.201035,40.787002],"type":"Point"}
}