{
  "type": "Feature",
  "properties": {
    "iso:country":"US",
    "sg:address":"291 Hudson Ave",
    "sg:city":"Albany",
    "sg:classifiers":[
        {
            "category":"Health Services",
            "subcategory":"Clinic",
            "type":"Services"
        }
    ],
    "sg:phone":"+1 518 463 9234",
    "sg:postcode":"12210",
    "sg:province":"NY",
    "sg:tags":[
        "specialty",
        "outpatient"
    ],
    "wof:name":"Peer Education Project",
    "wof:placetype":"venue"
},
  "geometry": {"coordinates":[-73.76264999999999,42.651708],"type":"Point"}
}