{
  "type": "Feature",
  "properties": {
    "addr:full":"122 Sheridan Blvd Inwood NY 11096",
    "addr:housenumber":"122",
    "addr:postcode":"11096",
    "addr:street":"Sheridan Blvd",
    "iso:country":"US",
    "sg:address":"122 Sheridan Blvd",
    "sg:city":"Inwood",
    "sg:classifiers":[
        {
            "category":"Deli",
            "type":"Food & Drink"
        },
        {
            "category":"Food & Beverages",
            "subcategory":"Bakery",
            "type":"Retail Goods"
        }
    ],
    "sg:phone":"+1 516 239 0048",
    "sg:postcode":"11096",
    "sg:province":"NY",
    "sg:tags":[
        "sandwich"
    ],
    "wof:name":"Geronimo Deli",
    "wof:placetype":"venue"
},
  "geometry": {"coordinates":[-73.752408,40.614818],"type":"Point"}
}