{
  "type": "Feature",
  "properties": {
    "iso:country":"US",
    "sg:address":"385 Greenvale Hwy",
    "sg:city":"Greenvale",
    "sg:classifiers":[
        {
            "category":"Home & Garden",
            "subcategory":"Building Materials",
            "type":"Retail Goods"
        }
    ],
    "sg:phone":"+1 516 671 1440",
    "sg:postcode":"11548",
    "sg:province":"NY",
    "sg:tags":[
        "equipment",
        "fixture",
        "lighting"
    ],
    "sg:website":"www.greenvaleelectric.com",
    "wof:name":"Greenvale Elec Supl Corp",
    "wof:placetype":"venue"
},
  "geometry": {"coordinates":[-73.628197,40.811199],"type":"Point"}
}