{
  "type": "Feature",
  "properties": {
    "addr:full":"4336 Ditmars Blvd Long Island City NY 11105",
    "addr:housenumber":"4336",
    "addr:postcode":"11105",
    "addr:street":"Ditmars Blvd",
    "iso:country":"US",
    "sg:address":"4336 Ditmars Blvd",
    "sg:city":"Long Island City",
    "sg:classifiers":[
        {
            "category":"Bars & Pubs",
            "subcategory":"Lounge",
            "type":"Food & Drink"
        }
    ],
    "sg:phone":"+1 718 204 9700",
    "sg:postcode":"11105",
    "sg:province":"NY",
    "wof:name":"Remi",
    "wof:placetype":"venue"
},
  "geometry": {"coordinates":[-73.90377100000001,40.771226],"type":"Point"}
}