{
  "type": "Feature",
  "properties": {
    "iso:country":"US",
    "sg:address":"12 Langford St",
    "sg:city":"Van Etten",
    "sg:classifiers":[
        {
            "category":"Wholesale",
            "subcategory":"Non-durable Goods",
            "type":"Manufacturing & Wholesale Goods"
        }
    ],
    "sg:phone":"+1 607 589 6769",
    "sg:postcode":"14889",
    "sg:province":"NY",
    "sg:tags":[
        "advertising"
    ],
    "wof:name":"Eddy Advertising Svc",
    "wof:placetype":"venue"
},
  "geometry": {"coordinates":[-76.554615,42.200498],"type":"Point"}
}