{
  "type": "Feature",
  "properties": {
    "addr:full":"69 Church St Buskirk NY 12037",
    "addr:housenumber":"69",
    "addr:postcode":"12037",
    "addr:street":"Church St",
    "iso:country":"US",
    "sg:address":"69 Church St",
    "sg:city":"Buskirk",
    "sg:classifiers":[
        {
            "category":"Social Services",
            "subcategory":"Child Care",
            "type":"Services"
        }
    ],
    "sg:phone":"+1 518 686 9373",
    "sg:postcode":"12037",
    "sg:province":"NY",
    "sg:tags":[
        "center",
        "day"
    ],
    "wof:name":"Commission On Ecnmc Opprtnty",
    "wof:placetype":"venue"
},
  "geometry": {"coordinates":[-73.606161,42.357974],"type":"Point"}
}