{
  "type": "Feature",
  "properties": {
    "iso:country":"US",
    "sg:address":"141 W Albany St",
    "sg:city":"Oswego",
    "sg:classifiers":[
        {
            "category":"Building & Trades",
            "subcategory":"Construction",
            "type":"Services"
        }
    ],
    "sg:phone":"+1 315 342 7122",
    "sg:postcode":"13126",
    "sg:province":"NY",
    "sg:tags":[
        "hanging",
        "contractor"
    ],
    "wof:name":"D McDougall Painting",
    "wof:placetype":"venue"
},
  "geometry": {"coordinates":[-76.520414,43.4485],"type":"Point"}
}