{
  "type": "Feature",
  "properties": {
    "addr:full":"229 W 28 St New York NY 10001",
    "addr:housenumber":"229",
    "addr:postcode":"10001",
    "addr:street":"W 28 St",
    "iso:country":"US",
    "sg:address":"229 W 28 St",
    "sg:city":"New York",
    "sg:classifiers":[
        {
            "category":"Social Services",
            "subcategory":"Job Training",
            "type":"Services"
        }
    ],
    "sg:phone":"+1 212 594 0437",
    "sg:postcode":"10001",
    "sg:province":"NY",
    "sg:tags":[
        "workshop",
        "sheltered"
    ],
    "wof:name":"Contemporary Guidance Service",
    "wof:placetype":"venue"
},
  "geometry": {"coordinates":[-73.99554500000001,40.74816],"type":"Point"}
}