{
  "type": "Feature",
  "properties": {
    "iso:country":"US",
    "sg:address":"19006 Linden Blvd",
    "sg:city":"Saint Albans",
    "sg:classifiers":[
        {
            "category":"Restaurant",
            "type":"Food & Drink"
        }
    ],
    "sg:menulink":"http://www.allmenus.com/ny/queens/236657-fish-net-restaurant/menu/",
    "sg:phone":"+1 718 943 6090",
    "sg:postcode":"11412",
    "sg:province":"NY",
    "sg:tags":[
        "american",
        "jamaican"
    ],
    "wof:name":"Fish Net Restaurant",
    "wof:placetype":"venue"
},
  "geometry": {"coordinates":[-73.761044,40.69202],"type":"Point"}
}