{
  "type": "Feature",
  "properties": {
    "addr:full":"31 S Cross Rd Staatsburg NY 12580",
    "addr:housenumber":"31",
    "addr:postcode":"12580",
    "addr:street":"S Cross Rd",
    "iso:country":"US",
    "sg:address":"31 S Cross Rd",
    "sg:city":"Staatsburg",
    "sg:classifiers":[
        {
            "category":"Building & Trades",
            "subcategory":"Equipment Rental",
            "type":"Services"
        }
    ],
    "sg:phone":"+1   ",
    "sg:postcode":"12580",
    "sg:province":"NY",
    "sg:tags":[
        "visual",
        "audio",
        "supply"
    ],
    "wof:name":"Video Shop",
    "wof:placetype":"venue"
},
  "geometry": {"coordinates":[-73.931493,41.830191],"type":"Point"}
}