{
  "type": "Feature",
  "properties": {
    "addr:full":"187 US Hwy 9w Haverstraw NY 10927",
    "addr:housenumber":"187",
    "addr:postcode":"10927",
    "addr:street":"Us Hwy 9W",
    "iso:country":"US",
    "sg:address":"187 US Hwy 9w",
    "sg:city":"Haverstraw",
    "sg:classifiers":[
        {
            "category":"Home & Garden",
            "subcategory":"Household Appliances",
            "type":"Retail Goods"
        }
    ],
    "sg:phone":"+1   ",
    "sg:postcode":"10927",
    "sg:province":"NY",
    "sg:tags":[
        "repair"
    ],
    "wof:name":"J & V Appliance Inc",
    "wof:placetype":"venue"
},
  "geometry": {"coordinates":[-73.983158,41.20031],"type":"Point"}
}