{
  "type": "Feature",
  "properties": {
    "iso:country":"US",
    "sg:address":"200 Parkway Dr S",
    "sg:city":"Hauppauge",
    "sg:classifiers":[
        {
            "category":"Professional",
            "subcategory":"Lawyer & Legal Services",
            "type":"Services"
        }
    ],
    "sg:phone":"+1 631 543 2900",
    "sg:postcode":"11788",
    "sg:province":"NY",
    "wof:name":"Davis Ronald J Atty",
    "wof:placetype":"venue"
},
  "geometry": {"coordinates":[-73.266502,40.819401],"type":"Point"}
}