{
  "type": "Feature",
  "properties": {
    "addr:full":"140 W 3rd St Mt Vernon NY 10550",
    "addr:housenumber":"140",
    "addr:postcode":"10550",
    "addr:street":"W 3Rd St",
    "iso:country":"US",
    "sg:address":"140 W 3rd St",
    "sg:city":"Mt Vernon",
    "sg:classifiers":[
        {
            "category":"Bars & Pubs",
            "type":"Food & Drink"
        }
    ],
    "sg:phone":"+1 914 664 9284",
    "sg:postcode":"10550",
    "sg:province":"NY",
    "wof:name":"Mc Cray's Sport Ctr",
    "wof:placetype":"venue"
},
  "geometry": {"coordinates":[-73.841528,40.905396],"type":"Point"}
}