{
  "type": "Feature",
  "properties": {
    "addr:full":"145 Java St Brooklyn NY 11222",
    "addr:housenumber":"145",
    "addr:postcode":"11222",
    "addr:street":"Java St",
    "iso:country":"US",
    "sg:address":"145 Java St",
    "sg:city":"Brooklyn",
    "sg:classifiers":[
        {
            "category":"Arena",
            "subcategory":"Sports Club",
            "type":"Entertainment"
        }
    ],
    "sg:phone":"+1 917 667 5239",
    "sg:postcode":"11222",
    "sg:province":"NY",
    "sg:tags":[
        "martial art",
        "instruction"
    ],
    "sg:website":"http://KARATENEWYORK.COM",
    "wof:name":"NY TRADITIONAL SHOTOKAN KARATE SCHOOL",
    "wof:placetype":"venue"
},
  "geometry": {"coordinates":[-73.954947,40.731558],"type":"Point"}
}