{
  "type": "Feature",
  "properties": {
    "addr:full":"2338 State Hwy 352 Elmira NY 14903",
    "addr:housenumber":"2338",
    "addr:postcode":"14903",
    "addr:street":"State Hwy 352",
    "iso:country":"US",
    "sg:address":"2338 State Hwy 352",
    "sg:city":"Elmira",
    "sg:classifiers":[
        {
            "category":"Food & Beverages",
            "subcategory":"Groceries & Convenience Stores",
            "type":"Retail Goods"
        }
    ],
    "sg:phone":"+1   ",
    "sg:postcode":"14903",
    "sg:province":"NY",
    "wof:name":"Lament Grocery",
    "wof:placetype":"venue"
},
  "geometry": {"coordinates":[-76.902868,42.095777],"type":"Point"}
}