{
  "type": "Feature",
  "properties": {
    "addr:full":"18 Wilderness Ln Valatie NY 12184",
    "addr:housenumber":"18",
    "addr:postcode":"12184",
    "addr:street":"Wilderness Ln",
    "iso:country":"US",
    "sg:address":"18 Wilderness Ln",
    "sg:city":"Valatie",
    "sg:classifiers":[
        {
            "category":"Professional",
            "subcategory":"Testing Lab",
            "type":"Services"
        },
        {
            "category":"Health Services",
            "subcategory":"Medical Lab",
            "type":"Services"
        }
    ],
    "sg:phone":"+1 518 758 9505",
    "sg:postcode":"12184",
    "sg:province":"NY",
    "sg:tags":[
        "laboratory",
        "dental"
    ],
    "sg:website":"http://www.photicsllc.com",
    "wof:name":"Photics Inc",
    "wof:placetype":"venue"
},
  "geometry": {"coordinates":[-73.6835,42.421799],"type":"Point"}
}