{
  "type": "Feature",
  "properties": {
    "iso:country":"US",
    "sg:address":"449 N Seward Ave",
    "sg:city":"Auburn",
    "sg:classifiers":[
        {
            "category":"Building & Trades",
            "subcategory":"Construction",
            "type":"Services"
        }
    ],
    "sg:phone":"+1 315 252 4512",
    "sg:postcode":"13021",
    "sg:province":"NY",
    "sg:tags":[
        "contractor"
    ],
    "wof:name":"Prewire Plus",
    "wof:placetype":"venue"
},
  "geometry": {"coordinates":[-76.547771,42.938621],"type":"Point"}
}