{
  "type": "Feature",
  "properties": {
    "iso:country":"US",
    "sg:address":"5803 5th Ave Ste 1",
    "sg:city":"Brooklyn",
    "sg:classifiers":[
        {
            "category":"Sports & Exercise",
            "subcategory":"Bicycle Rental",
            "type":"Entertainment"
        }
    ],
    "sg:phone":"+1 718 439 5105",
    "sg:postcode":"11220",
    "sg:province":"NY",
    "sg:tags":[
        "wear"
    ],
    "wof:name":"Euromex Sports Incorporated",
    "wof:placetype":"venue"
},
  "geometry": {"coordinates":[-74.014995,40.640591],"type":"Point"}
}