{
  "type": "Feature",
  "properties": {
    "iso:country":"US",
    "sg:address":"47 W 69 St",
    "sg:city":"New York",
    "sg:classifiers":[
        {
            "category":"Wholesale",
            "subcategory":"Groceries",
            "type":"Manufacturing & Wholesale Goods"
        }
    ],
    "sg:phone":"+1 212 799 0550",
    "sg:postcode":"10023",
    "sg:province":"NY",
    "wof:name":"Sarah Cumming Associates",
    "wof:placetype":"venue"
},
  "geometry": {"coordinates":[-73.979159,40.774982],"type":"Point"}
}