{
  "type": "Feature",
  "properties": {
    "iso:country":"US",
    "sg:address":"2830 Tuscarora Rd",
    "sg:city":"Erieville",
    "sg:classifiers":[
        {
            "category":"Professional",
            "subcategory":"Engineering",
            "type":"Services"
        }
    ],
    "sg:phone":"+1 315 662 3243",
    "sg:postcode":"13061",
    "sg:province":"NY",
    "wof:name":"Modern Energy Technology Corp",
    "wof:placetype":"venue"
},
  "geometry": {"coordinates":[-75.752291,42.858649],"type":"Point"}
}