{
  "type": "Feature",
  "properties": {
    "addr:full":"130 Smith St Brooklyn NY 11201",
    "addr:housenumber":"130",
    "addr:postcode":"11201",
    "addr:street":"Smith St",
    "iso:country":"US",
    "sg:address":"130 Smith St",
    "sg:city":"Brooklyn",
    "sg:classifiers":[
        {
            "category":"Restaurant",
            "type":"Food & Drink"
        }
    ],
    "sg:phone":"+1 718 624 7202",
    "sg:postcode":"11201",
    "sg:province":"NY",
    "sg:tags":[
        "massage"
    ],
    "wof:name":"Two Rabbits",
    "wof:placetype":"venue"
},
  "geometry": {"coordinates":[-73.990319,40.687302],"type":"Point"}
}