{
  "type": "Feature",
  "properties": {
    "iso:country":"US",
    "sg:address":"589 Tuckahoe Rd",
    "sg:city":"Yonkers",
    "sg:classifiers":[
        {
            "category":"Personal",
            "type":"Services"
        },
        {
            "category":"Sports & Exercise",
            "subcategory":"Gym",
            "type":"Entertainment"
        },
        {
            "category":"Arena",
            "subcategory":"Sports Club",
            "type":"Entertainment"
        }
    ],
    "sg:phone":"+1 914 840 5110",
    "sg:postcode":"10710",
    "sg:province":"NY",
    "sg:tags":[
        "trainer",
        "consultant",
        "gymnasium",
        "program",
        "health",
        "fitness",
        "physical"
    ],
    "sg:website":"http://clickserve.dartsearch.net/link/click?lid=43000000196565615",
    "wof:name":"Bally Total Fitness",
    "wof:placetype":"venue"
},
  "geometry": {"coordinates":[-73.847094,40.953664],"type":"Point"}
}