{
  "type": "Feature",
  "properties": {
    "iso:country":"US",
    "sg:address":"200 Powell Ave",
    "sg:city":"Central Islip",
    "sg:classifiers":[
        {
            "category":"Building & Trades",
            "subcategory":"Construction",
            "type":"Services"
        }
    ],
    "sg:phone":"+1 631 234 5619",
    "sg:postcode":"11722",
    "sg:province":"NY",
    "sg:tags":[
        "contractor"
    ],
    "wof:name":"K S Roofing",
    "wof:placetype":"venue"
},
  "geometry": {"coordinates":[-73.187984,40.797531],"type":"Point"}
}