{
  "type": "Feature",
  "properties": {
    "addr:full":"1231 Mohawk St Utica NY 13501",
    "addr:housenumber":"1231",
    "addr:postcode":"13501",
    "addr:street":"Mohawk St",
    "iso:country":"US",
    "sg:address":"1231 Mohawk St",
    "sg:city":"Utica",
    "sg:classifiers":[
        {
            "category":"Health Services",
            "subcategory":"Doctor",
            "type":"Services"
        },
        {
            "category":"Health Services",
            "subcategory":"Dentist",
            "type":"Services"
        }
    ],
    "sg:phone":"+1 315 732 6824",
    "sg:postcode":"13501",
    "sg:province":"NY",
    "sg:tags":[
        "dentists-oral",
        "physician",
        "maxillofacial",
        "surgeons",
        "surgery",
        "oral"
    ],
    "wof:name":"Patrick Cardinale Dmd",
    "wof:placetype":"venue"
},
  "geometry": {"coordinates":[-75.22438,43.08704],"type":"Point"}
}