{
  "type": "Feature",
  "properties": {
    "iso:country":"US",
    "sg:address":"1163 Jericho Tpke",
    "sg:city":"Commack",
    "sg:classifiers":[
        {
            "category":"Shopping",
            "subcategory":"Pharmacy",
            "type":"Retail Goods"
        }
    ],
    "sg:phone":"+1 631 543 3331",
    "sg:postcode":"11725",
    "sg:province":"NY",
    "sg:tags":[
        "drugstore"
    ],
    "sg:website":"www.rxexpresspharmacy.com",
    "wof:name":"Rx Express Pharmacy",
    "wof:placetype":"venue"
},
  "geometry": {"coordinates":[-73.270203,40.845501],"type":"Point"}
}