{
  "type": "Feature",
  "properties": {
    "addr:full":"461 Fulton St Troy NY 12180",
    "addr:housenumber":"461",
    "addr:postcode":"12180",
    "addr:street":"Fulton St",
    "iso:country":"US",
    "sg:address":"461 Fulton St",
    "sg:city":"Troy",
    "sg:classifiers":[
        {
            "category":"Food & Beverages",
            "subcategory":"Groceries & Convenience Stores",
            "type":"Retail Goods"
        }
    ],
    "sg:phone":"+1   ",
    "sg:postcode":"12180",
    "sg:province":"NY",
    "wof:name":"Provisions Community Food",
    "wof:placetype":"venue"
},
  "geometry": {"coordinates":[-73.687754,42.732235],"type":"Point"}
}