{
  "type": "Feature",
  "properties": {
    "addr:full":"432 Elmont Rd Elmont NY 11003",
    "addr:housenumber":"432",
    "addr:postcode":"11003",
    "addr:street":"Elmont Rd",
    "iso:country":"US",
    "sg:address":"432 Elmont Rd",
    "sg:city":"Elmont",
    "sg:classifiers":[
        {
            "category":"Building & Trades",
            "subcategory":"Pest Control",
            "type":"Services"
        }
    ],
    "sg:phone":"+1 516 354 5020",
    "sg:postcode":"11003",
    "sg:province":"NY",
    "wof:name":"Bestway Exterminating Inc",
    "wof:placetype":"venue"
},
  "geometry": {"coordinates":[-73.714313,40.698668],"type":"Point"}
}