{
  "type": "Feature",
  "properties": {
    "addr:full":"339 Winona Blvd Rochester NY 14617",
    "addr:housenumber":"339",
    "addr:postcode":"14617",
    "addr:street":"Winona Blvd",
    "iso:country":"US",
    "sg:address":"339 Winona Blvd",
    "sg:city":"Rochester",
    "sg:classifiers":[
        {
            "category":"Home & Garden",
            "subcategory":"Building Materials",
            "type":"Retail Goods"
        }
    ],
    "sg:phone":"+1 585 342 6320",
    "sg:postcode":"14617",
    "sg:province":"NY",
    "sg:tags":[
        "downspouts",
        "gutter"
    ],
    "wof:name":"Dattalo John",
    "wof:placetype":"venue"
},
  "geometry": {"coordinates":[-77.617237,43.210505],"type":"Point"}
}