{
  "type": "Feature",
  "properties": {
    "iso:country":"US",
    "sg:address":"250 W Montauk Hwy",
    "sg:city":"Hampton Bays",
    "sg:classifiers":[
        {
            "category":"Sports & Exercise",
            "subcategory":"Gym",
            "type":"Entertainment"
        }
    ],
    "sg:phone":"+1 631 723 3174",
    "sg:postcode":"11946",
    "sg:province":"NY",
    "sg:tags":[
        "club",
        "health",
        "studio",
        "gymnasium"
    ],
    "sg:website":"www.worldgym.com",
    "wof:name":"World Gym Hampton Bays",
    "wof:placetype":"venue"
},
  "geometry": {"coordinates":[-72.548119,40.8669],"type":"Point"}
}