{
  "type": "Feature",
  "properties": {
    "addr:full":"1336 Hempstead Tpke Elmont NY 11003",
    "addr:housenumber":"1336",
    "addr:postcode":"11003",
    "addr:street":"Hempstead Tpke",
    "iso:country":"US",
    "sg:address":"1336 Hempstead Tpke",
    "sg:city":"Elmont",
    "sg:classifiers":[
        {
            "category":"Restaurant",
            "type":"Food & Drink"
        }
    ],
    "sg:menulink":"http://www.allmenus.com/ny/franklin-square/233548-stop-20/menu/",
    "sg:phone":"+1 516 358 7142",
    "sg:postcode":"11003",
    "sg:province":"NY",
    "sg:tags":[
        "american",
        "diner"
    ],
    "wof:name":"Stop 20",
    "wof:placetype":"venue"
},
  "geometry": {"coordinates":[-73.68975500000001,40.708527],"type":"Point"}
}