{
  "type": "Feature",
  "properties": {
    "iso:country":"US",
    "sg:address":"847 Main St",
    "sg:city":"Buffalo",
    "sg:classifiers":[
        {
            "category":"Professional",
            "subcategory":"Research",
            "type":"Services"
        }
    ],
    "sg:phone":"+1 716 270 0920",
    "sg:postcode":"14203",
    "sg:province":"NY",
    "sg:tags":[
        "commercial",
        "physical"
    ],
    "wof:name":"Kinex Pharmaceutical",
    "wof:placetype":"venue"
},
  "geometry": {"coordinates":[-78.87012900000001,42.898375],"type":"Point"}
}