{
  "type": "Feature",
  "properties": {
    "addr:full":"29 Avenue A New York NY 10009",
    "addr:housenumber":"29",
    "addr:postcode":"10009",
    "addr:street":"Avenue A",
    "iso:country":"US",
    "sg:address":"29 Avenue A",
    "sg:city":"New York",
    "sg:classifiers":[
        {
            "category":"Shopping",
            "subcategory":"Pets & Pet Supplies",
            "type":"Retail Goods"
        }
    ],
    "sg:phone":"+1 212 353 2863",
    "sg:postcode":"10009",
    "sg:province":"NY",
    "sg:tags":[
        "store"
    ],
    "wof:name":"Petopia",
    "wof:placetype":"venue"
},
  "geometry": {"coordinates":[-73.985761,40.722946],"type":"Point"}
}