{
  "type": "Feature",
  "properties": {
    "addr:full":"54 Sawkill Rd Kingston NY 12401",
    "addr:housenumber":"54",
    "addr:postcode":"12401",
    "addr:street":"Sawkill Rd",
    "iso:country":"US",
    "sg:address":"54 Sawkill Rd",
    "sg:city":"Kingston",
    "sg:classifiers":[
        {
            "category":"Health Services",
            "subcategory":"Doctor",
            "type":"Services"
        }
    ],
    "sg:phone":"+1 845 331 7751",
    "sg:postcode":"12401",
    "sg:province":"NY",
    "sg:tags":[
        "medical"
    ],
    "wof:name":"Occupational Hlth Wellness Ctr",
    "wof:placetype":"venue"
},
  "geometry": {"coordinates":[-74.02396,41.944334],"type":"Point"}
}