{
  "type": "Feature",
  "properties": {
    "iso:country":"US",
    "sg:address":"14993 Heritage Dr",
    "sg:city":"Clayton",
    "sg:classifiers":[
        {
            "category":"Farming",
            "subcategory":"Dairy Farm",
            "type":"Manufacturing & Wholesale Goods"
        }
    ],
    "sg:phone":"+1 315 686 3200",
    "sg:postcode":"13624",
    "sg:province":"NY",
    "wof:name":"Wetterhahn Grald Mple View Frm",
    "wof:placetype":"venue"
},
  "geometry": {"coordinates":[-76.066653,44.22448],"type":"Point"}
}