{
  "type": "Feature",
  "properties": {
    "addr:full":"8002 Kew Gardens Rd Ste 1030 Kew Gardens NY 11415",
    "addr:housenumber":"8002",
    "addr:postcode":"11415",
    "addr:street":"Kew Gardens Rd Ste 1030",
    "iso:country":"US",
    "sg:address":"8002 Kew Gardens Rd Ste 1030",
    "sg:city":"Kew Gardens",
    "sg:classifiers":[
        {
            "category":"Professional",
            "subcategory":"Lawyer & Legal Services",
            "type":"Services"
        }
    ],
    "sg:phone":"+1 718 575 5145",
    "sg:postcode":"11415",
    "sg:province":"NY",
    "wof:name":"Didio Robert Atty",
    "wof:placetype":"venue"
},
  "geometry": {"coordinates":[-73.830789,40.713751],"type":"Point"}
}