{
  "type": "Feature",
  "properties": {
    "iso:country":"US",
    "sg:address":"620 Union St",
    "sg:city":"Hudson",
    "sg:classifiers":[
        {
            "category":"Social Services",
            "subcategory":"Adult Care",
            "type":"Services"
        }
    ],
    "sg:phone":"+1 518 828 3215",
    "sg:postcode":"12534",
    "sg:province":"NY",
    "sg:tags":[
        "residential"
    ],
    "wof:name":"The Home For Aged",
    "wof:placetype":"venue"
},
  "geometry": {"coordinates":[-73.78515400000001,42.247328],"type":"Point"}
}