{
  "type": "Feature",
  "properties": {
    "iso:country":"US",
    "sg:address":"286 State Hwy 59",
    "sg:city":"Nanuet",
    "sg:classifiers":[
        {
            "category":"Restaurant",
            "type":"Food & Drink"
        }
    ],
    "sg:phone":"+1 845 623 9729",
    "sg:postcode":"10954",
    "sg:province":"NY",
    "wof:name":"KFC",
    "wof:placetype":"venue"
},
  "geometry": {"coordinates":[-74.003857,41.094321],"type":"Point"}
}