{
  "type": "Feature",
  "properties": {
    "addr:full":"2381 Merrick Rd Bellmore NY 11710",
    "addr:housenumber":"2381",
    "addr:postcode":"11710",
    "addr:street":"Merrick Rd",
    "iso:country":"US",
    "sg:address":"2381 Merrick Rd",
    "sg:city":"Bellmore",
    "sg:classifiers":[
        {
            "category":"Restaurant",
            "type":"Food & Drink"
        }
    ],
    "sg:phone":"+1   ",
    "sg:postcode":"11710",
    "sg:province":"NY",
    "sg:tags":[
        "eating"
    ],
    "wof:name":"Viva Loco Italian Mexican Cafe",
    "wof:placetype":"venue"
},
  "geometry": {"coordinates":[-73.538664,40.661386],"type":"Point"}
}