{
  "type": "Feature",
  "properties": {
    "addr:full":"1016 Fifth Ave New York NY 10028",
    "addr:housenumber":"1016",
    "addr:postcode":"10028",
    "addr:street":"Fifth Ave",
    "iso:country":"US",
    "sg:address":"1016 Fifth Ave",
    "sg:city":"New York",
    "sg:classifiers":[
        {
            "category":"Health Services",
            "subcategory":"Doctor",
            "type":"Services"
        }
    ],
    "sg:phone":"+1 212 535 5500",
    "sg:postcode":"10028",
    "sg:province":"NY",
    "sg:tags":[
        "surgeon",
        "cosmetic"
    ],
    "wof:name":"A. Peter Salas, MD, FACS, FACM",
    "wof:placetype":"venue"
},
  "geometry": {"coordinates":[-73.96155,40.779279],"type":"Point"}
}