{
  "type": "Feature",
  "properties": {
    "addr:full":"199 Lafayette New York NY 10012",
    "addr:housenumber":"199",
    "addr:postcode":"10012",
    "addr:street":"Lafayette",
    "iso:country":"US",
    "sg:address":"199 Lafayette",
    "sg:city":"New York",
    "sg:classifiers":[
        {
            "category":"Home & Garden",
            "subcategory":"Home Furnishings",
            "type":"Retail Goods"
        }
    ],
    "sg:phone":"+1 212 925 6200",
    "sg:postcode":"10012",
    "sg:province":"NY",
    "sg:tags":[
        "decor"
    ],
    "sg:website":"www.calypso-celle.com",
    "wof:name":"Calypso Home",
    "wof:placetype":"venue"
},
  "geometry": {"coordinates":[-73.997902,40.721298],"type":"Point"}
}