{
  "type": "Feature",
  "properties": {
    "addr:full":"200 Centre St New York NY 10013",
    "addr:housenumber":"200",
    "addr:postcode":"10013",
    "addr:street":"Centre St",
    "iso:country":"US",
    "sg:address":"200 Centre St",
    "sg:city":"New York",
    "sg:classifiers":[
        {
            "category":"Professional",
            "subcategory":"Business Services",
            "type":"Services"
        }
    ],
    "sg:phone":"+1 212 941 0557",
    "sg:postcode":"10013",
    "sg:province":"NY",
    "sg:tags":[
        "development",
        "art",
        "entertainment",
        "game",
        "design",
        "video"
    ],
    "sg:website":"www.templar.com",
    "wof:name":"Templar Studios LLC",
    "wof:placetype":"venue"
},
  "geometry": {"coordinates":[-73.999199,40.718899],"type":"Point"}
}