{
  "type": "Feature",
  "properties": {
    "addr:full":"2 W Main St Webster NY 14580",
    "addr:housenumber":"2",
    "addr:postcode":"14580",
    "addr:street":"W Main St",
    "iso:country":"US",
    "sg:address":"2 W Main St",
    "sg:city":"Webster",
    "sg:classifiers":[
        {
            "category":"Building & Trades",
            "subcategory":"Plumbing",
            "type":"Services"
        }
    ],
    "sg:phone":"+1 585 265 9338",
    "sg:postcode":"14580",
    "sg:province":"NY",
    "sg:tags":[
        "plumber",
        "contractor"
    ],
    "wof:name":"Living Water Plumbing",
    "wof:placetype":"venue"
},
  "geometry": {"coordinates":[-77.43032100000001,43.2122],"type":"Point"}
}