{
  "type": "Feature",
  "properties": {
    "addr:full":"25A Catherine St New York NY 10002",
    "addr:housenumber":"25a",
    "addr:postcode":"10002",
    "addr:street":"Catherine St",
    "iso:country":"US",
    "sg:address":"25A Catherine St",
    "sg:city":"New York",
    "sg:classifiers":[
        {
            "category":"Restaurant",
            "type":"Food & Drink"
        }
    ],
    "sg:phone":"+1 212 766 1777",
    "sg:postcode":"10002",
    "sg:province":"NY",
    "sg:tags":[
        "chinese"
    ],
    "wof:name":"Sweet Spring Restaurant",
    "wof:placetype":"venue"
},
  "geometry": {"coordinates":[-73.997117,40.712865],"type":"Point"}
}