{
  "type": "Feature",
  "properties": {
    "addr:full":"554 W 235th St Bronx NY 10463",
    "addr:housenumber":"554",
    "addr:postcode":"10463",
    "addr:street":"W 235Th St",
    "iso:country":"US",
    "sg:address":"554 W 235th St",
    "sg:city":"Bronx",
    "sg:classifiers":[
        {
            "category":"Restaurant",
            "type":"Food & Drink"
        }
    ],
    "sg:phone":"+1 718 884 5700",
    "sg:postcode":"10463",
    "sg:province":"NY",
    "sg:tags":[
        "style",
        "family",
        "pizza"
    ],
    "wof:name":"Nonno Tonys",
    "wof:placetype":"venue"
},
  "geometry": {"coordinates":[-73.909834,40.885631],"type":"Point"}
}