{
  "type": "Feature",
  "properties": {
    "iso:country":"US",
    "sg:address":"1016 Atlantic Ave",
    "sg:city":"Baldwin",
    "sg:classifiers":[
        {
            "category":"Real Estate",
            "subcategory":"Real Estate Agent",
            "type":"Services"
        }
    ],
    "sg:phone":"+1 516 771 8276",
    "sg:postcode":"11510",
    "sg:province":"NY",
    "wof:name":"Atlantico Realty",
    "wof:placetype":"venue"
},
  "geometry": {"coordinates":[-73.604422,40.640213],"type":"Point"}
}