{
  "type": "Feature",
  "properties": {
    "iso:country":"US",
    "sg:address":"47 N Cottage St",
    "sg:city":"Valley Stream",
    "sg:classifiers":[
        {
            "category":"Professional",
            "subcategory":"Detective & Security Services",
            "type":"Services"
        }
    ],
    "sg:phone":"+1   ",
    "sg:postcode":"11580",
    "sg:province":"NY",
    "sg:tags":[
        "car"
    ],
    "wof:name":"Car Lynn Security",
    "wof:placetype":"venue"
},
  "geometry": {"coordinates":[-73.693963,40.665946],"type":"Point"}
}