{
  "type": "Feature",
  "properties": {
    "iso:country":"US",
    "sg:address":"108 Whitehouse Rd",
    "sg:city":"Hartwick",
    "sg:classifiers":[
        {
            "category":"Food & Beverages",
            "subcategory":"Meat & Fish",
            "type":"Retail Goods"
        }
    ],
    "sg:phone":"+1   ",
    "sg:postcode":"13348",
    "sg:province":"NY",
    "wof:name":"Tedesco Custom Meat Cutting",
    "wof:placetype":"venue"
},
  "geometry": {"coordinates":[-75.060385,42.690161],"type":"Point"}
}