{
  "type": "Feature",
  "properties": {
    "addr:full":"3113 N 7th St Allegany NY 14706",
    "addr:housenumber":"3113",
    "addr:postcode":"14706",
    "addr:street":"N 7Th St",
    "iso:country":"US",
    "sg:address":"3113 N 7th St",
    "sg:city":"Allegany",
    "sg:classifiers":[
        {
            "category":"Retail",
            "subcategory":"Auto Repair",
            "type":"Services"
        }
    ],
    "sg:phone":"+1 716 373 0888",
    "sg:postcode":"14706",
    "sg:province":"NY",
    "sg:tags":[
        "truck"
    ],
    "wof:name":"All American Truck Svc LLC",
    "wof:placetype":"venue"
},
  "geometry": {"coordinates":[-78.467777,42.093326],"type":"Point"}
}