{
  "type": "Feature",
  "properties": {
    "addr:full":"1155 Nine Foot Rd Phelps NY 14532",
    "addr:housenumber":"1155",
    "addr:postcode":"14532",
    "addr:street":"Foot Rd",
    "iso:country":"US",
    "sg:address":"1155 Nine Foot Rd",
    "sg:city":"Phelps",
    "sg:classifiers":[
        {
            "category":"Building & Trades",
            "subcategory":"Construction",
            "type":"Services"
        }
    ],
    "sg:phone":"+1 315 539 3845",
    "sg:postcode":"14532",
    "sg:province":"NY",
    "sg:tags":[
        "home"
    ],
    "wof:name":"Bowen Construction",
    "wof:placetype":"venue"
},
  "geometry": {"coordinates":[-76.92649900000001,42.973026],"type":"Point"}
}