{
  "type": "Feature",
  "properties": {
    "addr:full":"110 53rd St Brooklyn NY 11232",
    "addr:housenumber":"110",
    "addr:postcode":"11232",
    "addr:street":"53Rd St",
    "iso:country":"US",
    "sg:address":"110 53rd St",
    "sg:city":"Brooklyn",
    "sg:classifiers":[
        {
            "category":"Building & Trades",
            "subcategory":"Electrical",
            "type":"Services"
        }
    ],
    "sg:phone":"+1 718 567 3988",
    "sg:postcode":"11232",
    "sg:province":"NY",
    "sg:tags":[
        "electric",
        "contractor"
    ],
    "wof:name":"Sound Beyond Electrical Corp",
    "wof:placetype":"venue"
},
  "geometry": {"coordinates":[-74.020753,40.648548],"type":"Point"}
}