{
  "type": "Feature",
  "properties": {
    "iso:country":"US",
    "sg:address":"265 Co Rd 33",
    "sg:city":"Bloomville",
    "sg:phone":"+1 607 538 9808",
    "sg:postcode":"13760",
    "sg:province":"NY",
    "sg:tags":[
        "farm"
    ],
    "wof:name":"Gerard Stoeckel",
    "wof:placetype":"venue"
},
  "geometry": {"coordinates":[-76.017713,42.115954],"type":"Point"}
}