{
  "type": "Feature",
  "properties": {
    "iso:country":"US",
    "sg:address":"15 Maplewood Pkwy",
    "sg:city":"South Glens Falls",
    "sg:classifiers":[
        {
            "category":"Organizations",
            "subcategory":"Religious Organization",
            "type":"Services"
        }
    ],
    "sg:phone":"+1 518 793 1152",
    "sg:postcode":"12803",
    "sg:province":"NY",
    "wof:name":"South Glens Falls United Meth",
    "wof:placetype":"venue"
},
  "geometry": {"coordinates":[-73.648113,43.278164],"type":"Point"}
}