{
  "type": "Feature",
  "properties": {
    "addr:full":"19 Searington Dr Syosset NY 11791",
    "addr:housenumber":"19",
    "addr:postcode":"11791",
    "addr:street":"Searington Dr",
    "iso:country":"US",
    "sg:address":"19 Searington Dr",
    "sg:city":"Syosset",
    "sg:classifiers":[
        {
            "category":"Real Estate",
            "subcategory":"Real Estate Services",
            "type":"Services"
        },
        {
            "category":"Real Estate",
            "subcategory":"Real Estate Agent",
            "type":"Services"
        }
    ],
    "sg:phone":"+1 516 921 5858",
    "sg:postcode":"11791",
    "sg:province":"NY",
    "sg:tags":[
        "buyer",
        "broker"
    ],
    "wof:name":"Ron Bunch & Sons Realty Corp",
    "wof:placetype":"venue"
},
  "geometry": {"coordinates":[-73.485423,40.826458],"type":"Point"}
}