{
  "type": "Feature",
  "properties": {
    "addr:full":"4127 Broadway New York NY 10033",
    "addr:housenumber":"4127",
    "addr:postcode":"10033",
    "addr:street":"Broadway",
    "iso:country":"US",
    "sg:address":"4127 Broadway",
    "sg:city":"New York",
    "sg:classifiers":[
        {
            "category":"Communications",
            "type":"Services"
        }
    ],
    "sg:phone":"+1 212 781 4660",
    "sg:postcode":"10033",
    "sg:province":"NY",
    "wof:name":"Dominican Communication",
    "wof:placetype":"venue"
},
  "geometry": {"coordinates":[-73.93862300000001,40.845779],"type":"Point"}
}