{
  "type": "Feature",
  "properties": {
    "addr:full":"51 Campwoods Rd Ossining NY 10562",
    "addr:housenumber":"51",
    "addr:postcode":"10562",
    "addr:street":"Campwoods Rd",
    "iso:country":"US",
    "sg:address":"51 Campwoods Rd",
    "sg:city":"Ossining",
    "sg:phone":"+1 914 941 6525",
    "sg:postcode":"10562",
    "sg:province":"NY",
    "sg:tags":[
        "internet",
        "bicycle",
        "display",
        "sales"
    ],
    "wof:name":"Whatevers Clever Inc",
    "wof:placetype":"venue"
},
  "geometry": {"coordinates":[-73.84139999999999,41.170976],"type":"Point"}
}