{
  "type": "Feature",
  "properties": {
    "iso:country":"US",
    "sg:address":"3 Congress Dr",
    "sg:city":"Washingtonville",
    "sg:classifiers":[
        {
            "category":"Building & Trades",
            "subcategory":"Landscaping Services",
            "type":"Services"
        }
    ],
    "sg:phone":"+1 845 496 5295",
    "sg:postcode":"10992",
    "sg:province":"NY",
    "sg:tags":[
        "landscape"
    ],
    "wof:name":"Petes Landscaping",
    "wof:placetype":"venue"
},
  "geometry": {"coordinates":[-74.14279000000001,41.43626],"type":"Point"}
}