{
  "type": "Feature",
  "properties": {
    "addr:full":"6983 McKay Rd Mayville NY 14757",
    "addr:housenumber":"6983",
    "addr:postcode":"14757",
    "addr:street":"Mckay Rd",
    "iso:country":"US",
    "sg:address":"6983 McKay Rd",
    "sg:city":"Mayville",
    "sg:classifiers":[
        {
            "category":"Shopping",
            "subcategory":"Computers & Home Electronics",
            "type":"Retail Goods"
        }
    ],
    "sg:phone":"+1   ",
    "sg:postcode":"14757",
    "sg:province":"NY",
    "sg:tags":[
        "repair"
    ],
    "wof:name":"Westpfahl Sales & Service",
    "wof:placetype":"venue"
},
  "geometry": {"coordinates":[-79.515305,42.240871],"type":"Point"}
}