{
  "type": "Feature",
  "properties": {
    "iso:country":"US",
    "sg:address":"51 Chapel St",
    "sg:city":"Windsor",
    "sg:classifiers":[
        {
            "category":"Insurance",
            "subcategory":"Insurance Agent",
            "type":"Services"
        },
        {
            "category":"Insurance",
            "subcategory":"Hazard Insurance",
            "type":"Services"
        }
    ],
    "sg:phone":"+1 607 655 1291",
    "sg:postcode":"13865",
    "sg:province":"NY",
    "sg:tags":[
        "property",
        "commercial",
        "casualty",
        "business"
    ],
    "sg:website":"http://www.broomecooperative.com",
    "wof:name":"Broome County Cooperative Fire Insurance Company Inc",
    "wof:placetype":"venue"
},
  "geometry": {"coordinates":[-75.64320499999999,42.076266],"type":"Point"}
}