{
  "type": "Feature",
  "properties": {
    "iso:country":"US",
    "sg:address":"11 Weaver St",
    "sg:city":"Greenwich",
    "sg:classifiers":[
        {
            "category":"Communications",
            "type":"Services"
        }
    ],
    "sg:phone":"+1 203 531 9141",
    "sg:postcode":"06831",
    "sg:province":"NY",
    "sg:website":"www.theshermangroup.com",
    "wof:name":"Blackbird Communication",
    "wof:placetype":"venue"
},
  "geometry": {"coordinates":[-73.650238,41.01675],"type":"Point"}
}