{
  "type": "Feature",
  "properties": {
    "iso:country":"US",
    "sg:address":"327 Gloria Pl",
    "sg:city":"Franklin Square",
    "sg:classifiers":[
        {
            "category":"Professional",
            "subcategory":"Computer Services",
            "type":"Services"
        }
    ],
    "sg:phone":"+1 212 730 5965",
    "sg:postcode":"11010",
    "sg:province":"NY",
    "sg:tags":[
        "repair"
    ],
    "wof:name":"Superior Computer Svc",
    "wof:placetype":"venue"
},
  "geometry": {"coordinates":[-73.66647500000001,40.717035],"type":"Point"}
}