{
  "type": "Feature",
  "properties": {
    "iso:country":"US",
    "sg:address":"420 Main St",
    "sg:city":"Buffalo",
    "sg:classifiers":[
        {
            "category":"Professional",
            "subcategory":"Lawyer & Legal Services",
            "type":"Services"
        }
    ],
    "sg:phone":"+1 716 854 3400",
    "sg:postcode":"14202",
    "sg:province":"NY",
    "wof:name":"Pfalzgraf David R Jr Atty",
    "wof:placetype":"venue"
},
  "geometry": {"coordinates":[-78.874397,42.885502],"type":"Point"}
}