{
  "type": "Feature",
  "properties": {
    "iso:country":"US",
    "sg:address":"131 Varick Street 9th floor",
    "sg:city":"New York",
    "sg:classifiers":[
        {
            "category":"Professional",
            "subcategory":"Computer Services",
            "type":"Services"
        }
    ],
    "sg:phone":"+1 800 995 7586",
    "sg:postcode":"10013",
    "sg:province":"NY",
    "sg:tags":[
        "ivr",
        "saas",
        "voip",
        "voice",
        "speech-recognition",
        "voicexml"
    ],
    "sg:website":"http://www.plumvoice.com/",
    "wof:name":"Plum Voice ",
    "wof:placetype":"venue"
},
  "geometry": {"coordinates":[-74.00590699999999,40.725295],"type":"Point"}
}