{
  "type": "Feature",
  "properties": {
    "addr:full":"1448 Mill Rd East Aurora NY 14052",
    "addr:housenumber":"1448",
    "addr:postcode":"14052",
    "addr:street":"Mill Rd",
    "iso:country":"US",
    "sg:address":"1448 Mill Rd",
    "sg:city":"East Aurora",
    "sg:classifiers":[
        {
            "category":"Wholesale",
            "subcategory":"Home Furnishings",
            "type":"Manufacturing & Wholesale Goods"
        }
    ],
    "sg:phone":"+1 716 652 7530",
    "sg:postcode":"14052",
    "sg:province":"NY",
    "wof:name":"Ronald G Flett",
    "wof:placetype":"venue"
},
  "geometry": {"coordinates":[-78.65141,42.72558],"type":"Point"}
}