{
  "type": "Feature",
  "properties": {
    "addr:full":"17 1st St Utica NY 13501",
    "addr:housenumber":"17",
    "addr:postcode":"13501",
    "addr:street":"1St St",
    "iso:country":"US",
    "sg:address":"17 1st St",
    "sg:city":"Utica",
    "sg:classifiers":[
        {
            "category":"Manufacturing",
            "subcategory":"Printing",
            "type":"Manufacturing & Wholesale Goods"
        }
    ],
    "sg:phone":"+1   ",
    "sg:postcode":"13501",
    "sg:province":"NY",
    "sg:tags":[
        "lithographic",
        "commercial"
    ],
    "wof:name":"Quinn Printing Inc",
    "wof:placetype":"venue"
},
  "geometry": {"coordinates":[-75.222903,43.103683],"type":"Point"}
}