{
  "type": "Feature",
  "properties": {
    "iso:country":"US",
    "sg:address":"126 S Main St",
    "sg:city":"Naples",
    "sg:classifiers":[
        {
            "category":"Real Estate",
            "subcategory":"Real Estate Agent",
            "type":"Services"
        }
    ],
    "sg:phone":"+1 585 374 6560",
    "sg:postcode":"14512",
    "sg:province":"NY",
    "sg:website":"www.nothnagle.com",
    "wof:name":"Nothnagle Realtors",
    "wof:placetype":"venue"
},
  "geometry": {"coordinates":[-77.403205,42.614135],"type":"Point"}
}