{
  "type": "Feature",
  "properties": {
    "addr:full":"13533 38th Ave Flushing NY 11354",
    "addr:housenumber":"13533",
    "addr:postcode":"11354",
    "addr:street":"38Th Ave",
    "iso:country":"US",
    "sg:address":"13533 38th Ave",
    "sg:city":"Flushing",
    "sg:classifiers":[
        {
            "category":"Travel",
            "subcategory":"Hotels & Motels",
            "type":"Entertainment"
        }
    ],
    "sg:phone":"+1 718 461 3888",
    "sg:postcode":"11354",
    "sg:province":"NY",
    "wof:name":"Imperial Hotel",
    "wof:placetype":"venue"
},
  "geometry": {"coordinates":[-73.831299,40.7607],"type":"Point"}
}