{
  "type": "Feature",
  "properties": {
    "addr:full":"158 Lake Shore Dr E Dunkirk NY 14048",
    "addr:housenumber":"158",
    "addr:postcode":"14048",
    "addr:street":"Lake Shore Dr E",
    "iso:country":"US",
    "sg:address":"158 Lake Shore Dr E",
    "sg:city":"Dunkirk",
    "sg:classifiers":[
        {
            "category":"Personal",
            "subcategory":"Tattoo Parlor",
            "type":"Services"
        }
    ],
    "sg:phone":"+1 716 366 2706",
    "sg:postcode":"14048",
    "sg:province":"NY",
    "sg:tags":[
        "tattooing"
    ],
    "wof:name":"Cattoos",
    "wof:placetype":"venue"
},
  "geometry": {"coordinates":[-79.32699700000001,42.488595],"type":"Point"}
}