{
  "type": "Feature",
  "properties": {
    "iso:country":"US",
    "sg:address":"1285 1st Ave",
    "sg:city":"New York",
    "sg:classifiers":[
        {
            "category":"Banks & Credit Unions",
            "subcategory":"Bank",
            "type":"Services"
        }
    ],
    "sg:phone":"+1 212 249 4550",
    "sg:postcode":"10021",
    "sg:province":"NY",
    "sg:website":"www.citibank.com",
    "wof:name":"Citibank N A",
    "wof:placetype":"venue"
},
  "geometry": {"coordinates":[-73.957397,40.766102],"type":"Point"}
}