{
  "type": "Feature",
  "properties": {
    "addr:full":"205 E 167th St Bronx NY 10456",
    "addr:housenumber":"205",
    "addr:postcode":"10456",
    "addr:street":"E 167Th St",
    "iso:country":"US",
    "sg:address":"205 E 167th St",
    "sg:city":"Bronx",
    "sg:classifiers":[
        {
            "category":"Food & Beverages",
            "subcategory":"Groceries & Convenience Stores",
            "type":"Retail Goods"
        }
    ],
    "sg:phone":"+1   ",
    "sg:postcode":"10456",
    "sg:province":"NY",
    "wof:name":"De Las Nueces Grocery",
    "wof:placetype":"venue"
},
  "geometry": {"coordinates":[-73.91596,40.833971],"type":"Point"}
}