{
  "type": "Feature",
  "properties": {
    "iso:country":"US",
    "sg:address":"300 Morgan Ave",
    "sg:city":"Brooklyn",
    "sg:classifiers":[
        {
            "category":"Manufacturing",
            "subcategory":"Textiles",
            "type":"Manufacturing & Wholesale Goods"
        }
    ],
    "sg:phone":"+1   ",
    "sg:postcode":"11211",
    "sg:province":"NY",
    "sg:tags":[
        "upholstery",
        "mfg"
    ],
    "wof:name":"Contract Workroom Inc",
    "wof:placetype":"venue"
},
  "geometry": {"coordinates":[-73.934988,40.713807],"type":"Point"}
}