{
  "type": "Feature",
  "properties": {
    "addr:full":"RR 9 Box D Hughsonville NY 12537",
    "addr:postcode":"12537",
    "addr:street":"Rr 9 Box D Hughsonville",
    "iso:country":"US",
    "sg:address":"RR 9 Box D",
    "sg:city":"Hughsonville",
    "sg:classifiers":[
        {
            "category":"Food & Beverages",
            "subcategory":"Groceries & Convenience Stores",
            "type":"Retail Goods"
        }
    ],
    "sg:phone":"+1 845 297 9987",
    "sg:postcode":"12537",
    "sg:province":"NY",
    "wof:name":"Convenient Food Mart # 5614",
    "wof:placetype":"venue"
},
  "geometry": {"coordinates":[-73.91100299999999,41.578899],"type":"Point"}
}