{
  "type": "Feature",
  "properties": {
    "iso:country":"US",
    "sg:address":"266 Anchor Way",
    "sg:city":"Uniondale",
    "sg:classifiers":[
        {
            "category":"Building & Trades",
            "subcategory":"Construction",
            "type":"Services"
        }
    ],
    "sg:phone":"+1 516 489 8407",
    "sg:postcode":"11553",
    "sg:province":"NY",
    "sg:tags":[
        "home",
        "improvement"
    ],
    "wof:name":"Mr Fix It",
    "wof:placetype":"venue"
},
  "geometry": {"coordinates":[-73.583804,40.714107],"type":"Point"}
}