{
  "type": "Feature",
  "properties": {
    "addr:full":"1217 White Plains Rd Bronx NY 10472",
    "addr:housenumber":"1217",
    "addr:postcode":"10472",
    "addr:street":"White Plains Rd",
    "iso:country":"US",
    "sg:address":"1217 White Plains Rd",
    "sg:city":"Bronx",
    "sg:classifiers":[
        {
            "category":"Food & Beverages",
            "subcategory":"Groceries & Convenience Stores",
            "type":"Retail Goods"
        }
    ],
    "sg:phone":"+1   ",
    "sg:postcode":"10472",
    "sg:province":"NY",
    "wof:name":"Afteb Grocery Halalmeat",
    "wof:placetype":"venue"
},
  "geometry": {"coordinates":[-73.862632,40.832545],"type":"Point"}
}