{
  "type": "Feature",
  "properties": {
    "iso:country":"US",
    "sg:address":"514 West 169 Street Suite #1W",
    "sg:city":"New York",
    "sg:classifiers":[
        {
            "category":"Real Estate",
            "subcategory":"Real Estate Services",
            "type":"Services"
        }
    ],
    "sg:phone":"+1 212 543 1112",
    "sg:postcode":"10032",
    "sg:province":"NY",
    "sg:tags":[
        "management",
        "property"
    ],
    "sg:website":"www.cflmanagementservices.com",
    "wof:name":"CFL Management Services, LLC",
    "wof:placetype":"venue"
},
  "geometry": {"coordinates":[-73.93740699999999,40.840637],"type":"Point"}
}