{
  "type": "Feature",
  "properties": {
    "addr:full":"6351 S Bay Rd Cicero NY 13039",
    "addr:housenumber":"6351",
    "addr:postcode":"13039",
    "addr:street":"S Bay Rd",
    "iso:country":"US",
    "sg:address":"6351 S Bay Rd",
    "sg:city":"Cicero",
    "sg:classifiers":[
        {
            "category":"Utilities",
            "type":"Services"
        }
    ],
    "sg:phone":"+1 315 699 7562",
    "sg:postcode":"13039",
    "sg:province":"NY",
    "sg:tags":[
        "landscaping",
        "plowing",
        "snow",
        "contractor"
    ],
    "wof:name":"C Mattes Snowplowing & Ldscpg",
    "wof:placetype":"venue"
},
  "geometry": {"coordinates":[-76.08525,43.171969],"type":"Point"}
}