{
  "type": "Feature",
  "properties": {
    "iso:country":"US",
    "sg:address":"1919 Coon Hill Rd",
    "sg:city":"Skaneateles",
    "sg:classifiers":[
        {
            "category":"Wholesale",
            "subcategory":"Hardware",
            "type":"Manufacturing & Wholesale Goods"
        }
    ],
    "sg:phone":"+1 315 685 0672",
    "sg:postcode":"13152",
    "sg:province":"NY",
    "sg:tags":[
        "purifying",
        "cleaning",
        "air"
    ],
    "wof:name":"Hangar",
    "wof:placetype":"venue"
},
  "geometry": {"coordinates":[-76.362718,42.918448],"type":"Point"}
}