{
  "type": "Feature",
  "properties": {
    "addr:full":"1 Brush Hollow Rd Westbury NY 11590",
    "addr:housenumber":"1",
    "addr:postcode":"11590",
    "addr:street":"Brush Hollow Rd",
    "iso:country":"US",
    "sg:address":"1 Brush Hollow Rd",
    "sg:city":"Westbury",
    "sg:classifiers":[
        {
            "category":"Banks & Credit Unions",
            "subcategory":"Bank",
            "type":"Services"
        }
    ],
    "sg:phone":"+1 516 334 2280",
    "sg:postcode":"11590",
    "sg:province":"NY",
    "sg:website":"www.citibank.com",
    "wof:name":"Citibank N.A.",
    "wof:placetype":"venue"
},
  "geometry": {"coordinates":[-73.558587,40.778791],"type":"Point"}
}