{
  "type": "Feature",
  "properties": {
    "iso:country":"US",
    "sg:address":"4245 Coye Rd",
    "sg:city":"Jamesville",
    "sg:classifiers":[
        {
            "category":"Manufacturing",
            "subcategory":"Rubber & Plastics",
            "type":"Manufacturing & Wholesale Goods"
        }
    ],
    "sg:phone":"+1   ",
    "sg:postcode":"13078",
    "sg:province":"NY",
    "sg:tags":[
        "product",
        "mfg"
    ],
    "wof:name":"Pennon Company Inc",
    "wof:placetype":"venue"
},
  "geometry": {"coordinates":[-76.080065,42.97934],"type":"Point"}
}