{
  "type": "Feature",
  "properties": {
    "addr:full":"1540 Central Ave Albany NY 12205",
    "addr:housenumber":"1540",
    "addr:postcode":"12205",
    "addr:street":"Central Ave",
    "iso:country":"US",
    "sg:address":"1540 Central Ave",
    "sg:city":"Albany",
    "sg:classifiers":[
        {
            "category":"Personal",
            "subcategory":"Beauty Salon",
            "type":"Services"
        }
    ],
    "sg:phone":"+1 518 869 1391",
    "sg:postcode":"12205",
    "sg:province":"NY",
    "sg:tags":[
        "shop"
    ],
    "wof:name":"Scissors III Hair Nail Design",
    "wof:placetype":"venue"
},
  "geometry": {"coordinates":[-73.828228,42.71351],"type":"Point"}
}