{
  "type": "Feature",
  "properties": {
    "addr:full":"80 S Kensico Ave White Plains NY 10601",
    "addr:housenumber":"80",
    "addr:postcode":"10601",
    "addr:street":"S Kensico Ave",
    "iso:country":"US",
    "sg:address":"80 S Kensico Ave",
    "sg:city":"White Plains",
    "sg:classifiers":[
        {
            "category":"Freight",
            "type":"Transportation"
        }
    ],
    "sg:phone":"+1   ",
    "sg:postcode":"10601",
    "sg:province":"NY",
    "sg:tags":[
        "self",
        "storage",
        "facility"
    ],
    "wof:name":"Susa Partnership LP",
    "wof:placetype":"venue"
},
  "geometry": {"coordinates":[-73.758701,41.03726],"type":"Point"}
}