{
  "type": "Feature",
  "properties": {
    "iso:country":"US",
    "sg:address":"228 Washington St",
    "sg:city":"Saratoga Springs",
    "sg:classifiers":[
        {
            "category":"Building & Trades",
            "subcategory":"Construction",
            "type":"Services"
        }
    ],
    "sg:phone":"+1 518 583 2923",
    "sg:postcode":"12866",
    "sg:province":"NY",
    "sg:tags":[
        "contractor"
    ],
    "wof:name":"Islander Pools & Spas Plus",
    "wof:placetype":"venue"
},
  "geometry": {"coordinates":[-73.79815499999999,43.080048],"type":"Point"}
}