{
  "type": "Feature",
  "properties": {
    "addr:full":"135 E 144th St Bronx NY 10451",
    "addr:housenumber":"135",
    "addr:postcode":"10451",
    "addr:street":"E 144Th St",
    "iso:country":"US",
    "sg:address":"135 E 144th St",
    "sg:city":"Bronx",
    "sg:classifiers":[
        {
            "category":"Real Estate",
            "subcategory":"Real Estate Agent",
            "type":"Services"
        }
    ],
    "sg:phone":"+1 718 292 5810",
    "sg:postcode":"10451",
    "sg:province":"NY",
    "wof:name":"Bridge Realty Co",
    "wof:placetype":"venue"
},
  "geometry": {"coordinates":[-73.929672,40.817048],"type":"Point"}
}