{
  "type": "Feature",
  "properties": {
    "addr:full":"1 Utopian Ave Suffern NY 10901",
    "addr:housenumber":"1",
    "addr:postcode":"10901",
    "addr:street":"Utopian Ave",
    "iso:country":"US",
    "sg:address":"1 Utopian Ave",
    "sg:city":"Suffern",
    "sg:classifiers":[
        {
            "category":"Shopping",
            "subcategory":"Crafts & Fabrics",
            "type":"Retail Goods"
        }
    ],
    "sg:phone":"+1   ",
    "sg:postcode":"10901",
    "sg:province":"NY",
    "sg:tags":[
        "sewing"
    ],
    "wof:name":"Bucks",
    "wof:placetype":"venue"
},
  "geometry": {"coordinates":[-74.140636,41.123563],"type":"Point"}
}