{
  "type": "Feature",
  "properties": {
    "iso:country":"US",
    "sg:address":"100 Carver Loop",
    "sg:city":"Bronx",
    "sg:classifiers":[
        {
            "category":"Real Estate",
            "subcategory":"Real Estate Operator",
            "type":"Services"
        }
    ],
    "sg:phone":"+1 718 320 0193",
    "sg:postcode":"10475",
    "sg:province":"NY",
    "sg:tags":[
        "building",
        "apartment"
    ],
    "wof:name":"Gordon & Grant Apts",
    "wof:placetype":"venue"
},
  "geometry": {"coordinates":[-73.825351,40.879387],"type":"Point"}
}