{
  "type": "Feature",
  "properties": {
    "addr:full":"1169 Ocean Ave Brooklyn NY 11230",
    "addr:housenumber":"1169",
    "addr:postcode":"11230",
    "addr:street":"Ocean Ave",
    "iso:country":"US",
    "sg:address":"1169 Ocean Ave",
    "sg:city":"Brooklyn",
    "sg:classifiers":[
        {
            "category":"Shopping",
            "subcategory":"Jewelry",
            "type":"Retail Goods"
        }
    ],
    "sg:phone":"+1   ",
    "sg:postcode":"11230",
    "sg:province":"NY",
    "wof:name":"Karolyn Jewels",
    "wof:placetype":"venue"
},
  "geometry": {"coordinates":[-73.95790100000001,40.634486],"type":"Point"}
}