{
  "type": "Feature",
  "properties": {
    "iso:country":"US",
    "sg:address":"17 Peter Dr",
    "sg:city":"Albany",
    "sg:classifiers":[
        {
            "category":"Building & Trades",
            "subcategory":"Construction",
            "type":"Services"
        }
    ],
    "sg:phone":"+1 518 452 8636",
    "sg:postcode":"12205",
    "sg:province":"NY",
    "sg:tags":[
        "house",
        "general",
        "contractor"
    ],
    "wof:name":"Saratoga Contracting Services",
    "wof:placetype":"venue"
},
  "geometry": {"coordinates":[-73.82478,42.724359],"type":"Point"}
}