{
  "type": "Feature",
  "properties": {
    "addr:full":"82 E Meadow Ave East Meadow NY 11554",
    "addr:housenumber":"82",
    "addr:postcode":"11554",
    "addr:street":"E Meadow Ave",
    "iso:country":"US",
    "sg:address":"82 E Meadow Ave",
    "sg:city":"East Meadow",
    "sg:classifiers":[
        {
            "category":"Building & Trades",
            "subcategory":"Construction",
            "type":"Services"
        }
    ],
    "sg:phone":"+1 516 385 1899",
    "sg:postcode":"11554",
    "sg:province":"NY",
    "sg:tags":[
        "fence",
        "contractor"
    ],
    "wof:name":"Shamrock Fence",
    "wof:placetype":"venue"
},
  "geometry": {"coordinates":[-73.56546,40.721934],"type":"Point"}
}