{
  "type": "Feature",
  "properties": {
    "iso:country":"US",
    "sg:address":"2 Merryhill Dr",
    "sg:city":"Rochester",
    "sg:classifiers":[
        {
            "category":"Retail",
            "subcategory":"Auto Repair",
            "type":"Services"
        }
    ],
    "sg:phone":"+1   ",
    "sg:postcode":"14625",
    "sg:province":"NY",
    "sg:tags":[
        "body"
    ],
    "wof:name":"Klb Furniture Finishing Inc",
    "wof:placetype":"venue"
},
  "geometry": {"coordinates":[-77.502562,43.16513],"type":"Point"}
}