{
  "type": "Feature",
  "properties": {
    "iso:country":"US",
    "sg:address":"203 William St",
    "sg:city":"Elmira",
    "sg:classifiers":[
        {
            "category":"Government",
            "subcategory":"Office",
            "type":"Public Place"
        }
    ],
    "sg:phone":"+1 607 737 2987",
    "sg:postcode":"14901",
    "sg:province":"NY",
    "wof:name":"Chemung County Traffic Safety",
    "wof:placetype":"venue"
},
  "geometry": {"coordinates":[-76.800921,42.091196],"type":"Point"}
}