{
  "type": "Feature",
  "properties": {
    "addr:full":"80 Grasslands Rd Valhalla NY 10595",
    "addr:housenumber":"80",
    "addr:postcode":"10595",
    "addr:street":"Grasslands Rd",
    "iso:country":"US",
    "sg:address":"80 Grasslands Rd",
    "sg:city":"Valhalla",
    "sg:classifiers":[
        {
            "category":"Coffee & Tea",
            "type":"Food & Drink"
        },
        {
            "category":"Restaurant",
            "type":"Food & Drink"
        }
    ],
    "sg:phone":"+1 914 347 2666",
    "sg:postcode":"10595",
    "sg:province":"NY",
    "sg:tags":[
        "espresso"
    ],
    "wof:name":"Heritage Cafe",
    "wof:placetype":"venue"
},
  "geometry": {"coordinates":[-73.78349900000001,41.070075],"type":"Point"}
}