{
  "type": "Feature",
  "properties": {
    "iso:country":"US",
    "sg:address":"11 Fleetwood Ter",
    "sg:city":"Williamsville",
    "sg:classifiers":[
        {
            "category":"Health Services",
            "subcategory":"Doctor",
            "type":"Services"
        }
    ],
    "sg:phone":"+1 716 632 0114",
    "sg:postcode":"14221",
    "sg:province":"NY",
    "sg:tags":[
        "dentist"
    ],
    "wof:name":"Rene Perez-Bode DDS",
    "wof:placetype":"venue"
},
  "geometry": {"coordinates":[-78.7577,42.982807],"type":"Point"}
}