{
  "type": "Feature",
  "properties": {
    "iso:country":"US",
    "sg:address":"237 Pelton Avenue",
    "sg:city":"Staten Island",
    "sg:classifiers":[
        {
            "category":"Education",
            "subcategory":"School",
            "type":"Public Place"
        }
    ],
    "sg:phone":"+1 718 447 0291",
    "sg:postcode":"10310",
    "sg:province":"NY",
    "wof:name":"Notre Dame Academy",
    "wof:placetype":"venue"
},
  "geometry": {"coordinates":[-74.110046,40.634599],"type":"Point"}
}