{
  "type": "Feature",
  "properties": {
    "addr:full":"256 Glen St Glen Cove NY 11542",
    "addr:housenumber":"256",
    "addr:postcode":"11542",
    "addr:street":"Glen St",
    "iso:country":"US",
    "sg:address":"256 Glen St",
    "sg:city":"Glen Cove",
    "sg:classifiers":[
        {
            "category":"Insurance",
            "subcategory":"Insurance Agent",
            "type":"Services"
        }
    ],
    "sg:phone":"+1 516 759 9500",
    "sg:postcode":"11542",
    "sg:province":"NY",
    "wof:name":"Allstate Insurance Co",
    "wof:placetype":"venue"
},
  "geometry": {"coordinates":[-73.621599,40.860099],"type":"Point"}
}