{
  "type": "Feature",
  "properties": {
    "iso:country":"US",
    "sg:address":"22 Highland Dr",
    "sg:city":"East Aurora",
    "sg:classifiers":[
        {
            "category":"Professional",
            "type":"Services"
        }
    ],
    "sg:phone":"+1 716 652 6787",
    "sg:postcode":"14052",
    "sg:province":"NY",
    "sg:tags":[
        "establishment"
    ],
    "wof:name":"C N Development",
    "wof:placetype":"venue"
},
  "geometry": {"coordinates":[-78.616906,42.780145],"type":"Point"}
}