{
  "type": "Feature",
  "properties": {
    "iso:country":"US",
    "sg:address":"53 Rochelle St",
    "sg:city":"Rochester",
    "sg:classifiers":[
        {
            "category":"Building & Trades",
            "subcategory":"Construction",
            "type":"Services"
        }
    ],
    "sg:phone":"+1 585 621 3694",
    "sg:postcode":"14612",
    "sg:province":"NY",
    "sg:tags":[
        "contractor"
    ],
    "wof:name":"Wulfs Chimneys & Venting",
    "wof:placetype":"venue"
},
  "geometry": {"coordinates":[-77.627459,43.229178],"type":"Point"}
}