{
  "type": "Feature",
  "properties": {
    "addr:full":"2035 2 Ave New York NY 10029",
    "addr:housenumber":"2035",
    "addr:postcode":"10029",
    "addr:street":"2 Ave",
    "iso:country":"US",
    "sg:address":"2035 2 Ave",
    "sg:city":"New York",
    "sg:classifiers":[
        {
            "category":"Retail",
            "subcategory":"Repair Shop",
            "type":"Services"
        }
    ],
    "sg:phone":"+1 917 289 8073",
    "sg:postcode":"10029",
    "sg:province":"NY",
    "sg:tags":[
        "lock",
        "locksmith"
    ],
    "wof:name":"24 Hour 7 Day Emerg Locksmith",
    "wof:placetype":"venue"
},
  "geometry": {"coordinates":[-73.94658699999999,40.784941],"type":"Point"}
}