{
  "type": "Feature",
  "properties": {
    "iso:country":"US",
    "sg:address":"476 Clinton Ave",
    "sg:city":"Brooklyn",
    "sg:classifiers":[
        {
            "category":"Real Estate",
            "subcategory":"Real Estate Agent",
            "type":"Services"
        }
    ],
    "sg:phone":"+1 718 636 9659",
    "sg:postcode":"11238",
    "sg:province":"NY",
    "wof:name":"476 Properties Corporation",
    "wof:placetype":"venue"
},
  "geometry": {"coordinates":[-73.967001,40.683722],"type":"Point"}
}