{
  "type": "Feature",
  "properties": {
    "iso:country":"US",
    "sg:address":"224 Fair St",
    "sg:city":"Kingston",
    "sg:classifiers":[
        {
            "category":"Banks & Credit Unions",
            "subcategory":"Investment Brokerage",
            "type":"Services"
        }
    ],
    "sg:phone":"+1 845 331 3420",
    "sg:postcode":"12401",
    "sg:province":"NY",
    "sg:tags":[
        "consultant",
        "planning",
        "financial"
    ],
    "wof:name":"Center For Financial Planning",
    "wof:placetype":"venue"
},
  "geometry": {"coordinates":[-74.01701799999999,41.931145],"type":"Point"}
}