{
  "type": "Feature",
  "properties": {
    "iso:country":"US",
    "sg:address":"25 Village Sq",
    "sg:city":"Glen Cove",
    "sg:classifiers":[
        {
            "category":"Building & Trades",
            "subcategory":"Landscaping Services",
            "type":"Services"
        }
    ],
    "sg:phone":"+1 516 676 0072",
    "sg:postcode":"11542",
    "sg:province":"NY",
    "sg:tags":[
        "designer",
        "landscape"
    ],
    "wof:name":"Michael A Michel & Assoc",
    "wof:placetype":"venue"
},
  "geometry": {"coordinates":[-73.631874,40.864783],"type":"Point"}
}