{
  "type": "Feature",
  "properties": {
    "addr:full":"2725 State Hwy 14 Montour Falls NY 14865",
    "addr:housenumber":"2725",
    "addr:postcode":"14865",
    "addr:street":"State Hwy 14",
    "iso:country":"US",
    "sg:address":"2725 State Hwy 14",
    "sg:city":"Montour Falls",
    "sg:classifiers":[
        {
            "category":"Freight",
            "type":"Transportation"
        }
    ],
    "sg:phone":"+1 607 535 4471",
    "sg:postcode":"14865",
    "sg:province":"NY",
    "sg:tags":[
        "commercial",
        "storage"
    ],
    "wof:name":"Glen Mini-Storage",
    "wof:placetype":"venue"
},
  "geometry": {"coordinates":[-76.83968299999999,42.340881],"type":"Point"}
}