{
  "type": "Feature",
  "properties": {
    "addr:full":"34 Glenside Pl Chappaqua NY 10514",
    "addr:housenumber":"34",
    "addr:postcode":"10514",
    "addr:street":"Glenside Pl",
    "iso:country":"US",
    "sg:address":"34 Glenside Pl",
    "sg:city":"Chappaqua",
    "sg:classifiers":[
        {
            "category":"Communications",
            "type":"Services"
        }
    ],
    "sg:phone":"+1 914 238 2924",
    "sg:postcode":"10514",
    "sg:province":"NY",
    "wof:name":"Schiek Media Group",
    "wof:placetype":"venue"
},
  "geometry": {"coordinates":[-73.772706,41.1539],"type":"Point"}
}