{
  "type": "Feature",
  "properties": {
    "iso:country":"US",
    "sg:address":"331 Mc Kinstry Rd",
    "sg:city":"Gardiner",
    "sg:classifiers":[
        {
            "category":"Farming",
            "subcategory":"Vineyard",
            "type":"Manufacturing & Wholesale Goods"
        }
    ],
    "sg:phone":"+1 845 255 4613",
    "sg:postcode":"12525",
    "sg:province":"NY",
    "wof:name":"Whitecliff Vineyard & Winery",
    "wof:placetype":"venue"
},
  "geometry": {"coordinates":[-74.20779899999999,41.681023],"type":"Point"}
}