{
  "type": "Feature",
  "properties": {
    "addr:full":"372 Van Duzer St Staten Island NY 10304",
    "addr:housenumber":"372",
    "addr:postcode":"10304",
    "addr:street":"Van Duzer St",
    "iso:country":"US",
    "sg:address":"372 Van Duzer St",
    "sg:city":"Staten Island",
    "sg:classifiers":[
        {
            "category":"Bars & Pubs",
            "subcategory":"Lounge",
            "type":"Food & Drink"
        }
    ],
    "sg:phone":"+1 718 442 0660",
    "sg:postcode":"10304",
    "sg:province":"NY",
    "sg:website":"www.martini-red.com",
    "wof:name":"Martini Red",
    "wof:placetype":"venue"
},
  "geometry": {"coordinates":[-74.079611,40.629101],"type":"Point"}
}