{
  "type": "Feature",
  "properties": {
    "addr:full":"505 8 Ave New York NY 10018",
    "addr:housenumber":"505",
    "addr:postcode":"10018",
    "addr:street":"8 Ave",
    "iso:country":"US",
    "sg:address":"505 8 Ave",
    "sg:city":"New York",
    "sg:classifiers":[
        {
            "category":"Professional",
            "subcategory":"Advertising",
            "type":"Services"
        }
    ],
    "sg:phone":"+1 212 564 0237",
    "sg:postcode":"10018",
    "sg:province":"NY",
    "sg:tags":[
        "print",
        "medium",
        "outdoor",
        "representative"
    ],
    "wof:name":"Vital Visions Advertising",
    "wof:placetype":"venue"
},
  "geometry": {"coordinates":[-73.99252799999999,40.753474],"type":"Point"}
}