{
  "type": "Feature",
  "properties": {
    "addr:full":"8524 5th Avenue Brooklyn NY 11209",
    "addr:housenumber":"8524",
    "addr:postcode":"11209",
    "addr:street":"5Th Avenue",
    "iso:country":"US",
    "sg:address":"8524 5th Avenue",
    "sg:city":"Brooklyn",
    "sg:classifiers":[
        {
            "category":"Shopping",
            "subcategory":"Mobile Phones",
            "type":"Retail Goods"
        }
    ],
    "sg:phone":"+1 718 491 6680",
    "sg:postcode":"11209",
    "sg:province":"NY",
    "wof:name":"Verizon Wireless",
    "wof:placetype":"venue"
},
  "geometry": {"coordinates":[-74.026234,40.621685],"type":"Point"}
}