{
  "type": "Feature",
  "properties": {
    "addr:full":"400 Post Ave Westbury NY 11590",
    "addr:housenumber":"400",
    "addr:postcode":"11590",
    "addr:street":"Post Ave",
    "iso:country":"US",
    "sg:address":"400 Post Ave",
    "sg:city":"Westbury",
    "sg:classifiers":[
        {
            "category":"Professional",
            "subcategory":"Business Services",
            "type":"Services"
        }
    ],
    "sg:phone":"+1 516 997 0246",
    "sg:postcode":"11590",
    "sg:province":"NY",
    "sg:tags":[
        "inventory"
    ],
    "sg:website":"www.rgisinv.com",
    "wof:name":"RGIS Inventory Specialists",
    "wof:placetype":"venue"
},
  "geometry": {"coordinates":[-73.586816,40.762747],"type":"Point"}
}