{
  "type": "Feature",
  "properties": {
    "iso:country":"US",
    "sg:address":"691 Oakdale Rd",
    "sg:city":"Johnson City",
    "sg:classifiers":[
        {
            "category":"Shopping",
            "subcategory":"Clothing, Apparel, & Fashions",
            "type":"Retail Goods"
        }
    ],
    "sg:phone":"+1   ",
    "sg:postcode":"13790",
    "sg:province":"NY",
    "sg:tags":[
        "wear"
    ],
    "wof:name":"Limited Too",
    "wof:placetype":"venue"
},
  "geometry": {"coordinates":[-75.976979,42.13731],"type":"Point"}
}