{
  "type": "Feature",
  "properties": {
    "addr:full":"711 Nottingham Rd Syracuse NY 13224",
    "addr:housenumber":"711",
    "addr:postcode":"13224",
    "addr:street":"Nottingham Rd",
    "iso:country":"US",
    "sg:address":"711 Nottingham Rd",
    "sg:city":"Syracuse",
    "sg:classifiers":[
        {
            "category":"Manufacturing",
            "subcategory":"Toys & Sporting Goods",
            "type":"Manufacturing & Wholesale Goods"
        }
    ],
    "sg:phone":"+1   ",
    "sg:postcode":"13224",
    "sg:province":"NY",
    "sg:tags":[
        "mfg"
    ],
    "wof:name":"International Research Assoc",
    "wof:placetype":"venue"
},
  "geometry": {"coordinates":[-76.105639,43.020901],"type":"Point"}
}