{
  "type": "Feature",
  "properties": {
    "addr:full":"3005 Grand Concourse Bronx NY 10468",
    "addr:housenumber":"3005",
    "addr:postcode":"10468",
    "addr:street":"Grand Concourse",
    "iso:country":"US",
    "sg:address":"3005 Grand Concourse",
    "sg:city":"Bronx",
    "sg:classifiers":[
        {
            "category":"Health Services",
            "subcategory":"Doctor",
            "type":"Services"
        }
    ],
    "sg:phone":"+1 718 933 0998",
    "sg:postcode":"10468",
    "sg:province":"NY",
    "sg:tags":[
        "dentist"
    ],
    "wof:name":"Varsha D Shah DDS",
    "wof:placetype":"venue"
},
  "geometry": {"coordinates":[-73.88720000000001,40.873281],"type":"Point"}
}