{
  "type": "Feature",
  "properties": {
    "iso:country":"US",
    "sg:address":"168 Co Rd 101",
    "sg:city":"Gloversville",
    "sg:classifiers":[
        {
            "category":"Building & Trades",
            "subcategory":"Electrical",
            "type":"Services"
        }
    ],
    "sg:phone":"+1 518 725 4488",
    "sg:postcode":"12078",
    "sg:province":"NY",
    "sg:tags":[
        "electric",
        "contractor"
    ],
    "wof:name":"Duffek Electric Robert",
    "wof:placetype":"venue"
},
  "geometry": {"coordinates":[-74.384816,43.055387],"type":"Point"}
}