{
  "type": "Feature",
  "properties": {
    "iso:country":"US",
    "sg:address":"30 4th St",
    "sg:city":"Troy",
    "sg:classifiers":[
        {
            "category":"Shopping",
            "subcategory":"Used Merchandise",
            "type":"Retail Goods"
        }
    ],
    "sg:phone":"+1 518 271 8515",
    "sg:postcode":"12180",
    "sg:province":"NY",
    "sg:tags":[
        "pawnbroker"
    ],
    "wof:name":"Capital City Cash Inc",
    "wof:placetype":"venue"
},
  "geometry": {"coordinates":[-73.688658,42.732911],"type":"Point"}
}