{
  "type": "Feature",
  "properties": {
    "addr:full":"93 Forrest St Brooklyn NY 11206",
    "addr:housenumber":"93",
    "addr:postcode":"11206",
    "addr:street":"Forrest St",
    "iso:country":"US",
    "sg:address":"93 Forrest St",
    "sg:city":"Brooklyn",
    "sg:classifiers":[
        {
            "category":"Building & Trades",
            "subcategory":"Plumbing",
            "type":"Services"
        }
    ],
    "sg:phone":"+1 718 417 6008",
    "sg:postcode":"11206",
    "sg:province":"NY",
    "sg:tags":[
        "contractor"
    ],
    "wof:name":"Metro Plumbing and Heating",
    "wof:placetype":"venue"
},
  "geometry": {"coordinates":[-73.93184599999999,40.703509],"type":"Point"}
}