{
  "type": "Feature",
  "properties": {
    "iso:country":"US",
    "sg:address":"256 W 73 St",
    "sg:city":"New York",
    "sg:classifiers":[
        {
            "category":"Professional",
            "subcategory":"Management & Consulting",
            "type":"Services"
        }
    ],
    "sg:phone":"+1 212 787 3758",
    "sg:postcode":"10023",
    "sg:province":"NY",
    "sg:tags":[
        "consultant",
        "educational"
    ],
    "wof:name":"Dickens Workshop",
    "wof:placetype":"venue"
},
  "geometry": {"coordinates":[-73.98397300000001,40.780402],"type":"Point"}
}