{
  "type": "Feature",
  "properties": {
    "iso:country":"US",
    "sg:address":"1021 Portion Rd",
    "sg:city":"Ronkonkoma",
    "sg:classifiers":[
        {
            "category":"Retail",
            "subcategory":"Laundry & Dry Cleaning",
            "type":"Services"
        }
    ],
    "sg:phone":"+1 631 696 3994",
    "sg:postcode":"11779",
    "sg:province":"NY",
    "sg:tags":[
        "cleaner"
    ],
    "wof:name":"Rainbow Cleaners",
    "wof:placetype":"venue"
},
  "geometry": {"coordinates":[-73.067902,40.8353],"type":"Point"}
}