{
  "type": "Feature",
  "properties": {
    "iso:country":"US",
    "sg:address":"800 Carter St",
    "sg:city":"Rochester",
    "sg:classifiers":[
        {
            "category":"Social Services",
            "type":"Services"
        }
    ],
    "sg:phone":"+1 585 336 4340",
    "sg:postcode":"14621",
    "sg:province":"NY",
    "sg:tags":[
        "senior",
        "citizen"
    ],
    "wof:name":"Just Friends Senior Ctr",
    "wof:placetype":"venue"
},
  "geometry": {"coordinates":[-77.59220000000001,43.192896],"type":"Point"}
}