{
  "type": "Feature",
  "properties": {
    "iso:country":"US",
    "sg:address":"13 Fruitwood Ln",
    "sg:city":"Commack",
    "sg:classifiers":[
        {
            "category":"Insurance",
            "subcategory":"Insurance Agent",
            "type":"Services"
        }
    ],
    "sg:phone":"+1 631 462 2519",
    "sg:postcode":"11725",
    "sg:province":"NY",
    "wof:name":"S Sansone Svc",
    "wof:placetype":"venue"
},
  "geometry": {"coordinates":[-73.303241,40.83781],"type":"Point"}
}