{
  "type": "Feature",
  "properties": {
    "iso:country":"US",
    "sg:address":"799 Madison Ave Frnt",
    "sg:city":"New York",
    "sg:classifiers":[
        {
            "category":"Home & Garden",
            "subcategory":"Home Furnishings",
            "type":"Retail Goods"
        }
    ],
    "sg:phone":"+1 212 988 5221",
    "sg:postcode":"10021",
    "sg:province":"NY",
    "sg:tags":[
        "decor"
    ],
    "wof:name":"Frette Inc",
    "wof:placetype":"venue"
},
  "geometry": {"coordinates":[-73.967598,40.768799],"type":"Point"}
}