{
  "type": "Feature",
  "properties": {
    "iso:country":"US",
    "sg:address":"1485 Mount Read Blvd",
    "sg:city":"Rochester",
    "sg:classifiers":[
        {
            "category":"Shopping",
            "subcategory":"Music",
            "type":"Retail Goods"
        }
    ],
    "sg:phone":"+1 585 254 5810",
    "sg:postcode":"14606",
    "sg:province":"NY",
    "sg:tags":[
        "video",
        "disc",
        "tape",
        "cassette"
    ],
    "wof:name":"Industrial Video & News Inc",
    "wof:placetype":"venue"
},
  "geometry": {"coordinates":[-77.65948,43.185599],"type":"Point"}
}