{
  "type": "Feature",
  "properties": {
    "addr:full":"5023 Avenue N Brooklyn NY 11234",
    "addr:housenumber":"5023",
    "addr:postcode":"11234",
    "addr:street":"Avenue N",
    "iso:country":"US",
    "sg:address":"5023 Avenue N",
    "sg:city":"Brooklyn",
    "sg:classifiers":[
        {
            "category":"Restaurant",
            "type":"Food & Drink"
        }
    ],
    "sg:phone":"+1 718 677 9500",
    "sg:postcode":"11234",
    "sg:province":"NY",
    "sg:tags":[
        "african"
    ],
    "sg:website":"www.9javilla.com",
    "wof:name":"9ja Villa Nigerian Restaurant and Bar",
    "wof:placetype":"venue"
},
  "geometry": {"coordinates":[-73.926035,40.619225],"type":"Point"}
}