{
  "type": "Feature",
  "properties": {
    "iso:country":"US",
    "sg:address":"105 Holland Ave",
    "sg:city":"Elmont",
    "sg:classifiers":[
        {
            "category":"Manufacturing",
            "subcategory":"Tools & Machinery",
            "type":"Manufacturing & Wholesale Goods"
        }
    ],
    "sg:phone":"+1   ",
    "sg:postcode":"11003",
    "sg:province":"NY",
    "sg:tags":[
        "computer"
    ],
    "wof:name":"Laptop-America",
    "wof:placetype":"venue"
},
  "geometry": {"coordinates":[-73.713183,40.70705],"type":"Point"}
}