{
  "type": "Feature",
  "properties": {
    "iso:country":"US",
    "sg:address":"625 Panorama Trl",
    "sg:city":"Rochester",
    "sg:classifiers":[
        {
            "category":"Personal",
            "type":"Services"
        }
    ],
    "sg:phone":"+1 585 248 9010",
    "sg:postcode":"14625",
    "sg:province":"NY",
    "sg:tags":[
        "therapist",
        "massage"
    ],
    "wof:name":"Louise V Smyth",
    "wof:placetype":"venue"
},
  "geometry": {"coordinates":[-77.491434,43.135284],"type":"Point"}
}