{
  "type": "Feature",
  "properties": {
    "addr:full":"197 Lawrence St Uniondale NY 11553",
    "addr:housenumber":"197",
    "addr:postcode":"11553",
    "addr:street":"Lawrence St",
    "iso:country":"US",
    "sg:address":"197 Lawrence St",
    "sg:city":"Uniondale",
    "sg:classifiers":[
        {
            "category":"Organizations",
            "subcategory":"Religious Organization",
            "type":"Services"
        }
    ],
    "sg:phone":"+1 516 486 0061",
    "sg:postcode":"11553",
    "sg:province":"NY",
    "sg:tags":[
        "clergy"
    ],
    "wof:name":"Joseph J Howell",
    "wof:placetype":"venue"
},
  "geometry": {"coordinates":[-73.608559,40.720348],"type":"Point"}
}