{
  "type": "Feature",
  "properties": {
    "addr:full":"Broadway at 32nd St Queens NY 11106",
    "addr:postcode":"11106",
    "addr:street":"St",
    "iso:country":"US",
    "sg:address":"Broadway at 32nd St",
    "sg:city":"Queens",
    "sg:classifiers":[
        {
            "category":"Food Court",
            "type":"Food & Drink"
        }
    ],
    "sg:postcode":"11106",
    "sg:province":"NY",
    "sg:tags":[
        "stand"
    ],
    "wof:name":"Broadway Shish Kabob Cart",
    "wof:placetype":"venue"
},
  "geometry": {"coordinates":[-73.924583,40.761606],"type":"Point"}
}