{
  "type": "Feature",
  "properties": {
    "addr:full":"141 Mecox Rd Water Mill NY 11976",
    "addr:housenumber":"141",
    "addr:postcode":"11976",
    "addr:street":"Mecox Rd",
    "iso:country":"US",
    "sg:address":"141 Mecox Rd",
    "sg:city":"Water Mill",
    "sg:classifiers":[
        {
            "category":"Banks & Credit Unions",
            "subcategory":"Investment Brokerage",
            "type":"Services"
        }
    ],
    "sg:phone":"+1 631 537 7404",
    "sg:postcode":"11976",
    "sg:province":"NY",
    "wof:name":"Watermill Asset Mgt Corp",
    "wof:placetype":"venue"
},
  "geometry": {"coordinates":[-72.335707,40.923565],"type":"Point"}
}