{
  "type": "Feature",
  "properties": {
    "addr:full":"5104 Vernon Blvd Long Island City NY 11101",
    "addr:housenumber":"5104",
    "addr:postcode":"11101",
    "addr:street":"Vernon Blvd",
    "iso:country":"US",
    "sg:address":"5104 Vernon Blvd",
    "sg:city":"Long Island City",
    "sg:classifiers":[
        {
            "category":"Professional",
            "subcategory":"Lawyer & Legal Services",
            "type":"Services"
        }
    ],
    "sg:phone":"+1 718 729 6006",
    "sg:postcode":"11101",
    "sg:province":"NY",
    "wof:name":"Sugrue Daniel Atty",
    "wof:placetype":"venue"
},
  "geometry": {"coordinates":[-73.954498,40.742001],"type":"Point"}
}