{
  "type": "Feature",
  "properties": {
    "iso:country":"US",
    "sg:address":"1075 State Hwy 17M",
    "sg:city":"Monroe",
    "sg:classifiers":[
        {
            "category":"Home & Garden",
            "subcategory":"Home Furnishings",
            "type":"Retail Goods"
        },
        {
            "category":"Organizations",
            "subcategory":"Professional Association",
            "type":"Services"
        }
    ],
    "sg:phone":"+1 845 783 4205",
    "sg:postcode":"10950",
    "sg:province":"NY",
    "sg:tags":[
        "business",
        "wooden",
        "stove",
        "retailer",
        "contractor",
        "fireplace"
    ],
    "wof:name":"Thermal Steal Insulators",
    "wof:placetype":"venue"
},
  "geometry": {"coordinates":[-74.21575,41.34412],"type":"Point"}
}