{
  "type": "Feature",
  "properties": {
    "iso:country":"US",
    "sg:address":"39 Lake Rd",
    "sg:city":"Stillwater",
    "sg:classifiers":[
        {
            "category":"Personal",
            "subcategory":"Beauty Salon",
            "type":"Services"
        }
    ],
    "sg:phone":"+1   ",
    "sg:postcode":"12170",
    "sg:province":"NY",
    "sg:tags":[
        "shop"
    ],
    "wof:name":"Doll House Beauty Salon",
    "wof:placetype":"venue"
},
  "geometry": {"coordinates":[-73.665407,42.950125],"type":"Point"}
}