{
  "type": "Feature",
  "properties": {
    "addr:full":"725 Saratoga Rd Burnt Hills NY 12027",
    "addr:housenumber":"725",
    "addr:postcode":"12027",
    "addr:street":"Saratoga Rd",
    "iso:country":"US",
    "sg:address":"725 Saratoga Rd",
    "sg:city":"Burnt Hills",
    "sg:classifiers":[
        {
            "category":"Shopping",
            "subcategory":"Used Merchandise",
            "type":"Retail Goods"
        }
    ],
    "sg:phone":"+1 518 384 0702",
    "sg:postcode":"12027",
    "sg:province":"NY",
    "sg:tags":[
        "antique"
    ],
    "wof:name":"Affordable Antiques",
    "wof:placetype":"venue"
},
  "geometry": {"coordinates":[-73.904602,42.902901],"type":"Point"}
}