{
  "type": "Feature",
  "properties": {
    "iso:country":"US",
    "sg:address":"927 Fulton St",
    "sg:city":"Farmingdale",
    "sg:classifiers":[
        {
            "category":"Professional",
            "subcategory":"Testing Lab",
            "type":"Services"
        }
    ],
    "sg:phone":"+1 516 586 5999",
    "sg:postcode":"11735",
    "sg:province":"NY",
    "sg:tags":[
        "analytical",
        "laboratory"
    ],
    "wof:name":"Vivalab, Inc.",
    "wof:placetype":"venue"
},
  "geometry": {"coordinates":[-73.43843699999999,40.726033],"type":"Point"}
}