{
  "type": "Feature",
  "properties": {
    "addr:full":"113 Skye Island Dr Endicott NY 13760",
    "addr:housenumber":"113",
    "addr:postcode":"13760",
    "addr:street":"Skye Island Dr",
    "iso:country":"US",
    "sg:address":"113 Skye Island Dr",
    "sg:city":"Endicott",
    "sg:classifiers":[
        {
            "category":"Building & Trades",
            "subcategory":"Construction",
            "type":"Services"
        }
    ],
    "sg:phone":"+1 607 754 3971",
    "sg:postcode":"13760",
    "sg:province":"NY",
    "sg:tags":[
        "wallcoverings-installation",
        "wallpaper",
        "painting",
        "contractor"
    ],
    "wof:name":"Ready To Roll Painting",
    "wof:placetype":"venue"
},
  "geometry": {"coordinates":[-76.058071,42.108709],"type":"Point"}
}