{
  "type": "Feature",
  "properties": {
    "addr:full":"168 Broadway New Hyde Park NY 11040",
    "addr:housenumber":"168",
    "addr:postcode":"11040",
    "addr:street":"Broadway",
    "iso:country":"US",
    "sg:address":"168 Broadway",
    "sg:city":"New Hyde Park",
    "sg:classifiers":[
        {
            "category":"Building & Trades",
            "subcategory":"Construction",
            "type":"Services"
        }
    ],
    "sg:phone":"+1 516 747 7727",
    "sg:postcode":"11040",
    "sg:province":"NY",
    "sg:tags":[
        "masonry",
        "waterproofing",
        "contractor"
    ],
    "wof:name":"Rizzario Boccia",
    "wof:placetype":"venue"
},
  "geometry": {"coordinates":[-73.65876299999999,40.737841],"type":"Point"}
}