{
  "type": "Feature",
  "properties": {
    "addr:full":"1975 Wayneport Rd Macedon NY 14502",
    "addr:housenumber":"1975",
    "addr:postcode":"14502",
    "addr:street":"Wayneport Rd",
    "iso:country":"US",
    "sg:address":"1975 Wayneport Rd",
    "sg:city":"Macedon",
    "sg:classifiers":[
        {
            "category":"Government",
            "subcategory":"Court House",
            "type":"Public Place"
        }
    ],
    "sg:phone":"+1 315 986 9108",
    "sg:postcode":"14502",
    "sg:province":"NY",
    "sg:tags":[
        "city"
    ],
    "wof:name":"Justice Court",
    "wof:placetype":"venue"
},
  "geometry": {"coordinates":[-77.36141499999999,43.077213],"type":"Point"}
}