{
  "type": "Feature",
  "properties": {
    "iso:country":"US",
    "sg:address":"225 Eldert St Ste 1R",
    "sg:city":"Brooklyn",
    "sg:classifiers":[
        {
            "category":"Shopping",
            "subcategory":"Beauty & Cosmetics",
            "type":"Retail Goods"
        },
        {
            "category":"Personal",
            "subcategory":"Skin Care",
            "type":"Services"
        }
    ],
    "sg:phone":"+1 347 583 8578",
    "sg:postcode":"11207",
    "sg:province":"NY",
    "sg:tags":[
        "supply"
    ],
    "sg:website":"www.australianscent.com",
    "wof:name":"Australian Scent",
    "wof:placetype":"venue"
},
  "geometry": {"coordinates":[-73.909306,40.690918],"type":"Point"}
}