{
  "type": "Feature",
  "properties": {
    "addr:full":"800 2 Ave New York NY 10017",
    "addr:housenumber":"800",
    "addr:postcode":"10017",
    "addr:street":"2 Ave",
    "iso:country":"US",
    "sg:address":"800 2 Ave",
    "sg:city":"New York",
    "sg:classifiers":[
        {
            "category":"Professional",
            "subcategory":"Detective & Security Services",
            "type":"Services"
        }
    ],
    "sg:phone":"+1 212 883 9581",
    "sg:postcode":"10017",
    "sg:province":"NY",
    "sg:tags":[
        "guard",
        "patrol"
    ],
    "wof:name":"ADETECTIVEREFERRAL.COM",
    "wof:placetype":"venue"
},
  "geometry": {"coordinates":[-73.972692,40.749157],"type":"Point"}
}