{
  "type": "Feature",
  "properties": {
    "iso:country":"US",
    "sg:address":"271 Lincoln Ave",
    "sg:city":"Roosevelt",
    "sg:classifiers":[
        {
            "category":"Real Estate",
            "subcategory":"Real Estate Agent",
            "type":"Services"
        }
    ],
    "sg:phone":"+1 516 868 1840",
    "sg:postcode":"11575",
    "sg:province":"NY",
    "wof:name":"Elegant Quality Homes Realty",
    "wof:placetype":"venue"
},
  "geometry": {"coordinates":[-73.576221,40.68166],"type":"Point"}
}