{
  "type": "Feature",
  "properties": {
    "addr:full":"2340 Brighton Henrietta Town Line Rd Rochester NY 14623",
    "addr:housenumber":"2340",
    "addr:postcode":"14623",
    "addr:street":"Brighton Henrietta Town Line Rd",
    "iso:country":"US",
    "sg:address":"2340 Brighton Henrietta Town Line Rd",
    "sg:city":"Rochester",
    "sg:classifiers":[
        {
            "category":"Shopping",
            "subcategory":"Crafts & Fabrics",
            "type":"Retail Goods"
        }
    ],
    "sg:phone":"+1   ",
    "sg:postcode":"14623",
    "sg:province":"NY",
    "sg:tags":[
        "sewing"
    ],
    "wof:name":"Forster Fabric Structures",
    "wof:placetype":"venue"
},
  "geometry": {"coordinates":[-77.619654,43.094521],"type":"Point"}
}