{
  "type": "Feature",
  "properties": {
    "addr:full":"515 Madison Ave New York NY 10022",
    "addr:housenumber":"515",
    "addr:postcode":"10022",
    "addr:street":"Madison Ave",
    "iso:country":"US",
    "sg:address":"515 Madison Ave",
    "sg:city":"New York",
    "sg:classifiers":[
        {
            "category":"Sports & Exercise",
            "subcategory":"Golf",
            "type":"Entertainment"
        }
    ],
    "sg:phone":"+1 212 409 9585",
    "sg:postcode":"10022",
    "sg:province":"NY",
    "wof:name":"Fairways To Heaven Golf & Business Services",
    "wof:placetype":"venue"
},
  "geometry": {"coordinates":[-73.974098,40.7598],"type":"Point"}
}