{
  "type": "Feature",
  "properties": {
    "addr:full":"349 38th St Brooklyn NY 11232",
    "addr:housenumber":"349",
    "addr:postcode":"11232",
    "addr:street":"38Th St",
    "iso:country":"US",
    "sg:address":"349 38th St",
    "sg:city":"Brooklyn",
    "sg:classifiers":[
        {
            "category":"Manufacturing",
            "subcategory":"Wood Products",
            "type":"Manufacturing & Wholesale Goods"
        }
    ],
    "sg:phone":"+1   ",
    "sg:postcode":"11232",
    "sg:province":"NY",
    "sg:tags":[
        "frame",
        "mfg"
    ],
    "wof:name":"Framart Ltd",
    "wof:placetype":"venue"
},
  "geometry": {"coordinates":[-74.00688599999999,40.654218],"type":"Point"}
}