{
  "type": "Feature",
  "properties": {
    "addr:full":"878 Lafayette Ave Buffalo NY 14209",
    "addr:housenumber":"878",
    "addr:postcode":"14209",
    "addr:street":"Lafayette Ave",
    "iso:country":"US",
    "sg:address":"878 Lafayette Ave",
    "sg:city":"Buffalo",
    "sg:classifiers":[
        {
            "category":"Building & Trades",
            "subcategory":"Landscaping Services",
            "type":"Services"
        }
    ],
    "sg:phone":"+1 716 884 0317",
    "sg:postcode":"14209",
    "sg:province":"NY",
    "sg:tags":[
        "landscape"
    ],
    "wof:name":"Mikes Landscape Svce",
    "wof:placetype":"venue"
},
  "geometry": {"coordinates":[-78.866665,42.920648],"type":"Point"}
}