{
  "type": "Feature",
  "properties": {
    "addr:full":"11112 Flatlands Ave Brooklyn NY 11207",
    "addr:housenumber":"11112",
    "addr:postcode":"11207",
    "addr:street":"Flatlands Ave",
    "iso:country":"US",
    "sg:address":"11112 Flatlands Ave",
    "sg:city":"Brooklyn",
    "sg:classifiers":[
        {
            "category":"Food & Beverages",
            "subcategory":"Bakery",
            "type":"Retail Goods"
        }
    ],
    "sg:phone":"+1 718 257 4765",
    "sg:postcode":"11207",
    "sg:province":"NY",
    "sg:tags":[
        "bagel"
    ],
    "wof:name":"What's A Bagel",
    "wof:placetype":"venue"
},
  "geometry": {"coordinates":[-73.89004199999999,40.650966],"type":"Point"}
}