{
  "type": "Feature",
  "properties": {
    "addr:full":"436 Maple Ave Westbury NY 11590",
    "addr:housenumber":"436",
    "addr:postcode":"11590",
    "addr:street":"Maple Ave",
    "iso:country":"US",
    "sg:address":"436 Maple Ave",
    "sg:city":"Westbury",
    "sg:classifiers":[
        {
            "category":"Manufacturing",
            "subcategory":"Tools & Machinery",
            "type":"Manufacturing & Wholesale Goods"
        },
        {
            "category":"Manufacturing",
            "subcategory":"Electronics",
            "type":"Manufacturing & Wholesale Goods"
        },
        {
            "category":"Shopping",
            "subcategory":"Computers & Home Electronics",
            "type":"Retail Goods"
        }
    ],
    "sg:phone":"+1 516 333 8400",
    "sg:postcode":"11590",
    "sg:province":"NY",
    "sg:tags":[
        "electric",
        "electronic",
        "supplies-wholesale",
        "equipment-testing",
        "equipment",
        "consumer",
        "manufacturer"
    ],
    "sg:website":"http://www.gensemi.com",
    "wof:name":"Semimetals",
    "wof:placetype":"venue"
},
  "geometry": {"coordinates":[-73.583428,40.756329],"type":"Point"}
}