{
  "type": "Feature",
  "properties": {
    "addr:full":"255 Front St Oneonta NY 13827",
    "addr:housenumber":"255",
    "addr:postcode":"13827",
    "addr:street":"Front St",
    "iso:country":"US",
    "sg:address":"255 Front St",
    "sg:city":"Oneonta",
    "sg:classifiers":[
        {
            "category":"Food & Beverages",
            "subcategory":"Bakery",
            "type":"Retail Goods"
        }
    ],
    "sg:phone":"+1   ",
    "sg:postcode":"13827",
    "sg:province":"NY",
    "sg:tags":[
        "residential",
        "care"
    ],
    "wof:name":"Oneonta Bagel Co",
    "wof:placetype":"venue"
},
  "geometry": {"coordinates":[-76.25847,42.103499],"type":"Point"}
}