{
  "type": "Feature",
  "properties": {
    "iso:country":"US",
    "sg:address":"1707 Kings Hwy",
    "sg:city":"Brooklyn",
    "sg:classifiers":[
        {
            "category":"Real Estate",
            "subcategory":"Real Estate Agent",
            "type":"Services"
        }
    ],
    "sg:phone":"+1 718 339 1118",
    "sg:postcode":"11229",
    "sg:province":"NY",
    "wof:name":"European Investors Ctr",
    "wof:placetype":"venue"
},
  "geometry": {"coordinates":[-73.95567800000001,40.609982],"type":"Point"}
}