{
  "type": "Feature",
  "properties": {
    "addr:full":"94 Buffalo Ave E Atlantic Beach NY 11561",
    "addr:housenumber":"94",
    "addr:postcode":"11561",
    "addr:street":"Buffalo Ave E",
    "iso:country":"US",
    "sg:address":"94 Buffalo Ave",
    "sg:city":"E Atlantic Beach",
    "sg:classifiers":[
        {
            "category":"Professional",
            "type":"Services"
        }
    ],
    "sg:phone":"+1 516 897 5384",
    "sg:postcode":"11561",
    "sg:province":"NY",
    "sg:tags":[
        "establishment"
    ],
    "wof:name":"Future Beta",
    "wof:placetype":"venue"
},
  "geometry": {"coordinates":[-73.703154,40.586676],"type":"Point"}
}