{
  "type": "Feature",
  "properties": {
    "iso:country":"US",
    "sg:address":"1870 Whitehaven Rd",
    "sg:city":"Grand Island",
    "sg:classifiers":[
        {
            "category":"Professional",
            "subcategory":"Lawyer & Legal Services",
            "type":"Services"
        }
    ],
    "sg:phone":"+1 716 773 4688",
    "sg:postcode":"14072",
    "sg:province":"NY",
    "sg:tags":[
        "attorney"
    ],
    "wof:name":"Richard O Robinson PC",
    "wof:placetype":"venue"
},
  "geometry": {"coordinates":[-78.96048,43.021688],"type":"Point"}
}