{
  "type": "Feature",
  "properties": {
    "iso:country":"US",
    "sg:address":"107 Warren Rd",
    "sg:city":"Ilion",
    "sg:phone":"+1 315 866 3931",
    "sg:postcode":"13357",
    "sg:province":"NY",
    "sg:tags":[
        "farm",
        "field",
        "corn",
        "crop"
    ],
    "wof:name":"Ruth Brewer",
    "wof:placetype":"venue"
},
  "geometry": {"coordinates":[-75.039599,42.967501],"type":"Point"}
}