{
  "type": "Feature",
  "properties": {
    "addr:full":"648 Broadway Manhattan NY 10012",
    "addr:housenumber":"648",
    "addr:postcode":"10012",
    "addr:street":"Broadway",
    "iso:country":"US",
    "sg:address":"648 Broadway",
    "sg:city":"Manhattan",
    "sg:classifiers":[
        {
            "category":"Restaurant",
            "type":"Food & Drink"
        },
        {
            "category":"Deli",
            "type":"Food & Drink"
        },
        {
            "category":"Food & Beverages",
            "subcategory":"Bakery",
            "type":"Retail Goods"
        }
    ],
    "sg:phone":"+1 212 777 5201",
    "sg:postcode":"10012",
    "sg:province":"NY",
    "sg:tags":[
        "sandwich",
        "pizza"
    ],
    "wof:name":"Cafe Mercato",
    "wof:placetype":"venue"
},
  "geometry": {"coordinates":[-73.995299,40.726581],"type":"Point"}
}