{
  "type": "Feature",
  "properties": {
    "addr:full":"27 Denison Rd Schenectady NY 12309",
    "addr:housenumber":"27",
    "addr:postcode":"12309",
    "addr:street":"Denison Rd",
    "iso:country":"US",
    "sg:address":"27 Denison Rd",
    "sg:city":"Schenectady",
    "sg:classifiers":[
        {
            "category":"Building & Trades",
            "subcategory":"Construction",
            "type":"Services"
        }
    ],
    "sg:phone":"+1 518 452 1924",
    "sg:postcode":"12309",
    "sg:province":"NY",
    "sg:tags":[
        "house"
    ],
    "wof:name":"Precision Home Improvement",
    "wof:placetype":"venue"
},
  "geometry": {"coordinates":[-73.839179,42.763062],"type":"Point"}
}