{
  "type": "Feature",
  "properties": {
    "iso:country":"US",
    "sg:address":"165 Co Rd 60",
    "sg:city":"Oswegatchie",
    "sg:classifiers":[
        {
            "category":"Building & Trades",
            "subcategory":"Construction",
            "type":"Services"
        }
    ],
    "sg:phone":"+1 315 848 3358",
    "sg:postcode":"13670",
    "sg:province":"NY",
    "sg:tags":[
        "excavating",
        "contractor"
    ],
    "wof:name":"Langevin Excavation",
    "wof:placetype":"venue"
},
  "geometry": {"coordinates":[-75.044628,44.19292],"type":"Point"}
}