{
  "type": "Feature",
  "properties": {
    "iso:country":"US",
    "sg:address":"21291 State Hwy 12F",
    "sg:city":"Watertown",
    "sg:classifiers":[
        {
            "category":"Real Estate",
            "subcategory":"Real Estate Agent",
            "type":"Services"
        }
    ],
    "sg:phone":"+1 315 782 9981",
    "sg:postcode":"13601",
    "sg:province":"NY",
    "sg:tags":[
        "agency",
        "rental"
    ],
    "wof:name":"M-K Rental",
    "wof:placetype":"venue"
},
  "geometry": {"coordinates":[-75.947622,43.989736],"type":"Point"}
}