{
  "type": "Feature",
  "properties": {
    "addr:full":"316 Catherine St Syracuse NY 13203",
    "addr:housenumber":"316",
    "addr:postcode":"13203",
    "addr:street":"Catherine St",
    "iso:country":"US",
    "sg:address":"316 Catherine St",
    "sg:city":"Syracuse",
    "sg:classifiers":[
        {
            "category":"Social Services",
            "type":"Services"
        }
    ],
    "sg:phone":"+1 315 474 8226",
    "sg:postcode":"13203",
    "sg:province":"NY",
    "sg:tags":[
        "care",
        "center",
        "day"
    ],
    "wof:name":"Loretto Adult Medicle Day Care",
    "wof:placetype":"venue"
},
  "geometry": {"coordinates":[-76.14304,43.055003],"type":"Point"}
}