{
  "type": "Feature",
  "properties": {
    "addr:full":"86 Alpine Dr Latham NY 12110",
    "addr:housenumber":"86",
    "addr:postcode":"12110",
    "addr:street":"Alpine Dr",
    "iso:country":"US",
    "sg:address":"86 Alpine Dr",
    "sg:city":"Latham",
    "sg:classifiers":[
        {
            "category":"Organizations",
            "subcategory":"Religious Organization",
            "type":"Services"
        }
    ],
    "sg:phone":"+1 518 783 1074",
    "sg:postcode":"12110",
    "sg:province":"NY",
    "sg:tags":[
        "clergy"
    ],
    "wof:name":"Drown Maurice",
    "wof:placetype":"venue"
},
  "geometry": {"coordinates":[-73.788757,42.775341],"type":"Point"}
}