{
  "type": "Feature",
  "properties": {
    "addr:full":"128 Florida St Farmingdale NY 11735",
    "addr:housenumber":"128",
    "addr:postcode":"11735",
    "addr:street":"Florida St",
    "iso:country":"US",
    "sg:address":"128 Florida St",
    "sg:city":"Farmingdale",
    "sg:classifiers":[
        {
            "category":"Retail",
            "subcategory":"Repair Shop",
            "type":"Services"
        }
    ],
    "sg:phone":"+1 631 843 0227",
    "sg:postcode":"11735",
    "sg:province":"NY",
    "sg:tags":[
        "assembly",
        "electric",
        "mechanical"
    ],
    "wof:name":"Pro-Cision Industries Corp",
    "wof:placetype":"venue"
},
  "geometry": {"coordinates":[-73.418654,40.713996],"type":"Point"}
}