{
  "type": "Feature",
  "properties": {
    "iso:country":"US",
    "sg:address":"24 Norwood Way",
    "sg:city":"Schenectady",
    "sg:classifiers":[
        {
            "category":"Real Estate",
            "subcategory":"Real Estate Services",
            "type":"Services"
        },
        {
            "category":"Real Estate",
            "subcategory":"Real Estate Agent",
            "type":"Services"
        }
    ],
    "sg:phone":"+1 518 456 1945",
    "sg:postcode":"12309",
    "sg:province":"NY",
    "sg:tags":[
        "buyer",
        "broker"
    ],
    "wof:name":"American Heritage Homes Realty, Inc",
    "wof:placetype":"venue"
},
  "geometry": {"coordinates":[-73.873643,42.784932],"type":"Point"}
}