{
  "type": "Feature",
  "properties": {
    "iso:country":"US",
    "sg:address":"226 W 47 St",
    "sg:city":"New York",
    "sg:classifiers":[
        {
            "category":"Restaurant",
            "type":"Food & Drink"
        }
    ],
    "sg:phone":"+1   ",
    "sg:postcode":"10036",
    "sg:province":"NY",
    "sg:tags":[
        "eating"
    ],
    "wof:name":"Hakata Japanese Restaurant",
    "wof:placetype":"venue"
},
  "geometry": {"coordinates":[-73.98482300000001,40.759166],"type":"Point"}
}