{
  "type": "Feature",
  "properties": {
    "addr:full":"810 7th Avenue New York NY 10019",
    "addr:housenumber":"810",
    "addr:postcode":"10019",
    "addr:street":"7Th Avenue",
    "iso:country":"US",
    "sg:address":"810 7th Avenue",
    "sg:city":"New York",
    "sg:classifiers":[
        {
            "category":"Shopping",
            "subcategory":"Mobile Phones",
            "type":"Retail Goods"
        }
    ],
    "sg:phone":"+1 212 262 0447",
    "sg:postcode":"10019",
    "sg:province":"NY",
    "sg:website":"www.wireless.att.com",
    "wof:name":"Cinfular Wireless",
    "wof:placetype":"venue"
},
  "geometry": {"coordinates":[-73.982135,40.762682],"type":"Point"}
}