{
  "type": "Feature",
  "properties": {
    "iso:country":"US",
    "sg:address":"277 Alexander St Ste 510",
    "sg:city":"Rochester",
    "sg:classifiers":[
        {
            "category":"Health Services",
            "subcategory":"Doctor",
            "type":"Services"
        },
        {
            "category":"Health Services",
            "subcategory":"Clinic",
            "type":"Services"
        }
    ],
    "sg:phone":"+1 585 232 6160",
    "sg:postcode":"14607",
    "sg:province":"NY",
    "sg:tags":[
        "psychological",
        "psychologist"
    ],
    "wof:name":"Osborn Kent Phd",
    "wof:placetype":"venue"
},
  "geometry": {"coordinates":[-77.59526099999999,43.153431],"type":"Point"}
}