{
  "type": "Feature",
  "properties": {
    "addr:full":"777 Albany Ave Brooklyn NY 11203",
    "addr:housenumber":"777",
    "addr:postcode":"11203",
    "addr:street":"Albany Ave",
    "iso:country":"US",
    "sg:address":"777 Albany Ave",
    "sg:city":"Brooklyn",
    "sg:classifiers":[
        {
            "category":"Place Of Worship",
            "subcategory":"Church",
            "type":"Public Place"
        },
        {
            "category":"Place Of Worship",
            "type":"Public Place"
        },
        {
            "category":"Organizations",
            "subcategory":"Religious Organization",
            "type":"Services"
        }
    ],
    "sg:phone":"+1 718 735 7860",
    "sg:postcode":"11203",
    "sg:province":"NY",
    "sg:tags":[
        "churches-interdenominational",
        "churches-jehovah's",
        "churches-various",
        "witness",
        "denomination"
    ],
    "sg:website":"http://www.watchtower.org",
    "wof:name":"Utica Congregation of Jehovah's Witnesses",
    "wof:placetype":"venue"
},
  "geometry": {"coordinates":[-73.939301,40.6549],"type":"Point"}
}