{
  "type": "Feature",
  "properties": {
    "iso:country":"US",
    "sg:address":"5015 Centralia-Hartfield Rd",
    "sg:city":"Dewittville",
    "sg:classifiers":[
        {
            "category":"Farming",
            "subcategory":"Dairy Farm",
            "type":"Manufacturing & Wholesale Goods"
        }
    ],
    "sg:phone":"+1 716 753 7773",
    "sg:postcode":"14728",
    "sg:province":"NY",
    "wof:name":"Sunnycrest Farms",
    "wof:placetype":"venue"
},
  "geometry": {"coordinates":[-79.393896,42.26057],"type":"Point"}
}