{
  "type": "Feature",
  "properties": {
    "addr:full":"8020 Bay Pkwy Brooklyn NY 11214",
    "addr:housenumber":"8020",
    "addr:postcode":"11214",
    "addr:street":"Bay Pkwy",
    "iso:country":"US",
    "sg:address":"8020 Bay Pkwy",
    "sg:city":"Brooklyn",
    "sg:classifiers":[
        {
            "category":"Real Estate",
            "subcategory":"Real Estate Agent",
            "type":"Services"
        }
    ],
    "sg:phone":"+1 718 234 1851",
    "sg:postcode":"11214",
    "sg:province":"NY",
    "sg:tags":[
        "management"
    ],
    "wof:name":"8020 Corporation",
    "wof:placetype":"venue"
},
  "geometry": {"coordinates":[-73.990842,40.60493],"type":"Point"}
}