{
  "type": "Feature",
  "properties": {
    "addr:full":"1594 Unionport Rd Ste 7 Bronx NY 10462",
    "addr:housenumber":"1594",
    "addr:postcode":"10462",
    "addr:street":"Unionport Rd Ste 7",
    "iso:country":"US",
    "sg:address":"1594 Unionport Rd Ste 7",
    "sg:city":"Bronx",
    "sg:classifiers":[
        {
            "category":"Health Services",
            "subcategory":"Nursing And Care Facility",
            "type":"Services"
        },
        {
            "category":"Health Services",
            "subcategory":"Health Practitioner",
            "type":"Services"
        }
    ],
    "sg:phone":"+1 718 409 6815",
    "sg:postcode":"10462",
    "sg:province":"NY",
    "sg:tags":[
        "home",
        "eldercare-home"
    ],
    "wof:name":"Early Solutions Homecare Inc",
    "wof:placetype":"venue"
},
  "geometry": {"coordinates":[-73.863327,40.84119],"type":"Point"}
}