{
  "type": "Feature",
  "properties": {
    "addr:full":"273 Euclid Ave Brooklyn NY 11208",
    "addr:housenumber":"273",
    "addr:postcode":"11208",
    "addr:street":"Euclid Ave",
    "iso:country":"US",
    "sg:address":"273 Euclid Ave",
    "sg:city":"Brooklyn",
    "sg:classifiers":[
        {
            "category":"Banks & Credit Unions",
            "subcategory":"Financial Services",
            "type":"Services"
        }
    ],
    "sg:phone":"+1 718 827 1757",
    "sg:postcode":"11208",
    "sg:province":"NY",
    "sg:tags":[
        "investor"
    ],
    "wof:name":"S & W Investment LLC",
    "wof:placetype":"venue"
},
  "geometry": {"coordinates":[-73.87379199999999,40.682475],"type":"Point"}
}