{
  "type": "Feature",
  "properties": {
    "iso:country":"US",
    "sg:address":"1000 King St",
    "sg:city":"Chappaqua",
    "sg:classifiers":[
        {
            "category":"Building & Trades",
            "subcategory":"Construction",
            "type":"Services"
        }
    ],
    "sg:phone":"+1 914 769 7578",
    "sg:postcode":"10514",
    "sg:province":"NY",
    "sg:tags":[
        "house",
        "nonresidential"
    ],
    "wof:name":"Phelan Development Corp",
    "wof:placetype":"venue"
},
  "geometry": {"coordinates":[-73.749274,41.133326],"type":"Point"}
}