{
  "type": "Feature",
  "properties": {
    "addr:full":"1772 86th Street Brooklyn NY 11214",
    "addr:housenumber":"1772",
    "addr:postcode":"11214",
    "addr:street":"86Th Street",
    "iso:country":"US",
    "sg:address":"1772 86th Street",
    "sg:city":"Brooklyn",
    "sg:classifiers":[
        {
            "category":"Restaurant",
            "type":"Food & Drink"
        }
    ],
    "sg:phone":"+1 718 837 9471",
    "sg:postcode":"11214",
    "sg:province":"NY",
    "wof:name":"Debal Restaurant",
    "wof:placetype":"venue"
},
  "geometry": {"coordinates":[-74.002987,40.607322],"type":"Point"}
}