{
  "type": "Feature",
  "properties": {
    "addr:full":"10 Nosband Ave White Plains NY 10605",
    "addr:housenumber":"10",
    "addr:postcode":"10605",
    "addr:street":"Nosband Ave",
    "iso:country":"US",
    "sg:address":"10 Nosband Ave",
    "sg:city":"White Plains",
    "sg:classifiers":[
        {
            "category":"Utilities",
            "subcategory":"Electric",
            "type":"Services"
        }
    ],
    "sg:phone":"+1   ",
    "sg:postcode":"10605",
    "sg:province":"NY",
    "sg:tags":[
        "trader",
        "commodity"
    ],
    "wof:name":"Aleph One Inc",
    "wof:placetype":"venue"
},
  "geometry": {"coordinates":[-73.759587,41.019495],"type":"Point"}
}