{
  "type": "Feature",
  "properties": {
    "addr:full":"5600 1st Ave Brooklyn NY 11220",
    "addr:housenumber":"5600",
    "addr:postcode":"11220",
    "addr:street":"1St Ave",
    "iso:country":"US",
    "sg:address":"5600 1st Ave",
    "sg:city":"Brooklyn",
    "sg:classifiers":[
        {
            "category":"Food & Beverages",
            "subcategory":"Groceries & Convenience Stores",
            "type":"Retail Goods"
        }
    ],
    "sg:phone":"+1 718 765 1508",
    "sg:postcode":"11220",
    "sg:province":"NY",
    "wof:name":"Wholesale International Network Inc",
    "wof:placetype":"venue"
},
  "geometry": {"coordinates":[-74.022598,40.647099],"type":"Point"}
}