{
  "type": "Feature",
  "properties": {
    "iso:country":"US",
    "sg:address":"2222 State Hwy 417",
    "sg:city":"Andover",
    "sg:classifiers":[
        {
            "category":"Home & Garden",
            "subcategory":"Household Appliances",
            "type":"Retail Goods"
        }
    ],
    "sg:phone":"+1   ",
    "sg:postcode":"14806",
    "sg:province":"NY",
    "wof:name":"Kims Fabrics",
    "wof:placetype":"venue"
},
  "geometry": {"coordinates":[-77.856686,42.151432],"type":"Point"}
}