{
  "type": "Feature",
  "properties": {
    "iso:country":"US",
    "sg:address":"141 Dalewood Dr",
    "sg:city":"Buffalo",
    "sg:classifiers":[
        {
            "category":"Professional",
            "subcategory":"Business Services",
            "type":"Services"
        }
    ],
    "sg:phone":"+1 716 691 7489",
    "sg:postcode":"14228",
    "sg:province":"NY",
    "sg:tags":[
        "broker"
    ],
    "wof:name":"Platinum Business Brokers",
    "wof:placetype":"venue"
},
  "geometry": {"coordinates":[-78.80862,43.008837],"type":"Point"}
}