{
  "type": "Feature",
  "properties": {
    "addr:full":"319 W Church St Elmira NY 14901",
    "addr:housenumber":"319",
    "addr:postcode":"14901",
    "addr:street":"W Church St",
    "iso:country":"US",
    "sg:address":"319 W Church St",
    "sg:city":"Elmira",
    "sg:classifiers":[
        {
            "category":"Travel",
            "subcategory":"Travel Agent",
            "type":"Entertainment"
        }
    ],
    "sg:phone":"+1   ",
    "sg:postcode":"14901",
    "sg:province":"NY",
    "sg:tags":[
        "passenger",
        "agency",
        "transportation",
        "arrangement"
    ],
    "sg:website":"www.fourseasonstravel.com",
    "wof:name":"Four Seasons Travel Of Elmira",
    "wof:placetype":"venue"
},
  "geometry": {"coordinates":[-76.81100600000001,42.089043],"type":"Point"}
}