{
  "type": "Feature",
  "properties": {
    "addr:full":"712 Southern Blvd Bronx NY 10455",
    "addr:housenumber":"712",
    "addr:postcode":"10455",
    "addr:street":"Southern Blvd",
    "iso:country":"US",
    "sg:address":"712 Southern Blvd",
    "sg:city":"Bronx",
    "sg:classifiers":[
        {
            "category":"Manufacturing",
            "subcategory":"Glass & Minerals",
            "type":"Manufacturing & Wholesale Goods"
        }
    ],
    "sg:phone":"+1 914 632 4300",
    "sg:postcode":"10455",
    "sg:province":"NY",
    "sg:tags":[
        "plate",
        "window",
        "glass-auto"
    ],
    "wof:name":"Abie The Glazier Inc",
    "wof:placetype":"venue"
},
  "geometry": {"coordinates":[-73.89920600000001,40.813526],"type":"Point"}
}