{
  "type": "Feature",
  "properties": {
    "addr:full":"6500 Joy Rd East Syracuse NY 13057",
    "addr:housenumber":"6500",
    "addr:postcode":"13057",
    "addr:street":"Joy Rd",
    "iso:country":"US",
    "sg:address":"6500 Joy Rd",
    "sg:city":"East Syracuse",
    "sg:classifiers":[
        {
            "category":"Professional",
            "subcategory":"Management & Consulting",
            "type":"Services"
        }
    ],
    "sg:phone":"+1 315 431 4941",
    "sg:postcode":"13057",
    "sg:province":"NY",
    "sg:tags":[
        "export"
    ],
    "sg:website":"www.nuclimate.com",
    "wof:name":"Nu Climate Intl",
    "wof:placetype":"venue"
},
  "geometry": {"coordinates":[-76.08866999999999,43.09708],"type":"Point"}
}