{
  "type": "Feature",
  "properties": {
    "addr:full":"881 Montauk Hwy West Babylon NY 11704",
    "addr:housenumber":"881",
    "addr:postcode":"11704",
    "addr:street":"Montauk Hwy",
    "iso:country":"US",
    "sg:address":"881 Montauk Hwy",
    "sg:city":"West Babylon",
    "sg:classifiers":[
        {
            "category":"Shopping",
            "subcategory":"Clothing, Apparel, & Fashions",
            "type":"Retail Goods"
        }
    ],
    "sg:phone":"+1   ",
    "sg:postcode":"11704",
    "sg:province":"NY",
    "sg:tags":[
        "family",
        "store"
    ],
    "wof:name":"Old Navy",
    "wof:placetype":"venue"
},
  "geometry": {"coordinates":[-73.350274,40.684882],"type":"Point"}
}