{
  "type": "Feature",
  "properties": {
    "iso:country":"US",
    "sg:address":"46 Atwood Rd",
    "sg:city":"West Chazy",
    "sg:classifiers":[
        {
            "category":"Shopping",
            "subcategory":"Gifts & Souvenirs",
            "type":"Retail Goods"
        }
    ],
    "sg:phone":"+1   ",
    "sg:postcode":"12992",
    "sg:province":"NY",
    "wof:name":"Village Gift & Craft Shop",
    "wof:placetype":"venue"
},
  "geometry": {"coordinates":[-73.51176100000001,44.80572],"type":"Point"}
}