{
  "type": "Feature",
  "properties": {
    "iso:country":"US",
    "sg:address":"300 Hylan Dr",
    "sg:city":"Rochester",
    "sg:classifiers":[
        {
            "category":"Shopping",
            "subcategory":"Bicycles & Sporting Goods",
            "type":"Retail Goods"
        }
    ],
    "sg:phone":"+1 585 272 1980",
    "sg:postcode":"14623",
    "sg:province":"NY",
    "sg:tags":[
        "equipment",
        "golf",
        "supply"
    ],
    "wof:name":"Golf Galaxy",
    "wof:placetype":"venue"
},
  "geometry": {"coordinates":[-77.629677,43.085393],"type":"Point"}
}