{
  "type": "Feature",
  "properties": {
    "iso:country":"US",
    "sg:address":"9250 Flucker Hill Rd",
    "sg:city":"Forestville",
    "sg:classifiers":[
        {
            "category":"Shopping",
            "subcategory":"Hobbies, Toys, & Games",
            "type":"Retail Goods"
        }
    ],
    "sg:phone":"+1   ",
    "sg:postcode":"14062",
    "sg:province":"NY",
    "wof:name":"Wooden Stitch",
    "wof:placetype":"venue"
},
  "geometry": {"coordinates":[-79.075667,42.434279],"type":"Point"}
}