{
  "type": "Feature",
  "properties": {
    "iso:country":"US",
    "sg:address":"3413 School St",
    "sg:city":"Bliss",
    "sg:classifiers":[
        {
            "category":"Education",
            "subcategory":"Library",
            "type":"Public Place"
        }
    ],
    "sg:phone":"+1 585 322 7701",
    "sg:postcode":"14024",
    "sg:province":"NY",
    "wof:name":"Eagle Free Library",
    "wof:placetype":"venue"
},
  "geometry": {"coordinates":[-78.253861,42.579583],"type":"Point"}
}