{
  "type": "Feature",
  "properties": {
    "iso:country":"US",
    "sg:address":"715 5th Ave",
    "sg:city":"New York",
    "sg:classifiers":[
        {
            "category":"Shopping",
            "subcategory":"Clothing, Apparel, & Fashions",
            "type":"Retail Goods"
        }
    ],
    "sg:phone":"+1 212 755 2201",
    "sg:postcode":"10022",
    "sg:province":"NY",
    "wof:name":"Escada Inc",
    "wof:placetype":"venue"
},
  "geometry": {"coordinates":[-73.974915,40.761666],"type":"Point"}
}