{
  "type": "Feature",
  "properties": {
    "iso:country":"US",
    "sg:address":"32 Main St",
    "sg:city":"Brockport",
    "sg:classifiers":[
        {
            "category":"Restaurant",
            "type":"Food & Drink"
        }
    ],
    "sg:phone":"+1   ",
    "sg:postcode":"14420",
    "sg:province":"NY",
    "sg:tags":[
        "eating"
    ],
    "wof:name":"Eileens Bakery An Soup Kitchen",
    "wof:placetype":"venue"
},
  "geometry": {"coordinates":[-77.938541,43.215708],"type":"Point"}
}