{
  "type": "Feature",
  "properties": {
    "addr:full":"28 Union St Hamburg NY 14075",
    "addr:housenumber":"28",
    "addr:postcode":"14075",
    "addr:street":"Union St",
    "iso:country":"US",
    "sg:address":"28 Union St",
    "sg:city":"Hamburg",
    "sg:classifiers":[
        {
            "category":"Professional",
            "type":"Services"
        }
    ],
    "sg:phone":"+1 716 649 5940",
    "sg:postcode":"14075",
    "sg:province":"NY",
    "sg:tags":[
        "establishment"
    ],
    "wof:name":"Haws & Kluckhohn Co",
    "wof:placetype":"venue"
},
  "geometry": {"coordinates":[-78.83188699999999,42.717737],"type":"Point"}
}