{
  "type": "Feature",
  "properties": {
    "addr:full":"11 W Front St Ste 103 Addison NY 14801",
    "addr:housenumber":"11",
    "addr:postcode":"14801",
    "addr:street":"W Front St Ste 103",
    "iso:country":"US",
    "sg:address":"11 W Front St Ste 103",
    "sg:city":"Addison",
    "sg:classifiers":[
        {
            "category":"Restaurant",
            "type":"Food & Drink"
        }
    ],
    "sg:phone":"+1 607 359 2107",
    "sg:postcode":"14801",
    "sg:province":"NY",
    "wof:name":"Buzzy's Dream",
    "wof:placetype":"venue"
},
  "geometry": {"coordinates":[-77.233238,42.107898],"type":"Point"}
}