{
  "type": "Feature",
  "properties": {
    "addr:full":"235 Howard Hall Rd Catskill NY 12414",
    "addr:housenumber":"235",
    "addr:postcode":"12414",
    "addr:street":"Howard Hall Rd",
    "iso:country":"US",
    "sg:address":"235 Howard Hall Rd",
    "sg:city":"Catskill",
    "sg:classifiers":[
        {
            "category":"Building & Trades",
            "subcategory":"Construction",
            "type":"Services"
        }
    ],
    "sg:phone":"+1 518 945 3667",
    "sg:postcode":"12414",
    "sg:province":"NY",
    "sg:tags":[
        "residential"
    ],
    "wof:name":"Pogliani Bros General Contract",
    "wof:placetype":"venue"
},
  "geometry": {"coordinates":[-73.836125,42.273209],"type":"Point"}
}