{
  "type": "Feature",
  "properties": {
    "iso:country":"US",
    "sg:address":"9876 Queens Boulevard",
    "sg:city":"Rego Park",
    "sg:classifiers":[
        {
            "category":"Health Services",
            "subcategory":"Dentist",
            "type":"Services"
        }
    ],
    "sg:phone":"+1 718 459 7797",
    "sg:postcode":"11374",
    "sg:province":"NY",
    "wof:name":"Rubin Jos DDS",
    "wof:placetype":"venue"
},
  "geometry": {"coordinates":[-73.85569099999999,40.727433],"type":"Point"}
}