{
  "type": "Feature",
  "properties": {
    "addr:full":"114 Woodcut Dr Mastic Beach NY 11951",
    "addr:housenumber":"114",
    "addr:postcode":"11951",
    "addr:street":"Woodcut Dr",
    "iso:country":"US",
    "sg:address":"114 Woodcut Dr",
    "sg:city":"Mastic Beach",
    "sg:classifiers":[
        {
            "category":"Professional",
            "subcategory":"Engineering",
            "type":"Services"
        }
    ],
    "sg:phone":"+1 631 806 8939",
    "sg:postcode":"11951",
    "sg:province":"NY",
    "wof:name":"Idealparadigm",
    "wof:placetype":"venue"
},
  "geometry": {"coordinates":[-72.83291699999999,40.785409],"type":"Point"}
}