{
  "type": "Feature",
  "properties": {
    "addr:full":"37 Cat Rock Rd Garrison NY 10524",
    "addr:housenumber":"37",
    "addr:postcode":"10524",
    "addr:street":"Cat Rock Rd",
    "iso:country":"US",
    "sg:address":"37 Cat Rock Rd",
    "sg:city":"Garrison",
    "sg:classifiers":[
        {
            "category":"Health Services",
            "subcategory":"Health Practitioner",
            "type":"Services"
        },
        {
            "category":"Health Services",
            "subcategory":"Doctor",
            "type":"Services"
        }
    ],
    "sg:phone":"+1 845 424 4910",
    "sg:postcode":"10524",
    "sg:province":"NY",
    "sg:tags":[
        "physiotherapist",
        "medical"
    ],
    "wof:name":"Sarah Berry Tschinkel",
    "wof:placetype":"venue"
},
  "geometry": {"coordinates":[-73.925875,41.351504],"type":"Point"}
}