{
  "type": "Feature",
  "properties": {
    "addr:full":"1760 2nd Ave New York NY 10128",
    "addr:housenumber":"1760",
    "addr:postcode":"10128",
    "addr:street":"2Nd Ave",
    "iso:country":"US",
    "sg:address":"1760 2nd Ave",
    "sg:city":"New York",
    "sg:classifiers":[
        {
            "category":"Coffee & Tea",
            "type":"Food & Drink"
        },
        {
            "category":"Bagels",
            "subcategory":"None",
            "type":"Food & Drink"
        },
        {
            "category":"Donuts",
            "subcategory":"None",
            "type":"Food & Drink"
        }
    ],
    "sg:phone":"+1 212 876 3312",
    "sg:postcode":"10128",
    "sg:province":"NY",
    "sg:website":"www.dunkindonuts.com",
    "wof:name":"Dunkin' Donuts",
    "wof:placetype":"venue"
},
  "geometry": {"coordinates":[-73.94907600000001,40.781495],"type":"Point"}
}