{
  "type": "Feature",
  "properties": {
    "addr:full":"267 52nd St Brooklyn NY 11220",
    "addr:housenumber":"267",
    "addr:postcode":"11220",
    "addr:street":"52Nd St",
    "iso:country":"US",
    "sg:address":"267 52nd St",
    "sg:city":"Brooklyn",
    "sg:classifiers":[
        {
            "category":"Wholesale",
            "subcategory":"Durable Goods & Equipment",
            "type":"Manufacturing & Wholesale Goods"
        }
    ],
    "sg:phone":"+1 718 417 9281",
    "sg:postcode":"11220",
    "sg:province":"NY",
    "sg:tags":[
        "importer"
    ],
    "wof:name":"Allied Imports",
    "wof:placetype":"venue"
},
  "geometry": {"coordinates":[-74.016964,40.647596],"type":"Point"}
}