{
  "type": "Feature",
  "properties": {
    "addr:full":"182 W Old Country Rd Hicksville NY 11801",
    "addr:housenumber":"182",
    "addr:postcode":"11801",
    "addr:street":"W Old Country Rd",
    "iso:country":"US",
    "sg:address":"182 W Old Country Rd",
    "sg:city":"Hicksville",
    "sg:classifiers":[
        {
            "category":"Autos & Motor Vehicles",
            "subcategory":"Automobile Sales",
            "type":"Retail Goods"
        }
    ],
    "sg:phone":"+1 516 932 1681",
    "sg:postcode":"11801",
    "sg:province":"NY",
    "sg:tags":[
        "new",
        "car"
    ],
    "wof:name":"Winston Brodmerkel Agency Inc.",
    "wof:placetype":"venue"
},
  "geometry": {"coordinates":[-73.527559,40.761896],"type":"Point"}
}