{
  "type": "Feature",
  "properties": {
    "iso:country":"US",
    "sg:address":"7780 Cadwell Rd",
    "sg:city":"Bliss",
    "sg:classifiers":[
        {
            "category":"Farming",
            "subcategory":"Dairy Farm",
            "type":"Manufacturing & Wholesale Goods"
        }
    ],
    "sg:phone":"+1 585 322 8888",
    "sg:postcode":"14009",
    "sg:province":"NY",
    "wof:name":"George Anthony",
    "wof:placetype":"venue"
},
  "geometry": {"coordinates":[-78.299881,42.540778],"type":"Point"}
}