{
  "type": "Feature",
  "properties": {
    "iso:country":"US",
    "sg:address":"28 Linden Dr",
    "sg:city":"Newburgh",
    "sg:classifiers":[
        {
            "category":"Building & Trades",
            "subcategory":"Plumbing",
            "type":"Services"
        }
    ],
    "sg:phone":"+1 845 567 9521",
    "sg:postcode":"12550",
    "sg:province":"NY",
    "sg:tags":[
        "contractor"
    ],
    "wof:name":"Classic Plumbing Heating & Air",
    "wof:placetype":"venue"
},
  "geometry": {"coordinates":[-74.122388,41.51894],"type":"Point"}
}