{
  "type": "Feature",
  "properties": {
    "addr:full":"734 5th Avenue Brooklyn NY 11232",
    "addr:housenumber":"734",
    "addr:postcode":"11232",
    "addr:street":"5Th Avenue",
    "iso:country":"US",
    "sg:address":"734 5th Avenue",
    "sg:city":"Brooklyn",
    "sg:classifiers":[
        {
            "category":"Building & Trades",
            "subcategory":"Construction",
            "type":"Services"
        }
    ],
    "sg:phone":"+1 718 768 0400",
    "sg:postcode":"11232",
    "sg:province":"NY",
    "sg:tags":[
        "contractor"
    ],
    "wof:name":"National Pneumatic Systems Corporation",
    "wof:placetype":"venue"
},
  "geometry": {"coordinates":[-73.995132,40.659876],"type":"Point"}
}