{
  "type": "Feature",
  "properties": {
    "iso:country":"US",
    "sg:address":"260 W 72nd St 12th Fl",
    "sg:city":"Manhattan",
    "sg:classifiers":[
        {
            "category":"Professional",
            "subcategory":"Computer Services",
            "type":"Services"
        }
    ],
    "sg:phone":"+1 212 724 7400",
    "sg:postcode":"10023",
    "sg:province":"NY",
    "sg:tags":[
        "repair"
    ],
    "sg:website":"www.1hoursupport.com/",
    "wof:name":"1 Hour Computer Support",
    "wof:placetype":"venue"
},
  "geometry": {"coordinates":[-73.983547,40.779398],"type":"Point"}
}