{
  "type": "Feature",
  "properties": {
    "iso:country":"US",
    "sg:address":"1 Church St",
    "sg:city":"Catskill",
    "sg:classifiers":[
        {
            "category":"Banks & Credit Unions",
            "subcategory":"Bank",
            "type":"Services"
        }
    ],
    "sg:phone":"+1 518 943 4532",
    "sg:postcode":"12414",
    "sg:province":"NY",
    "sg:website":"www.greenecountybancorp.com",
    "wof:name":"Bank Of Greene County",
    "wof:placetype":"venue"
},
  "geometry": {"coordinates":[-73.866694,42.220332],"type":"Point"}
}