{
  "type": "Feature",
  "properties": {
    "addr:full":"1 S Brookside Ave Freeport NY 11520",
    "addr:housenumber":"1",
    "addr:postcode":"11520",
    "addr:street":"S Brookside Ave",
    "iso:country":"US",
    "sg:address":"1 S Brookside Ave",
    "sg:city":"Freeport",
    "sg:classifiers":[
        {
            "category":"Food & Beverages",
            "subcategory":"Liquor & Beverages",
            "type":"Retail Goods"
        }
    ],
    "sg:phone":"+1   ",
    "sg:postcode":"11520",
    "sg:province":"NY",
    "sg:tags":[
        "alcoholic"
    ],
    "wof:name":"Alexanders Liquor Store",
    "wof:placetype":"venue"
},
  "geometry": {"coordinates":[-73.601079,40.655927],"type":"Point"}
}