{
  "type": "Feature",
  "properties": {
    "addr:full":"150 Clove Rd Staten Island NY 10310",
    "addr:housenumber":"150",
    "addr:postcode":"10310",
    "addr:street":"Clove Rd",
    "iso:country":"US",
    "sg:address":"150 Clove Rd",
    "sg:city":"Staten Island",
    "sg:classifiers":[
        {
            "category":"Building & Trades",
            "subcategory":"Construction",
            "type":"Services"
        }
    ],
    "sg:phone":"+1 718 720 1480",
    "sg:postcode":"10310",
    "sg:province":"NY",
    "sg:tags":[
        "contractor"
    ],
    "wof:name":"Catherine Stlfridge",
    "wof:placetype":"venue"
},
  "geometry": {"coordinates":[-74.12661300000001,40.636234],"type":"Point"}
}