{
  "type": "Feature",
  "properties": {
    "addr:full":"25179 County Route 53 Watertown NY 13601",
    "addr:housenumber":"25179",
    "addr:postcode":"13601",
    "addr:street":"County Route 53",
    "iso:country":"US",
    "sg:address":"25179 County Route 53",
    "sg:city":"Watertown",
    "sg:classifiers":[
        {
            "category":"Manufacturing",
            "subcategory":"Buildings",
            "type":"Manufacturing & Wholesale Goods"
        },
        {
            "category":"Building & Trades",
            "subcategory":"Construction",
            "type":"Services"
        }
    ],
    "sg:phone":"+1 315 782 7721",
    "sg:postcode":"13601",
    "sg:province":"NY",
    "sg:tags":[
        "home",
        "builder",
        "contractor"
    ],
    "wof:name":"S Call & Sons",
    "wof:placetype":"venue"
},
  "geometry": {"coordinates":[-75.94129100000001,44.030727],"type":"Point"}
}