{
  "type": "Feature",
  "properties": {
    "addr:full":"7451 Seneca Rd N Hornell NY 14843",
    "addr:housenumber":"7451",
    "addr:postcode":"14843",
    "addr:street":"Seneca Rd N Hornell",
    "iso:country":"US",
    "sg:address":"7451 Seneca Rd N",
    "sg:city":"Hornell",
    "sg:classifiers":[
        {
            "category":"Shopping",
            "subcategory":"Discount & Variety Stores",
            "type":"Retail Goods"
        }
    ],
    "sg:phone":"+1 607 281 0140",
    "sg:postcode":"14843",
    "sg:province":"NY",
    "wof:name":"Dollar General",
    "wof:placetype":"venue"
},
  "geometry": {"coordinates":[-77.665327,42.361474],"type":"Point"}
}