{
  "type": "Feature",
  "properties": {
    "iso:country":"US",
    "sg:address":"6 Scarsdale Farm Rd",
    "sg:city":"Scarsdale",
    "sg:classifiers":[
        {
            "category":"Professional",
            "subcategory":"Lawyer & Legal Services",
            "type":"Services"
        }
    ],
    "sg:phone":"+1   ",
    "sg:postcode":"10583",
    "sg:province":"NY",
    "wof:name":"Silver & Silver",
    "wof:placetype":"venue"
},
  "geometry": {"coordinates":[-73.824978,40.997851],"type":"Point"}
}