{
  "type": "Feature",
  "properties": {
    "addr:full":"1061 Morris Park Ave Bronx NY 10461",
    "addr:housenumber":"1061",
    "addr:postcode":"10461",
    "addr:street":"Morris Park Ave",
    "iso:country":"US",
    "sg:address":"1061 Morris Park Ave",
    "sg:city":"Bronx",
    "sg:classifiers":[
        {
            "category":"Building & Trades",
            "subcategory":"Construction",
            "type":"Services"
        }
    ],
    "sg:phone":"+1 718 597 0224",
    "sg:postcode":"10461",
    "sg:province":"NY",
    "sg:tags":[
        "roofing",
        "contractor"
    ],
    "wof:name":"RCA Roofing",
    "wof:placetype":"venue"
},
  "geometry": {"coordinates":[-73.85417,40.849084],"type":"Point"}
}