{
  "type": "Feature",
  "properties": {
    "iso:country":"US",
    "sg:address":"720 Albany St",
    "sg:city":"Schenectady",
    "sg:classifiers":[
        {
            "category":"Social Services",
            "type":"Services"
        }
    ],
    "sg:phone":"+1 518 346 4800",
    "sg:postcode":"12307",
    "sg:province":"NY",
    "sg:tags":[
        "organization",
        "welfare"
    ],
    "wof:name":"Catholic Family & Community",
    "wof:placetype":"venue"
},
  "geometry": {"coordinates":[-73.938222,42.809169],"type":"Point"}
}