{
  "type": "Feature",
  "properties": {
    "addr:full":"1865 Clove Rd Staten Island NY 10304",
    "addr:housenumber":"1865",
    "addr:postcode":"10304",
    "addr:street":"Clove Rd",
    "iso:country":"US",
    "sg:address":"1865 Clove Rd",
    "sg:city":"Staten Island",
    "sg:classifiers":[
        {
            "category":"Insurance",
            "subcategory":"Hazard Insurance",
            "type":"Services"
        }
    ],
    "sg:phone":"+1 866 983 8726",
    "sg:postcode":"10304",
    "sg:province":"NY",
    "sg:website":"www.mjfinsurance.com",
    "wof:name":"MJF Insurance Agency",
    "wof:placetype":"venue"
},
  "geometry": {"coordinates":[-74.088336,40.607298],"type":"Point"}
}