{
  "type": "Feature",
  "properties": {
    "addr:full":"502 Bay St Staten Island NY 10304",
    "addr:housenumber":"502",
    "addr:postcode":"10304",
    "addr:street":"Bay St",
    "iso:country":"US",
    "sg:address":"502 Bay St",
    "sg:city":"Staten Island",
    "sg:classifiers":[
        {
            "category":"Personal",
            "subcategory":"Beauty Salon",
            "type":"Services"
        }
    ],
    "sg:phone":"+1 718 815 1878",
    "sg:postcode":"10304",
    "sg:province":"NY",
    "wof:name":"J 316 Next Level Salon",
    "wof:placetype":"venue"
},
  "geometry": {"coordinates":[-74.076787,40.630006],"type":"Point"}
}