{
  "type": "Feature",
  "properties": {
    "iso:country":"US",
    "sg:address":"2365 Niagara Falls Blvd",
    "sg:city":"Niagara Falls",
    "sg:classifiers":[
        {
            "category":"Wholesale",
            "subcategory":"Groceries",
            "type":"Manufacturing & Wholesale Goods"
        }
    ],
    "sg:phone":"+1 716 731 9007",
    "sg:postcode":"14304",
    "sg:province":"NY",
    "sg:tags":[
        "baker"
    ],
    "wof:name":"Rita Mae's",
    "wof:placetype":"venue"
},
  "geometry": {"coordinates":[-78.91489199999999,43.095856],"type":"Point"}
}