{
  "type": "Feature",
  "properties": {
    "addr:full":"169 Main St New Paltz NY 12561",
    "addr:housenumber":"169",
    "addr:postcode":"12561",
    "addr:street":"Main St",
    "iso:country":"US",
    "sg:address":"169 Main St",
    "sg:city":"New Paltz",
    "sg:classifiers":[
        {
            "category":"Professional",
            "subcategory":"Lawyer & Legal Services",
            "type":"Services"
        }
    ],
    "sg:phone":"+1 845 255 8448",
    "sg:postcode":"12561",
    "sg:province":"NY",
    "sg:tags":[
        "attorney"
    ],
    "wof:name":"Jonathan R Sennett PC",
    "wof:placetype":"venue"
},
  "geometry": {"coordinates":[-74.07978900000001,41.746716],"type":"Point"}
}