{
  "type": "Feature",
  "properties": {
    "iso:country":"US",
    "sg:address":"201 Main St",
    "sg:city":"Corinth",
    "sg:classifiers":[
        {
            "category":"Bars & Pubs",
            "type":"Food & Drink"
        }
    ],
    "sg:phone":"+1   ",
    "sg:postcode":"12822",
    "sg:province":"NY",
    "sg:tags":[
        "drinking"
    ],
    "wof:name":"Gil Hoolies Tavern",
    "wof:placetype":"venue"
},
  "geometry": {"coordinates":[-73.83301299999999,43.246361],"type":"Point"}
}