{
  "type": "Feature",
  "properties": {
    "addr:full":"8 Canning St Hilton NY 14468",
    "addr:housenumber":"8",
    "addr:postcode":"14468",
    "addr:street":"Canning St",
    "iso:country":"US",
    "sg:address":"8 Canning St",
    "sg:city":"Hilton",
    "sg:classifiers":[
        {
            "category":"Restaurant",
            "type":"Food & Drink"
        }
    ],
    "sg:phone":"+1 585 392 5180",
    "sg:postcode":"14468",
    "sg:province":"NY",
    "sg:tags":[
        "pizza"
    ],
    "wof:name":"Pontillo's Pizza & Pasta",
    "wof:placetype":"venue"
},
  "geometry": {"coordinates":[-77.787301,43.289122],"type":"Point"}
}