{
  "type": "Feature",
  "properties": {
    "iso:country":"US",
    "sg:address":"79 Maywood Dr",
    "sg:city":"Rochester",
    "sg:classifiers":[
        {
            "category":"Organizations",
            "subcategory":"Religious Organization",
            "type":"Services"
        }
    ],
    "sg:phone":"+1 585 244 4277",
    "sg:postcode":"14618",
    "sg:province":"NY",
    "sg:tags":[
        "clergy"
    ],
    "wof:name":"Raymond F Ferguson",
    "wof:placetype":"venue"
},
  "geometry": {"coordinates":[-77.557987,43.112457],"type":"Point"}
}