{
  "type": "Feature",
  "properties": {
    "iso:country":"US",
    "sg:address":"28 Baltic Ave",
    "sg:city":"Staten Island",
    "sg:classifiers":[
        {
            "category":"Professional",
            "subcategory":"Computer Services",
            "type":"Services"
        }
    ],
    "sg:phone":"+1 718 273 1705",
    "sg:postcode":"10304",
    "sg:province":"NY",
    "sg:tags":[
        "related"
    ],
    "wof:name":"Hanan Ahmed",
    "wof:placetype":"venue"
},
  "geometry": {"coordinates":[-74.09110200000001,40.606218],"type":"Point"}
}