{
  "type": "Feature",
  "properties": {
    "addr:full":"1 N Church St Schenectady NY 12305",
    "addr:housenumber":"1",
    "addr:postcode":"12305",
    "addr:street":"N Church St",
    "iso:country":"US",
    "sg:address":"1 N Church St",
    "sg:city":"Schenectady",
    "sg:classifiers":[
        {
            "category":"Restaurant",
            "type":"Food & Drink"
        }
    ],
    "sg:menulink":"http://www.allmenus.com/ny/schenectady/28333-the-stockade-inn/menu/",
    "sg:phone":"+1 518 346 3400",
    "sg:postcode":"12305",
    "sg:province":"NY",
    "sg:tags":[
        "american",
        "steakhouse"
    ],
    "wof:name":"The Stockade Inn",
    "wof:placetype":"venue"
},
  "geometry": {"coordinates":[-73.947507,42.816622],"type":"Point"}
}