{
  "type": "Feature",
  "properties": {
    "iso:country":"US",
    "sg:address":"190 Palmer Ave",
    "sg:city":"Buffalo",
    "sg:classifiers":[
        {
            "category":"Health Services",
            "subcategory":"Chiropractor",
            "type":"Services"
        }
    ],
    "sg:phone":"+1 716 873 9749",
    "sg:postcode":"14217",
    "sg:province":"NY",
    "sg:tags":[
        "chiropractic"
    ],
    "wof:name":"Battistella",
    "wof:placetype":"venue"
},
  "geometry": {"coordinates":[-78.878377,42.969942],"type":"Point"}
}