{
  "type": "Feature",
  "properties": {
    "addr:full":"4310 Syracuse Rd Cazenovia NY 13035",
    "addr:housenumber":"4310",
    "addr:postcode":"13035",
    "addr:street":"Syracuse Rd",
    "iso:country":"US",
    "sg:address":"4310 Syracuse Rd",
    "sg:city":"Cazenovia",
    "sg:classifiers":[
        {
            "category":"Building & Trades",
            "subcategory":"Electrical",
            "type":"Services"
        }
    ],
    "sg:phone":"+1 315 655 3419",
    "sg:postcode":"13035",
    "sg:province":"NY",
    "sg:tags":[
        "industrial",
        "electrician",
        "electric",
        "contractors-commercial"
    ],
    "wof:name":"Times Stevens Electric",
    "wof:placetype":"venue"
},
  "geometry": {"coordinates":[-75.875704,42.931727],"type":"Point"}
}