{
  "type": "Feature",
  "properties": {
    "addr:full":"664 Flushing Ave Brooklyn NY 11206",
    "addr:housenumber":"664",
    "addr:postcode":"11206",
    "addr:street":"Flushing Ave",
    "iso:country":"US",
    "sg:address":"664 Flushing Ave",
    "sg:city":"Brooklyn",
    "sg:classifiers":[
        {
            "category":"Wholesale",
            "subcategory":"Hardware",
            "type":"Manufacturing & Wholesale Goods"
        }
    ],
    "sg:phone":"+1 718 599 1682",
    "sg:postcode":"11206",
    "sg:province":"NY",
    "sg:tags":[
        "refrigeration"
    ],
    "wof:name":"Batista Rfrgn & A Conditioner",
    "wof:placetype":"venue"
},
  "geometry": {"coordinates":[-73.94712699999999,40.700123],"type":"Point"}
}