{
  "type": "Feature",
  "properties": {
    "iso:country":"US",
    "sg:address":"284 Broad St",
    "sg:city":"Salamanca",
    "sg:classifiers":[
        {
            "category":"Organizations",
            "subcategory":"Non-profit Organization",
            "type":"Services"
        }
    ],
    "sg:phone":"+1 716 945 0619",
    "sg:postcode":"14779",
    "sg:province":"NY",
    "sg:tags":[
        "charitable",
        "institution"
    ],
    "wof:name":"Catholic Charities",
    "wof:placetype":"venue"
},
  "geometry": {"coordinates":[-78.72418999999999,42.156338],"type":"Point"}
}