{
  "type": "Feature",
  "properties": {
    "iso:country":"US",
    "sg:address":"25 Mill Rd",
    "sg:city":"Eastchester",
    "sg:classifiers":[
        {
            "category":"Personal",
            "subcategory":"Nail Salon",
            "type":"Services"
        }
    ],
    "sg:phone":"+1 914 793 1888",
    "sg:postcode":"10709",
    "sg:province":"NY",
    "wof:name":"Classic Nail",
    "wof:placetype":"venue"
},
  "geometry": {"coordinates":[-73.811981,40.956249],"type":"Point"}
}