{
  "type": "Feature",
  "properties": {
    "iso:country":"US",
    "sg:address":"53 E 64 St",
    "sg:city":"New York",
    "sg:classifiers":[
        {
            "category":"Professional",
            "subcategory":"Research",
            "type":"Services"
        }
    ],
    "sg:phone":"+1 212 639 9585",
    "sg:postcode":"10065",
    "sg:province":"NY",
    "sg:tags":[
        "environmental",
        "ecological"
    ],
    "wof:name":"Allergy & Indoor Environ Svc",
    "wof:placetype":"venue"
},
  "geometry": {"coordinates":[-73.96789,40.76633],"type":"Point"}
}