{
  "type": "Feature",
  "properties": {
    "addr:full":"7612 18th Ave Brooklyn NY 11214",
    "addr:housenumber":"7612",
    "addr:postcode":"11214",
    "addr:street":"18Th Ave",
    "iso:country":"US",
    "sg:address":"7612 18th Ave",
    "sg:city":"Brooklyn",
    "sg:classifiers":[
        {
            "category":"Manufacturing",
            "subcategory":"Apparel",
            "type":"Manufacturing & Wholesale Goods"
        }
    ],
    "sg:phone":"+1 718 331 3622",
    "sg:postcode":"11214",
    "sg:province":"NY",
    "sg:tags":[
        "vintage",
        "used",
        "clothing",
        "consignment"
    ],
    "wof:name":"Drny Inc",
    "wof:placetype":"venue"
},
  "geometry": {"coordinates":[-73.99700199999999,40.612598],"type":"Point"}
}