{
  "type": "Feature",
  "properties": {
    "iso:country":"US",
    "sg:address":"58 Pine St",
    "sg:city":"New Canaan",
    "sg:classifiers":[
        {
            "category":"Wholesale",
            "subcategory":"Groceries",
            "type":"Manufacturing & Wholesale Goods"
        },
        {
            "category":"Insurance",
            "subcategory":"Insurance Agent",
            "type":"Services"
        }
    ],
    "sg:phone":"+1 203 966 4441",
    "sg:postcode":"06840",
    "sg:province":"NY",
    "sg:tags":[
        "tea",
        "coffee"
    ],
    "wof:name":"Fairfield Trading Brokers LLC",
    "wof:placetype":"venue"
},
  "geometry": {"coordinates":[-73.49648999999999,41.145138],"type":"Point"}
}