{
  "type": "Feature",
  "properties": {
    "iso:country":"US",
    "sg:address":"11 Crescent Pl",
    "sg:city":"Monroe",
    "sg:classifiers":[
        {
            "category":"Home & Garden",
            "subcategory":"Furniture",
            "type":"Retail Goods"
        }
    ],
    "sg:phone":"+1 845 782 5303",
    "sg:postcode":"10950",
    "sg:province":"NY",
    "sg:tags":[
        "store"
    ],
    "sg:website":"www.sleepys.com",
    "wof:name":"Sleepy's Llc",
    "wof:placetype":"venue"
},
  "geometry": {"coordinates":[-74.19712,41.324403],"type":"Point"}
}