{
  "type": "Feature",
  "properties": {
    "iso:country":"US",
    "sg:address":"53 Brown Rd",
    "sg:city":"Ithaca",
    "sg:classifiers":[
        {
            "category":"Professional",
            "subcategory":"Research",
            "type":"Services"
        }
    ],
    "sg:phone":"+1 607 257 0332",
    "sg:postcode":"14850",
    "sg:province":"NY",
    "sg:tags":[
        "development",
        "laboratory"
    ],
    "sg:website":"www.gnsbiotech.com",
    "wof:name":"Gene Network Sciences Inc",
    "wof:placetype":"venue"
},
  "geometry": {"coordinates":[-76.46252699999999,42.487533],"type":"Point"}
}