{
  "type": "Feature",
  "properties": {
    "addr:full":"126 N Harvest St Buffalo NY 14221",
    "addr:housenumber":"126",
    "addr:postcode":"14221",
    "addr:street":"N Harvest St",
    "iso:country":"US",
    "sg:address":"126 N Harvest St",
    "sg:city":"Buffalo",
    "sg:classifiers":[
        {
            "category":"Restaurant",
            "type":"Food & Drink"
        }
    ],
    "sg:phone":"+1   ",
    "sg:postcode":"14221",
    "sg:province":"NY",
    "sg:tags":[
        "eating"
    ],
    "wof:name":"Cape Restaurant Lounge",
    "wof:placetype":"venue"
},
  "geometry": {"coordinates":[-78.751142,42.955794],"type":"Point"}
}