{
  "type": "Feature",
  "properties": {
    "iso:country":"US",
    "sg:address":"7 Lawrence Hill Rd Ste 2",
    "sg:city":"Huntington",
    "sg:classifiers":[
        {
            "category":"Professional",
            "subcategory":"Art Services",
            "type":"Services"
        }
    ],
    "sg:phone":"+1 631 673 3060",
    "sg:postcode":"11743",
    "sg:province":"NY",
    "sg:tags":[
        "designer",
        "display",
        "producer"
    ],
    "sg:website":"http://www.skylardesign.com",
    "wof:name":"Skylar Design Inc",
    "wof:placetype":"venue"
},
  "geometry": {"coordinates":[-73.43450199999999,40.869282],"type":"Point"}
}