{
  "type": "Feature",
  "properties": {
    "iso:country":"US",
    "sg:address":"146 S Robinson Ave",
    "sg:city":"Newburgh",
    "sg:classifiers":[
        {
            "category":"Building & Trades",
            "subcategory":"Cleaning & Sanitation",
            "type":"Services"
        },
        {
            "category":"Building & Trades",
            "subcategory":"Construction",
            "type":"Services"
        },
        {
            "category":"Home & Garden",
            "subcategory":"Carpets & Floor Coverings",
            "type":"Retail Goods"
        }
    ],
    "sg:phone":"+1 845 561 8453",
    "sg:postcode":"12550",
    "sg:province":"NY",
    "sg:tags":[
        "tile-cleaning",
        "material",
        "refinishing",
        "sealing",
        "marble",
        "terrazzo"
    ],
    "wof:name":"Accutile",
    "wof:placetype":"venue"
},
  "geometry": {"coordinates":[-74.022087,41.494461],"type":"Point"}
}