{
  "type": "Feature",
  "properties": {
    "addr:full":"180 Varick St New York NY 10014",
    "addr:housenumber":"180",
    "addr:postcode":"10014",
    "addr:street":"Varick St",
    "iso:country":"US",
    "sg:address":"180 Varick St",
    "sg:city":"New York",
    "sg:classifiers":[
        {
            "category":"Professional",
            "type":"Services"
        }
    ],
    "sg:phone":"+1 212 741 9939",
    "sg:postcode":"10014",
    "sg:province":"NY",
    "sg:tags":[
        "establishment"
    ],
    "wof:name":"Eye Like-Hansel Digital Studio",
    "wof:placetype":"venue"
},
  "geometry": {"coordinates":[-74.005391,40.72756],"type":"Point"}
}