{
  "type": "Feature",
  "properties": {
    "addr:full":"171 Lee Ave Brooklyn NY 11211",
    "addr:housenumber":"171",
    "addr:postcode":"11211",
    "addr:street":"Lee Ave",
    "iso:country":"US",
    "sg:address":"171 Lee Ave",
    "sg:city":"Brooklyn",
    "sg:classifiers":[
        {
            "category":"Shopping",
            "subcategory":"Jewelry",
            "type":"Retail Goods"
        }
    ],
    "sg:phone":"+1   ",
    "sg:postcode":"11211",
    "sg:province":"NY",
    "wof:name":"Emile Fischer",
    "wof:placetype":"venue"
},
  "geometry": {"coordinates":[-73.95656200000001,40.702872],"type":"Point"}
}