{
  "type": "Feature",
  "properties": {
    "addr:full":"246 Buffalo St Hamburg NY 14075",
    "addr:housenumber":"246",
    "addr:postcode":"14075",
    "addr:street":"Buffalo St",
    "iso:country":"US",
    "sg:address":"246 Buffalo St",
    "sg:city":"Hamburg",
    "sg:classifiers":[
        {
            "category":"Health Services",
            "subcategory":"Health Practitioner",
            "type":"Services"
        }
    ],
    "sg:phone":"+1   ",
    "sg:postcode":"14075",
    "sg:province":"NY",
    "wof:name":"Southtowns Massage Therapy",
    "wof:placetype":"venue"
},
  "geometry": {"coordinates":[-78.825881,42.72168],"type":"Point"}
}