{
  "type": "Feature",
  "properties": {
    "addr:full":"2414 65th St Brooklyn NY 11204",
    "addr:housenumber":"2414",
    "addr:postcode":"11204",
    "addr:street":"65Th St",
    "iso:country":"US",
    "sg:address":"2414 65th St",
    "sg:city":"Brooklyn",
    "sg:classifiers":[
        {
            "category":"Wholesale",
            "subcategory":"Electrical",
            "type":"Manufacturing & Wholesale Goods"
        }
    ],
    "sg:phone":"+1 718 339 6922",
    "sg:postcode":"11204",
    "sg:province":"NY",
    "sg:tags":[
        "equipment",
        "video",
        "electronic"
    ],
    "wof:name":"Comp International",
    "wof:placetype":"venue"
},
  "geometry": {"coordinates":[-73.97654799999999,40.610836],"type":"Point"}
}