{
  "type": "Feature",
  "properties": {
    "iso:country":"US",
    "sg:address":"23 N Village Ave",
    "sg:city":"Rockville Centre",
    "sg:classifiers":[
        {
            "category":"Restaurant",
            "type":"Food & Drink"
        }
    ],
    "sg:phone":"+1   ",
    "sg:postcode":"11570",
    "sg:province":"NY",
    "sg:tags":[
        "eating"
    ],
    "wof:name":"Roma Pizzeria Inc",
    "wof:placetype":"venue"
},
  "geometry": {"coordinates":[-73.64762899999999,40.65695],"type":"Point"}
}