{
  "type": "Feature",
  "properties": {
    "addr:full":"327 Graham Ave Brooklyn NY 11211",
    "addr:housenumber":"327",
    "addr:postcode":"11211",
    "addr:street":"Graham Ave",
    "iso:country":"US",
    "sg:address":"327 Graham Ave",
    "sg:city":"Brooklyn",
    "sg:classifiers":[
        {
            "category":"Professional",
            "subcategory":"Lawyer & Legal Services",
            "type":"Services"
        }
    ],
    "sg:phone":"+1   ",
    "sg:postcode":"11211",
    "sg:province":"NY",
    "wof:name":"James Patrick Pepe",
    "wof:placetype":"venue"
},
  "geometry": {"coordinates":[-73.944427,40.714246],"type":"Point"}
}