{
  "type": "Feature",
  "properties": {
    "iso:country":"US",
    "sg:address":"223 Laurel Rd",
    "sg:city":"East Northport",
    "sg:classifiers":[
        {
            "category":"Food & Beverages",
            "subcategory":"Groceries & Convenience Stores",
            "type":"Retail Goods"
        }
    ],
    "sg:phone":"+1   ",
    "sg:postcode":"11731",
    "sg:province":"NY",
    "wof:name":"7-Eleven",
    "wof:placetype":"venue"
},
  "geometry": {"coordinates":[-73.332318,40.888385],"type":"Point"}
}