{
  "type": "Feature",
  "properties": {
    "iso:country":"US",
    "sg:address":"9643 Brewerton Rd",
    "sg:city":"Brewerton",
    "sg:classifiers":[
        {
            "category":"Shopping",
            "subcategory":"Catalog Store",
            "type":"Retail Goods"
        },
        {
            "category":"Shopping",
            "subcategory":"Gifts & Souvenirs",
            "type":"Retail Goods"
        }
    ],
    "sg:phone":"+1 315 668 2499",
    "sg:postcode":"13029",
    "sg:province":"NY",
    "sg:tags":[
        "house",
        "mail",
        "collectible"
    ],
    "wof:name":"Bev's Racing Images",
    "wof:placetype":"venue"
},
  "geometry": {"coordinates":[-76.140438,43.237007],"type":"Point"}
}