{
  "type": "Feature",
  "properties": {
    "iso:country":"US",
    "sg:address":"201 Woodland Ave",
    "sg:city":"Syracuse",
    "sg:classifiers":[
        {
            "category":"Personal",
            "subcategory":"Beauty Salon",
            "type":"Services"
        }
    ],
    "sg:phone":"+1 315 442 5944",
    "sg:postcode":"13205",
    "sg:province":"NY",
    "wof:name":"Orestes's Beauty Salon",
    "wof:placetype":"venue"
},
  "geometry": {"coordinates":[-76.14242299999999,43.029855],"type":"Point"}
}