{
  "type": "Feature",
  "properties": {
    "addr:full":"188 Rockaway Ave Valley Stream NY 11580",
    "addr:housenumber":"188",
    "addr:postcode":"11580",
    "addr:street":"Rockaway Ave",
    "iso:country":"US",
    "sg:address":"188 Rockaway Ave",
    "sg:city":"Valley Stream",
    "sg:classifiers":[
        {
            "category":"Organizations",
            "subcategory":"Religious Organization",
            "type":"Services"
        }
    ],
    "sg:phone":"+1 516 561 6150",
    "sg:postcode":"11580",
    "sg:province":"NY",
    "sg:tags":[
        "church"
    ],
    "sg:website":"www.ag.org",
    "wof:name":"Bethlehem Assembly of God",
    "wof:placetype":"venue"
},
  "geometry": {"coordinates":[-73.69945,40.661802],"type":"Point"}
}