{
  "type": "Feature",
  "properties": {
    "iso:country":"US",
    "sg:address":"39 Southard Ave",
    "sg:city":"Babylon",
    "sg:classifiers":[
        {
            "category":"Building & Trades",
            "subcategory":"Construction",
            "type":"Services"
        }
    ],
    "sg:phone":"+1 631 376 1282",
    "sg:postcode":"11704",
    "sg:province":"NY",
    "sg:tags":[
        "painter"
    ],
    "wof:name":"North Star Painting",
    "wof:placetype":"venue"
},
  "geometry": {"coordinates":[-73.346137,40.696829],"type":"Point"}
}