{
  "type": "Feature",
  "properties": {
    "addr:full":"5904 Junction Boulevard Elmhurst NY 11373",
    "addr:housenumber":"5904",
    "addr:postcode":"11373",
    "addr:street":"Junction Boulevard",
    "iso:country":"US",
    "sg:address":"5904 Junction Boulevard",
    "sg:city":"Elmhurst",
    "sg:classifiers":[
        {
            "category":"Building & Trades",
            "subcategory":"Locksmith",
            "type":"Services"
        }
    ],
    "sg:phone":"+1 718 334 0360",
    "sg:postcode":"11373",
    "sg:province":"NY",
    "sg:tags":[
        "key"
    ],
    "wof:name":"A 24 Hour A Corona Emergency Locksmith",
    "wof:placetype":"venue"
},
  "geometry": {"coordinates":[-73.86520299999999,40.735089],"type":"Point"}
}