{
  "type": "Feature",
  "properties": {
    "addr:full":"99 Robertson Ave White Plains NY 10606",
    "addr:housenumber":"99",
    "addr:postcode":"10606",
    "addr:street":"Robertson Ave",
    "iso:country":"US",
    "sg:address":"99 Robertson Ave",
    "sg:city":"White Plains",
    "sg:classifiers":[
        {
            "category":"Recreation",
            "type":"Entertainment"
        }
    ],
    "sg:phone":"+1 914 641 2610",
    "sg:postcode":"10606",
    "sg:province":"NY",
    "sg:tags":[
        "club",
        "membership"
    ],
    "wof:name":"Badger Swim Club",
    "wof:placetype":"venue"
},
  "geometry": {"coordinates":[-73.78318400000001,41.033792],"type":"Point"}
}