{
  "type": "Feature",
  "properties": {
    "addr:full":"9 Nelson Ave Wappingers Falls NY 12590",
    "addr:housenumber":"9",
    "addr:postcode":"12590",
    "addr:street":"Nelson Ave",
    "iso:country":"US",
    "sg:address":"9 Nelson Ave",
    "sg:city":"Wappingers Falls",
    "sg:classifiers":[
        {
            "category":"Building & Trades",
            "subcategory":"Construction",
            "type":"Services"
        }
    ],
    "sg:phone":"+1 845 297 2804",
    "sg:postcode":"12590",
    "sg:province":"NY",
    "sg:tags":[
        "blacktop",
        "contractor"
    ],
    "wof:name":"Marcojohn Construction",
    "wof:placetype":"venue"
},
  "geometry": {"coordinates":[-73.92288600000001,41.607995],"type":"Point"}
}