{
  "type": "Feature",
  "properties": {
    "addr:full":"4507 8th Ave Brooklyn NY 11220",
    "addr:housenumber":"4507",
    "addr:postcode":"11220",
    "addr:street":"8Th Ave",
    "iso:country":"US",
    "sg:address":"4507 8th Ave",
    "sg:city":"Brooklyn",
    "sg:classifiers":[
        {
            "category":"Shopping",
            "subcategory":"Pharmacy",
            "type":"Retail Goods"
        }
    ],
    "sg:phone":"+1 718 633 8388",
    "sg:postcode":"11220",
    "sg:province":"NY",
    "sg:tags":[
        "drugstore"
    ],
    "wof:name":"Family First Pharmacy & Surgical Supplies Inc",
    "wof:placetype":"venue"
},
  "geometry": {"coordinates":[-74.022575,40.643805],"type":"Point"}
}