{
  "type": "Feature",
  "properties": {
    "addr:full":"100 N Central Ave Valley Stream NY 11580",
    "addr:housenumber":"100",
    "addr:postcode":"11580",
    "addr:street":"N Central Ave",
    "iso:country":"US",
    "sg:address":"100 N Central Ave",
    "sg:city":"Valley Stream",
    "sg:classifiers":[
        {
            "category":"Health Services",
            "subcategory":"Doctor",
            "type":"Services"
        }
    ],
    "sg:phone":"+1 516 568 0076",
    "sg:postcode":"11580",
    "sg:province":"NY",
    "wof:name":"Vilceus Antenorp",
    "wof:placetype":"venue"
},
  "geometry": {"coordinates":[-73.70859,40.670309],"type":"Point"}
}