{
  "type": "Feature",
  "properties": {
    "iso:country":"US",
    "sg:address":"106 Blockhouse Creek Ct",
    "sg:city":"Albany",
    "sg:classifiers":[
        {
            "category":"Manufacturing",
            "subcategory":"Printing",
            "type":"Manufacturing & Wholesale Goods"
        }
    ],
    "sg:phone":"+1   ",
    "sg:postcode":"12203",
    "sg:province":"NY",
    "sg:tags":[
        "book"
    ],
    "wof:name":"Books Worth Writing",
    "wof:placetype":"venue"
},
  "geometry": {"coordinates":[-73.88547800000001,42.69018],"type":"Point"}
}