{
  "type": "Feature",
  "properties": {
    "iso:country":"US",
    "sg:address":"6100 Elm Ave",
    "sg:city":"Little York",
    "sg:classifiers":[
        {
            "category":"Arts & Performance",
            "subcategory":"Theater",
            "type":"Entertainment"
        }
    ],
    "sg:phone":"+1 607 749 2796",
    "sg:postcode":"13087",
    "sg:province":"NY",
    "sg:tags":[
        "music"
    ],
    "wof:name":"Jp Morgan Band",
    "wof:placetype":"venue"
},
  "geometry": {"coordinates":[-76.15777799999999,42.702906],"type":"Point"}
}