{
  "type": "Feature",
  "properties": {
    "iso:country":"US",
    "sg:address":"8 Preston Ct",
    "sg:city":"Brooklyn",
    "sg:classifiers":[
        {
            "category":"Building & Trades",
            "subcategory":"Construction",
            "type":"Services"
        }
    ],
    "sg:phone":"+1 718 251 8090",
    "sg:postcode":"11234",
    "sg:province":"NY",
    "sg:tags":[
        "woodworker"
    ],
    "wof:name":"International Woodworking Co",
    "wof:placetype":"venue"
},
  "geometry": {"coordinates":[-73.923126,40.638773],"type":"Point"}
}