{
  "type": "Feature",
  "properties": {
    "addr:full":"77 N Centre Ave Ste 315 Rockville Centre NY 11570",
    "addr:housenumber":"77",
    "addr:postcode":"11570",
    "addr:street":"N Centre Ave Ste 315",
    "iso:country":"US",
    "sg:address":"77 N Centre Ave Ste 315",
    "sg:city":"Rockville Centre",
    "sg:classifiers":[
        {
            "category":"Professional",
            "subcategory":"Accounting & Tax Preparation",
            "type":"Services"
        }
    ],
    "sg:phone":"+1 516 763 5567",
    "sg:postcode":"11570",
    "sg:province":"NY",
    "sg:tags":[
        "accountant"
    ],
    "wof:name":"Schwed Monroe A CPA",
    "wof:placetype":"venue"
},
  "geometry": {"coordinates":[-73.649597,40.659],"type":"Point"}
}