{
  "type": "Feature",
  "properties": {
    "addr:full":"571 McDonald Ave Brooklyn NY 11218",
    "addr:housenumber":"571",
    "addr:postcode":"11218",
    "addr:street":"Mcdonald Ave",
    "iso:country":"US",
    "sg:address":"571 McDonald Ave",
    "sg:city":"Brooklyn",
    "sg:classifiers":[
        {
            "category":"Health Services",
            "subcategory":"Clinic",
            "type":"Services"
        }
    ],
    "sg:phone":"+1 718 686 7600",
    "sg:postcode":"11218",
    "sg:province":"NY",
    "sg:tags":[
        "medical",
        "group",
        "doctor"
    ],
    "sg:website":"www.ezramedical.com",
    "wof:name":"Ezra Medical Center",
    "wof:placetype":"venue"
},
  "geometry": {"coordinates":[-73.978302,40.6381],"type":"Point"}
}