{
  "type": "Feature",
  "properties": {
    "addr:full":"7204 Avenue T Brooklyn NY 11234",
    "addr:housenumber":"7204",
    "addr:postcode":"11234",
    "addr:street":"Avenue T",
    "iso:country":"US",
    "sg:address":"7204 Avenue T",
    "sg:city":"Brooklyn",
    "sg:classifiers":[
        {
            "category":"Building & Trades",
            "subcategory":"Plumbing",
            "type":"Services"
        }
    ],
    "sg:phone":"+1 718 710 4357",
    "sg:postcode":"11234",
    "sg:province":"NY",
    "wof:name":"Aaa4u Plumbing",
    "wof:placetype":"venue"
},
  "geometry": {"coordinates":[-73.908254,40.621692],"type":"Point"}
}