{
  "type": "Feature",
  "properties": {
    "iso:country":"US",
    "sg:address":"1704 Avenue M Ground Fl",
    "sg:city":"Brooklyn",
    "sg:classifiers":[
        {
            "category":"Health Services",
            "subcategory":"Clinic",
            "type":"Services"
        },
        {
            "category":"Insurance",
            "subcategory":"Hazard Insurance",
            "type":"Services"
        },
        {
            "category":"Community Center",
            "type":"Public Place"
        }
    ],
    "sg:phone":"+1 718 339 6753",
    "sg:postcode":"11230",
    "sg:province":"NY",
    "sg:tags":[
        "medical",
        "group"
    ],
    "wof:name":"The World of Health",
    "wof:placetype":"venue"
},
  "geometry": {"coordinates":[-73.95809800000001,40.618214],"type":"Point"}
}