{
  "type": "Feature",
  "properties": {
    "addr:full":"29 Maple St Potsdam NY 13676",
    "addr:housenumber":"29",
    "addr:postcode":"13676",
    "addr:street":"Maple St",
    "iso:country":"US",
    "sg:address":"29 Maple St",
    "sg:city":"Potsdam",
    "sg:classifiers":[
        {
            "category":"Restaurant",
            "type":"Food & Drink"
        }
    ],
    "sg:phone":"+1 315 265 8720",
    "sg:postcode":"13676",
    "sg:province":"NY",
    "wof:name":"California Rotisserie Chicken",
    "wof:placetype":"venue"
},
  "geometry": {"coordinates":[-74.99122800000001,44.66735],"type":"Point"}
}