{
  "type": "Feature",
  "properties": {
    "iso:country":"US",
    "sg:address":"323 Tait Ave",
    "sg:city":"Rochester",
    "sg:classifiers":[
        {
            "category":"Building & Trades",
            "subcategory":"Plumbing",
            "type":"Services"
        }
    ],
    "sg:phone":"+1 585 663 1040",
    "sg:postcode":"14616",
    "sg:province":"NY",
    "sg:tags":[
        "contractor"
    ],
    "wof:name":"Help Services",
    "wof:placetype":"venue"
},
  "geometry": {"coordinates":[-77.650814,43.230833],"type":"Point"}
}