{
  "type": "Feature",
  "properties": {
    "addr:full":"555 5th Avenue New York NY 10017",
    "addr:housenumber":"555",
    "addr:postcode":"10017",
    "addr:street":"5Th Avenue",
    "iso:country":"US",
    "sg:address":"555 5th Avenue",
    "sg:city":"New York",
    "sg:classifiers":[
        {
            "category":"Professional",
            "subcategory":"Accounting & Tax Preparation",
            "type":"Services"
        }
    ],
    "sg:phone":"+1 212 697 0606",
    "sg:postcode":"10017",
    "sg:province":"NY",
    "sg:tags":[
        "accountant"
    ],
    "wof:name":"Brown Edwin S",
    "wof:placetype":"venue"
},
  "geometry": {"coordinates":[-73.979056,40.75581],"type":"Point"}
}