{
  "type": "Feature",
  "properties": {
    "addr:full":"141 W 62 St New York NY 10023",
    "addr:housenumber":"141",
    "addr:postcode":"10023",
    "addr:street":"W 62 St",
    "iso:country":"US",
    "sg:address":"141 W 62 St",
    "sg:city":"New York",
    "sg:classifiers":[
        {
            "category":"Shopping",
            "subcategory":"Shoes",
            "type":"Retail Goods"
        }
    ],
    "sg:phone":"+1 212 829 0778",
    "sg:postcode":"10023",
    "sg:province":"NY",
    "wof:name":"62nd Street Shoe Store Inc",
    "wof:placetype":"venue"
},
  "geometry": {"coordinates":[-73.985345,40.77189],"type":"Point"}
}