{
  "type": "Feature",
  "properties": {
    "addr:full":"463 Lexington Ave Manhattan NY 10017",
    "addr:housenumber":"463",
    "addr:postcode":"10017",
    "addr:street":"Lexington Ave",
    "iso:country":"US",
    "sg:address":"463 Lexington Ave",
    "sg:city":"Manhattan",
    "sg:classifiers":[
        {
            "category":"Restaurant",
            "type":"Food & Drink"
        }
    ],
    "sg:phone":"+1 212 867 8383",
    "sg:postcode":"10017",
    "sg:province":"NY",
    "sg:tags":[
        "new",
        "american"
    ],
    "wof:name":"Grand Central Star Cafe",
    "wof:placetype":"venue"
},
  "geometry": {"coordinates":[-73.974276,40.75346],"type":"Point"}
}