{
  "type": "Feature",
  "properties": {
    "addr:full":"250 W 100th St New York NY 10025",
    "addr:housenumber":"250",
    "addr:postcode":"10025",
    "addr:street":"W 100Th St",
    "iso:country":"US",
    "sg:address":"250 W 100th St",
    "sg:city":"New York",
    "sg:classifiers":[
        {
            "category":"Recreation",
            "type":"Entertainment"
        }
    ],
    "sg:phone":"+1 212 864 7253",
    "sg:postcode":"10025",
    "sg:province":"NY",
    "sg:tags":[
        "table",
        "tennis",
        "facility"
    ],
    "wof:name":"Manhattan Table Tennis Club",
    "wof:placetype":"venue"
},
  "geometry": {"coordinates":[-73.971161,40.79763],"type":"Point"}
}