{
  "type": "Feature",
  "properties": {
    "iso:country":"US",
    "sg:address":"39 N Broadway",
    "sg:city":"White Plains",
    "sg:classifiers":[
        {
            "category":"Shopping",
            "subcategory":"Used Merchandise",
            "type":"Retail Goods"
        }
    ],
    "sg:phone":"+1 914 949 1241",
    "sg:postcode":"10601",
    "sg:province":"NY",
    "sg:tags":[
        "shop",
        "thrift"
    ],
    "wof:name":"Thrift Shop Of White Plains",
    "wof:placetype":"venue"
},
  "geometry": {"coordinates":[-73.76626400000001,41.038286],"type":"Point"}
}