{
  "type": "Feature",
  "properties": {
    "iso:country":"US",
    "sg:address":"55 Kings Hwy",
    "sg:city":"Buffalo",
    "sg:classifiers":[
        {
            "category":"Education",
            "subcategory":"School",
            "type":"Public Place"
        }
    ],
    "sg:phone":"+1 716 362 7100",
    "sg:postcode":"14226",
    "sg:province":"NY",
    "sg:tags":[
        "middle"
    ],
    "sg:website":"http://www.amherst.k12.ny.us",
    "wof:name":"Amherst Middle School",
    "wof:placetype":"venue"
},
  "geometry": {"coordinates":[-78.79119300000001,42.956528],"type":"Point"}
}