{
  "type": "Feature",
  "properties": {
    "iso:country":"US",
    "sg:address":"14 Edgewood Dr",
    "sg:city":"Carmel",
    "sg:classifiers":[
        {
            "category":"Professional",
            "subcategory":"Management & Consulting",
            "type":"Services"
        }
    ],
    "sg:phone":"+1 845 276 0072",
    "sg:postcode":"10512",
    "sg:province":"NY",
    "sg:tags":[
        "consultant"
    ],
    "wof:name":"Porter Marketing Group Inc",
    "wof:placetype":"venue"
},
  "geometry": {"coordinates":[-73.674046,41.36144],"type":"Point"}
}