{
  "type": "Feature",
  "properties": {
    "iso:country":"US",
    "sg:address":"880 Oyster Bay Rd",
    "sg:city":"East Norwich",
    "sg:classifiers":[
        {
            "category":"Education",
            "subcategory":"School",
            "type":"Public Place"
        }
    ],
    "sg:phone":"+1 516 624 6559",
    "sg:postcode":"11732",
    "sg:province":"NY",
    "sg:tags":[
        "middle"
    ],
    "sg:website":"www.oben.powertolearn.com",
    "wof:name":"James H Vernon School",
    "wof:placetype":"venue"
},
  "geometry": {"coordinates":[-73.535809,40.849322],"type":"Point"}
}