{
  "type": "Feature",
  "properties": {
    "addr:full":"3579 Suncrest Ave Yorktown Heights NY 10598",
    "addr:housenumber":"3579",
    "addr:postcode":"10598",
    "addr:street":"Suncrest Ave",
    "iso:country":"US",
    "sg:address":"3579 Suncrest Ave",
    "sg:city":"Yorktown Heights",
    "sg:classifiers":[
        {
            "category":"Building & Trades",
            "subcategory":"Construction",
            "type":"Services"
        }
    ],
    "sg:phone":"+1 914 243 0590",
    "sg:postcode":"10598",
    "sg:province":"NY",
    "sg:tags":[
        "contractor"
    ],
    "wof:name":"Installation Services",
    "wof:placetype":"venue"
},
  "geometry": {"coordinates":[-73.812504,41.326697],"type":"Point"}
}