{
  "type": "Feature",
  "properties": {
    "addr:full":"792 Franklin Ave Brooklyn NY 11238",
    "addr:housenumber":"792",
    "addr:postcode":"11238",
    "addr:street":"Franklin Ave",
    "iso:country":"US",
    "sg:address":"792 Franklin Ave",
    "sg:city":"Brooklyn",
    "sg:classifiers":[
        {
            "category":"Real Estate",
            "subcategory":"Real Estate Agent",
            "type":"Services"
        },
        {
            "category":"Real Estate",
            "subcategory":"Real Estate Operator",
            "type":"Services"
        }
    ],
    "sg:phone":"+1 718 773 3255",
    "sg:postcode":"11238",
    "sg:province":"NY",
    "sg:tags":[
        "building",
        "apartment"
    ],
    "wof:name":"E Martin Rentals",
    "wof:placetype":"venue"
},
  "geometry": {"coordinates":[-73.958006,40.670823],"type":"Point"}
}