{
  "type": "Feature",
  "properties": {
    "iso:country":"US",
    "sg:address":"E Boyds Rd",
    "sg:city":"Carmel",
    "sg:classifiers":[
        {
            "category":"Education",
            "subcategory":"Special Training",
            "type":"Public Place"
        }
    ],
    "sg:phone":"+1 845 225 8226",
    "sg:postcode":"10512",
    "sg:province":"NY",
    "sg:tags":[
        "school",
        "specialty"
    ],
    "sg:website":"www.clearpool.org",
    "wof:name":"Clearpool Education Center",
    "wof:placetype":"venue"
},
  "geometry": {"coordinates":[-73.682098,41.448002],"type":"Point"}
}