{
  "type": "Feature",
  "properties": {
    "addr:full":"354 Woodland Ct Coram NY 11727",
    "addr:housenumber":"354",
    "addr:postcode":"11727",
    "addr:street":"Woodland Ct",
    "iso:country":"US",
    "sg:address":"354 Woodland Ct",
    "sg:city":"Coram",
    "sg:classifiers":[
        {
            "category":"Building & Trades",
            "subcategory":"Construction",
            "type":"Services"
        }
    ],
    "sg:phone":"+1 631 698 0681",
    "sg:postcode":"11727",
    "sg:province":"NY",
    "sg:tags":[
        "contractor"
    ],
    "wof:name":"Dunne Tile Works",
    "wof:placetype":"venue"
},
  "geometry": {"coordinates":[-73.010265,40.860942],"type":"Point"}
}