{
  "type": "Feature",
  "properties": {
    "addr:full":"11251 Roosevelt Avenue Corona NY 11368",
    "addr:housenumber":"11251",
    "addr:postcode":"11368",
    "addr:street":"Roosevelt Avenue",
    "iso:country":"US",
    "sg:address":"11251 Roosevelt Avenue",
    "sg:city":"Corona",
    "sg:classifiers":[
        {
            "category":"Restaurant",
            "type":"Food & Drink"
        }
    ],
    "sg:phone":"+1 718 335 4870",
    "sg:postcode":"11368",
    "sg:province":"NY",
    "wof:name":"El Chicano Bar & Restaurnat",
    "wof:placetype":"venue"
},
  "geometry": {"coordinates":[-73.854027,40.752236],"type":"Point"}
}