{
  "type": "Feature",
  "properties": {
    "iso:country":"US",
    "sg:address":"617 Kennedy Dr",
    "sg:city":"Spring Valley",
    "sg:classifiers":[
        {
            "category":"Building & Trades",
            "subcategory":"Construction",
            "type":"Services"
        }
    ],
    "sg:phone":"+1 845 354 0297",
    "sg:postcode":"10977",
    "sg:province":"NY",
    "sg:tags":[
        "general",
        "contractor"
    ],
    "wof:name":"Five Star General Contracting",
    "wof:placetype":"venue"
},
  "geometry": {"coordinates":[-74.05649200000001,41.102168],"type":"Point"}
}