{
  "type": "Feature",
  "properties": {
    "iso:country":"US",
    "sg:address":"1744 Old Rte 9",
    "sg:city":"Clifton Park",
    "sg:classifiers":[
        {
            "category":"Communications",
            "type":"Services"
        }
    ],
    "sg:phone":"+1 518 371 2881",
    "sg:postcode":"12065",
    "sg:province":"NY",
    "wof:name":"Capital Communications Fed",
    "wof:placetype":"venue"
},
  "geometry": {"coordinates":[-73.773044,42.867359],"type":"Point"}
}