{
  "type": "Feature",
  "properties": {
    "iso:country":"US",
    "sg:address":"2075 Jericho Tpke",
    "sg:city":"New Hyde Park",
    "sg:classifiers":[
        {
            "category":"Wholesale",
            "subcategory":"Construction Materials",
            "type":"Manufacturing & Wholesale Goods"
        }
    ],
    "sg:phone":"+1 516 326 2707",
    "sg:postcode":"11040",
    "sg:province":"NY",
    "sg:tags":[
        "kitchen",
        "cabinet"
    ],
    "wof:name":"Kongent Production",
    "wof:placetype":"venue"
},
  "geometry": {"coordinates":[-73.67183900000001,40.736752],"type":"Point"}
}