{
  "type": "Feature",
  "properties": {
    "addr:full":"729 7 Ave New York NY 10019",
    "addr:housenumber":"729",
    "addr:postcode":"10019",
    "addr:street":"7 Ave",
    "iso:country":"US",
    "sg:address":"729 7 Ave",
    "sg:city":"New York",
    "sg:classifiers":[
        {
            "category":"Social Services",
            "type":"Services"
        }
    ],
    "sg:phone":"+1 212 221 7300",
    "sg:postcode":"10019",
    "sg:province":"NY",
    "sg:tags":[
        "organization",
        "welfare"
    ],
    "sg:website":"www.actorsfund.org",
    "wof:name":"Actors Fund Of America",
    "wof:placetype":"venue"
},
  "geometry": {"coordinates":[-73.98372999999999,40.760456],"type":"Point"}
}