{
  "type": "Feature",
  "properties": {
    "iso:country":"US",
    "sg:address":"3062 Hermitage Rd",
    "sg:city":"Warsaw",
    "sg:classifiers":[
        {
            "category":"Wholesale",
            "subcategory":"Construction Materials",
            "type":"Manufacturing & Wholesale Goods"
        }
    ],
    "sg:phone":"+1 585 261 2619",
    "sg:postcode":"14569",
    "sg:province":"NY",
    "sg:tags":[
        "sand",
        "gravel"
    ],
    "wof:name":"Warsaw Sand & Gravel Inc",
    "wof:placetype":"venue"
},
  "geometry": {"coordinates":[-78.197827,42.737972],"type":"Point"}
}