{
  "type": "Feature",
  "properties": {
    "iso:country":"US",
    "sg:address":"33 Carlton Rd",
    "sg:city":"Monsey",
    "sg:classifiers":[
        {
            "category":"Organizations",
            "subcategory":"Religious Organization",
            "type":"Services"
        }
    ],
    "sg:phone":"+1 845 425 6256",
    "sg:postcode":"10952",
    "sg:province":"NY",
    "sg:tags":[
        "clergy"
    ],
    "wof:name":"Michel Chill",
    "wof:placetype":"venue"
},
  "geometry": {"coordinates":[-74.07092400000001,41.122823],"type":"Point"}
}