{
  "type": "Feature",
  "properties": {
    "iso:country":"US",
    "sg:address":"72 Saxon Ave",
    "sg:city":"Bay Shore",
    "sg:classifiers":[
        {
            "category":"Retail",
            "subcategory":"Auto Repair",
            "type":"Services"
        }
    ],
    "sg:phone":"+1 631 665 7820",
    "sg:postcode":"11706",
    "sg:province":"NY",
    "sg:tags":[
        "body",
        "shop"
    ],
    "wof:name":"Northeast Claims & Collision Works",
    "wof:placetype":"venue"
},
  "geometry": {"coordinates":[-73.228302,40.733898],"type":"Point"}
}