{
  "type": "Feature",
  "properties": {
    "addr:full":"38 Palmer Ave Bronxville NY 10708",
    "addr:housenumber":"38",
    "addr:postcode":"10708",
    "addr:street":"Palmer Ave",
    "iso:country":"US",
    "sg:address":"38 Palmer Ave",
    "sg:city":"Bronxville",
    "sg:classifiers":[
        {
            "category":"Food & Beverages",
            "subcategory":"Fruits & Vegetables",
            "type":"Retail Goods"
        }
    ],
    "sg:phone":"+1 914 337 7003",
    "sg:postcode":"10708",
    "sg:province":"NY",
    "sg:tags":[
        "produce"
    ],
    "wof:name":"Brother Fresh Fruit & Veg",
    "wof:placetype":"venue"
},
  "geometry": {"coordinates":[-73.83565400000001,40.941697],"type":"Point"}
}