{
  "type": "Feature",
  "properties": {
    "addr:full":"19 Ash St Oswego NY 13126",
    "addr:housenumber":"19",
    "addr:postcode":"13126",
    "addr:street":"Ash St",
    "iso:country":"US",
    "sg:address":"19 Ash St",
    "sg:city":"Oswego",
    "sg:classifiers":[
        {
            "category":"Retail",
            "subcategory":"Animal Services",
            "type":"Services"
        }
    ],
    "sg:phone":"+1 315 343 4994",
    "sg:postcode":"13126",
    "sg:province":"NY",
    "sg:tags":[
        "pet",
        "boarding",
        "sitting"
    ],
    "wof:name":"Dragonfly Meadow Petsitters",
    "wof:placetype":"venue"
},
  "geometry": {"coordinates":[-76.512349,43.4354],"type":"Point"}
}