{
  "type": "Feature",
  "properties": {
    "iso:country":"US",
    "sg:address":"140 Nassau St",
    "sg:city":"New York",
    "sg:classifiers":[
        {
            "category":"Professional",
            "subcategory":"Business Services",
            "type":"Services"
        }
    ],
    "sg:phone":"+1 212 227 0814",
    "sg:postcode":"10038",
    "sg:province":"NY",
    "sg:tags":[
        "mortgage"
    ],
    "wof:name":"Fxfund",
    "wof:placetype":"venue"
},
  "geometry": {"coordinates":[-74.005887,40.711581],"type":"Point"}
}