{
  "type": "Feature",
  "properties": {
    "iso:country":"US",
    "sg:address":"7 Edison Ave",
    "sg:city":"Mount Vernon",
    "sg:classifiers":[
        {
            "category":"Home & Garden",
            "subcategory":"Building Materials",
            "type":"Retail Goods"
        },
        {
            "category":"Building & Trades",
            "subcategory":"Construction",
            "type":"Services"
        }
    ],
    "sg:phone":"+1 914 699 3370",
    "sg:postcode":"10550",
    "sg:province":"NY",
    "sg:tags":[
        "manufacturer"
    ],
    "sg:website":"www.rcaasphalt.com",
    "wof:name":"RCA Asphalt",
    "wof:placetype":"venue"
},
  "geometry": {"coordinates":[-73.824719,40.891597],"type":"Point"}
}