{
  "type": "Feature",
  "properties": {
    "addr:full":"477 Central Park W Frnt New York NY 10025",
    "addr:housenumber":"477",
    "addr:postcode":"10025",
    "addr:street":"Central Park W Frnt",
    "iso:country":"US",
    "sg:address":"477 Central Park W Frnt",
    "sg:city":"New York",
    "sg:classifiers":[
        {
            "category":"Deli",
            "type":"Food & Drink"
        }
    ],
    "sg:phone":"+1 212 222 0471",
    "sg:postcode":"10025",
    "sg:province":"NY",
    "wof:name":"Park West Foods",
    "wof:placetype":"venue"
},
  "geometry": {"coordinates":[-73.959198,40.799301],"type":"Point"}
}