{
  "type": "Feature",
  "properties": {
    "addr:full":"104 Duane Street New York NY 10007",
    "addr:housenumber":"104",
    "addr:postcode":"10007",
    "addr:street":"Duane Street",
    "iso:country":"US",
    "sg:address":"104 Duane Street",
    "sg:city":"New York",
    "sg:classifiers":[
        {
            "category":"Deli",
            "type":"Food & Drink"
        }
    ],
    "sg:phone":"+1 212 349 6902",
    "sg:postcode":"10007",
    "sg:province":"NY",
    "wof:name":"Joe's Gourmet Deli and Grocery",
    "wof:placetype":"venue"
},
  "geometry": {"coordinates":[-74.00622199999999,40.715278],"type":"Point"}
}