{
  "type": "Feature",
  "properties": {
    "iso:country":"US",
    "sg:address":"154 W 127th St",
    "sg:city":"New York",
    "sg:classifiers":[
        {
            "category":"Professional",
            "subcategory":"Research",
            "type":"Services"
        }
    ],
    "sg:phone":"+1 212 866 6925",
    "sg:postcode":"10027",
    "sg:province":"NY",
    "sg:tags":[
        "development",
        "laboratory"
    ],
    "wof:name":"Cues",
    "wof:placetype":"venue"
},
  "geometry": {"coordinates":[-73.94622699999999,40.809547],"type":"Point"}
}