{
  "type": "Feature",
  "properties": {
    "iso:country":"US",
    "sg:address":"245 W Houston St",
    "sg:city":"New York",
    "sg:classifiers":[
        {
            "category":"Government",
            "subcategory":"Office",
            "type":"Public Place"
        }
    ],
    "sg:phone":"+1 212 807 3444",
    "sg:postcode":"10014",
    "sg:province":"NY",
    "sg:tags":[
        "affairs",
        "administrative"
    ],
    "wof:name":"Office of Inspector General",
    "wof:placetype":"venue"
},
  "geometry": {"coordinates":[-74.007009,40.728686],"type":"Point"}
}