{
  "type": "Feature",
  "properties": {
    "addr:full":"103 E 161st St Bronx NY 10451",
    "addr:housenumber":"103",
    "addr:postcode":"10451",
    "addr:street":"E 161St St",
    "iso:country":"US",
    "sg:address":"103 E 161st St",
    "sg:city":"Bronx",
    "sg:classifiers":[
        {
            "category":"Restaurant",
            "type":"Food & Drink"
        }
    ],
    "sg:menulink":"http://www.allmenus.com/ny/bronx/169806-burger-king/menu/",
    "sg:phone":"+1 718 537 3181",
    "sg:postcode":"10451",
    "sg:province":"NY",
    "sg:tags":[
        "burger",
        "american"
    ],
    "wof:name":"Burger King",
    "wof:placetype":"venue"
},
  "geometry": {"coordinates":[-73.924119,40.827428],"type":"Point"}
}