{
  "type": "Feature",
  "properties": {
    "iso:country":"US",
    "sg:address":"130 Quail Dr",
    "sg:city":"Kingston",
    "sg:classifiers":[
        {
            "category":"Restaurant",
            "type":"Food & Drink"
        }
    ],
    "sg:phone":"+1   ",
    "sg:postcode":"12401",
    "sg:province":"NY",
    "sg:tags":[
        "eating"
    ],
    "wof:name":"Thirty-Two Lunch",
    "wof:placetype":"venue"
},
  "geometry": {"coordinates":[-73.98863900000001,41.952316],"type":"Point"}
}