{
  "type": "Feature",
  "properties": {
    "iso:country":"US",
    "sg:address":"525 State St",
    "sg:city":"Schenectady",
    "sg:classifiers":[
        {
            "category":"Professional",
            "subcategory":"Lawyer & Legal Services",
            "type":"Services"
        }
    ],
    "sg:phone":"+1 518 374 1200",
    "sg:postcode":"12305",
    "sg:province":"NY",
    "sg:tags":[
        "attorney"
    ],
    "wof:name":"Kouray & Kouray",
    "wof:placetype":"venue"
},
  "geometry": {"coordinates":[-73.94005300000001,42.811753],"type":"Point"}
}