{
  "type": "Feature",
  "properties": {
    "addr:full":"16 Niblick Rd Selden NY 11784",
    "addr:housenumber":"16",
    "addr:postcode":"11784",
    "addr:street":"Niblick Rd",
    "iso:country":"US",
    "sg:address":"16 Niblick Rd",
    "sg:city":"Selden",
    "sg:classifiers":[
        {
            "category":"Building & Trades",
            "subcategory":"Construction",
            "type":"Services"
        }
    ],
    "sg:phone":"+1 631 696 5660",
    "sg:postcode":"11784",
    "sg:province":"NY",
    "sg:tags":[
        "concrete",
        "contractor"
    ],
    "wof:name":"Metro Contracting",
    "wof:placetype":"venue"
},
  "geometry": {"coordinates":[-73.024952,40.863575],"type":"Point"}
}