{
  "type": "Feature",
  "properties": {
    "iso:country":"US",
    "sg:address":"7407 Myrtle Ave",
    "sg:city":"Queens",
    "sg:classifiers":[
        {
            "category":"Health Services",
            "subcategory":"Dentist",
            "type":"Services"
        }
    ],
    "sg:phone":"+1 718 207 9604",
    "sg:postcode":"11385",
    "sg:province":"NY",
    "sg:website":"glendaledentalassociates.net",
    "wof:name":"Glendale Dental Associates",
    "wof:placetype":"venue"
},
  "geometry": {"coordinates":[-73.87410800000001,40.702664],"type":"Point"}
}