{
  "type": "Feature",
  "properties": {
    "iso:country":"US",
    "sg:address":"1168 Lenox Rd",
    "sg:city":"Brooklyn",
    "sg:classifiers":[
        {
            "category":"Restaurant",
            "type":"Food & Drink"
        }
    ],
    "sg:phone":"+1 718 342 8283",
    "sg:postcode":"11212",
    "sg:province":"NY",
    "wof:name":"C G West Indian & Amer Rstrnt",
    "wof:placetype":"venue"
},
  "geometry": {"coordinates":[-73.91798300000001,40.65947],"type":"Point"}
}