{
  "type": "Feature",
  "properties": {
    "iso:country":"US",
    "sg:address":"124 MacDougal Street",
    "sg:city":"New York",
    "sg:classifiers":[
        {
            "category":"Professional",
            "subcategory":"Computer Services",
            "type":"Services"
        }
    ],
    "sg:phone":"+1 212 730 5965",
    "sg:postcode":"10012",
    "sg:province":"NY",
    "sg:tags":[
        "repair"
    ],
    "wof:name":"Tech Lynk Services",
    "wof:placetype":"venue"
},
  "geometry": {"coordinates":[-74.000441,40.730003],"type":"Point"}
}