{
  "type": "Feature",
  "properties": {
    "iso:country":"US",
    "sg:address":"5 Brink Rd",
    "sg:city":"Prattsville",
    "sg:classifiers":[
        {
            "category":"Health Services",
            "subcategory":"Clinic",
            "type":"Services"
        }
    ],
    "sg:phone":"+1 518 734 5120",
    "sg:postcode":"12477",
    "sg:province":"NY",
    "wof:name":"Health Solutions",
    "wof:placetype":"venue"
},
  "geometry": {"coordinates":[-74.004311,42.114187],"type":"Point"}
}