{
  "type": "Feature",
  "properties": {
    "iso:country":"US",
    "sg:address":"310 W 106th St",
    "sg:city":"New York",
    "sg:classifiers":[
        {
            "category":"Professional",
            "subcategory":"Engineering",
            "type":"Services"
        }
    ],
    "sg:phone":"+1 212 665 4648",
    "sg:postcode":"10025",
    "sg:province":"NY",
    "sg:tags":[
        "engineer"
    ],
    "wof:name":"New Leaf Strategies",
    "wof:placetype":"venue"
},
  "geometry": {"coordinates":[-73.969971,40.802136],"type":"Point"}
}