{
  "type": "Feature",
  "properties": {
    "addr:full":"6224 Woodhaven Boulevard Rego Park NY 11374",
    "addr:housenumber":"6224",
    "addr:postcode":"11374",
    "addr:street":"Woodhaven Boulevard",
    "iso:country":"US",
    "sg:address":"6224 Woodhaven Boulevard",
    "sg:city":"Rego Park",
    "sg:classifiers":[
        {
            "category":"Fast Food",
            "type":"Food & Drink"
        },
        {
            "category":"Restaurant",
            "type":"Food & Drink"
        }
    ],
    "sg:phone":"+1 718 446 1006",
    "sg:postcode":"11374",
    "sg:province":"NY",
    "sg:tags":[
        "chinese"
    ],
    "wof:name":"Spring Garden",
    "wof:placetype":"venue"
},
  "geometry": {"coordinates":[-73.870497,40.726165],"type":"Point"}
}