{
  "type": "Feature",
  "properties": {
    "iso:country":"US",
    "sg:address":"4068 State Hwy 52",
    "sg:city":"Youngsville",
    "sg:classifiers":[
        {
            "category":"Government",
            "subcategory":"Post Office",
            "type":"Public Place"
        }
    ],
    "sg:phone":"+1 845 482 4295",
    "sg:postcode":"12726",
    "sg:province":"NY",
    "wof:name":"US Post Office",
    "wof:placetype":"venue"
},
  "geometry": {"coordinates":[-74.980334,41.65861],"type":"Point"}
}