{
  "type": "Feature",
  "properties": {
    "addr:full":"1811 43rd St Astoria NY 11105",
    "addr:housenumber":"1811",
    "addr:postcode":"11105",
    "addr:street":"43Rd St",
    "iso:country":"US",
    "sg:address":"1811 43rd St",
    "sg:city":"Astoria",
    "sg:phone":"+1 718 932 4100",
    "sg:postcode":"11105",
    "sg:province":"NY",
    "sg:website":"http://www.stihlusa.com/",
    "wof:name":"Cap Rents Supply LLC",
    "wof:placetype":"venue"
},
  "geometry": {"coordinates":[-73.895959,40.777836],"type":"Point"}
}