{
  "type": "Feature",
  "properties": {
    "iso:country":"US",
    "sg:address":"124 Ayers Rd",
    "sg:city":"Locust Valley",
    "sg:classifiers":[
        {
            "category":"Professional",
            "subcategory":"Management & Consulting",
            "type":"Services"
        }
    ],
    "sg:phone":"+1 516 674 4882",
    "sg:postcode":"11560",
    "sg:province":"NY",
    "sg:tags":[
        "business"
    ],
    "wof:name":"Hanes Associates Inc",
    "wof:placetype":"venue"
},
  "geometry": {"coordinates":[-73.571837,40.879433],"type":"Point"}
}