{
  "type": "Feature",
  "properties": {
    "addr:full":"3311 Veterans Memoril Hwy Ronkonkoma NY 11779",
    "addr:housenumber":"3311",
    "addr:postcode":"11779",
    "addr:street":"Veterans Memoril Hwy",
    "iso:country":"US",
    "sg:address":"3311 Veterans Memoril Hwy",
    "sg:city":"Ronkonkoma",
    "sg:classifiers":[
        {
            "category":"Restaurant",
            "type":"Food & Drink"
        }
    ],
    "sg:phone":"+1 631 588 0001",
    "sg:postcode":"11779",
    "sg:province":"NY",
    "wof:name":"Liu Ming Chen Restrnt",
    "wof:placetype":"venue"
},
  "geometry": {"coordinates":[-73.12979900000001,40.787498],"type":"Point"}
}