{
  "type": "Feature",
  "properties": {
    "iso:country":"US",
    "sg:address":"3087 US Hwy 11",
    "sg:city":"De Kalb Junction",
    "sg:classifiers":[
        {
            "category":"Building & Trades",
            "subcategory":"Construction",
            "type":"Services"
        }
    ],
    "sg:phone":"+1 315 287 4400",
    "sg:postcode":"13630",
    "sg:province":"NY",
    "sg:tags":[
        "paving",
        "contractor"
    ],
    "wof:name":"Parker Line Striping",
    "wof:placetype":"venue"
},
  "geometry": {"coordinates":[-75.356031,44.455099],"type":"Point"}
}