{
  "type": "Feature",
  "properties": {
    "addr:full":"805 W 187th St New York NY 10033",
    "addr:housenumber":"805",
    "addr:postcode":"10033",
    "addr:street":"W 187Th St",
    "iso:country":"US",
    "sg:address":"805 W 187th St",
    "sg:city":"New York",
    "sg:classifiers":[
        {
            "category":"Coffee & Tea",
            "type":"Food & Drink"
        }
    ],
    "sg:phone":"+1 212 927 8458",
    "sg:postcode":"10033",
    "sg:province":"NY",
    "wof:name":"Vicki's",
    "wof:placetype":"venue"
},
  "geometry": {"coordinates":[-73.937146,40.855189],"type":"Point"}
}