{
  "type": "Feature",
  "properties": {
    "addr:full":"11501 Farmers Blvd Saint Albans NY 11412",
    "addr:housenumber":"11501",
    "addr:postcode":"11412",
    "addr:street":"Farmers Blvd",
    "iso:country":"US",
    "sg:address":"11501 Farmers Blvd",
    "sg:city":"Saint Albans",
    "sg:classifiers":[
        {
            "category":"Education",
            "subcategory":"Music School",
            "type":"Public Place"
        }
    ],
    "sg:phone":"+1 718 723 3606",
    "sg:postcode":"11412",
    "sg:province":"NY",
    "sg:tags":[
        "instrument",
        "teacher",
        "musical"
    ],
    "wof:name":"VIP Deli Grocery",
    "wof:placetype":"venue"
},
  "geometry": {"coordinates":[-73.761399,40.69594],"type":"Point"}
}