{
  "type": "Feature",
  "properties": {
    "addr:full":"7114 Bay Pkwy Brooklyn NY 11204",
    "addr:housenumber":"7114",
    "addr:postcode":"11204",
    "addr:street":"Bay Pkwy",
    "iso:country":"US",
    "sg:address":"7114 Bay Pkwy",
    "sg:city":"Brooklyn",
    "sg:classifiers":[
        {
            "category":"Shopping",
            "subcategory":"Stationery & Office Supplies",
            "type":"Retail Goods"
        }
    ],
    "sg:phone":"+1   ",
    "sg:postcode":"11204",
    "sg:province":"NY",
    "sg:tags":[
        "printing",
        "commercial"
    ],
    "wof:name":"Parkway Printing & Stationery",
    "wof:placetype":"venue"
},
  "geometry": {"coordinates":[-73.98515399999999,40.610447],"type":"Point"}
}