{
  "type": "Feature",
  "properties": {
    "addr:full":"5192 Eckert Rd Newark NY 14513",
    "addr:housenumber":"5192",
    "addr:postcode":"14513",
    "addr:street":"Eckert Rd",
    "iso:country":"US",
    "sg:address":"5192 Eckert Rd",
    "sg:city":"Newark",
    "sg:classifiers":[
        {
            "category":"Farming",
            "subcategory":"Dairy Farm",
            "type":"Manufacturing & Wholesale Goods"
        }
    ],
    "sg:phone":"+1 315 331 3844",
    "sg:postcode":"14513",
    "sg:province":"NY",
    "wof:name":"Lane Lonley Farm",
    "wof:placetype":"venue"
},
  "geometry": {"coordinates":[-77.135915,43.068708],"type":"Point"}
}