{
  "type": "Feature",
  "properties": {
    "iso:country":"US",
    "sg:address":"850 Merrick Rd",
    "sg:city":"Baldwin",
    "sg:classifiers":[
        {
            "category":"Home & Garden",
            "subcategory":"Building Materials",
            "type":"Retail Goods"
        }
    ],
    "sg:phone":"+1   ",
    "sg:postcode":"11510",
    "sg:province":"NY",
    "wof:name":"Janovic-Paint House",
    "wof:placetype":"venue"
},
  "geometry": {"coordinates":[-73.61220400000001,40.650675],"type":"Point"}
}