{
  "type": "Feature",
  "properties": {
    "addr:full":"993 Front St Uniondale NY 11553",
    "addr:housenumber":"993",
    "addr:postcode":"11553",
    "addr:street":"Front St",
    "iso:country":"US",
    "sg:address":"993 Front St",
    "sg:city":"Uniondale",
    "sg:classifiers":[
        {
            "category":"Professional",
            "subcategory":"Accounting & Tax Preparation",
            "type":"Services"
        }
    ],
    "sg:phone":"+1 516 292 0095",
    "sg:postcode":"11553",
    "sg:province":"NY",
    "sg:tags":[
        "consultant",
        "return"
    ],
    "wof:name":"Omega Multiple Svces",
    "wof:placetype":"venue"
},
  "geometry": {"coordinates":[-73.59455199999999,40.70937],"type":"Point"}
}