{
  "type": "Feature",
  "properties": {
    "iso:country":"US",
    "sg:address":"21912 S Conduit Ave",
    "sg:city":"Springfield Gardens",
    "sg:classifiers":[
        {
            "category":"Retail",
            "subcategory":"Laundry & Dry Cleaning",
            "type":"Services"
        }
    ],
    "sg:phone":"+1 718 525 4562",
    "sg:postcode":"11413",
    "sg:province":"NY",
    "wof:name":"Cameo Cleaners",
    "wof:placetype":"venue"
},
  "geometry": {"coordinates":[-73.757896,40.665501],"type":"Point"}
}