{
  "type": "Feature",
  "properties": {
    "addr:full":"230 W 39 St New York NY 10018",
    "addr:housenumber":"230",
    "addr:postcode":"10018",
    "addr:street":"W 39 St",
    "iso:country":"US",
    "sg:address":"230 W 39 St",
    "sg:city":"New York",
    "sg:classifiers":[
        {
            "category":"Professional",
            "type":"Services"
        }
    ],
    "sg:phone":"+1 212 302 4238",
    "sg:postcode":"10018",
    "sg:province":"NY",
    "sg:tags":[
        "establishment"
    ],
    "wof:name":"Cath Kidston",
    "wof:placetype":"venue"
},
  "geometry": {"coordinates":[-73.990554,40.754897],"type":"Point"}
}