{
  "type": "Feature",
  "properties": {
    "iso:country":"US",
    "sg:address":"189 Bowery",
    "sg:city":"New York",
    "sg:classifiers":[
        {
            "category":"Home & Garden",
            "subcategory":"Household Appliances",
            "type":"Retail Goods"
        }
    ],
    "sg:phone":"+1 212 777 1276",
    "sg:postcode":"10002",
    "sg:province":"NY",
    "sg:tags":[
        "range",
        "stove"
    ],
    "wof:name":"Manhattan Commercial Kitchen",
    "wof:placetype":"venue"
},
  "geometry": {"coordinates":[-73.993859,40.720455],"type":"Point"}
}