{
  "type": "Feature",
  "properties": {
    "iso:country":"US",
    "sg:address":"757 Old Medford Ave",
    "sg:city":"Medford",
    "sg:classifiers":[
        {
            "category":"Professional",
            "type":"Services"
        }
    ],
    "sg:phone":"+1 631 289 3440",
    "sg:postcode":"11763",
    "sg:province":"NY",
    "sg:tags":[
        "establishment"
    ],
    "wof:name":"DDI",
    "wof:placetype":"venue"
},
  "geometry": {"coordinates":[-73.011261,40.806374],"type":"Point"}
}