{
  "type": "Feature",
  "properties": {
    "addr:full":"2750 Dodge Rd East Amherst NY 14051",
    "addr:housenumber":"2750",
    "addr:postcode":"14051",
    "addr:street":"Dodge Rd",
    "iso:country":"US",
    "sg:address":"2750 Dodge Rd",
    "sg:city":"East Amherst",
    "sg:classifiers":[
        {
            "category":"Banks & Credit Unions",
            "subcategory":"Financial Services",
            "type":"Services"
        }
    ],
    "sg:phone":"+1 716 689 9462",
    "sg:postcode":"14051",
    "sg:province":"NY",
    "sg:tags":[
        "investor"
    ],
    "wof:name":"Diversified Investment Group",
    "wof:placetype":"venue"
},
  "geometry": {"coordinates":[-78.706627,43.038029],"type":"Point"}
}