{
  "type": "Feature",
  "properties": {
    "addr:full":"10 Queens Hwy Kerhonkson NY 12446",
    "addr:housenumber":"10",
    "addr:postcode":"12446",
    "addr:street":"Queens Hwy",
    "iso:country":"US",
    "sg:address":"10 Queens Hwy",
    "sg:city":"Kerhonkson",
    "sg:classifiers":[
        {
            "category":"Building & Trades",
            "subcategory":"Construction",
            "type":"Services"
        }
    ],
    "sg:phone":"+1 845 626 3491",
    "sg:postcode":"12446",
    "sg:province":"NY",
    "sg:tags":[
        "carpentry",
        "contractor",
        "furniture"
    ],
    "sg:website":"www.stoneridgecabinetworks.com",
    "wof:name":"Stone Ridge Cabinet Works Inc",
    "wof:placetype":"venue"
},
  "geometry": {"coordinates":[-74.263389,41.790793],"type":"Point"}
}