{
  "type": "Feature",
  "properties": {
    "addr:full":"829 3rd Ave 2nd Fl New York NY 10022",
    "addr:housenumber":"829",
    "addr:postcode":"10022",
    "addr:street":"3Rd Ave 2Nd Fl",
    "iso:country":"US",
    "sg:address":"829 3rd Ave 2nd Fl",
    "sg:city":"New York",
    "sg:classifiers":[
        {
            "category":"Personal",
            "subcategory":"Skin Care",
            "type":"Services"
        }
    ],
    "sg:phone":"+1 212 980 8868",
    "sg:postcode":"10022",
    "sg:province":"NY",
    "sg:website":"www.aqualiaspa.com",
    "wof:name":"Aqualia Spa",
    "wof:placetype":"venue"
},
  "geometry": {"coordinates":[-73.970181,40.756599],"type":"Point"}
}