{
  "type": "Feature",
  "properties": {
    "addr:full":"72 Main St Phoenicia NY 12464",
    "addr:housenumber":"72",
    "addr:postcode":"12464",
    "addr:street":"Main St",
    "iso:country":"US",
    "sg:address":"72 Main St",
    "sg:city":"Phoenicia",
    "sg:classifiers":[
        {
            "category":"Health Services",
            "subcategory":"Health Practitioner",
            "type":"Services"
        }
    ],
    "sg:phone":"+1   ",
    "sg:postcode":"12464",
    "sg:province":"NY",
    "wof:name":"Jerry Egan",
    "wof:placetype":"venue"
},
  "geometry": {"coordinates":[-74.313345,42.083298],"type":"Point"}
}