{
  "type": "Feature",
  "properties": {
    "iso:country":"US",
    "sg:address":"13 Main St",
    "sg:city":"Tonawanda",
    "sg:classifiers":[
        {
            "category":"Restaurant",
            "type":"Food & Drink"
        }
    ],
    "sg:phone":"+1   ",
    "sg:postcode":"14150",
    "sg:province":"NY",
    "sg:tags":[
        "eating"
    ],
    "wof:name":"Towpath Cafe Inc",
    "wof:placetype":"venue"
},
  "geometry": {"coordinates":[-78.878146,43.020016],"type":"Point"}
}