{
  "type": "Feature",
  "properties": {
    "addr:full":"430 E Allen St Hudson NY 12534",
    "addr:housenumber":"430",
    "addr:postcode":"12534",
    "addr:street":"E Allen St",
    "iso:country":"US",
    "sg:address":"430 E Allen St",
    "sg:city":"Hudson",
    "sg:classifiers":[
        {
            "category":"Professional",
            "subcategory":"Lawyer & Legal Services",
            "type":"Services"
        }
    ],
    "sg:phone":"+1 518 697 3400",
    "sg:postcode":"12534",
    "sg:province":"NY",
    "sg:tags":[
        "divorce",
        "law",
        "family"
    ],
    "wof:name":"Law Office of Victoria Madonna",
    "wof:placetype":"venue"
},
  "geometry": {"coordinates":[-73.78980300000001,42.249298],"type":"Point"}
}