{
  "type": "Feature",
  "properties": {
    "iso:country":"US",
    "sg:address":"95 Ushers Rd",
    "sg:city":"Mechanicville",
    "sg:classifiers":[
        {
            "category":"Farming",
            "subcategory":"Livestock Farm",
            "type":"Manufacturing & Wholesale Goods"
        }
    ],
    "sg:phone":"+1 518 664 3634",
    "sg:postcode":"12118",
    "sg:province":"NY",
    "sg:tags":[
        "beef",
        "feedlot",
        "cattle"
    ],
    "wof:name":"Randals Lolly",
    "wof:placetype":"venue"
},
  "geometry": {"coordinates":[-73.764144,42.915906],"type":"Point"}
}