{
  "type": "Feature",
  "properties": {
    "addr:full":"1749 Amsterdam Ave New York NY 10031",
    "addr:housenumber":"1749",
    "addr:postcode":"10031",
    "addr:street":"Amsterdam Ave",
    "iso:country":"US",
    "sg:address":"1749 Amsterdam Ave",
    "sg:city":"New York",
    "sg:classifiers":[
        {
            "category":"Building & Trades",
            "subcategory":"Plumbing",
            "type":"Services"
        }
    ],
    "sg:phone":"+1 212 283 2700",
    "sg:postcode":"10031",
    "sg:province":"NY",
    "wof:name":"Quality Air Conditioning",
    "wof:placetype":"venue"
},
  "geometry": {"coordinates":[-73.946786,40.826146],"type":"Point"}
}