{
  "type": "Feature",
  "properties": {
    "iso:country":"US",
    "sg:address":"4418 4th Ave",
    "sg:city":"Brooklyn",
    "sg:classifiers":[
        {
            "category":"Food & Beverages",
            "subcategory":"Groceries & Convenience Stores",
            "type":"Retail Goods"
        }
    ],
    "sg:phone":"+1 718 768 6580",
    "sg:postcode":"11220",
    "sg:province":"NY",
    "wof:name":"Life Supermatket",
    "wof:placetype":"venue"
},
  "geometry": {"coordinates":[-74.009697,40.649502],"type":"Point"}
}