{
  "type": "Feature",
  "properties": {
    "iso:country":"US",
    "sg:address":"372 W Broadway",
    "sg:city":"New York",
    "sg:classifiers":[
        {
            "category":"Shopping",
            "type":"Retail Goods"
        }
    ],
    "sg:phone":"+1 917 237 0983",
    "sg:postcode":"10012",
    "sg:province":"NY",
    "sg:website":"www.hhilfiger.com",
    "wof:name":"H Hilfiger",
    "wof:placetype":"venue"
},
  "geometry": {"coordinates":[-74.002602,40.723701],"type":"Point"}
}