{
  "type": "Feature",
  "properties": {
    "addr:full":"537 Atlantic Ave Brooklyn NY 11217",
    "addr:housenumber":"537",
    "addr:postcode":"11217",
    "addr:street":"Atlantic Ave",
    "iso:country":"US",
    "sg:address":"537 Atlantic Ave",
    "sg:city":"Brooklyn",
    "sg:classifiers":[
        {
            "category":"Professional",
            "subcategory":"Computer Services",
            "type":"Services"
        }
    ],
    "sg:phone":"+1 718 260 9131",
    "sg:postcode":"11217",
    "sg:province":"NY",
    "sg:tags":[
        "repair"
    ],
    "wof:name":"Gene's Business Machines",
    "wof:placetype":"venue"
},
  "geometry": {"coordinates":[-73.97896,40.684802],"type":"Point"}
}