{
  "type": "Feature",
  "properties": {
    "addr:full":"Westerlo Coeymans NY 12045",
    "addr:postcode":"12045",
    "iso:country":"US",
    "sg:address":"Westerlo",
    "sg:city":"Coeymans",
    "sg:classifiers":[
        {
            "category":"Recreation",
            "subcategory":"Boat Charter",
            "type":"Entertainment"
        }
    ],
    "sg:phone":"+1 518 756 7400",
    "sg:postcode":"12045",
    "sg:province":"NY",
    "sg:tags":[
        "boating"
    ],
    "wof:name":"Coeymans Landing Marine Services",
    "wof:placetype":"venue"
},
  "geometry": {"coordinates":[-73.79389999999999,42.476101],"type":"Point"}
}