{
  "type": "Feature",
  "properties": {
    "iso:country":"US",
    "sg:address":"81 Post Ave",
    "sg:city":"Hilton",
    "sg:classifiers":[
        {
            "category":"Manufacturing",
            "subcategory":"Buildings",
            "type":"Manufacturing & Wholesale Goods"
        },
        {
            "category":"Building & Trades",
            "subcategory":"Construction",
            "type":"Services"
        }
    ],
    "sg:phone":"+1 585 392 2596",
    "sg:postcode":"14468",
    "sg:province":"NY",
    "sg:tags":[
        "home",
        "builder",
        "contractor"
    ],
    "wof:name":"H Vragel Construction",
    "wof:placetype":"venue"
},
  "geometry": {"coordinates":[-77.718442,43.2753],"type":"Point"}
}