{
  "type": "Feature",
  "properties": {
    "addr:full":"241 West 37 St Ste 720 Manhattan NY 10018",
    "addr:housenumber":"241",
    "addr:postcode":"10018",
    "addr:street":"West 37 St Ste 720",
    "iso:country":"US",
    "sg:address":"241 West 37 St Ste 720",
    "sg:city":"Manhattan",
    "sg:classifiers":[
        {
            "category":"Shopping",
            "subcategory":"Clothing, Apparel, & Fashions",
            "type":"Retail Goods"
        }
    ],
    "sg:phone":"+1 212 213 4680",
    "sg:postcode":"10018",
    "sg:province":"NY",
    "sg:tags":[
        "clothing",
        "women's"
    ],
    "sg:website":"www.kurta.com",
    "wof:name":"Karma-Highway",
    "wof:placetype":"venue"
},
  "geometry": {"coordinates":[-73.990871,40.753832],"type":"Point"}
}