{
  "type": "Feature",
  "properties": {
    "iso:country":"US",
    "sg:address":"1995 Fulton St",
    "sg:city":"Brooklyn",
    "sg:classifiers":[
        {
            "category":"Organizations",
            "subcategory":"Religious Organization",
            "type":"Services"
        }
    ],
    "sg:phone":"+1 718 485 9157",
    "sg:postcode":"11233",
    "sg:province":"NY",
    "sg:tags":[
        "church"
    ],
    "wof:name":"St Mathew Fire Baptised Chr",
    "wof:placetype":"venue"
},
  "geometry": {"coordinates":[-73.914708,40.678585],"type":"Point"}
}