{
  "type": "Feature",
  "properties": {
    "addr:full":"127 Central Ave Dunkirk NY 14048",
    "addr:housenumber":"127",
    "addr:postcode":"14048",
    "addr:street":"Central Ave",
    "iso:country":"US",
    "sg:address":"127 Central Ave",
    "sg:city":"Dunkirk",
    "sg:classifiers":[
        {
            "category":"Organizations",
            "subcategory":"Professional Association",
            "type":"Services"
        }
    ],
    "sg:phone":"+1 716 366 1827",
    "sg:postcode":"14048",
    "sg:province":"NY",
    "wof:name":"Mental Health Assn",
    "wof:placetype":"venue"
},
  "geometry": {"coordinates":[-79.335573,42.486968],"type":"Point"}
}