{
  "type": "Feature",
  "properties": {
    "addr:full":"300 International Dr Buffalo NY 14221",
    "addr:housenumber":"300",
    "addr:postcode":"14221",
    "addr:street":"International Dr",
    "iso:country":"US",
    "sg:address":"300 International Dr",
    "sg:city":"Buffalo",
    "sg:classifiers":[
        {
            "category":"Professional",
            "subcategory":"Engineering",
            "type":"Services"
        }
    ],
    "sg:phone":"+1 716 689 3291",
    "sg:postcode":"14221",
    "sg:province":"NY",
    "sg:tags":[
        "engineer"
    ],
    "wof:name":"Criterium Ferrari Engineers",
    "wof:placetype":"venue"
},
  "geometry": {"coordinates":[-78.731437,42.974277],"type":"Point"}
}