{
  "type": "Feature",
  "properties": {
    "addr:full":"2859 Frederick Douglass B New York NY 10039",
    "addr:housenumber":"2859",
    "addr:postcode":"10039",
    "addr:street":"Frederick Douglass B",
    "iso:country":"US",
    "sg:address":"2859 Frederick Douglass B",
    "sg:city":"New York",
    "sg:classifiers":[
        {
            "category":"Personal",
            "subcategory":"Barber",
            "type":"Services"
        }
    ],
    "sg:phone":"+1 212 694 8890",
    "sg:postcode":"10039",
    "sg:province":"NY",
    "wof:name":"Lace Masters",
    "wof:placetype":"venue"
},
  "geometry": {"coordinates":[-73.938653,40.827508],"type":"Point"}
}