{
  "type": "Feature",
  "properties": {
    "iso:country":"US",
    "sg:address":"10030 County Rd",
    "sg:city":"Clarence Center",
    "sg:classifiers":[
        {
            "category":"Manufacturing",
            "subcategory":"Metals",
            "type":"Manufacturing & Wholesale Goods"
        }
    ],
    "sg:phone":"+1 716 741 2780",
    "sg:postcode":"14032",
    "sg:province":"NY",
    "sg:tags":[
        "foundry"
    ],
    "wof:name":"Koby Environmental Inc",
    "wof:placetype":"venue"
},
  "geometry": {"coordinates":[-78.610418,43.031281],"type":"Point"}
}