{
  "type": "Feature",
  "properties": {
    "addr:full":"1407 Foster Ave Brooklyn NY 11230",
    "addr:housenumber":"1407",
    "addr:postcode":"11230",
    "addr:street":"Foster Ave",
    "iso:country":"US",
    "sg:address":"1407 Foster Ave",
    "sg:city":"Brooklyn",
    "sg:classifiers":[
        {
            "category":"Food & Beverages",
            "subcategory":"Groceries & Convenience Stores",
            "type":"Retail Goods"
        }
    ],
    "sg:phone":"+1 718 434 0181",
    "sg:postcode":"11230",
    "sg:province":"NY",
    "wof:name":"Key Food",
    "wof:placetype":"venue"
},
  "geometry": {"coordinates":[-73.96369900000001,40.6339],"type":"Point"}
}