{
  "type": "Feature",
  "properties": {
    "addr:full":"2481 Creston Ave Bronx NY 10468",
    "addr:housenumber":"2481",
    "addr:postcode":"10468",
    "addr:street":"Creston Ave",
    "iso:country":"US",
    "sg:address":"2481 Creston Ave",
    "sg:city":"Bronx",
    "sg:classifiers":[
        {
            "category":"Shopping",
            "subcategory":"Mobile Phones",
            "type":"Retail Goods"
        }
    ],
    "sg:phone":"+1 718 220 0599",
    "sg:postcode":"10468",
    "sg:province":"NY",
    "wof:name":"Fordham Cell Phone",
    "wof:placetype":"venue"
},
  "geometry": {"coordinates":[-73.898427,40.862555],"type":"Point"}
}