{
  "type": "Feature",
  "properties": {
    "addr:full":"916 Charlton Rd Schenectady NY 12302",
    "addr:housenumber":"916",
    "addr:postcode":"12302",
    "addr:street":"Charlton Rd",
    "iso:country":"US",
    "sg:address":"916 Charlton Rd",
    "sg:city":"Schenectady",
    "sg:classifiers":[
        {
            "category":"Farming",
            "subcategory":"Livestock Farm",
            "type":"Manufacturing & Wholesale Goods"
        }
    ],
    "sg:phone":"+1 518 399 9446",
    "sg:postcode":"12302",
    "sg:province":"NY",
    "sg:tags":[
        "beef",
        "feedlot",
        "cattle"
    ],
    "wof:name":"Hidden Acres Farm",
    "wof:placetype":"venue"
},
  "geometry": {"coordinates":[-74.004835,42.937999],"type":"Point"}
}