{
  "type": "Feature",
  "properties": {
    "addr:full":"254 Kingston Ave Brooklyn NY 11213",
    "addr:housenumber":"254",
    "addr:postcode":"11213",
    "addr:street":"Kingston Ave",
    "iso:country":"US",
    "sg:address":"254 Kingston Ave",
    "sg:city":"Brooklyn",
    "sg:classifiers":[
        {
            "category":"Banks & Credit Unions",
            "subcategory":"Bank",
            "type":"Services"
        }
    ],
    "sg:phone":"+1 718 778 4300",
    "sg:postcode":"11213",
    "sg:province":"NY",
    "sg:tags":[
        "cashing",
        "check"
    ],
    "wof:name":"Island Check Cashing Corp",
    "wof:placetype":"venue"
},
  "geometry": {"coordinates":[-73.942162,40.670628],"type":"Point"}
}