{
  "type": "Feature",
  "properties": {
    "addr:full":"4 Campion Rd New Hartford NY 13413",
    "addr:housenumber":"4",
    "addr:postcode":"13413",
    "addr:street":"Campion Rd",
    "iso:country":"US",
    "sg:address":"4 Campion Rd",
    "sg:city":"New Hartford",
    "sg:classifiers":[
        {
            "category":"Shopping",
            "subcategory":"Clothing, Apparel, & Fashions",
            "type":"Retail Goods"
        }
    ],
    "sg:phone":"+1 315 732 8307",
    "sg:postcode":"13413",
    "sg:province":"NY",
    "sg:tags":[
        "tailor"
    ],
    "wof:name":"Village Tailor Shop",
    "wof:placetype":"venue"
},
  "geometry": {"coordinates":[-75.287733,43.0736],"type":"Point"}
}