{
  "type": "Feature",
  "properties": {
    "addr:full":"26 Rhinecliff Rd Rhinebeck NY 12572",
    "addr:housenumber":"26",
    "addr:postcode":"12572",
    "addr:street":"Rhinecliff Rd",
    "iso:country":"US",
    "sg:address":"26 Rhinecliff Rd",
    "sg:city":"Rhinebeck",
    "sg:classifiers":[
        {
            "category":"Building & Trades",
            "subcategory":"Construction",
            "type":"Services"
        }
    ],
    "sg:phone":"+1 845 876 3412",
    "sg:postcode":"12572",
    "sg:province":"NY",
    "sg:tags":[
        "general",
        "contractor"
    ],
    "wof:name":"Construction Industries",
    "wof:placetype":"venue"
},
  "geometry": {"coordinates":[-73.928839,41.928074],"type":"Point"}
}