{
  "type": "Feature",
  "properties": {
    "iso:country":"US",
    "sg:address":"5225 Harris Hill Rd",
    "sg:city":"Williamsville",
    "sg:classifiers":[
        {
            "category":"Organizations",
            "subcategory":"Religious Organization",
            "type":"Services"
        }
    ],
    "sg:phone":"+1 716 688 6867",
    "sg:postcode":"14221",
    "sg:province":"NY",
    "sg:tags":[
        "church"
    ],
    "wof:name":"Harris Hills Mennonite",
    "wof:placetype":"venue"
},
  "geometry": {"coordinates":[-78.67695999999999,42.978997],"type":"Point"}
}