{
  "type": "Feature",
  "properties": {
    "addr:full":"350 Kenridge Rd Lawrence NY 11559",
    "addr:housenumber":"350",
    "addr:postcode":"11559",
    "addr:street":"Kenridge Rd",
    "iso:country":"US",
    "sg:address":"350 Kenridge Rd",
    "sg:city":"Lawrence",
    "sg:classifiers":[
        {
            "category":"Health Services",
            "subcategory":"Doctor",
            "type":"Services"
        }
    ],
    "sg:phone":"+1 516 371 4756",
    "sg:postcode":"11559",
    "sg:province":"NY",
    "sg:tags":[
        "medical"
    ],
    "wof:name":"Koplewicz Hirsch Psychiatric",
    "wof:placetype":"venue"
},
  "geometry": {"coordinates":[-73.725987,40.611278],"type":"Point"}
}