{
  "type": "Feature",
  "properties": {
    "iso:country":"US",
    "sg:address":"115 W 45th St",
    "sg:city":"New York",
    "sg:classifiers":[
        {
            "category":"Deli",
            "type":"Food & Drink"
        }
    ],
    "sg:phone":"+1 212 730 9495",
    "sg:postcode":"10036",
    "sg:province":"NY",
    "wof:name":"Cranberry Gourmet Deli",
    "wof:placetype":"venue"
},
  "geometry": {"coordinates":[-73.983372,40.757288],"type":"Point"}
}