{
  "type": "Feature",
  "properties": {
    "addr:full":"115 W 45th St New York NY 10036",
    "addr:housenumber":"115",
    "addr:postcode":"10036",
    "addr:street":"W 45Th St",
    "iso:country":"US",
    "sg:address":"115 W 45th St",
    "sg:city":"New York",
    "sg:classifiers":[
        {
            "category":"Deli",
            "type":"Food & Drink"
        }
    ],
    "sg:phone":"+1 212 730 9495",
    "sg:postcode":"10036",
    "sg:province":"NY",
    "wof:name":"Cranberry Gourmet Deli",
    "wof:placetype":"venue"
},
  "geometry": {"coordinates":[-73.983372,40.757288],"type":"Point"}
}