{
  "type": "Feature",
  "properties": {
    "iso:country":"US",
    "sg:address":"14 Jericho Tpke",
    "sg:city":"Floral Park",
    "sg:classifiers":[
        {
            "category":"Manufacturing",
            "subcategory":"Tools & Machinery",
            "type":"Manufacturing & Wholesale Goods"
        }
    ],
    "sg:phone":"+1   ",
    "sg:postcode":"11001",
    "sg:province":"NY",
    "sg:tags":[
        "instrument",
        "mfg"
    ],
    "wof:name":"East Coast Orthotic Prosthetic",
    "wof:placetype":"venue"
},
  "geometry": {"coordinates":[-73.70684199999999,40.728001],"type":"Point"}
}