{
  "type": "Feature",
  "properties": {
    "addr:full":"9350 State Hwy 22 Hillsdale NY 12529",
    "addr:housenumber":"9350",
    "addr:postcode":"12529",
    "addr:street":"State Hwy 22",
    "iso:country":"US",
    "sg:address":"9350 State Hwy 22",
    "sg:city":"Hillsdale",
    "sg:classifiers":[
        {
            "category":"Travel",
            "subcategory":"Hotels & Motels",
            "type":"Entertainment"
        }
    ],
    "sg:phone":"+1 518 325 3000",
    "sg:postcode":"12529",
    "sg:province":"NY",
    "sg:website":"www.silvanuslodge.com",
    "wof:name":"Silvanus Lodge",
    "wof:placetype":"venue"
},
  "geometry": {"coordinates":[-73.516769,42.185065],"type":"Point"}
}