{
  "type": "Feature",
  "properties": {
    "iso:country":"US",
    "sg:address":"1045 Hoosick Rd",
    "sg:city":"Troy",
    "sg:classifiers":[
        {
            "category":"Government",
            "subcategory":"Fire Station",
            "type":"Public Place"
        }
    ],
    "sg:phone":"+1 518 279 3878",
    "sg:postcode":"12180",
    "sg:province":"NY",
    "sg:tags":[
        "department"
    ],
    "wof:name":"Center Brunswick Volunteer",
    "wof:placetype":"venue"
},
  "geometry": {"coordinates":[-73.597939,42.760663],"type":"Point"}
}