{
  "type": "Feature",
  "properties": {
    "iso:country":"US",
    "sg:address":"65 Agnes St",
    "sg:city":"Freeport",
    "sg:classifiers":[
        {
            "category":"Professional",
            "subcategory":"Employment Agencies",
            "type":"Services"
        }
    ],
    "sg:phone":"+1 516 377 6357",
    "sg:postcode":"11520",
    "sg:province":"NY",
    "wof:name":"Umique Technologies",
    "wof:placetype":"venue"
},
  "geometry": {"coordinates":[-73.59034699999999,40.670255],"type":"Point"}
}