{
  "type": "Feature",
  "properties": {
    "iso:country":"US",
    "sg:address":"17 Fort George Hill",
    "sg:city":"New York",
    "sg:classifiers":[
        {
            "category":"Building & Trades",
            "subcategory":"Construction",
            "type":"Services"
        }
    ],
    "sg:phone":"+1 212 569 2550",
    "sg:postcode":"10040",
    "sg:province":"NY",
    "sg:tags":[
        "builder",
        "operative"
    ],
    "wof:name":"Inwood Heights Inc",
    "wof:placetype":"venue"
},
  "geometry": {"coordinates":[-73.924936,40.861518],"type":"Point"}
}