{
  "type": "Feature",
  "properties": {
    "addr:full":"67 James St Amsterdam NY 12010",
    "addr:housenumber":"67",
    "addr:postcode":"12010",
    "addr:street":"James St",
    "iso:country":"US",
    "sg:address":"67 James St",
    "sg:city":"Amsterdam",
    "sg:classifiers":[
        {
            "category":"Professional",
            "subcategory":"Computer Services",
            "type":"Services"
        }
    ],
    "sg:phone":"+1 518 843 4300",
    "sg:postcode":"12010",
    "sg:province":"NY",
    "sg:tags":[
        "internet"
    ],
    "wof:name":"Taylarnet Internet Svc",
    "wof:placetype":"venue"
},
  "geometry": {"coordinates":[-74.179052,42.93526],"type":"Point"}
}