{
  "type": "Feature",
  "properties": {
    "iso:country":"US",
    "sg:address":"8 Quarter Horse Ln",
    "sg:city":"Plattsburgh",
    "sg:classifiers":[
        {
            "category":"Insurance",
            "subcategory":"Hazard Insurance",
            "type":"Services"
        }
    ],
    "sg:phone":"+1 518 563 6893",
    "sg:postcode":"12901",
    "sg:province":"NY",
    "wof:name":"Lyle F Newman",
    "wof:placetype":"venue"
},
  "geometry": {"coordinates":[-73.385289,44.720456],"type":"Point"}
}