{
  "type": "Feature",
  "properties": {
    "addr:full":"1 Railroad Ave Stamford NY 12167",
    "addr:housenumber":"1",
    "addr:postcode":"12167",
    "addr:street":"Railroad Ave",
    "iso:country":"US",
    "sg:address":"1 Railroad Ave",
    "sg:city":"Stamford",
    "sg:classifiers":[
        {
            "category":"Organizations",
            "subcategory":"Religious Organization",
            "type":"Services"
        }
    ],
    "sg:phone":"+1 607 652 3660",
    "sg:postcode":"12167",
    "sg:province":"NY",
    "sg:tags":[
        "church"
    ],
    "wof:name":"Jehovah's Witnesses",
    "wof:placetype":"venue"
},
  "geometry": {"coordinates":[-74.616297,42.407906],"type":"Point"}
}