{
  "type": "Feature",
  "properties": {
    "addr:full":"85 E Marie St Hicksville NY 11801",
    "addr:housenumber":"85",
    "addr:postcode":"11801",
    "addr:street":"E Marie St",
    "iso:country":"US",
    "sg:address":"85 E Marie St",
    "sg:city":"Hicksville",
    "sg:classifiers":[
        {
            "category":"Insurance",
            "subcategory":"Insurance Agent",
            "type":"Services"
        }
    ],
    "sg:phone":"+1 516 931 5100",
    "sg:postcode":"11801",
    "sg:province":"NY",
    "wof:name":"Silberstein Insurance Group",
    "wof:placetype":"venue"
},
  "geometry": {"coordinates":[-73.518843,40.768122],"type":"Point"}
}