{
  "type": "Feature",
  "properties": {
    "iso:country":"US",
    "sg:address":"33-05 Broadway",
    "sg:city":"Astoria",
    "sg:classifiers":[
        {
            "category":"Bars & Pubs",
            "type":"Food & Drink"
        },
        {
            "category":"Restaurant",
            "type":"Food & Drink"
        }
    ],
    "sg:phone":"+1 718 932 0101",
    "sg:postcode":"11106",
    "sg:province":"NY",
    "sg:tags":[
        "tapa",
        "spanish"
    ],
    "sg:website":"larioja.webs.com/",
    "wof:name":"La Rioja",
    "wof:placetype":"venue"
},
  "geometry": {"coordinates":[-73.92374,40.76122],"type":"Point"}
}