{
  "type": "Feature",
  "properties": {
    "iso:country":"US",
    "sg:address":"131 Lawrence Ave",
    "sg:city":"Staten Island",
    "sg:classifiers":[
        {
            "category":"Building & Trades",
            "subcategory":"Construction",
            "type":"Services"
        }
    ],
    "sg:phone":"+1 718 720 0183",
    "sg:postcode":"10310",
    "sg:province":"NY",
    "sg:tags":[
        "repair"
    ],
    "wof:name":"Jfr Construction Corp",
    "wof:placetype":"venue"
},
  "geometry": {"coordinates":[-74.10672099999999,40.626934],"type":"Point"}
}