{
  "type": "Feature",
  "properties": {
    "addr:full":"454 Evergreen Ct Central Valley NY 10917",
    "addr:housenumber":"454",
    "addr:postcode":"10917",
    "addr:street":"Evergreen Ct",
    "iso:country":"US",
    "sg:address":"454 Evergreen Ct",
    "sg:city":"Central Valley",
    "sg:classifiers":[
        {
            "category":"Shopping",
            "subcategory":"Discount & Variety Stores",
            "type":"Retail Goods"
        }
    ],
    "sg:phone":"+1 845 928 4405",
    "sg:postcode":"10917",
    "sg:province":"NY",
    "sg:tags":[
        "outlet"
    ],
    "wof:name":"Woodbury Common Premium Outlets",
    "wof:placetype":"venue"
},
  "geometry": {"coordinates":[-74.127534,41.317436],"type":"Point"}
}