{
  "type": "Feature",
  "properties": {
    "iso:country":"US",
    "sg:address":"55 N Main St",
    "sg:city":"Freeport",
    "sg:classifiers":[
        {
            "category":"Wholesale",
            "subcategory":"Photographic Equipment",
            "type":"Manufacturing & Wholesale Goods"
        }
    ],
    "sg:phone":"+1 516 867 4900",
    "sg:postcode":"11520",
    "sg:province":"NY",
    "sg:tags":[
        "supplies-wholesale",
        "support",
        "camera",
        "imported",
        "manufacturer"
    ],
    "wof:name":"Sachtler Corp Of America",
    "wof:placetype":"venue"
},
  "geometry": {"coordinates":[-73.584521,40.658586],"type":"Point"}
}