{
  "type": "Feature",
  "properties": {
    "iso:country":"US",
    "sg:address":"1737 US Hwy 9w",
    "sg:city":"Selkirk",
    "sg:classifiers":[
        {
            "category":"Real Estate",
            "subcategory":"Real Estate Operator",
            "type":"Services"
        }
    ],
    "sg:phone":"+1 518 622 0815",
    "sg:postcode":"12158",
    "sg:province":"NY",
    "sg:tags":[
        "mobile",
        "home",
        "community"
    ],
    "wof:name":"Pine Ridge Estates",
    "wof:placetype":"venue"
},
  "geometry": {"coordinates":[-73.814027,42.516037],"type":"Point"}
}