{
  "type": "Feature",
  "properties": {
    "iso:country":"US",
    "sg:address":"1019 State Route 17M Ste 1",
    "sg:city":"Monroe",
    "sg:classifiers":[
        {
            "category":"Health Services",
            "subcategory":"Doctor",
            "type":"Services"
        },
        {
            "category":"Sports & Exercise",
            "subcategory":"Gym",
            "type":"Entertainment"
        },
        {
            "category":"Health Services",
            "subcategory":"Health Practitioner",
            "type":"Services"
        }
    ],
    "sg:phone":"+1 845 781 7470",
    "sg:postcode":"10950",
    "sg:province":"NY",
    "sg:tags":[
        "orthopedist",
        "therapy",
        "physical"
    ],
    "sg:website":"www.promotionphysicaltherapy.com",
    "wof:name":"Pro Motion Physical Therapy",
    "wof:placetype":"venue"
},
  "geometry": {"coordinates":[-74.199629,41.344313],"type":"Point"}
}