{
  "type": "Feature",
  "properties": {
    "iso:country":"US",
    "sg:address":"205 N Wellwood Ave",
    "sg:city":"Lindenhurst",
    "sg:classifiers":[
        {
            "category":"Personal",
            "subcategory":"Barber",
            "type":"Services"
        }
    ],
    "sg:phone":"+1 631 226 0762",
    "sg:postcode":"11757",
    "sg:province":"NY",
    "wof:name":"Wellwood Ave Barber",
    "wof:placetype":"venue"
},
  "geometry": {"coordinates":[-73.37594900000001,40.689208],"type":"Point"}
}