{
  "type": "Feature",
  "properties": {
    "iso:country":"US",
    "sg:address":"722 S Meadow St Ste 100",
    "sg:city":"Ithaca",
    "sg:classifiers":[
        {
            "category":"Health Services",
            "subcategory":"Optometrist",
            "type":"Services"
        },
        {
            "category":"Shopping",
            "subcategory":"Optical Goods",
            "type":"Retail Goods"
        },
        {
            "category":"Shopping",
            "subcategory":"Optician",
            "type":"Retail Goods"
        }
    ],
    "sg:phone":"+1 607 273 3300",
    "sg:postcode":"14850",
    "sg:province":"NY",
    "sg:tags":[
        "lens",
        "contact"
    ],
    "sg:website":"http://www.empirevision.com",
    "wof:name":"Empire Vision Center, Inc.",
    "wof:placetype":"venue"
},
  "geometry": {"coordinates":[-76.507997,42.431563],"type":"Point"}
}