{
  "type": "Feature",
  "properties": {
    "addr:full":"946 New Loudon Rd Latham NY 12110",
    "addr:housenumber":"946",
    "addr:postcode":"12110",
    "addr:street":"New Loudon Rd",
    "iso:country":"US",
    "sg:address":"946 New Loudon Rd",
    "sg:city":"Latham",
    "sg:classifiers":[
        {
            "category":"Retail",
            "subcategory":"Auto Rental",
            "type":"Services"
        }
    ],
    "sg:phone":"+1 518 783 1091",
    "sg:postcode":"12110",
    "sg:province":"NY",
    "sg:tags":[
        "renting",
        "automobile",
        "passenger",
        "car"
    ],
    "wof:name":"Enterprise Rent A Car",
    "wof:placetype":"venue"
},
  "geometry": {"coordinates":[-73.754441,42.766912],"type":"Point"}
}