{
  "type": "Feature",
  "properties": {
    "iso:country":"US",
    "sg:address":"198 Grand St",
    "sg:city":"Brooklyn",
    "sg:classifiers":[
        {
            "category":"Organizations",
            "subcategory":"Religious Organization",
            "type":"Services"
        }
    ],
    "sg:phone":"+1 718 388 4899",
    "sg:postcode":"11211",
    "sg:province":"NY",
    "sg:tags":[
        "church"
    ],
    "wof:name":"Damascus Christian Church",
    "wof:placetype":"venue"
},
  "geometry": {"coordinates":[-73.960471,40.714168],"type":"Point"}
}