{
  "type": "Feature",
  "properties": {
    "iso:country":"US",
    "sg:address":"7 Landau Ave",
    "sg:city":"Elmont",
    "sg:classifiers":[
        {
            "category":"Shopping",
            "subcategory":"Clothing, Apparel, & Fashions",
            "type":"Retail Goods"
        }
    ],
    "sg:phone":"+1 516 354 3085",
    "sg:postcode":"11003",
    "sg:province":"NY",
    "sg:tags":[
        "apron",
        "fancy"
    ],
    "wof:name":"Product Concepts & Solutions",
    "wof:placetype":"venue"
},
  "geometry": {"coordinates":[-73.694031,40.709109],"type":"Point"}
}