{
  "type": "Feature",
  "properties": {
    "iso:country":"US",
    "sg:address":"202 Newtown Rd",
    "sg:city":"Plainview",
    "sg:classifiers":[
        {
            "category":"Wholesale",
            "subcategory":"Electrical",
            "type":"Manufacturing & Wholesale Goods"
        }
    ],
    "sg:phone":"+1 516 420 5629",
    "sg:postcode":"11803",
    "sg:province":"NY",
    "sg:tags":[
        "alarm",
        "burglar",
        "system"
    ],
    "wof:name":"K Max Intl",
    "wof:placetype":"venue"
},
  "geometry": {"coordinates":[-73.451832,40.784706],"type":"Point"}
}