{
  "type": "Feature",
  "properties": {
    "addr:full":"3130 Amboy Road Staten Island NY 10306",
    "addr:housenumber":"3130",
    "addr:postcode":"10306",
    "addr:street":"Amboy Road",
    "iso:country":"US",
    "sg:address":"3130 Amboy Road",
    "sg:city":"Staten Island",
    "sg:classifiers":[
        {
            "category":"Banks & Credit Unions",
            "subcategory":"Financial Services",
            "type":"Services"
        }
    ],
    "sg:phone":"+1 718 987 1650",
    "sg:postcode":"10306",
    "sg:province":"NY",
    "sg:tags":[
        "broker",
        "mortgage"
    ],
    "wof:name":"Master Mortgage Brokers",
    "wof:placetype":"venue"
},
  "geometry": {"coordinates":[-74.132085,40.56411],"type":"Point"}
}