{
  "type": "Feature",
  "properties": {
    "addr:full":"14 Jericho Tpke Jericho NY 11753",
    "addr:housenumber":"14",
    "addr:postcode":"11753",
    "addr:street":"Jericho Tpke",
    "iso:country":"US",
    "sg:address":"14 Jericho Tpke",
    "sg:city":"Jericho",
    "sg:classifiers":[
        {
            "category":"Utilities",
            "subcategory":"Mobile Phone",
            "type":"Services"
        },
        {
            "category":"Shopping",
            "type":"Retail Goods"
        }
    ],
    "sg:phone":"+1 516 338 0400",
    "sg:postcode":"11753",
    "sg:province":"NY",
    "sg:tags":[
        "telephone",
        "cellular"
    ],
    "wof:name":"Cellular Only",
    "wof:placetype":"venue"
},
  "geometry": {"coordinates":[-73.554857,40.782037],"type":"Point"}
}