{
  "type": "Feature",
  "properties": {
    "iso:country":"US",
    "sg:address":"1376 Lincoln Ave",
    "sg:city":"Holbrook",
    "sg:classifiers":[
        {
            "category":"Retail",
            "subcategory":"Auto Repair",
            "type":"Services"
        }
    ],
    "sg:phone":"+1   ",
    "sg:postcode":"11741",
    "sg:province":"NY",
    "sg:tags":[
        "antique",
        "automotive"
    ],
    "wof:name":"Gaslite Garage Inc",
    "wof:placetype":"venue"
},
  "geometry": {"coordinates":[-73.083962,40.778656],"type":"Point"}
}