{
  "type": "Feature",
  "properties": {
    "iso:country":"US",
    "sg:address":"111 W State St",
    "sg:city":"Wellsville",
    "sg:classifiers":[
        {
            "category":"Government",
            "subcategory":"Office",
            "type":"Public Place"
        }
    ],
    "sg:phone":"+1 585 593 3333",
    "sg:postcode":"14895",
    "sg:province":"NY",
    "sg:tags":[
        "executive"
    ],
    "wof:name":"Wellsville Village Water",
    "wof:placetype":"venue"
},
  "geometry": {"coordinates":[-77.947518,42.118435],"type":"Point"}
}