{
  "type": "Feature",
  "properties": {
    "addr:full":"1401 Avenue Z Brooklyn NY 11235",
    "addr:housenumber":"1401",
    "addr:postcode":"11235",
    "addr:street":"Avenue Z",
    "iso:country":"US",
    "sg:address":"1401 Avenue Z",
    "sg:city":"Brooklyn",
    "sg:classifiers":[
        {
            "category":"Sports & Exercise",
            "subcategory":"Bicycle Rental",
            "type":"Entertainment"
        }
    ],
    "sg:phone":"+1 718 332 0615",
    "sg:postcode":"11235",
    "sg:province":"NY",
    "sg:tags":[
        "wear"
    ],
    "wof:name":"Fashion Code",
    "wof:placetype":"venue"
},
  "geometry": {"coordinates":[-73.955101,40.588001],"type":"Point"}
}