{
  "type": "Feature",
  "properties": {
    "iso:country":"US",
    "sg:address":"3393 James Rd",
    "sg:city":"Keuka Park",
    "sg:classifiers":[
        {
            "category":"Organizations",
            "subcategory":"Religious Organization",
            "type":"Services"
        }
    ],
    "sg:phone":"+1 315 536 5635",
    "sg:postcode":"14478",
    "sg:province":"NY",
    "sg:tags":[
        "church"
    ],
    "sg:website":"www.lds.org",
    "wof:name":"Church Of Jesus CHRIST-Lds",
    "wof:placetype":"venue"
},
  "geometry": {"coordinates":[-77.123726,42.600412],"type":"Point"}
}