{
  "type": "Feature",
  "properties": {
    "iso:country":"US",
    "sg:address":"400 E 71 St",
    "sg:city":"New York",
    "sg:classifiers":[
        {
            "category":"Health Services",
            "subcategory":"Doctor",
            "type":"Services"
        }
    ],
    "sg:phone":"+1 212 717 9533",
    "sg:postcode":"10021",
    "sg:province":"NY",
    "sg:tags":[
        "medical"
    ],
    "wof:name":"Allan Schneider Dr",
    "wof:placetype":"venue"
},
  "geometry": {"coordinates":[-73.95424800000001,40.766165],"type":"Point"}
}