{
  "type": "Feature",
  "properties": {
    "addr:full":"7 Marion St Greenvale NY 11548",
    "addr:housenumber":"7",
    "addr:postcode":"11548",
    "addr:street":"Marion St",
    "iso:country":"US",
    "sg:address":"7 Marion St",
    "sg:city":"Greenvale",
    "sg:classifiers":[
        {
            "category":"Building & Trades",
            "subcategory":"Construction",
            "type":"Services"
        }
    ],
    "sg:phone":"+1 516 625 8619",
    "sg:postcode":"11548",
    "sg:province":"NY",
    "sg:tags":[
        "general",
        "contractor"
    ],
    "wof:name":"J & S Construction",
    "wof:placetype":"venue"
},
  "geometry": {"coordinates":[-73.62324700000001,40.811592],"type":"Point"}
}