{
  "type": "Feature",
  "properties": {
    "addr:full":"1300 Hilton Parma Rd Hilton NY 14468",
    "addr:housenumber":"1300",
    "addr:postcode":"14468",
    "addr:street":"Hilton Parma Rd",
    "iso:country":"US",
    "sg:address":"1300 Hilton Parma Rd",
    "sg:city":"Hilton",
    "sg:classifiers":[
        {
            "category":"Government",
            "subcategory":"Office",
            "type":"Public Place"
        }
    ],
    "sg:phone":"+1 585 392 9455",
    "sg:postcode":"14468",
    "sg:province":"NY",
    "sg:tags":[
        "city",
        "taxation"
    ],
    "wof:name":"Assessors Office",
    "wof:placetype":"venue"
},
  "geometry": {"coordinates":[-77.791369,43.246114],"type":"Point"}
}