{
  "type": "Feature",
  "properties": {
    "iso:country":"US",
    "sg:address":"2 Willow Dr",
    "sg:city":"Hopewell Jct",
    "sg:classifiers":[
        {
            "category":"Health Services",
            "subcategory":"Doctor",
            "type":"Services"
        }
    ],
    "sg:phone":"+1 845 226 7548",
    "sg:postcode":"12533",
    "sg:province":"NY",
    "sg:tags":[
        "dentist"
    ],
    "wof:name":"Daniel Wheeler DDS",
    "wof:placetype":"venue"
},
  "geometry": {"coordinates":[-73.779748,41.585893],"type":"Point"}
}