{
  "type": "Feature",
  "properties": {
    "iso:country":"US",
    "sg:address":"521 Rte 111",
    "sg:city":"Hauppauge",
    "sg:classifiers":[
        {
            "category":"Health Services",
            "subcategory":"Doctor",
            "type":"Services"
        }
    ],
    "sg:phone":"+1 631 265 9645",
    "sg:postcode":"11788",
    "sg:province":"NY",
    "sg:tags":[
        "physician",
        "surgeon"
    ],
    "sg:website":"www.babradiology.com",
    "wof:name":"BAB Radiological-Hauppauge",
    "wof:placetype":"venue"
},
  "geometry": {"coordinates":[-73.199868,40.828337],"type":"Point"}
}