{
  "type": "Feature",
  "properties": {
    "iso:country":"US",
    "sg:address":"403 State Hwy 23B",
    "sg:city":"Hudson",
    "sg:classifiers":[
        {
            "category":"Autos & Motor Vehicles",
            "subcategory":"Automobile Sales",
            "type":"Retail Goods"
        }
    ],
    "sg:phone":"+1 518 851 2886",
    "sg:postcode":"12534",
    "sg:province":"NY",
    "sg:tags":[
        "car",
        "dealer"
    ],
    "wof:name":"Claverack Service Station",
    "wof:placetype":"venue"
},
  "geometry": {"coordinates":[-73.744488,42.224025],"type":"Point"}
}