{
  "type": "Feature",
  "properties": {
    "iso:country":"US",
    "sg:address":"1466 Broadway",
    "sg:city":"New York",
    "sg:classifiers":[
        {
            "category":"Professional",
            "subcategory":"Business Services",
            "type":"Services"
        }
    ],
    "sg:phone":"+1 646 562 0459",
    "sg:postcode":"10036",
    "sg:province":"NY",
    "sg:tags":[
        "merchandising"
    ],
    "wof:name":"Giant Merchandising",
    "wof:placetype":"venue"
},
  "geometry": {"coordinates":[-73.986467,40.755189],"type":"Point"}
}