{
  "type": "Feature",
  "properties": {
    "addr:full":"19 Norton Pl Fredonia NY 14063",
    "addr:housenumber":"19",
    "addr:postcode":"14063",
    "addr:street":"Norton Pl",
    "iso:country":"US",
    "sg:address":"19 Norton Pl",
    "sg:city":"Fredonia",
    "sg:classifiers":[
        {
            "category":"Manufacturing",
            "subcategory":"Printing",
            "type":"Manufacturing & Wholesale Goods"
        }
    ],
    "sg:phone":"+1 716 672 5686",
    "sg:postcode":"14063",
    "sg:province":"NY",
    "sg:tags":[
        "commercial",
        "offset"
    ],
    "wof:name":"Arkwright Printing Co Inc",
    "wof:placetype":"venue"
},
  "geometry": {"coordinates":[-79.329605,42.438779],"type":"Point"}
}