{
  "type": "Feature",
  "properties": {
    "addr:full":"12711 111th Avenue South Ozone Park NY 11420",
    "addr:housenumber":"12711",
    "addr:postcode":"11420",
    "addr:street":"111Th Avenue",
    "iso:country":"US",
    "sg:address":"12711 111th Avenue",
    "sg:city":"South Ozone Park",
    "sg:classifiers":[
        {
            "category":"Health Services",
            "subcategory":"Health Practitioner",
            "type":"Services"
        }
    ],
    "sg:phone":"+1 718 738 2236",
    "sg:postcode":"11420",
    "sg:province":"NY",
    "sg:tags":[
        "therapy",
        "physical"
    ],
    "wof:name":"Caring Hands Physical Therapy",
    "wof:placetype":"venue"
},
  "geometry": {"coordinates":[-73.81385400000001,40.682745],"type":"Point"}
}