{
  "type": "Feature",
  "properties": {
    "iso:country":"US",
    "sg:address":"23 Washington St",
    "sg:city":"Ellicottville",
    "sg:classifiers":[
        {
            "category":"Professional",
            "type":"Services"
        }
    ],
    "sg:phone":"+1 716 699 8848",
    "sg:postcode":"14731",
    "sg:province":"NY",
    "sg:tags":[
        "establishment"
    ],
    "wof:name":"Zeledon Inc",
    "wof:placetype":"venue"
},
  "geometry": {"coordinates":[-78.67130899999999,42.275654],"type":"Point"}
}