{
  "type": "Feature",
  "properties": {
    "iso:country":"US",
    "sg:address":"2155 Ocean Ave Ste D",
    "sg:city":"Ronkonkoma",
    "sg:classifiers":[
        {
            "category":"Autos & Motor Vehicles",
            "subcategory":"Fuel & Gas Station",
            "type":"Retail Goods"
        }
    ],
    "sg:phone":"+1 631 738 9524",
    "sg:postcode":"11779",
    "sg:province":"NY",
    "wof:name":"Hess Corporation",
    "wof:placetype":"venue"
},
  "geometry": {"coordinates":[-73.123003,40.799966],"type":"Point"}
}