{
  "type": "Feature",
  "properties": {
    "addr:full":"5035 Broadway New York NY 10034",
    "addr:housenumber":"5035",
    "addr:postcode":"10034",
    "addr:street":"Broadway",
    "iso:country":"US",
    "sg:address":"5035 Broadway",
    "sg:city":"New York",
    "sg:classifiers":[
        {
            "category":"Restaurant",
            "type":"Food & Drink"
        }
    ],
    "sg:phone":"+1 212 567 6640",
    "sg:postcode":"10034",
    "sg:province":"NY",
    "sg:tags":[
        "new",
        "american",
        "italian"
    ],
    "sg:website":"www.laestufarestaurant.com",
    "wof:name":"La Estufa",
    "wof:placetype":"venue"
},
  "geometry": {"coordinates":[-73.916301,40.869577],"type":"Point"}
}