{
  "type": "Feature",
  "properties": {
    "iso:country":"US",
    "sg:address":"10 Romeo Dr",
    "sg:city":"Smithtown",
    "sg:classifiers":[
        {
            "category":"Professional",
            "subcategory":"Accounting & Tax Preparation",
            "type":"Services"
        }
    ],
    "sg:phone":"+1 631 366 3683",
    "sg:postcode":"11787",
    "sg:province":"NY",
    "sg:tags":[
        "accountant"
    ],
    "wof:name":"Tedoldi & Assoc",
    "wof:placetype":"venue"
},
  "geometry": {"coordinates":[-73.241784,40.861304],"type":"Point"}
}