{
  "type": "Feature",
  "properties": {
    "iso:country":"US",
    "sg:address":"165 Chrystie St",
    "sg:city":"New York",
    "sg:phone":"+1 212 533 2356",
    "sg:postcode":"10002",
    "sg:province":"NY",
    "sg:tags":[
        "equipment",
        "commercial"
    ],
    "sg:website":"www.masterkitchensupplies.com",
    "wof:name":"Master Kitchen Supplies Inc",
    "wof:placetype":"venue"
},
  "geometry": {"coordinates":[-73.99255700000001,40.720637],"type":"Point"}
}