{
  "type": "Feature",
  "properties": {
    "addr:full":"21 Summers St Livonia NY 14487",
    "addr:housenumber":"21",
    "addr:postcode":"14487",
    "addr:street":"Summers St",
    "iso:country":"US",
    "sg:address":"21 Summers St",
    "sg:city":"Livonia",
    "sg:classifiers":[
        {
            "category":"Place Of Worship",
            "subcategory":"Church",
            "type":"Public Place"
        },
        {
            "category":"Place Of Worship",
            "type":"Public Place"
        }
    ],
    "sg:phone":"+1 585 346 3511",
    "sg:postcode":"14487",
    "sg:province":"NY",
    "sg:tags":[
        "churches-methodist"
    ],
    "wof:name":"United Methodist Church Of Livonia",
    "wof:placetype":"venue"
},
  "geometry": {"coordinates":[-77.662076,42.82413],"type":"Point"}
}