{
  "type": "Feature",
  "properties": {
    "addr:full":"47 Olive St Saranac Lake NY 12983",
    "addr:housenumber":"47",
    "addr:postcode":"12983",
    "addr:street":"Olive St",
    "iso:country":"US",
    "sg:address":"47 Olive St",
    "sg:city":"Saranac Lake",
    "sg:classifiers":[
        {
            "category":"Government",
            "subcategory":"Office",
            "type":"Public Place"
        }
    ],
    "sg:phone":"+1 518 891 6312",
    "sg:postcode":"12983",
    "sg:province":"NY",
    "wof:name":"County ARC",
    "wof:placetype":"venue"
},
  "geometry": {"coordinates":[-74.139473,44.326667],"type":"Point"}
}