{
  "type": "Feature",
  "properties": {
    "iso:country":"US",
    "sg:address":"7005 Fort Hamilton Pkwy",
    "sg:city":"Brooklyn",
    "sg:classifiers":[
        {
            "category":"Retail",
            "subcategory":"Laundry & Dry Cleaning",
            "type":"Services"
        }
    ],
    "sg:phone":"+1 718 836 7370",
    "sg:postcode":"11228",
    "sg:province":"NY",
    "sg:tags":[
        "cleaner",
        "commercial",
        "operated",
        "dryer",
        "laundries-self",
        "washer",
        "coin"
    ],
    "wof:name":"A T Laundramat",
    "wof:placetype":"venue"
},
  "geometry": {"coordinates":[-74.01289300000001,40.628189],"type":"Point"}
}