{
  "type": "Feature",
  "properties": {
    "addr:full":"68 Main St Nyack NY 10960",
    "addr:housenumber":"68",
    "addr:postcode":"10960",
    "addr:street":"Main St",
    "iso:country":"US",
    "sg:address":"68 Main St",
    "sg:city":"Nyack",
    "sg:classifiers":[
        {
            "category":"Government",
            "subcategory":"Fire Station",
            "type":"Public Place"
        }
    ],
    "sg:phone":"+1 845 358 9729",
    "sg:postcode":"10960",
    "sg:province":"NY",
    "sg:tags":[
        "department"
    ],
    "wof:name":"Mazeppa Engine Co",
    "wof:placetype":"venue"
},
  "geometry": {"coordinates":[-73.916927,41.090771],"type":"Point"}
}