{
  "type": "Feature",
  "properties": {
    "addr:full":"1023 S Salina St Syracuse NY 13202",
    "addr:housenumber":"1023",
    "addr:postcode":"13202",
    "addr:street":"S Salina St",
    "iso:country":"US",
    "sg:address":"1023 S Salina St",
    "sg:city":"Syracuse",
    "sg:classifiers":[
        {
            "category":"Home & Garden",
            "subcategory":"Building Materials",
            "type":"Retail Goods"
        }
    ],
    "sg:phone":"+1   ",
    "sg:postcode":"13202",
    "sg:province":"NY",
    "sg:tags":[
        "auto"
    ],
    "wof:name":"R KAMP & Sons",
    "wof:placetype":"venue"
},
  "geometry": {"coordinates":[-76.14959,43.037303],"type":"Point"}
}