{
  "type": "Feature",
  "properties": {
    "addr:full":"771 E 149th St Bronx NY 10455",
    "addr:housenumber":"771",
    "addr:postcode":"10455",
    "addr:street":"E 149Th St",
    "iso:country":"US",
    "sg:address":"771 E 149th St",
    "sg:city":"Bronx",
    "sg:classifiers":[
        {
            "category":"Travel",
            "subcategory":"Travel Agent",
            "type":"Entertainment"
        }
    ],
    "sg:phone":"+1 718 292 7171",
    "sg:postcode":"10455",
    "sg:province":"NY",
    "sg:tags":[
        "agency",
        "bureau"
    ],
    "wof:name":"149 Multi Svc",
    "wof:placetype":"venue"
},
  "geometry": {"coordinates":[-73.907754,40.813072],"type":"Point"}
}