{
  "type": "Feature",
  "properties": {
    "addr:full":"710 Main St Port Jefferson NY 11777",
    "addr:housenumber":"710",
    "addr:postcode":"11777",
    "addr:street":"Main St",
    "iso:country":"US",
    "sg:address":"710 Main St",
    "sg:city":"Port Jefferson",
    "sg:classifiers":[
        {
            "category":"Health Services",
            "subcategory":"Doctor",
            "type":"Services"
        }
    ],
    "sg:phone":"+1 631 474 4000",
    "sg:postcode":"11777",
    "sg:province":"NY",
    "sg:tags":[
        "physician"
    ],
    "wof:name":"Dr William Taibi MD",
    "wof:placetype":"venue"
},
  "geometry": {"coordinates":[-73.05868700000001,40.937699],"type":"Point"}
}