{
  "type": "Feature",
  "properties": {
    "iso:country":"US",
    "sg:address":"22 Alice Ct",
    "sg:city":"East Rockaway",
    "sg:classifiers":[
        {
            "category":"Professional",
            "type":"Services"
        }
    ],
    "sg:phone":"+1 516 593 8230",
    "sg:postcode":"11518",
    "sg:province":"NY",
    "sg:tags":[
        "establishment"
    ],
    "wof:name":"ACLD",
    "wof:placetype":"venue"
},
  "geometry": {"coordinates":[-73.66335599999999,40.639802],"type":"Point"}
}