{
  "type": "Feature",
  "properties": {
    "iso:country":"US",
    "sg:address":"250 Essjay Rd",
    "sg:city":"Buffalo",
    "sg:classifiers":[
        {
            "category":"Social Services",
            "subcategory":"Child Care",
            "type":"Services"
        }
    ],
    "sg:phone":"+1 716 565 9518",
    "sg:postcode":"14221",
    "sg:province":"NY",
    "sg:tags":[
        "day"
    ],
    "wof:name":"Childtime Learning Center",
    "wof:placetype":"venue"
},
  "geometry": {"coordinates":[-78.735849,42.976031],"type":"Point"}
}