{
  "type": "Feature",
  "properties": {
    "iso:country":"US",
    "sg:address":"85 Industrial Tract",
    "sg:city":"Hudson",
    "sg:classifiers":[
        {
            "category":"Shopping",
            "subcategory":"Musical Instruments",
            "type":"Retail Goods"
        }
    ],
    "sg:phone":"+1 518 828 7225",
    "sg:postcode":"12534",
    "sg:province":"NY",
    "sg:tags":[
        "music",
        "dealer"
    ],
    "wof:name":"Stagedoor Music Production",
    "wof:placetype":"venue"
},
  "geometry": {"coordinates":[-73.756593,42.249596],"type":"Point"}
}