{
  "type": "Feature",
  "properties": {
    "addr:full":"3 E Market St Rhinebeck NY 12572",
    "addr:housenumber":"3",
    "addr:postcode":"12572",
    "addr:street":"E Market St",
    "iso:country":"US",
    "sg:address":"3 E Market St",
    "sg:city":"Rhinebeck",
    "sg:classifiers":[
        {
            "category":"Shopping",
            "subcategory":"Shoes",
            "type":"Retail Goods"
        }
    ],
    "sg:phone":"+1 845 876 4881",
    "sg:postcode":"12572",
    "sg:province":"NY",
    "sg:website":"www.hudsonvalleyshoes.com",
    "wof:name":"Hudson Valley Footwear",
    "wof:placetype":"venue"
},
  "geometry": {"coordinates":[-73.912577,41.926991],"type":"Point"}
}