{
  "type": "Feature",
  "properties": {
    "addr:full":"26 E Church St Fairport NY 14450",
    "addr:housenumber":"26",
    "addr:postcode":"14450",
    "addr:street":"E Church St",
    "iso:country":"US",
    "sg:address":"26 E Church St",
    "sg:city":"Fairport",
    "sg:classifiers":[
        {
            "category":"Organizations",
            "subcategory":"Religious Organization",
            "type":"Services"
        }
    ],
    "sg:phone":"+1 585 223 0224",
    "sg:postcode":"14450",
    "sg:province":"NY",
    "sg:tags":[
        "church"
    ],
    "sg:website":"www.fairportucc.org",
    "wof:name":"First Congregational United",
    "wof:placetype":"venue"
},
  "geometry": {"coordinates":[-77.44098099999999,43.098472],"type":"Point"}
}