{
  "type": "Feature",
  "properties": {
    "addr:full":"3917 15th Ave Brooklyn NY 11218",
    "addr:housenumber":"3917",
    "addr:postcode":"11218",
    "addr:street":"15Th Ave",
    "iso:country":"US",
    "sg:address":"3917 15th Ave",
    "sg:city":"Brooklyn",
    "sg:classifiers":[
        {
            "category":"Retail",
            "subcategory":"Laundry & Dry Cleaning",
            "type":"Services"
        }
    ],
    "sg:phone":"+1 718 972 2400",
    "sg:postcode":"11218",
    "sg:province":"NY",
    "sg:tags":[
        "cleaner"
    ],
    "wof:name":"Happy Cleaners Inc",
    "wof:placetype":"venue"
},
  "geometry": {"coordinates":[-73.98200199999999,40.637901],"type":"Point"}
}