{
  "type": "Feature",
  "properties": {
    "iso:country":"US",
    "sg:address":"6600 Goodrich Rd",
    "sg:city":"Clarence Center",
    "sg:classifiers":[
        {
            "category":"Retail",
            "subcategory":"Auto Repair",
            "type":"Services"
        }
    ],
    "sg:phone":"+1 716 741 1930",
    "sg:postcode":"14032",
    "sg:province":"NY",
    "sg:tags":[
        "repairing",
        "automobile"
    ],
    "wof:name":"Mc Carthy Automotive Repair",
    "wof:placetype":"venue"
},
  "geometry": {"coordinates":[-78.637013,43.028363],"type":"Point"}
}