{
  "type": "Feature",
  "properties": {
    "addr:full":"311A Brighton Beach Avenue Brooklyn NY 11235",
    "addr:housenumber":"311a",
    "addr:postcode":"11235",
    "addr:street":"Brighton Beach Avenue",
    "iso:country":"US",
    "sg:address":"311A Brighton Beach Avenue",
    "sg:city":"Brooklyn",
    "sg:classifiers":[
        {
            "category":"Food & Beverages",
            "subcategory":"Groceries & Convenience Stores",
            "type":"Retail Goods"
        }
    ],
    "sg:phone":"+1 877 772 7753",
    "sg:postcode":"11235",
    "sg:province":"NY",
    "wof:name":"Big Apple Produce Market",
    "wof:placetype":"venue"
},
  "geometry": {"coordinates":[-73.96399700000001,40.577202],"type":"Point"}
}