{
  "type": "Feature",
  "properties": {
    "iso:country":"US",
    "sg:address":"550 W Old Country Rd",
    "sg:city":"Hicksville",
    "sg:classifiers":[
        {
            "category":"Personal",
            "type":"Services"
        },
        {
            "category":"Health Services",
            "subcategory":"Clinic",
            "type":"Services"
        }
    ],
    "sg:phone":"+1 516 935 7667",
    "sg:postcode":"11801",
    "sg:province":"NY",
    "sg:tags":[
        "home",
        "babysitting",
        "bureau",
        "companion"
    ],
    "wof:name":"Creative Rent-A-Sitter Inc",
    "wof:placetype":"venue"
},
  "geometry": {"coordinates":[-73.549423,40.75679],"type":"Point"}
}