{
  "type": "Feature",
  "properties": {
    "addr:full":"17 Charles Pl Brooklyn NY 11221",
    "addr:housenumber":"17",
    "addr:postcode":"11221",
    "addr:street":"Charles Pl",
    "iso:country":"US",
    "sg:address":"17 Charles Pl",
    "sg:city":"Brooklyn",
    "sg:classifiers":[
        {
            "category":"Organizations",
            "subcategory":"Non-profit Organization",
            "type":"Services"
        }
    ],
    "sg:phone":"+1 718 493 7219",
    "sg:postcode":"11221",
    "sg:province":"NY",
    "sg:tags":[
        "social"
    ],
    "wof:name":"Crow Hill Community Assn",
    "wof:placetype":"venue"
},
  "geometry": {"coordinates":[-73.93142,40.697623],"type":"Point"}
}