{
  "type": "Feature",
  "properties": {
    "addr:full":"4184 Albany Post Rd Hyde Park NY 12538",
    "addr:housenumber":"4184",
    "addr:postcode":"12538",
    "addr:street":"Albany Post Rd",
    "iso:country":"US",
    "sg:address":"4184 Albany Post Rd",
    "sg:city":"Hyde Park",
    "sg:classifiers":[
        {
            "category":"Restaurant",
            "type":"Food & Drink"
        }
    ],
    "sg:phone":"+1   ",
    "sg:postcode":"12538",
    "sg:province":"NY",
    "sg:tags":[
        "diner"
    ],
    "wof:name":"Eveready Diner Inc",
    "wof:placetype":"venue"
},
  "geometry": {"coordinates":[-73.934712,41.788295],"type":"Point"}
}