{
  "type": "Feature",
  "properties": {
    "addr:full":"309 Merrick Rd Rockville Centre NY 11570",
    "addr:housenumber":"309",
    "addr:postcode":"11570",
    "addr:street":"Merrick Rd",
    "iso:country":"US",
    "sg:address":"309 Merrick Rd",
    "sg:city":"Rockville Centre",
    "sg:classifiers":[
        {
            "category":"Shopping",
            "subcategory":"Pharmacy",
            "type":"Retail Goods"
        }
    ],
    "sg:phone":"+1 516 536 2463",
    "sg:postcode":"11570",
    "sg:province":"NY",
    "wof:name":"Rite Aid",
    "wof:placetype":"venue"
},
  "geometry": {"coordinates":[-73.645348,40.656164],"type":"Point"}
}