{
  "type": "Feature",
  "properties": {
    "addr:full":"2386 Ridge Rd Penn Yan NY 14527",
    "addr:housenumber":"2386",
    "addr:postcode":"14527",
    "addr:street":"Ridge Rd",
    "iso:country":"US",
    "sg:address":"2386 Ridge Rd",
    "sg:city":"Penn Yan",
    "sg:classifiers":[
        {
            "category":"Home & Garden",
            "subcategory":"Furniture",
            "type":"Retail Goods"
        },
        {
            "category":"Building & Trades",
            "subcategory":"Construction",
            "type":"Services"
        }
    ],
    "sg:phone":"+1 315 536 7817",
    "sg:postcode":"14527",
    "sg:province":"NY",
    "sg:tags":[
        "carpentry",
        "contractor"
    ],
    "wof:name":"Pine Ridge Woodworking",
    "wof:placetype":"venue"
},
  "geometry": {"coordinates":[-77.000441,42.648446],"type":"Point"}
}