{
  "type": "Feature",
  "properties": {
    "addr:full":"102 Westchester Ave Port Chester NY 10573",
    "addr:housenumber":"102",
    "addr:postcode":"10573",
    "addr:street":"Westchester Ave",
    "iso:country":"US",
    "sg:address":"102 Westchester Ave",
    "sg:city":"Port Chester",
    "sg:classifiers":[
        {
            "category":"Insurance",
            "subcategory":"Insurance Agent",
            "type":"Services"
        }
    ],
    "sg:phone":"+1 914 939 6000",
    "sg:postcode":"10573",
    "sg:province":"NY",
    "wof:name":"Carlos Insurance",
    "wof:placetype":"venue"
},
  "geometry": {"coordinates":[-73.664298,41.000372],"type":"Point"}
}