{
  "type": "Feature",
  "properties": {
    "addr:full":"437 Madison Ave Fl 40 New York NY 10022",
    "addr:housenumber":"437;40",
    "addr:postcode":"10022",
    "addr:street":"Madison Ave Fl",
    "iso:country":"US",
    "sg:address":"437 Madison Ave Fl 40",
    "sg:city":"New York",
    "sg:classifiers":[
        {
            "category":"Professional",
            "subcategory":"Lawyer & Legal Services",
            "type":"Services"
        }
    ],
    "sg:phone":"+1 212 622 7162",
    "sg:postcode":"10022",
    "sg:province":"NY",
    "wof:name":"Golenbock Eisieman Assoc",
    "wof:placetype":"venue"
},
  "geometry": {"coordinates":[-73.975728,40.757354],"type":"Point"}
}