{
  "type": "Feature",
  "properties": {
    "iso:country":"US",
    "sg:address":"18 Vine Ln",
    "sg:city":"East Northport",
    "sg:classifiers":[
        {
            "category":"Building & Trades",
            "subcategory":"Plumbing",
            "type":"Services"
        }
    ],
    "sg:phone":"+1 631 368 3404",
    "sg:postcode":"11731",
    "sg:province":"NY",
    "sg:tags":[
        "contractor"
    ],
    "wof:name":"Reliable Heating Services",
    "wof:placetype":"venue"
},
  "geometry": {"coordinates":[-73.303963,40.871536],"type":"Point"}
}