{
  "type": "Feature",
  "properties": {
    "addr:full":"2429 Turner Ave Schenectady NY 12306",
    "addr:housenumber":"2429",
    "addr:postcode":"12306",
    "addr:street":"Turner Ave",
    "iso:country":"US",
    "sg:address":"2429 Turner Ave",
    "sg:city":"Schenectady",
    "sg:classifiers":[
        {
            "category":"Restaurant",
            "type":"Food & Drink"
        }
    ],
    "sg:phone":"+1   ",
    "sg:postcode":"12306",
    "sg:province":"NY",
    "sg:tags":[
        "eating"
    ],
    "wof:name":"A JS Restaurant & Pub",
    "wof:placetype":"venue"
},
  "geometry": {"coordinates":[-73.974363,42.799406],"type":"Point"}
}