{
  "type": "Feature",
  "properties": {
    "iso:country":"US",
    "sg:address":"306 North St",
    "sg:city":"Endicott",
    "sg:classifiers":[
        {
            "category":"Retail",
            "subcategory":"Auto Repair",
            "type":"Services"
        }
    ],
    "sg:phone":"+1 607 754 6962",
    "sg:postcode":"13760",
    "sg:province":"NY",
    "sg:tags":[
        "repairing",
        "automobile"
    ],
    "wof:name":"Union Auto Repair",
    "wof:placetype":"venue"
},
  "geometry": {"coordinates":[-76.061589,42.099744],"type":"Point"}
}