{
  "type": "Feature",
  "properties": {
    "addr:full":"18 Sherman St Auburn NY 13021",
    "addr:housenumber":"18",
    "addr:postcode":"13021",
    "addr:street":"Sherman St",
    "iso:country":"US",
    "sg:address":"18 Sherman St",
    "sg:city":"Auburn",
    "sg:classifiers":[
        {
            "category":"Retail",
            "subcategory":"Repair Shop",
            "type":"Services"
        }
    ],
    "sg:phone":"+1 315 253 7914",
    "sg:postcode":"13021",
    "sg:province":"NY",
    "sg:tags":[
        "appliance"
    ],
    "wof:name":"Dello Stritto Appliance Repair",
    "wof:placetype":"venue"
},
  "geometry": {"coordinates":[-76.550999,42.93209],"type":"Point"}
}