{
  "type": "Feature",
  "properties": {
    "iso:country":"US",
    "sg:address":"1050 Clove Rd",
    "sg:city":"Staten Island",
    "sg:classifiers":[
        {
            "category":"Health Services",
            "subcategory":"Doctor",
            "type":"Services"
        }
    ],
    "sg:phone":"+1 718 816 3820",
    "sg:postcode":"10301",
    "sg:province":"NY",
    "sg:tags":[
        "surgeon",
        "cosmetic",
        "dermatologist"
    ],
    "sg:website":"www.simgwecare.com/cosmetic.cfm",
    "wof:name":"Daniel Buchen, MD",
    "wof:placetype":"venue"
},
  "geometry": {"coordinates":[-74.108385,40.619517],"type":"Point"}
}