{
  "type": "Feature",
  "properties": {
    "addr:full":"14 Unity Dr Centereach NY 11720",
    "addr:housenumber":"14",
    "addr:postcode":"11720",
    "addr:street":"Unity Dr",
    "iso:country":"US",
    "sg:address":"14 Unity Dr",
    "sg:city":"Centereach",
    "sg:classifiers":[
        {
            "category":"Building & Trades",
            "subcategory":"Electrical",
            "type":"Services"
        }
    ],
    "sg:phone":"+1 631 588 6601",
    "sg:postcode":"11720",
    "sg:province":"NY",
    "sg:tags":[
        "electrical",
        "contractor"
    ],
    "wof:name":"L & B Electric Co",
    "wof:placetype":"venue"
},
  "geometry": {"coordinates":[-73.082379,40.867403],"type":"Point"}
}