{
  "type": "Feature",
  "properties": {
    "addr:full":"1824 Bronxdale Ave Bronx NY 10462",
    "addr:housenumber":"1824",
    "addr:postcode":"10462",
    "addr:street":"Bronxdale Ave",
    "iso:country":"US",
    "sg:address":"1824 Bronxdale Ave",
    "sg:city":"Bronx",
    "sg:classifiers":[
        {
            "category":"Social Services",
            "type":"Services"
        }
    ],
    "sg:phone":"+1   ",
    "sg:postcode":"10462",
    "sg:province":"NY",
    "wof:name":"Morris Park Community Assn",
    "wof:placetype":"venue"
},
  "geometry": {"coordinates":[-73.860641,40.848358],"type":"Point"}
}