{
  "type": "Feature",
  "properties": {
    "iso:country":"US",
    "sg:address":"34 Altamont Rd",
    "sg:city":"Voorheesville",
    "sg:classifiers":[
        {
            "category":"Autos & Motor Vehicles",
            "subcategory":"Automobile Sales",
            "type":"Retail Goods"
        }
    ],
    "sg:phone":"+1   ",
    "sg:postcode":"12186",
    "sg:province":"NY",
    "sg:tags":[
        "department",
        "used",
        "store"
    ],
    "wof:name":"Ch Auto Sales",
    "wof:placetype":"venue"
},
  "geometry": {"coordinates":[-73.940764,42.652677],"type":"Point"}
}