{
  "type": "Feature",
  "properties": {
    "addr:full":"6 Main St Panama NY 14767",
    "addr:housenumber":"6",
    "addr:postcode":"14767",
    "addr:street":"Main St",
    "iso:country":"US",
    "sg:address":"6 Main St",
    "sg:city":"Panama",
    "sg:classifiers":[
        {
            "category":"Government",
            "subcategory":"Post Office",
            "type":"Public Place"
        }
    ],
    "sg:phone":"+1 716 782 2864",
    "sg:postcode":"14767",
    "sg:province":"NY",
    "wof:name":"US Post Office",
    "wof:placetype":"venue"
},
  "geometry": {"coordinates":[-79.482985,42.074936],"type":"Point"}
}