{
  "type": "Feature",
  "properties": {
    "addr:full":"36 Maiden Lane Rd Oswego NY 13126",
    "addr:housenumber":"36",
    "addr:postcode":"13126",
    "addr:street":"Maiden Lane Rd",
    "iso:country":"US",
    "sg:address":"36 Maiden Lane Rd",
    "sg:city":"Oswego",
    "sg:classifiers":[
        {
            "category":"Farming",
            "subcategory":"Farm",
            "type":"Manufacturing & Wholesale Goods"
        }
    ],
    "sg:phone":"+1 315 342 4879",
    "sg:postcode":"13126",
    "sg:province":"NY",
    "sg:tags":[
        "crop",
        "general"
    ],
    "wof:name":"Elmer Farms",
    "wof:placetype":"venue"
},
  "geometry": {"coordinates":[-76.41315400000001,43.464624],"type":"Point"}
}