{
  "type": "Feature",
  "properties": {
    "addr:full":"1010 Myrtle Ave Bay Shore NY 11706",
    "addr:housenumber":"1010",
    "addr:postcode":"11706",
    "addr:street":"Myrtle Ave",
    "iso:country":"US",
    "sg:address":"1010 Myrtle Ave",
    "sg:city":"Bay Shore",
    "sg:classifiers":[
        {
            "category":"Shopping",
            "type":"Retail Goods"
        }
    ],
    "sg:phone":"+1   ",
    "sg:postcode":"11706",
    "sg:province":"NY",
    "sg:tags":[
        "merchandise"
    ],
    "wof:name":"Ivys Merchandise",
    "wof:placetype":"venue"
},
  "geometry": {"coordinates":[-73.284508,40.71485],"type":"Point"}
}