{
  "type": "Feature",
  "properties": {
    "addr:full":"200 Driving Park Cir Newark NY 14513",
    "addr:housenumber":"200",
    "addr:postcode":"14513",
    "addr:street":"Driving Park Cir",
    "iso:country":"US",
    "sg:address":"200 Driving Park Cir",
    "sg:city":"Newark",
    "sg:classifiers":[
        {
            "category":"Health Services",
            "subcategory":"Nursing And Care Facility",
            "type":"Services"
        }
    ],
    "sg:phone":"+1 315 331 1574",
    "sg:postcode":"14513",
    "sg:province":"NY",
    "sg:tags":[
        "home",
        "retirement",
        "community"
    ],
    "wof:name":"Newark Housing Authority",
    "wof:placetype":"venue"
},
  "geometry": {"coordinates":[-77.101106,43.053982],"type":"Point"}
}