{
  "type": "Feature",
  "properties": {
    "iso:country":"US",
    "sg:address":"111 John St Rm 1070",
    "sg:city":"New York",
    "sg:classifiers":[
        {
            "category":"Professional",
            "subcategory":"Lawyer & Legal Services",
            "type":"Services"
        }
    ],
    "sg:phone":"+1 212 374 9101",
    "sg:postcode":"10038",
    "sg:province":"NY",
    "wof:name":"Brill & Associates PC",
    "wof:placetype":"venue"
},
  "geometry": {"coordinates":[-73.90786300000001,40.707086],"type":"Point"}
}