{
  "type": "Feature",
  "properties": {
    "addr:full":"7002 Main St Flushing NY 11367",
    "addr:housenumber":"7002",
    "addr:postcode":"11367",
    "addr:street":"Main St",
    "iso:country":"US",
    "sg:address":"7002 Main St",
    "sg:city":"Flushing",
    "sg:classifiers":[
        {
            "category":"Health Services",
            "subcategory":"Optometrist",
            "type":"Services"
        }
    ],
    "sg:phone":"+1 718 575 8100",
    "sg:postcode":"11367",
    "sg:province":"NY",
    "sg:website":"www.nextgeneyes.eyemd.org",
    "wof:name":"Admoni Marcel M MD",
    "wof:placetype":"venue"
},
  "geometry": {"coordinates":[-73.823098,40.729082],"type":"Point"}
}