{
  "type": "Feature",
  "properties": {
    "addr:full":"353 Paradise Point Rd Mayfield NY 12117",
    "addr:housenumber":"353",
    "addr:postcode":"12117",
    "addr:street":"Paradise Point Rd",
    "iso:country":"US",
    "sg:address":"353 Paradise Point Rd",
    "sg:city":"Mayfield",
    "sg:classifiers":[
        {
            "category":"Travel",
            "subcategory":"Hotels & Motels",
            "type":"Entertainment"
        },
        {
            "category":"Travel",
            "subcategory":"Resort",
            "type":"Entertainment"
        },
        {
            "category":"Recreation",
            "subcategory":"Campground",
            "type":"Entertainment"
        }
    ],
    "sg:phone":"+1 518 661 6187",
    "sg:postcode":"12117",
    "sg:province":"NY",
    "sg:tags":[
        "lodging",
        "recreational",
        "park",
        "vehicle"
    ],
    "sg:website":"http://www.sunsetbayny.com/",
    "wof:name":"Sunset Bay Vacation Resort",
    "wof:placetype":"venue"
},
  "geometry": {"coordinates":[-74.240182,43.126114],"type":"Point"}
}