{
  "type": "Feature",
  "properties": {
    "iso:country":"US",
    "sg:address":"575 Hoosick St",
    "sg:city":"Troy",
    "sg:classifiers":[
        {
            "category":"Food & Beverages",
            "subcategory":"Groceries & Convenience Stores",
            "type":"Retail Goods"
        }
    ],
    "sg:phone":"+1 518 272 9329",
    "sg:postcode":"12180",
    "sg:province":"NY",
    "wof:name":"Tekbay 99 Mini Mart",
    "wof:placetype":"venue"
},
  "geometry": {"coordinates":[-73.655027,42.741134],"type":"Point"}
}