{
  "type": "Feature",
  "properties": {
    "addr:full":"4105 Ave U Brooklyn NY 11234",
    "addr:housenumber":"4105",
    "addr:postcode":"11234",
    "addr:street":"Ave U",
    "iso:country":"US",
    "sg:address":"4105 Ave U",
    "sg:city":"Brooklyn",
    "sg:classifiers":[
        {
            "category":"Shopping",
            "subcategory":"Florist",
            "type":"Retail Goods"
        }
    ],
    "sg:phone":"+1   ",
    "sg:postcode":"11234",
    "sg:province":"NY",
    "wof:name":"Floral Fantasy Inc",
    "wof:placetype":"venue"
},
  "geometry": {"coordinates":[-73.92344,40.609293],"type":"Point"}
}