{
  "type": "Feature",
  "properties": {
    "addr:full":"7 N Mountain Dr Carmel NY 10522",
    "addr:housenumber":"7",
    "addr:postcode":"10522",
    "addr:street":"N Mountain Dr",
    "iso:country":"US",
    "sg:address":"7 N Mountain Dr",
    "sg:city":"Carmel",
    "sg:classifiers":[
        {
            "category":"Building & Trades",
            "subcategory":"Construction",
            "type":"Services"
        }
    ],
    "sg:phone":"+1 914 277 7300",
    "sg:postcode":"10522",
    "sg:province":"NY",
    "sg:tags":[
        "general",
        "contractor"
    ],
    "wof:name":"Peak Construction",
    "wof:placetype":"venue"
},
  "geometry": {"coordinates":[-73.858001,41.022103],"type":"Point"}
}