{
  "type": "Feature",
  "properties": {
    "addr:full":"206 W 104th St New York NY 10025",
    "addr:housenumber":"206",
    "addr:postcode":"10025",
    "addr:street":"W 104Th St",
    "iso:country":"US",
    "sg:address":"206 W 104th St",
    "sg:city":"New York",
    "sg:classifiers":[
        {
            "category":"Real Estate",
            "subcategory":"Real Estate Agent",
            "type":"Services"
        }
    ],
    "sg:phone":"+1 212 865 7800",
    "sg:postcode":"10025",
    "sg:province":"NY",
    "wof:name":"Bross Real Estate LLC",
    "wof:placetype":"venue"
},
  "geometry": {"coordinates":[-73.968058,40.799617],"type":"Point"}
}