{
  "type": "Feature",
  "properties": {
    "addr:full":"6832 Knight Settlement Rd Bath NY 14810",
    "addr:housenumber":"6832",
    "addr:postcode":"14810",
    "addr:street":"Knight Settlement Rd",
    "iso:country":"US",
    "sg:address":"6832 Knight Settlement Rd",
    "sg:city":"Bath",
    "sg:classifiers":[
        {
            "category":"Travel",
            "subcategory":"Campground",
            "type":"Entertainment"
        }
    ],
    "sg:phone":"+1 607 776 0328",
    "sg:postcode":"14810",
    "sg:province":"NY",
    "wof:name":"Campers Haven",
    "wof:placetype":"venue"
},
  "geometry": {"coordinates":[-77.377849,42.337955],"type":"Point"}
}