{
  "type": "Feature",
  "properties": {
    "iso:country":"US",
    "sg:address":"10 Ronway Dr",
    "sg:city":"Baldwinsville",
    "sg:classifiers":[
        {
            "category":"Communications",
            "subcategory":"Film & Video Production",
            "type":"Services"
        }
    ],
    "sg:phone":"+1   ",
    "sg:postcode":"13027",
    "sg:province":"NY",
    "sg:tags":[
        "motion"
    ],
    "wof:name":"Candlelight Communications",
    "wof:placetype":"venue"
},
  "geometry": {"coordinates":[-76.313497,43.157575],"type":"Point"}
}