{
  "type": "Feature",
  "properties": {
    "addr:full":"6296 Fly Rd East Syracuse NY 13057",
    "addr:housenumber":"6296",
    "addr:postcode":"13057",
    "addr:street":"Fly Rd",
    "iso:country":"US",
    "sg:address":"6296 Fly Rd",
    "sg:city":"East Syracuse",
    "sg:classifiers":[
        {
            "category":"Health Services",
            "subcategory":"Clinic",
            "type":"Services"
        }
    ],
    "sg:phone":"+1 315 295 3000",
    "sg:postcode":"13057",
    "sg:province":"NY",
    "sg:tags":[
        "wellness",
        "program"
    ],
    "wof:name":"Wellness Journies Inc",
    "wof:placetype":"venue"
},
  "geometry": {"coordinates":[-76.057998,43.074781],"type":"Point"}
}