{
  "type": "Feature",
  "properties": {
    "addr:full":"1695 Middle Country Rd Ridge NY 11961",
    "addr:housenumber":"1695",
    "addr:postcode":"11961",
    "addr:street":"Middle Country Rd",
    "iso:country":"US",
    "sg:address":"1695 Middle Country Rd",
    "sg:city":"Ridge",
    "sg:classifiers":[
        {
            "category":"Manufacturing",
            "subcategory":"Glass & Minerals",
            "type":"Manufacturing & Wholesale Goods"
        },
        {
            "category":"Manufacturing",
            "subcategory":"Building Materials",
            "type":"Manufacturing & Wholesale Goods"
        }
    ],
    "sg:phone":"+1 631 924 8575",
    "sg:postcode":"11961",
    "sg:province":"NY",
    "sg:tags":[
        "plate",
        "door",
        "repair",
        "screen",
        "glazier",
        "window",
        "replacement"
    ],
    "wof:name":"Ace Auto Glass",
    "wof:placetype":"venue"
},
  "geometry": {"coordinates":[-72.89805,40.89294],"type":"Point"}
}