{
  "type": "Feature",
  "properties": {
    "addr:full":"73 W Kingsbridge Road Bronx NY 10468",
    "addr:housenumber":"73",
    "addr:postcode":"10468",
    "addr:street":"W Kingsbridge Road",
    "iso:country":"US",
    "sg:address":"73 W Kingsbridge Road",
    "sg:city":"Bronx",
    "sg:classifiers":[
        {
            "category":"Wholesale",
            "subcategory":"Fruits & Vegetables",
            "type":"Manufacturing & Wholesale Goods"
        }
    ],
    "sg:phone":"+1 718 796 1747",
    "sg:postcode":"10468",
    "sg:province":"NY",
    "sg:tags":[
        "veggie"
    ],
    "wof:name":"New Greenway Fruit & Vegetables",
    "wof:placetype":"venue"
},
  "geometry": {"coordinates":[-73.900642,40.868053],"type":"Point"}
}