{
  "type": "Feature",
  "properties": {
    "iso:country":"US",
    "sg:address":"1570 60th St",
    "sg:city":"Brooklyn",
    "sg:classifiers":[
        {
            "category":"Sports & Exercise",
            "subcategory":"Bowling",
            "type":"Entertainment"
        }
    ],
    "sg:phone":"+1 718 331 9000",
    "sg:postcode":"11219",
    "sg:province":"NY",
    "sg:tags":[
        "center"
    ],
    "sg:website":"www.bowlmaple.com/",
    "wof:name":"Maple Lanes",
    "wof:placetype":"venue"
},
  "geometry": {"coordinates":[-73.992203,40.624901],"type":"Point"}
}