{
  "type": "Feature",
  "properties": {
    "addr:full":"132 Nagle Ave New York NY 10040",
    "addr:housenumber":"132",
    "addr:postcode":"10040",
    "addr:street":"Nagle Ave",
    "iso:country":"US",
    "sg:address":"132 Nagle Ave",
    "sg:city":"New York",
    "sg:classifiers":[
        {
            "category":"Restaurant",
            "type":"Food & Drink"
        }
    ],
    "sg:menulink":"http://www.allmenus.com/ny/new-york/47992-new-peking/menu/",
    "sg:phone":"+1 212 942 7287",
    "sg:postcode":"10040",
    "sg:province":"NY",
    "sg:tags":[
        "asian",
        "chinese"
    ],
    "wof:name":"New Peking",
    "wof:placetype":"venue"
},
  "geometry": {"coordinates":[-73.926084,40.861106],"type":"Point"}
}