{
  "type": "Feature",
  "properties": {
    "iso:country":"US",
    "sg:address":"338 Harris Hill Rd",
    "sg:city":"Buffalo",
    "sg:classifiers":[
        {
            "category":"Professional",
            "subcategory":"Detective & Security Services",
            "type":"Services"
        }
    ],
    "sg:phone":"+1 716 631 2100",
    "sg:postcode":"14221",
    "sg:province":"NY",
    "sg:tags":[
        "investigator"
    ],
    "sg:website":"www.pdsainc.com",
    "wof:name":"Philip D Smith & Assoc",
    "wof:placetype":"venue"
},
  "geometry": {"coordinates":[-78.67717399999999,42.949727],"type":"Point"}
}