{
  "type": "Feature",
  "properties": {
    "iso:country":"US",
    "sg:address":"93 Olde Erie Trl",
    "sg:city":"Rochester",
    "sg:classifiers":[
        {
            "category":"Retail",
            "subcategory":"Repair Shop",
            "type":"Services"
        }
    ],
    "sg:phone":"+1   ",
    "sg:postcode":"14626",
    "sg:province":"NY",
    "wof:name":"Carls Prof Sewer & Drain Svc",
    "wof:placetype":"venue"
},
  "geometry": {"coordinates":[-77.685166,43.192593],"type":"Point"}
}