{
  "type": "Feature",
  "properties": {
    "iso:country":"US",
    "sg:address":"1218 Broadway",
    "sg:city":"Hewlett",
    "sg:classifiers":[
        {
            "category":"Banks & Credit Unions",
            "subcategory":"Bank",
            "type":"Services"
        }
    ],
    "sg:phone":"+1 718 935 9935",
    "sg:postcode":"11557",
    "sg:province":"NY",
    "wof:name":"Chase Manhattan Bank",
    "wof:placetype":"venue"
},
  "geometry": {"coordinates":[-73.7033,40.635799],"type":"Point"}
}