{
  "type": "Feature",
  "properties": {
    "addr:full":"145 Goodrich Ave Syracuse NY 13210",
    "addr:housenumber":"145",
    "addr:postcode":"13210",
    "addr:street":"Goodrich Ave",
    "iso:country":"US",
    "sg:address":"145 Goodrich Ave",
    "sg:city":"Syracuse",
    "sg:classifiers":[
        {
            "category":"Real Estate",
            "subcategory":"Real Estate Services",
            "type":"Services"
        },
        {
            "category":"Real Estate",
            "subcategory":"Real Estate Agent",
            "type":"Services"
        }
    ],
    "sg:phone":"+1 315 849 1120",
    "sg:postcode":"13210",
    "sg:province":"NY",
    "sg:tags":[
        "management"
    ],
    "wof:name":"Orangecrest Properties",
    "wof:placetype":"venue"
},
  "geometry": {"coordinates":[-76.127093,43.020527],"type":"Point"}
}