{
  "type": "Feature",
  "properties": {
    "iso:country":"US",
    "sg:address":"6315 S Salina St",
    "sg:city":"Nedrow",
    "sg:classifiers":[
        {
            "category":"Retail",
            "subcategory":"Auto Rental",
            "type":"Services"
        }
    ],
    "sg:phone":"+1 315 498 4410",
    "sg:postcode":"13120",
    "sg:province":"NY",
    "sg:tags":[
        "renting",
        "truck",
        "leasing"
    ],
    "wof:name":"U-Haul Co",
    "wof:placetype":"venue"
},
  "geometry": {"coordinates":[-76.141931,42.97849],"type":"Point"}
}