{
  "type": "Feature",
  "properties": {
    "iso:country":"US",
    "sg:address":"5021 13th Ave",
    "sg:city":"Brooklyn",
    "sg:classifiers":[
        {
            "category":"Travel",
            "subcategory":"Travel Agent",
            "type":"Entertainment"
        }
    ],
    "sg:phone":"+1 718 436 3500",
    "sg:postcode":"11219",
    "sg:province":"NY",
    "sg:tags":[
        "agency",
        "bureau"
    ],
    "wof:name":"Express Travel",
    "wof:placetype":"venue"
},
  "geometry": {"coordinates":[-73.993135,40.633973],"type":"Point"}
}