{
  "type": "Feature",
  "properties": {
    "iso:country":"US",
    "sg:address":"35 Millers Ct",
    "sg:city":"Ronkonkoma",
    "sg:classifiers":[
        {
            "category":"Professional",
            "subcategory":"Business Services",
            "type":"Services"
        }
    ],
    "sg:phone":"+1   ",
    "sg:postcode":"11779",
    "sg:province":"NY",
    "sg:tags":[
        "crane",
        "lift"
    ],
    "wof:name":"High Lift of Long Island Inc",
    "wof:placetype":"venue"
},
  "geometry": {"coordinates":[-73.13225,40.824669],"type":"Point"}
}