{
  "type": "Feature",
  "properties": {
    "iso:country":"US",
    "sg:address":"17 John St",
    "sg:city":"Monticello",
    "sg:classifiers":[
        {
            "category":"Professional",
            "subcategory":"Lawyer & Legal Services",
            "type":"Services"
        }
    ],
    "sg:phone":"+1 845 791 7800",
    "sg:postcode":"12754",
    "sg:province":"NY",
    "sg:tags":[
        "attorney"
    ],
    "wof:name":"Ricciani & Jose",
    "wof:placetype":"venue"
},
  "geometry": {"coordinates":[-74.74513899999999,41.799047],"type":"Point"}
}