{
  "type": "Feature",
  "properties": {
    "addr:full":"57 W 57th St Ste 1209 New York NY 10019",
    "addr:housenumber":"57;1209",
    "addr:postcode":"10019",
    "addr:street":"W 57Th St Ste",
    "iso:country":"US",
    "sg:address":"57 W 57th St Ste 1209",
    "sg:city":"New York",
    "sg:classifiers":[
        {
            "category":"Health Services",
            "subcategory":"Doctor",
            "type":"Services"
        },
        {
            "category":"Health Services",
            "subcategory":"Chiropractor",
            "type":"Services"
        }
    ],
    "sg:phone":"+1 212 583 1110",
    "sg:postcode":"10019",
    "sg:province":"NY",
    "wof:name":"Sports Chiropractic PC",
    "wof:placetype":"venue"
},
  "geometry": {"coordinates":[-73.975899,40.763802],"type":"Point"}
}