{
  "type": "Feature",
  "properties": {
    "addr:full":"41 Van Wagner Rd Willow NY 12495",
    "addr:housenumber":"41",
    "addr:postcode":"12495",
    "addr:street":"Van Wagner Rd",
    "iso:country":"US",
    "sg:address":"41 Van Wagner Rd",
    "sg:city":"Willow",
    "sg:classifiers":[
        {
            "category":"Government",
            "subcategory":"Post Office",
            "type":"Public Place"
        }
    ],
    "sg:phone":"+1 845 679 6767",
    "sg:postcode":"12495",
    "sg:province":"NY",
    "wof:name":"US Post Office",
    "wof:placetype":"venue"
},
  "geometry": {"coordinates":[-74.22411700000001,42.073185],"type":"Point"}
}