{
  "type": "Feature",
  "properties": {
    "iso:country":"US",
    "sg:address":"67 Merrick Ave",
    "sg:city":"Merrick",
    "sg:classifiers":[
        {
            "category":"Shopping",
            "subcategory":"Clothing, Apparel, & Fashions",
            "type":"Retail Goods"
        }
    ],
    "sg:phone":"+1 516 377 1127",
    "sg:postcode":"11566",
    "sg:province":"NY",
    "sg:tags":[
        "children's",
        "clothing"
    ],
    "sg:website":"www.cathystouch.com",
    "wof:name":"Cathy's Touch",
    "wof:placetype":"venue"
},
  "geometry": {"coordinates":[-73.56559799999999,40.6968],"type":"Point"}
}