{
  "type": "Feature",
  "properties": {
    "iso:country":"US",
    "sg:address":"199 New Scotland Ave",
    "sg:city":"Albany",
    "sg:classifiers":[
        {
            "category":"Education",
            "subcategory":"Special Training",
            "type":"Public Place"
        }
    ],
    "sg:phone":"+1 518 459 0065",
    "sg:postcode":"12208",
    "sg:province":"NY",
    "sg:tags":[
        "educational"
    ],
    "wof:name":"Jewish Educational Resources",
    "wof:placetype":"venue"
},
  "geometry": {"coordinates":[-73.78498999999999,42.65295],"type":"Point"}
}