{
  "type": "Feature",
  "properties": {
    "iso:country":"US",
    "sg:address":"5688 Martz Rd",
    "sg:city":"Farmington",
    "sg:classifiers":[
        {
            "category":"Retail",
            "subcategory":"Laundry & Dry Cleaning",
            "type":"Services"
        }
    ],
    "sg:phone":"+1 585 924 9110",
    "sg:postcode":"14425",
    "sg:province":"NY",
    "sg:tags":[
        "cleaners",
        "rug",
        "carpet"
    ],
    "wof:name":"J P Svc",
    "wof:placetype":"venue"
},
  "geometry": {"coordinates":[-77.328569,43.012176],"type":"Point"}
}