{
  "type": "Feature",
  "properties": {
    "iso:country":"US",
    "sg:address":"25 Pleasant St",
    "sg:city":"Rochester",
    "sg:classifiers":[
        {
            "category":"Professional",
            "subcategory":"Lawyer & Legal Services",
            "type":"Services"
        }
    ],
    "sg:phone":"+1 585 325 1410",
    "sg:postcode":"14604",
    "sg:province":"NY",
    "sg:tags":[
        "attorney"
    ],
    "wof:name":"Passero & Meserve",
    "wof:placetype":"venue"
},
  "geometry": {"coordinates":[-77.60336599999999,43.159608],"type":"Point"}
}