{
  "type": "Feature",
  "properties": {
    "addr:full":"485 Mount Airy Rd New Windsor NY 12553",
    "addr:housenumber":"485",
    "addr:postcode":"12553",
    "addr:street":"Mount Airy Rd",
    "iso:country":"US",
    "sg:address":"485 Mount Airy Rd",
    "sg:city":"New Windsor",
    "sg:classifiers":[
        {
            "category":"Organizations",
            "subcategory":"Religious Organization",
            "type":"Services"
        }
    ],
    "sg:phone":"+1 845 564 6785",
    "sg:postcode":"12553",
    "sg:province":"NY",
    "sg:tags":[
        "church"
    ],
    "wof:name":"Lds Family History Ctr",
    "wof:placetype":"venue"
},
  "geometry": {"coordinates":[-74.08548,41.462164],"type":"Point"}
}