{
  "type": "Feature",
  "properties": {
    "addr:full":"11 Grand St New York NY 10013",
    "addr:housenumber":"11",
    "addr:postcode":"10013",
    "addr:street":"Grand St",
    "iso:country":"US",
    "sg:address":"11 Grand St",
    "sg:city":"New York",
    "sg:classifiers":[
        {
            "category":"Communications",
            "type":"Services"
        }
    ],
    "sg:phone":"+1 212 431 3290",
    "sg:postcode":"10013",
    "sg:province":"NY",
    "sg:tags":[
        "web",
        "design"
    ],
    "wof:name":"B T N Model Management Inc",
    "wof:placetype":"venue"
},
  "geometry": {"coordinates":[-74.005402,40.723099],"type":"Point"}
}