{
  "type": "Feature",
  "properties": {
    "addr:full":"1551 Sheridan Ave Bronx NY 10457",
    "addr:housenumber":"1551",
    "addr:postcode":"10457",
    "addr:street":"Sheridan Ave",
    "iso:country":"US",
    "sg:address":"1551 Sheridan Ave",
    "sg:city":"Bronx",
    "sg:classifiers":[
        {
            "category":"Food & Beverages",
            "subcategory":"Groceries & Convenience Stores",
            "type":"Retail Goods"
        }
    ],
    "sg:phone":"+1 718 299 9141",
    "sg:postcode":"10457",
    "sg:province":"NY",
    "sg:tags":[
        "grocer"
    ],
    "wof:name":"Kirssis Grocery",
    "wof:placetype":"venue"
},
  "geometry": {"coordinates":[-73.911253,40.841856],"type":"Point"}
}