{
  "type": "Feature",
  "properties": {
    "iso:country":"US",
    "sg:address":"357 Quentin Rd",
    "sg:city":"Brooklyn",
    "sg:classifiers":[
        {
            "category":"Wholesale",
            "subcategory":"Drugs",
            "type":"Manufacturing & Wholesale Goods"
        }
    ],
    "sg:phone":"+1 718 998 2589",
    "sg:postcode":"11223",
    "sg:province":"NY",
    "sg:tags":[
        "merchandise"
    ],
    "wof:name":"Licks",
    "wof:placetype":"venue"
},
  "geometry": {"coordinates":[-73.97331200000001,40.606641],"type":"Point"}
}