{
  "type": "Feature",
  "properties": {
    "addr:full":"1234 Broadway New York NY 10001",
    "addr:housenumber":"1234",
    "addr:postcode":"10001",
    "addr:street":"Broadway",
    "iso:country":"US",
    "sg:address":"1234 Broadway",
    "sg:city":"New York",
    "sg:classifiers":[
        {
            "category":"Retail",
            "subcategory":"Repair Shop",
            "type":"Services"
        }
    ],
    "sg:phone":"+1 212 695 8837",
    "sg:postcode":"10001",
    "sg:province":"NY",
    "sg:tags":[
        "watch"
    ],
    "wof:name":"M & A Watches",
    "wof:placetype":"venue"
},
  "geometry": {"coordinates":[-73.988317,40.746944],"type":"Point"}
}