{
  "type": "Feature",
  "properties": {
    "iso:country":"US",
    "sg:address":"9 N Chestnut St",
    "sg:city":"New Paltz",
    "sg:classifiers":[
        {
            "category":"Retail",
            "subcategory":"Repair Shop",
            "type":"Services"
        }
    ],
    "sg:phone":"+1 845 255 6615",
    "sg:postcode":"12561",
    "sg:province":"NY",
    "sg:tags":[
        "lock",
        "locksmith"
    ],
    "wof:name":"Allied Locksmiths",
    "wof:placetype":"venue"
},
  "geometry": {"coordinates":[-74.087,41.747723],"type":"Point"}
}