{
  "type": "Feature",
  "properties": {
    "iso:country":"US",
    "sg:address":"3 Virginia Rd",
    "sg:city":"Centereach",
    "sg:classifiers":[
        {
            "category":"Local Transit",
            "type":"Transportation"
        }
    ],
    "sg:phone":"+1   ",
    "sg:postcode":"11720",
    "sg:province":"NY",
    "sg:tags":[
        "passenger"
    ],
    "wof:name":"American Luxury Limousine Inc",
    "wof:placetype":"venue"
},
  "geometry": {"coordinates":[-73.0831,40.868901],"type":"Point"}
}