{
  "type": "Feature",
  "properties": {
    "addr:full":"508 N Carroll St Horseheads NY 14845",
    "addr:housenumber":"508",
    "addr:postcode":"14845",
    "addr:street":"N Carroll St",
    "iso:country":"US",
    "sg:address":"508 N Carroll St",
    "sg:city":"Horseheads",
    "sg:classifiers":[
        {
            "category":"Real Estate",
            "subcategory":"Real Estate Services",
            "type":"Services"
        },
        {
            "category":"Building & Trades",
            "subcategory":"Cleaning & Sanitation",
            "type":"Services"
        },
        {
            "category":"Building & Trades",
            "subcategory":"Construction",
            "type":"Services"
        }
    ],
    "sg:phone":"+1 607 738 8584",
    "sg:postcode":"14845",
    "sg:province":"NY",
    "sg:tags":[
        "altering",
        "cleaners-interior",
        "remodeling",
        "maintenance",
        "contractor"
    ],
    "wof:name":"Margeson Holding",
    "wof:placetype":"venue"
},
  "geometry": {"coordinates":[-76.82462200000001,42.164531],"type":"Point"}
}