{
  "type": "Feature",
  "properties": {
    "addr:full":"5102 6th Ave Brooklyn NY 11220",
    "addr:housenumber":"5102",
    "addr:postcode":"11220",
    "addr:street":"6Th Ave",
    "iso:country":"US",
    "sg:address":"5102 6th Ave",
    "sg:city":"Brooklyn",
    "sg:classifiers":[
        {
            "category":"Real Estate",
            "subcategory":"Architect",
            "type":"Services"
        }
    ],
    "sg:phone":"+1 718 853 2410",
    "sg:postcode":"11220",
    "sg:province":"NY",
    "sg:tags":[
        "specification",
        "architectural"
    ],
    "wof:name":"All Renovation Constr Corp",
    "wof:placetype":"venue"
},
  "geometry": {"coordinates":[-74.009331,40.642715],"type":"Point"}
}