{
  "type": "Feature",
  "properties": {
    "addr:full":"28 Water St Dundee NY 14837",
    "addr:housenumber":"28",
    "addr:postcode":"14837",
    "addr:street":"Water St",
    "iso:country":"US",
    "sg:address":"28 Water St",
    "sg:city":"Dundee",
    "sg:classifiers":[
        {
            "category":"Sports & Exercise",
            "subcategory":"Bowling",
            "type":"Entertainment"
        }
    ],
    "sg:phone":"+1 607 243 5940",
    "sg:postcode":"14837",
    "sg:province":"NY",
    "sg:tags":[
        "center"
    ],
    "wof:name":"Dundee Family Fun Center",
    "wof:placetype":"venue"
},
  "geometry": {"coordinates":[-76.97696500000001,42.52357],"type":"Point"}
}