{
  "type": "Feature",
  "properties": {
    "addr:full":"182 Trelawne Dr Rochester NY 14622",
    "addr:housenumber":"182",
    "addr:postcode":"14622",
    "addr:street":"Trelawne Dr",
    "iso:country":"US",
    "sg:address":"182 Trelawne Dr",
    "sg:city":"Rochester",
    "sg:classifiers":[
        {
            "category":"Building & Trades",
            "subcategory":"Construction",
            "type":"Services"
        }
    ],
    "sg:phone":"+1 585 323 1894",
    "sg:postcode":"14622",
    "sg:province":"NY",
    "sg:tags":[
        "hanging",
        "mill",
        "paper",
        "contractor"
    ],
    "wof:name":"Colleen Rothfuss",
    "wof:placetype":"venue"
},
  "geometry": {"coordinates":[-77.549224,43.23281],"type":"Point"}
}