{
  "type": "Feature",
  "properties": {
    "iso:country":"US",
    "sg:address":"20 W 22 St",
    "sg:city":"New York",
    "sg:classifiers":[
        {
            "category":"Professional",
            "subcategory":"Business Services",
            "type":"Services"
        }
    ],
    "sg:phone":"+1 212 414 4923",
    "sg:postcode":"10010",
    "sg:province":"NY",
    "sg:tags":[
        "literary",
        "agent"
    ],
    "wof:name":"Anne Edelstein Literary Agency",
    "wof:placetype":"venue"
},
  "geometry": {"coordinates":[-73.99287099999999,40.741914],"type":"Point"}
}