{
  "type": "Feature",
  "properties": {
    "addr:full":"95 Beekman Ave Sleepy Hollow NY 10591",
    "addr:housenumber":"95",
    "addr:postcode":"10591",
    "addr:street":"Beekman Ave",
    "iso:country":"US",
    "sg:address":"95 Beekman Ave",
    "sg:city":"Sleepy Hollow",
    "sg:classifiers":[
        {
            "category":"Professional",
            "subcategory":"Lawyer & Legal Services",
            "type":"Services"
        }
    ],
    "sg:phone":"+1 914 631 9214",
    "sg:postcode":"10591",
    "sg:province":"NY",
    "sg:tags":[
        "attorney"
    ],
    "wof:name":"Jessica A Hugel Esq",
    "wof:placetype":"venue"
},
  "geometry": {"coordinates":[-73.862601,41.084185],"type":"Point"}
}