{
  "type": "Feature",
  "properties": {
    "addr:full":"20 McCulloch Dr Dix Hills NY 11746",
    "addr:housenumber":"20",
    "addr:postcode":"11746",
    "addr:street":"Mcculloch Dr",
    "iso:country":"US",
    "sg:address":"20 McCulloch Dr",
    "sg:city":"Dix Hills",
    "sg:classifiers":[
        {
            "category":"Shopping",
            "type":"Retail Goods"
        }
    ],
    "sg:phone":"+1 516 333 5507",
    "sg:postcode":"11746",
    "sg:province":"NY",
    "sg:tags":[
        "equipment",
        "telephone",
        "supply"
    ],
    "wof:name":"Tcs Corp",
    "wof:placetype":"venue"
},
  "geometry": {"coordinates":[-73.311797,40.818197],"type":"Point"}
}