{
  "type": "Feature",
  "properties": {
    "addr:full":"308 State Rte 14A Penn Yan NY 14527",
    "addr:housenumber":"308",
    "addr:postcode":"14527",
    "addr:street":"State Rte 14A",
    "iso:country":"US",
    "sg:address":"308 State Rte 14A",
    "sg:city":"Penn Yan",
    "sg:classifiers":[
        {
            "category":"Home & Garden",
            "subcategory":"Home Furnishings",
            "type":"Retail Goods"
        }
    ],
    "sg:phone":"+1 315 536 7839",
    "sg:postcode":"14527",
    "sg:province":"NY",
    "sg:tags":[
        "window",
        "treatment"
    ],
    "wof:name":"Douglas Hunter Window Fashions",
    "wof:placetype":"venue"
},
  "geometry": {"coordinates":[-77.06749600000001,42.749519],"type":"Point"}
}