{
  "type": "Feature",
  "properties": {
    "iso:country":"US",
    "sg:address":"6520 Ridge Rd",
    "sg:city":"Lockport",
    "sg:classifiers":[
        {
            "category":"Retail",
            "subcategory":"Auto Repair",
            "type":"Services"
        }
    ],
    "sg:phone":"+1 716 439 0013",
    "sg:postcode":"14094",
    "sg:province":"NY",
    "sg:tags":[
        "wrecker"
    ],
    "wof:name":"Shane's Towing",
    "wof:placetype":"venue"
},
  "geometry": {"coordinates":[-78.66867999999999,43.234091],"type":"Point"}
}