{
  "type": "Feature",
  "properties": {
    "addr:full":"3 Lee Dr Airmont NY 10952",
    "addr:housenumber":"3",
    "addr:postcode":"10952",
    "addr:street":"Lee Dr",
    "iso:country":"US",
    "sg:address":"3 Lee Dr",
    "sg:city":"Airmont",
    "sg:classifiers":[
        {
            "category":"Social Services",
            "subcategory":"Adult Care",
            "type":"Services"
        }
    ],
    "sg:phone":"+1 845 352 2135",
    "sg:postcode":"10952",
    "sg:province":"NY",
    "sg:tags":[
        "home",
        "group"
    ],
    "sg:website":"www.campventure.org",
    "wof:name":"Venture/Camp Venture",
    "wof:placetype":"venue"
},
  "geometry": {"coordinates":[-74.081913,41.098696],"type":"Point"}
}