{
  "type": "Feature",
  "properties": {
    "iso:country":"US",
    "sg:address":"901 E 107th St",
    "sg:city":"Brooklyn",
    "sg:classifiers":[
        {
            "category":"Shopping",
            "subcategory":"Discount & Variety Stores",
            "type":"Retail Goods"
        }
    ],
    "sg:phone":"+1 718 345 9205",
    "sg:postcode":"11236",
    "sg:province":"NY",
    "wof:name":"Dollar Flatland Inc",
    "wof:placetype":"venue"
},
  "geometry": {"coordinates":[-73.89143199999999,40.646781],"type":"Point"}
}