{
  "type": "Feature",
  "properties": {
    "addr:full":"3912 Baychester Ave Bronx NY 10466",
    "addr:housenumber":"3912",
    "addr:postcode":"10466",
    "addr:street":"Baychester Ave",
    "iso:country":"US",
    "sg:address":"3912 Baychester Ave",
    "sg:city":"Bronx",
    "sg:classifiers":[
        {
            "category":"Real Estate",
            "subcategory":"Real Estate Agent",
            "type":"Services"
        }
    ],
    "sg:phone":"+1 718 994 8610",
    "sg:postcode":"10466",
    "sg:province":"NY",
    "wof:name":"Makal Realty Inc",
    "wof:placetype":"venue"
},
  "geometry": {"coordinates":[-73.84247499999999,40.889974],"type":"Point"}
}