{
  "type": "Feature",
  "properties": {
    "addr:full":"4382 162nd Street Flushing NY 11358",
    "addr:housenumber":"4382",
    "addr:postcode":"11358",
    "addr:street":"162Nd Street",
    "iso:country":"US",
    "sg:address":"4382 162nd Street",
    "sg:city":"Flushing",
    "sg:classifiers":[
        {
            "category":"Food & Beverages",
            "subcategory":"Groceries & Convenience Stores",
            "type":"Retail Goods"
        }
    ],
    "sg:phone":"+1 718 461 3434",
    "sg:postcode":"11358",
    "sg:province":"NY",
    "wof:name":"Happy Convenience Store",
    "wof:placetype":"venue"
},
  "geometry": {"coordinates":[-73.804501,40.757657],"type":"Point"}
}