{
  "type": "Feature",
  "properties": {
    "addr:full":"140 Co Rte 57 Phoenix NY 13135",
    "addr:housenumber":"140",
    "addr:postcode":"13135",
    "addr:street":"Co Rte 57",
    "iso:country":"US",
    "sg:address":"140 Co Rte 57",
    "sg:city":"Phoenix",
    "sg:classifiers":[
        {
            "category":"Travel",
            "subcategory":"Travel Agent",
            "type":"Entertainment"
        }
    ],
    "sg:phone":"+1   ",
    "sg:postcode":"13135",
    "sg:province":"NY",
    "sg:tags":[
        "operator",
        "tour"
    ],
    "wof:name":"Morgans Tours",
    "wof:placetype":"venue"
},
  "geometry": {"coordinates":[-76.28076299999999,43.208554],"type":"Point"}
}