{
  "type": "Feature",
  "properties": {
    "addr:full":"788 Tonawanda St Buffalo NY 14207",
    "addr:housenumber":"788",
    "addr:postcode":"14207",
    "addr:street":"Tonawanda St",
    "iso:country":"US",
    "sg:address":"788 Tonawanda St",
    "sg:city":"Buffalo",
    "sg:classifiers":[
        {
            "category":"Banks & Credit Unions",
            "subcategory":"Bank",
            "type":"Services"
        }
    ],
    "sg:phone":"+1 716 626 6611",
    "sg:postcode":"14207",
    "sg:province":"NY",
    "wof:name":"M & T Bank",
    "wof:placetype":"venue"
},
  "geometry": {"coordinates":[-78.903999,42.950298],"type":"Point"}
}