{
  "type": "Feature",
  "properties": {
    "addr:full":"5419 6th Avenue Brooklyn NY 11220",
    "addr:housenumber":"5419",
    "addr:postcode":"11220",
    "addr:street":"6Th Avenue",
    "iso:country":"US",
    "sg:address":"5419 6th Avenue",
    "sg:city":"Brooklyn",
    "sg:classifiers":[
        {
            "category":"Organizations",
            "subcategory":"Religious Organization",
            "type":"Services"
        }
    ],
    "sg:phone":"+1 718 686 7344",
    "sg:postcode":"11220",
    "sg:province":"NY",
    "wof:name":"Church of Grace To Fujianese N Y",
    "wof:placetype":"venue"
},
  "geometry": {"coordinates":[-74.01052,40.641423],"type":"Point"}
}