{
  "type": "Feature",
  "properties": {
    "addr:full":"152 Mamaroneck Ave Mamaroneck NY 10543",
    "addr:housenumber":"152",
    "addr:postcode":"10543",
    "addr:street":"Mamaroneck Ave",
    "iso:country":"US",
    "sg:address":"152 Mamaroneck Ave",
    "sg:city":"Mamaroneck",
    "sg:classifiers":[
        {
            "category":"Personal",
            "subcategory":"Beauty Salon",
            "type":"Services"
        }
    ],
    "sg:phone":"+1   ",
    "sg:postcode":"10543",
    "sg:province":"NY",
    "sg:tags":[
        "shop"
    ],
    "wof:name":"Village Nails",
    "wof:placetype":"venue"
},
  "geometry": {"coordinates":[-73.73329099999999,40.949194],"type":"Point"}
}