{
  "type": "Feature",
  "properties": {
    "iso:country":"US",
    "sg:address":"206 Fulton Ave",
    "sg:city":"Hempstead",
    "sg:classifiers":[
        {
            "category":"Banks & Credit Unions",
            "subcategory":"Bank",
            "type":"Services"
        }
    ],
    "sg:phone":"+1 516 481 7780",
    "sg:postcode":"11550",
    "sg:province":"NY",
    "sg:tags":[
        "finance"
    ],
    "wof:name":"Beneficial",
    "wof:placetype":"venue"
},
  "geometry": {"coordinates":[-73.62698899999999,40.707657],"type":"Point"}
}