{
  "type": "Feature",
  "properties": {
    "iso:country":"US",
    "sg:address":"80 Ladd Ave",
    "sg:city":"Staten Island",
    "sg:classifiers":[
        {
            "category":"Building & Trades",
            "subcategory":"Plumbing",
            "type":"Services"
        }
    ],
    "sg:phone":"+1 718 227 1989",
    "sg:postcode":"10312",
    "sg:province":"NY",
    "sg:tags":[
        "conditioning",
        "air",
        "system",
        "contractor"
    ],
    "wof:name":"Expert Service",
    "wof:placetype":"venue"
},
  "geometry": {"coordinates":[-74.175292,40.561225],"type":"Point"}
}