{
  "type": "Feature",
  "properties": {
    "addr:full":"48 Jones Dr Highland Mills NY 10930",
    "addr:housenumber":"48",
    "addr:postcode":"10930",
    "addr:street":"Jones Dr",
    "iso:country":"US",
    "sg:address":"48 Jones Dr",
    "sg:city":"Highland Mills",
    "sg:classifiers":[
        {
            "category":"Building & Trades",
            "subcategory":"Plumbing",
            "type":"Services"
        }
    ],
    "sg:phone":"+1 845 928 7548",
    "sg:postcode":"10930",
    "sg:province":"NY",
    "sg:tags":[
        "contractor"
    ],
    "wof:name":"Finest Plumbing",
    "wof:placetype":"venue"
},
  "geometry": {"coordinates":[-74.132411,41.358902],"type":"Point"}
}