{
  "type": "Feature",
  "properties": {
    "addr:full":"945 Amsterdam Ave Frnt 1 New York NY 10025",
    "addr:housenumber":"945;1",
    "addr:postcode":"10025",
    "addr:street":"Amsterdam Ave Frnt",
    "iso:country":"US",
    "sg:address":"945 Amsterdam Ave Frnt 1",
    "sg:city":"New York",
    "sg:classifiers":[
        {
            "category":"Deli",
            "type":"Food & Drink"
        },
        {
            "category":"Food & Beverages",
            "subcategory":"Bakery",
            "type":"Retail Goods"
        }
    ],
    "sg:phone":"+1 212 665 6410",
    "sg:postcode":"10025",
    "sg:province":"NY",
    "sg:tags":[
        "sandwich"
    ],
    "wof:name":"Columbia Deli Inc",
    "wof:placetype":"venue"
},
  "geometry": {"coordinates":[-73.96545500000001,40.800514],"type":"Point"}
}