{
  "type": "Feature",
  "properties": {
    "iso:country":"US",
    "sg:address":"155 Arizona Rd N",
    "sg:city":"West Babylon",
    "sg:classifiers":[
        {
            "category":"Shopping",
            "subcategory":"Clothing, Apparel, & Fashions",
            "type":"Retail Goods"
        }
    ],
    "sg:phone":"+1 631 643 3029",
    "sg:postcode":"11704",
    "sg:province":"NY",
    "wof:name":"S & B Handbags & Clothing",
    "wof:placetype":"venue"
},
  "geometry": {"coordinates":[-73.365517,40.732318],"type":"Point"}
}