{
  "type": "Feature",
  "properties": {
    "iso:country":"US",
    "sg:address":"137 E Lynde St",
    "sg:city":"Watertown",
    "sg:classifiers":[
        {
            "category":"Organizations",
            "subcategory":"Membership Organization",
            "type":"Services"
        }
    ],
    "sg:phone":"+1 315 786 8852",
    "sg:postcode":"13601",
    "sg:province":"NY",
    "wof:name":"Disabled Persons Action Orgnz",
    "wof:placetype":"venue"
},
  "geometry": {"coordinates":[-75.904639,43.980907],"type":"Point"}
}