{
  "type": "Feature",
  "properties": {
    "iso:country":"US",
    "sg:address":"509 5th Ave Fl 6",
    "sg:city":"New York",
    "sg:classifiers":[
        {
            "category":"Professional",
            "subcategory":"Accounting & Tax Preparation",
            "type":"Services"
        }
    ],
    "sg:phone":"+1 212 599 4600",
    "sg:postcode":"10017",
    "sg:province":"NY",
    "sg:tags":[
        "accountant"
    ],
    "wof:name":"Oshima Saito Llp",
    "wof:placetype":"venue"
},
  "geometry": {"coordinates":[-73.98041499999999,40.753772],"type":"Point"}
}