{
  "type": "Feature",
  "properties": {
    "iso:country":"US",
    "sg:address":"15 Lockhart Ln",
    "sg:city":"Highland",
    "sg:classifiers":[
        {
            "category":"Retail",
            "subcategory":"Repair Shop",
            "type":"Services"
        }
    ],
    "sg:phone":"+1   ",
    "sg:postcode":"12528",
    "sg:province":"NY",
    "sg:tags":[
        "electrical"
    ],
    "wof:name":"Prestige Electric",
    "wof:placetype":"venue"
},
  "geometry": {"coordinates":[-73.964438,41.724953],"type":"Point"}
}