{
  "type": "Feature",
  "properties": {
    "iso:country":"US",
    "sg:address":"118 Main St",
    "sg:city":"Geneseo",
    "sg:classifiers":[
        {
            "category":"Personal",
            "subcategory":"Beauty Salon",
            "type":"Services"
        }
    ],
    "sg:phone":"+1 585 243 5766",
    "sg:postcode":"14454",
    "sg:province":"NY",
    "wof:name":"Kerry's Cut Above",
    "wof:placetype":"venue"
},
  "geometry": {"coordinates":[-77.817046,42.795112],"type":"Point"}
}