{
  "type": "Feature",
  "properties": {
    "addr:full":"20 Hampton Rd Southampton NY 11968",
    "addr:housenumber":"20",
    "addr:postcode":"11968",
    "addr:street":"Hampton Rd",
    "iso:country":"US",
    "sg:address":"20 Hampton Rd",
    "sg:city":"Southampton",
    "sg:classifiers":[
        {
            "category":"Health Services",
            "subcategory":"Clinic",
            "type":"Services"
        }
    ],
    "sg:phone":"+1 631 204 1219",
    "sg:postcode":"11968",
    "sg:province":"NY",
    "sg:tags":[
        "wellness",
        "program"
    ],
    "wof:name":"Ananda Wellness Ctr & Boutique",
    "wof:placetype":"venue"
},
  "geometry": {"coordinates":[-72.38905200000001,40.887144],"type":"Point"}
}