{
  "type": "Feature",
  "properties": {
    "iso:country":"US",
    "sg:address":"660 Old Country Rd",
    "sg:city":"Garden City",
    "sg:classifiers":[
        {
            "category":"Professional",
            "subcategory":"Lawyer & Legal Services",
            "type":"Services"
        }
    ],
    "sg:phone":"+1 212 964 2702",
    "sg:postcode":"11530",
    "sg:province":"NY",
    "wof:name":"Keating Kevin",
    "wof:placetype":"venue"
},
  "geometry": {"coordinates":[-73.614116,40.743021],"type":"Point"}
}