{
  "type": "Feature",
  "properties": {
    "iso:country":"US",
    "sg:address":"5880 Bartlett Rd",
    "sg:city":"Rome",
    "sg:classifiers":[
        {
            "category":"Manufacturing",
            "subcategory":"Tools & Machinery",
            "type":"Manufacturing & Wholesale Goods"
        }
    ],
    "sg:phone":"+1   ",
    "sg:postcode":"13490",
    "sg:province":"NY",
    "sg:tags":[
        "devices",
        "mfg"
    ],
    "wof:name":"HCI Engineering",
    "wof:placetype":"venue"
},
  "geometry": {"coordinates":[-75.43935999999999,43.144675],"type":"Point"}
}