{
  "type": "Feature",
  "properties": {
    "iso:country":"US",
    "sg:address":"1550 Sunrise Hwy",
    "sg:city":"Copiague",
    "sg:classifiers":[
        {
            "category":"Building & Trades",
            "subcategory":"Construction",
            "type":"Services"
        },
        {
            "category":"Home & Garden",
            "subcategory":"Furniture",
            "type":"Retail Goods"
        }
    ],
    "sg:phone":"+1 631 789 5956",
    "sg:postcode":"11726",
    "sg:province":"NY",
    "sg:tags":[
        "top",
        "counter",
        "contractor"
    ],
    "wof:name":"King Tops Sales Co",
    "wof:placetype":"venue"
},
  "geometry": {"coordinates":[-73.397688,40.692426],"type":"Point"}
}