{
  "type": "Feature",
  "properties": {
    "addr:full":"6 Jeanne Dr Newburgh NY 12550",
    "addr:housenumber":"6",
    "addr:postcode":"12550",
    "addr:street":"Jeanne Dr",
    "iso:country":"US",
    "sg:address":"6 Jeanne Dr",
    "sg:city":"Newburgh",
    "sg:classifiers":[
        {
            "category":"Professional",
            "subcategory":"Lawyer & Legal Services",
            "type":"Services"
        }
    ],
    "sg:phone":"+1 845 566 8888",
    "sg:postcode":"12550",
    "sg:province":"NY",
    "sg:tags":[
        "personal",
        "injury"
    ],
    "wof:name":"Hankin Hanig Stall Caplicki & Curtin Llp",
    "wof:placetype":"venue"
},
  "geometry": {"coordinates":[-74.061302,41.542702],"type":"Point"}
}