{
  "type": "Feature",
  "properties": {
    "addr:full":"31 Wilbur Ln Roosevelt NY 11575",
    "addr:housenumber":"31",
    "addr:postcode":"11575",
    "addr:street":"Wilbur Ln",
    "iso:country":"US",
    "sg:address":"31 Wilbur Ln",
    "sg:city":"Roosevelt",
    "sg:classifiers":[
        {
            "category":"Autos & Motor Vehicles",
            "subcategory":"Fuel & Gas Station",
            "type":"Retail Goods"
        }
    ],
    "sg:phone":"+1 516 868 2429",
    "sg:postcode":"11575",
    "sg:province":"NY",
    "sg:website":"www.bigafuel.com",
    "wof:name":"Big A Fuel & Oil",
    "wof:placetype":"venue"
},
  "geometry": {"coordinates":[-73.60104,40.684749],"type":"Point"}
}