{
  "type": "Feature",
  "properties": {
    "addr:full":"15724 22nd Ave Whitestone NY 11357",
    "addr:housenumber":"15724",
    "addr:postcode":"11357",
    "addr:street":"22Nd Ave",
    "iso:country":"US",
    "sg:address":"15724 22nd Ave",
    "sg:city":"Whitestone",
    "sg:classifiers":[
        {
            "category":"Autos & Motor Vehicles",
            "subcategory":"Automobile Sales",
            "type":"Retail Goods"
        }
    ],
    "sg:phone":"+1 718 738 3543",
    "sg:postcode":"11357",
    "sg:province":"NY",
    "sg:tags":[
        "limo"
    ],
    "wof:name":"Lexington Limousine & Transportation Svc",
    "wof:placetype":"venue"
},
  "geometry": {"coordinates":[-73.80590100000001,40.778099],"type":"Point"}
}