{
  "type": "Feature",
  "properties": {
    "iso:country":"US",
    "sg:address":"24 N Broadway",
    "sg:city":"Yonkers",
    "sg:classifiers":[
        {
            "category":"Travel",
            "subcategory":"Travel Agent",
            "type":"Entertainment"
        }
    ],
    "sg:phone":"+1 914 423 8100",
    "sg:postcode":"10701",
    "sg:province":"NY",
    "sg:tags":[
        "agency",
        "bureau"
    ],
    "wof:name":"Cisnes Travel & Variedades",
    "wof:placetype":"venue"
},
  "geometry": {"coordinates":[-73.898005,40.93358],"type":"Point"}
}