{
  "type": "Feature",
  "properties": {
    "addr:full":"209 Havemeyer St Brooklyn NY 11211",
    "addr:housenumber":"209",
    "addr:postcode":"11211",
    "addr:street":"Havemeyer St",
    "iso:country":"US",
    "sg:address":"209 Havemeyer St",
    "sg:city":"Brooklyn",
    "sg:classifiers":[
        {
            "category":"Banks & Credit Unions",
            "subcategory":"Bank",
            "type":"Services"
        }
    ],
    "sg:phone":"+1 718 782 6200",
    "sg:postcode":"11211",
    "sg:province":"NY",
    "wof:name":"Dime Savings Bank of Williamsburg",
    "wof:placetype":"venue"
},
  "geometry": {"coordinates":[-73.95819899999999,40.7103],"type":"Point"}
}