{
  "type": "Feature",
  "properties": {
    "iso:country":"US",
    "sg:address":"99 Liberty Ave",
    "sg:city":"North Babylon",
    "sg:classifiers":[
        {
            "category":"Professional",
            "subcategory":"Lawyer & Legal Services",
            "type":"Services"
        }
    ],
    "sg:phone":"+1   ",
    "sg:postcode":"11703",
    "sg:province":"NY",
    "wof:name":"Milagros Rogers",
    "wof:placetype":"venue"
},
  "geometry": {"coordinates":[-73.322384,40.717127],"type":"Point"}
}