{
  "type": "Feature",
  "properties": {
    "addr:full":"1386 Creek Rd Esperance NY 12066",
    "addr:housenumber":"1386",
    "addr:postcode":"12066",
    "addr:street":"Creek Rd",
    "iso:country":"US",
    "sg:address":"1386 Creek Rd",
    "sg:city":"Esperance",
    "sg:classifiers":[
        {
            "category":"Arts & Performance",
            "subcategory":"Theater",
            "type":"Entertainment"
        }
    ],
    "sg:phone":"+1   ",
    "sg:postcode":"12066",
    "sg:province":"NY",
    "sg:tags":[
        "group"
    ],
    "wof:name":"Savoy Tf Inc",
    "wof:placetype":"venue"
},
  "geometry": {"coordinates":[-74.298267,42.749273],"type":"Point"}
}