{
  "type": "Feature",
  "properties": {
    "addr:full":"113 Ireland Pl Amityville NY 11701",
    "addr:housenumber":"113",
    "addr:postcode":"11701",
    "addr:street":"Ireland Pl",
    "iso:country":"US",
    "sg:address":"113 Ireland Pl",
    "sg:city":"Amityville",
    "sg:classifiers":[
        {
            "category":"Home & Garden",
            "subcategory":"Carpets & Floor Coverings",
            "type":"Retail Goods"
        }
    ],
    "sg:phone":"+1 631 789 8038",
    "sg:postcode":"11701",
    "sg:province":"NY",
    "sg:tags":[
        "dealer",
        "rug"
    ],
    "wof:name":"Image Flooring Inc",
    "wof:placetype":"venue"
},
  "geometry": {"coordinates":[-73.422145,40.6784],"type":"Point"}
}