{
  "type": "Feature",
  "properties": {
    "addr:full":"414 Webster Rd Webster NY 14580",
    "addr:housenumber":"414",
    "addr:postcode":"14580",
    "addr:street":"Webster Rd",
    "iso:country":"US",
    "sg:address":"414 Webster Rd",
    "sg:city":"Webster",
    "sg:classifiers":[
        {
            "category":"Building & Trades",
            "subcategory":"Landscaping Services",
            "type":"Services"
        }
    ],
    "sg:phone":"+1 585 281 1851",
    "sg:postcode":"14580",
    "sg:province":"NY",
    "wof:name":"Educated Pro Lawn & Landscape",
    "wof:placetype":"venue"
},
  "geometry": {"coordinates":[-77.428657,43.247929],"type":"Point"}
}