{
  "type": "Feature",
  "properties": {
    "addr:full":"2070 Attica Rd Darien Center NY 14040",
    "addr:postcode":"2070;14040",
    "addr:street":"Attica Rd",
    "iso:country":"US",
    "sg:address":"2070 Attica Rd",
    "sg:city":"Darien Center",
    "sg:classifiers":[
        {
            "category":"Wholesale",
            "subcategory":"Non-durable Goods",
            "type":"Manufacturing & Wholesale Goods"
        }
    ],
    "sg:phone":"+1 585 547 9995",
    "sg:postcode":"14040",
    "sg:province":"NY",
    "wof:name":"Wexstan Mastiffs",
    "wof:placetype":"venue"
},
  "geometry": {"coordinates":[-78.34656099999999,42.896795],"type":"Point"}
}