{
  "type": "Feature",
  "properties": {
    "iso:country":"US",
    "sg:address":"116 Keyland Ct",
    "sg:city":"Bohemia",
    "sg:classifiers":[
        {
            "category":"Retail",
            "subcategory":"Auto Repair",
            "type":"Services"
        }
    ],
    "sg:phone":"+1 631 563 8896",
    "sg:postcode":"11716",
    "sg:province":"NY",
    "sg:tags":[
        "machine",
        "automobile",
        "shop"
    ],
    "wof:name":"Francois Belvisi Co Inc",
    "wof:placetype":"venue"
},
  "geometry": {"coordinates":[-73.098889,40.776829],"type":"Point"}
}