{
  "type": "Feature",
  "properties": {
    "iso:country":"US",
    "sg:address":"42 Phillips Rd",
    "sg:city":"Stillwater",
    "sg:classifiers":[
        {
            "category":"Real Estate",
            "subcategory":"Real Estate Operator",
            "type":"Services"
        }
    ],
    "sg:phone":"+1 518 581 8310",
    "sg:postcode":"12170",
    "sg:province":"NY",
    "sg:tags":[
        "mobile",
        "home",
        "site"
    ],
    "wof:name":"Colonial Heritage Mobile",
    "wof:placetype":"venue"
},
  "geometry": {"coordinates":[-73.61832099999999,43.012462],"type":"Point"}
}