{
  "type": "Feature",
  "properties": {
    "addr:full":"252 Elizabeth St New York NY 10012",
    "addr:housenumber":"252",
    "addr:postcode":"10012",
    "addr:street":"Elizabeth St",
    "iso:country":"US",
    "sg:address":"252 Elizabeth St",
    "sg:city":"New York",
    "sg:classifiers":[
        {
            "category":"Shopping",
            "subcategory":"Clothing, Apparel, & Fashions",
            "type":"Retail Goods"
        }
    ],
    "sg:phone":"+1 212 925 6414",
    "sg:postcode":"10012",
    "sg:province":"NY",
    "sg:tags":[
        "handbag"
    ],
    "wof:name":"Jack Gomme",
    "wof:placetype":"venue"
},
  "geometry": {"coordinates":[-73.993678,40.72346],"type":"Point"}
}