{
  "type": "Feature",
  "properties": {
    "iso:country":"US",
    "sg:address":"126 Gnarled Hollow Rd",
    "sg:city":"East Setauket",
    "sg:classifiers":[
        {
            "category":"Health Services",
            "subcategory":"Doctor",
            "type":"Services"
        }
    ],
    "sg:phone":"+1 631 689 9777",
    "sg:postcode":"11733",
    "sg:province":"NY",
    "sg:tags":[
        "surgeon",
        "oral"
    ],
    "wof:name":"Koeppel Ira D DDS",
    "wof:placetype":"venue"
},
  "geometry": {"coordinates":[-73.100601,40.933201],"type":"Point"}
}