{
  "type": "Feature",
  "properties": {
    "iso:country":"US",
    "sg:address":"91 Millard Ave",
    "sg:city":"Bronxville",
    "sg:classifiers":[
        {
            "category":"Professional",
            "subcategory":"Business Services",
            "type":"Services"
        }
    ],
    "sg:phone":"+1   ",
    "sg:postcode":"10708",
    "sg:province":"NY",
    "wof:name":"Tamco Partners",
    "wof:placetype":"venue"
},
  "geometry": {"coordinates":[-73.84528400000001,40.94405],"type":"Point"}
}