{
  "type": "Feature",
  "properties": {
    "addr:full":"1410 Avenue M Brooklyn NY 11230",
    "addr:housenumber":"1410",
    "addr:postcode":"11230",
    "addr:street":"Avenue M",
    "iso:country":"US",
    "sg:address":"1410 Avenue M",
    "sg:city":"Brooklyn",
    "sg:classifiers":[
        {
            "category":"Personal",
            "subcategory":"Shoe Repair & Shine",
            "type":"Services"
        }
    ],
    "sg:phone":"+1 718 998 4181",
    "sg:postcode":"11230",
    "sg:province":"NY",
    "wof:name":"Yakupov Murod Shoe Repair",
    "wof:placetype":"venue"
},
  "geometry": {"coordinates":[-73.96080000000001,40.617802],"type":"Point"}
}