{
  "type": "Feature",
  "properties": {
    "addr:full":"300 Walzer Rd Rochester NY 14622",
    "addr:housenumber":"300",
    "addr:postcode":"14622",
    "addr:street":"Walzer Rd",
    "iso:country":"US",
    "sg:address":"300 Walzer Rd",
    "sg:city":"Rochester",
    "sg:classifiers":[
        {
            "category":"Restaurant",
            "type":"Food & Drink"
        }
    ],
    "sg:phone":"+1 585 338 9283",
    "sg:postcode":"14622",
    "sg:province":"NY",
    "sg:tags":[
        "caterer"
    ],
    "wof:name":"Deliciously Different Catering",
    "wof:placetype":"venue"
},
  "geometry": {"coordinates":[-77.563914,43.21108],"type":"Point"}
}