{
  "type": "Feature",
  "properties": {
    "iso:country":"US",
    "sg:address":"564 Meacham Ave",
    "sg:city":"Elmont",
    "sg:classifiers":[
        {
            "category":"Wholesale",
            "subcategory":"Medical Equipment & Supplies",
            "type":"Manufacturing & Wholesale Goods"
        }
    ],
    "sg:phone":"+1 516 488 0158",
    "sg:postcode":"11003",
    "sg:province":"NY",
    "sg:tags":[
        "specializing",
        "x",
        "solution",
        "apparatus",
        "f"
    ],
    "wof:name":"D & A Solutions & X Ray",
    "wof:placetype":"venue"
},
  "geometry": {"coordinates":[-73.691216,40.692713],"type":"Point"}
}