{
  "type": "Feature",
  "properties": {
    "iso:country":"US",
    "sg:address":"898 Broadway",
    "sg:city":"Brooklyn",
    "sg:classifiers":[
        {
            "category":"Personal",
            "subcategory":"Barber",
            "type":"Services"
        }
    ],
    "sg:phone":"+1 718 455 3553",
    "sg:postcode":"11206",
    "sg:province":"NY",
    "wof:name":"Stylez",
    "wof:placetype":"venue"
},
  "geometry": {"coordinates":[-73.93703600000001,40.697815],"type":"Point"}
}