{
  "type": "Feature",
  "properties": {
    "addr:full":"1986 Lakeview Rd Lake View NY 14085",
    "addr:housenumber":"1986",
    "addr:postcode":"14085",
    "addr:street":"Lakeview Rd",
    "iso:country":"US",
    "sg:address":"1986 Lakeview Rd",
    "sg:city":"Lake View",
    "sg:classifiers":[
        {
            "category":"Restaurant",
            "type":"Food & Drink"
        }
    ],
    "sg:phone":"+1 716 627 3499",
    "sg:postcode":"14085",
    "sg:province":"NY",
    "wof:name":"J P's Pub & Pizzeria",
    "wof:placetype":"venue"
},
  "geometry": {"coordinates":[-78.936386,42.711453],"type":"Point"}
}