{
  "type": "Feature",
  "properties": {
    "addr:full":"4 W Main St Irvington NY 10533",
    "addr:housenumber":"4",
    "addr:postcode":"ny 10533",
    "addr:street":"W Main St",
    "iso:country":"US",
    "sg:address":"4 W Main St",
    "sg:city":"Irvington",
    "sg:classifiers":[
        {
            "category":"Restaurant",
            "type":"Food & Drink"
        }
    ],
    "sg:phone":"+1 914 591 5500",
    "sg:postcode":"10533",
    "sg:province":"NY",
    "sg:tags":[
        "indian"
    ],
    "sg:website":"http://www.chutneymasalabistro.com",
    "wof:name":"Chutney Masala Indian Bistro",
    "wof:placetype":"venue"
},
  "geometry": {"coordinates":[-73.872657,41.039804],"type":"Point"}
}