{
  "type": "Feature",
  "properties": {
    "addr:full":"2255 Bedford Ave Brooklyn NY 11226",
    "addr:housenumber":"2255",
    "addr:postcode":"11226",
    "addr:street":"Bedford Ave",
    "iso:country":"US",
    "sg:address":"2255 Bedford Ave",
    "sg:city":"Brooklyn",
    "sg:classifiers":[
        {
            "category":"Retail",
            "subcategory":"Portrait Studio",
            "type":"Services"
        }
    ],
    "sg:phone":"+1 718 941 5258",
    "sg:postcode":"11226",
    "sg:province":"NY",
    "sg:tags":[
        "photography"
    ],
    "wof:name":"Impressive Photo Studio Video",
    "wof:placetype":"venue"
},
  "geometry": {"coordinates":[-73.955703,40.649304],"type":"Point"}
}