{
  "type": "Feature",
  "properties": {
    "addr:full":"4 Harmony Ln Westbury NY 11590",
    "addr:housenumber":"4",
    "addr:postcode":"11590",
    "addr:street":"Harmony Ln",
    "iso:country":"US",
    "sg:address":"4 Harmony Ln",
    "sg:city":"Westbury",
    "sg:classifiers":[
        {
            "category":"Utilities",
            "subcategory":"Telephone",
            "type":"Services"
        }
    ],
    "sg:phone":"+1   ",
    "sg:postcode":"11590",
    "sg:province":"NY",
    "sg:tags":[
        "tel"
    ],
    "wof:name":"Amcs",
    "wof:placetype":"venue"
},
  "geometry": {"coordinates":[-73.548821,40.738319],"type":"Point"}
}