{
  "type": "Feature",
  "properties": {
    "addr:full":"28 Shore Rd Patchogue NY 11772",
    "addr:housenumber":"28",
    "addr:postcode":"11772",
    "addr:street":"Shore Rd",
    "iso:country":"US",
    "sg:address":"28 Shore Rd",
    "sg:city":"Patchogue",
    "sg:classifiers":[
        {
            "category":"Utilities",
            "subcategory":"Telephone",
            "type":"Services"
        }
    ],
    "sg:phone":"+1   ",
    "sg:postcode":"11772",
    "sg:province":"NY",
    "sg:tags":[
        "communications"
    ],
    "wof:name":"Business Source Zero",
    "wof:placetype":"venue"
},
  "geometry": {"coordinates":[-73.02108200000001,40.772251],"type":"Point"}
}