{
  "type": "Feature",
  "properties": {
    "addr:full":"23 Park Ave Yonkers NY 10703",
    "addr:housenumber":"23",
    "addr:postcode":"10703",
    "addr:street":"Park Ave",
    "iso:country":"US",
    "sg:address":"23 Park Ave",
    "sg:city":"Yonkers",
    "sg:classifiers":[
        {
            "category":"Health Services",
            "subcategory":"Clinic",
            "type":"Services"
        }
    ],
    "sg:phone":"+1   ",
    "sg:postcode":"10703",
    "sg:province":"NY",
    "wof:name":"Yonkers General Hospital Inc",
    "wof:placetype":"venue"
},
  "geometry": {"coordinates":[-73.892132,40.940639],"type":"Point"}
}