{
  "type": "Feature",
  "properties": {
    "addr:full":"2250 Park St Syracuse NY 13208",
    "addr:housenumber":"2250",
    "addr:postcode":"13208",
    "addr:street":"Park St",
    "iso:country":"US",
    "sg:address":"2250 Park St",
    "sg:city":"Syracuse",
    "sg:classifiers":[
        {
            "category":"Autos & Motor Vehicles",
            "subcategory":"Automobile Sales",
            "type":"Retail Goods"
        }
    ],
    "sg:phone":"+1 315 474 1615",
    "sg:postcode":"13208",
    "sg:province":"NY",
    "sg:tags":[
        "car",
        "used",
        "dealer"
    ],
    "wof:name":"Brian Farmers Auto Sales",
    "wof:placetype":"venue"
},
  "geometry": {"coordinates":[-76.171981,43.075493],"type":"Point"}
}