{
  "type": "Feature",
  "properties": {
    "iso:country":"US",
    "sg:address":"73 W 83rd St",
    "sg:city":"Manhattan",
    "sg:classifiers":[
        {
            "category":"Retail",
            "subcategory":"Laundry & Dry Cleaning",
            "type":"Services"
        }
    ],
    "sg:postcode":"10024",
    "sg:province":"NY",
    "wof:name":"HOYAA Landry and Cleaners",
    "wof:placetype":"venue"
},
  "geometry": {"coordinates":[-73.9731,40.784345],"type":"Point"}
}