{
  "type": "Feature",
  "properties": {
    "addr:full":"295 Saw Mill River Rd Yonkers NY 10701",
    "addr:housenumber":"295",
    "addr:postcode":"10701",
    "addr:street":"Saw Mill River Rd",
    "iso:country":"US",
    "sg:address":"295 Saw Mill River Rd",
    "sg:city":"Yonkers",
    "sg:classifiers":[
        {
            "category":"Personal",
            "subcategory":"Beauty Salon",
            "type":"Services"
        }
    ],
    "sg:phone":"+1 914 969 1400",
    "sg:postcode":"10701",
    "sg:province":"NY",
    "wof:name":"Hair Hut",
    "wof:placetype":"venue"
},
  "geometry": {"coordinates":[-73.877075,40.946803],"type":"Point"}
}