{
  "type": "Feature",
  "properties": {
    "addr:full":"78 Ozone St Manorville NY 11949",
    "addr:housenumber":"78",
    "addr:postcode":"11949",
    "addr:street":"Ozone St",
    "iso:country":"US",
    "sg:address":"78 Ozone St",
    "sg:city":"Manorville",
    "sg:classifiers":[
        {
            "category":"Professional",
            "subcategory":"Research",
            "type":"Services"
        }
    ],
    "sg:phone":"+1 631 878 6817",
    "sg:postcode":"11949",
    "sg:province":"NY",
    "sg:tags":[
        "environmental",
        "ecological"
    ],
    "wof:name":"Emington Environmental Inc",
    "wof:placetype":"venue"
},
  "geometry": {"coordinates":[-72.811842,40.848015],"type":"Point"}
}