{
  "type": "Feature",
  "properties": {
    "addr:full":"21 W 86th St New York NY 10024",
    "addr:housenumber":"21",
    "addr:postcode":"10024",
    "addr:street":"W 86Th St",
    "iso:country":"US",
    "sg:address":"21 W 86th St",
    "sg:city":"New York",
    "sg:classifiers":[
        {
            "category":"Health Services",
            "subcategory":"Health Practitioner",
            "type":"Services"
        }
    ],
    "sg:phone":"+1 212 580 0125",
    "sg:postcode":"10024",
    "sg:province":"NY",
    "sg:tags":[
        "therapy",
        "physical"
    ],
    "sg:website":"www.riversideptnyc.com/",
    "wof:name":"Riverside Physical Therapy",
    "wof:placetype":"venue"
},
  "geometry": {"coordinates":[-73.970276,40.786005],"type":"Point"}
}