{
  "type": "Feature",
  "properties": {
    "addr:full":"21 Wentworth Avenue Staten Island NY 10305",
    "addr:housenumber":"21",
    "addr:postcode":"10305",
    "addr:street":"Wentworth Avenue",
    "iso:country":"US",
    "sg:address":"21 Wentworth Avenue",
    "sg:city":"Staten Island",
    "sg:classifiers":[
        {
            "category":"Arena",
            "subcategory":"Sports Club",
            "type":"Entertainment"
        }
    ],
    "sg:phone":"+1 718 585 8878",
    "sg:postcode":"10305",
    "sg:province":"NY",
    "sg:tags":[
        "martial art"
    ],
    "sg:website":"www.zenbujujutsu.com",
    "wof:name":"Zenbu Jujutsu Ryu",
    "wof:placetype":"venue"
},
  "geometry": {"coordinates":[-74.071647,40.59192],"type":"Point"}
}