{
  "type": "Feature",
  "properties": {
    "iso:country":"US",
    "sg:address":"400 Post Ave Ste 302",
    "sg:city":"Westbury",
    "sg:classifiers":[
        {
            "category":"Autos & Motor Vehicles",
            "subcategory":"Automobile Sales",
            "type":"Retail Goods"
        }
    ],
    "sg:phone":"+1 516 478 4162",
    "sg:postcode":"11590",
    "sg:province":"NY",
    "sg:tags":[
        "limo"
    ],
    "wof:name":"Big City Limo",
    "wof:placetype":"venue"
},
  "geometry": {"coordinates":[-73.586868,40.762296],"type":"Point"}
}