{
  "type": "Feature",
  "properties": {
    "iso:country":"US",
    "sg:address":"616 Empire Blvd",
    "sg:city":"Brooklyn",
    "sg:classifiers":[
        {
            "category":"Organizations",
            "subcategory":"Religious Organization",
            "type":"Services"
        }
    ],
    "sg:phone":"+1 718 493 0279",
    "sg:postcode":"11213",
    "sg:province":"NY",
    "sg:tags":[
        "clergy"
    ],
    "wof:name":"Joseph H Rosenfeld",
    "wof:placetype":"venue"
},
  "geometry": {"coordinates":[-73.94059799999999,40.663876],"type":"Point"}
}