{
  "type": "Feature",
  "properties": {
    "addr:full":"895 E Gate Blvd Garden City NY 11530",
    "addr:housenumber":"895",
    "addr:postcode":"11530",
    "addr:street":"E Gate Blvd",
    "iso:country":"US",
    "sg:address":"895 E Gate Blvd",
    "sg:city":"Garden City",
    "sg:classifiers":[
        {
            "category":"Home & Garden",
            "subcategory":"Furniture",
            "type":"Retail Goods"
        }
    ],
    "sg:phone":"+1   ",
    "sg:postcode":"11530",
    "sg:province":"NY",
    "sg:website":"www.levitz.com",
    "wof:name":"Levitz Furniture",
    "wof:placetype":"venue"
},
  "geometry": {"coordinates":[-73.607513,40.744461],"type":"Point"}
}