{
  "type": "Feature",
  "properties": {
    "iso:country":"US",
    "sg:address":"477 Gates Ave",
    "sg:city":"Brooklyn",
    "sg:classifiers":[
        {
            "category":"Shopping",
            "subcategory":"Clothing, Apparel, & Fashions",
            "type":"Retail Goods"
        }
    ],
    "sg:phone":"+1 718 398 0550",
    "sg:postcode":"11216",
    "sg:province":"NY",
    "sg:tags":[
        "baby",
        "accessory"
    ],
    "wof:name":"Community Baby Sit",
    "wof:placetype":"venue"
},
  "geometry": {"coordinates":[-73.949636,40.686323],"type":"Point"}
}