{
  "type": "Feature",
  "properties": {
    "addr:full":"522 46th Avenue Long Island City NY 11101",
    "addr:housenumber":"522",
    "addr:postcode":"11101",
    "addr:street":"46Th Avenue",
    "iso:country":"US",
    "sg:address":"522 46th Avenue",
    "sg:city":"Long Island City",
    "sg:classifiers":[
        {
            "category":"Restaurant",
            "type":"Food & Drink"
        }
    ],
    "sg:phone":"+1 718 937 9503",
    "sg:postcode":"11101",
    "sg:province":"NY",
    "wof:name":"Temp Tu Marketing",
    "wof:placetype":"venue"
},
  "geometry": {"coordinates":[-73.95494100000001,40.747316],"type":"Point"}
}