{
  "type": "Feature",
  "properties": {
    "iso:country":"US",
    "sg:address":"156 5th Ave",
    "sg:city":"New York",
    "sg:classifiers":[
        {
            "category":"Professional",
            "subcategory":"Lawyer & Legal Services",
            "type":"Services"
        }
    ],
    "sg:phone":"+1 212 741 3938",
    "sg:postcode":"10010",
    "sg:province":"NY",
    "wof:name":"Hamburg Frances",
    "wof:placetype":"venue"
},
  "geometry": {"coordinates":[-73.9907,40.739899],"type":"Point"}
}