{
  "type": "Feature",
  "properties": {
    "iso:country":"US",
    "sg:address":"3560 Long Beach Rd",
    "sg:city":"Oceanside",
    "sg:classifiers":[
        {
            "category":"Shopping",
            "subcategory":"Gifts & Souvenirs",
            "type":"Retail Goods"
        }
    ],
    "sg:phone":"+1   ",
    "sg:postcode":"11572",
    "sg:province":"NY",
    "sg:tags":[
        "shop"
    ],
    "wof:name":"Fond Memories",
    "wof:placetype":"venue"
},
  "geometry": {"coordinates":[-73.63958,40.62475],"type":"Point"}
}