{
  "type": "Feature",
  "properties": {
    "addr:full":"13 Hartford Ave Glens Falls NY 12801",
    "addr:housenumber":"13",
    "addr:postcode":"12801",
    "addr:street":"Hartford Ave",
    "iso:country":"US",
    "sg:address":"13 Hartford Ave",
    "sg:city":"Glens Falls",
    "sg:classifiers":[
        {
            "category":"Real Estate",
            "subcategory":"Real Estate Operator",
            "type":"Services"
        }
    ],
    "sg:phone":"+1 518 792 2980",
    "sg:postcode":"12801",
    "sg:province":"NY",
    "sg:tags":[
        "apartment"
    ],
    "wof:name":"Colonial Gardens Apartments",
    "wof:placetype":"venue"
},
  "geometry": {"coordinates":[-73.63884400000001,43.32478],"type":"Point"}
}