{
  "type": "Feature",
  "properties": {
    "addr:full":"36 N Broadway Yonkers NY 10701",
    "addr:housenumber":"36",
    "addr:postcode":"10701",
    "addr:street":"N Broadway",
    "iso:country":"US",
    "sg:address":"36 N Broadway",
    "sg:city":"Yonkers",
    "sg:classifiers":[
        {
            "category":"Health Services",
            "subcategory":"Doctor",
            "type":"Services"
        }
    ],
    "sg:phone":"+1 914 963 5866",
    "sg:postcode":"10701",
    "sg:province":"NY",
    "sg:tags":[
        "physician",
        "surgeon"
    ],
    "wof:name":"Riverside Pediatrics",
    "wof:placetype":"venue"
},
  "geometry": {"coordinates":[-73.897739,40.93419],"type":"Point"}
}