{
  "type": "Feature",
  "properties": {
    "iso:country":"US",
    "sg:address":"907 Church Ave",
    "sg:city":"Brooklyn",
    "sg:classifiers":[
        {
            "category":"Professional",
            "subcategory":"Computer Services",
            "type":"Services"
        }
    ],
    "sg:phone":"+1 718 284 3082",
    "sg:postcode":"11218",
    "sg:province":"NY",
    "sg:tags":[
        "repair"
    ],
    "wof:name":"Twiz Computer Media LLC",
    "wof:placetype":"venue"
},
  "geometry": {"coordinates":[-73.970814,40.646559],"type":"Point"}
}