{
  "type": "Feature",
  "properties": {
    "addr:full":"1501 Broadway Ste 2015 New York NY 10036",
    "addr:housenumber":"1501",
    "addr:postcode":"2015;10036",
    "addr:street":"Broadway Ste",
    "iso:country":"US",
    "sg:address":"1501 Broadway Ste 2015",
    "sg:city":"New York",
    "sg:classifiers":[
        {
            "category":"Landmark",
            "subcategory":"Tourist Information",
            "type":"Public Place"
        }
    ],
    "sg:phone":"+1 212 768 8705",
    "sg:postcode":"10036",
    "sg:province":"NY",
    "sg:tags":[
        "tour"
    ],
    "wof:name":"Dodger Touring",
    "wof:placetype":"venue"
},
  "geometry": {"coordinates":[-73.986099,40.756599],"type":"Point"}
}