{
  "type": "Feature",
  "properties": {
    "addr:full":"20 Vanderventer Ave Port Washington NY 11050",
    "addr:housenumber":"20",
    "addr:postcode":"11050",
    "addr:street":"Vanderventer Ave",
    "iso:country":"US",
    "sg:address":"20 Vanderventer Ave",
    "sg:city":"Port Washington",
    "sg:classifiers":[
        {
            "category":"Professional",
            "subcategory":"Lawyer & Legal Services",
            "type":"Services"
        }
    ],
    "sg:phone":"+1 516 944 5062",
    "sg:postcode":"11050",
    "sg:province":"NY",
    "wof:name":"Froccarro James Atty",
    "wof:placetype":"venue"
},
  "geometry": {"coordinates":[-73.685427,40.828035],"type":"Point"}
}