{
  "type": "Feature",
  "properties": {
    "iso:country":"US",
    "sg:address":"263 Route 17K",
    "sg:city":"Newburgh",
    "sg:classifiers":[
        {
            "category":"Shopping",
            "subcategory":"Department Store",
            "type":"Retail Goods"
        },
        {
            "category":"Shopping",
            "subcategory":"Discount & Variety Stores",
            "type":"Retail Goods"
        }
    ],
    "sg:phone":"+1 845 567 9645",
    "sg:postcode":"12550",
    "sg:province":"NY",
    "wof:name":"Best Buy Ny District Forty Eight",
    "wof:placetype":"venue"
},
  "geometry": {"coordinates":[-74.11824799999999,41.524399],"type":"Point"}
}