{
  "type": "Feature",
  "properties": {
    "addr:full":"109 Elmcroft Rd Rochester NY 14609",
    "addr:housenumber":"109",
    "addr:postcode":"14609",
    "addr:street":"Elmcroft Rd",
    "iso:country":"US",
    "sg:address":"109 Elmcroft Rd",
    "sg:city":"Rochester",
    "sg:classifiers":[
        {
            "category":"Building & Trades",
            "subcategory":"Landscaping Services",
            "type":"Services"
        }
    ],
    "sg:phone":"+1 585 288 6478",
    "sg:postcode":"14609",
    "sg:province":"NY",
    "wof:name":"Q Landscaping",
    "wof:placetype":"venue"
},
  "geometry": {"coordinates":[-77.546094,43.160461],"type":"Point"}
}