{
  "type": "Feature",
  "properties": {
    "addr:full":"34 W 32nd St New York NY 10001",
    "addr:housenumber":"34",
    "addr:postcode":"10001",
    "addr:street":"W 32Nd St",
    "iso:country":"US",
    "sg:address":"34 W 32nd St",
    "sg:city":"New York",
    "sg:classifiers":[
        {
            "category":"Restaurant",
            "type":"Food & Drink"
        }
    ],
    "sg:phone":"+1 212 736 0099",
    "sg:postcode":"10001",
    "sg:province":"NY",
    "sg:tags":[
        "korean"
    ],
    "sg:website":"www.restaurant24hours.com",
    "wof:name":"NY24HRS Restaurant",
    "wof:placetype":"venue"
},
  "geometry": {"coordinates":[-73.987791,40.748112],"type":"Point"}
}