{
  "type": "Feature",
  "properties": {
    "addr:full":"40 Bidwell Pkwy Buffalo NY 14222",
    "addr:housenumber":"40",
    "addr:postcode":"14222",
    "addr:street":"Bidwell Pkwy",
    "iso:country":"US",
    "sg:address":"40 Bidwell Pkwy",
    "sg:city":"Buffalo",
    "sg:classifiers":[
        {
            "category":"Wholesale",
            "subcategory":"Medical Equipment & Supplies",
            "type":"Manufacturing & Wholesale Goods"
        }
    ],
    "sg:phone":"+1 716 883 6881",
    "sg:postcode":"14222",
    "sg:province":"NY",
    "wof:name":"Unimed",
    "wof:placetype":"venue"
},
  "geometry": {"coordinates":[-78.880049,42.921233],"type":"Point"}
}