{
  "type": "Feature",
  "properties": {
    "iso:country":"US",
    "sg:address":"86 S Main St",
    "sg:city":"Franklinville",
    "sg:classifiers":[
        {
            "category":"Government",
            "subcategory":"Office",
            "type":"Public Place"
        }
    ],
    "sg:phone":"+1 716 676 5004",
    "sg:postcode":"14737",
    "sg:province":"NY",
    "wof:name":"North County Counseling Ctr",
    "wof:placetype":"venue"
},
  "geometry": {"coordinates":[-78.460618,42.328932],"type":"Point"}
}