{
  "type": "Feature",
  "properties": {
    "addr:full":"297 River St Troy NY 12180",
    "addr:housenumber":"297",
    "addr:postcode":"12180",
    "addr:street":"River St",
    "iso:country":"US",
    "sg:address":"297 River St",
    "sg:city":"Troy",
    "sg:classifiers":[
        {
            "category":"Real Estate",
            "subcategory":"Architect",
            "type":"Services"
        }
    ],
    "sg:phone":"+1 518 266 1194",
    "sg:postcode":"12180",
    "sg:province":"NY",
    "wof:name":"SMRT Architects & Engineers",
    "wof:placetype":"venue"
},
  "geometry": {"coordinates":[-73.69074500000001,42.732236],"type":"Point"}
}