{
  "type": "Feature",
  "properties": {
    "addr:full":"1217 2nd Ave New York NY 10021",
    "addr:housenumber":"1217",
    "addr:postcode":"10021",
    "addr:street":"2Nd Ave",
    "iso:country":"US",
    "sg:address":"1217 2nd Ave",
    "sg:city":"New York",
    "sg:classifiers":[
        {
            "category":"Food & Beverages",
            "subcategory":"Specialty",
            "type":"Retail Goods"
        }
    ],
    "sg:phone":"+1 212 838 6223",
    "sg:postcode":"10021",
    "sg:province":"NY",
    "sg:website":"chickengourmetnyc.com",
    "wof:name":"Chicken Gourmet",
    "wof:placetype":"venue"
},
  "geometry": {"coordinates":[-73.96230300000001,40.763599],"type":"Point"}
}