{
  "type": "Feature",
  "properties": {
    "addr:full":"2197 George Urban Blvd Depew NY 14043",
    "addr:housenumber":"2197",
    "addr:postcode":"14043",
    "addr:street":"George Urban Blvd",
    "iso:country":"US",
    "sg:address":"2197 George Urban Blvd",
    "sg:city":"Depew",
    "sg:classifiers":[
        {
            "category":"Retail",
            "subcategory":"Laundry & Dry Cleaning",
            "type":"Services"
        }
    ],
    "sg:phone":"+1 716 683 0400",
    "sg:postcode":"14043",
    "sg:province":"NY",
    "sg:tags":[
        "cleaners"
    ],
    "wof:name":"Classic Cleaners",
    "wof:placetype":"venue"
},
  "geometry": {"coordinates":[-78.726428,42.918644],"type":"Point"}
}