{
  "type": "Feature",
  "properties": {
    "addr:full":"299 Crystal Run Rd Middletown NY 10941",
    "addr:housenumber":"299",
    "addr:postcode":"10941",
    "addr:street":"Crystal Run Rd",
    "iso:country":"US",
    "sg:address":"299 Crystal Run Rd",
    "sg:city":"Middletown",
    "sg:classifiers":[
        {
            "category":"Home & Garden",
            "subcategory":"Building Materials",
            "type":"Retail Goods"
        }
    ],
    "sg:phone":"+1 845 692 4486",
    "sg:postcode":"10941",
    "sg:province":"NY",
    "sg:tags":[
        "supply"
    ],
    "wof:name":"Tetz E & Sons Inc",
    "wof:placetype":"venue"
},
  "geometry": {"coordinates":[-74.34030199999999,41.4585],"type":"Point"}
}