{
  "type": "Feature",
  "properties": {
    "iso:country":"US",
    "sg:address":"2381 US Hwy 9w",
    "sg:city":"Ravena",
    "sg:classifiers":[
        {
            "category":"Restaurant",
            "type":"Food & Drink"
        }
    ],
    "sg:phone":"+1 518 756 7211",
    "sg:postcode":"12143",
    "sg:province":"NY",
    "wof:name":"Joey's Pizza & Pasta Rstrnt",
    "wof:placetype":"venue"
},
  "geometry": {"coordinates":[-73.818496,42.473657],"type":"Point"}
}