{
  "type": "Feature",
  "properties": {
    "iso:country":"US",
    "sg:address":"58 Horn Ln",
    "sg:city":"Levittown",
    "sg:classifiers":[
        {
            "category":"Freight",
            "type":"Transportation"
        }
    ],
    "sg:phone":"+1 516 735 6206",
    "sg:postcode":"11756",
    "sg:province":"NY",
    "sg:tags":[
        "courier"
    ],
    "wof:name":"Small Comets Inc",
    "wof:placetype":"venue"
},
  "geometry": {"coordinates":[-73.521697,40.74012],"type":"Point"}
}