{
  "type": "Feature",
  "properties": {
    "addr:full":"95-51 Roosevelt Ave Jackson Heights NY 11372",
    "addr:housenumber":"95-51",
    "addr:postcode":"11372",
    "addr:street":"Roosevelt Ave",
    "iso:country":"US",
    "sg:address":"95-51 Roosevelt Ave",
    "sg:city":"Jackson Heights",
    "sg:classifiers":[
        {
            "category":"Restaurant",
            "type":"Food & Drink"
        }
    ],
    "sg:phone":"+1 718 429 4388",
    "sg:postcode":"11372",
    "sg:province":"NY",
    "sg:tags":[
        "american",
        "latin",
        "steakhouse"
    ],
    "sg:website":"lacabanaargentina.com",
    "wof:name":"La Cabana Argentina Restaurant",
    "wof:placetype":"venue"
},
  "geometry": {"coordinates":[-73.870223,40.749075],"type":"Point"}
}