{
  "type": "Feature",
  "properties": {
    "addr:full":"95 Virginia Rd White Plains NY 10603",
    "addr:housenumber":"95",
    "addr:postcode":"10603",
    "addr:street":"Virginia Rd",
    "iso:country":"US",
    "sg:address":"95 Virginia Rd",
    "sg:city":"White Plains",
    "sg:classifiers":[
        {
            "category":"Freight",
            "type":"Transportation"
        }
    ],
    "sg:phone":"+1   ",
    "sg:postcode":"10603",
    "sg:province":"NY",
    "sg:tags":[
        "moving",
        "storage"
    ],
    "wof:name":"Gold Service Movers Inc",
    "wof:placetype":"venue"
},
  "geometry": {"coordinates":[-73.772223,41.060239],"type":"Point"}
}