{
  "type": "Feature",
  "properties": {
    "addr:full":"1225 Broadway New York NY 10001",
    "addr:housenumber":"1225",
    "addr:postcode":"10001",
    "addr:street":"Broadway",
    "iso:country":"US",
    "sg:address":"1225 Broadway",
    "sg:city":"New York",
    "sg:classifiers":[
        {
            "category":"Shopping",
            "subcategory":"Discount & Variety Stores",
            "type":"Retail Goods"
        },
        {
            "category":"Professional",
            "subcategory":"Business Services",
            "type":"Services"
        },
        {
            "category":"Shopping",
            "subcategory":"Clothing, Apparel, & Fashions",
            "type":"Retail Goods"
        }
    ],
    "sg:phone":"+1 212 696 9623",
    "sg:postcode":"10001",
    "sg:province":"NY",
    "sg:tags":[
        "post",
        "trading",
        "merchandising"
    ],
    "wof:name":"Limon Trading Corporation",
    "wof:placetype":"venue"
},
  "geometry": {"coordinates":[-73.988615,40.746172],"type":"Point"}
}