{
  "type": "Feature",
  "properties": {
    "iso:country":"US",
    "sg:address":"91 Fairview Park Dr",
    "sg:city":"Elmsford",
    "sg:classifiers":[
        {
            "category":"Restaurant",
            "type":"Food & Drink"
        }
    ],
    "sg:phone":"+1   ",
    "sg:postcode":"10523",
    "sg:province":"NY",
    "sg:tags":[
        "cafe"
    ],
    "wof:name":"Skybox Cafe",
    "wof:placetype":"venue"
},
  "geometry": {"coordinates":[-73.81576699999999,41.067682],"type":"Point"}
}