{
  "type": "Feature",
  "properties": {
    "iso:country":"US",
    "sg:address":"2004 Jericho Tpke",
    "sg:city":"East Northport",
    "sg:classifiers":[
        {
            "category":"Retail",
            "subcategory":"Auto Rental",
            "type":"Services"
        }
    ],
    "sg:phone":"+1 631 421 7368",
    "sg:postcode":"11731",
    "sg:province":"NY",
    "sg:tags":[
        "car"
    ],
    "wof:name":"Replacement Car Rental",
    "wof:placetype":"venue"
},
  "geometry": {"coordinates":[-73.331596,40.8381],"type":"Point"}
}