{
  "type": "Feature",
  "properties": {
    "iso:country":"US",
    "sg:address":"42 Loop Rd",
    "sg:city":"White Plains",
    "sg:classifiers":[
        {
            "category":"Airport",
            "type":"Transportation"
        }
    ],
    "sg:phone":"+1   ",
    "sg:postcode":"10604",
    "sg:province":"NY",
    "wof:name":"U S Tobacco Aviation",
    "wof:placetype":"venue"
},
  "geometry": {"coordinates":[-73.710533,41.078519],"type":"Point"}
}