{
  "type": "Feature",
  "properties": {
    "addr:full":"326 Wall St Kingston NY 12401",
    "addr:housenumber":"326",
    "addr:postcode":"12401",
    "addr:street":"Wall St",
    "iso:country":"US",
    "sg:address":"326 Wall St",
    "sg:city":"Kingston",
    "sg:classifiers":[
        {
            "category":"Real Estate",
            "subcategory":"Real Estate Agent",
            "type":"Services"
        }
    ],
    "sg:phone":"+1 845 339 4444",
    "sg:postcode":"12401",
    "sg:province":"NY",
    "sg:website":"www.jonhoytrealty.com",
    "wof:name":"Jon Hoyt Realty LTD",
    "wof:placetype":"venue"
},
  "geometry": {"coordinates":[-74.019887,41.934817],"type":"Point"}
}