{
  "type": "Feature",
  "properties": {
    "iso:country":"US",
    "sg:address":"229 E 53rd St",
    "sg:city":"New York",
    "sg:classifiers":[
        {
            "category":"Bars & Pubs",
            "subcategory":"Wine Bar",
            "type":"Food & Drink"
        }
    ],
    "sg:phone":"+1 917 475 1131",
    "sg:postcode":"10022",
    "sg:province":"NY",
    "sg:website":"www.cellowinebar.com",
    "wof:name":"Cello Wine Bar",
    "wof:placetype":"venue"
},
  "geometry": {"coordinates":[-73.968101,40.757416],"type":"Point"}
}