{
  "type": "Feature",
  "properties": {
    "addr:full":"63 E Pond Rd Woodridge NY 12789",
    "addr:housenumber":"63",
    "addr:postcode":"12789",
    "addr:street":"E Pond Rd",
    "iso:country":"US",
    "sg:address":"63 E Pond Rd",
    "sg:city":"Woodridge",
    "sg:classifiers":[
        {
            "category":"Organizations",
            "subcategory":"Religious Organization",
            "type":"Services"
        }
    ],
    "sg:phone":"+1 845 434 1592",
    "sg:postcode":"12789",
    "sg:province":"NY",
    "wof:name":"Under His Wings Ministries",
    "wof:placetype":"venue"
},
  "geometry": {"coordinates":[-74.58663300000001,41.725999],"type":"Point"}
}