{
  "type": "Feature",
  "properties": {
    "iso:country":"US",
    "sg:address":"737 Main St",
    "sg:city":"Buffalo",
    "sg:classifiers":[
        {
            "category":"Health Services",
            "subcategory":"Doctor",
            "type":"Services"
        }
    ],
    "sg:phone":"+1 716 883 1833",
    "sg:postcode":"14203",
    "sg:province":"NY",
    "sg:tags":[
        "medical"
    ],
    "wof:name":"Eps Settlements Group",
    "wof:placetype":"venue"
},
  "geometry": {"coordinates":[-78.871443,42.894404],"type":"Point"}
}