{
  "type": "Feature",
  "properties": {
    "iso:country":"US",
    "sg:address":"4374 Sunrise Hwy",
    "sg:city":"Massapequa",
    "sg:classifiers":[
        {
            "category":"Retail",
            "subcategory":"Auto Rental",
            "type":"Services"
        }
    ],
    "sg:phone":"+1 516 541 5339",
    "sg:postcode":"11758",
    "sg:province":"NY",
    "sg:tags":[
        "truck",
        "leasing"
    ],
    "wof:name":"Hertz",
    "wof:placetype":"venue"
},
  "geometry": {"coordinates":[-73.471762,40.676013],"type":"Point"}
}