{
  "type": "Feature",
  "properties": {
    "addr:full":"100 N Main St Port Chester NY 10573",
    "addr:housenumber":"100",
    "addr:postcode":"10573",
    "addr:street":"N Main St",
    "iso:country":"US",
    "sg:address":"100 N Main St",
    "sg:city":"Port Chester",
    "sg:classifiers":[
        {
            "category":"Cafe",
            "type":"Food & Drink"
        }
    ],
    "sg:menulink":"http://www.allmenus.com/ny/rye/146654-misti-cafe/menu/",
    "sg:phone":"+1 914 939 2204",
    "sg:postcode":"10573",
    "sg:province":"NY",
    "sg:tags":[
        "caribbean"
    ],
    "wof:name":"Misti Cafe",
    "wof:placetype":"venue"
},
  "geometry": {"coordinates":[-73.662111,41.00211],"type":"Point"}
}