{
  "type": "Feature",
  "properties": {
    "addr:full":"2253 E 28th St Brooklyn NY 11229",
    "addr:housenumber":"2253",
    "addr:postcode":"11229",
    "addr:street":"E 28Th St",
    "iso:country":"US",
    "sg:address":"2253 E 28th St",
    "sg:city":"Brooklyn",
    "sg:classifiers":[
        {
            "category":"Banks & Credit Unions",
            "subcategory":"Bank",
            "type":"Services"
        }
    ],
    "sg:phone":"+1 718 891 2256",
    "sg:postcode":"11229",
    "sg:province":"NY",
    "sg:tags":[
        "federal"
    ],
    "wof:name":"Horodoker David Federal Cr Un",
    "wof:placetype":"venue"
},
  "geometry": {"coordinates":[-73.943067,40.596986],"type":"Point"}
}