{
  "type": "Feature",
  "properties": {
    "iso:country":"US",
    "sg:address":"71 Broadway",
    "sg:city":"New York",
    "sg:classifiers":[
        {
            "category":"Personal",
            "subcategory":"Beauty Salon",
            "type":"Services"
        }
    ],
    "sg:phone":"+1 212 514 6444",
    "sg:postcode":"10006",
    "sg:province":"NY",
    "sg:tags":[
        "shop"
    ],
    "wof:name":"International Hair Cutters",
    "wof:placetype":"venue"
},
  "geometry": {"coordinates":[-74.012508,40.706767],"type":"Point"}
}