{
  "type": "Feature",
  "properties": {
    "iso:country":"US",
    "sg:address":"757 Hewitt Ln",
    "sg:city":"New Windsor",
    "sg:classifiers":[
        {
            "category":"Real Estate",
            "subcategory":"Real Estate Agent",
            "type":"Services"
        }
    ],
    "sg:phone":"+1 845 565 6728",
    "sg:postcode":"12553",
    "sg:province":"NY",
    "sg:tags":[
        "broker"
    ],
    "wof:name":"Walsh Chateau",
    "wof:placetype":"venue"
},
  "geometry": {"coordinates":[-74.014588,41.468747],"type":"Point"}
}