{
  "type": "Feature",
  "properties": {
    "iso:country":"US",
    "sg:address":"17 E Main St",
    "sg:city":"Gowanda",
    "sg:classifiers":[
        {
            "category":"Autos & Motor Vehicles",
            "subcategory":"Fuel & Gas Station",
            "type":"Retail Goods"
        }
    ],
    "sg:phone":"+1 716 532 2334",
    "sg:postcode":"14070",
    "sg:province":"NY",
    "sg:tags":[
        "oil"
    ],
    "wof:name":"Mattco Service Station",
    "wof:placetype":"venue"
},
  "geometry": {"coordinates":[-78.93455299999999,42.463407],"type":"Point"}
}