{
  "type": "Feature",
  "properties": {
    "iso:country":"US",
    "sg:address":"22 E Main St",
    "sg:city":"East Islip",
    "sg:classifiers":[
        {
            "category":"Restaurant",
            "type":"Food & Drink"
        }
    ],
    "sg:menulink":"http://www.allmenus.com/ny/islip/254601-martinos-pizza-and-restaurant/menu/",
    "sg:phone":"+1 631 277 6141",
    "sg:postcode":"11730",
    "sg:province":"NY",
    "sg:tags":[
        "american",
        "italian",
        "pizza"
    ],
    "wof:name":"Martino's Pizza And Restaurant",
    "wof:placetype":"venue"
},
  "geometry": {"coordinates":[-73.18969800000001,40.731377],"type":"Point"}
}