{
  "type": "Feature",
  "properties": {
    "addr:full":"197 Sickles Ave Nyack NY 10960",
    "addr:housenumber":"197",
    "addr:postcode":"10960",
    "addr:street":"Sickles Ave",
    "iso:country":"US",
    "sg:address":"197 Sickles Ave",
    "sg:city":"Nyack",
    "sg:classifiers":[
        {
            "category":"Professional",
            "type":"Services"
        }
    ],
    "sg:phone":"+1 845 358 0812",
    "sg:postcode":"10960",
    "sg:province":"NY",
    "sg:tags":[
        "establishment"
    ],
    "wof:name":"Common Ground Assoc",
    "wof:placetype":"venue"
},
  "geometry": {"coordinates":[-73.92579600000001,41.094541],"type":"Point"}
}