{
  "type": "Feature",
  "properties": {
    "addr:full":"1504 Sheepshead Bay Rd Brooklyn NY 11235",
    "addr:housenumber":"1504",
    "addr:postcode":"11235",
    "addr:street":"Sheepshead Bay Rd",
    "iso:country":"US",
    "sg:address":"1504 Sheepshead Bay Rd",
    "sg:city":"Brooklyn",
    "sg:classifiers":[
        {
            "category":"Professional",
            "subcategory":"Management & Consulting",
            "type":"Services"
        }
    ],
    "sg:phone":"+1 718 648 0506",
    "sg:postcode":"11235",
    "sg:province":"NY",
    "wof:name":"ALA Management LLC",
    "wof:placetype":"venue"
},
  "geometry": {"coordinates":[-73.954139,40.587272],"type":"Point"}
}