{
  "type": "Feature",
  "properties": {
    "addr:full":"208 E 30 St New York NY 10016",
    "addr:housenumber":"208;30",
    "addr:postcode":"10016",
    "addr:street":"E",
    "iso:country":"US",
    "sg:address":"208 E 30 St",
    "sg:city":"New York",
    "sg:classifiers":[
        {
            "category":"Organizations",
            "subcategory":"Membership Organization",
            "type":"Services"
        }
    ],
    "sg:phone":"+1   ",
    "sg:postcode":"10016",
    "sg:province":"NY",
    "wof:name":"Piasa",
    "wof:placetype":"venue"
},
  "geometry": {"coordinates":[-73.97785,40.74227],"type":"Point"}
}