{
  "type": "Feature",
  "properties": {
    "addr:full":"573 West St New York NY 10014",
    "addr:housenumber":"573",
    "addr:postcode":"10014",
    "addr:street":"West St",
    "iso:country":"US",
    "sg:address":"573 West St",
    "sg:city":"New York",
    "sg:classifiers":[
        {
            "category":"Wholesale",
            "subcategory":"Groceries",
            "type":"Manufacturing & Wholesale Goods"
        }
    ],
    "sg:phone":"+1 212 925 0192",
    "sg:postcode":"10014",
    "sg:province":"NY",
    "sg:tags":[
        "food",
        "product"
    ],
    "wof:name":"MFP Metro Inc",
    "wof:placetype":"venue"
},
  "geometry": {"coordinates":[-74.009721,40.738763],"type":"Point"}
}