{
  "type": "Feature",
  "properties": {
    "iso:country":"US",
    "sg:address":"2 E Burnside Ave",
    "sg:city":"Bronx",
    "sg:classifiers":[
        {
            "category":"Food & Beverages",
            "subcategory":"Groceries & Convenience Stores",
            "type":"Retail Goods"
        }
    ],
    "sg:phone":"+1   ",
    "sg:postcode":"10453",
    "sg:province":"NY",
    "wof:name":"First Aden Grocery Corp",
    "wof:placetype":"venue"
},
  "geometry": {"coordinates":[-73.906448,40.853474],"type":"Point"}
}