{
  "type": "Feature",
  "properties": {
    "iso:country":"US",
    "sg:address":"381 Rothermich Rd",
    "sg:city":"Ithaca",
    "sg:classifiers":[
        {
            "category":"Shopping",
            "type":"Retail Goods"
        }
    ],
    "sg:phone":"+1 607 277 5981",
    "sg:postcode":"14850",
    "sg:province":"NY",
    "sg:tags":[
        "trophy",
        "medal",
        "award"
    ],
    "wof:name":"Deb's Awards",
    "wof:placetype":"venue"
},
  "geometry": {"coordinates":[-76.648067,42.423732],"type":"Point"}
}