{
  "type": "Feature",
  "properties": {
    "addr:full":"527 High St Port Jefferson NY 11777",
    "addr:housenumber":"527",
    "addr:postcode":"11777",
    "addr:street":"High St",
    "iso:country":"US",
    "sg:address":"527 High St",
    "sg:city":"Port Jefferson",
    "sg:classifiers":[
        {
            "category":"Building & Trades",
            "subcategory":"Construction",
            "type":"Services"
        }
    ],
    "sg:phone":"+1 631 331 1551",
    "sg:postcode":"11777",
    "sg:province":"NY",
    "sg:tags":[
        "carpentry",
        "contractor"
    ],
    "wof:name":"Forty Contracting Co Inc",
    "wof:placetype":"venue"
},
  "geometry": {"coordinates":[-73.06293100000001,40.943396],"type":"Point"}
}