{
  "type": "Feature",
  "properties": {
    "iso:country":"US",
    "sg:address":"7464 Seneca Rd N",
    "sg:city":"Hornell",
    "sg:classifiers":[
        {
            "category":"Restaurant",
            "type":"Food & Drink"
        }
    ],
    "sg:phone":"+1 607 324 3000",
    "sg:postcode":"14843",
    "sg:province":"NY",
    "wof:name":"Rupert's At The Lodge",
    "wof:placetype":"venue"
},
  "geometry": {"coordinates":[-77.666113,42.362342],"type":"Point"}
}