{
  "type": "Feature",
  "properties": {
    "addr:full":"25 Madison St Cortland NY 13045",
    "addr:housenumber":"25",
    "addr:postcode":"13045",
    "addr:street":"Madison St",
    "iso:country":"US",
    "sg:address":"25 Madison St",
    "sg:city":"Cortland",
    "sg:classifiers":[
        {
            "category":"Shopping",
            "subcategory":"Gifts & Souvenirs",
            "type":"Retail Goods"
        }
    ],
    "sg:phone":"+1   ",
    "sg:postcode":"13045",
    "sg:province":"NY",
    "wof:name":"Harp and Dragon",
    "wof:placetype":"venue"
},
  "geometry": {"coordinates":[-76.182244,42.604472],"type":"Point"}
}