{
  "type": "Feature",
  "properties": {
    "iso:country":"US",
    "sg:address":"2003 Jerome Ave",
    "sg:city":"Bronx",
    "sg:classifiers":[
        {
            "category":"Restaurant",
            "type":"Food & Drink"
        }
    ],
    "sg:phone":"+1 718 299 0223",
    "sg:postcode":"10453",
    "sg:province":"NY",
    "wof:name":"Rey Del Sol Div",
    "wof:placetype":"venue"
},
  "geometry": {"coordinates":[-73.908759,40.852295],"type":"Point"}
}