{
  "type": "Feature",
  "properties": {
    "addr:full":"2003 Jerome Ave Bronx NY 10453",
    "addr:housenumber":"2003",
    "addr:postcode":"10453",
    "addr:street":"Jerome Ave",
    "iso:country":"US",
    "sg:address":"2003 Jerome Ave",
    "sg:city":"Bronx",
    "sg:classifiers":[
        {
            "category":"Restaurant",
            "type":"Food & Drink"
        }
    ],
    "sg:phone":"+1 718 299 0223",
    "sg:postcode":"10453",
    "sg:province":"NY",
    "wof:name":"Rey Del Sol Div",
    "wof:placetype":"venue"
},
  "geometry": {"coordinates":[-73.908759,40.852295],"type":"Point"}
}