{
  "type": "Feature",
  "properties": {
    "iso:country":"US",
    "sg:address":"2733 Frederick Douglass B",
    "sg:city":"New York",
    "sg:classifiers":[
        {
            "category":"Restaurant",
            "type":"Food & Drink"
        }
    ],
    "sg:phone":"+1 212 281 3830",
    "sg:postcode":"10039",
    "sg:province":"NY",
    "sg:tags":[
        "caribbean"
    ],
    "wof:name":"People's Choice",
    "wof:placetype":"venue"
},
  "geometry": {"coordinates":[-73.941805,40.823019],"type":"Point"}
}