{
  "type": "Feature",
  "properties": {
    "addr:full":"15 Palisade Ave Yonkers NY 10701",
    "addr:housenumber":"15",
    "addr:postcode":"10701",
    "addr:street":"Palisade Ave",
    "iso:country":"US",
    "sg:address":"15 Palisade Ave",
    "sg:city":"Yonkers",
    "sg:classifiers":[
        {
            "category":"Banks & Credit Unions",
            "subcategory":"Bank",
            "type":"Services"
        }
    ],
    "sg:phone":"+1 914 476 5332",
    "sg:postcode":"10701",
    "sg:province":"NY",
    "sg:tags":[
        "brokerage"
    ],
    "wof:name":"Supreme Funding LLC",
    "wof:placetype":"venue"
},
  "geometry": {"coordinates":[-73.89578,40.93457],"type":"Point"}
}