{
  "type": "Feature",
  "properties": {
    "iso:country":"US",
    "sg:address":"1641 Broadway",
    "sg:city":"Brooklyn",
    "sg:classifiers":[
        {
            "category":"Home & Garden",
            "subcategory":"Building Materials",
            "type":"Retail Goods"
        }
    ],
    "sg:phone":"+1   ",
    "sg:postcode":"11207",
    "sg:province":"NY",
    "wof:name":"Bayne Walter Glass Co",
    "wof:placetype":"venue"
},
  "geometry": {"coordinates":[-73.91423500000001,40.685226],"type":"Point"}
}