{
  "type": "Feature",
  "properties": {
    "addr:full":"18357 N Harbor Rd Adams Center NY 13606",
    "addr:housenumber":"18357",
    "addr:postcode":"13606",
    "addr:street":"N Harbor Rd",
    "iso:country":"US",
    "sg:address":"18357 N Harbor Rd",
    "sg:city":"Adams Center",
    "sg:classifiers":[
        {
            "category":"Building & Trades",
            "subcategory":"Pest Control",
            "type":"Services"
        }
    ],
    "sg:phone":"+1   ",
    "sg:postcode":"13606",
    "sg:province":"NY",
    "wof:name":"All Season Pest Control Inc",
    "wof:placetype":"venue"
},
  "geometry": {"coordinates":[-76.015112,43.873327],"type":"Point"}
}