{
  "type": "Feature",
  "properties": {
    "addr:full":"40 Buffalo St Hamburg NY 14075",
    "addr:housenumber":"40",
    "addr:postcode":"14075",
    "addr:street":"Buffalo St",
    "iso:country":"US",
    "sg:address":"40 Buffalo St",
    "sg:city":"Hamburg",
    "sg:classifiers":[
        {
            "category":"Restaurant",
            "type":"Food & Drink"
        }
    ],
    "sg:phone":"+1 716 648 4750",
    "sg:postcode":"14075",
    "sg:province":"NY",
    "wof:name":"John & Mary's",
    "wof:placetype":"venue"
},
  "geometry": {"coordinates":[-78.829419,42.716521],"type":"Point"}
}