{
  "type": "Feature",
  "properties": {
    "addr:full":"76 Bathgate St Staten Island NY 10312",
    "addr:housenumber":"76",
    "addr:postcode":"10312",
    "addr:street":"Bathgate St",
    "iso:country":"US",
    "sg:address":"76 Bathgate St",
    "sg:city":"Staten Island",
    "sg:classifiers":[
        {
            "category":"Building & Trades",
            "subcategory":"Electrical",
            "type":"Services"
        }
    ],
    "sg:phone":"+1 718 668 1908",
    "sg:postcode":"10312",
    "sg:province":"NY",
    "sg:tags":[
        "electric",
        "contractor"
    ],
    "wof:name":"A & M Electrical Svc",
    "wof:placetype":"venue"
},
  "geometry": {"coordinates":[-74.161419,40.530032],"type":"Point"}
}