{
  "type": "Feature",
  "properties": {
    "addr:full":"3706 Heatherwood Dr Hamburg NY 14075",
    "addr:housenumber":"3706",
    "addr:postcode":"14075",
    "addr:street":"Heatherwood Dr",
    "iso:country":"US",
    "sg:address":"3706 Heatherwood Dr",
    "sg:city":"Hamburg",
    "sg:classifiers":[
        {
            "category":"Professional",
            "type":"Services"
        }
    ],
    "sg:phone":"+1   ",
    "sg:postcode":"14075",
    "sg:province":"NY",
    "wof:name":"Linda Kemp",
    "wof:placetype":"venue"
},
  "geometry": {"coordinates":[-78.84625200000001,42.76192],"type":"Point"}
}