{
  "type": "Feature",
  "properties": {
    "iso:country":"US",
    "sg:address":"100 Park Ave",
    "sg:city":"Herkimer",
    "sg:classifiers":[
        {
            "category":"Manufacturing",
            "subcategory":"Printing",
            "type":"Manufacturing & Wholesale Goods"
        }
    ],
    "sg:phone":"+1 315 866 1600",
    "sg:postcode":"13350",
    "sg:province":"NY",
    "sg:tags":[
        "newspaper"
    ],
    "wof:name":"Observer Dispatch",
    "wof:placetype":"venue"
},
  "geometry": {"coordinates":[-74.987105,43.026588],"type":"Point"}
}