{
  "type": "Feature",
  "properties": {
    "addr:full":"233 W 10th St New York NY 10014",
    "addr:housenumber":"233",
    "addr:postcode":"10014",
    "addr:street":"W 10Th St",
    "iso:country":"US",
    "sg:address":"233 W 10th St",
    "sg:city":"New York",
    "sg:classifiers":[
        {
            "category":"Government",
            "subcategory":"Police Station",
            "type":"Public Place"
        },
        {
            "category":"Landmark",
            "subcategory":"Historic",
            "type":"Public Place"
        }
    ],
    "sg:phone":"+1 212 741 4811",
    "sg:postcode":"10014",
    "sg:province":"NY",
    "sg:tags":[
        "building",
        "department",
        "historical"
    ],
    "sg:website":"www.nyc.gov/html/nypd/html/preci...",
    "wof:name":"NYPD - 6th Precinct",
    "wof:placetype":"venue"
},
  "geometry": {"coordinates":[-74.00541699999999,40.733893],"type":"Point"}
}