{
  "type": "Feature",
  "properties": {
    "addr:full":"3738 72nd St Jackson Heights NY 11372",
    "addr:housenumber":"3738",
    "addr:postcode":"11372",
    "addr:street":"72Nd St",
    "iso:country":"US",
    "sg:address":"3738 72nd St",
    "sg:city":"Jackson Heights",
    "sg:classifiers":[
        {
            "category":"Food & Beverages",
            "subcategory":"Ethnic Foods",
            "type":"Retail Goods"
        }
    ],
    "sg:phone":"+1 718 457 7766",
    "sg:postcode":"11372",
    "sg:province":"NY",
    "wof:name":"Tawa Food",
    "wof:placetype":"venue"
},
  "geometry": {"coordinates":[-73.893997,40.747799],"type":"Point"}
}