{
  "type": "Feature",
  "properties": {
    "addr:full":"22 N Park St Exd Cambridge NY 12816",
    "addr:housenumber":"22",
    "addr:postcode":"12816",
    "addr:street":"N Park St Exd",
    "iso:country":"US",
    "sg:address":"22 N Park St Exd",
    "sg:city":"Cambridge",
    "sg:classifiers":[
        {
            "category":"Health Services",
            "subcategory":"Doctor",
            "type":"Services"
        }
    ],
    "sg:phone":"+1 518 677 2626",
    "sg:postcode":"12816",
    "sg:province":"NY",
    "sg:tags":[
        "medical"
    ],
    "wof:name":"Ellen Biggers",
    "wof:placetype":"venue"
},
  "geometry": {"coordinates":[-73.376441,43.032689],"type":"Point"}
}