{
  "type": "Feature",
  "properties": {
    "addr:full":"5 Oak Ridge Rd Hopewell Junction NY 12533",
    "addr:housenumber":"5",
    "addr:postcode":"12533",
    "addr:street":"Oak Ridge Rd",
    "iso:country":"US",
    "sg:address":"5 Oak Ridge Rd",
    "sg:city":"Hopewell Junction",
    "sg:classifiers":[
        {
            "category":"Insurance",
            "subcategory":"Life Insurance",
            "type":"Services"
        }
    ],
    "sg:phone":"+1 845 221 1193",
    "sg:postcode":"12533",
    "sg:province":"NY",
    "wof:name":"Equitable Life Assurance",
    "wof:placetype":"venue"
},
  "geometry": {"coordinates":[-73.79419300000001,41.580299],"type":"Point"}
}