{
  "type": "Feature",
  "properties": {
    "iso:country":"US",
    "sg:address":"3801 Broadway",
    "sg:city":"Astoria",
    "sg:classifiers":[
        {
            "category":"Personal",
            "subcategory":"Barber",
            "type":"Services"
        }
    ],
    "sg:phone":"+1 718 545 6900",
    "sg:postcode":"11103",
    "sg:province":"NY",
    "wof:name":"Enrique & Ramon Barbershop",
    "wof:placetype":"venue"
},
  "geometry": {"coordinates":[-73.919712,40.759473],"type":"Point"}
}