{
  "type": "Feature",
  "properties": {
    "iso:country":"US",
    "sg:address":"845 Cayuga St",
    "sg:city":"Lewiston",
    "sg:classifiers":[
        {
            "category":"Sports & Exercise",
            "subcategory":"Bowling",
            "type":"Entertainment"
        },
        {
            "category":"Shopping",
            "subcategory":"Bicycles & Sporting Goods",
            "type":"Retail Goods"
        }
    ],
    "sg:phone":"+1 716 754 8248",
    "sg:postcode":"14092",
    "sg:province":"NY",
    "sg:tags":[
        "apparel",
        "alley",
        "accessory"
    ],
    "wof:name":"Frontier Lanes Inc",
    "wof:placetype":"venue"
},
  "geometry": {"coordinates":[-79.035938,43.170888],"type":"Point"}
}