{
  "type": "Feature",
  "properties": {
    "addr:full":"1839 Gilford Ave New Hyde Park NY 11040",
    "addr:housenumber":"1839",
    "addr:postcode":"11040",
    "addr:street":"Gilford Ave",
    "iso:country":"US",
    "sg:address":"1839 Gilford Ave",
    "sg:city":"New Hyde Park",
    "sg:classifiers":[
        {
            "category":"Retail",
            "subcategory":"Auto Repair",
            "type":"Services"
        }
    ],
    "sg:phone":"+1 516 616 5404",
    "sg:postcode":"11040",
    "sg:province":"NY",
    "sg:tags":[
        "body",
        "shop"
    ],
    "wof:name":"Tip-Top Auto Body",
    "wof:placetype":"venue"
},
  "geometry": {"coordinates":[-73.672096,40.742699],"type":"Point"}
}