{
  "type": "Feature",
  "properties": {
    "iso:country":"US",
    "sg:address":"1573 Co Rte 4",
    "sg:city":"Central Square",
    "sg:classifiers":[
        {
            "category":"Building & Trades",
            "subcategory":"Construction",
            "type":"Services"
        }
    ],
    "sg:phone":"+1 315 598 3440",
    "sg:postcode":"13036",
    "sg:province":"NY",
    "sg:tags":[
        "contractor"
    ],
    "wof:name":"Creighton Contracting",
    "wof:placetype":"venue"
},
  "geometry": {"coordinates":[-76.241659,43.36728],"type":"Point"}
}