{
  "type": "Feature",
  "properties": {
    "addr:full":"2 E Village Grn Levittown NY 11756",
    "addr:housenumber":"2",
    "addr:postcode":"11756",
    "addr:street":"E Village Grn",
    "iso:country":"US",
    "sg:address":"2 E Village Grn",
    "sg:city":"Levittown",
    "sg:classifiers":[
        {
            "category":"Social Services",
            "subcategory":"Child Care",
            "type":"Services"
        }
    ],
    "sg:phone":"+1 516 731 3263",
    "sg:postcode":"11756",
    "sg:province":"NY",
    "sg:tags":[
        "day"
    ],
    "wof:name":"Teachers Pets Child Care Centers Inc",
    "wof:placetype":"venue"
},
  "geometry": {"coordinates":[-73.5112,40.739201],"type":"Point"}
}