{
  "type": "Feature",
  "properties": {
    "addr:full":"7935 New Floyd Rd Rome NY 13440",
    "addr:housenumber":"7935",
    "addr:postcode":"13440",
    "addr:street":"New Floyd Rd",
    "iso:country":"US",
    "sg:address":"7935 New Floyd Rd",
    "sg:city":"Rome",
    "sg:classifiers":[
        {
            "category":"Retail",
            "subcategory":"Auto Repair",
            "type":"Services"
        }
    ],
    "sg:phone":"+1   ",
    "sg:postcode":"13440",
    "sg:province":"NY",
    "sg:tags":[
        "body"
    ],
    "wof:name":"Ricks Body Shop",
    "wof:placetype":"venue"
},
  "geometry": {"coordinates":[-75.363714,43.211473],"type":"Point"}
}