{
  "type": "Feature",
  "properties": {
    "addr:full":"200 Seth Green Dr Rochester NY 14621",
    "addr:housenumber":"200",
    "addr:postcode":"14621",
    "addr:street":"Seth Green Dr",
    "iso:country":"US",
    "sg:address":"200 Seth Green Dr",
    "sg:city":"Rochester",
    "sg:classifiers":[
        {
            "category":"Real Estate",
            "subcategory":"Real Estate Operator",
            "type":"Services"
        }
    ],
    "sg:phone":"+1 585 467 3727",
    "sg:postcode":"14621",
    "sg:province":"NY",
    "sg:tags":[
        "apartment"
    ],
    "wof:name":"Seneca Towers",
    "wof:placetype":"venue"
},
  "geometry": {"coordinates":[-77.621556,43.188847],"type":"Point"}
}