{
  "type": "Feature",
  "properties": {
    "addr:full":"2658 Arthur Ln Bellmore NY 11710",
    "addr:housenumber":"2658",
    "addr:postcode":"11710",
    "addr:street":"Arthur Ln",
    "iso:country":"US",
    "sg:address":"2658 Arthur Ln",
    "sg:city":"Bellmore",
    "sg:classifiers":[
        {
            "category":"Insurance",
            "subcategory":"Insurance Agent",
            "type":"Services"
        }
    ],
    "sg:phone":"+1 516 783 6107",
    "sg:postcode":"11710",
    "sg:province":"NY",
    "wof:name":"Steve Kaneris Insurance",
    "wof:placetype":"venue"
},
  "geometry": {"coordinates":[-73.529464,40.673878],"type":"Point"}
}