{
  "type": "Feature",
  "properties": {
    "iso:country":"US",
    "sg:address":"501 South St",
    "sg:city":"Utica",
    "sg:classifiers":[
        {
            "category":"Retail",
            "subcategory":"Auto Repair",
            "type":"Services"
        }
    ],
    "sg:phone":"+1 315 732 5555",
    "sg:postcode":"13501",
    "sg:province":"NY",
    "sg:tags":[
        "automobile",
        "lubrication"
    ],
    "wof:name":"Quick Change Inc",
    "wof:placetype":"venue"
},
  "geometry": {"coordinates":[-75.224835,43.093337],"type":"Point"}
}