{
  "type": "Feature",
  "properties": {
    "addr:full":"108 Fir St Valley Stream NY 11580",
    "addr:housenumber":"108",
    "addr:postcode":"11580",
    "addr:street":"Fir St",
    "iso:country":"US",
    "sg:address":"108 Fir St",
    "sg:city":"Valley Stream",
    "sg:classifiers":[
        {
            "category":"Health Services",
            "subcategory":"Optometrist",
            "type":"Services"
        }
    ],
    "sg:phone":"+1 516 825 2848",
    "sg:postcode":"11580",
    "sg:province":"NY",
    "wof:name":"Purvin Arthur M Od",
    "wof:placetype":"venue"
},
  "geometry": {"coordinates":[-73.72196599999999,40.666755],"type":"Point"}
}