{
  "type": "Feature",
  "properties": {
    "addr:full":"40 W 57th St New York NY 10019",
    "addr:housenumber":"40",
    "addr:postcode":"10019",
    "addr:street":"W 57Th St",
    "iso:country":"US",
    "sg:address":"40 W 57th St",
    "sg:city":"New York",
    "sg:classifiers":[
        {
            "category":"Professional",
            "subcategory":"Lawyer & Legal Services",
            "type":"Services"
        }
    ],
    "sg:phone":"+1 212 974 7474",
    "sg:postcode":"10019",
    "sg:province":"NY",
    "wof:name":"Swevey Kenneth Atty",
    "wof:placetype":"venue"
},
  "geometry": {"coordinates":[-73.97519699999999,40.7635],"type":"Point"}
}