{
  "type": "Feature",
  "properties": {
    "iso:country":"US",
    "sg:address":"887 Prospect Ave",
    "sg:city":"Buffalo",
    "sg:classifiers":[
        {
            "category":"Recreation",
            "type":"Entertainment"
        }
    ],
    "sg:phone":"+1 716 885 2710",
    "sg:postcode":"14213",
    "sg:province":"NY",
    "sg:tags":[
        "martial",
        "arts",
        "instruction"
    ],
    "wof:name":"Barkley's Taekwon-Do",
    "wof:placetype":"venue"
},
  "geometry": {"coordinates":[-78.89921200000001,42.910559],"type":"Point"}
}