{
  "type": "Feature",
  "properties": {
    "addr:full":"215 E Lakewood St Patchogue NY 11772",
    "addr:housenumber":"215",
    "addr:postcode":"11772",
    "addr:street":"E Lakewood St",
    "iso:country":"US",
    "sg:address":"215 E Lakewood St",
    "sg:city":"Patchogue",
    "sg:classifiers":[
        {
            "category":"Autos & Motor Vehicles",
            "subcategory":"Boat Sales",
            "type":"Retail Goods"
        }
    ],
    "sg:phone":"+1   ",
    "sg:postcode":"11772",
    "sg:province":"NY",
    "wof:name":"Coast To Coast Boat Trnspt Lt",
    "wof:placetype":"venue"
},
  "geometry": {"coordinates":[-73.00311600000001,40.773203],"type":"Point"}
}