{
  "type": "Feature",
  "properties": {
    "addr:full":"9 Pine Dr Port Washington NY 11050",
    "addr:housenumber":"9",
    "addr:postcode":"11050",
    "addr:street":"Pine Dr",
    "iso:country":"US",
    "sg:address":"9 Pine Dr",
    "sg:city":"Port Washington",
    "sg:classifiers":[
        {
            "category":"Social Services",
            "type":"Services"
        }
    ],
    "sg:phone":"+1 516 883 0528",
    "sg:postcode":"11050",
    "sg:province":"NY",
    "sg:tags":[
        "counselor",
        "marriage",
        "family"
    ],
    "wof:name":"Sandra Rosengarten",
    "wof:placetype":"venue"
},
  "geometry": {"coordinates":[-73.70391600000001,40.825419],"type":"Point"}
}