{
  "type": "Feature",
  "properties": {
    "addr:full":"1400 Mount Hope Ave Rochester NY 14620",
    "addr:housenumber":"1400",
    "addr:postcode":"14620",
    "addr:street":"Mount Hope Ave",
    "iso:country":"US",
    "sg:address":"1400 Mount Hope Ave",
    "sg:city":"Rochester",
    "sg:classifiers":[
        {
            "category":"Food Court",
            "type":"Food & Drink"
        },
        {
            "category":"Restaurant",
            "type":"Food & Drink"
        },
        {
            "category":"Bagels",
            "subcategory":"None",
            "type":"Food & Drink"
        },
        {
            "category":"Coffee & Tea",
            "type":"Food & Drink"
        },
        {
            "category":"Bakery",
            "type":"Food & Drink"
        },
        {
            "category":"Food & Beverages",
            "subcategory":"Groceries & Convenience Stores",
            "type":"Retail Goods"
        }
    ],
    "sg:phone":"+1 585 442 4860",
    "sg:postcode":"14620",
    "sg:province":"NY",
    "sg:tags":[
        "shop",
        "box",
        "sandwich",
        "espresso",
        "lunch",
        "brunch",
        "breakfast"
    ],
    "sg:website":"http://www.brueggers.com",
    "wof:name":"Bruegger's",
    "wof:placetype":"venue"
},
  "geometry": {"coordinates":[-77.61846300000001,43.122701],"type":"Point"}
}