{
  "type": "Feature",
  "properties": {
    "addr:full":"51 Auerbach Ln Lawrence NY 11559",
    "addr:housenumber":"51",
    "addr:postcode":"11559",
    "addr:street":"Auerbach Ln",
    "iso:country":"US",
    "sg:address":"51 Auerbach Ln",
    "sg:city":"Lawrence",
    "sg:classifiers":[
        {
            "category":"Wholesale",
            "subcategory":"Motor Vehicles",
            "type":"Manufacturing & Wholesale Goods"
        }
    ],
    "sg:phone":"+1 516 908 4365",
    "sg:postcode":"11559",
    "sg:province":"NY",
    "sg:tags":[
        "automobile",
        "truck",
        "broker"
    ],
    "wof:name":"Lender Services LLC",
    "wof:placetype":"venue"
},
  "geometry": {"coordinates":[-73.71886499999999,40.617089],"type":"Point"}
}