{
  "type": "Feature",
  "properties": {
    "addr:full":"564 Amsterdam Ave Frnt 1 New York NY 10024",
    "addr:housenumber":"564;1",
    "addr:postcode":"10024",
    "addr:street":"Amsterdam Ave Frnt",
    "iso:country":"US",
    "sg:address":"564 Amsterdam Ave Frnt 1",
    "sg:city":"New York",
    "sg:classifiers":[
        {
            "category":"Personal",
            "subcategory":"Day Spa",
            "type":"Services"
        }
    ],
    "sg:phone":"+1 212 362 3301",
    "sg:postcode":"10024",
    "sg:province":"NY",
    "wof:name":"Beauty Zone Spa",
    "wof:placetype":"venue"
},
  "geometry": {"coordinates":[-73.97454399999999,40.788597],"type":"Point"}
}