{
  "type": "Feature",
  "properties": {
    "addr:full":"147 Hoosick St Troy NY 12180",
    "addr:housenumber":"147",
    "addr:postcode":"12180",
    "addr:street":"Hoosick St",
    "iso:country":"US",
    "sg:address":"147 Hoosick St",
    "sg:city":"Troy",
    "sg:classifiers":[
        {
            "category":"Health Services",
            "subcategory":"Doctor",
            "type":"Services"
        }
    ],
    "sg:phone":"+1 518 268 5380",
    "sg:postcode":"12180",
    "sg:province":"NY",
    "sg:tags":[
        "physician",
        "surgeon"
    ],
    "wof:name":"Seton Incontinence & Wound Svc",
    "wof:placetype":"venue"
},
  "geometry": {"coordinates":[-73.678922,42.73947],"type":"Point"}
}