{
  "type": "Feature",
  "properties": {
    "addr:full":"7254 County Route 27 Canton NY 13617",
    "addr:housenumber":"7254",
    "addr:postcode":"13617",
    "addr:street":"County Route 27",
    "iso:country":"US",
    "sg:address":"7254 County Route 27",
    "sg:city":"Canton",
    "sg:classifiers":[
        {
            "category":"Place Of Worship",
            "type":"Public Place"
        }
    ],
    "sg:phone":"+1 315 386 3342",
    "sg:postcode":"13617",
    "sg:province":"NY",
    "sg:tags":[
        "church"
    ],
    "wof:name":"Morley Wesleyan Church",
    "wof:placetype":"venue"
},
  "geometry": {"coordinates":[-75.197746,44.664695],"type":"Point"}
}