{
  "type": "Feature",
  "properties": {
    "addr:full":"2647 Main St Niagara Falls NY 14305",
    "addr:housenumber":"2647",
    "addr:postcode":"14305",
    "addr:street":"Main St",
    "iso:country":"US",
    "sg:address":"2647 Main St",
    "sg:city":"Niagara Falls",
    "sg:classifiers":[
        {
            "category":"Restaurant",
            "type":"Food & Drink"
        }
    ],
    "sg:phone":"+1   ",
    "sg:postcode":"14305",
    "sg:province":"NY",
    "sg:tags":[
        "eating"
    ],
    "wof:name":"La Palermo Restaurant",
    "wof:placetype":"venue"
},
  "geometry": {"coordinates":[-79.05525400000001,43.112723],"type":"Point"}
}