{
  "type": "Feature",
  "properties": {
    "addr:full":"221 W High St Ballston Spa NY 12020",
    "addr:housenumber":"221",
    "addr:postcode":"12020",
    "addr:street":"W High St",
    "iso:country":"US",
    "sg:address":"221 W High St",
    "sg:city":"Ballston Spa",
    "sg:classifiers":[
        {
            "category":"Health Services",
            "subcategory":"Chiropractor",
            "type":"Services"
        }
    ],
    "sg:phone":"+1 518 885 8999",
    "sg:postcode":"12020",
    "sg:province":"NY",
    "wof:name":"Roger L Pitman DC",
    "wof:placetype":"venue"
},
  "geometry": {"coordinates":[-73.86026699999999,42.99988],"type":"Point"}
}