{
  "type": "Feature",
  "properties": {
    "iso:country":"US",
    "sg:address":"223 E Felton St",
    "sg:city":"North Tonawanda",
    "sg:classifiers":[
        {
            "category":"Insurance",
            "subcategory":"Insurance Agent",
            "type":"Services"
        }
    ],
    "sg:phone":"+1 716 693 0117",
    "sg:postcode":"14120",
    "sg:province":"NY",
    "wof:name":"Afco Credit Corporation",
    "wof:placetype":"venue"
},
  "geometry": {"coordinates":[-78.884112,43.05421],"type":"Point"}
}