{
  "type": "Feature",
  "properties": {
    "addr:full":"11187 Southwestern Blvd Irving NY 14081",
    "addr:housenumber":"11187",
    "addr:postcode":"14081",
    "addr:street":"Southwestern Blvd",
    "iso:country":"US",
    "sg:address":"11187 Southwestern Blvd",
    "sg:city":"Irving",
    "sg:classifiers":[
        {
            "category":"Food & Beverages",
            "subcategory":"Meat & Fish",
            "type":"Retail Goods"
        }
    ],
    "sg:phone":"+1 716 549 7706",
    "sg:postcode":"14081",
    "sg:province":"NY",
    "sg:tags":[
        "smoking",
        "curing"
    ],
    "wof:name":"J R's Enterprise",
    "wof:placetype":"venue"
},
  "geometry": {"coordinates":[-79.062393,42.587204],"type":"Point"}
}