{
  "type": "Feature",
  "properties": {
    "iso:country":"US",
    "sg:address":"5300 S Salina St",
    "sg:city":"Syracuse",
    "sg:classifiers":[
        {
            "category":"Professional",
            "subcategory":"Computer Services",
            "type":"Services"
        }
    ],
    "sg:phone":"+1 315 701 0857",
    "sg:postcode":"13205",
    "sg:province":"NY",
    "sg:tags":[
        "design",
        "system"
    ],
    "wof:name":"Jeff Vahey",
    "wof:placetype":"venue"
},
  "geometry": {"coordinates":[-76.143838,42.992799],"type":"Point"}
}