{
  "type": "Feature",
  "properties": {
    "addr:full":"3514 Delaware Ave Buffalo NY 14217",
    "addr:housenumber":"3514",
    "addr:postcode":"14217",
    "addr:street":"Delaware Ave",
    "iso:country":"US",
    "sg:address":"3514 Delaware Ave",
    "sg:city":"Buffalo",
    "sg:classifiers":[
        {
            "category":"Autos & Motor Vehicles",
            "subcategory":"Auto Supplies",
            "type":"Retail Goods"
        },
        {
            "category":"Wholesale",
            "subcategory":"Electrical",
            "type":"Manufacturing & Wholesale Goods"
        },
        {
            "category":"Wholesale",
            "subcategory":"Auto Parts",
            "type":"Manufacturing & Wholesale Goods"
        }
    ],
    "sg:phone":"+1 716 875 8750",
    "sg:postcode":"14217",
    "sg:province":"NY",
    "sg:tags":[
        "battery",
        "automobile",
        "accessory",
        "equipment",
        "truck",
        "engines-supplies"
    ],
    "sg:website":"http://ad.doubleclick.net/clk;221862232;45455595;j?http://www.carquest.com/carquest/store_locator.html",
    "wof:name":"CARQUEST Auto Parts",
    "wof:placetype":"venue"
},
  "geometry": {"coordinates":[-78.87217099999999,42.979833],"type":"Point"}
}