{
  "type": "Feature",
  "properties": {
    "iso:country":"US",
    "sg:address":"357 E 62nd Street",
    "sg:city":"New York",
    "sg:classifiers":[
        {
            "category":"Personal",
            "subcategory":"Skin Care",
            "type":"Services"
        }
    ],
    "sg:phone":"+1 212 230 1345",
    "sg:postcode":"10021",
    "sg:province":"NY",
    "sg:website":"www.leahsskincare.com",
    "wof:name":"Leah's Skin Care",
    "wof:placetype":"venue"
},
  "geometry": {"coordinates":[-73.962081,40.761967],"type":"Point"}
}