{
  "type": "Feature",
  "properties": {
    "addr:full":"1270 Webster Ave Bronx NY 10456",
    "addr:housenumber":"1270",
    "addr:postcode":"10456",
    "addr:street":"Webster Ave",
    "iso:country":"US",
    "sg:address":"1270 Webster Ave",
    "sg:city":"Bronx",
    "sg:classifiers":[
        {
            "category":"Shopping",
            "subcategory":"Jewelry",
            "type":"Retail Goods"
        }
    ],
    "sg:phone":"+1 347 879 7509",
    "sg:postcode":"10456",
    "sg:province":"NY",
    "sg:tags":[
        "pearl"
    ],
    "wof:name":"Lauren Precious Pearls",
    "wof:placetype":"venue"
},
  "geometry": {"coordinates":[-73.909047,40.833269],"type":"Point"}
}