{
  "type": "Feature",
  "properties": {
    "iso:country":"US",
    "sg:address":"615 Allen St",
    "sg:city":"Syracuse",
    "sg:classifiers":[
        {
            "category":"Professional",
            "subcategory":"Lawyer & Legal Services",
            "type":"Services"
        }
    ],
    "sg:phone":"+1 315 471 2413",
    "sg:postcode":"13210",
    "sg:province":"NY",
    "sg:tags":[
        "attorney"
    ],
    "wof:name":"William S Andrews",
    "wof:placetype":"venue"
},
  "geometry": {"coordinates":[-76.11649300000001,43.041229],"type":"Point"}
}