{
  "type": "Feature",
  "properties": {
    "iso:country":"US",
    "sg:address":"127 Dovecote Ln",
    "sg:city":"Central Islip",
    "sg:classifiers":[
        {
            "category":"Professional",
            "subcategory":"Management & Consulting",
            "type":"Services"
        }
    ],
    "sg:phone":"+1   ",
    "sg:postcode":"11722",
    "sg:province":"NY",
    "sg:tags":[
        "telecommunication",
        "business"
    ],
    "sg:website":"www.callcenter-results.com",
    "wof:name":"Call Center Results",
    "wof:placetype":"venue"
},
  "geometry": {"coordinates":[-73.18911300000001,40.793599],"type":"Point"}
}