{
  "type": "Feature",
  "properties": {
    "addr:full":"4180 White Plains Rd Bronx NY 10466",
    "addr:housenumber":"4180",
    "addr:postcode":"10466",
    "addr:street":"White Plains Rd",
    "iso:country":"US",
    "sg:address":"4180 White Plains Rd",
    "sg:city":"Bronx",
    "sg:classifiers":[
        {
            "category":"Restaurant",
            "type":"Food & Drink"
        }
    ],
    "sg:menulink":"http://www.allmenus.com/ny/bronx/156778-kennedy-fried-chicken--pizza/menu/",
    "sg:phone":"+1 718 994 7599",
    "sg:postcode":"10466",
    "sg:province":"NY",
    "sg:tags":[
        "american",
        "pizza"
    ],
    "wof:name":"Kennedy Fried Chicken & Pizza",
    "wof:placetype":"venue"
},
  "geometry": {"coordinates":[-73.85770100000001,40.892977],"type":"Point"}
}