{
  "type": "Feature",
  "properties": {
    "addr:full":"1420 Williamsbridge Rd Bronx NY 10461",
    "addr:housenumber":"1420",
    "addr:postcode":"10461",
    "addr:street":"Williamsbridge Rd",
    "iso:country":"US",
    "sg:address":"1420 Williamsbridge Rd",
    "sg:city":"Bronx",
    "sg:classifiers":[
        {
            "category":"Shopping",
            "type":"Retail Goods"
        },
        {
            "category":"Shopping",
            "subcategory":"Gifts & Souvenirs",
            "type":"Retail Goods"
        }
    ],
    "sg:phone":"+1 718 597 0668",
    "sg:postcode":"10461",
    "sg:province":"NY",
    "sg:tags":[
        "cards",
        "sport",
        "baseball",
        "memorabilia"
    ],
    "wof:name":"Cosmo's Cards & Collectables",
    "wof:placetype":"venue"
},
  "geometry": {"coordinates":[-73.84433900000001,40.842413],"type":"Point"}
}