{
  "type": "Feature",
  "properties": {
    "addr:full":"6218 11th Ave Brooklyn NY 11219",
    "addr:housenumber":"6218",
    "addr:postcode":"11219",
    "addr:street":"11Th Ave",
    "iso:country":"US",
    "sg:address":"6218 11th Ave",
    "sg:city":"Brooklyn",
    "sg:classifiers":[
        {
            "category":"Restaurant",
            "type":"Food & Drink"
        }
    ],
    "sg:phone":"+1 718 833 0676",
    "sg:postcode":"11219",
    "sg:province":"NY",
    "sg:tags":[
        "out"
    ],
    "wof:name":"New China",
    "wof:placetype":"venue"
},
  "geometry": {"coordinates":[-74.004696,40.629953],"type":"Point"}
}