{
  "type": "Feature",
  "properties": {
    "iso:country":"US",
    "sg:address":"20 N Mac Questen Pkwy",
    "sg:city":"Mt Vernon",
    "sg:classifiers":[
        {
            "category":"Manufacturing",
            "subcategory":"Tools & Machinery",
            "type":"Manufacturing & Wholesale Goods"
        }
    ],
    "sg:phone":"+1 914 699 1616",
    "sg:postcode":"10550",
    "sg:province":"NY",
    "sg:tags":[
        "devices"
    ],
    "wof:name":"Mc Nab Inc",
    "wof:placetype":"venue"
},
  "geometry": {"coordinates":[-73.847757,40.914154],"type":"Point"}
}