{
  "type": "Feature",
  "properties": {
    "addr:full":"305 Amsterdam Ave New York NY 10023",
    "addr:housenumber":"305",
    "addr:postcode":"10023",
    "addr:street":"Amsterdam Ave",
    "iso:country":"US",
    "sg:address":"305 Amsterdam Ave",
    "sg:city":"New York",
    "sg:classifiers":[
        {
            "category":"Personal",
            "subcategory":"Beauty Salon",
            "type":"Services"
        }
    ],
    "sg:phone":"+1   ",
    "sg:postcode":"10023",
    "sg:province":"NY",
    "sg:tags":[
        "shop"
    ],
    "wof:name":"Infinity Unisex Palace",
    "wof:placetype":"venue"
},
  "geometry": {"coordinates":[-73.980249,40.780334],"type":"Point"}
}