{
  "type": "Feature",
  "properties": {
    "addr:full":"3 Barker Ave White Plains NY 10601",
    "addr:housenumber":"3",
    "addr:postcode":"10601",
    "addr:street":"Barker Ave",
    "iso:country":"US",
    "sg:address":"3 Barker Ave",
    "sg:city":"White Plains",
    "sg:classifiers":[
        {
            "category":"Banks & Credit Unions",
            "subcategory":"Investment Brokerage",
            "type":"Services"
        }
    ],
    "sg:phone":"+1 914 948 1018",
    "sg:postcode":"10601",
    "sg:province":"NY",
    "sg:tags":[
        "security"
    ],
    "wof:name":"Westmont Venture Partners",
    "wof:placetype":"venue"
},
  "geometry": {"coordinates":[-73.770779,41.034542],"type":"Point"}
}