{
  "type": "Feature",
  "properties": {
    "addr:full":"505 E Lincoln Ave Mount Vernon NY 10552",
    "addr:housenumber":"505",
    "addr:postcode":"10552",
    "addr:street":"E Lincoln Ave",
    "iso:country":"US",
    "sg:address":"505 E Lincoln Ave",
    "sg:city":"Mount Vernon",
    "sg:classifiers":[
        {
            "category":"Health Services",
            "subcategory":"Doctor",
            "type":"Services"
        }
    ],
    "sg:phone":"+1 914 667 1602",
    "sg:postcode":"10552",
    "sg:province":"NY",
    "sg:tags":[
        "medical"
    ],
    "wof:name":"Maurice M D Ronel",
    "wof:placetype":"venue"
},
  "geometry": {"coordinates":[-73.82053500000001,40.917974],"type":"Point"}
}