{
  "type": "Feature",
  "properties": {
    "addr:full":"7307 Wakefield Dr Fayetteville NY 13066",
    "addr:housenumber":"7307",
    "addr:postcode":"13066",
    "addr:street":"Wakefield Dr",
    "iso:country":"US",
    "sg:address":"7307 Wakefield Dr",
    "sg:city":"Fayetteville",
    "sg:classifiers":[
        {
            "category":"Professional",
            "subcategory":"Lawyer & Legal Services",
            "type":"Services"
        }
    ],
    "sg:phone":"+1 315 637 4830",
    "sg:postcode":"13066",
    "sg:province":"NY",
    "sg:tags":[
        "attorney"
    ],
    "wof:name":"Thomas N Kaufmann",
    "wof:placetype":"venue"
},
  "geometry": {"coordinates":[-76.01719799999999,43.012899],"type":"Point"}
}