{
  "type": "Feature",
  "properties": {
    "iso:country":"US",
    "sg:address":"1846 Victor St",
    "sg:city":"Bronx",
    "sg:classifiers":[
        {
            "category":"Health Services",
            "subcategory":"Doctor",
            "type":"Services"
        }
    ],
    "sg:phone":"+1 718 892 0701",
    "sg:postcode":"10462",
    "sg:province":"NY",
    "sg:tags":[
        "physician",
        "surgeon"
    ],
    "wof:name":"Family Physician Ctr",
    "wof:placetype":"venue"
},
  "geometry": {"coordinates":[-73.867345,40.84626],"type":"Point"}
}