{
  "type": "Feature",
  "properties": {
    "addr:full":"3555 Bartz St Oceanside NY 11572",
    "addr:housenumber":"3555",
    "addr:postcode":"11572",
    "addr:street":"Bartz St",
    "iso:country":"US",
    "sg:address":"3555 Bartz St",
    "sg:city":"Oceanside",
    "sg:classifiers":[
        {
            "category":"Recreation",
            "subcategory":"Marina",
            "type":"Entertainment"
        }
    ],
    "sg:phone":"+1   ",
    "sg:postcode":"11572",
    "sg:province":"NY",
    "wof:name":"Baileys Marina Ltd Inc",
    "wof:placetype":"venue"
},
  "geometry": {"coordinates":[-73.658565,40.623931],"type":"Point"}
}