{
  "type": "Feature",
  "properties": {
    "iso:country":"US",
    "sg:address":"100 S Main St",
    "sg:city":"New City",
    "sg:classifiers":[
        {
            "category":"Wholesale",
            "subcategory":"Non-durable Goods",
            "type":"Manufacturing & Wholesale Goods"
        }
    ],
    "sg:phone":"+1 845 639 8145",
    "sg:postcode":"10956",
    "sg:province":"NY",
    "sg:tags":[
        "advertising"
    ],
    "wof:name":"RHB Marketing",
    "wof:placetype":"venue"
},
  "geometry": {"coordinates":[-73.98959499999999,41.146156],"type":"Point"}
}