{
  "type": "Feature",
  "properties": {
    "iso:country":"US",
    "sg:address":"692 Baldwin Ave",
    "sg:city":"North Baldwin",
    "sg:classifiers":[
        {
            "category":"Retail",
            "subcategory":"Repair Shop",
            "type":"Services"
        }
    ],
    "sg:phone":"+1 516 379 2577",
    "sg:postcode":"11510",
    "sg:province":"NY",
    "sg:tags":[
        "appliance"
    ],
    "wof:name":"Shawn Appliance Svc",
    "wof:placetype":"venue"
},
  "geometry": {"coordinates":[-73.61004200000001,40.658989],"type":"Point"}
}