{
  "type": "Feature",
  "properties": {
    "addr:full":"246 W 20th St New York NY 10011",
    "addr:housenumber":"246",
    "addr:postcode":"10011",
    "addr:street":"W 20Th St",
    "iso:country":"US",
    "sg:address":"246 W 20th St",
    "sg:city":"New York",
    "sg:classifiers":[
        {
            "category":"Professional",
            "type":"Services"
        }
    ],
    "sg:phone":"+1 212 924 0962",
    "sg:postcode":"10011",
    "sg:province":"NY",
    "wof:name":"National Lifetime Reminder Svc",
    "wof:placetype":"venue"
},
  "geometry": {"coordinates":[-73.998874,40.742797],"type":"Point"}
}