{
  "type": "Feature",
  "properties": {
    "addr:full":"95 Main St Canton NY 13617",
    "addr:housenumber":"95",
    "addr:postcode":"13617",
    "addr:street":"Main St",
    "iso:country":"US",
    "sg:address":"95 Main St",
    "sg:city":"Canton",
    "sg:classifiers":[
        {
            "category":"Real Estate",
            "subcategory":"Real Estate Agent",
            "type":"Services"
        }
    ],
    "sg:phone":"+1 315 386 1599",
    "sg:postcode":"13617",
    "sg:province":"NY",
    "wof:name":"Plumley Real Estate",
    "wof:placetype":"venue"
},
  "geometry": {"coordinates":[-75.170395,44.595597],"type":"Point"}
}