{
  "type": "Feature",
  "properties": {
    "addr:full":"176 Niagara Frontier Foo Buffalo NY 14206",
    "addr:housenumber":"176;frontier",
    "addr:postcode":"14206",
    "addr:street":"Niagara",
    "iso:country":"US",
    "sg:address":"176 Niagara Frontier Foo",
    "sg:city":"Buffalo",
    "sg:classifiers":[
        {
            "category":"Wholesale",
            "subcategory":"Groceries",
            "type":"Manufacturing & Wholesale Goods"
        }
    ],
    "sg:phone":"+1 716 826 7777",
    "sg:postcode":"14206",
    "sg:province":"NY",
    "sg:tags":[
        "food",
        "broker"
    ],
    "wof:name":"C T Militello Food Brokers",
    "wof:placetype":"venue"
},
  "geometry": {"coordinates":[-78.82143499999999,42.872921],"type":"Point"}
}