{
  "type": "Feature",
  "properties": {
    "iso:country":"US",
    "sg:address":"498 County Rd 111",
    "sg:city":"Manorville",
    "sg:classifiers":[
        {
            "category":"Autos & Motor Vehicles",
            "subcategory":"Fuel & Gas Station",
            "type":"Retail Goods"
        }
    ],
    "sg:phone":"+1 631 878 6655",
    "sg:postcode":"11949",
    "sg:province":"NY",
    "wof:name":"Mobil On the Run",
    "wof:placetype":"venue"
},
  "geometry": {"coordinates":[-72.737577,40.847464],"type":"Point"}
}