{
  "type": "Feature",
  "properties": {
    "addr:full":"2184 Nesconset Hwy Stony Brook NY 11790",
    "addr:housenumber":"2184",
    "addr:postcode":"11790",
    "addr:street":"Nesconset Hwy",
    "iso:country":"US",
    "sg:address":"2184 Nesconset Hwy",
    "sg:city":"Stony Brook",
    "sg:classifiers":[
        {
            "category":"Food & Beverages",
            "subcategory":"Bakery",
            "type":"Retail Goods"
        }
    ],
    "sg:phone":"+1 631 689 5091",
    "sg:postcode":"11790",
    "sg:province":"NY",
    "sg:tags":[
        "bagel"
    ],
    "wof:name":"Strathmore Bagels",
    "wof:placetype":"venue"
},
  "geometry": {"coordinates":[-73.106219,40.883482],"type":"Point"}
}