{
  "type": "Feature",
  "properties": {
    "addr:full":"660 Main St East Aurora NY 14052",
    "addr:housenumber":"660",
    "addr:postcode":"14052",
    "addr:street":"Main St",
    "iso:country":"US",
    "sg:address":"660 Main St",
    "sg:city":"East Aurora",
    "sg:classifiers":[
        {
            "category":"Shopping",
            "type":"Retail Goods"
        }
    ],
    "sg:phone":"+1   ",
    "sg:postcode":"14052",
    "sg:province":"NY",
    "sg:tags":[
        "merchandise"
    ],
    "wof:name":"Cosefini LLC",
    "wof:placetype":"venue"
},
  "geometry": {"coordinates":[-78.61077899999999,42.767957],"type":"Point"}
}