{
  "type": "Feature",
  "properties": {
    "iso:country":"US",
    "sg:address":"1 Roslyn Rd",
    "sg:city":"Roslyn Heights",
    "sg:classifiers":[
        {
            "category":"Banks & Credit Unions",
            "subcategory":"Investment Brokerage",
            "type":"Services"
        }
    ],
    "sg:phone":"+1 516 621 0200",
    "sg:postcode":"11577",
    "sg:province":"NY",
    "sg:tags":[
        "stock",
        "bond"
    ],
    "sg:website":"www.prherzig.com",
    "wof:name":"P R Herzig",
    "wof:placetype":"venue"
},
  "geometry": {"coordinates":[-73.643036,40.793427],"type":"Point"}
}