{
  "type": "Feature",
  "properties": {
    "addr:full":"1 Prospect Park W Brooklyn NY 11215",
    "addr:housenumber":"1",
    "addr:postcode":"11215",
    "addr:street":"Prospect Park W",
    "iso:country":"US",
    "sg:address":"1 Prospect Park W",
    "sg:city":"Brooklyn",
    "sg:classifiers":[
        {
            "category":"Health Services",
            "subcategory":"Doctor",
            "type":"Services"
        }
    ],
    "sg:phone":"+1 718 780 5780",
    "sg:postcode":"11215",
    "sg:province":"NY",
    "wof:name":"Bialik Ilya MD",
    "wof:placetype":"venue"
},
  "geometry": {"coordinates":[-73.97071699999999,40.672316],"type":"Point"}
}