{
  "type": "Feature",
  "properties": {
    "addr:full":"230 W 41st St Fl 14 New York NY 10036",
    "addr:housenumber":"230;14",
    "addr:postcode":"10036",
    "addr:street":"W 41St St Fl",
    "iso:country":"US",
    "sg:address":"230 W 41st St Fl 14",
    "sg:city":"New York",
    "sg:classifiers":[
        {
            "category":"Professional",
            "subcategory":"Employment Agencies",
            "type":"Services"
        }
    ],
    "sg:phone":"+1 212 221 0540",
    "sg:postcode":"10036",
    "sg:province":"NY",
    "wof:name":"Bounty Jobs",
    "wof:placetype":"venue"
},
  "geometry": {"coordinates":[-73.988364,40.755611],"type":"Point"}
}