{
  "type": "Feature",
  "properties": {
    "iso:country":"US",
    "sg:address":"66 Ruggles Rd",
    "sg:city":"Saratoga Springs",
    "sg:classifiers":[
        {
            "category":"Manufacturing",
            "subcategory":"Retail Goods",
            "type":"Manufacturing & Wholesale Goods"
        }
    ],
    "sg:phone":"+1   ",
    "sg:postcode":"12866",
    "sg:province":"NY",
    "sg:tags":[
        "product",
        "mfg"
    ],
    "wof:name":"Vintage Daydreams",
    "wof:placetype":"venue"
},
  "geometry": {"coordinates":[-73.700232,43.102229],"type":"Point"}
}