{
  "type": "Feature",
  "properties": {
    "addr:full":"65 Main St Hastings On Hudson NY 10706",
    "addr:housenumber":"65",
    "addr:postcode":"10706",
    "addr:street":"Main St",
    "iso:country":"US",
    "sg:address":"65 Main St",
    "sg:city":"Hastings On Hudson",
    "sg:classifiers":[
        {
            "category":"Banks & Credit Unions",
            "subcategory":"Bank",
            "type":"Services"
        }
    ],
    "sg:phone":"+1 914 478 4422",
    "sg:postcode":"10706",
    "sg:province":"NY",
    "sg:tags":[
        "national",
        "commercial"
    ],
    "wof:name":"Citibank",
    "wof:placetype":"venue"
},
  "geometry": {"coordinates":[-73.880464,40.994242],"type":"Point"}
}