{
  "type": "Feature",
  "properties": {
    "iso:country":"US",
    "sg:address":"5555 Main St",
    "sg:city":"Williamsville",
    "sg:classifiers":[
        {
            "category":"Shopping",
            "subcategory":"Computers & Home Electronics",
            "type":"Retail Goods"
        }
    ],
    "sg:phone":"+1 716 626 1517",
    "sg:postcode":"14221",
    "sg:province":"NY",
    "sg:tags":[
        "software"
    ],
    "sg:website":"www.legalstar.com",
    "wof:name":"Legalstar Inc",
    "wof:placetype":"venue"
},
  "geometry": {"coordinates":[-78.74676599999999,42.96252],"type":"Point"}
}