{
  "type": "Feature",
  "properties": {
    "addr:full":"33 Pryer Ter New Rochelle NY 10804",
    "addr:housenumber":"33",
    "addr:postcode":"10804",
    "addr:street":"Pryer Ter",
    "iso:country":"US",
    "sg:address":"33 Pryer Ter",
    "sg:city":"New Rochelle",
    "sg:classifiers":[
        {
            "category":"Education",
            "subcategory":"Junior College",
            "type":"Public Place"
        }
    ],
    "sg:phone":"+1 914 636 6194",
    "sg:postcode":"10804",
    "sg:province":"NY",
    "sg:tags":[
        "technical",
        "institute"
    ],
    "wof:name":"Christian Brothers Institute",
    "wof:placetype":"venue"
},
  "geometry": {"coordinates":[-73.782842,40.929668],"type":"Point"}
}