{
  "type": "Feature",
  "properties": {
    "iso:country":"US",
    "sg:address":"1423 Mill Ave",
    "sg:city":"Brooklyn",
    "sg:classifiers":[
        {
            "category":"Food & Beverages",
            "subcategory":"Liquor & Beverages",
            "type":"Retail Goods"
        }
    ],
    "sg:phone":"+1   ",
    "sg:postcode":"11234",
    "sg:province":"NY",
    "sg:tags":[
        "alcoholic"
    ],
    "wof:name":"Foster Ave Liquor Store",
    "wof:placetype":"venue"
},
  "geometry": {"coordinates":[-73.91588299999999,40.61741],"type":"Point"}
}