{
  "type": "Feature",
  "properties": {
    "addr:full":"4 W State St Gloversville NY 12078",
    "addr:housenumber":"4",
    "addr:postcode":"12078",
    "addr:street":"W State St",
    "iso:country":"US",
    "sg:address":"4 W State St",
    "sg:city":"Gloversville",
    "sg:classifiers":[
        {
            "category":"Wholesale",
            "subcategory":"Non-durable Goods",
            "type":"Manufacturing & Wholesale Goods"
        }
    ],
    "sg:phone":"+1 518 725 1367",
    "sg:postcode":"12078",
    "sg:province":"NY",
    "wof:name":"Leatherconsultantscom",
    "wof:placetype":"venue"
},
  "geometry": {"coordinates":[-74.343585,43.067508],"type":"Point"}
}