{
  "type": "Feature",
  "properties": {
    "addr:full":"2727 Coney Island Ave Brooklyn NY 11235",
    "addr:housenumber":"2727",
    "addr:postcode":"11235",
    "addr:street":"Coney Island Ave",
    "iso:country":"US",
    "sg:address":"2727 Coney Island Ave",
    "sg:city":"Brooklyn",
    "sg:classifiers":[
        {
            "category":"Organizations",
            "subcategory":"Religious Organization",
            "type":"Services"
        }
    ],
    "sg:phone":"+1 718 332 5775",
    "sg:postcode":"11235",
    "sg:province":"NY",
    "sg:tags":[
        "mosque"
    ],
    "wof:name":"Universal Foundation LTD",
    "wof:placetype":"venue"
},
  "geometry": {"coordinates":[-73.960517,40.589453],"type":"Point"}
}