{
  "type": "Feature",
  "properties": {
    "addr:full":"2 Wilson Pl Mount Vernon NY 10550",
    "addr:housenumber":"2",
    "addr:postcode":"10550",
    "addr:street":"Wilson Pl",
    "iso:country":"US",
    "sg:address":"2 Wilson Pl",
    "sg:city":"Mount Vernon",
    "sg:classifiers":[
        {
            "category":"Home & Garden",
            "subcategory":"Furniture",
            "type":"Retail Goods"
        }
    ],
    "sg:phone":"+1   ",
    "sg:postcode":"10550",
    "sg:province":"NY",
    "sg:tags":[
        "repairing",
        "refinishing"
    ],
    "wof:name":"Hahns Furnishings Inc",
    "wof:placetype":"venue"
},
  "geometry": {"coordinates":[-73.83900800000001,40.911288],"type":"Point"}
}