{
  "type": "Feature",
  "properties": {
    "addr:full":"50 Lester Ave Freeport NY 11520",
    "addr:housenumber":"50",
    "addr:postcode":"11520",
    "addr:street":"Lester Ave",
    "iso:country":"US",
    "sg:address":"50 Lester Ave",
    "sg:city":"Freeport",
    "sg:classifiers":[
        {
            "category":"Building & Trades",
            "subcategory":"Construction",
            "type":"Services"
        }
    ],
    "sg:phone":"+1 516 223 0671",
    "sg:postcode":"11520",
    "sg:province":"NY",
    "sg:tags":[
        "house"
    ],
    "wof:name":"Ld Construction",
    "wof:placetype":"venue"
},
  "geometry": {"coordinates":[-73.594139,40.635054],"type":"Point"}
}