{
  "type": "Feature",
  "properties": {
    "addr:full":"5795 Widewaters Pkwy Syracuse NY 13214",
    "addr:housenumber":"5795",
    "addr:postcode":"13214",
    "addr:street":"Widewaters Pkwy",
    "iso:country":"US",
    "sg:address":"5795 Widewaters Pkwy",
    "sg:city":"Syracuse",
    "sg:classifiers":[
        {
            "category":"Professional",
            "subcategory":"Engineering",
            "type":"Services"
        }
    ],
    "sg:phone":"+1 315 446 9201",
    "sg:postcode":"13214",
    "sg:province":"NY",
    "sg:tags":[
        "consulting",
        "engineer"
    ],
    "sg:website":"www.khhpc.com",
    "wof:name":"Klepper Hahn & Hyatt",
    "wof:placetype":"venue"
},
  "geometry": {"coordinates":[-76.06352800000001,43.045921],"type":"Point"}
}