{
  "type": "Feature",
  "properties": {
    "iso:country":"US",
    "sg:address":"500 Chestnut Ridge Rd",
    "sg:city":"Spring Valley",
    "sg:classifiers":[
        {
            "category":"Insurance",
            "subcategory":"Insurance Agent",
            "type":"Services"
        }
    ],
    "sg:phone":"+1 845 352 9600",
    "sg:postcode":"10977",
    "sg:province":"NY",
    "wof:name":"Allstate Insurance Co",
    "wof:placetype":"venue"
},
  "geometry": {"coordinates":[-74.04787399999999,41.096973],"type":"Point"}
}