{
  "type": "Feature",
  "properties": {
    "addr:full":"525 Fashion Ave Rm 510 New York NY 10018",
    "addr:housenumber":"525;510",
    "addr:postcode":"10018",
    "addr:street":"Fashion Ave Rm",
    "iso:country":"US",
    "sg:address":"525 Fashion Ave Rm 510",
    "sg:city":"New York",
    "sg:classifiers":[
        {
            "category":"Banks & Credit Unions",
            "subcategory":"Bank",
            "type":"Services"
        }
    ],
    "sg:phone":"+1 212 278 8902",
    "sg:postcode":"10018",
    "sg:province":"NY",
    "wof:name":"Everest America Inc",
    "wof:placetype":"venue"
},
  "geometry": {"coordinates":[-73.98842999999999,40.753684],"type":"Point"}
}