{
  "type": "Feature",
  "properties": {
    "iso:country":"US",
    "sg:address":"9027 Council House Rd",
    "sg:city":"Caneadea",
    "sg:classifiers":[
        {
            "category":"Retail",
            "subcategory":"Auto Repair",
            "type":"Services"
        }
    ],
    "sg:phone":"+1 585 365 2031",
    "sg:postcode":"14717",
    "sg:province":"NY",
    "sg:tags":[
        "muffler",
        "exhaust",
        "system"
    ],
    "wof:name":"Rose's Exhaust Svc",
    "wof:placetype":"venue"
},
  "geometry": {"coordinates":[-78.153198,42.392903],"type":"Point"}
}