{
  "type": "Feature",
  "properties": {
    "addr:full":"124 Susquehanna Ave Great Neck NY 11021",
    "addr:housenumber":"124",
    "addr:postcode":"11021",
    "addr:street":"Susquehanna Ave",
    "iso:country":"US",
    "sg:address":"124 Susquehanna Ave",
    "sg:city":"Great Neck",
    "sg:classifiers":[
        {
            "category":"Travel",
            "subcategory":"Bed & Breakfast",
            "type":"Entertainment"
        }
    ],
    "sg:phone":"+1   ",
    "sg:postcode":"11021",
    "sg:province":"NY",
    "sg:tags":[
        "house"
    ],
    "wof:name":"Studio Camnitzer",
    "wof:placetype":"venue"
},
  "geometry": {"coordinates":[-73.714737,40.784442],"type":"Point"}
}