{
  "type": "Feature",
  "properties": {
    "addr:full":"278 W 11th St New York NY 10014",
    "addr:housenumber":"278",
    "addr:postcode":"10014",
    "addr:street":"W 11Th St",
    "iso:country":"US",
    "sg:address":"278 W 11th St",
    "sg:city":"New York",
    "sg:classifiers":[
        {
            "category":"Travel",
            "subcategory":"Bed & Breakfast",
            "type":"Entertainment"
        }
    ],
    "sg:phone":"+1 212 675 7897",
    "sg:postcode":"10014",
    "sg:province":"NY",
    "sg:website":"www.west-eleventh.com",
    "wof:name":"West Eleventh Townhouse Apartments",
    "wof:placetype":"venue"
},
  "geometry": {"coordinates":[-74.00455700000001,40.735843],"type":"Point"}
}