{
  "type": "Feature",
  "properties": {
    "iso:country":"US",
    "sg:address":"44 Kirbytown Rd",
    "sg:city":"Middletown",
    "sg:classifiers":[
        {
            "category":"Building & Trades",
            "subcategory":"Construction",
            "type":"Services"
        }
    ],
    "sg:phone":"+1 845 343 4508",
    "sg:postcode":"10940",
    "sg:province":"NY",
    "sg:tags":[
        "contractor"
    ],
    "wof:name":"Hudson Masonry Corp",
    "wof:placetype":"venue"
},
  "geometry": {"coordinates":[-74.436627,41.418478],"type":"Point"}
}