{
  "type": "Feature",
  "properties": {
    "addr:full":"3843 E Tremont Ave Bronx NY 10465",
    "addr:housenumber":"3843",
    "addr:postcode":"10465",
    "addr:street":"E Tremont Ave",
    "iso:country":"US",
    "sg:address":"3843 E Tremont Ave",
    "sg:city":"Bronx",
    "sg:classifiers":[
        {
            "category":"Personal",
            "subcategory":"Beauty Salon",
            "type":"Services"
        }
    ],
    "sg:phone":"+1 718 518 0685",
    "sg:postcode":"10465",
    "sg:province":"NY",
    "wof:name":"Hair In Motion Unisex Salon",
    "wof:placetype":"venue"
},
  "geometry": {"coordinates":[-73.820123,40.824351],"type":"Point"}
}