{
  "type": "Feature",
  "properties": {
    "iso:country":"US",
    "sg:address":"210 Dorothy St Ste 2",
    "sg:city":"Syracuse",
    "sg:classifiers":[
        {
            "category":"Personal",
            "subcategory":"Beauty Salon",
            "type":"Services"
        },
        {
            "category":"Personal",
            "subcategory":"Barber",
            "type":"Services"
        }
    ],
    "sg:phone":"+1 315 432 8808",
    "sg:postcode":"13203",
    "sg:province":"NY",
    "wof:name":"Salon Surreal",
    "wof:placetype":"venue"
},
  "geometry": {"coordinates":[-76.127032,43.061693],"type":"Point"}
}