{
  "type": "Feature",
  "properties": {
    "addr:full":"415 Fox Run Ln Carmel NY 10512",
    "addr:housenumber":"415",
    "addr:postcode":"10512",
    "addr:street":"Fox Run Ln",
    "iso:country":"US",
    "sg:address":"415 Fox Run Ln",
    "sg:city":"Carmel",
    "sg:classifiers":[
        {
            "category":"Building & Trades",
            "subcategory":"Construction",
            "type":"Services"
        }
    ],
    "sg:phone":"+1 845 225 1186",
    "sg:postcode":"10512",
    "sg:province":"NY",
    "sg:tags":[
        "contractor"
    ],
    "wof:name":"James Kennedy Contractor",
    "wof:placetype":"venue"
},
  "geometry": {"coordinates":[-73.63664199999999,41.454803],"type":"Point"}
}