{
  "type": "Feature",
  "properties": {
    "addr:full":"545 8th Avenue New York NY 10018",
    "addr:housenumber":"545",
    "addr:postcode":"10018",
    "addr:street":"8Th Avenue",
    "iso:country":"US",
    "sg:address":"545 8th Avenue",
    "sg:city":"New York",
    "sg:classifiers":[
        {
            "category":"Shopping",
            "subcategory":"Adult",
            "type":"Retail Goods"
        }
    ],
    "sg:phone":"+1 212 330 8088",
    "sg:postcode":"10018",
    "sg:province":"NY",
    "sg:tags":[
        "entertainment"
    ],
    "wof:name":"Centerfold Stars Striptease-To-Go",
    "wof:placetype":"venue"
},
  "geometry": {"coordinates":[-73.99198,40.754223],"type":"Point"}
}