{
  "type": "Feature",
  "properties": {
    "iso:country":"US",
    "sg:address":"1393 State Highway 29",
    "sg:city":"Gloversville",
    "sg:classifiers":[
        {
            "category":"Building & Trades",
            "subcategory":"Construction",
            "type":"Services"
        },
        {
            "category":"Home & Garden",
            "subcategory":"Household Appliances",
            "type":"Retail Goods"
        },
        {
            "category":"Retail",
            "subcategory":"Laundry & Dry Cleaning",
            "type":"Services"
        },
        {
            "category":"Home & Garden",
            "subcategory":"Building Materials",
            "type":"Retail Goods"
        },
        {
            "category":"Industrial Area",
            "type":"Public Place"
        },
        {
            "category":"Manufacturing",
            "subcategory":"Tools & Machinery",
            "type":"Manufacturing & Wholesale Goods"
        }
    ],
    "sg:phone":"+1 518 883 3957",
    "sg:postcode":"12078",
    "sg:province":"NY",
    "sg:tags":[
        "systems-repairing",
        "major",
        "machinery-rebuild",
        "system",
        "specialty",
        "equipment",
        "heating",
        "contractor",
        "repair",
        "equipment-repairing"
    ],
    "wof:name":"Action Heat",
    "wof:placetype":"venue"
},
  "geometry": {"coordinates":[-74.228685,43.047899],"type":"Point"}
}