{
  "type": "Feature",
  "properties": {
    "addr:full":"103 Chester St Mount Vernon NY 10552",
    "addr:housenumber":"103",
    "addr:postcode":"10552",
    "addr:street":"Chester St",
    "iso:country":"US",
    "sg:address":"103 Chester St",
    "sg:city":"Mount Vernon",
    "sg:classifiers":[
        {
            "category":"Building & Trades",
            "subcategory":"Construction",
            "type":"Services"
        }
    ],
    "sg:phone":"+1 914 665 8961",
    "sg:postcode":"10552",
    "sg:province":"NY",
    "sg:tags":[
        "general",
        "contractor"
    ],
    "wof:name":"Belezaire Construction Inc",
    "wof:placetype":"venue"
},
  "geometry": {"coordinates":[-73.83225899999999,40.918681],"type":"Point"}
}