{
  "type": "Feature",
  "properties": {
    "addr:full":"51 Brookridge Rd New Rochelle NY 10804",
    "addr:housenumber":"51",
    "addr:postcode":"10804",
    "addr:street":"Brookridge Rd",
    "iso:country":"US",
    "sg:address":"51 Brookridge Rd",
    "sg:city":"New Rochelle",
    "sg:classifiers":[
        {
            "category":"Wholesale",
            "subcategory":"Non-durable Goods",
            "type":"Manufacturing & Wholesale Goods"
        }
    ],
    "sg:phone":"+1 914 636 3758",
    "sg:postcode":"10804",
    "sg:province":"NY",
    "wof:name":"Admagination",
    "wof:placetype":"venue"
},
  "geometry": {"coordinates":[-73.77409,40.957987],"type":"Point"}
}