{
  "type": "Feature",
  "properties": {
    "iso:country":"US",
    "sg:address":"734 Chemung St",
    "sg:city":"Horseheads",
    "sg:classifiers":[
        {
            "category":"Communications",
            "subcategory":"Radio Station",
            "type":"Services"
        }
    ],
    "sg:phone":"+1 607 795 0795",
    "sg:postcode":"14845",
    "sg:province":"NY",
    "sg:tags":[
        "company",
        "broadcasting"
    ],
    "wof:name":"WPHD",
    "wof:placetype":"venue"
},
  "geometry": {"coordinates":[-76.83243400000001,42.156465],"type":"Point"}
}