{
  "type": "Feature",
  "properties": {
    "addr:full":"2914 Elmwood Ave Kenmore NY 14217",
    "addr:housenumber":"2914",
    "addr:postcode":"14217",
    "addr:street":"Elmwood Ave",
    "iso:country":"US",
    "sg:address":"2914 Elmwood Ave",
    "sg:city":"Kenmore",
    "sg:classifiers":[
        {
            "category":"Health Services",
            "subcategory":"Hospital",
            "type":"Services"
        }
    ],
    "sg:phone":"+1 716 447 6671",
    "sg:postcode":"14217",
    "sg:province":"NY",
    "wof:name":"Catholic Health Systems",
    "wof:placetype":"venue"
},
  "geometry": {"coordinates":[-78.87875099999999,42.977051],"type":"Point"}
}