{
  "type": "Feature",
  "properties": {
    "addr:full":"3300 Chambers Rd Horseheads NY 14845",
    "addr:housenumber":"3300",
    "addr:postcode":"14845",
    "addr:street":"Chambers Rd",
    "iso:country":"US",
    "sg:address":"3300 Chambers Rd",
    "sg:city":"Horseheads",
    "sg:classifiers":[
        {
            "category":"Shopping",
            "subcategory":"Computers & Home Electronics",
            "type":"Retail Goods"
        }
    ],
    "sg:phone":"+1 607 796 6310",
    "sg:postcode":"14845",
    "sg:province":"NY",
    "sg:tags":[
        "television",
        "radio"
    ],
    "wof:name":"Rex TV & Appliances",
    "wof:placetype":"venue"
},
  "geometry": {"coordinates":[-76.877031,42.155046],"type":"Point"}
}