{
  "type": "Feature",
  "properties": {
    "addr:full":"103 Pennsylvania Ave Medford NY 11763",
    "addr:housenumber":"103",
    "addr:postcode":"11763",
    "addr:street":"Pennsylvania Ave",
    "iso:country":"US",
    "sg:address":"103 Pennsylvania Ave",
    "sg:city":"Medford",
    "sg:classifiers":[
        {
            "category":"Professional",
            "subcategory":"Business Services",
            "type":"Services"
        }
    ],
    "sg:phone":"+1   ",
    "sg:postcode":"11763",
    "sg:province":"NY",
    "wof:name":"St Johns Embroidery",
    "wof:placetype":"venue"
},
  "geometry": {"coordinates":[-72.993681,40.807181],"type":"Point"}
}