{
  "type": "Feature",
  "properties": {
    "iso:country":"US",
    "sg:address":"650 Piermont Ave",
    "sg:city":"Piermont",
    "sg:classifiers":[
        {
            "category":"Building & Trades",
            "subcategory":"Construction",
            "type":"Services"
        }
    ],
    "sg:phone":"+1 845 398 0521",
    "sg:postcode":"10968",
    "sg:province":"NY",
    "sg:tags":[
        "house"
    ],
    "wof:name":"Chadwick Construction",
    "wof:placetype":"venue"
},
  "geometry": {"coordinates":[-73.917462,41.043073],"type":"Point"}
}