{
  "type": "Feature",
  "properties": {
    "iso:country":"US",
    "sg:address":"627 Manida St",
    "sg:city":"Bronx",
    "sg:classifiers":[
        {
            "category":"Personal",
            "subcategory":"Beauty Salon",
            "type":"Services"
        }
    ],
    "sg:phone":"+1 718 542 2616",
    "sg:postcode":"10474",
    "sg:province":"NY",
    "wof:name":"Preciosa Beauty Salon",
    "wof:placetype":"venue"
},
  "geometry": {"coordinates":[-73.888279,40.813604],"type":"Point"}
}