{
  "type": "Feature",
  "properties": {
    "addr:full":"5 Stirrup Dr Albany NY 12205",
    "addr:housenumber":"5",
    "addr:postcode":"12205",
    "addr:street":"Stirrup Dr",
    "iso:country":"US",
    "sg:address":"5 Stirrup Dr",
    "sg:city":"Albany",
    "sg:classifiers":[
        {
            "category":"Building & Trades",
            "subcategory":"Construction",
            "type":"Services"
        }
    ],
    "sg:phone":"+1 518 869 7617",
    "sg:postcode":"12205",
    "sg:province":"NY",
    "sg:tags":[
        "painter"
    ],
    "wof:name":"Kc's Painting",
    "wof:placetype":"venue"
},
  "geometry": {"coordinates":[-73.83018,42.727998],"type":"Point"}
}