{
  "type": "Feature",
  "properties": {
    "addr:full":"145 Nagle Ave New York NY 10040",
    "addr:housenumber":"145",
    "addr:postcode":"10040",
    "addr:street":"Nagle Ave",
    "iso:country":"US",
    "sg:address":"145 Nagle Ave",
    "sg:city":"New York",
    "sg:classifiers":[
        {
            "category":"Personal",
            "subcategory":"Beauty Salon",
            "type":"Services"
        }
    ],
    "sg:phone":"+1 212 544 7684",
    "sg:postcode":"10040",
    "sg:province":"NY",
    "wof:name":"New Century",
    "wof:placetype":"venue"
},
  "geometry": {"coordinates":[-73.924865,40.861491],"type":"Point"}
}