{
  "type": "Feature",
  "properties": {
    "iso:country":"US",
    "sg:address":"649 W Montauk Hwy",
    "sg:city":"Bay Shore",
    "sg:classifiers":[
        {
            "category":"Health Services",
            "subcategory":"Doctor",
            "type":"Services"
        }
    ],
    "sg:phone":"+1 631 665 2700",
    "sg:postcode":"11706",
    "sg:province":"NY",
    "sg:tags":[
        "physician",
        "surgeon"
    ],
    "wof:name":"Bay Shore Allergy Group",
    "wof:placetype":"venue"
},
  "geometry": {"coordinates":[-73.273473,40.702979],"type":"Point"}
}