{
  "type": "Feature",
  "properties": {
    "iso:country":"US",
    "sg:address":"14 S Church St",
    "sg:city":"Canaseraga",
    "sg:classifiers":[
        {
            "category":"Manufacturing",
            "subcategory":"Tools & Machinery",
            "type":"Manufacturing & Wholesale Goods"
        }
    ],
    "sg:phone":"+1 607 545 6561",
    "sg:postcode":"14822",
    "sg:province":"NY",
    "sg:tags":[
        "farm",
        "equipment"
    ],
    "wof:name":"Oliver Charles F & Son LLC",
    "wof:placetype":"venue"
},
  "geometry": {"coordinates":[-77.777126,42.460463],"type":"Point"}
}