{
  "type": "Feature",
  "properties": {
    "iso:country":"US",
    "sg:address":"529 77th St",
    "sg:city":"Brooklyn",
    "sg:classifiers":[
        {
            "category":"Wholesale",
            "subcategory":"Stationery",
            "type":"Manufacturing & Wholesale Goods"
        }
    ],
    "sg:phone":"+1 718 836 4819",
    "sg:postcode":"11209",
    "sg:province":"NY",
    "sg:tags":[
        "card"
    ],
    "sg:website":"www.irasperipheralvisions.com",
    "wof:name":"Ira's Peripheral Vision",
    "wof:placetype":"venue"
},
  "geometry": {"coordinates":[-74.0224,40.627602],"type":"Point"}
}