{
  "type": "Feature",
  "properties": {
    "iso:country":"US",
    "sg:address":"3223 Ridge Rd W",
    "sg:city":"Rochester",
    "sg:classifiers":[
        {
            "category":"Professional",
            "subcategory":"Business Services",
            "type":"Services"
        }
    ],
    "sg:phone":"+1 585 453 2000",
    "sg:postcode":"14626",
    "sg:province":"NY",
    "sg:tags":[
        "paging",
        "answering"
    ],
    "wof:name":"Northside Telephone Exchange",
    "wof:placetype":"venue"
},
  "geometry": {"coordinates":[-77.717046,43.211941],"type":"Point"}
}