{
  "type": "Feature",
  "properties": {
    "iso:country":"US",
    "sg:address":"1408 Davis Ave",
    "sg:city":"Endicott",
    "sg:classifiers":[
        {
            "category":"Building & Trades",
            "subcategory":"Electrical",
            "type":"Services"
        }
    ],
    "sg:phone":"+1 607 754 2321",
    "sg:postcode":"13760",
    "sg:province":"NY",
    "sg:tags":[
        "installs",
        "control",
        "energy",
        "retail",
        "product"
    ],
    "wof:name":"Energy Savers Unlimited",
    "wof:placetype":"venue"
},
  "geometry": {"coordinates":[-76.06891400000001,42.091738],"type":"Point"}
}