{
  "type": "Feature",
  "properties": {
    "addr:full":"8 Turner Rd Central Valley NY 10917",
    "addr:housenumber":"8",
    "addr:postcode":"10917",
    "addr:street":"Turner Rd",
    "iso:country":"US",
    "sg:address":"8 Turner Rd",
    "sg:city":"Central Valley",
    "sg:classifiers":[
        {
            "category":"Real Estate",
            "subcategory":"Architect",
            "type":"Services"
        }
    ],
    "sg:phone":"+1 845 928 3988",
    "sg:postcode":"10917",
    "sg:province":"NY",
    "sg:tags":[
        "architectural"
    ],
    "wof:name":"Pendergast & Terach PC",
    "wof:placetype":"venue"
},
  "geometry": {"coordinates":[-74.125727,41.320361],"type":"Point"}
}