{
  "type": "Feature",
  "properties": {
    "addr:full":"525 Half Hollow Rd Huntington Station NY 11746",
    "addr:housenumber":"525",
    "addr:postcode":"11746",
    "addr:street":"Half Hollow Rd",
    "iso:country":"US",
    "sg:address":"525 Half Hollow Rd",
    "sg:city":"Huntington Station",
    "sg:classifiers":[
        {
            "category":"Education",
            "subcategory":"School",
            "type":"Public Place"
        }
    ],
    "sg:phone":"+1 631 592 3025",
    "sg:postcode":"11746",
    "sg:province":"NY",
    "sg:tags":[
        "district"
    ],
    "wof:name":"Half Hollow Hills Central Schl",
    "wof:placetype":"venue"
},
  "geometry": {"coordinates":[-73.35228499999999,40.793051],"type":"Point"}
}