{
  "type": "Feature",
  "properties": {
    "iso:country":"US",
    "sg:address":"55 Maple Ave",
    "sg:city":"Spring Valley",
    "sg:classifiers":[
        {
            "category":"Food & Beverages",
            "subcategory":"Groceries & Convenience Stores",
            "type":"Retail Goods"
        },
        {
            "category":"Restaurant",
            "type":"Food & Drink"
        }
    ],
    "sg:phone":"+1 845 356 4346",
    "sg:postcode":"10977",
    "sg:province":"NY",
    "sg:tags":[
        "product",
        "eating"
    ],
    "wof:name":"Eric's Food Store",
    "wof:placetype":"venue"
},
  "geometry": {"coordinates":[-74.05147100000001,41.117076],"type":"Point"}
}