{
  "type": "Feature",
  "properties": {
    "iso:country":"US",
    "sg:address":"1100 W Church St",
    "sg:city":"Elmira",
    "sg:classifiers":[
        {
            "category":"Organizations",
            "subcategory":"Religious Organization",
            "type":"Services"
        }
    ],
    "sg:phone":"+1 607 733 1412",
    "sg:postcode":"14905",
    "sg:province":"NY",
    "sg:tags":[
        "church"
    ],
    "wof:name":"Our Lady Of Lourdes Church",
    "wof:placetype":"venue"
},
  "geometry": {"coordinates":[-76.837334,42.081282],"type":"Point"}
}