{
  "type": "Feature",
  "properties": {
    "iso:country":"US",
    "sg:address":"460 Mamaroneck Ave",
    "sg:city":"White Plains",
    "sg:classifiers":[
        {
            "category":"Shopping",
            "subcategory":"Pharmacy",
            "type":"Retail Goods"
        }
    ],
    "sg:phone":"+1   ",
    "sg:postcode":"10605",
    "sg:province":"NY",
    "wof:name":"Saxon Chemists Inc",
    "wof:placetype":"venue"
},
  "geometry": {"coordinates":[-73.759598,41.022577],"type":"Point"}
}