{
  "type": "Feature",
  "properties": {
    "addr:full":"2704 Watch Hill Dr Tarrytown NY 10591",
    "addr:housenumber":"2704",
    "addr:postcode":"10591",
    "addr:street":"Watch Hill Dr",
    "iso:country":"US",
    "sg:address":"2704 Watch Hill Dr",
    "sg:city":"Tarrytown",
    "sg:classifiers":[
        {
            "category":"Professional",
            "subcategory":"Advertising",
            "type":"Services"
        }
    ],
    "sg:phone":"+1   ",
    "sg:postcode":"10591",
    "sg:province":"NY",
    "sg:tags":[
        "development",
        "web",
        "consulting",
        "medium"
    ],
    "wof:name":"Valkrys Enterprises Inc",
    "wof:placetype":"venue"
},
  "geometry": {"coordinates":[-73.829391,41.064107],"type":"Point"}
}