{
  "type": "Feature",
  "properties": {
    "addr:full":"36 Bleecker St Greenwich NY 12834",
    "addr:housenumber":"36",
    "addr:postcode":"12834",
    "addr:street":"Bleecker St",
    "iso:country":"US",
    "sg:address":"36 Bleecker St",
    "sg:city":"Greenwich",
    "sg:classifiers":[
        {
            "category":"Organizations",
            "subcategory":"Religious Organization",
            "type":"Services"
        }
    ],
    "sg:phone":"+1 518 692 2159",
    "sg:postcode":"12834",
    "sg:province":"NY",
    "wof:name":"St Joseph Catholic Church",
    "wof:placetype":"venue"
},
  "geometry": {"coordinates":[-73.503164,43.090041],"type":"Point"}
}