{
  "type": "Feature",
  "properties": {
    "iso:country":"US",
    "sg:address":"510 E 85th St",
    "sg:city":"New York",
    "sg:classifiers":[
        {
            "category":"Professional",
            "subcategory":"Lawyer & Legal Services",
            "type":"Services"
        }
    ],
    "sg:phone":"+1 212 472 3000",
    "sg:postcode":"10028",
    "sg:province":"NY",
    "wof:name":"Legal Search",
    "wof:placetype":"venue"
},
  "geometry": {"coordinates":[-73.945486,40.774288],"type":"Point"}
}