{
  "type": "Feature",
  "properties": {
    "addr:full":"4305 7th Ave Brooklyn NY 11232",
    "addr:housenumber":"4305",
    "addr:postcode":"11232",
    "addr:street":"7Th Ave",
    "iso:country":"US",
    "sg:address":"4305 7th Ave",
    "sg:city":"Brooklyn",
    "sg:classifiers":[
        {
            "category":"Education",
            "subcategory":"School",
            "type":"Public Place"
        }
    ],
    "sg:phone":"+1 718 330 9370",
    "sg:postcode":"11232",
    "sg:province":"NY",
    "wof:name":"PS 169",
    "wof:placetype":"venue"
},
  "geometry": {"coordinates":[-74.00233799999999,40.645785],"type":"Point"}
}