{
  "type": "Feature",
  "properties": {
    "addr:full":"10 Fair St Carmel NY 10512",
    "addr:housenumber":"10",
    "addr:postcode":"10512",
    "addr:street":"Fair St",
    "iso:country":"US",
    "sg:address":"10 Fair St",
    "sg:city":"Carmel",
    "sg:classifiers":[
        {
            "category":"Education",
            "subcategory":"Dance Studio",
            "type":"Public Place"
        }
    ],
    "sg:phone":"+1 845 225 2230",
    "sg:postcode":"10512",
    "sg:province":"NY",
    "sg:tags":[
        "instruction",
        "dancing"
    ],
    "wof:name":"Carmel School Of Dance",
    "wof:placetype":"venue"
},
  "geometry": {"coordinates":[-73.677881,41.427251],"type":"Point"}
}