{
  "type": "Feature",
  "properties": {
    "iso:country":"US",
    "sg:address":"9 Buell St",
    "sg:city":"Bath",
    "sg:classifiers":[
        {
            "category":"Shopping",
            "type":"Retail Goods"
        }
    ],
    "sg:phone":"+1   ",
    "sg:postcode":"14810",
    "sg:province":"NY",
    "sg:tags":[
        "water",
        "softener",
        "purification"
    ],
    "wof:name":"Servisoft",
    "wof:placetype":"venue"
},
  "geometry": {"coordinates":[-77.31895799999999,42.334535],"type":"Point"}
}