{
  "type": "Feature",
  "properties": {
    "addr:full":"15 Raymond Pl Yonkers NY 10704",
    "addr:housenumber":"15",
    "addr:postcode":"10704",
    "addr:street":"Raymond Pl",
    "iso:country":"US",
    "sg:address":"15 Raymond Pl",
    "sg:city":"Yonkers",
    "sg:classifiers":[
        {
            "category":"Building & Trades",
            "subcategory":"Construction",
            "type":"Services"
        }
    ],
    "sg:phone":"+1 914 803 1007",
    "sg:postcode":"10704",
    "sg:province":"NY",
    "sg:tags":[
        "general",
        "contractor"
    ],
    "wof:name":"New England Contracting Co",
    "wof:placetype":"venue"
},
  "geometry": {"coordinates":[-73.855144,40.915744],"type":"Point"}
}