{
  "type": "Feature",
  "properties": {
    "addr:full":"963 Southern Blvd Bronx NY 10459",
    "addr:housenumber":"963",
    "addr:postcode":"10459",
    "addr:street":"Southern Blvd",
    "iso:country":"US",
    "sg:address":"963 Southern Blvd",
    "sg:city":"Bronx",
    "sg:classifiers":[
        {
            "category":"Shopping",
            "subcategory":"Pharmacy",
            "type":"Retail Goods"
        }
    ],
    "sg:phone":"+1 718 328 3509",
    "sg:postcode":"10459",
    "sg:province":"NY",
    "sg:tags":[
        "drugstore"
    ],
    "sg:website":"www.duanereade.com",
    "wof:name":"Duane Reade Drugs",
    "wof:placetype":"venue"
},
  "geometry": {"coordinates":[-73.8918,40.821701],"type":"Point"}
}