{
  "type": "Feature",
  "properties": {
    "addr:full":"25 Cherrywood Dr Goshen NY 10924",
    "addr:housenumber":"25",
    "addr:postcode":"10924",
    "addr:street":"Cherrywood Dr",
    "iso:country":"US",
    "sg:address":"25 Cherrywood Dr",
    "sg:city":"Goshen",
    "sg:classifiers":[
        {
            "category":"Professional",
            "type":"Services"
        }
    ],
    "sg:phone":"+1   ",
    "sg:postcode":"10924",
    "sg:province":"NY",
    "wof:name":"Norris Quality Trimmers Inc",
    "wof:placetype":"venue"
},
  "geometry": {"coordinates":[-74.306906,41.372693],"type":"Point"}
}