{
  "type": "Feature",
  "properties": {
    "addr:full":"14965 254th St Rosedale NY 11422",
    "addr:housenumber":"14965",
    "addr:postcode":"11422",
    "addr:street":"254Th St",
    "iso:country":"US",
    "sg:address":"14965 254th St",
    "sg:city":"Rosedale",
    "sg:classifiers":[
        {
            "category":"Education",
            "subcategory":"School",
            "type":"Public Place"
        }
    ],
    "sg:phone":"+1 718 712 3112",
    "sg:postcode":"11422",
    "sg:province":"NY",
    "wof:name":"Junior Rhodes",
    "wof:placetype":"venue"
},
  "geometry": {"coordinates":[-73.73589200000001,40.650557],"type":"Point"}
}