{
  "type": "Feature",
  "properties": {
    "iso:country":"US",
    "sg:address":"1521 Balltown Rd",
    "sg:city":"Schenectady",
    "sg:classifiers":[
        {
            "category":"Real Estate",
            "subcategory":"Real Estate Agent",
            "type":"Services"
        }
    ],
    "sg:phone":"+1 518 374 8800",
    "sg:postcode":"12309",
    "sg:province":"NY",
    "wof:name":"Re/Max Park Place",
    "wof:placetype":"venue"
},
  "geometry": {"coordinates":[-73.89261500000001,42.8165],"type":"Point"}
}