{
  "type": "Feature",
  "properties": {
    "iso:country":"US",
    "sg:address":"703 E Maple Ave",
    "sg:city":"Newark",
    "sg:classifiers":[
        {
            "category":"Government",
            "subcategory":"Office",
            "type":"Public Place"
        }
    ],
    "sg:phone":"+1 315 331 6183",
    "sg:postcode":"14513",
    "sg:province":"NY",
    "sg:tags":[
        "state",
        "program",
        "health"
    ],
    "wof:name":"Mental Hygiene Legal Svc",
    "wof:placetype":"venue"
},
  "geometry": {"coordinates":[-77.082702,43.03945],"type":"Point"}
}