{
  "type": "Feature",
  "properties": {
    "addr:full":"950 W Fingerboard Rd Staten Island NY 10305",
    "addr:housenumber":"950",
    "addr:postcode":"10305",
    "addr:street":"W Fingerboard Rd",
    "iso:country":"US",
    "sg:address":"950 W Fingerboard Rd",
    "sg:city":"Staten Island",
    "sg:classifiers":[
        {
            "category":"Manufacturing",
            "subcategory":"Printing",
            "type":"Manufacturing & Wholesale Goods"
        }
    ],
    "sg:phone":"+1 718 981 1234",
    "sg:postcode":"10305",
    "sg:province":"NY",
    "sg:tags":[
        "newspaper"
    ],
    "sg:website":"www.advance.net",
    "wof:name":"Advance Publications Inc",
    "wof:placetype":"venue"
},
  "geometry": {"coordinates":[-74.084571,40.601822],"type":"Point"}
}