{
  "type": "Feature",
  "properties": {
    "iso:country":"US",
    "sg:address":"7110 20th Ave",
    "sg:city":"Brooklyn",
    "sg:classifiers":[
        {
            "category":"Home & Garden",
            "subcategory":"Household Appliances",
            "type":"Retail Goods"
        }
    ],
    "sg:phone":"+1 718 256 1555",
    "sg:postcode":"11204",
    "sg:province":"NY",
    "sg:tags":[
        "machine",
        "sewing",
        "attachment"
    ],
    "wof:name":"Empire Sewing Supply Co",
    "wof:placetype":"venue"
},
  "geometry": {"coordinates":[-73.98999000000001,40.612665],"type":"Point"}
}