{
  "type": "Feature",
  "properties": {
    "addr:full":"115 Glenmore Rd Troy NY 12180",
    "addr:housenumber":"115",
    "addr:postcode":"12180",
    "addr:street":"Glenmore Rd",
    "iso:country":"US",
    "sg:address":"115 Glenmore Rd",
    "sg:city":"Troy",
    "sg:classifiers":[
        {
            "category":"Autos & Motor Vehicles",
            "subcategory":"Automobile Sales",
            "type":"Retail Goods"
        }
    ],
    "sg:phone":"+1 518 286 4220",
    "sg:postcode":"12180",
    "sg:province":"NY",
    "sg:tags":[
        "car",
        "dealer"
    ],
    "sg:website":"www.theautobuyingservices.com",
    "wof:name":"Auto Buying Svc",
    "wof:placetype":"venue"
},
  "geometry": {"coordinates":[-73.703605,42.69104],"type":"Point"}
}