{
  "type": "Feature",
  "properties": {
    "addr:full":"618 Bluebird Ct Central Valley NY 10917",
    "addr:housenumber":"618",
    "addr:postcode":"10917",
    "addr:street":"Bluebird Ct",
    "iso:country":"US",
    "sg:address":"618 Bluebird Ct",
    "sg:city":"Central Valley",
    "sg:classifiers":[
        {
            "category":"Shopping",
            "subcategory":"Discount & Variety Stores",
            "type":"Retail Goods"
        }
    ],
    "sg:phone":"+1 845 928 7708",
    "sg:postcode":"10917",
    "sg:province":"NY",
    "sg:tags":[
        "outlet"
    ],
    "wof:name":"Woodbury Common Premium Outlets",
    "wof:placetype":"venue"
},
  "geometry": {"coordinates":[-74.125823,41.314009],"type":"Point"}
}