{
  "type": "Feature",
  "properties": {
    "addr:full":"4805 Fort Hamilton Pkwy Brooklyn NY 11219",
    "addr:housenumber":"4805",
    "addr:postcode":"11219",
    "addr:street":"Fort Hamilton Pkwy",
    "iso:country":"US",
    "sg:address":"4805 Fort Hamilton Pkwy",
    "sg:city":"Brooklyn",
    "sg:classifiers":[
        {
            "category":"Health Services",
            "subcategory":"Doctor",
            "type":"Services"
        }
    ],
    "sg:phone":"+1 718 972 2600",
    "sg:postcode":"11219",
    "sg:province":"NY",
    "sg:tags":[
        "physician",
        "surgeon",
        "imaging",
        "center"
    ],
    "wof:name":"All Borough Imaging PC",
    "wof:placetype":"venue"
},
  "geometry": {"coordinates":[-73.997586,40.638337],"type":"Point"}
}