{
  "type": "Feature",
  "properties": {
    "addr:full":"390 2nd Ave Troy NY 12182",
    "addr:housenumber":"390",
    "addr:postcode":"12182",
    "addr:street":"2Nd Ave",
    "iso:country":"US",
    "sg:address":"390 2nd Ave",
    "sg:city":"Troy",
    "sg:classifiers":[
        {
            "category":"Retail",
            "subcategory":"Auto Repair",
            "type":"Services"
        }
    ],
    "sg:phone":"+1   ",
    "sg:postcode":"12182",
    "sg:province":"NY",
    "sg:tags":[
        "re",
        "station",
        "gasoline",
        "trailer",
        "general"
    ],
    "wof:name":"U-Haul",
    "wof:placetype":"venue"
},
  "geometry": {"coordinates":[-73.68014100000001,42.76792],"type":"Point"}
}