{
  "type": "Feature",
  "properties": {
    "addr:full":"355 Main St Catskill NY 12414",
    "addr:housenumber":"355",
    "addr:postcode":"12414",
    "addr:street":"Main St",
    "iso:country":"US",
    "sg:address":"355 Main St",
    "sg:city":"Catskill",
    "sg:classifiers":[
        {
            "category":"Wholesale",
            "subcategory":"Home Furnishings",
            "type":"Manufacturing & Wholesale Goods"
        }
    ],
    "sg:phone":"+1 518 943 7943",
    "sg:postcode":"12414",
    "sg:province":"NY",
    "sg:tags":[
        "plate",
        "tapas/small"
    ],
    "sg:website":"www.cafe355.com",
    "wof:name":"Cafe 355",
    "wof:placetype":"venue"
},
  "geometry": {"coordinates":[-73.865335,42.218247],"type":"Point"}
}