{
  "type": "Feature",
  "properties": {
    "addr:full":"1763 45th St Brooklyn NY 11204",
    "addr:housenumber":"1763",
    "addr:postcode":"11204",
    "addr:street":"45Th St",
    "iso:country":"US",
    "sg:address":"1763 45th St",
    "sg:city":"Brooklyn",
    "sg:classifiers":[
        {
            "category":"Real Estate",
            "subcategory":"Developer",
            "type":"Services"
        }
    ],
    "sg:phone":"+1 718 436 1019",
    "sg:postcode":"11204",
    "sg:province":"NY",
    "wof:name":"Geula Estates Inc",
    "wof:placetype":"venue"
},
  "geometry": {"coordinates":[-73.979342,40.631297],"type":"Point"}
}