{
  "type": "Feature",
  "properties": {
    "iso:country":"US",
    "sg:address":"2075 Niagara Falls Blvd",
    "sg:city":"Buffalo",
    "sg:classifiers":[
        {
            "category":"Bakery",
            "type":"Food & Drink"
        }
    ],
    "sg:menulink":"http://www.allmenus.com/ny/amherst/116485-the-original-pancake-house/menu/",
    "sg:phone":"+1 716 691 8219",
    "sg:postcode":"14228",
    "sg:province":"NY",
    "sg:tags":[
        "american",
        "pastry",
        "diner"
    ],
    "wof:name":"The Original Pancake House",
    "wof:placetype":"venue"
},
  "geometry": {"coordinates":[-78.822057,43.010789],"type":"Point"}
}