{
  "type": "Feature",
  "properties": {
    "iso:country":"US",
    "sg:address":"80 Wooster St",
    "sg:city":"New York",
    "sg:classifiers":[
        {
            "category":"Shopping",
            "subcategory":"Clothing, Apparel, & Fashions",
            "type":"Retail Goods"
        }
    ],
    "sg:phone":"+1 212 965 9009",
    "sg:postcode":"10012",
    "sg:province":"NY",
    "sg:website":"www.christopherfischer.com/",
    "wof:name":"Christopher Fischer",
    "wof:placetype":"venue"
},
  "geometry": {"coordinates":[-74.001508,40.723707],"type":"Point"}
}