{
  "type": "Feature",
  "properties": {
    "addr:full":"408 E 53rd St Brooklyn NY 11203",
    "addr:housenumber":"408",
    "addr:postcode":"11203",
    "addr:street":"E 53Rd St",
    "iso:country":"US",
    "sg:address":"408 E 53rd St",
    "sg:city":"Brooklyn",
    "sg:classifiers":[
        {
            "category":"Building & Trades",
            "subcategory":"Construction",
            "type":"Services"
        }
    ],
    "sg:phone":"+1 718 485 6655",
    "sg:postcode":"11203",
    "sg:province":"NY",
    "sg:tags":[
        "home",
        "improvement"
    ],
    "wof:name":"H & V Allen Contracting Corp",
    "wof:placetype":"venue"
},
  "geometry": {"coordinates":[-73.92720300000001,40.648823],"type":"Point"}
}