{
  "type": "Feature",
  "properties": {
    "iso:country":"US",
    "sg:address":"295 Madison Ave",
    "sg:city":"New York",
    "sg:classifiers":[
        {
            "category":"Professional",
            "subcategory":"Advertising",
            "type":"Services"
        }
    ],
    "sg:phone":"+1 212 686 4400",
    "sg:postcode":"10017",
    "sg:province":"NY",
    "sg:tags":[
        "agency"
    ],
    "wof:name":"Kaufmann Advertising",
    "wof:placetype":"venue"
},
  "geometry": {"coordinates":[-73.980007,40.751554],"type":"Point"}
}