{
  "type": "Feature",
  "properties": {
    "addr:full":"81 Eastern Blvd Canandaigua NY 14424",
    "addr:housenumber":"81",
    "addr:postcode":"14424",
    "addr:street":"Eastern Blvd",
    "iso:country":"US",
    "sg:address":"81 Eastern Blvd",
    "sg:city":"Canandaigua",
    "sg:classifiers":[
        {
            "category":"Shopping",
            "subcategory":"Gifts & Souvenirs",
            "type":"Retail Goods"
        }
    ],
    "sg:phone":"+1 585 394 2560",
    "sg:postcode":"14424",
    "sg:province":"NY",
    "sg:tags":[
        "shop",
        "novelty"
    ],
    "wof:name":"Annie's Hallmark",
    "wof:placetype":"venue"
},
  "geometry": {"coordinates":[-77.26639400000001,42.877869],"type":"Point"}
}