{
  "type": "Feature",
  "properties": {
    "addr:full":"316 Delaware Ave Albany NY 12209",
    "addr:housenumber":"316",
    "addr:postcode":"12209",
    "addr:street":"Delaware Ave",
    "iso:country":"US",
    "sg:address":"316 Delaware Ave",
    "sg:city":"Albany",
    "sg:classifiers":[
        {
            "category":"Personal",
            "subcategory":"Beauty Salon",
            "type":"Services"
        }
    ],
    "sg:phone":"+1 518 434 1691",
    "sg:postcode":"12209",
    "sg:province":"NY",
    "wof:name":"Patricia's",
    "wof:placetype":"venue"
},
  "geometry": {"coordinates":[-73.77779200000001,42.642687],"type":"Point"}
}