{
  "type": "Feature",
  "properties": {
    "addr:full":"31 Hanson Place Brooklyn NY 11217",
    "addr:housenumber":"31",
    "addr:postcode":"11217",
    "addr:street":"Hanson Place",
    "iso:country":"US",
    "sg:address":"31 Hanson Place",
    "sg:city":"Brooklyn",
    "sg:classifiers":[
        {
            "category":"Shopping",
            "subcategory":"Gifts & Souvenirs",
            "type":"Retail Goods"
        },
        {
            "category":"Shopping",
            "subcategory":"Used Merchandise",
            "type":"Retail Goods"
        }
    ],
    "sg:phone":"+1 718 852 6053",
    "sg:postcode":"11217",
    "sg:province":"NY",
    "sg:tags":[
        "vintage",
        "flower",
        "consignment"
    ],
    "sg:website":"www.saffron-brooklyn.com",
    "wof:name":"Saffron Brooklyn",
    "wof:placetype":"venue"
},
  "geometry": {"coordinates":[-73.976658,40.685257],"type":"Point"}
}