{
  "type": "Feature",
  "properties": {
    "addr:full":"1130 49th Ave Long Island City NY 11101",
    "addr:housenumber":"1130",
    "addr:postcode":"11101",
    "addr:street":"49Th Ave",
    "iso:country":"US",
    "sg:address":"1130 49th Ave",
    "sg:city":"Long Island City",
    "sg:classifiers":[
        {
            "category":"Building & Trades",
            "subcategory":"Cleaning & Sanitation",
            "type":"Services"
        }
    ],
    "sg:phone":"+1 718 707 9640",
    "sg:postcode":"11101",
    "sg:province":"NY",
    "sg:tags":[
        "carpet"
    ],
    "wof:name":"Spotless Carpet Care Llc",
    "wof:placetype":"venue"
},
  "geometry": {"coordinates":[-73.950203,40.742599],"type":"Point"}
}