{
  "type": "Feature",
  "properties": {
    "addr:full":"8409 35th Avenue Jackson Heights NY 11372",
    "addr:housenumber":"8409",
    "addr:postcode":"11372",
    "addr:street":"35Th Avenue",
    "iso:country":"US",
    "sg:address":"8409 35th Avenue",
    "sg:city":"Jackson Heights",
    "sg:classifiers":[
        {
            "category":"Health Services",
            "subcategory":"Dentist",
            "type":"Services"
        }
    ],
    "sg:phone":"+1 718 446 3219",
    "sg:postcode":"11372",
    "sg:province":"NY",
    "wof:name":"Dyzenhaus Abraham DDS",
    "wof:placetype":"venue"
},
  "geometry": {"coordinates":[-73.88275,40.752007],"type":"Point"}
}