{
  "type": "Feature",
  "properties": {
    "iso:country":"US",
    "sg:address":"12301 Lax Ave",
    "sg:city":"College Point",
    "sg:classifiers":[
        {
            "category":"Real Estate",
            "subcategory":"Real Estate Services",
            "type":"Services"
        }
    ],
    "sg:phone":"+1 718 358 8088",
    "sg:postcode":"11356",
    "sg:province":"NY",
    "wof:name":"A V R Realty",
    "wof:placetype":"venue"
},
  "geometry": {"coordinates":[-73.844774,40.792791],"type":"Point"}
}