{
  "type": "Feature",
  "properties": {
    "addr:full":"1102 Saint Johns Place Brooklyn NY 11213",
    "addr:housenumber":"1102",
    "addr:postcode":"11213",
    "addr:street":"Saint Johns Place",
    "iso:country":"US",
    "sg:address":"1102 Saint Johns Place",
    "sg:city":"Brooklyn",
    "sg:classifiers":[
        {
            "category":"Cinema",
            "subcategory":"Movie Rental",
            "type":"Entertainment"
        }
    ],
    "sg:phone":"+1 718 953 4459",
    "sg:postcode":"11213",
    "sg:province":"NY",
    "sg:tags":[
        "game",
        "video"
    ],
    "wof:name":"St Jones Video Store",
    "wof:placetype":"venue"
},
  "geometry": {"coordinates":[-73.94060399999999,40.670992],"type":"Point"}
}