{
  "type": "Feature",
  "properties": {
    "iso:country":"US",
    "sg:address":"110 Elm St",
    "sg:city":"Penn Yan",
    "sg:classifiers":[
        {
            "category":"Shopping",
            "subcategory":"Clothing, Apparel, & Fashions",
            "type":"Retail Goods"
        }
    ],
    "sg:phone":"+1 315 536 8030",
    "sg:postcode":"14527",
    "sg:province":"NY",
    "wof:name":"Clothes Outs",
    "wof:placetype":"venue"
},
  "geometry": {"coordinates":[-77.05409899999999,42.660776],"type":"Point"}
}