{
  "type": "Feature",
  "properties": {
    "addr:full":"964 Ridge Rd Webster NY 14580",
    "addr:housenumber":"964",
    "addr:postcode":"14580",
    "addr:street":"Ridge Rd",
    "iso:country":"US",
    "sg:address":"964 Ridge Rd",
    "sg:city":"Webster",
    "sg:classifiers":[
        {
            "category":"Banks & Credit Unions",
            "subcategory":"Bank",
            "type":"Services"
        }
    ],
    "sg:phone":"+1 585 671 8880",
    "sg:postcode":"14580",
    "sg:province":"NY",
    "sg:tags":[
        "state",
        "commercial"
    ],
    "wof:name":"Chase Manhattan",
    "wof:placetype":"venue"
},
  "geometry": {"coordinates":[-77.46660199999999,43.207321],"type":"Point"}
}