{
  "type": "Feature",
  "properties": {
    "addr:full":"58 Columbine Ln Kings Park NY 11754",
    "addr:housenumber":"58",
    "addr:postcode":"11754",
    "addr:street":"Columbine Ln",
    "iso:country":"US",
    "sg:address":"58 Columbine Ln",
    "sg:city":"Kings Park",
    "sg:classifiers":[
        {
            "category":"Professional",
            "subcategory":"Management & Consulting",
            "type":"Services"
        }
    ],
    "sg:phone":"+1   ",
    "sg:postcode":"11754",
    "sg:province":"NY",
    "wof:name":"Richard Rennert Inc",
    "wof:placetype":"venue"
},
  "geometry": {"coordinates":[-73.238553,40.882835],"type":"Point"}
}