{
  "type": "Feature",
  "properties": {
    "addr:full":"2 Victorian Ct Holtsville NY 11743",
    "addr:housenumber":"2",
    "addr:postcode":"11743",
    "addr:street":"Victorian Ct",
    "iso:country":"US",
    "sg:address":"2 Victorian Ct",
    "sg:city":"Holtsville",
    "sg:classifiers":[
        {
            "category":"Building & Trades",
            "subcategory":"Landscaping Services",
            "type":"Services"
        }
    ],
    "sg:phone":"+1 631 758 8671",
    "sg:postcode":"11743",
    "sg:province":"NY",
    "sg:tags":[
        "landscape",
        "contractor"
    ],
    "wof:name":"Victorian Gardens Inc",
    "wof:placetype":"venue"
},
  "geometry": {"coordinates":[-73.416842,40.87074],"type":"Point"}
}