{
  "type": "Feature",
  "properties": {
    "addr:full":"650 Morgan Ave Fl 2 Brooklyn NY 11222",
    "addr:housenumber":"650;2",
    "addr:postcode":"11222",
    "addr:street":"Morgan Ave Fl",
    "iso:country":"US",
    "sg:address":"650 Morgan Ave Fl 2",
    "sg:city":"Brooklyn",
    "sg:classifiers":[
        {
            "category":"Organizations",
            "subcategory":"Professional Association",
            "type":"Services"
        }
    ],
    "sg:phone":"+1 718 302 3330",
    "sg:postcode":"11222",
    "sg:province":"NY",
    "sg:tags":[
        "agency",
        "bureau",
        "entertainment"
    ],
    "sg:website":"http://www.tinrage.com",
    "wof:name":"Tin Rage Productions, Inc",
    "wof:placetype":"venue"
},
  "geometry": {"coordinates":[-73.939888,40.726507],"type":"Point"}
}