{
  "type": "Feature",
  "properties": {
    "addr:full":"37 Drake Rd Scarsdale NY 10583",
    "addr:housenumber":"37",
    "addr:postcode":"10583",
    "addr:street":"Drake Rd",
    "iso:country":"US",
    "sg:address":"37 Drake Rd",
    "sg:city":"Scarsdale",
    "sg:classifiers":[
        {
            "category":"Organizations",
            "subcategory":"Community Association",
            "type":"Services"
        }
    ],
    "sg:phone":"+1   ",
    "sg:postcode":"10583",
    "sg:province":"NY",
    "wof:name":"Scarsdale Womans Club Inc",
    "wof:placetype":"venue"
},
  "geometry": {"coordinates":[-73.79457499999999,40.987826],"type":"Point"}
}