{
  "type": "Feature",
  "properties": {
    "addr:full":"192 Split Rock Rd Syosset NY 11791",
    "addr:housenumber":"192",
    "addr:postcode":"11791",
    "addr:street":"Split Rock Rd",
    "iso:country":"US",
    "sg:address":"192 Split Rock Rd",
    "sg:city":"Syosset",
    "sg:classifiers":[
        {
            "category":"Wholesale",
            "subcategory":"Hardware",
            "type":"Manufacturing & Wholesale Goods"
        }
    ],
    "sg:phone":"+1 516 921 2423",
    "sg:postcode":"11791",
    "sg:province":"NY",
    "sg:tags":[
        "plumbing",
        "electrical",
        "supply"
    ],
    "wof:name":"Berg Enterprises",
    "wof:placetype":"venue"
},
  "geometry": {"coordinates":[-73.506523,40.832527],"type":"Point"}
}