{
  "type": "Feature",
  "properties": {
    "addr:full":"515 Avenue of the Americ New York NY 10011",
    "addr:housenumber":"515",
    "addr:postcode":"10011",
    "addr:street":"Avenue Of The",
    "iso:country":"US",
    "sg:address":"515 Avenue of the Americ",
    "sg:city":"New York",
    "sg:classifiers":[
        {
            "category":"Cinema",
            "subcategory":"Movie Rental",
            "type":"Entertainment"
        }
    ],
    "sg:phone":"+1 212 924 1466",
    "sg:postcode":"10011",
    "sg:province":"NY",
    "sg:tags":[
        "game",
        "video"
    ],
    "wof:name":"Star Entertainment",
    "wof:placetype":"venue"
},
  "geometry": {"coordinates":[-73.99729000000001,40.736967],"type":"Point"}
}