{
  "type": "Feature",
  "properties": {
    "addr:full":"2102 Utica Ave Brooklyn NY 11234",
    "addr:housenumber":"2102",
    "addr:postcode":"11234",
    "addr:street":"Utica Ave",
    "iso:country":"US",
    "sg:address":"2102 Utica Ave",
    "sg:city":"Brooklyn",
    "sg:classifiers":[
        {
            "category":"Home & Garden",
            "subcategory":"Furniture",
            "type":"Retail Goods"
        }
    ],
    "sg:phone":"+1   ",
    "sg:postcode":"11234",
    "sg:province":"NY",
    "sg:tags":[
        "matte"
    ],
    "wof:name":"Rfk Mattress and Furn Depo",
    "wof:placetype":"venue"
},
  "geometry": {"coordinates":[-73.927019,40.619747],"type":"Point"}
}