{
  "type": "Feature",
  "properties": {
    "iso:country":"US",
    "sg:address":"33 W 17 St",
    "sg:city":"New York",
    "sg:classifiers":[
        {
            "category":"Communications",
            "subcategory":"Film & Video Production",
            "type":"Services"
        }
    ],
    "sg:phone":"+1 212 620 0966",
    "sg:postcode":"10011",
    "sg:province":"NY",
    "sg:tags":[
        "taping"
    ],
    "wof:name":"Fountainhead Films",
    "wof:placetype":"venue"
},
  "geometry": {"coordinates":[-73.994612,40.738895],"type":"Point"}
}