{
  "type": "Feature",
  "properties": {
    "iso:country":"US",
    "sg:address":"2375 Rochester Rd",
    "sg:city":"Canandaigua",
    "sg:classifiers":[
        {
            "category":"Home & Garden",
            "subcategory":"Carpets & Floor Coverings",
            "type":"Retail Goods"
        }
    ],
    "sg:phone":"+1 585 919 0099",
    "sg:postcode":"14424",
    "sg:province":"NY",
    "sg:tags":[
        "dealer",
        "rug"
    ],
    "wof:name":"Kenny Carpet Of Canandaigua",
    "wof:placetype":"venue"
},
  "geometry": {"coordinates":[-77.30297899999999,42.915608],"type":"Point"}
}