{
  "type": "Feature",
  "properties": {
    "iso:country":"US",
    "sg:address":"619 Hudson Ave",
    "sg:city":"Rochester",
    "sg:classifiers":[
        {
            "category":"Restaurant",
            "type":"Food & Drink"
        }
    ],
    "sg:phone":"+1 585 266 8760",
    "sg:postcode":"14621",
    "sg:province":"NY",
    "wof:name":"Sooul Good",
    "wof:placetype":"venue"
},
  "geometry": {"coordinates":[-77.59890900000001,43.175612],"type":"Point"}
}