{
  "type": "Feature",
  "properties": {
    "addr:full":"325 Washington Ave Exd Albany NY 12205",
    "addr:housenumber":"325",
    "addr:postcode":"12205",
    "addr:street":"Washington Ave Exd",
    "iso:country":"US",
    "sg:address":"325 Washington Ave Exd",
    "sg:city":"Albany",
    "sg:classifiers":[
        {
            "category":"Manufacturing",
            "subcategory":"Tools & Machinery",
            "type":"Manufacturing & Wholesale Goods"
        }
    ],
    "sg:phone":"+1   ",
    "sg:postcode":"12205",
    "sg:province":"NY",
    "sg:tags":[
        "mfg",
        "research",
        "physical"
    ],
    "sg:website":"www.mtiinstruments.com",
    "wof:name":"MTI Instruments Inc",
    "wof:placetype":"venue"
},
  "geometry": {"coordinates":[-73.862382,42.707296],"type":"Point"}
}