{
  "type": "Feature",
  "properties": {
    "iso:country":"US",
    "sg:address":"6443 Ridings Rd",
    "sg:city":"Syracuse",
    "sg:classifiers":[
        {
            "category":"Wholesale",
            "subcategory":"Electrical",
            "type":"Manufacturing & Wholesale Goods"
        }
    ],
    "sg:phone":"+1 315 434 1849",
    "sg:postcode":"13206",
    "sg:province":"NY",
    "sg:tags":[
        "fire",
        "alarm",
        "system"
    ],
    "wof:name":"Electronic Technologies Co",
    "wof:placetype":"venue"
},
  "geometry": {"coordinates":[-76.10787000000001,43.081959],"type":"Point"}
}