{
  "type": "Feature",
  "properties": {
    "iso:country":"US",
    "sg:address":"8121 New Utrecht Ave",
    "sg:city":"Brooklyn",
    "sg:classifiers":[
        {
            "category":"Food & Beverages",
            "subcategory":"Groceries & Convenience Stores",
            "type":"Retail Goods"
        }
    ],
    "sg:phone":"+1 718 232 9651",
    "sg:postcode":"11214",
    "sg:province":"NY",
    "sg:tags":[
        "grocer"
    ],
    "wof:name":"Waldbaums Supermarkets",
    "wof:placetype":"venue"
},
  "geometry": {"coordinates":[-74.00129699999999,40.610699],"type":"Point"}
}