{
  "type": "Feature",
  "properties": {
    "iso:country":"US",
    "sg:address":"1137 Herkimer St",
    "sg:city":"Brooklyn",
    "sg:classifiers":[
        {
            "category":"Education",
            "subcategory":"School",
            "type":"Public Place"
        }
    ],
    "sg:phone":"+1 718 495 7787",
    "sg:postcode":"11233",
    "sg:province":"NY",
    "wof:name":"J M Coleman Junior High School",
    "wof:placetype":"venue"
},
  "geometry": {"coordinates":[-73.91555,40.677858],"type":"Point"}
}