{
  "type": "Feature",
  "properties": {
    "iso:country":"US",
    "sg:address":"25 W 54 St",
    "sg:city":"New York",
    "sg:classifiers":[
        {
            "category":"Professional",
            "subcategory":"Management & Consulting",
            "type":"Services"
        }
    ],
    "sg:phone":"+1 212 245 6613",
    "sg:postcode":"10019",
    "sg:province":"NY",
    "wof:name":"Lawrence P Fraiberg LLC",
    "wof:placetype":"venue"
},
  "geometry": {"coordinates":[-73.977966,40.762129],"type":"Point"}
}