{
  "type": "Feature",
  "properties": {
    "addr:full":"207 York St Rochester NY 14611",
    "addr:housenumber":"207",
    "addr:postcode":"14611",
    "addr:street":"York St",
    "iso:country":"US",
    "sg:address":"207 York St",
    "sg:city":"Rochester",
    "sg:classifiers":[
        {
            "category":"Home & Garden",
            "subcategory":"Furniture",
            "type":"Retail Goods"
        }
    ],
    "sg:phone":"+1   ",
    "sg:postcode":"14611",
    "sg:province":"NY",
    "sg:tags":[
        "carpentry",
        "contractor"
    ],
    "wof:name":"Design Concepts Custom Furn",
    "wof:placetype":"venue"
},
  "geometry": {"coordinates":[-77.637587,43.155132],"type":"Point"}
}