{
  "type": "Feature",
  "properties": {
    "addr:full":"105 W Main St Patchogue NY 11772",
    "addr:housenumber":"105",
    "addr:postcode":"11772",
    "addr:street":"W Main St",
    "iso:country":"US",
    "sg:address":"105 W Main St",
    "sg:city":"Patchogue",
    "sg:classifiers":[
        {
            "category":"Health Services",
            "subcategory":"Nursing And Care Facility",
            "type":"Services"
        }
    ],
    "sg:phone":"+1 631 687 2960",
    "sg:postcode":"11772",
    "sg:province":"NY",
    "sg:tags":[
        "skilled"
    ],
    "wof:name":"Brookhaven Memorial Hospice",
    "wof:placetype":"venue"
},
  "geometry": {"coordinates":[-73.01753600000001,40.765927],"type":"Point"}
}