{
  "type": "Feature",
  "properties": {
    "iso:country":"US",
    "sg:address":"57 Main St",
    "sg:city":"Southampton",
    "sg:classifiers":[
        {
            "category":"Manufacturing",
            "subcategory":"Jewelry",
            "type":"Manufacturing & Wholesale Goods"
        },
        {
            "category":"Retail",
            "subcategory":"Repair Shop",
            "type":"Services"
        },
        {
            "category":"Shopping",
            "subcategory":"Jewelry",
            "type":"Retail Goods"
        }
    ],
    "sg:phone":"+1 631 283 5757",
    "sg:postcode":"11968",
    "sg:province":"NY",
    "sg:tags":[
        "repairing",
        "jeweler",
        "designer",
        "clock"
    ],
    "sg:website":"http://www.rosejewelers.com",
    "wof:name":"Rose, Patchogue, Inc.",
    "wof:placetype":"venue"
},
  "geometry": {"coordinates":[-72.389449,40.885847],"type":"Point"}
}