{
  "type": "Feature",
  "properties": {
    "addr:full":"5480 Walker Rd Utica NY 13502",
    "addr:housenumber":"5480",
    "addr:postcode":"13502",
    "addr:street":"Walker Rd",
    "iso:country":"US",
    "sg:address":"5480 Walker Rd",
    "sg:city":"Utica",
    "sg:classifiers":[
        {
            "category":"Building & Trades",
            "subcategory":"Construction",
            "type":"Services"
        }
    ],
    "sg:phone":"+1 315 797 8836",
    "sg:postcode":"13502",
    "sg:province":"NY",
    "sg:tags":[
        "home",
        "improvement"
    ],
    "wof:name":"Sessions Small Home Repairs",
    "wof:placetype":"venue"
},
  "geometry": {"coordinates":[-75.201926,43.127082],"type":"Point"}
}