{
  "type": "Feature",
  "properties": {
    "iso:country":"US",
    "sg:address":"150 W 28th Street",
    "sg:city":"New York",
    "sg:classifiers":[
        {
            "category":"Health Services",
            "subcategory":"Hospital",
            "type":"Services"
        }
    ],
    "sg:phone":"+1 212 366 0702",
    "sg:postcode":"10001",
    "sg:province":"NY",
    "wof:name":"Rll Associates",
    "wof:placetype":"venue"
},
  "geometry": {"coordinates":[-73.991961,40.746627],"type":"Point"}
}