{
  "type": "Feature",
  "properties": {
    "addr:full":"1855 Richmond Ave Staten Island NY 10314",
    "addr:housenumber":"1855",
    "addr:postcode":"10314",
    "addr:street":"Richmond Ave",
    "iso:country":"US",
    "sg:address":"1855 Richmond Ave",
    "sg:city":"Staten Island",
    "sg:classifiers":[
        {
            "category":"Health Services",
            "subcategory":"Doctor",
            "type":"Services"
        }
    ],
    "sg:phone":"+1 718 761 2950",
    "sg:postcode":"10314",
    "sg:province":"NY",
    "sg:tags":[
        "physician",
        "surgeon"
    ],
    "wof:name":"North East Insomnia Sleep Mdcn",
    "wof:placetype":"venue"
},
  "geometry": {"coordinates":[-74.162876,40.60315],"type":"Point"}
}