{
  "type": "Feature",
  "properties": {
    "addr:full":"55 Roberta Ave Farmingville NY 11738",
    "addr:housenumber":"55",
    "addr:postcode":"11738",
    "addr:street":"Roberta Ave",
    "iso:country":"US",
    "sg:address":"55 Roberta Ave",
    "sg:city":"Farmingville",
    "sg:classifiers":[
        {
            "category":"Professional",
            "subcategory":"Art Services",
            "type":"Services"
        }
    ],
    "sg:phone":"+1 631 698 4154",
    "sg:postcode":"11738",
    "sg:province":"NY",
    "sg:tags":[
        "designer",
        "display",
        "producer"
    ],
    "wof:name":"Bonsai Designs Subhhadra Inc",
    "wof:placetype":"venue"
},
  "geometry": {"coordinates":[-73.04257200000001,40.84429],"type":"Point"}
}