{
  "type": "Feature",
  "properties": {
    "addr:full":"1307 W Main St Riverhead NY 11901",
    "addr:housenumber":"1307",
    "addr:postcode":"11901",
    "addr:street":"W Main St",
    "iso:country":"US",
    "sg:address":"1307 W Main St",
    "sg:city":"Riverhead",
    "sg:classifiers":[
        {
            "category":"Shopping",
            "subcategory":"Jewelry",
            "type":"Retail Goods"
        }
    ],
    "sg:phone":"+1 631 369 7143",
    "sg:postcode":"11901",
    "sg:province":"NY",
    "wof:name":"Ultra V Gold & Diamond Outlet",
    "wof:placetype":"venue"
},
  "geometry": {"coordinates":[-72.68470000000001,40.9151],"type":"Point"}
}