{
  "type": "Feature",
  "properties": {
    "iso:country":"US",
    "sg:address":"34 Hampton Rd",
    "sg:city":"Southampton",
    "sg:classifiers":[
        {
            "category":"Home & Garden",
            "subcategory":"Furniture",
            "type":"Retail Goods"
        }
    ],
    "sg:phone":"+1 631 283 2884",
    "sg:postcode":"11968",
    "sg:province":"NY",
    "wof:name":"Hampton Furniture Consignment",
    "wof:placetype":"venue"
},
  "geometry": {"coordinates":[-72.38861199999999,40.887264],"type":"Point"}
}