{
  "type": "Feature",
  "properties": {
    "iso:country":"US",
    "sg:address":"11 W 102nd St",
    "sg:city":"New York",
    "sg:classifiers":[
        {
            "category":"Real Estate",
            "subcategory":"Real Estate Operator",
            "type":"Services"
        }
    ],
    "sg:phone":"+1 212 663 0001",
    "sg:postcode":"10025",
    "sg:province":"NY",
    "sg:tags":[
        "apartment"
    ],
    "wof:name":"Kurt & Leah Schneider Apts",
    "wof:placetype":"venue"
},
  "geometry": {"coordinates":[-73.963117,40.796047],"type":"Point"}
}