{
  "type": "Feature",
  "properties": {
    "iso:country":"US",
    "sg:address":"150 71st St",
    "sg:city":"Niagara Falls",
    "sg:classifiers":[
        {
            "category":"Social Services",
            "subcategory":"Child Care",
            "type":"Services"
        }
    ],
    "sg:phone":"+1 716 283 2879",
    "sg:postcode":"14304",
    "sg:province":"NY",
    "sg:tags":[
        "day"
    ],
    "wof:name":"We Care Daycare",
    "wof:placetype":"venue"
},
  "geometry": {"coordinates":[-78.982832,43.074834],"type":"Point"}
}