{
  "type": "Feature",
  "properties": {
    "addr:full":"70 Champlin Ave Liberty NY 12754",
    "addr:housenumber":"70",
    "addr:postcode":"12754",
    "addr:street":"Champlin Ave",
    "iso:country":"US",
    "sg:address":"70 Champlin Ave",
    "sg:city":"Liberty",
    "sg:classifiers":[
        {
            "category":"Shopping",
            "type":"Retail Goods"
        }
    ],
    "sg:phone":"+1   ",
    "sg:postcode":"12754",
    "sg:province":"NY",
    "sg:tags":[
        "merchandise"
    ],
    "wof:name":"Harvey Smiths Coins",
    "wof:placetype":"venue"
},
  "geometry": {"coordinates":[-74.751604,41.802537],"type":"Point"}
}