{
  "type": "Feature",
  "properties": {
    "addr:full":"483 Hamilton St Geneva NY 14456",
    "addr:housenumber":"483",
    "addr:postcode":"14456",
    "addr:street":"Hamilton St",
    "iso:country":"US",
    "sg:address":"483 Hamilton St",
    "sg:city":"Geneva",
    "sg:classifiers":[
        {
            "category":"Restaurant",
            "type":"Food & Drink"
        }
    ],
    "sg:phone":"+1 315 789 2463",
    "sg:postcode":"14456",
    "sg:province":"NY",
    "wof:name":"Wendy's",
    "wof:placetype":"venue"
},
  "geometry": {"coordinates":[-77.00573799999999,42.856621],"type":"Point"}
}