{
  "type": "Feature",
  "properties": {
    "iso:country":"US",
    "sg:address":"124 Tapscott St",
    "sg:city":"Brooklyn",
    "sg:classifiers":[
        {
            "category":"Freight",
            "type":"Transportation"
        }
    ],
    "sg:phone":"+1   ",
    "sg:postcode":"11212",
    "sg:province":"NY",
    "sg:tags":[
        "operator",
        "local",
        "trucking"
    ],
    "wof:name":"Walter Trucking",
    "wof:placetype":"venue"
},
  "geometry": {"coordinates":[-73.920287,40.664922],"type":"Point"}
}