{
  "type": "Feature",
  "properties": {
    "iso:country":"US",
    "sg:address":"247 W 35 St",
    "sg:city":"New York",
    "sg:classifiers":[
        {
            "category":"Building & Trades",
            "subcategory":"Construction",
            "type":"Services"
        }
    ],
    "sg:phone":"+1 212 244 5566",
    "sg:postcode":"10001",
    "sg:province":"NY",
    "sg:tags":[
        "house"
    ],
    "wof:name":"Keptech Builders Group LLC",
    "wof:placetype":"venue"
},
  "geometry": {"coordinates":[-73.99193,40.752359],"type":"Point"}
}