{
  "type": "Feature",
  "properties": {
    "addr:full":"35 Main St Poughkeepsie NY 12601",
    "addr:housenumber":"35",
    "addr:postcode":"12601",
    "addr:street":"Main St",
    "iso:country":"US",
    "sg:address":"35 Main St",
    "sg:city":"Poughkeepsie",
    "sg:classifiers":[
        {
            "category":"Professional",
            "type":"Services"
        }
    ],
    "sg:phone":"+1 845 485 8556",
    "sg:postcode":"12601",
    "sg:province":"NY",
    "sg:tags":[
        "establishment"
    ],
    "wof:name":"Homeward Bound",
    "wof:placetype":"venue"
},
  "geometry": {"coordinates":[-73.93806600000001,41.705624],"type":"Point"}
}