{
  "type": "Feature",
  "properties": {
    "addr:full":"180 Buffalo St Hamburg NY 14075",
    "addr:housenumber":"180",
    "addr:postcode":"14075",
    "addr:street":"Buffalo St",
    "iso:country":"US",
    "sg:address":"180 Buffalo St",
    "sg:city":"Hamburg",
    "sg:classifiers":[
        {
            "category":"Professional",
            "subcategory":"Art Services",
            "type":"Services"
        }
    ],
    "sg:phone":"+1   ",
    "sg:postcode":"14075",
    "sg:province":"NY",
    "sg:tags":[
        "commercial",
        "printing",
        "design"
    ],
    "wof:name":"Southtown Sports Center",
    "wof:placetype":"venue"
},
  "geometry": {"coordinates":[-78.828253,42.719235],"type":"Point"}
}