{
  "type": "Feature",
  "properties": {
    "iso:country":"US",
    "sg:address":"1 Liberty Plz 22nd Fl",
    "sg:city":"New York",
    "sg:classifiers":[
        {
            "category":"Education",
            "subcategory":"Special Training",
            "type":"Public Place"
        }
    ],
    "sg:phone":"+1 888 527 5268",
    "sg:postcode":"10006",
    "sg:province":"NY",
    "sg:tags":[
        "educational"
    ],
    "sg:website":"www.kaplank12.com",
    "wof:name":"Kaplan K12 Learning",
    "wof:placetype":"venue"
},
  "geometry": {"coordinates":[-74.011588,40.709331],"type":"Point"}
}