{
  "type": "Feature",
  "properties": {
    "addr:full":"150 Marcy Ave Brooklyn NY 11211",
    "addr:housenumber":"150",
    "addr:postcode":"11211",
    "addr:street":"Marcy Ave",
    "iso:country":"US",
    "sg:address":"150 Marcy Ave",
    "sg:city":"Brooklyn",
    "sg:classifiers":[
        {
            "category":"Banks & Credit Unions",
            "subcategory":"Bank",
            "type":"Services"
        }
    ],
    "sg:phone":"+1 718 302 1069",
    "sg:postcode":"11211",
    "sg:province":"NY",
    "wof:name":"Dime Savings Bank",
    "wof:placetype":"venue"
},
  "geometry": {"coordinates":[-73.957435,40.709456],"type":"Point"}
}