{
  "type": "Feature",
  "properties": {
    "addr:full":"242 E State St Ext Gloversville NY 12078",
    "addr:housenumber":"242",
    "addr:postcode":"12078",
    "addr:street":"E State St Ext",
    "iso:country":"US",
    "sg:address":"242 E State St Ext",
    "sg:city":"Gloversville",
    "sg:classifiers":[
        {
            "category":"Health Services",
            "subcategory":"Doctor",
            "type":"Services"
        }
    ],
    "sg:phone":"+1 518 725 2227",
    "sg:postcode":"12078",
    "sg:province":"NY",
    "sg:tags":[
        "medicine",
        "physician",
        "surgeon",
        "internal",
        "surgeons"
    ],
    "wof:name":"Warner Jr Robert C Md",
    "wof:placetype":"venue"
},
  "geometry": {"coordinates":[-74.31381500000001,43.07258],"type":"Point"}
}