{
  "type": "Feature",
  "properties": {
    "iso:country":"US",
    "sg:address":"200 Franklin St",
    "sg:city":"Watertown",
    "sg:classifiers":[
        {
            "category":"Real Estate",
            "subcategory":"Real Estate Operator",
            "type":"Services"
        }
    ],
    "sg:phone":"+1 315 788 7720",
    "sg:postcode":"13601",
    "sg:province":"NY",
    "sg:tags":[
        "building",
        "nonresidential"
    ],
    "wof:name":"Phelps Corporation",
    "wof:placetype":"venue"
},
  "geometry": {"coordinates":[-75.908934,43.973701],"type":"Point"}
}