{
  "type": "Feature",
  "properties": {
    "iso:country":"US",
    "sg:address":"4 Elizabeth St",
    "sg:city":"Scarsdale",
    "sg:classifiers":[
        {
            "category":"Shopping",
            "subcategory":"Pets & Pet Supplies",
            "type":"Retail Goods"
        }
    ],
    "sg:phone":"+1 914 328 7122",
    "sg:postcode":"10583",
    "sg:province":"NY",
    "sg:tags":[
        "specialty"
    ],
    "wof:name":"Westchester Barkery",
    "wof:placetype":"venue"
},
  "geometry": {"coordinates":[-73.810895,41.013893],"type":"Point"}
}