{
  "type": "Feature",
  "properties": {
    "addr:full":"198 N Plank Rd Newburgh NY 12550",
    "addr:housenumber":"198",
    "addr:postcode":"12550",
    "addr:street":"N Plank Rd",
    "iso:country":"US",
    "sg:address":"198 N Plank Rd",
    "sg:city":"Newburgh",
    "sg:classifiers":[
        {
            "category":"Food & Beverages",
            "subcategory":"Liquor & Beverages",
            "type":"Retail Goods"
        }
    ],
    "sg:phone":"+1 845 561 2738",
    "sg:postcode":"12550",
    "sg:province":"NY",
    "wof:name":"Welch's Wine & Liquor",
    "wof:placetype":"venue"
},
  "geometry": {"coordinates":[-74.044997,41.541326],"type":"Point"}
}