{
  "type": "Feature",
  "properties": {
    "iso:country":"US",
    "sg:address":"54 West Ave",
    "sg:city":"Fairport",
    "sg:classifiers":[
        {
            "category":"Health Services",
            "subcategory":"Medical Lab",
            "type":"Services"
        }
    ],
    "sg:phone":"+1   ",
    "sg:postcode":"14450",
    "sg:province":"NY",
    "sg:tags":[
        "dental",
        "restoration",
        "mfg"
    ],
    "wof:name":"D & M Crown & Bridge Inc",
    "wof:placetype":"venue"
},
  "geometry": {"coordinates":[-77.444169,43.101568],"type":"Point"}
}