{
  "type": "Feature",
  "properties": {
    "addr:full":"749 Middle Neck Rd Great Neck NY 11024",
    "addr:housenumber":"749",
    "addr:postcode":"11024",
    "addr:street":"Middle Neck Rd",
    "iso:country":"US",
    "sg:address":"749 Middle Neck Rd",
    "sg:city":"Great Neck",
    "sg:classifiers":[
        {
            "category":"Shopping",
            "subcategory":"Computers & Home Electronics",
            "type":"Retail Goods"
        }
    ],
    "sg:phone":"+1 212 288 2855",
    "sg:postcode":"11024",
    "sg:province":"NY",
    "sg:tags":[
        "equipment",
        "electronic",
        "supply"
    ],
    "wof:name":"Ears Nova High Fidelity",
    "wof:placetype":"venue"
},
  "geometry": {"coordinates":[-73.73551999999999,40.808477],"type":"Point"}
}