{
  "type": "Feature",
  "properties": {
    "iso:country":"US",
    "sg:address":"265 Spagnoli Rd",
    "sg:city":"Melville",
    "sg:classifiers":[
        {
            "category":"Professional",
            "type":"Services"
        }
    ],
    "sg:phone":"+1 631 845 2026",
    "sg:postcode":"11747",
    "sg:province":"NY",
    "sg:tags":[
        "establishment"
    ],
    "wof:name":"Chyron Corp",
    "wof:placetype":"venue"
},
  "geometry": {"coordinates":[-73.42408,40.762823],"type":"Point"}
}