{
  "type": "Feature",
  "properties": {
    "addr:full":"339 Flatbush Ave Brooklyn NY 11217",
    "addr:housenumber":"339",
    "addr:postcode":"11217",
    "addr:street":"Flatbush Ave",
    "iso:country":"US",
    "sg:address":"339 Flatbush Ave",
    "sg:city":"Brooklyn",
    "sg:classifiers":[
        {
            "category":"Shopping",
            "subcategory":"Clothing, Apparel, & Fashions",
            "type":"Retail Goods"
        }
    ],
    "sg:phone":"+1 718 622 3804",
    "sg:postcode":"11217",
    "sg:province":"NY",
    "sg:tags":[
        "accessory",
        "clothing",
        "women's"
    ],
    "wof:name":"Redberi",
    "wof:placetype":"venue"
},
  "geometry": {"coordinates":[-73.97262000000001,40.677697],"type":"Point"}
}