{
  "type": "Feature",
  "properties": {
    "addr:full":"341 Commack Rd Commack NY 11725",
    "addr:housenumber":"341",
    "addr:postcode":"11725",
    "addr:street":"Commack Rd",
    "iso:country":"US",
    "sg:address":"341 Commack Rd",
    "sg:city":"Commack",
    "sg:classifiers":[
        {
            "category":"Shopping",
            "subcategory":"Pharmacy",
            "type":"Retail Goods"
        }
    ],
    "sg:phone":"+1 631 462 9169",
    "sg:postcode":"11725",
    "sg:province":"NY",
    "sg:tags":[
        "drugstore"
    ],
    "wof:name":"C V S Pharmacy",
    "wof:placetype":"venue"
},
  "geometry": {"coordinates":[-73.2929,40.827301],"type":"Point"}
}