{
  "type": "Feature",
  "properties": {
    "addr:full":"1881 Wantagh Ave Wantagh NY 11793",
    "addr:housenumber":"1881",
    "addr:postcode":"11793",
    "addr:street":"Wantagh Ave",
    "iso:country":"US",
    "sg:address":"1881 Wantagh Ave",
    "sg:city":"Wantagh",
    "sg:classifiers":[
        {
            "category":"Social Services",
            "type":"Services"
        }
    ],
    "sg:phone":"+1 516 679 5744",
    "sg:postcode":"11793",
    "sg:province":"NY",
    "sg:tags":[
        "youth",
        "organization",
        "center"
    ],
    "wof:name":"Wantagh Little League",
    "wof:placetype":"venue"
},
  "geometry": {"coordinates":[-73.510008,40.674092],"type":"Point"}
}