{
  "type": "Feature",
  "properties": {
    "iso:country":"US",
    "sg:address":"589 Fort Washington Ave",
    "sg:city":"New York",
    "sg:classifiers":[
        {
            "category":"Food & Beverages",
            "subcategory":"Groceries & Convenience Stores",
            "type":"Retail Goods"
        }
    ],
    "sg:phone":"+1 212 781 9534",
    "sg:postcode":"10033",
    "sg:province":"NY",
    "wof:name":"Fort Tryon Deli",
    "wof:placetype":"venue"
},
  "geometry": {"coordinates":[-73.93710299999999,40.854801],"type":"Point"}
}