{
  "type": "Feature",
  "properties": {
    "addr:full":"10901 Union Hall St Jamaica NY 11433",
    "addr:housenumber":"10901",
    "addr:postcode":"11433",
    "addr:street":"Union Hall St",
    "iso:country":"US",
    "sg:address":"10901 Union Hall St",
    "sg:city":"Jamaica",
    "sg:classifiers":[
        {
            "category":"Organizations",
            "subcategory":"Religious Organization",
            "type":"Services"
        }
    ],
    "sg:phone":"+1 718 523 8847",
    "sg:postcode":"11433",
    "sg:province":"NY",
    "wof:name":"Free Wheel Missionary Baptist Church",
    "wof:placetype":"venue"
},
  "geometry": {"coordinates":[-73.790802,40.694599],"type":"Point"}
}