{
  "type": "Feature",
  "properties": {
    "addr:full":"229 Elm Ave E Selkirk NY 12158",
    "addr:housenumber":"229",
    "addr:postcode":"12158",
    "addr:street":"Elm Ave E",
    "iso:country":"US",
    "sg:address":"229 Elm Ave E",
    "sg:city":"Selkirk",
    "sg:classifiers":[
        {
            "category":"Banks & Credit Unions",
            "subcategory":"Investment Brokerage",
            "type":"Services"
        }
    ],
    "sg:phone":"+1 518 478 7204",
    "sg:postcode":"12158",
    "sg:province":"NY",
    "sg:tags":[
        "consultant",
        "planning",
        "financial"
    ],
    "wof:name":"Linsco Private Ledger",
    "wof:placetype":"venue"
},
  "geometry": {"coordinates":[-73.825498,42.579956],"type":"Point"}
}