{
  "type": "Feature",
  "properties": {
    "addr:full":"16 College St Clinton NY 13323",
    "addr:housenumber":"16",
    "addr:postcode":"13323",
    "addr:street":"College St",
    "iso:country":"US",
    "sg:address":"16 College St",
    "sg:city":"Clinton",
    "sg:classifiers":[
        {
            "category":"Real Estate",
            "subcategory":"Real Estate Agent",
            "type":"Services"
        }
    ],
    "sg:phone":"+1 315 853 3535",
    "sg:postcode":"13323",
    "sg:province":"NY",
    "sg:website":"www.sextonrealestate.com",
    "wof:name":"Sexton Real Estate",
    "wof:placetype":"venue"
},
  "geometry": {"coordinates":[-75.380045,43.048287],"type":"Point"}
}