{
  "type": "Feature",
  "properties": {
    "iso:country":"US",
    "sg:address":"1467 Madison St",
    "sg:city":"Elmont",
    "sg:classifiers":[
        {
            "category":"Manufacturing",
            "subcategory":"Tools & Machinery",
            "type":"Manufacturing & Wholesale Goods"
        }
    ],
    "sg:phone":"+1   ",
    "sg:postcode":"11003",
    "sg:province":"NY",
    "sg:tags":[
        "industrial",
        "mfg"
    ],
    "wof:name":"Zorlenzans Amusements Inc",
    "wof:placetype":"venue"
},
  "geometry": {"coordinates":[-73.69522600000001,40.710736],"type":"Point"}
}