{
  "type": "Feature",
  "properties": {
    "iso:country":"US",
    "sg:address":"9 Oval Ct",
    "sg:city":"Stony Brook",
    "sg:classifiers":[
        {
            "category":"Home & Garden",
            "subcategory":"Home Furnishings",
            "type":"Retail Goods"
        }
    ],
    "sg:phone":"+1 631 751 0552",
    "sg:postcode":"11790",
    "sg:province":"NY",
    "sg:tags":[
        "blind",
        "window",
        "treatment",
        "shade"
    ],
    "wof:name":"Superior Window Treatments",
    "wof:placetype":"venue"
},
  "geometry": {"coordinates":[-73.12400100000001,40.883801],"type":"Point"}
}