{
  "type": "Feature",
  "properties": {
    "addr:full":"5621 Avenue N Brooklyn NY 11234",
    "addr:housenumber":"5621",
    "addr:postcode":"11234",
    "addr:street":"Avenue N",
    "iso:country":"US",
    "sg:address":"5621 Avenue N",
    "sg:city":"Brooklyn",
    "sg:classifiers":[
        {
            "category":"Building & Trades",
            "subcategory":"Construction",
            "type":"Services"
        }
    ],
    "sg:phone":"+1 718 797 2616",
    "sg:postcode":"11234",
    "sg:province":"NY",
    "sg:tags":[
        "repair",
        "inspector",
        "installation",
        "consulting",
        "elevator-consultants"
    ],
    "wof:name":"Direct Elevator Co Corp",
    "wof:placetype":"venue"
},
  "geometry": {"coordinates":[-73.92091000000001,40.619315],"type":"Point"}
}