{
  "type": "Feature",
  "properties": {
    "addr:full":"122 E Genesee St Syracuse NY 13202",
    "addr:housenumber":"122",
    "addr:postcode":"13202",
    "addr:street":"E Genesee St",
    "iso:country":"US",
    "sg:address":"122 E Genesee St",
    "sg:city":"Syracuse",
    "sg:classifiers":[
        {
            "category":"Bars & Pubs",
            "type":"Food & Drink"
        },
        {
            "category":"Restaurant",
            "type":"Food & Drink"
        }
    ],
    "sg:phone":"+1 315 425 1784",
    "sg:postcode":"13202",
    "sg:province":"NY",
    "sg:tags":[
        "drinking"
    ],
    "wof:name":"Quigley's Tavern",
    "wof:placetype":"venue"
},
  "geometry": {"coordinates":[-76.150926,43.05022],"type":"Point"}
}