{
  "type": "Feature",
  "properties": {
    "addr:full":"525 Broome St New York NY 10013",
    "addr:housenumber":"525",
    "addr:postcode":"10013",
    "addr:street":"Broome St",
    "iso:country":"US",
    "sg:address":"525 Broome St",
    "sg:city":"New York",
    "sg:classifiers":[
        {
            "category":"Wholesale",
            "subcategory":"Durable Goods & Equipment",
            "type":"Manufacturing & Wholesale Goods"
        }
    ],
    "sg:phone":"+1 212 216 0025",
    "sg:postcode":"10013",
    "sg:province":"NY",
    "sg:tags":[
        "importer"
    ],
    "wof:name":"Gatto Iop Enterprise Inc",
    "wof:placetype":"venue"
},
  "geometry": {"coordinates":[-74.004023,40.723729],"type":"Point"}
}