{
  "type": "Feature",
  "properties": {
    "addr:full":"1 Main St Dundee NY 14837",
    "addr:housenumber":"1",
    "addr:postcode":"14837",
    "addr:street":"Main St",
    "iso:country":"US",
    "sg:address":"1 Main St",
    "sg:city":"Dundee",
    "sg:classifiers":[
        {
            "category":"Professional",
            "subcategory":"Accounting & Tax Preparation",
            "type":"Services"
        }
    ],
    "sg:phone":"+1 607 243 5800",
    "sg:postcode":"14837",
    "sg:province":"NY",
    "sg:tags":[
        "accountant"
    ],
    "wof:name":"Herrmann's Business Svc Inc",
    "wof:placetype":"venue"
},
  "geometry": {"coordinates":[-76.976871,42.523385],"type":"Point"}
}