{
  "type": "Feature",
  "properties": {
    "iso:country":"US",
    "sg:address":"295 N Sea Rd",
    "sg:city":"Southampton",
    "sg:classifiers":[
        {
            "category":"Professional",
            "type":"Services"
        }
    ],
    "sg:phone":"+1 631 287 6500",
    "sg:postcode":"11968",
    "sg:province":"NY",
    "sg:tags":[
        "establishment"
    ],
    "wof:name":"John D KERN Esquire PC",
    "wof:placetype":"venue"
},
  "geometry": {"coordinates":[-72.397739,40.895168],"type":"Point"}
}