{
  "type": "Feature",
  "properties": {
    "addr:full":"115 E 61st Street Bsmt New York NY 10021",
    "addr:housenumber":"115",
    "addr:postcode":"10021",
    "addr:street":"E 61St Street",
    "iso:country":"US",
    "sg:address":"115 E 61st Street Bsmt",
    "sg:city":"New York",
    "sg:classifiers":[
        {
            "category":"Health Services",
            "subcategory":"Dentist",
            "type":"Services"
        }
    ],
    "sg:phone":"+1 212 421 8118",
    "sg:postcode":"10021",
    "sg:province":"NY",
    "wof:name":"Zinner Ira D DDS PC",
    "wof:placetype":"venue"
},
  "geometry": {"coordinates":[-73.968205,40.763887],"type":"Point"}
}