{
  "type": "Feature",
  "properties": {
    "addr:full":"1327 Cold Spring Rd Forestburgh NY 12777",
    "addr:housenumber":"1327",
    "addr:postcode":"12777",
    "addr:street":"Cold Spring Rd",
    "iso:country":"US",
    "sg:address":"1327 Cold Spring Rd",
    "sg:city":"Forestburgh",
    "sg:classifiers":[
        {
            "category":"Farming",
            "subcategory":"Aquatic Farm",
            "type":"Manufacturing & Wholesale Goods"
        }
    ],
    "sg:phone":"+1 845 796 1749",
    "sg:postcode":"12777",
    "sg:province":"NY",
    "sg:tags":[
        "fish"
    ],
    "wof:name":"Eden Brook Trout Hatchery",
    "wof:placetype":"venue"
},
  "geometry": {"coordinates":[-74.67213599999999,41.573039],"type":"Point"}
}