{
  "type": "Feature",
  "properties": {
    "iso:country":"US",
    "sg:address":"12 Hemlock Ln",
    "sg:city":"Bay Shore",
    "sg:classifiers":[
        {
            "category":"Building & Trades",
            "subcategory":"Plumbing",
            "type":"Services"
        }
    ],
    "sg:phone":"+1 631 666 0640",
    "sg:postcode":"11706",
    "sg:province":"NY",
    "sg:tags":[
        "plumbing",
        "heating",
        "contractor"
    ],
    "wof:name":"Excel Plumbing & Heating Co",
    "wof:placetype":"venue"
},
  "geometry": {"coordinates":[-73.257223,40.716663],"type":"Point"}
}