{
  "type": "Feature",
  "properties": {
    "iso:country":"US",
    "sg:address":"219 E 5 St",
    "sg:city":"New York",
    "sg:classifiers":[
        {
            "category":"Personal",
            "subcategory":"Beauty Salon",
            "type":"Services"
        }
    ],
    "sg:phone":"+1 212 228 5009",
    "sg:postcode":"10003",
    "sg:province":"NY",
    "wof:name":"Hair In The City",
    "wof:placetype":"venue"
},
  "geometry": {"coordinates":[-73.99020299999999,40.727556],"type":"Point"}
}