{
  "type": "Feature",
  "properties": {
    "iso:country":"US",
    "sg:address":"17748 106th Rd",
    "sg:city":"Jamaica",
    "sg:classifiers":[
        {
            "category":"Building & Trades",
            "subcategory":"Construction",
            "type":"Services"
        }
    ],
    "sg:phone":"+1 718 206 1030",
    "sg:postcode":"11433",
    "sg:province":"NY",
    "sg:tags":[
        "carpenter"
    ],
    "wof:name":"W & U Construction, Inc.",
    "wof:placetype":"venue"
},
  "geometry": {"coordinates":[-73.780165,40.702382],"type":"Point"}
}