{
  "type": "Feature",
  "properties": {
    "iso:country":"US",
    "sg:address":"20 Dongan Pl",
    "sg:city":"New York",
    "sg:classifiers":[
        {
            "category":"Professional",
            "subcategory":"Computer Services",
            "type":"Services"
        }
    ],
    "sg:phone":"+1   ",
    "sg:postcode":"10040",
    "sg:province":"NY",
    "sg:tags":[
        "related"
    ],
    "wof:name":"Gigtech Inc",
    "wof:placetype":"venue"
},
  "geometry": {"coordinates":[-73.929079,40.863407],"type":"Point"}
}