{
  "type": "Feature",
  "properties": {
    "addr:full":"15703 89th Street Howard Beach NY 11414",
    "addr:housenumber":"15703",
    "addr:postcode":"11414",
    "addr:street":"89Th Street",
    "iso:country":"US",
    "sg:address":"15703 89th Street",
    "sg:city":"Howard Beach",
    "sg:classifiers":[
        {
            "category":"Building & Trades",
            "subcategory":"Plumbing",
            "type":"Services"
        }
    ],
    "sg:phone":"+1 718 641 3500",
    "sg:postcode":"11414",
    "sg:province":"NY",
    "wof:name":"L & I Mechanical Contractors Corporation",
    "wof:placetype":"venue"
},
  "geometry": {"coordinates":[-73.844266,40.661817],"type":"Point"}
}