{
  "type": "Feature",
  "properties": {
    "iso:country":"US",
    "sg:address":"299 Fullerton Ave",
    "sg:city":"Newburgh",
    "sg:classifiers":[
        {
            "category":"Health Services",
            "subcategory":"Chiropractor",
            "type":"Services"
        }
    ],
    "sg:phone":"+1 845 565 6290",
    "sg:postcode":"12550",
    "sg:province":"NY",
    "sg:website":"baltsas.chiroweb.com",
    "wof:name":"Baltsas Chiropractic",
    "wof:placetype":"venue"
},
  "geometry": {"coordinates":[-74.025299,41.512798],"type":"Point"}
}