{
  "type": "Feature",
  "properties": {
    "addr:full":"10 Little Ln Hauppauge NY 11788",
    "addr:housenumber":"10",
    "addr:postcode":"11788",
    "addr:street":"Little Ln",
    "iso:country":"US",
    "sg:address":"10 Little Ln",
    "sg:city":"Hauppauge",
    "sg:classifiers":[
        {
            "category":"Shopping",
            "subcategory":"Beauty & Cosmetics",
            "type":"Retail Goods"
        }
    ],
    "sg:phone":"+1 631 375 8817",
    "sg:postcode":"11788",
    "sg:province":"NY",
    "sg:tags":[
        "perfume"
    ],
    "wof:name":"Avon Mlm",
    "wof:placetype":"venue"
},
  "geometry": {"coordinates":[-73.189609,40.818164],"type":"Point"}
}