{
  "type": "Feature",
  "properties": {
    "iso:country":"US",
    "sg:address":"175 Front St",
    "sg:city":"Vestal",
    "sg:classifiers":[
        {
            "category":"Personal",
            "subcategory":"Beauty Salon",
            "type":"Services"
        }
    ],
    "sg:phone":"+1 607 785 0660",
    "sg:postcode":"13850",
    "sg:province":"NY",
    "wof:name":"All Natural",
    "wof:placetype":"venue"
},
  "geometry": {"coordinates":[-76.05955299999999,42.083476],"type":"Point"}
}