{
  "type": "Feature",
  "properties": {
    "iso:country":"US",
    "sg:address":"375 Central Ave",
    "sg:city":"Bohemia",
    "sg:classifiers":[
        {
            "category":"Organizations",
            "subcategory":"Labor Organization",
            "type":"Services"
        }
    ],
    "sg:phone":"+1 631 567 3083",
    "sg:postcode":"11716",
    "sg:province":"NY",
    "wof:name":"Plumbers",
    "wof:placetype":"venue"
},
  "geometry": {"coordinates":[-73.090124,40.779868],"type":"Point"}
}