{
  "type": "Feature",
  "properties": {
    "iso:country":"US",
    "sg:address":"1461 Franklin Ave",
    "sg:city":"Garden City",
    "sg:classifiers":[
        {
            "category":"Professional",
            "subcategory":"Lawyer & Legal Services",
            "type":"Services"
        }
    ],
    "sg:phone":"+1 516 535 6660",
    "sg:postcode":"11530",
    "sg:province":"NY",
    "sg:tags":[
        "attorney"
    ],
    "wof:name":"Robert D Rosen Attorney",
    "wof:placetype":"venue"
},
  "geometry": {"coordinates":[-73.638409,40.736341],"type":"Point"}
}