{
  "type": "Feature",
  "properties": {
    "addr:full":"1361 Amsterdam Ave New York NY 10027",
    "addr:housenumber":"1361",
    "addr:postcode":"10027",
    "addr:street":"Amsterdam Ave",
    "iso:country":"US",
    "sg:address":"1361 Amsterdam Ave",
    "sg:city":"New York",
    "sg:classifiers":[
        {
            "category":"Arts & Performance",
            "subcategory":"Theater",
            "type":"Entertainment"
        }
    ],
    "sg:phone":"+1 212 663 2300",
    "sg:postcode":"10027",
    "sg:province":"NY",
    "sg:tags":[
        "theatrical",
        "supply",
        "wholesale",
        "rent",
        "props",
        "janitorial"
    ],
    "wof:name":"State Supply Equipment & Props",
    "wof:placetype":"venue"
},
  "geometry": {"coordinates":[-73.95541,40.814418],"type":"Point"}
}