{
  "type": "Feature",
  "properties": {
    "iso:country":"US",
    "sg:address":"495 Winding Rd N",
    "sg:city":"Ardsley",
    "sg:classifiers":[
        {
            "category":"Wholesale",
            "subcategory":"Machinery & Supplies",
            "type":"Manufacturing & Wholesale Goods"
        }
    ],
    "sg:phone":"+1 914 693 0772",
    "sg:postcode":"10502",
    "sg:province":"NY",
    "sg:tags":[
        "industrial",
        "miscellaneous"
    ],
    "wof:name":"Photographic Equipment Svc",
    "wof:placetype":"venue"
},
  "geometry": {"coordinates":[-73.850942,41.002684],"type":"Point"}
}