{
  "type": "Feature",
  "properties": {
    "iso:country":"US",
    "sg:address":"97 Lemon St",
    "sg:city":"Buffalo",
    "sg:classifiers":[
        {
            "category":"Organizations",
            "subcategory":"Non-profit Organization",
            "type":"Services"
        }
    ],
    "sg:phone":"+1 716 856 0363",
    "sg:postcode":"14204",
    "sg:province":"NY",
    "sg:tags":[
        "agency",
        "human"
    ],
    "wof:name":"Bfnc",
    "wof:placetype":"venue"
},
  "geometry": {"coordinates":[-78.85954700000001,42.898094],"type":"Point"}
}