{
  "type": "Feature",
  "properties": {
    "iso:country":"US",
    "sg:address":"69 Greenview Ct",
    "sg:city":"Oakdale",
    "sg:classifiers":[
        {
            "category":"Professional",
            "type":"Services"
        }
    ],
    "sg:phone":"+1 631 218 1771",
    "sg:postcode":"11769",
    "sg:province":"NY",
    "sg:tags":[
        "establishment"
    ],
    "wof:name":"Greenview Court",
    "wof:placetype":"venue"
},
  "geometry": {"coordinates":[-73.127729,40.743122],"type":"Point"}
}