{
  "type": "Feature",
  "properties": {
    "addr:full":"37 Wisconsin Ave Queensbury NY 12804",
    "addr:postcode":"12804",
    "addr:street":"37 Wisconsin Ave",
    "iso:country":"US",
    "sg:address":"37 Wisconsin Ave",
    "sg:city":"Queensbury",
    "sg:classifiers":[
        {
            "category":"Personal",
            "subcategory":"Beauty Salon",
            "type":"Services"
        }
    ],
    "sg:phone":"+1 518 798 9671",
    "sg:postcode":"12804",
    "sg:province":"NY",
    "wof:name":"Master Cuts",
    "wof:placetype":"venue"
},
  "geometry": {"coordinates":[-73.68959599999999,43.299062],"type":"Point"}
}