{
  "type": "Feature",
  "properties": {
    "addr:full":"9 Desbrosses St New York NY 10013",
    "addr:housenumber":"9",
    "addr:postcode":"10013",
    "addr:street":"Desbrosses St",
    "iso:country":"US",
    "sg:address":"9 Desbrosses St",
    "sg:city":"New York",
    "sg:classifiers":[
        {
            "category":"Professional",
            "subcategory":"Art Services",
            "type":"Services"
        }
    ],
    "sg:phone":"+1 212 941 1329",
    "sg:postcode":"10013",
    "sg:province":"NY",
    "sg:tags":[
        "graphic",
        "design",
        "designer"
    ],
    "wof:name":"Hudson Street Design",
    "wof:placetype":"venue"
},
  "geometry": {"coordinates":[-74.009029,40.723292],"type":"Point"}
}