{
  "type": "Feature",
  "properties": {
    "addr:full":"50 Owasco St Auburn NY 13021",
    "addr:housenumber":"50",
    "addr:postcode":"13021",
    "addr:street":"Owasco St",
    "iso:country":"US",
    "sg:address":"50 Owasco St",
    "sg:city":"Auburn",
    "sg:classifiers":[
        {
            "category":"Food & Beverages",
            "subcategory":"Groceries & Convenience Stores",
            "type":"Retail Goods"
        }
    ],
    "sg:phone":"+1 315 255 1008",
    "sg:postcode":"13021",
    "sg:province":"NY",
    "wof:name":"Fine Food & Gas",
    "wof:placetype":"venue"
},
  "geometry": {"coordinates":[-76.558815,42.930659],"type":"Point"}
}