{
  "type": "Feature",
  "properties": {
    "addr:full":"88 Delancey St New York NY 10002",
    "addr:housenumber":"88",
    "addr:postcode":"10002",
    "addr:street":"Delancey St",
    "iso:country":"US",
    "sg:address":"88 Delancey St",
    "sg:city":"New York",
    "sg:classifiers":[
        {
            "category":"Shopping",
            "subcategory":"Clothing, Apparel, & Fashions",
            "type":"Retail Goods"
        }
    ],
    "sg:phone":"+1 212 260 0100",
    "sg:postcode":"10002",
    "sg:province":"NY",
    "sg:tags":[
        "infant",
        "wear"
    ],
    "wof:name":"Kids Playhouse",
    "wof:placetype":"venue"
},
  "geometry": {"coordinates":[-73.98907800000001,40.718904],"type":"Point"}
}