{
  "type": "Feature",
  "properties": {
    "addr:full":"48 7 Ave New York NY 10011",
    "addr:postcode":"10011",
    "addr:street":"48 7 Ave",
    "iso:country":"US",
    "sg:address":"48 7 Ave",
    "sg:city":"New York",
    "sg:classifiers":[
        {
            "category":"Retail",
            "subcategory":"Laundry & Dry Cleaning",
            "type":"Services"
        }
    ],
    "sg:phone":"+1 212 627 7999",
    "sg:postcode":"10011",
    "sg:province":"NY",
    "sg:tags":[
        "drycleaning",
        "plant",
        "cleaners"
    ],
    "wof:name":"Jo Quality Dry Cleaners",
    "wof:placetype":"venue"
},
  "geometry": {"coordinates":[-74.000693,40.736974],"type":"Point"}
}