{
  "type": "Feature",
  "properties": {
    "iso:country":"US",
    "sg:address":"2909 Court St",
    "sg:city":"Syracuse",
    "sg:classifiers":[
        {
            "category":"Government",
            "subcategory":"Fire Station",
            "type":"Public Place"
        }
    ],
    "sg:phone":"+1 315 455 6570",
    "sg:postcode":"13208",
    "sg:province":"NY",
    "sg:tags":[
        "protection"
    ],
    "wof:name":"Lyncourt Fire District",
    "wof:placetype":"venue"
},
  "geometry": {"coordinates":[-76.127185,43.083196],"type":"Point"}
}