{
  "type": "Feature",
  "properties": {
    "iso:country":"US",
    "sg:address":"9 Squaw Ln",
    "sg:city":"Mastic",
    "sg:classifiers":[
        {
            "category":"Retail",
            "subcategory":"Repair Shop",
            "type":"Services"
        }
    ],
    "sg:phone":"+1 631 964 5352",
    "sg:postcode":"11950",
    "sg:province":"NY",
    "sg:tags":[
        "lock",
        "locksmith"
    ],
    "wof:name":"24 Hour EMERGENCY Locksmith",
    "wof:placetype":"venue"
},
  "geometry": {"coordinates":[-72.835703,40.789749],"type":"Point"}
}