{
  "type": "Feature",
  "properties": {
    "iso:country":"US",
    "sg:address":"6274 Route 25A",
    "sg:city":"Wading River",
    "sg:classifiers":[
        {
            "category":"Ice Cream",
            "type":"Food & Drink"
        }
    ],
    "sg:phone":"+1 631 929 4944",
    "sg:postcode":"11792",
    "sg:province":"NY",
    "sg:tags":[
        "frozen",
        "yogurt"
    ],
    "wof:name":"Ice Cream Chicken & Rib Depot",
    "wof:placetype":"venue"
},
  "geometry": {"coordinates":[-72.832802,40.944599],"type":"Point"}
}