{
  "type": "Feature",
  "properties": {
    "iso:country":"US",
    "sg:address":"92 Atlantic Ave",
    "sg:city":"Freeport",
    "sg:classifiers":[
        {
            "category":"Professional",
            "subcategory":"Engineering",
            "type":"Services"
        }
    ],
    "sg:phone":"+1 516 378 2064",
    "sg:postcode":"11520",
    "sg:province":"NY",
    "wof:name":"L J Strandberg Assoc Conslting",
    "wof:placetype":"venue"
},
  "geometry": {"coordinates":[-73.580911,40.646105],"type":"Point"}
}