{
  "type": "Feature",
  "properties": {
    "addr:full":"605 Broadway Newburgh NY 12550",
    "addr:housenumber":"605",
    "addr:postcode":"12550",
    "addr:street":"Broadway",
    "iso:country":"US",
    "sg:address":"605 Broadway",
    "sg:city":"Newburgh",
    "sg:classifiers":[
        {
            "category":"Freight",
            "type":"Transportation"
        }
    ],
    "sg:phone":"+1 845 569 8183",
    "sg:postcode":"12550",
    "sg:province":"NY",
    "sg:tags":[
        "trucking"
    ],
    "wof:name":"J B Hunt Transport Inc",
    "wof:placetype":"venue"
},
  "geometry": {"coordinates":[-74.038538,41.501885],"type":"Point"}
}