{
  "type": "Feature",
  "properties": {
    "iso:country":"US",
    "sg:address":"6655 Bliss Rd",
    "sg:city":"Oakfield",
    "sg:classifiers":[
        {
            "category":"Farming",
            "subcategory":"Dairy Farm",
            "type":"Manufacturing & Wholesale Goods"
        }
    ],
    "sg:phone":"+1 585 948 5116",
    "sg:postcode":"14125",
    "sg:province":"NY",
    "wof:name":"Lamb Farms",
    "wof:placetype":"venue"
},
  "geometry": {"coordinates":[-78.294303,43.093504],"type":"Point"}
}