{
  "type": "Feature",
  "properties": {
    "addr:full":"201 W. 89th Street #4A New York NY 10024",
    "addr:housenumber":"201",
    "addr:postcode":"10024",
    "addr:street":"W. 89Th Street # 4A",
    "iso:country":"US",
    "sg:address":"201 W. 89th Street #4A",
    "sg:city":"New York",
    "sg:classifiers":[
        {
            "category":"Professional",
            "subcategory":"Computer Services",
            "type":"Services"
        }
    ],
    "sg:phone":"+1 650 520 9205",
    "sg:postcode":"10024",
    "sg:province":"NY",
    "sg:website":"http://www.juiceboxjungle.com/",
    "wof:name":"JuiceBoxJungle",
    "wof:placetype":"venue"
},
  "geometry": {"coordinates":[-73.975026,40.790213],"type":"Point"}
}