{
  "type": "Feature",
  "properties": {
    "iso:country":"US",
    "sg:address":"337 Middle Country Rd",
    "sg:city":"Selden",
    "sg:classifiers":[
        {
            "category":"Shopping",
            "subcategory":"Tobacco",
            "type":"Retail Goods"
        }
    ],
    "sg:phone":"+1 631 736 1959",
    "sg:postcode":"11784",
    "sg:province":"NY",
    "sg:tags":[
        "shop"
    ],
    "wof:name":"Pop Shoppe",
    "wof:placetype":"venue"
},
  "geometry": {"coordinates":[-73.030098,40.867199],"type":"Point"}
}