{
  "type": "Feature",
  "properties": {
    "iso:country":"US",
    "sg:address":"278 Clark St",
    "sg:city":"Auburn",
    "sg:classifiers":[
        {
            "category":"Building & Trades",
            "subcategory":"Plumbing",
            "type":"Services"
        }
    ],
    "sg:phone":"+1 315 255 0183",
    "sg:postcode":"13021",
    "sg:province":"NY",
    "sg:tags":[
        "contractor"
    ],
    "wof:name":"Bc Htg Air",
    "wof:placetype":"venue"
},
  "geometry": {"coordinates":[-76.584357,42.931407],"type":"Point"}
}