{
  "type": "Feature",
  "properties": {
    "iso:country":"US",
    "sg:address":"1661 Glenwood Rd",
    "sg:city":"Vestal",
    "sg:classifiers":[
        {
            "category":"Building & Trades",
            "subcategory":"Construction",
            "type":"Services"
        }
    ],
    "sg:phone":"+1 607 785 7122",
    "sg:postcode":"13850",
    "sg:province":"NY",
    "sg:tags":[
        "contractor"
    ],
    "wof:name":"Robert Laman Jr Construction",
    "wof:placetype":"venue"
},
  "geometry": {"coordinates":[-76.038685,42.054106],"type":"Point"}
}