{
  "type": "Feature",
  "properties": {
    "iso:country":"US",
    "sg:address":"997 Rosedale Rd",
    "sg:city":"Valley Stream",
    "sg:classifiers":[
        {
            "category":"Health Services",
            "subcategory":"Dentist",
            "type":"Services"
        }
    ],
    "sg:phone":"+1 516 532 3510",
    "sg:postcode":"11581",
    "sg:province":"NY",
    "sg:website":"www.drdragos.com",
    "wof:name":"FIFTH AVE DENTAL SPA",
    "wof:placetype":"venue"
},
  "geometry": {"coordinates":[-73.721374,40.652345],"type":"Point"}
}