{
  "type": "Feature",
  "properties": {
    "addr:full":"1914 W 8th St Brooklyn NY 11223",
    "addr:housenumber":"1914",
    "addr:postcode":"11223",
    "addr:street":"W 8Th St",
    "iso:country":"US",
    "sg:address":"1914 W 8th St",
    "sg:city":"Brooklyn",
    "sg:classifiers":[
        {
            "category":"Professional",
            "subcategory":"Business Services",
            "type":"Services"
        }
    ],
    "sg:phone":"+1 718 266 6184",
    "sg:postcode":"11223",
    "sg:province":"NY",
    "wof:name":"V I P Courier Systems Inc",
    "wof:placetype":"venue"
},
  "geometry": {"coordinates":[-73.979981,40.598879],"type":"Point"}
}