{
  "type": "Feature",
  "properties": {
    "iso:country":"US",
    "sg:address":"125 Lark St",
    "sg:city":"Albany",
    "sg:classifiers":[
        {
            "category":"Restaurant",
            "type":"Food & Drink"
        }
    ],
    "sg:phone":"+1   ",
    "sg:postcode":"12210",
    "sg:province":"NY",
    "sg:tags":[
        "eating"
    ],
    "wof:name":"Shahnees Caribbean Bky Restrnt",
    "wof:placetype":"venue"
},
  "geometry": {"coordinates":[-73.76049399999999,42.659411],"type":"Point"}
}