{
  "type": "Feature",
  "properties": {
    "iso:country":"US",
    "sg:address":"50 Norfolk St",
    "sg:city":"New York",
    "sg:classifiers":[
        {
            "category":"Health Services",
            "subcategory":"Nursing And Care Facility",
            "type":"Services"
        }
    ],
    "sg:phone":"+1 212 475 7730",
    "sg:postcode":"10002",
    "sg:province":"NY",
    "sg:tags":[
        "home",
        "rest"
    ],
    "wof:name":"Chinatown Planning Council",
    "wof:placetype":"venue"
},
  "geometry": {"coordinates":[-73.988086,40.71666],"type":"Point"}
}