{
  "type": "Feature",
  "properties": {
    "iso:country":"US",
    "sg:address":"131 S Union St",
    "sg:city":"Spencerport",
    "sg:classifiers":[
        {
            "category":"Shopping",
            "subcategory":"Gifts & Souvenirs",
            "type":"Retail Goods"
        }
    ],
    "sg:phone":"+1   ",
    "sg:postcode":"14559",
    "sg:province":"NY",
    "wof:name":"Hilton Antique Co Op",
    "wof:placetype":"venue"
},
  "geometry": {"coordinates":[-77.800704,43.192296],"type":"Point"}
}