{
  "type": "Feature",
  "properties": {
    "addr:full":"253 Broome St New York NY 10002",
    "addr:housenumber":"253",
    "addr:postcode":"10002",
    "addr:street":"Broome St",
    "iso:country":"US",
    "sg:address":"253 Broome St",
    "sg:city":"New York",
    "sg:classifiers":[
        {
            "category":"Bars & Pubs",
            "type":"Food & Drink"
        },
        {
            "category":"Restaurant",
            "type":"Food & Drink"
        }
    ],
    "sg:menulink":"http://www.allmenus.com/ny/new-york/250101-barrio-chino/menu/",
    "sg:phone":"+1 212 228 6710",
    "sg:postcode":"10002",
    "sg:province":"NY",
    "sg:tags":[
        "mexican"
    ],
    "wof:name":"Barrio Chino",
    "wof:placetype":"venue"
},
  "geometry": {"coordinates":[-73.99002,40.718059],"type":"Point"}
}