{
  "type": "Feature",
  "properties": {
    "addr:full":"175 Broadway Amityville NY 11701",
    "addr:housenumber":"175",
    "addr:postcode":"11701",
    "addr:street":"Broadway",
    "iso:country":"US",
    "sg:address":"175 Broadway",
    "sg:city":"Amityville",
    "sg:classifiers":[
        {
            "category":"Organizations",
            "subcategory":"Religious Organization",
            "type":"Services"
        }
    ],
    "sg:phone":"+1 631 691 9289",
    "sg:postcode":"11701",
    "sg:province":"NY",
    "sg:tags":[
        "church"
    ],
    "wof:name":"St Mary's Church",
    "wof:placetype":"venue"
},
  "geometry": {"coordinates":[-73.417394,40.67812],"type":"Point"}
}