{
  "type": "Feature",
  "properties": {
    "iso:country":"US",
    "sg:address":"3455 Hyde Park Blvd",
    "sg:city":"Niagara Falls",
    "sg:phone":"+1 716 278 0044",
    "sg:postcode":"14305",
    "sg:province":"NY",
    "sg:tags":[
        "scale"
    ],
    "wof:name":"Espera NA Inc",
    "wof:placetype":"venue"
},
  "geometry": {"coordinates":[-79.03464099999999,43.118767],"type":"Point"}
}