{
  "type": "Feature",
  "properties": {
    "iso:country":"US",
    "sg:address":"19 Saybrook Valley Rd",
    "sg:city":"Oak Hill",
    "sg:classifiers":[
        {
            "category":"Home & Garden",
            "subcategory":"Home Furnishings",
            "type":"Retail Goods"
        }
    ],
    "sg:phone":"+1   ",
    "sg:postcode":"12460",
    "sg:province":"NY",
    "sg:tags":[
        "repair"
    ],
    "wof:name":"Needles In Haystack",
    "wof:placetype":"venue"
},
  "geometry": {"coordinates":[-74.13594000000001,42.406641],"type":"Point"}
}