{
  "type": "Feature",
  "properties": {
    "iso:country":"US",
    "sg:address":"107 Oakwood Ave",
    "sg:city":"Bayport",
    "sg:classifiers":[
        {
            "category":"Real Estate",
            "subcategory":"Real Estate Agent",
            "type":"Services"
        }
    ],
    "sg:phone":"+1 631 472 1655",
    "sg:postcode":"11705",
    "sg:province":"NY",
    "sg:tags":[
        "appraiser"
    ],
    "wof:name":"Long Island Appraisal Network",
    "wof:placetype":"venue"
},
  "geometry": {"coordinates":[-73.061378,40.739511],"type":"Point"}
}