{
  "type": "Feature",
  "properties": {
    "iso:country":"US",
    "sg:address":"95 5th St",
    "sg:city":"Garden City",
    "sg:classifiers":[
        {
            "category":"Shopping",
            "subcategory":"Stationery & Office Supplies",
            "type":"Retail Goods"
        }
    ],
    "sg:phone":"+1 516 873 8900",
    "sg:postcode":"11530",
    "sg:province":"NY",
    "sg:tags":[
        "equipment"
    ],
    "wof:name":"Knoll Inc",
    "wof:placetype":"venue"
},
  "geometry": {"coordinates":[-73.637562,40.721639],"type":"Point"}
}