{
  "type": "Feature",
  "properties": {
    "iso:country":"US",
    "sg:address":"1818 Bellmore Ave",
    "sg:city":"Bellmore",
    "sg:classifiers":[
        {
            "category":"Professional",
            "subcategory":"Accounting & Tax Preparation",
            "type":"Services"
        }
    ],
    "sg:phone":"+1 516 785 4999",
    "sg:postcode":"11710",
    "sg:province":"NY",
    "wof:name":"Borneman & Tusa Cpas",
    "wof:placetype":"venue"
},
  "geometry": {"coordinates":[-73.532445,40.679446],"type":"Point"}
}