{
  "type": "Feature",
  "properties": {
    "iso:country":"US",
    "sg:address":"1 Cabernet Cir",
    "sg:city":"Fairport",
    "sg:classifiers":[
        {
            "category":"Wholesale",
            "subcategory":"Durable Goods & Equipment",
            "type":"Manufacturing & Wholesale Goods"
        }
    ],
    "sg:phone":"+1 585 425 3753",
    "sg:postcode":"14450",
    "sg:province":"NY",
    "sg:tags":[
        "representative",
        "manufacturer"
    ],
    "sg:website":"www.saelig.com",
    "wof:name":"Saelig Com",
    "wof:placetype":"venue"
},
  "geometry": {"coordinates":[-77.442314,43.046726],"type":"Point"}
}