{
  "type": "Feature",
  "properties": {
    "addr:full":"150 Midvale Dr Fairport NY 14450",
    "addr:housenumber":"150",
    "addr:postcode":"14450",
    "addr:street":"Midvale Dr",
    "iso:country":"US",
    "sg:address":"150 Midvale Dr",
    "sg:city":"Fairport",
    "sg:classifiers":[
        {
            "category":"Shopping",
            "subcategory":"Musical Instruments",
            "type":"Retail Goods"
        }
    ],
    "sg:phone":"+1 585 383 8910",
    "sg:postcode":"14450",
    "sg:province":"NY",
    "sg:website":"www.primetimefunk.com",
    "wof:name":"Drum Corner",
    "wof:placetype":"venue"
},
  "geometry": {"coordinates":[-77.467316,43.109107],"type":"Point"}
}