{
  "type": "Feature",
  "properties": {
    "addr:full":"1237 2nd Ave Frnt 1 New York NY 10065",
    "addr:housenumber":"1237;1",
    "addr:postcode":"10065",
    "addr:street":"2Nd Ave Frnt",
    "iso:country":"US",
    "sg:address":"1237 2nd Ave Frnt 1",
    "sg:city":"New York",
    "sg:classifiers":[
        {
            "category":"Retail",
            "subcategory":"Laundry & Dry Cleaning",
            "type":"Services"
        }
    ],
    "sg:phone":"+1 212 355 4747",
    "sg:postcode":"10065",
    "sg:province":"NY",
    "sg:website":"www.carlton-cleaners.com",
    "wof:name":"Carlton Tower Cleaners",
    "wof:placetype":"venue"
},
  "geometry": {"coordinates":[-73.96184599999999,40.764302],"type":"Point"}
}