{
  "type": "Feature",
  "properties": {
    "addr:full":"30 Garth Rd Scarsdale NY 10583",
    "addr:housenumber":"30",
    "addr:postcode":"10583",
    "addr:street":"Garth Rd",
    "iso:country":"US",
    "sg:address":"30 Garth Rd",
    "sg:city":"Scarsdale",
    "sg:classifiers":[
        {
            "category":"Restaurant",
            "type":"Food & Drink"
        }
    ],
    "sg:menulink":"http://www.allmenus.com/ny/scarsdale/141287-kirari-new-wave-sushi/menu/",
    "sg:phone":"+1 914 725 3730",
    "sg:postcode":"10583",
    "sg:province":"NY",
    "sg:tags":[
        "sushi",
        "asian"
    ],
    "wof:name":"Kirari New Wave Sushi",
    "wof:placetype":"venue"
},
  "geometry": {"coordinates":[-73.809826,40.98808],"type":"Point"}
}