{
  "type": "Feature",
  "properties": {
    "addr:full":"444 E Henrietta Rd Rochester NY 14620",
    "addr:housenumber":"444",
    "addr:postcode":"14620",
    "addr:street":"E Henrietta Rd",
    "iso:country":"US",
    "sg:address":"444 E Henrietta Rd",
    "sg:city":"Rochester",
    "sg:classifiers":[
        {
            "category":"Government",
            "subcategory":"Office",
            "type":"Public Place"
        }
    ],
    "sg:phone":"+1 585 760 7600",
    "sg:postcode":"14620",
    "sg:province":"NY",
    "wof:name":"Monroe County Ind Waste",
    "wof:placetype":"venue"
},
  "geometry": {"coordinates":[-77.61601899999999,43.112326],"type":"Point"}
}