{
  "type": "Feature",
  "properties": {
    "addr:full":"239 Central Park W New York NY 10024",
    "addr:housenumber":"239",
    "addr:postcode":"10024",
    "addr:street":"Central Park W",
    "iso:country":"US",
    "sg:address":"239 Central Park W",
    "sg:city":"New York",
    "sg:classifiers":[
        {
            "category":"Health Services",
            "subcategory":"Doctor",
            "type":"Services"
        }
    ],
    "sg:phone":"+1 212 496 7826",
    "sg:postcode":"10024",
    "sg:province":"NY",
    "wof:name":"Harris Deena R MD",
    "wof:placetype":"venue"
},
  "geometry": {"coordinates":[-73.970831,40.783954],"type":"Point"}
}