{
  "type": "Feature",
  "properties": {
    "addr:full":"557 Tennyson Drive Staten Island NY 10312",
    "addr:housenumber":"557",
    "addr:postcode":"10312",
    "addr:street":"Tennyson Drive",
    "iso:country":"US",
    "sg:address":"557 Tennyson Drive",
    "sg:city":"Staten Island",
    "sg:classifiers":[
        {
            "category":"Arts & Performance",
            "subcategory":"Art Gallery",
            "type":"Entertainment"
        }
    ],
    "sg:phone":"+1 718 420 9328",
    "sg:postcode":"10312",
    "sg:province":"NY",
    "sg:website":"www.artmaxx.com",
    "wof:name":"Artmaxx",
    "wof:placetype":"venue"
},
  "geometry": {"coordinates":[-74.153198,40.532216],"type":"Point"}
}