{
  "type": "Feature",
  "properties": {
    "iso:country":"US",
    "sg:address":"1021 8th Ave",
    "sg:city":"Brooklyn",
    "sg:classifiers":[
        {
            "category":"Food & Beverages",
            "subcategory":"Groceries & Convenience Stores",
            "type":"Retail Goods"
        }
    ],
    "sg:phone":"+1 800 924 8598",
    "sg:postcode":"11215",
    "sg:province":"NY",
    "wof:name":"11 St Grocery",
    "wof:placetype":"venue"
},
  "geometry": {"coordinates":[-73.97967199999999,40.664948],"type":"Point"}
}