{
  "type": "Feature",
  "properties": {
    "iso:country":"US",
    "sg:address":"238 E 14th St",
    "sg:city":"New York",
    "sg:classifiers":[
        {
            "category":"Restaurant",
            "type":"Food & Drink"
        }
    ],
    "sg:phone":"+1 212 228 1852",
    "sg:postcode":"10003",
    "sg:province":"NY",
    "wof:name":"Chinatown Restaurant",
    "wof:placetype":"venue"
},
  "geometry": {"coordinates":[-73.98629800000001,40.732899],"type":"Point"}
}