{
  "type": "Feature",
  "properties": {
    "addr:full":"497 N Broadway Yonkers NY 10701",
    "addr:housenumber":"497",
    "addr:postcode":"10701",
    "addr:street":"N Broadway",
    "iso:country":"US",
    "sg:address":"497 N Broadway",
    "sg:city":"Yonkers",
    "sg:classifiers":[
        {
            "category":"Health Services",
            "subcategory":"Doctor",
            "type":"Services"
        }
    ],
    "sg:phone":"+1   ",
    "sg:postcode":"10701",
    "sg:province":"NY",
    "sg:tags":[
        "physician"
    ],
    "wof:name":"Julieta Polintan MD",
    "wof:placetype":"venue"
},
  "geometry": {"coordinates":[-73.891949,40.950029],"type":"Point"}
}