{
  "type": "Feature",
  "properties": {
    "addr:full":"117 N Grove St East Aurora NY 14052",
    "addr:housenumber":"117",
    "addr:postcode":"14052",
    "addr:street":"N Grove St",
    "iso:country":"US",
    "sg:address":"117 N Grove St",
    "sg:city":"East Aurora",
    "sg:classifiers":[
        {
            "category":"Professional",
            "subcategory":"Business Services",
            "type":"Services"
        }
    ],
    "sg:phone":"+1   ",
    "sg:postcode":"14052",
    "sg:province":"NY",
    "sg:tags":[
        "interior",
        "designer"
    ],
    "wof:name":"Le Petit Carousel Inc",
    "wof:placetype":"venue"
},
  "geometry": {"coordinates":[-78.617743,42.771386],"type":"Point"}
}