{
  "type": "Feature",
  "properties": {
    "addr:full":"24 E 12th Street New York NY 10003",
    "addr:housenumber":"24",
    "addr:postcode":"10003",
    "addr:street":"E 12Th Street",
    "iso:country":"US",
    "sg:address":"24 E 12th Street",
    "sg:city":"New York",
    "sg:classifiers":[
        {
            "category":"Health Services",
            "subcategory":"Health Practitioner",
            "type":"Services"
        }
    ],
    "sg:phone":"+1 212 337 1138",
    "sg:postcode":"10003",
    "sg:province":"NY",
    "sg:tags":[
        "therapy",
        "physical"
    ],
    "wof:name":"Mruk Karen Physthrpst",
    "wof:placetype":"venue"
},
  "geometry": {"coordinates":[-73.993253,40.734109],"type":"Point"}
}