{
  "type": "Feature",
  "properties": {
    "addr:full":"215 Pearl Street New York NY 10038",
    "addr:housenumber":"215",
    "addr:postcode":"10038",
    "addr:street":"Pearl Street",
    "iso:country":"US",
    "sg:address":"215 Pearl Street",
    "sg:city":"New York",
    "sg:classifiers":[
        {
            "category":"Restaurant",
            "type":"Food & Drink"
        }
    ],
    "sg:phone":"+1 212 269 6180",
    "sg:postcode":"10038",
    "sg:province":"NY",
    "wof:name":"La Borsa Di Roma Restaurant",
    "wof:placetype":"venue"
},
  "geometry": {"coordinates":[-74.006243,40.707184],"type":"Point"}
}