{
  "type": "Feature",
  "properties": {
    "addr:full":"2415 Jerusalem Ave North Bellmore NY 11710",
    "addr:housenumber":"2415",
    "addr:postcode":"11710",
    "addr:street":"Jerusalem Ave North",
    "iso:country":"US",
    "sg:address":"2415 Jerusalem Ave",
    "sg:city":"North Bellmore",
    "sg:classifiers":[
        {
            "category":"Health Services",
            "subcategory":"Doctor",
            "type":"Services"
        }
    ],
    "sg:phone":"+1 516 221 5151",
    "sg:postcode":"11710",
    "sg:province":"NY",
    "wof:name":"Schultheis Eric MD",
    "wof:placetype":"venue"
},
  "geometry": {"coordinates":[-73.54161499999999,40.691306],"type":"Point"}
}