{
  "type": "Feature",
  "properties": {
    "addr:full":"14 Kiwassa Rd Saranac Lake NY 12983",
    "addr:housenumber":"14",
    "addr:postcode":"12983",
    "addr:street":"Kiwassa Rd",
    "iso:country":"US",
    "sg:address":"14 Kiwassa Rd",
    "sg:city":"Saranac Lake",
    "sg:classifiers":[
        {
            "category":"Real Estate",
            "subcategory":"Real Estate Operator",
            "type":"Services"
        }
    ],
    "sg:phone":"+1 518 891 3050",
    "sg:postcode":"12983",
    "sg:province":"NY",
    "sg:tags":[
        "apartment"
    ],
    "wof:name":"Lake Flower Apartments",
    "wof:placetype":"venue"
},
  "geometry": {"coordinates":[-74.128995,44.319257],"type":"Point"}
}