{
  "type": "Feature",
  "properties": {
    "iso:country":"US",
    "sg:address":"105 Shelley Cir",
    "sg:city":"Monsey",
    "sg:classifiers":[
        {
            "category":"Health Services",
            "subcategory":"Doctor",
            "type":"Services"
        }
    ],
    "sg:phone":"+1 845 362 0408",
    "sg:postcode":"10952",
    "sg:province":"NY",
    "sg:tags":[
        "physician",
        "family",
        "medical",
        "practice",
        "surgeons",
        "medicine"
    ],
    "wof:name":"Daniel Schlusselberg Md",
    "wof:placetype":"venue"
},
  "geometry": {"coordinates":[-74.073786,41.145801],"type":"Point"}
}