{
  "type": "Feature",
  "properties": {
    "addr:full":"27 Bobann Dr Nesconset NY 11767",
    "addr:housenumber":"27",
    "addr:postcode":"11767",
    "addr:street":"Bobann Dr",
    "iso:country":"US",
    "sg:address":"27 Bobann Dr",
    "sg:city":"Nesconset",
    "sg:classifiers":[
        {
            "category":"Freight",
            "type":"Transportation"
        }
    ],
    "sg:phone":"+1   ",
    "sg:postcode":"11767",
    "sg:province":"NY",
    "sg:tags":[
        "operator",
        "local",
        "trucking"
    ],
    "wof:name":"FTM Trucking Corporation",
    "wof:placetype":"venue"
},
  "geometry": {"coordinates":[-73.13937900000001,40.851758],"type":"Point"}
}