{
  "type": "Feature",
  "properties": {
    "addr:full":"106 Route 59 Spring Valley NY 10977",
    "addr:housenumber":"106",
    "addr:postcode":"10977",
    "addr:street":"Route 59",
    "iso:country":"US",
    "sg:address":"106 Route 59",
    "sg:city":"Spring Valley",
    "sg:classifiers":[
        {
            "category":"Restaurant",
            "type":"Food & Drink"
        }
    ],
    "sg:menulink":"http://www.allmenus.com/ny/clarkstown/188793-mcdonalds/menu/",
    "sg:phone":"+1 845 356 5520",
    "sg:postcode":"10977",
    "sg:province":"NY",
    "sg:tags":[
        "burger",
        "american"
    ],
    "wof:name":"McDonald's",
    "wof:placetype":"venue"
},
  "geometry": {"coordinates":[-74.036382,41.107203],"type":"Point"}
}