{
  "type": "Feature",
  "properties": {
    "addr:full":"912 Kelly St Bronx NY 10459",
    "addr:housenumber":"912",
    "addr:postcode":"10459",
    "addr:street":"Kelly St",
    "iso:country":"US",
    "sg:address":"912 Kelly St",
    "sg:city":"Bronx",
    "sg:classifiers":[
        {
            "category":"Professional",
            "subcategory":"Advertising",
            "type":"Services"
        }
    ],
    "sg:phone":"+1 718 860 2555",
    "sg:postcode":"10459",
    "sg:province":"NY",
    "sg:tags":[
        "distribution"
    ],
    "wof:name":"Top Choice Distributors",
    "wof:placetype":"venue"
},
  "geometry": {"coordinates":[-73.895831,40.82058],"type":"Point"}
}