{
  "type": "Feature",
  "properties": {
    "addr:full":"300 Payne Ave North Tonawanda NY 14120",
    "addr:housenumber":"300",
    "addr:postcode":"14120",
    "addr:street":"Payne Ave",
    "iso:country":"US",
    "sg:address":"300 Payne Ave",
    "sg:city":"North Tonawanda",
    "sg:classifiers":[
        {
            "category":"Shopping",
            "type":"Retail Goods"
        }
    ],
    "sg:phone":"+1 716 694 4485",
    "sg:postcode":"14120",
    "sg:province":"NY",
    "sg:tags":[
        "cosmetic",
        "perfume"
    ],
    "sg:website":"www.merlenorman.com",
    "wof:name":"Merle Norman Cosmetics",
    "wof:placetype":"venue"
},
  "geometry": {"coordinates":[-78.86982999999999,43.030194],"type":"Point"}
}