{
  "type": "Feature",
  "properties": {
    "addr:full":"10 Dawnwood Dr Manorville NY 11949",
    "addr:housenumber":"10",
    "addr:postcode":"11949",
    "addr:street":"Dawnwood Dr",
    "iso:country":"US",
    "sg:address":"10 Dawnwood Dr",
    "sg:city":"Manorville",
    "sg:classifiers":[
        {
            "category":"Building & Trades",
            "subcategory":"Construction",
            "type":"Services"
        }
    ],
    "sg:phone":"+1 631 874 3832",
    "sg:postcode":"11949",
    "sg:province":"NY",
    "sg:tags":[
        "dock"
    ],
    "wof:name":"Bulkheading Inc Shoreline",
    "wof:placetype":"venue"
},
  "geometry": {"coordinates":[-72.830444,40.824461],"type":"Point"}
}