{
  "type": "Feature",
  "properties": {
    "iso:country":"US",
    "sg:address":"90 Kisco Ave",
    "sg:city":"Mt Kisco",
    "sg:classifiers":[
        {
            "category":"Health Services",
            "subcategory":"Doctor",
            "type":"Services"
        }
    ],
    "sg:phone":"+1 914 241 1051",
    "sg:postcode":"10549",
    "sg:province":"NY",
    "sg:tags":[
        "physician",
        "surgeon"
    ],
    "wof:name":"Mark P Altman MD",
    "wof:placetype":"venue"
},
  "geometry": {"coordinates":[-73.725966,41.215009],"type":"Point"}
}