{
  "type": "Feature",
  "properties": {
    "addr:full":"85 Grandview Dr Mount Kisco NY 10549",
    "addr:housenumber":"85",
    "addr:postcode":"10549",
    "addr:street":"Grandview Dr",
    "iso:country":"US",
    "sg:address":"85 Grandview Dr",
    "sg:city":"Mount Kisco",
    "sg:classifiers":[
        {
            "category":"Banks & Credit Unions",
            "subcategory":"Investment Brokerage",
            "type":"Services"
        }
    ],
    "sg:phone":"+1 914 241 0158",
    "sg:postcode":"10549",
    "sg:province":"NY",
    "sg:tags":[
        "commodity",
        "contract"
    ],
    "wof:name":"B and G Commodities",
    "wof:placetype":"venue"
},
  "geometry": {"coordinates":[-73.737922,41.206172],"type":"Point"}
}