{
  "type": "Feature",
  "properties": {
    "addr:full":"45 Engineers Rd Hauppauge NY 11788",
    "addr:housenumber":"45",
    "addr:postcode":"11788",
    "addr:street":"Engineers Rd",
    "iso:country":"US",
    "sg:address":"45 Engineers Rd",
    "sg:city":"Hauppauge",
    "sg:classifiers":[
        {
            "category":"Manufacturing",
            "subcategory":"Metals",
            "type":"Manufacturing & Wholesale Goods"
        }
    ],
    "sg:phone":"+1   ",
    "sg:postcode":"11788",
    "sg:province":"NY",
    "sg:tags":[
        "manufacture",
        "stampings",
        "fine",
        "precision",
        "blanking"
    ],
    "sg:website":"www.whstamp.com",
    "wof:name":"W & H Stampings Inc",
    "wof:placetype":"venue"
},
  "geometry": {"coordinates":[-73.233896,40.812936],"type":"Point"}
}