{
  "type": "Feature",
  "properties": {
    "addr:full":"721 Middle Neck Rd Great Neck NY 11024",
    "addr:housenumber":"721",
    "addr:postcode":"11024",
    "addr:street":"Middle Neck Rd",
    "iso:country":"US",
    "sg:address":"721 Middle Neck Rd",
    "sg:city":"Great Neck",
    "sg:classifiers":[
        {
            "category":"Building & Trades",
            "subcategory":"Cleaning & Sanitation",
            "type":"Services"
        }
    ],
    "sg:phone":"+1 516 482 4741",
    "sg:postcode":"11024",
    "sg:province":"NY",
    "sg:tags":[
        "house"
    ],
    "wof:name":"Molly Maids",
    "wof:placetype":"venue"
},
  "geometry": {"coordinates":[-73.735257,40.806753],"type":"Point"}
}