{
  "type": "Feature",
  "properties": {
    "iso:country":"US",
    "sg:address":"5185 US Hwy 209",
    "sg:city":"Accord",
    "sg:classifiers":[
        {
            "category":"Retail",
            "subcategory":"Auto Repair",
            "type":"Services"
        }
    ],
    "sg:phone":"+1 845 626 2000",
    "sg:postcode":"12446",
    "sg:province":"NY",
    "sg:tags":[
        "repairing",
        "automobile"
    ],
    "wof:name":"C J's Automotive",
    "wof:placetype":"venue"
},
  "geometry": {"coordinates":[-74.24768299999999,41.789812],"type":"Point"}
}