{
  "type": "Feature",
  "properties": {
    "addr:full":"330 W 85 St New York NY 10024",
    "addr:housenumber":"330",
    "addr:postcode":"10024",
    "addr:street":"W 85 St",
    "iso:country":"US",
    "sg:address":"330 W 85 St",
    "sg:city":"New York",
    "sg:classifiers":[
        {
            "category":"Retail",
            "subcategory":"Repair Shop",
            "type":"Services"
        }
    ],
    "sg:phone":"+1 646 224 0721",
    "sg:postcode":"10024",
    "sg:province":"NY",
    "sg:tags":[
        "lock",
        "locksmith"
    ],
    "wof:name":"AAA 24 Hour Number 1 Lcksmth",
    "wof:placetype":"venue"
},
  "geometry": {"coordinates":[-73.980542,40.788994],"type":"Point"}
}