{
  "type": "Feature",
  "properties": {
    "addr:full":"1400 Linden Blvd Brooklyn NY 11212",
    "addr:housenumber":"1400",
    "addr:postcode":"11212",
    "addr:street":"Linden Blvd",
    "iso:country":"US",
    "sg:address":"1400 Linden Blvd",
    "sg:city":"Brooklyn",
    "sg:classifiers":[
        {
            "category":"Manufacturing",
            "subcategory":"Printing",
            "type":"Manufacturing & Wholesale Goods"
        }
    ],
    "sg:phone":"+1 718 342 5588",
    "sg:postcode":"11212",
    "sg:province":"NY",
    "sg:tags":[
        "publisher"
    ],
    "wof:name":"Clc Publications",
    "wof:placetype":"venue"
},
  "geometry": {"coordinates":[-73.907856,40.654589],"type":"Point"}
}