{
  "type": "Feature",
  "properties": {
    "addr:full":"747 3rd Ave Fl 38 New York NY 10017",
    "addr:housenumber":"747;38",
    "addr:postcode":"10017",
    "addr:street":"3Rd Ave Fl",
    "iso:country":"US",
    "sg:address":"747 3rd Ave Fl 38",
    "sg:city":"New York",
    "sg:classifiers":[
        {
            "category":"Banks & Credit Unions",
            "subcategory":"Investment Brokerage",
            "type":"Services"
        }
    ],
    "sg:phone":"+1 212 207 4370",
    "sg:postcode":"10017",
    "sg:province":"NY",
    "sg:tags":[
        "investing"
    ],
    "wof:name":"O And M Partners",
    "wof:placetype":"venue"
},
  "geometry": {"coordinates":[-73.972238,40.753498],"type":"Point"}
}