{
  "type": "Feature",
  "properties": {
    "addr:full":"66 Washington St Rensselaer NY 12144",
    "addr:housenumber":"66",
    "addr:postcode":"12144",
    "addr:street":"Washington St",
    "iso:country":"US",
    "sg:address":"66 Washington St",
    "sg:city":"Rensselaer",
    "sg:classifiers":[
        {
            "category":"Professional",
            "subcategory":"Business Services",
            "type":"Services"
        }
    ],
    "sg:phone":"+1 518 462 2818",
    "sg:postcode":"12144",
    "sg:province":"NY",
    "sg:tags":[
        "interior",
        "consultant",
        "design",
        "decorator"
    ],
    "wof:name":"Contract Interiors Group Inc",
    "wof:placetype":"venue"
},
  "geometry": {"coordinates":[-73.745803,42.638048],"type":"Point"}
}