{
  "type": "Feature",
  "properties": {
    "addr:full":"10 W 32 St New York NY 10001",
    "addr:housenumber":"10",
    "addr:postcode":"10001",
    "addr:street":"W 32 St",
    "iso:country":"US",
    "sg:address":"10 W 32 St",
    "sg:city":"New York",
    "sg:classifiers":[
        {
            "category":"Professional",
            "type":"Services"
        }
    ],
    "sg:phone":"+1 212 564 3808",
    "sg:postcode":"10001",
    "sg:province":"NY",
    "sg:tags":[
        "establishment"
    ],
    "wof:name":"Conus Corp",
    "wof:placetype":"venue"
},
  "geometry": {"coordinates":[-73.987889,40.748042],"type":"Point"}
}