{
  "type": "Feature",
  "properties": {
    "addr:full":"65 Center St Waterloo NY 13165",
    "addr:housenumber":"65",
    "addr:postcode":"13165",
    "addr:street":"Center St",
    "iso:country":"US",
    "sg:address":"65 Center St",
    "sg:city":"Waterloo",
    "sg:classifiers":[
        {
            "category":"Education",
            "subcategory":"School",
            "type":"Public Place"
        }
    ],
    "sg:phone":"+1 315 539 1550",
    "sg:postcode":"13165",
    "sg:province":"NY",
    "wof:name":"Waterloo Senior High School",
    "wof:placetype":"venue"
},
  "geometry": {"coordinates":[-76.864902,42.910095],"type":"Point"}
}