{
  "type": "Feature",
  "properties": {
    "iso:country":"US",
    "sg:address":"1214 N Country Rd",
    "sg:city":"Stony Brook",
    "sg:classifiers":[
        {
            "category":"Wholesale",
            "subcategory":"Durable Goods & Equipment",
            "type":"Manufacturing & Wholesale Goods"
        }
    ],
    "sg:phone":"+1 631 444 0077",
    "sg:postcode":"11790",
    "sg:province":"NY",
    "wof:name":"Cow Harbor Folk Art LTD",
    "wof:placetype":"venue"
},
  "geometry": {"coordinates":[-73.141581,40.910482],"type":"Point"}
}