{
  "type": "Feature",
  "properties": {
    "iso:country":"US",
    "sg:address":"318 Old Country Rd",
    "sg:city":"Elmsford",
    "sg:classifiers":[
        {
            "category":"Real Estate",
            "subcategory":"Real Estate Agent",
            "type":"Services"
        }
    ],
    "sg:phone":"+1 914 592 4907",
    "sg:postcode":"10523",
    "sg:province":"NY",
    "wof:name":"Moore Appraisal Co",
    "wof:placetype":"venue"
},
  "geometry": {"coordinates":[-73.808583,41.066289],"type":"Point"}
}