{
  "type": "Feature",
  "properties": {
    "addr:full":"9710 Wehrle Dr Clarence NY 14031",
    "addr:housenumber":"9710",
    "addr:postcode":"14031",
    "addr:street":"Wehrle Dr",
    "iso:country":"US",
    "sg:address":"9710 Wehrle Dr",
    "sg:city":"Clarence",
    "sg:classifiers":[
        {
            "category":"Building & Trades",
            "subcategory":"Plumbing",
            "type":"Services"
        }
    ],
    "sg:phone":"+1 716 759 6711",
    "sg:postcode":"14031",
    "sg:province":"NY",
    "sg:tags":[
        "contractor"
    ],
    "wof:name":"Weimer Heating & AC",
    "wof:placetype":"venue"
},
  "geometry": {"coordinates":[-78.63023099999999,42.958944],"type":"Point"}
}