{
  "type": "Feature",
  "properties": {
    "addr:full":"47 Spring Street Rd Loudonville NY 12211",
    "addr:housenumber":"47",
    "addr:postcode":"12211",
    "addr:street":"Spring Street Rd",
    "iso:country":"US",
    "sg:address":"47 Spring Street Rd",
    "sg:city":"Loudonville",
    "sg:classifiers":[
        {
            "category":"Health Services",
            "subcategory":"Doctor",
            "type":"Services"
        }
    ],
    "sg:phone":"+1 518 785 5279",
    "sg:postcode":"12211",
    "sg:province":"NY",
    "sg:tags":[
        "dentist"
    ],
    "wof:name":"Essepian John P DDS PC Ofc",
    "wof:placetype":"venue"
},
  "geometry": {"coordinates":[-73.753739,42.715827],"type":"Point"}
}