{
  "type": "Feature",
  "properties": {
    "iso:country":"US",
    "sg:address":"800 Sheldon Avenue",
    "sg:city":"Staten Island",
    "sg:classifiers":[
        {
            "category":"Building & Trades",
            "subcategory":"Construction",
            "type":"Services"
        }
    ],
    "sg:phone":"+1 718 356 4141",
    "sg:postcode":"10309",
    "sg:province":"NY",
    "sg:tags":[
        "contractor"
    ],
    "wof:name":"Verrazano Artisans",
    "wof:placetype":"venue"
},
  "geometry": {"coordinates":[-74.20100499999999,40.536881],"type":"Point"}
}