{
  "type": "Feature",
  "properties": {
    "iso:country":"US",
    "sg:address":"212 Ave B",
    "sg:city":"New York",
    "sg:classifiers":[
        {
            "category":"Professional",
            "subcategory":"Engineering",
            "type":"Services"
        }
    ],
    "sg:phone":"+1 917 364 3487",
    "sg:postcode":"10009",
    "sg:province":"NY",
    "sg:tags":[
        "design"
    ],
    "wof:name":"DAmato Jon Anthony",
    "wof:placetype":"venue"
},
  "geometry": {"coordinates":[-73.97891199999999,40.728213],"type":"Point"}
}