{
  "type": "Feature",
  "properties": {
    "iso:country":"US",
    "sg:address":"104 S Central Ave",
    "sg:city":"Valley Stream",
    "sg:classifiers":[
        {
            "category":"Building & Trades",
            "subcategory":"Construction",
            "type":"Services"
        }
    ],
    "sg:phone":"+1 516 825 7700",
    "sg:postcode":"11580",
    "sg:province":"NY",
    "sg:tags":[
        "new",
        "dwelling",
        "renovation",
        "build"
    ],
    "wof:name":"Wagman Construction Co Inc",
    "wof:placetype":"venue"
},
  "geometry": {"coordinates":[-73.708547,40.664707],"type":"Point"}
}