{
  "type": "Feature",
  "properties": {
    "iso:country":"US",
    "sg:address":"532 Broad Hollow Rd",
    "sg:city":"Melville",
    "sg:classifiers":[
        {
            "category":"Professional",
            "subcategory":"Lawyer & Legal Services",
            "type":"Services"
        }
    ],
    "sg:phone":"+1 631 752 2590",
    "sg:postcode":"11747",
    "sg:province":"NY",
    "sg:tags":[
        "attorney"
    ],
    "wof:name":"Lawrence Pohly",
    "wof:placetype":"venue"
},
  "geometry": {"coordinates":[-73.42338700000001,40.763285],"type":"Point"}
}