{
  "type": "Feature",
  "properties": {
    "iso:country":"US",
    "sg:address":"4160 Sunrise Hwy",
    "sg:city":"Massapequa",
    "sg:classifiers":[
        {
            "category":"Home & Garden",
            "subcategory":"Furniture",
            "type":"Retail Goods"
        }
    ],
    "sg:phone":"+1 516 797 8679",
    "sg:postcode":"11758",
    "sg:province":"NY",
    "sg:tags":[
        "repair"
    ],
    "wof:name":"Dinettes Plus",
    "wof:placetype":"venue"
},
  "geometry": {"coordinates":[-73.478841,40.675279],"type":"Point"}
}