{
  "type": "Feature",
  "properties": {
    "iso:country":"US",
    "sg:address":"268 Warrensburg Rd",
    "sg:city":"Stony Creek",
    "sg:classifiers":[
        {
            "category":"Social Services",
            "type":"Services"
        }
    ],
    "sg:phone":"+1   ",
    "sg:postcode":"12878",
    "sg:province":"NY",
    "wof:name":"Christian Counseling",
    "wof:placetype":"venue"
},
  "geometry": {"coordinates":[-73.88401399999999,43.413199],"type":"Point"}
}