{
  "type": "Feature",
  "properties": {
    "addr:full":"5 Midfield St Stony Brook NY 11790",
    "addr:housenumber":"5",
    "addr:postcode":"11790",
    "addr:street":"Midfield St",
    "iso:country":"US",
    "sg:address":"5 Midfield St",
    "sg:city":"Stony Brook",
    "sg:classifiers":[
        {
            "category":"Health Services",
            "subcategory":"Doctor",
            "type":"Services"
        },
        {
            "category":"Health Services",
            "subcategory":"Clinic",
            "type":"Services"
        }
    ],
    "sg:phone":"+1 631 751 1055",
    "sg:postcode":"11790",
    "sg:province":"NY",
    "sg:tags":[
        "counseling",
        "mental"
    ],
    "wof:name":"Goldberg Barbara PHD",
    "wof:placetype":"venue"
},
  "geometry": {"coordinates":[-73.132103,40.874199],"type":"Point"}
}