{
  "type": "Feature",
  "properties": {
    "addr:full":"271 Doughty Blvd Inwood NY 11096",
    "addr:housenumber":"271",
    "addr:postcode":"11096",
    "addr:street":"Doughty Blvd",
    "iso:country":"US",
    "sg:address":"271 Doughty Blvd",
    "sg:city":"Inwood",
    "sg:classifiers":[
        {
            "category":"Health Services",
            "subcategory":"Doctor",
            "type":"Services"
        }
    ],
    "sg:phone":"+1 516 371 6884",
    "sg:postcode":"11096",
    "sg:province":"NY",
    "sg:tags":[
        "medicine",
        "practice",
        "internal",
        "family"
    ],
    "wof:name":"Detweiler Allan MD",
    "wof:placetype":"venue"
},
  "geometry": {"coordinates":[-73.746696,40.6194],"type":"Point"}
}