{
  "type": "Feature",
  "properties": {
    "addr:full":"437 Tarrytown Rd White Plains NY 10607",
    "addr:housenumber":"437",
    "addr:postcode":"10607",
    "addr:street":"Tarrytown Rd",
    "iso:country":"US",
    "sg:address":"437 Tarrytown Rd",
    "sg:city":"White Plains",
    "sg:classifiers":[
        {
            "category":"Shopping",
            "subcategory":"Shoes",
            "type":"Retail Goods"
        }
    ],
    "sg:phone":"+1 914 289 0270",
    "sg:postcode":"10607",
    "sg:province":"NY",
    "wof:name":"Marty's Shoe Outlet",
    "wof:placetype":"venue"
},
  "geometry": {"coordinates":[-73.79803699999999,41.043295],"type":"Point"}
}