{
  "type": "Feature",
  "properties": {
    "iso:country":"US",
    "sg:address":"39 N Auringer Rd",
    "sg:city":"Constantia",
    "sg:classifiers":[
        {
            "category":"Building & Trades",
            "subcategory":"Construction",
            "type":"Services"
        }
    ],
    "sg:phone":"+1 315 623 9722",
    "sg:postcode":"13044",
    "sg:province":"NY",
    "sg:tags":[
        "carpentry",
        "contractor",
        "help",
        "supply"
    ],
    "wof:name":"To The Line Timber Frames",
    "wof:placetype":"venue"
},
  "geometry": {"coordinates":[-76.02204,43.299221],"type":"Point"}
}