{
  "type": "Feature",
  "properties": {
    "addr:full":"288 8th St Brooklyn NY 11215",
    "addr:housenumber":"288",
    "addr:postcode":"11215",
    "addr:street":"8Th St",
    "iso:country":"US",
    "sg:address":"288 8th St",
    "sg:city":"Brooklyn",
    "sg:classifiers":[
        {
            "category":"Real Estate",
            "subcategory":"Real Estate Agent",
            "type":"Services"
        }
    ],
    "sg:phone":"+1 718 768 7489",
    "sg:postcode":"11215",
    "sg:province":"NY",
    "wof:name":"Royal Slope Realty",
    "wof:placetype":"venue"
},
  "geometry": {"coordinates":[-73.983638,40.668682],"type":"Point"}
}