{
  "type": "Feature",
  "properties": {
    "iso:country":"US",
    "sg:address":"122 Colton Ave",
    "sg:city":"Sayville",
    "sg:classifiers":[
        {
            "category":"Building & Trades",
            "subcategory":"Construction",
            "type":"Services"
        }
    ],
    "sg:phone":"+1 631 567 8812",
    "sg:postcode":"11782",
    "sg:province":"NY",
    "sg:tags":[
        "wallpaper",
        "painting",
        "contractor"
    ],
    "wof:name":"Don Regnier Wallpaper & Pntg",
    "wof:placetype":"venue"
},
  "geometry": {"coordinates":[-73.07895600000001,40.731109],"type":"Point"}
}