{
  "type": "Feature",
  "properties": {
    "iso:country":"US",
    "sg:address":"1009 Kellogg Ave",
    "sg:city":"Utica",
    "sg:classifiers":[
        {
            "category":"Professional",
            "type":"Services"
        }
    ],
    "sg:phone":"+1 315 733 2960",
    "sg:postcode":"13502",
    "sg:province":"NY",
    "sg:tags":[
        "establishment"
    ],
    "wof:name":"Phanthavong Khamsouk",
    "wof:placetype":"venue"
},
  "geometry": {"coordinates":[-75.26295399999999,43.106882],"type":"Point"}
}