{
  "type": "Feature",
  "properties": {
    "iso:country":"US",
    "sg:address":"4946 State Hwy 21",
    "sg:city":"Alfred Station",
    "sg:classifiers":[
        {
            "category":"Home & Garden",
            "subcategory":"Building Materials",
            "type":"Retail Goods"
        }
    ],
    "sg:phone":"+1 607 478 8337",
    "sg:postcode":"14803",
    "sg:province":"NY",
    "sg:tags":[
        "glass",
        "leaded"
    ],
    "wof:name":"Warriner Stained Glass",
    "wof:placetype":"venue"
},
  "geometry": {"coordinates":[-77.78951000000001,42.224025],"type":"Point"}
}