{
  "type": "Feature",
  "properties": {
    "addr:full":"160 Farber Ln Buffalo NY 14221",
    "addr:housenumber":"160",
    "addr:postcode":"14221",
    "addr:street":"Farber Ln",
    "iso:country":"US",
    "sg:address":"160 Farber Ln",
    "sg:city":"Buffalo",
    "sg:classifiers":[
        {
            "category":"Health Services",
            "subcategory":"Doctor",
            "type":"Services"
        }
    ],
    "sg:phone":"+1 716 829 2070",
    "sg:postcode":"14221",
    "sg:province":"NY",
    "sg:tags":[
        "medical"
    ],
    "wof:name":"John Leddy",
    "wof:placetype":"venue"
},
  "geometry": {"coordinates":[-78.733953,42.969884],"type":"Point"}
}