{
  "type": "Feature",
  "properties": {
    "iso:country":"US",
    "sg:address":"3010 Boston Rd",
    "sg:city":"Bronx",
    "sg:classifiers":[
        {
            "category":"Retail",
            "subcategory":"Auto Repair",
            "type":"Services"
        }
    ],
    "sg:phone":"+1 718 882 2800",
    "sg:postcode":"10469",
    "sg:province":"NY",
    "sg:tags":[
        "repairing",
        "automobile"
    ],
    "wof:name":"Auto Stop Auto & Tire Ctr",
    "wof:placetype":"venue"
},
  "geometry": {"coordinates":[-73.856674,40.870195],"type":"Point"}
}