{
  "type": "Feature",
  "properties": {
    "addr:full":"1969 Madison Ave New York NY 10035",
    "addr:housenumber":"1969",
    "addr:postcode":"10035",
    "addr:street":"Madison Ave",
    "iso:country":"US",
    "sg:address":"1969 Madison Ave",
    "sg:city":"New York",
    "sg:classifiers":[
        {
            "category":"Social Services",
            "type":"Services"
        }
    ],
    "sg:phone":"+1   ",
    "sg:postcode":"10035",
    "sg:province":"NY",
    "wof:name":"Association of Black Social Wr",
    "wof:placetype":"venue"
},
  "geometry": {"coordinates":[-73.94025999999999,40.806067],"type":"Point"}
}