{
  "type": "Feature",
  "properties": {
    "iso:country":"US",
    "sg:address":"149 Ludlow Street",
    "sg:city":"New York",
    "sg:classifiers":[
        {
            "category":"Shopping",
            "subcategory":"Clothing, Apparel, & Fashions",
            "type":"Retail Goods"
        }
    ],
    "sg:phone":"+1 212 529 2111",
    "sg:postcode":"10002",
    "sg:province":"NY",
    "sg:tags":[
        "clothing",
        "women's"
    ],
    "wof:name":"DV",
    "wof:placetype":"venue"
},
  "geometry": {"coordinates":[-73.988197,40.720798],"type":"Point"}
}