{
  "type": "Feature",
  "properties": {
    "addr:full":"3 Garet Pl Commack NY 11725",
    "addr:housenumber":"3",
    "addr:postcode":"11725",
    "addr:street":"Garet Pl",
    "iso:country":"US",
    "sg:address":"3 Garet Pl",
    "sg:city":"Commack",
    "sg:classifiers":[
        {
            "category":"Organizations",
            "subcategory":"Labor Organization",
            "type":"Services"
        }
    ],
    "sg:phone":"+1 631 462 0030",
    "sg:postcode":"11725",
    "sg:province":"NY",
    "wof:name":"C S E A",
    "wof:placetype":"venue"
},
  "geometry": {"coordinates":[-73.28952,40.808663],"type":"Point"}
}