{
  "type": "Feature",
  "properties": {
    "addr:full":"19 Hayes Ct Monroe NY 10950",
    "addr:housenumber":"19",
    "addr:postcode":"10950",
    "addr:street":"Hayes Ct",
    "iso:country":"US",
    "sg:address":"19 Hayes Ct",
    "sg:city":"Monroe",
    "sg:classifiers":[
        {
            "category":"Restaurant",
            "type":"Food & Drink"
        }
    ],
    "sg:phone":"+1   ",
    "sg:postcode":"10950",
    "sg:province":"NY",
    "sg:tags":[
        "eating"
    ],
    "wof:name":"KY Manor",
    "wof:placetype":"venue"
},
  "geometry": {"coordinates":[-74.165142,41.344791],"type":"Point"}
}