{
  "type": "Feature",
  "properties": {
    "addr:full":"1315 53rd Street Brooklyn NY 11219",
    "addr:housenumber":"1315",
    "addr:postcode":"11219",
    "addr:street":"53Rd Street",
    "iso:country":"US",
    "sg:address":"1315 53rd Street",
    "sg:city":"Brooklyn",
    "sg:classifiers":[
        {
            "category":"Health Services",
            "subcategory":"Dentist",
            "type":"Services"
        }
    ],
    "sg:phone":"+1 718 436 0202",
    "sg:postcode":"11219",
    "sg:province":"NY",
    "wof:name":"Kappel Simon DDS",
    "wof:placetype":"venue"
},
  "geometry": {"coordinates":[-73.993799,40.632536],"type":"Point"}
}