{
  "type": "Feature",
  "properties": {
    "addr:full":"678 Rutland Rd Brooklyn NY 11203",
    "addr:housenumber":"678",
    "addr:postcode":"11203",
    "addr:street":"Rutland Rd",
    "iso:country":"US",
    "sg:address":"678 Rutland Rd",
    "sg:city":"Brooklyn",
    "sg:classifiers":[
        {
            "category":"Building & Trades",
            "subcategory":"Plumbing",
            "type":"Services"
        },
        {
            "category":"Building & Trades",
            "subcategory":"Construction",
            "type":"Services"
        }
    ],
    "sg:phone":"+1 718 773 7300",
    "sg:postcode":"11203",
    "sg:province":"NY",
    "sg:tags":[
        "system",
        "specialty",
        "heating",
        "clean",
        "mechanical",
        "contractor",
        "air conditioning",
        "boilers-repair"
    ],
    "wof:name":"Ub Mechanical",
    "wof:placetype":"venue"
},
  "geometry": {"coordinates":[-73.938208,40.660161],"type":"Point"}
}