{
  "type": "Feature",
  "properties": {
    "iso:country":"US",
    "sg:address":"270 Wheatley Rd",
    "sg:city":"Old Westbury",
    "sg:classifiers":[
        {
            "category":"Sports & Exercise",
            "subcategory":"Golf",
            "type":"Entertainment"
        }
    ],
    "sg:phone":"+1 516 621 7740",
    "sg:postcode":"11568",
    "sg:province":"NY",
    "wof:name":"Old Westbury Golf & Country Club",
    "wof:placetype":"venue"
},
  "geometry": {"coordinates":[-73.59279600000001,40.794102],"type":"Point"}
}