{
  "type": "Feature",
  "properties": {
    "addr:full":"6265 Rt 25A Wading River NY 11792",
    "addr:postcode":"6265;11792",
    "addr:street":"Rt 25A",
    "iso:country":"US",
    "sg:address":"6265 Rt 25A",
    "sg:city":"Wading River",
    "sg:classifiers":[
        {
            "category":"Restaurant",
            "type":"Food & Drink"
        },
        {
            "category":"Food & Beverages",
            "subcategory":"Bakery",
            "type":"Retail Goods"
        }
    ],
    "sg:phone":"+1 631 929 4452",
    "sg:postcode":"11792",
    "sg:province":"NY",
    "sg:tags":[
        "sandwich",
        "pizza"
    ],
    "wof:name":"Focaccia Oven",
    "wof:placetype":"venue"
},
  "geometry": {"coordinates":[-72.838604,40.94427],"type":"Point"}
}