{
  "type": "Feature",
  "properties": {
    "iso:country":"US",
    "sg:address":"540 Madison Ave",
    "sg:city":"New York",
    "sg:classifiers":[
        {
            "category":"Autos & Motor Vehicles",
            "subcategory":"Automobile Sales",
            "type":"Retail Goods"
        }
    ],
    "sg:phone":"+1 212 644 0396",
    "sg:postcode":"10022",
    "sg:province":"NY",
    "sg:tags":[
        "car",
        "dealer"
    ],
    "wof:name":"American Honda",
    "wof:placetype":"venue"
},
  "geometry": {"coordinates":[-73.97354799999999,40.760712],"type":"Point"}
}