{
  "type": "Feature",
  "properties": {
    "addr:full":"86 Mineola Ave Roslyn Heights NY 11577",
    "addr:housenumber":"86",
    "addr:postcode":"11577",
    "addr:street":"Mineola Ave",
    "iso:country":"US",
    "sg:address":"86 Mineola Ave",
    "sg:city":"Roslyn Heights",
    "sg:classifiers":[
        {
            "category":"Retail",
            "subcategory":"Portrait Studio",
            "type":"Services"
        },
        {
            "category":"Professional",
            "subcategory":"Art Services",
            "type":"Services"
        }
    ],
    "sg:phone":"+1 516 621 4242",
    "sg:postcode":"11577",
    "sg:province":"NY",
    "sg:tags":[
        "photographer",
        "photography",
        "store"
    ],
    "wof:name":"Brett Matthews Photograghers",
    "wof:placetype":"venue"
},
  "geometry": {"coordinates":[-73.651802,40.789101],"type":"Point"}
}