{
  "type": "Feature",
  "properties": {
    "iso:country":"US",
    "sg:address":"33 Parkway Dr",
    "sg:city":"Roslyn Heights",
    "sg:classifiers":[
        {
            "category":"Shopping",
            "subcategory":"Clothing, Apparel, & Fashions",
            "type":"Retail Goods"
        }
    ],
    "sg:phone":"+1   ",
    "sg:postcode":"11577",
    "sg:province":"NY",
    "wof:name":"TDP Design Inc",
    "wof:placetype":"venue"
},
  "geometry": {"coordinates":[-73.62823299999999,40.779261],"type":"Point"}
}