{
  "type": "Feature",
  "properties": {
    "addr:full":"280 Weidner Rd Rochester NY 14624",
    "addr:housenumber":"280",
    "addr:postcode":"14624",
    "addr:street":"Weidner Rd",
    "iso:country":"US",
    "sg:address":"280 Weidner Rd",
    "sg:city":"Rochester",
    "sg:classifiers":[
        {
            "category":"Government",
            "subcategory":"Office",
            "type":"Public Place"
        }
    ],
    "sg:phone":"+1 585 783 5400",
    "sg:postcode":"14624",
    "sg:province":"NY",
    "sg:tags":[
        "national",
        "security"
    ],
    "wof:name":"Aasf 2",
    "wof:placetype":"venue"
},
  "geometry": {"coordinates":[-77.672984,43.112523],"type":"Point"}
}