{
  "type": "Feature",
  "properties": {
    "addr:full":"399 Tarrytown Rd White Plains NY 10607",
    "addr:housenumber":"399",
    "addr:postcode":"10607",
    "addr:street":"Tarrytown Rd",
    "iso:country":"US",
    "sg:address":"399 Tarrytown Rd",
    "sg:city":"White Plains",
    "sg:classifiers":[
        {
            "category":"Shopping",
            "subcategory":"Department Store",
            "type":"Retail Goods"
        }
    ],
    "sg:phone":"+1   ",
    "sg:postcode":"10607",
    "sg:province":"NY",
    "wof:name":"Kmart",
    "wof:placetype":"venue"
},
  "geometry": {"coordinates":[-73.796719,41.042945],"type":"Point"}
}