{
  "type": "Feature",
  "properties": {
    "iso:country":"US",
    "sg:address":"220 Green St",
    "sg:city":"Albany",
    "sg:classifiers":[
        {
            "category":"Social Services",
            "type":"Services"
        }
    ],
    "sg:phone":"+1   ",
    "sg:postcode":"12202",
    "sg:province":"NY",
    "wof:name":"Women Inf & Children Program",
    "wof:placetype":"venue"
},
  "geometry": {"coordinates":[-73.75466299999999,42.64129],"type":"Point"}
}