{
  "type": "Feature",
  "properties": {
    "addr:full":"115 N 15th St Olean NY 14760",
    "addr:housenumber":"115",
    "addr:postcode":"14760",
    "addr:street":"N 15Th St",
    "iso:country":"US",
    "sg:address":"115 N 15th St",
    "sg:city":"Olean",
    "sg:classifiers":[
        {
            "category":"Autos & Motor Vehicles",
            "subcategory":"Auto Supplies",
            "type":"Retail Goods"
        }
    ],
    "sg:phone":"+1 716 372 7304",
    "sg:postcode":"14760",
    "sg:province":"NY",
    "sg:tags":[
        "automobile",
        "part"
    ],
    "wof:name":"Albert A Zemer",
    "wof:placetype":"venue"
},
  "geometry": {"coordinates":[-78.44817500000001,42.077724],"type":"Point"}
}