{
  "type": "Feature",
  "properties": {
    "addr:full":"1743 Amsterdam Ave New York NY 10031",
    "addr:housenumber":"1743",
    "addr:postcode":"10031",
    "addr:street":"Amsterdam Ave",
    "iso:country":"US",
    "sg:address":"1743 Amsterdam Ave",
    "sg:city":"New York",
    "sg:classifiers":[
        {
            "category":"Home & Garden",
            "subcategory":"Household Appliances",
            "type":"Retail Goods"
        }
    ],
    "sg:phone":"+1 212 281 6900",
    "sg:postcode":"10031",
    "sg:province":"NY",
    "wof:name":"B & W Appliance Maintenance",
    "wof:placetype":"venue"
},
  "geometry": {"coordinates":[-73.94667099999999,40.826354],"type":"Point"}
}