{
  "type": "Feature",
  "properties": {
    "addr:full":"275 Ave U Brooklyn NY 11223",
    "addr:housenumber":"275",
    "addr:postcode":"11223",
    "addr:street":"Ave U",
    "iso:country":"US",
    "sg:address":"275 Ave U",
    "sg:city":"Brooklyn",
    "sg:classifiers":[
        {
            "category":"Manufacturing",
            "subcategory":"Apparel",
            "type":"Manufacturing & Wholesale Goods"
        },
        {
            "category":"Home & Garden",
            "subcategory":"Home Furnishings",
            "type":"Retail Goods"
        }
    ],
    "sg:phone":"+1 718 266 2400",
    "sg:postcode":"11223",
    "sg:province":"NY",
    "sg:tags":[
        "curtain",
        "window",
        "treatment",
        "drapery",
        "mfg"
    ],
    "wof:name":"Windows & Walls II",
    "wof:placetype":"venue"
},
  "geometry": {"coordinates":[-73.973308,40.597044],"type":"Point"}
}