{
  "type": "Feature",
  "properties": {
    "addr:full":"111 Bedford Rd Armonk NY 10504",
    "addr:housenumber":"111",
    "addr:postcode":"10504",
    "addr:street":"Bedford Rd",
    "iso:country":"US",
    "sg:address":"111 Bedford Rd",
    "sg:city":"Armonk",
    "sg:classifiers":[
        {
            "category":"Restaurant",
            "type":"Food & Drink"
        }
    ],
    "sg:phone":"+1 914 273 4186",
    "sg:postcode":"10504",
    "sg:province":"NY",
    "sg:tags":[
        "italian"
    ],
    "wof:name":"Onda Blu Restaurant",
    "wof:placetype":"venue"
},
  "geometry": {"coordinates":[-73.700203,41.124901],"type":"Point"}
}