{
  "type": "Feature",
  "properties": {
    "iso:country":"US",
    "sg:address":"1 Nicoll St",
    "sg:city":"Washingtonville",
    "sg:classifiers":[
        {
            "category":"Social Services",
            "subcategory":"Child Care",
            "type":"Services"
        }
    ],
    "sg:phone":"+1   ",
    "sg:postcode":"10992",
    "sg:province":"NY",
    "wof:name":"Kourtneys Korner",
    "wof:placetype":"venue"
},
  "geometry": {"coordinates":[-74.15583599999999,41.42653],"type":"Point"}
}