{
  "type": "Feature",
  "properties": {
    "iso:country":"US",
    "sg:address":"10136 Stones Falls Rd",
    "sg:city":"Dansville",
    "sg:classifiers":[
        {
            "category":"Building & Trades",
            "subcategory":"Construction",
            "type":"Services"
        }
    ],
    "sg:phone":"+1 585 335 2164",
    "sg:postcode":"14437",
    "sg:province":"NY",
    "sg:tags":[
        "contractor"
    ],
    "wof:name":"Scotties Glass Shop",
    "wof:placetype":"venue"
},
  "geometry": {"coordinates":[-77.67553599999999,42.541541],"type":"Point"}
}