{
  "type": "Feature",
  "properties": {
    "addr:full":"215 Briarwood Dr Rochester NY 14617",
    "addr:housenumber":"215",
    "addr:postcode":"14617",
    "addr:street":"Briarwood Dr",
    "iso:country":"US",
    "sg:address":"215 Briarwood Dr",
    "sg:city":"Rochester",
    "sg:classifiers":[
        {
            "category":"Education",
            "subcategory":"School",
            "type":"Public Place"
        }
    ],
    "sg:phone":"+1 585 336 1618",
    "sg:postcode":"14617",
    "sg:province":"NY",
    "wof:name":"West Irondequoit Central Schl",
    "wof:placetype":"venue"
},
  "geometry": {"coordinates":[-77.60375000000001,43.215087],"type":"Point"}
}