{
  "type": "Feature",
  "properties": {
    "addr:full":"144 W Hill Rd Vestal NY 13850",
    "addr:housenumber":"144",
    "addr:postcode":"13850",
    "addr:street":"W Hill Rd",
    "iso:country":"US",
    "sg:address":"144 W Hill Rd",
    "sg:city":"Vestal",
    "sg:classifiers":[
        {
            "category":"Professional",
            "subcategory":"Engineering",
            "type":"Services"
        }
    ],
    "sg:phone":"+1   ",
    "sg:postcode":"13850",
    "sg:province":"NY",
    "sg:tags":[
        "consulting",
        "management"
    ],
    "wof:name":"Imagitek Inc",
    "wof:placetype":"venue"
},
  "geometry": {"coordinates":[-76.05192099999999,42.021922],"type":"Point"}
}