{
  "type": "Feature",
  "properties": {
    "addr:full":"1666 67th St. Brooklyn NY 11204",
    "addr:housenumber":"1666",
    "addr:postcode":"11204",
    "addr:street":"67Th St.",
    "iso:country":"US",
    "sg:address":"1666 67th St.",
    "sg:city":"Brooklyn",
    "sg:classifiers":[
        {
            "category":"Building & Trades",
            "subcategory":"Locksmith",
            "type":"Services"
        }
    ],
    "sg:phone":"+1 718 236 3245",
    "sg:postcode":"11204",
    "sg:province":"NY",
    "sg:tags":[
        "key"
    ],
    "wof:name":"Advantage Locksmith Inc",
    "wof:placetype":"venue"
},
  "geometry": {"coordinates":[-73.99471,40.61963],"type":"Point"}
}