{
  "type": "Feature",
  "properties": {
    "addr:full":"62 Burd St Nyack NY 10960",
    "addr:housenumber":"62",
    "addr:postcode":"10960",
    "addr:street":"Burd St",
    "iso:country":"US",
    "sg:address":"62 Burd St",
    "sg:city":"Nyack",
    "sg:classifiers":[
        {
            "category":"Real Estate",
            "subcategory":"Architect",
            "type":"Services"
        }
    ],
    "sg:phone":"+1 845 348 0574",
    "sg:postcode":"10960",
    "sg:province":"NY",
    "wof:name":"Hall & Lane Architects PC",
    "wof:placetype":"venue"
},
  "geometry": {"coordinates":[-73.917619,41.090313],"type":"Point"}
}