{
  "type": "Feature",
  "properties": {
    "addr:full":"241 West 37th St,  Suite 408 New York  NY 10018",
    "addr:housenumber":"241;408",
    "addr:postcode":"10018",
    "addr:street":"West 37Th St Suite",
    "iso:country":"US",
    "sg:address":"241 West 37th St,  Suite 408",
    "sg:city":"New York ",
    "sg:classifiers":[
        {
            "category":"Professional",
            "subcategory":"Computer Services",
            "type":"Services"
        }
    ],
    "sg:phone":"+1 561 753 0776",
    "sg:postcode":"10018",
    "sg:province":"NY",
    "sg:tags":[
        "iphone-app-development",
        "mobile-apps",
        "iphone-apps",
        "iphone-developer",
        "iphone-app-developer"
    ],
    "sg:website":"http://www.bluewhalews.com",
    "wof:name":"Blue Whale Web Solutions",
    "wof:placetype":"venue"
},
  "geometry": {"coordinates":[-73.991165,40.753667],"type":"Point"}
}