{
  "type": "Feature",
  "properties": {
    "iso:country":"US",
    "sg:address":"936 Delaware Ave",
    "sg:city":"Buffalo",
    "sg:classifiers":[
        {
            "category":"Health Services",
            "subcategory":"Doctor",
            "type":"Services"
        }
    ],
    "sg:phone":"+1 716 878 1050",
    "sg:postcode":"14209",
    "sg:province":"NY",
    "sg:tags":[
        "group",
        "association"
    ],
    "wof:name":"Childrens Guild The",
    "wof:placetype":"venue"
},
  "geometry": {"coordinates":[-78.870422,42.91117],"type":"Point"}
}