{
  "type": "Feature",
  "properties": {
    "addr:full":"713 Walt Whitman Rd Melville NY 11747",
    "addr:housenumber":"713",
    "addr:postcode":"11747",
    "addr:street":"Walt Whitman Rd",
    "iso:country":"US",
    "sg:address":"713 Walt Whitman Rd",
    "sg:city":"Melville",
    "sg:classifiers":[
        {
            "category":"Professional",
            "subcategory":"Lawyer & Legal Services",
            "type":"Services"
        }
    ],
    "sg:phone":"+1 631 421 3107",
    "sg:postcode":"11747",
    "sg:province":"NY",
    "sg:tags":[
        "attorney"
    ],
    "wof:name":"Marci Goldfarb Attorney At Law",
    "wof:placetype":"venue"
},
  "geometry": {"coordinates":[-73.410653,40.805561],"type":"Point"}
}