{
  "type": "Feature",
  "properties": {
    "addr:full":"1551 E Genesee St Syracuse NY 13210",
    "addr:housenumber":"1551",
    "addr:postcode":"13210",
    "addr:street":"E Genesee St",
    "iso:country":"US",
    "sg:address":"1551 E Genesee St",
    "sg:city":"Syracuse",
    "sg:classifiers":[
        {
            "category":"Banks & Credit Unions",
            "subcategory":"Investment Brokerage",
            "type":"Services"
        }
    ],
    "sg:phone":"+1 315 685 3158",
    "sg:postcode":"13210",
    "sg:province":"NY",
    "sg:tags":[
        "advisory",
        "financial"
    ],
    "wof:name":"Summit Financial Resources",
    "wof:placetype":"venue"
},
  "geometry": {"coordinates":[-76.12636999999999,43.047088],"type":"Point"}
}