{
  "type": "Feature",
  "properties": {
    "addr:full":"450 Glen Cove Ave Glen Head NY 11545",
    "addr:housenumber":"450",
    "addr:postcode":"11545",
    "addr:street":"Glen Cove Ave Glen",
    "iso:country":"US",
    "sg:address":"450 Glen Cove Ave",
    "sg:city":"Glen Head",
    "sg:classifiers":[
        {
            "category":"Education",
            "subcategory":"School",
            "type":"Public Place"
        }
    ],
    "sg:phone":"+1 516 705 0200",
    "sg:postcode":"11545",
    "sg:province":"NY",
    "wof:name":"North Shore High School",
    "wof:placetype":"venue"
},
  "geometry": {"coordinates":[-73.631917,40.83649],"type":"Point"}
}