{
  "type": "Feature",
  "properties": {
    "addr:full":"50 Williams Ave Wellsville NY 14895",
    "addr:housenumber":"50",
    "addr:postcode":"14895",
    "addr:street":"Williams Ave",
    "iso:country":"US",
    "sg:address":"50 Williams Ave",
    "sg:city":"Wellsville",
    "sg:classifiers":[
        {
            "category":"Shopping",
            "subcategory":"Florist",
            "type":"Retail Goods"
        }
    ],
    "sg:phone":"+1 585 593 2760",
    "sg:postcode":"14895",
    "sg:province":"NY",
    "wof:name":"Kerton Florist",
    "wof:placetype":"venue"
},
  "geometry": {"coordinates":[-77.93029199999999,42.11971],"type":"Point"}
}