{
  "type": "Feature",
  "properties": {
    "iso:country":"US",
    "sg:address":"11 North St",
    "sg:city":"Canandaigua",
    "sg:classifiers":[
        {
            "category":"Insurance",
            "subcategory":"Insurance Agent",
            "type":"Services"
        },
        {
            "category":"Insurance",
            "subcategory":"Hazard Insurance",
            "type":"Services"
        },
        {
            "category":"Insurance",
            "subcategory":"Title Insurance",
            "type":"Services"
        },
        {
            "category":"Insurance",
            "subcategory":"Life Insurance",
            "type":"Services"
        }
    ],
    "sg:phone":"+1 585 396 3130",
    "sg:postcode":"14424",
    "sg:province":"NY",
    "sg:tags":[
        "business",
        "auto",
        "commercial",
        "homeowner",
        "motorcycle",
        "renter"
    ],
    "wof:name":"Allstate Insurance Company - Patricia Hook",
    "wof:placetype":"venue"
},
  "geometry": {"coordinates":[-77.29397,42.904677],"type":"Point"}
}