{
  "type": "Feature",
  "properties": {
    "iso:country":"US",
    "sg:address":"24 Church St",
    "sg:city":"Pittsford",
    "sg:classifiers":[
        {
            "category":"Building & Trades",
            "subcategory":"Landscaping Services",
            "type":"Services"
        },
        {
            "category":"Wholesale",
            "subcategory":"Machinery & Supplies",
            "type":"Manufacturing & Wholesale Goods"
        },
        {
            "category":"Professional",
            "subcategory":"Business Services",
            "type":"Services"
        }
    ],
    "sg:phone":"+1 585 381 7370",
    "sg:postcode":"14534",
    "sg:province":"NY",
    "sg:tags":[
        "lawn",
        "consultant",
        "irrigation",
        "system",
        "equipment",
        "maintenance"
    ],
    "wof:name":"Irrigation Tech",
    "wof:placetype":"venue"
},
  "geometry": {"coordinates":[-77.51493499999999,43.089807],"type":"Point"}
}