{
  "type": "Feature",
  "properties": {
    "iso:country":"US",
    "sg:address":"18 James St",
    "sg:city":"Homer",
    "sg:classifiers":[
        {
            "category":"Building & Trades",
            "subcategory":"Construction",
            "type":"Services"
        }
    ],
    "sg:phone":"+1 607 749 5957",
    "sg:postcode":"13077",
    "sg:province":"NY",
    "sg:tags":[
        "house"
    ],
    "wof:name":"Major Wenz Builders",
    "wof:placetype":"venue"
},
  "geometry": {"coordinates":[-76.180324,42.636921],"type":"Point"}
}