{
  "type": "Feature",
  "properties": {
    "iso:country":"US",
    "sg:address":"179 Co Rte 64",
    "sg:city":"Mexico",
    "sg:classifiers":[
        {
            "category":"Education",
            "subcategory":"School",
            "type":"Public Place"
        }
    ],
    "sg:phone":"+1 315 963 4313",
    "sg:postcode":"13114",
    "sg:province":"NY",
    "wof:name":"Technical Career Center",
    "wof:placetype":"venue"
},
  "geometry": {"coordinates":[-76.26488999999999,43.459937],"type":"Point"}
}