{
  "type": "Feature",
  "properties": {
    "addr:full":"1233 Niagara Falls Blvd Amherst NY 14226",
    "addr:housenumber":"1233",
    "addr:postcode":"14226",
    "addr:street":"Niagara Falls Blvd",
    "iso:country":"US",
    "sg:address":"1233 Niagara Falls Blvd",
    "sg:city":"Amherst",
    "sg:classifiers":[
        {
            "category":"Shopping",
            "subcategory":"Clothing, Apparel, & Fashions",
            "type":"Retail Goods"
        }
    ],
    "sg:phone":"+1 716 836 1486",
    "sg:postcode":"14226",
    "sg:province":"NY",
    "wof:name":"Gap Kids",
    "wof:placetype":"venue"
},
  "geometry": {"coordinates":[-78.82252,42.989525],"type":"Point"}
}