{
  "type": "Feature",
  "properties": {
    "iso:country":"US",
    "sg:address":"1781 Atlantic Avenue",
    "sg:city":"Brooklyn",
    "sg:classifiers":[
        {
            "category":"Retail",
            "subcategory":"Auto Repair",
            "type":"Services"
        }
    ],
    "sg:phone":"+1 718 778 5509",
    "sg:postcode":"11233",
    "sg:province":"NY",
    "wof:name":"D-Top Auto Repair",
    "wof:placetype":"venue"
},
  "geometry": {"coordinates":[-73.927718,40.677449],"type":"Point"}
}