{
  "type": "Feature",
  "properties": {
    "iso:country":"US",
    "sg:address":"2790 Broadway",
    "sg:city":"New York",
    "sg:classifiers":[
        {
            "category":"Professional",
            "subcategory":"Management & Consulting",
            "type":"Services"
        }
    ],
    "sg:phone":"+1 212 961 9252",
    "sg:postcode":"10025",
    "sg:province":"NY",
    "sg:tags":[
        "business"
    ],
    "wof:name":"Galdun Frankel Environmetal",
    "wof:placetype":"venue"
},
  "geometry": {"coordinates":[-73.967578,40.802603],"type":"Point"}
}