{
  "type": "Feature",
  "properties": {
    "iso:country":"US",
    "sg:address":"442 S Main St",
    "sg:city":"North Syracuse",
    "sg:classifiers":[
        {
            "category":"Real Estate",
            "subcategory":"Real Estate Operator",
            "type":"Services"
        }
    ],
    "sg:phone":"+1 315 452 0959",
    "sg:postcode":"13212",
    "sg:province":"NY",
    "sg:tags":[
        "apartment"
    ],
    "wof:name":"Queen Mary Apartments",
    "wof:placetype":"venue"
},
  "geometry": {"coordinates":[-76.133685,43.129653],"type":"Point"}
}