{
  "type": "Feature",
  "properties": {
    "addr:full":"56 W Main St Bay Shore NY 11706",
    "addr:housenumber":"56",
    "addr:postcode":"11706",
    "addr:street":"W Main St",
    "iso:country":"US",
    "sg:address":"56 W Main St",
    "sg:city":"Bay Shore",
    "sg:classifiers":[
        {
            "category":"Health Services",
            "subcategory":"Chiropractor",
            "type":"Services"
        }
    ],
    "sg:phone":"+1 631 665 3714",
    "sg:postcode":"11706",
    "sg:province":"NY",
    "wof:name":"Total Chiropractic Care",
    "wof:placetype":"venue"
},
  "geometry": {"coordinates":[-73.2509,40.719799],"type":"Point"}
}