{
  "type": "Feature",
  "properties": {
    "iso:country":"US",
    "sg:address":"1431 Route 300",
    "sg:city":"Newburgh",
    "sg:classifiers":[
        {
            "category":"Restaurant",
            "type":"Food & Drink"
        }
    ],
    "sg:phone":"+1 845 566 8383",
    "sg:postcode":"12550",
    "sg:province":"NY",
    "sg:tags":[
        "buffet"
    ],
    "wof:name":"Newburgh Buffet Ltd",
    "wof:placetype":"venue"
},
  "geometry": {"coordinates":[-74.070854,41.522516],"type":"Point"}
}