{
  "type": "Feature",
  "properties": {
    "addr:full":"34 Shirley Ln White Plains NY 10607",
    "addr:housenumber":"34",
    "addr:postcode":"10607",
    "addr:street":"Shirley Ln",
    "iso:country":"US",
    "sg:address":"34 Shirley Ln",
    "sg:city":"White Plains",
    "sg:classifiers":[
        {
            "category":"Professional",
            "subcategory":"Computer Services",
            "type":"Services"
        }
    ],
    "sg:phone":"+1 914 949 6429",
    "sg:postcode":"10607",
    "sg:province":"NY",
    "sg:tags":[
        "related"
    ],
    "wof:name":"American Technology Intl",
    "wof:placetype":"venue"
},
  "geometry": {"coordinates":[-73.811761,41.043711],"type":"Point"}
}