{
  "type": "Feature",
  "properties": {
    "iso:country":"US",
    "sg:address":"2695 Stillwell Ave",
    "sg:city":"Brooklyn",
    "sg:classifiers":[
        {
            "category":"Personal",
            "type":"Services"
        },
        {
            "category":"Retail",
            "subcategory":"Auto Repair",
            "type":"Services"
        }
    ],
    "sg:phone":"+1 718 372 7676",
    "sg:postcode":"11224",
    "sg:province":"NY",
    "sg:tags":[
        "body",
        "shop",
        "towing"
    ],
    "wof:name":"Citation Collision Corp",
    "wof:placetype":"venue"
},
  "geometry": {"coordinates":[-73.982101,40.5807],"type":"Point"}
}