{
  "type": "Feature",
  "properties": {
    "addr:full":"610 Lexington Ave New York NY 10022",
    "addr:housenumber":"610",
    "addr:postcode":"10022",
    "addr:street":"Lexington Ave",
    "iso:country":"US",
    "sg:address":"610 Lexington Ave",
    "sg:city":"New York",
    "sg:classifiers":[
        {
            "category":"Education",
            "subcategory":"School",
            "type":"Public Place"
        }
    ],
    "sg:phone":"+1 212 935 8535",
    "sg:postcode":"10022",
    "sg:province":"NY",
    "wof:name":"Japanese Children's Society",
    "wof:placetype":"venue"
},
  "geometry": {"coordinates":[-73.971328,40.757924],"type":"Point"}
}