{
  "type": "Feature",
  "properties": {
    "addr:full":"7010 Webster Rd Westfield NY 14787",
    "addr:housenumber":"7010",
    "addr:postcode":"14787",
    "addr:street":"Webster Rd",
    "iso:country":"US",
    "sg:address":"7010 Webster Rd",
    "sg:city":"Westfield",
    "sg:classifiers":[
        {
            "category":"Farming",
            "subcategory":"Vineyard",
            "type":"Manufacturing & Wholesale Goods"
        }
    ],
    "sg:phone":"+1 716 326 3370",
    "sg:postcode":"14787",
    "sg:province":"NY",
    "sg:tags":[
        "grape"
    ],
    "wof:name":"Woleben Ferris",
    "wof:placetype":"venue"
},
  "geometry": {"coordinates":[-79.51588700000001,42.353015],"type":"Point"}
}