{
  "type": "Feature",
  "properties": {
    "iso:country":"US",
    "sg:address":"585 5th Ave",
    "sg:city":"Brooklyn",
    "sg:classifiers":[
        {
            "category":"Restaurant",
            "type":"Food & Drink"
        }
    ],
    "sg:phone":"+1 718 965 5035",
    "sg:postcode":"11215",
    "sg:province":"NY",
    "sg:tags":[
        "chinese"
    ],
    "wof:name":"Food Kitchen New King",
    "wof:placetype":"venue"
},
  "geometry": {"coordinates":[-73.989932,40.664622],"type":"Point"}
}