{
  "type": "Feature",
  "properties": {
    "addr:full":"68 Van Dyke St Brooklyn NY 11231",
    "addr:housenumber":"68",
    "addr:postcode":"11231",
    "addr:street":"Van Dyke St",
    "iso:country":"US",
    "sg:address":"68 Van Dyke St",
    "sg:city":"Brooklyn",
    "sg:classifiers":[
        {
            "category":"Retail",
            "subcategory":"Repair Shop",
            "type":"Services"
        }
    ],
    "sg:phone":"+1   ",
    "sg:postcode":"11231",
    "sg:province":"NY",
    "sg:tags":[
        "equipment",
        "industrial",
        "marine",
        "fabricated"
    ],
    "sg:website":"www.amertech.org",
    "wof:name":"Amertech Industries Inc",
    "wof:placetype":"venue"
},
  "geometry": {"coordinates":[-74.012252,40.673884],"type":"Point"}
}