{
  "type": "Feature",
  "properties": {
    "iso:country":"US",
    "sg:address":"271 Beach 20",
    "sg:city":"Floral Park",
    "sg:classifiers":[
        {
            "category":"Shopping",
            "subcategory":"Pharmacy",
            "type":"Retail Goods"
        }
    ],
    "sg:phone":"+1 718 337 3027",
    "sg:postcode":"11001",
    "sg:province":"NY",
    "sg:tags":[
        "drugstore"
    ],
    "sg:website":"www.cvs.com",
    "wof:name":"CVS pharmacy",
    "wof:placetype":"venue"
},
  "geometry": {"coordinates":[-73.70438799999999,40.71361],"type":"Point"}
}