{
  "type": "Feature",
  "properties": {
    "iso:country":"US",
    "sg:address":"4801 31st Pl",
    "sg:city":"Long Island City",
    "sg:classifiers":[
        {
            "category":"Organizations",
            "subcategory":"Religious Organization",
            "type":"Services"
        }
    ],
    "sg:phone":"+1 718 721 8881",
    "sg:postcode":"11101",
    "sg:province":"NY",
    "wof:name":"Indonesian Muslim Community",
    "wof:placetype":"venue"
},
  "geometry": {"coordinates":[-73.935238,40.741074],"type":"Point"}
}