{
  "type": "Feature",
  "properties": {
    "iso:country":"US",
    "sg:address":"1267 Hempstead Tpke",
    "sg:city":"Elmont",
    "sg:classifiers":[
        {
            "category":"Real Estate",
            "subcategory":"Real Estate Agent",
            "type":"Services"
        }
    ],
    "sg:phone":"+1 516 333 3383",
    "sg:postcode":"11003",
    "sg:province":"NY",
    "wof:name":"Russell Biomagnetics",
    "wof:placetype":"venue"
},
  "geometry": {"coordinates":[-73.686983,40.708355],"type":"Point"}
}