{
  "type": "Feature",
  "properties": {
    "addr:full":"88 Seigel St Brooklyn NY 11206",
    "addr:housenumber":"88",
    "addr:postcode":"11206",
    "addr:street":"Seigel St",
    "iso:country":"US",
    "sg:address":"88 Seigel St",
    "sg:city":"Brooklyn",
    "sg:classifiers":[
        {
            "category":"Shopping",
            "subcategory":"Pharmacy",
            "type":"Retail Goods"
        }
    ],
    "sg:phone":"+1   ",
    "sg:postcode":"11206",
    "sg:province":"NY",
    "sg:tags":[
        "drugstore"
    ],
    "wof:name":"Farmacia Selecta",
    "wof:placetype":"venue"
},
  "geometry": {"coordinates":[-73.943465,40.704357],"type":"Point"}
}