{
  "type": "Feature",
  "properties": {
    "iso:country":"US",
    "sg:address":"1000 E Genesee St Ste 100",
    "sg:city":"Syracuse",
    "sg:classifiers":[
        {
            "category":"Health Services",
            "subcategory":"Doctor",
            "type":"Services"
        },
        {
            "category":"Health Services",
            "subcategory":"Clinic",
            "type":"Services"
        }
    ],
    "sg:phone":"+1 315 423 4155",
    "sg:postcode":"13210",
    "sg:province":"NY",
    "sg:tags":[
        "physician",
        "surgeon",
        "outpatient"
    ],
    "wof:name":"Goriganti",
    "wof:placetype":"venue"
},
  "geometry": {"coordinates":[-76.136543,43.04686],"type":"Point"}
}