{
  "type": "Feature",
  "properties": {
    "addr:full":"149 Lynn Cir Syracuse NY 13205",
    "addr:housenumber":"149",
    "addr:postcode":"13205",
    "addr:street":"Lynn Cir",
    "iso:country":"US",
    "sg:address":"149 Lynn Cir",
    "sg:city":"Syracuse",
    "sg:classifiers":[
        {
            "category":"Food & Beverages",
            "subcategory":"Groceries & Convenience Stores",
            "type":"Retail Goods"
        }
    ],
    "sg:phone":"+1 315 476 7572",
    "sg:postcode":"13205",
    "sg:province":"NY",
    "sg:tags":[
        "grocer"
    ],
    "wof:name":"Colvin Super Market",
    "wof:placetype":"venue"
},
  "geometry": {"coordinates":[-76.13607399999999,42.993361],"type":"Point"}
}