{
  "type": "Feature",
  "properties": {
    "addr:full":"271 E 10 St New York NY 10009",
    "addr:housenumber":"271;10",
    "addr:postcode":"10009",
    "addr:street":"E;St",
    "iso:country":"US",
    "sg:address":"271 E 10 St",
    "sg:city":"New York",
    "sg:classifiers":[
        {
            "category":"Professional",
            "subcategory":"Printing & Photocopies",
            "type":"Services"
        }
    ],
    "sg:phone":"+1   ",
    "sg:postcode":"10009",
    "sg:province":"NY",
    "sg:tags":[
        "photocopying"
    ],
    "wof:name":"Superior Copy Center",
    "wof:placetype":"venue"
},
  "geometry": {"coordinates":[-73.983142,40.72844],"type":"Point"}
}