{
  "type": "Feature",
  "properties": {
    "addr:full":"71 Burgoyne Ave Fort Edward NY 12828",
    "addr:housenumber":"71",
    "addr:postcode":"12828",
    "addr:street":"Burgoyne Ave",
    "iso:country":"US",
    "sg:address":"71 Burgoyne Ave",
    "sg:city":"Fort Edward",
    "sg:classifiers":[
        {
            "category":"Wholesale",
            "subcategory":"Machinery & Supplies",
            "type":"Manufacturing & Wholesale Goods"
        }
    ],
    "sg:phone":"+1 518 747 8079",
    "sg:postcode":"12828",
    "sg:province":"NY",
    "sg:tags":[
        "equipment",
        "sewer",
        "cleaning"
    ],
    "wof:name":"Municipal Services",
    "wof:placetype":"venue"
},
  "geometry": {"coordinates":[-73.582784,43.279972],"type":"Point"}
}