{
  "type": "Feature",
  "properties": {
    "iso:country":"US",
    "sg:address":"8 Pepperday Ave",
    "sg:city":"Port Washington",
    "sg:classifiers":[
        {
            "category":"Professional",
            "subcategory":"Management & Consulting",
            "type":"Services"
        }
    ],
    "sg:phone":"+1 516 883 6980",
    "sg:postcode":"11050",
    "sg:province":"NY",
    "sg:tags":[
        "consultant",
        "investigation",
        "business",
        "credit"
    ],
    "sg:website":"www.dandhcredit.com",
    "wof:name":"D & H Credit Svces Inc",
    "wof:placetype":"venue"
},
  "geometry": {"coordinates":[-73.695459,40.847113],"type":"Point"}
}