{
  "type": "Feature",
  "properties": {
    "addr:full":"370 S Sunrise Rd West Babylon NY 11704",
    "addr:housenumber":"370",
    "addr:postcode":"11704",
    "addr:street":"S Sunrise Rd",
    "iso:country":"US",
    "sg:address":"370 S Sunrise Rd",
    "sg:city":"West Babylon",
    "sg:classifiers":[
        {
            "category":"Organizations",
            "subcategory":"Religious Organization",
            "type":"Services"
        }
    ],
    "sg:phone":"+1 631 321 7093",
    "sg:postcode":"11704",
    "sg:province":"NY",
    "sg:tags":[
        "church"
    ],
    "wof:name":"Mt Carmel Full Gospel Temple",
    "wof:placetype":"venue"
},
  "geometry": {"coordinates":[-73.36461199999999,40.712181],"type":"Point"}
}