{
  "type": "Feature",
  "properties": {
    "addr:full":"77 Honorine Dr Depew NY 14043",
    "addr:housenumber":"77",
    "addr:postcode":"14043",
    "addr:street":"Honorine Dr",
    "iso:country":"US",
    "sg:address":"77 Honorine Dr",
    "sg:city":"Depew",
    "sg:classifiers":[
        {
            "category":"Organizations",
            "subcategory":"Community Association",
            "type":"Services"
        }
    ],
    "sg:phone":"+1   ",
    "sg:postcode":"14043",
    "sg:province":"NY",
    "wof:name":"Victor W Reinstein",
    "wof:placetype":"venue"
},
  "geometry": {"coordinates":[-78.718346,42.895219],"type":"Point"}
}