{
  "type": "Feature",
  "properties": {
    "iso:country":"US",
    "sg:address":"161 McMaster St",
    "sg:city":"Owego",
    "sg:classifiers":[
        {
            "category":"Wholesale",
            "subcategory":"Construction Materials",
            "type":"Manufacturing & Wholesale Goods"
        }
    ],
    "sg:phone":"+1 607 687 3809",
    "sg:postcode":"13827",
    "sg:province":"NY",
    "sg:tags":[
        "glass"
    ],
    "wof:name":"Architectural Glazing",
    "wof:placetype":"venue"
},
  "geometry": {"coordinates":[-76.267385,42.105085],"type":"Point"}
}