{
  "type": "Feature",
  "properties": {
    "addr:full":"10518 Metropolitan Avenue Forest Hills NY 11375",
    "addr:housenumber":"10518",
    "addr:postcode":"11375",
    "addr:street":"Metropolitan Avenue",
    "iso:country":"US",
    "sg:address":"10518 Metropolitan Avenue",
    "sg:city":"Forest Hills",
    "sg:classifiers":[
        {
            "category":"Shopping",
            "subcategory":"Hobbies, Toys, & Games",
            "type":"Retail Goods"
        },
        {
            "category":"Shopping",
            "subcategory":"Antiques",
            "type":"Retail Goods"
        }
    ],
    "sg:phone":"+1 718 520 9700",
    "sg:postcode":"11375",
    "sg:province":"NY",
    "sg:tags":[
        "toy",
        "store"
    ],
    "wof:name":"World of Trains",
    "wof:placetype":"venue"
},
  "geometry": {"coordinates":[-73.847459,40.709805],"type":"Point"}
}