{
  "type": "Feature",
  "properties": {
    "addr:full":"6 Glade Ln Levittown NY 11756",
    "addr:housenumber":"6",
    "addr:postcode":"11756",
    "addr:street":"Glade Ln",
    "iso:country":"US",
    "sg:address":"6 Glade Ln",
    "sg:city":"Levittown",
    "sg:classifiers":[
        {
            "category":"Building & Trades",
            "subcategory":"Construction",
            "type":"Services"
        }
    ],
    "sg:phone":"+1 516 520 7006",
    "sg:postcode":"11756",
    "sg:province":"NY",
    "sg:tags":[
        "contractor"
    ],
    "wof:name":"John Dineen Contracting",
    "wof:placetype":"venue"
},
  "geometry": {"coordinates":[-73.514534,40.71475],"type":"Point"}
}