{
  "type": "Feature",
  "properties": {
    "iso:country":"US",
    "sg:address":"6094 Italy Valley Rd",
    "sg:city":"Naples",
    "sg:classifiers":[
        {
            "category":"Government",
            "subcategory":"Office",
            "type":"Public Place"
        }
    ],
    "sg:phone":"+1 585 374 8210",
    "sg:postcode":"14512",
    "sg:province":"NY",
    "sg:tags":[
        "village"
    ],
    "wof:name":"Italy Town Supervisor",
    "wof:placetype":"venue"
},
  "geometry": {"coordinates":[-77.324423,42.600186],"type":"Point"}
}