{
  "type": "Feature",
  "properties": {
    "iso:country":"US",
    "sg:address":"7357 Campus Heights Rd",
    "sg:city":"Houghton",
    "sg:classifiers":[
        {
            "category":"Shopping",
            "subcategory":"Books",
            "type":"Retail Goods"
        }
    ],
    "sg:phone":"+1   ",
    "sg:postcode":"14744",
    "sg:province":"NY",
    "wof:name":"Womens Source Books",
    "wof:placetype":"venue"
},
  "geometry": {"coordinates":[-78.15397,42.428578],"type":"Point"}
}