{
  "type": "Feature",
  "properties": {
    "addr:full":"5116 8th Ave Brooklyn NY 11220",
    "addr:housenumber":"5116",
    "addr:postcode":"11220",
    "addr:street":"8Th Ave",
    "iso:country":"US",
    "sg:address":"5116 8th Ave",
    "sg:city":"Brooklyn",
    "sg:classifiers":[
        {
            "category":"Personal",
            "subcategory":"Beauty Salon",
            "type":"Services"
        }
    ],
    "sg:phone":"+1 718 437 3537",
    "sg:postcode":"11220",
    "sg:province":"NY",
    "sg:tags":[
        "shop"
    ],
    "wof:name":"Hair Color Salon Inc",
    "wof:placetype":"venue"
},
  "geometry": {"coordinates":[-74.004864,40.640133],"type":"Point"}
}