{
  "type": "Feature",
  "properties": {
    "iso:country":"US",
    "sg:address":"409 N Cayuga St",
    "sg:city":"Ithaca",
    "sg:classifiers":[
        {
            "category":"Restaurant",
            "type":"Food & Drink"
        }
    ],
    "sg:phone":"+1   ",
    "sg:postcode":"14850",
    "sg:province":"NY",
    "sg:tags":[
        "eating"
    ],
    "wof:name":"East Side Restaurant",
    "wof:placetype":"venue"
},
  "geometry": {"coordinates":[-76.499171,42.444025],"type":"Point"}
}