{
  "type": "Feature",
  "properties": {
    "addr:full":"317 W 51st St New York NY 10019",
    "addr:housenumber":"317",
    "addr:postcode":"10019",
    "addr:street":"W 51St St",
    "iso:country":"US",
    "sg:address":"317 W 51st St",
    "sg:city":"New York",
    "sg:classifiers":[
        {
            "category":"Professional",
            "type":"Services"
        }
    ],
    "sg:phone":"+1 212 586 6379",
    "sg:postcode":"10019",
    "sg:province":"NY",
    "sg:tags":[
        "establishment"
    ],
    "wof:name":"Damascus & Vali",
    "wof:placetype":"venue"
},
  "geometry": {"coordinates":[-73.986857,40.763455],"type":"Point"}
}