{
  "type": "Feature",
  "properties": {
    "addr:full":"17 Avenue D New York NY 10009",
    "addr:housenumber":"17",
    "addr:postcode":"10009",
    "addr:street":"Avenue D",
    "iso:country":"US",
    "sg:address":"17 Avenue D",
    "sg:city":"New York",
    "sg:classifiers":[
        {
            "category":"Health Services",
            "subcategory":"Dentist",
            "type":"Services"
        }
    ],
    "sg:phone":"+1 212 674 1588",
    "sg:postcode":"10009",
    "sg:province":"NY",
    "wof:name":"Shah Arvind DDS",
    "wof:placetype":"venue"
},
  "geometry": {"coordinates":[-73.978357,40.720472],"type":"Point"}
}