{
  "type": "Feature",
  "properties": {
    "addr:full":"202 Sheridan Blvd Inwood NY 11096",
    "addr:housenumber":"202",
    "addr:postcode":"11096",
    "addr:street":"Sheridan Blvd",
    "iso:country":"US",
    "sg:address":"202 Sheridan Blvd",
    "sg:city":"Inwood",
    "sg:classifiers":[
        {
            "category":"Insurance",
            "subcategory":"Hazard Insurance",
            "type":"Services"
        }
    ],
    "sg:phone":"+1 516 371 0435",
    "sg:postcode":"11096",
    "sg:province":"NY",
    "sg:tags":[
        "commercial",
        "business"
    ],
    "sg:website":"http://www.csainsurance.com",
    "wof:name":"C S A Insurance",
    "wof:placetype":"venue"
},
  "geometry": {"coordinates":[-73.751734,40.616758],"type":"Point"}
}