{
  "type": "Feature",
  "properties": {
    "addr:full":"200 Utica Ave Brooklyn NY 11213",
    "addr:housenumber":"200",
    "addr:postcode":"11213",
    "addr:street":"Utica Ave",
    "iso:country":"US",
    "sg:address":"200 Utica Ave",
    "sg:city":"Brooklyn",
    "sg:classifiers":[
        {
            "category":"Organizations",
            "subcategory":"Religious Organization",
            "type":"Services"
        }
    ],
    "sg:phone":"+1 718 756 7922",
    "sg:postcode":"11213",
    "sg:province":"NY",
    "sg:tags":[
        "church"
    ],
    "wof:name":"Ebenezer Holiness Pentecostal",
    "wof:placetype":"venue"
},
  "geometry": {"coordinates":[-73.930916,40.67185],"type":"Point"}
}