{
  "type": "Feature",
  "properties": {
    "addr:full":"100 Violet Ave Floral Park NY 11001",
    "addr:housenumber":"100",
    "addr:postcode":"11001",
    "addr:street":"Violet Ave",
    "iso:country":"US",
    "sg:address":"100 Violet Ave",
    "sg:city":"Floral Park",
    "sg:classifiers":[
        {
            "category":"Building & Trades",
            "subcategory":"Construction",
            "type":"Services"
        }
    ],
    "sg:phone":"+1 516 775 6330",
    "sg:postcode":"11001",
    "sg:province":"NY",
    "sg:tags":[
        "floor",
        "laying",
        "contractor"
    ],
    "wof:name":"J X Floors",
    "wof:placetype":"venue"
},
  "geometry": {"coordinates":[-73.70579499999999,40.721432],"type":"Point"}
}