{
  "type": "Feature",
  "properties": {
    "addr:full":"327 New South Rd Hicksville NY 11801",
    "addr:housenumber":"327",
    "addr:postcode":"11801",
    "addr:street":"New South Rd",
    "iso:country":"US",
    "sg:address":"327 New South Rd",
    "sg:city":"Hicksville",
    "sg:classifiers":[
        {
            "category":"Professional",
            "subcategory":"Art Services",
            "type":"Services"
        }
    ],
    "sg:phone":"+1 516 942 9651",
    "sg:postcode":"11801",
    "sg:province":"NY",
    "sg:tags":[
        "graphic",
        "designer"
    ],
    "wof:name":"Finishing Inc Dynamic Graphic",
    "wof:placetype":"venue"
},
  "geometry": {"coordinates":[-73.505719,40.756293],"type":"Point"}
}