{
  "type": "Feature",
  "properties": {
    "addr:full":"1064 Wtry Rd Niskayuna NY 12309",
    "addr:housenumber":"1064",
    "addr:postcode":"12309",
    "addr:street":"Wtry Rd",
    "iso:country":"US",
    "sg:address":"1064 Wtry Rd",
    "sg:city":"Niskayuna",
    "sg:classifiers":[
        {
            "category":"Communications",
            "subcategory":"Radio Station",
            "type":"Services"
        }
    ],
    "sg:phone":"+1 518 476 9799",
    "sg:postcode":"12309",
    "sg:province":"NY",
    "sg:tags":[
        "company",
        "broadcasting"
    ],
    "wof:name":"WPYX",
    "wof:placetype":"venue"
},
  "geometry": {"coordinates":[-73.836034,42.78114],"type":"Point"}
}