{
  "type": "Feature",
  "properties": {
    "addr:full":"4 Aerial Way Syosset NY 11791",
    "addr:housenumber":"4",
    "addr:postcode":"11791",
    "addr:street":"Aerial Way",
    "iso:country":"US",
    "sg:address":"4 Aerial Way",
    "sg:city":"Syosset",
    "sg:classifiers":[
        {
            "category":"Wholesale",
            "subcategory":"Auto Parts",
            "type":"Manufacturing & Wholesale Goods"
        }
    ],
    "sg:phone":"+1 631 434 1516",
    "sg:postcode":"11791",
    "sg:province":"NY",
    "sg:tags":[
        "automobile",
        "repair",
        "supply"
    ],
    "wof:name":"Metrix the Parts Warehouse",
    "wof:placetype":"venue"
},
  "geometry": {"coordinates":[-73.5158,40.797901],"type":"Point"}
}