{
  "type": "Feature",
  "properties": {
    "addr:full":"6 Dale Carnegie Great Neck NY 11020",
    "addr:housenumber":"6",
    "addr:postcode":"11020",
    "addr:street":"Dale Carnegie",
    "iso:country":"US",
    "sg:address":"6 Dale Carnegie",
    "sg:city":"Great Neck",
    "sg:classifiers":[
        {
            "category":"Real Estate",
            "subcategory":"Real Estate Agent",
            "type":"Services"
        }
    ],
    "sg:phone":"+1 718 359 7834",
    "sg:postcode":"11020",
    "sg:province":"NY",
    "wof:name":"Chu Han Realty Inc",
    "wof:placetype":"venue"
},
  "geometry": {"coordinates":[-73.719483,40.766596],"type":"Point"}
}