{
  "type": "Feature",
  "properties": {
    "addr:full":"7 W 22nd St. 9th Fl. New York NY 10010",
    "addr:housenumber":"7",
    "addr:postcode":"10010",
    "addr:street":"W 22Nd St.",
    "iso:country":"US",
    "sg:address":"7 W 22nd St. 9th Fl.",
    "sg:city":"New York",
    "sg:classifiers":[
        {
            "category":"Professional",
            "subcategory":"Computer Services",
            "type":"Services"
        }
    ],
    "sg:postcode":"10010",
    "sg:province":"NY",
    "sg:tags":[
        "social-network",
        "research",
        "research-papers",
        "academics",
        "academic-publishing",
        "bibliography",
        "reference-management"
    ],
    "sg:website":"http://www.mendeley.com",
    "wof:name":"Mendeley",
    "wof:placetype":"venue"
},
  "geometry": {"coordinates":[-73.993106,40.742216],"type":"Point"}
}