{
  "type": "Feature",
  "properties": {
    "addr:full":"974 52nd St Brooklyn NY 11219",
    "addr:housenumber":"974",
    "addr:postcode":"11219",
    "addr:street":"52Nd St",
    "iso:country":"US",
    "sg:address":"974 52nd St",
    "sg:city":"Brooklyn",
    "sg:classifiers":[
        {
            "category":"Health Services",
            "subcategory":"Doctor",
            "type":"Services"
        }
    ],
    "sg:phone":"+1 718 435 2000",
    "sg:postcode":"11219",
    "sg:province":"NY",
    "sg:tags":[
        "physician",
        "surgeon"
    ],
    "wof:name":"Alan M Crystal MD",
    "wof:placetype":"venue"
},
  "geometry": {"coordinates":[-74.001778,40.638282],"type":"Point"}
}