{
  "type": "Feature",
  "properties": {
    "iso:country":"US",
    "sg:address":"451 Meyer Rd",
    "sg:city":"Buffalo",
    "sg:classifiers":[
        {
            "category":"Building & Trades",
            "subcategory":"Landscaping Services",
            "type":"Services"
        }
    ],
    "sg:phone":"+1 716 834 3500",
    "sg:postcode":"14226",
    "sg:province":"NY",
    "sg:tags":[
        "snowplowing",
        "landscape",
        "contractor"
    ],
    "wof:name":"Hausraths Landscape Maint",
    "wof:placetype":"venue"
},
  "geometry": {"coordinates":[-78.809349,42.99457],"type":"Point"}
}