{
  "type": "Feature",
  "properties": {
    "addr:full":"37-15 31st Avenue Queens NY 11103",
    "addr:housenumber":"37-15",
    "addr:postcode":"11103",
    "addr:street":"31St Avenue",
    "iso:country":"US",
    "sg:address":"37-15 31st Avenue",
    "sg:city":"Queens",
    "sg:classifiers":[
        {
            "category":"Food & Beverages",
            "subcategory":"Groceries & Convenience Stores",
            "type":"Retail Goods"
        }
    ],
    "sg:phone":"+1 718 728 0852",
    "sg:postcode":"11103",
    "sg:province":"NY",
    "wof:name":"Associated Supermarket",
    "wof:placetype":"venue"
},
  "geometry": {"coordinates":[-73.91807900000001,40.761803],"type":"Point"}
}