{
  "type": "Feature",
  "properties": {
    "addr:full":"99 E Main St Ste 4 East Islip NY 11730",
    "addr:housenumber":"99",
    "addr:postcode":"11730",
    "addr:street":"E Main St Ste 4",
    "iso:country":"US",
    "sg:address":"99 E Main St Ste 4",
    "sg:city":"East Islip",
    "sg:classifiers":[
        {
            "category":"Building & Trades",
            "subcategory":"Plumbing",
            "type":"Services"
        }
    ],
    "sg:phone":"+1 631 859 3171",
    "sg:postcode":"11730",
    "sg:province":"NY",
    "wof:name":"Acura Plumbing & Heating Inc",
    "wof:placetype":"venue"
},
  "geometry": {"coordinates":[-73.18620300000001,40.732101],"type":"Point"}
}