{
  "type": "Feature",
  "properties": {
    "addr:full":"1273 53rd St Brooklyn NY 11219",
    "addr:housenumber":"1273",
    "addr:postcode":"11219",
    "addr:street":"53Rd St",
    "iso:country":"US",
    "sg:address":"1273 53rd St",
    "sg:city":"Brooklyn",
    "sg:classifiers":[
        {
            "category":"Education",
            "subcategory":"Special Training",
            "type":"Public Place"
        },
        {
            "category":"Education",
            "subcategory":"University",
            "type":"Public Place"
        }
    ],
    "sg:phone":"+1 718 871 6187",
    "sg:postcode":"11219",
    "sg:province":"NY",
    "sg:tags":[
        "educational",
        "college",
        "school",
        "language"
    ],
    "sg:website":"http://www.touro.edu",
    "wof:name":"Touro College Russian Program",
    "wof:placetype":"venue"
},
  "geometry": {"coordinates":[-73.99495400000001,40.633081],"type":"Point"}
}