{
  "type": "Feature",
  "properties": {
    "addr:full":"194 Merritts Rd Farmingdale NY 11735",
    "addr:housenumber":"194",
    "addr:postcode":"11735",
    "addr:street":"Merritts Rd",
    "iso:country":"US",
    "sg:address":"194 Merritts Rd",
    "sg:city":"Farmingdale",
    "sg:classifiers":[
        {
            "category":"Building & Trades",
            "subcategory":"Electrical",
            "type":"Services"
        }
    ],
    "sg:phone":"+1 516 221 9870",
    "sg:postcode":"11735",
    "sg:province":"NY",
    "sg:tags":[
        "installs",
        "repair",
        "telephone",
        "communication"
    ],
    "wof:name":"Telephone Dynamics Corporation",
    "wof:placetype":"venue"
},
  "geometry": {"coordinates":[-73.45842399999999,40.722867],"type":"Point"}
}