{
  "type": "Feature",
  "properties": {
    "iso:country":"US",
    "sg:address":"93 Newport Bridge Rd",
    "sg:city":"Warwick",
    "sg:classifiers":[
        {
            "category":"Building & Trades",
            "subcategory":"Landscaping Services",
            "type":"Services"
        }
    ],
    "sg:phone":"+1 845 986 0101",
    "sg:postcode":"10990",
    "sg:province":"NY",
    "sg:tags":[
        "lawn"
    ],
    "wof:name":"Clean Cut",
    "wof:placetype":"venue"
},
  "geometry": {"coordinates":[-74.450953,41.268505],"type":"Point"}
}