{
  "type": "Feature",
  "properties": {
    "iso:country":"US",
    "sg:address":"123 E Neck Rd",
    "sg:city":"Huntington",
    "sg:classifiers":[
        {
            "category":"Manufacturing",
            "subcategory":"Chemicals & Compounds",
            "type":"Manufacturing & Wholesale Goods"
        }
    ],
    "sg:phone":"+1 631 547 5984",
    "sg:postcode":"11743",
    "sg:province":"NY",
    "sg:tags":[
        "miller",
        "drug"
    ],
    "wof:name":"Vitaflo",
    "wof:placetype":"venue"
},
  "geometry": {"coordinates":[-73.390317,40.90559],"type":"Point"}
}