{
  "type": "Feature",
  "properties": {
    "addr:full":"90 Broadhollow Rd Farmingdale NY 11735",
    "addr:housenumber":"90",
    "addr:postcode":"11735",
    "addr:street":"Broadhollow Rd",
    "iso:country":"US",
    "sg:address":"90 Broadhollow Rd",
    "sg:city":"Farmingdale",
    "sg:classifiers":[
        {
            "category":"Restaurant",
            "type":"Food & Drink"
        }
    ],
    "sg:menulink":"http://www.allmenus.com/ny/babylon/146727-boston-market/menu/",
    "sg:phone":"+1 631 753 3777",
    "sg:postcode":"11735",
    "sg:province":"NY",
    "sg:tags":[
        "barbecue",
        "american",
        "soup"
    ],
    "wof:name":"Boston Market",
    "wof:placetype":"venue"
},
  "geometry": {"coordinates":[-73.42941399999999,40.711544],"type":"Point"}
}