{
  "type": "Feature",
  "properties": {
    "addr:full":"936 Woodycrest Ave Bronx NY 10452",
    "addr:housenumber":"936",
    "addr:postcode":"10452",
    "addr:street":"Woodycrest Ave",
    "iso:country":"US",
    "sg:address":"936 Woodycrest Ave",
    "sg:city":"Bronx",
    "sg:classifiers":[
        {
            "category":"Health Services",
            "subcategory":"Nursing And Care Facility",
            "type":"Services"
        },
        {
            "category":"Organizations",
            "subcategory":"Non-profit Organization",
            "type":"Services"
        }
    ],
    "sg:phone":"+1 718 293 3200",
    "sg:postcode":"10452",
    "sg:province":"NY",
    "sg:tags":[
        "hospital",
        "skilled"
    ],
    "wof:name":"Highbridge-Woodycrest Center, Inc",
    "wof:placetype":"venue"
},
  "geometry": {"coordinates":[-73.92973499999999,40.83039],"type":"Point"}
}