{
  "type": "Feature",
  "properties": {
    "addr:full":"3502 Country Club Rd Endicott NY 13760",
    "addr:housenumber":"3502",
    "addr:postcode":"13760",
    "addr:street":"Country Club Rd",
    "iso:country":"US",
    "sg:address":"3502 Country Club Rd",
    "sg:city":"Endicott",
    "sg:classifiers":[
        {
            "category":"Professional",
            "subcategory":"Computer Services",
            "type":"Services"
        }
    ],
    "sg:phone":"+1 607 754 7378",
    "sg:postcode":"13760",
    "sg:province":"NY",
    "sg:tags":[
        "repair"
    ],
    "wof:name":"Tech Man Computer Svc",
    "wof:placetype":"venue"
},
  "geometry": {"coordinates":[-76.01940999999999,42.116127],"type":"Point"}
}