{
  "type": "Feature",
  "properties": {
    "iso:country":"US",
    "sg:address":"2324 Forest Ave",
    "sg:city":"Staten Island",
    "sg:classifiers":[
        {
            "category":"Organizations",
            "subcategory":"Professional Association",
            "type":"Services"
        }
    ],
    "sg:phone":"+1 718 447 8205",
    "sg:postcode":"10303",
    "sg:province":"NY",
    "wof:name":"United Cerebral Palsy",
    "wof:placetype":"venue"
},
  "geometry": {"coordinates":[-74.16782000000001,40.627514],"type":"Point"}
}