{
  "type": "Feature",
  "properties": {
    "addr:full":"1333 60th St Brooklyn NY 11219",
    "addr:housenumber":"1333",
    "addr:postcode":"11219",
    "addr:street":"60Th St",
    "iso:country":"US",
    "sg:address":"1333 60th St",
    "sg:city":"Brooklyn",
    "sg:classifiers":[
        {
            "category":"Real Estate",
            "subcategory":"Real Estate Agent",
            "type":"Services"
        }
    ],
    "sg:phone":"+1 212 812 2600",
    "sg:postcode":"11219",
    "sg:province":"NY",
    "sg:website":"www.nationwidesettlements.com",
    "wof:name":"Nationwide Settlements",
    "wof:placetype":"venue"
},
  "geometry": {"coordinates":[-73.99700300000001,40.628093],"type":"Point"}
}