{
  "type": "Feature",
  "properties": {
    "iso:country":"US",
    "sg:address":"14 Railroad Ave",
    "sg:city":"Warwick",
    "sg:classifiers":[
        {
            "category":"Professional",
            "subcategory":"Printing & Photocopies",
            "type":"Services"
        }
    ],
    "sg:phone":"+1 845 986 8177",
    "sg:postcode":"10990",
    "sg:province":"NY",
    "sg:tags":[
        "duplicating",
        "copying"
    ],
    "wof:name":"Gaint Copy Shop",
    "wof:placetype":"venue"
},
  "geometry": {"coordinates":[-74.358835,41.256272],"type":"Point"}
}