{
  "type": "Feature",
  "properties": {
    "addr:full":"740 E 13th Street New York NY 10009",
    "addr:housenumber":"740",
    "addr:postcode":"10009",
    "addr:street":"E 13Th Street",
    "iso:country":"US",
    "sg:address":"740 E 13th Street",
    "sg:city":"New York",
    "sg:classifiers":[
        {
            "category":"Organizations",
            "subcategory":"Religious Organization",
            "type":"Services"
        }
    ],
    "sg:phone":"+1 212 228 4494",
    "sg:postcode":"10009",
    "sg:province":"NY",
    "wof:name":"St Emeric's Church",
    "wof:placetype":"venue"
},
  "geometry": {"coordinates":[-73.97431400000001,40.726822],"type":"Point"}
}