{
  "type": "Feature",
  "properties": {
    "addr:full":"1 Holly Street Staten Island NY 10304",
    "addr:housenumber":"1",
    "addr:postcode":"10304",
    "addr:street":"Holly Street",
    "iso:country":"US",
    "sg:address":"1 Holly Street",
    "sg:city":"Staten Island",
    "sg:classifiers":[
        {
            "category":"Real Estate",
            "subcategory":"Real Estate Services",
            "type":"Services"
        }
    ],
    "sg:phone":"+1 718 979 5005",
    "sg:postcode":"10304",
    "sg:province":"NY",
    "wof:name":"Lyke Elizabeth Rl Est",
    "wof:placetype":"venue"
},
  "geometry": {"coordinates":[-74.09400599999999,40.600945],"type":"Point"}
}