{
  "type": "Feature",
  "properties": {
    "addr:full":"10 Tanager Ln Northport NY 11768",
    "addr:housenumber":"10",
    "addr:postcode":"11768",
    "addr:street":"Tanager Ln",
    "iso:country":"US",
    "sg:address":"10 Tanager Ln",
    "sg:city":"Northport",
    "sg:classifiers":[
        {
            "category":"Professional",
            "subcategory":"Management & Consulting",
            "type":"Services"
        }
    ],
    "sg:phone":"+1   ",
    "sg:postcode":"11768",
    "sg:province":"NY",
    "sg:tags":[
        "public",
        "relations"
    ],
    "wof:name":"Big Top Promotions Inc",
    "wof:placetype":"venue"
},
  "geometry": {"coordinates":[-73.30201,40.885321],"type":"Point"}
}