{
  "type": "Feature",
  "properties": {
    "addr:full":"168 Canal Street Lbby Canal Street NY 10013",
    "addr:housenumber":"168",
    "addr:postcode":"10013",
    "addr:street":"Canal Street;Canal Street",
    "iso:country":"US",
    "sg:address":"168 Canal Street Lbby",
    "sg:city":"Canal Street",
    "sg:classifiers":[
        {
            "category":"Health Services",
            "subcategory":"Doctor",
            "type":"Services"
        }
    ],
    "sg:phone":"+1 212 219 8010",
    "sg:postcode":"10013",
    "sg:province":"NY",
    "wof:name":"Chan Anthony P Y Physician PC",
    "wof:placetype":"venue"
},
  "geometry": {"coordinates":[-73.99730099999999,40.716581],"type":"Point"}
}