{
  "type": "Feature",
  "properties": {
    "iso:country":"US",
    "sg:address":"2245 English Rd",
    "sg:city":"Rochester",
    "sg:classifiers":[
        {
            "category":"Social Services",
            "type":"Services"
        }
    ],
    "sg:phone":"+1 585 227 9808",
    "sg:postcode":"14616",
    "sg:province":"NY",
    "sg:tags":[
        "organization",
        "welfare"
    ],
    "wof:name":"Mary Cariola Children's Ctr",
    "wof:placetype":"venue"
},
  "geometry": {"coordinates":[-77.71145199999999,43.238619],"type":"Point"}
}