{
  "type": "Feature",
  "properties": {
    "addr:full":"12 Lindenwood Rd Staten Island NY 10308",
    "addr:housenumber":"12",
    "addr:postcode":"10308",
    "addr:street":"Lindenwood Rd",
    "iso:country":"US",
    "sg:address":"12 Lindenwood Rd",
    "sg:city":"Staten Island",
    "sg:classifiers":[
        {
            "category":"Building & Trades",
            "subcategory":"Construction",
            "type":"Services"
        }
    ],
    "sg:phone":"+1 718 984 4147",
    "sg:postcode":"10308",
    "sg:province":"NY",
    "sg:tags":[
        "contractor"
    ],
    "wof:name":"Bam Bam Construction Corp",
    "wof:placetype":"venue"
},
  "geometry": {"coordinates":[-74.15334199999999,40.550966],"type":"Point"}
}