{
  "type": "Feature",
  "properties": {
    "iso:country":"US",
    "sg:address":"13504 State Rte 31",
    "sg:city":"Albion",
    "sg:classifiers":[
        {
            "category":"Building & Trades",
            "subcategory":"Construction",
            "type":"Services"
        }
    ],
    "sg:phone":"+1 585 589 1394",
    "sg:postcode":"14411",
    "sg:province":"NY",
    "sg:tags":[
        "graphic",
        "mfg",
        "custom",
        "design",
        "cabinet",
        "furniture"
    ],
    "wof:name":"Lonowood Art Co Inc",
    "wof:placetype":"venue"
},
  "geometry": {"coordinates":[-78.24424399999999,43.229544],"type":"Point"}
}