{
  "type": "Feature",
  "properties": {
    "addr:full":"3385 Bailey Ave Buffalo NY 14215",
    "addr:housenumber":"3385",
    "addr:postcode":"14215",
    "addr:street":"Bailey Ave",
    "iso:country":"US",
    "sg:address":"3385 Bailey Ave",
    "sg:city":"Buffalo",
    "sg:classifiers":[
        {
            "category":"Professional",
            "subcategory":"Accounting & Tax Preparation",
            "type":"Services"
        }
    ],
    "sg:phone":"+1 716 446 9832",
    "sg:postcode":"14215",
    "sg:province":"NY",
    "sg:tags":[
        "return",
        "filing"
    ],
    "wof:name":"Compro Tax YP",
    "wof:placetype":"venue"
},
  "geometry": {"coordinates":[-78.813603,42.947348],"type":"Point"}
}