{
  "type": "Feature",
  "properties": {
    "addr:full":"817 Meeker Ave Brooklyn NY 11222",
    "addr:housenumber":"817",
    "addr:postcode":"11222",
    "addr:street":"Meeker Ave",
    "iso:country":"US",
    "sg:address":"817 Meeker Ave",
    "sg:city":"Brooklyn",
    "sg:classifiers":[
        {
            "category":"Retail",
            "subcategory":"Auto Repair",
            "type":"Services"
        },
        {
            "category":"Manufacturing",
            "subcategory":"Motor Vehicles & Parts",
            "type":"Manufacturing & Wholesale Goods"
        }
    ],
    "sg:phone":"+1 718 384 4242",
    "sg:postcode":"11222",
    "sg:province":"NY",
    "sg:tags":[
        "equipment",
        "truck",
        "supply"
    ],
    "wof:name":"John's Truck Parts",
    "wof:placetype":"venue"
},
  "geometry": {"coordinates":[-73.93539699999999,40.725907],"type":"Point"}
}