{
  "type": "Feature",
  "properties": {
    "addr:full":"6659 Amboy Rd Staten Island NY 10309",
    "addr:housenumber":"6659",
    "addr:postcode":"10309",
    "addr:street":"Amboy Rd",
    "iso:country":"US",
    "sg:address":"6659 Amboy Rd",
    "sg:city":"Staten Island",
    "sg:classifiers":[
        {
            "category":"Health Services",
            "subcategory":"Chiropractor",
            "type":"Services"
        }
    ],
    "sg:phone":"+1 718 605 2225",
    "sg:postcode":"10309",
    "sg:province":"NY",
    "wof:name":"Back To Health",
    "wof:placetype":"venue"
},
  "geometry": {"coordinates":[-74.224356,40.518589],"type":"Point"}
}