{
  "type": "Feature",
  "properties": {
    "iso:country":"US",
    "sg:address":"5833 S Transit Rd",
    "sg:city":"Lockport",
    "sg:classifiers":[
        {
            "category":"Insurance",
            "subcategory":"Insurance Agent",
            "type":"Services"
        }
    ],
    "sg:phone":"+1 716 433 0097",
    "sg:postcode":"14094",
    "sg:province":"NY",
    "wof:name":"Robert A Muffler Agency",
    "wof:placetype":"venue"
},
  "geometry": {"coordinates":[-78.69680099999999,43.1413],"type":"Point"}
}