{
  "type": "Feature",
  "properties": {
    "addr:full":"140 Jackson St Brooklyn NY 11211",
    "addr:housenumber":"140",
    "addr:postcode":"11211",
    "addr:street":"Jackson St",
    "iso:country":"US",
    "sg:address":"140 Jackson St",
    "sg:city":"Brooklyn",
    "sg:classifiers":[
        {
            "category":"Professional",
            "type":"Services"
        }
    ],
    "sg:phone":"+1   ",
    "sg:postcode":"11211",
    "sg:province":"NY",
    "wof:name":"Faces of World",
    "wof:placetype":"venue"
},
  "geometry": {"coordinates":[-73.945362,40.716494],"type":"Point"}
}