{
  "type": "Feature",
  "properties": {
    "iso:country":"US",
    "sg:address":"719 Ocean View Ave",
    "sg:city":"Brooklyn",
    "sg:classifiers":[
        {
            "category":"Health Services",
            "subcategory":"Doctor",
            "type":"Services"
        }
    ],
    "sg:phone":"+1 347 462 1551",
    "sg:postcode":"11235",
    "sg:province":"NY",
    "wof:name":"Executive Medical Care Pc",
    "wof:placetype":"venue"
},
  "geometry": {"coordinates":[-73.960869,40.579993],"type":"Point"}
}