{
  "type": "Feature",
  "properties": {
    "addr:full":"15118 6th Road Whitestone NY 11357",
    "addr:housenumber":"15118",
    "addr:postcode":"11357",
    "addr:street":"6Th Road",
    "iso:country":"US",
    "sg:address":"15118 6th Road",
    "sg:city":"Whitestone",
    "sg:classifiers":[
        {
            "category":"Real Estate",
            "subcategory":"Real Estate Services",
            "type":"Services"
        }
    ],
    "sg:phone":"+1 718 767 2900",
    "sg:postcode":"11357",
    "sg:province":"NY",
    "sg:tags":[
        "home",
        "inspector"
    ],
    "wof:name":"Big Apple Testing",
    "wof:placetype":"venue"
},
  "geometry": {"coordinates":[-73.812258,40.795804],"type":"Point"}
}