{
  "type": "Feature",
  "properties": {
    "addr:full":"1 Newbridge Rd Hicksville NY 11801",
    "addr:housenumber":"1",
    "addr:postcode":"11801",
    "addr:street":"Newbridge Rd",
    "iso:country":"US",
    "sg:address":"1 Newbridge Rd",
    "sg:city":"Hicksville",
    "sg:classifiers":[
        {
            "category":"Professional",
            "subcategory":"Computer Services",
            "type":"Services"
        }
    ],
    "sg:phone":"+1 516 938 0157",
    "sg:postcode":"11801",
    "sg:province":"NY",
    "sg:tags":[
        "stereo",
        "installation"
    ],
    "wof:name":"Audio Designs",
    "wof:placetype":"venue"
},
  "geometry": {"coordinates":[-73.527298,40.772301],"type":"Point"}
}