{
  "type": "Feature",
  "properties": {
    "addr:full":"307 Columbus Ave Tuckahoe NY 10707",
    "addr:housenumber":"307",
    "addr:postcode":"10707",
    "addr:street":"Columbus Ave",
    "iso:country":"US",
    "sg:address":"307 Columbus Ave",
    "sg:city":"Tuckahoe",
    "sg:classifiers":[
        {
            "category":"Restaurant",
            "type":"Food & Drink"
        }
    ],
    "sg:phone":"+1 914 337 4880",
    "sg:postcode":"10707",
    "sg:province":"NY",
    "wof:name":"Roberto's Italian Restaurant",
    "wof:placetype":"venue"
},
  "geometry": {"coordinates":[-73.820549,40.959032],"type":"Point"}
}