{
  "type": "Feature",
  "properties": {
    "iso:country":"US",
    "sg:address":"501 Pletcher Rd",
    "sg:city":"Lewiston",
    "sg:classifiers":[
        {
            "category":"Government",
            "subcategory":"Office",
            "type":"Public Place"
        }
    ],
    "sg:phone":"+1 716 754 8291",
    "sg:postcode":"14092",
    "sg:province":"NY",
    "sg:tags":[
        "city",
        "program"
    ],
    "wof:name":"Lewiston Water Pollution Cntrl",
    "wof:placetype":"venue"
},
  "geometry": {"coordinates":[-79.041768,43.20205],"type":"Point"}
}