{
  "type": "Feature",
  "properties": {
    "addr:full":"10406 Ridge Rd Medina NY 14103",
    "addr:housenumber":"10406",
    "addr:postcode":"14103",
    "addr:street":"Ridge Rd",
    "iso:country":"US",
    "sg:address":"10406 Ridge Rd",
    "sg:city":"Medina",
    "sg:classifiers":[
        {
            "category":"Retail",
            "subcategory":"Auto Repair",
            "type":"Services"
        }
    ],
    "sg:phone":"+1   ",
    "sg:postcode":"14103",
    "sg:province":"NY",
    "sg:tags":[
        "body",
        "automobile",
        "used"
    ],
    "wof:name":"Klinos Collision",
    "wof:placetype":"venue"
},
  "geometry": {"coordinates":[-78.45089400000001,43.256431],"type":"Point"}
}