{
  "type": "Feature",
  "properties": {
    "addr:full":"27 South St Orangeburg NY 10940",
    "addr:housenumber":"27",
    "addr:postcode":"10940",
    "addr:street":"South St",
    "iso:country":"US",
    "sg:address":"27 South St",
    "sg:city":"Orangeburg",
    "sg:classifiers":[
        {
            "category":"Shopping",
            "subcategory":"Catalog Store",
            "type":"Retail Goods"
        }
    ],
    "sg:phone":"+1   ",
    "sg:postcode":"10940",
    "sg:province":"NY",
    "sg:tags":[
        "house",
        "mail"
    ],
    "wof:name":"Direct Source Inc",
    "wof:placetype":"venue"
},
  "geometry": {"coordinates":[-74.420858,41.443793],"type":"Point"}
}