{
  "type": "Feature",
  "properties": {
    "addr:full":"218 Houseman St Mayfield NY 12117",
    "addr:housenumber":"218",
    "addr:postcode":"12117",
    "addr:street":"Houseman St",
    "iso:country":"US",
    "sg:address":"218 Houseman St",
    "sg:city":"Mayfield",
    "sg:classifiers":[
        {
            "category":"Real Estate",
            "subcategory":"Real Estate Agent",
            "type":"Services"
        }
    ],
    "sg:phone":"+1 518 863 2362",
    "sg:postcode":"12117",
    "sg:province":"NY",
    "wof:name":"Lakeside Mobile",
    "wof:placetype":"venue"
},
  "geometry": {"coordinates":[-74.179495,43.195553],"type":"Point"}
}