{
  "type": "Feature",
  "properties": {
    "iso:country":"US",
    "sg:address":"120 Schuyler St",
    "sg:city":"Boonville",
    "sg:classifiers":[
        {
            "category":"Health Services",
            "subcategory":"Clinic",
            "type":"Services"
        }
    ],
    "sg:phone":"+1   ",
    "sg:postcode":"13309",
    "sg:province":"NY",
    "sg:tags":[
        "specialty",
        "outpatient"
    ],
    "wof:name":"Mountain Mental Health Group",
    "wof:placetype":"venue"
},
  "geometry": {"coordinates":[-75.336906,43.483659],"type":"Point"}
}