{
  "type": "Feature",
  "properties": {
    "addr:full":"1618 43rd St Brooklyn NY 11204",
    "addr:housenumber":"1618",
    "addr:postcode":"11204",
    "addr:street":"43Rd St",
    "iso:country":"US",
    "sg:address":"1618 43rd St",
    "sg:city":"Brooklyn",
    "sg:classifiers":[
        {
            "category":"Education",
            "subcategory":"Special Training",
            "type":"Public Place"
        }
    ],
    "sg:phone":"+1 718 436 4999",
    "sg:postcode":"11204",
    "sg:province":"NY",
    "sg:tags":[
        "educational"
    ],
    "wof:name":"Dial A Daf",
    "wof:placetype":"venue"
},
  "geometry": {"coordinates":[-73.979947,40.633126],"type":"Point"}
}