{
  "type": "Feature",
  "properties": {
    "iso:country":"US",
    "sg:address":"122 Rollstone Ave",
    "sg:city":"West Sayville",
    "sg:classifiers":[
        {
            "category":"Wholesale",
            "subcategory":"Seafood",
            "type":"Manufacturing & Wholesale Goods"
        }
    ],
    "sg:phone":"+1 631 567 1005",
    "sg:postcode":"11796",
    "sg:province":"NY",
    "wof:name":"Harris Shellfish Inc",
    "wof:placetype":"venue"
},
  "geometry": {"coordinates":[-73.099142,40.735532],"type":"Point"}
}