{
  "type": "Feature",
  "properties": {
    "addr:full":"13215 218th Street Springfield Gardens NY 11413",
    "addr:housenumber":"13215",
    "addr:postcode":"11413",
    "addr:street":"218Th Street",
    "iso:country":"US",
    "sg:address":"13215 218th Street",
    "sg:city":"Springfield Gardens",
    "sg:classifiers":[
        {
            "category":"Education",
            "subcategory":"School",
            "type":"Public Place"
        }
    ],
    "sg:phone":"+1 718 528 5734",
    "sg:postcode":"11413",
    "sg:province":"NY",
    "sg:tags":[
        "high",
        "middle",
        "elementary"
    ],
    "wof:name":"N Y City of",
    "wof:placetype":"venue"
},
  "geometry": {"coordinates":[-73.74971600000001,40.682192],"type":"Point"}
}