{
  "type": "Feature",
  "properties": {
    "addr:full":"1164 Erie Blvd W Rome NY 13440",
    "addr:housenumber":"1164",
    "addr:postcode":"13440",
    "addr:street":"Erie Blvd W",
    "iso:country":"US",
    "sg:address":"1164 Erie Blvd W",
    "sg:city":"Rome",
    "sg:classifiers":[
        {
            "category":"Restaurant",
            "type":"Food & Drink"
        }
    ],
    "sg:menulink":"http://www.allmenus.com/ny/rome/208339-taco-bell/menu/",
    "sg:phone":"+1 315 339 7960",
    "sg:postcode":"13440",
    "sg:province":"NY",
    "sg:tags":[
        "mexican"
    ],
    "wof:name":"Taco Bell",
    "wof:placetype":"venue"
},
  "geometry": {"coordinates":[-75.485314,43.224433],"type":"Point"}
}