{
  "type": "Feature",
  "properties": {
    "iso:country":"US",
    "sg:address":"6 Lester Ct",
    "sg:city":"East Northport",
    "sg:classifiers":[
        {
            "category":"Recreation",
            "type":"Entertainment"
        }
    ],
    "sg:phone":"+1 631 368 3392",
    "sg:postcode":"11731",
    "sg:province":"NY",
    "sg:tags":[
        "club",
        "baseball"
    ],
    "wof:name":"Larkfield Little League Inc",
    "wof:placetype":"venue"
},
  "geometry": {"coordinates":[-73.30574900000001,40.872282],"type":"Point"}
}