{
  "type": "Feature",
  "properties": {
    "iso:country":"US",
    "sg:address":"44 Oakland Ave",
    "sg:city":"Walden",
    "sg:classifiers":[
        {
            "category":"Building & Trades",
            "subcategory":"Construction",
            "type":"Services"
        }
    ],
    "sg:phone":"+1 845 778 0668",
    "sg:postcode":"12586",
    "sg:province":"NY",
    "sg:tags":[
        "concrete",
        "contractor"
    ],
    "wof:name":"USA Concrete",
    "wof:placetype":"venue"
},
  "geometry": {"coordinates":[-74.179413,41.567349],"type":"Point"}
}