{
  "type": "Feature",
  "properties": {
    "addr:full":"1441 Broadway New York NY 10018",
    "addr:housenumber":"1441",
    "addr:postcode":"10018",
    "addr:street":"Broadway",
    "iso:country":"US",
    "sg:address":"1441 Broadway",
    "sg:city":"New York",
    "sg:classifiers":[
        {
            "category":"Shopping",
            "subcategory":"Clothing, Apparel, & Fashions",
            "type":"Retail Goods"
        }
    ],
    "sg:phone":"+1 212 719 2520",
    "sg:postcode":"10018",
    "sg:province":"NY",
    "wof:name":"GMR Fashion Inc",
    "wof:placetype":"venue"
},
  "geometry": {"coordinates":[-73.986807,40.754654],"type":"Point"}
}