{
  "type": "Feature",
  "properties": {
    "iso:country":"US",
    "sg:address":"375 W Onondaga St",
    "sg:city":"Syracuse",
    "sg:classifiers":[
        {
            "category":"Retail",
            "subcategory":"Auto Repair",
            "type":"Services"
        }
    ],
    "sg:phone":"+1 315 479 7305",
    "sg:postcode":"13202",
    "sg:province":"NY",
    "sg:tags":[
        "body",
        "automobile",
        "painting"
    ],
    "wof:name":"T & R Custom Collision",
    "wof:placetype":"venue"
},
  "geometry": {"coordinates":[-76.155959,43.041989],"type":"Point"}
}