{
  "type": "Feature",
  "properties": {
    "addr:full":"45 Wall St New York NY 10005",
    "addr:housenumber":"45",
    "addr:postcode":"10005",
    "addr:street":"Wall St",
    "iso:country":"US",
    "sg:address":"45 Wall St",
    "sg:city":"New York",
    "sg:classifiers":[
        {
            "category":"Banks & Credit Unions",
            "subcategory":"Financial Services",
            "type":"Services"
        }
    ],
    "sg:phone":"+1 212 425 5356",
    "sg:postcode":"10005",
    "sg:province":"NY",
    "sg:tags":[
        "international",
        "trade"
    ],
    "wof:name":"JSH Trading LLC",
    "wof:placetype":"venue"
},
  "geometry": {"coordinates":[-74.010262,40.706911],"type":"Point"}
}