{
  "type": "Feature",
  "properties": {
    "addr:full":"338 Nassau Rd Roosevelt NY 11575",
    "addr:housenumber":"338",
    "addr:postcode":"11575",
    "addr:street":"Nassau Rd",
    "iso:country":"US",
    "sg:address":"338 Nassau Rd",
    "sg:city":"Roosevelt",
    "sg:classifiers":[
        {
            "category":"Restaurant",
            "type":"Food & Drink"
        }
    ],
    "sg:phone":"+1 516 378 0843",
    "sg:postcode":"11575",
    "sg:province":"NY",
    "sg:tags":[
        "delicatessen"
    ],
    "wof:name":"J C Deli & Groceries",
    "wof:placetype":"venue"
},
  "geometry": {"coordinates":[-73.59079699999999,40.681],"type":"Point"}
}