{
  "type": "Feature",
  "properties": {
    "iso:country":"US",
    "sg:address":"102 Cortelyou Rd",
    "sg:city":"Brooklyn",
    "sg:classifiers":[
        {
            "category":"Manufacturing",
            "subcategory":"Retail Goods",
            "type":"Manufacturing & Wholesale Goods"
        }
    ],
    "sg:phone":"+1   ",
    "sg:postcode":"11218",
    "sg:province":"NY",
    "sg:tags":[
        "product",
        "mfg"
    ],
    "wof:name":"Borfel Manufacturing Corp",
    "wof:placetype":"venue"
},
  "geometry": {"coordinates":[-73.97735,40.63799],"type":"Point"}
}