{
  "type": "Feature",
  "properties": {
    "iso:country":"US",
    "sg:address":"214 Berkeley St",
    "sg:city":"Rochester",
    "sg:classifiers":[
        {
            "category":"Building & Trades",
            "subcategory":"Construction",
            "type":"Services"
        }
    ],
    "sg:phone":"+1 585 244 8507",
    "sg:postcode":"14607",
    "sg:province":"NY",
    "sg:tags":[
        "wallcoverings-installation",
        "wallpaper",
        "painting",
        "contractor"
    ],
    "wof:name":"Ultimate Painting",
    "wof:placetype":"venue"
},
  "geometry": {"coordinates":[-77.578789,43.146495],"type":"Point"}
}