{
  "type": "Feature",
  "properties": {
    "addr:full":"3111 Saunders Settlement Rd Sanborn NY 14132",
    "addr:housenumber":"3111",
    "addr:postcode":"14132",
    "addr:street":"Saunders Settlement Rd",
    "iso:country":"US",
    "sg:address":"3111 Saunders Settlement Rd",
    "sg:city":"Sanborn",
    "sg:classifiers":[
        {
            "category":"Education",
            "subcategory":"College",
            "type":"Public Place"
        }
    ],
    "sg:phone":"+1 716 434 3815",
    "sg:postcode":"14132",
    "sg:province":"NY",
    "sg:tags":[
        "academic",
        "school"
    ],
    "wof:name":"Small Business Development Ctr",
    "wof:placetype":"venue"
},
  "geometry": {"coordinates":[-78.874291,43.143228],"type":"Point"}
}