{
  "type": "Feature",
  "properties": {
    "iso:country":"US",
    "sg:address":"81 S Peru St",
    "sg:city":"Plattsburgh",
    "sg:classifiers":[
        {
            "category":"Building & Trades",
            "subcategory":"Construction",
            "type":"Services"
        },
        {
            "category":"Government",
            "subcategory":"Office",
            "type":"Public Place"
        }
    ],
    "sg:phone":"+1 518 563 2020",
    "sg:postcode":"12901",
    "sg:province":"NY",
    "sg:tags":[
        "state",
        "program"
    ],
    "sg:website":"www.dot.state.ny.us",
    "wof:name":"Transportation New York Dept",
    "wof:placetype":"venue"
},
  "geometry": {"coordinates":[-73.454891,44.680713],"type":"Point"}
}