{
  "type": "Feature",
  "properties": {
    "addr:full":"6167 Strickland Avenue Brooklyn NY 11234",
    "addr:housenumber":"6167",
    "addr:postcode":"11234",
    "addr:street":"Strickland Avenue",
    "iso:country":"US",
    "sg:address":"6167 Strickland Avenue",
    "sg:city":"Brooklyn",
    "sg:classifiers":[
        {
            "category":"Restaurant",
            "type":"Food & Drink"
        }
    ],
    "sg:phone":"+1 718 763 8091",
    "sg:postcode":"11234",
    "sg:province":"NY",
    "sg:tags":[
        "pizza"
    ],
    "wof:name":"Christina Pizza Place",
    "wof:placetype":"venue"
},
  "geometry": {"coordinates":[-73.912605,40.612484],"type":"Point"}
}