{
  "type": "Feature",
  "properties": {
    "addr:full":"630 Ridge Rd W Rochester NY 14420",
    "addr:housenumber":"630",
    "addr:postcode":"14420",
    "addr:street":"Ridge Rd W",
    "iso:country":"US",
    "sg:address":"630 Ridge Rd W",
    "sg:city":"Rochester",
    "sg:classifiers":[
        {
            "category":"Personal",
            "subcategory":"Beauty Salon",
            "type":"Services"
        }
    ],
    "sg:phone":"+1 585 254 2880",
    "sg:postcode":"14420",
    "sg:province":"NY",
    "wof:name":"Dennis Coccia Hair Salon",
    "wof:placetype":"venue"
},
  "geometry": {"coordinates":[-77.643079,43.202063],"type":"Point"}
}