{
  "type": "Feature",
  "properties": {
    "iso:country":"US",
    "sg:address":"8341 Merrill Dr",
    "sg:city":"Eden",
    "sg:classifiers":[
        {
            "category":"Professional",
            "type":"Services"
        }
    ],
    "sg:phone":"+1   ",
    "sg:postcode":"14057",
    "sg:province":"NY",
    "wof:name":"Buffalo Stamps & Stuff",
    "wof:placetype":"venue"
},
  "geometry": {"coordinates":[-78.87424900000001,42.660033],"type":"Point"}
}