{
  "type": "Feature",
  "properties": {
    "addr:full":"72 Spring St New York NY 10012",
    "addr:housenumber":"72",
    "addr:postcode":"10012",
    "addr:street":"Spring St",
    "iso:country":"US",
    "sg:address":"72 Spring St",
    "sg:city":"New York",
    "sg:classifiers":[
        {
            "category":"Arts & Performance",
            "subcategory":"Theater",
            "type":"Entertainment"
        }
    ],
    "sg:phone":"+1 212 625 9124",
    "sg:postcode":"10012",
    "sg:province":"NY",
    "sg:tags":[
        "bureau"
    ],
    "wof:name":"Digital Entertainment Network",
    "wof:placetype":"venue"
},
  "geometry": {"coordinates":[-73.99764500000001,40.722391],"type":"Point"}
}