{
  "type": "Feature",
  "properties": {
    "iso:country":"US",
    "sg:address":"100 Park St",
    "sg:city":"Glens Falls",
    "sg:classifiers":[
        {
            "category":"Health Services",
            "subcategory":"Doctor",
            "type":"Services"
        }
    ],
    "sg:phone":"+1 518 926 3841",
    "sg:postcode":"12801",
    "sg:province":"NY",
    "sg:tags":[
        "medical"
    ],
    "wof:name":"Lee Woong MD",
    "wof:placetype":"venue"
},
  "geometry": {"coordinates":[-73.646247,43.307183],"type":"Point"}
}