{
  "type": "Feature",
  "properties": {
    "iso:country":"US",
    "sg:address":"123 S Cayuga St",
    "sg:city":"Ithaca",
    "sg:classifiers":[
        {
            "category":"Government",
            "subcategory":"Office",
            "type":"Public Place"
        }
    ],
    "sg:phone":"+1 607 273 1388",
    "sg:postcode":"14850",
    "sg:province":"NY",
    "sg:tags":[
        "legislative",
        "body"
    ],
    "wof:name":"Congress",
    "wof:placetype":"venue"
},
  "geometry": {"coordinates":[-76.49893899999999,42.439335],"type":"Point"}
}