{
  "type": "Feature",
  "properties": {
    "addr:full":"495 S Broadway Yonkers NY 10705",
    "addr:housenumber":"495",
    "addr:postcode":"10705",
    "addr:street":"S Broadway",
    "iso:country":"US",
    "sg:address":"495 S Broadway",
    "sg:city":"Yonkers",
    "sg:classifiers":[
        {
            "category":"Place Of Worship",
            "subcategory":"Church",
            "type":"Public Place"
        },
        {
            "category":"Place Of Worship",
            "type":"Public Place"
        }
    ],
    "sg:phone":"+1 914 652 1453",
    "sg:postcode":"10705",
    "sg:province":"NY",
    "sg:tags":[
        "churches-interdenominational",
        "churches-various",
        "denomination"
    ],
    "wof:name":"United",
    "wof:placetype":"venue"
},
  "geometry": {"coordinates":[-73.896851,40.916149],"type":"Point"}
}