{
  "type": "Feature",
  "properties": {
    "addr:full":"65 Seaview Ave Northport NY 11768",
    "addr:housenumber":"65",
    "addr:postcode":"11768",
    "addr:street":"Seaview Ave",
    "iso:country":"US",
    "sg:address":"65 Seaview Ave",
    "sg:city":"Northport",
    "sg:classifiers":[
        {
            "category":"Insurance",
            "subcategory":"Insurance Agent",
            "type":"Services"
        }
    ],
    "sg:phone":"+1 631 754 7636",
    "sg:postcode":"11768",
    "sg:province":"NY",
    "wof:name":"James Ryan",
    "wof:placetype":"venue"
},
  "geometry": {"coordinates":[-73.34501899999999,40.897214],"type":"Point"}
}