{
  "type": "Feature",
  "properties": {
    "iso:country":"US",
    "sg:address":"207 W 16 St",
    "sg:city":"New York",
    "sg:classifiers":[
        {
            "category":"Health Services",
            "subcategory":"Doctor",
            "type":"Services"
        }
    ],
    "sg:phone":"+1 212 979 2020",
    "sg:postcode":"10011",
    "sg:province":"NY",
    "sg:tags":[
        "medical"
    ],
    "wof:name":"Curreri & Hornfeld",
    "wof:placetype":"venue"
},
  "geometry": {"coordinates":[-74.00138699999999,40.741072],"type":"Point"}
}