{
  "type": "Feature",
  "properties": {
    "addr:full":"30 South St Goshen NY 10924",
    "addr:housenumber":"30",
    "addr:postcode":"10924",
    "addr:street":"South St",
    "iso:country":"US",
    "sg:address":"30 South St",
    "sg:city":"Goshen",
    "sg:classifiers":[
        {
            "category":"Restaurant",
            "type":"Food & Drink"
        }
    ],
    "sg:phone":"+1   ",
    "sg:postcode":"10924",
    "sg:province":"NY",
    "sg:tags":[
        "eating"
    ],
    "wof:name":"Olivers of Goshen",
    "wof:placetype":"venue"
},
  "geometry": {"coordinates":[-74.320547,41.397512],"type":"Point"}
}