{
  "type": "Feature",
  "properties": {
    "addr:full":"112 Henry Rd Southampton NY 11968",
    "addr:housenumber":"112",
    "addr:postcode":"11968",
    "addr:street":"Henry Rd",
    "iso:country":"US",
    "sg:address":"112 Henry Rd",
    "sg:city":"Southampton",
    "sg:classifiers":[
        {
            "category":"Building & Trades",
            "subcategory":"Landscaping Services",
            "type":"Services"
        }
    ],
    "sg:phone":"+1 631 287 5617",
    "sg:postcode":"11968",
    "sg:province":"NY",
    "wof:name":"Foleys Lawn Care",
    "wof:placetype":"venue"
},
  "geometry": {"coordinates":[-72.40264500000001,40.90595],"type":"Point"}
}