{
  "type": "Feature",
  "properties": {
    "addr:full":"20889 Weaver Rd Watertown NY 13601",
    "addr:housenumber":"20889",
    "addr:postcode":"13601",
    "addr:street":"Weaver Rd",
    "iso:country":"US",
    "sg:address":"20889 Weaver Rd",
    "sg:city":"Watertown",
    "sg:classifiers":[
        {
            "category":"Professional",
            "subcategory":"Lawyer & Legal Services",
            "type":"Services"
        }
    ],
    "sg:phone":"+1 315 782 5650",
    "sg:postcode":"13601",
    "sg:province":"NY",
    "sg:tags":[
        "attorney"
    ],
    "wof:name":"Daniel S Dickinson III",
    "wof:placetype":"venue"
},
  "geometry": {"coordinates":[-75.865087,43.968332],"type":"Point"}
}