{
  "type": "Feature",
  "properties": {
    "addr:full":"21 Kendall Way Ballston Spa NY 12020",
    "addr:housenumber":"21",
    "addr:postcode":"12020",
    "addr:street":"Kendall Way",
    "iso:country":"US",
    "sg:address":"21 Kendall Way",
    "sg:city":"Ballston Spa",
    "sg:classifiers":[
        {
            "category":"Restaurant",
            "type":"Food & Drink"
        }
    ],
    "sg:phone":"+1 518 899 4855",
    "sg:postcode":"12020",
    "sg:province":"NY",
    "sg:tags":[
        "chinese"
    ],
    "wof:name":"Tasty Chinese Restaurant State",
    "wof:placetype":"venue"
},
  "geometry": {"coordinates":[-73.79312899999999,42.973378],"type":"Point"}
}