{
  "type": "Feature",
  "properties": {
    "addr:full":"693 Old Country Rd Dix Hills NY 11746",
    "addr:housenumber":"693",
    "addr:postcode":"11746",
    "addr:street":"Old Country Rd",
    "iso:country":"US",
    "sg:address":"693 Old Country Rd",
    "sg:city":"Dix Hills",
    "sg:classifiers":[
        {
            "category":"Insurance",
            "subcategory":"Insurance Agent",
            "type":"Services"
        }
    ],
    "sg:phone":"+1 631 425 9700",
    "sg:postcode":"11746",
    "sg:province":"NY",
    "wof:name":"Allstate Insurance Co",
    "wof:placetype":"venue"
},
  "geometry": {"coordinates":[-73.35819100000001,40.831972],"type":"Point"}
}