{
  "type": "Feature",
  "properties": {
    "addr:full":"2528 Broadway Astoria NY 11106",
    "addr:housenumber":"2528",
    "addr:postcode":"11106",
    "addr:street":"Broadway",
    "iso:country":"US",
    "sg:address":"2528 Broadway",
    "sg:city":"Astoria",
    "sg:classifiers":[
        {
            "category":"Professional",
            "subcategory":"Lawyer & Legal Services",
            "type":"Services"
        }
    ],
    "sg:phone":"+1 718 267 1717",
    "sg:postcode":"11106",
    "sg:province":"NY",
    "wof:name":"Murphy Michael S Atty",
    "wof:placetype":"venue"
},
  "geometry": {"coordinates":[-73.927803,40.763],"type":"Point"}
}