{
  "type": "Feature",
  "properties": {
    "iso:country":"US",
    "sg:address":"5748 S Park Ave",
    "sg:city":"Hamburg",
    "sg:classifiers":[
        {
            "category":"Restaurant",
            "type":"Food & Drink"
        }
    ],
    "sg:phone":"+1 716 649 9639",
    "sg:postcode":"14075",
    "sg:province":"NY",
    "sg:tags":[
        "eating"
    ],
    "wof:name":"Pegasus Family Restaurant Inc",
    "wof:placetype":"venue"
},
  "geometry": {"coordinates":[-78.825312,42.735117],"type":"Point"}
}