{
  "type": "Feature",
  "properties": {
    "addr:full":"450 Plandome Rd Ste 101 Manhasset NY 11030",
    "addr:housenumber":"450",
    "addr:postcode":"11030",
    "addr:street":"Plandome Rd Ste 101",
    "iso:country":"US",
    "sg:address":"450 Plandome Rd Ste 101",
    "sg:city":"Manhasset",
    "sg:classifiers":[
        {
            "category":"Sports & Exercise",
            "subcategory":"Gym",
            "type":"Entertainment"
        },
        {
            "category":"Health Services",
            "subcategory":"Health Practitioner",
            "type":"Services"
        }
    ],
    "sg:phone":"+1 516 684 3404",
    "sg:postcode":"11030",
    "sg:province":"NY",
    "sg:tags":[
        "trainer",
        "therapy",
        "physical"
    ],
    "sg:website":"www.fospt.com",
    "wof:name":"FAMILY ORTHOPAEDIC & SPORTS PHYSICAL THERAPY",
    "wof:placetype":"venue"
},
  "geometry": {"coordinates":[-73.699985,40.798885],"type":"Point"}
}