{
  "type": "Feature",
  "properties": {
    "addr:full":"230 5th Ave New York NY 10001",
    "addr:housenumber":"230",
    "addr:postcode":"10001",
    "addr:street":"5Th Ave",
    "iso:country":"US",
    "sg:address":"230 5th Ave",
    "sg:city":"New York",
    "sg:classifiers":[
        {
            "category":"Travel",
            "subcategory":"Hotels & Motels",
            "type":"Entertainment"
        },
        {
            "category":"Home & Garden",
            "subcategory":"Home Furnishings",
            "type":"Retail Goods"
        }
    ],
    "sg:phone":"+1 212 679 1703",
    "sg:postcode":"10001",
    "sg:province":"NY",
    "sg:tags":[
        "decor"
    ],
    "wof:name":"Niki International",
    "wof:placetype":"venue"
},
  "geometry": {"coordinates":[-73.98772099999999,40.744094],"type":"Point"}
}