{
  "type": "Feature",
  "properties": {
    "addr:full":"1078 Rte 112 Port Jefferson Station NY 11776",
    "addr:housenumber":"1078",
    "addr:postcode":"11776",
    "addr:street":"Rte 112",
    "iso:country":"US",
    "sg:address":"1078 Rte 112",
    "sg:city":"Port Jefferson Station",
    "sg:classifiers":[
        {
            "category":"Manufacturing",
            "subcategory":"Printing",
            "type":"Manufacturing & Wholesale Goods"
        }
    ],
    "sg:phone":"+1   ",
    "sg:postcode":"11776",
    "sg:province":"NY",
    "sg:tags":[
        "book"
    ],
    "wof:name":"YS Woman",
    "wof:placetype":"venue"
},
  "geometry": {"coordinates":[-73.04456399999999,40.922133],"type":"Point"}
}