{
  "type": "Feature",
  "properties": {
    "addr:full":"18 Pearl St Schuylerville NY 12871",
    "addr:housenumber":"18",
    "addr:postcode":"12871",
    "addr:street":"Pearl St",
    "iso:country":"US",
    "sg:address":"18 Pearl St",
    "sg:city":"Schuylerville",
    "sg:classifiers":[
        {
            "category":"Organizations",
            "subcategory":"Religious Organization",
            "type":"Services"
        }
    ],
    "sg:phone":"+1 518 695 3391",
    "sg:postcode":"12871",
    "sg:province":"NY",
    "sg:tags":[
        "clergy"
    ],
    "wof:name":"Notre Dame Visitation Church",
    "wof:placetype":"venue"
},
  "geometry": {"coordinates":[-73.585387,43.096224],"type":"Point"}
}