{
  "type": "Feature",
  "properties": {
    "iso:country":"US",
    "sg:address":"407 N Village Ave",
    "sg:city":"Rockville Centre",
    "sg:classifiers":[
        {
            "category":"Wholesale",
            "subcategory":"Machinery & Supplies",
            "type":"Manufacturing & Wholesale Goods"
        }
    ],
    "sg:phone":"+1 516 763 9369",
    "sg:postcode":"11570",
    "sg:province":"NY",
    "sg:tags":[
        "equipment"
    ],
    "wof:name":"Scordato Sales LTD",
    "wof:placetype":"venue"
},
  "geometry": {"coordinates":[-73.645377,40.668521],"type":"Point"}
}