{
  "type": "Feature",
  "properties": {
    "addr:full":"195 Ridge Rd Lackawanna NY 14218",
    "addr:housenumber":"195",
    "addr:postcode":"14218",
    "addr:street":"Ridge Rd",
    "iso:country":"US",
    "sg:address":"195 Ridge Rd",
    "sg:city":"Lackawanna",
    "sg:classifiers":[
        {
            "category":"Organizations",
            "subcategory":"Religious Organization",
            "type":"Services"
        }
    ],
    "sg:phone":"+1 716 826 8579",
    "sg:postcode":"14218",
    "sg:province":"NY",
    "sg:tags":[
        "church"
    ],
    "wof:name":"Ebenezer Baptist Church",
    "wof:placetype":"venue"
},
  "geometry": {"coordinates":[-78.84433,42.82713],"type":"Point"}
}