{
  "type": "Feature",
  "properties": {
    "addr:full":"133 Humboldt St Rochester NY 14610",
    "addr:housenumber":"133",
    "addr:postcode":"14610",
    "addr:street":"Humboldt St",
    "iso:country":"US",
    "sg:address":"133 Humboldt St",
    "sg:city":"Rochester",
    "sg:classifiers":[
        {
            "category":"Manufacturing",
            "subcategory":"Tools & Machinery",
            "type":"Manufacturing & Wholesale Goods"
        }
    ],
    "sg:phone":"+1   ",
    "sg:postcode":"14610",
    "sg:province":"NY",
    "sg:tags":[
        "mfg"
    ],
    "wof:name":"Die Max of Rochester",
    "wof:placetype":"venue"
},
  "geometry": {"coordinates":[-77.566405,43.155147],"type":"Point"}
}