{
  "type": "Feature",
  "properties": {
    "addr:full":"838 Myrtle Ave Brooklyn NY 11206",
    "addr:housenumber":"838",
    "addr:postcode":"11206",
    "addr:street":"Myrtle Ave",
    "iso:country":"US",
    "sg:address":"838 Myrtle Ave",
    "sg:city":"Brooklyn",
    "sg:classifiers":[
        {
            "category":"Building & Trades",
            "subcategory":"Construction",
            "type":"Services"
        }
    ],
    "sg:phone":"+1 718 388 4708",
    "sg:postcode":"11206",
    "sg:province":"NY",
    "sg:tags":[
        "contractor"
    ],
    "wof:name":"HLS Builders Corp",
    "wof:placetype":"venue"
},
  "geometry": {"coordinates":[-73.946681,40.69558],"type":"Point"}
}