{
  "type": "Feature",
  "properties": {
    "addr:full":"10082 Darien Rd Holland NY 14080",
    "addr:housenumber":"10082",
    "addr:postcode":"14080",
    "addr:street":"Darien Rd",
    "iso:country":"US",
    "sg:address":"10082 Darien Rd",
    "sg:city":"Holland",
    "sg:classifiers":[
        {
            "category":"Building & Trades",
            "subcategory":"Construction",
            "type":"Services"
        }
    ],
    "sg:phone":"+1 716 655 3496",
    "sg:postcode":"14080",
    "sg:province":"NY",
    "sg:tags":[
        "contractor"
    ],
    "wof:name":"M & M Masons",
    "wof:placetype":"venue"
},
  "geometry": {"coordinates":[-78.62111,42.684218],"type":"Point"}
}