{
  "type": "Feature",
  "properties": {
    "addr:full":"202 W 107th St New York NY 10025",
    "addr:housenumber":"202",
    "addr:postcode":"10025",
    "addr:street":"W 107Th St",
    "iso:country":"US",
    "sg:address":"202 W 107th St",
    "sg:city":"New York",
    "sg:classifiers":[
        {
            "category":"Communications",
            "subcategory":"Film & Video Production",
            "type":"Services"
        }
    ],
    "sg:phone":"+1 212 663 2266",
    "sg:postcode":"10025",
    "sg:province":"NY",
    "wof:name":"Character Studies Productions",
    "wof:placetype":"venue"
},
  "geometry": {"coordinates":[-73.967786,40.802112],"type":"Point"}
}