{
  "type": "Feature",
  "properties": {
    "iso:country":"US",
    "sg:address":"170 Clinton Ave",
    "sg:city":"Cortland",
    "sg:classifiers":[
        {
            "category":"Ice Cream",
            "type":"Food & Drink"
        }
    ],
    "sg:menulink":"http://www.allmenus.com/ny/cortland/98775-friendlys/menu/",
    "sg:phone":"+1 607 756 9805",
    "sg:postcode":"13045",
    "sg:province":"NY",
    "sg:tags":[
        "burger",
        "american"
    ],
    "wof:name":"Friendly's",
    "wof:placetype":"venue"
},
  "geometry": {"coordinates":[-76.170378,42.607938],"type":"Point"}
}