{
  "type": "Feature",
  "properties": {
    "iso:country":"US",
    "sg:address":"7 Dempsey Pl",
    "sg:city":"Eastchester",
    "sg:classifiers":[
        {
            "category":"Professional",
            "subcategory":"Lawyer & Legal Services",
            "type":"Services"
        }
    ],
    "sg:phone":"+1 914 787 1933",
    "sg:postcode":"10709",
    "sg:province":"NY",
    "sg:tags":[
        "attorney"
    ],
    "wof:name":"Christopher P Tiso Attorney",
    "wof:placetype":"venue"
},
  "geometry": {"coordinates":[-73.818872,40.948886],"type":"Point"}
}