{
  "type": "Feature",
  "properties": {
    "addr:full":"5 Appletree Ln Great Neck NY 11024",
    "addr:housenumber":"5",
    "addr:postcode":"11024",
    "addr:street":"Appletree Ln",
    "iso:country":"US",
    "sg:address":"5 Appletree Ln",
    "sg:city":"Great Neck",
    "sg:classifiers":[
        {
            "category":"Shopping",
            "subcategory":"Computers & Home Electronics",
            "type":"Retail Goods"
        }
    ],
    "sg:phone":"+1 516 829 3434",
    "sg:postcode":"11024",
    "sg:province":"NY",
    "sg:tags":[
        "software"
    ],
    "wof:name":"Integrated Computer Solutions",
    "wof:placetype":"venue"
},
  "geometry": {"coordinates":[-73.73439999999999,40.810339],"type":"Point"}
}