{
  "type": "Feature",
  "properties": {
    "iso:country":"US",
    "sg:address":"319 Ontario St",
    "sg:city":"Albany",
    "sg:classifiers":[
        {
            "category":"Wholesale",
            "subcategory":"Plants",
            "type":"Manufacturing & Wholesale Goods"
        }
    ],
    "sg:phone":"+1 518 458 2600",
    "sg:postcode":"12208",
    "sg:province":"NY",
    "sg:tags":[
        "florist"
    ],
    "wof:name":"Ramblin Rose Flowers & Gifts",
    "wof:placetype":"venue"
},
  "geometry": {"coordinates":[-73.782617,42.660036],"type":"Point"}
}