{
  "type": "Feature",
  "properties": {
    "addr:full":"567 Farmers Mills Rd Carmel NY 10512",
    "addr:housenumber":"567",
    "addr:postcode":"10512",
    "addr:street":"Farmers Mills Rd",
    "iso:country":"US",
    "sg:address":"567 Farmers Mills Rd",
    "sg:city":"Carmel",
    "sg:classifiers":[
        {
            "category":"Building & Trades",
            "subcategory":"Landscaping Services",
            "type":"Services"
        }
    ],
    "sg:phone":"+1 845 228 1175",
    "sg:postcode":"10512",
    "sg:province":"NY",
    "sg:tags":[
        "landscape",
        "contractor"
    ],
    "wof:name":"Bladderunner Landscape Inc",
    "wof:placetype":"venue"
},
  "geometry": {"coordinates":[-73.738298,41.495991],"type":"Point"}
}