{
  "type": "Feature",
  "properties": {
    "iso:country":"US",
    "sg:address":"213 W 21st St",
    "sg:city":"New York",
    "sg:classifiers":[
        {
            "category":"Professional",
            "subcategory":"Business Services",
            "type":"Services"
        }
    ],
    "sg:phone":"+1 212 675 0883",
    "sg:postcode":"10011",
    "sg:province":"NY",
    "sg:tags":[
        "designer",
        "fashion",
        "accessory"
    ],
    "wof:name":"Design Bureau Intl LLC",
    "wof:placetype":"venue"
},
  "geometry": {"coordinates":[-73.999122,40.743928],"type":"Point"}
}