{
  "type": "Feature",
  "properties": {
    "addr:full":"314 Trinacria Ct Schenectady NY 12303",
    "addr:housenumber":"314",
    "addr:postcode":"12303",
    "addr:street":"Trinacria Ct",
    "iso:country":"US",
    "sg:address":"314 Trinacria Ct",
    "sg:city":"Schenectady",
    "sg:classifiers":[
        {
            "category":"Building & Trades",
            "subcategory":"Construction",
            "type":"Services"
        }
    ],
    "sg:phone":"+1 518 355 5914",
    "sg:postcode":"12303",
    "sg:province":"NY",
    "sg:tags":[
        "house"
    ],
    "wof:name":"John B Tralongo Builders Inc",
    "wof:placetype":"venue"
},
  "geometry": {"coordinates":[-73.929947,42.739504],"type":"Point"}
}