{
  "type": "Feature",
  "properties": {
    "addr:full":"1 N Central Ave Hartsdale NY 10530",
    "addr:housenumber":"1",
    "addr:postcode":"10530",
    "addr:street":"N Central Ave",
    "iso:country":"US",
    "sg:address":"1 N Central Ave",
    "sg:city":"Hartsdale",
    "sg:classifiers":[
        {
            "category":"Shopping",
            "subcategory":"Pharmacy",
            "type":"Retail Goods"
        }
    ],
    "sg:phone":"+1   ",
    "sg:postcode":"10530",
    "sg:province":"NY",
    "sg:tags":[
        "drug",
        "store"
    ],
    "wof:name":"Duane Reade 274",
    "wof:placetype":"venue"
},
  "geometry": {"coordinates":[-73.796279,41.021009],"type":"Point"}
}