{
  "type": "Feature",
  "properties": {
    "addr:full":"50 Ave A New York NY 10009",
    "addr:postcode":"10009",
    "addr:street":"50 Ave A",
    "iso:country":"US",
    "sg:address":"50 Ave A",
    "sg:city":"New York",
    "sg:classifiers":[
        {
            "category":"Coffee & Tea",
            "type":"Food & Drink"
        }
    ],
    "sg:phone":"+1 212 228 8110",
    "sg:postcode":"10009",
    "sg:province":"NY",
    "wof:name":"Native Bean",
    "wof:placetype":"venue"
},
  "geometry": {"coordinates":[-73.984864,40.723804],"type":"Point"}
}