{
  "type": "Feature",
  "properties": {
    "addr:full":"9000 Shore Road Brooklyn NY 11209",
    "addr:housenumber":"9000",
    "addr:postcode":"11209",
    "addr:street":"Shore Road",
    "iso:country":"US",
    "sg:address":"9000 Shore Road",
    "sg:city":"Brooklyn",
    "sg:classifiers":[
        {
            "category":"Health Services",
            "subcategory":"Dentist",
            "type":"Services"
        }
    ],
    "sg:phone":"+1 718 836 8988",
    "sg:postcode":"11209",
    "sg:province":"NY",
    "wof:name":"Shore Road Medical Associate",
    "wof:placetype":"venue"
},
  "geometry": {"coordinates":[-74.04033200000001,40.622555],"type":"Point"}
}