{
  "type": "Feature",
  "properties": {
    "addr:full":"1039 Southern Blvd Bronx NY 10459",
    "addr:housenumber":"1039",
    "addr:postcode":"10459",
    "addr:street":"Southern Blvd",
    "iso:country":"US",
    "sg:address":"1039 Southern Blvd",
    "sg:city":"Bronx",
    "sg:classifiers":[
        {
            "category":"Home & Garden",
            "subcategory":"Household Appliances",
            "type":"Retail Goods"
        }
    ],
    "sg:phone":"+1 718 328 8970",
    "sg:postcode":"10459",
    "sg:province":"NY",
    "sg:tags":[
        "machine",
        "sewing"
    ],
    "wof:name":"Fabric Save A Thon",
    "wof:placetype":"venue"
},
  "geometry": {"coordinates":[-73.891931,40.823541],"type":"Point"}
}