{
  "type": "Feature",
  "properties": {
    "iso:country":"US",
    "sg:address":"135 Dogwood Ave",
    "sg:city":"Roslyn",
    "sg:classifiers":[
        {
            "category":"Building & Trades",
            "subcategory":"Construction",
            "type":"Services"
        }
    ],
    "sg:phone":"+1 516 484 4278",
    "sg:postcode":"11576",
    "sg:province":"NY",
    "sg:tags":[
        "residential"
    ],
    "wof:name":"Baam Inc",
    "wof:placetype":"venue"
},
  "geometry": {"coordinates":[-73.633723,40.811032],"type":"Point"}
}