{
  "type": "Feature",
  "properties": {
    "addr:full":"6 Dows Ln Irvington NY 10533",
    "addr:housenumber":"6",
    "addr:postcode":"ny 10533",
    "addr:street":"Dows Ln",
    "iso:country":"US",
    "sg:address":"6 Dows Ln",
    "sg:city":"Irvington",
    "sg:classifiers":[
        {
            "category":"Education",
            "subcategory":"School",
            "type":"Public Place"
        }
    ],
    "sg:phone":"+1 914 591 1961",
    "sg:postcode":"10533",
    "sg:province":"NY",
    "sg:website":"www.irvingtonschools.org",
    "wof:name":"Dows Lane Elementary School",
    "wof:placetype":"venue"
},
  "geometry": {"coordinates":[-73.869636,41.033218],"type":"Point"}
}