{
  "type": "Feature",
  "properties": {
    "addr:full":"129 Ellsworth Ave Harrison NY 10528",
    "addr:housenumber":"129",
    "addr:postcode":"10528",
    "addr:street":"Ellsworth Ave",
    "iso:country":"US",
    "sg:address":"129 Ellsworth Ave",
    "sg:city":"Harrison",
    "sg:classifiers":[
        {
            "category":"Building & Trades",
            "subcategory":"Landscaping Services",
            "type":"Services"
        }
    ],
    "sg:phone":"+1 914 835 5733",
    "sg:postcode":"10528",
    "sg:province":"NY",
    "wof:name":"Navarra Peter A Jr Ldscpg Co",
    "wof:placetype":"venue"
},
  "geometry": {"coordinates":[-73.718197,40.974866],"type":"Point"}
}