{
  "type": "Feature",
  "properties": {
    "addr:full":"1638 McVean Rd Caledonia NY 14423",
    "addr:housenumber":"1638",
    "addr:postcode":"14423",
    "addr:street":"Mcvean Rd",
    "iso:country":"US",
    "sg:address":"1638 McVean Rd",
    "sg:city":"Caledonia",
    "sg:classifiers":[
        {
            "category":"Farming",
            "subcategory":"Dairy Farm",
            "type":"Manufacturing & Wholesale Goods"
        }
    ],
    "sg:phone":"+1 585 226 3696",
    "sg:postcode":"14423",
    "sg:province":"NY",
    "wof:name":"William C Korth",
    "wof:placetype":"venue"
},
  "geometry": {"coordinates":[-77.81922900000001,42.9116],"type":"Point"}
}