{
  "type": "Feature",
  "properties": {
    "iso:country":"US",
    "sg:address":"168 Madison Ave",
    "sg:city":"New York",
    "sg:classifiers":[
        {
            "category":"Professional",
            "subcategory":"Employment Agencies",
            "type":"Services"
        }
    ],
    "sg:phone":"+1 212 213 1925",
    "sg:postcode":"10016",
    "sg:province":"NY",
    "sg:tags":[
        "opportunity"
    ],
    "wof:name":"New Horizon Employment Svc",
    "wof:placetype":"venue"
},
  "geometry": {"coordinates":[-73.983814,40.746582],"type":"Point"}
}