{
  "type": "Feature",
  "properties": {
    "addr:full":"346 Oliver St North Tonawanda NY 14120",
    "addr:housenumber":"346",
    "addr:postcode":"14120",
    "addr:street":"Oliver St",
    "iso:country":"US",
    "sg:address":"346 Oliver St",
    "sg:city":"North Tonawanda",
    "sg:classifiers":[
        {
            "category":"Building & Trades",
            "subcategory":"Construction",
            "type":"Services"
        }
    ],
    "sg:phone":"+1 716 693 9500",
    "sg:postcode":"14120",
    "sg:province":"NY",
    "sg:tags":[
        "painter"
    ],
    "wof:name":"Alba Painting & Decorating Co",
    "wof:placetype":"venue"
},
  "geometry": {"coordinates":[-78.876159,43.03111],"type":"Point"}
}