{
  "type": "Feature",
  "properties": {
    "iso:country":"US",
    "sg:address":"230 N Broad St",
    "sg:city":"Oneida",
    "sg:classifiers":[
        {
            "category":"Building & Trades",
            "subcategory":"Electrical",
            "type":"Services"
        }
    ],
    "sg:phone":"+1 315 366 3431",
    "sg:postcode":"13421",
    "sg:province":"NY",
    "sg:tags":[
        "electric",
        "contractor"
    ],
    "wof:name":"Madonia Electric",
    "wof:placetype":"venue"
},
  "geometry": {"coordinates":[-75.657082,43.09865],"type":"Point"}
}