{
  "type": "Feature",
  "properties": {
    "iso:country":"US",
    "sg:address":"8778 Bay Pkwy",
    "sg:city":"Brooklyn",
    "sg:classifiers":[
        {
            "category":"Health Services",
            "subcategory":"Doctor",
            "type":"Services"
        }
    ],
    "sg:phone":"+1 718 333 1394",
    "sg:postcode":"11214",
    "sg:province":"NY",
    "sg:website":"www.medbillny.com",
    "wof:name":"Pier 17 Professional Medical Management",
    "wof:placetype":"venue"
},
  "geometry": {"coordinates":[-73.997647,40.598283],"type":"Point"}
}