{
  "type": "Feature",
  "properties": {
    "addr:full":"4188 Lake Shore Rd Hamburg NY 14075",
    "addr:housenumber":"4188",
    "addr:postcode":"14075",
    "addr:street":"Lake Shore Rd",
    "iso:country":"US",
    "sg:address":"4188 Lake Shore Rd",
    "sg:city":"Hamburg",
    "sg:classifiers":[
        {
            "category":"Retail",
            "subcategory":"Portrait Studio",
            "type":"Services"
        }
    ],
    "sg:phone":"+1 716 627 7065",
    "sg:postcode":"14075",
    "sg:province":"NY",
    "sg:tags":[
        "photographer"
    ],
    "wof:name":"Territo Photography",
    "wof:placetype":"venue"
},
  "geometry": {"coordinates":[-78.865736,42.771325],"type":"Point"}
}