{
  "type": "Feature",
  "properties": {
    "addr:full":"2272 Webster Ave Bronx NY 10457",
    "addr:housenumber":"2272",
    "addr:postcode":"10457",
    "addr:street":"Webster Ave",
    "iso:country":"US",
    "sg:address":"2272 Webster Ave",
    "sg:city":"Bronx",
    "sg:classifiers":[
        {
            "category":"Personal",
            "subcategory":"Beauty Salon",
            "type":"Services"
        }
    ],
    "sg:phone":"+1 718 295 1132",
    "sg:postcode":"10457",
    "sg:province":"NY",
    "wof:name":"Ledi Unisex Salon",
    "wof:placetype":"venue"
},
  "geometry": {"coordinates":[-73.89569299999999,40.855852],"type":"Point"}
}