{
  "type": "Feature",
  "properties": {
    "addr:full":"1704 Old Country Rd Riverhead NY 11901",
    "addr:housenumber":"1704",
    "addr:postcode":"11901",
    "addr:street":"Old Country Rd",
    "iso:country":"US",
    "sg:address":"1704 Old Country Rd",
    "sg:city":"Riverhead",
    "sg:classifiers":[
        {
            "category":"Home & Garden",
            "subcategory":"Building Materials",
            "type":"Retail Goods"
        }
    ],
    "sg:phone":"+1 631 727 1616",
    "sg:postcode":"11901",
    "sg:province":"NY",
    "sg:tags":[
        "paint",
        "floor",
        "covering"
    ],
    "wof:name":"Sherwin-Williams Paints",
    "wof:placetype":"venue"
},
  "geometry": {"coordinates":[-72.685445,40.928166],"type":"Point"}
}