{
  "type": "Feature",
  "properties": {
    "addr:full":"2211 5th Ave Ste B Ronkonkoma NY 11779",
    "addr:housenumber":"2211",
    "addr:postcode":"11779",
    "addr:street":"5Th Ave Ste B",
    "iso:country":"US",
    "sg:address":"2211 5th Ave Ste B",
    "sg:city":"Ronkonkoma",
    "sg:classifiers":[
        {
            "category":"Shopping",
            "subcategory":"Antiques",
            "type":"Retail Goods"
        }
    ],
    "sg:phone":"+1 631 676 2198",
    "sg:postcode":"11779",
    "sg:province":"NY",
    "wof:name":"DPO Antique Furniture",
    "wof:placetype":"venue"
},
  "geometry": {"coordinates":[-73.13888900000001,40.796813],"type":"Point"}
}