{
  "type": "Feature",
  "properties": {
    "addr:full":"42030 State Hwy 10 Delhi NY 13753",
    "addr:housenumber":"42030",
    "addr:postcode":"13753",
    "addr:street":"State Hwy 10",
    "iso:country":"US",
    "sg:address":"42030 State Hwy 10",
    "sg:city":"Delhi",
    "sg:classifiers":[
        {
            "category":"Shopping",
            "subcategory":"Used Merchandise",
            "type":"Retail Goods"
        }
    ],
    "sg:phone":"+1 607 746 7644",
    "sg:postcode":"13753",
    "sg:province":"NY",
    "sg:tags":[
        "antique"
    ],
    "wof:name":"Horsefeathers Antiques",
    "wof:placetype":"venue"
},
  "geometry": {"coordinates":[-74.955388,42.257886],"type":"Point"}
}