{
  "type": "Feature",
  "properties": {
    "iso:country":"US",
    "sg:address":"100 Harbor Rd",
    "sg:city":"Port Washington",
    "sg:classifiers":[
        {
            "category":"Recreation",
            "type":"Entertainment"
        }
    ],
    "sg:phone":"+1 516 883 6425",
    "sg:postcode":"11050",
    "sg:province":"NY",
    "sg:tags":[
        "academy",
        "tennis",
        "instruction"
    ],
    "sg:website":"www.pwta.com",
    "wof:name":"Port Washington Tennis Academy",
    "wof:placetype":"venue"
},
  "geometry": {"coordinates":[-73.697424,40.839141],"type":"Point"}
}