{
  "type": "Feature",
  "properties": {
    "addr:full":"724 Delaware Ave Buffalo NY 14209",
    "addr:housenumber":"724",
    "addr:postcode":"14209",
    "addr:street":"Delaware Ave",
    "iso:country":"US",
    "sg:address":"724 Delaware Ave",
    "sg:city":"Buffalo",
    "sg:classifiers":[
        {
            "category":"Social Services",
            "subcategory":"Child Care",
            "type":"Services"
        }
    ],
    "sg:phone":"+1 716 884 9438",
    "sg:postcode":"14209",
    "sg:province":"NY",
    "sg:tags":[
        "day"
    ],
    "wof:name":"Westminster Early Childhood Programs",
    "wof:placetype":"venue"
},
  "geometry": {"coordinates":[-78.86930099999999,42.912701],"type":"Point"}
}