{
  "type": "Feature",
  "properties": {
    "addr:full":"2728 Henry Hudson Pkwy E Bronx NY 10463",
    "addr:housenumber":"2728",
    "addr:postcode":"10463",
    "addr:street":"Henry Hudson Pkwy E",
    "iso:country":"US",
    "sg:address":"2728 Henry Hudson Pkwy E",
    "sg:city":"Bronx",
    "sg:classifiers":[
        {
            "category":"Shopping",
            "type":"Retail Goods"
        }
    ],
    "sg:phone":"+1 718 781 5542",
    "sg:postcode":"10463",
    "sg:province":"NY",
    "sg:tags":[
        "art",
        "gallery",
        "dealer"
    ],
    "wof:name":"D'Lugoff Art & Avital",
    "wof:placetype":"venue"
},
  "geometry": {"coordinates":[-73.91581600000001,40.882311],"type":"Point"}
}