{
  "type": "Feature",
  "properties": {
    "iso:country":"US",
    "sg:address":"672 Delaware Ave",
    "sg:city":"Buffalo",
    "sg:classifiers":[
        {
            "category":"Education",
            "subcategory":"College",
            "type":"Public Place"
        }
    ],
    "sg:phone":"+1   ",
    "sg:postcode":"14209",
    "sg:province":"NY",
    "wof:name":"Ub Center For Entrepreneurial",
    "wof:placetype":"venue"
},
  "geometry": {"coordinates":[-78.872383,42.904373],"type":"Point"}
}