{
  "type": "Feature",
  "properties": {
    "addr:full":"764 W End Avenue New York NY 10025",
    "addr:housenumber":"764",
    "addr:postcode":"10025",
    "addr:street":"W End Avenue",
    "iso:country":"US",
    "sg:address":"764 W End Avenue",
    "sg:city":"New York",
    "sg:classifiers":[
        {
            "category":"Building & Trades",
            "subcategory":"Construction",
            "type":"Services"
        }
    ],
    "sg:phone":"+1 212 330 6820",
    "sg:postcode":"10025",
    "sg:province":"NY",
    "sg:tags":[
        "contractor"
    ],
    "wof:name":"Gallagher & Quots Contracting",
    "wof:placetype":"venue"
},
  "geometry": {"coordinates":[-73.972414,40.796084],"type":"Point"}
}