{
  "type": "Feature",
  "properties": {
    "iso:country":"US",
    "sg:address":"6705 Woodside Ave",
    "sg:city":"Woodside",
    "sg:classifiers":[
        {
            "category":"Food & Beverages",
            "subcategory":"Groceries & Convenience Stores",
            "type":"Retail Goods"
        }
    ],
    "sg:phone":"+1 718 779 8883",
    "sg:postcode":"11377",
    "sg:province":"NY",
    "wof:name":"New Age Asia Market",
    "wof:placetype":"venue"
},
  "geometry": {"coordinates":[-73.897263,40.743204],"type":"Point"}
}