{
  "type": "Feature",
  "properties": {
    "addr:full":"344 Ave P Brooklyn NY 11204",
    "addr:housenumber":"344",
    "addr:postcode":"11204",
    "addr:street":"Ave P",
    "iso:country":"US",
    "sg:address":"344 Ave P",
    "sg:city":"Brooklyn",
    "sg:classifiers":[
        {
            "category":"Health Services",
            "subcategory":"Doctor",
            "type":"Services"
        }
    ],
    "sg:phone":"+1   ",
    "sg:postcode":"11204",
    "sg:province":"NY",
    "wof:name":"Jeffrey Burns DDS",
    "wof:placetype":"venue"
},
  "geometry": {"coordinates":[-73.97591799999999,40.608495],"type":"Point"}
}