{
  "type": "Feature",
  "properties": {
    "addr:full":"4110 New Court Ave Syracuse NY 13206",
    "addr:housenumber":"4110",
    "addr:postcode":"13206",
    "addr:street":"New Court Ave",
    "iso:country":"US",
    "sg:address":"4110 New Court Ave",
    "sg:city":"Syracuse",
    "sg:classifiers":[
        {
            "category":"Organizations",
            "subcategory":"Labor Organization",
            "type":"Services"
        }
    ],
    "sg:phone":"+1 315 463 0774",
    "sg:postcode":"13206",
    "sg:province":"NY",
    "wof:name":"Local 527",
    "wof:placetype":"venue"
},
  "geometry": {"coordinates":[-76.10602,43.076806],"type":"Point"}
}