{
  "type": "Feature",
  "properties": {
    "iso:country":"US",
    "sg:address":"70 Winthrop Pl",
    "sg:city":"Staten Island",
    "sg:classifiers":[
        {
            "category":"Organizations",
            "subcategory":"Religious Organization",
            "type":"Services"
        }
    ],
    "sg:phone":"+1   ",
    "sg:postcode":"10314",
    "sg:province":"NY",
    "wof:name":"Faith Community Church Intl",
    "wof:placetype":"venue"
},
  "geometry": {"coordinates":[-74.121331,40.612123],"type":"Point"}
}