{
  "type": "Feature",
  "properties": {
    "addr:full":"18 Peconic Ave Medford NY 11763",
    "addr:housenumber":"18",
    "addr:postcode":"11763",
    "addr:street":"Peconic Ave",
    "iso:country":"US",
    "sg:address":"18 Peconic Ave",
    "sg:city":"Medford",
    "sg:classifiers":[
        {
            "category":"Wholesale",
            "subcategory":"Auto Parts",
            "type":"Manufacturing & Wholesale Goods"
        }
    ],
    "sg:phone":"+1 631 447 9558",
    "sg:postcode":"11763",
    "sg:province":"NY",
    "sg:tags":[
        "automotive"
    ],
    "wof:name":"LI Proliner Customs",
    "wof:placetype":"venue"
},
  "geometry": {"coordinates":[-72.96876,40.817665],"type":"Point"}
}