{
  "type": "Feature",
  "properties": {
    "addr:full":"207 Islip Ave Islip NY 11751",
    "addr:housenumber":"207",
    "addr:postcode":"11751",
    "addr:street":"Islip Ave",
    "iso:country":"US",
    "sg:address":"207 Islip Ave",
    "sg:city":"Islip",
    "sg:classifiers":[
        {
            "category":"Food & Beverages",
            "subcategory":"Liquor & Beverages",
            "type":"Retail Goods"
        }
    ],
    "sg:phone":"+1 631 581 1680",
    "sg:postcode":"11751",
    "sg:province":"NY",
    "wof:name":"Wine & Liquor Depot",
    "wof:placetype":"venue"
},
  "geometry": {"coordinates":[-73.20774299999999,40.737261],"type":"Point"}
}