{
  "type": "Feature",
  "properties": {
    "iso:country":"US",
    "sg:address":"2190 Mount Read Blvd",
    "sg:city":"Rochester",
    "sg:classifiers":[
        {
            "category":"Manufacturing",
            "subcategory":"Paper Products",
            "type":"Manufacturing & Wholesale Goods"
        }
    ],
    "sg:phone":"+1 585 254 9190",
    "sg:postcode":"14606",
    "sg:province":"NY",
    "sg:tags":[
        "packaging",
        "material"
    ],
    "wof:name":"Jamestown Container Rochester",
    "wof:placetype":"venue"
},
  "geometry": {"coordinates":[-77.659476,43.191538],"type":"Point"}
}