{
  "type": "Feature",
  "properties": {
    "addr:full":"220 Ferris Ave White Plains NY 10603",
    "addr:housenumber":"220",
    "addr:postcode":"10603",
    "addr:street":"Ferris Ave",
    "iso:country":"US",
    "sg:address":"220 Ferris Ave",
    "sg:city":"White Plains",
    "sg:classifiers":[
        {
            "category":"Retail",
            "subcategory":"Animal Services",
            "type":"Services"
        }
    ],
    "sg:phone":"+1 914 946 0308",
    "sg:postcode":"10603",
    "sg:province":"NY",
    "sg:tags":[
        "pet",
        "training"
    ],
    "wof:name":"Port Chester Obedience Train",
    "wof:placetype":"venue"
},
  "geometry": {"coordinates":[-73.774078,41.044197],"type":"Point"}
}