{
  "type": "Feature",
  "properties": {
    "addr:full":"32 Almar Ln Katonah NY 10536",
    "addr:housenumber":"32",
    "addr:postcode":"10536",
    "addr:street":"Almar Ln",
    "iso:country":"US",
    "sg:address":"32 Almar Ln",
    "sg:city":"Katonah",
    "sg:classifiers":[
        {
            "category":"Banks & Credit Unions",
            "subcategory":"Financial Services",
            "type":"Services"
        }
    ],
    "sg:phone":"+1 914 232 0854",
    "sg:postcode":"10536",
    "sg:province":"NY",
    "sg:tags":[
        "investor"
    ],
    "wof:name":"S & R Properties",
    "wof:placetype":"venue"
},
  "geometry": {"coordinates":[-73.675224,41.268318],"type":"Point"}
}