{
  "type": "Feature",
  "properties": {
    "addr:full":"636 Baldwin Ave North Baldwin NY 11510",
    "addr:housenumber":"636",
    "addr:postcode":"11510",
    "addr:street":"Baldwin Ave North",
    "iso:country":"US",
    "sg:address":"636 Baldwin Ave",
    "sg:city":"North Baldwin",
    "sg:classifiers":[
        {
            "category":"Shopping",
            "subcategory":"News",
            "type":"Retail Goods"
        }
    ],
    "sg:phone":"+1 516 623 4567",
    "sg:postcode":"11510",
    "sg:province":"NY",
    "sg:tags":[
        "dealer"
    ],
    "wof:name":"Noticia Hispanoamericana",
    "wof:placetype":"venue"
},
  "geometry": {"coordinates":[-73.613416,40.65909],"type":"Point"}
}