{
  "type": "Feature",
  "properties": {
    "addr:full":"11 Newton Pl Hauppauge NY 11788",
    "addr:housenumber":"11",
    "addr:postcode":"11788",
    "addr:street":"Newton Pl",
    "iso:country":"US",
    "sg:address":"11 Newton Pl",
    "sg:city":"Hauppauge",
    "sg:classifiers":[
        {
            "category":"Manufacturing",
            "subcategory":"Toys & Sporting Goods",
            "type":"Manufacturing & Wholesale Goods"
        }
    ],
    "sg:phone":"+1 631 582 3535",
    "sg:postcode":"11788",
    "sg:province":"NY",
    "sg:tags":[
        "equipment",
        "swimming",
        "pool",
        "supply"
    ],
    "wof:name":"Baystate Pool Supplies Inc",
    "wof:placetype":"venue"
},
  "geometry": {"coordinates":[-73.22574899999999,40.805197],"type":"Point"}
}