{
  "type": "Feature",
  "properties": {
    "addr:full":"303 Park Ave S New York NY 10010",
    "addr:housenumber":"303",
    "addr:postcode":"10010",
    "addr:street":"Park Ave S",
    "iso:country":"US",
    "sg:address":"303 Park Ave S",
    "sg:city":"New York",
    "sg:classifiers":[
        {
            "category":"Professional",
            "type":"Services"
        },
        {
            "category":"Deli",
            "type":"Food & Drink"
        },
        {
            "category":"Food & Beverages",
            "subcategory":"Bakery",
            "type":"Retail Goods"
        }
    ],
    "sg:phone":"+1 212 353 0862",
    "sg:postcode":"10010",
    "sg:province":"NY",
    "sg:tags":[
        "sandwich",
        "caterer"
    ],
    "sg:website":"www.paxfood.com",
    "wof:name":"Pax Wholesome Foods",
    "wof:placetype":"venue"
},
  "geometry": {"coordinates":[-73.986197,40.740287],"type":"Point"}
}