{
  "type": "Feature",
  "properties": {
    "addr:full":"84 Bowery New York NY 10013",
    "addr:housenumber":"84",
    "addr:postcode":"10013",
    "addr:street":"Bowery",
    "iso:country":"US",
    "sg:address":"84 Bowery",
    "sg:city":"New York",
    "sg:classifiers":[
        {
            "category":"Wholesale",
            "subcategory":"Jewelry",
            "type":"Manufacturing & Wholesale Goods"
        }
    ],
    "sg:phone":"+1 212 941 7655",
    "sg:postcode":"10013",
    "sg:province":"NY",
    "sg:tags":[
        "stone"
    ],
    "wof:name":"Star Findings",
    "wof:placetype":"venue"
},
  "geometry": {"coordinates":[-73.995914,40.716394],"type":"Point"}
}