{
  "type": "Feature",
  "properties": {
    "iso:country":"US",
    "sg:address":"4343 45th St",
    "sg:city":"Sunnyside",
    "sg:classifiers":[
        {
            "category":"Health Services",
            "subcategory":"Dentist",
            "type":"Services"
        }
    ],
    "sg:phone":"+1 718 786 0071",
    "sg:postcode":"11104",
    "sg:province":"NY",
    "wof:name":"Bedoya Dental Lab",
    "wof:placetype":"venue"
},
  "geometry": {"coordinates":[-73.919197,40.744598],"type":"Point"}
}