{
  "type": "Feature",
  "properties": {
    "addr:full":"44 South Broadway 2nd Floor White Plains NY 10601",
    "addr:housenumber":"44;2nd floor",
    "addr:postcode":"10601",
    "addr:street":"South Broadway",
    "iso:country":"US",
    "sg:address":"44 South Broadway 2nd Floor",
    "sg:city":"White Plains",
    "sg:classifiers":[
        {
            "category":"Professional",
            "subcategory":"Computer Services",
            "type":"Services"
        }
    ],
    "sg:phone":"+1 914 227 9107",
    "sg:postcode":"10601",
    "sg:province":"NY",
    "sg:tags":[
        "inflight-entertainment-systems",
        "embedded-systems",
        "rich-internet-applications"
    ],
    "sg:website":"http://cokinetic.com",
    "wof:name":"CoKinetic Systems Corp",
    "wof:placetype":"venue"
},
  "geometry": {"coordinates":[-73.76234700000001,41.030614],"type":"Point"}
}