{
  "type": "Feature",
  "properties": {
    "iso:country":"US",
    "sg:address":"11328 N Collins Rd",
    "sg:city":"North Collins",
    "sg:classifiers":[
        {
            "category":"Building & Trades",
            "subcategory":"Construction",
            "type":"Services"
        }
    ],
    "sg:phone":"+1 716 337 2400",
    "sg:postcode":"14111",
    "sg:province":"NY",
    "sg:tags":[
        "excavation",
        "contractor"
    ],
    "wof:name":"Charles J Alessi",
    "wof:placetype":"venue"
},
  "geometry": {"coordinates":[-78.938019,42.573864],"type":"Point"}
}