{
  "type": "Feature",
  "properties": {
    "addr:full":"13 Elizabeth St New York NY 10013",
    "addr:housenumber":"13",
    "addr:postcode":"10013",
    "addr:street":"Elizabeth St",
    "iso:country":"US",
    "sg:address":"13 Elizabeth St",
    "sg:city":"New York",
    "sg:classifiers":[
        {
            "category":"Health Services",
            "subcategory":"Doctor",
            "type":"Services"
        }
    ],
    "sg:phone":"+1 212 334 3999",
    "sg:postcode":"10013",
    "sg:province":"NY",
    "wof:name":"Chan Alexander C MD",
    "wof:placetype":"venue"
},
  "geometry": {"coordinates":[-73.997587,40.715859],"type":"Point"}
}