{
  "type": "Feature",
  "properties": {
    "iso:country":"US",
    "sg:address":"3210 137th St",
    "sg:city":"Flushing",
    "sg:classifiers":[
        {
            "category":"Retail",
            "subcategory":"Auto Repair",
            "type":"Services"
        }
    ],
    "sg:phone":"+1 718 762 0068",
    "sg:postcode":"11354",
    "sg:province":"NY",
    "wof:name":"Brothers Complete Auto Repair",
    "wof:placetype":"venue"
},
  "geometry": {"coordinates":[-73.830803,40.767601],"type":"Point"}
}