{
  "type": "Feature",
  "properties": {
    "iso:country":"US",
    "sg:address":"58 Pershing Ave",
    "sg:city":"Poughkeepsie",
    "sg:classifiers":[
        {
            "category":"Wholesale",
            "subcategory":"Vending Machines",
            "type":"Manufacturing & Wholesale Goods"
        }
    ],
    "sg:phone":"+1   ",
    "sg:postcode":"12601",
    "sg:province":"NY",
    "sg:tags":[
        "operator"
    ],
    "wof:name":"Paramount Amusement",
    "wof:placetype":"venue"
},
  "geometry": {"coordinates":[-73.913191,41.702307],"type":"Point"}
}