{
  "type": "Feature",
  "properties": {
    "addr:full":"3770 Carman Rd Schenectady NY 12303",
    "addr:housenumber":"3770",
    "addr:postcode":"12303",
    "addr:street":"Carman Rd",
    "iso:country":"US",
    "sg:address":"3770 Carman Rd",
    "sg:city":"Schenectady",
    "sg:classifiers":[
        {
            "category":"Social Services",
            "subcategory":"Child Care",
            "type":"Services"
        }
    ],
    "sg:phone":"+1 518 688 0895",
    "sg:postcode":"12303",
    "sg:province":"NY",
    "wof:name":"Kidz Korner",
    "wof:placetype":"venue"
},
  "geometry": {"coordinates":[-73.93639,42.724538],"type":"Point"}
}