{
  "type": "Feature",
  "properties": {
    "addr:full":"72-15 Kissena Blvd Flushing NY 11367",
    "addr:housenumber":"72-15",
    "addr:postcode":"11367",
    "addr:street":"Kissena Blvd",
    "iso:country":"US",
    "sg:address":"72-15 Kissena Blvd",
    "sg:city":"Flushing",
    "sg:classifiers":[
        {
            "category":"Food & Beverages",
            "subcategory":"Groceries & Convenience Stores",
            "type":"Retail Goods"
        }
    ],
    "sg:phone":"+1 718 380 7300",
    "sg:postcode":"11367",
    "sg:province":"NY",
    "sg:website":"www.kissenafarms.com/",
    "wof:name":"Aron's Kissena Farms",
    "wof:placetype":"venue"
},
  "geometry": {"coordinates":[-73.813832,40.727813],"type":"Point"}
}