{
  "type": "Feature",
  "properties": {
    "addr:full":"170 Maple Ave White Plains NY 10601",
    "addr:housenumber":"170",
    "addr:postcode":"10601",
    "addr:street":"Maple Ave",
    "iso:country":"US",
    "sg:address":"170 Maple Ave",
    "sg:city":"White Plains",
    "sg:classifiers":[
        {
            "category":"Shopping",
            "subcategory":"Pharmacy",
            "type":"Retail Goods"
        },
        {
            "category":"Shopping",
            "subcategory":"Beauty & Cosmetics",
            "type":"Retail Goods"
        }
    ],
    "sg:phone":"+1 914 949 7000",
    "sg:postcode":"10601",
    "sg:province":"NY",
    "sg:tags":[
        "surgical",
        "appliance",
        "supply"
    ],
    "wof:name":"Medical Center Pharmacy",
    "wof:placetype":"venue"
},
  "geometry": {"coordinates":[-73.76866099999999,41.025222],"type":"Point"}
}