{
  "type": "Feature",
  "properties": {
    "iso:country":"US",
    "sg:address":"100 Cross Keys Office Park",
    "sg:city":"Fairport",
    "sg:classifiers":[
        {
            "category":"Health Services",
            "subcategory":"Medical Lab",
            "type":"Services"
        }
    ],
    "sg:phone":"+1 585 247 3500",
    "sg:postcode":"14450",
    "sg:province":"NY",
    "sg:tags":[
        "laboratories-pathological",
        "laboratory"
    ],
    "sg:website":"http://www.acmlab.com",
    "wof:name":"Acm Medical Laboratory, Inc.",
    "wof:placetype":"venue"
},
  "geometry": {"coordinates":[-77.434448,43.068699],"type":"Point"}
}