{
  "type": "Feature",
  "properties": {
    "iso:country":"US",
    "sg:address":"1411 2nd Ave",
    "sg:city":"New York",
    "sg:classifiers":[
        {
            "category":"Restaurant",
            "type":"Food & Drink"
        }
    ],
    "sg:menulink":"http://www.allmenus.com/ny/new-york/53047-subway/menu/",
    "sg:phone":"+1 212 327 0468",
    "sg:postcode":"10021",
    "sg:province":"NY",
    "sg:tags":[
        "american",
        "sandwich"
    ],
    "wof:name":"Subway",
    "wof:placetype":"venue"
},
  "geometry": {"coordinates":[-73.95796799999999,40.769981],"type":"Point"}
}