{
  "type": "Feature",
  "properties": {
    "addr:full":"4753 Verplank Rd Clay NY 13041",
    "addr:housenumber":"4753",
    "addr:postcode":"13041",
    "addr:street":"Verplank Rd",
    "iso:country":"US",
    "sg:address":"4753 Verplank Rd",
    "sg:city":"Clay",
    "sg:classifiers":[
        {
            "category":"Retail",
            "subcategory":"Auto Repair",
            "type":"Services"
        }
    ],
    "sg:phone":"+1 315 699 5375",
    "sg:postcode":"13041",
    "sg:province":"NY",
    "sg:tags":[
        "body",
        "automobile",
        "painting"
    ],
    "wof:name":"Michael's Auto Body",
    "wof:placetype":"venue"
},
  "geometry": {"coordinates":[-76.197125,43.195542],"type":"Point"}
}