{
  "type": "Feature",
  "properties": {
    "iso:country":"US",
    "sg:address":"414 Sunrise Hwy",
    "sg:city":"Lynbrook",
    "sg:classifiers":[
        {
            "category":"Personal",
            "subcategory":"Day Spa",
            "type":"Services"
        }
    ],
    "sg:phone":"+1 516 593 2211",
    "sg:postcode":"11563",
    "sg:province":"NY",
    "wof:name":"Anna Spa Incorporated",
    "wof:placetype":"venue"
},
  "geometry": {"coordinates":[-73.67204599999999,40.655157],"type":"Point"}
}