{
  "type": "Feature",
  "properties": {
    "addr:full":"170 W Tremont Avenue Bronx NY 10453",
    "addr:housenumber":"170",
    "addr:postcode":"10453",
    "addr:street":"W Tremont Avenue",
    "iso:country":"US",
    "sg:address":"170 W Tremont Avenue",
    "sg:city":"Bronx",
    "sg:classifiers":[
        {
            "category":"Food & Beverages",
            "subcategory":"Groceries & Convenience Stores",
            "type":"Retail Goods"
        }
    ],
    "sg:phone":"+1 718 466 2160",
    "sg:postcode":"10453",
    "sg:province":"NY",
    "wof:name":"Santos Food Corporation",
    "wof:placetype":"venue"
},
  "geometry": {"coordinates":[-73.915843,40.851316],"type":"Point"}
}