{
  "type": "Feature",
  "properties": {
    "addr:full":"63 Wall St New York NY 10005",
    "addr:housenumber":"63",
    "addr:postcode":"10005",
    "addr:street":"Wall St",
    "iso:country":"US",
    "sg:address":"63 Wall St",
    "sg:city":"New York",
    "sg:classifiers":[
        {
            "category":"Food & Beverages",
            "subcategory":"Chocolate",
            "type":"Retail Goods"
        }
    ],
    "sg:phone":"+1 212 952 1123",
    "sg:postcode":"10005",
    "sg:province":"NY",
    "sg:tags":[
        "shop",
        "chocolatiers"
    ],
    "sg:website":"www.lamaisonduchocolat.com/",
    "wof:name":"La Maison Du Chocolat",
    "wof:placetype":"venue"
},
  "geometry": {"coordinates":[-74.008302,40.705715],"type":"Point"}
}