{
  "type": "Feature",
  "properties": {
    "addr:full":"144 Old Post Rd S Croton On Hudson NY 10520",
    "addr:housenumber":"144",
    "addr:postcode":"10520",
    "addr:street":"Old Post Rd",
    "iso:country":"US",
    "sg:address":"144 Old Post Rd S",
    "sg:city":"Croton On Hudson",
    "sg:classifiers":[
        {
            "category":"Professional",
            "subcategory":"Art Services",
            "type":"Services"
        }
    ],
    "sg:phone":"+1 914 271 1200",
    "sg:postcode":"10520",
    "sg:province":"NY",
    "sg:tags":[
        "photographer"
    ],
    "wof:name":"Photomondo Inc",
    "wof:placetype":"venue"
},
  "geometry": {"coordinates":[-73.87456899999999,41.203264],"type":"Point"}
}