{
  "type": "Feature",
  "properties": {
    "iso:country":"US",
    "sg:address":"661 State Hwy 29",
    "sg:city":"Broadalbin",
    "sg:classifiers":[
        {
            "category":"Restaurant",
            "type":"Food & Drink"
        },
        {
            "category":"Bars & Pubs",
            "type":"Food & Drink"
        }
    ],
    "sg:phone":"+1 518 883 5813",
    "sg:postcode":"12025",
    "sg:province":"NY",
    "sg:tags":[
        "drinking"
    ],
    "wof:name":"Mary Ann S Restaurant",
    "wof:placetype":"venue"
},
  "geometry": {"coordinates":[-74.177683,43.059664],"type":"Point"}
}