{
  "type": "Feature",
  "properties": {
    "iso:country":"US",
    "sg:address":"1250 84th St",
    "sg:city":"Brooklyn",
    "sg:classifiers":[
        {
            "category":"Real Estate",
            "subcategory":"Real Estate Agent",
            "type":"Services"
        }
    ],
    "sg:phone":"+1 718 748 2352",
    "sg:postcode":"11228",
    "sg:province":"NY",
    "wof:name":"Chieco Realty Co LLC",
    "wof:placetype":"venue"
},
  "geometry": {"coordinates":[-74.013608,40.615847],"type":"Point"}
}