{
  "type": "Feature",
  "properties": {
    "iso:country":"US",
    "sg:address":"208 E Main St",
    "sg:city":"Port Jervis",
    "sg:classifiers":[
        {
            "category":"Real Estate",
            "subcategory":"Real Estate Operator",
            "type":"Services"
        }
    ],
    "sg:phone":"+1 845 856 4700",
    "sg:postcode":"12771",
    "sg:province":"NY",
    "sg:tags":[
        "apartment"
    ],
    "wof:name":"Waters Edge LP",
    "wof:placetype":"venue"
},
  "geometry": {"coordinates":[-74.683971,41.364687],"type":"Point"}
}