{
  "type": "Feature",
  "properties": {
    "iso:country":"US",
    "sg:address":"1 Bank St",
    "sg:city":"Walden",
    "sg:classifiers":[
        {
            "category":"Professional",
            "subcategory":"Accounting & Tax Preparation",
            "type":"Services"
        }
    ],
    "sg:phone":"+1 845 778 0183",
    "sg:postcode":"12586",
    "sg:province":"NY",
    "sg:tags":[
        "payroll"
    ],
    "wof:name":"A Plus Payroll Processing",
    "wof:placetype":"venue"
},
  "geometry": {"coordinates":[-74.18932,41.561749],"type":"Point"}
}