{
  "type": "Feature",
  "properties": {
    "iso:country":"US",
    "sg:address":"168 S MAIN ST",
    "sg:city":"ALBION",
    "sg:classifiers":[
        {
            "category":"Home & Garden",
            "subcategory":"Household Appliances",
            "type":"Retail Goods"
        },
        {
            "category":"Communications",
            "subcategory":"Radio Station",
            "type":"Services"
        },
        {
            "category":"Shopping",
            "subcategory":"Computers & Home Electronics",
            "type":"Retail Goods"
        },
        {
            "category":"Home & Garden",
            "subcategory":"Furniture",
            "type":"Retail Goods"
        }
    ],
    "sg:phone":"+1 585 589 0100",
    "sg:postcode":"14411",
    "sg:province":"NY",
    "sg:tags":[
        "renting",
        "television",
        "leasing",
        "radio-renting",
        "equipment",
        "rental"
    ],
    "sg:website":"http://www.rentacenter.com/",
    "wof:name":"Rent-A-Center",
    "wof:placetype":"venue"
},
  "geometry": {"coordinates":[-78.193893,43.240978],"type":"Point"}
}