{
  "type": "Feature",
  "properties": {
    "iso:country":"US",
    "sg:address":"57 Beverly Rd",
    "sg:city":"Great Neck",
    "sg:classifiers":[
        {
            "category":"Real Estate",
            "subcategory":"Real Estate Agent",
            "type":"Services"
        }
    ],
    "sg:phone":"+1 516 773 3091",
    "sg:postcode":"11021",
    "sg:province":"NY",
    "wof:name":"Baruch Realty LLC",
    "wof:placetype":"venue"
},
  "geometry": {"coordinates":[-73.72188800000001,40.792635],"type":"Point"}
}