{
  "type": "Feature",
  "properties": {
    "iso:country":"US",
    "sg:address":"22 Norton Ave",
    "sg:city":"Clinton",
    "sg:classifiers":[
        {
            "category":"Building & Trades",
            "subcategory":"Construction",
            "type":"Services"
        },
        {
            "category":"Building & Trades",
            "subcategory":"Plumbing",
            "type":"Services"
        }
    ],
    "sg:phone":"+1 315 853 5305",
    "sg:postcode":"13323",
    "sg:province":"NY",
    "sg:tags":[
        "excavation",
        "septic",
        "contractor"
    ],
    "wof:name":"Vernon Septic Tank Svce",
    "wof:placetype":"venue"
},
  "geometry": {"coordinates":[-75.378204,43.053763],"type":"Point"}
}