{
  "type": "Feature",
  "properties": {
    "addr:full":"529 Oriskany St W Utica NY 13502",
    "addr:housenumber":"529",
    "addr:postcode":"13502",
    "addr:street":"Oriskany St W",
    "iso:country":"US",
    "sg:address":"529 Oriskany St W",
    "sg:city":"Utica",
    "sg:classifiers":[
        {
            "category":"Building & Trades",
            "subcategory":"Plumbing",
            "type":"Services"
        }
    ],
    "sg:phone":"+1 315 797 0858",
    "sg:postcode":"13502",
    "sg:province":"NY",
    "sg:tags":[
        "mechanical",
        "contractor"
    ],
    "wof:name":"Schmalz Mechanical Contractors",
    "wof:placetype":"venue"
},
  "geometry": {"coordinates":[-75.23713600000001,43.105508],"type":"Point"}
}