{
  "type": "Feature",
  "properties": {
    "iso:country":"US",
    "sg:address":"52 Garden St",
    "sg:city":"Roslyn Heights",
    "sg:classifiers":[
        {
            "category":"Professional",
            "subcategory":"Business Services",
            "type":"Services"
        },
        {
            "category":"Travel",
            "subcategory":"Travel Agent",
            "type":"Entertainment"
        }
    ],
    "sg:phone":"+1 516 484 8138",
    "sg:postcode":"11577",
    "sg:province":"NY",
    "sg:tags":[
        "agency",
        "bureau"
    ],
    "wof:name":"Maxworld Groups Inc",
    "wof:placetype":"venue"
},
  "geometry": {"coordinates":[-73.653265,40.790144],"type":"Point"}
}