{
  "type": "Feature",
  "properties": {
    "addr:full":"3340 127th Pl Corona NY 11368",
    "addr:housenumber":"3340",
    "addr:postcode":"11368",
    "addr:street":"127Th Pl",
    "iso:country":"US",
    "sg:address":"3340 127th Pl",
    "sg:city":"Corona",
    "sg:classifiers":[
        {
            "category":"Freight",
            "type":"Transportation"
        },
        {
            "category":"Restaurant",
            "type":"Food & Drink"
        }
    ],
    "sg:phone":"+1 718 478 7060",
    "sg:postcode":"11368",
    "sg:province":"NY",
    "sg:tags":[
        "cargo",
        "container",
        "pizza"
    ],
    "wof:name":"P H U Dorand Pizza",
    "wof:placetype":"venue"
},
  "geometry": {"coordinates":[-73.842344,40.761128],"type":"Point"}
}