{
  "type": "Feature",
  "properties": {
    "addr:full":"123 Allen Blvd Farmingdale NY 11735",
    "addr:housenumber":"123",
    "addr:postcode":"11735",
    "addr:street":"Allen Blvd",
    "iso:country":"US",
    "sg:address":"123 Allen Blvd",
    "sg:city":"Farmingdale",
    "sg:classifiers":[
        {
            "category":"Home & Garden",
            "subcategory":"Furniture",
            "type":"Retail Goods"
        }
    ],
    "sg:phone":"+1 631 293 2221",
    "sg:postcode":"11735",
    "sg:province":"NY",
    "sg:tags":[
        "top",
        "counter"
    ],
    "wof:name":"Counter-Tech Industries",
    "wof:placetype":"venue"
},
  "geometry": {"coordinates":[-73.41609800000001,40.715881],"type":"Point"}
}