{
  "type": "Feature",
  "properties": {
    "addr:full":"1043 Slosson Rd West Chazy NY 12992",
    "addr:housenumber":"1043",
    "addr:postcode":"12992",
    "addr:street":"Slosson Rd",
    "iso:country":"US",
    "sg:address":"1043 Slosson Rd",
    "sg:city":"West Chazy",
    "sg:classifiers":[
        {
            "category":"Shopping",
            "subcategory":"Gifts & Souvenirs",
            "type":"Retail Goods"
        }
    ],
    "sg:phone":"+1 518 493 6761",
    "sg:postcode":"12992",
    "sg:province":"NY",
    "sg:tags":[
        "shop"
    ],
    "wof:name":"Parker Family Maple Sugar Farm",
    "wof:placetype":"venue"
},
  "geometry": {"coordinates":[-73.547833,44.83071],"type":"Point"}
}