{
  "type": "Feature",
  "properties": {
    "iso:country":"US",
    "sg:address":"2713 Guilderland Ave",
    "sg:city":"Schenectady",
    "sg:classifiers":[
        {
            "category":"Food & Beverages",
            "subcategory":"Groceries & Convenience Stores",
            "type":"Retail Goods"
        },
        {
            "category":"Food & Beverages",
            "subcategory":"Meat & Fish",
            "type":"Retail Goods"
        }
    ],
    "sg:phone":"+1 518 346 0408",
    "sg:postcode":"12306",
    "sg:province":"NY",
    "sg:tags":[
        "grocer"
    ],
    "wof:name":"Sal's Quality Market",
    "wof:placetype":"venue"
},
  "geometry": {"coordinates":[-73.971054,42.786879],"type":"Point"}
}