{
  "type": "Feature",
  "properties": {
    "iso:country":"US",
    "sg:address":"61 Hester St",
    "sg:city":"New York",
    "sg:classifiers":[
        {
            "category":"Restaurant",
            "type":"Food & Drink"
        }
    ],
    "sg:phone":"+1 212 477 2427",
    "sg:postcode":"10002",
    "sg:province":"NY",
    "sg:tags":[
        "new",
        "american"
    ],
    "sg:website":"www.greenbrownorange.com",
    "wof:name":"Brown Cafe",
    "wof:placetype":"venue"
},
  "geometry": {"coordinates":[-73.9903,40.715915],"type":"Point"}
}