{
  "type": "Feature",
  "properties": {
    "addr:full":"444 Patchogue Yaphank Rd Yaphank NY 11980",
    "addr:housenumber":"444",
    "addr:postcode":"11980",
    "addr:street":"Patchogue Yaphank Rd",
    "iso:country":"US",
    "sg:address":"444 Patchogue Yaphank Rd",
    "sg:city":"Yaphank",
    "sg:classifiers":[
        {
            "category":"Restaurant",
            "type":"Food & Drink"
        }
    ],
    "sg:phone":"+1   ",
    "sg:postcode":"11980",
    "sg:province":"NY",
    "sg:tags":[
        "eating"
    ],
    "wof:name":"Kitchen Decor",
    "wof:placetype":"venue"
},
  "geometry": {"coordinates":[-72.95390999999999,40.810038],"type":"Point"}
}