{
  "type": "Feature",
  "properties": {
    "iso:country":"US",
    "sg:address":"670 W End Ave",
    "sg:city":"New York",
    "sg:classifiers":[
        {
            "category":"Professional",
            "type":"Services"
        }
    ],
    "sg:phone":"+1 212 362 4632",
    "sg:postcode":"10025",
    "sg:province":"NY",
    "sg:tags":[
        "establishment"
    ],
    "wof:name":"670 Associates",
    "wof:placetype":"venue"
},
  "geometry": {"coordinates":[-73.97475799999999,40.792911],"type":"Point"}
}