{
  "type": "Feature",
  "properties": {
    "addr:full":"180 E Main St Patchogue NY 11772",
    "addr:housenumber":"180",
    "addr:postcode":"11772",
    "addr:street":"E Main St",
    "iso:country":"US",
    "sg:address":"180 E Main St",
    "sg:city":"Patchogue",
    "sg:classifiers":[
        {
            "category":"Organizations",
            "subcategory":"Professional Association",
            "type":"Services"
        }
    ],
    "sg:phone":"+1 631 499 4400",
    "sg:postcode":"11772",
    "sg:province":"NY",
    "sg:tags":[
        "chambers",
        "commerce"
    ],
    "wof:name":"Chamber Of Commerce",
    "wof:placetype":"venue"
},
  "geometry": {"coordinates":[-73.010857,40.765729],"type":"Point"}
}