{
  "type": "Feature",
  "properties": {
    "addr:full":"268 Manning Blvd Albany NY 12206",
    "addr:housenumber":"268",
    "addr:postcode":"12206",
    "addr:street":"Manning Blvd",
    "iso:country":"US",
    "sg:address":"268 Manning Blvd",
    "sg:city":"Albany",
    "sg:classifiers":[
        {
            "category":"Organizations",
            "subcategory":"Religious Organization",
            "type":"Services"
        }
    ],
    "sg:phone":"+1 518 482 2079",
    "sg:postcode":"12206",
    "sg:province":"NY",
    "sg:tags":[
        "monastery",
        "convent"
    ],
    "wof:name":"Sisters Of St Joseph",
    "wof:placetype":"venue"
},
  "geometry": {"coordinates":[-73.78796699999999,42.671868],"type":"Point"}
}