{
  "type": "Feature",
  "properties": {
    "iso:country":"US",
    "sg:address":"260 Mill St",
    "sg:city":"Poughkeepsie",
    "sg:classifiers":[
        {
            "category":"Organizations",
            "subcategory":"Religious Organization",
            "type":"Services"
        }
    ],
    "sg:phone":"+1 845 454 1340",
    "sg:postcode":"12601",
    "sg:province":"NY",
    "sg:tags":[
        "church"
    ],
    "wof:name":"First Baptist Church Inc",
    "wof:placetype":"venue"
},
  "geometry": {"coordinates":[-73.92658400000001,41.704955],"type":"Point"}
}