{
  "type": "Feature",
  "properties": {
    "addr:full":"137 Essex Manhattan NY 10002",
    "addr:housenumber":"137",
    "addr:postcode":"10002",
    "addr:street":"Essex",
    "iso:country":"US",
    "sg:address":"137 Essex",
    "sg:city":"Manhattan",
    "sg:classifiers":[
        {
            "category":"Retail",
            "subcategory":"Event Space",
            "type":"Services"
        },
        {
            "category":"Recreation",
            "subcategory":"Dance Hall",
            "type":"Entertainment"
        }
    ],
    "sg:phone":"+1 212 253 2066",
    "sg:postcode":"10002",
    "sg:province":"NY",
    "sg:tags":[
        "club",
        "venue"
    ],
    "sg:website":"www.foundationnyc.com",
    "wof:name":"Foundation Nyc",
    "wof:placetype":"venue"
},
  "geometry": {"coordinates":[-73.987493,40.720306],"type":"Point"}
}