{
  "type": "Feature",
  "properties": {
    "iso:country":"US",
    "sg:address":"8284 Carney Hollow Rd",
    "sg:city":"Wayland",
    "sg:classifiers":[
        {
            "category":"Farming",
            "subcategory":"Farm",
            "type":"Manufacturing & Wholesale Goods"
        }
    ],
    "sg:phone":"+1 585 669 2773",
    "sg:postcode":"14572",
    "sg:province":"NY",
    "sg:tags":[
        "food",
        "ornamental",
        "nursery",
        "crop",
        "covered"
    ],
    "wof:name":"Hu-Gen Farms",
    "wof:placetype":"venue"
},
  "geometry": {"coordinates":[-77.63251099999999,42.624244],"type":"Point"}
}