{
  "type": "Feature",
  "properties": {
    "addr:full":"79 Church Ave Brooklyn NY 11218",
    "addr:housenumber":"79",
    "addr:postcode":"11218",
    "addr:street":"Church Ave",
    "iso:country":"US",
    "sg:address":"79 Church Ave",
    "sg:city":"Brooklyn",
    "sg:classifiers":[
        {
            "category":"Food & Beverages",
            "subcategory":"Groceries & Convenience Stores",
            "type":"Retail Goods"
        }
    ],
    "sg:phone":"+1 718 435 6764",
    "sg:postcode":"11218",
    "sg:province":"NY",
    "wof:name":"C B S Food Market",
    "wof:placetype":"venue"
},
  "geometry": {"coordinates":[-73.9804,40.642502],"type":"Point"}
}