{
  "type": "Feature",
  "properties": {
    "addr:full":"448 W 37th St New York NY 10018",
    "addr:housenumber":"448",
    "addr:postcode":"10018",
    "addr:street":"W 37Th St",
    "iso:country":"US",
    "sg:address":"448 W 37th St",
    "sg:city":"New York",
    "sg:classifiers":[
        {
            "category":"Retail",
            "subcategory":"Portrait Studio",
            "type":"Services"
        }
    ],
    "sg:phone":"+1 212 620 6110",
    "sg:postcode":"10018",
    "sg:province":"NY",
    "sg:tags":[
        "photography"
    ],
    "wof:name":"Joseph Mulligan Photographer",
    "wof:placetype":"venue"
},
  "geometry": {"coordinates":[-73.997457,40.756234],"type":"Point"}
}