{
  "type": "Feature",
  "properties": {
    "addr:full":"16 John St South Glens Falls NY 12803",
    "addr:housenumber":"16",
    "addr:postcode":"12803",
    "addr:street":"John St",
    "iso:country":"US",
    "sg:address":"16 John St",
    "sg:city":"South Glens Falls",
    "sg:classifiers":[
        {
            "category":"Organizations",
            "subcategory":"Community Association",
            "type":"Services"
        }
    ],
    "sg:phone":"+1   ",
    "sg:postcode":"12803",
    "sg:province":"NY",
    "wof:name":"700 Bowling Clubs of America",
    "wof:placetype":"venue"
},
  "geometry": {"coordinates":[-73.627645,43.290237],"type":"Point"}
}