{
  "type": "Feature",
  "properties": {
    "addr:full":"14 Joan Ln Wappingers Falls NY 12590",
    "addr:housenumber":"14",
    "addr:postcode":"12590",
    "addr:street":"Joan Ln",
    "iso:country":"US",
    "sg:address":"14 Joan Ln",
    "sg:city":"Wappingers Falls",
    "sg:classifiers":[
        {
            "category":"Building & Trades",
            "subcategory":"Landscaping Services",
            "type":"Services"
        }
    ],
    "sg:phone":"+1 845 226 3018",
    "sg:postcode":"12590",
    "sg:province":"NY",
    "sg:tags":[
        "landscape",
        "contractor"
    ],
    "wof:name":"Allen Brian Tree & Landscape",
    "wof:placetype":"venue"
},
  "geometry": {"coordinates":[-73.81794600000001,41.621851],"type":"Point"}
}