{
  "type": "Feature",
  "properties": {
    "addr:full":"3682 Fred Rd Cohocton NY 14826",
    "addr:housenumber":"3682",
    "addr:postcode":"14826",
    "addr:street":"Fred Rd",
    "iso:country":"US",
    "sg:address":"3682 Fred Rd",
    "sg:city":"Cohocton",
    "sg:classifiers":[
        {
            "category":"Farming",
            "subcategory":"Farm",
            "type":"Manufacturing & Wholesale Goods"
        }
    ],
    "sg:phone":"+1 585 384 5355",
    "sg:postcode":"14826",
    "sg:province":"NY",
    "sg:tags":[
        "crop",
        "general"
    ],
    "wof:name":"J&B Family Farm",
    "wof:placetype":"venue"
},
  "geometry": {"coordinates":[-77.509288,42.453603],"type":"Point"}
}