{
  "type": "Feature",
  "properties": {
    "iso:country":"US",
    "sg:address":"35559 Co Rd 136",
    "sg:city":"Theresa",
    "sg:classifiers":[
        {
            "category":"Retail",
            "subcategory":"Auto Repair",
            "type":"Services"
        }
    ],
    "sg:phone":"+1 315 628 5725",
    "sg:postcode":"13691",
    "sg:province":"NY",
    "sg:tags":[
        "body",
        "automobile",
        "painting"
    ],
    "wof:name":"D & M Collision",
    "wof:placetype":"venue"
},
  "geometry": {"coordinates":[-75.818127,44.183083],"type":"Point"}
}