{
  "type": "Feature",
  "properties": {
    "iso:country":"US",
    "sg:address":"227 Genesee St",
    "sg:city":"Chittenango",
    "sg:classifiers":[
        {
            "category":"Museum",
            "type":"Entertainment"
        }
    ],
    "sg:phone":"+1 315 687 3423",
    "sg:postcode":"13037",
    "sg:province":"NY",
    "sg:tags":[
        "gallery"
    ],
    "wof:name":"Oz Museum",
    "wof:placetype":"venue"
},
  "geometry": {"coordinates":[-75.86676199999999,43.044452],"type":"Point"}
}