{
  "type": "Feature",
  "properties": {
    "addr:full":"309 Brighton Beach Ave Brooklyn NY 11235",
    "addr:housenumber":"309",
    "addr:postcode":"11235",
    "addr:street":"Brighton Beach Ave",
    "iso:country":"US",
    "sg:address":"309 Brighton Beach Ave",
    "sg:city":"Brooklyn",
    "sg:classifiers":[
        {
            "category":"Health Services",
            "subcategory":"Doctor",
            "type":"Services"
        }
    ],
    "sg:phone":"+1 718 332 2228",
    "sg:postcode":"11235",
    "sg:province":"NY",
    "sg:tags":[
        "dentist"
    ],
    "wof:name":"Family & Cosmetic Dental",
    "wof:placetype":"venue"
},
  "geometry": {"coordinates":[-73.963356,40.577267],"type":"Point"}
}