{
  "type": "Feature",
  "properties": {
    "addr:full":"151 W 46 St New York NY 10036",
    "addr:housenumber":"151",
    "addr:postcode":"10036",
    "addr:street":"W 46 St",
    "iso:country":"US",
    "sg:address":"151 W 46 St",
    "sg:city":"New York",
    "sg:classifiers":[
        {
            "category":"Professional",
            "subcategory":"Advertising",
            "type":"Services"
        }
    ],
    "sg:phone":"+1 212 302 6740",
    "sg:postcode":"10036",
    "sg:province":"NY",
    "wof:name":"FOREVERFLAWLESS.COM",
    "wof:placetype":"venue"
},
  "geometry": {"coordinates":[-73.98395499999999,40.758041],"type":"Point"}
}