{
  "type": "Feature",
  "properties": {
    "addr:full":"1128 Myrtle Avenue Brooklyn NY 11206",
    "addr:housenumber":"1128",
    "addr:postcode":"11206",
    "addr:street":"Myrtle Avenue",
    "iso:country":"US",
    "sg:address":"1128 Myrtle Avenue",
    "sg:city":"Brooklyn",
    "sg:classifiers":[
        {
            "category":"Retail",
            "subcategory":"Laundry & Dry Cleaning",
            "type":"Services"
        }
    ],
    "sg:phone":"+1 718 573 5531",
    "sg:postcode":"11206",
    "sg:province":"NY",
    "wof:name":"New Crystal Cleaner",
    "wof:placetype":"venue"
},
  "geometry": {"coordinates":[-73.935306,40.696859],"type":"Point"}
}