{
  "type": "Feature",
  "properties": {
    "addr:full":"556 State St Binghamton NY 13901",
    "addr:housenumber":"556",
    "addr:postcode":"13901",
    "addr:street":"State St",
    "iso:country":"US",
    "sg:address":"556 State St",
    "sg:city":"Binghamton",
    "sg:classifiers":[
        {
            "category":"Freight",
            "type":"Transportation"
        }
    ],
    "sg:phone":"+1 607 217 0080",
    "sg:postcode":"13901",
    "sg:province":"NY",
    "sg:tags":[
        "trucking"
    ],
    "sg:website":"www.grosstrucking.com",
    "wof:name":"Gross Trucking Inc",
    "wof:placetype":"venue"
},
  "geometry": {"coordinates":[-75.89984800000001,42.11281],"type":"Point"}
}