{
  "type": "Feature",
  "properties": {
    "iso:country":"US",
    "sg:address":"667 Old Country Rd",
    "sg:city":"Plainview",
    "sg:classifiers":[
        {
            "category":"Insurance",
            "subcategory":"Insurance Agent",
            "type":"Services"
        }
    ],
    "sg:phone":"+1 516 822 9321",
    "sg:postcode":"11803",
    "sg:province":"NY",
    "wof:name":"Tim Mee Agency Inc",
    "wof:placetype":"venue"
},
  "geometry": {"coordinates":[-73.48933599999999,40.77203],"type":"Point"}
}