{
  "type": "Feature",
  "properties": {
    "addr:full":"145 E 48th St New York NY 10017",
    "addr:housenumber":"145",
    "addr:postcode":"10017",
    "addr:street":"E 48Th St",
    "iso:country":"US",
    "sg:address":"145 E 48th St",
    "sg:city":"New York",
    "sg:classifiers":[
        {
            "category":"Banks & Credit Unions",
            "subcategory":"Financial Services",
            "type":"Services"
        }
    ],
    "sg:phone":"+1 212 593 3110",
    "sg:postcode":"10017",
    "sg:province":"NY",
    "sg:tags":[
        "relate",
        "consulting",
        "management",
        "investor",
        "computer"
    ],
    "wof:name":"Chinook Equities Ltd",
    "wof:placetype":"venue"
},
  "geometry": {"coordinates":[-73.971917,40.754789],"type":"Point"}
}