{
  "type": "Feature",
  "properties": {
    "addr:full":"2747 King Rd Sauquoit NY 13456",
    "addr:housenumber":"2747",
    "addr:postcode":"13456",
    "addr:street":"King Rd",
    "iso:country":"US",
    "sg:address":"2747 King Rd",
    "sg:city":"Sauquoit",
    "sg:classifiers":[
        {
            "category":"Building & Trades",
            "subcategory":"Construction",
            "type":"Services"
        }
    ],
    "sg:phone":"+1 315 737 7785",
    "sg:postcode":"13456",
    "sg:province":"NY",
    "sg:tags":[
        "contractor"
    ],
    "wof:name":"Kevin J Gaffney",
    "wof:placetype":"venue"
},
  "geometry": {"coordinates":[-75.218802,42.996608],"type":"Point"}
}