{
  "type": "Feature",
  "properties": {
    "iso:country":"US",
    "sg:address":"1560 State Rte 54",
    "sg:city":"Penn Yan",
    "sg:classifiers":[
        {
            "category":"Wholesale",
            "subcategory":"Sporting Goods",
            "type":"Manufacturing & Wholesale Goods"
        }
    ],
    "sg:phone":"+1 315 536 8106",
    "sg:postcode":"14527",
    "sg:province":"NY",
    "sg:tags":[
        "retail"
    ],
    "wof:name":"Traps Parts and Repairs",
    "wof:placetype":"venue"
},
  "geometry": {"coordinates":[-77.009816,42.678289],"type":"Point"}
}