{
  "type": "Feature",
  "properties": {
    "addr:full":"370 Main St Catskill NY 12414",
    "addr:housenumber":"370",
    "addr:postcode":"12414",
    "addr:street":"Main St",
    "iso:country":"US",
    "sg:address":"370 Main St",
    "sg:city":"Catskill",
    "sg:classifiers":[
        {
            "category":"Professional",
            "subcategory":"Lawyer & Legal Services",
            "type":"Services"
        }
    ],
    "sg:phone":"+1 518 943 1300",
    "sg:postcode":"12414",
    "sg:province":"NY",
    "sg:tags":[
        "attorney"
    ],
    "wof:name":"Tully Rincley & Assoc Pllc",
    "wof:placetype":"venue"
},
  "geometry": {"coordinates":[-73.865303,42.218719],"type":"Point"}
}