{
  "type": "Feature",
  "properties": {
    "addr:full":"8957 US Hwy 9 Chazy NY 12921",
    "addr:housenumber":"8957",
    "addr:postcode":"12921",
    "addr:street":"Us Hwy 9 Chazy",
    "iso:country":"US",
    "sg:address":"8957 US Hwy 9",
    "sg:city":"Chazy",
    "sg:classifiers":[
        {
            "category":"Farming",
            "subcategory":"Poultry Farm",
            "type":"Manufacturing & Wholesale Goods"
        }
    ],
    "sg:phone":"+1 518 846 7300",
    "sg:postcode":"12921",
    "sg:province":"NY",
    "wof:name":"Giroux's Poultry",
    "wof:placetype":"venue"
},
  "geometry": {"coordinates":[-73.429441,44.833618],"type":"Point"}
}