{
  "type": "Feature",
  "properties": {
    "addr:full":"3565 Crompond Rd Cortlandt Manor NY 10567",
    "addr:housenumber":"3565",
    "addr:postcode":"10567",
    "addr:street":"Crompond Rd",
    "iso:country":"US",
    "sg:address":"3565 Crompond Rd",
    "sg:city":"Cortlandt Manor",
    "sg:classifiers":[
        {
            "category":"Sports & Exercise",
            "subcategory":"Gym",
            "type":"Entertainment"
        }
    ],
    "sg:phone":"+1 914 737 1177",
    "sg:postcode":"10567",
    "sg:province":"NY",
    "sg:tags":[
        "club",
        "health",
        "studio",
        "gymnasium"
    ],
    "wof:name":"Curves",
    "wof:placetype":"venue"
},
  "geometry": {"coordinates":[-73.85926600000001,41.292704],"type":"Point"}
}