{
  "type": "Feature",
  "properties": {
    "addr:full":"1510 86th St Brooklyn NY 11228",
    "addr:housenumber":"1510",
    "addr:postcode":"11228",
    "addr:street":"86Th St",
    "iso:country":"US",
    "sg:address":"1510 86th St",
    "sg:city":"Brooklyn",
    "sg:classifiers":[
        {
            "category":"Banks & Credit Unions",
            "subcategory":"Bank",
            "type":"Services"
        }
    ],
    "sg:phone":"+1 718 234 1627",
    "sg:postcode":"11228",
    "sg:province":"NY",
    "sg:tags":[
        "loan",
        "broker"
    ],
    "wof:name":"Financial Resources New York",
    "wof:placetype":"venue"
},
  "geometry": {"coordinates":[-74.00901500000001,40.611058],"type":"Point"}
}