{
  "type": "Feature",
  "properties": {
    "iso:country":"US",
    "sg:address":"33 Maiden Ln",
    "sg:city":"New York",
    "sg:classifiers":[
        {
            "category":"Banks & Credit Unions",
            "subcategory":"Bank",
            "type":"Services"
        }
    ],
    "sg:phone":"+1 212 651 7600",
    "sg:postcode":"10038",
    "sg:province":"NY",
    "sg:tags":[
        "loan",
        "real estate"
    ],
    "sg:website":"www.mortgageit.com",
    "wof:name":"Mortgage IT",
    "wof:placetype":"venue"
},
  "geometry": {"coordinates":[-74.008015,40.708136],"type":"Point"}
}