{
  "type": "Feature",
  "properties": {
    "iso:country":"US",
    "sg:address":"2093 Broadway St",
    "sg:city":"Buffalo",
    "sg:classifiers":[
        {
            "category":"Restaurant",
            "type":"Food & Drink"
        }
    ],
    "sg:phone":"+1 716 892 8200",
    "sg:postcode":"14212",
    "sg:province":"NY",
    "wof:name":"Sebastiano Restaurant",
    "wof:placetype":"venue"
},
  "geometry": {"coordinates":[-78.796718,42.898985],"type":"Point"}
}