{
  "type": "Feature",
  "properties": {
    "addr:full":"572 Victor Egypt Rd Victor NY 14564",
    "addr:housenumber":"572",
    "addr:postcode":"14564",
    "addr:street":"Victor Egypt Rd",
    "iso:country":"US",
    "sg:address":"572 Victor Egypt Rd",
    "sg:city":"Victor",
    "sg:classifiers":[
        {
            "category":"Building & Trades",
            "subcategory":"Construction",
            "type":"Services"
        }
    ],
    "sg:phone":"+1 585 924 3144",
    "sg:postcode":"14564",
    "sg:province":"NY",
    "sg:tags":[
        "concrete",
        "contractor"
    ],
    "wof:name":"Coston Roosevelt",
    "wof:placetype":"venue"
},
  "geometry": {"coordinates":[-77.399162,43.010246],"type":"Point"}
}