{
  "type": "Feature",
  "properties": {
    "addr:full":"97 North Tenth Street Suite 204 Brooklyn NY 11211",
    "addr:housenumber":"97",
    "addr:postcode":"11211",
    "addr:street":"North Tenth Street Suite 204",
    "iso:country":"US",
    "sg:address":"97 North Tenth Street Suite 204",
    "sg:city":"Brooklyn",
    "sg:classifiers":[
        {
            "category":"Professional",
            "subcategory":"Computer Services",
            "type":"Services"
        }
    ],
    "sg:postcode":"11211",
    "sg:province":"NY",
    "sg:tags":[
        "iptv",
        "web-video",
        "online-video"
    ],
    "sg:website":"http://www.vbs.tv",
    "wof:name":"VBS TV",
    "wof:placetype":"venue"
},
  "geometry": {"coordinates":[-73.953098,40.712597],"type":"Point"}
}