{
  "type": "Feature",
  "properties": {
    "iso:country":"US",
    "sg:address":"44 Sylvia Ln",
    "sg:city":"Plainview",
    "sg:classifiers":[
        {
            "category":"Health Services",
            "subcategory":"Health Practitioner",
            "type":"Services"
        }
    ],
    "sg:phone":"+1 516 942 8271",
    "sg:postcode":"11803",
    "sg:province":"NY",
    "sg:tags":[
        "pathologist",
        "speech"
    ],
    "wof:name":"Amy Sommers Speech & Language",
    "wof:placetype":"venue"
},
  "geometry": {"coordinates":[-73.483335,40.778678],"type":"Point"}
}