{
  "type": "Feature",
  "properties": {
    "addr:full":"117 E 57th St New York NY 10022",
    "addr:housenumber":"117",
    "addr:postcode":"10022",
    "addr:street":"E 57Th St",
    "iso:country":"US",
    "sg:address":"117 E 57th St",
    "sg:city":"New York",
    "sg:classifiers":[
        {
            "category":"Wholesale",
            "subcategory":"Chemicals & Plastics",
            "type":"Manufacturing & Wholesale Goods"
        }
    ],
    "sg:phone":"+1 212 751 5693",
    "sg:postcode":"10022",
    "sg:province":"NY",
    "sg:tags":[
        "import",
        "export",
        "machinery"
    ],
    "wof:name":"Overseas Chemicals & Machinery",
    "wof:placetype":"venue"
},
  "geometry": {"coordinates":[-73.96964,40.761297],"type":"Point"}
}