{
  "type": "Feature",
  "properties": {
    "iso:country":"US",
    "sg:address":"125 E Prospect Ave",
    "sg:city":"Mamaroneck",
    "sg:classifiers":[
        {
            "category":"Shopping",
            "subcategory":"Used Merchandise",
            "type":"Retail Goods"
        }
    ],
    "sg:phone":"+1 914 777 1195",
    "sg:postcode":"10543",
    "sg:province":"NY",
    "sg:tags":[
        "antique"
    ],
    "wof:name":"Alkadim Arts & Antiques",
    "wof:placetype":"venue"
},
  "geometry": {"coordinates":[-73.73240199999999,40.950266],"type":"Point"}
}