{
  "type": "Feature",
  "properties": {
    "addr:full":"1172 Amsterdam Ave 300 Avery Hall New York NY 10027",
    "addr:housenumber":"1172;300",
    "addr:postcode":"10027",
    "addr:street":"Amsterdam Ave",
    "iso:country":"US",
    "sg:address":"1172 Amsterdam Ave 300 Avery Hall",
    "sg:city":"New York",
    "sg:classifiers":[
        {
            "category":"Food & Beverages",
            "subcategory":"Bakery",
            "type":"Retail Goods"
        }
    ],
    "sg:phone":"+1 212 854 1754",
    "sg:postcode":"10027",
    "sg:province":"NY",
    "sg:tags":[
        "sandwich"
    ],
    "wof:name":"Brownie's Cafe",
    "wof:placetype":"venue"
},
  "geometry": {"coordinates":[-73.96069799999999,40.807362],"type":"Point"}
}