{
  "type": "Feature",
  "properties": {
    "addr:full":"2595 Steinway Street Astoria NY 11103",
    "addr:housenumber":"2595",
    "addr:postcode":"11103",
    "addr:street":"Steinway Street",
    "iso:country":"US",
    "sg:address":"2595 Steinway Street",
    "sg:city":"Astoria",
    "sg:classifiers":[
        {
            "category":"Arts & Performance",
            "subcategory":"Arts Center",
            "type":"Entertainment"
        },
        {
            "category":"Arts & Performance",
            "subcategory":"Dance",
            "type":"Entertainment"
        }
    ],
    "sg:phone":"+1 718 278 1567",
    "sg:postcode":"11103",
    "sg:province":"NY",
    "sg:tags":[
        "school",
        "performing"
    ],
    "sg:website":"www.astoriadancecentre.com",
    "wof:name":"Astoria Dance Centre",
    "wof:placetype":"venue"
},
  "geometry": {"coordinates":[-73.91345099999999,40.76557],"type":"Point"}
}