{
  "type": "Feature",
  "properties": {
    "addr:full":"40 Hopewell St Albany NY 12208",
    "addr:housenumber":"40",
    "addr:postcode":"12208",
    "addr:street":"Hopewell St",
    "iso:country":"US",
    "sg:address":"40 Hopewell St",
    "sg:city":"Albany",
    "sg:classifiers":[
        {
            "category":"Organizations",
            "subcategory":"Religious Organization",
            "type":"Services"
        }
    ],
    "sg:phone":"+1 518 489 3204",
    "sg:postcode":"12208",
    "sg:province":"NY",
    "sg:tags":[
        "church"
    ],
    "wof:name":"St Catherine Of Siena Chr Ofc",
    "wof:placetype":"venue"
},
  "geometry": {"coordinates":[-73.814201,42.654886],"type":"Point"}
}