{
  "type": "Feature",
  "properties": {
    "addr:full":"189 Calebs Path Central Islip NY 11722",
    "addr:housenumber":"189",
    "addr:postcode":"11722",
    "addr:street":"Calebs Path",
    "iso:country":"US",
    "sg:address":"189 Calebs Path",
    "sg:city":"Central Islip",
    "sg:classifiers":[
        {
            "category":"Restaurant",
            "type":"Food & Drink"
        }
    ],
    "sg:menulink":"http://www.allmenus.com/ny/islip/217276-caribbean-delight/menu/",
    "sg:phone":"+1 631 582 4441",
    "sg:postcode":"11722",
    "sg:province":"NY",
    "sg:tags":[
        "american",
        "creole",
        "cajun"
    ],
    "wof:name":"Caribbean Delight",
    "wof:placetype":"venue"
},
  "geometry": {"coordinates":[-73.227237,40.798867],"type":"Point"}
}