{
  "type": "Feature",
  "properties": {
    "addr:full":"13679 Roosevelt Avenue Flushing NY 11354",
    "addr:housenumber":"13679",
    "addr:postcode":"11354",
    "addr:street":"Roosevelt Avenue",
    "iso:country":"US",
    "sg:address":"13679 Roosevelt Avenue",
    "sg:city":"Flushing",
    "sg:classifiers":[
        {
            "category":"Retail",
            "subcategory":"Portrait Studio",
            "type":"Services"
        },
        {
            "category":"Professional",
            "subcategory":"Art Services",
            "type":"Services"
        }
    ],
    "sg:phone":"+1 718 961 5180",
    "sg:postcode":"11354",
    "sg:province":"NY",
    "sg:tags":[
        "photographer",
        "photography",
        "store"
    ],
    "sg:website":"www.livingimagephotostudios.com",
    "wof:name":"Living Image",
    "wof:placetype":"venue"
},
  "geometry": {"coordinates":[-73.82774999999999,40.760152],"type":"Point"}
}