{
  "type": "Feature",
  "properties": {
    "iso:country":"US",
    "sg:address":"71 Cedarhurst Ave",
    "sg:city":"Selden",
    "sg:classifiers":[
        {
            "category":"Building & Trades",
            "subcategory":"Construction",
            "type":"Services"
        }
    ],
    "sg:phone":"+1 631 736 5181",
    "sg:postcode":"11784",
    "sg:province":"NY",
    "sg:tags":[
        "contractor"
    ],
    "wof:name":"Boyd Masonry",
    "wof:placetype":"venue"
},
  "geometry": {"coordinates":[-73.04164,40.863012],"type":"Point"}
}