{
  "type": "Feature",
  "properties": {
    "iso:country":"US",
    "sg:address":"7176 E Port Bay Rd",
    "sg:city":"Wolcott",
    "sg:classifiers":[
        {
            "category":"Organizations",
            "subcategory":"Religious Organization",
            "type":"Services"
        }
    ],
    "sg:phone":"+1 315 594 8335",
    "sg:postcode":"14590",
    "sg:province":"NY",
    "sg:tags":[
        "church"
    ],
    "wof:name":"New Start Ministry",
    "wof:placetype":"venue"
},
  "geometry": {"coordinates":[-76.810965,43.256697],"type":"Point"}
}