{
  "type": "Feature",
  "properties": {
    "iso:country":"US",
    "sg:address":"73 Spring Street",
    "sg:city":"New York",
    "sg:classifiers":[
        {
            "category":"Arts & Performance",
            "subcategory":"Art Gallery",
            "type":"Entertainment"
        },
        {
            "category":"Professional",
            "subcategory":"Lawyer & Legal Services",
            "type":"Services"
        }
    ],
    "sg:phone":"+1 212 334 7993",
    "sg:postcode":"10012",
    "sg:province":"NY",
    "wof:name":"Carley Ann M Atty",
    "wof:placetype":"venue"
},
  "geometry": {"coordinates":[-73.99785,40.722605],"type":"Point"}
}