{
  "type": "Feature",
  "properties": {
    "iso:country":"US",
    "sg:address":"100 Dawnbrook Ln",
    "sg:city":"Buffalo",
    "sg:classifiers":[
        {
            "category":"Communications",
            "subcategory":"Television Station",
            "type":"Services"
        }
    ],
    "sg:phone":"+1 716 565 0652",
    "sg:postcode":"14221",
    "sg:province":"NY",
    "sg:tags":[
        "satellite",
        "antenna",
        "cable",
        "tv",
        "system",
        "equipment"
    ],
    "wof:name":"Pro Satellitecom",
    "wof:placetype":"venue"
},
  "geometry": {"coordinates":[-78.769352,42.975547],"type":"Point"}
}