{
  "type": "Feature",
  "properties": {
    "addr:full":"1078 Dobbs Ferry Rd White Plains NY 10607",
    "addr:housenumber":"1078",
    "addr:postcode":"10607",
    "addr:street":"Dobbs Ferry Rd",
    "iso:country":"US",
    "sg:address":"1078 Dobbs Ferry Rd",
    "sg:city":"White Plains",
    "sg:classifiers":[
        {
            "category":"Taxi",
            "type":"Transportation"
        }
    ],
    "sg:phone":"+1   ",
    "sg:postcode":"10607",
    "sg:province":"NY",
    "sg:tags":[
        "taxicab"
    ],
    "wof:name":"Select Taxi Corp",
    "wof:placetype":"venue"
},
  "geometry": {"coordinates":[-73.827307,41.034362],"type":"Point"}
}