{
  "type": "Feature",
  "properties": {
    "addr:full":"41 Harris Hill Rd Elmira NY 14903",
    "addr:housenumber":"41",
    "addr:postcode":"14903",
    "addr:street":"Harris Hill Rd",
    "iso:country":"US",
    "sg:address":"41 Harris Hill Rd",
    "sg:city":"Elmira",
    "sg:classifiers":[
        {
            "category":"Professional",
            "subcategory":"Business Services",
            "type":"Services"
        }
    ],
    "sg:phone":"+1 607 737 3664",
    "sg:postcode":"14903",
    "sg:province":"NY",
    "sg:tags":[
        "water",
        "treatment"
    ],
    "wof:name":"Bailey Water Conditioning",
    "wof:placetype":"venue"
},
  "geometry": {"coordinates":[-76.907341,42.100754],"type":"Point"}
}