{
  "type": "Feature",
  "properties": {
    "addr:full":"2586 Carmel Ave Brewster NY 10509",
    "addr:housenumber":"2586",
    "addr:postcode":"10509",
    "addr:street":"Carmel Ave",
    "iso:country":"US",
    "sg:address":"2586 Carmel Ave",
    "sg:city":"Brewster",
    "sg:classifiers":[
        {
            "category":"Deli",
            "type":"Food & Drink"
        },
        {
            "category":"Food & Beverages",
            "subcategory":"Groceries & Convenience Stores",
            "type":"Retail Goods"
        }
    ],
    "sg:phone":"+1 856 279 1586",
    "sg:postcode":"10509",
    "sg:province":"NY",
    "wof:name":"Brewster Superette",
    "wof:placetype":"venue"
},
  "geometry": {"coordinates":[-73.625603,41.3993],"type":"Point"}
}