{
  "type": "Feature",
  "properties": {
    "addr:full":"174 Java St Brooklyn NY 11222",
    "addr:housenumber":"174",
    "addr:postcode":"11222",
    "addr:street":"Java St",
    "iso:country":"US",
    "sg:address":"174 Java St",
    "sg:city":"Brooklyn",
    "sg:classifiers":[
        {
            "category":"Professional",
            "type":"Services"
        }
    ],
    "sg:phone":"+1 718 609 1147",
    "sg:postcode":"11222",
    "sg:province":"NY",
    "sg:tags":[
        "establishment"
    ],
    "wof:name":"Buidlers For Families",
    "wof:placetype":"venue"
},
  "geometry": {"coordinates":[-73.95234000000001,40.73173],"type":"Point"}
}