{
  "type": "Feature",
  "properties": {
    "iso:country":"US",
    "sg:address":"913 W Beech St",
    "sg:city":"Long Beach",
    "sg:classifiers":[
        {
            "category":"Restaurant",
            "type":"Food & Drink"
        }
    ],
    "sg:menulink":"http://www.allmenus.com/ny/long-beach/254123-merry-land-chinese-restaurant/menu/",
    "sg:phone":"+1 516 431 1122",
    "sg:postcode":"11561",
    "sg:province":"NY",
    "sg:tags":[
        "asian",
        "chinese"
    ],
    "wof:name":"Merry Land Chinese Restaurant",
    "wof:placetype":"venue"
},
  "geometry": {"coordinates":[-73.69223,40.586021],"type":"Point"}
}