{
  "type": "Feature",
  "properties": {
    "addr:full":"1841 Park Ave New York NY 10035",
    "addr:housenumber":"1841",
    "addr:postcode":"10035",
    "addr:street":"Park Ave",
    "iso:country":"US",
    "sg:address":"1841 Park Ave",
    "sg:city":"New York",
    "sg:classifiers":[
        {
            "category":"Organizations",
            "subcategory":"Professional Association",
            "type":"Services"
        }
    ],
    "sg:phone":"+1 212 534 8622",
    "sg:postcode":"10035",
    "sg:province":"NY",
    "wof:name":"Association To Benefit Child",
    "wof:placetype":"venue"
},
  "geometry": {"coordinates":[-73.93808799999999,40.806353],"type":"Point"}
}