{
  "type": "Feature",
  "properties": {
    "iso:country":"US",
    "sg:address":"100 Corporate Dr",
    "sg:city":"Yonkers",
    "sg:classifiers":[
        {
            "category":"Health Services",
            "subcategory":"Medical Lab",
            "type":"Services"
        }
    ],
    "sg:phone":"+1 914 969 3399",
    "sg:postcode":"10701",
    "sg:province":"NY",
    "sg:tags":[
        "genetic",
        "testing",
        "human"
    ],
    "wof:name":"Genzyme Genetics",
    "wof:placetype":"venue"
},
  "geometry": {"coordinates":[-73.87729899999999,40.970546],"type":"Point"}
}