{
  "type": "Feature",
  "properties": {
    "addr:full":"1299 Boston Rd Bronx NY 10456",
    "addr:housenumber":"1299",
    "addr:postcode":"10456",
    "addr:street":"Boston Rd",
    "iso:country":"US",
    "sg:address":"1299 Boston Rd",
    "sg:city":"Bronx",
    "sg:classifiers":[
        {
            "category":"Restaurant",
            "type":"Food & Drink"
        }
    ],
    "sg:menulink":"http://www.allmenus.com/ny/bronx/60879-golden-krust/menu/",
    "sg:phone":"+1 718 378 1133",
    "sg:postcode":"10456",
    "sg:province":"NY",
    "sg:tags":[
        "caribbean"
    ],
    "wof:name":"Golden Krust",
    "wof:placetype":"venue"
},
  "geometry": {"coordinates":[-73.899562,40.831671],"type":"Point"}
}