{
  "type": "Feature",
  "properties": {
    "addr:full":"493 Amherst St Buffalo NY 14207",
    "addr:housenumber":"493",
    "addr:postcode":"14207",
    "addr:street":"Amherst St",
    "iso:country":"US",
    "sg:address":"493 Amherst St",
    "sg:city":"Buffalo",
    "sg:classifiers":[
        {
            "category":"Insurance",
            "subcategory":"Insurance Agent",
            "type":"Services"
        }
    ],
    "sg:phone":"+1 716 876 5888",
    "sg:postcode":"14207",
    "sg:province":"NY",
    "wof:name":"L T Insurance",
    "wof:placetype":"venue"
},
  "geometry": {"coordinates":[-78.886066,42.93947],"type":"Point"}
}