{
  "type": "Feature",
  "properties": {
    "addr:full":"74-02 43 Ave Ste 5A Elmhurst NY 11373",
    "addr:housenumber":"74-02",
    "addr:postcode":"11373",
    "addr:street":"43 Ave Ste 5A",
    "iso:country":"US",
    "sg:address":"74-02 43 Ave Ste 5A",
    "sg:city":"Elmhurst",
    "sg:classifiers":[
        {
            "category":"Professional",
            "subcategory":"Art Services",
            "type":"Services"
        },
        {
            "category":"Communications",
            "type":"Services"
        },
        {
            "category":"Professional",
            "subcategory":"Computer Services",
            "type":"Services"
        }
    ],
    "sg:phone":"+1 347 418 8728",
    "sg:postcode":"11373",
    "sg:province":"NY",
    "sg:tags":[
        "repair",
        "graphic",
        "design",
        "web"
    ],
    "sg:website":"www.airlure.com",
    "wof:name":"Airlure Seo Web Design Consulting & Website Development Company",
    "wof:placetype":"venue"
},
  "geometry": {"coordinates":[-73.869248,40.745245],"type":"Point"}
}