{
  "type": "Feature",
  "properties": {
    "iso:country":"US",
    "sg:address":"155 All Angels Hill Rd",
    "sg:city":"Wappingers Falls",
    "sg:classifiers":[
        {
            "category":"Health Services",
            "subcategory":"Chiropractor",
            "type":"Services"
        }
    ],
    "sg:phone":"+1   ",
    "sg:postcode":"12590",
    "sg:province":"NY",
    "wof:name":"Thomas J Amodeo",
    "wof:placetype":"venue"
},
  "geometry": {"coordinates":[-73.86892899999999,41.595927],"type":"Point"}
}