{
  "type": "Feature",
  "properties": {
    "addr:full":"148 Heyward St Brentwood NY 11717",
    "addr:housenumber":"148",
    "addr:postcode":"11717",
    "addr:street":"Heyward St",
    "iso:country":"US",
    "sg:address":"148 Heyward St",
    "sg:city":"Brentwood",
    "sg:classifiers":[
        {
            "category":"Autos & Motor Vehicles",
            "subcategory":"Auto Supplies",
            "type":"Retail Goods"
        }
    ],
    "sg:phone":"+1 631 273 6262",
    "sg:postcode":"11717",
    "sg:province":"NY",
    "sg:tags":[
        "automobile",
        "part"
    ],
    "wof:name":"Auto Parts Depot Inc",
    "wof:placetype":"venue"
},
  "geometry": {"coordinates":[-73.250248,40.798338],"type":"Point"}
}