{
  "type": "Feature",
  "properties": {
    "iso:country":"US",
    "sg:address":"922 Rte 25A",
    "sg:city":"Miller Place",
    "sg:classifiers":[
        {
            "category":"Freight",
            "type":"Transportation"
        }
    ],
    "sg:phone":"+1   ",
    "sg:postcode":"11764",
    "sg:province":"NY",
    "sg:tags":[
        "special",
        "merchandise"
    ],
    "wof:name":"East End Storage",
    "wof:placetype":"venue"
},
  "geometry": {"coordinates":[-72.96728400000001,40.944167],"type":"Point"}
}