{
  "type": "Feature",
  "properties": {
    "iso:country":"US",
    "sg:address":"4 W Main St",
    "sg:city":"Cambridge",
    "sg:classifiers":[
        {
            "category":"Restaurant",
            "type":"Food & Drink"
        }
    ],
    "sg:phone":"+1 518 677 6001",
    "sg:postcode":"12816",
    "sg:province":"NY",
    "wof:name":"Cambridge Fare Restaurant",
    "wof:placetype":"venue"
},
  "geometry": {"coordinates":[-73.381027,43.028011],"type":"Point"}
}