{
  "type": "Feature",
  "properties": {
    "iso:country":"US",
    "sg:address":"8 W 30th Street",
    "sg:city":"Brooklyn",
    "sg:classifiers":[
        {
            "category":"Building & Trades",
            "subcategory":"Locksmith",
            "type":"Services"
        }
    ],
    "sg:phone":"+1 347 225 8927",
    "sg:postcode":"11224",
    "sg:province":"NY",
    "sg:tags":[
        "key"
    ],
    "wof:name":"24 Hr Locksmith Svc On 30 St",
    "wof:placetype":"venue"
},
  "geometry": {"coordinates":[-73.989278,40.577572],"type":"Point"}
}