{
  "type": "Feature",
  "properties": {
    "addr:full":"4351 Churton Rd Vernon NY 13476",
    "addr:housenumber":"4351",
    "addr:postcode":"13476",
    "addr:street":"Churton Rd",
    "iso:country":"US",
    "sg:address":"4351 Churton Rd",
    "sg:city":"Vernon",
    "sg:classifiers":[
        {
            "category":"Restaurant",
            "type":"Food & Drink"
        }
    ],
    "sg:phone":"+1   ",
    "sg:postcode":"13476",
    "sg:province":"NY",
    "sg:tags":[
        "drinking",
        "eating"
    ],
    "wof:name":"Black Stallion Restaurant",
    "wof:placetype":"venue"
},
  "geometry": {"coordinates":[-75.506168,43.054798],"type":"Point"}
}