{
  "type": "Feature",
  "properties": {
    "iso:country":"US",
    "sg:address":"811 Maine Ave",
    "sg:city":"Bay Shore",
    "sg:classifiers":[
        {
            "category":"Wholesale",
            "subcategory":"Vending Machines",
            "type":"Manufacturing & Wholesale Goods"
        }
    ],
    "sg:phone":"+1   ",
    "sg:postcode":"11706",
    "sg:province":"NY",
    "sg:tags":[
        "operator"
    ],
    "wof:name":"Desantis Vending Svc",
    "wof:placetype":"venue"
},
  "geometry": {"coordinates":[-73.246792,40.762237],"type":"Point"}
}