{
  "type": "Feature",
  "properties": {
    "addr:full":"319 Flatbush Ave Brooklyn NY 11217",
    "addr:housenumber":"319",
    "addr:postcode":"11217",
    "addr:street":"Flatbush Ave",
    "iso:country":"US",
    "sg:address":"319 Flatbush Ave",
    "sg:city":"Brooklyn",
    "sg:classifiers":[
        {
            "category":"Professional",
            "subcategory":"Printing & Photocopies",
            "type":"Services"
        }
    ],
    "sg:phone":"+1 718 399 8530",
    "sg:postcode":"11217",
    "sg:province":"NY",
    "sg:tags":[
        "duplicating",
        "copying"
    ],
    "wof:name":"One Hour Photo",
    "wof:placetype":"venue"
},
  "geometry": {"coordinates":[-73.9727,40.677654],"type":"Point"}
}