{
  "type": "Feature",
  "properties": {
    "addr:full":"8 Rivington St New York NY 10002",
    "addr:housenumber":"8",
    "addr:postcode":"10002",
    "addr:street":"Rivington St",
    "iso:country":"US",
    "sg:address":"8 Rivington St",
    "sg:city":"New York",
    "sg:classifiers":[
        {
            "category":"Building & Trades",
            "subcategory":"Construction",
            "type":"Services"
        }
    ],
    "sg:phone":"+1 212 387 7831",
    "sg:postcode":"10002",
    "sg:province":"NY",
    "sg:tags":[
        "house"
    ],
    "wof:name":"Sansum Construction Inc",
    "wof:placetype":"venue"
},
  "geometry": {"coordinates":[-73.992237,40.721247],"type":"Point"}
}