{
  "type": "Feature",
  "properties": {
    "addr:full":"180 Lake St Rouses Point NY 12979",
    "addr:housenumber":"180",
    "addr:postcode":"12979",
    "addr:street":"Lake St",
    "iso:country":"US",
    "sg:address":"180 Lake St",
    "sg:city":"Rouses Point",
    "sg:classifiers":[
        {
            "category":"Real Estate",
            "subcategory":"Real Estate Agent",
            "type":"Services"
        }
    ],
    "sg:phone":"+1 518 297 3739",
    "sg:postcode":"12979",
    "sg:province":"NY",
    "wof:name":"OH Real Est Inc",
    "wof:placetype":"venue"
},
  "geometry": {"coordinates":[-73.363567,44.986535],"type":"Point"}
}