{
  "type": "Feature",
  "properties": {
    "iso:country":"US",
    "sg:address":"543 W Merrick Rd",
    "sg:city":"Valley Stream",
    "sg:classifiers":[
        {
            "category":"Retail",
            "subcategory":"Self-service Laundry",
            "type":"Services"
        }
    ],
    "sg:phone":"+1 516 825 8287",
    "sg:postcode":"11580",
    "sg:province":"NY",
    "wof:name":"Laundry Express",
    "wof:placetype":"venue"
},
  "geometry": {"coordinates":[-73.713897,40.668947],"type":"Point"}
}