{
  "type": "Feature",
  "properties": {
    "addr:full":"680 Chenango St Binghamton NY 13901",
    "addr:housenumber":"680",
    "addr:postcode":"13901",
    "addr:street":"Chenango St",
    "iso:country":"US",
    "sg:address":"680 Chenango St",
    "sg:city":"Binghamton",
    "sg:classifiers":[
        {
            "category":"Real Estate",
            "subcategory":"Real Estate Agent",
            "type":"Services"
        }
    ],
    "sg:phone":"+1 607 723 8359",
    "sg:postcode":"13901",
    "sg:province":"NY",
    "sg:tags":[
        "business"
    ],
    "wof:name":"Coldwell Banker",
    "wof:placetype":"venue"
},
  "geometry": {"coordinates":[-75.896717,42.128722],"type":"Point"}
}