{
  "type": "Feature",
  "properties": {
    "addr:full":"37 Mott St New York NY 10013",
    "addr:housenumber":"37",
    "addr:postcode":"10013",
    "addr:street":"Mott St",
    "iso:country":"US",
    "sg:address":"37 Mott St",
    "sg:city":"New York",
    "sg:classifiers":[
        {
            "category":"Shopping",
            "subcategory":"Clothing, Apparel, & Fashions",
            "type":"Retail Goods"
        }
    ],
    "sg:phone":"+1   ",
    "sg:postcode":"10013",
    "sg:province":"NY",
    "sg:tags":[
        "ready",
        "clothes",
        "shoe",
        "accessory"
    ],
    "wof:name":"Gee Boutique",
    "wof:placetype":"venue"
},
  "geometry": {"coordinates":[-73.998796,40.714501],"type":"Point"}
}