{
  "type": "Feature",
  "properties": {
    "iso:country":"US",
    "sg:address":"34 East Ln",
    "sg:city":"Spring Valley",
    "sg:classifiers":[
        {
            "category":"Social Services",
            "type":"Services"
        }
    ],
    "sg:phone":"+1   ",
    "sg:postcode":"10977",
    "sg:province":"NY",
    "sg:website":"www.focusing.org",
    "wof:name":"Focusing Institute",
    "wof:placetype":"venue"
},
  "geometry": {"coordinates":[-74.056164,41.163401],"type":"Point"}
}