{
  "type": "Feature",
  "properties": {
    "addr:full":"53 E 34 St New York NY 10016",
    "addr:housenumber":"53;34",
    "addr:postcode":"10016",
    "addr:street":"E;St",
    "iso:country":"US",
    "sg:address":"53 E 34 St",
    "sg:city":"New York",
    "sg:classifiers":[
        {
            "category":"Professional",
            "subcategory":"Detective & Security Services",
            "type":"Services"
        }
    ],
    "sg:phone":"+1 212 683 3465",
    "sg:postcode":"10016",
    "sg:province":"NY",
    "sg:tags":[
        "car",
        "legal"
    ],
    "wof:name":"Counter-Tech Investigations",
    "wof:placetype":"venue"
},
  "geometry": {"coordinates":[-73.981741,40.747424],"type":"Point"}
}