{
  "type": "Feature",
  "properties": {
    "addr:full":"82 Tompkins Rd Verbank NY 12585",
    "addr:housenumber":"82",
    "addr:postcode":"12585",
    "addr:street":"Tompkins Rd",
    "iso:country":"US",
    "sg:address":"82 Tompkins Rd",
    "sg:city":"Verbank",
    "sg:classifiers":[
        {
            "category":"Food & Beverages",
            "subcategory":"Groceries & Convenience Stores",
            "type":"Retail Goods"
        }
    ],
    "sg:phone":"+1 845 677 3882",
    "sg:postcode":"12585",
    "sg:province":"NY",
    "wof:name":"Badda Bing Ii",
    "wof:placetype":"venue"
},
  "geometry": {"coordinates":[-73.730226,41.719353],"type":"Point"}
}