{
  "type": "Feature",
  "properties": {
    "addr:full":"252 Soundview Ave White Plains NY 10606",
    "addr:housenumber":"252",
    "addr:postcode":"10606",
    "addr:street":"Soundview Ave",
    "iso:country":"US",
    "sg:address":"252 Soundview Ave",
    "sg:city":"White Plains",
    "sg:classifiers":[
        {
            "category":"Social Services",
            "subcategory":"Child Care",
            "type":"Services"
        }
    ],
    "sg:phone":"+1 914 949 0067",
    "sg:postcode":"10606",
    "sg:province":"NY",
    "wof:name":"Kodomono KUNI Inc",
    "wof:placetype":"venue"
},
  "geometry": {"coordinates":[-73.76693400000001,41.004192],"type":"Point"}
}