{
  "type": "Feature",
  "properties": {
    "addr:full":"585 Plandome Rd Manhasset NY 11030",
    "addr:housenumber":"585",
    "addr:postcode":"11030",
    "addr:street":"Plandome Rd",
    "iso:country":"US",
    "sg:address":"585 Plandome Rd",
    "sg:city":"Manhasset",
    "sg:classifiers":[
        {
            "category":"Health Services",
            "subcategory":"Doctor",
            "type":"Services"
        }
    ],
    "sg:phone":"+1 516 627 1525",
    "sg:postcode":"11030",
    "sg:province":"NY",
    "sg:tags":[
        "physician",
        "surgeon"
    ],
    "wof:name":"Shelter Rock Orthopedic Group",
    "wof:placetype":"venue"
},
  "geometry": {"coordinates":[-73.702966,40.801351],"type":"Point"}
}