{
  "type": "Feature",
  "properties": {
    "addr:full":"53 Ludlow St Manhattan NY 10002",
    "addr:housenumber":"53",
    "addr:postcode":"10002",
    "addr:street":"Ludlow St",
    "iso:country":"US",
    "sg:address":"53 Ludlow St",
    "sg:city":"Manhattan",
    "sg:classifiers":[
        {
            "category":"Personal",
            "type":"Services"
        },
        {
            "category":"Professional",
            "subcategory":"Art Services",
            "type":"Services"
        }
    ],
    "sg:phone":"+1 917 512 8553",
    "sg:postcode":"10002",
    "sg:province":"NY",
    "sg:tags":[
        "photographer",
        "planning",
        "wedding"
    ],
    "sg:website":"www.chrischenstudios.com",
    "wof:name":"Chris Chen Studios",
    "wof:placetype":"venue"
},
  "geometry": {"coordinates":[-73.99036,40.716662],"type":"Point"}
}