{
  "type": "Feature",
  "properties": {
    "addr:full":"3800 W Henrietta Rd Rochester NY 14623",
    "addr:housenumber":"3800",
    "addr:postcode":"14623",
    "addr:street":"W Henrietta Rd",
    "iso:country":"US",
    "sg:address":"3800 W Henrietta Rd",
    "sg:city":"Rochester",
    "sg:classifiers":[
        {
            "category":"Shopping",
            "subcategory":"Adult",
            "type":"Retail Goods"
        },
        {
            "category":"Bars & Pubs",
            "subcategory":"Nightclub",
            "type":"Food & Drink"
        },
        {
            "category":"Organizations",
            "subcategory":"Community Association",
            "type":"Services"
        }
    ],
    "sg:phone":"+1 585 359 8639",
    "sg:postcode":"14623",
    "sg:province":"NY",
    "sg:tags":[
        "club",
        "night",
        "entertainment"
    ],
    "sg:website":"http://www.klassycattavern.com",
    "wof:name":"Klassy Cat",
    "wof:placetype":"venue"
},
  "geometry": {"coordinates":[-77.641693,43.07803],"type":"Point"}
}