{
  "type": "Feature",
  "properties": {
    "iso:country":"US",
    "sg:address":"315 5th Ave",
    "sg:city":"Brooklyn",
    "sg:classifiers":[
        {
            "category":"Professional",
            "type":"Services"
        }
    ],
    "sg:phone":"+1 718 788 6622",
    "sg:postcode":"11215",
    "sg:province":"NY",
    "sg:tags":[
        "establishment"
    ],
    "wof:name":"Zvi",
    "wof:placetype":"venue"
},
  "geometry": {"coordinates":[-73.98288100000001,40.673292],"type":"Point"}
}