{
  "type": "Feature",
  "properties": {
    "addr:full":"42 Barrett Rd Lawrence NY 11559",
    "addr:housenumber":"42",
    "addr:postcode":"11559",
    "addr:street":"Barrett Rd",
    "iso:country":"US",
    "sg:address":"42 Barrett Rd",
    "sg:city":"Lawrence",
    "sg:classifiers":[
        {
            "category":"Banks & Credit Unions",
            "subcategory":"Bank",
            "type":"Services"
        }
    ],
    "sg:phone":"+1 516 239 2360",
    "sg:postcode":"11559",
    "sg:province":"NY",
    "sg:tags":[
        "company",
        "investment"
    ],
    "wof:name":"Madison Venture Capital II",
    "wof:placetype":"venue"
},
  "geometry": {"coordinates":[-73.720972,40.610913],"type":"Point"}
}