{
  "type": "Feature",
  "properties": {
    "addr:full":"14229 37th Avenue Flushing NY 11354",
    "addr:housenumber":"14229",
    "addr:postcode":"11354",
    "addr:street":"37Th Avenue",
    "iso:country":"US",
    "sg:address":"14229 37th Avenue",
    "sg:city":"Flushing",
    "sg:classifiers":[
        {
            "category":"Health Services",
            "subcategory":"Health Practitioner",
            "type":"Services"
        }
    ],
    "sg:phone":"+1 718 939 6700",
    "sg:postcode":"11354",
    "sg:province":"NY",
    "sg:tags":[
        "acupuncture"
    ],
    "wof:name":"Hamsoa Ny",
    "wof:placetype":"venue"
},
  "geometry": {"coordinates":[-73.825833,40.762957],"type":"Point"}
}