{
  "type": "Feature",
  "properties": {
    "addr:full":"Flushing Meadow Park Flushing NY 11351",
    "addr:postcode":"11351",
    "addr:street":"Flushing Meadow Park",
    "iso:country":"US",
    "sg:address":"Flushing Meadow Park",
    "sg:city":"Flushing",
    "sg:classifiers":[
        {
            "category":"Restaurant",
            "type":"Food & Drink"
        }
    ],
    "sg:phone":"+1 718 595 1561",
    "sg:postcode":"11351",
    "sg:province":"NY",
    "wof:name":"Restaurant Assocs",
    "wof:placetype":"venue"
},
  "geometry": {"coordinates":[-73.826651,40.781647],"type":"Point"}
}