{
  "type": "Feature",
  "properties": {
    "addr:full":"979 3rd Ave Ste 1640 New York NY 10022",
    "addr:housenumber":"979",
    "addr:postcode":"1640;10022",
    "addr:street":"3Rd Ave Ste",
    "iso:country":"US",
    "sg:address":"979 3rd Ave Ste 1640",
    "sg:city":"New York",
    "sg:classifiers":[
        {
            "category":"Home & Garden",
            "subcategory":"Furniture",
            "type":"Retail Goods"
        }
    ],
    "sg:phone":"+1 646 497 1502",
    "sg:postcode":"10022",
    "sg:province":"NY",
    "sg:tags":[
        "store"
    ],
    "sg:website":"www.michaeltaylordesigns.com",
    "wof:name":"Michael Taylor Designs",
    "wof:placetype":"venue"
},
  "geometry": {"coordinates":[-73.966607,40.761126],"type":"Point"}
}