{
  "type": "Feature",
  "properties": {
    "addr:full":"2409 Robinson Rd Chittenango NY 13037",
    "addr:housenumber":"2409",
    "addr:postcode":"13037",
    "addr:street":"Robinson Rd",
    "iso:country":"US",
    "sg:address":"2409 Robinson Rd",
    "sg:city":"Chittenango",
    "sg:classifiers":[
        {
            "category":"Shopping",
            "subcategory":"Stationery & Office Supplies",
            "type":"Retail Goods"
        },
        {
            "category":"Wholesale",
            "subcategory":"Office Equipment",
            "type":"Manufacturing & Wholesale Goods"
        },
        {
            "category":"Professional",
            "subcategory":"Business Services",
            "type":"Services"
        },
        {
            "category":"Professional",
            "subcategory":"Printing & Photocopies",
            "type":"Services"
        },
        {
            "category":"Manufacturing",
            "subcategory":"Paper Products",
            "type":"Manufacturing & Wholesale Goods"
        }
    ],
    "sg:phone":"+1 315 687 0186",
    "sg:postcode":"13037",
    "sg:province":"NY",
    "sg:tags":[
        "form",
        "register",
        "autographic",
        "system",
        "printers-business",
        "stationery-wholesale",
        "store",
        "manufacturer"
    ],
    "sg:website":"http://www.standardregister.com/",
    "wof:name":"Standard Register",
    "wof:placetype":"venue"
},
  "geometry": {"coordinates":[-75.83040699999999,43.054762],"type":"Point"}
}