{
  "type": "Feature",
  "properties": {
    "addr:full":"246 Riverside Blvd Long Beach NY 11561",
    "addr:housenumber":"246",
    "addr:postcode":"11561",
    "addr:street":"Riverside Blvd",
    "iso:country":"US",
    "sg:address":"246 Riverside Blvd",
    "sg:city":"Long Beach",
    "sg:classifiers":[
        {
            "category":"Organizations",
            "subcategory":"Religious Organization",
            "type":"Services"
        }
    ],
    "sg:phone":"+1 516 889 2075",
    "sg:postcode":"11561",
    "sg:province":"NY",
    "sg:tags":[
        "clergy"
    ],
    "wof:name":"Moishe Gross",
    "wof:placetype":"venue"
},
  "geometry": {"coordinates":[-73.66105,40.587575],"type":"Point"}
}