{
  "type": "Feature",
  "properties": {
    "addr:full":"619 9th Ave Frnt 1 New York NY 10036",
    "addr:housenumber":"619;1",
    "addr:postcode":"10036",
    "addr:street":"9Th Ave Frnt",
    "iso:country":"US",
    "sg:address":"619 9th Ave Frnt 1",
    "sg:city":"New York",
    "sg:classifiers":[
        {
            "category":"Shopping",
            "subcategory":"Pharmacy",
            "type":"Retail Goods"
        }
    ],
    "sg:phone":"+1 212 957 1407",
    "sg:postcode":"10036",
    "sg:province":"NY",
    "sg:tags":[
        "drugstore"
    ],
    "wof:name":"Duanereade",
    "wof:placetype":"venue"
},
  "geometry": {"coordinates":[-73.99187999999999,40.759721],"type":"Point"}
}