{
  "type": "Feature",
  "properties": {
    "addr:full":"115 E 87 St New York NY 10128",
    "addr:housenumber":"115;87",
    "addr:postcode":"10128",
    "addr:street":"E;St",
    "iso:country":"US",
    "sg:address":"115 E 87 St",
    "sg:city":"New York",
    "sg:classifiers":[
        {
            "category":"Manufacturing",
            "subcategory":"Apparel",
            "type":"Manufacturing & Wholesale Goods"
        }
    ],
    "sg:phone":"+1   ",
    "sg:postcode":"10128",
    "sg:province":"NY",
    "sg:tags":[
        "clothing",
        "mfg"
    ],
    "wof:name":"Royal Baby Incorporated",
    "wof:placetype":"venue"
},
  "geometry": {"coordinates":[-73.955444,40.780455],"type":"Point"}
}