{
  "type": "Feature",
  "properties": {
    "addr:full":"112 North Ave Owego NY 13827",
    "addr:housenumber":"112",
    "addr:postcode":"13827",
    "addr:street":"North Ave",
    "iso:country":"US",
    "sg:address":"112 North Ave",
    "sg:city":"Owego",
    "sg:classifiers":[
        {
            "category":"Food & Beverages",
            "subcategory":"Groceries & Convenience Stores",
            "type":"Retail Goods"
        }
    ],
    "sg:phone":"+1 607 687 1411",
    "sg:postcode":"13827",
    "sg:province":"NY",
    "wof:name":"JHA Petroleum Inc",
    "wof:placetype":"venue"
},
  "geometry": {"coordinates":[-76.26364599999999,42.10524],"type":"Point"}
}