{
  "type": "Feature",
  "properties": {
    "iso:country":"US",
    "sg:address":"5978 Washington St",
    "sg:city":"Olcott",
    "sg:classifiers":[
        {
            "category":"Professional",
            "subcategory":"Engineering",
            "type":"Services"
        }
    ],
    "sg:phone":"+1 716 438 2150",
    "sg:postcode":"14126",
    "sg:province":"NY",
    "sg:tags":[
        "engineer"
    ],
    "wof:name":"Nurkwit Engineering",
    "wof:placetype":"venue"
},
  "geometry": {"coordinates":[-78.713071,43.336491],"type":"Point"}
}