{
  "type": "Feature",
  "properties": {
    "addr:full":"4 Scott Dr Middletown NY 10941",
    "addr:housenumber":"4",
    "addr:postcode":"10941",
    "addr:street":"Scott Dr",
    "iso:country":"US",
    "sg:address":"4 Scott Dr",
    "sg:city":"Middletown",
    "sg:classifiers":[
        {
            "category":"Social Services",
            "subcategory":"Child Care",
            "type":"Services"
        }
    ],
    "sg:phone":"+1 845 692 7338",
    "sg:postcode":"10941",
    "sg:province":"NY",
    "wof:name":"Little Friends Daycare",
    "wof:placetype":"venue"
},
  "geometry": {"coordinates":[-74.368917,41.483678],"type":"Point"}
}