{
  "type": "Feature",
  "properties": {
    "addr:full":"4234 White Plains Rd Bronx NY 10466",
    "addr:housenumber":"4234",
    "addr:postcode":"10466",
    "addr:street":"White Plains Rd",
    "iso:country":"US",
    "sg:address":"4234 White Plains Rd",
    "sg:city":"Bronx",
    "sg:phone":"+1 718 324 0568",
    "sg:postcode":"10466",
    "sg:province":"NY",
    "sg:tags":[
        "showroom",
        "supply"
    ],
    "wof:name":"High Quality Cabinets",
    "wof:placetype":"venue"
},
  "geometry": {"coordinates":[-73.856582,40.894632],"type":"Point"}
}