{
  "type": "Feature",
  "properties": {
    "addr:full":"1 Cold Spring Hills Rd Huntington NY 11743",
    "addr:housenumber":"1",
    "addr:postcode":"11743",
    "addr:street":"Cold Spring Hills Rd",
    "iso:country":"US",
    "sg:address":"1 Cold Spring Hills Rd",
    "sg:city":"Huntington",
    "sg:classifiers":[
        {
            "category":"Manufacturing",
            "subcategory":"Printing",
            "type":"Manufacturing & Wholesale Goods"
        }
    ],
    "sg:phone":"+1   ",
    "sg:postcode":"11743",
    "sg:province":"NY",
    "sg:tags":[
        "publishing"
    ],
    "wof:name":"Dada Visage Inc",
    "wof:placetype":"venue"
},
  "geometry": {"coordinates":[-73.443377,40.837264],"type":"Point"}
}