{
  "type": "Feature",
  "properties": {
    "addr:full":"43 E 10 St New York NY 10003",
    "addr:housenumber":"43;10",
    "addr:postcode":"10003",
    "addr:street":"E;St",
    "iso:country":"US",
    "sg:address":"43 E 10 St",
    "sg:city":"New York",
    "sg:classifiers":[
        {
            "category":"Shopping",
            "subcategory":"Used Merchandise",
            "type":"Retail Goods"
        }
    ],
    "sg:phone":"+1   ",
    "sg:postcode":"10003",
    "sg:province":"NY",
    "wof:name":"Cathers & Dembrosky",
    "wof:placetype":"venue"
},
  "geometry": {"coordinates":[-73.99241499999999,40.732355],"type":"Point"}
}