{
  "type": "Feature",
  "properties": {
    "iso:country":"US",
    "sg:address":"2 Kings Court Way",
    "sg:city":"Rochester",
    "sg:classifiers":[
        {
            "category":"Real Estate",
            "subcategory":"Real Estate Operator",
            "type":"Services"
        }
    ],
    "sg:phone":"+1 585 544 5340",
    "sg:postcode":"14617",
    "sg:province":"NY",
    "sg:tags":[
        "apartment"
    ],
    "wof:name":"Kings Court",
    "wof:placetype":"venue"
},
  "geometry": {"coordinates":[-77.57738999999999,43.205006],"type":"Point"}
}