{
  "type": "Feature",
  "properties": {
    "iso:country":"US",
    "sg:address":"425 Maple Ave",
    "sg:city":"Westbury",
    "sg:classifiers":[
        {
            "category":"Professional",
            "subcategory":"Accounting & Tax Preparation",
            "type":"Services"
        }
    ],
    "sg:phone":"+1 516 333 0155",
    "sg:postcode":"11590",
    "sg:province":"NY",
    "sg:tags":[
        "bookkeeping",
        "billing"
    ],
    "wof:name":"Rainbow Stake Service Inc",
    "wof:placetype":"venue"
},
  "geometry": {"coordinates":[-73.583814,40.756284],"type":"Point"}
}