{
  "type": "Feature",
  "properties": {
    "iso:country":"US",
    "sg:address":"491 Lexington Ave",
    "sg:city":"Mount Kisco",
    "sg:classifiers":[
        {
            "category":"Professional",
            "subcategory":"Lawyer & Legal Services",
            "type":"Services"
        }
    ],
    "sg:phone":"+1 914 241 7900",
    "sg:postcode":"10549",
    "sg:province":"NY",
    "wof:name":"Edelstein & Lochner",
    "wof:placetype":"venue"
},
  "geometry": {"coordinates":[-73.732399,41.191299],"type":"Point"}
}