{
  "type": "Feature",
  "properties": {
    "addr:full":"145 Tulip Ave Floral Park NY 11001",
    "addr:housenumber":"145",
    "addr:postcode":"11001",
    "addr:street":"Tulip Ave",
    "iso:country":"US",
    "sg:address":"145 Tulip Ave",
    "sg:city":"Floral Park",
    "sg:classifiers":[
        {
            "category":"Restaurant",
            "type":"Food & Drink"
        }
    ],
    "sg:phone":"+1 516 358 3690",
    "sg:postcode":"11001",
    "sg:province":"NY",
    "wof:name":"Halligan's Pub",
    "wof:placetype":"venue"
},
  "geometry": {"coordinates":[-73.703796,40.724499],"type":"Point"}
}