{
  "type": "Feature",
  "properties": {
    "addr:full":"361 W 121st St New York NY 10027",
    "addr:housenumber":"361",
    "addr:postcode":"10027",
    "addr:street":"W 121St St",
    "iso:country":"US",
    "sg:address":"361 W 121st St",
    "sg:city":"New York",
    "sg:classifiers":[
        {
            "category":"Personal",
            "subcategory":"Beauty Salon",
            "type":"Services"
        }
    ],
    "sg:phone":"+1   ",
    "sg:postcode":"10027",
    "sg:province":"NY",
    "sg:tags":[
        "shop"
    ],
    "wof:name":"Q Tees Hairstylist",
    "wof:placetype":"venue"
},
  "geometry": {"coordinates":[-73.955158,40.808487],"type":"Point"}
}