{
  "type": "Feature",
  "properties": {
    "addr:full":"5016 Church Ave Brooklyn NY 11203",
    "addr:housenumber":"5016",
    "addr:postcode":"11203",
    "addr:street":"Church Ave",
    "iso:country":"US",
    "sg:address":"5016 Church Ave",
    "sg:city":"Brooklyn",
    "sg:classifiers":[
        {
            "category":"Food & Beverages",
            "subcategory":"Groceries & Convenience Stores",
            "type":"Retail Goods"
        }
    ],
    "sg:phone":"+1 718 345 0938",
    "sg:postcode":"11203",
    "sg:province":"NY",
    "wof:name":"5016 Church Ave Food Corp",
    "wof:placetype":"venue"
},
  "geometry": {"coordinates":[-73.930164,40.651607],"type":"Point"}
}