{
  "type": "Feature",
  "properties": {
    "iso:country":"US",
    "sg:address":"30 Saratoga Ave",
    "sg:city":"Waterford",
    "sg:classifiers":[
        {
            "category":"Food & Beverages",
            "subcategory":"Groceries & Convenience Stores",
            "type":"Retail Goods"
        }
    ],
    "sg:phone":"+1 518 235 8679",
    "sg:postcode":"12188",
    "sg:province":"NY",
    "sg:website":"www.stewartsicecream.com",
    "wof:name":"Stewart's Shop",
    "wof:placetype":"venue"
},
  "geometry": {"coordinates":[-73.696034,42.781262],"type":"Point"}
}