{
  "type": "Feature",
  "properties": {
    "addr:full":"2363 Pinnacle Rd Rush NY 14543",
    "addr:housenumber":"2363",
    "addr:postcode":"14543",
    "addr:street":"Pinnacle Rd",
    "iso:country":"US",
    "sg:address":"2363 Pinnacle Rd",
    "sg:city":"Rush",
    "sg:classifiers":[
        {
            "category":"Organizations",
            "subcategory":"Religious Organization",
            "type":"Services"
        }
    ],
    "sg:phone":"+1 585 533 1350",
    "sg:postcode":"14543",
    "sg:province":"NY",
    "sg:tags":[
        "church"
    ],
    "wof:name":"Korean United Presbyterian Chr",
    "wof:placetype":"venue"
},
  "geometry": {"coordinates":[-77.615014,43.018011],"type":"Point"}
}