{
  "type": "Feature",
  "properties": {
    "addr:full":"9330 43rd Ave Ste 1 Elmhurst NY 11373",
    "addr:housenumber":"9330",
    "addr:postcode":"11373",
    "addr:street":"43Rd Ave Ste 1",
    "iso:country":"US",
    "sg:address":"9330 43rd Ave Ste 1",
    "sg:city":"Elmhurst",
    "sg:classifiers":[
        {
            "category":"Shopping",
            "subcategory":"Pharmacy",
            "type":"Retail Goods"
        }
    ],
    "sg:phone":"+1 718 779 1700",
    "sg:postcode":"11373",
    "sg:province":"NY",
    "sg:tags":[
        "drugstore"
    ],
    "wof:name":"Chemist Pharmacy",
    "wof:placetype":"venue"
},
  "geometry": {"coordinates":[-73.87145,40.744075],"type":"Point"}
}