{
  "type": "Feature",
  "properties": {
    "addr:full":"447 Willis Ave Bronx NY 10455",
    "addr:housenumber":"447",
    "addr:postcode":"10455",
    "addr:street":"Willis Ave",
    "iso:country":"US",
    "sg:address":"447 Willis Ave",
    "sg:city":"Bronx",
    "sg:classifiers":[
        {
            "category":"Retail",
            "subcategory":"Laundry & Dry Cleaning",
            "type":"Services"
        }
    ],
    "sg:phone":"+1   ",
    "sg:postcode":"10455",
    "sg:province":"NY",
    "sg:tags":[
        "drycleaning",
        "plant"
    ],
    "wof:name":"One Stop Cleaner",
    "wof:placetype":"venue"
},
  "geometry": {"coordinates":[-73.919382,40.813972],"type":"Point"}
}