{
  "type": "Feature",
  "properties": {
    "addr:full":"302 E 19th St New York NY 10003",
    "addr:housenumber":"302",
    "addr:postcode":"10003",
    "addr:street":"E 19Th St",
    "iso:country":"US",
    "sg:address":"302 E 19th St",
    "sg:city":"New York",
    "sg:classifiers":[
        {
            "category":"Professional",
            "subcategory":"Lawyer & Legal Services",
            "type":"Services"
        }
    ],
    "sg:phone":"+1 347 614 7006",
    "sg:postcode":"10003",
    "sg:province":"NY",
    "wof:name":"Manfredi Law Group Pllc",
    "wof:placetype":"venue"
},
  "geometry": {"coordinates":[-73.98272,40.735273],"type":"Point"}
}