{
  "type": "Feature",
  "properties": {
    "iso:country":"US",
    "sg:address":"146 Getz Ave",
    "sg:city":"Staten Island",
    "sg:classifiers":[
        {
            "category":"Manufacturing",
            "subcategory":"Printing",
            "type":"Manufacturing & Wholesale Goods"
        }
    ],
    "sg:phone":"+1   ",
    "sg:postcode":"10312",
    "sg:province":"NY",
    "sg:tags":[
        "publishing"
    ],
    "wof:name":"Always On Point Inc",
    "wof:placetype":"venue"
},
  "geometry": {"coordinates":[-74.16612000000001,40.55635],"type":"Point"}
}