{
  "type": "Feature",
  "properties": {
    "addr:full":"19 Coons Rd Coeymans Hollow NY 12046",
    "addr:housenumber":"19",
    "addr:postcode":"12046",
    "addr:street":"Coons Rd",
    "iso:country":"US",
    "sg:address":"19 Coons Rd",
    "sg:city":"Coeymans Hollow",
    "sg:classifiers":[
        {
            "category":"Building & Trades",
            "subcategory":"Plumbing",
            "type":"Services"
        },
        {
            "category":"Manufacturing",
            "subcategory":"Tools & Machinery",
            "type":"Manufacturing & Wholesale Goods"
        }
    ],
    "sg:phone":"+1 518 756 3403",
    "sg:postcode":"12046",
    "sg:province":"NY",
    "sg:tags":[
        "industrial",
        "equipment",
        "material",
        "handling",
        "contractor"
    ],
    "wof:name":"Catskill Mountain Mechanical",
    "wof:placetype":"venue"
},
  "geometry": {"coordinates":[-73.90526300000001,42.482952],"type":"Point"}
}