{
  "type": "Feature",
  "properties": {
    "iso:country":"US",
    "sg:address":"1454 State Rte 104",
    "sg:city":"Ontario",
    "sg:classifiers":[
        {
            "category":"Restaurant",
            "type":"Food & Drink"
        }
    ],
    "sg:phone":"+1 315 524 8611",
    "sg:postcode":"14519",
    "sg:province":"NY",
    "wof:name":"Digravio Pizzaria",
    "wof:placetype":"venue"
},
  "geometry": {"coordinates":[-77.316016,43.2276],"type":"Point"}
}