{
  "type": "Feature",
  "properties": {
    "addr:full":"236 E 13th St New York NY 10003",
    "addr:housenumber":"236",
    "addr:postcode":"10003",
    "addr:street":"E 13Th St",
    "iso:country":"US",
    "sg:address":"236 E 13th St",
    "sg:city":"New York",
    "sg:classifiers":[
        {
            "category":"Personal",
            "subcategory":"Day Spa",
            "type":"Services"
        },
        {
            "category":"Personal",
            "subcategory":"Skin Care",
            "type":"Services"
        }
    ],
    "sg:phone":"+1 212 505 1599",
    "sg:postcode":"10003",
    "sg:province":"NY",
    "sg:website":"tamago-skincare.com/index.html",
    "wof:name":"Tamago Skin Care",
    "wof:placetype":"venue"
},
  "geometry": {"coordinates":[-73.98628600000001,40.731755],"type":"Point"}
}