{
  "type": "Feature",
  "properties": {
    "addr:full":"140 W 76 St New York NY 10023",
    "addr:housenumber":"140",
    "addr:postcode":"10023",
    "addr:street":"W 76 St",
    "iso:country":"US",
    "sg:address":"140 W 76 St",
    "sg:city":"New York",
    "sg:classifiers":[
        {
            "category":"Manufacturing",
            "subcategory":"Printing",
            "type":"Manufacturing & Wholesale Goods"
        }
    ],
    "sg:phone":"+1 212 799 7999",
    "sg:postcode":"10023",
    "sg:province":"NY",
    "sg:tags":[
        "multimedia"
    ],
    "wof:name":"121 Media",
    "wof:placetype":"venue"
},
  "geometry": {"coordinates":[-73.978905,40.78064],"type":"Point"}
}