{
  "type": "Feature",
  "properties": {
    "iso:country":"US",
    "sg:address":"4302 1st Ave",
    "sg:city":"Brooklyn",
    "sg:classifiers":[
        {
            "category":"Wholesale",
            "subcategory":"Groceries",
            "type":"Manufacturing & Wholesale Goods"
        }
    ],
    "sg:phone":"+1 718 499 3985",
    "sg:postcode":"11232",
    "sg:province":"NY",
    "sg:tags":[
        "beverage"
    ],
    "wof:name":"K & L Beverages Inc",
    "wof:placetype":"venue"
},
  "geometry": {"coordinates":[-74.015682,40.653837],"type":"Point"}
}