{
  "type": "Feature",
  "properties": {
    "addr:full":"155 E 72nd Street New York NY 10021",
    "addr:housenumber":"155",
    "addr:postcode":"10021",
    "addr:street":"E 72Nd Street",
    "iso:country":"US",
    "sg:address":"155 E 72nd Street",
    "sg:city":"New York",
    "sg:classifiers":[
        {
            "category":"Real Estate",
            "subcategory":"Real Estate Operator",
            "type":"Services"
        }
    ],
    "sg:phone":"+1 212 288 3751",
    "sg:postcode":"10021",
    "sg:province":"NY",
    "sg:tags":[
        "apartment"
    ],
    "wof:name":"Apartments & Apartment Houses",
    "wof:placetype":"venue"
},
  "geometry": {"coordinates":[-73.96156000000001,40.770145],"type":"Point"}
}