{
  "type": "Feature",
  "properties": {
    "addr:full":"235 Hampton Rd Southampton NY 11968",
    "addr:housenumber":"235",
    "addr:postcode":"11968",
    "addr:street":"Hampton Rd",
    "iso:country":"US",
    "sg:address":"235 Hampton Rd",
    "sg:city":"Southampton",
    "sg:classifiers":[
        {
            "category":"Professional",
            "subcategory":"Lawyer & Legal Services",
            "type":"Services"
        }
    ],
    "sg:phone":"+1 631 287 3972",
    "sg:postcode":"11968",
    "sg:province":"NY",
    "sg:tags":[
        "attorney"
    ],
    "wof:name":"Linda Riley",
    "wof:placetype":"venue"
},
  "geometry": {"coordinates":[-72.382823,40.889796],"type":"Point"}
}