{
  "type": "Feature",
  "properties": {
    "addr:full":"103 Stafford Way Rochester NY 14626",
    "addr:housenumber":"103",
    "addr:postcode":"14626",
    "addr:street":"Stafford Way",
    "iso:country":"US",
    "sg:address":"103 Stafford Way",
    "sg:city":"Rochester",
    "sg:classifiers":[
        {
            "category":"Building & Trades",
            "subcategory":"Construction",
            "type":"Services"
        }
    ],
    "sg:phone":"+1 585 368 0982",
    "sg:postcode":"14626",
    "sg:province":"NY",
    "wof:name":"J-E-C Construction",
    "wof:placetype":"venue"
},
  "geometry": {"coordinates":[-77.714581,43.217508],"type":"Point"}
}