{
  "type": "Feature",
  "properties": {
    "iso:country":"US",
    "sg:address":"350 Park Ave",
    "sg:city":"New York",
    "sg:classifiers":[
        {
            "category":"Banks & Credit Unions",
            "subcategory":"Bank",
            "type":"Services"
        }
    ],
    "sg:phone":"+1 212 415 1000",
    "sg:postcode":"10022",
    "sg:province":"NY",
    "wof:name":"Chase Manhattan",
    "wof:placetype":"venue"
},
  "geometry": {"coordinates":[-73.973341,40.758094],"type":"Point"}
}