{
  "type": "Feature",
  "properties": {
    "addr:full":"2576 3rd Ave Bronx NY 10454",
    "addr:housenumber":"2576",
    "addr:postcode":"10454",
    "addr:street":"3Rd Ave",
    "iso:country":"US",
    "sg:address":"2576 3rd Ave",
    "sg:city":"Bronx",
    "sg:phone":"+1 718 292 9470",
    "sg:postcode":"10454",
    "sg:province":"NY",
    "sg:website":"http://newyork.citysearch.com/profile/external/603158242/bronx_ny/sweetwater_s_bar_grill_lounge.html?publisher=yellowpages&reference_id=1&placement=ypwebsitemip",
    "wof:name":"Sweetwater's Bar, Grill & Lounge",
    "wof:placetype":"venue"
},
  "geometry": {"coordinates":[-73.926254,40.811591],"type":"Point"}
}