{
  "type": "Feature",
  "properties": {
    "addr:full":"107 Marshall St Syracuse NY 13210",
    "addr:housenumber":"107",
    "addr:postcode":"13210",
    "addr:street":"Marshall St",
    "iso:country":"US",
    "sg:address":"107 Marshall St",
    "sg:city":"Syracuse",
    "sg:classifiers":[
        {
            "category":"Restaurant",
            "type":"Food & Drink"
        }
    ],
    "sg:menulink":"http://www.allmenus.com/ny/syracuse/18780-the-pita-pit/menu/",
    "sg:phone":"+1 315 479 0473",
    "sg:postcode":"13210",
    "sg:province":"NY",
    "sg:tags":[
        "pita",
        "american"
    ],
    "wof:name":"The Pita Pit",
    "wof:placetype":"venue"
},
  "geometry": {"coordinates":[-76.136428,43.041595],"type":"Point"}
}