{
  "type": "Feature",
  "properties": {
    "addr:full":"271 New Scotland South Rd Slingerlands NY 12159",
    "addr:housenumber":"271",
    "addr:postcode":"12159",
    "addr:street":"New Scotland South Rd",
    "iso:country":"US",
    "sg:address":"271 New Scotland South Rd",
    "sg:city":"Slingerlands",
    "sg:classifiers":[
        {
            "category":"Professional",
            "subcategory":"Accounting & Tax Preparation",
            "type":"Services"
        }
    ],
    "sg:phone":"+1 518 439 0153",
    "sg:postcode":"12159",
    "sg:province":"NY",
    "sg:tags":[
        "public",
        "accountants-certified"
    ],
    "wof:name":"Anthony J Maddaloni",
    "wof:placetype":"venue"
},
  "geometry": {"coordinates":[-73.907692,42.617298],"type":"Point"}
}