{
  "type": "Feature",
  "properties": {
    "iso:country":"US",
    "sg:address":"130 Orinoco Dr",
    "sg:city":"Brightwaters",
    "sg:classifiers":[
        {
            "category":"Professional",
            "subcategory":"Management & Consulting",
            "type":"Services"
        }
    ],
    "sg:phone":"+1 631 665 6475",
    "sg:postcode":"11718",
    "sg:province":"NY",
    "wof:name":"Brightwter Elder Spcalist Team",
    "wof:placetype":"venue"
},
  "geometry": {"coordinates":[-73.263959,40.721463],"type":"Point"}
}