{
  "type": "Feature",
  "properties": {
    "addr:full":"3411 Danbury Rd Brewster NY 10509",
    "addr:housenumber":"3411",
    "addr:postcode":"10509",
    "addr:street":"Danbury Rd",
    "iso:country":"US",
    "sg:address":"3411 Danbury Rd",
    "sg:city":"Brewster",
    "sg:classifiers":[
        {
            "category":"Autos & Motor Vehicles",
            "subcategory":"Fuel & Gas Station",
            "type":"Retail Goods"
        }
    ],
    "sg:phone":"+1 845 940 1095",
    "sg:postcode":"10509",
    "sg:province":"NY",
    "wof:name":"Friendly Service Inc",
    "wof:placetype":"venue"
},
  "geometry": {"coordinates":[-73.59434899999999,41.392221],"type":"Point"}
}