{
  "type": "Feature",
  "properties": {
    "addr:full":"186 Joralemon St Ste 1010 Brooklyn NY 11201",
    "addr:housenumber":"186",
    "addr:postcode":"11201",
    "addr:street":"Joralemon St Ste 1010",
    "iso:country":"US",
    "sg:address":"186 Joralemon St Ste 1010",
    "sg:city":"Brooklyn",
    "sg:classifiers":[
        {
            "category":"Professional",
            "subcategory":"Lawyer & Legal Services",
            "type":"Services"
        }
    ],
    "sg:phone":"+1 718 858 4880",
    "sg:postcode":"11201",
    "sg:province":"NY",
    "wof:name":"Groberg Susan F Atty",
    "wof:placetype":"venue"
},
  "geometry": {"coordinates":[-73.991834,40.692417],"type":"Point"}
}