{
  "type": "Feature",
  "properties": {
    "iso:country":"US",
    "sg:address":"1863 Pond Rd",
    "sg:city":"Ronkonkoma",
    "sg:classifiers":[
        {
            "category":"Building & Trades",
            "subcategory":"Construction",
            "type":"Services"
        }
    ],
    "sg:phone":"+1 631 737 8020",
    "sg:postcode":"11779",
    "sg:province":"NY",
    "sg:tags":[
        "steel",
        "structural",
        "erection",
        "general",
        "contractor"
    ],
    "wof:name":"Swingline Construction Co Inc",
    "wof:placetype":"venue"
},
  "geometry": {"coordinates":[-73.11772499999999,40.793554],"type":"Point"}
}