{
  "type": "Feature",
  "properties": {
    "iso:country":"US",
    "sg:address":"515 Jefferson Ave",
    "sg:city":"Mamaroneck",
    "sg:classifiers":[
        {
            "category":"Professional",
            "type":"Services"
        }
    ],
    "sg:phone":"+1   ",
    "sg:postcode":"10543",
    "sg:province":"NY",
    "wof:name":"Rs Info Syst Inc",
    "wof:placetype":"venue"
},
  "geometry": {"coordinates":[-73.73336999999999,40.957263],"type":"Point"}
}