{
  "type": "Feature",
  "properties": {
    "addr:full":"29 Central Ave Hauppauge NY 11788",
    "addr:housenumber":"29",
    "addr:postcode":"11788",
    "addr:street":"Central Ave",
    "iso:country":"US",
    "sg:address":"29 Central Ave",
    "sg:city":"Hauppauge",
    "sg:classifiers":[
        {
            "category":"Professional",
            "subcategory":"Management & Consulting",
            "type":"Services"
        }
    ],
    "sg:phone":"+1 631 234 8444",
    "sg:postcode":"11788",
    "sg:province":"NY",
    "sg:tags":[
        "consultant",
        "training"
    ],
    "sg:website":"www.rjtedu.com",
    "wof:name":"R J & T Edicational Training",
    "wof:placetype":"venue"
},
  "geometry": {"coordinates":[-73.217713,40.807064],"type":"Point"}
}