{
  "type": "Feature",
  "properties": {
    "addr:full":"403 College Ave Staten Island NY 10314",
    "addr:housenumber":"403",
    "addr:postcode":"10314",
    "addr:street":"College Ave",
    "iso:country":"US",
    "sg:address":"403 College Ave",
    "sg:city":"Staten Island",
    "sg:classifiers":[
        {
            "category":"Building & Trades",
            "subcategory":"Electrical",
            "type":"Services"
        }
    ],
    "sg:phone":"+1 718 556 7800",
    "sg:postcode":"10314",
    "sg:province":"NY",
    "sg:tags":[
        "electrician"
    ],
    "wof:name":"Fallon Electric Inc",
    "wof:placetype":"venue"
},
  "geometry": {"coordinates":[-74.133904,40.6213],"type":"Point"}
}