{
  "type": "Feature",
  "properties": {
    "addr:full":"28 Israel Zupnick Dr Monroe NY 10950",
    "addr:housenumber":"28",
    "addr:postcode":"10950",
    "addr:street":"Israel Zupnick Dr",
    "iso:country":"US",
    "sg:address":"28 Israel Zupnick Dr",
    "sg:city":"Monroe",
    "sg:classifiers":[
        {
            "category":"Organizations",
            "subcategory":"Religious Organization",
            "type":"Services"
        }
    ],
    "sg:phone":"+1 845 783 7182",
    "sg:postcode":"10950",
    "sg:province":"NY",
    "wof:name":"Congregation Shari Vaad Tov",
    "wof:placetype":"venue"
},
  "geometry": {"coordinates":[-74.16027800000001,41.34145],"type":"Point"}
}