{
  "type": "Feature",
  "properties": {
    "addr:full":"36 Stobe Ave Staten Island NY 10306",
    "addr:housenumber":"36",
    "addr:postcode":"10306",
    "addr:street":"Stobe Ave",
    "iso:country":"US",
    "sg:address":"36 Stobe Ave",
    "sg:city":"Staten Island",
    "sg:classifiers":[
        {
            "category":"Shopping",
            "subcategory":"Gifts & Souvenirs",
            "type":"Retail Goods"
        }
    ],
    "sg:phone":"+1   ",
    "sg:postcode":"10306",
    "sg:province":"NY",
    "sg:tags":[
        "cards"
    ],
    "wof:name":"Expressions Card & Gifts Btq",
    "wof:placetype":"venue"
},
  "geometry": {"coordinates":[-74.102767,40.585331],"type":"Point"}
}