{
  "type": "Feature",
  "properties": {
    "addr:full":"314 Hoffman Ln Hauppauge NY 11788",
    "addr:housenumber":"314",
    "addr:postcode":"11788",
    "addr:street":"Hoffman Ln",
    "iso:country":"US",
    "sg:address":"314 Hoffman Ln",
    "sg:city":"Hauppauge",
    "sg:classifiers":[
        {
            "category":"Professional",
            "subcategory":"Management & Consulting",
            "type":"Services"
        }
    ],
    "sg:phone":"+1 631 582 3716",
    "sg:postcode":"11788",
    "sg:province":"NY",
    "sg:tags":[
        "business"
    ],
    "wof:name":"Simpco Cable Company",
    "wof:placetype":"venue"
},
  "geometry": {"coordinates":[-73.186584,40.813621],"type":"Point"}
}