{
  "type": "Feature",
  "properties": {
    "addr:full":"215 Lexington Ave Fl 13 New York NY 10016",
    "addr:housenumber":"215;13",
    "addr:postcode":"10016",
    "addr:street":"Lexington Ave Fl",
    "iso:country":"US",
    "sg:address":"215 Lexington Ave Fl 13",
    "sg:city":"New York",
    "sg:classifiers":[
        {
            "category":"Communications",
            "subcategory":"Newspaper",
            "type":"Services"
        }
    ],
    "sg:phone":"+1 212 447 7072",
    "sg:postcode":"10016",
    "sg:province":"NY",
    "sg:tags":[
        "print",
        "medium"
    ],
    "wof:name":"R P Media Group Inc",
    "wof:placetype":"venue"
},
  "geometry": {"coordinates":[-73.980103,40.7458],"type":"Point"}
}