{
  "type": "Feature",
  "properties": {
    "addr:full":"4 Amarr Dr Shirley NY 11967",
    "addr:housenumber":"4",
    "addr:postcode":"11967",
    "addr:street":"Amarr Dr",
    "iso:country":"US",
    "sg:address":"4 Amarr Dr",
    "sg:city":"Shirley",
    "sg:classifiers":[
        {
            "category":"Building & Trades",
            "subcategory":"Electrical",
            "type":"Services"
        }
    ],
    "sg:phone":"+1 631 838 1877",
    "sg:postcode":"11967",
    "sg:province":"NY",
    "sg:tags":[
        "electrician"
    ],
    "wof:name":"Graphix Electrical Service",
    "wof:placetype":"venue"
},
  "geometry": {"coordinates":[-72.86457,40.777987],"type":"Point"}
}