{
  "type": "Feature",
  "properties": {
    "addr:full":"31 Chauncy Rd Riverhead NY 11901",
    "addr:housenumber":"31",
    "addr:postcode":"11901",
    "addr:street":"Chauncy Rd",
    "iso:country":"US",
    "sg:address":"31 Chauncy Rd",
    "sg:city":"Riverhead",
    "sg:classifiers":[
        {
            "category":"Professional",
            "subcategory":"Management & Consulting",
            "type":"Services"
        }
    ],
    "sg:phone":"+1 631 298 1077",
    "sg:postcode":"11901",
    "sg:province":"NY",
    "sg:tags":[
        "facility"
    ],
    "wof:name":"Flawless Floor",
    "wof:placetype":"venue"
},
  "geometry": {"coordinates":[-72.623268,40.904481],"type":"Point"}
}