{
  "type": "Feature",
  "properties": {
    "iso:country":"US",
    "sg:address":"14813 Hillside Avenue",
    "sg:city":"Jamaica",
    "sg:classifiers":[
        {
            "category":"Food & Beverages",
            "subcategory":"Groceries & Convenience Stores",
            "type":"Retail Goods"
        }
    ],
    "sg:phone":"+1 718 739 8553",
    "sg:postcode":"11435",
    "sg:province":"NY",
    "wof:name":"Ahmed Grocery Store",
    "wof:placetype":"venue"
},
  "geometry": {"coordinates":[-73.80840000000001,40.706245],"type":"Point"}
}