{
  "type": "Feature",
  "properties": {
    "addr:full":"17 North St Marcellus NY 13108",
    "addr:housenumber":"17",
    "addr:postcode":"13108",
    "addr:street":"North St",
    "iso:country":"US",
    "sg:address":"17 North St",
    "sg:city":"Marcellus",
    "sg:classifiers":[
        {
            "category":"Professional",
            "subcategory":"Lawyer & Legal Services",
            "type":"Services"
        }
    ],
    "sg:phone":"+1 315 673 2053",
    "sg:postcode":"13108",
    "sg:province":"NY",
    "sg:tags":[
        "attorney",
        "real estate"
    ],
    "sg:website":"http://www.douglaswtaylor.com",
    "wof:name":"Douglas W. Taylor, Attorney",
    "wof:placetype":"venue"
},
  "geometry": {"coordinates":[-76.340101,42.982996],"type":"Point"}
}