{
  "type": "Feature",
  "properties": {
    "iso:country":"US",
    "sg:address":"2094 Fulton St",
    "sg:city":"Brooklyn",
    "sg:classifiers":[
        {
            "category":"Shopping",
            "subcategory":"Department Store",
            "type":"Retail Goods"
        }
    ],
    "sg:phone":"+1 718 385 8081",
    "sg:postcode":"11233",
    "sg:province":"NY",
    "sg:tags":[
        "shop"
    ],
    "wof:name":"Neighborhood Variety Store",
    "wof:placetype":"venue"
},
  "geometry": {"coordinates":[-73.91548899999999,40.678491],"type":"Point"}
}