{
  "type": "Feature",
  "properties": {
    "addr:full":"502 5th Ave Owego NY 13827",
    "addr:housenumber":"502",
    "addr:postcode":"13827",
    "addr:street":"5Th Ave",
    "iso:country":"US",
    "sg:address":"502 5th Ave",
    "sg:city":"Owego",
    "sg:classifiers":[
        {
            "category":"Health Services",
            "subcategory":"Podiatrist",
            "type":"Services"
        }
    ],
    "sg:phone":"+1 607 687 5252",
    "sg:postcode":"13827",
    "sg:province":"NY",
    "wof:name":"Associates In Foot Surgery",
    "wof:placetype":"venue"
},
  "geometry": {"coordinates":[-76.24507699999999,42.104517],"type":"Point"}
}