{
  "type": "Feature",
  "properties": {
    "iso:country":"US",
    "sg:address":"180 Oser Ave Ste 300",
    "sg:city":"Hauppauge",
    "sg:classifiers":[
        {
            "category":"Community Center",
            "type":"Public Place"
        }
    ],
    "sg:phone":"+1 631 952 3800",
    "sg:postcode":"11788",
    "sg:province":"NY",
    "sg:tags":[
        "medical"
    ],
    "sg:website":"www.azpharmaceutical.com",
    "wof:name":"A & Z Pharmaceutical Inc",
    "wof:placetype":"venue"
},
  "geometry": {"coordinates":[-73.252403,40.817001],"type":"Point"}
}