{
  "type": "Feature",
  "properties": {
    "iso:country":"US",
    "sg:address":"2175 70th St",
    "sg:city":"Brooklyn",
    "sg:classifiers":[
        {
            "category":"Social Services",
            "subcategory":"Job Training",
            "type":"Services"
        }
    ],
    "sg:phone":"+1   ",
    "sg:postcode":"11204",
    "sg:province":"NY",
    "sg:tags":[
        "automotive",
        "association"
    ],
    "wof:name":"Metropolitan NY Tow/Auto Bdy",
    "wof:placetype":"venue"
},
  "geometry": {"coordinates":[-73.98561599999999,40.612082],"type":"Point"}
}