{
  "type": "Feature",
  "properties": {
    "addr:full":"211 Park Ave Hicksville NY 11801",
    "addr:housenumber":"211",
    "addr:postcode":"11801",
    "addr:street":"Park Ave",
    "iso:country":"US",
    "sg:address":"211 Park Ave",
    "sg:city":"Hicksville",
    "sg:classifiers":[
        {
            "category":"Personal",
            "type":"Services"
        }
    ],
    "sg:phone":"+1 718 268 0907",
    "sg:postcode":"11801",
    "sg:province":"NY",
    "sg:tags":[
        "mover"
    ],
    "wof:name":"L I Express Moving & Storage Inc",
    "wof:placetype":"venue"
},
  "geometry": {"coordinates":[-73.52010300000001,40.770802],"type":"Point"}
}