{
  "type": "Feature",
  "properties": {
    "iso:country":"US",
    "sg:address":"20 S Main St",
    "sg:city":"Moravia",
    "sg:classifiers":[
        {
            "category":"Professional",
            "subcategory":"Business Services",
            "type":"Services"
        }
    ],
    "sg:phone":"+1 315 497 3038",
    "sg:postcode":"13118",
    "sg:province":"NY",
    "sg:tags":[
        "embroidery"
    ],
    "wof:name":"Crane Brook Studios",
    "wof:placetype":"venue"
},
  "geometry": {"coordinates":[-76.421279,42.709769],"type":"Point"}
}