{
  "type": "Feature",
  "properties": {
    "addr:full":"668 Crescent Avenue Bronx NY 10458",
    "addr:housenumber":"668",
    "addr:postcode":"10458",
    "addr:street":"Crescent Avenue",
    "iso:country":"US",
    "sg:address":"668 Crescent Avenue",
    "sg:city":"Bronx",
    "sg:classifiers":[
        {
            "category":"Food & Beverages",
            "subcategory":"Groceries & Convenience Stores",
            "type":"Retail Goods"
        }
    ],
    "sg:phone":"+1 718 933 4410",
    "sg:postcode":"10458",
    "sg:province":"NY",
    "wof:name":"Air-Electric",
    "wof:placetype":"venue"
},
  "geometry": {"coordinates":[-73.88645699999999,40.854042],"type":"Point"}
}