{
  "type": "Feature",
  "properties": {
    "addr:full":"6935 Astoria Blvd Jackson Heights NY 11370",
    "addr:housenumber":"6935",
    "addr:postcode":"11370",
    "addr:street":"Astoria Blvd",
    "iso:country":"US",
    "sg:address":"6935 Astoria Blvd",
    "sg:city":"Jackson Heights",
    "sg:classifiers":[
        {
            "category":"Fast Food",
            "type":"Food & Drink"
        },
        {
            "category":"Restaurant",
            "type":"Food & Drink"
        }
    ],
    "sg:phone":"+1 718 204 7070",
    "sg:postcode":"11370",
    "sg:province":"NY",
    "sg:tags":[
        "burger",
        "diner"
    ],
    "sg:website":"www.jacksonholeburgers.com/defau...",
    "wof:name":"Jackson Hole",
    "wof:placetype":"venue"
},
  "geometry": {"coordinates":[-73.899912,40.767471],"type":"Point"}
}