{
  "type": "Feature",
  "properties": {
    "addr:full":"59 New Dorp Plz Staten Island NY 10306",
    "addr:housenumber":"59",
    "addr:postcode":"10306",
    "addr:street":"New Dorp Plz",
    "iso:country":"US",
    "sg:address":"59 New Dorp Plz",
    "sg:city":"Staten Island",
    "sg:classifiers":[
        {
            "category":"Shopping",
            "subcategory":"Used Merchandise",
            "type":"Retail Goods"
        },
        {
            "category":"Shopping",
            "subcategory":"Clothing, Apparel, & Fashions",
            "type":"Retail Goods"
        }
    ],
    "sg:phone":"+1 718 987 0853",
    "sg:postcode":"10306",
    "sg:province":"NY",
    "sg:tags":[
        "shop",
        "ready",
        "consignment"
    ],
    "wof:name":"Time After Time Ltd",
    "wof:placetype":"venue"
},
  "geometry": {"coordinates":[-74.117233,40.574],"type":"Point"}
}