{
  "type": "Feature",
  "properties": {
    "addr:full":"3902 14th Avenue Brooklyn NY 11218",
    "addr:housenumber":"3902",
    "addr:postcode":"11218",
    "addr:street":"14Th Avenue",
    "iso:country":"US",
    "sg:address":"3902 14th Avenue",
    "sg:city":"Brooklyn",
    "sg:classifiers":[
        {
            "category":"Professional",
            "subcategory":"Lawyer & Legal Services",
            "type":"Services"
        }
    ],
    "sg:phone":"+1 718 431 1166",
    "sg:postcode":"11218",
    "sg:province":"NY",
    "wof:name":"Charles Mandlebaum",
    "wof:placetype":"venue"
},
  "geometry": {"coordinates":[-73.984392,40.639175],"type":"Point"}
}