{
  "type": "Feature",
  "properties": {
    "addr:full":"2 Clinton St New York NY 10002",
    "addr:housenumber":"2",
    "addr:postcode":"10002",
    "addr:street":"Clinton St",
    "iso:country":"US",
    "sg:address":"2 Clinton St",
    "sg:city":"New York",
    "sg:classifiers":[
        {
            "category":"Food & Beverages",
            "subcategory":"Groceries & Convenience Stores",
            "type":"Retail Goods"
        }
    ],
    "sg:phone":"+1 212 475 3377",
    "sg:postcode":"10002",
    "sg:province":"NY",
    "wof:name":"Angelica",
    "wof:placetype":"venue"
},
  "geometry": {"coordinates":[-73.98388799999999,40.721369],"type":"Point"}
}