{
  "type": "Feature",
  "properties": {
    "addr:full":"1 Delaware Dr New Hyde Park NY 11042",
    "addr:housenumber":"1",
    "addr:postcode":"11042",
    "addr:street":"Delaware Dr New",
    "iso:country":"US",
    "sg:address":"1 Delaware Dr",
    "sg:city":"New Hyde Park",
    "sg:classifiers":[
        {
            "category":"Animal Shelter",
            "type":"Public Place"
        },
        {
            "category":"Shopping",
            "subcategory":"Pets & Pet Supplies",
            "type":"Retail Goods"
        }
    ],
    "sg:phone":"+1 516 437 2963",
    "sg:postcode":"11042",
    "sg:province":"NY",
    "sg:tags":[
        "store"
    ],
    "wof:name":"The We're Group",
    "wof:placetype":"venue"
},
  "geometry": {"coordinates":[-73.69450399999999,40.759399],"type":"Point"}
}