{
  "type": "Feature",
  "properties": {
    "addr:full":"317 Route 52 Carmel NY 10512",
    "addr:housenumber":"317",
    "addr:postcode":"10512",
    "addr:street":"Route 52",
    "iso:country":"US",
    "sg:address":"317 Route 52",
    "sg:city":"Carmel",
    "sg:classifiers":[
        {
            "category":"Professional",
            "type":"Services"
        }
    ],
    "sg:phone":"+1 845 228 9277",
    "sg:postcode":"10512",
    "sg:province":"NY",
    "sg:tags":[
        "caterer"
    ],
    "sg:website":"www.cookiesandspice.com",
    "wof:name":"COOKIES & SPICE",
    "wof:placetype":"venue"
},
  "geometry": {"coordinates":[-73.676727,41.443471],"type":"Point"}
}