{
  "type": "Feature",
  "properties": {
    "addr:full":"629 Plank Rd Schenectady NY 12302",
    "addr:housenumber":"629",
    "addr:postcode":"12302",
    "addr:street":"Plank Rd",
    "iso:country":"US",
    "sg:address":"629 Plank Rd",
    "sg:city":"Schenectady",
    "sg:classifiers":[
        {
            "category":"Personal",
            "type":"Services"
        },
        {
            "category":"Professional",
            "subcategory":"Printing & Photocopies",
            "type":"Services"
        }
    ],
    "sg:phone":"+1 518 373 5848",
    "sg:postcode":"12302",
    "sg:province":"NY",
    "sg:tags":[
        "mover"
    ],
    "wof:name":"Ups Store the",
    "wof:placetype":"venue"
},
  "geometry": {"coordinates":[-73.949501,42.860298],"type":"Point"}
}