{
  "type": "Feature",
  "properties": {
    "iso:country":"US",
    "sg:address":"8752 Turin Rd",
    "sg:city":"Rome",
    "sg:classifiers":[
        {
            "category":"Restaurant",
            "type":"Food & Drink"
        }
    ],
    "sg:phone":"+1 315 339 3742",
    "sg:postcode":"13440",
    "sg:province":"NY",
    "wof:name":"Fric & Frac's Flying Food Factory",
    "wof:placetype":"venue"
},
  "geometry": {"coordinates":[-75.47092000000001,43.284612],"type":"Point"}
}