{
  "type": "Feature",
  "properties": {
    "iso:country":"US",
    "sg:address":"533 W Caswell Ave",
    "sg:city":"Staten Island",
    "sg:classifiers":[
        {
            "category":"Building & Trades",
            "subcategory":"Construction",
            "type":"Services"
        }
    ],
    "sg:phone":"+1 718 761 5291",
    "sg:postcode":"10314",
    "sg:province":"NY",
    "sg:tags":[
        "house"
    ],
    "wof:name":"Lisiewicz Cnstrctn Inc",
    "wof:placetype":"venue"
},
  "geometry": {"coordinates":[-74.154083,40.616056],"type":"Point"}
}