{
  "type": "Feature",
  "properties": {
    "iso:country":"US",
    "sg:address":"460 Henry Blvd",
    "sg:city":"Holbrook",
    "sg:classifiers":[
        {
            "category":"Social Services",
            "type":"Services"
        }
    ],
    "sg:phone":"+1 631 471 8694",
    "sg:postcode":"11741",
    "sg:province":"NY",
    "sg:tags":[
        "counselor",
        "marriage",
        "family"
    ],
    "wof:name":"Christian Psychotherapy Office",
    "wof:placetype":"venue"
},
  "geometry": {"coordinates":[-73.068303,40.792066],"type":"Point"}
}