{
  "type": "Feature",
  "properties": {
    "addr:full":"12089 County Line Rd Delevan NY 14042",
    "addr:housenumber":"12089",
    "addr:postcode":"14042",
    "addr:street":"County Line Rd",
    "iso:country":"US",
    "sg:address":"12089 County Line Rd",
    "sg:city":"Delevan",
    "sg:classifiers":[
        {
            "category":"Real Estate",
            "subcategory":"Real Estate Operator",
            "type":"Services"
        }
    ],
    "sg:phone":"+1 716 492 5590",
    "sg:postcode":"14042",
    "sg:province":"NY",
    "sg:tags":[
        "apartment"
    ],
    "wof:name":"Yorkshire Corner Apartments",
    "wof:placetype":"venue"
},
  "geometry": {"coordinates":[-78.464159,42.529459],"type":"Point"}
}