{
  "type": "Feature",
  "properties": {
    "iso:country":"US",
    "sg:address":"17 Main St",
    "sg:city":"Penn Yan",
    "sg:classifiers":[
        {
            "category":"Shopping",
            "subcategory":"Tobacco",
            "type":"Retail Goods"
        }
    ],
    "sg:phone":"+1   ",
    "sg:postcode":"14527",
    "sg:province":"NY",
    "sg:tags":[
        "product"
    ],
    "wof:name":"Tobacco Road",
    "wof:placetype":"venue"
},
  "geometry": {"coordinates":[-77.05352999999999,42.660856],"type":"Point"}
}