{
  "type": "Feature",
  "properties": {
    "addr:full":"943 Dean St Niskayuna NY 12309",
    "addr:housenumber":"943",
    "addr:postcode":"12309",
    "addr:street":"Dean St",
    "iso:country":"US",
    "sg:address":"943 Dean St",
    "sg:city":"Niskayuna",
    "sg:classifiers":[
        {
            "category":"Personal",
            "subcategory":"Beauty Salon",
            "type":"Services"
        }
    ],
    "sg:phone":"+1 518 346 7038",
    "sg:postcode":"12309",
    "sg:province":"NY",
    "sg:tags":[
        "shop"
    ],
    "wof:name":"Lords and Ladies Hair Boutique",
    "wof:placetype":"venue"
},
  "geometry": {"coordinates":[-73.90346700000001,42.803822],"type":"Point"}
}