{
  "type": "Feature",
  "properties": {
    "addr:full":"2800 Broadway New York NY 10079",
    "addr:housenumber":"2800",
    "addr:postcode":"10079",
    "addr:street":"Broadway",
    "iso:country":"US",
    "sg:address":"2800 Broadway",
    "sg:city":"New York",
    "sg:classifiers":[
        {
            "category":"Restaurant",
            "type":"Food & Drink"
        }
    ],
    "sg:phone":"+1 212 932 9059",
    "sg:postcode":"10079",
    "sg:province":"NY",
    "sg:tags":[
        "diner"
    ],
    "wof:name":"Westway Cafe",
    "wof:placetype":"venue"
},
  "geometry": {"coordinates":[-73.967457,40.802919],"type":"Point"}
}