{
  "type": "Feature",
  "properties": {
    "addr:full":"111 Franklin Ave Brooklyn NY 11205",
    "addr:housenumber":"111",
    "addr:postcode":"11205",
    "addr:street":"Franklin Ave",
    "iso:country":"US",
    "sg:address":"111 Franklin Ave",
    "sg:city":"Brooklyn",
    "sg:classifiers":[
        {
            "category":"Restaurant",
            "type":"Food & Drink"
        }
    ],
    "sg:phone":"+1 718 389 1827",
    "sg:postcode":"11205",
    "sg:province":"NY",
    "sg:tags":[
        "delicatessen"
    ],
    "wof:name":"Cruz Deli",
    "wof:placetype":"venue"
},
  "geometry": {"coordinates":[-73.958067,40.695341],"type":"Point"}
}