{
  "type": "Feature",
  "properties": {
    "iso:country":"US",
    "sg:address":"76 Washington St",
    "sg:city":"Saratoga Springs",
    "sg:classifiers":[
        {
            "category":"Insurance",
            "subcategory":"Insurance Agent",
            "type":"Services"
        }
    ],
    "sg:phone":"+1 518 584 4564",
    "sg:postcode":"12866",
    "sg:province":"NY",
    "wof:name":"Kristina Saddlemire",
    "wof:placetype":"venue"
},
  "geometry": {"coordinates":[-73.789749,43.080214],"type":"Point"}
}