{
  "type": "Feature",
  "properties": {
    "iso:country":"US",
    "sg:address":"1234 Simpson St",
    "sg:city":"Bronx",
    "sg:classifiers":[
        {
            "category":"Organizations",
            "subcategory":"Religious Organization",
            "type":"Services"
        }
    ],
    "sg:phone":"+1 718 328 2416",
    "sg:postcode":"10459",
    "sg:province":"NY",
    "sg:tags":[
        "clergy"
    ],
    "wof:name":"Graciano Torres",
    "wof:placetype":"venue"
},
  "geometry": {"coordinates":[-73.892819,40.828957],"type":"Point"}
}