{
  "type": "Feature",
  "properties": {
    "iso:country":"US",
    "sg:address":"285 W Broadway",
    "sg:city":"New York",
    "sg:classifiers":[
        {
            "category":"Manufacturing",
            "subcategory":"Printing",
            "type":"Manufacturing & Wholesale Goods"
        }
    ],
    "sg:phone":"+1 516 354 6300",
    "sg:postcode":"10013",
    "sg:province":"NY",
    "sg:tags":[
        "multimedia"
    ],
    "wof:name":"Mx Media Solutions",
    "wof:placetype":"venue"
},
  "geometry": {"coordinates":[-74.004845,40.720857],"type":"Point"}
}