{
  "type": "Feature",
  "properties": {
    "iso:country":"US",
    "sg:address":"2303 Main St",
    "sg:city":"Buffalo",
    "sg:classifiers":[
        {
            "category":"Shopping",
            "subcategory":"Computers & Home Electronics",
            "type":"Retail Goods"
        }
    ],
    "sg:phone":"+1 716 832 3377",
    "sg:postcode":"14214",
    "sg:province":"NY",
    "sg:tags":[
        "equipment",
        "electronic",
        "supply"
    ],
    "wof:name":"Burgio's TV Svc",
    "wof:placetype":"venue"
},
  "geometry": {"coordinates":[-78.84722600000001,42.931529],"type":"Point"}
}