{
  "type": "Feature",
  "properties": {
    "addr:full":"175 Dingens St Buffalo NY 14206",
    "addr:housenumber":"175",
    "addr:postcode":"14206",
    "addr:street":"Dingens St",
    "iso:country":"US",
    "sg:address":"175 Dingens St",
    "sg:city":"Buffalo",
    "sg:classifiers":[
        {
            "category":"Government",
            "subcategory":"Office",
            "type":"Public Place"
        }
    ],
    "sg:phone":"+1 716 825 2885",
    "sg:postcode":"14206",
    "sg:province":"NY",
    "sg:tags":[
        "state",
        "program"
    ],
    "wof:name":"Thruway Authority",
    "wof:placetype":"venue"
},
  "geometry": {"coordinates":[-78.809307,42.87775],"type":"Point"}
}