{
  "type": "Feature",
  "properties": {
    "addr:full":"653 Old Willets Path Hauppauge NY 11788",
    "addr:housenumber":"653",
    "addr:postcode":"11788",
    "addr:street":"Old Willets Path",
    "iso:country":"US",
    "sg:address":"653 Old Willets Path",
    "sg:city":"Hauppauge",
    "sg:classifiers":[
        {
            "category":"Wholesale",
            "subcategory":"Groceries",
            "type":"Manufacturing & Wholesale Goods"
        }
    ],
    "sg:phone":"+1 631 232 1712",
    "sg:postcode":"11788",
    "sg:province":"NY",
    "sg:tags":[
        "nut",
        "processing"
    ],
    "wof:name":"Hemisphere Group Inc",
    "wof:placetype":"venue"
},
  "geometry": {"coordinates":[-73.233339,40.811589],"type":"Point"}
}