{
  "type": "Feature",
  "properties": {
    "addr:full":"2150 Elmwood Ave Buffalo NY 14207",
    "addr:housenumber":"2150",
    "addr:postcode":"14207",
    "addr:street":"Elmwood Ave",
    "iso:country":"US",
    "sg:address":"2150 Elmwood Ave",
    "sg:city":"Buffalo",
    "sg:classifiers":[
        {
            "category":"Manufacturing",
            "subcategory":"Tools & Machinery",
            "type":"Manufacturing & Wholesale Goods"
        }
    ],
    "sg:phone":"+1 716 876 9951",
    "sg:postcode":"14207",
    "sg:province":"NY",
    "sg:tags":[
        "industrial",
        "instr"
    ],
    "sg:website":"www.mokon.com",
    "wof:name":"Mokon",
    "wof:placetype":"venue"
},
  "geometry": {"coordinates":[-78.878348,42.952411],"type":"Point"}
}