{
  "type": "Feature",
  "properties": {
    "iso:country":"US",
    "sg:address":"9535 Oswego Rd",
    "sg:city":"Phoenix",
    "sg:classifiers":[
        {
            "category":"Professional",
            "subcategory":"Business Services",
            "type":"Services"
        },
        {
            "category":"Real Estate",
            "subcategory":"Real Estate Agent",
            "type":"Services"
        }
    ],
    "sg:phone":"+1 315 695 5809",
    "sg:postcode":"13135",
    "sg:province":"NY",
    "sg:tags":[
        "auction",
        "auctioneer"
    ],
    "wof:name":"Sellers Unlimited",
    "wof:placetype":"venue"
},
  "geometry": {"coordinates":[-76.35228600000001,43.230703],"type":"Point"}
}