{
  "type": "Feature",
  "properties": {
    "addr:full":"2080 Hillside Ave New Hyde Park NY 11040",
    "addr:housenumber":"2080",
    "addr:postcode":"11040",
    "addr:street":"Hillside Ave",
    "iso:country":"US",
    "sg:address":"2080 Hillside Ave",
    "sg:city":"New Hyde Park",
    "sg:classifiers":[
        {
            "category":"Retail",
            "subcategory":"Car Wash",
            "type":"Services"
        }
    ],
    "sg:phone":"+1 516 328 6111",
    "sg:postcode":"11040",
    "sg:province":"NY",
    "sg:tags":[
        "carwash"
    ],
    "wof:name":"Five Corners Car Wash",
    "wof:placetype":"venue"
},
  "geometry": {"coordinates":[-73.673784,40.751334],"type":"Point"}
}