{
  "type": "Feature",
  "properties": {
    "addr:full":"103-07 Metropolitan Avenue Forest Hills NY 11375",
    "addr:housenumber":"103-07",
    "addr:postcode":"11375",
    "addr:street":"Metropolitan Avenue",
    "iso:country":"US",
    "sg:address":"103-07 Metropolitan Avenue",
    "sg:city":"Forest Hills",
    "sg:classifiers":[
        {
            "category":"Home & Garden",
            "subcategory":"Home Furnishings",
            "type":"Retail Goods"
        },
        {
            "category":"Professional",
            "subcategory":"Art Services",
            "type":"Services"
        }
    ],
    "sg:phone":"+1 718 793 7200",
    "sg:postcode":"11375",
    "sg:province":"NY",
    "sg:tags":[
        "decor",
        "framing"
    ],
    "wof:name":"ArtWorld",
    "wof:placetype":"venue"
},
  "geometry": {"coordinates":[-73.849493,40.710442],"type":"Point"}
}