{
  "type": "Feature",
  "properties": {
    "iso:country":"US",
    "sg:address":"112 32nd St",
    "sg:city":"Lindenhurst",
    "sg:classifiers":[
        {
            "category":"Building & Trades",
            "subcategory":"Construction",
            "type":"Services"
        }
    ],
    "sg:phone":"+1 631 957 7223",
    "sg:postcode":"11757",
    "sg:province":"NY",
    "sg:tags":[
        "carpentry",
        "contractor"
    ],
    "wof:name":"Johnny T Carpentry",
    "wof:placetype":"venue"
},
  "geometry": {"coordinates":[-73.382448,40.688055],"type":"Point"}
}