{
  "type": "Feature",
  "properties": {
    "addr:full":"37 Crosby St New York NY 10013",
    "addr:housenumber":"37",
    "addr:postcode":"10013",
    "addr:street":"Crosby St",
    "iso:country":"US",
    "sg:address":"37 Crosby St",
    "sg:city":"New York",
    "sg:classifiers":[
        {
            "category":"Communications",
            "subcategory":"Film & Video Production",
            "type":"Services"
        }
    ],
    "sg:phone":"+1   ",
    "sg:postcode":"10013",
    "sg:province":"NY",
    "sg:tags":[
        "motion",
        "picture"
    ],
    "wof:name":"Greg Ford Co Inc",
    "wof:placetype":"venue"
},
  "geometry": {"coordinates":[-73.999522,40.720516],"type":"Point"}
}