{
  "type": "Feature",
  "properties": {
    "iso:country":"US",
    "sg:address":"2804 Doran Rd",
    "sg:city":"Lima",
    "sg:classifiers":[
        {
            "category":"Building & Trades",
            "subcategory":"Electrical",
            "type":"Services"
        }
    ],
    "sg:phone":"+1 585 624 3868",
    "sg:postcode":"14485",
    "sg:province":"NY",
    "sg:tags":[
        "electric",
        "contractor"
    ],
    "wof:name":"D & D Electric",
    "wof:placetype":"venue"
},
  "geometry": {"coordinates":[-77.570454,42.861301],"type":"Point"}
}