{
  "type": "Feature",
  "properties": {
    "addr:full":"841 Holt Rd Webster NY 14580",
    "addr:housenumber":"841",
    "addr:postcode":"14580",
    "addr:street":"Holt Rd",
    "iso:country":"US",
    "sg:address":"841 Holt Rd",
    "sg:city":"Webster",
    "sg:classifiers":[
        {
            "category":"Real Estate",
            "subcategory":"Real Estate Services",
            "type":"Services"
        },
        {
            "category":"Building & Trades",
            "subcategory":"Cleaning & Sanitation",
            "type":"Services"
        },
        {
            "category":"Building & Trades",
            "subcategory":"Construction",
            "type":"Services"
        }
    ],
    "sg:phone":"+1 585 872 4611",
    "sg:postcode":"14580",
    "sg:province":"NY",
    "sg:tags":[
        "management",
        "contractor"
    ],
    "sg:website":"http://www.integratedfacilitysolutions.com",
    "wof:name":"I FS",
    "wof:placetype":"venue"
},
  "geometry": {"coordinates":[-77.446613,43.219189],"type":"Point"}
}