{
  "type": "Feature",
  "properties": {
    "addr:full":"4876 Broadway New York NY 10034",
    "addr:housenumber":"4876",
    "addr:postcode":"10034",
    "addr:street":"Broadway",
    "iso:country":"US",
    "sg:address":"4876 Broadway",
    "sg:city":"New York",
    "sg:classifiers":[
        {
            "category":"Travel",
            "subcategory":"Travel Agent",
            "type":"Entertainment"
        }
    ],
    "sg:phone":"+1   ",
    "sg:postcode":"10034",
    "sg:province":"NY",
    "sg:tags":[
        "agency"
    ],
    "wof:name":"J Erazo Brokerage & Travel",
    "wof:placetype":"venue"
},
  "geometry": {"coordinates":[-73.924435,40.866304],"type":"Point"}
}