{
  "type": "Feature",
  "properties": {
    "addr:full":"2469 Merrick Rd Bellmore NY 11710",
    "addr:housenumber":"2469",
    "addr:postcode":"11710",
    "addr:street":"Merrick Rd",
    "iso:country":"US",
    "sg:address":"2469 Merrick Rd",
    "sg:city":"Bellmore",
    "sg:classifiers":[
        {
            "category":"Health Services",
            "subcategory":"Optometrist",
            "type":"Services"
        }
    ],
    "sg:phone":"+1 516 221 2400",
    "sg:postcode":"11710",
    "sg:province":"NY",
    "wof:name":"Merrick Bellmore Optometic Ctr",
    "wof:placetype":"venue"
},
  "geometry": {"coordinates":[-73.53354400000001,40.662169],"type":"Point"}
}