{
  "type": "Feature",
  "properties": {
    "iso:country":"US",
    "sg:address":"108 E 4th St",
    "sg:city":"New York",
    "sg:classifiers":[
        {
            "category":"Restaurant",
            "type":"Food & Drink"
        },
        {
            "category":"Wholesale",
            "subcategory":"Home Furnishings",
            "type":"Manufacturing & Wholesale Goods"
        }
    ],
    "sg:phone":"+1 212 777 1978",
    "sg:postcode":"10003",
    "sg:province":"NY",
    "sg:tags":[
        "plate",
        "tapas/small",
        "japanese"
    ],
    "sg:website":"www.wasan-ny.com",
    "wof:name":"Wasan",
    "wof:placetype":"venue"
},
  "geometry": {"coordinates":[-73.988375,40.725499],"type":"Point"}
}