{
  "type": "Feature",
  "properties": {
    "addr:full":"839 39th St Brooklyn NY 11232",
    "addr:housenumber":"839",
    "addr:postcode":"11232",
    "addr:street":"39Th St",
    "iso:country":"US",
    "sg:address":"839 39th St",
    "sg:city":"Brooklyn",
    "sg:classifiers":[
        {
            "category":"Parking",
            "type":"Transportation"
        }
    ],
    "sg:phone":"+1 718 871 9200",
    "sg:postcode":"11232",
    "sg:province":"NY",
    "sg:tags":[
        "auto",
        "repair",
        "storage",
        "automotive",
        "towing"
    ],
    "sg:website":"www.modelgarageinc.com",
    "wof:name":"Model Garage Inc",
    "wof:placetype":"venue"
},
  "geometry": {"coordinates":[-73.99569700000001,40.6465],"type":"Point"}
}