{
  "type": "Feature",
  "properties": {
    "addr:full":"99 Plainfield Ave Floral Park NY 11001",
    "addr:housenumber":"99",
    "addr:postcode":"11001",
    "addr:street":"Plainfield Ave",
    "iso:country":"US",
    "sg:address":"99 Plainfield Ave",
    "sg:city":"Floral Park",
    "sg:classifiers":[
        {
            "category":"Autos & Motor Vehicles",
            "subcategory":"Automobile Sales",
            "type":"Retail Goods"
        }
    ],
    "sg:phone":"+1   ",
    "sg:postcode":"11001",
    "sg:province":"NY",
    "sg:tags":[
        "used"
    ],
    "wof:name":"Candlewood Motors",
    "wof:placetype":"venue"
},
  "geometry": {"coordinates":[-73.701142,40.72642],"type":"Point"}
}