{
  "type": "Feature",
  "properties": {
    "iso:country":"US",
    "sg:address":"890 Plymouth Ave N",
    "sg:city":"Rochester",
    "sg:classifiers":[
        {
            "category":"Retail",
            "subcategory":"Funeral Services",
            "type":"Services"
        }
    ],
    "sg:phone":"+1 585 458 3070",
    "sg:postcode":"14608",
    "sg:province":"NY",
    "sg:tags":[
        "director"
    ],
    "wof:name":"Gregory Sears Funeral Home",
    "wof:placetype":"venue"
},
  "geometry": {"coordinates":[-77.62846500000001,43.16742],"type":"Point"}
}