{
  "type": "Feature",
  "properties": {
    "iso:country":"US",
    "sg:address":"17 Ramsey Rd",
    "sg:city":"Scarsdale",
    "sg:classifiers":[
        {
            "category":"Farming",
            "subcategory":"Farm",
            "type":"Manufacturing & Wholesale Goods"
        }
    ],
    "sg:phone":"+1 914 723 3817",
    "sg:postcode":"10583",
    "sg:province":"NY",
    "sg:tags":[
        "food",
        "covered",
        "corn",
        "crop"
    ],
    "wof:name":"Ramseys Farms",
    "wof:placetype":"venue"
},
  "geometry": {"coordinates":[-73.766744,40.989919],"type":"Point"}
}