{
  "type": "Feature",
  "properties": {
    "addr:full":"68 Victory Boulevard Staten Island NY 10301",
    "addr:housenumber":"68",
    "addr:postcode":"10301",
    "addr:street":"Victory Boulevard",
    "iso:country":"US",
    "sg:address":"68 Victory Boulevard",
    "sg:city":"Staten Island",
    "sg:classifiers":[
        {
            "category":"Home & Garden",
            "subcategory":"Hardware",
            "type":"Retail Goods"
        }
    ],
    "sg:phone":"+1 718 727 1772",
    "sg:postcode":"10301",
    "sg:province":"NY",
    "sg:tags":[
        "store"
    ],
    "sg:website":"www.benjaminmoore.com",
    "wof:name":"Dembner's Hardware & Paints",
    "wof:placetype":"venue"
},
  "geometry": {"coordinates":[-74.08134,40.637013],"type":"Point"}
}