{
  "type": "Feature",
  "properties": {
    "addr:full":"13 Clarence Harder Dr Tonawanda NY 14150",
    "addr:housenumber":"13",
    "addr:postcode":"14150",
    "addr:street":"Clarence Harder Dr",
    "iso:country":"US",
    "sg:address":"13 Clarence Harder Dr",
    "sg:city":"Tonawanda",
    "sg:classifiers":[
        {
            "category":"Wholesale",
            "subcategory":"Office Equipment",
            "type":"Manufacturing & Wholesale Goods"
        }
    ],
    "sg:phone":"+1 716 695 7129",
    "sg:postcode":"14150",
    "sg:province":"NY",
    "sg:tags":[
        "copier"
    ],
    "wof:name":"Clean Copies",
    "wof:placetype":"venue"
},
  "geometry": {"coordinates":[-78.87715300000001,43.002941],"type":"Point"}
}