{
  "type": "Feature",
  "properties": {
    "addr:full":"5725 Sunrise Hwy Holbrook NY 11741",
    "addr:housenumber":"5725",
    "addr:postcode":"11741",
    "addr:street":"Sunrise Hwy",
    "iso:country":"US",
    "sg:address":"5725 Sunrise Hwy",
    "sg:city":"Holbrook",
    "sg:classifiers":[
        {
            "category":"Home & Garden",
            "subcategory":"Carpets & Floor Coverings",
            "type":"Retail Goods"
        }
    ],
    "sg:phone":"+1 631 218 3444",
    "sg:postcode":"11741",
    "sg:province":"NY",
    "sg:tags":[
        "material"
    ],
    "wof:name":"Sunrise Floors",
    "wof:placetype":"venue"
},
  "geometry": {"coordinates":[-73.068353,40.768327],"type":"Point"}
}