{
  "type": "Feature",
  "properties": {
    "iso:country":"US",
    "sg:address":"205 Wawayanda Ave",
    "sg:city":"Middletown",
    "sg:classifiers":[
        {
            "category":"Education",
            "subcategory":"School",
            "type":"Public Place"
        }
    ],
    "sg:phone":"+1 845 343 8836",
    "sg:postcode":"10940",
    "sg:province":"NY",
    "sg:tags":[
        "religious"
    ],
    "sg:website":"www.mtcarmelparish.org",
    "wof:name":"Our Lady Of Mt Carmel School",
    "wof:placetype":"venue"
},
  "geometry": {"coordinates":[-74.43478899999999,41.432334],"type":"Point"}
}