{
  "type": "Feature",
  "properties": {
    "iso:country":"US",
    "sg:address":"9580 Grove Springs Rd",
    "sg:city":"Hammondsport",
    "sg:classifiers":[
        {
            "category":"Building & Trades",
            "subcategory":"Construction",
            "type":"Services"
        }
    ],
    "sg:phone":"+1 607 569 2930",
    "sg:postcode":"14840",
    "sg:province":"NY",
    "sg:tags":[
        "house"
    ],
    "wof:name":"Rinehart Construction",
    "wof:placetype":"venue"
},
  "geometry": {"coordinates":[-77.154314,42.459858],"type":"Point"}
}