{
  "type": "Feature",
  "properties": {
    "iso:country":"US",
    "sg:address":"574 Stewart Ave",
    "sg:city":"Bethpage",
    "sg:classifiers":[
        {
            "category":"Shopping",
            "subcategory":"Tobacco",
            "type":"Retail Goods"
        }
    ],
    "sg:phone":"+1   ",
    "sg:postcode":"11714",
    "sg:province":"NY",
    "sg:tags":[
        "product"
    ],
    "wof:name":"One Stop Smoke Shop",
    "wof:placetype":"venue"
},
  "geometry": {"coordinates":[-73.481759,40.743024],"type":"Point"}
}