{
  "type": "Feature",
  "properties": {
    "addr:full":"64 Jackson Ave Buffalo NY 14212",
    "addr:housenumber":"64",
    "addr:postcode":"14212",
    "addr:street":"Jackson Ave",
    "iso:country":"US",
    "sg:address":"64 Jackson Ave",
    "sg:city":"Buffalo",
    "sg:phone":"+1 716 822 4292",
    "sg:postcode":"14212",
    "sg:province":"NY",
    "wof:name":"Mulberry Cafe",
    "wof:placetype":"venue"
},
  "geometry": {"coordinates":[-78.786422,42.896458],"type":"Point"}
}