{
  "type": "Feature",
  "properties": {
    "addr:full":"98 Bond St Westbury NY 11590",
    "addr:housenumber":"98",
    "addr:postcode":"11590",
    "addr:street":"Bond St",
    "iso:country":"US",
    "sg:address":"98 Bond St",
    "sg:city":"Westbury",
    "sg:classifiers":[
        {
            "category":"Home & Garden",
            "subcategory":"Garden Supply",
            "type":"Retail Goods"
        }
    ],
    "sg:phone":"+1 516 338 6265",
    "sg:postcode":"11590",
    "sg:province":"NY",
    "sg:tags":[
        "engine"
    ],
    "wof:name":"Phalen Lawn Mower Repair",
    "wof:placetype":"venue"
},
  "geometry": {"coordinates":[-73.55801099999999,40.758677],"type":"Point"}
}