{
  "type": "Feature",
  "properties": {
    "iso:country":"US",
    "sg:address":"786 Grand Blvd",
    "sg:city":"Deer Park",
    "sg:classifiers":[
        {
            "category":"Retail",
            "subcategory":"Repair Shop",
            "type":"Services"
        }
    ],
    "sg:phone":"+1 631 892 0280",
    "sg:postcode":"11729",
    "sg:province":"NY",
    "sg:tags":[
        "lock",
        "locksmith"
    ],
    "wof:name":"24 Hour Emergency Locksmith",
    "wof:placetype":"venue"
},
  "geometry": {"coordinates":[-73.30839899999999,40.761496],"type":"Point"}
}