{
  "type": "Feature",
  "properties": {
    "addr:full":"548 Kenwood Ave Delmar NY 12054",
    "addr:housenumber":"548",
    "addr:postcode":"12054",
    "addr:street":"Kenwood Ave",
    "iso:country":"US",
    "sg:address":"548 Kenwood Ave",
    "sg:city":"Delmar",
    "sg:classifiers":[
        {
            "category":"Insurance",
            "subcategory":"Insurance Agent",
            "type":"Services"
        }
    ],
    "sg:phone":"+1 518 478 9995",
    "sg:postcode":"12054",
    "sg:province":"NY",
    "wof:name":"Shephard Co",
    "wof:placetype":"venue"
},
  "geometry": {"coordinates":[-73.84886299999999,42.624098],"type":"Point"}
}