{
  "type": "Feature",
  "properties": {
    "iso:country":"US",
    "sg:address":"28 E 35th Street",
    "sg:city":"New York",
    "sg:classifiers":[
        {
            "category":"Organizations",
            "subcategory":"Religious Organization",
            "type":"Services"
        }
    ],
    "sg:phone":"+1 212 683 4988",
    "sg:postcode":"10016",
    "sg:province":"NY",
    "wof:name":"Funeral Society of Community Church",
    "wof:placetype":"venue"
},
  "geometry": {"coordinates":[-73.981973,40.748089],"type":"Point"}
}