{
  "type": "Feature",
  "properties": {
    "addr:full":"2095 Schoolheimer Rd Canastota NY 13032",
    "addr:housenumber":"2095",
    "addr:postcode":"13032",
    "addr:street":"Schoolheimer Rd",
    "iso:country":"US",
    "sg:address":"2095 Schoolheimer Rd",
    "sg:city":"Canastota",
    "sg:classifiers":[
        {
            "category":"Building & Trades",
            "subcategory":"Plumbing",
            "type":"Services"
        },
        {
            "category":"Home & Garden",
            "subcategory":"Hardware",
            "type":"Retail Goods"
        }
    ],
    "sg:phone":"+1 315 363 8084",
    "sg:postcode":"13032",
    "sg:province":"NY",
    "sg:tags":[
        "filtration",
        "supply",
        "work",
        "purification",
        "water",
        "equipment"
    ],
    "wof:name":"Cotten Brothers Supply",
    "wof:placetype":"venue"
},
  "geometry": {"coordinates":[-75.702747,43.119337],"type":"Point"}
}