{
  "type": "Feature",
  "properties": {
    "iso:country":"US",
    "sg:address":"78 Washington Ave",
    "sg:city":"Schenectady",
    "sg:classifiers":[
        {
            "category":"Food & Beverages",
            "subcategory":"Groceries & Convenience Stores",
            "type":"Retail Goods"
        }
    ],
    "sg:phone":"+1 518 393 7522",
    "sg:postcode":"12305",
    "sg:province":"NY",
    "sg:tags":[
        "product"
    ],
    "wof:name":"Quality Food Mgmt Inc",
    "wof:placetype":"venue"
},
  "geometry": {"coordinates":[-73.949321,42.81615],"type":"Point"}
}