{
  "type": "Feature",
  "properties": {
    "addr:full":"1399 Atlantic Ave Brooklyn NY 11216",
    "addr:housenumber":"1399",
    "addr:postcode":"11216",
    "addr:street":"Atlantic Ave",
    "iso:country":"US",
    "sg:address":"1399 Atlantic Ave",
    "sg:city":"Brooklyn",
    "sg:classifiers":[
        {
            "category":"Organizations",
            "subcategory":"Religious Organization",
            "type":"Services"
        }
    ],
    "sg:phone":"+1 718 287 4573",
    "sg:postcode":"11216",
    "sg:province":"NY",
    "wof:name":"Church of Deliverance Tabernacle of Prayer",
    "wof:placetype":"venue"
},
  "geometry": {"coordinates":[-73.94347,40.678364],"type":"Point"}
}