{
  "type": "Feature",
  "properties": {
    "iso:country":"US",
    "sg:address":"128 Putnam St",
    "sg:city":"Syracuse",
    "sg:classifiers":[
        {
            "category":"Communications",
            "type":"Services"
        }
    ],
    "sg:phone":"+1 315 475 4923",
    "sg:postcode":"13204",
    "sg:province":"NY",
    "sg:tags":[
        "consultant",
        "engineer"
    ],
    "wof:name":"Leo Consulting",
    "wof:placetype":"venue"
},
  "geometry": {"coordinates":[-76.168983,43.03511],"type":"Point"}
}