{
  "type": "Feature",
  "properties": {
    "addr:full":"66 Oakland Ave Lynbrook NY 11563",
    "addr:housenumber":"66",
    "addr:postcode":"11563",
    "addr:street":"Oakland Ave",
    "iso:country":"US",
    "sg:address":"66 Oakland Ave",
    "sg:city":"Lynbrook",
    "sg:classifiers":[
        {
            "category":"Professional",
            "subcategory":"Management & Consulting",
            "type":"Services"
        }
    ],
    "sg:phone":"+1 516 599 5661",
    "sg:postcode":"11563",
    "sg:province":"NY",
    "sg:tags":[
        "newspaper",
        "delivery"
    ],
    "wof:name":"J & B News Delivery",
    "wof:placetype":"venue"
},
  "geometry": {"coordinates":[-73.676591,40.652625],"type":"Point"}
}