{
  "type": "Feature",
  "properties": {
    "iso:country":"US",
    "sg:address":"4437 Kear Rd",
    "sg:city":"Canandaigua",
    "sg:classifiers":[
        {
            "category":"Travel",
            "subcategory":"Campground",
            "type":"Entertainment"
        }
    ],
    "sg:phone":"+1 585 394 9875",
    "sg:postcode":"14424",
    "sg:province":"NY",
    "sg:tags":[
        "camp"
    ],
    "wof:name":"Camp Bristol Hills 4-H Camp",
    "wof:placetype":"venue"
},
  "geometry": {"coordinates":[-77.37504199999999,42.812142],"type":"Point"}
}