{
  "type": "Feature",
  "properties": {
    "addr:full":"2667 Merrick Rd Bellmore NY 11710",
    "addr:housenumber":"2667",
    "addr:postcode":"11710",
    "addr:street":"Merrick Rd",
    "iso:country":"US",
    "sg:address":"2667 Merrick Rd",
    "sg:city":"Bellmore",
    "sg:classifiers":[
        {
            "category":"Home & Garden",
            "subcategory":"Hardware",
            "type":"Retail Goods"
        }
    ],
    "sg:phone":"+1 516 221 0010",
    "sg:postcode":"11710",
    "sg:province":"NY",
    "sg:website":"www.acehardware.com",
    "wof:name":"Ace Hardware",
    "wof:placetype":"venue"
},
  "geometry": {"coordinates":[-73.52587800000001,40.663672],"type":"Point"}
}