{
  "type": "Feature",
  "properties": {
    "addr:full":"42 Ralph Ave Brooklyn NY 11221",
    "addr:housenumber":"42",
    "addr:postcode":"11221",
    "addr:street":"Ralph Ave",
    "iso:country":"US",
    "sg:address":"42 Ralph Ave",
    "sg:city":"Brooklyn",
    "sg:classifiers":[
        {
            "category":"Building & Trades",
            "subcategory":"Plumbing",
            "type":"Services"
        }
    ],
    "sg:phone":"+1 347 787 5456",
    "sg:postcode":"11221",
    "sg:province":"NY",
    "wof:name":"Sunset Plumbing",
    "wof:placetype":"venue"
},
  "geometry": {"coordinates":[-73.92406699999999,40.688837],"type":"Point"}
}