{
  "type": "Feature",
  "properties": {
    "addr:full":"177 Beach 116th St Far Rockaway NY 11694",
    "addr:housenumber":"177",
    "addr:postcode":"11694",
    "addr:street":"Beach 116Th St",
    "iso:country":"US",
    "sg:address":"177 Beach 116th St",
    "sg:city":"Far Rockaway",
    "sg:classifiers":[
        {
            "category":"Professional",
            "subcategory":"Management & Consulting",
            "type":"Services"
        }
    ],
    "sg:phone":"+1 718 474 4600",
    "sg:postcode":"11694",
    "sg:province":"NY",
    "sg:tags":[
        "marketing",
        "program"
    ],
    "sg:website":"www.odgroup.com",
    "wof:name":"Orion Development Group",
    "wof:placetype":"venue"
},
  "geometry": {"coordinates":[-73.836595,40.578193],"type":"Point"}
}