{
  "type": "Feature",
  "properties": {
    "addr:full":"19 Bellemeade Ave Smithtown NY 11787",
    "addr:housenumber":"19",
    "addr:postcode":"11787",
    "addr:street":"Bellemeade Ave",
    "iso:country":"US",
    "sg:address":"19 Bellemeade Ave",
    "sg:city":"Smithtown",
    "sg:classifiers":[
        {
            "category":"Manufacturing",
            "subcategory":"Printing",
            "type":"Manufacturing & Wholesale Goods"
        }
    ],
    "sg:phone":"+1 631 361 6916",
    "sg:postcode":"11787",
    "sg:province":"NY",
    "sg:tags":[
        "publisher"
    ],
    "wof:name":"Tradewins Publshng Corp",
    "wof:placetype":"venue"
},
  "geometry": {"coordinates":[-73.18995200000001,40.856608],"type":"Point"}
}