{
  "type": "Feature",
  "properties": {
    "iso:country":"US",
    "sg:address":"304 W German St",
    "sg:city":"Herkimer",
    "sg:classifiers":[
        {
            "category":"Professional",
            "type":"Services"
        }
    ],
    "sg:phone":"+1 315 866 2052",
    "sg:postcode":"13350",
    "sg:province":"NY",
    "sg:tags":[
        "establishment"
    ],
    "wof:name":"Herkimer Area Resource Ctr",
    "wof:placetype":"venue"
},
  "geometry": {"coordinates":[-74.993808,43.029783],"type":"Point"}
}