{
  "type": "Feature",
  "properties": {
    "addr:full":"161 Royleston Rd Rochester NY 14609",
    "addr:housenumber":"161",
    "addr:postcode":"14609",
    "addr:street":"Royleston Rd",
    "iso:country":"US",
    "sg:address":"161 Royleston Rd",
    "sg:city":"Rochester",
    "sg:classifiers":[
        {
            "category":"Manufacturing",
            "subcategory":"Retail Goods",
            "type":"Manufacturing & Wholesale Goods"
        }
    ],
    "sg:phone":"+1 585 654 7464",
    "sg:postcode":"14609",
    "sg:province":"NY",
    "sg:tags":[
        "marking",
        "devices"
    ],
    "wof:name":"Amjet Domino Inc",
    "wof:placetype":"venue"
},
  "geometry": {"coordinates":[-77.547844,43.161643],"type":"Point"}
}