{
  "type": "Feature",
  "properties": {
    "addr:full":"254 W 31 St New York NY 10001",
    "addr:housenumber":"254",
    "addr:postcode":"10001",
    "addr:street":"W 31 St",
    "iso:country":"US",
    "sg:address":"254 W 31 St",
    "sg:city":"New York",
    "sg:classifiers":[
        {
            "category":"Professional",
            "type":"Services"
        }
    ],
    "sg:phone":"+1 212 244 5970",
    "sg:postcode":"10001",
    "sg:province":"NY",
    "sg:tags":[
        "establishment"
    ],
    "wof:name":"G Unit Records Inc",
    "wof:placetype":"venue"
},
  "geometry": {"coordinates":[-73.993696,40.74957],"type":"Point"}
}