{
  "type": "Feature",
  "properties": {
    "addr:full":"400 N Orchard Rd Syracuse NY 13209",
    "addr:housenumber":"400",
    "addr:postcode":"13209",
    "addr:street":"N Orchard Rd",
    "iso:country":"US",
    "sg:address":"400 N Orchard Rd",
    "sg:city":"Syracuse",
    "sg:classifiers":[
        {
            "category":"Professional",
            "type":"Services"
        }
    ],
    "sg:phone":"+1 315 468 2120",
    "sg:postcode":"13209",
    "sg:province":"NY",
    "sg:tags":[
        "establishment"
    ],
    "wof:name":"Caradalli C",
    "wof:placetype":"venue"
},
  "geometry": {"coordinates":[-76.207562,43.054057],"type":"Point"}
}