{
  "type": "Feature",
  "properties": {
    "addr:full":"200 S Broadway Yonkers NY 10701",
    "addr:housenumber":"200",
    "addr:postcode":"10701",
    "addr:street":"S Broadway",
    "iso:country":"US",
    "sg:address":"200 S Broadway",
    "sg:city":"Yonkers",
    "sg:classifiers":[
        {
            "category":"Autos & Motor Vehicles",
            "subcategory":"Fuel & Gas Station",
            "type":"Retail Goods"
        }
    ],
    "sg:phone":"+1 914 375 0956",
    "sg:postcode":"10701",
    "sg:province":"NY",
    "wof:name":"Dino's Gas Center",
    "wof:placetype":"venue"
},
  "geometry": {"coordinates":[-73.895735,40.926519],"type":"Point"}
}