{
  "type": "Feature",
  "properties": {
    "iso:country":"US",
    "sg:address":"23 Rte 111",
    "sg:city":"Smithtown",
    "sg:classifiers":[
        {
            "category":"Insurance",
            "subcategory":"Insurance Agent",
            "type":"Services"
        }
    ],
    "sg:phone":"+1 631 360 0100",
    "sg:postcode":"11787",
    "sg:province":"NY",
    "wof:name":"Lighthouse Insurance",
    "wof:placetype":"venue"
},
  "geometry": {"coordinates":[-73.18751399999999,40.854045],"type":"Point"}
}