{
  "type": "Feature",
  "properties": {
    "addr:full":"2528 Bailey Ave Buffalo NY 14215",
    "addr:housenumber":"2528",
    "addr:postcode":"14215",
    "addr:street":"Bailey Ave",
    "iso:country":"US",
    "sg:address":"2528 Bailey Ave",
    "sg:city":"Buffalo",
    "sg:classifiers":[
        {
            "category":"Retail",
            "subcategory":"Funeral Services",
            "type":"Services"
        }
    ],
    "sg:phone":"+1 716 894 0325",
    "sg:postcode":"14215",
    "sg:province":"NY",
    "sg:tags":[
        "cemetery"
    ],
    "wof:name":"Lewis Brian K Funeral Home",
    "wof:placetype":"venue"
},
  "geometry": {"coordinates":[-78.81349899999999,42.9235],"type":"Point"}
}