{
  "type": "Feature",
  "properties": {
    "addr:full":"205 E 42nd St New York NY 10017",
    "addr:housenumber":"205",
    "addr:postcode":"10017",
    "addr:street":"E 42Nd St",
    "iso:country":"US",
    "sg:address":"205 E 42nd St",
    "sg:city":"New York",
    "sg:classifiers":[
        {
            "category":"Building & Trades",
            "subcategory":"Construction",
            "type":"Services"
        }
    ],
    "sg:phone":"+1 212 661 9378",
    "sg:postcode":"10017",
    "sg:province":"NY",
    "sg:tags":[
        "contractor"
    ],
    "wof:name":"Puppy House Publishing",
    "wof:placetype":"venue"
},
  "geometry": {"coordinates":[-73.974098,40.750702],"type":"Point"}
}