{
  "type": "Feature",
  "properties": {
    "addr:full":"5 Richbell Rd White Plains NY 10605",
    "addr:housenumber":"5",
    "addr:postcode":"10605",
    "addr:street":"Richbell Rd",
    "iso:country":"US",
    "sg:address":"5 Richbell Rd",
    "sg:city":"White Plains",
    "sg:classifiers":[
        {
            "category":"Professional",
            "subcategory":"Management & Consulting",
            "type":"Services"
        }
    ],
    "sg:phone":"+1   ",
    "sg:postcode":"10605",
    "sg:province":"NY",
    "sg:tags":[
        "business"
    ],
    "wof:name":"Birks Consulting Corp",
    "wof:placetype":"venue"
},
  "geometry": {"coordinates":[-73.74559600000001,41.005754],"type":"Point"}
}