{
  "type": "Feature",
  "properties": {
    "iso:country":"US",
    "sg:address":"45 W Main St",
    "sg:city":"Fredonia",
    "sg:classifiers":[
        {
            "category":"Restaurant",
            "type":"Food & Drink"
        }
    ],
    "sg:menulink":"http://www.allmenus.com/ny/pomfret/148378-subway/menu/",
    "sg:phone":"+1 716 672 7960",
    "sg:postcode":"14063",
    "sg:province":"NY",
    "sg:tags":[
        "american",
        "sandwich"
    ],
    "wof:name":"Subway",
    "wof:placetype":"venue"
},
  "geometry": {"coordinates":[-79.332446,42.439374],"type":"Point"}
}