{
  "type": "Feature",
  "properties": {
    "addr:full":"1 Christopher St Binghamton NY 13903",
    "addr:housenumber":"1",
    "addr:postcode":"13903",
    "addr:street":"Christopher St",
    "iso:country":"US",
    "sg:address":"1 Christopher St",
    "sg:city":"Binghamton",
    "sg:classifiers":[
        {
            "category":"Professional",
            "subcategory":"Detective & Security Services",
            "type":"Services"
        }
    ],
    "sg:phone":"+1 607 427 3584",
    "sg:postcode":"13903",
    "sg:province":"NY",
    "sg:tags":[
        "guard",
        "patrol"
    ],
    "wof:name":"Edward G Plonski",
    "wof:placetype":"venue"
},
  "geometry": {"coordinates":[-75.91134599999999,42.08329],"type":"Point"}
}