{
  "type": "Feature",
  "properties": {
    "iso:country":"US",
    "sg:address":"305 E Shore Rd",
    "sg:city":"Great Neck",
    "sg:classifiers":[
        {
            "category":"Professional",
            "type":"Services"
        }
    ],
    "sg:phone":"+1 516 829 3028",
    "sg:postcode":"11030",
    "sg:province":"NY",
    "sg:tags":[
        "establishment"
    ],
    "wof:name":"Mallikarjuna MC",
    "wof:placetype":"venue"
},
  "geometry": {"coordinates":[-73.708865,40.790686],"type":"Point"}
}