{
  "type": "Feature",
  "properties": {
    "addr:full":"7200 Ridge Boulevard Brooklyn NY 11209",
    "addr:housenumber":"7200",
    "addr:postcode":"11209",
    "addr:street":"Ridge Boulevard",
    "iso:country":"US",
    "sg:address":"7200 Ridge Boulevard",
    "sg:city":"Brooklyn",
    "sg:classifiers":[
        {
            "category":"Real Estate",
            "subcategory":"Real Estate Services",
            "type":"Services"
        }
    ],
    "sg:phone":"+1 718 745 1900",
    "sg:postcode":"11209",
    "sg:province":"NY",
    "sg:tags":[
        "management",
        "property"
    ],
    "wof:name":"Flagg Court Realty Company",
    "wof:placetype":"venue"
},
  "geometry": {"coordinates":[-74.029206,40.624722],"type":"Point"}
}