{
  "type": "Feature",
  "properties": {
    "iso:country":"US",
    "sg:address":"776 Watervliet Shaker Rd",
    "sg:city":"Latham",
    "sg:classifiers":[
        {
            "category":"Health Services",
            "subcategory":"Health Practitioner",
            "type":"Services"
        },
        {
            "category":"Health Services",
            "subcategory":"Doctor",
            "type":"Services"
        }
    ],
    "sg:phone":"+1 518 782 2200",
    "sg:postcode":"12110",
    "sg:province":"NY",
    "sg:tags":[
        "physician",
        "training",
        "safety",
        "c",
        "occupational"
    ],
    "sg:website":"www.accesshealthsystems.com",
    "wof:name":"Access Health Systems",
    "wof:placetype":"venue"
},
  "geometry": {"coordinates":[-73.79612400000001,42.73902],"type":"Point"}
}