{
  "type": "Feature",
  "properties": {
    "addr:full":"373 Smithtown Byp Hauppauge NY 11788",
    "addr:housenumber":"373",
    "addr:postcode":"11788",
    "addr:street":"Byp",
    "iso:country":"US",
    "sg:address":"373 Smithtown Byp",
    "sg:city":"Hauppauge",
    "sg:classifiers":[
        {
            "category":"Manufacturing",
            "subcategory":"Printing",
            "type":"Manufacturing & Wholesale Goods"
        }
    ],
    "sg:phone":"+1 631 293 3877",
    "sg:postcode":"11788",
    "sg:province":"NY",
    "sg:tags":[
        "printer"
    ],
    "wof:name":"Systematic Impression Inc",
    "wof:placetype":"venue"
},
  "geometry": {"coordinates":[-73.175686,40.842791],"type":"Point"}
}