{
  "type": "Feature",
  "properties": {
    "addr:full":"126 Saint Marks Pl New York NY 10009",
    "addr:housenumber":"126",
    "addr:postcode":"10009",
    "addr:street":"Saint Marks Pl",
    "iso:country":"US",
    "sg:address":"126 Saint Marks Pl",
    "sg:city":"New York",
    "sg:classifiers":[
        {
            "category":"Restaurant",
            "type":"Food & Drink"
        }
    ],
    "sg:menulink":"http://www.allmenus.com/ny/new-york/7011-why-curry/menu/",
    "sg:phone":"+1 212 473 1620",
    "sg:postcode":"10009",
    "sg:province":"NY",
    "sg:tags":[
        "indian",
        "asian"
    ],
    "wof:name":"Why Curry",
    "wof:placetype":"venue"
},
  "geometry": {"coordinates":[-73.983806,40.726701],"type":"Point"}
}