{
  "type": "Feature",
  "properties": {
    "iso:country":"US",
    "sg:address":"200 Lexington Ave Rm 420",
    "sg:city":"New York",
    "sg:classifiers":[
        {
            "category":"Building & Trades",
            "subcategory":"Construction",
            "type":"Services"
        }
    ],
    "sg:phone":"+1 212 726 9708",
    "sg:postcode":"10016",
    "sg:province":"NY",
    "sg:tags":[
        "interior",
        "design"
    ],
    "wof:name":"Interior Options",
    "wof:placetype":"venue"
},
  "geometry": {"coordinates":[-73.977203,40.744499],"type":"Point"}
}