{
  "type": "Feature",
  "properties": {
    "addr:full":"15 Home St White Plains NY 10606",
    "addr:housenumber":"15",
    "addr:postcode":"10606",
    "addr:street":"Home St",
    "iso:country":"US",
    "sg:address":"15 Home St",
    "sg:city":"White Plains",
    "sg:classifiers":[
        {
            "category":"Building & Trades",
            "subcategory":"Plumbing",
            "type":"Services"
        }
    ],
    "sg:phone":"+1 914 769 1612",
    "sg:postcode":"10606",
    "sg:province":"NY",
    "sg:tags":[
        "air",
        "heating",
        "conditioning",
        "contractor"
    ],
    "wof:name":"Tempaire Heating & Cooling",
    "wof:placetype":"venue"
},
  "geometry": {"coordinates":[-73.77623199999999,41.027309],"type":"Point"}
}