{
  "type": "Feature",
  "properties": {
    "addr:full":"161 Lancaster Ave Buffalo NY 14222",
    "addr:housenumber":"161",
    "addr:postcode":"14222",
    "addr:street":"Lancaster Ave",
    "iso:country":"US",
    "sg:address":"161 Lancaster Ave",
    "sg:city":"Buffalo",
    "sg:classifiers":[
        {
            "category":"Building & Trades",
            "subcategory":"Cleaning & Sanitation",
            "type":"Services"
        }
    ],
    "sg:phone":"+1 716 884 8586",
    "sg:postcode":"14222",
    "sg:province":"NY",
    "sg:tags":[
        "fireplace",
        "chimney"
    ],
    "wof:name":"John Canna Construction",
    "wof:placetype":"venue"
},
  "geometry": {"coordinates":[-78.875148,42.919549],"type":"Point"}
}