{
  "type": "Feature",
  "properties": {
    "addr:full":"740 Hempstead Tpke Franklin Square NY 11010",
    "addr:housenumber":"740",
    "addr:postcode":"11010",
    "addr:street":"Hempstead Tpke",
    "iso:country":"US",
    "sg:address":"740 Hempstead Tpke",
    "sg:city":"Franklin Square",
    "sg:classifiers":[
        {
            "category":"Autos & Motor Vehicles",
            "subcategory":"Fuel & Gas Station",
            "type":"Retail Goods"
        }
    ],
    "sg:phone":"+1 516 280 5257",
    "sg:postcode":"11010",
    "sg:province":"NY",
    "wof:name":"Star Gas Station",
    "wof:placetype":"venue"
},
  "geometry": {"coordinates":[-73.66703099999999,40.706946],"type":"Point"}
}