{
  "type": "Feature",
  "properties": {
    "addr:full":"4100 Vestal Rd Ste 104 Vestal NY 13850",
    "addr:housenumber":"4100",
    "addr:postcode":"13850",
    "addr:street":"Vestal Rd Ste 104",
    "iso:country":"US",
    "sg:address":"4100 Vestal Rd Ste 104",
    "sg:city":"Vestal",
    "sg:classifiers":[
        {
            "category":"Community Center",
            "type":"Public Place"
        }
    ],
    "sg:phone":"+1 607 798 1808",
    "sg:postcode":"13850",
    "sg:province":"NY",
    "sg:tags":[
        "medical"
    ],
    "wof:name":"Riverfront Medical Services",
    "wof:placetype":"venue"
},
  "geometry": {"coordinates":[-75.97618799999999,42.09573],"type":"Point"}
}