{
  "type": "Feature",
  "properties": {
    "addr:full":"110 Saint Nicholas Ave New York NY 10026",
    "addr:housenumber":"110",
    "addr:postcode":"10026",
    "addr:street":"Saint Nicholas Ave",
    "iso:country":"US",
    "sg:address":"110 Saint Nicholas Ave",
    "sg:city":"New York",
    "sg:classifiers":[
        {
            "category":"Fast Food",
            "type":"Food & Drink"
        }
    ],
    "sg:phone":"+1 646 684 4404",
    "sg:postcode":"10026",
    "sg:province":"NY",
    "sg:tags":[
        "chicken",
        "wing"
    ],
    "wof:name":"S & T Fried Chicken Inc",
    "wof:placetype":"venue"
},
  "geometry": {"coordinates":[-73.952568,40.802982],"type":"Point"}
}