{
  "type": "Feature",
  "properties": {
    "addr:full":"946 Hempstead Tpke Franklin Square NY 11010",
    "addr:housenumber":"946",
    "addr:postcode":"11010",
    "addr:street":"Hempstead Tpke",
    "iso:country":"US",
    "sg:address":"946 Hempstead Tpke",
    "sg:city":"Franklin Square",
    "sg:classifiers":[
        {
            "category":"Arts & Performance",
            "subcategory":"Arts Center",
            "type":"Entertainment"
        }
    ],
    "sg:phone":"+1 516 352 8815",
    "sg:postcode":"11010",
    "sg:province":"NY",
    "sg:tags":[
        "performing"
    ],
    "wof:name":"American Dance Center",
    "wof:placetype":"venue"
},
  "geometry": {"coordinates":[-73.6717,40.7071],"type":"Point"}
}