{
  "type": "Feature",
  "properties": {
    "addr:full":"24912 Jericho Tpke Floral Park NY 11001",
    "addr:housenumber":"24912",
    "addr:postcode":"11001",
    "addr:street":"Jericho Tpke",
    "iso:country":"US",
    "sg:address":"24912 Jericho Tpke",
    "sg:city":"Floral Park",
    "sg:classifiers":[
        {
            "category":"Health Services",
            "subcategory":"Doctor",
            "type":"Services"
        }
    ],
    "sg:phone":"+1 516 328 3111",
    "sg:postcode":"11001",
    "sg:province":"NY",
    "sg:tags":[
        "podiatrist"
    ],
    "wof:name":"Greenberg Alan J Dr",
    "wof:placetype":"venue"
},
  "geometry": {"coordinates":[-73.711304,40.727001],"type":"Point"}
}