{
  "type": "Feature",
  "properties": {
    "addr:full":"25 Water St Baldwinsville NY 13027",
    "addr:housenumber":"25",
    "addr:postcode":"13027",
    "addr:street":"Water St",
    "iso:country":"US",
    "sg:address":"25 Water St",
    "sg:city":"Baldwinsville",
    "sg:classifiers":[
        {
            "category":"Professional",
            "subcategory":"Management & Consulting",
            "type":"Services"
        }
    ],
    "sg:phone":"+1 315 635 6382",
    "sg:postcode":"13027",
    "sg:province":"NY",
    "sg:tags":[
        "consultant",
        "business"
    ],
    "wof:name":"North American Business Svc",
    "wof:placetype":"venue"
},
  "geometry": {"coordinates":[-76.332824,43.155615],"type":"Point"}
}