{
  "type": "Feature",
  "properties": {
    "addr:full":"449 Boston Post Rd Port Chester NY 10573",
    "addr:housenumber":"449",
    "addr:postcode":"10573",
    "addr:street":"Boston Post Rd",
    "iso:country":"US",
    "sg:address":"449 Boston Post Rd",
    "sg:city":"Port Chester",
    "sg:classifiers":[
        {
            "category":"Utilities",
            "subcategory":"Mobile Phone",
            "type":"Services"
        }
    ],
    "sg:phone":"+1 914 939 4028",
    "sg:postcode":"10573",
    "sg:province":"NY",
    "sg:tags":[
        "telephone",
        "cellular"
    ],
    "wof:name":"Verizon Wireless",
    "wof:placetype":"venue"
},
  "geometry": {"coordinates":[-73.674458,40.994053],"type":"Point"}
}