{
  "type": "Feature",
  "properties": {
    "addr:full":"56 E 30th St New York NY 10016",
    "addr:housenumber":"56",
    "addr:postcode":"10016",
    "addr:street":"E 30Th St",
    "iso:country":"US",
    "sg:address":"56 E 30th St",
    "sg:city":"New York",
    "sg:classifiers":[
        {
            "category":"Building & Trades",
            "subcategory":"Cleaning & Sanitation",
            "type":"Services"
        }
    ],
    "sg:phone":"+1 212 561 5047",
    "sg:postcode":"10016",
    "sg:province":"NY",
    "sg:tags":[
        "carpet"
    ],
    "wof:name":"Anytime Carpets Cleaning",
    "wof:placetype":"venue"
},
  "geometry": {"coordinates":[-73.983677,40.74475],"type":"Point"}
}