{
  "type": "Feature",
  "properties": {
    "addr:full":"325 Clear View Ln Massapequa NY 11758",
    "addr:housenumber":"325",
    "addr:postcode":"11758",
    "addr:street":"Clear View Ln",
    "iso:country":"US",
    "sg:address":"325 Clear View Ln",
    "sg:city":"Massapequa",
    "sg:classifiers":[
        {
            "category":"Banks & Credit Unions",
            "subcategory":"Investment Brokerage",
            "type":"Services"
        }
    ],
    "sg:phone":"+1 516 799 1417",
    "sg:postcode":"11758",
    "sg:province":"NY",
    "sg:tags":[
        "security"
    ],
    "wof:name":"Debra A Bushman",
    "wof:placetype":"venue"
},
  "geometry": {"coordinates":[-73.465451,40.651234],"type":"Point"}
}