{
  "type": "Feature",
  "properties": {
    "iso:country":"US",
    "sg:address":"15 Oakland Ave",
    "sg:city":"Warwick",
    "sg:classifiers":[
        {
            "category":"Real Estate",
            "subcategory":"Real Estate Agent",
            "type":"Services"
        }
    ],
    "sg:phone":"+1 845 986 1592",
    "sg:postcode":"10990",
    "sg:province":"NY",
    "wof:name":"Better Homes and Gardens",
    "wof:placetype":"venue"
},
  "geometry": {"coordinates":[-74.359979,41.254639],"type":"Point"}
}