{
  "type": "Feature",
  "properties": {
    "iso:country":"US",
    "sg:address":"41 Ross Ave",
    "sg:city":"Melville",
    "sg:classifiers":[
        {
            "category":"Professional",
            "subcategory":"Lawyer & Legal Services",
            "type":"Services"
        }
    ],
    "sg:phone":"+1   ",
    "sg:postcode":"11747",
    "sg:province":"NY",
    "wof:name":"Badash Larry Law Office of",
    "wof:placetype":"venue"
},
  "geometry": {"coordinates":[-73.414063,40.791731],"type":"Point"}
}