{
  "type": "Feature",
  "properties": {
    "iso:country":"US",
    "sg:address":"151 W 46th Street",
    "sg:city":"New York",
    "sg:classifiers":[
        {
            "category":"Shopping",
            "subcategory":"Jewelry",
            "type":"Retail Goods"
        }
    ],
    "sg:phone":"+1 212 302 6073",
    "sg:postcode":"10036",
    "sg:province":"NY",
    "sg:website":"www.finelasercut.com",
    "wof:name":"Infinity Jewelers of Ny",
    "wof:placetype":"venue"
},
  "geometry": {"coordinates":[-73.984589,40.758274],"type":"Point"}
}