{
  "type": "Feature",
  "properties": {
    "addr:full":"486 Dekalb Ave Brooklyn NY 11205",
    "addr:housenumber":"486",
    "addr:postcode":"11205",
    "addr:street":"Dekalb Ave",
    "iso:country":"US",
    "sg:address":"486 Dekalb Ave",
    "sg:city":"Brooklyn",
    "sg:classifiers":[
        {
            "category":"Restaurant",
            "type":"Food & Drink"
        }
    ],
    "sg:phone":"+1 718 398 4733",
    "sg:postcode":"11205",
    "sg:province":"NY",
    "wof:name":"Sammy's Pizzeria",
    "wof:placetype":"venue"
},
  "geometry": {"coordinates":[-73.956518,40.690699],"type":"Point"}
}