{
  "type": "Feature",
  "properties": {
    "iso:country":"US",
    "sg:address":"35 Center St",
    "sg:city":"Ardsley",
    "sg:classifiers":[
        {
            "category":"Banks & Credit Unions",
            "subcategory":"Bank",
            "type":"Services"
        }
    ],
    "sg:phone":"+1 914 693 3663",
    "sg:postcode":"10502",
    "sg:province":"NY",
    "sg:tags":[
        "savings",
        "loan",
        "association"
    ],
    "wof:name":"Peoples Westchester Savings",
    "wof:placetype":"venue"
},
  "geometry": {"coordinates":[-73.846039,41.012558],"type":"Point"}
}