{
  "type": "Feature",
  "properties": {
    "addr:full":"726 Graves St Clayton NY 13624",
    "addr:housenumber":"726",
    "addr:postcode":"13624",
    "addr:street":"Graves St",
    "iso:country":"US",
    "sg:address":"726 Graves St",
    "sg:city":"Clayton",
    "sg:classifiers":[
        {
            "category":"Retail",
            "subcategory":"Self-service Laundry",
            "type":"Services"
        }
    ],
    "sg:phone":"+1   ",
    "sg:postcode":"13624",
    "sg:province":"NY",
    "sg:tags":[
        "coin"
    ],
    "wof:name":"Kleen It Center",
    "wof:placetype":"venue"
},
  "geometry": {"coordinates":[-76.078959,44.235707],"type":"Point"}
}