{
  "type": "Feature",
  "properties": {
    "addr:full":"25 Washington Blvd Commack NY 11725",
    "addr:housenumber":"25",
    "addr:postcode":"11725",
    "addr:street":"Washington Blvd",
    "iso:country":"US",
    "sg:address":"25 Washington Blvd",
    "sg:city":"Commack",
    "sg:classifiers":[
        {
            "category":"Building & Trades",
            "subcategory":"Landscaping Services",
            "type":"Services"
        }
    ],
    "sg:phone":"+1 631 543 2109",
    "sg:postcode":"11725",
    "sg:province":"NY",
    "sg:tags":[
        "excavation",
        "landscape",
        "contractor"
    ],
    "wof:name":"Kohler Landscaping",
    "wof:placetype":"venue"
},
  "geometry": {"coordinates":[-73.265371,40.857502],"type":"Point"}
}