{
  "type": "Feature",
  "properties": {
    "iso:country":"US",
    "sg:address":"808 Reed St",
    "sg:city":"Olean",
    "sg:phone":"+1 716 372 4646",
    "sg:postcode":"14760",
    "sg:province":"NY",
    "wof:name":"Southern Tier Taxi",
    "wof:placetype":"venue"
},
  "geometry": {"coordinates":[-78.43978,42.083288],"type":"Point"}
}