{
  "type": "Feature",
  "properties": {
    "addr:full":"7 N Main St Angola NY 14006",
    "addr:housenumber":"7",
    "addr:postcode":"14006",
    "addr:street":"N Main St",
    "iso:country":"US",
    "sg:address":"7 N Main St",
    "sg:city":"Angola",
    "sg:classifiers":[
        {
            "category":"Home & Garden",
            "subcategory":"Building Materials",
            "type":"Retail Goods"
        }
    ],
    "sg:phone":"+1 716 549 2444",
    "sg:postcode":"14006",
    "sg:province":"NY",
    "sg:tags":[
        "glass",
        "window",
        "plate"
    ],
    "wof:name":"Loretto Glass Svc",
    "wof:placetype":"venue"
},
  "geometry": {"coordinates":[-79.027627,42.638797],"type":"Point"}
}