{
  "type": "Feature",
  "properties": {
    "addr:full":"4301 Broadway Astoria NY 11103",
    "addr:housenumber":"4301",
    "addr:postcode":"11103",
    "addr:street":"Broadway",
    "iso:country":"US",
    "sg:address":"4301 Broadway",
    "sg:city":"Astoria",
    "sg:classifiers":[
        {
            "category":"Health Services",
            "subcategory":"Health Practitioner",
            "type":"Services"
        }
    ],
    "sg:phone":"+1 718 274 4200",
    "sg:postcode":"11103",
    "sg:province":"NY",
    "sg:tags":[
        "therapy",
        "physical"
    ],
    "wof:name":"Seong Chan Cho Physical Therapy Pc",
    "wof:placetype":"venue"
},
  "geometry": {"coordinates":[-73.916524,40.757964],"type":"Point"}
}