{
  "type": "Feature",
  "properties": {
    "addr:full":"9020 Wehrle Dr Clarence NY 14031",
    "addr:postcode":"9020;14031",
    "addr:street":"Wehrle Dr",
    "iso:country":"US",
    "sg:address":"9020 Wehrle Dr",
    "sg:city":"Clarence",
    "sg:classifiers":[
        {
            "category":"Wholesale",
            "subcategory":"Electrical",
            "type":"Manufacturing & Wholesale Goods"
        }
    ],
    "sg:phone":"+1 716 626 9020",
    "sg:postcode":"14031",
    "sg:province":"NY",
    "sg:tags":[
        "intercommunication"
    ],
    "sg:website":"www.transwave.net",
    "wof:name":"Transwave Communication System",
    "wof:placetype":"venue"
},
  "geometry": {"coordinates":[-78.65622399999999,42.96027],"type":"Point"}
}