{
  "type": "Feature",
  "properties": {
    "iso:country":"US",
    "sg:address":"503 W 43rd Street",
    "sg:city":"New York",
    "sg:classifiers":[
        {
            "category":"Professional",
            "type":"Services"
        }
    ],
    "sg:phone":"+1 212 947 2480",
    "sg:postcode":"10036",
    "sg:province":"NY",
    "sg:tags":[
        "caterer"
    ],
    "wof:name":"Canard",
    "wof:placetype":"venue"
},
  "geometry": {"coordinates":[-73.995188,40.76039],"type":"Point"}
}