{
  "type": "Feature",
  "properties": {
    "iso:country":"US",
    "sg:address":"8528 E Main St",
    "sg:city":"Honeoye",
    "sg:classifiers":[
        {
            "category":"Education",
            "subcategory":"School",
            "type":"Public Place"
        }
    ],
    "sg:phone":"+1 585 229 4125",
    "sg:postcode":"14471",
    "sg:province":"NY",
    "wof:name":"Honeoye Superintendent's Ofc",
    "wof:placetype":"venue"
},
  "geometry": {"coordinates":[-77.50366699999999,42.789677],"type":"Point"}
}