{
  "type": "Feature",
  "properties": {
    "addr:full":"252 Wellington Rd S Garden City NY 11530",
    "addr:housenumber":"252",
    "addr:postcode":"11530",
    "addr:street":"Wellington Rd S",
    "iso:country":"US",
    "sg:address":"252 Wellington Rd S",
    "sg:city":"Garden City",
    "sg:classifiers":[
        {
            "category":"Social Services",
            "subcategory":"Child Care",
            "type":"Services"
        }
    ],
    "sg:phone":"+1   ",
    "sg:postcode":"11530",
    "sg:province":"NY",
    "sg:tags":[
        "day"
    ],
    "wof:name":"Little Saints Preschool",
    "wof:placetype":"venue"
},
  "geometry": {"coordinates":[-73.662721,40.712903],"type":"Point"}
}