{
  "type": "Feature",
  "properties": {
    "addr:full":"1261 Willoughby Ave Brooklyn NY 11237",
    "addr:housenumber":"1261",
    "addr:postcode":"11237",
    "addr:street":"Willoughby Ave",
    "iso:country":"US",
    "sg:address":"1261 Willoughby Ave",
    "sg:city":"Brooklyn",
    "sg:classifiers":[
        {
            "category":"Manufacturing",
            "subcategory":"Metals",
            "type":"Manufacturing & Wholesale Goods"
        }
    ],
    "sg:phone":"+1 718 386 5960",
    "sg:postcode":"11237",
    "sg:province":"NY",
    "sg:tags":[
        "plating"
    ],
    "wof:name":"Tru-Tone Metal Products Inc",
    "wof:placetype":"venue"
},
  "geometry": {"coordinates":[-73.921903,40.705136],"type":"Point"}
}