{
  "type": "Feature",
  "properties": {
    "iso:country":"US",
    "sg:address":"268 E Main St",
    "sg:city":"Springville",
    "sg:classifiers":[
        {
            "category":"Insurance",
            "subcategory":"Insurance Agent",
            "type":"Services"
        }
    ],
    "sg:phone":"+1 716 592 4813",
    "sg:postcode":"14141",
    "sg:province":"NY",
    "sg:tags":[
        "agency"
    ],
    "wof:name":"Nationwide",
    "wof:placetype":"venue"
},
  "geometry": {"coordinates":[-78.65825599999999,42.508558],"type":"Point"}
}