{
  "type": "Feature",
  "properties": {
    "iso:country":"US",
    "sg:address":"11 Greenridge Cres",
    "sg:city":"Hamlin",
    "sg:classifiers":[
        {
            "category":"Building & Trades",
            "subcategory":"Plumbing",
            "type":"Services"
        }
    ],
    "sg:phone":"+1 585 964 7840",
    "sg:postcode":"14464",
    "sg:province":"NY",
    "sg:tags":[
        "contractor"
    ],
    "wof:name":"Gene Brunette Plumbing",
    "wof:placetype":"venue"
},
  "geometry": {"coordinates":[-77.910472,43.287041],"type":"Point"}
}