{
  "type": "Feature",
  "properties": {
    "addr:full":"111 Nassau St Elmont NY 11003",
    "addr:housenumber":"111",
    "addr:postcode":"11003",
    "addr:street":"Nassau St",
    "iso:country":"US",
    "sg:address":"111 Nassau St",
    "sg:city":"Elmont",
    "sg:classifiers":[
        {
            "category":"Professional",
            "subcategory":"Lawyer & Legal Services",
            "type":"Services"
        }
    ],
    "sg:phone":"+1 516 305 4039",
    "sg:postcode":"11003",
    "sg:province":"NY",
    "wof:name":"Tre Taid Legal Service",
    "wof:placetype":"venue"
},
  "geometry": {"coordinates":[-73.704302,40.690749],"type":"Point"}
}