{
  "type": "Feature",
  "properties": {
    "addr:full":"1020 Ave of the Americas New York NY 10018",
    "addr:housenumber":"1020",
    "addr:postcode":"10018",
    "addr:street":"Ave Of The Americas",
    "iso:country":"US",
    "sg:address":"1020 Ave of the Americas",
    "sg:city":"New York",
    "sg:classifiers":[
        {
            "category":"Wholesale",
            "subcategory":"Apparel",
            "type":"Manufacturing & Wholesale Goods"
        }
    ],
    "sg:phone":"+1 212 944 0835",
    "sg:postcode":"10018",
    "sg:province":"NY",
    "sg:tags":[
        "clothing"
    ],
    "wof:name":"Fashion For Ever Inc",
    "wof:placetype":"venue"
},
  "geometry": {"coordinates":[-73.985488,40.752935],"type":"Point"}
}