{
  "type": "Feature",
  "properties": {
    "iso:country":"US",
    "sg:address":"333 W 52nd St",
    "sg:city":"New York",
    "sg:classifiers":[
        {
            "category":"Professional",
            "subcategory":"Research",
            "type":"Services"
        }
    ],
    "sg:phone":"+1 212 397 3911",
    "sg:postcode":"10019",
    "sg:province":"NY",
    "wof:name":"Jarvik Research Inc",
    "wof:placetype":"venue"
},
  "geometry": {"coordinates":[-73.987292,40.764413],"type":"Point"}
}