{
  "type": "Feature",
  "properties": {
    "addr:full":"88 Co Rte 32 Hastings NY 13076",
    "addr:housenumber":"88",
    "addr:postcode":"13076",
    "addr:street":"Co Rte 32",
    "iso:country":"US",
    "sg:address":"88 Co Rte 32",
    "sg:city":"Hastings",
    "sg:classifiers":[
        {
            "category":"Professional",
            "subcategory":"Management & Consulting",
            "type":"Services"
        }
    ],
    "sg:phone":"+1 315 668 6633",
    "sg:postcode":"13076",
    "sg:province":"NY",
    "sg:tags":[
        "construction"
    ],
    "wof:name":"Mallory Lumber & Steel",
    "wof:placetype":"venue"
},
  "geometry": {"coordinates":[-76.11648,43.323495],"type":"Point"}
}