{
  "type": "Feature",
  "properties": {
    "iso:country":"US",
    "sg:address":"1232 Virginia Ave",
    "sg:city":"Bronx",
    "sg:classifiers":[
        {
            "category":"Building & Trades",
            "subcategory":"Locksmith",
            "type":"Services"
        }
    ],
    "sg:phone":"+1 718 536 2868",
    "sg:postcode":"10472",
    "sg:province":"NY",
    "sg:tags":[
        "key"
    ],
    "wof:name":"1 Hour 24 Hour 7 Day Bronx Emerge Loc",
    "wof:placetype":"venue"
},
  "geometry": {"coordinates":[-73.86073500000001,40.831443],"type":"Point"}
}