{
  "type": "Feature",
  "properties": {
    "iso:country":"US",
    "sg:address":"6525 US Hwy 209",
    "sg:city":"Kerhonkson",
    "sg:classifiers":[
        {
            "category":"Restaurant",
            "type":"Food & Drink"
        }
    ],
    "sg:phone":"+1   ",
    "sg:postcode":"12446",
    "sg:province":"NY",
    "sg:tags":[
        "eating"
    ],
    "wof:name":"Mineweska Motors",
    "wof:placetype":"venue"
},
  "geometry": {"coordinates":[-74.31474300000001,41.771323],"type":"Point"}
}