{
  "type": "Feature",
  "properties": {
    "iso:country":"US",
    "sg:address":"66 W 39 St",
    "sg:city":"New York",
    "sg:classifiers":[
        {
            "category":"Real Estate",
            "subcategory":"Real Estate Agent",
            "type":"Services"
        }
    ],
    "sg:phone":"+1 212 982 9442",
    "sg:postcode":"10018",
    "sg:province":"NY",
    "wof:name":"CBR Assoc",
    "wof:placetype":"venue"
},
  "geometry": {"coordinates":[-73.983902,40.751964],"type":"Point"}
}