{
  "type": "Feature",
  "properties": {
    "iso:country":"US",
    "sg:address":"92 West Ave",
    "sg:city":"Saratoga Springs",
    "sg:classifiers":[
        {
            "category":"Professional",
            "subcategory":"Accounting & Tax Preparation",
            "type":"Services"
        }
    ],
    "sg:phone":"+1 518 587 7595",
    "sg:postcode":"12866",
    "sg:province":"NY",
    "sg:tags":[
        "return",
        "filing"
    ],
    "sg:website":"www.libertytax.com",
    "wof:name":"Liberty Tax Svc",
    "wof:placetype":"venue"
},
  "geometry": {"coordinates":[-73.80390199999999,43.079855],"type":"Point"}
}