{
  "type": "Feature",
  "properties": {
    "addr:full":"229 Beartown Rd Painted Post NY 14870",
    "addr:housenumber":"229",
    "addr:postcode":"14870",
    "addr:street":"Beartown Rd",
    "iso:country":"US",
    "sg:address":"229 Beartown Rd",
    "sg:city":"Painted Post",
    "sg:classifiers":[
        {
            "category":"Building & Trades",
            "subcategory":"Landscaping Services",
            "type":"Services"
        }
    ],
    "sg:phone":"+1 607 962 1320",
    "sg:postcode":"14870",
    "sg:province":"NY",
    "sg:tags":[
        "lawn",
        "maintenance",
        "grounds"
    ],
    "wof:name":"Lawn Boss",
    "wof:placetype":"venue"
},
  "geometry": {"coordinates":[-77.131399,42.142801],"type":"Point"}
}