{
  "type": "Feature",
  "properties": {
    "iso:country":"US",
    "sg:address":"78 W Main St",
    "sg:city":"Riverhead",
    "sg:classifiers":[
        {
            "category":"Wholesale",
            "subcategory":"Metals & Minerals",
            "type":"Manufacturing & Wholesale Goods"
        }
    ],
    "sg:phone":"+1   ",
    "sg:postcode":"11901",
    "sg:province":"NY",
    "sg:tags":[
        "machine",
        "tool",
        "accessory",
        "center",
        "mfg"
    ],
    "wof:name":"Rival Resources Company",
    "wof:placetype":"venue"
},
  "geometry": {"coordinates":[-72.66286599999999,40.917014],"type":"Point"}
}