{
  "type": "Feature",
  "properties": {
    "iso:country":"US",
    "sg:address":"349 5th Ave",
    "sg:city":"Brooklyn",
    "sg:classifiers":[
        {
            "category":"Restaurant",
            "type":"Food & Drink"
        }
    ],
    "sg:phone":"+1 718 788 2548",
    "sg:postcode":"11215",
    "sg:province":"NY",
    "sg:tags":[
        "caribbean"
    ],
    "wof:name":"Nibble Nook",
    "wof:placetype":"venue"
},
  "geometry": {"coordinates":[-73.984047,40.671855],"type":"Point"}
}