{
  "type": "Feature",
  "properties": {
    "addr:full":"50 E State St Sherburne NY 13460",
    "addr:housenumber":"50",
    "addr:postcode":"13460",
    "addr:street":"E State St",
    "iso:country":"US",
    "sg:address":"50 E State St",
    "sg:city":"Sherburne",
    "sg:classifiers":[
        {
            "category":"Farming",
            "subcategory":"Dairy Farm",
            "type":"Manufacturing & Wholesale Goods"
        }
    ],
    "sg:phone":"+1 607 674 6211",
    "sg:postcode":"13460",
    "sg:province":"NY",
    "wof:name":"Willdale",
    "wof:placetype":"venue"
},
  "geometry": {"coordinates":[-75.49270199999999,42.678007],"type":"Point"}
}