{
  "type": "Feature",
  "properties": {
    "addr:full":"460 Park Ave New York NY 10022",
    "addr:housenumber":"460",
    "addr:postcode":"10022",
    "addr:street":"Park Ave",
    "iso:country":"US",
    "sg:address":"460 Park Ave",
    "sg:city":"New York",
    "sg:classifiers":[
        {
            "category":"Wholesale",
            "subcategory":"Drugs",
            "type":"Manufacturing & Wholesale Goods"
        },
        {
            "category":"Professional",
            "type":"Services"
        }
    ],
    "sg:phone":"+1 212 715 7337",
    "sg:postcode":"10022",
    "sg:province":"NY",
    "sg:tags":[
        "establishment",
        "perfume"
    ],
    "wof:name":"Mode Et Parfums Corp",
    "wof:placetype":"venue"
},
  "geometry": {"coordinates":[-73.970417,40.762154],"type":"Point"}
}