{
  "type": "Feature",
  "properties": {
    "addr:full":"80 W 40 St New York NY 10018",
    "addr:housenumber":"80",
    "addr:postcode":"10018",
    "addr:street":"W 40 St",
    "iso:country":"US",
    "sg:address":"80 W 40 St",
    "sg:city":"New York",
    "sg:classifiers":[
        {
            "category":"Shopping",
            "subcategory":"Clothing, Apparel, & Fashions",
            "type":"Retail Goods"
        }
    ],
    "sg:phone":"+1 212 719 4596",
    "sg:postcode":"10018",
    "sg:province":"NY",
    "sg:tags":[
        "sportswear"
    ],
    "sg:website":"www.freecountry.com",
    "wof:name":"Free Country",
    "wof:placetype":"venue"
},
  "geometry": {"coordinates":[-73.983097,40.752385],"type":"Point"}
}