{
  "type": "Feature",
  "properties": {
    "addr:full":"90 Vandam St New York NY 10013",
    "addr:housenumber":"90",
    "addr:postcode":"10013",
    "addr:street":"Vandam St",
    "iso:country":"US",
    "sg:address":"90 Vandam St",
    "sg:city":"New York",
    "sg:classifiers":[
        {
            "category":"Shopping",
            "subcategory":"Hobbies, Toys, & Games",
            "type":"Retail Goods"
        }
    ],
    "sg:phone":"+1   ",
    "sg:postcode":"10013",
    "sg:province":"NY",
    "sg:tags":[
        "supply"
    ],
    "wof:name":"Tcs Inc",
    "wof:placetype":"venue"
},
  "geometry": {"coordinates":[-74.008247,40.726577],"type":"Point"}
}