{
  "type": "Feature",
  "properties": {
    "addr:full":"757 Stone Rd West Winfield NY 13491",
    "addr:housenumber":"757",
    "addr:postcode":"13491",
    "addr:street":"Stone Rd",
    "iso:country":"US",
    "sg:address":"757 Stone Rd",
    "sg:city":"West Winfield",
    "sg:classifiers":[
        {
            "category":"Shopping",
            "subcategory":"Florist",
            "type":"Retail Goods"
        }
    ],
    "sg:phone":"+1 315 822 6956",
    "sg:postcode":"13491",
    "sg:province":"NY",
    "wof:name":"Stone Road Farm & Flower Shop",
    "wof:placetype":"venue"
},
  "geometry": {"coordinates":[-75.19898999999999,42.908198],"type":"Point"}
}