{
  "type": "Feature",
  "properties": {
    "iso:country":"US",
    "sg:address":"2754 Niagara Falls Blvd",
    "sg:city":"Niagara Falls",
    "sg:classifiers":[
        {
            "category":"Travel",
            "subcategory":"Hotels & Motels",
            "type":"Entertainment"
        }
    ],
    "sg:phone":"+1 716 692 6650",
    "sg:postcode":"14304",
    "sg:province":"NY",
    "wof:name":"Driftwood Motel",
    "wof:placetype":"venue"
},
  "geometry": {"coordinates":[-78.897931,43.090651],"type":"Point"}
}