{
  "type": "Feature",
  "properties": {
    "addr:full":"130 Seeley Rd Syracuse NY 13224",
    "addr:housenumber":"130",
    "addr:postcode":"13224",
    "addr:street":"Seeley Rd",
    "iso:country":"US",
    "sg:address":"130 Seeley Rd",
    "sg:city":"Syracuse",
    "sg:classifiers":[
        {
            "category":"Personal",
            "subcategory":"Beauty Salon",
            "type":"Services"
        }
    ],
    "sg:phone":"+1 315 449 1111",
    "sg:postcode":"13224",
    "sg:province":"NY",
    "wof:name":"Headlines",
    "wof:placetype":"venue"
},
  "geometry": {"coordinates":[-76.104096,43.052612],"type":"Point"}
}