{
  "type": "Feature",
  "properties": {
    "addr:full":"451 E New York Ave Brooklyn NY 11225",
    "addr:housenumber":"451",
    "addr:postcode":"11225",
    "addr:street":"E New York Ave",
    "iso:country":"US",
    "sg:address":"451 E New York Ave",
    "sg:city":"Brooklyn",
    "sg:classifiers":[
        {
            "category":"Bars & Pubs",
            "type":"Food & Drink"
        }
    ],
    "sg:phone":"+1   ",
    "sg:postcode":"11225",
    "sg:province":"NY",
    "sg:tags":[
        "drinking"
    ],
    "wof:name":"Keg Lounge Inc",
    "wof:placetype":"venue"
},
  "geometry": {"coordinates":[-73.945621,40.661952],"type":"Point"}
}