{
  "type": "Feature",
  "properties": {
    "addr:full":"220 E 42nd St New York NY 10017",
    "addr:housenumber":"220",
    "addr:postcode":"10017",
    "addr:street":"E 42Nd St",
    "iso:country":"US",
    "sg:address":"220 E 42nd St",
    "sg:city":"New York",
    "sg:classifiers":[
        {
            "category":"Wholesale",
            "subcategory":"Non-durable Goods",
            "type":"Manufacturing & Wholesale Goods"
        },
        {
            "category":"Wholesale",
            "subcategory":"Durable Goods & Equipment",
            "type":"Manufacturing & Wholesale Goods"
        }
    ],
    "sg:phone":"+1 212 953 3200",
    "sg:postcode":"10017",
    "sg:province":"NY",
    "sg:tags":[
        "trader",
        "product",
        "importer",
        "forest"
    ],
    "wof:name":"Heinzel Import Export Inc",
    "wof:placetype":"venue"
},
  "geometry": {"coordinates":[-73.972587,40.74995],"type":"Point"}
}