{
  "type": "Feature",
  "properties": {
    "iso:country":"US",
    "sg:address":"143 Main St",
    "sg:city":"Johnson City",
    "sg:classifiers":[
        {
            "category":"Education",
            "subcategory":"School",
            "type":"Public Place"
        }
    ],
    "sg:phone":"+1 607 797 5444",
    "sg:postcode":"13790",
    "sg:province":"NY",
    "sg:tags":[
        "religious"
    ],
    "sg:website":"www.st-james-ms.org",
    "wof:name":"St James Middle School",
    "wof:placetype":"venue"
},
  "geometry": {"coordinates":[-75.950188,42.113244],"type":"Point"}
}