{
  "type": "Feature",
  "properties": {
    "iso:country":"US",
    "sg:address":"27 Glenmere Way",
    "sg:city":"Holbrook",
    "sg:classifiers":[
        {
            "category":"Retail",
            "subcategory":"Repair Shop",
            "type":"Services"
        }
    ],
    "sg:phone":"+1 631 472 5206",
    "sg:postcode":"11741",
    "sg:province":"NY",
    "sg:tags":[
        "business",
        "mfg",
        "wall",
        "pro",
        "wood",
        "cleaning"
    ],
    "sg:website":"http://www.eastendwoodstrippers.com",
    "wof:name":"East End Woodstripping",
    "wof:placetype":"venue"
},
  "geometry": {"coordinates":[-73.056104,40.778302],"type":"Point"}
}