{
  "type": "Feature",
  "properties": {
    "addr:full":"295 Brick Church Rd Troy NY 12180",
    "addr:housenumber":"295",
    "addr:postcode":"12180",
    "addr:street":"Brick Church Rd",
    "iso:country":"US",
    "sg:address":"295 Brick Church Rd",
    "sg:city":"Troy",
    "sg:classifiers":[
        {
            "category":"Government",
            "subcategory":"Police Station",
            "type":"Public Place"
        }
    ],
    "sg:phone":"+1 518 686 5342",
    "sg:postcode":"12180",
    "sg:province":"NY",
    "sg:tags":[
        "state"
    ],
    "wof:name":"State Police Dept",
    "wof:placetype":"venue"
},
  "geometry": {"coordinates":[-73.578306,42.753435],"type":"Point"}
}