{
  "type": "Feature",
  "properties": {
    "iso:country":"US",
    "sg:address":"45 W 45th St",
    "sg:city":"New York",
    "sg:classifiers":[
        {
            "category":"Professional",
            "subcategory":"Employment Agencies",
            "type":"Services"
        }
    ],
    "sg:phone":"+1 866 895 7983",
    "sg:postcode":"10036",
    "sg:province":"NY",
    "wof:name":"Epix",
    "wof:placetype":"venue"
},
  "geometry": {"coordinates":[-73.980904,40.756001],"type":"Point"}
}