{
  "type": "Feature",
  "properties": {
    "addr:full":"303 Division Ave Brooklyn NY 11211",
    "addr:housenumber":"303",
    "addr:postcode":"11211",
    "addr:street":"Division Ave",
    "iso:country":"US",
    "sg:address":"303 Division Ave",
    "sg:city":"Brooklyn",
    "sg:classifiers":[
        {
            "category":"Retail",
            "subcategory":"Auto Repair",
            "type":"Services"
        }
    ],
    "sg:phone":"+1   ",
    "sg:postcode":"11211",
    "sg:province":"NY",
    "sg:tags":[
        "automotive"
    ],
    "wof:name":"P & F Auto Shop",
    "wof:placetype":"venue"
},
  "geometry": {"coordinates":[-73.955465,40.707101],"type":"Point"}
}