{
  "type": "Feature",
  "properties": {
    "iso:country":"US",
    "sg:address":"136 E 73rd St",
    "sg:city":"New York",
    "sg:classifiers":[
        {
            "category":"Real Estate",
            "subcategory":"Architect",
            "type":"Services"
        }
    ],
    "sg:phone":"+1 212 535 1800",
    "sg:postcode":"10021",
    "sg:province":"NY",
    "wof:name":"Claus Rademalher F Architect PC",
    "wof:placetype":"venue"
},
  "geometry": {"coordinates":[-73.961899,40.771099],"type":"Point"}
}