{
  "type": "Feature",
  "properties": {
    "addr:full":"3076 Bailey Ave Buffalo NY 14215",
    "addr:housenumber":"3076",
    "addr:postcode":"14215",
    "addr:street":"Bailey Ave",
    "iso:country":"US",
    "sg:address":"3076 Bailey Ave",
    "sg:city":"Buffalo",
    "sg:classifiers":[
        {
            "category":"Bars & Pubs",
            "subcategory":"Sports Bar",
            "type":"Food & Drink"
        }
    ],
    "sg:phone":"+1 716 836 3166",
    "sg:postcode":"14215",
    "sg:province":"NY",
    "wof:name":"Good Life Sports Bar & Grill",
    "wof:placetype":"venue"
},
  "geometry": {"coordinates":[-78.81382600000001,42.93859],"type":"Point"}
}