{
  "type": "Feature",
  "properties": {
    "addr:full":"7455 Morgan Rd Liverpool NY 13090",
    "addr:housenumber":"7455",
    "addr:postcode":"13090",
    "addr:street":"Morgan Rd",
    "iso:country":"US",
    "sg:address":"7455 Morgan Rd",
    "sg:city":"Liverpool",
    "sg:classifiers":[
        {
            "category":"Sports & Exercise",
            "subcategory":"Gym",
            "type":"Entertainment"
        }
    ],
    "sg:phone":"+1 315 451 5050",
    "sg:postcode":"13090",
    "sg:province":"NY",
    "sg:tags":[
        "c",
        "facility",
        "club",
        "gymnasium",
        "membership",
        "studio",
        "fitness",
        "health",
        "physical"
    ],
    "sg:website":"www.goldsgym.com/liverpoolny",
    "wof:name":"Gold's Gym",
    "wof:placetype":"venue"
},
  "geometry": {"coordinates":[-76.205613,43.126639],"type":"Point"}
}