{
  "type": "Feature",
  "properties": {
    "addr:full":"15 Hill St Glen Cove NY 11542",
    "addr:housenumber":"15",
    "addr:postcode":"11542",
    "addr:street":"Hill St",
    "iso:country":"US",
    "sg:address":"15 Hill St",
    "sg:city":"Glen Cove",
    "sg:classifiers":[
        {
            "category":"Organizations",
            "subcategory":"Community Association",
            "type":"Services"
        }
    ],
    "sg:phone":"+1   ",
    "sg:postcode":"11542",
    "sg:province":"NY",
    "sg:tags":[
        "veteran"
    ],
    "sg:website":"www.vfw.org",
    "wof:name":"Veterans Of Foreign Wars",
    "wof:placetype":"venue"
},
  "geometry": {"coordinates":[-73.63577100000001,40.86633],"type":"Point"}
}