{
  "type": "Feature",
  "properties": {
    "addr:full":"59 Grove St., New York, NY 10014",
    "wof:name":"Marie's Crisis Cafe",
    "wof:placetype":"venue"
},
  "geometry": {"coordinates":[-74.003389,40.733208],"type":"Point"}
}