{
  "type": "Feature",
  "properties": {
    "iso:country":"US",
    "sg:address":"758 South Ave Ste 3",
    "sg:city":"Rochester",
    "sg:classifiers":[
        {
            "category":"Manufacturing",
            "subcategory":"Buildings",
            "type":"Manufacturing & Wholesale Goods"
        },
        {
            "category":"Real Estate",
            "subcategory":"Real Estate Services",
            "type":"Services"
        },
        {
            "category":"Real Estate",
            "subcategory":"Developer",
            "type":"Services"
        }
    ],
    "sg:phone":"+1 585 473 8410",
    "sg:postcode":"14620",
    "sg:province":"NY",
    "sg:tags":[
        "home",
        "builder",
        "management"
    ],
    "sg:website":"http://www.midlandmanagement.com",
    "wof:name":"Midland Management Ltd",
    "wof:placetype":"venue"
},
  "geometry": {"coordinates":[-77.60507200000001,43.140498],"type":"Point"}
}