{
  "type": "Feature",
  "properties": {
    "addr:full":"52 N Main St Albion NY 14411",
    "addr:housenumber":"52",
    "addr:postcode":"14411",
    "addr:street":"N Main St",
    "iso:country":"US",
    "sg:address":"52 N Main St",
    "sg:city":"Albion",
    "sg:classifiers":[
        {
            "category":"Home & Garden",
            "subcategory":"Carpets & Floor Coverings",
            "type":"Retail Goods"
        }
    ],
    "sg:phone":"+1   ",
    "sg:postcode":"14411",
    "sg:province":"NY",
    "wof:name":"Carpet House",
    "wof:placetype":"venue"
},
  "geometry": {"coordinates":[-78.19380099999999,43.247028],"type":"Point"}
}