{
  "type": "Feature",
  "properties": {
    "addr:full":"150 W 15 St New York NY 10011",
    "addr:housenumber":"150",
    "addr:postcode":"10011",
    "addr:street":"W 15 St",
    "iso:country":"US",
    "sg:address":"150 W 15 St",
    "sg:city":"New York",
    "sg:classifiers":[
        {
            "category":"Retail",
            "subcategory":"Auto Repair",
            "type":"Services"
        }
    ],
    "sg:phone":"+1 646 237 9478",
    "sg:postcode":"10011",
    "sg:province":"NY",
    "sg:tags":[
        "wrecker"
    ],
    "wof:name":"Affordable Towing 24 Hours",
    "wof:placetype":"venue"
},
  "geometry": {"coordinates":[-73.99734100000001,40.738162],"type":"Point"}
}