{
  "type": "Feature",
  "properties": {
    "addr:full":"930 Ditmas Ave Brooklyn NY 11218",
    "addr:housenumber":"930",
    "addr:postcode":"11218",
    "addr:street":"Ditmas Ave",
    "iso:country":"US",
    "sg:address":"930 Ditmas Ave",
    "sg:city":"Brooklyn",
    "sg:classifiers":[
        {
            "category":"Communications",
            "type":"Services"
        }
    ],
    "sg:phone":"+1   ",
    "sg:postcode":"11218",
    "sg:province":"NY",
    "sg:tags":[
        "communication"
    ],
    "wof:name":"Smile Vision Communications",
    "wof:placetype":"venue"
},
  "geometry": {"coordinates":[-73.968334,40.636532],"type":"Point"}
}