{
  "type": "Feature",
  "properties": {
    "iso:country":"US",
    "sg:address":"277 S 4th St",
    "sg:city":"Lindenhurst",
    "sg:classifiers":[
        {
            "category":"Organizations",
            "subcategory":"Religious Organization",
            "type":"Services"
        }
    ],
    "sg:phone":"+1   ",
    "sg:postcode":"11757",
    "sg:province":"NY",
    "wof:name":"Church of Ancient Ways",
    "wof:placetype":"venue"
},
  "geometry": {"coordinates":[-73.375822,40.683227],"type":"Point"}
}