{
  "type": "Feature",
  "properties": {
    "addr:full":"6 Wisteria Pl Syosset NY 11791",
    "addr:housenumber":"6",
    "addr:postcode":"11791",
    "addr:street":"Wisteria Pl",
    "iso:country":"US",
    "sg:address":"6 Wisteria Pl",
    "sg:city":"Syosset",
    "sg:classifiers":[
        {
            "category":"Food & Beverages",
            "subcategory":"Groceries & Convenience Stores",
            "type":"Retail Goods"
        }
    ],
    "sg:phone":"+1   ",
    "sg:postcode":"11791",
    "sg:province":"NY",
    "wof:name":"Mbs Food Creations Corp",
    "wof:placetype":"venue"
},
  "geometry": {"coordinates":[-73.497878,40.830507],"type":"Point"}
}