{
  "type": "Feature",
  "properties": {
    "iso:country":"US",
    "sg:address":"471 Barks Rd",
    "sg:city":"Caledonia",
    "sg:classifiers":[
        {
            "category":"Building & Trades",
            "subcategory":"Construction",
            "type":"Services"
        }
    ],
    "sg:phone":"+1 585 538 6890",
    "sg:postcode":"14423",
    "sg:province":"NY",
    "sg:tags":[
        "company"
    ],
    "wof:name":"A Polisseni Construction Corp",
    "wof:placetype":"venue"
},
  "geometry": {"coordinates":[-77.83069,42.964028],"type":"Point"}
}