{
  "type": "Feature",
  "properties": {
    "iso:country":"US",
    "sg:address":"3 Hiview Rd",
    "sg:city":"Wappingers Falls",
    "sg:classifiers":[
        {
            "category":"Social Services",
            "subcategory":"Child Care",
            "type":"Services"
        }
    ],
    "sg:phone":"+1 845 297 0920",
    "sg:postcode":"12590",
    "sg:province":"NY",
    "wof:name":"Rockingham Daycare",
    "wof:placetype":"venue"
},
  "geometry": {"coordinates":[-73.85653499999999,41.606662],"type":"Point"}
}