{
  "type": "Feature",
  "properties": {
    "iso:country":"US",
    "sg:address":"17 Marion St",
    "sg:city":"Greenvale",
    "sg:classifiers":[
        {
            "category":"Real Estate",
            "subcategory":"Real Estate Agent",
            "type":"Services"
        }
    ],
    "sg:phone":"+1 516 626 3612",
    "sg:postcode":"11548",
    "sg:province":"NY",
    "wof:name":"Ron Paradiso Realty LTD",
    "wof:placetype":"venue"
},
  "geometry": {"coordinates":[-73.62433799999999,40.814597],"type":"Point"}
}