{
  "type": "Feature",
  "properties": {
    "iso:country":"US",
    "sg:address":"19 Searingtown Rd",
    "sg:city":"Albertson",
    "sg:classifiers":[
        {
            "category":"Shopping",
            "subcategory":"Crafts & Fabrics",
            "type":"Retail Goods"
        }
    ],
    "sg:phone":"+1 516 248 0575",
    "sg:postcode":"11507",
    "sg:province":"NY",
    "sg:tags":[
        "store"
    ],
    "wof:name":"Only Silk Inc",
    "wof:placetype":"venue"
},
  "geometry": {"coordinates":[-73.65818,40.771075],"type":"Point"}
}