{
  "type": "Feature",
  "properties": {
    "addr:full":"276 Delaware Ave Staten Island NY 10305",
    "addr:housenumber":"276",
    "addr:postcode":"10305",
    "addr:street":"Delaware Ave",
    "iso:country":"US",
    "sg:address":"276 Delaware Ave",
    "sg:city":"Staten Island",
    "sg:classifiers":[
        {
            "category":"Restaurant",
            "type":"Food & Drink"
        }
    ],
    "sg:phone":"+1 718 815 8757",
    "sg:postcode":"10305",
    "sg:province":"NY",
    "sg:tags":[
        "delicatessen"
    ],
    "wof:name":"1153 Forest Avenue Corp",
    "wof:placetype":"venue"
},
  "geometry": {"coordinates":[-74.090069,40.589076],"type":"Point"}
}