{
  "type": "Feature",
  "properties": {
    "addr:full":"1111 Marcus Ave New Hyde Park NY 11042",
    "addr:housenumber":"1111",
    "addr:postcode":"11042",
    "addr:street":"Marcus Ave",
    "iso:country":"US",
    "sg:address":"1111 Marcus Ave",
    "sg:city":"New Hyde Park",
    "sg:classifiers":[
        {
            "category":"Health Services",
            "subcategory":"Clinic",
            "type":"Services"
        }
    ],
    "sg:phone":"+1 516 488 2405",
    "sg:postcode":"11042",
    "sg:province":"NY",
    "wof:name":"North Shore LIJ Health",
    "wof:placetype":"venue"
},
  "geometry": {"coordinates":[-73.69001900000001,40.756512],"type":"Point"}
}