{
  "type": "Feature",
  "properties": {
    "iso:country":"US",
    "sg:address":"1200 Clinton St",
    "sg:city":"Buffalo",
    "sg:classifiers":[
        {
            "category":"Manufacturing",
            "subcategory":"Tools & Machinery",
            "type":"Manufacturing & Wholesale Goods"
        }
    ],
    "sg:phone":"+1 716 823 4646",
    "sg:postcode":"14206",
    "sg:province":"NY",
    "sg:tags":[
        "machine",
        "shop"
    ],
    "sg:website":"www.ejmckenica.com",
    "wof:name":"Edwin J Mc Kenica & Sons Inc",
    "wof:placetype":"venue"
},
  "geometry": {"coordinates":[-78.830904,42.876406],"type":"Point"}
}