{
  "type": "Feature",
  "properties": {
    "addr:full":"410 Park Ave Fl 18 New York NY 10022",
    "addr:housenumber":"410;18",
    "addr:postcode":"10022",
    "addr:street":"Park Ave Fl",
    "iso:country":"US",
    "sg:address":"410 Park Ave Fl 18",
    "sg:city":"New York",
    "sg:classifiers":[
        {
            "category":"Banks & Credit Unions",
            "subcategory":"Bank",
            "type":"Services"
        }
    ],
    "sg:phone":"+1 212 588 7000",
    "sg:postcode":"10022",
    "sg:province":"NY",
    "wof:name":"Citic Ka Wah Bank",
    "wof:placetype":"venue"
},
  "geometry": {"coordinates":[-73.972105,40.760112],"type":"Point"}
}