{
  "type": "Feature",
  "properties": {
    "iso:country":"US",
    "sg:address":"3292 Main St",
    "sg:city":"Buffalo",
    "sg:classifiers":[
        {
            "category":"Food & Beverages",
            "subcategory":"Meat & Fish",
            "type":"Retail Goods"
        }
    ],
    "sg:phone":"+1 716 636 7922",
    "sg:postcode":"14214",
    "sg:province":"NY",
    "wof:name":"Ziad Market II",
    "wof:placetype":"venue"
},
  "geometry": {"coordinates":[-78.823228,42.953579],"type":"Point"}
}