{
  "type": "Feature",
  "properties": {
    "addr:full":"428 Atlantic Ave Brooklyn NY 11217",
    "addr:housenumber":"428",
    "addr:postcode":"11217",
    "addr:street":"Atlantic Ave",
    "iso:country":"US",
    "sg:address":"428 Atlantic Ave",
    "sg:city":"Brooklyn",
    "sg:classifiers":[
        {
            "category":"Wholesale",
            "subcategory":"Drugs",
            "type":"Manufacturing & Wholesale Goods"
        }
    ],
    "sg:phone":"+1 718 875 3791",
    "sg:postcode":"11217",
    "sg:province":"NY",
    "sg:tags":[
        "cosmetic",
        "beauty",
        "supply"
    ],
    "sg:website":"www.anwaarco.com/",
    "wof:name":"Anwaar Co.",
    "wof:placetype":"venue"
},
  "geometry": {"coordinates":[-73.984032,40.686619],"type":"Point"}
}