{
  "type": "Feature",
  "properties": {
    "iso:country":"US",
    "sg:address":"358 Veterans Memorial Hwy",
    "sg:city":"Commack",
    "sg:classifiers":[
        {
            "category":"Insurance",
            "subcategory":"Insurance Agent",
            "type":"Services"
        }
    ],
    "sg:phone":"+1 631 543 5817",
    "sg:postcode":"11725",
    "sg:province":"NY",
    "wof:name":"Thomas Mansuetto",
    "wof:placetype":"venue"
},
  "geometry": {"coordinates":[-73.259731,40.832494],"type":"Point"}
}