{
  "type": "Feature",
  "properties": {
    "addr:full":"2717 Broadway New York NY 10025",
    "addr:housenumber":"2717",
    "addr:postcode":"10025",
    "addr:street":"Broadway",
    "iso:country":"US",
    "sg:address":"2717 Broadway",
    "sg:city":"New York",
    "sg:classifiers":[
        {
            "category":"Wholesale",
            "subcategory":"Fruits & Vegetables",
            "type":"Manufacturing & Wholesale Goods"
        }
    ],
    "sg:phone":"+1 212 663 6036",
    "sg:postcode":"10025",
    "sg:province":"NY",
    "sg:tags":[
        "veggie"
    ],
    "wof:name":"104 Broadway Farm Inc",
    "wof:placetype":"venue"
},
  "geometry": {"coordinates":[-73.968614,40.799628],"type":"Point"}
}