{
  "type": "Feature",
  "properties": {
    "iso:country":"US",
    "sg:address":"1261 54th St",
    "sg:city":"Brooklyn",
    "sg:classifiers":[
        {
            "category":"Home & Garden",
            "subcategory":"Home Furnishings",
            "type":"Retail Goods"
        }
    ],
    "sg:phone":"+1 718 435 1045",
    "sg:postcode":"11219",
    "sg:province":"NY",
    "sg:tags":[
        "linen"
    ],
    "wof:name":"D'rose Linens Inc",
    "wof:placetype":"venue"
},
  "geometry": {"coordinates":[-73.995746,40.632657],"type":"Point"}
}