{
  "type": "Feature",
  "properties": {
    "addr:full":"2341 Ridge Rd W Rochester NY 14626",
    "addr:housenumber":"2341",
    "addr:postcode":"14626",
    "addr:street":"Ridge Rd W",
    "iso:country":"US",
    "sg:address":"2341 Ridge Rd W",
    "sg:city":"Rochester",
    "sg:classifiers":[
        {
            "category":"Restaurant",
            "type":"Food & Drink"
        }
    ],
    "sg:menulink":"http://www.allmenus.com/ny/greece/188990-mcdonalds/menu/",
    "sg:postcode":"14626",
    "sg:province":"NY",
    "sg:tags":[
        "burger",
        "american"
    ],
    "wof:name":"McDonald's",
    "wof:placetype":"venue"
},
  "geometry": {"coordinates":[-77.690354,43.208938],"type":"Point"}
}