{
  "type": "Feature",
  "properties": {
    "addr:full":"11 Jean St Rye NY 10580",
    "addr:housenumber":"11",
    "addr:postcode":"10580",
    "addr:street":"Jean St",
    "iso:country":"US",
    "sg:address":"11 Jean St",
    "sg:city":"Rye",
    "sg:classifiers":[
        {
            "category":"Building & Trades",
            "subcategory":"Plumbing",
            "type":"Services"
        }
    ],
    "sg:phone":"+1 914 921 3153",
    "sg:postcode":"10580",
    "sg:province":"NY",
    "sg:tags":[
        "contractor",
        "system",
        "air conditioning"
    ],
    "wof:name":"Climate Systems",
    "wof:placetype":"venue"
},
  "geometry": {"coordinates":[-73.685091,40.959183],"type":"Point"}
}