{
  "type": "Feature",
  "properties": {
    "iso:country":"US",
    "sg:address":"39 Roma Orchard Rd",
    "sg:city":"Peekskill",
    "sg:classifiers":[
        {
            "category":"Professional",
            "subcategory":"Management & Consulting",
            "type":"Services"
        }
    ],
    "sg:phone":"+1 914 734 8440",
    "sg:postcode":"10566",
    "sg:province":"NY",
    "sg:tags":[
        "consultant",
        "educational"
    ],
    "wof:name":"College Connection",
    "wof:placetype":"venue"
},
  "geometry": {"coordinates":[-73.90272299999999,41.285071],"type":"Point"}
}