{
  "type": "Feature",
  "properties": {
    "addr:full":"1164 Broadway New York NY 10001",
    "addr:housenumber":"1164",
    "addr:postcode":"10001",
    "addr:street":"Broadway",
    "iso:country":"US",
    "sg:address":"1164 Broadway",
    "sg:city":"New York",
    "sg:classifiers":[
        {
            "category":"Shopping",
            "type":"Retail Goods"
        }
    ],
    "sg:phone":"+1 212 447 4400",
    "sg:postcode":"10001",
    "sg:province":"NY",
    "sg:tags":[
        "mobile",
        "phone",
        "telephone",
        "cellular",
        "equipment"
    ],
    "wof:name":"Lucky Wireless",
    "wof:placetype":"venue"
},
  "geometry": {"coordinates":[-73.988806,40.74483],"type":"Point"}
}