{
  "type": "Feature",
  "properties": {
    "addr:full":"17 W John St Hicksville NY 11801",
    "addr:housenumber":"17",
    "addr:postcode":"11801",
    "addr:street":"W John St",
    "iso:country":"US",
    "sg:address":"17 W John St",
    "sg:city":"Hicksville",
    "sg:classifiers":[
        {
            "category":"Professional",
            "subcategory":"Accounting & Tax Preparation",
            "type":"Services"
        }
    ],
    "sg:phone":"+1 516 933 3800",
    "sg:postcode":"11801",
    "sg:province":"NY",
    "wof:name":"Weisberg Moland Company",
    "wof:placetype":"venue"
},
  "geometry": {"coordinates":[-73.526701,40.769337],"type":"Point"}
}