{
  "type": "Feature",
  "properties": {
    "iso:country":"US",
    "sg:address":"879 Montauk Hwy",
    "sg:city":"Shirley",
    "sg:classifiers":[
        {
            "category":"Autos & Motor Vehicles",
            "subcategory":"Auto Supplies",
            "type":"Retail Goods"
        }
    ],
    "sg:phone":"+1 631 399 6761",
    "sg:postcode":"11967",
    "sg:province":"NY",
    "sg:tags":[
        "tire"
    ],
    "wof:name":"J & C Tire",
    "wof:placetype":"venue"
},
  "geometry": {"coordinates":[-72.863602,40.801701],"type":"Point"}
}