{
  "type": "Feature",
  "properties": {
    "addr:full":"1207 49th St Brooklyn NY 11219",
    "addr:housenumber":"1207",
    "addr:postcode":"11219",
    "addr:street":"49Th St",
    "iso:country":"US",
    "sg:address":"1207 49th St",
    "sg:city":"Brooklyn",
    "sg:classifiers":[
        {
            "category":"Bars & Pubs",
            "subcategory":"Nightclub",
            "type":"Food & Drink"
        }
    ],
    "sg:phone":"+1 718 436 0500",
    "sg:postcode":"11219",
    "sg:province":"NY",
    "sg:tags":[
        "nightlife"
    ],
    "wof:name":"Toast Bar",
    "wof:placetype":"venue"
},
  "geometry": {"coordinates":[-73.994091,40.636385],"type":"Point"}
}