{
  "type": "Feature",
  "properties": {
    "addr:full":"57 Borden Ave Norwich NY 13815",
    "addr:housenumber":"57",
    "addr:postcode":"13815",
    "addr:street":"Borden Ave",
    "iso:country":"US",
    "sg:address":"57 Borden Ave",
    "sg:city":"Norwich",
    "sg:classifiers":[
        {
            "category":"Manufacturing",
            "subcategory":"Printing",
            "type":"Manufacturing & Wholesale Goods"
        }
    ],
    "sg:phone":"+1 607 337 3034",
    "sg:postcode":"13815",
    "sg:province":"NY",
    "sg:tags":[
        "printer"
    ],
    "wof:name":"Sun Printing",
    "wof:placetype":"venue"
},
  "geometry": {"coordinates":[-75.52282099999999,42.540809],"type":"Point"}
}