{
  "type": "Feature",
  "properties": {
    "addr:full":"7070 Ridge Rd Lockport NY 14094",
    "addr:housenumber":"7070",
    "addr:postcode":"14094",
    "addr:street":"Ridge Rd",
    "iso:country":"US",
    "sg:address":"7070 Ridge Rd",
    "sg:city":"Lockport",
    "sg:classifiers":[
        {
            "category":"Organizations",
            "subcategory":"Religious Organization",
            "type":"Services"
        }
    ],
    "sg:phone":"+1 716 434 5774",
    "sg:postcode":"14094",
    "sg:province":"NY",
    "sg:tags":[
        "church"
    ],
    "sg:website":"www.ridgewoodbible.org",
    "wof:name":"Ridgewood Bible Church",
    "wof:placetype":"venue"
},
  "geometry": {"coordinates":[-78.648129,43.247367],"type":"Point"}
}