{
  "type": "Feature",
  "properties": {
    "iso:country":"US",
    "sg:address":"481 Middle Neck Rd",
    "sg:city":"Great Neck",
    "sg:classifiers":[
        {
            "category":"Personal",
            "subcategory":"Barber",
            "type":"Services"
        }
    ],
    "sg:phone":"+1 516 829 8184",
    "sg:postcode":"11023",
    "sg:province":"NY",
    "wof:name":"Benny's Barber Shop",
    "wof:placetype":"venue"
},
  "geometry": {"coordinates":[-73.734066,40.799549],"type":"Point"}
}