{
  "type": "Feature",
  "properties": {
    "iso:country":"US",
    "sg:address":"3152 Briarcliff Ave",
    "sg:city":"Vestal",
    "sg:classifiers":[
        {
            "category":"Building & Trades",
            "subcategory":"Construction",
            "type":"Services"
        }
    ],
    "sg:phone":"+1 607 729 5051",
    "sg:postcode":"13850",
    "sg:province":"NY",
    "sg:tags":[
        "house"
    ],
    "wof:name":"Chaneys Remodeling",
    "wof:placetype":"venue"
},
  "geometry": {"coordinates":[-75.99645,42.090633],"type":"Point"}
}