{
  "type": "Feature",
  "properties": {
    "addr:full":"2338 Lyell Ave Rochester NY 14606",
    "addr:housenumber":"2338",
    "addr:postcode":"14606",
    "addr:street":"Lyell Ave",
    "iso:country":"US",
    "sg:address":"2338 Lyell Ave",
    "sg:city":"Rochester",
    "sg:classifiers":[
        {
            "category":"Personal",
            "subcategory":"Barber",
            "type":"Services"
        }
    ],
    "sg:phone":"+1 585 429 6406",
    "sg:postcode":"14606",
    "sg:province":"NY",
    "wof:name":"Ralph's Barber Shop",
    "wof:placetype":"venue"
},
  "geometry": {"coordinates":[-77.690631,43.164786],"type":"Point"}
}