{
  "type": "Feature",
  "properties": {
    "iso:country":"US",
    "sg:address":"25 Sycamore Cir",
    "sg:city":"Stony Brook",
    "sg:classifiers":[
        {
            "category":"Shopping",
            "subcategory":"Pharmacy",
            "type":"Retail Goods"
        }
    ],
    "sg:phone":"+1   ",
    "sg:postcode":"11790",
    "sg:province":"NY",
    "wof:name":"Seaport Chemists Inc",
    "wof:placetype":"venue"
},
  "geometry": {"coordinates":[-73.107658,40.896422],"type":"Point"}
}