{
  "type": "Feature",
  "properties": {
    "addr:full":"600 Rte 25A East Setauket NY 11733",
    "addr:housenumber":"600",
    "addr:postcode":"11733",
    "addr:street":"Rte 25A East",
    "iso:country":"US",
    "sg:address":"600 Rte 25A",
    "sg:city":"East Setauket",
    "sg:classifiers":[
        {
            "category":"Airline",
            "type":"Transportation"
        }
    ],
    "sg:phone":"+1   ",
    "sg:postcode":"11733",
    "sg:province":"NY",
    "sg:tags":[
        "charter"
    ],
    "wof:name":"Silver Stream Aviation LLC",
    "wof:placetype":"venue"
},
  "geometry": {"coordinates":[-73.084825,40.945404],"type":"Point"}
}