{
  "type": "Feature",
  "properties": {
    "iso:country":"US",
    "sg:address":"26 Edison St",
    "sg:city":"Staten Island",
    "sg:classifiers":[
        {
            "category":"Building & Trades",
            "subcategory":"Electrical",
            "type":"Services"
        }
    ],
    "sg:phone":"+1 718 667 5405",
    "sg:postcode":"10306",
    "sg:province":"NY",
    "sg:tags":[
        "electric",
        "contractor"
    ],
    "wof:name":"Go Electric",
    "wof:placetype":"venue"
},
  "geometry": {"coordinates":[-74.10527999999999,40.580381],"type":"Point"}
}