{
  "type": "Feature",
  "properties": {
    "addr:full":"3653 Main St Flushing NY 11354",
    "addr:housenumber":"3653",
    "addr:postcode":"11354",
    "addr:street":"Main St",
    "iso:country":"US",
    "sg:address":"3653 Main St",
    "sg:city":"Flushing",
    "sg:classifiers":[
        {
            "category":"Home & Garden",
            "subcategory":"Furniture",
            "type":"Retail Goods"
        }
    ],
    "sg:phone":"+1 718 321 3686",
    "sg:postcode":"11354",
    "sg:province":"NY",
    "sg:tags":[
        "store"
    ],
    "wof:name":"O Concept Furniture Incorporated",
    "wof:placetype":"venue"
},
  "geometry": {"coordinates":[-73.831305,40.762209],"type":"Point"}
}