{
  "type": "Feature",
  "properties": {
    "addr:full":"1160 3rd Ave New York NY 10065",
    "addr:housenumber":"1160",
    "addr:postcode":"10065",
    "addr:street":"3Rd Ave",
    "iso:country":"US",
    "sg:address":"1160 3rd Ave",
    "sg:city":"New York",
    "sg:classifiers":[
        {
            "category":"Retail",
            "subcategory":"Portrait Studio",
            "type":"Services"
        },
        {
            "category":"Shopping",
            "subcategory":"Pharmacy",
            "type":"Retail Goods"
        }
    ],
    "sg:phone":"+1 212 861 0291",
    "sg:postcode":"10065",
    "sg:province":"NY",
    "sg:tags":[
        "photography",
        "drugstore",
        "store"
    ],
    "sg:website":"www.walgreens.com",
    "wof:name":"Walgreens",
    "wof:placetype":"venue"
},
  "geometry": {"coordinates":[-73.962855,40.767009],"type":"Point"}
}