{
  "type": "Feature",
  "properties": {
    "addr:full":"495 Co Rd 50 New Hampton NY 10958",
    "addr:housenumber":"495;50",
    "addr:postcode":"10958",
    "addr:street":"Co Rd",
    "iso:country":"US",
    "sg:address":"495 Co Rd 50",
    "sg:city":"New Hampton",
    "sg:classifiers":[
        {
            "category":"Building & Trades",
            "subcategory":"Construction",
            "type":"Services"
        }
    ],
    "sg:phone":"+1 845 294 5005",
    "sg:postcode":"10958",
    "sg:province":"NY",
    "sg:tags":[
        "house",
        "nonresident",
        "general",
        "family",
        "contractor"
    ],
    "wof:name":"J Cassel Construction Inc",
    "wof:placetype":"venue"
},
  "geometry": {"coordinates":[-74.39168100000001,41.414536],"type":"Point"}
}