{
  "type": "Feature",
  "properties": {
    "addr:full":"4865 Keller Rd Hamburg NY 14075",
    "addr:housenumber":"4865",
    "addr:postcode":"14075",
    "addr:street":"Keller Rd",
    "iso:country":"US",
    "sg:address":"4865 Keller Rd",
    "sg:city":"Hamburg",
    "sg:classifiers":[
        {
            "category":"Farming",
            "subcategory":"Dairy Farm",
            "type":"Manufacturing & Wholesale Goods"
        }
    ],
    "sg:phone":"+1 716 941 3906",
    "sg:postcode":"14075",
    "sg:province":"NY",
    "wof:name":"Stephen Blasz",
    "wof:placetype":"venue"
},
  "geometry": {"coordinates":[-78.81213099999999,42.663827],"type":"Point"}
}