{
  "type": "Feature",
  "properties": {
    "addr:full":"5 Hommocks Rd Larchmont NY 10538",
    "addr:housenumber":"5",
    "addr:postcode":"10538",
    "addr:street":"Hommocks Rd",
    "iso:country":"US",
    "sg:address":"5 Hommocks Rd",
    "sg:city":"Larchmont",
    "sg:classifiers":[
        {
            "category":"Wholesale",
            "subcategory":"Construction Materials",
            "type":"Manufacturing & Wholesale Goods"
        }
    ],
    "sg:phone":"+1 914 833 5042",
    "sg:postcode":"10538",
    "sg:province":"NY",
    "sg:tags":[
        "medical",
        "export",
        "tile",
        "import",
        "marble",
        "furniture"
    ],
    "wof:name":"Optima Trading Co",
    "wof:placetype":"venue"
},
  "geometry": {"coordinates":[-73.746583,40.934837],"type":"Point"}
}