{
  "type": "Feature",
  "properties": {
    "iso:country":"US",
    "sg:address":"24507 Francis Lewis Boulevard",
    "sg:city":"Rosedale",
    "sg:classifiers":[
        {
            "category":"Professional",
            "subcategory":"Lawyer & Legal Services",
            "type":"Services"
        }
    ],
    "sg:phone":"+1 718 276 2729",
    "sg:postcode":"11422",
    "sg:province":"NY",
    "wof:name":"The Law Offices of Audrey A Thomas PC",
    "wof:placetype":"venue"
},
  "geometry": {"coordinates":[-73.734814,40.664857],"type":"Point"}
}