{
  "type": "Feature",
  "properties": {
    "addr:full":"226 Bennett Ave Yonkers NY 10701",
    "addr:housenumber":"226",
    "addr:postcode":"10701",
    "addr:street":"Bennett Ave",
    "iso:country":"US",
    "sg:address":"226 Bennett Ave",
    "sg:city":"Yonkers",
    "sg:classifiers":[
        {
            "category":"Retail",
            "subcategory":"Auto Repair",
            "type":"Services"
        }
    ],
    "sg:phone":"+1 914 964 8825",
    "sg:postcode":"10701",
    "sg:province":"NY",
    "sg:tags":[
        "wrecker"
    ],
    "wof:name":"Karl's Snow Plowing Svc",
    "wof:placetype":"venue"
},
  "geometry": {"coordinates":[-73.862641,40.939502],"type":"Point"}
}