{
  "type": "Feature",
  "properties": {
    "addr:full":"254 Henry St Inwood NY 11096",
    "addr:housenumber":"254",
    "addr:postcode":"11096",
    "addr:street":"Henry St",
    "iso:country":"US",
    "sg:address":"254 Henry St",
    "sg:city":"Inwood",
    "sg:classifiers":[
        {
            "category":"Professional",
            "subcategory":"Advertising",
            "type":"Services"
        }
    ],
    "sg:phone":"+1 516 371 9898",
    "sg:postcode":"11096",
    "sg:province":"NY",
    "sg:tags":[
        "distribution"
    ],
    "wof:name":"Buzz Dstrbtn Inc",
    "wof:placetype":"venue"
},
  "geometry": {"coordinates":[-73.741856,40.621147],"type":"Point"}
}