{
  "type": "Feature",
  "properties": {
    "addr:full":"86 W 12 St New York NY 10011",
    "addr:housenumber":"86",
    "addr:postcode":"10011",
    "addr:street":"W 12 St",
    "iso:country":"US",
    "sg:address":"86 W 12 St",
    "sg:city":"New York",
    "sg:classifiers":[
        {
            "category":"Communications",
            "subcategory":"Film & Video Production",
            "type":"Services"
        }
    ],
    "sg:phone":"+1   ",
    "sg:postcode":"10011",
    "sg:province":"NY",
    "sg:tags":[
        "motion"
    ],
    "wof:name":"Right Size Media",
    "wof:placetype":"venue"
},
  "geometry": {"coordinates":[-73.995707,40.734776],"type":"Point"}
}