{
  "type": "Feature",
  "properties": {
    "iso:country":"US",
    "sg:address":"80 Rosebud Ave",
    "sg:city":"Merrick",
    "sg:classifiers":[
        {
            "category":"Professional",
            "subcategory":"Management & Consulting",
            "type":"Services"
        }
    ],
    "sg:phone":"+1 516 623 7778",
    "sg:postcode":"11566",
    "sg:province":"NY",
    "sg:tags":[
        "consultant"
    ],
    "wof:name":"Calvache Associates Corp",
    "wof:placetype":"venue"
},
  "geometry": {"coordinates":[-73.55365399999999,40.650982],"type":"Point"}
}