{
  "type": "Feature",
  "properties": {
    "iso:country":"US",
    "sg:address":"461 5th Ave",
    "sg:city":"New York",
    "sg:classifiers":[
        {
            "category":"Shopping",
            "subcategory":"Clothing, Apparel, & Fashions",
            "type":"Retail Goods"
        }
    ],
    "sg:postcode":"10079",
    "sg:province":"NY",
    "sg:tags":[
        "clothing",
        "women's"
    ],
    "sg:website":"www.bcbg.com",
    "wof:name":"BCBG Max Azria",
    "wof:placetype":"venue"
},
  "geometry": {"coordinates":[-73.98174899999999,40.752204],"type":"Point"}
}