{
  "type": "Feature",
  "properties": {
    "addr:full":"1661 McDonald Ave Brooklyn NY 11230",
    "addr:housenumber":"1661",
    "addr:postcode":"11230",
    "addr:street":"Mcdonald Ave",
    "iso:country":"US",
    "sg:address":"1661 McDonald Ave",
    "sg:city":"Brooklyn",
    "sg:classifiers":[
        {
            "category":"Professional",
            "subcategory":"Computer Services",
            "type":"Services"
        }
    ],
    "sg:phone":"+1 718 627 0903",
    "sg:postcode":"11230",
    "sg:province":"NY",
    "sg:tags":[
        "processing",
        "datum"
    ],
    "wof:name":"Visual Dimensions Inc",
    "wof:placetype":"venue"
},
  "geometry": {"coordinates":[-73.973484,40.611371],"type":"Point"}
}