{
  "type": "Feature",
  "properties": {
    "addr:full":"77 E Main St Walden NY 12586",
    "addr:housenumber":"77",
    "addr:postcode":"12586",
    "addr:street":"E Main St",
    "iso:country":"US",
    "sg:address":"77 E Main St",
    "sg:city":"Walden",
    "sg:classifiers":[
        {
            "category":"Restaurant",
            "type":"Food & Drink"
        }
    ],
    "sg:phone":"+1   ",
    "sg:postcode":"12586",
    "sg:province":"NY",
    "sg:tags":[
        "eating"
    ],
    "wof:name":"Stewarts Shop 381",
    "wof:placetype":"venue"
},
  "geometry": {"coordinates":[-74.18222,41.561471],"type":"Point"}
}