{
  "type": "Feature",
  "properties": {
    "addr:full":"323 N Iowa Ave Massapequa NY 11758",
    "addr:housenumber":"323",
    "addr:postcode":"11758",
    "addr:street":"N Iowa Ave",
    "iso:country":"US",
    "sg:address":"323 N Iowa Ave",
    "sg:city":"Massapequa",
    "sg:classifiers":[
        {
            "category":"Professional",
            "type":"Services"
        }
    ],
    "sg:phone":"+1   ",
    "sg:postcode":"11758",
    "sg:province":"NY",
    "wof:name":"Ftw Inc",
    "wof:placetype":"venue"
},
  "geometry": {"coordinates":[-73.47039100000001,40.715184],"type":"Point"}
}