{
  "type": "Feature",
  "properties": {
    "addr:full":"30 Remsen Street Brooklyn NY 11201",
    "addr:housenumber":"30",
    "addr:postcode":"11201",
    "addr:street":"Remsen Street",
    "iso:country":"US",
    "sg:address":"30 Remsen Street",
    "sg:city":"Brooklyn",
    "sg:classifiers":[
        {
            "category":"Real Estate",
            "subcategory":"Real Estate Operator",
            "type":"Services"
        }
    ],
    "sg:phone":"+1 718 802 1347",
    "sg:postcode":"11201",
    "sg:province":"NY",
    "sg:tags":[
        "apartment"
    ],
    "wof:name":"30 Remsen St Apt Corporation",
    "wof:placetype":"venue"
},
  "geometry": {"coordinates":[-73.991437,40.694006],"type":"Point"}
}