{
  "type": "Feature",
  "properties": {
    "iso:country":"US",
    "sg:address":"34-06 36th Avenue",
    "sg:city":"New York",
    "sg:classifiers":[
        {
            "category":"Restaurant",
            "type":"Food & Drink"
        }
    ],
    "sg:phone":"+1 718 361 0565",
    "sg:postcode":"11106",
    "sg:province":"NY",
    "sg:tags":[
        "american",
        "latin"
    ],
    "wof:name":"La Casa del Artista",
    "wof:placetype":"venue"
},
  "geometry": {"coordinates":[-73.927297,40.755437],"type":"Point"}
}