{
  "type": "Feature",
  "properties": {
    "iso:country":"US",
    "sg:address":"586 Morris Ave",
    "sg:city":"Bronx",
    "sg:classifiers":[
        {
            "category":"Professional",
            "subcategory":"Computer Services",
            "type":"Services"
        }
    ],
    "sg:phone":"+1 646 404 5035",
    "sg:postcode":"10451",
    "sg:province":"NY",
    "sg:tags":[
        "repair"
    ],
    "wof:name":"Global Technology Source Inc",
    "wof:placetype":"venue"
},
  "geometry": {"coordinates":[-73.922156,40.818282],"type":"Point"}
}