{
  "type": "Feature",
  "properties": {
    "iso:country":"US",
    "sg:address":"2029 Grand Concourse",
    "sg:city":"Bronx",
    "sg:classifiers":[
        {
            "category":"Shopping",
            "subcategory":"Florist",
            "type":"Retail Goods"
        }
    ],
    "sg:phone":"+1   ",
    "sg:postcode":"10453",
    "sg:province":"NY",
    "wof:name":"Concourse Florist",
    "wof:placetype":"venue"
},
  "geometry": {"coordinates":[-73.90406299999999,40.851967],"type":"Point"}
}