{
  "type": "Feature",
  "properties": {
    "addr:full":"475 S Broadway Yonkers NY 10705",
    "addr:housenumber":"475",
    "addr:postcode":"10705",
    "addr:street":"S Broadway",
    "iso:country":"US",
    "sg:address":"475 S Broadway",
    "sg:city":"Yonkers",
    "sg:classifiers":[
        {
            "category":"Food & Beverages",
            "subcategory":"Fruits & Vegetables",
            "type":"Retail Goods"
        }
    ],
    "sg:phone":"+1 914 423 1417",
    "sg:postcode":"10705",
    "sg:province":"NY",
    "sg:tags":[
        "produce"
    ],
    "wof:name":"Sun Market",
    "wof:placetype":"venue"
},
  "geometry": {"coordinates":[-73.89681299999999,40.917224],"type":"Point"}
}