{
  "type": "Feature",
  "properties": {
    "addr:full":"1 Penn Plz 33rd St & 8th Ave New York NY 10119",
    "addr:housenumber":"1",
    "addr:postcode":"10119",
    "addr:street":"Penn Plz 33Rd St & 8Th Ave",
    "iso:country":"US",
    "sg:address":"1 Penn Plz 33rd St & 8th Ave",
    "sg:city":"New York",
    "sg:classifiers":[
        {
            "category":"Bars & Pubs",
            "type":"Food & Drink"
        },
        {
            "category":"Restaurant",
            "type":"Food & Drink"
        }
    ],
    "sg:phone":"+1 212 629 7070",
    "sg:postcode":"10119",
    "sg:province":"NY",
    "sg:website":"www.localcafenyc.com",
    "wof:name":"Local West",
    "wof:placetype":"venue"
},
  "geometry": {"coordinates":[-73.99166200000001,40.749559],"type":"Point"}
}