{
  "type": "Feature",
  "properties": {
    "addr:full":"1 S Main Ave Albany NY 12208",
    "addr:housenumber":"1",
    "addr:postcode":"12208",
    "addr:street":"S Main Ave",
    "iso:country":"US",
    "sg:address":"1 S Main Ave",
    "sg:city":"Albany",
    "sg:classifiers":[
        {
            "category":"Social Services",
            "subcategory":"Adult Care",
            "type":"Services"
        }
    ],
    "sg:phone":"+1 518 438 2738",
    "sg:postcode":"12208",
    "sg:province":"NY",
    "sg:tags":[
        "home",
        "group"
    ],
    "wof:name":"South Main Residence",
    "wof:placetype":"venue"
},
  "geometry": {"coordinates":[-73.79011199999999,42.663455],"type":"Point"}
}