{
  "type": "Feature",
  "properties": {
    "addr:full":"354 Atlantic Ave Freeport NY 11520",
    "addr:housenumber":"354",
    "addr:postcode":"11520",
    "addr:street":"Atlantic Ave",
    "iso:country":"US",
    "sg:address":"354 Atlantic Ave",
    "sg:city":"Freeport",
    "sg:classifiers":[
        {
            "category":"Personal",
            "subcategory":"Beauty Salon",
            "type":"Services"
        }
    ],
    "sg:phone":"+1 516 379 8810",
    "sg:postcode":"11520",
    "sg:province":"NY",
    "wof:name":"Diva's Style Salon",
    "wof:placetype":"venue"
},
  "geometry": {"coordinates":[-73.590867,40.644973],"type":"Point"}
}