{
  "type": "Feature",
  "properties": {
    "iso:country":"US",
    "sg:address":"375 E Main St",
    "sg:city":"Bay Shore",
    "sg:classifiers":[
        {
            "category":"Health Services",
            "subcategory":"Doctor",
            "type":"Services"
        }
    ],
    "sg:phone":"+1 631 665 1330",
    "sg:postcode":"11706",
    "sg:province":"NY",
    "wof:name":"Morabito Carmine D MD",
    "wof:placetype":"venue"
},
  "geometry": {"coordinates":[-73.236198,40.726299],"type":"Point"}
}