{
  "type": "Feature",
  "properties": {
    "addr:full":"2 Fredericks Rd Scotia NY 12302",
    "addr:housenumber":"2",
    "addr:postcode":"12302",
    "addr:street":"Fredericks Rd",
    "iso:country":"US",
    "sg:address":"2 Fredericks Rd",
    "sg:city":"Scotia",
    "sg:classifiers":[
        {
            "category":"Professional",
            "type":"Services"
        }
    ],
    "sg:phone":"+1 518 384 2503",
    "sg:postcode":"12302",
    "sg:province":"NY",
    "sg:tags":[
        "establishment"
    ],
    "wof:name":"Alternative Living Group Inc",
    "wof:placetype":"venue"
},
  "geometry": {"coordinates":[-73.91583300000001,42.891729],"type":"Point"}
}