{
  "type": "Feature",
  "properties": {
    "addr:full":"61 Roslyn Rd Roslyn Heights NY 11577",
    "addr:housenumber":"61",
    "addr:postcode":"11577",
    "addr:street":"Roslyn Rd",
    "iso:country":"US",
    "sg:address":"61 Roslyn Rd",
    "sg:city":"Roslyn Heights",
    "sg:classifiers":[
        {
            "category":"Building & Trades",
            "subcategory":"Electrical",
            "type":"Services"
        }
    ],
    "sg:phone":"+1 516 625 1901",
    "sg:postcode":"11577",
    "sg:province":"NY",
    "sg:tags":[
        "electrician",
        "electric",
        "contractor"
    ],
    "wof:name":"Glen Electric & Communication",
    "wof:placetype":"venue"
},
  "geometry": {"coordinates":[-73.64070100000001,40.791901],"type":"Point"}
}