{
  "type": "Feature",
  "properties": {
    "iso:country":"US",
    "sg:address":"550 Franklin Ave",
    "sg:city":"Brooklyn",
    "sg:classifiers":[
        {
            "category":"Organizations",
            "subcategory":"Non-profit Organization",
            "type":"Services"
        }
    ],
    "sg:phone":"+1 718 622 3923",
    "sg:postcode":"11238",
    "sg:province":"NY",
    "wof:name":"NECC",
    "wof:placetype":"venue"
},
  "geometry": {"coordinates":[-73.95528899999999,40.679202],"type":"Point"}
}