{
  "type": "Feature",
  "properties": {
    "iso:country":"US",
    "sg:address":"11 Groton Ave",
    "sg:city":"Cortland",
    "sg:classifiers":[
        {
            "category":"Restaurant",
            "type":"Food & Drink"
        }
    ],
    "sg:phone":"+1 607 756 7504",
    "sg:postcode":"13045",
    "sg:province":"NY",
    "wof:name":"Barsoni's Pizza",
    "wof:placetype":"venue"
},
  "geometry": {"coordinates":[-76.180982,42.601094],"type":"Point"}
}