{
  "type": "Feature",
  "properties": {
    "iso:country":"US",
    "sg:address":"32 W Main St",
    "sg:city":"Mayfield",
    "sg:classifiers":[
        {
            "category":"Manufacturing",
            "subcategory":"Buildings",
            "type":"Manufacturing & Wholesale Goods"
        },
        {
            "category":"Home & Garden",
            "subcategory":"Building Materials",
            "type":"Retail Goods"
        },
        {
            "category":"Building & Trades",
            "subcategory":"Construction",
            "type":"Services"
        }
    ],
    "sg:phone":"+1 518 661 5351",
    "sg:postcode":"12117",
    "sg:province":"NY",
    "sg:tags":[
        "altering",
        "builder",
        "carpenter",
        "contractor",
        "improvement",
        "remodeling"
    ],
    "wof:name":"Timberline Builders",
    "wof:placetype":"venue"
},
  "geometry": {"coordinates":[-74.267912,43.104432],"type":"Point"}
}