{
  "type": "Feature",
  "properties": {
    "addr:full":"5 Tudor City Pl New York NY 10017",
    "addr:housenumber":"5",
    "addr:postcode":"10017",
    "addr:street":"Tudor City Pl",
    "iso:country":"US",
    "sg:address":"5 Tudor City Pl",
    "sg:city":"New York",
    "sg:classifiers":[
        {
            "category":"Shopping",
            "subcategory":"Florist",
            "type":"Retail Goods"
        }
    ],
    "sg:phone":"+1 212 883 0304",
    "sg:postcode":"10017",
    "sg:province":"NY",
    "sg:website":"www.michaelgeorgeflowers.com",
    "wof:name":"Michael Georges Flowers Inc",
    "wof:placetype":"venue"
},
  "geometry": {"coordinates":[-73.970947,40.74823],"type":"Point"}
}