{
  "type": "Feature",
  "properties": {
    "addr:full":"Twin Arch Rd Rock Tavern NY 12575",
    "addr:postcode":"12575",
    "addr:street":"Twin Arch Rd",
    "iso:country":"US",
    "sg:address":"Twin Arch Rd",
    "sg:city":"Rock Tavern",
    "sg:classifiers":[
        {
            "category":"Health Services",
            "subcategory":"Clinic",
            "type":"Services"
        }
    ],
    "sg:phone":"+1 845 427 9049",
    "sg:postcode":"12575",
    "sg:province":"NY",
    "sg:tags":[
        "counseling",
        "mental"
    ],
    "wof:name":"Marks Beth Msw-Acsw R",
    "wof:placetype":"venue"
},
  "geometry": {"coordinates":[-74.164597,41.470402],"type":"Point"}
}