{
  "type": "Feature",
  "properties": {
    "addr:full":"2528 Foster Ave Brooklyn NY 11210",
    "addr:housenumber":"2528",
    "addr:postcode":"11210",
    "addr:street":"Foster Ave",
    "iso:country":"US",
    "sg:address":"2528 Foster Ave",
    "sg:city":"Brooklyn",
    "sg:classifiers":[
        {
            "category":"Retail",
            "subcategory":"Auto Repair",
            "type":"Services"
        }
    ],
    "sg:phone":"+1   ",
    "sg:postcode":"11210",
    "sg:province":"NY",
    "sg:tags":[
        "general"
    ],
    "wof:name":"Saint Bernard Kenwrick",
    "wof:placetype":"venue"
},
  "geometry": {"coordinates":[-73.95226599999999,40.638348],"type":"Point"}
}