{
  "type": "Feature",
  "properties": {
    "iso:country":"US",
    "sg:address":"25 Broad St",
    "sg:city":"Gloversville",
    "sg:classifiers":[
        {
            "category":"Freight",
            "type":"Transportation"
        }
    ],
    "sg:phone":"+1   ",
    "sg:postcode":"12078",
    "sg:province":"NY",
    "sg:tags":[
        "general"
    ],
    "wof:name":"Doverridge LLC",
    "wof:placetype":"venue"
},
  "geometry": {"coordinates":[-74.35142399999999,43.043708],"type":"Point"}
}