{
  "type": "Feature",
  "properties": {
    "addr:full":"12743 Willets Point Blvd Corona NY 11368",
    "addr:housenumber":"12743",
    "addr:postcode":"11368",
    "addr:street":"Willets Point Blvd",
    "iso:country":"US",
    "sg:address":"12743 Willets Point Blvd",
    "sg:city":"Corona",
    "sg:classifiers":[
        {
            "category":"Retail",
            "subcategory":"Auto Repair",
            "type":"Services"
        }
    ],
    "sg:phone":"+1 718 429 9059",
    "sg:postcode":"11368",
    "sg:province":"NY",
    "sg:tags":[
        "body",
        "shop"
    ],
    "wof:name":"Roosevelt Auto Wrecking Inc",
    "wof:placetype":"venue"
},
  "geometry": {"coordinates":[-73.841599,40.7593],"type":"Point"}
}