{
  "type": "Feature",
  "properties": {
    "addr:full":"628 Broadway New York NY 10012",
    "addr:housenumber":"628",
    "addr:postcode":"10012",
    "addr:street":"Broadway",
    "iso:country":"US",
    "sg:address":"628 Broadway",
    "sg:city":"New York",
    "sg:classifiers":[
        {
            "category":"Professional",
            "type":"Services"
        }
    ],
    "sg:phone":"+1 212 533 3050",
    "sg:postcode":"10012",
    "sg:province":"NY",
    "sg:tags":[
        "establishment"
    ],
    "wof:name":"Context Integration",
    "wof:placetype":"venue"
},
  "geometry": {"coordinates":[-73.99621,40.725817],"type":"Point"}
}