{
  "type": "Feature",
  "properties": {
    "iso:country":"US",
    "sg:address":"1133 Park Ave",
    "sg:city":"New York",
    "sg:classifiers":[
        {
            "category":"Professional",
            "subcategory":"Business Services",
            "type":"Services"
        }
    ],
    "sg:phone":"+1   ",
    "sg:postcode":"10128",
    "sg:province":"NY",
    "wof:name":"Boehmler Interiors Otto",
    "wof:placetype":"venue"
},
  "geometry": {"coordinates":[-73.955082,40.78284],"type":"Point"}
}