{
  "type": "Feature",
  "properties": {
    "addr:full":"512 County Highway 123 Mayfield NY 12117",
    "addr:housenumber":"512",
    "addr:postcode":"12117",
    "addr:street":"County Highway 123",
    "iso:country":"US",
    "sg:address":"512 County Highway 123",
    "sg:city":"Mayfield",
    "sg:classifiers":[
        {
            "category":"Utilities",
            "subcategory":"Recycling",
            "type":"Services"
        },
        {
            "category":"Building & Trades",
            "subcategory":"Construction",
            "type":"Services"
        }
    ],
    "sg:phone":"+1 518 661 9981",
    "sg:postcode":"12117",
    "sg:province":"NY",
    "sg:tags":[
        "removal",
        "painting",
        "rubbish",
        "contractor"
    ],
    "wof:name":"J And R Used Stuff & Antiques - Trash Out Services",
    "wof:placetype":"venue"
},
  "geometry": {"coordinates":[-74.23178900000001,43.165989],"type":"Point"}
}