{
  "type": "Feature",
  "properties": {
    "addr:full":"14206 Oak Ave Flushing NY 11355",
    "addr:housenumber":"14206",
    "addr:postcode":"11355",
    "addr:street":"Oak Ave",
    "iso:country":"US",
    "sg:address":"14206 Oak Ave",
    "sg:city":"Flushing",
    "sg:phone":"+1 718 359 6435",
    "sg:postcode":"11355",
    "sg:province":"NY",
    "wof:name":"Zheng Ying Bao Acupuncturist",
    "wof:placetype":"venue"
},
  "geometry": {"coordinates":[-73.814043,40.74894],"type":"Point"}
}