{
  "type": "Feature",
  "properties": {
    "iso:country":"US",
    "sg:address":"31 Champlin Ave",
    "sg:city":"East Islip",
    "sg:classifiers":[
        {
            "category":"Building & Trades",
            "subcategory":"Construction",
            "type":"Services"
        }
    ],
    "sg:phone":"+1 631 277 2581",
    "sg:postcode":"11730",
    "sg:province":"NY",
    "sg:tags":[
        "contractor"
    ],
    "wof:name":"Anthonys Professional Services",
    "wof:placetype":"venue"
},
  "geometry": {"coordinates":[-73.18438399999999,40.735574],"type":"Point"}
}