{
  "type": "Feature",
  "properties": {
    "addr:full":"28 Vesey St New York NY 10007",
    "addr:housenumber":"28",
    "addr:postcode":"10007",
    "addr:street":"Vesey St",
    "iso:country":"US",
    "sg:address":"28 Vesey St",
    "sg:city":"New York",
    "sg:classifiers":[
        {
            "category":"Real Estate",
            "subcategory":"Real Estate Agent",
            "type":"Services"
        }
    ],
    "sg:phone":"+1 212 292 2707",
    "sg:postcode":"10007",
    "sg:province":"NY",
    "wof:name":"African American Realty Co",
    "wof:placetype":"venue"
},
  "geometry": {"coordinates":[-74.00910399999999,40.711529],"type":"Point"}
}