{
  "type": "Feature",
  "properties": {
    "iso:country":"US",
    "sg:address":"55 E 72 St",
    "sg:city":"New York",
    "sg:classifiers":[
        {
            "category":"Professional",
            "subcategory":"Management & Consulting",
            "type":"Services"
        }
    ],
    "sg:phone":"+1   ",
    "sg:postcode":"10021",
    "sg:province":"NY",
    "sg:tags":[
        "public",
        "relations"
    ],
    "wof:name":"Hoving Uncle Inc",
    "wof:placetype":"venue"
},
  "geometry": {"coordinates":[-73.964218,40.771409],"type":"Point"}
}