{
  "type": "Feature",
  "properties": {
    "addr:full":"1936 Ralph Ave Brooklyn NY 11234",
    "addr:housenumber":"1936",
    "addr:postcode":"11234",
    "addr:street":"Ralph Ave",
    "iso:country":"US",
    "sg:address":"1936 Ralph Ave",
    "sg:city":"Brooklyn",
    "sg:classifiers":[
        {
            "category":"Retail",
            "subcategory":"Portrait Studio",
            "type":"Services"
        },
        {
            "category":"Professional",
            "subcategory":"Art Services",
            "type":"Services"
        }
    ],
    "sg:phone":"+1 718 968 0504",
    "sg:postcode":"11234",
    "sg:province":"NY",
    "sg:tags":[
        "photographer",
        "photography",
        "store"
    ],
    "wof:name":"Spectrum Photo Studio",
    "wof:placetype":"venue"
},
  "geometry": {"coordinates":[-73.91860200000001,40.629869],"type":"Point"}
}