{
  "type": "Feature",
  "properties": {
    "addr:full":"156 Brewster Rd Scarsdale NY 10583",
    "addr:housenumber":"156",
    "addr:postcode":"10583",
    "addr:street":"Brewster Rd",
    "iso:country":"US",
    "sg:address":"156 Brewster Rd",
    "sg:city":"Scarsdale",
    "sg:classifiers":[
        {
            "category":"Health Services",
            "subcategory":"Doctor",
            "type":"Services"
        }
    ],
    "sg:phone":"+1 914 472 4822",
    "sg:postcode":"10583",
    "sg:province":"NY",
    "sg:tags":[
        "medical"
    ],
    "wof:name":"Sheldon Eisenman MD",
    "wof:placetype":"venue"
},
  "geometry": {"coordinates":[-73.78528300000001,41.012158],"type":"Point"}
}