{
  "type": "Feature",
  "properties": {
    "iso:country":"US",
    "sg:address":"7150 Morgan Rd",
    "sg:city":"Liverpool",
    "sg:classifiers":[
        {
            "category":"Professional",
            "subcategory":"Management & Consulting",
            "type":"Services"
        }
    ],
    "sg:phone":"+1 315 451 6054",
    "sg:postcode":"13090",
    "sg:province":"NY",
    "sg:tags":[
        "agency",
        "employment"
    ],
    "wof:name":"Onondaga Crtland Madison Boces",
    "wof:placetype":"venue"
},
  "geometry": {"coordinates":[-76.204899,43.116764],"type":"Point"}
}