{
  "type": "Feature",
  "properties": {
    "iso:country":"US",
    "sg:address":"854 Quincy St",
    "sg:city":"Brooklyn",
    "sg:classifiers":[
        {
            "category":"Social Services",
            "subcategory":"Child Care",
            "type":"Services"
        }
    ],
    "sg:phone":"+1   ",
    "sg:postcode":"11221",
    "sg:province":"NY",
    "sg:tags":[
        "day"
    ],
    "wof:name":"Happy Hearts Sitter Daycare",
    "wof:placetype":"venue"
},
  "geometry": {"coordinates":[-73.925749,40.689685],"type":"Point"}
}