{
  "type": "Feature",
  "properties": {
    "iso:country":"US",
    "sg:address":"53 2nd Avenue",
    "sg:city":"Manhattan",
    "sg:classifiers":[
        {
            "category":"Restaurant",
            "type":"Food & Drink"
        }
    ],
    "sg:postcode":"10003",
    "sg:province":"NY",
    "sg:tags":[
        "middle",
        "eastern"
    ],
    "wof:name":"Yem Yem Falafel",
    "wof:placetype":"venue"
},
  "geometry": {"coordinates":[-73.990101,40.725814],"type":"Point"}
}