{
  "type": "Feature",
  "properties": {
    "iso:country":"US",
    "sg:address":"824 State Route 50",
    "sg:city":"Burnt Hills",
    "sg:classifiers":[
        {
            "category":"Restaurant",
            "type":"Food & Drink"
        }
    ],
    "sg:phone":"+1 518 384 1997",
    "sg:postcode":"12027",
    "sg:province":"NY",
    "sg:tags":[
        "chinese"
    ],
    "wof:name":"Sam's Chinese Restaurant",
    "wof:placetype":"venue"
},
  "geometry": {"coordinates":[-73.895203,42.913898],"type":"Point"}
}