{
  "type": "Feature",
  "properties": {
    "iso:country":"US",
    "sg:address":"85 Page Ave",
    "sg:city":"Staten Island",
    "sg:classifiers":[
        {
            "category":"Food & Beverages",
            "subcategory":"Meat & Fish",
            "type":"Retail Goods"
        }
    ],
    "sg:phone":"+1 718 227 2828",
    "sg:postcode":"10309",
    "sg:province":"NY",
    "wof:name":"Mona Lisa Salumeria & Pork",
    "wof:placetype":"venue"
},
  "geometry": {"coordinates":[-74.234926,40.522403],"type":"Point"}
}