{
  "type": "Feature",
  "properties": {
    "iso:country":"US",
    "sg:address":"2701 Goethals Rd N",
    "sg:city":"Staten Island",
    "sg:classifiers":[
        {
            "category":"Building & Trades",
            "subcategory":"Construction",
            "type":"Services"
        }
    ],
    "sg:phone":"+1 718 982 0097",
    "sg:postcode":"10303",
    "sg:province":"NY",
    "sg:tags":[
        "floor",
        "laying",
        "contractor"
    ],
    "wof:name":"Americas Value Floor",
    "wof:placetype":"venue"
},
  "geometry": {"coordinates":[-74.181237,40.627846],"type":"Point"}
}