{
  "type": "Feature",
  "properties": {
    "addr:full":"258 Main St Johnson City NY 13790",
    "addr:housenumber":"258",
    "addr:postcode":"13790",
    "addr:street":"Main St",
    "iso:country":"US",
    "sg:address":"258 Main St",
    "sg:city":"Johnson City",
    "sg:classifiers":[
        {
            "category":"Restaurant",
            "type":"Food & Drink"
        }
    ],
    "sg:phone":"+1   ",
    "sg:postcode":"13790",
    "sg:province":"NY",
    "sg:tags":[
        "eating"
    ],
    "wof:name":"Green Owl Diner",
    "wof:placetype":"venue"
},
  "geometry": {"coordinates":[-75.955264,42.115012],"type":"Point"}
}