{
  "type": "Feature",
  "properties": {
    "addr:full":"10701 71st Avenue Forest Hills NY 11375",
    "addr:housenumber":"10701",
    "addr:postcode":"11375",
    "addr:street":"71St Avenue",
    "iso:country":"US",
    "sg:address":"10701 71st Avenue",
    "sg:city":"Forest Hills",
    "sg:classifiers":[
        {
            "category":"Banks & Credit Unions",
            "subcategory":"Bank",
            "type":"Services"
        }
    ],
    "sg:phone":"+1 718 268 8910",
    "sg:postcode":"11375",
    "sg:province":"NY",
    "wof:name":"Citibank Na",
    "wof:placetype":"venue"
},
  "geometry": {"coordinates":[-73.844876,40.720271],"type":"Point"}
}