{
  "type": "Feature",
  "properties": {
    "iso:country":"US",
    "sg:address":"320 N Robinson Ave",
    "sg:city":"Newburgh",
    "sg:classifiers":[
        {
            "category":"Health Services",
            "subcategory":"Doctor",
            "type":"Services"
        }
    ],
    "sg:phone":"+1 845 863 1000",
    "sg:postcode":"12550",
    "sg:province":"NY",
    "sg:tags":[
        "medical"
    ],
    "wof:name":"Hudson Vly Spt Mdcine Rblttion",
    "wof:placetype":"venue"
},
  "geometry": {"coordinates":[-74.019977,41.516245],"type":"Point"}
}