{
  "type": "Feature",
  "properties": {
    "addr:full":"202 E 179th St Bronx NY 10457",
    "addr:housenumber":"202",
    "addr:postcode":"10457",
    "addr:street":"E 179Th St",
    "iso:country":"US",
    "sg:address":"202 E 179th St",
    "sg:city":"Bronx",
    "sg:classifiers":[
        {
            "category":"Real Estate",
            "subcategory":"Real Estate Operator",
            "type":"Services"
        }
    ],
    "sg:phone":"+1 718 716 9079",
    "sg:postcode":"10457",
    "sg:province":"NY",
    "sg:tags":[
        "owner"
    ],
    "wof:name":"EDS Management",
    "wof:placetype":"venue"
},
  "geometry": {"coordinates":[-73.90289900000001,40.850676],"type":"Point"}
}