{
  "type": "Feature",
  "properties": {
    "addr:full":"188 2nd Ave New York NY 10003",
    "addr:housenumber":"188",
    "addr:postcode":"10003",
    "addr:street":"2Nd Ave",
    "iso:country":"US",
    "sg:address":"188 2nd Ave",
    "sg:city":"New York",
    "sg:classifiers":[
        {
            "category":"Restaurant",
            "type":"Food & Drink"
        }
    ],
    "sg:menulink":"http://www.allmenus.com/ny/new-york/60223-shima/menu/",
    "sg:phone":"+1 212 260 6303",
    "sg:postcode":"10003",
    "sg:province":"NY",
    "sg:tags":[
        "japanese",
        "asian"
    ],
    "wof:name":"Shima",
    "wof:placetype":"venue"
},
  "geometry": {"coordinates":[-73.985688,40.730777],"type":"Point"}
}