{
  "type": "Feature",
  "properties": {
    "addr:full":"771 Washington Ave Brooklyn NY 11238",
    "addr:housenumber":"771",
    "addr:postcode":"11238",
    "addr:street":"Washington Ave",
    "iso:country":"US",
    "sg:address":"771 Washington Ave",
    "sg:city":"Brooklyn",
    "sg:classifiers":[
        {
            "category":"Restaurant",
            "type":"Food & Drink"
        }
    ],
    "sg:menulink":"http://www.allmenus.com/ny/brooklyn/22620-3ds-place/menu/",
    "sg:phone":"+1 718 623 2310",
    "sg:postcode":"11238",
    "sg:province":"NY",
    "sg:tags":[
        "jamaican"
    ],
    "wof:name":"3D's Place",
    "wof:placetype":"venue"
},
  "geometry": {"coordinates":[-73.96298,40.67376],"type":"Point"}
}