{
  "type": "Feature",
  "properties": {
    "addr:full":"20 Main St Tonawanda NY 14150",
    "addr:housenumber":"20",
    "addr:postcode":"14150",
    "addr:street":"Main St",
    "iso:country":"US",
    "sg:address":"20 Main St",
    "sg:city":"Tonawanda",
    "sg:classifiers":[
        {
            "category":"Banks & Credit Unions",
            "subcategory":"Bank",
            "type":"Services"
        }
    ],
    "sg:phone":"+1 716 693 2440",
    "sg:postcode":"14150",
    "sg:province":"NY",
    "sg:tags":[
        "national",
        "commercial"
    ],
    "wof:name":"Charter One",
    "wof:placetype":"venue"
},
  "geometry": {"coordinates":[-78.878308,43.020283],"type":"Point"}
}