{
  "type": "Feature",
  "properties": {
    "addr:full":"161 Albany Post Rd Buchanan NY 10511",
    "addr:housenumber":"161",
    "addr:postcode":"10511",
    "addr:street":"Albany Post Rd",
    "iso:country":"US",
    "sg:address":"161 Albany Post Rd",
    "sg:city":"Buchanan",
    "sg:classifiers":[
        {
            "category":"Real Estate",
            "subcategory":"Real Estate Services",
            "type":"Services"
        },
        {
            "category":"Real Estate",
            "subcategory":"Real Estate Agent",
            "type":"Services"
        }
    ],
    "sg:phone":"+1 845 739 1901",
    "sg:postcode":"10511",
    "sg:province":"NY",
    "sg:tags":[
        "management"
    ],
    "wof:name":"Buchanan Realty Corp",
    "wof:placetype":"venue"
},
  "geometry": {"coordinates":[-73.935267,41.260099],"type":"Point"}
}