{
  "type": "Feature",
  "properties": {
    "addr:full":"153 Centre St New York NY 10013",
    "addr:housenumber":"153",
    "addr:postcode":"10013",
    "addr:street":"Centre St",
    "iso:country":"US",
    "sg:address":"153 Centre St",
    "sg:city":"New York",
    "sg:classifiers":[
        {
            "category":"Wholesale",
            "subcategory":"Non-durable Goods",
            "type":"Manufacturing & Wholesale Goods"
        }
    ],
    "sg:phone":"+1 212 226 5489",
    "sg:postcode":"10013",
    "sg:province":"NY",
    "wof:name":"Bright View Trading",
    "wof:placetype":"venue"
},
  "geometry": {"coordinates":[-74.0001,40.717922],"type":"Point"}
}