{
  "type": "Feature",
  "properties": {
    "addr:full":"143 Parkway Rd Bronxville NY 10708",
    "addr:housenumber":"143",
    "addr:postcode":"10708",
    "addr:street":"Parkway Rd",
    "iso:country":"US",
    "sg:address":"143 Parkway Rd",
    "sg:city":"Bronxville",
    "sg:classifiers":[
        {
            "category":"Coffee & Tea",
            "type":"Food & Drink"
        },
        {
            "category":"Restaurant",
            "type":"Food & Drink"
        }
    ],
    "sg:phone":"+1 914 337 3351",
    "sg:postcode":"10708",
    "sg:province":"NY",
    "sg:tags":[
        "american",
        "espresso"
    ],
    "wof:name":"The Village Cafe",
    "wof:placetype":"venue"
},
  "geometry": {"coordinates":[-73.835764,40.940986],"type":"Point"}
}