{
  "type": "Feature",
  "properties": {
    "iso:country":"US",
    "sg:address":"744 10th St",
    "sg:city":"Niagara Falls",
    "sg:classifiers":[
        {
            "category":"Real Estate",
            "subcategory":"Real Estate Operator",
            "type":"Services"
        }
    ],
    "sg:phone":"+1 716 285 6961",
    "sg:postcode":"14301",
    "sg:province":"NY",
    "sg:tags":[
        "building",
        "apartment",
        "executive"
    ],
    "wof:name":"Niagra Falls Housing Authority",
    "wof:placetype":"venue"
},
  "geometry": {"coordinates":[-79.050668,43.095789],"type":"Point"}
}