{
  "type": "Feature",
  "properties": {
    "iso:country":"US",
    "sg:address":"10 Columbia Pl Ste 8",
    "sg:city":"Brooklyn",
    "sg:classifiers":[
        {
            "category":"Health Services",
            "subcategory":"Doctor",
            "type":"Services"
        }
    ],
    "sg:phone":"+1 718 935 9393",
    "sg:postcode":"11201",
    "sg:province":"NY",
    "sg:tags":[
        "obstetrician",
        "gynecologist"
    ],
    "sg:website":"facebook.com/orchidgynecology",
    "wof:name":"Judith Weinstock",
    "wof:placetype":"venue"
},
  "geometry": {"coordinates":[-73.99847200000001,40.693415],"type":"Point"}
}