{
  "type": "Feature",
  "properties": {
    "iso:country":"US",
    "sg:address":"100 S Clinton St",
    "sg:city":"Syracuse",
    "sg:classifiers":[
        {
            "category":"Banks & Credit Unions",
            "subcategory":"Bank",
            "type":"Services"
        }
    ],
    "sg:phone":"+1 315 426 4219",
    "sg:postcode":"13202",
    "sg:province":"NY",
    "sg:tags":[
        "state",
        "commercial"
    ],
    "wof:name":"Fleet",
    "wof:placetype":"venue"
},
  "geometry": {"coordinates":[-76.15355700000001,43.049602],"type":"Point"}
}