{
  "type": "Feature",
  "properties": {
    "iso:country":"US",
    "sg:address":"2994 Navajo St",
    "sg:city":"Yorktown Heights",
    "sg:classifiers":[
        {
            "category":"Building & Trades",
            "subcategory":"Landscaping Services",
            "type":"Services"
        }
    ],
    "sg:phone":"+1 914 248 0576",
    "sg:postcode":"10598",
    "sg:province":"NY",
    "sg:tags":[
        "tree"
    ],
    "wof:name":"Rayal Tree Care Co",
    "wof:placetype":"venue"
},
  "geometry": {"coordinates":[-73.784182,41.337294],"type":"Point"}
}