{
  "type": "Feature",
  "properties": {
    "addr:full":"29 Rocky Point Landing Rd Rocky Point NY 11789",
    "addr:housenumber":"29",
    "addr:postcode":"11789",
    "addr:street":"Rocky Point Landing Rd",
    "iso:country":"US",
    "sg:address":"29 Rocky Point Landing Rd",
    "sg:city":"Rocky Point",
    "sg:classifiers":[
        {
            "category":"Organizations",
            "subcategory":"Community Association",
            "type":"Services"
        }
    ],
    "sg:phone":"+1 631 744 3911",
    "sg:postcode":"11789",
    "sg:province":"NY",
    "sg:tags":[
        "fraternal"
    ],
    "wof:name":"Sons Of Italy In America",
    "wof:placetype":"venue"
},
  "geometry": {"coordinates":[-72.961393,40.962703],"type":"Point"}
}