{
  "type": "Feature",
  "properties": {
    "addr:full":"442 3rd Ave Brooklyn NY 11215",
    "addr:housenumber":"442",
    "addr:postcode":"11215",
    "addr:street":"3Rd Ave",
    "iso:country":"US",
    "sg:address":"442 3rd Ave",
    "sg:city":"Brooklyn",
    "sg:classifiers":[
        {
            "category":"Retail",
            "subcategory":"Auto Repair",
            "type":"Services"
        }
    ],
    "sg:phone":"+1 718 788 6324",
    "sg:postcode":"11215",
    "sg:province":"NY",
    "wof:name":"Ridge Transport",
    "wof:placetype":"venue"
},
  "geometry": {"coordinates":[-73.99050099999999,40.672298],"type":"Point"}
}