{
  "type": "Feature",
  "properties": {
    "addr:full":"1479 53rd St Brooklyn NY 11219",
    "addr:housenumber":"1479",
    "addr:postcode":"11219",
    "addr:street":"53Rd St",
    "iso:country":"US",
    "sg:address":"1479 53rd St",
    "sg:city":"Brooklyn",
    "sg:classifiers":[
        {
            "category":"Organizations",
            "subcategory":"Religious Organization",
            "type":"Services"
        }
    ],
    "sg:phone":"+1 718 851 7150",
    "sg:postcode":"11219",
    "sg:province":"NY",
    "sg:tags":[
        "clergy"
    ],
    "wof:name":"Baruch D Halberstam",
    "wof:placetype":"venue"
},
  "geometry": {"coordinates":[-73.991328,40.631243],"type":"Point"}
}