{
  "type": "Feature",
  "properties": {
    "iso:country":"US",
    "sg:address":"20 Canal St",
    "sg:city":"Lyons",
    "sg:classifiers":[
        {
            "category":"Health Services",
            "subcategory":"Doctor",
            "type":"Services"
        }
    ],
    "sg:phone":"+1 315 946 4000",
    "sg:postcode":"14489",
    "sg:province":"NY",
    "sg:tags":[
        "dentist"
    ],
    "wof:name":"Anthony J D'Amico DDS",
    "wof:placetype":"venue"
},
  "geometry": {"coordinates":[-76.99137,43.064117],"type":"Point"}
}