{
  "type": "Feature",
  "properties": {
    "addr:full":"259 W 54 St New York NY 10019",
    "addr:housenumber":"259",
    "addr:postcode":"10019",
    "addr:street":"W 54 St",
    "iso:country":"US",
    "sg:address":"259 W 54 St",
    "sg:city":"New York",
    "sg:classifiers":[
        {
            "category":"Retail",
            "subcategory":"Photofinishing",
            "type":"Services"
        }
    ],
    "sg:phone":"+1 212 246 7171",
    "sg:postcode":"10019",
    "sg:province":"NY",
    "sg:tags":[
        "photo",
        "finishing"
    ],
    "wof:name":"LAH Film Corp",
    "wof:placetype":"venue"
},
  "geometry": {"coordinates":[-73.98368000000001,40.764545],"type":"Point"}
}