{
  "type": "Feature",
  "properties": {
    "addr:full":"1409 Richmond Ave Staten Island NY 10314",
    "addr:housenumber":"1409",
    "addr:postcode":"10314",
    "addr:street":"Richmond Ave",
    "iso:country":"US",
    "sg:address":"1409 Richmond Ave",
    "sg:city":"Staten Island",
    "sg:classifiers":[
        {
            "category":"Retail",
            "subcategory":"Veterinary Services",
            "type":"Services"
        }
    ],
    "sg:phone":"+1 718 370 0700",
    "sg:postcode":"10314",
    "sg:province":"NY",
    "sg:tags":[
        "hospital",
        "animal"
    ],
    "wof:name":"Aadobe Animal Hospital",
    "wof:placetype":"venue"
},
  "geometry": {"coordinates":[-74.158551,40.613208],"type":"Point"}
}