{
  "type": "Feature",
  "properties": {
    "addr:full":"7301 Stagecoach Rd Dansville NY 14437",
    "addr:housenumber":"7301",
    "addr:postcode":"14437",
    "addr:street":"Stagecoach Rd",
    "iso:country":"US",
    "sg:address":"7301 Stagecoach Rd",
    "sg:city":"Dansville",
    "sg:classifiers":[
        {
            "category":"Retail",
            "subcategory":"Repair Shop",
            "type":"Services"
        }
    ],
    "sg:phone":"+1 585 335 7504",
    "sg:postcode":"14437",
    "sg:province":"NY",
    "sg:tags":[
        "upholsterer"
    ],
    "wof:name":"Pete Hoffman Custom Upholstery",
    "wof:placetype":"venue"
},
  "geometry": {"coordinates":[-77.685242,42.666547],"type":"Point"}
}