{
  "type": "Feature",
  "properties": {
    "addr:full":"170 Cedar Shore Dr Massapequa NY 11758",
    "addr:housenumber":"170",
    "addr:postcode":"11758",
    "addr:street":"Cedar Shore Dr",
    "iso:country":"US",
    "sg:address":"170 Cedar Shore Dr",
    "sg:city":"Massapequa",
    "sg:classifiers":[
        {
            "category":"Freight",
            "type":"Transportation"
        }
    ],
    "sg:phone":"+1   ",
    "sg:postcode":"11758",
    "sg:province":"NY",
    "sg:tags":[
        "operator",
        "trucking"
    ],
    "wof:name":"Kruse Overland Marine Trnspt",
    "wof:placetype":"venue"
},
  "geometry": {"coordinates":[-73.458777,40.65649],"type":"Point"}
}