{
  "type": "Feature",
  "properties": {
    "addr:full":"184 E 76 St New York NY 10021",
    "addr:housenumber":"184;76",
    "addr:postcode":"10021",
    "addr:street":"E;St",
    "iso:country":"US",
    "sg:address":"184 E 76 St",
    "sg:city":"New York",
    "sg:classifiers":[
        {
            "category":"Professional",
            "type":"Services"
        }
    ],
    "sg:phone":"+1 212 288 1971",
    "sg:postcode":"10021",
    "sg:province":"NY",
    "sg:tags":[
        "establishment"
    ],
    "wof:name":"Blessed Sacrament Fathers",
    "wof:placetype":"venue"
},
  "geometry": {"coordinates":[-73.95871699999999,40.772331],"type":"Point"}
}