{
  "type": "Feature",
  "properties": {
    "addr:full":"1200 State Hwy 208 Monroe NY 10950",
    "addr:housenumber":"1200",
    "addr:postcode":"10950",
    "addr:street":"State Hwy 208",
    "iso:country":"US",
    "sg:address":"1200 State Hwy 208",
    "sg:city":"Monroe",
    "sg:classifiers":[
        {
            "category":"Sports & Exercise",
            "subcategory":"Gym",
            "type":"Entertainment"
        }
    ],
    "sg:phone":"+1 845 782 8847",
    "sg:postcode":"10950",
    "sg:province":"NY",
    "sg:tags":[
        "club",
        "health",
        "studio",
        "gymnasium"
    ],
    "wof:name":"Ladies Workout Express",
    "wof:placetype":"venue"
},
  "geometry": {"coordinates":[-74.175898,41.383928],"type":"Point"}
}