{
  "type": "Feature",
  "properties": {
    "addr:full":"694 W Sunrise Hwy Valley Stream NY 11581",
    "addr:housenumber":"694",
    "addr:postcode":"11581",
    "addr:street":"W Sunrise Hwy",
    "iso:country":"US",
    "sg:address":"694 W Sunrise Hwy",
    "sg:city":"Valley Stream",
    "sg:classifiers":[
        {
            "category":"Restaurant",
            "type":"Food & Drink"
        }
    ],
    "sg:menulink":"http://www.allmenus.com/ny/valley-stream/240737-bronx-b-b-q/menu/",
    "sg:phone":"+1 516 256 2049",
    "sg:postcode":"11581",
    "sg:province":"NY",
    "sg:tags":[
        "barbecue",
        "american"
    ],
    "wof:name":"Bronx B B Q",
    "wof:placetype":"venue"
},
  "geometry": {"coordinates":[-73.724417,40.665402],"type":"Point"}
}