{
  "type": "Feature",
  "properties": {
    "iso:country":"US",
    "sg:address":"1042 Main St",
    "sg:city":"Fishkill",
    "sg:classifiers":[
        {
            "category":"Banks & Credit Unions",
            "subcategory":"Bank",
            "type":"Services"
        }
    ],
    "sg:phone":"+1 845 896 2880",
    "sg:postcode":"12524",
    "sg:province":"NY",
    "wof:name":"Park Avenue Bank",
    "wof:placetype":"venue"
},
  "geometry": {"coordinates":[-73.904612,41.533968],"type":"Point"}
}