{
  "type": "Feature",
  "properties": {
    "addr:full":"984 Leasure Hill Rd Nichols NY 13812",
    "addr:housenumber":"984",
    "addr:postcode":"13812",
    "addr:street":"Leasure Hill Rd",
    "iso:country":"US",
    "sg:address":"984 Leasure Hill Rd",
    "sg:city":"Nichols",
    "sg:classifiers":[
        {
            "category":"Real Estate",
            "subcategory":"Real Estate Operator",
            "type":"Services"
        }
    ],
    "sg:phone":"+1 607 699 7918",
    "sg:postcode":"13812",
    "sg:province":"NY",
    "sg:tags":[
        "property",
        "lessor"
    ],
    "wof:name":"Charles Briggs",
    "wof:placetype":"venue"
},
  "geometry": {"coordinates":[-76.393094,42.008349],"type":"Point"}
}