{
  "type": "Feature",
  "properties": {
    "iso:country":"US",
    "sg:address":"279 Rte 25A",
    "sg:city":"Rocky Point",
    "sg:classifiers":[
        {
            "category":"Restaurant",
            "type":"Food & Drink"
        }
    ],
    "sg:phone":"+1 631 821 3969",
    "sg:postcode":"11778",
    "sg:province":"NY",
    "wof:name":"Antino's Pizzeria & Restaurant",
    "wof:placetype":"venue"
},
  "geometry": {"coordinates":[-72.950119,40.944937],"type":"Point"}
}