{
  "type": "Feature",
  "properties": {
    "iso:country":"US",
    "sg:address":"1954 Fowler Ave",
    "sg:city":"Bronx",
    "sg:classifiers":[
        {
            "category":"Building & Trades",
            "subcategory":"Construction",
            "type":"Services"
        }
    ],
    "sg:phone":"+1 718 892 5535",
    "sg:postcode":"10462",
    "sg:province":"NY",
    "sg:tags":[
        "general",
        "contractor"
    ],
    "wof:name":"RAM Contracting Co",
    "wof:placetype":"venue"
},
  "geometry": {"coordinates":[-73.86105000000001,40.849867],"type":"Point"}
}