{
  "type": "Feature",
  "properties": {
    "addr:full":"693 East Ave Rochester NY 14607",
    "addr:housenumber":"693",
    "addr:postcode":"14607",
    "addr:street":"East Ave",
    "iso:country":"US",
    "sg:address":"693 East Ave",
    "sg:city":"Rochester",
    "sg:classifiers":[
        {
            "category":"Real Estate",
            "subcategory":"Real Estate Operator",
            "type":"Services"
        }
    ],
    "sg:phone":"+1 585 442 4110",
    "sg:postcode":"14607",
    "sg:province":"NY",
    "sg:tags":[
        "building",
        "nonresidential"
    ],
    "wof:name":"New ERA Enterprises LLC",
    "wof:placetype":"venue"
},
  "geometry": {"coordinates":[-77.58646,43.153091],"type":"Point"}
}