{
  "type": "Feature",
  "properties": {
    "iso:country":"US",
    "sg:address":"206 E 117th St",
    "sg:city":"New York",
    "sg:classifiers":[
        {
            "category":"Social Services",
            "type":"Services"
        }
    ],
    "sg:phone":"+1 212 996 5899",
    "sg:postcode":"10035",
    "sg:province":"NY",
    "sg:tags":[
        "instruction",
        "health",
        "care"
    ],
    "wof:name":"Holistic Healing System",
    "wof:placetype":"venue"
},
  "geometry": {"coordinates":[-73.93742,40.79767],"type":"Point"}
}