{
  "type": "Feature",
  "properties": {
    "addr:full":"605 Main St Port Jefferson NY 11777",
    "addr:housenumber":"605",
    "addr:postcode":"11777",
    "addr:street":"Main St",
    "iso:country":"US",
    "sg:address":"605 Main St",
    "sg:city":"Port Jefferson",
    "sg:classifiers":[
        {
            "category":"Social Services",
            "subcategory":"Child Care",
            "type":"Services"
        }
    ],
    "sg:phone":"+1   ",
    "sg:postcode":"11777",
    "sg:province":"NY",
    "sg:tags":[
        "day"
    ],
    "wof:name":"Harbor View Nursery School",
    "wof:placetype":"venue"
},
  "geometry": {"coordinates":[-73.06699399999999,40.94365],"type":"Point"}
}