{
  "type": "Feature",
  "properties": {
    "addr:full":"78 Lafayette Ave Suffern NY 10901",
    "addr:housenumber":"78",
    "addr:postcode":"10901",
    "addr:street":"Lafayette Ave",
    "iso:country":"US",
    "sg:address":"78 Lafayette Ave",
    "sg:city":"Suffern",
    "sg:classifiers":[
        {
            "category":"Social Services",
            "type":"Services"
        }
    ],
    "sg:phone":"+1 845 368 4590",
    "sg:postcode":"10901",
    "sg:province":"NY",
    "sg:tags":[
        "worker"
    ],
    "wof:name":"Laura Woolis",
    "wof:placetype":"venue"
},
  "geometry": {"coordinates":[-74.150667,41.115278],"type":"Point"}
}