{
  "type": "Feature",
  "properties": {
    "iso:country":"US",
    "sg:address":"8593 Turin Rd",
    "sg:city":"Rome",
    "sg:classifiers":[
        {
            "category":"Professional",
            "subcategory":"Accounting & Tax Preparation",
            "type":"Services"
        }
    ],
    "sg:phone":"+1 315 337 9330",
    "sg:postcode":"13440",
    "sg:province":"NY",
    "sg:tags":[
        "accountant"
    ],
    "wof:name":"Stephen F Schink CPA",
    "wof:placetype":"venue"
},
  "geometry": {"coordinates":[-75.469826,43.27728],"type":"Point"}
}