{
  "type": "Feature",
  "properties": {
    "iso:country":"US",
    "sg:address":"6 Cedar Ct",
    "sg:city":"Poughkeepsie",
    "sg:classifiers":[
        {
            "category":"Manufacturing",
            "subcategory":"Paper Products",
            "type":"Manufacturing & Wholesale Goods"
        }
    ],
    "sg:phone":"+1   ",
    "sg:postcode":"12603",
    "sg:province":"NY",
    "sg:tags":[
        "packaging",
        "mfg"
    ],
    "wof:name":"Advanced Thin Film Technology",
    "wof:placetype":"venue"
},
  "geometry": {"coordinates":[-73.84256499999999,41.66261],"type":"Point"}
}