{
  "type": "Feature",
  "properties": {
    "addr:full":"669 Coney Island Ave Brooklyn NY 11218",
    "addr:housenumber":"669",
    "addr:postcode":"11218",
    "addr:street":"Coney Island Ave",
    "iso:country":"US",
    "sg:address":"669 Coney Island Ave",
    "sg:city":"Brooklyn",
    "sg:classifiers":[
        {
            "category":"Communications",
            "type":"Services"
        }
    ],
    "sg:phone":"+1 718 703 0056",
    "sg:postcode":"11218",
    "sg:province":"NY",
    "wof:name":"Task Communication Technolgies",
    "wof:placetype":"venue"
},
  "geometry": {"coordinates":[-73.968897,40.640019],"type":"Point"}
}