{
  "type": "Feature",
  "properties": {
    "iso:country":"US",
    "sg:address":"3922 Hogmire Rd",
    "sg:city":"Avon",
    "sg:classifiers":[
        {
            "category":"Building & Trades",
            "subcategory":"Cleaning & Sanitation",
            "type":"Services"
        }
    ],
    "sg:phone":"+1 585 226 2960",
    "sg:postcode":"14414",
    "sg:province":"NY",
    "sg:tags":[
        "fireplace",
        "chimney"
    ],
    "wof:name":"Genesee Valley Chimney Sweep",
    "wof:placetype":"venue"
},
  "geometry": {"coordinates":[-77.79509,42.875188],"type":"Point"}
}