{
  "type": "Feature",
  "properties": {
    "iso:country":"US",
    "sg:address":"641 Hickory Rd",
    "sg:city":"Angola",
    "sg:classifiers":[
        {
            "category":"Organizations",
            "subcategory":"Community Association",
            "type":"Services"
        }
    ],
    "sg:phone":"+1   ",
    "sg:postcode":"14006",
    "sg:province":"NY",
    "wof:name":"Disabled American Veteran",
    "wof:placetype":"venue"
},
  "geometry": {"coordinates":[-79.06139899999999,42.645489],"type":"Point"}
}