{
  "type": "Feature",
  "properties": {
    "addr:full":"104 W Point Hwy Highland Falls NY 10928",
    "addr:housenumber":"104",
    "addr:postcode":"10928",
    "addr:street":"W Point Hwy",
    "iso:country":"US",
    "sg:address":"104 W Point Hwy",
    "sg:city":"Highland Falls",
    "sg:classifiers":[
        {
            "category":"Restaurant",
            "type":"Food & Drink"
        }
    ],
    "sg:phone":"+1   ",
    "sg:postcode":"10928",
    "sg:province":"NY",
    "sg:tags":[
        "eating"
    ],
    "wof:name":"McDonalds",
    "wof:placetype":"venue"
},
  "geometry": {"coordinates":[-73.963967,41.371247],"type":"Point"}
}