{
  "type": "Feature",
  "properties": {
    "addr:full":"694 E 149th St Bronx NY 10455",
    "addr:housenumber":"694",
    "addr:postcode":"10455",
    "addr:street":"E 149Th St",
    "iso:country":"US",
    "sg:address":"694 E 149th St",
    "sg:city":"Bronx",
    "sg:classifiers":[
        {
            "category":"Professional",
            "type":"Services"
        }
    ],
    "sg:phone":"+1 718 742 0630",
    "sg:postcode":"10455",
    "sg:province":"NY",
    "sg:tags":[
        "establishment"
    ],
    "wof:name":"Bath Productions",
    "wof:placetype":"venue"
},
  "geometry": {"coordinates":[-73.909412,40.813249],"type":"Point"}
}