{
  "type": "Feature",
  "properties": {
    "iso:country":"US",
    "sg:address":"110 Birch Dr",
    "sg:city":"Roslyn",
    "sg:classifiers":[
        {
            "category":"Real Estate",
            "subcategory":"Real Estate Services",
            "type":"Services"
        }
    ],
    "sg:phone":"+1 516 466 1800",
    "sg:postcode":"11576",
    "sg:province":"NY",
    "sg:tags":[
        "commercial"
    ],
    "wof:name":"Erb Partners",
    "wof:placetype":"venue"
},
  "geometry": {"coordinates":[-73.631299,40.801375],"type":"Point"}
}