{
  "type": "Feature",
  "properties": {
    "addr:full":"474 Old Country Rd Westbury NY 11590",
    "addr:housenumber":"474",
    "addr:postcode":"11590",
    "addr:street":"Old Country Rd",
    "iso:country":"US",
    "sg:address":"474 Old Country Rd",
    "sg:city":"Westbury",
    "sg:classifiers":[
        {
            "category":"Travel",
            "subcategory":"Hotels & Motels",
            "type":"Entertainment"
        }
    ],
    "sg:phone":"+1 516 997 2222",
    "sg:postcode":"11590",
    "sg:province":"NY",
    "wof:name":"Empire Palace Inc",
    "wof:placetype":"venue"
},
  "geometry": {"coordinates":[-73.578292,40.749641],"type":"Point"}
}