{
  "type": "Feature",
  "properties": {
    "iso:country":"US",
    "sg:address":"1364 Lexington Ave",
    "sg:city":"New York",
    "sg:classifiers":[
        {
            "category":"Personal",
            "subcategory":"Beauty Salon",
            "type":"Services"
        }
    ],
    "sg:phone":"+1 212 360 5557",
    "sg:postcode":"10128",
    "sg:province":"NY",
    "sg:tags":[
        "hair",
        "shop"
    ],
    "sg:website":"www.giovannisacchi.com/homepage/",
    "wof:name":"Giovanni Sacchi Hair Salon",
    "wof:placetype":"venue"
},
  "geometry": {"coordinates":[-73.953598,40.782101],"type":"Point"}
}