{
  "type": "Feature",
  "properties": {
    "addr:full":"115 2nd Pl Brooklyn NY 11231",
    "addr:housenumber":"115",
    "addr:postcode":"11231",
    "addr:street":"2Nd Pl",
    "iso:country":"US",
    "sg:address":"115 2nd Pl",
    "sg:city":"Brooklyn",
    "sg:classifiers":[
        {
            "category":"Farming",
            "subcategory":"Farm",
            "type":"Manufacturing & Wholesale Goods"
        }
    ],
    "sg:phone":"+1 718 522 6253",
    "sg:postcode":"11231",
    "sg:province":"NY",
    "sg:tags":[
        "crop",
        "general"
    ],
    "wof:name":"Terebessy John",
    "wof:placetype":"venue"
},
  "geometry": {"coordinates":[-73.996149,40.679303],"type":"Point"}
}