{
  "type": "Feature",
  "properties": {
    "addr:full":"300 Elmwood Ave Buffalo NY 14222",
    "addr:housenumber":"300",
    "addr:postcode":"14222",
    "addr:street":"Elmwood Ave",
    "iso:country":"US",
    "sg:address":"300 Elmwood Ave",
    "sg:city":"Buffalo",
    "sg:classifiers":[
        {
            "category":"Donuts",
            "subcategory":"None",
            "type":"Food & Drink"
        }
    ],
    "sg:phone":"+1 716 885 8709",
    "sg:postcode":"14222",
    "sg:province":"NY",
    "wof:name":"Bakerman Inc",
    "wof:placetype":"venue"
},
  "geometry": {"coordinates":[-78.877098,42.905399],"type":"Point"}
}