{
  "type": "Feature",
  "properties": {
    "addr:full":"1220 W Church St Elmira NY 14905",
    "addr:housenumber":"1220",
    "addr:postcode":"14905",
    "addr:street":"W Church St",
    "iso:country":"US",
    "sg:address":"1220 W Church St",
    "sg:city":"Elmira",
    "sg:classifiers":[
        {
            "category":"Professional",
            "subcategory":"Lawyer & Legal Services",
            "type":"Services"
        }
    ],
    "sg:phone":"+1 607 733 2698",
    "sg:postcode":"14905",
    "sg:province":"NY",
    "sg:tags":[
        "attorney"
    ],
    "wof:name":"William A Shaffer Jr",
    "wof:placetype":"venue"
},
  "geometry": {"coordinates":[-76.840306,42.080626],"type":"Point"}
}