{
  "type": "Feature",
  "properties": {
    "iso:country":"US",
    "sg:address":"15 Terrace Rd",
    "sg:city":"Cortland",
    "sg:classifiers":[
        {
            "category":"Building & Trades",
            "subcategory":"Construction",
            "type":"Services"
        }
    ],
    "sg:phone":"+1 607 756 8241",
    "sg:postcode":"13045",
    "sg:province":"NY",
    "sg:tags":[
        "marking",
        "maintenance",
        "parking"
    ],
    "wof:name":"Cortlandville Highway Dept",
    "wof:placetype":"venue"
},
  "geometry": {"coordinates":[-76.209825,42.579654],"type":"Point"}
}