{
  "type": "Feature",
  "properties": {
    "iso:country":"US",
    "sg:address":"3199 Long Beach Rd",
    "sg:city":"Oceanside",
    "sg:classifiers":[
        {
            "category":"Shopping",
            "subcategory":"Pharmacy",
            "type":"Retail Goods"
        }
    ],
    "sg:phone":"+1 516 766 7201",
    "sg:postcode":"11572",
    "sg:province":"NY",
    "wof:name":"Genovese Drug Stores Inc",
    "wof:placetype":"venue"
},
  "geometry": {"coordinates":[-73.64064399999999,40.633392],"type":"Point"}
}