{
  "type": "Feature",
  "properties": {
    "addr:full":"11240 116th St Jamaica NY 11420",
    "addr:housenumber":"11240",
    "addr:postcode":"11420",
    "addr:street":"116Th St",
    "iso:country":"US",
    "sg:address":"11240 116th St",
    "sg:city":"Jamaica",
    "sg:classifiers":[
        {
            "category":"Professional",
            "type":"Services"
        }
    ],
    "sg:phone":"+1 718 835 7655",
    "sg:postcode":"11420",
    "sg:province":"NY",
    "sg:tags":[
        "establishment"
    ],
    "wof:name":"LLC Nafs",
    "wof:placetype":"venue"
},
  "geometry": {"coordinates":[-73.82372599999999,40.67973],"type":"Point"}
}