{
  "type": "Feature",
  "properties": {
    "iso:country":"US",
    "sg:address":"78 5th Ave",
    "sg:city":"New York",
    "sg:classifiers":[
        {
            "category":"Professional",
            "type":"Services"
        }
    ],
    "sg:phone":"+1 212 691 0576",
    "sg:postcode":"10011",
    "sg:province":"NY",
    "sg:tags":[
        "establishment"
    ],
    "wof:name":"Green Cross Flying Doctors",
    "wof:placetype":"venue"
},
  "geometry": {"coordinates":[-73.99398600000001,40.735487],"type":"Point"}
}