{
  "type": "Feature",
  "properties": {
    "iso:country":"US",
    "sg:address":"1308 Flatbush Ave",
    "sg:city":"Brooklyn",
    "sg:classifiers":[
        {
            "category":"Organizations",
            "subcategory":"Professional Association",
            "type":"Services"
        }
    ],
    "sg:phone":"+1 718 434 6038",
    "sg:postcode":"11210",
    "sg:province":"NY",
    "wof:name":"Kaybamz Inc",
    "wof:placetype":"venue"
},
  "geometry": {"coordinates":[-73.952951,40.637732],"type":"Point"}
}