{
  "type": "Feature",
  "properties": {
    "addr:full":"200 Cleveland Dr Buffalo NY 14215",
    "addr:housenumber":"200",
    "addr:postcode":"14215",
    "addr:street":"Cleveland Dr",
    "iso:country":"US",
    "sg:address":"200 Cleveland Dr",
    "sg:city":"Buffalo",
    "sg:classifiers":[
        {
            "category":"Organizations",
            "subcategory":"Religious Organization",
            "type":"Services"
        }
    ],
    "sg:phone":"+1 716 834 2947",
    "sg:postcode":"14215",
    "sg:province":"NY",
    "sg:tags":[
        "clergy"
    ],
    "wof:name":"W D O'Hara",
    "wof:placetype":"venue"
},
  "geometry": {"coordinates":[-78.79168,42.944982],"type":"Point"}
}