{
  "type": "Feature",
  "properties": {
    "addr:full":"336 Clifton Park Center Rd Clifton Park NY 12065",
    "addr:housenumber":"336",
    "addr:postcode":"12065",
    "addr:street":"Clifton Park Center Rd",
    "iso:country":"US",
    "sg:address":"336 Clifton Park Center Rd",
    "sg:city":"Clifton Park",
    "sg:classifiers":[
        {
            "category":"Government",
            "subcategory":"Office",
            "type":"Public Place"
        }
    ],
    "sg:phone":"+1 518 383 2480",
    "sg:postcode":"12065",
    "sg:province":"NY",
    "sg:website":"www.nysdmv.com",
    "wof:name":"Saratoga County Motor Vehicle",
    "wof:placetype":"venue"
},
  "geometry": {"coordinates":[-73.776432,42.85821],"type":"Point"}
}