{
  "type": "Feature",
  "properties": {
    "addr:full":"8305 98th St Woodhaven NY 11421",
    "addr:housenumber":"8305",
    "addr:postcode":"11421",
    "addr:street":"98Th St",
    "iso:country":"US",
    "sg:address":"8305 98th St",
    "sg:city":"Woodhaven",
    "sg:classifiers":[
        {
            "category":"Real Estate",
            "subcategory":"Real Estate Agent",
            "type":"Services"
        }
    ],
    "sg:phone":"+1 718 805 3951",
    "sg:postcode":"11421",
    "sg:province":"NY",
    "wof:name":"Dolores Vescova Realtor",
    "wof:placetype":"venue"
},
  "geometry": {"coordinates":[-73.84932000000001,40.698013],"type":"Point"}
}