{
  "type": "Feature",
  "properties": {
    "addr:full":"5091 S Catherine St Plattsburgh NY 12901",
    "addr:housenumber":"5091",
    "addr:postcode":"12901",
    "addr:street":"S Catherine St",
    "iso:country":"US",
    "sg:address":"5091 S Catherine St",
    "sg:city":"Plattsburgh",
    "sg:classifiers":[
        {
            "category":"Personal",
            "subcategory":"Beauty Salon",
            "type":"Services"
        }
    ],
    "sg:phone":"+1 518 566 8118",
    "sg:postcode":"12901",
    "sg:province":"NY",
    "wof:name":"Stev Ann's",
    "wof:placetype":"venue"
},
  "geometry": {"coordinates":[-73.457773,44.694705],"type":"Point"}
}