{
  "type": "Feature",
  "properties": {
    "iso:country":"US",
    "sg:address":"169 Saint Paul St",
    "sg:city":"Rochester",
    "sg:classifiers":[
        {
            "category":"Communications",
            "subcategory":"Radio Station",
            "type":"Services"
        }
    ],
    "sg:phone":"+1 585 232 5890",
    "sg:postcode":"14604",
    "sg:province":"NY",
    "sg:tags":[
        "company",
        "broadcasting"
    ],
    "sg:website":"www.universalbuzz.com",
    "wof:name":"Universal Buzz Radio",
    "wof:placetype":"venue"
},
  "geometry": {"coordinates":[-77.610246,43.160827],"type":"Point"}
}