{
  "type": "Feature",
  "properties": {
    "iso:country":"US",
    "sg:address":"116 Main St",
    "sg:city":"Moravia",
    "sg:classifiers":[
        {
            "category":"Restaurant",
            "type":"Food & Drink"
        }
    ],
    "sg:phone":"+1 315 497 2288",
    "sg:postcode":"13118",
    "sg:province":"NY",
    "sg:tags":[
        "asian",
        "chinese",
        "pan"
    ],
    "wof:name":"Great Garden Chinese Restaurant",
    "wof:placetype":"venue"
},
  "geometry": {"coordinates":[-76.42147300000001,42.711795],"type":"Point"}
}