{
  "type": "Feature",
  "properties": {
    "iso:country":"US",
    "sg:address":"658 Motor Pkwy",
    "sg:city":"Hauppauge",
    "sg:classifiers":[
        {
            "category":"Health Services",
            "subcategory":"Chiropractor",
            "type":"Services"
        }
    ],
    "sg:phone":"+1 631 348 5175",
    "sg:postcode":"11788",
    "sg:province":"NY",
    "wof:name":"Healing Edge Chiropractic",
    "wof:placetype":"venue"
},
  "geometry": {"coordinates":[-73.232181,40.804976],"type":"Point"}
}