{
  "type": "Feature",
  "properties": {
    "addr:full":"140 Pumphouse Rd Brewster NY 10509",
    "addr:housenumber":"140",
    "addr:postcode":"10509",
    "addr:street":"Pumphouse Rd",
    "iso:country":"US",
    "sg:address":"140 Pumphouse Rd",
    "sg:city":"Brewster",
    "sg:classifiers":[
        {
            "category":"Recreation",
            "type":"Entertainment"
        }
    ],
    "sg:phone":"+1 845 279 3915",
    "sg:postcode":"10509",
    "sg:province":"NY",
    "sg:tags":[
        "parks"
    ],
    "wof:name":"Southeast Recreation Dept",
    "wof:placetype":"venue"
},
  "geometry": {"coordinates":[-73.61351999999999,41.417429],"type":"Point"}
}