{
  "type": "Feature",
  "properties": {
    "iso:country":"US",
    "sg:address":"1755 Pitkin Ave",
    "sg:city":"Brooklyn",
    "sg:classifiers":[
        {
            "category":"Home & Garden",
            "subcategory":"Furniture",
            "type":"Retail Goods"
        }
    ],
    "sg:phone":"+1 718 385 5937",
    "sg:postcode":"11212",
    "sg:province":"NY",
    "wof:name":"Armstrong Furniture Corp",
    "wof:placetype":"venue"
},
  "geometry": {"coordinates":[-73.90842499999999,40.670084],"type":"Point"}
}