{
  "type": "Feature",
  "properties": {
    "addr:full":"7 W Prospect Ave Mt Vernon NY 10550",
    "addr:housenumber":"7",
    "addr:postcode":"10550",
    "addr:street":"W Prospect Ave",
    "iso:country":"US",
    "sg:address":"7 W Prospect Ave",
    "sg:city":"Mt Vernon",
    "sg:classifiers":[
        {
            "category":"Personal",
            "subcategory":"Beauty Salon",
            "type":"Services"
        }
    ],
    "sg:phone":"+1 914 699 5670",
    "sg:postcode":"10550",
    "sg:province":"NY",
    "wof:name":"African Store & Hair Braiding",
    "wof:placetype":"venue"
},
  "geometry": {"coordinates":[-73.838049,40.912781],"type":"Point"}
}