{
  "type": "Feature",
  "properties": {
    "addr:full":"900 South Avenue Staten Island NY 10314",
    "addr:housenumber":"900",
    "addr:postcode":"10314",
    "addr:street":"South Avenue",
    "iso:country":"US",
    "sg:address":"900 South Avenue",
    "sg:city":"Staten Island",
    "sg:classifiers":[
        {
            "category":"Wholesale",
            "subcategory":"Computers",
            "type":"Manufacturing & Wholesale Goods"
        }
    ],
    "sg:phone":"+1 718 568 3542",
    "sg:postcode":"10314",
    "sg:province":"NY",
    "wof:name":"Tech World Technology",
    "wof:placetype":"venue"
},
  "geometry": {"coordinates":[-74.17429,40.614078],"type":"Point"}
}