{
  "type": "Feature",
  "properties": {
    "addr:full":"2217 Crescent St Astoria NY 11105",
    "addr:housenumber":"2217",
    "addr:postcode":"11105",
    "addr:street":"Crescent St",
    "iso:country":"US",
    "sg:address":"2217 Crescent St",
    "sg:city":"Astoria",
    "sg:classifiers":[
        {
            "category":"Home & Garden",
            "subcategory":"Household Appliances",
            "type":"Retail Goods"
        },
        {
            "category":"Professional",
            "subcategory":"Engineering",
            "type":"Services"
        }
    ],
    "sg:phone":"+1 718 728 4417",
    "sg:postcode":"11105",
    "sg:province":"NY",
    "sg:tags":[
        "major",
        "system",
        "appliances-small",
        "equipment",
        "air conditioning"
    ],
    "wof:name":"Ihvac Corp",
    "wof:placetype":"venue"
},
  "geometry": {"coordinates":[-73.914552,40.778695],"type":"Point"}
}