{
  "type": "Feature",
  "properties": {
    "addr:full":"8 E 41st St New York NY 10017",
    "addr:housenumber":"8",
    "addr:postcode":"10017",
    "addr:street":"E 41St St",
    "iso:country":"US",
    "sg:address":"8 E 41st St",
    "sg:city":"New York",
    "sg:classifiers":[
        {
            "category":"Local Transit",
            "type":"Transportation"
        }
    ],
    "sg:phone":"+1 212 564 8484",
    "sg:postcode":"10017",
    "sg:province":"NY",
    "sg:tags":[
        "public"
    ],
    "wof:name":"Port Authority of New York & New Jersey",
    "wof:placetype":"venue"
},
  "geometry": {"coordinates":[-73.98110200000001,40.752602],"type":"Point"}
}