{
  "type": "Feature",
  "properties": {
    "iso:country":"US",
    "sg:address":"275 Bills Rd",
    "sg:city":"Macedon",
    "sg:classifiers":[
        {
            "category":"Building & Trades",
            "subcategory":"Landscaping Services",
            "type":"Services"
        }
    ],
    "sg:phone":"+1 585 388 9113",
    "sg:postcode":"14502",
    "sg:province":"NY",
    "sg:tags":[
        "consultant",
        "designer",
        "landscape",
        "contractor"
    ],
    "wof:name":"Wyse Landscaping",
    "wof:placetype":"venue"
},
  "geometry": {"coordinates":[-77.363664,43.148431],"type":"Point"}
}