{
  "type": "Feature",
  "properties": {
    "addr:full":"1518 Fillmore Ave Buffalo NY 14211",
    "addr:housenumber":"1518",
    "addr:postcode":"14211",
    "addr:street":"Fillmore Ave",
    "iso:country":"US",
    "sg:address":"1518 Fillmore Ave",
    "sg:city":"Buffalo",
    "sg:classifiers":[
        {
            "category":"Building & Trades",
            "subcategory":"Cleaning & Sanitation",
            "type":"Services"
        }
    ],
    "sg:phone":"+1 716 892 2355",
    "sg:postcode":"14211",
    "sg:province":"NY",
    "sg:tags":[
        "janitor"
    ],
    "wof:name":"Mc Cloud Maintenance Jntrl Svc",
    "wof:placetype":"venue"
},
  "geometry": {"coordinates":[-78.839229,42.915038],"type":"Point"}
}