{
  "type": "Feature",
  "properties": {
    "addr:full":"48 Otis St West Babylon NY 11704",
    "addr:housenumber":"48",
    "addr:postcode":"11704",
    "addr:street":"Otis St",
    "iso:country":"US",
    "sg:address":"48 Otis St",
    "sg:city":"West Babylon",
    "sg:classifiers":[
        {
            "category":"Wholesale",
            "subcategory":"Machinery & Supplies",
            "type":"Manufacturing & Wholesale Goods"
        },
        {
            "category":"Wholesale",
            "subcategory":"Hardware",
            "type":"Manufacturing & Wholesale Goods"
        }
    ],
    "sg:phone":"+1 631 491 5150",
    "sg:postcode":"11704",
    "sg:province":"NY",
    "sg:tags":[
        "plumbing",
        "valve",
        "merchandise"
    ],
    "wof:name":"Thermaquip Inc",
    "wof:placetype":"venue"
},
  "geometry": {"coordinates":[-73.375083,40.740164],"type":"Point"}
}