{
  "type": "Feature",
  "properties": {
    "addr:full":"139 N Fulton Ave Mount Vernon NY 10550",
    "addr:housenumber":"139",
    "addr:postcode":"10550",
    "addr:street":"N Fulton Ave",
    "iso:country":"US",
    "sg:address":"139 N Fulton Ave",
    "sg:city":"Mount Vernon",
    "sg:classifiers":[
        {
            "category":"Professional",
            "subcategory":"Lawyer & Legal Services",
            "type":"Services"
        }
    ],
    "sg:phone":"+1   ",
    "sg:postcode":"10550",
    "sg:province":"NY",
    "wof:name":"Heyward Law",
    "wof:placetype":"venue"
},
  "geometry": {"coordinates":[-73.82925,40.915406],"type":"Point"}
}