{
  "type": "Feature",
  "properties": {
    "iso:country":"US",
    "sg:address":"355 Crooked Hill Rd",
    "sg:city":"Brentwood",
    "sg:classifiers":[
        {
            "category":"Shopping",
            "type":"Retail Goods"
        }
    ],
    "sg:phone":"+1 631 273 9393",
    "sg:postcode":"11717",
    "sg:province":"NY",
    "sg:tags":[
        "pet",
        "shop"
    ],
    "sg:website":"www.allpet.com",
    "wof:name":"All Pet Distributors",
    "wof:placetype":"venue"
},
  "geometry": {"coordinates":[-73.268559,40.784923],"type":"Point"}
}