{
  "type": "Feature",
  "properties": {
    "iso:country":"US",
    "sg:address":"432 Sprout Brook Rd",
    "sg:city":"Garrison",
    "sg:classifiers":[
        {
            "category":"Professional",
            "subcategory":"Management & Consulting",
            "type":"Services"
        }
    ],
    "sg:phone":"+1   ",
    "sg:postcode":"10524",
    "sg:province":"NY",
    "sg:tags":[
        "public",
        "relations"
    ],
    "wof:name":"Web Publicity Co LLC",
    "wof:placetype":"venue"
},
  "geometry": {"coordinates":[-73.891724,41.354668],"type":"Point"}
}