{
  "type": "Feature",
  "properties": {
    "addr:full":"165 Hester St New York NY 10013",
    "addr:housenumber":"165",
    "addr:postcode":"10013",
    "addr:street":"Hester St",
    "iso:country":"US",
    "sg:address":"165 Hester St",
    "sg:city":"New York",
    "sg:classifiers":[
        {
            "category":"Restaurant",
            "type":"Food & Drink"
        }
    ],
    "sg:phone":"+1 212 925 0120",
    "sg:postcode":"10013",
    "sg:province":"NY",
    "wof:name":"Leung Hing Ming",
    "wof:placetype":"venue"
},
  "geometry": {"coordinates":[-73.99690699999999,40.71786],"type":"Point"}
}