{
  "type": "Feature",
  "properties": {
    "iso:country":"US",
    "sg:address":"355 S William St",
    "sg:city":"Newburgh",
    "sg:classifiers":[
        {
            "category":"Government",
            "subcategory":"Office",
            "type":"Public Place"
        }
    ],
    "sg:phone":"+1 845 569 9611",
    "sg:postcode":"12550",
    "sg:province":"NY",
    "sg:tags":[
        "national",
        "security"
    ],
    "wof:name":"B Battery",
    "wof:placetype":"venue"
},
  "geometry": {"coordinates":[-74.021914,41.496709],"type":"Point"}
}