{
  "type": "Feature",
  "properties": {
    "addr:full":"1323 School Rd Victor NY 14564",
    "addr:housenumber":"1323",
    "addr:postcode":"14564",
    "addr:street":"School Rd",
    "iso:country":"US",
    "sg:address":"1323 School Rd",
    "sg:city":"Victor",
    "sg:classifiers":[
        {
            "category":"Building & Trades",
            "subcategory":"Construction",
            "type":"Services"
        }
    ],
    "sg:phone":"+1 585 924 2587",
    "sg:postcode":"14564",
    "sg:province":"NY",
    "sg:tags":[
        "carpentry",
        "contractor"
    ],
    "wof:name":"Bw Carpntry Extrior Structures",
    "wof:placetype":"venue"
},
  "geometry": {"coordinates":[-77.42430899999999,42.961689],"type":"Point"}
}