{
  "type": "Feature",
  "properties": {
    "iso:country":"US",
    "sg:address":"3 Chevy Chase",
    "sg:city":"Amityville",
    "sg:classifiers":[
        {
            "category":"Building & Trades",
            "subcategory":"Cleaning & Sanitation",
            "type":"Services"
        }
    ],
    "sg:phone":"+1   ",
    "sg:postcode":"11701",
    "sg:province":"NY",
    "sg:tags":[
        "party",
        "planning"
    ],
    "wof:name":"Amme Innovative Services",
    "wof:placetype":"venue"
},
  "geometry": {"coordinates":[-73.406758,40.694878],"type":"Point"}
}