{
  "type": "Feature",
  "properties": {
    "addr:full":"1919 Hylan Blvd Staten Island NY 10305",
    "addr:housenumber":"1919",
    "addr:postcode":"10305",
    "addr:street":"Hylan Blvd",
    "iso:country":"US",
    "sg:address":"1919 Hylan Blvd",
    "sg:city":"Staten Island",
    "sg:classifiers":[
        {
            "category":"Home & Garden",
            "subcategory":"Furniture",
            "type":"Retail Goods"
        }
    ],
    "sg:phone":"+1 718 667 5906",
    "sg:postcode":"10305",
    "sg:province":"NY",
    "sg:tags":[
        "mattress"
    ],
    "wof:name":"Dial-A-Mattress",
    "wof:placetype":"venue"
},
  "geometry": {"coordinates":[-74.09653,40.582888],"type":"Point"}
}