{
  "type": "Feature",
  "properties": {
    "addr:full":"60 E 42nd St Rm 1753 New York NY 10165",
    "addr:housenumber":"60",
    "addr:postcode":"1753;10165",
    "addr:street":"E 42Nd St",
    "iso:country":"US",
    "sg:address":"60 E 42nd St Rm 1753",
    "sg:city":"New York",
    "sg:classifiers":[
        {
            "category":"Personal",
            "type":"Services"
        }
    ],
    "sg:phone":"+1 212 697 0428",
    "sg:postcode":"10165",
    "sg:province":"NY",
    "sg:tags":[
        "sewing",
        "alteration"
    ],
    "wof:name":"Mohan's",
    "wof:placetype":"venue"
},
  "geometry": {"coordinates":[-73.97930100000001,40.752102],"type":"Point"}
}