{
  "type": "Feature",
  "properties": {
    "iso:country":"US",
    "sg:address":"143 Troy Schenectady Rd",
    "sg:city":"Watervliet",
    "sg:classifiers":[
        {
            "category":"Shopping",
            "subcategory":"Jewelry",
            "type":"Retail Goods"
        },
        {
            "category":"Manufacturing",
            "subcategory":"Jewelry",
            "type":"Manufacturing & Wholesale Goods"
        },
        {
            "category":"Retail",
            "subcategory":"Repair Shop",
            "type":"Services"
        }
    ],
    "sg:phone":"+1 518 272 2000",
    "sg:postcode":"12189",
    "sg:province":"NY",
    "sg:tags":[
        "repairing",
        "stone",
        "designer",
        "clock",
        "jeweler",
        "precious",
        "semi-precious"
    ],
    "wof:name":"Top Custom Jewelers Inc",
    "wof:placetype":"venue"
},
  "geometry": {"coordinates":[-73.722843,42.736515],"type":"Point"}
}