{
  "type": "Feature",
  "properties": {
    "addr:full":"101 Harbour Ln Bay Shore NY 11706",
    "addr:housenumber":"101",
    "addr:postcode":"11706",
    "addr:street":"Harbour Ln",
    "iso:country":"US",
    "sg:address":"101 Harbour Ln",
    "sg:city":"Bay Shore",
    "sg:classifiers":[
        {
            "category":"Organizations",
            "subcategory":"Professional Association",
            "type":"Services"
        }
    ],
    "sg:phone":"+1   ",
    "sg:postcode":"11706",
    "sg:province":"NY",
    "wof:name":"Zonta International",
    "wof:placetype":"venue"
},
  "geometry": {"coordinates":[-73.25979,40.705999],"type":"Point"}
}