{
  "type": "Feature",
  "properties": {
    "iso:country":"US",
    "sg:address":"168 W Park Ave",
    "sg:city":"Long Beach",
    "sg:classifiers":[
        {
            "category":"Shopping",
            "subcategory":"News",
            "type":"Retail Goods"
        }
    ],
    "sg:phone":"+1 516 897 0900",
    "sg:postcode":"11561",
    "sg:province":"NY",
    "sg:tags":[
        "magazine"
    ],
    "wof:name":"Newlife Magazine",
    "wof:placetype":"venue"
},
  "geometry": {"coordinates":[-73.66824200000001,40.588386],"type":"Point"}
}