{
  "type": "Feature",
  "properties": {
    "addr:full":"3795 Richmond Ave Staten Island NY 10312",
    "addr:housenumber":"3795",
    "addr:postcode":"10312",
    "addr:street":"Richmond Ave",
    "iso:country":"US",
    "sg:address":"3795 Richmond Ave",
    "sg:city":"Staten Island",
    "sg:classifiers":[
        {
            "category":"Building & Trades",
            "subcategory":"Construction",
            "type":"Services"
        }
    ],
    "sg:phone":"+1 718 984 4084",
    "sg:postcode":"10312",
    "sg:province":"NY",
    "sg:tags":[
        "contractor"
    ],
    "wof:name":"Dial A Professional Contractor",
    "wof:placetype":"venue"
},
  "geometry": {"coordinates":[-74.16556799999999,40.545725],"type":"Point"}
}