{
  "type": "Feature",
  "properties": {
    "iso:country":"US",
    "sg:address":"407 E Main St",
    "sg:city":"Port Jefferson",
    "sg:classifiers":[
        {
            "category":"Professional",
            "subcategory":"Lawyer & Legal Services",
            "type":"Services"
        }
    ],
    "sg:phone":"+1 631 331 0642",
    "sg:postcode":"11777",
    "sg:province":"NY",
    "sg:tags":[
        "attorney"
    ],
    "wof:name":"Dennis Collins CP",
    "wof:placetype":"venue"
},
  "geometry": {"coordinates":[-73.067007,40.945422],"type":"Point"}
}