{
  "type": "Feature",
  "properties": {
    "addr:full":"10 Delancey St New York NY 10002",
    "addr:housenumber":"10",
    "addr:postcode":"10002",
    "addr:street":"Delancey St",
    "iso:country":"US",
    "sg:address":"10 Delancey St",
    "sg:city":"New York",
    "sg:classifiers":[
        {
            "category":"Manufacturing",
            "subcategory":"Signs",
            "type":"Manufacturing & Wholesale Goods"
        }
    ],
    "sg:phone":"+1   ",
    "sg:postcode":"10002",
    "sg:province":"NY",
    "sg:tags":[
        "mfg"
    ],
    "wof:name":"Aa Awning & Sign Supply",
    "wof:placetype":"venue"
},
  "geometry": {"coordinates":[-73.993213,40.720182],"type":"Point"}
}