{
  "type": "Feature",
  "properties": {
    "addr:full":"208 W 23rd St New York NY 10011",
    "addr:housenumber":"208",
    "addr:postcode":"10011",
    "addr:street":"W 23Rd St",
    "iso:country":"US",
    "sg:address":"208 W 23rd St",
    "sg:city":"New York",
    "sg:classifiers":[
        {
            "category":"Professional",
            "subcategory":"Management & Consulting",
            "type":"Services"
        }
    ],
    "sg:phone":"+1 212 243 4125",
    "sg:postcode":"10011",
    "sg:province":"NY",
    "wof:name":"Applied Systems Resources Inc",
    "wof:placetype":"venue"
},
  "geometry": {"coordinates":[-73.998347,40.745131],"type":"Point"}
}