{
  "type": "Feature",
  "properties": {
    "addr:full":"1385 Broadway New York NY 10018",
    "addr:housenumber":"1385",
    "addr:postcode":"10018",
    "addr:street":"Broadway",
    "iso:country":"US",
    "sg:address":"1385 Broadway",
    "sg:city":"New York",
    "sg:classifiers":[
        {
            "category":"Shopping",
            "subcategory":"Pharmacy",
            "type":"Retail Goods"
        }
    ],
    "sg:phone":"+1 212 575 6868",
    "sg:postcode":"10018",
    "sg:province":"NY",
    "sg:tags":[
        "drugstore"
    ],
    "wof:name":"Gideon's Drugs",
    "wof:placetype":"venue"
},
  "geometry": {"coordinates":[-73.987443,40.752476],"type":"Point"}
}