{
  "type": "Feature",
  "properties": {
    "iso:country":"US",
    "sg:address":"712 Washington Avenue Suite A",
    "sg:city":"Brooklyn",
    "sg:classifiers":[
        {
            "category":"Personal",
            "subcategory":"Beauty Salon",
            "type":"Services"
        }
    ],
    "sg:phone":"+1 718 953 5733",
    "sg:postcode":"11238",
    "sg:province":"NY",
    "sg:tags":[
        "hair"
    ],
    "wof:name":"Nu Wave Kultural Kreations",
    "wof:placetype":"venue"
},
  "geometry": {"coordinates":[-73.963555,40.676618],"type":"Point"}
}