{
  "type": "Feature",
  "properties": {
    "addr:full":"8781 State Rte 21 Naples NY 14512",
    "addr:housenumber":"8781",
    "addr:postcode":"14512",
    "addr:street":"State Rte 21",
    "iso:country":"US",
    "sg:address":"8781 State Rte 21",
    "sg:city":"Naples",
    "sg:classifiers":[
        {
            "category":"Shopping",
            "subcategory":"Computers & Home Electronics",
            "type":"Retail Goods"
        }
    ],
    "sg:phone":"+1 585 374 5872",
    "sg:postcode":"14512",
    "sg:province":"NY",
    "sg:tags":[
        "software"
    ],
    "wof:name":"Lambchop Software",
    "wof:placetype":"venue"
},
  "geometry": {"coordinates":[-77.42608199999999,42.597487],"type":"Point"}
}