{
  "type": "Feature",
  "properties": {
    "iso:country":"US",
    "sg:address":"1839 Flatbush Ave",
    "sg:city":"Brooklyn",
    "sg:classifiers":[
        {
            "category":"Travel",
            "subcategory":"Hotels & Motels",
            "type":"Entertainment"
        },
        {
            "category":"Travel",
            "subcategory":"Bed & Breakfast",
            "type":"Entertainment"
        }
    ],
    "sg:phone":"+1 718 484 3783",
    "sg:postcode":"11210",
    "sg:province":"NY",
    "wof:name":"Eve Bed And Breakfast",
    "wof:placetype":"venue"
},
  "geometry": {"coordinates":[-73.939294,40.625136],"type":"Point"}
}