{
  "type": "Feature",
  "properties": {
    "addr:full":"54 Riverside Dr New York NY 10024",
    "addr:housenumber":"54",
    "addr:postcode":"10024",
    "addr:street":"Riverside Dr",
    "iso:country":"US",
    "sg:address":"54 Riverside Dr",
    "sg:city":"New York",
    "sg:classifiers":[
        {
            "category":"Personal",
            "type":"Services"
        },
        {
            "category":"Retail",
            "subcategory":"Event Space",
            "type":"Services"
        }
    ],
    "sg:phone":"+1 646 736 7481",
    "sg:postcode":"10024",
    "sg:province":"NY",
    "sg:tags":[
        "planning",
        "venue",
        "wedding"
    ],
    "sg:website":"www.weddinginnewyork.net",
    "wof:name":"Wedding In New York",
    "wof:placetype":"venue"
},
  "geometry": {"coordinates":[-73.983082,40.784242],"type":"Point"}
}