{
  "type": "Feature",
  "properties": {
    "addr:full":"28 S Terminal Dr Plainview NY 11803",
    "addr:housenumber":"28",
    "addr:postcode":"11803",
    "addr:street":"S Terminal Dr",
    "iso:country":"US",
    "sg:address":"28 S Terminal Dr",
    "sg:city":"Plainview",
    "sg:classifiers":[
        {
            "category":"Health Services",
            "subcategory":"Medical Lab",
            "type":"Services"
        }
    ],
    "sg:phone":"+1 516 775 8103",
    "sg:postcode":"11803",
    "sg:province":"NY",
    "sg:tags":[
        "laboratory"
    ],
    "sg:website":"www.acupath.com",
    "wof:name":"Acupath Inc",
    "wof:placetype":"venue"
},
  "geometry": {"coordinates":[-73.46671600000001,40.790444],"type":"Point"}
}