{
  "type": "Feature",
  "properties": {
    "addr:full":"217 Christian Ave Stony Brook NY 11790",
    "addr:housenumber":"217",
    "addr:postcode":"11790",
    "addr:street":"Christian Ave",
    "iso:country":"US",
    "sg:address":"217 Christian Ave",
    "sg:city":"Stony Brook",
    "sg:classifiers":[
        {
            "category":"Organizations",
            "subcategory":"Religious Organization",
            "type":"Services"
        }
    ],
    "sg:phone":"+1 631 689 3404",
    "sg:postcode":"11790",
    "sg:province":"NY",
    "sg:tags":[
        "church"
    ],
    "wof:name":"Stonybrook Community Church",
    "wof:placetype":"venue"
},
  "geometry": {"coordinates":[-73.143878,40.923936],"type":"Point"}
}