{
  "type": "Feature",
  "properties": {
    "addr:full":"15 McKinley Ave Valhalla NY 10595",
    "addr:housenumber":"15",
    "addr:postcode":"10595",
    "addr:street":"Mckinley Ave",
    "iso:country":"US",
    "sg:address":"15 McKinley Ave",
    "sg:city":"Valhalla",
    "sg:classifiers":[
        {
            "category":"Taxi",
            "type":"Transportation"
        }
    ],
    "sg:phone":"+1   ",
    "sg:postcode":"10595",
    "sg:province":"NY",
    "sg:tags":[
        "taxicab"
    ],
    "wof:name":"Purchase Street Taxi",
    "wof:placetype":"venue"
},
  "geometry": {"coordinates":[-73.776583,41.070048],"type":"Point"}
}