{
  "type": "Feature",
  "properties": {
    "addr:full":"153 Hudson Ave Freeport NY 11520",
    "addr:housenumber":"153",
    "addr:postcode":"11520",
    "addr:street":"Hudson Ave",
    "iso:country":"US",
    "sg:address":"153 Hudson Ave",
    "sg:city":"Freeport",
    "sg:classifiers":[
        {
            "category":"Marine",
            "type":"Transportation"
        }
    ],
    "sg:phone":"+1 516 867 5103",
    "sg:postcode":"11520",
    "sg:province":"NY",
    "sg:tags":[
        "cleaning",
        "boat"
    ],
    "wof:name":"Waves & Wheels Inc",
    "wof:placetype":"venue"
},
  "geometry": {"coordinates":[-73.576868,40.635003],"type":"Point"}
}