{
  "type": "Feature",
  "properties": {
    "addr:full":"1 Ike Pl Woodmere NY 11598",
    "addr:housenumber":"1",
    "addr:postcode":"11598",
    "addr:street":"Ike Pl",
    "iso:country":"US",
    "sg:address":"1 Ike Pl",
    "sg:city":"Woodmere",
    "sg:classifiers":[
        {
            "category":"Professional",
            "subcategory":"Business Services",
            "type":"Services"
        }
    ],
    "sg:phone":"+1   ",
    "sg:postcode":"11598",
    "sg:province":"NY",
    "wof:name":"Phyllis & Elaine Interior",
    "wof:placetype":"venue"
},
  "geometry": {"coordinates":[-73.698418,40.627842],"type":"Point"}
}