{
  "type": "Feature",
  "properties": {
    "iso:country":"US",
    "sg:address":"706 Grand St",
    "sg:city":"Brooklyn",
    "sg:classifiers":[
        {
            "category":"Shopping",
            "subcategory":"Jewelry",
            "type":"Retail Goods"
        }
    ],
    "sg:phone":"+1 718 782 0619",
    "sg:postcode":"11211",
    "sg:province":"NY",
    "sg:tags":[
        "jeweler"
    ],
    "wof:name":"Grand Variety",
    "wof:placetype":"venue"
},
  "geometry": {"coordinates":[-73.944737,40.711462],"type":"Point"}
}