{
  "type": "Feature",
  "properties": {
    "iso:country":"US",
    "sg:address":"55 Ann Ave",
    "sg:city":"Riverhead",
    "sg:classifiers":[
        {
            "category":"Building & Trades",
            "subcategory":"Construction",
            "type":"Services"
        }
    ],
    "sg:phone":"+1 631 208 0940",
    "sg:postcode":"11901",
    "sg:province":"NY",
    "sg:tags":[
        "company"
    ],
    "wof:name":"Wildwood Home Construction Crp",
    "wof:placetype":"venue"
},
  "geometry": {"coordinates":[-72.67253700000001,40.89871],"type":"Point"}
}