{
  "type": "Feature",
  "properties": {
    "iso:country":"US",
    "sg:address":"120 E 56th St Ste 610",
    "sg:city":"New York",
    "sg:classifiers":[
        {
            "category":"Health Services",
            "subcategory":"Dentist",
            "type":"Services"
        }
    ],
    "sg:phone":"+1 212 826 2322",
    "sg:postcode":"10022",
    "sg:province":"NY",
    "sg:website":"www.park56dental.com",
    "wof:name":"Park 56 Dental Group",
    "wof:placetype":"venue"
},
  "geometry": {"coordinates":[-73.97054199999999,40.760573],"type":"Point"}
}