{
  "type": "Feature",
  "properties": {
    "addr:full":"4471 Walden Ave Lancaster NY 14086",
    "addr:housenumber":"4471",
    "addr:postcode":"14086",
    "addr:street":"Walden Ave",
    "iso:country":"US",
    "sg:address":"4471 Walden Ave",
    "sg:city":"Lancaster",
    "sg:classifiers":[
        {
            "category":"Manufacturing",
            "subcategory":"Chemicals & Compounds",
            "type":"Manufacturing & Wholesale Goods"
        }
    ],
    "sg:phone":"+1   ",
    "sg:postcode":"14086",
    "sg:province":"NY",
    "sg:tags":[
        "synthetic",
        "rubber",
        "mfg"
    ],
    "wof:name":"Silicone Products & Technology",
    "wof:placetype":"venue"
},
  "geometry": {"coordinates":[-78.603578,42.926525],"type":"Point"}
}