{
  "type": "Feature",
  "properties": {
    "addr:full":"265 E 30 St New York NY 10016",
    "addr:housenumber":"265;30",
    "addr:postcode":"10016",
    "addr:street":"E",
    "iso:country":"US",
    "sg:address":"265 E 30 St",
    "sg:city":"New York",
    "sg:classifiers":[
        {
            "category":"Home & Garden",
            "subcategory":"Carpets & Floor Coverings",
            "type":"Retail Goods"
        }
    ],
    "sg:phone":"+1   ",
    "sg:postcode":"10016",
    "sg:province":"NY",
    "wof:name":"Arpa Tomi Restorations",
    "wof:placetype":"venue"
},
  "geometry": {"coordinates":[-73.978768,40.742942],"type":"Point"}
}