{
  "type": "Feature",
  "properties": {
    "addr:full":"461 8th Ave New York NY 10001",
    "addr:housenumber":"461",
    "addr:postcode":"10001",
    "addr:street":"8Th Ave",
    "iso:country":"US",
    "sg:address":"461 8th Ave",
    "sg:city":"New York",
    "sg:classifiers":[
        {
            "category":"Deli",
            "type":"Food & Drink"
        }
    ],
    "sg:phone":"+1 212 868 9655",
    "sg:postcode":"10001",
    "sg:province":"NY",
    "sg:website":"www.stagedoordeli.com",
    "wof:name":"Stage Door Delicatessen",
    "wof:placetype":"venue"
},
  "geometry": {"coordinates":[-73.993797,40.751499],"type":"Point"}
}