{
  "type": "Feature",
  "properties": {
    "addr:full":"868 Route 9D Wappingers Falls NY 12590",
    "addr:housenumber":"868",
    "addr:postcode":"12590",
    "addr:street":"Route 9D",
    "iso:country":"US",
    "sg:address":"868 Route 9D",
    "sg:city":"Wappingers Falls",
    "sg:classifiers":[
        {
            "category":"Retail",
            "subcategory":"Auto Rental",
            "type":"Services"
        }
    ],
    "sg:phone":"+1 845 297 3100",
    "sg:postcode":"12590",
    "sg:province":"NY",
    "sg:tags":[
        "car"
    ],
    "sg:website":"www.enterprise.com",
    "wof:name":"Enterprise Rent-A Car",
    "wof:placetype":"venue"
},
  "geometry": {"coordinates":[-73.94381799999999,41.546284],"type":"Point"}
}