{
  "type": "Feature",
  "properties": {
    "addr:full":"273 Nassau Blvd Garden City NY 11530",
    "addr:housenumber":"273",
    "addr:postcode":"11530",
    "addr:street":"Nassau Blvd",
    "iso:country":"US",
    "sg:address":"273 Nassau Blvd",
    "sg:city":"Garden City",
    "sg:classifiers":[
        {
            "category":"Bars & Pubs",
            "type":"Food & Drink"
        }
    ],
    "sg:menulink":"http://www.allmenus.com/ny/garden-city/238908-j-p-mc-geevers-pub/menu/",
    "sg:phone":"+1 516 486 8929",
    "sg:postcode":"11530",
    "sg:province":"NY",
    "sg:tags":[
        "american"
    ],
    "wof:name":"J P Mc Geever's Pub",
    "wof:placetype":"venue"
},
  "geometry": {"coordinates":[-73.660668,40.734002],"type":"Point"}
}