{
  "type": "Feature",
  "properties": {
    "iso:country":"US",
    "sg:address":"273 E 10 St",
    "sg:city":"New York",
    "sg:classifiers":[
        {
            "category":"Professional",
            "type":"Services"
        }
    ],
    "sg:phone":"+1 212 673 5452",
    "sg:postcode":"10009",
    "sg:province":"NY",
    "sg:tags":[
        "establishment"
    ],
    "wof:name":"Alphaville Films",
    "wof:placetype":"venue"
},
  "geometry": {"coordinates":[-73.983215,40.728481],"type":"Point"}
}