{
  "type": "Feature",
  "properties": {
    "iso:country":"US",
    "sg:address":"55 Brightonwood Rd",
    "sg:city":"Glenmont",
    "sg:classifiers":[
        {
            "category":"Health Services",
            "subcategory":"Doctor",
            "type":"Services"
        }
    ],
    "sg:phone":"+1 518 478 0216",
    "sg:postcode":"12077",
    "sg:province":"NY",
    "sg:tags":[
        "psychologist"
    ],
    "wof:name":"Oskar R Harmon Phd",
    "wof:placetype":"venue"
},
  "geometry": {"coordinates":[-73.808483,42.599051],"type":"Point"}
}