{
  "type": "Feature",
  "properties": {
    "iso:country":"US",
    "sg:address":"25 Taylor Ave",
    "sg:city":"East Islip",
    "sg:classifiers":[
        {
            "category":"Building & Trades",
            "subcategory":"Construction",
            "type":"Services"
        }
    ],
    "sg:phone":"+1 631 224 5182",
    "sg:postcode":"11730",
    "sg:province":"NY",
    "sg:tags":[
        "house"
    ],
    "wof:name":"Ron A Bilello Construction",
    "wof:placetype":"venue"
},
  "geometry": {"coordinates":[-73.197205,40.739381],"type":"Point"}
}