{
  "type": "Feature",
  "properties": {
    "iso:country":"US",
    "sg:address":"568 Coburn St",
    "sg:city":"Elmira",
    "sg:classifiers":[
        {
            "category":"Wholesale",
            "subcategory":"Non-durable Goods",
            "type":"Manufacturing & Wholesale Goods"
        }
    ],
    "sg:phone":"+1 607 734 0098",
    "sg:postcode":"14904",
    "sg:province":"NY",
    "wof:name":"Roger Wich",
    "wof:placetype":"venue"
},
  "geometry": {"coordinates":[-76.813974,42.076319],"type":"Point"}
}