{
  "type": "Feature",
  "properties": {
    "addr:full":"360 Lexington Ave Lbby New York NY 10017",
    "addr:housenumber":"360",
    "addr:postcode":"10017",
    "addr:street":"Lexington Ave",
    "iso:country":"US",
    "sg:address":"360 Lexington Ave Lbby",
    "sg:city":"New York",
    "sg:classifiers":[
        {
            "category":"Professional",
            "subcategory":"Lawyer & Legal Services",
            "type":"Services"
        }
    ],
    "sg:phone":"+1 212 757 8000",
    "sg:postcode":"10017",
    "sg:province":"NY",
    "wof:name":"Negin Jay Atty",
    "wof:placetype":"venue"
},
  "geometry": {"coordinates":[-73.976601,40.750599],"type":"Point"}
}