{
  "type": "Feature",
  "properties": {
    "iso:country":"US",
    "sg:address":"879 Madison Ave",
    "sg:city":"Albany",
    "sg:classifiers":[
        {
            "category":"Health Services",
            "subcategory":"Chiropractor",
            "type":"Services"
        }
    ],
    "sg:phone":"+1 518 465 3331",
    "sg:postcode":"12208",
    "sg:province":"NY",
    "wof:name":"Albany Central Chiropractic",
    "wof:placetype":"venue"
},
  "geometry": {"coordinates":[-73.783198,42.661218],"type":"Point"}
}