{
  "type": "Feature",
  "properties": {
    "iso:country":"US",
    "sg:address":"40 W Oak St",
    "sg:city":"Farmingdale",
    "sg:classifiers":[
        {
            "category":"Professional",
            "type":"Services"
        }
    ],
    "sg:phone":"+1   ",
    "sg:postcode":"11735",
    "sg:province":"NY",
    "wof:name":"Brub Corp",
    "wof:placetype":"venue"
},
  "geometry": {"coordinates":[-73.463053,40.724246],"type":"Point"}
}