{
  "type": "Feature",
  "properties": {
    "iso:country":"US",
    "sg:address":"5710 Seneca St",
    "sg:city":"West Seneca",
    "sg:classifiers":[
        {
            "category":"Autos & Motor Vehicles",
            "subcategory":"Recreational Vehicle Sales",
            "type":"Retail Goods"
        }
    ],
    "sg:phone":"+1 716 675 6600",
    "sg:postcode":"14224",
    "sg:province":"NY",
    "sg:tags":[
        "canopy",
        "shell",
        "truck",
        "cap"
    ],
    "wof:name":"Van City LLC",
    "wof:placetype":"venue"
},
  "geometry": {"coordinates":[-78.788618,42.848034],"type":"Point"}
}