{
  "type": "Feature",
  "properties": {
    "iso:country":"US",
    "sg:address":"611 2 St",
    "sg:city":"Greenport",
    "sg:classifiers":[
        {
            "category":"Building & Trades",
            "subcategory":"Landscaping Services",
            "type":"Services"
        }
    ],
    "sg:phone":"+1 631 477 2158",
    "sg:postcode":"11944",
    "sg:province":"NY",
    "sg:tags":[
        "lawn",
        "care"
    ],
    "wof:name":"Oscar L Shedreick",
    "wof:placetype":"venue"
},
  "geometry": {"coordinates":[-72.36215799999999,41.103193],"type":"Point"}
}