{
  "type": "Feature",
  "properties": {
    "addr:full":"118 Franklin St Watertown NY 13601",
    "addr:housenumber":"118",
    "addr:postcode":"13601",
    "addr:street":"Franklin St",
    "iso:country":"US",
    "sg:address":"118 Franklin St",
    "sg:city":"Watertown",
    "sg:classifiers":[
        {
            "category":"Social Services",
            "type":"Services"
        }
    ],
    "sg:phone":"+1 315 782 4493",
    "sg:postcode":"13601",
    "sg:province":"NY",
    "wof:name":"Christian Care Center",
    "wof:placetype":"venue"
},
  "geometry": {"coordinates":[-75.909491,43.973992],"type":"Point"}
}