{
  "type": "Feature",
  "properties": {
    "addr:full":"269 Lindsley Rd Rushville NY 14544",
    "addr:housenumber":"269",
    "addr:postcode":"14544",
    "addr:street":"Lindsley Rd",
    "iso:country":"US",
    "sg:address":"269 Lindsley Rd",
    "sg:city":"Rushville",
    "sg:classifiers":[
        {
            "category":"Utilities",
            "subcategory":"Telephone",
            "type":"Services"
        }
    ],
    "sg:phone":"+1   ",
    "sg:postcode":"14544",
    "sg:province":"NY",
    "sg:tags":[
        "communications"
    ],
    "wof:name":"Tumerianet",
    "wof:placetype":"venue"
},
  "geometry": {"coordinates":[-77.256568,42.751083],"type":"Point"}
}