{
  "type": "Feature",
  "properties": {
    "addr:full":"105 Brookview Dr Liverpool NY 13088",
    "addr:housenumber":"105",
    "addr:postcode":"13088",
    "addr:street":"Brookview Dr",
    "iso:country":"US",
    "sg:address":"105 Brookview Dr",
    "sg:city":"Liverpool",
    "sg:classifiers":[
        {
            "category":"Education",
            "subcategory":"Dance Studio",
            "type":"Public Place"
        }
    ],
    "sg:phone":"+1 315 697 8295",
    "sg:postcode":"13088",
    "sg:province":"NY",
    "sg:tags":[
        "instruction",
        "dancing"
    ],
    "wof:name":"D K Dance Ctr",
    "wof:placetype":"venue"
},
  "geometry": {"coordinates":[-76.19578199999999,43.103097],"type":"Point"}
}