{
  "type": "Feature",
  "properties": {
    "addr:full":"601 Coates Ave Holbrook NY 11741",
    "addr:housenumber":"601",
    "addr:postcode":"11741",
    "addr:street":"Coates Ave",
    "iso:country":"US",
    "sg:address":"601 Coates Ave",
    "sg:city":"Holbrook",
    "sg:classifiers":[
        {
            "category":"Wholesale",
            "subcategory":"Machinery & Supplies",
            "type":"Manufacturing & Wholesale Goods"
        }
    ],
    "sg:phone":"+1 631 563 7600",
    "sg:postcode":"11741",
    "sg:province":"NY",
    "sg:tags":[
        "equipment"
    ],
    "wof:name":"Edward Ehrbar Inc",
    "wof:placetype":"venue"
},
  "geometry": {"coordinates":[-73.078638,40.780514],"type":"Point"}
}