{
  "type": "Feature",
  "properties": {
    "addr:full":"221 Buffalo St Hamburg NY 14075",
    "addr:housenumber":"221",
    "addr:postcode":"14075",
    "addr:street":"Buffalo St",
    "iso:country":"US",
    "sg:address":"221 Buffalo St",
    "sg:city":"Hamburg",
    "sg:classifiers":[
        {
            "category":"Food & Beverages",
            "subcategory":"Bakery",
            "type":"Retail Goods"
        }
    ],
    "sg:phone":"+1 716 649 4099",
    "sg:postcode":"14075",
    "sg:province":"NY",
    "sg:tags":[
        "baker"
    ],
    "wof:name":"Great Harvest Bread",
    "wof:placetype":"venue"
},
  "geometry": {"coordinates":[-78.826398,42.720932],"type":"Point"}
}