{
  "type": "Feature",
  "properties": {
    "iso:country":"US",
    "sg:address":"257 Carleton Ave",
    "sg:city":"East Islip",
    "sg:classifiers":[
        {
            "category":"Shopping",
            "subcategory":"Tobacco",
            "type":"Retail Goods"
        }
    ],
    "sg:phone":"+1 631 224 4074",
    "sg:postcode":"11730",
    "sg:province":"NY",
    "sg:tags":[
        "shop"
    ],
    "wof:name":"Yildiz Dstrbtrs Inc",
    "wof:placetype":"venue"
},
  "geometry": {"coordinates":[-73.193001,40.742699],"type":"Point"}
}