{
  "type": "Feature",
  "properties": {
    "iso:country":"US",
    "sg:address":"4205 US Hwy 209",
    "sg:city":"Stone Ridge",
    "sg:classifiers":[
        {
            "category":"Home & Garden",
            "subcategory":"Garden Supply",
            "type":"Retail Goods"
        }
    ],
    "sg:phone":"+1   ",
    "sg:postcode":"12484",
    "sg:province":"NY",
    "sg:tags":[
        "repair",
        "lawn",
        "equipment"
    ],
    "wof:name":"G & G House of Wheels Inc",
    "wof:placetype":"venue"
},
  "geometry": {"coordinates":[-74.165674,41.831295],"type":"Point"}
}