{
  "type": "Feature",
  "properties": {
    "addr:full":"23 John St Lynbrook NY 11563",
    "addr:housenumber":"23",
    "addr:postcode":"11563",
    "addr:street":"John St",
    "iso:country":"US",
    "sg:address":"23 John St",
    "sg:city":"Lynbrook",
    "sg:classifiers":[
        {
            "category":"Building & Trades",
            "subcategory":"Landscaping Services",
            "type":"Services"
        }
    ],
    "sg:phone":"+1 516 599 1418",
    "sg:postcode":"11563",
    "sg:province":"NY",
    "sg:tags":[
        "landscape"
    ],
    "wof:name":"Associated Landscaping Inc",
    "wof:placetype":"venue"
},
  "geometry": {"coordinates":[-73.679025,40.657661],"type":"Point"}
}