{
  "type": "Feature",
  "properties": {
    "iso:country":"US",
    "sg:address":"1098 E 92nd St",
    "sg:city":"Brooklyn",
    "sg:classifiers":[
        {
            "category":"Building & Trades",
            "subcategory":"Cleaning & Sanitation",
            "type":"Services"
        }
    ],
    "sg:phone":"+1 516 884 0696",
    "sg:postcode":"11236",
    "sg:province":"NY",
    "sg:tags":[
        "duct",
        "air"
    ],
    "wof:name":"Latino Hood And Duct Clea",
    "wof:placetype":"venue"
},
  "geometry": {"coordinates":[-73.906013,40.642306],"type":"Point"}
}