{
  "type": "Feature",
  "properties": {
    "addr:full":"265 W Main St Babylon NY 11702",
    "addr:housenumber":"265",
    "addr:postcode":"11702",
    "addr:street":"W Main St",
    "iso:country":"US",
    "sg:address":"265 W Main St",
    "sg:city":"Babylon",
    "sg:classifiers":[
        {
            "category":"Building & Trades",
            "subcategory":"Construction",
            "type":"Services"
        }
    ],
    "sg:phone":"+1 631 669 3236",
    "sg:postcode":"11702",
    "sg:province":"NY",
    "sg:tags":[
        "contractor"
    ],
    "wof:name":"Barbash Associates",
    "wof:placetype":"venue"
},
  "geometry": {"coordinates":[-73.330275,40.694469],"type":"Point"}
}