{
  "type": "Feature",
  "properties": {
    "iso:country":"US",
    "sg:address":"7 S Broadway",
    "sg:city":"White Plains",
    "sg:classifiers":[
        {
            "category":"Health Services",
            "subcategory":"Doctor",
            "type":"Services"
        }
    ],
    "sg:phone":"+1 914 948 2600",
    "sg:postcode":"10601",
    "sg:province":"NY",
    "sg:tags":[
        "physician",
        "surgeon"
    ],
    "wof:name":"Birgit Elias MD",
    "wof:placetype":"venue"
},
  "geometry": {"coordinates":[-73.762277,41.0324],"type":"Point"}
}