{
  "type": "Feature",
  "properties": {
    "addr:full":"3148 Valhalla Dr Bronx NY 10465",
    "addr:housenumber":"3148",
    "addr:postcode":"10465",
    "addr:street":"Valhalla Dr",
    "iso:country":"US",
    "sg:address":"3148 Valhalla Dr",
    "sg:city":"Bronx",
    "sg:classifiers":[
        {
            "category":"Building & Trades",
            "subcategory":"Construction",
            "type":"Services"
        }
    ],
    "sg:phone":"+1 800 854 5994",
    "sg:postcode":"10465",
    "sg:province":"NY",
    "sg:tags":[
        "contractor"
    ],
    "wof:name":"Chiappetta Joe Contracting",
    "wof:placetype":"venue"
},
  "geometry": {"coordinates":[-73.823303,40.840599],"type":"Point"}
}