{
  "type": "Feature",
  "properties": {
    "iso:country":"US",
    "sg:address":"1966 Broad Hollow Rd",
    "sg:city":"Farmingdale",
    "sg:classifiers":[
        {
            "category":"Autos & Motor Vehicles",
            "subcategory":"Auto Supplies",
            "type":"Retail Goods"
        }
    ],
    "sg:phone":"+1 631 454 0550",
    "sg:postcode":"11735",
    "sg:province":"NY",
    "sg:tags":[
        "automobile",
        "parts"
    ],
    "wof:name":"Husslein Auto Parts & Supplies",
    "wof:placetype":"venue"
},
  "geometry": {"coordinates":[-73.422365,40.745992],"type":"Point"}
}