{
  "type": "Feature",
  "properties": {
    "addr:full":"770 Broadway New York NY 10003",
    "addr:housenumber":"770",
    "addr:postcode":"10003",
    "addr:street":"Broadway",
    "iso:country":"US",
    "sg:address":"770 Broadway",
    "sg:city":"New York",
    "sg:classifiers":[
        {
            "category":"Professional",
            "subcategory":"Employment Agencies",
            "type":"Services"
        }
    ],
    "sg:phone":"+1 212 228 7668",
    "sg:postcode":"10003",
    "sg:province":"NY",
    "wof:name":"Officeteam",
    "wof:placetype":"venue"
},
  "geometry": {"coordinates":[-73.991997,40.731098],"type":"Point"}
}