{
  "type": "Feature",
  "properties": {
    "addr:full":"299 Crown St Brooklyn NY 11225",
    "addr:housenumber":"299",
    "addr:postcode":"11225",
    "addr:street":"Crown St",
    "iso:country":"US",
    "sg:address":"299 Crown St",
    "sg:city":"Brooklyn",
    "sg:classifiers":[
        {
            "category":"Organizations",
            "subcategory":"Religious Organization",
            "type":"Services"
        }
    ],
    "sg:phone":"+1 718 363 8417",
    "sg:postcode":"11225",
    "sg:province":"NY",
    "sg:tags":[
        "synagogue"
    ],
    "wof:name":"Nota Kuperman",
    "wof:placetype":"venue"
},
  "geometry": {"coordinates":[-73.948961,40.666278],"type":"Point"}
}