{
  "type": "Feature",
  "properties": {
    "iso:country":"US",
    "sg:address":"81 Washington St",
    "sg:city":"Brooklyn",
    "sg:classifiers":[
        {
            "category":"Professional",
            "type":"Services"
        }
    ],
    "sg:phone":"+1 718 596 6700",
    "sg:postcode":"11201",
    "sg:province":"NY",
    "sg:tags":[
        "sculptor"
    ],
    "wof:name":"Paige Bradley Fine Art",
    "wof:placetype":"venue"
},
  "geometry": {"coordinates":[-73.98957799999999,40.702184],"type":"Point"}
}