{
  "type": "Feature",
  "properties": {
    "iso:country":"US",
    "sg:address":"239 N Main St",
    "sg:city":"Sayville",
    "sg:classifiers":[
        {
            "category":"Restaurant",
            "type":"Food & Drink"
        }
    ],
    "sg:phone":"+1 631 589 8822",
    "sg:postcode":"11782",
    "sg:province":"NY",
    "wof:name":"Taste Of China",
    "wof:placetype":"venue"
},
  "geometry": {"coordinates":[-73.079403,40.739906],"type":"Point"}
}