{
  "type": "Feature",
  "properties": {
    "addr:full":"81 Mott Street New York NY 10013",
    "addr:housenumber":"81",
    "addr:postcode":"10013",
    "addr:street":"Mott Street",
    "iso:country":"US",
    "sg:address":"81 Mott Street",
    "sg:city":"New York",
    "sg:classifiers":[
        {
            "category":"Restaurant",
            "type":"Food & Drink"
        }
    ],
    "sg:phone":"+1 212 374 1312",
    "sg:postcode":"10013",
    "sg:province":"NY",
    "wof:name":"Double Hey Restrnt",
    "wof:placetype":"venue"
},
  "geometry": {"coordinates":[-73.99801600000001,40.716456],"type":"Point"}
}