{
  "type": "Feature",
  "properties": {
    "iso:country":"US",
    "sg:address":"531 Farber Lakes Dr",
    "sg:city":"Buffalo",
    "sg:classifiers":[
        {
            "category":"Health Services",
            "subcategory":"Doctor",
            "type":"Services"
        }
    ],
    "sg:phone":"+1 716 204 9080",
    "sg:postcode":"14221",
    "sg:province":"NY",
    "sg:tags":[
        "physician",
        "surgeon"
    ],
    "wof:name":"Joseph A Murphy MD",
    "wof:placetype":"venue"
},
  "geometry": {"coordinates":[-78.73258199999999,42.976185],"type":"Point"}
}