{
  "type": "Feature",
  "properties": {
    "iso:country":"US",
    "sg:address":"4380 Heritage Dr",
    "sg:city":"Liverpool",
    "sg:classifiers":[
        {
            "category":"Wholesale",
            "subcategory":"Fruits & Vegetables",
            "type":"Manufacturing & Wholesale Goods"
        }
    ],
    "sg:phone":"+1 315 622 6697",
    "sg:postcode":"13090",
    "sg:province":"NY",
    "wof:name":"Dirubbo Produce Co",
    "wof:placetype":"venue"
},
  "geometry": {"coordinates":[-76.209774,43.151413],"type":"Point"}
}