{
  "type": "Feature",
  "properties": {
    "addr:full":"1109 Bellmore Rd North Bellmore NY 11710",
    "addr:housenumber":"1109",
    "addr:postcode":"11710",
    "addr:street":"Bellmore Rd",
    "iso:country":"US",
    "sg:address":"1109 Bellmore Rd",
    "sg:city":"North Bellmore",
    "sg:classifiers":[
        {
            "category":"Banks & Credit Unions",
            "subcategory":"Investment Brokerage",
            "type":"Services"
        }
    ],
    "sg:phone":"+1 516 785 1550",
    "sg:postcode":"11710",
    "sg:province":"NY",
    "sg:tags":[
        "advisory",
        "financial"
    ],
    "wof:name":"Secreast Financial",
    "wof:placetype":"venue"
},
  "geometry": {"coordinates":[-73.53357200000001,40.693421],"type":"Point"}
}