{
  "type": "Feature",
  "properties": {
    "addr:full":"6 E 45th Street New York NY 10017",
    "addr:housenumber":"6",
    "addr:postcode":"10017",
    "addr:street":"E 45Th Street",
    "iso:country":"US",
    "sg:address":"6 E 45th Street",
    "sg:city":"New York",
    "sg:classifiers":[
        {
            "category":"Professional",
            "subcategory":"Employment Agencies",
            "type":"Services"
        }
    ],
    "sg:phone":"+1 212 557 1354",
    "sg:postcode":"10017",
    "sg:province":"NY",
    "wof:name":"Advisor's Education Group",
    "wof:placetype":"venue"
},
  "geometry": {"coordinates":[-73.97892400000001,40.755164],"type":"Point"}
}