{
  "type": "Feature",
  "properties": {
    "iso:country":"US",
    "sg:address":"4276 Saint Francis Dr",
    "sg:city":"Hamburg",
    "sg:classifiers":[
        {
            "category":"Shopping",
            "subcategory":"Bicycles & Sporting Goods",
            "type":"Retail Goods"
        }
    ],
    "sg:phone":"+1   ",
    "sg:postcode":"14075",
    "sg:province":"NY",
    "sg:website":"www.curtissportconnection.com",
    "wof:name":"Curtis Sport Connection",
    "wof:placetype":"venue"
},
  "geometry": {"coordinates":[-78.86563200000001,42.767386],"type":"Point"}
}