{
  "type": "Feature",
  "properties": {
    "addr:full":"10 W 33rd St Rm 1122 New York NY 10001",
    "addr:housenumber":"10",
    "addr:postcode":"1122;10001",
    "addr:street":"W 33Rd St",
    "iso:country":"US",
    "sg:address":"10 W 33rd St Rm 1122",
    "sg:city":"New York",
    "sg:classifiers":[
        {
            "category":"Arts & Performance",
            "subcategory":"Arts Center",
            "type":"Entertainment"
        }
    ],
    "sg:phone":"+1 212 244 1045",
    "sg:postcode":"10001",
    "sg:province":"NY",
    "sg:tags":[
        "performing"
    ],
    "wof:name":"Elegant Headwear Company",
    "wof:placetype":"venue"
},
  "geometry": {"coordinates":[-73.985348,40.747747],"type":"Point"}
}