{
  "type": "Feature",
  "properties": {
    "iso:country":"US",
    "sg:address":"9 Cornelius Ln",
    "sg:city":"Baldwin Place",
    "sg:classifiers":[
        {
            "category":"Professional",
            "subcategory":"Computer Services",
            "type":"Services"
        }
    ],
    "sg:phone":"+1   ",
    "sg:postcode":"10505",
    "sg:province":"NY",
    "sg:tags":[
        "related"
    ],
    "wof:name":"Protech It Consultant",
    "wof:placetype":"venue"
},
  "geometry": {"coordinates":[-73.74540500000001,41.345046],"type":"Point"}
}