{
  "type": "Feature",
  "properties": {
    "addr:full":"743 Busti-Sugar Grove Rd Jamestown NY 14701",
    "addr:housenumber":"743",
    "addr:postcode":"14701",
    "addr:street":"Busti-Sugar Grove Rd",
    "iso:country":"US",
    "sg:address":"743 Busti-Sugar Grove Rd",
    "sg:city":"Jamestown",
    "sg:classifiers":[
        {
            "category":"Food & Beverages",
            "subcategory":"Candy",
            "type":"Retail Goods"
        },
        {
            "category":"Manufacturing",
            "subcategory":"Food",
            "type":"Manufacturing & Wholesale Goods"
        }
    ],
    "sg:phone":"+1 716 487 1595",
    "sg:postcode":"14701",
    "sg:province":"NY",
    "sg:tags":[
        "mfr",
        "confectionery"
    ],
    "wof:name":"Peterson's Candies",
    "wof:placetype":"venue"
},
  "geometry": {"coordinates":[-79.29428299999999,42.029652],"type":"Point"}
}