{
  "type": "Feature",
  "properties": {
    "addr:full":"3600 Brewerton Rd Syracuse NY 13211",
    "addr:housenumber":"3600",
    "addr:postcode":"13211",
    "addr:street":"Brewerton Rd",
    "iso:country":"US",
    "sg:address":"3600 Brewerton Rd",
    "sg:city":"Syracuse",
    "sg:classifiers":[
        {
            "category":"Personal",
            "subcategory":"Beauty Salon",
            "type":"Services"
        }
    ],
    "sg:phone":"+1 315 455 5883",
    "sg:postcode":"13211",
    "sg:province":"NY",
    "sg:tags":[
        "shop"
    ],
    "wof:name":"Northern Hair Design",
    "wof:placetype":"venue"
},
  "geometry": {"coordinates":[-76.14552500000001,43.115136],"type":"Point"}
}