{
  "type": "Feature",
  "properties": {
    "iso:country":"US",
    "sg:address":"242 W 36th Street Lbby",
    "sg:city":"New York",
    "sg:classifiers":[
        {
            "category":"Shopping",
            "subcategory":"Thrift Store",
            "type":"Retail Goods"
        }
    ],
    "sg:phone":"+1 212 564 6650",
    "sg:postcode":"10018",
    "sg:province":"NY",
    "wof:name":"What Goes Around Comes Around",
    "wof:placetype":"venue"
},
  "geometry": {"coordinates":[-73.99093000000001,40.752781],"type":"Point"}
}