{
  "type": "Feature",
  "properties": {
    "iso:country":"US",
    "sg:address":"26 Schrempp Ln",
    "sg:city":"Pine Bush",
    "sg:classifiers":[
        {
            "category":"Building & Trades",
            "subcategory":"Construction",
            "type":"Services"
        }
    ],
    "sg:phone":"+1 845 744 4866",
    "sg:postcode":"12566",
    "sg:province":"NY",
    "sg:tags":[
        "home",
        "improvement"
    ],
    "wof:name":"A & C Home Improvement",
    "wof:placetype":"venue"
},
  "geometry": {"coordinates":[-74.296274,41.623087],"type":"Point"}
}