{
  "type": "Feature",
  "properties": {
    "addr:full":"330 E 53rd St New York NY 10022",
    "addr:housenumber":"330",
    "addr:postcode":"10022",
    "addr:street":"E 53Rd St",
    "iso:country":"US",
    "sg:address":"330 E 53rd St",
    "sg:city":"New York",
    "sg:classifiers":[
        {
            "category":"Shopping",
            "subcategory":"Pets & Pet Supplies",
            "type":"Retail Goods"
        },
        {
            "category":"Retail",
            "subcategory":"Pet Boarding",
            "type":"Services"
        }
    ],
    "sg:phone":"+1 212 471 0228",
    "sg:postcode":"10022",
    "sg:province":"NY",
    "sg:tags":[
        "boarding/pet",
        "store",
        "sitting"
    ],
    "sg:website":"www.birdcamp.com",
    "wof:name":"Bird Camp",
    "wof:placetype":"venue"
},
  "geometry": {"coordinates":[-73.966499,40.756302],"type":"Point"}
}