{
  "type": "Feature",
  "properties": {
    "addr:full":"29 Vatrano Rd Albany NY 12205",
    "addr:housenumber":"29",
    "addr:postcode":"12205",
    "addr:street":"Vatrano Rd",
    "iso:country":"US",
    "sg:address":"29 Vatrano Rd",
    "sg:city":"Albany",
    "sg:classifiers":[
        {
            "category":"Shopping",
            "subcategory":"Bicycles & Sporting Goods",
            "type":"Retail Goods"
        }
    ],
    "sg:phone":"+1 518 482 9396",
    "sg:postcode":"12205",
    "sg:province":"NY",
    "wof:name":"Sussers Sporting Goods",
    "wof:placetype":"venue"
},
  "geometry": {"coordinates":[-73.794858,42.687991],"type":"Point"}
}