{
  "type": "Feature",
  "properties": {
    "iso:country":"US",
    "sg:address":"4244 Ridge Lea Rd Ste 47",
    "sg:city":"Buffalo",
    "sg:classifiers":[
        {
            "category":"Health Services",
            "subcategory":"Doctor",
            "type":"Services"
        },
        {
            "category":"Health Services",
            "subcategory":"Hospital",
            "type":"Services"
        }
    ],
    "sg:phone":"+1 716 836 0653",
    "sg:postcode":"14226",
    "sg:province":"NY",
    "sg:tags":[
        "consultant",
        "medical",
        "practice",
        "nursing",
        "home"
    ],
    "sg:website":"http://www.medgassystems.com",
    "wof:name":"Medical Gas System Solutions Inc",
    "wof:placetype":"venue"
},
  "geometry": {"coordinates":[-78.81432100000001,43.000118],"type":"Point"}
}