{
  "type": "Feature",
  "properties": {
    "iso:country":"US",
    "sg:address":"30 Howard Pl",
    "sg:city":"Ronkonkoma",
    "sg:classifiers":[
        {
            "category":"Building & Trades",
            "subcategory":"Electrical",
            "type":"Services"
        },
        {
            "category":"Wholesale",
            "subcategory":"Electrical",
            "type":"Manufacturing & Wholesale Goods"
        }
    ],
    "sg:phone":"+1 631 467 7799",
    "sg:postcode":"11779",
    "sg:province":"NY",
    "sg:tags":[
        "control",
        "management",
        "installs",
        "energy",
        "system",
        "design"
    ],
    "wof:name":"Control Concepts II",
    "wof:placetype":"venue"
},
  "geometry": {"coordinates":[-73.115261,40.795488],"type":"Point"}
}