{
  "type": "Feature",
  "properties": {
    "addr:full":"232 E 59th St New York NY 10022",
    "addr:housenumber":"232",
    "addr:postcode":"10022",
    "addr:street":"E 59Th St",
    "iso:country":"US",
    "sg:address":"232 E 59th St",
    "sg:city":"New York",
    "sg:classifiers":[
        {
            "category":"Shopping",
            "subcategory":"Crafts & Fabrics",
            "type":"Retail Goods"
        }
    ],
    "sg:phone":"+1 212 223 0373",
    "sg:postcode":"10022",
    "sg:province":"NY",
    "sg:tags":[
        "store"
    ],
    "sg:website":"www.bennisonfabrics.com",
    "wof:name":"Bennison Fabrics Inc",
    "wof:placetype":"venue"
},
  "geometry": {"coordinates":[-73.96579699999999,40.7612],"type":"Point"}
}