{
  "type": "Feature",
  "properties": {
    "addr:full":"777 Broadway Amityville NY 11701",
    "addr:housenumber":"777",
    "addr:postcode":"11701",
    "addr:street":"Broadway",
    "iso:country":"US",
    "sg:address":"777 Broadway",
    "sg:city":"Amityville",
    "sg:classifiers":[
        {
            "category":"Restaurant",
            "type":"Food & Drink"
        }
    ],
    "sg:phone":"+1 631 789 6990",
    "sg:postcode":"11701",
    "sg:province":"NY",
    "wof:name":"Brothers Pizza & Pasta",
    "wof:placetype":"venue"
},
  "geometry": {"coordinates":[-73.42671199999999,40.700879],"type":"Point"}
}