{
  "type": "Feature",
  "properties": {
    "addr:full":"393 Ave P Brooklyn NY 11223",
    "addr:housenumber":"393",
    "addr:postcode":"11223",
    "addr:street":"Ave P",
    "iso:country":"US",
    "sg:address":"393 Ave P",
    "sg:city":"Brooklyn",
    "sg:classifiers":[
        {
            "category":"Shopping",
            "subcategory":"Tobacco",
            "type":"Retail Goods"
        }
    ],
    "sg:phone":"+1   ",
    "sg:postcode":"11223",
    "sg:province":"NY",
    "sg:tags":[
        "product"
    ],
    "wof:name":"Avenue Pconveient Store",
    "wof:placetype":"venue"
},
  "geometry": {"coordinates":[-73.971913,40.608936],"type":"Point"}
}