{
  "type": "Feature",
  "properties": {
    "addr:full":"218 Otisco St Syracuse NY 13204",
    "addr:housenumber":"218",
    "addr:postcode":"13204",
    "addr:street":"Otisco St",
    "iso:country":"US",
    "sg:address":"218 Otisco St",
    "sg:city":"Syracuse",
    "sg:classifiers":[
        {
            "category":"Bars & Pubs",
            "type":"Food & Drink"
        }
    ],
    "sg:phone":"+1   ",
    "sg:postcode":"13204",
    "sg:province":"NY",
    "sg:tags":[
        "drinking"
    ],
    "wof:name":"Top Cat Lounge Inc",
    "wof:placetype":"venue"
},
  "geometry": {"coordinates":[-76.160509,43.04634],"type":"Point"}
}