{
  "type": "Feature",
  "properties": {
    "iso:country":"US",
    "sg:address":"275 Kohr Rd",
    "sg:city":"Kings Park",
    "sg:classifiers":[
        {
            "category":"Banks & Credit Unions",
            "subcategory":"Investment Brokerage",
            "type":"Services"
        }
    ],
    "sg:phone":"+1 631 269 1111",
    "sg:postcode":"11754",
    "sg:province":"NY",
    "sg:tags":[
        "security"
    ],
    "wof:name":"L P L Financial Services",
    "wof:placetype":"venue"
},
  "geometry": {"coordinates":[-73.25649,40.903642],"type":"Point"}
}