{
  "type": "Feature",
  "properties": {
    "addr:full":"861 Broadway Frnt 1 New York NY 10003",
    "addr:housenumber":"861;1",
    "addr:postcode":"10003",
    "addr:street":"Broadway Frnt",
    "iso:country":"US",
    "sg:address":"861 Broadway Frnt 1",
    "sg:city":"New York",
    "sg:classifiers":[
        {
            "category":"Shopping",
            "subcategory":"Shoes",
            "type":"Retail Goods"
        }
    ],
    "sg:phone":"+1 212 206 1682",
    "sg:postcode":"10003",
    "sg:province":"NY",
    "sg:tags":[
        "store"
    ],
    "wof:name":"Steve Madden Ltd",
    "wof:placetype":"venue"
},
  "geometry": {"coordinates":[-73.990403,40.737349],"type":"Point"}
}