{
  "type": "Feature",
  "properties": {
    "iso:country":"US",
    "sg:address":"311 W State St",
    "sg:city":"Olean",
    "sg:classifiers":[
        {
            "category":"Retail",
            "subcategory":"Repair Shop",
            "type":"Services"
        }
    ],
    "sg:phone":"+1 716 372 1075",
    "sg:postcode":"14760",
    "sg:province":"NY",
    "sg:tags":[
        "cleaners",
        "parts",
        "vacuum"
    ],
    "wof:name":"Jim's Vacuum Cleaner Repair",
    "wof:placetype":"venue"
},
  "geometry": {"coordinates":[-78.433775,42.077385],"type":"Point"}
}