{
  "type": "Feature",
  "properties": {
    "iso:country":"US",
    "sg:address":"268 Rensselaer Ave",
    "sg:city":"Staten Island",
    "sg:classifiers":[
        {
            "category":"Restaurant",
            "type":"Food & Drink"
        }
    ],
    "sg:phone":"+1   ",
    "sg:postcode":"10312",
    "sg:province":"NY",
    "sg:tags":[
        "eating"
    ],
    "wof:name":"G A Hotdogs",
    "wof:placetype":"venue"
},
  "geometry": {"coordinates":[-74.18608999999999,40.543727],"type":"Point"}
}