{
  "type": "Feature",
  "properties": {
    "iso:country":"US",
    "sg:address":"262 Central Park W",
    "sg:city":"New York",
    "sg:classifiers":[
        {
            "category":"Health Services",
            "subcategory":"Doctor",
            "type":"Services"
        }
    ],
    "sg:phone":"+1 212 877 1600",
    "sg:postcode":"10024",
    "sg:province":"NY",
    "sg:tags":[
        "physician",
        "surgeon"
    ],
    "wof:name":"Nancy Joachim DO",
    "wof:placetype":"venue"
},
  "geometry": {"coordinates":[-73.968962,40.785906],"type":"Point"}
}