{
  "type": "Feature",
  "properties": {
    "iso:country":"US",
    "sg:address":"38 Brotherhood Plaza Dr",
    "sg:city":"Washingtonville",
    "sg:classifiers":[
        {
            "category":"Shopping",
            "subcategory":"Pharmacy",
            "type":"Retail Goods"
        }
    ],
    "sg:phone":"+1 845 496 4858",
    "sg:postcode":"10992",
    "sg:province":"NY",
    "sg:tags":[
        "drugstore"
    ],
    "wof:name":"Revco Drug Stores",
    "wof:placetype":"venue"
},
  "geometry": {"coordinates":[-74.16239899999999,41.428699],"type":"Point"}
}