{
  "type": "Feature",
  "properties": {
    "iso:country":"US",
    "sg:address":"1114 Parkside Dr",
    "sg:city":"Webster",
    "sg:classifiers":[
        {
            "category":"Manufacturing",
            "subcategory":"Glass & Minerals",
            "type":"Manufacturing & Wholesale Goods"
        }
    ],
    "sg:phone":"+1   ",
    "sg:postcode":"14580",
    "sg:province":"NY",
    "sg:tags":[
        "product",
        "mfg"
    ],
    "wof:name":"La Lights",
    "wof:placetype":"venue"
},
  "geometry": {"coordinates":[-77.51016199999999,43.198885],"type":"Point"}
}