{
  "type": "Feature",
  "properties": {
    "addr:full":"445 Central Ave Unit 102 Cedarhurst NY 11516",
    "addr:housenumber":"445;102",
    "addr:postcode":"11516",
    "addr:street":"Central Ave Unit",
    "iso:country":"US",
    "sg:address":"445 Central Ave Unit 102",
    "sg:city":"Cedarhurst",
    "sg:classifiers":[
        {
            "category":"Shopping",
            "subcategory":"Clothing, Apparel, & Fashions",
            "type":"Retail Goods"
        }
    ],
    "sg:phone":"+1 516 569 7766",
    "sg:postcode":"11516",
    "sg:province":"NY",
    "sg:tags":[
        "clothing",
        "women's"
    ],
    "sg:website":"www.tommieco.com",
    "wof:name":"Tommie & Co",
    "wof:placetype":"venue"
},
  "geometry": {"coordinates":[-73.72517499999999,40.620337],"type":"Point"}
}