{
  "type": "Feature",
  "properties": {
    "addr:full":"318 N Hoopes Ave Auburn NY 13021",
    "addr:housenumber":"318",
    "addr:postcode":"13021",
    "addr:street":"N Hoopes Ave",
    "iso:country":"US",
    "sg:address":"318 N Hoopes Ave",
    "sg:city":"Auburn",
    "sg:classifiers":[
        {
            "category":"Manufacturing",
            "subcategory":"Pottery",
            "type":"Manufacturing & Wholesale Goods"
        }
    ],
    "sg:phone":"+1   ",
    "sg:postcode":"13021",
    "sg:province":"NY",
    "sg:tags":[
        "product",
        "mfg"
    ],
    "wof:name":"Jenny Dorcy",
    "wof:placetype":"venue"
},
  "geometry": {"coordinates":[-76.545982,42.938953],"type":"Point"}
}