{
  "type": "Feature",
  "properties": {
    "addr:full":"18 Freedom Rd Pleasant Valley NY 12569",
    "addr:housenumber":"18",
    "addr:postcode":"12569",
    "addr:street":"Freedom Rd",
    "iso:country":"US",
    "sg:address":"18 Freedom Rd",
    "sg:city":"Pleasant Valley",
    "sg:classifiers":[
        {
            "category":"Building & Trades",
            "subcategory":"Construction",
            "type":"Services"
        }
    ],
    "sg:phone":"+1 845 635 8670",
    "sg:postcode":"12569",
    "sg:province":"NY",
    "sg:tags":[
        "masonry",
        "contractor"
    ],
    "wof:name":"J C Construction",
    "wof:placetype":"venue"
},
  "geometry": {"coordinates":[-73.820437,41.728259],"type":"Point"}
}