{
  "type": "Feature",
  "properties": {
    "addr:full":"512 E 240th St Bronx NY 10470",
    "addr:housenumber":"512",
    "addr:postcode":"10470",
    "addr:street":"E 240Th St",
    "iso:country":"US",
    "sg:address":"512 E 240th St",
    "sg:city":"Bronx",
    "sg:classifiers":[
        {
            "category":"Retail",
            "subcategory":"Repair Shop",
            "type":"Services"
        }
    ],
    "sg:phone":"+1 718 766 2649",
    "sg:postcode":"10470",
    "sg:province":"NY",
    "sg:tags":[
        "lock",
        "locksmith"
    ],
    "wof:name":"USA Locksmiths",
    "wof:placetype":"venue"
},
  "geometry": {"coordinates":[-73.86462899999999,40.901197],"type":"Point"}
}