{
  "type": "Feature",
  "properties": {
    "iso:country":"US",
    "sg:address":"12 Ellwood St",
    "sg:city":"New York",
    "sg:classifiers":[
        {
            "category":"Education",
            "subcategory":"Library",
            "type":"Public Place"
        }
    ],
    "sg:phone":"+1 212 567 4725",
    "sg:postcode":"10040",
    "sg:province":"NY",
    "wof:name":"Brooklyn Public Library",
    "wof:placetype":"venue"
},
  "geometry": {"coordinates":[-73.927933,40.859289],"type":"Point"}
}