{
  "type": "Feature",
  "properties": {
    "iso:country":"US",
    "sg:address":"364 Broadway",
    "sg:city":"New York",
    "sg:classifiers":[
        {
            "category":"Shopping",
            "subcategory":"Clothing, Apparel, & Fashions",
            "type":"Retail Goods"
        },
        {
            "category":"Shopping",
            "subcategory":"Shoes",
            "type":"Retail Goods"
        }
    ],
    "sg:postcode":"10003",
    "sg:province":"NY",
    "sg:tags":[
        "men's",
        "clothing",
        "store",
        "women's"
    ],
    "wof:name":"Antique Orange",
    "wof:placetype":"venue"
},
  "geometry": {"coordinates":[-74.003477,40.717461],"type":"Point"}
}