{
  "type": "Feature",
  "properties": {
    "addr:full":"642 Bay St Staten Island NY 10304",
    "addr:housenumber":"642",
    "addr:postcode":"10304",
    "addr:street":"Bay St",
    "iso:country":"US",
    "sg:address":"642 Bay St",
    "sg:city":"Staten Island",
    "sg:classifiers":[
        {
            "category":"Shopping",
            "type":"Retail Goods"
        }
    ],
    "sg:phone":"+1   ",
    "sg:postcode":"10304",
    "sg:province":"NY",
    "sg:tags":[
        "merchandise"
    ],
    "wof:name":"Alex Communications",
    "wof:placetype":"venue"
},
  "geometry": {"coordinates":[-74.07544300000001,40.626256],"type":"Point"}
}