{
  "type": "Feature",
  "properties": {
    "addr:full":"6638 Grand Ave Maspeth NY 11378",
    "addr:housenumber":"6638",
    "addr:postcode":"11378",
    "addr:street":"Grand Ave",
    "iso:country":"US",
    "sg:address":"6638 Grand Ave",
    "sg:city":"Maspeth",
    "sg:classifiers":[
        {
            "category":"Shopping",
            "subcategory":"Pharmacy",
            "type":"Retail Goods"
        }
    ],
    "sg:phone":"+1 718 424 8273",
    "sg:postcode":"11378",
    "sg:province":"NY",
    "sg:tags":[
        "drugstore"
    ],
    "wof:name":"Mediciti Drugs Inc",
    "wof:placetype":"venue"
},
  "geometry": {"coordinates":[-73.89780399999999,40.724435],"type":"Point"}
}