{
  "type": "Feature",
  "properties": {
    "iso:country":"US",
    "sg:address":"176 Windsor Hwy",
    "sg:city":"New Windsor",
    "sg:classifiers":[
        {
            "category":"Restaurant",
            "type":"Food & Drink"
        }
    ],
    "sg:phone":"+1 845 563 9100",
    "sg:postcode":"12553",
    "sg:province":"NY",
    "sg:tags":[
        "pizza"
    ],
    "wof:name":"Pizza Mia",
    "wof:placetype":"venue"
},
  "geometry": {"coordinates":[-74.04246999999999,41.477247],"type":"Point"}
}