{
  "type": "Feature",
  "properties": {
    "iso:country":"US",
    "sg:address":"882 Broadway",
    "sg:city":"Brooklyn",
    "sg:classifiers":[
        {
            "category":"Personal",
            "subcategory":"Tattoo Parlor",
            "type":"Services"
        }
    ],
    "sg:phone":"+1 718 453 6140",
    "sg:postcode":"11206",
    "sg:province":"NY",
    "sg:tags":[
        "tattooing"
    ],
    "sg:website":"www.crazymonkeytattoo.com",
    "wof:name":"Crazy Monkey Tattoo",
    "wof:placetype":"venue"
},
  "geometry": {"coordinates":[-73.93755899999999,40.698142],"type":"Point"}
}