{
  "type": "Feature",
  "properties": {
    "addr:full":"920 Broadway 8th Fl Ste 11 Manhattan NY 10010",
    "addr:housenumber":"920",
    "addr:postcode":"10010",
    "addr:street":"Broadway;Ste 11",
    "iso:country":"US",
    "sg:address":"920 Broadway 8th Fl Ste 11",
    "sg:city":"Manhattan",
    "sg:classifiers":[
        {
            "category":"Health Services",
            "subcategory":"Clinic",
            "type":"Services"
        }
    ],
    "sg:phone":"+1 201 650 4224",
    "sg:postcode":"10010",
    "sg:province":"NY",
    "sg:tags":[
        "counseling",
        "mental"
    ],
    "wof:name":"Barbara Medlin NP-P/BC",
    "wof:placetype":"venue"
},
  "geometry": {"coordinates":[-73.98957,40.739838],"type":"Point"}
}