{
  "type": "Feature",
  "properties": {
    "addr:full":"684 Bay St Staten Island NY 10304",
    "addr:housenumber":"684",
    "addr:postcode":"10304",
    "addr:street":"Bay St",
    "iso:country":"US",
    "sg:address":"684 Bay St",
    "sg:city":"Staten Island",
    "sg:classifiers":[
        {
            "category":"Shopping",
            "subcategory":"Pharmacy",
            "type":"Retail Goods"
        }
    ],
    "sg:phone":"+1 718 524 1100",
    "sg:postcode":"10304",
    "sg:province":"NY",
    "wof:name":"Your Pharmacy Inc",
    "wof:placetype":"venue"
},
  "geometry": {"coordinates":[-74.075011,40.625463],"type":"Point"}
}