{
  "type": "Feature",
  "properties": {
    "iso:country":"US",
    "sg:address":"811 W Jericho Tpke",
    "sg:city":"Smithtown",
    "sg:classifiers":[
        {
            "category":"Social Services",
            "type":"Services"
        }
    ],
    "sg:phone":"+1 631 265 9850",
    "sg:postcode":"11787",
    "sg:province":"NY",
    "sg:tags":[
        "counselor",
        "marriage",
        "family"
    ],
    "wof:name":"Child & Family Psychological",
    "wof:placetype":"venue"
},
  "geometry": {"coordinates":[-73.248205,40.848352],"type":"Point"}
}