{
  "type": "Feature",
  "properties": {
    "iso:country":"US",
    "sg:address":"124 Saw Mill River Rd",
    "sg:city":"Elmsford",
    "sg:classifiers":[
        {
            "category":"Organizations",
            "subcategory":"Labor Organization",
            "type":"Services"
        }
    ],
    "sg:phone":"+1   ",
    "sg:postcode":"10523",
    "sg:province":"NY",
    "wof:name":"Amalgamated Construction",
    "wof:placetype":"venue"
},
  "geometry": {"coordinates":[-73.816694,41.058007],"type":"Point"}
}