{
  "type": "Feature",
  "properties": {
    "addr:full":"390 Bleecker St New York NY 10014",
    "addr:housenumber":"390",
    "addr:postcode":"10014",
    "addr:street":"Bleecker St",
    "iso:country":"US",
    "sg:address":"390 Bleecker St",
    "sg:city":"New York",
    "sg:classifiers":[
        {
            "category":"Shopping",
            "subcategory":"Crafts & Fabrics",
            "type":"Retail Goods"
        }
    ],
    "sg:phone":"+1 212 645 5020",
    "sg:postcode":"10014",
    "sg:province":"NY",
    "sg:tags":[
        "sewing",
        "used",
        "d",
        "merchandise"
    ],
    "wof:name":"Susan Parrish Antiques",
    "wof:placetype":"venue"
},
  "geometry": {"coordinates":[-74.005156,40.735756],"type":"Point"}
}