{
  "type": "Feature",
  "properties": {
    "addr:full":"92 Lake Shore Dr E Dunkirk NY 14048",
    "addr:housenumber":"92",
    "addr:postcode":"14048",
    "addr:street":"Lake Shore Dr E",
    "iso:country":"US",
    "sg:address":"92 Lake Shore Dr E",
    "sg:city":"Dunkirk",
    "sg:classifiers":[
        {
            "category":"Coffee & Tea",
            "type":"Food & Drink"
        },
        {
            "category":"Restaurant",
            "type":"Food & Drink"
        },
        {
            "category":"Food & Beverages",
            "subcategory":"Groceries & Convenience Stores",
            "type":"Retail Goods"
        }
    ],
    "sg:phone":"+1 716 672 9759",
    "sg:postcode":"14048",
    "sg:province":"NY",
    "sg:tags":[
        "shop",
        "sandwich",
        "espresso",
        "lunch",
        "brunch",
        "breakfast"
    ],
    "sg:website":"http://www.timhortons.com/",
    "wof:name":"Tim Horton's",
    "wof:placetype":"venue"
},
  "geometry": {"coordinates":[-79.33052499999999,42.488032],"type":"Point"}
}