{
  "type": "Feature",
  "properties": {
    "iso:country":"US",
    "sg:address":"448 Hawley Ave",
    "sg:city":"Syracuse",
    "sg:classifiers":[
        {
            "category":"Personal",
            "subcategory":"Beauty Salon",
            "type":"Services"
        }
    ],
    "sg:phone":"+1 240 346 6169",
    "sg:postcode":"13203",
    "sg:province":"NY",
    "wof:name":"Judy Luttrell Hair Stylist",
    "wof:placetype":"venue"
},
  "geometry": {"coordinates":[-76.137776,43.05329],"type":"Point"}
}