{
  "type": "Feature",
  "properties": {
    "addr:full":"6309 Flushing Ave Maspeth NY 11378",
    "addr:housenumber":"6309",
    "addr:postcode":"11378",
    "addr:street":"Flushing Ave",
    "iso:country":"US",
    "sg:address":"6309 Flushing Ave",
    "sg:city":"Maspeth",
    "sg:classifiers":[
        {
            "category":"Banks & Credit Unions",
            "subcategory":"Bank",
            "type":"Services"
        }
    ],
    "sg:phone":"+1 718 386 4251",
    "sg:postcode":"11378",
    "sg:province":"NY",
    "wof:name":"Valley National Bank",
    "wof:placetype":"venue"
},
  "geometry": {"coordinates":[-73.902295,40.722294],"type":"Point"}
}