{
  "type": "Feature",
  "properties": {
    "iso:country":"US",
    "sg:address":"2170 Atlantic Ave",
    "sg:city":"Brooklyn",
    "sg:classifiers":[
        {
            "category":"Wholesale",
            "subcategory":"Electrical",
            "type":"Manufacturing & Wholesale Goods"
        }
    ],
    "sg:phone":"+1 718 495 1325",
    "sg:postcode":"11233",
    "sg:province":"NY",
    "sg:tags":[
        "control",
        "security",
        "system"
    ],
    "wof:name":"Take One Security & Co",
    "wof:placetype":"venue"
},
  "geometry": {"coordinates":[-73.915267,40.676517],"type":"Point"}
}