{
  "type": "Feature",
  "properties": {
    "iso:country":"US",
    "sg:address":"35 Cedar St",
    "sg:city":"Morrisville",
    "sg:classifiers":[
        {
            "category":"Government",
            "subcategory":"Office",
            "type":"Public Place"
        }
    ],
    "sg:phone":"+1 315 684 3118",
    "sg:postcode":"13408",
    "sg:province":"NY",
    "sg:tags":[
        "village"
    ],
    "wof:name":"Town Garage",
    "wof:placetype":"venue"
},
  "geometry": {"coordinates":[-75.64651600000001,42.899091],"type":"Point"}
}