{
  "type": "Feature",
  "properties": {
    "addr:full":"301 W 113th St New York NY 10026",
    "addr:housenumber":"301",
    "addr:postcode":"10026",
    "addr:street":"W 113Th St",
    "iso:country":"US",
    "sg:address":"301 W 113th St",
    "sg:city":"New York",
    "sg:classifiers":[
        {
            "category":"Retail",
            "subcategory":"Repair Shop",
            "type":"Services"
        }
    ],
    "sg:phone":"+1 917 546 1671",
    "sg:postcode":"10026",
    "sg:province":"NY",
    "sg:tags":[
        "lock",
        "locksmith"
    ],
    "wof:name":"Emergency 7 Day Towing",
    "wof:placetype":"venue"
},
  "geometry": {"coordinates":[-73.958249,40.803107],"type":"Point"}
}