{
  "type": "Feature",
  "properties": {
    "addr:full":"5977 E Henrietta Rd Rush NY 14543",
    "addr:housenumber":"5977",
    "addr:postcode":"14543",
    "addr:street":"E Henrietta Rd",
    "iso:country":"US",
    "sg:address":"5977 E Henrietta Rd",
    "sg:city":"Rush",
    "sg:classifiers":[
        {
            "category":"Recreation",
            "type":"Entertainment"
        }
    ],
    "sg:phone":"+1 585 533 2340",
    "sg:postcode":"14543",
    "sg:province":"NY",
    "sg:tags":[
        "center"
    ],
    "wof:name":"Recreation Office",
    "wof:placetype":"venue"
},
  "geometry": {"coordinates":[-77.64558,42.994017],"type":"Point"}
}