{
  "type": "Feature",
  "properties": {
    "addr:full":"470 North Ave New Rochelle NY 10801",
    "addr:housenumber":"470",
    "addr:postcode":"10801",
    "addr:street":"North Ave",
    "iso:country":"US",
    "sg:address":"470 North Ave",
    "sg:city":"New Rochelle",
    "sg:classifiers":[
        {
            "category":"Organizations",
            "subcategory":"Religious Organization",
            "type":"Services"
        }
    ],
    "sg:phone":"+1 914 633 3291",
    "sg:postcode":"10801",
    "sg:province":"NY",
    "sg:tags":[
        "church"
    ],
    "wof:name":"First Holiness Church",
    "wof:placetype":"venue"
},
  "geometry": {"coordinates":[-73.786477,40.918534],"type":"Point"}
}