{
  "type": "Feature",
  "properties": {
    "addr:full":"25 Pine St Middletown NY 10940",
    "addr:housenumber":"25",
    "addr:postcode":"10940",
    "addr:street":"Pine St",
    "iso:country":"US",
    "sg:address":"25 Pine St",
    "sg:city":"Middletown",
    "sg:classifiers":[
        {
            "category":"Health Services",
            "subcategory":"Doctor",
            "type":"Services"
        }
    ],
    "sg:phone":"+1 845 343 5397",
    "sg:postcode":"10940",
    "sg:province":"NY",
    "sg:tags":[
        "medical"
    ],
    "wof:name":"Marjory Lapadura",
    "wof:placetype":"venue"
},
  "geometry": {"coordinates":[-74.43767800000001,41.442751],"type":"Point"}
}