{
  "type": "Feature",
  "properties": {
    "addr:full":"115 West 29th Street Suite 801 New York NY 10001",
    "addr:housenumber":"115;801",
    "addr:postcode":"10001",
    "addr:street":"West 29Th Street Suite",
    "iso:country":"US",
    "sg:address":"115 West 29th Street Suite 801",
    "sg:city":"New York",
    "sg:classifiers":[
        {
            "category":"Building & Trades",
            "subcategory":"Construction",
            "type":"Services"
        }
    ],
    "sg:phone":"+1 212 697 4040",
    "sg:postcode":"10001",
    "sg:province":"NY",
    "sg:tags":[
        "contractor"
    ],
    "sg:website":"www.tecny.com",
    "wof:name":"Tecny Group",
    "wof:placetype":"venue"
},
  "geometry": {"coordinates":[-73.990847,40.747193],"type":"Point"}
}