{
  "type": "Feature",
  "properties": {
    "iso:country":"US",
    "sg:address":"218 Dutchess Ave",
    "sg:city":"Staten Island",
    "sg:classifiers":[
        {
            "category":"Social Services",
            "subcategory":"Child Care",
            "type":"Services"
        }
    ],
    "sg:phone":"+1 718 980 2082",
    "sg:postcode":"10304",
    "sg:province":"NY",
    "sg:tags":[
        "day"
    ],
    "wof:name":"Day-Care Family",
    "wof:placetype":"venue"
},
  "geometry": {"coordinates":[-74.10226,40.594474],"type":"Point"}
}