{
  "type": "Feature",
  "properties": {
    "addr:full":"55 Lumber Rd Roslyn NY 11576",
    "addr:postcode":"11576",
    "addr:street":"Lumber Rd",
    "iso:country":"US",
    "sg:address":"55 Lumber Rd",
    "sg:city":"Roslyn",
    "sg:classifiers":[
        {
            "category":"Home & Garden",
            "subcategory":"Household Appliances",
            "type":"Retail Goods"
        }
    ],
    "sg:phone":"+1 516 484 4436",
    "sg:postcode":"11576",
    "sg:province":"NY",
    "wof:name":"Mr Jay Appliances",
    "wof:placetype":"venue"
},
  "geometry": {"coordinates":[-73.651974,40.803076],"type":"Point"}
}