{
  "type": "Feature",
  "properties": {
    "addr:full":"151 Bellport Ave Medford NY 11763",
    "addr:housenumber":"151",
    "addr:postcode":"11763",
    "addr:street":"Bellport Ave",
    "iso:country":"US",
    "sg:address":"151 Bellport Ave",
    "sg:city":"Medford",
    "sg:classifiers":[
        {
            "category":"Utilities",
            "subcategory":"Refuse",
            "type":"Services"
        }
    ],
    "sg:phone":"+1 631 345 3782",
    "sg:postcode":"11763",
    "sg:province":"NY",
    "sg:tags":[
        "garbage",
        "collection"
    ],
    "wof:name":"Kennedy Contracting",
    "wof:placetype":"venue"
},
  "geometry": {"coordinates":[-72.943625,40.803844],"type":"Point"}
}