{
  "type": "Feature",
  "properties": {
    "addr:full":"613 Hudson Street New York NY 10014",
    "addr:housenumber":"613",
    "addr:postcode":"10014",
    "addr:street":"Hudson Street",
    "iso:country":"US",
    "sg:address":"613 Hudson Street",
    "sg:city":"New York",
    "sg:classifiers":[
        {
            "category":"Arts & Performance",
            "subcategory":"Art Gallery",
            "type":"Entertainment"
        }
    ],
    "sg:phone":"+1 212 206 6845",
    "sg:postcode":"10014",
    "sg:province":"NY",
    "wof:name":"Abingdon Twelve",
    "wof:placetype":"venue"
},
  "geometry": {"coordinates":[-74.005803,40.737741],"type":"Point"}
}