{
  "type": "Feature",
  "properties": {
    "iso:country":"US",
    "sg:address":"2 St John St",
    "sg:city":"Goshen",
    "sg:classifiers":[
        {
            "category":"Social Services",
            "type":"Services"
        }
    ],
    "sg:phone":"+1 845 294 5252",
    "sg:postcode":"10924",
    "sg:province":"NY",
    "sg:tags":[
        "counselor",
        "marriage",
        "family"
    ],
    "wof:name":"Benowitz & Burke",
    "wof:placetype":"venue"
},
  "geometry": {"coordinates":[-74.324602,41.40307],"type":"Point"}
}