{
  "type": "Feature",
  "properties": {
    "iso:country":"US",
    "sg:address":"77 Motley Ave",
    "sg:city":"Staten Island",
    "sg:classifiers":[
        {
            "category":"Travel",
            "subcategory":"Travel Agent",
            "type":"Entertainment"
        }
    ],
    "sg:phone":"+1 718 983 0832",
    "sg:postcode":"10314",
    "sg:province":"NY",
    "sg:tags":[
        "agency",
        "bureau"
    ],
    "wof:name":"Cousins Cruises",
    "wof:placetype":"venue"
},
  "geometry": {"coordinates":[-74.11575999999999,40.608124],"type":"Point"}
}