{
  "type": "Feature",
  "properties": {
    "iso:country":"US",
    "sg:address":"5 Durham Rd",
    "sg:city":"New Hyde Park",
    "sg:classifiers":[
        {
            "category":"Organizations",
            "subcategory":"Religious Organization",
            "type":"Services"
        }
    ],
    "sg:phone":"+1 516 354 8883",
    "sg:postcode":"11040",
    "sg:province":"NY",
    "sg:tags":[
        "church"
    ],
    "sg:website":"www.trinitynewhydepark.org",
    "wof:name":"Trinity Lutheran Church",
    "wof:placetype":"venue"
},
  "geometry": {"coordinates":[-73.686302,40.751598],"type":"Point"}
}