{
  "type": "Feature",
  "properties": {
    "iso:country":"US",
    "sg:address":"1211 E 224th St",
    "sg:city":"Bronx",
    "sg:classifiers":[
        {
            "category":"Communications",
            "type":"Services"
        }
    ],
    "sg:phone":"+1   ",
    "sg:postcode":"10466",
    "sg:province":"NY",
    "sg:tags":[
        "communication"
    ],
    "wof:name":"Jamvista Communications",
    "wof:placetype":"venue"
},
  "geometry": {"coordinates":[-73.84539100000001,40.881812],"type":"Point"}
}