{
  "type": "Feature",
  "properties": {
    "addr:full":"109 E Midland Pond Ct Moriches NY 11955",
    "addr:housenumber":"109",
    "addr:postcode":"11955",
    "addr:street":"E Midland Pond Ct",
    "iso:country":"US",
    "sg:address":"109 E Midland Pond Ct",
    "sg:city":"Moriches",
    "sg:classifiers":[
        {
            "category":"Social Services",
            "subcategory":"Child Care",
            "type":"Services"
        }
    ],
    "sg:phone":"+1   ",
    "sg:postcode":"11955",
    "sg:province":"NY",
    "sg:tags":[
        "day"
    ],
    "wof:name":"Life Love & Laughter Fund",
    "wof:placetype":"venue"
},
  "geometry": {"coordinates":[-72.82657500000001,40.799348],"type":"Point"}
}