{
  "type": "Feature",
  "properties": {
    "iso:country":"US",
    "sg:address":"1301 Hempstead Tpke",
    "sg:city":"Elmont",
    "sg:classifiers":[
        {
            "category":"Building & Trades",
            "subcategory":"Construction",
            "type":"Services"
        }
    ],
    "sg:phone":"+1 516 437 0810",
    "sg:postcode":"11003",
    "sg:province":"NY",
    "sg:tags":[
        "general",
        "contractor"
    ],
    "wof:name":"Federal Construction",
    "wof:placetype":"venue"
},
  "geometry": {"coordinates":[-73.68830800000001,40.708303],"type":"Point"}
}