{
  "type": "Feature",
  "properties": {
    "iso:country":"US",
    "sg:address":"2200 E Genesee St",
    "sg:city":"Syracuse",
    "sg:classifiers":[
        {
            "category":"Wholesale",
            "subcategory":"Medical Equipment & Supplies",
            "type":"Manufacturing & Wholesale Goods"
        }
    ],
    "sg:phone":"+1 315 472 9529",
    "sg:postcode":"13210",
    "sg:province":"NY",
    "sg:tags":[
        "hospital"
    ],
    "wof:name":"Upstate Homecare",
    "wof:placetype":"venue"
},
  "geometry": {"coordinates":[-76.11574,43.045413],"type":"Point"}
}