{
  "type": "Feature",
  "properties": {
    "iso:country":"US",
    "sg:address":"369 Middle Country Rd",
    "sg:city":"Coram",
    "sg:classifiers":[
        {
            "category":"Health Services",
            "subcategory":"Doctor",
            "type":"Services"
        }
    ],
    "sg:phone":"+1 631 698 1967",
    "sg:postcode":"11727",
    "sg:province":"NY",
    "sg:tags":[
        "surgeon",
        "oral"
    ],
    "wof:name":"Roseman Stephen DDS",
    "wof:placetype":"venue"
},
  "geometry": {"coordinates":[-73.02130099999999,40.876598],"type":"Point"}
}