{
  "type": "Feature",
  "properties": {
    "addr:full":"134 Knollwood Cir S Ava NY 13303",
    "addr:housenumber":"134",
    "addr:postcode":"13303",
    "addr:street":"Knollwood Cir S",
    "iso:country":"US",
    "sg:address":"134 Knollwood Cir S",
    "sg:city":"Ava",
    "sg:classifiers":[
        {
            "category":"Professional",
            "subcategory":"Lawyer & Legal Services",
            "type":"Services"
        }
    ],
    "sg:phone":"+1 315 336 1149",
    "sg:postcode":"13303",
    "sg:province":"NY",
    "wof:name":"Oshea McDonald Pennzone",
    "wof:placetype":"venue"
},
  "geometry": {"coordinates":[-75.44211300000001,43.304393],"type":"Point"}
}