{
  "type": "Feature",
  "properties": {
    "addr:full":"2 E 20th St New York NY 10003",
    "addr:housenumber":"2",
    "addr:postcode":"10003",
    "addr:street":"E 20Th St",
    "iso:country":"US",
    "sg:address":"2 E 20th St",
    "sg:city":"New York",
    "sg:classifiers":[
        {
            "category":"Personal",
            "type":"Services"
        }
    ],
    "sg:phone":"+1 917 237 4693",
    "sg:postcode":"10003",
    "sg:province":"NY",
    "sg:tags":[
        "towing"
    ],
    "wof:name":"A Emergency A Towing 24 Hour",
    "wof:placetype":"venue"
},
  "geometry": {"coordinates":[-73.99009700000001,40.732399],"type":"Point"}
}