{
  "type": "Feature",
  "properties": {
    "addr:full":"180 Atlantic Ave New Hyde Park NY 11040",
    "addr:housenumber":"180",
    "addr:postcode":"11040",
    "addr:street":"Atlantic Ave",
    "iso:country":"US",
    "sg:address":"180 Atlantic Ave",
    "sg:city":"New Hyde Park",
    "sg:classifiers":[
        {
            "category":"Wholesale",
            "subcategory":"Groceries",
            "type":"Manufacturing & Wholesale Goods"
        }
    ],
    "sg:phone":"+1 212 262 2233",
    "sg:postcode":"11040",
    "sg:province":"NY",
    "sg:tags":[
        "beverage"
    ],
    "wof:name":"Instant Beverages Inc",
    "wof:placetype":"venue"
},
  "geometry": {"coordinates":[-73.657791,40.736677],"type":"Point"}
}