{
  "type": "Feature",
  "properties": {
    "addr:full":"1273 State Hwy 5 Elbridge NY 13060",
    "addr:housenumber":"1273",
    "addr:postcode":"13060",
    "addr:street":"State Hwy 5",
    "iso:country":"US",
    "sg:address":"1273 State Hwy 5",
    "sg:city":"Elbridge",
    "sg:classifiers":[
        {
            "category":"Shopping",
            "subcategory":"Gifts & Souvenirs",
            "type":"Retail Goods"
        }
    ],
    "sg:phone":"+1 315 689 6450",
    "sg:postcode":"13060",
    "sg:province":"NY",
    "sg:tags":[
        "shop"
    ],
    "wof:name":"North Country Florist",
    "wof:placetype":"venue"
},
  "geometry": {"coordinates":[-76.420671,43.038091],"type":"Point"}
}