{
  "type": "Feature",
  "properties": {
    "iso:country":"US",
    "sg:address":"5973 Walworth Rd",
    "sg:city":"Ontario",
    "sg:classifiers":[
        {
            "category":"Health Services",
            "subcategory":"Doctor",
            "type":"Services"
        }
    ],
    "sg:phone":"+1 315 524 2881",
    "sg:postcode":"14519",
    "sg:province":"NY",
    "sg:tags":[
        "medicine",
        "physician",
        "practice",
        "surgeons",
        "family"
    ],
    "wof:name":"Neil Smith Md",
    "wof:placetype":"venue"
},
  "geometry": {"coordinates":[-77.283629,43.216869],"type":"Point"}
}