{
  "type": "Feature",
  "properties": {
    "iso:country":"US",
    "sg:address":"323 Clapp Hill Rd",
    "sg:city":"Lagrangeville",
    "sg:classifiers":[
        {
            "category":"Building & Trades",
            "subcategory":"Plumbing",
            "type":"Services"
        },
        {
            "category":"Wholesale",
            "subcategory":"Electrical",
            "type":"Manufacturing & Wholesale Goods"
        }
    ],
    "sg:phone":"+1 845 223 5615",
    "sg:postcode":"12540",
    "sg:province":"NY",
    "sg:tags":[
        "sprinkler",
        "fire",
        "system",
        "equipment",
        "protection",
        "install"
    ],
    "wof:name":"Apf Fire Protection Inc",
    "wof:placetype":"venue"
},
  "geometry": {"coordinates":[-73.74441400000001,41.635474],"type":"Point"}
}