{
  "type": "Feature",
  "properties": {
    "addr:full":"1868 Webster Ave Bronx NY 10457",
    "addr:housenumber":"1868",
    "addr:postcode":"10457",
    "addr:street":"Webster Ave",
    "iso:country":"US",
    "sg:address":"1868 Webster Ave",
    "sg:city":"Bronx",
    "sg:classifiers":[
        {
            "category":"Autos & Motor Vehicles",
            "subcategory":"Auto Supplies",
            "type":"Retail Goods"
        },
        {
            "category":"Shopping",
            "subcategory":"Computers & Home Electronics",
            "type":"Retail Goods"
        }
    ],
    "sg:phone":"+1 718 294 4063",
    "sg:postcode":"10457",
    "sg:province":"NY",
    "sg:tags":[
        "sound",
        "stereo",
        "glass",
        "automobile",
        "equipment",
        "radio",
        "automotive"
    ],
    "wof:name":"Webster Auto Sound & Glass Inc",
    "wof:placetype":"venue"
},
  "geometry": {"coordinates":[-73.90100099999999,40.847301],"type":"Point"}
}