{
  "type": "Feature",
  "properties": {
    "addr:full":"2403 Ave X Brooklyn NY 11235",
    "addr:housenumber":"2403",
    "addr:postcode":"11235",
    "addr:street":"Ave X",
    "iso:country":"US",
    "sg:address":"2403 Ave X",
    "sg:city":"Brooklyn",
    "sg:classifiers":[
        {
            "category":"Wholesale",
            "subcategory":"Medical Equipment & Supplies",
            "type":"Manufacturing & Wholesale Goods"
        }
    ],
    "sg:phone":"+1 718 332 7800",
    "sg:postcode":"11235",
    "sg:province":"NY",
    "sg:tags":[
        "sales"
    ],
    "wof:name":"Igm Sales Inc",
    "wof:placetype":"venue"
},
  "geometry": {"coordinates":[-73.94540000000001,40.593352],"type":"Point"}
}