{
  "type": "Feature",
  "properties": {
    "iso:country":"US",
    "sg:address":"47 Mott Ave",
    "sg:city":"Inwood",
    "sg:classifiers":[
        {
            "category":"Building & Trades",
            "subcategory":"Construction",
            "type":"Services"
        }
    ],
    "sg:phone":"+1 718 327 7008",
    "sg:postcode":"11096",
    "sg:province":"NY",
    "sg:tags":[
        "system",
        "specialty",
        "heating",
        "contractor",
        "air conditioning"
    ],
    "wof:name":"Tri State Air Conditioning Corp",
    "wof:placetype":"venue"
},
  "geometry": {"coordinates":[-73.738704,40.618463],"type":"Point"}
}