{
  "type": "Feature",
  "properties": {
    "iso:country":"US",
    "sg:address":"17 Center St",
    "sg:city":"Ardsley",
    "sg:classifiers":[
        {
            "category":"Health Services",
            "subcategory":"Clinic",
            "type":"Services"
        }
    ],
    "sg:phone":"+1 914 478 8780",
    "sg:postcode":"10502",
    "sg:province":"NY",
    "wof:name":"Health SOS",
    "wof:placetype":"venue"
},
  "geometry": {"coordinates":[-73.845671,41.012435],"type":"Point"}
}