{
  "type": "Feature",
  "properties": {
    "addr:full":"277 Broadway New York NY 10007",
    "addr:housenumber":"277",
    "addr:postcode":"10007",
    "addr:street":"Broadway",
    "iso:country":"US",
    "sg:address":"277 Broadway",
    "sg:city":"New York",
    "sg:classifiers":[
        {
            "category":"Professional",
            "subcategory":"Lawyer & Legal Services",
            "type":"Services"
        }
    ],
    "sg:phone":"+1 212 869 1924",
    "sg:postcode":"10007",
    "sg:province":"NY",
    "sg:tags":[
        "attorney"
    ],
    "wof:name":"Krantz J Samuel ESQ",
    "wof:placetype":"venue"
},
  "geometry": {"coordinates":[-74.006153,40.714333],"type":"Point"}
}