{
  "type": "Feature",
  "properties": {
    "iso:country":"US",
    "sg:address":"403 New Karner Rd",
    "sg:city":"Albany",
    "sg:classifiers":[
        {
            "category":"Professional",
            "subcategory":"Lawyer & Legal Services",
            "type":"Services"
        }
    ],
    "sg:phone":"+1 518 464 0600",
    "sg:postcode":"12205",
    "sg:province":"NY",
    "wof:name":"Timothy J OConnor",
    "wof:placetype":"venue"
},
  "geometry": {"coordinates":[-73.84822,42.733664],"type":"Point"}
}