{
  "type": "Feature",
  "properties": {
    "addr:full":"110 W 90th Street New York NY 10024",
    "addr:housenumber":"110",
    "addr:postcode":"10024",
    "addr:street":"W 90Th Street",
    "iso:country":"US",
    "sg:address":"110 W 90th Street",
    "sg:city":"New York",
    "sg:classifiers":[
        {
            "category":"Education",
            "subcategory":"School",
            "type":"Public Place"
        }
    ],
    "sg:phone":"+1 212 877 2524",
    "sg:postcode":"10024",
    "sg:province":"NY",
    "wof:name":"Columbus Common Condominium",
    "wof:placetype":"venue"
},
  "geometry": {"coordinates":[-73.970857,40.789258],"type":"Point"}
}