{
  "type": "Feature",
  "properties": {
    "addr:full":"889 Harrison Ave Riverhead NY 11901",
    "addr:housenumber":"889",
    "addr:postcode":"11901",
    "addr:street":"Harrison Ave",
    "iso:country":"US",
    "sg:address":"889 Harrison Ave",
    "sg:city":"Riverhead",
    "sg:classifiers":[
        {
            "category":"Professional",
            "subcategory":"Management & Consulting",
            "type":"Services"
        }
    ],
    "sg:phone":"+1 631 369 2009",
    "sg:postcode":"11901",
    "sg:province":"NY",
    "sg:tags":[
        "consultant",
        "business"
    ],
    "wof:name":"Andrew & Son",
    "wof:placetype":"venue"
},
  "geometry": {"coordinates":[-72.683211,40.932023],"type":"Point"}
}