{
  "type": "Feature",
  "properties": {
    "addr:full":"3200 Orchard Park Rd Orchard Park NY 14127",
    "addr:housenumber":"3200",
    "addr:postcode":"14127",
    "addr:street":"Orchard Park Rd",
    "iso:country":"US",
    "sg:address":"3200 Orchard Park Rd",
    "sg:city":"Orchard Park",
    "sg:classifiers":[
        {
            "category":"Restaurant",
            "type":"Food & Drink"
        }
    ],
    "sg:menulink":"http://www.allmenus.com/ny/orchard-park/11525-dennys/menu/",
    "sg:phone":"+1 716 674 1331",
    "sg:postcode":"14127",
    "sg:province":"NY",
    "sg:tags":[
        "american",
        "diner"
    ],
    "wof:name":"Denny's",
    "wof:placetype":"venue"
},
  "geometry": {"coordinates":[-78.751634,42.797563],"type":"Point"}
}