{
  "type": "Feature",
  "properties": {
    "iso:country":"US",
    "sg:address":"50 State St",
    "sg:city":"Pittsford",
    "sg:classifiers":[
        {
            "category":"Shopping",
            "subcategory":"Gifts & Souvenirs",
            "type":"Retail Goods"
        }
    ],
    "sg:phone":"+1   ",
    "sg:postcode":"14534",
    "sg:province":"NY",
    "sg:tags":[
        "shop"
    ],
    "wof:name":"The Pedestal Inc",
    "wof:placetype":"venue"
},
  "geometry": {"coordinates":[-77.510639,43.089333],"type":"Point"}
}