{
  "type": "Feature",
  "properties": {
    "iso:country":"US",
    "sg:address":"163 Park St",
    "sg:city":"Malone",
    "sg:classifiers":[
        {
            "category":"Professional",
            "subcategory":"Lawyer & Legal Services",
            "type":"Services"
        }
    ],
    "sg:phone":"+1 518 483 6171",
    "sg:postcode":"12953",
    "sg:province":"NY",
    "sg:tags":[
        "attorney",
        "practice",
        "general"
    ],
    "wof:name":"Lillian A Anderson-Duffy",
    "wof:placetype":"venue"
},
  "geometry": {"coordinates":[-74.292495,44.858219],"type":"Point"}
}