{
  "type": "Feature",
  "properties": {
    "iso:country":"US",
    "sg:address":"1200 Waters Place",
    "sg:city":"Bronx",
    "sg:classifiers":[
        {
            "category":"Social Services",
            "subcategory":"Child Care",
            "type":"Services"
        },
        {
            "category":"Education",
            "subcategory":"School",
            "type":"Public Place"
        }
    ],
    "sg:phone":"+1 718 239 1062",
    "sg:postcode":"10461",
    "sg:province":"NY",
    "sg:tags":[
        "day"
    ],
    "sg:website":"www.childrenscornergroup.com",
    "wof:name":"Children's Corner Learning Center",
    "wof:placetype":"venue"
},
  "geometry": {"coordinates":[-73.838374,40.842658],"type":"Point"}
}