{
  "type": "Feature",
  "properties": {
    "addr:full":"1740 E Tremont Ave Bronx NY 10460",
    "addr:housenumber":"1740",
    "addr:postcode":"10460",
    "addr:street":"E Tremont Ave",
    "iso:country":"US",
    "sg:address":"1740 E Tremont Ave",
    "sg:city":"Bronx",
    "sg:classifiers":[
        {
            "category":"Retail",
            "subcategory":"Repair Shop",
            "type":"Services"
        }
    ],
    "sg:phone":"+1 718 409 9562",
    "sg:postcode":"10460",
    "sg:province":"NY",
    "sg:tags":[
        "work",
        "iron"
    ],
    "wof:name":"Dynamic Welding Inc",
    "wof:placetype":"venue"
},
  "geometry": {"coordinates":[-73.86951000000001,40.839381],"type":"Point"}
}