{
  "type": "Feature",
  "properties": {
    "iso:country":"US",
    "sg:address":"12807 Merrick Blvd",
    "sg:city":"Jamaica",
    "sg:classifiers":[
        {
            "category":"Retail",
            "subcategory":"Laundry & Dry Cleaning",
            "type":"Services"
        }
    ],
    "sg:phone":"+1 718 977 0870",
    "sg:postcode":"11434",
    "sg:province":"NY",
    "wof:name":"Rite Centers Clean",
    "wof:placetype":"venue"
},
  "geometry": {"coordinates":[-73.76465399999999,40.68139],"type":"Point"}
}