{
  "type": "Feature",
  "properties": {
    "iso:country":"US",
    "sg:address":"2600 State Rte 20A",
    "sg:city":"Varysburg",
    "sg:classifiers":[
        {
            "category":"Food & Beverages",
            "subcategory":"Groceries & Convenience Stores",
            "type":"Retail Goods"
        }
    ],
    "sg:phone":"+1   ",
    "sg:postcode":"14167",
    "sg:province":"NY",
    "sg:tags":[
        "filling",
        "station"
    ],
    "wof:name":"C & G Praller Grocery Inc",
    "wof:placetype":"venue"
},
  "geometry": {"coordinates":[-78.308081,42.75758],"type":"Point"}
}