{
  "type": "Feature",
  "properties": {
    "iso:country":"US",
    "sg:address":"197 Lakeshore Dr",
    "sg:city":"Monticello",
    "sg:classifiers":[
        {
            "category":"Building & Trades",
            "subcategory":"Construction",
            "type":"Services"
        }
    ],
    "sg:phone":"+1 845 791 8305",
    "sg:postcode":"12701",
    "sg:province":"NY",
    "sg:tags":[
        "home",
        "builder"
    ],
    "wof:name":"Habitat For Humanity",
    "wof:placetype":"venue"
},
  "geometry": {"coordinates":[-74.780067,41.645945],"type":"Point"}
}