{
  "type": "Feature",
  "properties": {
    "iso:country":"US",
    "sg:address":"12 Cedar Ln",
    "sg:city":"Poughkeepsie",
    "sg:classifiers":[
        {
            "category":"Banks & Credit Unions",
            "subcategory":"Bank",
            "type":"Services"
        },
        {
            "category":"Banks & Credit Unions",
            "subcategory":"Financial Services",
            "type":"Services"
        }
    ],
    "sg:phone":"+1 845 454 1026",
    "sg:postcode":"12601",
    "sg:province":"NY",
    "wof:name":"Fleet D",
    "wof:placetype":"venue"
},
  "geometry": {"coordinates":[-73.91490899999999,41.740606],"type":"Point"}
}