{
  "type": "Feature",
  "properties": {
    "addr:full":"164 Lockwood Ave Yonkers NY 10701",
    "addr:housenumber":"164",
    "addr:postcode":"10701",
    "addr:street":"Lockwood Ave",
    "iso:country":"US",
    "sg:address":"164 Lockwood Ave",
    "sg:city":"Yonkers",
    "sg:classifiers":[
        {
            "category":"Wholesale",
            "subcategory":"Painting Supplies",
            "type":"Manufacturing & Wholesale Goods"
        }
    ],
    "sg:phone":"+1 914 964 5412",
    "sg:postcode":"10701",
    "sg:province":"NY",
    "sg:tags":[
        "tape"
    ],
    "wof:name":"Briker Sales & Packaging Co",
    "wof:placetype":"venue"
},
  "geometry": {"coordinates":[-73.86656600000001,40.948378],"type":"Point"}
}