{
  "type": "Feature",
  "properties": {
    "addr:full":"1808 Lurting Ave Bronx NY 10461",
    "addr:housenumber":"1808",
    "addr:postcode":"10461",
    "addr:street":"Lurting Ave",
    "iso:country":"US",
    "sg:address":"1808 Lurting Ave",
    "sg:city":"Bronx",
    "sg:classifiers":[
        {
            "category":"Personal",
            "subcategory":"Barber",
            "type":"Services"
        }
    ],
    "sg:phone":"+1 718 409 5814",
    "sg:postcode":"10461",
    "sg:province":"NY",
    "wof:name":"Big Jay Barber Shop",
    "wof:placetype":"venue"
},
  "geometry": {"coordinates":[-73.85522400000001,40.851022],"type":"Point"}
}