{
  "type": "Feature",
  "properties": {
    "iso:country":"US",
    "sg:address":"5748 Sunrise Hwy",
    "sg:city":"Sayville",
    "sg:classifiers":[
        {
            "category":"Professional",
            "type":"Services"
        }
    ],
    "sg:phone":"+1 631 218 3306",
    "sg:postcode":"11782",
    "sg:province":"NY",
    "sg:tags":[
        "establishment"
    ],
    "wof:name":"Cheesecake King",
    "wof:placetype":"venue"
},
  "geometry": {"coordinates":[-73.07117,40.767624],"type":"Point"}
}