{
  "type": "Feature",
  "properties": {
    "iso:country":"US",
    "sg:address":"121 Broadway",
    "sg:city":"Lynbrook",
    "sg:classifiers":[
        {
            "category":"Personal",
            "subcategory":"Beauty Salon",
            "type":"Services"
        },
        {
            "category":"Personal",
            "subcategory":"Tanning Parlor",
            "type":"Services"
        }
    ],
    "sg:phone":"+1 516 284 7574",
    "sg:postcode":"11563",
    "sg:province":"NY",
    "wof:name":"Lee And King Incorporated",
    "wof:placetype":"venue"
},
  "geometry": {"coordinates":[-73.676176,40.654146],"type":"Point"}
}