{
  "type": "Feature",
  "properties": {
    "addr:full":"76 Green St Hudson NY 12534",
    "addr:housenumber":"76",
    "addr:postcode":"12534",
    "addr:street":"Green St",
    "iso:country":"US",
    "sg:address":"76 Green St",
    "sg:city":"Hudson",
    "sg:classifiers":[
        {
            "category":"Professional",
            "subcategory":"Lawyer & Legal Services",
            "type":"Services"
        }
    ],
    "sg:phone":"+1 518 828 2712",
    "sg:postcode":"12534",
    "sg:province":"NY",
    "wof:name":"Connor John Jr Atty",
    "wof:placetype":"venue"
},
  "geometry": {"coordinates":[-73.777584,42.248732],"type":"Point"}
}