{
  "type": "Feature",
  "properties": {
    "iso:country":"US",
    "sg:address":"29 E 19 St",
    "sg:city":"New York",
    "sg:classifiers":[
        {
            "category":"Professional",
            "subcategory":"Business Services",
            "type":"Services"
        }
    ],
    "sg:phone":"+1 212 253 5955",
    "sg:postcode":"10003",
    "sg:province":"NY",
    "wof:name":"Harry's Loft",
    "wof:placetype":"venue"
},
  "geometry": {"coordinates":[-73.98826200000001,40.737875],"type":"Point"}
}