{
  "type": "Feature",
  "properties": {
    "addr:full":"331 New Dorp Lane Staten Island NY 10306",
    "addr:housenumber":"331",
    "addr:postcode":"10306",
    "addr:street":"New Dorp Lane",
    "iso:country":"US",
    "sg:address":"331 New Dorp Lane",
    "sg:city":"Staten Island",
    "sg:classifiers":[
        {
            "category":"Restaurant",
            "type":"Food & Drink"
        }
    ],
    "sg:phone":"+1 718 987 2323",
    "sg:postcode":"10306",
    "sg:province":"NY",
    "sg:tags":[
        "chinese"
    ],
    "wof:name":"King's Chef",
    "wof:placetype":"venue"
},
  "geometry": {"coordinates":[-74.11139,40.571477],"type":"Point"}
}