{
  "type": "Feature",
  "properties": {
    "iso:country":"US",
    "sg:address":"485 W John St",
    "sg:city":"Hicksville",
    "sg:classifiers":[
        {
            "category":"Arts & Performance",
            "subcategory":"Theater",
            "type":"Entertainment"
        }
    ],
    "sg:phone":"+1 516 681 5288",
    "sg:postcode":"11801",
    "sg:province":"NY",
    "sg:tags":[
        "equipment",
        "theatrical",
        "supply"
    ],
    "sg:website":"www.litetrol.com",
    "wof:name":"Lite-Trol Svc Co",
    "wof:placetype":"venue"
},
  "geometry": {"coordinates":[-73.54591499999999,40.765642],"type":"Point"}
}