{
  "type": "Feature",
  "properties": {
    "iso:country":"US",
    "sg:address":"380 Madison Ave",
    "sg:city":"New York",
    "sg:classifiers":[
        {
            "category":"Professional",
            "type":"Services"
        }
    ],
    "sg:phone":"+1 212 856 4442",
    "sg:postcode":"10017",
    "sg:province":"NY",
    "sg:tags":[
        "establishment"
    ],
    "wof:name":"Kathleen Boyle Wheat First But",
    "wof:placetype":"venue"
},
  "geometry": {"coordinates":[-73.97711099999999,40.75586],"type":"Point"}
}