{
  "type": "Feature",
  "properties": {
    "addr:full":"5505 Broadway St Lancaster NY 14086",
    "addr:housenumber":"5505",
    "addr:postcode":"14086",
    "addr:street":"Broadway St",
    "iso:country":"US",
    "sg:address":"5505 Broadway St",
    "sg:city":"Lancaster",
    "sg:classifiers":[
        {
            "category":"Organizations",
            "subcategory":"Religious Organization",
            "type":"Services"
        }
    ],
    "sg:phone":"+1 716 683 5293",
    "sg:postcode":"14086",
    "sg:province":"NY",
    "sg:website":"www.faithlancaster.org",
    "wof:name":"Faith United Methodist Church",
    "wof:placetype":"venue"
},
  "geometry": {"coordinates":[-78.66745,42.899657],"type":"Point"}
}