{
  "type": "Feature",
  "properties": {
    "addr:full":"7457 Seneca Rd N Hornell NY 14843",
    "addr:housenumber":"7457",
    "addr:postcode":"14843",
    "addr:street":"Seneca Rd N Hornell",
    "iso:country":"US",
    "sg:address":"7457 Seneca Rd N",
    "sg:city":"Hornell",
    "sg:classifiers":[
        {
            "category":"Autos & Motor Vehicles",
            "subcategory":"Automobile Sales",
            "type":"Retail Goods"
        }
    ],
    "sg:phone":"+1   ",
    "sg:postcode":"14843",
    "sg:province":"NY",
    "sg:tags":[
        "used"
    ],
    "wof:name":"Guthries Repair Shop",
    "wof:placetype":"venue"
},
  "geometry": {"coordinates":[-77.665296,42.361444],"type":"Point"}
}