{
  "type": "Feature",
  "properties": {
    "iso:country":"US",
    "sg:address":"156 S Broadway",
    "sg:city":"Yonkers",
    "sg:classifiers":[
        {
            "category":"Personal",
            "subcategory":"Barber",
            "type":"Services"
        }
    ],
    "sg:phone":"+1 914 423 0652",
    "sg:postcode":"10701",
    "sg:province":"NY",
    "wof:name":"Gabriel Barber Shop Unisez",
    "wof:placetype":"venue"
},
  "geometry": {"coordinates":[-73.896463,40.928923],"type":"Point"}
}