{
  "type": "Feature",
  "properties": {
    "addr:full":"421 W 13th St New York NY 10014",
    "addr:housenumber":"421",
    "addr:postcode":"10014",
    "addr:street":"W 13Th St",
    "iso:country":"US",
    "sg:address":"421 W 13th St",
    "sg:city":"New York",
    "sg:classifiers":[
        {
            "category":"Shopping",
            "subcategory":"Books",
            "type":"Retail Goods"
        }
    ],
    "sg:phone":"+1 212 278 8214",
    "sg:postcode":"10014",
    "sg:province":"NY",
    "sg:tags":[
        "bookstore"
    ],
    "sg:website":"www.rag-bone.com",
    "wof:name":"Rag & Bone LLC",
    "wof:placetype":"venue"
},
  "geometry": {"coordinates":[-74.73561100000001,40.740778],"type":"Point"}
}