{
  "type": "Feature",
  "properties": {
    "iso:country":"US",
    "sg:address":"559 US Hwy 6",
    "sg:city":"Mahopac",
    "sg:classifiers":[
        {
            "category":"Insurance",
            "subcategory":"Insurance Agent",
            "type":"Services"
        }
    ],
    "sg:phone":"+1 845 628 2828",
    "sg:postcode":"10541",
    "sg:province":"NY",
    "wof:name":"Allstate",
    "wof:placetype":"venue"
},
  "geometry": {"coordinates":[-73.75240700000001,41.350614],"type":"Point"}
}