{
  "type": "Feature",
  "properties": {
    "addr:full":"1807 Brentwood Rd Brentwood NY 11717",
    "addr:housenumber":"1807",
    "addr:postcode":"11717",
    "addr:street":"Brentwood Rd",
    "iso:country":"US",
    "sg:address":"1807 Brentwood Rd",
    "sg:city":"Brentwood",
    "sg:classifiers":[
        {
            "category":"Personal",
            "subcategory":"Beauty Salon",
            "type":"Services"
        }
    ],
    "sg:phone":"+1   ",
    "sg:postcode":"11717",
    "sg:province":"NY",
    "sg:tags":[
        "shop"
    ],
    "wof:name":"P C Nail Salon II",
    "wof:placetype":"venue"
},
  "geometry": {"coordinates":[-73.246098,40.778462],"type":"Point"}
}