{
  "type": "Feature",
  "properties": {
    "iso:country":"US",
    "sg:address":"1390 Boston Rd",
    "sg:city":"Bronx",
    "sg:classifiers":[
        {
            "category":"Shopping",
            "subcategory":"Computers & Home Electronics",
            "type":"Retail Goods"
        }
    ],
    "sg:phone":"+1 718 861 4604",
    "sg:postcode":"10456",
    "sg:province":"NY",
    "sg:tags":[
        "equipment",
        "electronic",
        "supply"
    ],
    "wof:name":"C W Electronics",
    "wof:placetype":"venue"
},
  "geometry": {"coordinates":[-73.896771,40.833223],"type":"Point"}
}