{
  "type": "Feature",
  "properties": {
    "iso:country":"US",
    "sg:address":"15 Ives Rd",
    "sg:city":"Hewlett",
    "sg:classifiers":[
        {
            "category":"Health Services",
            "subcategory":"Health Practitioner",
            "type":"Services"
        }
    ],
    "sg:phone":"+1   ",
    "sg:postcode":"11557",
    "sg:province":"NY",
    "wof:name":"Laurie Zelinger PHD",
    "wof:placetype":"venue"
},
  "geometry": {"coordinates":[-73.70121399999999,40.637105],"type":"Point"}
}