{
  "type": "Feature",
  "properties": {
    "addr:full":"214 E Church St Elmira NY 14901",
    "addr:housenumber":"214",
    "addr:postcode":"14901",
    "addr:street":"E Church St",
    "iso:country":"US",
    "sg:address":"214 E Church St",
    "sg:city":"Elmira",
    "sg:classifiers":[
        {
            "category":"Professional",
            "subcategory":"Management & Consulting",
            "type":"Services"
        }
    ],
    "sg:phone":"+1   ",
    "sg:postcode":"14901",
    "sg:province":"NY",
    "sg:tags":[
        "real estate"
    ],
    "wof:name":"T J Yunis Real Estate",
    "wof:placetype":"venue"
},
  "geometry": {"coordinates":[-76.804886,42.090671],"type":"Point"}
}