{
  "type": "Feature",
  "properties": {
    "addr:full":"3603 28th Avenue Astoria NY 11103",
    "addr:housenumber":"3603",
    "addr:postcode":"11103",
    "addr:street":"28Th Avenue",
    "iso:country":"US",
    "sg:address":"3603 28th Avenue",
    "sg:city":"Astoria",
    "sg:classifiers":[
        {
            "category":"Professional",
            "subcategory":"Accounting & Tax Preparation",
            "type":"Services"
        }
    ],
    "sg:phone":"+1 718 204 5400",
    "sg:postcode":"11103",
    "sg:province":"NY",
    "sg:tags":[
        "accountant"
    ],
    "wof:name":"Timotheou Theodoros CPA",
    "wof:placetype":"venue"
},
  "geometry": {"coordinates":[-73.915717,40.766553],"type":"Point"}
}