{
  "type": "Feature",
  "properties": {
    "iso:country":"US",
    "sg:address":"1975 Amsterdam Ave",
    "sg:city":"New York",
    "sg:classifiers":[
        {
            "category":"Personal",
            "type":"Services"
        }
    ],
    "sg:phone":"+1 212 507 9050",
    "sg:postcode":"10032",
    "sg:province":"NY",
    "sg:tags":[
        "towing"
    ],
    "wof:name":"Tow",
    "wof:placetype":"venue"
},
  "geometry": {"coordinates":[-73.94180299999999,40.833401],"type":"Point"}
}