{
  "type": "Feature",
  "properties": {
    "addr:full":"288 Halleck St Bronx NY 10474",
    "addr:housenumber":"288",
    "addr:postcode":"10474",
    "addr:street":"Halleck St",
    "iso:country":"US",
    "sg:address":"288 Halleck St",
    "sg:city":"Bronx",
    "sg:classifiers":[
        {
            "category":"Wholesale",
            "subcategory":"Auto Parts",
            "type":"Manufacturing & Wholesale Goods"
        }
    ],
    "sg:phone":"+1 718 589 7733",
    "sg:postcode":"10474",
    "sg:province":"NY",
    "sg:tags":[
        "automobile",
        "wrecking"
    ],
    "wof:name":"Oil Extractors Of America Inc",
    "wof:placetype":"venue"
},
  "geometry": {"coordinates":[-73.87963999999999,40.8058],"type":"Point"}
}