{
  "type": "Feature",
  "properties": {
    "iso:country":"US",
    "sg:address":"7 Flowerfield",
    "sg:city":"Saint James",
    "sg:classifiers":[
        {
            "category":"Arena",
            "subcategory":"Sports Club",
            "type":"Entertainment"
        }
    ],
    "sg:phone":"+1 631 949 0109",
    "sg:postcode":"11780",
    "sg:province":"NY",
    "sg:tags":[
        "martial art"
    ],
    "sg:website":"askd.us",
    "wof:name":"Shotokan Kodokan Dojo",
    "wof:placetype":"venue"
},
  "geometry": {"coordinates":[-73.146224,40.895855],"type":"Point"}
}