{
  "type": "Feature",
  "properties": {
    "iso:country":"US",
    "sg:address":"360 E 55th St",
    "sg:city":"New York",
    "sg:classifiers":[
        {
            "category":"Bakery",
            "type":"Food & Drink"
        }
    ],
    "sg:phone":"+1 212 838 5411",
    "sg:postcode":"10022",
    "sg:province":"NY",
    "wof:name":"Wine and Roses Gift Baskets",
    "wof:placetype":"venue"
},
  "geometry": {"coordinates":[-73.96489699999999,40.757401],"type":"Point"}
}