{
  "type": "Feature",
  "properties": {
    "addr:full":"2 Beacon Hill Rd Port Washington NY 11050",
    "addr:housenumber":"2",
    "addr:postcode":"11050",
    "addr:street":"Beacon Hill Rd",
    "iso:country":"US",
    "sg:address":"2 Beacon Hill Rd",
    "sg:city":"Port Washington",
    "sg:classifiers":[
        {
            "category":"Organizations",
            "subcategory":"Religious Organization",
            "type":"Services"
        }
    ],
    "sg:phone":"+1 516 883 1977",
    "sg:postcode":"11050",
    "sg:province":"NY",
    "sg:tags":[
        "church"
    ],
    "wof:name":"N Y Philadelphia Presbyterian",
    "wof:placetype":"venue"
},
  "geometry": {"coordinates":[-73.683722,40.83238],"type":"Point"}
}