{
  "type": "Feature",
  "properties": {
    "iso:country":"US",
    "sg:address":"738 Black Oak Rd",
    "sg:city":"Newfield",
    "sg:classifiers":[
        {
            "category":"Wholesale",
            "subcategory":"Scrap",
            "type":"Manufacturing & Wholesale Goods"
        }
    ],
    "sg:phone":"+1 607 272 1908",
    "sg:postcode":"14867",
    "sg:province":"NY",
    "sg:tags":[
        "metal",
        "iron"
    ],
    "wof:name":"Teets & Son Scrap Metal Rcylng",
    "wof:placetype":"venue"
},
  "geometry": {"coordinates":[-76.667348,42.395212],"type":"Point"}
}