{
  "type": "Feature",
  "properties": {
    "addr:full":"36 Grand Ave Northport NY 11768",
    "addr:housenumber":"36",
    "addr:postcode":"11768",
    "addr:street":"Grand Ave",
    "iso:country":"US",
    "sg:address":"36 Grand Ave",
    "sg:city":"Northport",
    "sg:classifiers":[
        {
            "category":"Building & Trades",
            "subcategory":"Plumbing",
            "type":"Services"
        }
    ],
    "sg:phone":"+1 631 261 7412",
    "sg:postcode":"11768",
    "sg:province":"NY",
    "wof:name":"Bob's Plumbing & Heating",
    "wof:placetype":"venue"
},
  "geometry": {"coordinates":[-73.330399,40.927502],"type":"Point"}
}