{
  "type": "Feature",
  "properties": {
    "addr:full":"20 W Fairview Ave Valley Stream NY 11580",
    "addr:housenumber":"20",
    "addr:postcode":"11580",
    "addr:street":"W Fairview Ave",
    "iso:country":"US",
    "sg:address":"20 W Fairview Ave",
    "sg:city":"Valley Stream",
    "sg:classifiers":[
        {
            "category":"Freight",
            "type":"Transportation"
        }
    ],
    "sg:phone":"+1 516 825 3330",
    "sg:postcode":"11580",
    "sg:province":"NY",
    "wof:name":"Eagle Transport Svc",
    "wof:placetype":"venue"
},
  "geometry": {"coordinates":[-73.69967200000001,40.663657],"type":"Point"}
}