{
  "type": "Feature",
  "properties": {
    "addr:full":"1237 College Ave Bronx NY 10456",
    "addr:housenumber":"1237",
    "addr:postcode":"10456",
    "addr:street":"College Ave",
    "iso:country":"US",
    "sg:address":"1237 College Ave",
    "sg:city":"Bronx",
    "sg:classifiers":[
        {
            "category":"Building & Trades",
            "subcategory":"Cleaning & Sanitation",
            "type":"Services"
        }
    ],
    "sg:phone":"+1 718 618 0100",
    "sg:postcode":"10456",
    "sg:province":"NY",
    "sg:tags":[
        "home"
    ],
    "wof:name":"Martinez",
    "wof:placetype":"venue"
},
  "geometry": {"coordinates":[-73.912964,40.833778],"type":"Point"}
}