{
  "type": "Feature",
  "properties": {
    "addr:full":"3012 Bond Dr Merrick NY 11566",
    "addr:housenumber":"3012",
    "addr:postcode":"11566",
    "addr:street":"Bond Dr",
    "iso:country":"US",
    "sg:address":"3012 Bond Dr",
    "sg:city":"Merrick",
    "sg:classifiers":[
        {
            "category":"Building & Trades",
            "subcategory":"Construction",
            "type":"Services"
        }
    ],
    "sg:phone":"+1 516 623 3447",
    "sg:postcode":"11566",
    "sg:province":"NY",
    "sg:tags":[
        "contractor"
    ],
    "wof:name":"L K Consultants Inc",
    "wof:placetype":"venue"
},
  "geometry": {"coordinates":[-73.550943,40.644194],"type":"Point"}
}