{
  "type": "Feature",
  "properties": {
    "iso:country":"US",
    "sg:address":"10 Thompson Pl",
    "sg:city":"Larchmont",
    "sg:classifiers":[
        {
            "category":"Banks & Credit Unions",
            "subcategory":"Financial Services",
            "type":"Services"
        }
    ],
    "sg:phone":"+1 914 834 8506",
    "sg:postcode":"10538",
    "sg:province":"NY",
    "sg:tags":[
        "trust",
        "investment",
        "real estate"
    ],
    "wof:name":"Thompson Partners LLC",
    "wof:placetype":"venue"
},
  "geometry": {"coordinates":[-73.750466,40.929945],"type":"Point"}
}