{
  "type": "Feature",
  "properties": {
    "addr:full":"3506 Broadway Astoria NY 11106",
    "addr:housenumber":"3506",
    "addr:postcode":"11106",
    "addr:street":"Broadway",
    "iso:country":"US",
    "sg:address":"3506 Broadway",
    "sg:city":"Astoria",
    "sg:classifiers":[
        {
            "category":"Building & Trades",
            "subcategory":"Locksmith",
            "type":"Services"
        }
    ],
    "sg:phone":"+1 718 807 4236",
    "sg:postcode":"11106",
    "sg:province":"NY",
    "sg:tags":[
        "key"
    ],
    "wof:name":"Progressive Locksmith",
    "wof:placetype":"venue"
},
  "geometry": {"coordinates":[-73.921898,40.760201],"type":"Point"}
}