{
  "type": "Feature",
  "properties": {
    "addr:full":"5268 Main St Williamsville NY 14221",
    "addr:housenumber":"5268",
    "addr:postcode":"14221",
    "addr:street":"Main St",
    "iso:country":"US",
    "sg:address":"5268 Main St",
    "sg:city":"Williamsville",
    "sg:classifiers":[
        {
            "category":"Restaurant",
            "type":"Food & Drink"
        }
    ],
    "sg:phone":"+1 716 633 5033",
    "sg:postcode":"14221",
    "sg:province":"NY",
    "sg:tags":[
        "asian",
        "chinese",
        "pan"
    ],
    "wof:name":"Bamboo China Restaurant",
    "wof:placetype":"venue"
},
  "geometry": {"coordinates":[-78.756686,42.960914],"type":"Point"}
}