{
  "type": "Feature",
  "properties": {
    "iso:country":"US",
    "sg:address":"193 Griffing Ave",
    "sg:city":"Riverhead",
    "sg:classifiers":[
        {
            "category":"Freight",
            "type":"Transportation"
        },
        {
            "category":"Personal",
            "type":"Services"
        }
    ],
    "sg:phone":"+1 631 727 6802",
    "sg:postcode":"11901",
    "sg:province":"NY",
    "sg:tags":[
        "commercial",
        "storage",
        "special"
    ],
    "wof:name":"Westhampton Mini Storage",
    "wof:placetype":"venue"
},
  "geometry": {"coordinates":[-72.66586599999999,40.919649],"type":"Point"}
}