{
  "type": "Feature",
  "properties": {
    "iso:country":"US",
    "sg:address":"110 Partrick Dr",
    "sg:city":"Pulaski",
    "sg:classifiers":[
        {
            "category":"Travel",
            "subcategory":"Campground",
            "type":"Entertainment"
        }
    ],
    "sg:phone":"+1   ",
    "sg:postcode":"13142",
    "sg:province":"NY",
    "sg:tags":[
        "camp"
    ],
    "wof:name":"Chedlard Campsite",
    "wof:placetype":"venue"
},
  "geometry": {"coordinates":[-76.20115699999999,43.541978],"type":"Point"}
}