{
  "type": "Feature",
  "properties": {
    "addr:full":"4722 48th St Woodside NY 11377",
    "addr:housenumber":"4722",
    "addr:postcode":"11377",
    "addr:street":"48Th St",
    "iso:country":"US",
    "sg:address":"4722 48th St",
    "sg:city":"Woodside",
    "sg:classifiers":[
        {
            "category":"Cafe",
            "type":"Food & Drink"
        }
    ],
    "sg:menulink":"http://www.allmenus.com/ny/queens/93954-the-haab-mexican-cafe/menu/",
    "sg:phone":"+1 718 729 4838",
    "sg:postcode":"11377",
    "sg:province":"NY",
    "sg:tags":[
        "mexican"
    ],
    "wof:name":"The Haab Mexican Cafe",
    "wof:placetype":"venue"
},
  "geometry": {"coordinates":[-73.91732500000001,40.740516],"type":"Point"}
}