{
  "type": "Feature",
  "properties": {
    "addr:full":"1350 Ralph Ave Brooklyn NY 11236",
    "addr:housenumber":"1350",
    "addr:postcode":"11236",
    "addr:street":"Ralph Ave",
    "iso:country":"US",
    "sg:address":"1350 Ralph Ave",
    "sg:city":"Brooklyn",
    "sg:classifiers":[
        {
            "category":"Wholesale",
            "subcategory":"Medical Equipment & Supplies",
            "type":"Manufacturing & Wholesale Goods"
        }
    ],
    "sg:phone":"+1 718 415 3735",
    "sg:postcode":"11236",
    "sg:province":"NY",
    "wof:name":"E Dash Kit Inc",
    "wof:placetype":"venue"
},
  "geometry": {"coordinates":[-73.919826,40.642995],"type":"Point"}
}