{
  "type": "Feature",
  "properties": {
    "iso:country":"US",
    "sg:address":"837 Niagara St",
    "sg:city":"Buffalo",
    "sg:classifiers":[
        {
            "category":"Food & Beverages",
            "subcategory":"Groceries & Convenience Stores",
            "type":"Retail Goods"
        }
    ],
    "sg:phone":"+1 716 884 4144",
    "sg:postcode":"14213",
    "sg:province":"NY",
    "wof:name":"99 Oriental Food Store",
    "wof:placetype":"venue"
},
  "geometry": {"coordinates":[-78.897003,42.906101],"type":"Point"}
}