{
  "type": "Feature",
  "properties": {
    "addr:full":"54 Seymour St Auburn NY 13021",
    "addr:housenumber":"54",
    "addr:postcode":"13021",
    "addr:street":"Seymour St",
    "iso:country":"US",
    "sg:address":"54 Seymour St",
    "sg:city":"Auburn",
    "sg:classifiers":[
        {
            "category":"Personal",
            "subcategory":"Beauty Salon",
            "type":"Services"
        }
    ],
    "sg:phone":"+1   ",
    "sg:postcode":"13021",
    "sg:province":"NY",
    "sg:tags":[
        "shop"
    ],
    "wof:name":"Studio 54 Full Service Salon",
    "wof:placetype":"venue"
},
  "geometry": {"coordinates":[-76.561273,42.937912],"type":"Point"}
}