{
  "type": "Feature",
  "properties": {
    "iso:country":"US",
    "sg:address":"719 S Meadow St",
    "sg:city":"Ithaca",
    "sg:classifiers":[
        {
            "category":"Cinema",
            "subcategory":"Movie Rental",
            "type":"Entertainment"
        }
    ],
    "sg:phone":"+1 607 272 4864",
    "sg:postcode":"14850",
    "sg:province":"NY",
    "sg:tags":[
        "video",
        "game",
        "leasing"
    ],
    "sg:website":"www.gamecrazy.com",
    "wof:name":"Game Crazy",
    "wof:placetype":"venue"
},
  "geometry": {"coordinates":[-76.507958,42.432416],"type":"Point"}
}