{
  "type": "Feature",
  "properties": {
    "iso:country":"US",
    "sg:address":"284 Oakwood Rd",
    "sg:city":"Huntington Station",
    "sg:classifiers":[
        {
            "category":"Health Services",
            "subcategory":"Doctor",
            "type":"Services"
        }
    ],
    "sg:phone":"+1 631 423 2110",
    "sg:postcode":"11746",
    "sg:province":"NY",
    "sg:tags":[
        "dermatologist"
    ],
    "wof:name":"Maiwald Diane C MD",
    "wof:placetype":"venue"
},
  "geometry": {"coordinates":[-73.431,40.845699],"type":"Point"}
}