{
  "type": "Feature",
  "properties": {
    "iso:country":"US",
    "sg:address":"176 Sheridan Blvd",
    "sg:city":"Inwood",
    "sg:classifiers":[
        {
            "category":"Home & Garden",
            "subcategory":"Household Appliances",
            "type":"Retail Goods"
        }
    ],
    "sg:phone":"+1 516 371 3560",
    "sg:postcode":"11096",
    "sg:province":"NY",
    "wof:name":"Dependable Home Appliance Inc",
    "wof:placetype":"venue"
},
  "geometry": {"coordinates":[-73.75179900000001,40.616117],"type":"Point"}
}