{
  "type": "Feature",
  "properties": {
    "iso:country":"US",
    "sg:address":"6320 11th Avenue",
    "sg:city":"Brooklyn",
    "sg:classifiers":[
        {
            "category":"Professional",
            "subcategory":"Computer Services",
            "type":"Services"
        }
    ],
    "sg:phone":"+1 718 238 9639",
    "sg:postcode":"11219",
    "sg:province":"NY",
    "sg:tags":[
        "repair"
    ],
    "wof:name":"Sig228 Communications Group",
    "wof:placetype":"venue"
},
  "geometry": {"coordinates":[-74.004847,40.629703],"type":"Point"}
}