{
  "type": "Feature",
  "properties": {
    "iso:country":"US",
    "sg:address":"980 Atlantic Ave",
    "sg:city":"Brooklyn",
    "sg:classifiers":[
        {
            "category":"Parking",
            "type":"Transportation"
        }
    ],
    "sg:phone":"+1 718 622 9699",
    "sg:postcode":"11238",
    "sg:province":"NY",
    "sg:tags":[
        "attendant"
    ],
    "wof:name":"976-984 Atlantic Parking Corp",
    "wof:placetype":"venue"
},
  "geometry": {"coordinates":[-73.96269700000001,40.680771],"type":"Point"}
}