{
  "type": "Feature",
  "properties": {
    "addr:full":"194 E 10th St Huntington Station NY 11746",
    "addr:housenumber":"194",
    "addr:postcode":"11746",
    "addr:street":"E 10Th St",
    "iso:country":"US",
    "sg:address":"194 E 10th St",
    "sg:city":"Huntington Station",
    "sg:classifiers":[
        {
            "category":"Building & Trades",
            "subcategory":"Cleaning & Sanitation",
            "type":"Services"
        }
    ],
    "sg:phone":"+1 631 427 5384",
    "sg:postcode":"11746",
    "sg:province":"NY",
    "sg:tags":[
        "house",
        "maintenance"
    ],
    "wof:name":"Palace Cleaning Svces",
    "wof:placetype":"venue"
},
  "geometry": {"coordinates":[-73.40143500000001,40.848148],"type":"Point"}
}