{
  "type": "Feature",
  "properties": {
    "addr:full":"350 Warburton Ave Yonkers NY 10701",
    "addr:housenumber":"350",
    "addr:postcode":"10701",
    "addr:street":"Warburton Ave",
    "iso:country":"US",
    "sg:address":"350 Warburton Ave",
    "sg:city":"Yonkers",
    "sg:classifiers":[
        {
            "category":"Building & Trades",
            "subcategory":"Construction",
            "type":"Services"
        }
    ],
    "sg:phone":"+1 914 476 3610",
    "sg:postcode":"10701",
    "sg:province":"NY",
    "sg:tags":[
        "repairing",
        "remodeling",
        "contractor"
    ],
    "wof:name":"Allied Renovation Corp",
    "wof:placetype":"venue"
},
  "geometry": {"coordinates":[-73.896406,40.947826],"type":"Point"}
}