{
  "type": "Feature",
  "properties": {
    "addr:full":"8118 3rd Avenue Brooklyn NY 11209",
    "addr:housenumber":"8118",
    "addr:postcode":"11209",
    "addr:street":"3Rd Avenue",
    "iso:country":"US",
    "sg:address":"8118 3rd Avenue",
    "sg:city":"Brooklyn",
    "sg:classifiers":[
        {
            "category":"Retail",
            "subcategory":"Laundry & Dry Cleaning",
            "type":"Services"
        }
    ],
    "sg:phone":"+1 718 921 5100",
    "sg:postcode":"11209",
    "sg:province":"NY",
    "wof:name":"NY'S - Finest 2 French Cleaners, Inc.",
    "wof:placetype":"venue"
},
  "geometry": {"coordinates":[-74.03008199999999,40.626609],"type":"Point"}
}