{
  "type": "Feature",
  "properties": {
    "addr:full":"957 Arsenal St Watertown NY 13601",
    "addr:housenumber":"957",
    "addr:postcode":"13601",
    "addr:street":"Arsenal St",
    "iso:country":"US",
    "sg:address":"957 Arsenal St",
    "sg:city":"Watertown",
    "sg:classifiers":[
        {
            "category":"Restaurant",
            "type":"Food & Drink"
        }
    ],
    "sg:menulink":"http://www.allmenus.com/ny/watertown/175286-arbys/menu/",
    "sg:phone":"+1 315 782 9809",
    "sg:postcode":"13601",
    "sg:province":"NY",
    "sg:tags":[
        "burger",
        "american"
    ],
    "wof:name":"Arby's",
    "wof:placetype":"venue"
},
  "geometry": {"coordinates":[-75.93311799999999,43.976016],"type":"Point"}
}