{
  "type": "Feature",
  "properties": {
    "addr:full":"1 Riverdale Ave Bronx NY 10463",
    "addr:housenumber":"1",
    "addr:postcode":"10463",
    "addr:street":"Riverdale Ave",
    "iso:country":"US",
    "sg:address":"1 Riverdale Ave",
    "sg:city":"Bronx",
    "sg:classifiers":[
        {
            "category":"Real Estate",
            "subcategory":"Architect",
            "type":"Services"
        }
    ],
    "sg:phone":"+1 718 884 2629",
    "sg:postcode":"10463",
    "sg:province":"NY",
    "wof:name":"T II Corp",
    "wof:placetype":"venue"
},
  "geometry": {"coordinates":[-73.910185,40.880705],"type":"Point"}
}