{
  "type": "Feature",
  "properties": {
    "addr:full":"1416 Willis Ave Syracuse NY 13204",
    "addr:housenumber":"1416",
    "addr:postcode":"13204",
    "addr:street":"Willis Ave",
    "iso:country":"US",
    "sg:address":"1416 Willis Ave",
    "sg:city":"Syracuse",
    "sg:classifiers":[
        {
            "category":"Wholesale",
            "subcategory":"Scrap",
            "type":"Manufacturing & Wholesale Goods"
        }
    ],
    "sg:phone":"+1 315 487 4346",
    "sg:postcode":"13204",
    "sg:province":"NY",
    "sg:tags":[
        "recycling",
        "center"
    ],
    "wof:name":"Syracuse Fiber Recycling",
    "wof:placetype":"venue"
},
  "geometry": {"coordinates":[-76.199488,43.063376],"type":"Point"}
}