{
  "type": "Feature",
  "properties": {
    "addr:full":"104 Touissant Ave Yonkers NY 10710",
    "addr:housenumber":"104",
    "addr:postcode":"10710",
    "addr:street":"Touissant Ave",
    "iso:country":"US",
    "sg:address":"104 Touissant Ave",
    "sg:city":"Yonkers",
    "sg:classifiers":[
        {
            "category":"Personal",
            "type":"Services"
        }
    ],
    "sg:phone":"+1 914 968 5031",
    "sg:postcode":"10710",
    "sg:province":"NY",
    "sg:tags":[
        "car",
        "loading",
        "unloading"
    ],
    "wof:name":"Warburton Movers Inc",
    "wof:placetype":"venue"
},
  "geometry": {"coordinates":[-73.866775,40.956439],"type":"Point"}
}