{
  "type": "Feature",
  "properties": {
    "addr:full":"793 Southern Blvd Bronx NY 10455",
    "addr:housenumber":"793",
    "addr:postcode":"10455",
    "addr:street":"Southern Blvd",
    "iso:country":"US",
    "sg:address":"793 Southern Blvd",
    "sg:city":"Bronx",
    "sg:classifiers":[
        {
            "category":"Food & Beverages",
            "subcategory":"Liquor & Beverages",
            "type":"Retail Goods"
        }
    ],
    "sg:phone":"+1   ",
    "sg:postcode":"10455",
    "sg:province":"NY",
    "sg:tags":[
        "alcoholic"
    ],
    "wof:name":"Wine & Liquor Corp",
    "wof:placetype":"venue"
},
  "geometry": {"coordinates":[-73.897221,40.815154],"type":"Point"}
}