{
  "type": "Feature",
  "properties": {
    "addr:full":"6 Putnam Dr Carmel NY 10512",
    "addr:housenumber":"6",
    "addr:postcode":"10512",
    "addr:street":"Putnam Dr",
    "iso:country":"US",
    "sg:address":"6 Putnam Dr",
    "sg:city":"Carmel",
    "sg:classifiers":[
        {
            "category":"Restaurant",
            "type":"Food & Drink"
        }
    ],
    "sg:phone":"+1 845 225 6914",
    "sg:postcode":"10512",
    "sg:province":"NY",
    "sg:tags":[
        "pizza"
    ],
    "sg:website":"www.pasqualetrattoria.com",
    "wof:name":"Pasquale Trattoria",
    "wof:placetype":"venue"
},
  "geometry": {"coordinates":[-73.662701,41.468215],"type":"Point"}
}