{
  "type": "Feature",
  "properties": {
    "addr:full":"70 7th Ave Brooklyn NY 11217",
    "addr:housenumber":"70",
    "addr:postcode":"11217",
    "addr:street":"7Th Ave",
    "iso:country":"US",
    "sg:address":"70 7th Ave",
    "sg:city":"Brooklyn",
    "sg:classifiers":[
        {
            "category":"Real Estate",
            "subcategory":"Real Estate Agent",
            "type":"Services"
        }
    ],
    "sg:phone":"+1 718 783 1010",
    "sg:postcode":"11217",
    "sg:province":"NY",
    "wof:name":"Frederick Palmer Realty Inc",
    "wof:placetype":"venue"
},
  "geometry": {"coordinates":[-73.974908,40.675494],"type":"Point"}
}