{
  "type": "Feature",
  "properties": {
    "addr:full":"1500 Astor Ave Lbby 1A Bronx NY 10469",
    "addr:housenumber":"1500;1a",
    "addr:postcode":"10469",
    "addr:street":"Astor Ave Lbby",
    "iso:country":"US",
    "sg:address":"1500 Astor Ave Lbby 1A",
    "sg:city":"Bronx",
    "sg:classifiers":[
        {
            "category":"Health Services",
            "subcategory":"Optometrist",
            "type":"Services"
        }
    ],
    "sg:phone":"+1 718 654 0023",
    "sg:postcode":"10469",
    "sg:province":"NY",
    "wof:name":"Binstock Lanny OD",
    "wof:placetype":"venue"
},
  "geometry": {"coordinates":[-73.84298,40.859484],"type":"Point"}
}