{
  "type": "Feature",
  "properties": {
    "iso:country":"US",
    "sg:address":"150 N French Rd",
    "sg:city":"Buffalo",
    "sg:classifiers":[
        {
            "category":"Building & Trades",
            "subcategory":"Construction",
            "type":"Services"
        }
    ],
    "sg:phone":"+1 716 691 1256",
    "sg:postcode":"14228",
    "sg:province":"NY",
    "sg:tags":[
        "house",
        "general",
        "contractor"
    ],
    "wof:name":"Fedeson & Son Construction Co",
    "wof:placetype":"venue"
},
  "geometry": {"coordinates":[-78.816723,43.034479],"type":"Point"}
}