{
  "type": "Feature",
  "properties": {
    "addr:full":"106 S Oxford St Brooklyn NY 11217",
    "addr:housenumber":"106",
    "addr:postcode":"11217",
    "addr:street":"S Oxford St",
    "iso:country":"US",
    "sg:address":"106 S Oxford St",
    "sg:city":"Brooklyn",
    "sg:classifiers":[
        {
            "category":"Health Services",
            "subcategory":"Doctor",
            "type":"Services"
        },
        {
            "category":"Social Services",
            "type":"Services"
        },
        {
            "category":"Personal",
            "type":"Services"
        }
    ],
    "sg:phone":"+1 718 797 3220",
    "sg:postcode":"11217",
    "sg:province":"NY",
    "sg:tags":[
        "counseling",
        "family",
        "counselors-licensed",
        "psychologist",
        "individual",
        "marriage",
        "child",
        "professional",
        "counselor"
    ],
    "wof:name":"Brooklyn Social Therapy",
    "wof:placetype":"venue"
},
  "geometry": {"coordinates":[-73.97349699999999,40.686323],"type":"Point"}
}