{
  "type": "Feature",
  "properties": {
    "iso:country":"US",
    "sg:address":"144 W 19th St ",
    "sg:city":"New York",
    "sg:classifiers":[
        {
            "category":"Restaurant",
            "type":"Food & Drink"
        }
    ],
    "sg:menulink":"http://www.allmenus.com/ny/new-york/284584-go-go-thai/menu/",
    "sg:phone":"+1 212 929 9998",
    "sg:postcode":"10011",
    "sg:province":"NY",
    "sg:tags":[
        "thai",
        "asian"
    ],
    "wof:name":"Go Go Thai",
    "wof:placetype":"venue"
},
  "geometry": {"coordinates":[-73.996669,40.741102],"type":"Point"}
}