{
  "type": "Feature",
  "properties": {
    "addr:full":"215 Rock Island St Gouverneur NY 13642",
    "addr:housenumber":"215",
    "addr:postcode":"13642",
    "addr:street":"Rock Island St",
    "iso:country":"US",
    "sg:address":"215 Rock Island St",
    "sg:city":"Gouverneur",
    "sg:classifiers":[
        {
            "category":"Recreation",
            "type":"Entertainment"
        }
    ],
    "sg:phone":"+1 315 287 0524",
    "sg:postcode":"13642",
    "sg:province":"NY",
    "sg:tags":[
        "center"
    ],
    "wof:name":"Gouverneur Village Recreation",
    "wof:placetype":"venue"
},
  "geometry": {"coordinates":[-75.46247,44.345672],"type":"Point"}
}