{
  "type": "Feature",
  "properties": {
    "addr:full":"19 Eastlake Rd Ithaca NY 14850",
    "addr:housenumber":"19",
    "addr:postcode":"14850",
    "addr:street":"Eastlake Rd",
    "iso:country":"US",
    "sg:address":"19 Eastlake Rd",
    "sg:city":"Ithaca",
    "sg:classifiers":[
        {
            "category":"Sports & Exercise",
            "subcategory":"Gym",
            "type":"Entertainment"
        }
    ],
    "sg:phone":"+1   ",
    "sg:postcode":"14850",
    "sg:province":"NY",
    "sg:tags":[
        "fitness",
        "physical",
        "facility"
    ],
    "wof:name":"Eastlake Recreation Club",
    "wof:placetype":"venue"
},
  "geometry": {"coordinates":[-76.50897399999999,42.514595],"type":"Point"}
}