{
  "type": "Feature",
  "properties": {
    "addr:full":"1180 Liberty Ave Brooklyn NY 11208",
    "addr:housenumber":"1180",
    "addr:postcode":"11208",
    "addr:street":"Liberty Ave",
    "iso:country":"US",
    "sg:address":"1180 Liberty Ave",
    "sg:city":"Brooklyn",
    "sg:classifiers":[
        {
            "category":"Shopping",
            "subcategory":"Discount & Variety Stores",
            "type":"Retail Goods"
        }
    ],
    "sg:phone":"+1 718 647 1361",
    "sg:postcode":"11208",
    "sg:province":"NY",
    "wof:name":"ABC Bargain Store",
    "wof:placetype":"venue"
},
  "geometry": {"coordinates":[-73.865567,40.678893],"type":"Point"}
}