{
  "type": "Feature",
  "properties": {
    "addr:full":"50 E 42nd St New York NY 10017",
    "addr:housenumber":"50",
    "addr:postcode":"10017",
    "addr:street":"E 42Nd St",
    "iso:country":"US",
    "sg:address":"50 E 42nd St",
    "sg:city":"New York",
    "sg:classifiers":[
        {
            "category":"Professional",
            "subcategory":"Employment Agencies",
            "type":"Services"
        }
    ],
    "sg:phone":"+1 212 370 0221",
    "sg:postcode":"10017",
    "sg:province":"NY",
    "wof:name":"Dena Kaufman & Associates",
    "wof:placetype":"venue"
},
  "geometry": {"coordinates":[-73.978996,40.752499],"type":"Point"}
}