{
  "type": "Feature",
  "properties": {
    "iso:country":"US",
    "sg:address":"76 Loganberry Ct",
    "sg:city":"Hopewell Junction",
    "sg:classifiers":[
        {
            "category":"Wholesale",
            "subcategory":"Groceries",
            "type":"Manufacturing & Wholesale Goods"
        }
    ],
    "sg:phone":"+1 845 226 4656",
    "sg:postcode":"12533",
    "sg:province":"NY",
    "sg:tags":[
        "general"
    ],
    "wof:name":"Western N Y Food Products Inc",
    "wof:placetype":"venue"
},
  "geometry": {"coordinates":[-73.78318400000001,41.625822],"type":"Point"}
}