{
  "type": "Feature",
  "properties": {
    "addr:full":"1450 65th St Brooklyn NY 11219",
    "addr:housenumber":"1450",
    "addr:postcode":"11219",
    "addr:street":"65Th St",
    "iso:country":"US",
    "sg:address":"1450 65th St",
    "sg:city":"Brooklyn",
    "sg:classifiers":[
        {
            "category":"Autos & Motor Vehicles",
            "subcategory":"Auto Supplies",
            "type":"Retail Goods"
        }
    ],
    "sg:phone":"+1 718 837 7768",
    "sg:postcode":"11219",
    "sg:province":"NY",
    "sg:tags":[
        "tire"
    ],
    "wof:name":"A To Z Tire",
    "wof:placetype":"venue"
},
  "geometry": {"coordinates":[-73.998199,40.623901],"type":"Point"}
}