{
  "type": "Feature",
  "properties": {
    "iso:country":"US",
    "sg:address":"331 81st St",
    "sg:city":"Brooklyn",
    "sg:classifiers":[
        {
            "category":"Building & Trades",
            "subcategory":"Plumbing",
            "type":"Services"
        }
    ],
    "sg:phone":"+1 718 748 5133",
    "sg:postcode":"11209",
    "sg:province":"NY",
    "sg:tags":[
        "contractor"
    ],
    "wof:name":"G K Piping & Heating Corp",
    "wof:placetype":"venue"
},
  "geometry": {"coordinates":[-74.02746500000001,40.626728],"type":"Point"}
}