{
  "type": "Feature",
  "properties": {
    "iso:country":"US",
    "sg:address":"63 Cloister Pl",
    "sg:city":"Staten Island",
    "sg:classifiers":[
        {
            "category":"Organizations",
            "subcategory":"Religious Organization",
            "type":"Services"
        }
    ],
    "sg:phone":"+1 718 351 8589",
    "sg:postcode":"10306",
    "sg:province":"NY",
    "sg:tags":[
        "church"
    ],
    "wof:name":"Our Lady Queen Of Peace",
    "wof:placetype":"venue"
},
  "geometry": {"coordinates":[-74.116574,40.574943],"type":"Point"}
}