{
  "type": "Feature",
  "properties": {
    "iso:country":"US",
    "sg:address":"605 Shepherd Avenue",
    "sg:city":"Brooklyn",
    "sg:classifiers":[
        {
            "category":"Education",
            "subcategory":"School",
            "type":"Public Place"
        }
    ],
    "sg:phone":"+1 718 345 4100",
    "sg:postcode":"11208",
    "sg:province":"NY",
    "sg:tags":[
        "high",
        "middle",
        "elementary"
    ],
    "wof:name":"New York City Community School District 19 Region 5",
    "wof:placetype":"venue"
},
  "geometry": {"coordinates":[-73.879541,40.669679],"type":"Point"}
}