{
  "type": "Feature",
  "properties": {
    "iso:country":"US",
    "sg:address":"6412 New Utrecht Avenue",
    "sg:city":"Brooklyn",
    "sg:classifiers":[
        {
            "category":"Cinema",
            "subcategory":"Movie Rental",
            "type":"Entertainment"
        }
    ],
    "sg:phone":"+1 718 259 2311",
    "sg:postcode":"11219",
    "sg:province":"NY",
    "sg:tags":[
        "game",
        "video"
    ],
    "wof:name":"Excellent Dvd",
    "wof:placetype":"venue"
},
  "geometry": {"coordinates":[-73.997578,40.624509],"type":"Point"}
}