{
  "type": "Feature",
  "properties": {
    "addr:full":"174 Willow Ave Cornwall NY 12518",
    "addr:housenumber":"174",
    "addr:postcode":"12518",
    "addr:street":"Willow Ave",
    "iso:country":"US",
    "sg:address":"174 Willow Ave",
    "sg:city":"Cornwall",
    "sg:classifiers":[
        {
            "category":"Building & Trades",
            "subcategory":"Construction",
            "type":"Services"
        }
    ],
    "sg:phone":"+1 845 534 4391",
    "sg:postcode":"12518",
    "sg:province":"NY",
    "sg:tags":[
        "painting",
        "contractor"
    ],
    "wof:name":"Anthony Adolino Painting",
    "wof:placetype":"venue"
},
  "geometry": {"coordinates":[-74.043362,41.442851],"type":"Point"}
}