{
  "type": "Feature",
  "properties": {
    "addr:full":"2567 Youngstown Lockport Rd Ransomville NY 14131",
    "addr:housenumber":"2567",
    "addr:postcode":"14131",
    "addr:street":"Lockport Rd",
    "iso:country":"US",
    "sg:address":"2567 Youngstown Lockport Rd",
    "sg:city":"Ransomville",
    "sg:classifiers":[
        {
            "category":"Government",
            "subcategory":"Post Office",
            "type":"Public Place"
        }
    ],
    "sg:phone":"+1 716 791 3223",
    "sg:postcode":"14131",
    "sg:province":"NY",
    "wof:name":"US Post Office",
    "wof:placetype":"venue"
},
  "geometry": {"coordinates":[-78.907467,43.238068],"type":"Point"}
}