{
  "type": "Feature",
  "properties": {
    "addr:full":"160 Cedar Ave Patchogue NY 11772",
    "addr:housenumber":"160",
    "addr:postcode":"11772",
    "addr:street":"Cedar Ave",
    "iso:country":"US",
    "sg:address":"160 Cedar Ave",
    "sg:city":"Patchogue",
    "sg:classifiers":[
        {
            "category":"Shopping",
            "subcategory":"Bicycles & Sporting Goods",
            "type":"Retail Goods"
        }
    ],
    "sg:phone":"+1   ",
    "sg:postcode":"11772",
    "sg:province":"NY",
    "wof:name":"Euphoria Surf Wear",
    "wof:placetype":"venue"
},
  "geometry": {"coordinates":[-73.013074,40.754931],"type":"Point"}
}