{
  "type": "Feature",
  "properties": {
    "iso:country":"US",
    "sg:address":"1406 Madison Avenue",
    "sg:city":"New York",
    "sg:classifiers":[
        {
            "category":"Personal",
            "subcategory":"Shoe Repair & Shine",
            "type":"Services"
        }
    ],
    "sg:phone":"+1 212 876 1708",
    "sg:postcode":"10029",
    "sg:province":"NY",
    "wof:name":"Palace Shoe Repair",
    "wof:placetype":"venue"
},
  "geometry": {"coordinates":[-73.953473,40.787988],"type":"Point"}
}