{
  "type": "Feature",
  "properties": {
    "addr:full":"2876 Broadway New York NY 10025",
    "addr:housenumber":"2876",
    "addr:postcode":"10025",
    "addr:street":"Broadway",
    "iso:country":"US",
    "sg:address":"2876 Broadway",
    "sg:city":"New York",
    "sg:classifiers":[
        {
            "category":"Shopping",
            "subcategory":"Tobacco",
            "type":"Retail Goods"
        }
    ],
    "sg:phone":"+1 212 280 5071",
    "sg:postcode":"10025",
    "sg:province":"NY",
    "sg:tags":[
        "cigarette",
        "cigar",
        "dealer"
    ],
    "wof:name":"Global Ink",
    "wof:placetype":"venue"
},
  "geometry": {"coordinates":[-73.965856,40.805136],"type":"Point"}
}