{
  "type": "Feature",
  "properties": {
    "addr:full":"2080 E 24th St Brooklyn NY 11229",
    "addr:housenumber":"2080",
    "addr:postcode":"11229",
    "addr:street":"E 24Th St",
    "iso:country":"US",
    "sg:address":"2080 E 24th St",
    "sg:city":"Brooklyn",
    "sg:classifiers":[
        {
            "category":"Building & Trades",
            "subcategory":"Construction",
            "type":"Services"
        }
    ],
    "sg:phone":"+1 718 891 4453",
    "sg:postcode":"11229",
    "sg:province":"NY",
    "sg:tags":[
        "house"
    ],
    "wof:name":"Y and E Construction and Dev",
    "wof:placetype":"venue"
},
  "geometry": {"coordinates":[-73.947934,40.601631],"type":"Point"}
}