{
  "type": "Feature",
  "properties": {
    "iso:country":"US",
    "sg:address":"50 White Dr",
    "sg:city":"Frewsburg",
    "sg:classifiers":[
        {
            "category":"Building & Trades",
            "subcategory":"Plumbing",
            "type":"Services"
        },
        {
            "category":"Home & Garden",
            "subcategory":"Building Materials",
            "type":"Retail Goods"
        },
        {
            "category":"Building & Trades",
            "subcategory":"Construction",
            "type":"Services"
        }
    ],
    "sg:phone":"+1 716 569 3045",
    "sg:postcode":"14738",
    "sg:province":"NY",
    "sg:tags":[
        "concrete",
        "tank",
        "system",
        "septic",
        "contractor"
    ],
    "wof:name":"Shotcrete Service",
    "wof:placetype":"venue"
},
  "geometry": {"coordinates":[-79.156029,42.064245],"type":"Point"}
}