{
  "type": "Feature",
  "properties": {
    "addr:full":"2 Chestnut St Cooperstown NY 13326",
    "addr:housenumber":"2",
    "addr:postcode":"13326",
    "addr:street":"Chestnut St",
    "iso:country":"US",
    "sg:address":"2 Chestnut St",
    "sg:city":"Cooperstown",
    "sg:classifiers":[
        {
            "category":"Travel",
            "subcategory":"Hotels & Motels",
            "type":"Entertainment"
        }
    ],
    "sg:phone":"+1   ",
    "sg:postcode":"13326",
    "sg:province":"NY",
    "sg:tags":[
        "operation"
    ],
    "wof:name":"Wynterholm",
    "wof:placetype":"venue"
},
  "geometry": {"coordinates":[-74.92567,42.702796],"type":"Point"}
}