{
  "type": "Feature",
  "properties": {
    "addr:full":"724 5th Ave New York NY 10019",
    "addr:housenumber":"724",
    "addr:postcode":"10019",
    "addr:street":"5Th Ave",
    "iso:country":"US",
    "sg:address":"724 5th Ave",
    "sg:city":"New York",
    "sg:classifiers":[
        {
            "category":"Shopping",
            "type":"Retail Goods"
        },
        {
            "category":"Shopping",
            "subcategory":"Used Merchandise",
            "type":"Retail Goods"
        }
    ],
    "sg:phone":"+1 212 757 2884",
    "sg:postcode":"10019",
    "sg:province":"NY",
    "sg:tags":[
        "antique",
        "art",
        "gallery"
    ],
    "sg:website":"www.merringallery.com",
    "wof:name":"Merrin Gallery",
    "wof:placetype":"venue"
},
  "geometry": {"coordinates":[-73.974591,40.762682],"type":"Point"}
}