{
  "type": "Feature",
  "properties": {
    "iso:country":"US",
    "sg:address":"379 Church Rd",
    "sg:city":"Albany",
    "sg:classifiers":[
        {
            "category":"Retail",
            "subcategory":"Portrait Studio",
            "type":"Services"
        }
    ],
    "sg:phone":"+1 518 782 9584",
    "sg:postcode":"12203",
    "sg:province":"NY",
    "sg:tags":[
        "photographer"
    ],
    "wof:name":"Kathleen Marie Photography",
    "wof:placetype":"venue"
},
  "geometry": {"coordinates":[-73.86963,42.681536],"type":"Point"}
}