{
  "type": "Feature",
  "properties": {
    "addr:full":"2 Pleasantville Rd Pleasantville NY 10570",
    "addr:housenumber":"2",
    "addr:postcode":"10570",
    "addr:street":"Pleasantville Rd",
    "iso:country":"US",
    "sg:address":"2 Pleasantville Rd",
    "sg:city":"Pleasantville",
    "sg:classifiers":[
        {
            "category":"Autos & Motor Vehicles",
            "subcategory":"Fuel & Gas Station",
            "type":"Retail Goods"
        }
    ],
    "sg:phone":"+1 914 769 9831",
    "sg:postcode":"10570",
    "sg:province":"NY",
    "wof:name":"Pleasant Auto Service",
    "wof:placetype":"venue"
},
  "geometry": {"coordinates":[-73.794899,41.133099],"type":"Point"}
}