{
  "type": "Feature",
  "properties": {
    "iso:country":"US",
    "sg:address":"2349 62nd St",
    "sg:city":"Brooklyn",
    "sg:classifiers":[
        {
            "category":"Bars & Pubs",
            "type":"Food & Drink"
        }
    ],
    "sg:phone":"+1   ",
    "sg:postcode":"11204",
    "sg:province":"NY",
    "sg:tags":[
        "drinking"
    ],
    "wof:name":"Lolas Lounge",
    "wof:placetype":"venue"
},
  "geometry": {"coordinates":[-73.975979,40.613597],"type":"Point"}
}