{
  "type": "Feature",
  "properties": {
    "addr:full":"21 Gorham St Rochester NY 14605",
    "addr:housenumber":"21",
    "addr:postcode":"14605",
    "addr:street":"Gorham St",
    "iso:country":"US",
    "sg:address":"21 Gorham St",
    "sg:city":"Rochester",
    "sg:classifiers":[
        {
            "category":"Communications",
            "subcategory":"Television Station",
            "type":"Services"
        }
    ],
    "sg:phone":"+1 585 586 4382",
    "sg:postcode":"14605",
    "sg:province":"NY",
    "sg:tags":[
        "satellite",
        "cable"
    ],
    "wof:name":"Peoples Cable Corp",
    "wof:placetype":"venue"
},
  "geometry": {"coordinates":[-77.614159,43.1662],"type":"Point"}
}