{
  "type": "Feature",
  "properties": {
    "addr:full":"1903 Clinton St Buffalo NY 14206",
    "addr:housenumber":"1903",
    "addr:postcode":"14206",
    "addr:street":"Clinton St",
    "iso:country":"US",
    "sg:address":"1903 Clinton St",
    "sg:city":"Buffalo",
    "sg:classifiers":[
        {
            "category":"Restaurant",
            "type":"Food & Drink"
        }
    ],
    "sg:phone":"+1 716 826 6873",
    "sg:postcode":"14206",
    "sg:province":"NY",
    "sg:tags":[
        "eating"
    ],
    "wof:name":"Lucky's Texas Red Hots",
    "wof:placetype":"venue"
},
  "geometry": {"coordinates":[-78.806456,42.871777],"type":"Point"}
}