{
  "type": "Feature",
  "properties": {
    "iso:country":"US",
    "sg:address":"23 W 32nd Street",
    "sg:city":"New York",
    "sg:classifiers":[
        {
            "category":"Bars & Pubs",
            "subcategory":"Lounge",
            "type":"Food & Drink"
        }
    ],
    "sg:phone":"+1 212 629 7171",
    "sg:postcode":"10001",
    "sg:province":"NY",
    "sg:tags":[
        "karaoke"
    ],
    "wof:name":"Grammy Karaoke",
    "wof:placetype":"venue"
},
  "geometry": {"coordinates":[-73.987149,40.747718],"type":"Point"}
}