{
  "type": "Feature",
  "properties": {
    "iso:country":"US",
    "sg:address":"325 E 64 St",
    "sg:city":"New York",
    "sg:classifiers":[
        {
            "category":"Wholesale",
            "subcategory":"Apparel",
            "type":"Manufacturing & Wholesale Goods"
        }
    ],
    "sg:phone":"+1 212 744 5600",
    "sg:postcode":"10065",
    "sg:province":"NY",
    "sg:tags":[
        "clothing",
        "accessory"
    ],
    "wof:name":"Y Z Fashion Inc",
    "wof:placetype":"venue"
},
  "geometry": {"coordinates":[-73.960098,40.763049],"type":"Point"}
}