{
  "type": "Feature",
  "properties": {
    "iso:country":"US",
    "sg:address":"320 Carleton Ave",
    "sg:city":"Central Islip",
    "sg:classifiers":[
        {
            "category":"Professional",
            "subcategory":"Lawyer & Legal Services",
            "type":"Services"
        }
    ],
    "sg:phone":"+1 631 234 2511",
    "sg:postcode":"11722",
    "sg:province":"NY",
    "sg:tags":[
        "attorney"
    ],
    "wof:name":"Jason Bassett Law Office",
    "wof:placetype":"venue"
},
  "geometry": {"coordinates":[-73.199713,40.779537],"type":"Point"}
}