{
  "type": "Feature",
  "properties": {
    "addr:full":"1161 Montauk Hwy Mastic NY 11950",
    "addr:housenumber":"1161",
    "addr:postcode":"11950",
    "addr:street":"Montauk Hwy",
    "iso:country":"US",
    "sg:address":"1161 Montauk Hwy",
    "sg:city":"Mastic",
    "sg:classifiers":[
        {
            "category":"Manufacturing",
            "subcategory":"Electronics",
            "type":"Manufacturing & Wholesale Goods"
        }
    ],
    "sg:phone":"+1 631 399 2574",
    "sg:postcode":"11950",
    "sg:province":"NY",
    "sg:tags":[
        "signal"
    ],
    "wof:name":"Sign Design",
    "wof:placetype":"venue"
},
  "geometry": {"coordinates":[-72.855924,40.803326],"type":"Point"}
}