{
  "type": "Feature",
  "properties": {
    "iso:country":"US",
    "sg:address":"7379 Oswego Rd",
    "sg:city":"Liverpool",
    "sg:classifiers":[
        {
            "category":"Banks & Credit Unions",
            "subcategory":"Bank",
            "type":"Services"
        }
    ],
    "sg:phone":"+1 315 451 9404",
    "sg:postcode":"13090",
    "sg:province":"NY",
    "sg:tags":[
        "state",
        "commercial"
    ],
    "wof:name":"H S B C Bank U S A",
    "wof:placetype":"venue"
},
  "geometry": {"coordinates":[-76.21732799999999,43.124647],"type":"Point"}
}