{
  "type": "Feature",
  "properties": {
    "addr:full":"229 Chestnut St Oneonta NY 13820",
    "addr:housenumber":"229",
    "addr:postcode":"13820",
    "addr:street":"Chestnut St",
    "iso:country":"US",
    "sg:address":"229 Chestnut St",
    "sg:city":"Oneonta",
    "sg:classifiers":[
        {
            "category":"Retail",
            "subcategory":"Repair Shop",
            "type":"Services"
        }
    ],
    "sg:phone":"+1 607 432 4799",
    "sg:postcode":"13820",
    "sg:province":"NY",
    "sg:tags":[
        "plumbing",
        "drain",
        "plumbing-drain",
        "cleaning",
        "sewer"
    ],
    "sg:website":"http://www.goulds.com",
    "wof:name":"Gregory Plumbing & Heating Inc",
    "wof:placetype":"venue"
},
  "geometry": {"coordinates":[-75.07727300000001,42.450745],"type":"Point"}
}