{
  "type": "Feature",
  "properties": {
    "addr:full":"5258 State Hwy 41 Smithville Flats NY 13841",
    "addr:housenumber":"5258",
    "addr:postcode":"13841",
    "addr:street":"State Hwy 41;Flats",
    "iso:country":"US",
    "sg:address":"5258 State Hwy 41",
    "sg:city":"Smithville Flats",
    "sg:classifiers":[
        {
            "category":"Personal",
            "subcategory":"Beauty Salon",
            "type":"Services"
        }
    ],
    "sg:phone":"+1 607 656 9284",
    "sg:postcode":"13841",
    "sg:province":"NY",
    "wof:name":"Cutting Edge",
    "wof:placetype":"venue"
},
  "geometry": {"coordinates":[-75.80815,42.39586],"type":"Point"}
}