{
  "type": "Feature",
  "properties": {
    "addr:full":"118 Maple Ave New City NY 10956",
    "addr:housenumber":"118",
    "addr:postcode":"10956",
    "addr:street":"Maple Ave",
    "iso:country":"US",
    "sg:address":"118 Maple Ave",
    "sg:city":"New City",
    "sg:classifiers":[
        {
            "category":"Real Estate",
            "subcategory":"Real Estate Services",
            "type":"Services"
        }
    ],
    "sg:phone":"+1 845 634 8794",
    "sg:postcode":"10956",
    "sg:province":"NY",
    "sg:tags":[
        "insurance",
        "agent",
        "title"
    ],
    "wof:name":"Hudson Valley Abstract Co",
    "wof:placetype":"venue"
},
  "geometry": {"coordinates":[-73.98903799999999,41.142457],"type":"Point"}
}