{
  "type": "Feature",
  "properties": {
    "iso:country":"US",
    "sg:address":"279 E 196th St",
    "sg:city":"Bronx",
    "sg:classifiers":[
        {
            "category":"Utilities",
            "type":"Services"
        }
    ],
    "sg:phone":"+1   ",
    "sg:postcode":"10458",
    "sg:province":"NY",
    "sg:tags":[
        "sanitary"
    ],
    "wof:name":"Kevin Gibson",
    "wof:placetype":"venue"
},
  "geometry": {"coordinates":[-73.890584,40.866871],"type":"Point"}
}