{
  "type": "Feature",
  "properties": {
    "iso:country":"US",
    "sg:address":"275 Main St",
    "sg:city":"Owego",
    "sg:classifiers":[
        {
            "category":"Education",
            "subcategory":"Library",
            "type":"Public Place"
        }
    ],
    "sg:phone":"+1   ",
    "sg:postcode":"13827",
    "sg:province":"NY",
    "wof:name":"Coburn Free Library",
    "wof:placetype":"venue"
},
  "geometry": {"coordinates":[-76.258978,42.105303],"type":"Point"}
}