{
  "type": "Feature",
  "properties": {
    "iso:country":"US",
    "sg:address":"1200 Paterson St",
    "sg:city":"Ogdensburg",
    "sg:classifiers":[
        {
            "category":"Travel",
            "subcategory":"Hotels & Motels",
            "type":"Entertainment"
        }
    ],
    "sg:phone":"+1 315 393 3200",
    "sg:postcode":"13669",
    "sg:province":"NY",
    "wof:name":"Days Inn",
    "wof:placetype":"venue"
},
  "geometry": {"coordinates":[-75.47575399999999,44.690999],"type":"Point"}
}