{
  "type": "Feature",
  "properties": {
    "iso:country":"US",
    "sg:address":"34 Convent Ave",
    "sg:city":"Yonkers",
    "sg:classifiers":[
        {
            "category":"Education",
            "subcategory":"School",
            "type":"Public Place"
        }
    ],
    "sg:phone":"+1 914 963 5318",
    "sg:postcode":"10703",
    "sg:province":"NY",
    "sg:tags":[
        "elementary"
    ],
    "sg:website":"http://www.holy-child.org",
    "wof:name":"Sacred Heart Grade School",
    "wof:placetype":"venue"
},
  "geometry": {"coordinates":[-73.886528,40.949317],"type":"Point"}
}