{
  "type": "Feature",
  "properties": {
    "iso:country":"US",
    "sg:address":"610 S Decatur St",
    "sg:city":"Watkins Glen",
    "sg:classifiers":[
        {
            "category":"Education",
            "subcategory":"Library",
            "type":"Public Place"
        }
    ],
    "sg:phone":"+1 607 535 2346",
    "sg:postcode":"14891",
    "sg:province":"NY",
    "wof:name":"Glen Watkins Public Library",
    "wof:placetype":"venue"
},
  "geometry": {"coordinates":[-76.86624,42.37157],"type":"Point"}
}