{
  "type": "Feature",
  "properties": {
    "iso:country":"US",
    "sg:address":"5360 Nesconset Hwy",
    "sg:city":"Port Jeffrsn Sta",
    "sg:classifiers":[
        {
            "category":"Health Services",
            "subcategory":"Health Practitioner",
            "type":"Services"
        }
    ],
    "sg:phone":"+1 631 978 0051",
    "sg:postcode":"11776",
    "sg:province":"NY",
    "sg:tags":[
        "pathologist",
        "speech"
    ],
    "wof:name":"Amato & Volz Speech Pthlgsts",
    "wof:placetype":"venue"
},
  "geometry": {"coordinates":[-73.042706,40.927703],"type":"Point"}
}