{
  "type": "Feature",
  "properties": {
    "iso:country":"US",
    "sg:address":"9481 Long Shore Rd",
    "sg:city":"Westernville",
    "sg:classifiers":[
        {
            "category":"Professional",
            "subcategory":"Management & Consulting",
            "type":"Services"
        }
    ],
    "sg:phone":"+1 315 827 4289",
    "sg:postcode":"13486",
    "sg:province":"NY",
    "sg:tags":[
        "consultant",
        "business"
    ],
    "wof:name":"Big Brook Consultants Inc",
    "wof:placetype":"venue"
},
  "geometry": {"coordinates":[-75.324195,43.310209],"type":"Point"}
}