{
  "type": "Feature",
  "properties": {
    "iso:country":"US",
    "sg:address":"3117 Oak Ave",
    "sg:city":"Youngstown",
    "sg:classifiers":[
        {
            "category":"Manufacturing",
            "subcategory":"Retail Goods",
            "type":"Manufacturing & Wholesale Goods"
        }
    ],
    "sg:phone":"+1   ",
    "sg:postcode":"14174",
    "sg:province":"NY",
    "sg:tags":[
        "product",
        "mfg"
    ],
    "wof:name":"Sewing & Crafts By Nancy",
    "wof:placetype":"venue"
},
  "geometry": {"coordinates":[-79.043897,43.26769],"type":"Point"}
}