{
  "type": "Feature",
  "properties": {
    "addr:full":"373 Broadway Kingston NY 12401",
    "addr:housenumber":"373",
    "addr:postcode":"12401",
    "addr:street":"Broadway",
    "iso:country":"US",
    "sg:address":"373 Broadway",
    "sg:city":"Kingston",
    "sg:classifiers":[
        {
            "category":"Health Services",
            "subcategory":"Doctor",
            "type":"Services"
        }
    ],
    "sg:phone":"+1 845 338 8546",
    "sg:postcode":"12401",
    "sg:province":"NY",
    "sg:tags":[
        "physician",
        "surgeon",
        "surgeons",
        "surgery-general"
    ],
    "wof:name":"Richard W Moscowitz, Md Pa Pc",
    "wof:placetype":"venue"
},
  "geometry": {"coordinates":[-73.994744,41.926166],"type":"Point"}
}