{
  "type": "Feature",
  "properties": {
    "addr:full":"4872 W Seneca Tpke Syracuse NY 13215",
    "addr:housenumber":"4872",
    "addr:postcode":"13215",
    "addr:street":"W Seneca Tpke",
    "iso:country":"US",
    "sg:address":"4872 W Seneca Tpke",
    "sg:city":"Syracuse",
    "sg:classifiers":[
        {
            "category":"Building & Trades",
            "subcategory":"Construction",
            "type":"Services"
        }
    ],
    "sg:phone":"+1 315 498 4902",
    "sg:postcode":"13215",
    "sg:province":"NY",
    "sg:tags":[
        "painter"
    ],
    "wof:name":"Residential Painting Coml",
    "wof:placetype":"venue"
},
  "geometry": {"coordinates":[-76.181702,43.005103],"type":"Point"}
}