{
  "type": "Feature",
  "properties": {
    "addr:full":"676 Cradle Ave Angola NY 14006",
    "addr:housenumber":"676",
    "addr:postcode":"14006",
    "addr:street":"Cradle Ave",
    "iso:country":"US",
    "sg:address":"676 Cradle Ave",
    "sg:city":"Angola",
    "sg:classifiers":[
        {
            "category":"Professional",
            "type":"Services"
        }
    ],
    "sg:phone":"+1   ",
    "sg:postcode":"14006",
    "sg:province":"NY",
    "wof:name":"Ralph Hogg",
    "wof:placetype":"venue"
},
  "geometry": {"coordinates":[-79.058998,42.647225],"type":"Point"}
}