{
  "type": "Feature",
  "properties": {
    "addr:full":"1409 Richmond Ave Staten Island NY 10314",
    "addr:housenumber":"1409",
    "addr:postcode":"10314",
    "addr:street":"Richmond Ave",
    "iso:country":"US",
    "sg:address":"1409 Richmond Ave",
    "sg:city":"Staten Island",
    "sg:classifiers":[
        {
            "category":"Restaurant",
            "type":"Food & Drink"
        }
    ],
    "sg:menulink":"http://www.allmenus.com/ny/staten-island/142493-subway/menu/",
    "sg:phone":"+1 718 494 7100",
    "sg:postcode":"10314",
    "sg:province":"NY",
    "sg:tags":[
        "american",
        "sandwich"
    ],
    "wof:name":"Subway",
    "wof:placetype":"venue"
},
  "geometry": {"coordinates":[-74.157749,40.614018],"type":"Point"}
}