{
  "type": "Feature",
  "properties": {
    "iso:country":"US",
    "sg:address":"1239 Hancock St",
    "sg:city":"Brooklyn",
    "sg:classifiers":[
        {
            "category":"Food & Beverages",
            "subcategory":"Groceries & Convenience Stores",
            "type":"Retail Goods"
        }
    ],
    "sg:phone":"+1   ",
    "sg:postcode":"11221",
    "sg:province":"NY",
    "wof:name":"N A Grocery",
    "wof:placetype":"venue"
},
  "geometry": {"coordinates":[-73.909605,40.693832],"type":"Point"}
}