{
  "type": "Feature",
  "properties": {
    "addr:full":"189 Montague St Brooklyn NY 11201",
    "addr:housenumber":"189",
    "addr:postcode":"11201",
    "addr:street":"Montague St",
    "iso:country":"US",
    "sg:address":"189 Montague St",
    "sg:city":"Brooklyn",
    "sg:classifiers":[
        {
            "category":"Health Services",
            "subcategory":"Optometrist",
            "type":"Services"
        }
    ],
    "sg:phone":"+1 718 855 2333",
    "sg:postcode":"11201",
    "sg:province":"NY",
    "wof:name":"Cohen's Fashion Optical",
    "wof:placetype":"venue"
},
  "geometry": {"coordinates":[-73.992401,40.694302],"type":"Point"}
}