{
  "type": "Feature",
  "properties": {
    "iso:country":"US",
    "sg:address":"363 Birdsall Dr",
    "sg:city":"Yorktown Heights",
    "sg:classifiers":[
        {
            "category":"Real Estate",
            "subcategory":"Surveying",
            "type":"Services"
        }
    ],
    "sg:phone":"+1 914 243 4224",
    "sg:postcode":"10598",
    "sg:province":"NY",
    "wof:name":"Eliot Senor",
    "wof:placetype":"venue"
},
  "geometry": {"coordinates":[-73.77632800000001,41.237888],"type":"Point"}
}