{
  "type": "Feature",
  "properties": {
    "addr:full":"40 The Crossing at Blind Brook Purchase NY 10577",
    "addr:housenumber":"40",
    "addr:postcode":"10577",
    "addr:street":"The Crossing;Brook",
    "iso:country":"US",
    "sg:address":"40 The Crossing at Blind Brook",
    "sg:city":"Purchase",
    "sg:classifiers":[
        {
            "category":"Professional",
            "type":"Services"
        }
    ],
    "sg:phone":"+1 914 694 3754",
    "sg:postcode":"10577",
    "sg:province":"NY",
    "sg:tags":[
        "establishment"
    ],
    "wof:name":"Dextra Baldwin Mc Gonagle",
    "wof:placetype":"venue"
},
  "geometry": {"coordinates":[-73.708736,41.028583],"type":"Point"}
}