{
  "type": "Feature",
  "properties": {
    "iso:country":"US",
    "sg:address":"2444 E Tremont Ave",
    "sg:city":"Bronx",
    "sg:classifiers":[
        {
            "category":"Real Estate",
            "subcategory":"Real Estate Agent",
            "type":"Services"
        }
    ],
    "sg:phone":"+1 718 792 3222",
    "sg:postcode":"10461",
    "sg:province":"NY",
    "wof:name":"Diplomat Realty Of New York",
    "wof:placetype":"venue"
},
  "geometry": {"coordinates":[-73.852312,40.842586],"type":"Point"}
}