{
  "type": "Feature",
  "properties": {
    "iso:country":"US",
    "sg:address":"3660 Route 112",
    "sg:city":"Coram",
    "sg:classifiers":[
        {
            "category":"Retail",
            "subcategory":"Veterinary Services",
            "type":"Services"
        }
    ],
    "sg:phone":"+1 631 698 1666",
    "sg:postcode":"11727",
    "sg:province":"NY",
    "sg:tags":[
        "veterinarian"
    ],
    "sg:website":"www.coramanimalclinic.com",
    "wof:name":"Coram Animal Clinic",
    "wof:placetype":"venue"
},
  "geometry": {"coordinates":[-72.997597,40.8493],"type":"Point"}
}