{
  "type": "Feature",
  "properties": {
    "addr:full":"325 Cherry St Jamestown NY 14701",
    "addr:housenumber":"325",
    "addr:postcode":"14701",
    "addr:street":"Cherry St",
    "iso:country":"US",
    "sg:address":"325 Cherry St",
    "sg:city":"Jamestown",
    "sg:classifiers":[
        {
            "category":"Government",
            "subcategory":"Office",
            "type":"Public Place"
        }
    ],
    "sg:phone":"+1 716 664 3141",
    "sg:postcode":"14701",
    "sg:province":"NY",
    "wof:name":"Retardation Office",
    "wof:placetype":"venue"
},
  "geometry": {"coordinates":[-79.242779,42.096798],"type":"Point"}
}