{
  "type": "Feature",
  "properties": {
    "addr:full":"205 Nassau Blvd Garden City NY 11530",
    "addr:housenumber":"205",
    "addr:postcode":"11530",
    "addr:street":"Nassau Blvd",
    "iso:country":"US",
    "sg:address":"205 Nassau Blvd",
    "sg:city":"Garden City",
    "sg:classifiers":[
        {
            "category":"Real Estate",
            "subcategory":"Real Estate Services",
            "type":"Services"
        }
    ],
    "sg:phone":"+1 516 746 1630",
    "sg:postcode":"11530",
    "sg:province":"NY",
    "sg:tags":[
        "management",
        "property"
    ],
    "wof:name":"Wilson Francis B Management Co",
    "wof:placetype":"venue"
},
  "geometry": {"coordinates":[-73.660797,40.729698],"type":"Point"}
}