{
  "type": "Feature",
  "properties": {
    "iso:country":"US",
    "sg:address":"311 N Meadow St",
    "sg:city":"Ithaca",
    "sg:classifiers":[
        {
            "category":"Professional",
            "subcategory":"Accounting & Tax Preparation",
            "type":"Services"
        }
    ],
    "sg:phone":"+1 607 277 1656",
    "sg:postcode":"14850",
    "sg:province":"NY",
    "sg:tags":[
        "return",
        "filing"
    ],
    "wof:name":"Jackson Hewitt Tax Svc",
    "wof:placetype":"venue"
},
  "geometry": {"coordinates":[-76.50842400000001,42.442192],"type":"Point"}
}