{
  "type": "Feature",
  "properties": {
    "addr:full":"3478 Webster Ave Bronx NY 10467",
    "addr:housenumber":"3478",
    "addr:postcode":"10467",
    "addr:street":"Webster Ave",
    "iso:country":"US",
    "sg:address":"3478 Webster Ave",
    "sg:city":"Bronx",
    "sg:classifiers":[
        {
            "category":"Insurance",
            "subcategory":"Insurance Agent",
            "type":"Services"
        }
    ],
    "sg:phone":"+1 718 654 0003",
    "sg:postcode":"10467",
    "sg:province":"NY",
    "wof:name":"Priceline Insurance",
    "wof:placetype":"venue"
},
  "geometry": {"coordinates":[-73.871876,40.877114],"type":"Point"}
}