{
  "type": "Feature",
  "properties": {
    "addr:full":"2190 University Ave Bronx NY 10453",
    "addr:housenumber":"2190",
    "addr:postcode":"10453",
    "addr:street":"University Ave",
    "iso:country":"US",
    "sg:address":"2190 University Ave",
    "sg:city":"Bronx",
    "sg:classifiers":[
        {
            "category":"Social Services",
            "type":"Services"
        }
    ],
    "sg:phone":"+1 718 365 1400",
    "sg:postcode":"10453",
    "sg:province":"NY",
    "sg:tags":[
        "counselor",
        "marriage",
        "family"
    ],
    "wof:name":"North Bronx Family Service Ctr",
    "wof:placetype":"venue"
},
  "geometry": {"coordinates":[-73.909814,40.856651],"type":"Point"}
}