{
  "type": "Feature",
  "properties": {
    "iso:country":"US",
    "sg:address":"251 E. 45th St",
    "sg:city":"Manhattan",
    "sg:classifiers":[
        {
            "category":"Restaurant",
            "type":"Food & Drink"
        }
    ],
    "sg:phone":"+1 212 922 9668",
    "sg:postcode":"10017",
    "sg:province":"NY",
    "sg:tags":[
        "chinese"
    ],
    "wof:name":"New Wylie's Hibachi Grill Inc.",
    "wof:placetype":"venue"
},
  "geometry": {"coordinates":[-73.97133599999999,40.751994],"type":"Point"}
}