{
  "type": "Feature",
  "properties": {
    "addr:full":"6323 Knickerbocker Rd Ontario NY 14519",
    "addr:housenumber":"6323",
    "addr:postcode":"14519",
    "addr:street":"Knickerbocker Rd",
    "iso:country":"US",
    "sg:address":"6323 Knickerbocker Rd",
    "sg:city":"Ontario",
    "sg:classifiers":[
        {
            "category":"Banks & Credit Unions",
            "subcategory":"Investment Brokerage",
            "type":"Services"
        },
        {
            "category":"Banks & Credit Unions",
            "subcategory":"Bank",
            "type":"Services"
        },
        {
            "category":"Banks & Credit Unions",
            "subcategory":"Financial Services",
            "type":"Services"
        }
    ],
    "sg:phone":"+1 866 307 2470",
    "sg:postcode":"14519",
    "sg:province":"NY",
    "sg:tags":[
        "advisory",
        "mutual",
        "retirement",
        "annuity",
        "broker",
        "fund",
        "planning",
        "plan",
        "consultant",
        "security",
        "bond",
        "insurance",
        "stock"
    ],
    "sg:website":"http://rochester.citysearch.com/profile/external/604308142/ontario_ny/edward_jones_marie_a_thomas.html?publisher=yellowpages&reference_id=1&placement=ypwebsitemip",
    "wof:name":"Edward Jones - MARIE A THOMAS",
    "wof:placetype":"venue"
},
  "geometry": {"coordinates":[-77.286222,43.228326],"type":"Point"}
}