{
  "type": "Feature",
  "properties": {
    "iso:country":"US",
    "sg:address":"8466 Morganville Rd",
    "sg:city":"Stafford",
    "sg:classifiers":[
        {
            "category":"Place Of Worship",
            "subcategory":"Church",
            "type":"Public Place"
        },
        {
            "category":"Place Of Worship",
            "type":"Public Place"
        }
    ],
    "sg:phone":"+1 585 343 6019",
    "sg:postcode":"14143",
    "sg:province":"NY",
    "sg:tags":[
        "testament",
        "christ-new",
        "churches-church",
        "christ"
    ],
    "wof:name":"Morganville United Church Of Christ",
    "wof:placetype":"venue"
},
  "geometry": {"coordinates":[-78.07570200000001,43.003633],"type":"Point"}
}