{
  "type": "Feature",
  "properties": {
    "addr:full":"417 E 57th St New York NY 10022",
    "addr:housenumber":"417",
    "addr:postcode":"10022",
    "addr:street":"E 57Th St",
    "iso:country":"US",
    "sg:address":"417 E 57th St",
    "sg:city":"New York",
    "sg:classifiers":[
        {
            "category":"Professional",
            "subcategory":"Business Services",
            "type":"Services"
        }
    ],
    "sg:phone":"+1 212 980 1282",
    "sg:postcode":"10022",
    "sg:province":"NY",
    "sg:tags":[
        "fashion",
        "design",
        "accessory"
    ],
    "wof:name":"Tck Designs Ltd",
    "wof:placetype":"venue"
},
  "geometry": {"coordinates":[-73.96091300000001,40.757583],"type":"Point"}
}