{
  "type": "Feature",
  "properties": {
    "addr:full":"134 Union St Brooklyn NY 11231",
    "addr:housenumber":"134",
    "addr:postcode":"11231",
    "addr:street":"Union St",
    "iso:country":"US",
    "sg:address":"134 Union St",
    "sg:city":"Brooklyn",
    "sg:classifiers":[
        {
            "category":"Retail",
            "subcategory":"Laundry & Dry Cleaning",
            "type":"Services"
        }
    ],
    "sg:phone":"+1 718 422 7722",
    "sg:postcode":"11231",
    "sg:province":"NY",
    "wof:name":"Bernies Laundrymat",
    "wof:placetype":"venue"
},
  "geometry": {"coordinates":[-74.002363,40.684193],"type":"Point"}
}