{
  "type": "Feature",
  "properties": {
    "iso:country":"US",
    "sg:address":"24 E Main St",
    "sg:city":"Gowanda",
    "sg:classifiers":[
        {
            "category":"Organizations",
            "subcategory":"Labor Organization",
            "type":"Services"
        }
    ],
    "sg:phone":"+1 716 532 4150",
    "sg:postcode":"14070",
    "sg:province":"NY",
    "wof:name":"CSEA Local 425",
    "wof:placetype":"venue"
},
  "geometry": {"coordinates":[-78.934217,42.463783],"type":"Point"}
}