{
  "type": "Feature",
  "properties": {
    "addr:full":"5316 35th St Fl 2 Long Island City NY 11101",
    "addr:housenumber":"5316;2",
    "addr:postcode":"11101",
    "addr:street":"35Th St",
    "iso:country":"US",
    "sg:address":"5316 35th St Fl 2",
    "sg:city":"Long Island City",
    "sg:classifiers":[
        {
            "category":"Shopping",
            "subcategory":"Clothing, Apparel, & Fashions",
            "type":"Retail Goods"
        }
    ],
    "sg:phone":"+1 718 392 7565",
    "sg:postcode":"11101",
    "sg:province":"NY",
    "sg:tags":[
        "lingerie"
    ],
    "wof:name":"La Perla Direct Inc",
    "wof:placetype":"venue"
},
  "geometry": {"coordinates":[-73.937121,40.735577],"type":"Point"}
}