{
  "type": "Feature",
  "properties": {
    "addr:full":"2736 Merrick Rd Bellmore NY 11710",
    "addr:housenumber":"2736",
    "addr:postcode":"11710",
    "addr:street":"Merrick Rd",
    "iso:country":"US",
    "sg:address":"2736 Merrick Rd",
    "sg:city":"Bellmore",
    "sg:classifiers":[
        {
            "category":"Social Services",
            "type":"Services"
        },
        {
            "category":"Shopping",
            "subcategory":"Used Merchandise",
            "type":"Retail Goods"
        },
        {
            "category":"Banks & Credit Unions",
            "subcategory":"Bank",
            "type":"Services"
        },
        {
            "category":"Shopping",
            "subcategory":"Thrift Store",
            "type":"Retail Goods"
        },
        {
            "category":"Organizations",
            "subcategory":"Non-profit Organization",
            "type":"Services"
        }
    ],
    "sg:phone":"+1 516 409 5951",
    "sg:postcode":"11710",
    "sg:province":"NY",
    "sg:tags":[
        "shop",
        "foundations-educational",
        "philanthropic",
        "research",
        "resale",
        "second",
        "hand",
        "furniture",
        "charity"
    ],
    "sg:website":"http://www.goodwill.org",
    "wof:name":"Goodwill Stores",
    "wof:placetype":"venue"
},
  "geometry": {"coordinates":[-73.524727,40.66386],"type":"Point"}
}