{
  "type": "Feature",
  "properties": {
    "addr:full":"217 Bedford Ave Buffalo NY 14216",
    "addr:housenumber":"217",
    "addr:postcode":"14216",
    "addr:street":"Bedford Ave",
    "iso:country":"US",
    "sg:address":"217 Bedford Ave",
    "sg:city":"Buffalo",
    "sg:classifiers":[
        {
            "category":"Retail",
            "subcategory":"Laundry & Dry Cleaning",
            "type":"Services"
        }
    ],
    "sg:phone":"+1 716 873 2249",
    "sg:postcode":"14216",
    "sg:province":"NY",
    "sg:tags":[
        "cleaners"
    ],
    "wof:name":"Park Dry Cleaners",
    "wof:placetype":"venue"
},
  "geometry": {"coordinates":[-78.87815399999999,42.939699],"type":"Point"}
}