{
  "type": "Feature",
  "properties": {
    "addr:full":"150 Richmond Ave Medford NY 11763",
    "addr:housenumber":"150",
    "addr:postcode":"11763",
    "addr:street":"Richmond Ave",
    "iso:country":"US",
    "sg:address":"150 Richmond Ave",
    "sg:city":"Medford",
    "sg:classifiers":[
        {
            "category":"Manufacturing",
            "subcategory":"Metals",
            "type":"Manufacturing & Wholesale Goods"
        }
    ],
    "sg:phone":"+1   ",
    "sg:postcode":"11763",
    "sg:province":"NY",
    "sg:tags":[
        "blast",
        "furnace",
        "works"
    ],
    "wof:name":"Thomas J Friedrich",
    "wof:placetype":"venue"
},
  "geometry": {"coordinates":[-72.998935,40.800252],"type":"Point"}
}