{
  "type": "Feature",
  "properties": {
    "iso:country":"US",
    "sg:address":"415 S Broadway",
    "sg:city":"Hicksville",
    "sg:classifiers":[
        {
            "category":"Food & Beverages",
            "subcategory":"Groceries & Convenience Stores",
            "type":"Retail Goods"
        }
    ],
    "sg:phone":"+1 516 465 3969",
    "sg:postcode":"11801",
    "sg:province":"NY",
    "wof:name":"Patel Brothers",
    "wof:placetype":"venue"
},
  "geometry": {"coordinates":[-73.51215500000001,40.758786],"type":"Point"}
}