{
  "type": "Feature",
  "properties": {
    "iso:country":"US",
    "sg:address":"Horsblck Rd",
    "sg:city":"Holtsville",
    "sg:classifiers":[
        {
            "category":"Autos & Motor Vehicles",
            "subcategory":"Auto Supplies",
            "type":"Retail Goods"
        },
        {
            "category":"Personal",
            "type":"Services"
        },
        {
            "category":"Retail",
            "subcategory":"Auto Repair",
            "type":"Services"
        }
    ],
    "sg:phone":"+1 631 732 3704",
    "sg:postcode":"11742",
    "sg:province":"NY",
    "sg:tags":[
        "towing",
        "tire"
    ],
    "wof:name":"Fogerty & Son Bus & Car Maintenance",
    "wof:placetype":"venue"
},
  "geometry": {"coordinates":[-73.038101,40.808899],"type":"Point"}
}