{
  "type": "Feature",
  "properties": {
    "addr:full":"15 W Shore Dr Massapequa NY 11758",
    "addr:housenumber":"15",
    "addr:postcode":"11758",
    "addr:street":"W Shore Dr",
    "iso:country":"US",
    "sg:address":"15 W Shore Dr",
    "sg:city":"Massapequa",
    "sg:classifiers":[
        {
            "category":"Building & Trades",
            "subcategory":"Construction",
            "type":"Services"
        }
    ],
    "sg:phone":"+1 516 799 5189",
    "sg:postcode":"11758",
    "sg:province":"NY",
    "sg:tags":[
        "house"
    ],
    "wof:name":"Daniel T Ancesty",
    "wof:placetype":"venue"
},
  "geometry": {"coordinates":[-73.443174,40.664731],"type":"Point"}
}