{
  "type": "Feature",
  "properties": {
    "addr:full":"677 Glen Cove Ave Glen Head NY 11545",
    "addr:housenumber":"677",
    "addr:postcode":"11545",
    "addr:street":"Glen Cove Ave Glen",
    "iso:country":"US",
    "sg:address":"677 Glen Cove Ave",
    "sg:city":"Glen Head",
    "sg:classifiers":[
        {
            "category":"Shopping",
            "subcategory":"Discount & Variety Stores",
            "type":"Retail Goods"
        }
    ],
    "sg:phone":"+1   ",
    "sg:postcode":"11545",
    "sg:province":"NY",
    "wof:name":"Value Mart",
    "wof:placetype":"venue"
},
  "geometry": {"coordinates":[-73.62982,40.832689],"type":"Point"}
}