{
  "type": "Feature",
  "properties": {
    "iso:country":"US",
    "sg:address":"1150 Sycamore St",
    "sg:city":"Buffalo",
    "sg:classifiers":[
        {
            "category":"Retail",
            "subcategory":"Auto Repair",
            "type":"Services"
        },
        {
            "category":"Wholesale",
            "subcategory":"Auto Parts",
            "type":"Manufacturing & Wholesale Goods"
        }
    ],
    "sg:phone":"+1 716 892 0865",
    "sg:postcode":"14212",
    "sg:province":"NY",
    "sg:tags":[
        "equipment",
        "truck",
        "general"
    ],
    "wof:name":"Bison Radiator Svce",
    "wof:placetype":"venue"
},
  "geometry": {"coordinates":[-78.829295,42.900819],"type":"Point"}
}