{
  "type": "Feature",
  "properties": {
    "iso:country":"US",
    "sg:address":"870 Hunts Point Ave",
    "sg:city":"Bronx",
    "sg:classifiers":[
        {
            "category":"Shopping",
            "subcategory":"Department Store",
            "type":"Retail Goods"
        }
    ],
    "sg:phone":"+1   ",
    "sg:postcode":"10474",
    "sg:province":"NY",
    "wof:name":"Dollar Goal Inc",
    "wof:placetype":"venue"
},
  "geometry": {"coordinates":[-73.889713,40.819433],"type":"Point"}
}