{
  "type": "Feature",
  "properties": {
    "addr:full":"17511 148th Ave Jamaica NY 11434",
    "addr:housenumber":"17511",
    "addr:postcode":"11434",
    "addr:street":"148Th Ave",
    "iso:country":"US",
    "sg:address":"17511 148th Ave",
    "sg:city":"Jamaica",
    "sg:classifiers":[
        {
            "category":"Airline",
            "type":"Transportation"
        }
    ],
    "sg:phone":"+1 718 656 0055",
    "sg:postcode":"11434",
    "sg:province":"NY",
    "sg:tags":[
        "shuttle",
        "airport"
    ],
    "wof:name":"Nakamura Air Express U S A",
    "wof:placetype":"venue"
},
  "geometry": {"coordinates":[-73.770191,40.659393],"type":"Point"}
}