{
  "type": "Feature",
  "properties": {
    "addr:full":"170 E 118th St New York NY 10035",
    "addr:housenumber":"170",
    "addr:postcode":"10035",
    "addr:street":"E 118Th St",
    "iso:country":"US",
    "sg:address":"170 E 118th St",
    "sg:city":"New York",
    "sg:classifiers":[
        {
            "category":"Retail",
            "subcategory":"Repair Shop",
            "type":"Services"
        }
    ],
    "sg:phone":"+1 917 546 1722",
    "sg:postcode":"10035",
    "sg:province":"NY",
    "sg:tags":[
        "lock",
        "locksmith"
    ],
    "wof:name":"24 Hour 7 Day Emerg Locksmith",
    "wof:placetype":"venue"
},
  "geometry": {"coordinates":[-73.93906200000001,40.799253],"type":"Point"}
}