{
  "type": "Feature",
  "properties": {
    "addr:full":"291 W Main St Smithtown NY 11787",
    "addr:housenumber":"291",
    "addr:postcode":"11787",
    "addr:street":"W Main St",
    "iso:country":"US",
    "sg:address":"291 W Main St",
    "sg:city":"Smithtown",
    "sg:classifiers":[
        {
            "category":"Professional",
            "type":"Services"
        }
    ],
    "sg:phone":"+1 631 361 7017",
    "sg:postcode":"11787",
    "sg:province":"NY",
    "sg:tags":[
        "establishment"
    ],
    "wof:name":"M I Sterling Silver",
    "wof:placetype":"venue"
},
  "geometry": {"coordinates":[-73.204037,40.856793],"type":"Point"}
}