{
  "type": "Feature",
  "properties": {
    "iso:country":"US",
    "sg:address":"393 Middle Country Rd",
    "sg:city":"Coram",
    "sg:classifiers":[
        {
            "category":"Restaurant",
            "type":"Food & Drink"
        }
    ],
    "sg:phone":"+1 631 736 5000",
    "sg:postcode":"11727",
    "sg:province":"NY",
    "sg:website":"www.honeybaked.com",
    "wof:name":"Honey Baked Ham Co",
    "wof:placetype":"venue"
},
  "geometry": {"coordinates":[-73.023343,40.867889],"type":"Point"}
}