{
  "type": "Feature",
  "properties": {
    "addr:full":"1207 Quentin Rd Brooklyn NY 11229",
    "addr:housenumber":"1207",
    "addr:postcode":"11229",
    "addr:street":"Quentin Rd",
    "iso:country":"US",
    "sg:address":"1207 Quentin Rd",
    "sg:city":"Brooklyn",
    "sg:classifiers":[
        {
            "category":"Education",
            "subcategory":"Dance Studio",
            "type":"Public Place"
        }
    ],
    "sg:phone":"+1 718 336 3627",
    "sg:postcode":"11229",
    "sg:province":"NY",
    "wof:name":"Kings Dancesport Center I",
    "wof:placetype":"venue"
},
  "geometry": {"coordinates":[-73.960088,40.6081],"type":"Point"}
}