{
  "type": "Feature",
  "properties": {
    "addr:full":"460 Prospect Pl Brooklyn NY 11238",
    "addr:housenumber":"460",
    "addr:postcode":"11238",
    "addr:street":"Prospect Pl",
    "iso:country":"US",
    "sg:address":"460 Prospect Pl",
    "sg:city":"Brooklyn",
    "sg:classifiers":[
        {
            "category":"Wholesale",
            "subcategory":"Toys & Hobbies",
            "type":"Manufacturing & Wholesale Goods"
        }
    ],
    "sg:phone":"+1 718 789 2531",
    "sg:postcode":"11238",
    "sg:province":"NY",
    "wof:name":"Pierre Craft Johanna",
    "wof:placetype":"venue"
},
  "geometry": {"coordinates":[-73.96108099999999,40.676043],"type":"Point"}
}