{
  "type": "Feature",
  "properties": {
    "addr:full":"325 Clinton Ave Brooklyn NY 11205",
    "addr:housenumber":"325",
    "addr:postcode":"11205",
    "addr:street":"Clinton Ave",
    "iso:country":"US",
    "sg:address":"325 Clinton Ave",
    "sg:city":"Brooklyn",
    "sg:classifiers":[
        {
            "category":"Professional",
            "subcategory":"Lawyer & Legal Services",
            "type":"Services"
        }
    ],
    "sg:phone":"+1 718 783 1677",
    "sg:postcode":"11205",
    "sg:province":"NY",
    "sg:tags":[
        "information",
        "attorney",
        "referral"
    ],
    "wof:name":"Michael C Phillip",
    "wof:placetype":"venue"
},
  "geometry": {"coordinates":[-73.967812,40.687981],"type":"Point"}
}