{
  "type": "Feature",
  "properties": {
    "iso:country":"US",
    "sg:address":"16 Eiseman Ave",
    "sg:city":"Buffalo",
    "sg:classifiers":[
        {
            "category":"Wholesale",
            "subcategory":"Apparel",
            "type":"Manufacturing & Wholesale Goods"
        }
    ],
    "sg:phone":"+1 716 875 9084",
    "sg:postcode":"14217",
    "sg:province":"NY",
    "sg:tags":[
        "clothing"
    ],
    "wof:name":"Adorn Accessories Inc",
    "wof:placetype":"venue"
},
  "geometry": {"coordinates":[-78.873154,42.973443],"type":"Point"}
}