{
  "type": "Feature",
  "properties": {
    "iso:country":"US",
    "sg:address":"1550 Flatbush Ave",
    "sg:city":"Brooklyn",
    "sg:classifiers":[
        {
            "category":"Banks & Credit Unions",
            "subcategory":"Bank",
            "type":"Services"
        }
    ],
    "sg:phone":"+1 718 859 5300",
    "sg:postcode":"11210",
    "sg:province":"NY",
    "sg:tags":[
        "savings",
        "loan",
        "association"
    ],
    "sg:website":"www.asfc.com",
    "wof:name":"Astoria Federal Savings & Loan",
    "wof:placetype":"venue"
},
  "geometry": {"coordinates":[-73.94841,40.633619],"type":"Point"}
}