{
  "type": "Feature",
  "properties": {
    "iso:country":"US",
    "sg:address":"21 Middlesex Dr",
    "sg:city":"Slingerlands",
    "sg:classifiers":[
        {
            "category":"Real Estate",
            "subcategory":"Real Estate Agent",
            "type":"Services"
        }
    ],
    "sg:phone":"+1 518 439 8531",
    "sg:postcode":"12159",
    "sg:province":"NY",
    "sg:tags":[
        "manager"
    ],
    "wof:name":"Khaikin Yakov & Anne Marie",
    "wof:placetype":"venue"
},
  "geometry": {"coordinates":[-73.864045,42.633],"type":"Point"}
}