{
  "type": "Feature",
  "properties": {
    "addr:full":"9 Fordham Hill Oval 1B Bronx NY 10468",
    "addr:housenumber":"9;1b",
    "addr:postcode":"10468",
    "addr:street":"Fordham Hill Oval",
    "iso:country":"US",
    "sg:address":"9 Fordham Hill Oval 1B",
    "sg:city":"Bronx",
    "sg:classifiers":[
        {
            "category":"Social Services",
            "type":"Services"
        },
        {
            "category":"Personal",
            "type":"Services"
        }
    ],
    "sg:phone":"+1 718 733 5541",
    "sg:postcode":"10468",
    "sg:province":"NY",
    "sg:tags":[
        "family",
        "professional",
        "counselors-licensed",
        "individual",
        "marriage",
        "child",
        "counseling",
        "counselor"
    ],
    "wof:name":"Professional Counseling Center",
    "wof:placetype":"venue"
},
  "geometry": {"coordinates":[-73.907449,40.864687],"type":"Point"}
}