{
  "type": "Feature",
  "properties": {
    "iso:country":"US",
    "sg:address":"1400 Hollingsworth Ave",
    "sg:city":"Utica",
    "sg:classifiers":[
        {
            "category":"Building & Trades",
            "subcategory":"Electrical",
            "type":"Services"
        }
    ],
    "sg:phone":"+1 315 733 4880",
    "sg:postcode":"13501",
    "sg:province":"NY",
    "sg:tags":[
        "electrical",
        "contractor"
    ],
    "wof:name":"A & A Electric",
    "wof:placetype":"venue"
},
  "geometry": {"coordinates":[-75.209858,43.085795],"type":"Point"}
}