{
  "type": "Feature",
  "properties": {
    "addr:full":"330 E 39th St New York NY 10016",
    "addr:housenumber":"330",
    "addr:postcode":"10016",
    "addr:street":"E 39Th St",
    "iso:country":"US",
    "sg:address":"330 E 39th St",
    "sg:city":"New York",
    "sg:classifiers":[
        {
            "category":"Real Estate",
            "subcategory":"Real Estate Operator",
            "type":"Services"
        },
        {
            "category":"Real Estate",
            "subcategory":"Real Estate Agent",
            "type":"Services"
        }
    ],
    "sg:phone":"+1 212 741 9700",
    "sg:postcode":"10016",
    "sg:province":"NY",
    "sg:tags":[
        "apartment"
    ],
    "sg:website":"www.nyc-re.com",
    "wof:name":"Jennifer Towers Apartment Corp",
    "wof:placetype":"venue"
},
  "geometry": {"coordinates":[-73.97244999999999,40.747184],"type":"Point"}
}