{
  "type": "Feature",
  "properties": {
    "addr:full":"91 Glenmont Dr Rochester NY 14617",
    "addr:housenumber":"91",
    "addr:postcode":"14617",
    "addr:street":"Glenmont Dr",
    "iso:country":"US",
    "sg:address":"91 Glenmont Dr",
    "sg:city":"Rochester",
    "sg:classifiers":[
        {
            "category":"Real Estate",
            "subcategory":"Real Estate Agent",
            "type":"Services"
        }
    ],
    "sg:phone":"+1 585 338 3788",
    "sg:postcode":"14617",
    "sg:province":"NY",
    "wof:name":"Advanced Appraisal Solutions",
    "wof:placetype":"venue"
},
  "geometry": {"coordinates":[-77.59316800000001,43.238828],"type":"Point"}
}