{
  "type": "Feature",
  "properties": {
    "iso:country":"US",
    "sg:address":"800 Tait Ave",
    "sg:city":"Rochester",
    "sg:classifiers":[
        {
            "category":"Education",
            "subcategory":"School",
            "type":"Public Place"
        }
    ],
    "sg:phone":"+1 585 966 3800",
    "sg:postcode":"14616",
    "sg:province":"NY",
    "wof:name":"Greece Central School District District Administrative Offices",
    "wof:placetype":"venue"
},
  "geometry": {"coordinates":[-77.650841,43.239702],"type":"Point"}
}