{
  "type": "Feature",
  "properties": {
    "addr:full":"308 Sheep Pasture Rd East Setauket NY 11733",
    "addr:housenumber":"308",
    "addr:postcode":"11733",
    "addr:street":"Sheep Pasture Rd",
    "iso:country":"US",
    "sg:address":"308 Sheep Pasture Rd",
    "sg:city":"East Setauket",
    "sg:classifiers":[
        {
            "category":"Building & Trades",
            "subcategory":"Construction",
            "type":"Services"
        }
    ],
    "sg:phone":"+1 631 331 3004",
    "sg:postcode":"11733",
    "sg:province":"NY",
    "sg:tags":[
        "resurfacing",
        "laying",
        "refinishing",
        "floor"
    ],
    "wof:name":"White Knight Flooring",
    "wof:placetype":"venue"
},
  "geometry": {"coordinates":[-73.081581,40.924319],"type":"Point"}
}