{
  "type": "Feature",
  "properties": {
    "addr:full":"519 W 181st St New York NY 10033",
    "addr:housenumber":"519",
    "addr:postcode":"10033",
    "addr:street":"W 181St St",
    "iso:country":"US",
    "sg:address":"519 W 181st St",
    "sg:city":"New York",
    "sg:classifiers":[
        {
            "category":"Building & Trades",
            "subcategory":"Equipment Rental",
            "type":"Services"
        }
    ],
    "sg:phone":"+1 212 543 2490",
    "sg:postcode":"10033",
    "sg:province":"NY",
    "wof:name":"Rent-A-Center",
    "wof:placetype":"venue"
},
  "geometry": {"coordinates":[-73.93185,40.848548],"type":"Point"}
}