{
  "type": "Feature",
  "properties": {
    "addr:full":"125 Columbus Ave New York NY 10023",
    "addr:housenumber":"125",
    "addr:postcode":"10023",
    "addr:street":"Columbus Ave",
    "iso:country":"US",
    "sg:address":"125 Columbus Ave",
    "sg:city":"New York",
    "sg:classifiers":[
        {
            "category":"Organizations",
            "subcategory":"Religious Organization",
            "type":"Services"
        }
    ],
    "sg:phone":"+1 212 579 2661",
    "sg:postcode":"10023",
    "sg:province":"NY",
    "sg:tags":[
        "church"
    ],
    "wof:name":"Manhattan Seventh Deaf Branch",
    "wof:placetype":"venue"
},
  "geometry": {"coordinates":[-73.981748,40.773175],"type":"Point"}
}