{
  "type": "Feature",
  "properties": {
    "addr:full":"1412 North St Endicott NY 13760",
    "addr:housenumber":"1412",
    "addr:postcode":"13760",
    "addr:street":"North St",
    "iso:country":"US",
    "sg:address":"1412 North St",
    "sg:city":"Endicott",
    "sg:classifiers":[
        {
            "category":"Restaurant",
            "type":"Food & Drink"
        }
    ],
    "sg:phone":"+1 607 786 0744",
    "sg:postcode":"13760",
    "sg:province":"NY",
    "wof:name":"Touch Of Sicily Cafe",
    "wof:placetype":"venue"
},
  "geometry": {"coordinates":[-76.046178,42.105047],"type":"Point"}
}