{
  "type": "Feature",
  "properties": {
    "addr:full":"835 Dekalb Ave Brooklyn NY 11221",
    "addr:housenumber":"835",
    "addr:postcode":"11221",
    "addr:street":"Dekalb Ave",
    "iso:country":"US",
    "sg:address":"835 Dekalb Ave",
    "sg:city":"Brooklyn",
    "sg:classifiers":[
        {
            "category":"Restaurant",
            "type":"Food & Drink"
        }
    ],
    "sg:phone":"+1   ",
    "sg:postcode":"11221",
    "sg:province":"NY",
    "sg:tags":[
        "eating"
    ],
    "wof:name":"Hing Lung Kitchen",
    "wof:placetype":"venue"
},
  "geometry": {"coordinates":[-73.94564099999999,40.692032],"type":"Point"}
}