{
  "type": "Feature",
  "properties": {
    "addr:full":"601 Edgewood Ave Rochester NY 14618",
    "addr:housenumber":"601",
    "addr:postcode":"14618",
    "addr:street":"Edgewood Ave",
    "iso:country":"US",
    "sg:address":"601 Edgewood Ave",
    "sg:city":"Rochester",
    "sg:classifiers":[
        {
            "category":"Organizations",
            "subcategory":"Religious Organization",
            "type":"Services"
        }
    ],
    "sg:phone":"+1 585 244 3010",
    "sg:postcode":"14618",
    "sg:province":"NY",
    "sg:tags":[
        "church"
    ],
    "wof:name":"Our Lady Queen Of Peace",
    "wof:placetype":"venue"
},
  "geometry": {"coordinates":[-77.56179400000001,43.108294],"type":"Point"}
}