{
  "type": "Feature",
  "properties": {
    "addr:full":"307 Clinton St Hempstead NY 11550",
    "addr:housenumber":"307",
    "addr:postcode":"11550",
    "addr:street":"Clinton St",
    "iso:country":"US",
    "sg:address":"307 Clinton St",
    "sg:city":"Hempstead",
    "sg:classifiers":[
        {
            "category":"Building & Trades",
            "subcategory":"Plumbing",
            "type":"Services"
        }
    ],
    "sg:phone":"+1 516 483 8622",
    "sg:postcode":"11550",
    "sg:province":"NY",
    "sg:tags":[
        "contractor"
    ],
    "wof:name":"Ziminski Inc",
    "wof:placetype":"venue"
},
  "geometry": {"coordinates":[-73.62078700000001,40.715917],"type":"Point"}
}