{
  "type": "Feature",
  "properties": {
    "addr:full":"24 Gillette Ave Sayville NY 11782",
    "addr:housenumber":"24",
    "addr:postcode":"11782",
    "addr:street":"Gillette Ave",
    "iso:country":"US",
    "sg:address":"24 Gillette Ave",
    "sg:city":"Sayville",
    "sg:classifiers":[
        {
            "category":"Personal",
            "subcategory":"Beauty Salon",
            "type":"Services"
        }
    ],
    "sg:phone":"+1 631 567 2224",
    "sg:postcode":"11782",
    "sg:province":"NY",
    "wof:name":"Studio 24",
    "wof:placetype":"venue"
},
  "geometry": {"coordinates":[-73.082002,40.735247],"type":"Point"}
}