{
  "type": "Feature",
  "properties": {
    "iso:country":"US",
    "sg:address":"163 Verdi St",
    "sg:city":"Farmingdale",
    "sg:classifiers":[
        {
            "category":"Wholesale",
            "subcategory":"Scrap",
            "type":"Manufacturing & Wholesale Goods"
        }
    ],
    "sg:phone":"+1 631 752 2522",
    "sg:postcode":"11735",
    "sg:province":"NY",
    "sg:tags":[
        "material"
    ],
    "wof:name":"Yee Sheng Inc",
    "wof:placetype":"venue"
},
  "geometry": {"coordinates":[-73.41576999999999,40.713397],"type":"Point"}
}