{
  "type": "Feature",
  "properties": {
    "addr:full":"3409 Bishop Hill Rd Marcellus NY 13108",
    "addr:housenumber":"3409",
    "addr:postcode":"13108",
    "addr:street":"Bishop Hill Rd",
    "iso:country":"US",
    "sg:address":"3409 Bishop Hill Rd",
    "sg:city":"Marcellus",
    "sg:classifiers":[
        {
            "category":"Restaurant",
            "type":"Food & Drink"
        }
    ],
    "sg:phone":"+1 315 673 4927",
    "sg:postcode":"13108",
    "sg:province":"NY",
    "sg:tags":[
        "parlor",
        "ice",
        "cream"
    ],
    "wof:name":"Wegman's Dairy",
    "wof:placetype":"venue"
},
  "geometry": {"coordinates":[-76.35242700000001,42.946964],"type":"Point"}
}