{
  "type": "Feature",
  "properties": {
    "iso:country":"US",
    "sg:address":"525 W Main St",
    "sg:city":"Endicott",
    "sg:classifiers":[
        {
            "category":"Building & Trades",
            "subcategory":"Construction",
            "type":"Services"
        }
    ],
    "sg:phone":"+1 607 658 9072",
    "sg:postcode":"13760",
    "sg:province":"NY",
    "sg:tags":[
        "general",
        "contractor"
    ],
    "wof:name":"M Markoff & Sons Construction",
    "wof:placetype":"venue"
},
  "geometry": {"coordinates":[-76.07444,42.093075],"type":"Point"}
}