{
  "type": "Feature",
  "properties": {
    "addr:full":"2468 E Henrietta Rd Rochester NY 14623",
    "addr:housenumber":"2468",
    "addr:postcode":"14623",
    "addr:street":"E Henrietta Rd",
    "iso:country":"US",
    "sg:address":"2468 E Henrietta Rd",
    "sg:city":"Rochester",
    "sg:classifiers":[
        {
            "category":"Professional",
            "subcategory":"Lawyer & Legal Services",
            "type":"Services"
        }
    ],
    "sg:phone":"+1 585 334 4270",
    "sg:postcode":"14623",
    "sg:province":"NY",
    "sg:tags":[
        "attorney",
        "real estate",
        "law",
        "bankruptcy"
    ],
    "sg:website":"http://www.rschwartzlaw.com/",
    "wof:name":"Schwartz Robert A",
    "wof:placetype":"venue"
},
  "geometry": {"coordinates":[-77.607519,43.069947],"type":"Point"}
}