{
  "type": "Feature",
  "properties": {
    "addr:full":"8606 Ave L Brooklyn NY 11236",
    "addr:housenumber":"8606",
    "addr:postcode":"11236",
    "addr:street":"Ave L",
    "iso:country":"US",
    "sg:address":"8606 Ave L",
    "sg:city":"Brooklyn",
    "sg:classifiers":[
        {
            "category":"Organizations",
            "subcategory":"Community Association",
            "type":"Services"
        }
    ],
    "sg:phone":"+1 718 531 4546",
    "sg:postcode":"11236",
    "sg:province":"NY",
    "sg:tags":[
        "youth",
        "empowerment"
    ],
    "wof:name":"Miss Black Wrld NY Orgnization",
    "wof:placetype":"venue"
},
  "geometry": {"coordinates":[-73.90267799999999,40.633809],"type":"Point"}
}