{
  "type": "Feature",
  "properties": {
    "iso:country":"US",
    "sg:address":"629 Co Rd 26A",
    "sg:city":"Stuyvesant",
    "sg:classifiers":[
        {
            "category":"Building & Trades",
            "subcategory":"Construction",
            "type":"Services"
        }
    ],
    "sg:phone":"+1 518 758 1660",
    "sg:postcode":"12173",
    "sg:province":"NY",
    "sg:tags":[
        "painter"
    ],
    "wof:name":"C G Dick Painting",
    "wof:placetype":"venue"
},
  "geometry": {"coordinates":[-73.73405700000001,42.377858],"type":"Point"}
}