{
  "type": "Feature",
  "properties": {
    "addr:full":"55 Suto Rd Voorheesville NY 12186",
    "addr:housenumber":"55",
    "addr:postcode":"12186",
    "addr:street":"Suto Rd",
    "iso:country":"US",
    "sg:address":"55 Suto Rd",
    "sg:city":"Voorheesville",
    "sg:classifiers":[
        {
            "category":"Building & Trades",
            "subcategory":"Landscaping Services",
            "type":"Services"
        }
    ],
    "sg:phone":"+1 518 872 0350",
    "sg:postcode":"12186",
    "sg:province":"NY",
    "wof:name":"Shade Tree Landscaping",
    "wof:placetype":"venue"
},
  "geometry": {"coordinates":[-74.025846,42.641552],"type":"Point"}
}