{
  "type": "Feature",
  "properties": {
    "iso:country":"US",
    "sg:address":"141 Groton Ave",
    "sg:city":"Cortland",
    "sg:classifiers":[
        {
            "category":"Health Services",
            "subcategory":"Doctor",
            "type":"Services"
        }
    ],
    "sg:phone":"+1 607 756 0709",
    "sg:postcode":"13045",
    "sg:province":"NY",
    "sg:tags":[
        "physician",
        "medical",
        "surgeon"
    ],
    "wof:name":"Otter Creek Medical Office",
    "wof:placetype":"venue"
},
  "geometry": {"coordinates":[-76.19210200000001,42.600778],"type":"Point"}
}