{
  "type": "Feature",
  "properties": {
    "addr:full":"1151 Pittsford Victor Rd Pittsford NY 14534",
    "addr:housenumber":"1151",
    "addr:postcode":"14534",
    "addr:street":"Pittsford Victor Rd",
    "iso:country":"US",
    "sg:address":"1151 Pittsford Victor Rd",
    "sg:city":"Pittsford",
    "sg:classifiers":[
        {
            "category":"Utilities",
            "subcategory":"Telephone",
            "type":"Services"
        }
    ],
    "sg:phone":"+1   ",
    "sg:postcode":"14534",
    "sg:province":"NY",
    "sg:tags":[
        "communications"
    ],
    "wof:name":"Inter-Media Communications",
    "wof:placetype":"venue"
},
  "geometry": {"coordinates":[-77.46789,43.046395],"type":"Point"}
}