{
  "type": "Feature",
  "properties": {
    "addr:full":"2919 Tiemann Ave Bronx NY 10469",
    "addr:housenumber":"2919",
    "addr:postcode":"10469",
    "addr:street":"Tiemann Ave",
    "iso:country":"US",
    "sg:address":"2919 Tiemann Ave",
    "sg:city":"Bronx",
    "sg:classifiers":[
        {
            "category":"Wholesale",
            "subcategory":"Groceries",
            "type":"Manufacturing & Wholesale Goods"
        }
    ],
    "sg:phone":"+1 718 320 5365",
    "sg:postcode":"10469",
    "sg:province":"NY",
    "sg:tags":[
        "beverage"
    ],
    "wof:name":"Pat's Exotic Beverages",
    "wof:placetype":"venue"
},
  "geometry": {"coordinates":[-73.839855,40.869952],"type":"Point"}
}