{
  "type": "Feature",
  "properties": {
    "iso:country":"US",
    "sg:address":"315 W 70 St",
    "sg:city":"New York",
    "sg:classifiers":[
        {
            "category":"Health Services",
            "subcategory":"Doctor",
            "type":"Services"
        }
    ],
    "sg:phone":"+1 212 501 7177",
    "sg:postcode":"10023",
    "sg:province":"NY",
    "wof:name":"Gadol Elmira",
    "wof:placetype":"venue"
},
  "geometry": {"coordinates":[-73.98688,40.779131],"type":"Point"}
}