{
  "type": "Feature",
  "properties": {
    "addr:full":"700 W 180th St New York NY 10033",
    "addr:housenumber":"700",
    "addr:postcode":"10033",
    "addr:street":"W 180Th St",
    "iso:country":"US",
    "sg:address":"700 W 180th St",
    "sg:city":"New York",
    "sg:classifiers":[
        {
            "category":"Education",
            "subcategory":"University",
            "type":"Public Place"
        }
    ],
    "sg:phone":"+1 212 923 0803",
    "sg:postcode":"10033",
    "sg:province":"NY",
    "sg:tags":[
        "college"
    ],
    "wof:name":"La Salle University",
    "wof:placetype":"venue"
},
  "geometry": {"coordinates":[-73.936418,40.849396],"type":"Point"}
}