{
  "type": "Feature",
  "properties": {
    "addr:full":"90 Vermilyea Ave New York NY 10034",
    "addr:housenumber":"90",
    "addr:postcode":"10034",
    "addr:street":"Vermilyea Ave",
    "iso:country":"US",
    "sg:address":"90 Vermilyea Ave",
    "sg:city":"New York",
    "sg:classifiers":[
        {
            "category":"Government",
            "subcategory":"Post Office",
            "type":"Public Place"
        }
    ],
    "sg:phone":"+1 212 567 7821",
    "sg:postcode":"10034",
    "sg:province":"NY",
    "sg:website":"www.usps.com",
    "wof:name":"US Post Office",
    "wof:placetype":"venue"
},
  "geometry": {"coordinates":[-73.92281199999999,40.866081],"type":"Point"}
}