{
  "type": "Feature",
  "properties": {
    "iso:country":"US",
    "sg:address":"1350 Broadway",
    "sg:city":"New York",
    "sg:classifiers":[
        {
            "category":"Professional",
            "subcategory":"Lawyer & Legal Services",
            "type":"Services"
        }
    ],
    "sg:phone":"+1 212 904 1234",
    "sg:postcode":"10018",
    "sg:province":"NY",
    "wof:name":"Dreier Llp",
    "wof:placetype":"venue"
},
  "geometry": {"coordinates":[-73.98765,40.75075],"type":"Point"}
}