{
  "type": "Feature",
  "properties": {
    "iso:country":"US",
    "sg:address":"552 Main St",
    "sg:city":"Phoenix",
    "sg:classifiers":[
        {
            "category":"Education",
            "subcategory":"School",
            "type":"Public Place"
        }
    ],
    "sg:phone":"+1 315 695 1632",
    "sg:postcode":"13135",
    "sg:province":"NY",
    "wof:name":"John C Birdlebough High School",
    "wof:placetype":"venue"
},
  "geometry": {"coordinates":[-76.302661,43.233284],"type":"Point"}
}