{
  "type": "Feature",
  "properties": {
    "iso:country":"US",
    "sg:address":"3138 Erie Blvd E",
    "sg:city":"Syracuse",
    "sg:classifiers":[
        {
            "category":"Personal",
            "subcategory":"Beauty Salon",
            "type":"Services"
        }
    ],
    "sg:phone":"+1 315 446 7045",
    "sg:postcode":"13214",
    "sg:province":"NY",
    "sg:tags":[
        "shop"
    ],
    "wof:name":"Hair Theater Inc",
    "wof:placetype":"venue"
},
  "geometry": {"coordinates":[-76.079072,43.055329],"type":"Point"}
}