{
  "type": "Feature",
  "properties": {
    "iso:country":"US",
    "sg:address":"2401 Marion Ave",
    "sg:city":"Bronx",
    "sg:classifiers":[
        {
            "category":"Organizations",
            "subcategory":"Religious Organization",
            "type":"Services"
        }
    ],
    "sg:phone":"+1 718 367 6937",
    "sg:postcode":"10458",
    "sg:province":"NY",
    "wof:name":"Grace Temple",
    "wof:placetype":"venue"
},
  "geometry": {"coordinates":[-73.89558,40.858694],"type":"Point"}
}