{
  "type": "Feature",
  "properties": {
    "addr:full":"498 Saint Paul St Rochester NY 14605",
    "addr:housenumber":"498",
    "addr:postcode":"14605",
    "addr:street":"Saint Paul St",
    "iso:country":"US",
    "sg:address":"498 Saint Paul St",
    "sg:city":"Rochester",
    "sg:classifiers":[
        {
            "category":"Restaurant",
            "type":"Food & Drink"
        }
    ],
    "sg:phone":"+1 585 546 6699",
    "sg:postcode":"14605",
    "sg:province":"NY",
    "sg:tags":[
        "bar"
    ],
    "wof:name":"Fast Eddie's Bar & Grill",
    "wof:placetype":"venue"
},
  "geometry": {"coordinates":[-77.614709,43.165284],"type":"Point"}
}