{
  "type": "Feature",
  "properties": {
    "iso:country":"US",
    "sg:address":"315 Darrow Ave",
    "sg:city":"Syracuse",
    "sg:classifiers":[
        {
            "category":"Retail",
            "subcategory":"Auto Repair",
            "type":"Services"
        }
    ],
    "sg:phone":"+1   ",
    "sg:postcode":"13209",
    "sg:province":"NY",
    "sg:tags":[
        "general"
    ],
    "wof:name":"Northerntier Auto",
    "wof:placetype":"venue"
},
  "geometry": {"coordinates":[-76.225708,43.057097],"type":"Point"}
}