{
  "type": "Feature",
  "properties": {
    "iso:country":"US",
    "sg:address":"390 E Suffolk Ave",
    "sg:city":"Islandia",
    "sg:classifiers":[
        {
            "category":"Taxi",
            "type":"Transportation"
        }
    ],
    "sg:phone":"+1 631 342 1111",
    "sg:postcode":"11749",
    "sg:province":"NY",
    "sg:tags":[
        "taxicab"
    ],
    "wof:name":"Reliable Taxi",
    "wof:placetype":"venue"
},
  "geometry": {"coordinates":[-73.177046,40.795897],"type":"Point"}
}