{
  "type": "Feature",
  "properties": {
    "iso:country":"US",
    "sg:address":"639 Main St",
    "sg:city":"Poughkeepsie",
    "sg:classifiers":[
        {
            "category":"Bars & Pubs",
            "type":"Food & Drink"
        }
    ],
    "sg:phone":"+1 845 454 1094",
    "sg:postcode":"12601",
    "sg:province":"NY",
    "sg:tags":[
        "lounge",
        "cocktail"
    ],
    "wof:name":"William's Lounge",
    "wof:placetype":"venue"
},
  "geometry": {"coordinates":[-73.912858,41.698717],"type":"Point"}
}