{
  "type": "Feature",
  "properties": {
    "addr:full":"455 Lenox Ave New York NY 10037",
    "addr:housenumber":"455",
    "addr:postcode":"10037",
    "addr:street":"Lenox Ave",
    "iso:country":"US",
    "sg:address":"455 Lenox Ave",
    "sg:city":"New York",
    "sg:classifiers":[
        {
            "category":"Retail",
            "subcategory":"Funeral Services",
            "type":"Services"
        }
    ],
    "sg:phone":"+1 212 926 6565",
    "sg:postcode":"10037",
    "sg:province":"NY",
    "sg:tags":[
        "crematory"
    ],
    "wof:name":"Bailey's Funeral Home",
    "wof:placetype":"venue"
},
  "geometry": {"coordinates":[-73.942083,40.81246],"type":"Point"}
}