{
  "type": "Feature",
  "properties": {
    "iso:country":"US",
    "sg:address":"423 Broadway",
    "sg:city":"Newburgh",
    "sg:classifiers":[
        {
            "category":"Shopping",
            "subcategory":"Department Store",
            "type":"Retail Goods"
        }
    ],
    "sg:phone":"+1 845 561 7079",
    "sg:postcode":"12550",
    "sg:province":"NY",
    "wof:name":"Family Dollar Stores Inc",
    "wof:placetype":"venue"
},
  "geometry": {"coordinates":[-74.0271,41.500999],"type":"Point"}
}