{
  "type": "Feature",
  "properties": {
    "addr:full":"1033 Morris Park Ave Bronx NY 10461",
    "addr:housenumber":"1033",
    "addr:postcode":"10461",
    "addr:street":"Morris Park Ave",
    "iso:country":"US",
    "sg:address":"1033 Morris Park Ave",
    "sg:city":"Bronx",
    "sg:classifiers":[
        {
            "category":"Retail",
            "subcategory":"Portrait Studio",
            "type":"Services"
        },
        {
            "category":"Professional",
            "subcategory":"Art Services",
            "type":"Services"
        }
    ],
    "sg:phone":"+1 718 918 2653",
    "sg:postcode":"10461",
    "sg:province":"NY",
    "sg:tags":[
        "photographer",
        "photography",
        "store"
    ],
    "wof:name":"Photo Department",
    "wof:placetype":"venue"
},
  "geometry": {"coordinates":[-73.8535,40.8493],"type":"Point"}
}