{
  "type": "Feature",
  "properties": {
    "addr:full":"3960 Merrick Rd Seaford NY 11783",
    "addr:housenumber":"3960",
    "addr:postcode":"11783",
    "addr:street":"Merrick Rd",
    "iso:country":"US",
    "sg:address":"3960 Merrick Rd",
    "sg:city":"Seaford",
    "sg:classifiers":[
        {
            "category":"Social Services",
            "type":"Services"
        }
    ],
    "sg:phone":"+1 516 375 3836",
    "sg:postcode":"11783",
    "sg:province":"NY",
    "sg:tags":[
        "counselor",
        "marriage",
        "family"
    ],
    "wof:name":"Karyn Elari",
    "wof:placetype":"venue"
},
  "geometry": {"coordinates":[-73.484939,40.666294],"type":"Point"}
}