{
  "type": "Feature",
  "properties": {
    "addr:full":"1310 Kings Hwy Brooklyn NY 11229",
    "addr:housenumber":"1310",
    "addr:postcode":"11229",
    "addr:street":"Kings Hwy",
    "iso:country":"US",
    "sg:address":"1310 Kings Hwy",
    "sg:city":"Brooklyn",
    "sg:classifiers":[
        {
            "category":"Shopping",
            "subcategory":"Clothing, Apparel, & Fashions",
            "type":"Retail Goods"
        }
    ],
    "sg:phone":"+1 718 336 7058",
    "sg:postcode":"11229",
    "sg:province":"NY",
    "wof:name":"Image Activewear",
    "wof:placetype":"venue"
},
  "geometry": {"coordinates":[-73.95918899999999,40.608281],"type":"Point"}
}