{
  "type": "Feature",
  "properties": {
    "addr:full":"17218 Roosevelt Hwy Kendall NY 14476",
    "addr:housenumber":"17218",
    "addr:postcode":"14476",
    "addr:street":"Roosevelt Hwy",
    "iso:country":"US",
    "sg:address":"17218 Roosevelt Hwy",
    "sg:city":"Kendall",
    "sg:classifiers":[
        {
            "category":"Manufacturing",
            "subcategory":"Jewelry",
            "type":"Manufacturing & Wholesale Goods"
        },
        {
            "category":"Professional",
            "type":"Services"
        }
    ],
    "sg:phone":"+1 585 659 8001",
    "sg:postcode":"14476",
    "sg:province":"NY",
    "sg:tags":[
        "mfg",
        "arts",
        "ware",
        "artist"
    ],
    "sg:website":"www.markusenmetal.com",
    "wof:name":"Markusen Metal Studios Inc",
    "wof:placetype":"venue"
},
  "geometry": {"coordinates":[-78.013518,43.3185],"type":"Point"}
}