{
  "type": "Feature",
  "properties": {
    "iso:country":"US",
    "sg:address":"29 Douglass St",
    "sg:city":"Brentwood",
    "sg:classifiers":[
        {
            "category":"Building & Trades",
            "subcategory":"Construction",
            "type":"Services"
        }
    ],
    "sg:phone":"+1 631 273 6835",
    "sg:postcode":"11717",
    "sg:province":"NY",
    "sg:tags":[
        "fire",
        "restoration",
        "damage"
    ],
    "wof:name":"Islandwide Restoration Co Inc",
    "wof:placetype":"venue"
},
  "geometry": {"coordinates":[-73.24381200000001,40.800375],"type":"Point"}
}