{
  "type": "Feature",
  "properties": {
    "addr:full":"81 Irving Pl New York NY 10003",
    "addr:housenumber":"81",
    "addr:postcode":"10003",
    "addr:street":"Irving Pl",
    "iso:country":"US",
    "sg:address":"81 Irving Pl",
    "sg:city":"New York",
    "sg:classifiers":[
        {
            "category":"Social Services",
            "subcategory":"Job Training",
            "type":"Services"
        }
    ],
    "sg:phone":"+1 212 674 4523",
    "sg:postcode":"10003",
    "sg:province":"NY",
    "sg:tags":[
        "career",
        "counseling",
        "vocational"
    ],
    "wof:name":"Bruce D Herman Career Cnsltng",
    "wof:placetype":"venue"
},
  "geometry": {"coordinates":[-73.98612,40.73764],"type":"Point"}
}