{
  "type": "Feature",
  "properties": {
    "iso:country":"US",
    "sg:address":"3298 Balltown Rd",
    "sg:city":"Schenectady",
    "sg:classifiers":[
        {
            "category":"Building & Trades",
            "subcategory":"Cleaning & Sanitation",
            "type":"Services"
        }
    ],
    "sg:phone":"+1 518 374 3108",
    "sg:postcode":"12304",
    "sg:province":"NY",
    "sg:tags":[
        "house"
    ],
    "wof:name":"ACK Cleaning Svc",
    "wof:placetype":"venue"
},
  "geometry": {"coordinates":[-73.89335699999999,42.779661],"type":"Point"}
}