{
  "type": "Feature",
  "properties": {
    "addr:full":"671 Bay St Staten Island NY 10304",
    "addr:housenumber":"671",
    "addr:postcode":"10304",
    "addr:street":"Bay St",
    "iso:country":"US",
    "sg:address":"671 Bay St",
    "sg:city":"Staten Island",
    "sg:classifiers":[
        {
            "category":"Personal",
            "subcategory":"Beauty Salon",
            "type":"Services"
        }
    ],
    "sg:phone":"+1 718 876 7100",
    "sg:postcode":"10304",
    "sg:province":"NY",
    "wof:name":"Shampoo",
    "wof:placetype":"venue"
},
  "geometry": {"coordinates":[-74.075244,40.626006],"type":"Point"}
}