{
  "type": "Feature",
  "properties": {
    "addr:full":"224 W 49 St New York NY 10019",
    "addr:housenumber":"224",
    "addr:postcode":"10019",
    "addr:street":"W 49 St",
    "iso:country":"US",
    "sg:address":"224 W 49 St",
    "sg:city":"New York",
    "sg:classifiers":[
        {
            "category":"Organizations",
            "subcategory":"Community Association",
            "type":"Services"
        }
    ],
    "sg:phone":"+1 212 757 5966",
    "sg:postcode":"10019",
    "sg:province":"NY",
    "sg:tags":[
        "club"
    ],
    "wof:name":"LA Gazelle",
    "wof:placetype":"venue"
},
  "geometry": {"coordinates":[-73.986315,40.761437],"type":"Point"}
}