{
  "type": "Feature",
  "properties": {
    "iso:country":"US",
    "sg:address":"1582 Jerome Ave",
    "sg:city":"Bronx",
    "sg:classifiers":[
        {
            "category":"Personal",
            "subcategory":"Nail Salon",
            "type":"Services"
        }
    ],
    "sg:phone":"+1 718 731 0786",
    "sg:postcode":"10452",
    "sg:province":"NY",
    "wof:name":"Apple Nail Salon",
    "wof:placetype":"venue"
},
  "geometry": {"coordinates":[-73.91468500000001,40.844371],"type":"Point"}
}