{
  "type": "Feature",
  "properties": {
    "addr:full":"233 Elizabeth St Utica NY 13501",
    "addr:housenumber":"233",
    "addr:postcode":"13501",
    "addr:street":"Elizabeth St",
    "iso:country":"US",
    "sg:address":"233 Elizabeth St",
    "sg:city":"Utica",
    "sg:classifiers":[
        {
            "category":"Wholesale",
            "subcategory":"Medical Equipment & Supplies",
            "type":"Manufacturing & Wholesale Goods"
        }
    ],
    "sg:phone":"+1 315 732 7040",
    "sg:postcode":"13501",
    "sg:province":"NY",
    "sg:tags":[
        "merchandise"
    ],
    "wof:name":"Saint Regis Medical Equipment",
    "wof:placetype":"venue"
},
  "geometry": {"coordinates":[-75.229192,43.100686],"type":"Point"}
}