{
  "type": "Feature",
  "properties": {
    "addr:full":"312 E 93rd St Brooklyn NY 11212",
    "addr:housenumber":"312",
    "addr:postcode":"11212",
    "addr:street":"E 93Rd St",
    "iso:country":"US",
    "sg:address":"312 E 93rd St",
    "sg:city":"Brooklyn",
    "sg:classifiers":[
        {
            "category":"Autos & Motor Vehicles",
            "subcategory":"Automobile Sales",
            "type":"Retail Goods"
        }
    ],
    "sg:phone":"+1   ",
    "sg:postcode":"11212",
    "sg:province":"NY",
    "wof:name":"Satchell Beswick",
    "wof:placetype":"venue"
},
  "geometry": {"coordinates":[-73.92209800000001,40.658186],"type":"Point"}
}