{
  "type": "Feature",
  "properties": {
    "addr:full":"538W 207th St Manhattan NY 10034",
    "addr:housenumber":"538w",
    "addr:postcode":"10034",
    "addr:street":"St",
    "iso:country":"US",
    "sg:address":"538W 207th St",
    "sg:city":"Manhattan",
    "sg:classifiers":[
        {
            "category":"Restaurant",
            "type":"Food & Drink"
        }
    ],
    "sg:phone":"+1 212 942 7451",
    "sg:postcode":"10034",
    "sg:province":"NY",
    "wof:name":"Genesis",
    "wof:placetype":"venue"
},
  "geometry": {"coordinates":[-73.91992399999999,40.865676],"type":"Point"}
}