{
  "type": "Feature",
  "properties": {
    "iso:country":"US",
    "sg:address":"6601 Ward Rd",
    "sg:city":"Niagara Falls",
    "sg:classifiers":[
        {
            "category":"Building & Trades",
            "subcategory":"Plumbing",
            "type":"Services"
        }
    ],
    "sg:phone":"+1 716 731 2654",
    "sg:postcode":"14304",
    "sg:province":"NY",
    "sg:tags":[
        "contractor"
    ],
    "wof:name":"Superior Htg Coolg Niagra Cnty",
    "wof:placetype":"venue"
},
  "geometry": {"coordinates":[-78.889776,43.103578],"type":"Point"}
}