{
  "type": "Feature",
  "properties": {
    "addr:full":"1506 Mermaid Avenue Brooklyn NY 11224",
    "addr:housenumber":"1506",
    "addr:postcode":"11224",
    "addr:street":"Mermaid Avenue",
    "iso:country":"US",
    "sg:address":"1506 Mermaid Avenue",
    "sg:city":"Brooklyn",
    "sg:classifiers":[
        {
            "category":"Retail",
            "subcategory":"Laundry & Dry Cleaning",
            "type":"Services"
        }
    ],
    "sg:phone":"+1 718 372 8086",
    "sg:postcode":"11224",
    "sg:province":"NY",
    "wof:name":"Golden Bell Cleaners",
    "wof:placetype":"venue"
},
  "geometry": {"coordinates":[-73.982837,40.576939],"type":"Point"}
}