{
  "type": "Feature",
  "properties": {
    "iso:country":"US",
    "sg:address":"454 5th Ave",
    "sg:city":"Brooklyn",
    "sg:classifiers":[
        {
            "category":"Shopping",
            "subcategory":"Pharmacy",
            "type":"Retail Goods"
        }
    ],
    "sg:phone":"+1 718 768 0600",
    "sg:postcode":"11215",
    "sg:province":"NY",
    "sg:tags":[
        "drugstore"
    ],
    "sg:website":"www.neergaardpharmacies.com",
    "wof:name":"Neergaard Pharmacies",
    "wof:placetype":"venue"
},
  "geometry": {"coordinates":[-73.986801,40.6688],"type":"Point"}
}