{
  "type": "Feature",
  "properties": {
    "addr:full":"1156 Merrick Ave Merrick NY 11566",
    "addr:housenumber":"1156",
    "addr:postcode":"11566",
    "addr:street":"Merrick Ave",
    "iso:country":"US",
    "sg:address":"1156 Merrick Ave",
    "sg:city":"Merrick",
    "sg:classifiers":[
        {
            "category":"Personal",
            "subcategory":"Barber",
            "type":"Services"
        }
    ],
    "sg:phone":"+1 516 481 7180",
    "sg:postcode":"11566",
    "sg:province":"NY",
    "wof:name":"Bob's Shear Bobs Barber Stylist",
    "wof:placetype":"venue"
},
  "geometry": {"coordinates":[-73.55950199999999,40.681198],"type":"Point"}
}