{
  "type": "Feature",
  "properties": {
    "iso:country":"US",
    "sg:address":"98 Craft Rd",
    "sg:city":"Centereach",
    "sg:classifiers":[
        {
            "category":"Retail",
            "subcategory":"Portrait Studio",
            "type":"Services"
        }
    ],
    "sg:phone":"+1   ",
    "sg:postcode":"11720",
    "sg:province":"NY",
    "sg:tags":[
        "photo"
    ],
    "wof:name":"Laurie Studio",
    "wof:placetype":"venue"
},
  "geometry": {"coordinates":[-73.094533,40.863861],"type":"Point"}
}