{
  "type": "Feature",
  "properties": {
    "addr:full":"2160 Merrick Ave Merrick NY 11566",
    "addr:housenumber":"2160",
    "addr:postcode":"11566",
    "addr:street":"Merrick Ave",
    "iso:country":"US",
    "sg:address":"2160 Merrick Ave",
    "sg:city":"Merrick",
    "sg:classifiers":[
        {
            "category":"Food & Beverages",
            "subcategory":"Groceries & Convenience Stores",
            "type":"Retail Goods"
        }
    ],
    "sg:phone":"+1 516 867 9892",
    "sg:postcode":"11566",
    "sg:province":"NY",
    "sg:tags":[
        "grocer"
    ],
    "sg:website":"www.stopshop.com",
    "wof:name":"Stop & Shop Supermarket",
    "wof:placetype":"venue"
},
  "geometry": {"coordinates":[-73.553247,40.666323],"type":"Point"}
}