{
  "type": "Feature",
  "properties": {
    "addr:full":"277 Broadway New York NY 10007",
    "addr:housenumber":"277",
    "addr:postcode":"10007",
    "addr:street":"Broadway",
    "iso:country":"US",
    "sg:address":"277 Broadway",
    "sg:city":"New York",
    "sg:classifiers":[
        {
            "category":"Professional",
            "subcategory":"Lawyer & Legal Services",
            "type":"Services"
        }
    ],
    "sg:phone":"+1 212 964 9414",
    "sg:postcode":"10007",
    "sg:province":"NY",
    "wof:name":"Ebby Koney Lwyr",
    "wof:placetype":"venue"
},
  "geometry": {"coordinates":[-74.00630200000001,40.714298],"type":"Point"}
}