{
  "type": "Feature",
  "properties": {
    "addr:full":"45 Everett St Valley Stream NY 11580",
    "addr:housenumber":"45",
    "addr:postcode":"11580",
    "addr:street":"Everett St",
    "iso:country":"US",
    "sg:address":"45 Everett St",
    "sg:city":"Valley Stream",
    "sg:classifiers":[
        {
            "category":"Social Services",
            "subcategory":"Child Care",
            "type":"Services"
        }
    ],
    "sg:phone":"+1   ",
    "sg:postcode":"11580",
    "sg:province":"NY",
    "sg:tags":[
        "organization",
        "religious",
        "day"
    ],
    "wof:name":"Trinity Lutheran Nursery Schl",
    "wof:placetype":"venue"
},
  "geometry": {"coordinates":[-73.72205,40.684227],"type":"Point"}
}