{
  "type": "Feature",
  "properties": {
    "addr:full":"1125 Cassell Ave Bay Shore NY 11706",
    "addr:housenumber":"1125",
    "addr:postcode":"11706",
    "addr:street":"Cassell Ave",
    "iso:country":"US",
    "sg:address":"1125 Cassell Ave",
    "sg:city":"Bay Shore",
    "sg:classifiers":[
        {
            "category":"Banks & Credit Unions",
            "subcategory":"Bank",
            "type":"Services"
        }
    ],
    "sg:phone":"+1 631 968 6900",
    "sg:postcode":"11706",
    "sg:province":"NY",
    "sg:tags":[
        "loan",
        "real estate"
    ],
    "wof:name":"Sunset Mortgage",
    "wof:placetype":"venue"
},
  "geometry": {"coordinates":[-73.28597499999999,40.722452],"type":"Point"}
}