{
  "type": "Feature",
  "properties": {
    "addr:full":"1011 Fort Salonga Rd Northport NY 11768",
    "addr:housenumber":"1011",
    "addr:postcode":"11768",
    "addr:street":"Fort Salonga Rd",
    "iso:country":"US",
    "sg:address":"1011 Fort Salonga Rd",
    "sg:city":"Northport",
    "sg:classifiers":[
        {
            "category":"Autos & Motor Vehicles",
            "subcategory":"Fuel & Gas Station",
            "type":"Retail Goods"
        }
    ],
    "sg:phone":"+1 631 757 9863",
    "sg:postcode":"11768",
    "sg:province":"NY",
    "wof:name":"Salonga Svces",
    "wof:placetype":"venue"
},
  "geometry": {"coordinates":[-73.278603,40.9063],"type":"Point"}
}