{
  "type": "Feature",
  "properties": {
    "addr:full":"312 Sand Creek Rd Albany NY 12205",
    "addr:housenumber":"312",
    "addr:postcode":"12205",
    "addr:street":"Sand Creek Rd",
    "iso:country":"US",
    "sg:address":"312 Sand Creek Rd",
    "sg:city":"Albany",
    "sg:classifiers":[
        {
            "category":"Building & Trades",
            "subcategory":"Electrical",
            "type":"Services"
        }
    ],
    "sg:phone":"+1 518 438 3662",
    "sg:postcode":"12205",
    "sg:province":"NY",
    "sg:tags":[
        "electrical",
        "contractor"
    ],
    "wof:name":"Tony Rome Electrical Contg",
    "wof:placetype":"venue"
},
  "geometry": {"coordinates":[-73.800421,42.705217],"type":"Point"}
}