{
  "type": "Feature",
  "properties": {
    "addr:full":"1148 5th Ave New York NY 10128",
    "addr:housenumber":"1148",
    "addr:postcode":"10128",
    "addr:street":"5Th Ave",
    "iso:country":"US",
    "sg:address":"1148 5th Ave",
    "sg:city":"New York",
    "sg:classifiers":[
        {
            "category":"Health Services",
            "subcategory":"Health Practitioner",
            "type":"Services"
        }
    ],
    "sg:phone":"+1 212 996 1020",
    "sg:postcode":"10128",
    "sg:province":"NY",
    "sg:tags":[
        "pathologist",
        "speech"
    ],
    "wof:name":"Evan Lipman Ma",
    "wof:placetype":"venue"
},
  "geometry": {"coordinates":[-73.956262,40.787223],"type":"Point"}
}