{
  "type": "Feature",
  "properties": {
    "addr:full":"9325 Hunting Valley Rd N Clarence NY 14031",
    "addr:housenumber":"9325",
    "addr:postcode":"14031",
    "addr:street":"Hunting Valley Rd N",
    "iso:country":"US",
    "sg:address":"9325 Hunting Valley Rd N",
    "sg:city":"Clarence",
    "sg:classifiers":[
        {
            "category":"Real Estate",
            "subcategory":"Developer",
            "type":"Services"
        }
    ],
    "sg:phone":"+1 716 741 9295",
    "sg:postcode":"14031",
    "sg:province":"NY",
    "wof:name":"Suntreader Development Inc",
    "wof:placetype":"venue"
},
  "geometry": {"coordinates":[-78.64373000000001,42.982496],"type":"Point"}
}