{
  "type": "Feature",
  "properties": {
    "iso:country":"US",
    "sg:address":"51 N State St",
    "sg:city":"Heuvelton",
    "sg:classifiers":[
        {
            "category":"Government",
            "subcategory":"Office",
            "type":"Public Place"
        }
    ],
    "sg:phone":"+1 315 344 7284",
    "sg:postcode":"13654",
    "sg:province":"NY",
    "sg:tags":[
        "village"
    ],
    "wof:name":"Oswegatchie Town Justice",
    "wof:placetype":"venue"
},
  "geometry": {"coordinates":[-75.408869,44.619052],"type":"Point"}
}