{
  "type": "Feature",
  "properties": {
    "addr:full":"250 E 40th St New York NY 10016",
    "addr:housenumber":"250",
    "addr:postcode":"10016",
    "addr:street":"E 40Th St",
    "iso:country":"US",
    "sg:address":"250 E 40th St",
    "sg:city":"New York",
    "sg:classifiers":[
        {
            "category":"Real Estate",
            "subcategory":"Real Estate Agent",
            "type":"Services"
        }
    ],
    "sg:phone":"+1 212 986 7776",
    "sg:postcode":"10016",
    "sg:province":"NY",
    "sg:tags":[
        "building",
        "condominium"
    ],
    "wof:name":"Highpoint Condominium",
    "wof:placetype":"venue"
},
  "geometry": {"coordinates":[-73.97335699999999,40.748572],"type":"Point"}
}