{
  "type": "Feature",
  "properties": {
    "addr:full":"716 Hoosick Rd Troy NY 12180",
    "addr:housenumber":"716",
    "addr:postcode":"12180",
    "addr:street":"Hoosick Rd",
    "iso:country":"US",
    "sg:address":"716 Hoosick Rd",
    "sg:city":"Troy",
    "sg:classifiers":[
        {
            "category":"Food & Beverages",
            "subcategory":"Groceries & Convenience Stores",
            "type":"Retail Goods"
        },
        {
            "category":"Shopping",
            "subcategory":"Florist",
            "type":"Retail Goods"
        }
    ],
    "sg:phone":"+1 518 266 9947",
    "sg:postcode":"12180",
    "sg:province":"NY",
    "sg:tags":[
        "supermarket"
    ],
    "sg:website":"www.pricechopper.com",
    "wof:name":"Price Chopper 3",
    "wof:placetype":"venue"
},
  "geometry": {"coordinates":[-73.644666,42.743933],"type":"Point"}
}