{
  "type": "Feature",
  "properties": {
    "addr:full":"66 Endicott Dr Buffalo NY 14226",
    "addr:housenumber":"66",
    "addr:postcode":"14226",
    "addr:street":"Endicott Dr",
    "iso:country":"US",
    "sg:address":"66 Endicott Dr",
    "sg:city":"Buffalo",
    "sg:classifiers":[
        {
            "category":"Professional",
            "subcategory":"Lawyer & Legal Services",
            "type":"Services"
        }
    ],
    "sg:phone":"+1 716 832 6796",
    "sg:postcode":"14226",
    "sg:province":"NY",
    "sg:tags":[
        "convention",
        "reporters-court"
    ],
    "wof:name":"Diann M Smith",
    "wof:placetype":"venue"
},
  "geometry": {"coordinates":[-78.808577,42.96554],"type":"Point"}
}