{
  "type": "Feature",
  "properties": {
    "addr:full":"855 E 218th St Bronx NY 10467",
    "addr:housenumber":"855",
    "addr:postcode":"10467",
    "addr:street":"E 218Th St",
    "iso:country":"US",
    "sg:address":"855 E 218th St",
    "sg:city":"Bronx",
    "sg:classifiers":[
        {
            "category":"Real Estate",
            "subcategory":"Developer",
            "type":"Services"
        },
        {
            "category":"Professional",
            "subcategory":"Business Services",
            "type":"Services"
        }
    ],
    "sg:phone":"+1 718 798 0423",
    "sg:postcode":"10467",
    "sg:province":"NY",
    "sg:tags":[
        "messenger"
    ],
    "wof:name":"Jam AM Development Corp",
    "wof:placetype":"venue"
},
  "geometry": {"coordinates":[-73.858617,40.881616],"type":"Point"}
}