{
  "type": "Feature",
  "properties": {
    "addr:full":"6632 Wetherole Street Rego Park NY 11374",
    "addr:postcode":"6632;11374",
    "addr:street":"Wetherole Street",
    "iso:country":"US",
    "sg:address":"6632 Wetherole Street",
    "sg:city":"Rego Park",
    "sg:classifiers":[
        {
            "category":"Shopping",
            "subcategory":"Books",
            "type":"Retail Goods"
        }
    ],
    "sg:phone":"+1 718 997 7661",
    "sg:postcode":"11374",
    "sg:province":"NY",
    "sg:tags":[
        "bookstore"
    ],
    "sg:website":"www.bastosbooks.com",
    "wof:name":"Bastos Educational Books",
    "wof:placetype":"venue"
},
  "geometry": {"coordinates":[-73.855707,40.724987],"type":"Point"}
}