{
  "type": "Feature",
  "properties": {
    "addr:full":"13657 Roosevelt Avenue Flushing NY 11354",
    "addr:housenumber":"13657",
    "addr:postcode":"11354",
    "addr:street":"Roosevelt Avenue",
    "iso:country":"US",
    "sg:address":"13657 Roosevelt Avenue",
    "sg:city":"Flushing",
    "sg:classifiers":[
        {
            "category":"Shopping",
            "subcategory":"Mobile Phones",
            "type":"Retail Goods"
        }
    ],
    "sg:phone":"+1 718 359 5372",
    "sg:postcode":"11354",
    "sg:province":"NY",
    "sg:website":"www.sprint.com",
    "wof:name":"Sprint Pcs Personal Communications Svcs",
    "wof:placetype":"venue"
},
  "geometry": {"coordinates":[-73.82801499999999,40.760203],"type":"Point"}
}