{
  "type": "Feature",
  "properties": {
    "iso:country":"US",
    "sg:address":"142 Washington Ave",
    "sg:city":"Albany",
    "sg:classifiers":[
        {
            "category":"Professional",
            "type":"Services"
        }
    ],
    "sg:phone":"+1   ",
    "sg:postcode":"12210",
    "sg:province":"NY",
    "sg:tags":[
        "eating"
    ],
    "wof:name":"Next Door",
    "wof:placetype":"venue"
},
  "geometry": {"coordinates":[-73.759716,42.654448],"type":"Point"}
}