{
  "type": "Feature",
  "properties": {
    "iso:country":"US",
    "sg:address":"2138 Flatbush Ave",
    "sg:city":"Brooklyn",
    "sg:classifiers":[
        {
            "category":"Restaurant",
            "type":"Food & Drink"
        }
    ],
    "sg:phone":"+1   ",
    "sg:postcode":"11234",
    "sg:province":"NY",
    "sg:tags":[
        "eating"
    ],
    "wof:name":"Good Ground Buffet",
    "wof:placetype":"venue"
},
  "geometry": {"coordinates":[-73.930745,40.616973],"type":"Point"}
}