{
  "type": "Feature",
  "properties": {
    "iso:country":"US",
    "sg:address":"37 W 65 St",
    "sg:city":"New York",
    "sg:classifiers":[
        {
            "category":"Real Estate",
            "subcategory":"Real Estate Agent",
            "type":"Services"
        },
        {
            "category":"Real Estate",
            "subcategory":"Real Estate Operator",
            "type":"Services"
        }
    ],
    "sg:phone":"+1 212 787 1270",
    "sg:postcode":"10023",
    "sg:province":"NY",
    "sg:tags":[
        "building",
        "apartment"
    ],
    "wof:name":"Natben Realty Co",
    "wof:placetype":"venue"
},
  "geometry": {"coordinates":[-73.981235,40.77261],"type":"Point"}
}