{
  "type": "Feature",
  "properties": {
    "addr:full":"429 Jerusalem Ave Uniondale NY 11553",
    "addr:housenumber":"429",
    "addr:postcode":"11553",
    "addr:street":"Jerusalem Ave",
    "iso:country":"US",
    "sg:address":"429 Jerusalem Ave",
    "sg:city":"Uniondale",
    "sg:classifiers":[
        {
            "category":"Organizations",
            "subcategory":"Religious Organization",
            "type":"Services"
        }
    ],
    "sg:phone":"+1 516 538 3325",
    "sg:postcode":"11553",
    "sg:province":"NY",
    "sg:tags":[
        "church"
    ],
    "wof:name":"Iglesia Jesus El Buen Pastor",
    "wof:placetype":"venue"
},
  "geometry": {"coordinates":[-73.60118300000001,40.702014],"type":"Point"}
}