{
  "type": "Feature",
  "properties": {
    "addr:full":"11520 Main St Clarence NY 14031",
    "addr:housenumber":"11520",
    "addr:postcode":"14031",
    "addr:street":"Main St",
    "iso:country":"US",
    "sg:address":"11520 Main St",
    "sg:city":"Clarence",
    "sg:classifiers":[
        {
            "category":"Autos & Motor Vehicles",
            "subcategory":"Automobile Sales",
            "type":"Retail Goods"
        }
    ],
    "sg:phone":"+1 716 759 7475",
    "sg:postcode":"14031",
    "sg:province":"NY",
    "sg:tags":[
        "car",
        "dealer"
    ],
    "wof:name":"G W Hauer Ent",
    "wof:placetype":"venue"
},
  "geometry": {"coordinates":[-78.555119,42.989712],"type":"Point"}
}