{
  "type": "Feature",
  "properties": {
    "addr:full":"2011-2031 Utica Avenue South Ozone Park NY 11420",
    "addr:housenumber":"2011-2031",
    "addr:postcode":"11420",
    "addr:street":"Utica Avenue",
    "iso:country":"US",
    "sg:address":"2011-2031 Utica Avenue",
    "sg:city":"South Ozone Park",
    "sg:classifiers":[
        {
            "category":"Autos & Motor Vehicles",
            "subcategory":"Auto Supplies",
            "type":"Retail Goods"
        }
    ],
    "sg:phone":"+1 718 444 0726",
    "sg:postcode":"11420",
    "sg:province":"NY",
    "sg:tags":[
        "tire"
    ],
    "wof:name":"Strauss Discount Auto",
    "wof:placetype":"venue"
},
  "geometry": {"coordinates":[-73.816348,40.67596],"type":"Point"}
}