{
  "type": "Feature",
  "properties": {
    "addr:full":"240 7th Ave Brooklyn NY 11215",
    "addr:housenumber":"240",
    "addr:postcode":"11215",
    "addr:street":"7Th Ave",
    "iso:country":"US",
    "sg:address":"240 7th Ave",
    "sg:city":"Brooklyn",
    "sg:classifiers":[
        {
            "category":"Wholesale",
            "subcategory":"Drugs",
            "type":"Manufacturing & Wholesale Goods"
        }
    ],
    "sg:phone":"+1 718 219 5658",
    "sg:postcode":"11215",
    "sg:province":"NY",
    "sg:tags":[
        "marketing"
    ],
    "wof:name":"Pena Group Inc",
    "wof:placetype":"venue"
},
  "geometry": {"coordinates":[-73.9795,40.669552],"type":"Point"}
}