{
  "type": "Feature",
  "properties": {
    "iso:country":"US",
    "sg:address":"16 Cres Bch Rd",
    "sg:city":"Staten Island",
    "sg:classifiers":[
        {
            "category":"Wholesale",
            "subcategory":"Construction Materials",
            "type":"Manufacturing & Wholesale Goods"
        }
    ],
    "sg:phone":"+1 718 967 2328",
    "sg:postcode":"10308",
    "sg:province":"NY",
    "sg:tags":[
        "fence"
    ],
    "wof:name":"L D's Fence Co",
    "wof:placetype":"venue"
},
  "geometry": {"coordinates":[-74.14384699999999,40.537161],"type":"Point"}
}