{
  "type": "Feature",
  "properties": {
    "iso:country":"US",
    "sg:address":"7 S Highland Ave",
    "sg:city":"Ossining",
    "sg:classifiers":[
        {
            "category":"Organizations",
            "subcategory":"Membership Organization",
            "type":"Services"
        }
    ],
    "sg:phone":"+1   ",
    "sg:postcode":"10562",
    "sg:province":"NY",
    "wof:name":"Poder America Inc",
    "wof:placetype":"venue"
},
  "geometry": {"coordinates":[-73.85959800000001,41.151762],"type":"Point"}
}