{
  "type": "Feature",
  "properties": {
    "addr:full":"7 Kenwood Dr St James NY 11780",
    "addr:housenumber":"7",
    "addr:postcode":"11780",
    "addr:street":"Kenwood Dr",
    "iso:country":"US",
    "sg:address":"7 Kenwood Dr",
    "sg:city":"St James",
    "sg:classifiers":[
        {
            "category":"Building & Trades",
            "subcategory":"Construction",
            "type":"Services"
        }
    ],
    "sg:phone":"+1 631 584 4423",
    "sg:postcode":"11780",
    "sg:province":"NY",
    "sg:tags":[
        "general",
        "contractor"
    ],
    "wof:name":"All Season General Contr Inc",
    "wof:placetype":"venue"
},
  "geometry": {"coordinates":[-73.138965,40.892842],"type":"Point"}
}