{
  "type": "Feature",
  "properties": {
    "addr:full":"932 Broadway Woodmere NY 11598",
    "addr:housenumber":"932",
    "addr:postcode":"11598",
    "addr:street":"Broadway",
    "iso:country":"US",
    "sg:address":"932 Broadway",
    "sg:city":"Woodmere",
    "sg:classifiers":[
        {
            "category":"Health Services",
            "subcategory":"Doctor",
            "type":"Services"
        }
    ],
    "sg:phone":"+1 516 295 7767",
    "sg:postcode":"11598",
    "sg:province":"NY",
    "sg:tags":[
        "dentist"
    ],
    "wof:name":"Berstein & Roz",
    "wof:placetype":"venue"
},
  "geometry": {"coordinates":[-73.70956200000001,40.6291],"type":"Point"}
}