{
  "type": "Feature",
  "properties": {
    "iso:country":"US",
    "sg:address":"232 W 37th Street",
    "sg:city":"New York",
    "sg:classifiers":[
        {
            "category":"Shopping",
            "subcategory":"Crafts & Fabrics",
            "type":"Retail Goods"
        }
    ],
    "sg:phone":"+1 212 868 0944",
    "sg:postcode":"10018",
    "sg:province":"NY",
    "sg:tags":[
        "store"
    ],
    "sg:website":"www.stretchhouse.com/",
    "wof:name":"Stretch House",
    "wof:placetype":"venue"
},
  "geometry": {"coordinates":[-73.99011,40.75328],"type":"Point"}
}