{
  "type": "Feature",
  "properties": {
    "addr:full":"5000 Brush Hollow Rd Westbury NY 11590",
    "addr:housenumber":"5000",
    "addr:postcode":"11590",
    "addr:street":"Brush Hollow Rd",
    "iso:country":"US",
    "sg:address":"5000 Brush Hollow Rd",
    "sg:city":"Westbury",
    "sg:classifiers":[
        {
            "category":"Shopping",
            "subcategory":"Jewelry",
            "type":"Retail Goods"
        }
    ],
    "sg:phone":"+1 516 333 4885",
    "sg:postcode":"11590",
    "sg:province":"NY",
    "wof:name":"D & D Wholesale Jewelery",
    "wof:placetype":"venue"
},
  "geometry": {"coordinates":[-73.563103,40.772099],"type":"Point"}
}