{
  "type": "Feature",
  "properties": {
    "addr:full":"254 Canal Street Rm 3002 New York NY 10013",
    "addr:housenumber":"254",
    "addr:postcode":"3002;10013",
    "addr:street":"Canal Street",
    "iso:country":"US",
    "sg:address":"254 Canal Street Rm 3002",
    "sg:city":"New York",
    "sg:classifiers":[
        {
            "category":"Health Services",
            "subcategory":"Doctor",
            "type":"Services"
        }
    ],
    "sg:phone":"+1 212 431 8808",
    "sg:postcode":"10013",
    "sg:province":"NY",
    "sg:tags":[
        "cardiologist"
    ],
    "wof:name":"Chin Warren W MD Facc",
    "wof:placetype":"venue"
},
  "geometry": {"coordinates":[-74.000609,40.718484],"type":"Point"}
}