{
  "type": "Feature",
  "properties": {
    "addr:full":"5 Winfield St Staten Island NY 10305",
    "addr:housenumber":"5",
    "addr:postcode":"10305",
    "addr:street":"Winfield St",
    "iso:country":"US",
    "sg:address":"5 Winfield St",
    "sg:city":"Staten Island",
    "sg:classifiers":[
        {
            "category":"Retail",
            "subcategory":"Laundry & Dry Cleaning",
            "type":"Services"
        }
    ],
    "sg:phone":"+1 718 351 5003",
    "sg:postcode":"10305",
    "sg:province":"NY",
    "sg:tags":[
        "cleaners",
        "rug",
        "carpet"
    ],
    "wof:name":"John Ando Carpet Care",
    "wof:placetype":"venue"
},
  "geometry": {"coordinates":[-74.07809399999999,40.589856],"type":"Point"}
}