{
  "type": "Feature",
  "properties": {
    "addr:full":"244 Madison Ave Ste 8888 New York NY 10016",
    "addr:housenumber":"244",
    "addr:postcode":"10016",
    "addr:street":"Madison Ave Ste 8888",
    "iso:country":"US",
    "sg:address":"244 Madison Ave Ste 8888",
    "sg:city":"New York",
    "sg:classifiers":[
        {
            "category":"Professional",
            "type":"Services"
        }
    ],
    "sg:phone":"+1 877 771 0145",
    "sg:postcode":"10016",
    "sg:province":"NY",
    "sg:website":"www.jrlanguage.com/translation-s...",
    "wof:name":"JR Language",
    "wof:placetype":"venue"
},
  "geometry": {"coordinates":[-73.98138899999999,40.750071],"type":"Point"}
}