{
  "type": "Feature",
  "properties": {
    "addr:full":"7626 Kirkville Rd Kirkville NY 13082",
    "addr:housenumber":"7626",
    "addr:postcode":"13082",
    "addr:street":"Kirkville Rd",
    "iso:country":"US",
    "sg:address":"7626 Kirkville Rd",
    "sg:city":"Kirkville",
    "sg:classifiers":[
        {
            "category":"Shopping",
            "subcategory":"Clothing, Apparel, & Fashions",
            "type":"Retail Goods"
        }
    ],
    "sg:phone":"+1 315 656 0827",
    "sg:postcode":"13082",
    "sg:province":"NY",
    "sg:tags":[
        "theatrical",
        "costume"
    ],
    "wof:name":"Monique's",
    "wof:placetype":"venue"
},
  "geometry": {"coordinates":[-75.997224,43.088039],"type":"Point"}
}