{
  "type": "Feature",
  "properties": {
    "addr:full":"50-22 39th Ave Woodside NY 11377",
    "addr:housenumber":"50-22",
    "addr:postcode":"11377",
    "addr:street":"39Th Ave",
    "iso:country":"US",
    "sg:address":"50-22 39th Ave",
    "sg:city":"Woodside",
    "sg:classifiers":[
        {
            "category":"Restaurant",
            "type":"Food & Drink"
        }
    ],
    "sg:phone":"+1 718 507 4591",
    "sg:postcode":"11377",
    "sg:province":"NY",
    "sg:tags":[
        "italian",
        "pizza"
    ],
    "sg:website":"www.donatospol.com",
    "wof:name":"Donato's Restaurant",
    "wof:placetype":"venue"
},
  "geometry": {"coordinates":[-73.913522,40.748902],"type":"Point"}
}