{
  "type": "Feature",
  "properties": {
    "addr:full":"1034 5th Ave New York NY 10028",
    "addr:housenumber":"1034",
    "addr:postcode":"10028",
    "addr:street":"5Th Ave",
    "iso:country":"US",
    "sg:address":"1034 5th Ave",
    "sg:city":"New York",
    "sg:classifiers":[
        {
            "category":"Health Services",
            "subcategory":"Doctor",
            "type":"Services"
        }
    ],
    "sg:phone":"+1 212 628 2300",
    "sg:postcode":"10028",
    "sg:province":"NY",
    "sg:tags":[
        "physician",
        "surgeon"
    ],
    "wof:name":"Elahi Ebrahim MD",
    "wof:placetype":"venue"
},
  "geometry": {"coordinates":[-73.96094100000001,40.780482],"type":"Point"}
}