{
  "type": "Feature",
  "properties": {
    "addr:full":"1838 Grant Blvd Syracuse NY 13208",
    "addr:housenumber":"1838",
    "addr:postcode":"13208",
    "addr:street":"Grant Blvd",
    "iso:country":"US",
    "sg:address":"1838 Grant Blvd",
    "sg:city":"Syracuse",
    "sg:classifiers":[
        {
            "category":"Shopping",
            "subcategory":"Used Merchandise",
            "type":"Retail Goods"
        }
    ],
    "sg:phone":"+1 315 478 4345",
    "sg:postcode":"13208",
    "sg:province":"NY",
    "sg:tags":[
        "shop",
        "consignment"
    ],
    "wof:name":"Martha's Madness",
    "wof:placetype":"venue"
},
  "geometry": {"coordinates":[-76.14089800000001,43.072261],"type":"Point"}
}