{
  "type": "Feature",
  "properties": {
    "iso:country":"US",
    "sg:address":"46 E Main St",
    "sg:city":"Springville",
    "sg:classifiers":[
        {
            "category":"Home & Garden",
            "subcategory":"Hardware",
            "type":"Retail Goods"
        }
    ],
    "sg:phone":"+1   ",
    "sg:postcode":"14141",
    "sg:province":"NY",
    "sg:tags":[
        "store"
    ],
    "wof:name":"Springville Hardware Inc",
    "wof:placetype":"venue"
},
  "geometry": {"coordinates":[-78.669766,42.508788],"type":"Point"}
}