{
  "type": "Feature",
  "properties": {
    "iso:country":"US",
    "sg:address":"14 Soundview Ave",
    "sg:city":"White Plains",
    "sg:classifiers":[
        {
            "category":"Health Services",
            "subcategory":"Doctor",
            "type":"Services"
        }
    ],
    "sg:phone":"+1 914 948 7016",
    "sg:postcode":"10606",
    "sg:province":"NY",
    "sg:tags":[
        "medical"
    ],
    "wof:name":"Morton H Berman",
    "wof:placetype":"venue"
},
  "geometry": {"coordinates":[-73.77446999999999,41.019333],"type":"Point"}
}