{
  "type": "Feature",
  "properties": {
    "addr:full":"13175 234th St Rosedale NY 11422",
    "addr:housenumber":"13175",
    "addr:postcode":"11422",
    "addr:street":"234Th St",
    "iso:country":"US",
    "sg:address":"13175 234th St",
    "sg:city":"Rosedale",
    "sg:classifiers":[
        {
            "category":"Health Services",
            "subcategory":"Doctor",
            "type":"Services"
        }
    ],
    "sg:phone":"+1 718 276 1474",
    "sg:postcode":"11422",
    "sg:province":"NY",
    "wof:name":"Thenor-Louis Wesner MD",
    "wof:placetype":"venue"
},
  "geometry": {"coordinates":[-73.734497,40.677101],"type":"Point"}
}