{
  "type": "Feature",
  "properties": {
    "iso:country":"US",
    "sg:address":"18 Highland Mews",
    "sg:city":"Glen Cove",
    "sg:classifiers":[
        {
            "category":"Wholesale",
            "subcategory":"Durable Goods & Equipment",
            "type":"Manufacturing & Wholesale Goods"
        }
    ],
    "sg:phone":"+1 516 671 3637",
    "sg:postcode":"11542",
    "sg:province":"NY",
    "sg:tags":[
        "importer"
    ],
    "wof:name":"Tsm Imports Inc",
    "wof:placetype":"venue"
},
  "geometry": {"coordinates":[-73.629915,40.866173],"type":"Point"}
}