{
  "type": "Feature",
  "properties": {
    "addr:full":"831 Sunrise Hwy Lynbrook NY 11563",
    "addr:housenumber":"831",
    "addr:postcode":"11563",
    "addr:street":"Sunrise Hwy",
    "iso:country":"US",
    "sg:address":"831 Sunrise Hwy",
    "sg:city":"Lynbrook",
    "sg:classifiers":[
        {
            "category":"Shopping",
            "type":"Retail Goods"
        }
    ],
    "sg:phone":"+1   ",
    "sg:postcode":"11563",
    "sg:province":"NY",
    "sg:tags":[
        "merchandise",
        "furniture"
    ],
    "wof:name":"Harrows 1",
    "wof:placetype":"venue"
},
  "geometry": {"coordinates":[-73.68212800000001,40.656554],"type":"Point"}
}