{
  "type": "Feature",
  "properties": {
    "iso:country":"US",
    "sg:address":"168 7th Ave",
    "sg:city":"Brooklyn",
    "sg:classifiers":[
        {
            "category":"Shopping",
            "subcategory":"News",
            "type":"Retail Goods"
        }
    ],
    "sg:phone":"+1   ",
    "sg:postcode":"11215",
    "sg:province":"NY",
    "sg:tags":[
        "newsstand"
    ],
    "wof:name":"Dnd Inc",
    "wof:placetype":"venue"
},
  "geometry": {"coordinates":[-73.977294,40.672272],"type":"Point"}
}