{
  "type": "Feature",
  "properties": {
    "addr:full":"3155 State St Caledonia NY 14423",
    "addr:housenumber":"3155",
    "addr:postcode":"14423",
    "addr:street":"State St",
    "iso:country":"US",
    "sg:address":"3155 State St",
    "sg:city":"Caledonia",
    "sg:classifiers":[
        {
            "category":"Banks & Credit Unions",
            "subcategory":"Bank",
            "type":"Services"
        }
    ],
    "sg:phone":"+1 585 538 2110",
    "sg:postcode":"14423",
    "sg:province":"NY",
    "sg:tags":[
        "state",
        "commercial"
    ],
    "sg:website":"www.bankofcastile.com",
    "wof:name":"Bank of Castile",
    "wof:placetype":"venue"
},
  "geometry": {"coordinates":[-77.85279800000001,42.973099],"type":"Point"}
}