{
  "type": "Feature",
  "properties": {
    "iso:country":"US",
    "sg:address":"11 S Washington St",
    "sg:city":"Binghamton",
    "sg:classifiers":[
        {
            "category":"Professional",
            "subcategory":"Research",
            "type":"Services"
        }
    ],
    "sg:phone":"+1 607 724 0478",
    "sg:postcode":"13903",
    "sg:province":"NY",
    "sg:tags":[
        "environmental",
        "ecological"
    ],
    "wof:name":"Upstate Laboratories Inc",
    "wof:placetype":"venue"
},
  "geometry": {"coordinates":[-75.914055,42.090946],"type":"Point"}
}