{
  "type": "Feature",
  "properties": {
    "iso:country":"US",
    "sg:address":"1150 Niagara St",
    "sg:city":"Buffalo",
    "sg:classifiers":[
        {
            "category":"Banks & Credit Unions",
            "subcategory":"Bank",
            "type":"Services"
        }
    ],
    "sg:phone":"+1 716 878 8000",
    "sg:postcode":"14213",
    "sg:province":"NY",
    "sg:tags":[
        "state"
    ],
    "wof:name":"Rich Products Employees Cr Un",
    "wof:placetype":"venue"
},
  "geometry": {"coordinates":[-78.899547,42.914919],"type":"Point"}
}