{
  "type": "Feature",
  "properties": {
    "addr:full":"150 Plainfield Ave Elmont NY 11003",
    "addr:housenumber":"150",
    "addr:postcode":"11003",
    "addr:street":"Plainfield Ave",
    "iso:country":"US",
    "sg:address":"150 Plainfield Ave",
    "sg:city":"Elmont",
    "sg:classifiers":[
        {
            "category":"Building & Trades",
            "subcategory":"Construction",
            "type":"Services"
        }
    ],
    "sg:phone":"+1 516 326 3416",
    "sg:postcode":"11003",
    "sg:province":"NY",
    "sg:tags":[
        "elevator"
    ],
    "wof:name":"Whitaker Co Of Long Island",
    "wof:placetype":"venue"
},
  "geometry": {"coordinates":[-73.708713,40.711605],"type":"Point"}
}