{
  "type": "Feature",
  "properties": {
    "addr:full":"375 Broadway Schenectady NY 12305",
    "addr:housenumber":"375",
    "addr:postcode":"12305",
    "addr:street":"Broadway",
    "iso:country":"US",
    "sg:address":"375 Broadway",
    "sg:city":"Schenectady",
    "sg:classifiers":[
        {
            "category":"Social Services",
            "type":"Services"
        }
    ],
    "sg:phone":"+1 518 374 5511",
    "sg:postcode":"12305",
    "sg:province":"NY",
    "sg:tags":[
        "senior",
        "citizen"
    ],
    "wof:name":"Ten Eyck Senior Meal Site",
    "wof:placetype":"venue"
},
  "geometry": {"coordinates":[-73.945769,42.808323],"type":"Point"}
}