{
  "type": "Feature",
  "properties": {
    "iso:country":"US",
    "sg:address":"638 Brown St",
    "sg:city":"Rochester",
    "sg:classifiers":[
        {
            "category":"Organizations",
            "subcategory":"Religious Organization",
            "type":"Services"
        }
    ],
    "sg:phone":"+1 585 235 7558",
    "sg:postcode":"14611",
    "sg:province":"NY",
    "sg:tags":[
        "church"
    ],
    "wof:name":"Greater Deliverance Church",
    "wof:placetype":"venue"
},
  "geometry": {"coordinates":[-77.631917,43.153505],"type":"Point"}
}