{
  "type": "Feature",
  "properties": {
    "iso:country":"US",
    "sg:address":"1 Rockefeller Plz",
    "sg:city":"New York",
    "sg:classifiers":[
        {
            "category":"Professional",
            "type":"Services"
        }
    ],
    "sg:phone":"+1 212 265 5286",
    "sg:postcode":"10020",
    "sg:province":"NY",
    "sg:tags":[
        "establishment"
    ],
    "wof:name":"Durrer GT",
    "wof:placetype":"venue"
},
  "geometry": {"coordinates":[-73.978911,40.758435],"type":"Point"}
}