{
  "type": "Feature",
  "properties": {
    "addr:full":"12 S Park St Cambridge NY 12816",
    "addr:housenumber":"12",
    "addr:postcode":"12816",
    "addr:street":"S Park St",
    "iso:country":"US",
    "sg:address":"12 S Park St",
    "sg:city":"Cambridge",
    "sg:classifiers":[
        {
            "category":"Wholesale",
            "subcategory":"Machinery & Supplies",
            "type":"Manufacturing & Wholesale Goods"
        }
    ],
    "sg:phone":"+1 518 677 2638",
    "sg:postcode":"12816",
    "sg:province":"NY",
    "sg:tags":[
        "equipment",
        "safety",
        "clothing"
    ],
    "wof:name":"Boeri USA Inc",
    "wof:placetype":"venue"
},
  "geometry": {"coordinates":[-73.375992,43.025596],"type":"Point"}
}