{
  "type": "Feature",
  "properties": {
    "addr:full":"656 E 133rd St Bronx NY 10454",
    "addr:housenumber":"656",
    "addr:postcode":"10454",
    "addr:street":"E 133Rd St",
    "iso:country":"US",
    "sg:address":"656 E 133rd St",
    "sg:city":"Bronx",
    "sg:classifiers":[
        {
            "category":"Autos & Motor Vehicles",
            "subcategory":"Auto Supplies",
            "type":"Retail Goods"
        }
    ],
    "sg:phone":"+1   ",
    "sg:postcode":"10454",
    "sg:province":"NY",
    "wof:name":"Najot Enterprises",
    "wof:placetype":"venue"
},
  "geometry": {"coordinates":[-73.91944700000001,40.803434],"type":"Point"}
}