{
  "type": "Feature",
  "properties": {
    "addr:full":"688 Ave of the Americas New York NY 10010",
    "addr:housenumber":"688",
    "addr:postcode":"10010",
    "addr:street":"Ave Of The Americas",
    "iso:country":"US",
    "sg:address":"688 Ave of the Americas",
    "sg:city":"New York",
    "sg:classifiers":[
        {
            "category":"Professional",
            "subcategory":"Management & Consulting",
            "type":"Services"
        }
    ],
    "sg:phone":"+1 212 206 8887",
    "sg:postcode":"10010",
    "sg:province":"NY",
    "sg:tags":[
        "business",
        "merchandise"
    ],
    "wof:name":"Menorah Technique Inc",
    "wof:placetype":"venue"
},
  "geometry": {"coordinates":[-73.99346300000001,40.741766],"type":"Point"}
}