{
  "type": "Feature",
  "properties": {
    "iso:country":"US",
    "sg:address":"99 Tulip Ave",
    "sg:city":"Floral Park",
    "sg:classifiers":[
        {
            "category":"Insurance",
            "subcategory":"Insurance Agent",
            "type":"Services"
        }
    ],
    "sg:phone":"+1 516 775 8594",
    "sg:postcode":"11001",
    "sg:province":"NY",
    "sg:tags":[
        "agency"
    ],
    "wof:name":"Cacchioli John J",
    "wof:placetype":"venue"
},
  "geometry": {"coordinates":[-73.70802999999999,40.726434],"type":"Point"}
}