{
  "type": "Feature",
  "properties": {
    "addr:full":"201 S Main St Syracuse NY 13212",
    "addr:housenumber":"201",
    "addr:postcode":"13212",
    "addr:street":"S Main St",
    "iso:country":"US",
    "sg:address":"201 S Main St",
    "sg:city":"Syracuse",
    "sg:classifiers":[
        {
            "category":"Professional",
            "subcategory":"Advertising",
            "type":"Services"
        }
    ],
    "sg:phone":"+1 315 458 3212",
    "sg:postcode":"13212",
    "sg:province":"NY",
    "sg:tags":[
        "distribution",
        "material"
    ],
    "wof:name":"Val Pak of Central New York",
    "wof:placetype":"venue"
},
  "geometry": {"coordinates":[-76.130605,43.133666],"type":"Point"}
}