{
  "type": "Feature",
  "properties": {
    "iso:country":"US",
    "sg:address":"67 Rochester St",
    "sg:city":"Rochester",
    "sg:classifiers":[
        {
            "category":"Building & Trades",
            "subcategory":"Construction",
            "type":"Services"
        }
    ],
    "sg:phone":"+1 585 746 4316",
    "sg:postcode":"14611",
    "sg:province":"NY",
    "sg:tags":[
        "fire",
        "restoration",
        "damage"
    ],
    "wof:name":"Envirosafe Strip Clean",
    "wof:placetype":"venue"
},
  "geometry": {"coordinates":[-77.663195,43.159288],"type":"Point"}
}