{
  "type": "Feature",
  "properties": {
    "iso:country":"US",
    "sg:address":"600 Plant St",
    "sg:city":"Utica",
    "sg:classifiers":[
        {
            "category":"Manufacturing",
            "subcategory":"Printing",
            "type":"Manufacturing & Wholesale Goods"
        }
    ],
    "sg:phone":"+1 315 735 5522",
    "sg:postcode":"13502",
    "sg:province":"NY",
    "sg:tags":[
        "offset",
        "commercial",
        "publishing",
        "desktop"
    ],
    "sg:website":"www.gwcanfield.com",
    "wof:name":"G W Canfield & Son Inc",
    "wof:placetype":"venue"
},
  "geometry": {"coordinates":[-75.245791,43.097479],"type":"Point"}
}