{
  "type": "Feature",
  "properties": {
    "addr:full":"1362 65th St Brooklyn NY 11219",
    "addr:housenumber":"1362",
    "addr:postcode":"11219",
    "addr:street":"65Th St",
    "iso:country":"US",
    "sg:address":"1362 65th St",
    "sg:city":"Brooklyn",
    "sg:classifiers":[
        {
            "category":"Building & Trades",
            "subcategory":"Construction",
            "type":"Services"
        }
    ],
    "sg:phone":"+1 718 234 0278",
    "sg:postcode":"11219",
    "sg:province":"NY",
    "sg:tags":[
        "contractor"
    ],
    "wof:name":"Unique Contracting Co",
    "wof:placetype":"venue"
},
  "geometry": {"coordinates":[-74.000424,40.625437],"type":"Point"}
}