{
  "type": "Feature",
  "properties": {
    "addr:full":"21 Jerusalem Ave Hicksville NY 11801",
    "addr:housenumber":"21",
    "addr:postcode":"11801",
    "addr:street":"Jerusalem Ave",
    "iso:country":"US",
    "sg:address":"21 Jerusalem Ave",
    "sg:city":"Hicksville",
    "sg:classifiers":[
        {
            "category":"Professional",
            "subcategory":"Accounting & Tax Preparation",
            "type":"Services"
        }
    ],
    "sg:phone":"+1 516 681 1040",
    "sg:postcode":"11801",
    "sg:province":"NY",
    "wof:name":"Fligel Brint & Co",
    "wof:placetype":"venue"
},
  "geometry": {"coordinates":[-73.52497,40.766417],"type":"Point"}
}