{
  "type": "Feature",
  "properties": {
    "addr:full":"15 Elmgrove Park Rochester NY 14624",
    "addr:housenumber":"15",
    "addr:postcode":"14624",
    "addr:street":"Elmgrove Park",
    "iso:country":"US",
    "sg:address":"15 Elmgrove Park",
    "sg:city":"Rochester",
    "sg:classifiers":[
        {
            "category":"Retail",
            "subcategory":"Auto Repair",
            "type":"Services"
        }
    ],
    "sg:phone":"+1 585 247 1522",
    "sg:postcode":"14624",
    "sg:province":"NY",
    "sg:tags":[
        "body",
        "automobile",
        "painting",
        "repairing"
    ],
    "sg:website":"http://www.nulookcollision.com",
    "wof:name":"Nu-Look Collision Inc",
    "wof:placetype":"venue"
},
  "geometry": {"coordinates":[-77.733046,43.161282],"type":"Point"}
}