{
  "type": "Feature",
  "properties": {
    "addr:full":"152 E 7 St New York NY 10009",
    "addr:housenumber":"152;7",
    "addr:postcode":"10009",
    "addr:street":"E",
    "iso:country":"US",
    "sg:address":"152 E 7 St",
    "sg:city":"New York",
    "sg:classifiers":[
        {
            "category":"Real Estate",
            "subcategory":"Real Estate Agent",
            "type":"Services"
        }
    ],
    "sg:phone":"+1 212 307 0637",
    "sg:postcode":"10009",
    "sg:province":"NY",
    "wof:name":"ABC Realty",
    "wof:placetype":"venue"
},
  "geometry": {"coordinates":[-73.98195200000001,40.725399],"type":"Point"}
}