{
  "type": "Feature",
  "properties": {
    "iso:country":"US",
    "sg:address":"6659 W Main Rd",
    "sg:city":"Lima",
    "sg:classifiers":[
        {
            "category":"Restaurant",
            "type":"Food & Drink"
        }
    ],
    "sg:phone":"+1 585 582 1297",
    "sg:postcode":"14485",
    "sg:province":"NY",
    "wof:name":"Jack & Jill Inn",
    "wof:placetype":"venue"
},
  "geometry": {"coordinates":[-77.649407,42.901416],"type":"Point"}
}