{
  "type": "Feature",
  "properties": {
    "iso:country":"US",
    "sg:address":"333 S Westchester Ave",
    "sg:city":"White Plains",
    "sg:classifiers":[
        {
            "category":"Professional",
            "type":"Services"
        }
    ],
    "sg:phone":"+1 914 761 0623",
    "sg:postcode":"10604",
    "sg:province":"NY",
    "sg:tags":[
        "establishment"
    ],
    "wof:name":"Eureka",
    "wof:placetype":"venue"
},
  "geometry": {"coordinates":[-73.750011,41.03034],"type":"Point"}
}