{
  "type": "Feature",
  "properties": {
    "addr:full":"6910 Bay Pkwy Brooklyn NY 11204",
    "addr:housenumber":"6910",
    "addr:postcode":"11204",
    "addr:street":"Bay Pkwy",
    "iso:country":"US",
    "sg:address":"6910 Bay Pkwy",
    "sg:city":"Brooklyn",
    "sg:classifiers":[
        {
            "category":"Health Services",
            "subcategory":"Doctor",
            "type":"Services"
        }
    ],
    "sg:phone":"+1 718 236 3900",
    "sg:postcode":"11204",
    "sg:province":"NY",
    "sg:tags":[
        "medical"
    ],
    "wof:name":"Mayer Adler MD PC",
    "wof:placetype":"venue"
},
  "geometry": {"coordinates":[-73.984072,40.611454],"type":"Point"}
}