{
  "type": "Feature",
  "properties": {
    "addr:full":"81 Emjay Blvd Brentwood NY 11717",
    "addr:housenumber":"81",
    "addr:postcode":"11717",
    "addr:street":"Emjay Blvd",
    "iso:country":"US",
    "sg:address":"81 Emjay Blvd",
    "sg:city":"Brentwood",
    "sg:classifiers":[
        {
            "category":"Professional",
            "subcategory":"Business Services",
            "type":"Services"
        }
    ],
    "sg:phone":"+1 631 435 8500",
    "sg:postcode":"11717",
    "sg:province":"NY",
    "sg:tags":[
        "fund",
        "promotion",
        "raising"
    ],
    "wof:name":"PPMG Promotion Products",
    "wof:placetype":"venue"
},
  "geometry": {"coordinates":[-73.274072,40.776029],"type":"Point"}
}