{
  "type": "Feature",
  "properties": {
    "iso:country":"US",
    "sg:address":"14 Fams Dr",
    "sg:city":"Plainview",
    "sg:classifiers":[
        {
            "category":"Wholesale",
            "subcategory":"Medical Equipment & Supplies",
            "type":"Manufacturing & Wholesale Goods"
        },
        {
            "category":"Shopping",
            "subcategory":"Pharmacy",
            "type":"Retail Goods"
        }
    ],
    "sg:phone":"+1 516 931 4803",
    "sg:postcode":"11803",
    "sg:province":"NY",
    "sg:tags":[
        "pharmaceutical",
        "medicines-patent",
        "proprietary",
        "products-wholesale",
        "manufacturer"
    ],
    "wof:name":"Powder Processing Inc.",
    "wof:placetype":"venue"
},
  "geometry": {"coordinates":[-73.471964,40.765033],"type":"Point"}
}