{
  "type": "Feature",
  "properties": {
    "addr:full":"Riverside Park New York NY 10023",
    "addr:postcode":"10023",
    "addr:street":"Park",
    "iso:country":"US",
    "sg:address":"Riverside Park",
    "sg:city":"New York",
    "sg:classifiers":[
        {
            "category":"Sports & Exercise",
            "subcategory":"Bicycle Rental",
            "type":"Entertainment"
        },
        {
            "category":"Landmark",
            "subcategory":"Tourist Information",
            "type":"Public Place"
        }
    ],
    "sg:phone":"+1 212 260 0400",
    "sg:postcode":"10023",
    "sg:province":"NY",
    "sg:tags":[
        "tour",
        "bike"
    ],
    "sg:website":"bikeandroll.com/newyork",
    "wof:name":"Bike and Roll NYC",
    "wof:placetype":"venue"
},
  "geometry": {"coordinates":[-73.98806999999999,40.779599],"type":"Point"}
}