{
  "type": "Feature",
  "properties": {
    "addr:full":"209 Cambon Ave Saint James NY 11780",
    "addr:housenumber":"209",
    "addr:postcode":"11780",
    "addr:street":"Cambon Ave",
    "iso:country":"US",
    "sg:address":"209 Cambon Ave",
    "sg:city":"Saint James",
    "sg:classifiers":[
        {
            "category":"Banks & Credit Unions",
            "subcategory":"Financial Services",
            "type":"Services"
        }
    ],
    "sg:phone":"+1 631 862 6924",
    "sg:postcode":"11780",
    "sg:province":"NY",
    "sg:tags":[
        "company",
        "holding"
    ],
    "wof:name":"Valuable Property Holdings LLC",
    "wof:placetype":"venue"
},
  "geometry": {"coordinates":[-73.146275,40.87387],"type":"Point"}
}