{
  "type": "Feature",
  "properties": {
    "addr:full":"310 National Blvd Long Beach NY 11561",
    "addr:housenumber":"310",
    "addr:postcode":"11561",
    "addr:street":"National Blvd",
    "iso:country":"US",
    "sg:address":"310 National Blvd",
    "sg:city":"Long Beach",
    "sg:classifiers":[
        {
            "category":"Social Services",
            "subcategory":"Child Care",
            "type":"Services"
        },
        {
            "category":"Education",
            "subcategory":"Preschool",
            "type":"Public Place"
        }
    ],
    "sg:phone":"+1 516 431 2929",
    "sg:postcode":"11561",
    "sg:province":"NY",
    "sg:tags":[
        "day"
    ],
    "sg:website":"www.friedbergjcc.org",
    "wof:name":"Long Beach Ym-Ywha",
    "wof:placetype":"venue"
},
  "geometry": {"coordinates":[-73.666702,40.587601],"type":"Point"}
}