{
  "type": "Feature",
  "properties": {
    "iso:country":"US",
    "sg:address":"18 Tinder Ln",
    "sg:city":"Levittown",
    "sg:classifiers":[
        {
            "category":"Wholesale",
            "subcategory":"Hardware",
            "type":"Manufacturing & Wholesale Goods"
        }
    ],
    "sg:phone":"+1 516 731 1919",
    "sg:postcode":"11756",
    "sg:province":"NY",
    "sg:tags":[
        "equipment",
        "fountain",
        "soda"
    ],
    "wof:name":"Bar & Restaurant Soda Systems",
    "wof:placetype":"venue"
},
  "geometry": {"coordinates":[-73.519227,40.738269],"type":"Point"}
}