{
  "type": "Feature",
  "properties": {
    "iso:country":"US",
    "sg:address":"613 Lake Ave",
    "sg:city":"Lake Luzerne",
    "sg:classifiers":[
        {
            "category":"Building & Trades",
            "subcategory":"Construction",
            "type":"Services"
        }
    ],
    "sg:phone":"+1 518 696 4387",
    "sg:postcode":"12846",
    "sg:province":"NY",
    "sg:tags":[
        "house"
    ],
    "wof:name":"Barrett Bros Construction Inc",
    "wof:placetype":"venue"
},
  "geometry": {"coordinates":[-73.837396,43.341532],"type":"Point"}
}