{
  "type": "Feature",
  "properties": {
    "iso:country":"US",
    "sg:address":"591 Bicycle Path",
    "sg:city":"Port Jefferson Station",
    "sg:classifiers":[
        {
            "category":"Manufacturing",
            "subcategory":"Tools & Machinery",
            "type":"Manufacturing & Wholesale Goods"
        }
    ],
    "sg:phone":"+1   ",
    "sg:postcode":"11776",
    "sg:province":"NY",
    "sg:tags":[
        "limb",
        "retail",
        "artificial",
        "braces",
        "mfg"
    ],
    "wof:name":"North Shore Orthtics Prsthtics",
    "wof:placetype":"venue"
},
  "geometry": {"coordinates":[-73.037446,40.90669],"type":"Point"}
}