{
  "type": "Feature",
  "properties": {
    "iso:country":"US",
    "sg:address":"621 10th St",
    "sg:city":"Niagara Falls",
    "sg:classifiers":[
        {
            "category":"Shopping",
            "type":"Retail Goods"
        }
    ],
    "sg:phone":"+1 716 871 9915",
    "sg:postcode":"14302",
    "sg:province":"NY",
    "sg:tags":[
        "hearing",
        "equipment",
        "supply",
        "impaired"
    ],
    "wof:name":"Diversified Hearing Svc",
    "wof:placetype":"venue"
},
  "geometry": {"coordinates":[-79.0504,43.093102],"type":"Point"}
}