{
  "type": "Feature",
  "properties": {
    "iso:country":"US",
    "sg:address":"301 Halstead Ave",
    "sg:city":"Harrison",
    "sg:classifiers":[
        {
            "category":"Restaurant",
            "type":"Food & Drink"
        }
    ],
    "sg:menulink":"http://www.allmenus.com/ny/harrison/142060-trattoria-vivolo/menu/",
    "sg:phone":"+1 914 835 6199",
    "sg:postcode":"10528",
    "sg:province":"NY",
    "sg:tags":[
        "italian"
    ],
    "wof:name":"Trattoria Vivolo",
    "wof:placetype":"venue"
},
  "geometry": {"coordinates":[-73.711403,40.969146],"type":"Point"}
}