{
  "type": "Feature",
  "properties": {
    "addr:full":"1112 Morton Blvd Kingston NY 12401",
    "addr:housenumber":"1112",
    "addr:postcode":"12401",
    "addr:street":"Morton Blvd",
    "iso:country":"US",
    "sg:address":"1112 Morton Blvd",
    "sg:city":"Kingston",
    "sg:classifiers":[
        {
            "category":"Building & Trades",
            "subcategory":"Construction",
            "type":"Services"
        }
    ],
    "sg:phone":"+1 845 336 6290",
    "sg:postcode":"12401",
    "sg:province":"NY",
    "sg:tags":[
        "floor",
        "laying",
        "contractor"
    ],
    "wof:name":"Oakdale Flooring Co",
    "wof:placetype":"venue"
},
  "geometry": {"coordinates":[-73.99298,41.962146],"type":"Point"}
}