{
  "type": "Feature",
  "properties": {
    "iso:country":"US",
    "sg:address":"8395 Lake Street Rd",
    "sg:city":"Le Roy",
    "sg:classifiers":[
        {
            "category":"Manufacturing",
            "subcategory":"Wood Products",
            "type":"Manufacturing & Wholesale Goods"
        }
    ],
    "sg:phone":"+1   ",
    "sg:postcode":"14482",
    "sg:province":"NY",
    "sg:tags":[
        "pallet",
        "mfg"
    ],
    "wof:name":"Gortons Pallets",
    "wof:placetype":"venue"
},
  "geometry": {"coordinates":[-77.977413,43.0077],"type":"Point"}
}