{
  "type": "Feature",
  "properties": {
    "iso:country":"US",
    "sg:address":"43 Watson Pl",
    "sg:city":"Islip",
    "sg:classifiers":[
        {
            "category":"Building & Trades",
            "subcategory":"Landscaping Services",
            "type":"Services"
        }
    ],
    "sg:phone":"+1 631 859 8541",
    "sg:postcode":"11751",
    "sg:province":"NY",
    "sg:tags":[
        "tree"
    ],
    "wof:name":"Buzz Cutz Tree Svc",
    "wof:placetype":"venue"
},
  "geometry": {"coordinates":[-73.214129,40.73316],"type":"Point"}
}