{
  "type": "Feature",
  "properties": {
    "addr:full":"36 Roxbury St Huntington Station NY 11746",
    "addr:housenumber":"36",
    "addr:postcode":"11746",
    "addr:street":"Roxbury St",
    "iso:country":"US",
    "sg:address":"36 Roxbury St",
    "sg:city":"Huntington Station",
    "sg:classifiers":[
        {
            "category":"Building & Trades",
            "subcategory":"Construction",
            "type":"Services"
        }
    ],
    "sg:phone":"+1 631 271 4495",
    "sg:postcode":"11746",
    "sg:province":"NY",
    "sg:tags":[
        "hanging",
        "contractor"
    ],
    "wof:name":"Saundash Painting Inc",
    "wof:placetype":"venue"
},
  "geometry": {"coordinates":[-73.391638,40.829872],"type":"Point"}
}