{
  "type": "Feature",
  "properties": {
    "addr:full":"Sweet Hollow Rd Huntington NY 11743",
    "addr:postcode":"11743",
    "addr:street":"Sweet Hollow Rd",
    "iso:country":"US",
    "sg:address":"Sweet Hollow Rd",
    "sg:city":"Huntington",
    "sg:classifiers":[
        {
            "category":"Real Estate",
            "subcategory":"Real Estate Operator",
            "type":"Services"
        }
    ],
    "sg:phone":"+1 631 424 7206",
    "sg:postcode":"11743",
    "sg:province":"NY",
    "sg:tags":[
        "apartment"
    ],
    "wof:name":"U G Corp",
    "wof:placetype":"venue"
},
  "geometry": {"coordinates":[-73.410698,40.867802],"type":"Point"}
}