{
  "type": "Feature",
  "properties": {
    "iso:country":"US",
    "sg:address":"19025 Woodhull Ave Apt 1L",
    "sg:city":"Hollis",
    "sg:classifiers":[
        {
            "category":"Arts & Performance",
            "subcategory":"Music",
            "type":"Entertainment"
        }
    ],
    "sg:phone":"+1 718 664 0787",
    "sg:postcode":"11423",
    "sg:province":"NY",
    "sg:tags":[
        "wedding"
    ],
    "wof:name":"Qnz Entertainment",
    "wof:placetype":"venue"
},
  "geometry": {"coordinates":[-73.76351200000001,40.7129],"type":"Point"}
}