{
  "type": "Feature",
  "properties": {
    "iso:country":"US",
    "sg:address":"215 N Clinton St",
    "sg:city":"Syracuse",
    "sg:classifiers":[
        {
            "category":"Professional",
            "subcategory":"Lawyer & Legal Services",
            "type":"Services"
        }
    ],
    "sg:phone":"+1   ",
    "sg:postcode":"13202",
    "sg:province":"NY",
    "wof:name":"Samuel J Costa Attorney",
    "wof:placetype":"venue"
},
  "geometry": {"coordinates":[-76.153552,43.052233],"type":"Point"}
}