{
  "type": "Feature",
  "properties": {
    "addr:full":"93 Charles St Floral Park NY 11001",
    "addr:housenumber":"93",
    "addr:postcode":"11001",
    "addr:street":"Charles St",
    "iso:country":"US",
    "sg:address":"93 Charles St",
    "sg:city":"Floral Park",
    "sg:classifiers":[
        {
            "category":"Wholesale",
            "subcategory":"Vending Machines",
            "type":"Manufacturing & Wholesale Goods"
        }
    ],
    "sg:phone":"+1   ",
    "sg:postcode":"11001",
    "sg:province":"NY",
    "sg:tags":[
        "operator"
    ],
    "wof:name":"Globe Vending Co Inc",
    "wof:placetype":"venue"
},
  "geometry": {"coordinates":[-73.69689700000001,40.727395],"type":"Point"}
}