{
  "type": "Feature",
  "properties": {
    "iso:country":"US",
    "sg:address":"2792 Eggert Rd",
    "sg:city":"Tonawanda",
    "sg:classifiers":[
        {
            "category":"Autos & Motor Vehicles",
            "subcategory":"Automobile Sales",
            "type":"Retail Goods"
        }
    ],
    "sg:phone":"+1 716 834 2792",
    "sg:postcode":"14150",
    "sg:province":"NY",
    "sg:tags":[
        "car",
        "dealer"
    ],
    "wof:name":"Ron Smith's Automotive Repair",
    "wof:placetype":"venue"
},
  "geometry": {"coordinates":[-78.83877,42.989685],"type":"Point"}
}