{
  "type": "Feature",
  "properties": {
    "addr:full":"6250 S Bay Rd Cicero NY 13039",
    "addr:housenumber":"6250",
    "addr:postcode":"13039",
    "addr:street":"S Bay Rd",
    "iso:country":"US",
    "sg:address":"6250 S Bay Rd",
    "sg:city":"Cicero",
    "sg:classifiers":[
        {
            "category":"Banks & Credit Unions",
            "subcategory":"Investment Brokerage",
            "type":"Services"
        },
        {
            "category":"Insurance",
            "subcategory":"Hazard Insurance",
            "type":"Services"
        }
    ],
    "sg:phone":"+1 315 699 5195",
    "sg:postcode":"13039",
    "sg:province":"NY",
    "sg:tags":[
        "agent",
        "resume"
    ],
    "wof:name":"Aegis Group Of Central Ny Inc",
    "wof:placetype":"venue"
},
  "geometry": {"coordinates":[-76.09013400000001,43.167583],"type":"Point"}
}