{
  "type": "Feature",
  "properties": {
    "iso:country":"US",
    "sg:address":"220 White Plains Rd",
    "sg:city":"Tarrytown",
    "sg:classifiers":[
        {
            "category":"Professional",
            "subcategory":"Employment Agencies",
            "type":"Services"
        }
    ],
    "sg:phone":"+1 914 631 3361",
    "sg:postcode":"10591",
    "sg:province":"NY",
    "sg:tags":[
        "help",
        "contractor"
    ],
    "wof:name":"Tech 2000 Svc & Staffing Inc",
    "wof:placetype":"venue"
},
  "geometry": {"coordinates":[-73.844323,41.06326],"type":"Point"}
}