{
  "type": "Feature",
  "properties": {
    "iso:country":"US",
    "sg:address":"611 W Broad St",
    "sg:city":"Rochester",
    "sg:classifiers":[
        {
            "category":"Retail",
            "subcategory":"Car Wash",
            "type":"Services"
        }
    ],
    "sg:phone":"+1 585 262 2070",
    "sg:postcode":"14608",
    "sg:province":"NY",
    "wof:name":"Chester's Carwash",
    "wof:placetype":"venue"
},
  "geometry": {"coordinates":[-77.625908,43.158588],"type":"Point"}
}