{
  "type": "Feature",
  "properties": {
    "addr:full":"7 Hannelore Way Woodbury NY 11797",
    "addr:housenumber":"7",
    "addr:postcode":"11797",
    "addr:street":"Hannelore Way",
    "iso:country":"US",
    "sg:address":"7 Hannelore Way",
    "sg:city":"Woodbury",
    "sg:classifiers":[
        {
            "category":"Insurance",
            "subcategory":"Insurance Agent",
            "type":"Services"
        }
    ],
    "sg:phone":"+1 516 682 9220",
    "sg:postcode":"11797",
    "sg:province":"NY",
    "sg:website":"www.motorcycleexpress.com",
    "wof:name":"Michael I Mandell Inc",
    "wof:placetype":"venue"
},
  "geometry": {"coordinates":[-73.46557300000001,40.82835],"type":"Point"}
}