{
  "type": "Feature",
  "properties": {
    "addr:full":"1150 Liberty Avenue Brooklyn NY 11208",
    "addr:housenumber":"1150",
    "addr:postcode":"11208",
    "addr:street":"Liberty Avenue",
    "iso:country":"US",
    "sg:address":"1150 Liberty Avenue",
    "sg:city":"Brooklyn",
    "sg:classifiers":[
        {
            "category":"Shopping",
            "subcategory":"Mobile Phones",
            "type":"Retail Goods"
        }
    ],
    "sg:phone":"+1 718 235 6831",
    "sg:postcode":"11208",
    "sg:province":"NY",
    "wof:name":"Bhs Communications",
    "wof:placetype":"venue"
},
  "geometry": {"coordinates":[-73.86671699999999,40.678638],"type":"Point"}
}