{
  "type": "Feature",
  "properties": {
    "addr:full":"1156 State Hwy 96 Phelps NY 14532",
    "addr:housenumber":"1156",
    "addr:postcode":"14532",
    "addr:street":"State Hwy 96",
    "iso:country":"US",
    "sg:address":"1156 State Hwy 96",
    "sg:city":"Phelps",
    "sg:classifiers":[
        {
            "category":"Wholesale",
            "subcategory":"Furniture",
            "type":"Manufacturing & Wholesale Goods"
        }
    ],
    "sg:phone":"+1 315 548 2240",
    "sg:postcode":"14532",
    "sg:province":"NY",
    "wof:name":"The Knoll Group",
    "wof:placetype":"venue"
},
  "geometry": {"coordinates":[-77.045142,42.953517],"type":"Point"}
}