{
  "type": "Feature",
  "properties": {
    "iso:country":"US",
    "sg:address":"151 S Main St",
    "sg:city":"New City",
    "sg:classifiers":[
        {
            "category":"Professional",
            "subcategory":"Lawyer & Legal Services",
            "type":"Services"
        }
    ],
    "sg:phone":"+1 845 638 3902",
    "sg:postcode":"10956",
    "sg:province":"NY",
    "sg:tags":[
        "attorney"
    ],
    "wof:name":"Lurlyn Winchester Youngblood",
    "wof:placetype":"venue"
},
  "geometry": {"coordinates":[-73.990398,41.142418],"type":"Point"}
}