{
  "type": "Feature",
  "properties": {
    "iso:country":"US",
    "sg:address":"6381 Seneca St",
    "sg:city":"Elma",
    "sg:classifiers":[
        {
            "category":"Retail",
            "subcategory":"Auto Repair",
            "type":"Services"
        }
    ],
    "sg:phone":"+1 716 652 2997",
    "sg:postcode":"14059",
    "sg:province":"NY",
    "sg:tags":[
        "body",
        "automobile",
        "painting"
    ],
    "wof:name":"Elma Collision",
    "wof:placetype":"venue"
},
  "geometry": {"coordinates":[-78.680172,42.820817],"type":"Point"}
}