{
  "type": "Feature",
  "properties": {
    "iso:country":"US",
    "sg:address":"1607 Blockville-Watts Flats Rd",
    "sg:city":"Ashville",
    "sg:classifiers":[
        {
            "category":"Sports & Exercise",
            "subcategory":"Golf",
            "type":"Entertainment"
        }
    ],
    "sg:phone":"+1 716 782 4550",
    "sg:postcode":"14710",
    "sg:province":"NY",
    "sg:tags":[
        "course",
        "public"
    ],
    "wof:name":"Timber Creek Golf Course",
    "wof:placetype":"venue"
},
  "geometry": {"coordinates":[-79.41230400000001,42.077644],"type":"Point"}
}