{
  "type": "Feature",
  "properties": {
    "iso:country":"US",
    "sg:address":"19 Longshore St",
    "sg:city":"Bay Shore",
    "sg:classifiers":[
        {
            "category":"Building & Trades",
            "subcategory":"Plumbing",
            "type":"Services"
        }
    ],
    "sg:phone":"+1 631 667 2112",
    "sg:postcode":"11706",
    "sg:province":"NY",
    "sg:tags":[
        "tank",
        "septic"
    ],
    "wof:name":"AAA Apex Cesspool Sewer",
    "wof:placetype":"venue"
},
  "geometry": {"coordinates":[-73.297085,40.744707],"type":"Point"}
}