{
  "type": "Feature",
  "properties": {
    "addr:full":"150 W 105th St New York NY 10025",
    "addr:housenumber":"150",
    "addr:postcode":"10025",
    "addr:street":"W 105Th St",
    "iso:country":"US",
    "sg:address":"150 W 105th St",
    "sg:city":"New York",
    "sg:classifiers":[
        {
            "category":"Retail",
            "subcategory":"Repair Shop",
            "type":"Services"
        }
    ],
    "sg:phone":"+1 646 224 9244",
    "sg:postcode":"10025",
    "sg:province":"NY",
    "sg:tags":[
        "lock",
        "locksmith"
    ],
    "wof:name":"Locksmith 24 Hour",
    "wof:placetype":"venue"
},
  "geometry": {"coordinates":[-73.965143,40.799085],"type":"Point"}
}