{
  "type": "Feature",
  "properties": {
    "addr:full":"801 Pioneer Dr North Tonawanda NY 14120",
    "addr:housenumber":"801",
    "addr:postcode":"14120",
    "addr:street":"Pioneer Dr",
    "iso:country":"US",
    "sg:address":"801 Pioneer Dr",
    "sg:city":"North Tonawanda",
    "sg:classifiers":[
        {
            "category":"Professional",
            "subcategory":"Engineering",
            "type":"Services"
        }
    ],
    "sg:phone":"+1 716 692 6034",
    "sg:postcode":"14120",
    "sg:province":"NY",
    "sg:tags":[
        "engineer"
    ],
    "wof:name":"Fabritherm Corp",
    "wof:placetype":"venue"
},
  "geometry": {"coordinates":[-78.865377,43.055983],"type":"Point"}
}