{
  "type": "Feature",
  "properties": {
    "addr:full":"510 Pre Emption Rd Geneva NY 14456",
    "addr:housenumber":"510",
    "addr:postcode":"14456",
    "addr:street":"Pre Emption Rd",
    "iso:country":"US",
    "sg:address":"510 Pre Emption Rd",
    "sg:city":"Geneva",
    "sg:classifiers":[
        {
            "category":"Shopping",
            "type":"Retail Goods"
        }
    ],
    "sg:phone":"+1 315 781 5173",
    "sg:postcode":"14456",
    "sg:province":"NY",
    "sg:tags":[
        "orthopedic",
        "appliance"
    ],
    "wof:name":"Creative Orthotics & Prsthtcs",
    "wof:placetype":"venue"
},
  "geometry": {"coordinates":[-77.011365,42.876694],"type":"Point"}
}