{
  "type": "Feature",
  "properties": {
    "addr:full":"1580 Flatbush Ave Brooklyn NY 11210",
    "addr:housenumber":"1580",
    "addr:postcode":"11210",
    "addr:street":"Flatbush Ave",
    "iso:country":"US",
    "sg:address":"1580 Flatbush Ave",
    "sg:city":"Brooklyn",
    "sg:classifiers":[
        {
            "category":"Coffee & Tea",
            "type":"Food & Drink"
        },
        {
            "category":"Bakery",
            "type":"Food & Drink"
        },
        {
            "category":"Donuts",
            "type":"Food & Drink"
        }
    ],
    "sg:menulink":"http://www.allmenus.com/ny/brooklyn/222384-donut-connection/menu/",
    "sg:phone":"+1 718 434 9642",
    "sg:postcode":"11210",
    "sg:province":"NY",
    "sg:tags":[
        "american",
        "pastry"
    ],
    "wof:name":"Donut Connection",
    "wof:placetype":"venue"
},
  "geometry": {"coordinates":[-73.94726300000001,40.632455],"type":"Point"}
}