{
  "type": "Feature",
  "properties": {
    "addr:full":"1077 Coney Island Ave Brooklyn NY 11230",
    "addr:housenumber":"1077",
    "addr:postcode":"11230",
    "addr:street":"Coney Island Ave",
    "iso:country":"US",
    "sg:address":"1077 Coney Island Ave",
    "sg:city":"Brooklyn",
    "sg:classifiers":[
        {
            "category":"Wholesale",
            "subcategory":"Hardware",
            "type":"Manufacturing & Wholesale Goods"
        }
    ],
    "sg:phone":"+1 718 859 2424",
    "sg:postcode":"11230",
    "sg:province":"NY",
    "sg:tags":[
        "equipment",
        "oil",
        "burner"
    ],
    "wof:name":"H & L Oil Burner & Htg Supl",
    "wof:placetype":"venue"
},
  "geometry": {"coordinates":[-73.966111,40.630141],"type":"Point"}
}